Workbook
Name BALANCE1_LDA01: '[1]Financial Statements'!$E$112
Name BALANCE1_LDA12: '[1]Financial Statements'!$E$123
Name BALANCE2_LDA01: '[1]Financial Statements'!$F$112
Name BALANCE2_LDA12: '[1]Financial Statements'!$F$123
Name BALANCE3_LDA01: '[1]Financial Statements'!$G$112
Name BALANCE3_LDA12: '[1]Financial Statements'!$G$123
Name BALANCE4_LDA01: '[1]Financial Statements'!$H$112
Name BALANCE4_LDA12: '[1]Financial Statements'!$H$123
Name BALANCE5_LDA01: '[1]Financial Statements'!$I$112
Name BALANCE5_LDA12: '[1]Financial Statements'!$I$123
Name BALANCE6_LDA01: '[1]Financial Statements'!$J$112
Name BALANCE6_LDA12: '[1]Financial Statements'!$J$123
Name NotApplicable: CAELS!$B$25
Name PEARLS1_LA002: '[1]Financial Statements'!$E$280
Name PEARLS1_LE008: '[1]Financial Statements'!$E$275
Name PEARLS1_LE009: '[1]Financial Statements'!$E$276
Name PEARLS1_LR001: '[1]Financial Statements'!$E$282
Name PEARLS1_LR005: '[1]Financial Statements'!$E$286
Name PEARLS1_LR006: '[1]Financial Statements'!$E$287
Name PEARLS1_LR007: '[1]Financial Statements'!$E$288
Name PEARLS1_LR009: '[1]Financial Statements'!$E$290
Name PEARLS1_LS001: '[1]Financial Statements'!$E$298
Name PEARLS1_LS005: '[1]Financial Statements'!$E$302
Name PEARLS1_LS011: '[1]Financial Statements'!$E$308
Name PEARLS2_LA002: '[1]Financial Statements'!$F$280
Name PEARLS2_LE008: '[1]Financial Statements'!$F$275
Name PEARLS2_LE009: '[1]Financial Statements'!$F$276
Name PEARLS2_LR001: '[1]Financial Statements'!$F$282
Name PEARLS2_LR005: '[1]Financial Statements'!$F$286
Name PEARLS2_LR006: '[1]Financial Statements'!$F$287
Name PEARLS2_LR007: '[1]Financial Statements'!$F$288
Name PEARLS2_LR009: '[1]Financial Statements'!$F$290
Name PEARLS2_LS001: '[1]Financial Statements'!$F$298
Name PEARLS2_LS005: '[1]Financial Statements'!$F$302
Name PEARLS2_LS010: '[1]Financial Statements'!$F$307
Name PEARLS2_LS011: '[1]Financial Statements'!$F$308
Name PEARLS3_LA002: '[1]Financial Statements'!$G$280
Name PEARLS3_LE008: '[1]Financial Statements'!$G$275
Name PEARLS3_LE009: '[1]Financial Statements'!$G$276
Name PEARLS3_LR001: '[1]Financial Statements'!$G$282
Name PEARLS3_LR005: '[1]Financial Statements'!$G$286
Name PEARLS3_LR006: '[1]Financial Statements'!$G$287
Name PEARLS3_LR007: '[1]Financial Statements'!$G$288
Name PEARLS3_LR009: '[1]Financial Statements'!$G$290
Name PEARLS3_LS001: '[1]Financial Statements'!$G$298
Name PEARLS3_LS005: '[1]Financial Statements'!$G$302
Name PEARLS3_LS010: '[1]Financial Statements'!$G$307
Name PEARLS3_LS011: '[1]Financial Statements'!$G$308
Name PEARLS4_LA002: '[1]Financial Statements'!$H$280
Name PEARLS4_LE008: '[1]Financial Statements'!$H$275
Name PEARLS4_LE009: '[1]Financial Statements'!$H$276
Name PEARLS4_LR001: '[1]Financial Statements'!$H$282
Name PEARLS4_LR005: '[1]Financial Statements'!$H$286
Name PEARLS4_LR006: '[1]Financial Statements'!$H$287
Name PEARLS4_LR007: '[1]Financial Statements'!$H$288
Name PEARLS4_LR009: '[1]Financial Statements'!$H$290
Name PEARLS4_LS001: '[1]Financial Statements'!$H$298
Name PEARLS4_LS005: '[1]Financial Statements'!$H$302
Name PEARLS4_LS010: '[1]Financial Statements'!$H$307
Name PEARLS4_LS011: '[1]Financial Statements'!$H$308

Sheet Trend
B3: DEFENCE SACCO | J3: Base Year
C4: 2013 | D4: 2014 | E4: Audit 2015 | F4: Audit 2016 | G4: Audit 2017 | H4: Audited 2018 | I4: Audited 2019 | J4: Audited 2020 | K4: Audited 2021 | L4: 44562 | M4: 44593 | N4: 44621 | O4: 44652 | P4: 44682 | Q4: 44713 | R4: 44743 | S4: 44774 | T4: 44805 | U4: 44835 | V4: 44866 | W4: 44896 | X4: Audited-2022 | Y4: 44949 | Z4: 44980 | AA4: 45008 | AB4: 45039 | AC4: 45069 | AD4: 45100
B5: Cash and Cash Equivalent | J5: =J6+J7 -> 375933615 | K5: =K6+K7 -> 583646239 | L5: =L6+L7 -> 5.3005126e+08 | M5: =M6+M7 -> 4.1482331e+08 | N5: =N6+N7 -> 6.7492501e+08 | O5: =O6+O7 -> 6.5037254e+08 | P5: =P6+P7 -> 6.8629423e+08 | Q5: =Q6+Q7 -> 7.0539082e+08 | ... AD5: =AD6+AD7 -> 8.2005767e+08
B6: Cash in Hand | J6: 0 | L6: 200100 | M6: 1199830 | N6: 4094100 | O6: 2951700 | P6: 8750 | Q6: 4948100 | R6: 5149700 | S6: 4506450 | T6: 7058650 | U6: 5160050 | V6: 5408800 | W6: 6948900 | X6: =6948900+44915433+11276757 -> 63141090 | Y6: 2665250 | Z6: 4277700 | AA6: 4143400 | AB6: 6607350 | AC6: 5756000 | AD6: 2455300
B7: Cash at Bank | J7: 375933615 | K7: 583646239 | L7: 5.2985116e+08 | M7: 4.1362348e+08 | N7: 6.7083091e+08 | O7: 6.4742084e+08 | P7: 6.8628548e+08 | Q7: 7.0044272e+08 | R7: 3.8653254e+08 | S7: 8.9762557e+08 | T7: 8.9475624e+08 | U7: 9.1670022e+08 | V7: 8.9582156e+08 | W7: 3.0547507e+08 | X7: =15309747+557326+24720482+8561345+200000000+60000000+51511250+2867694 -> 363527844 | Y7: 9.0808746e+08 | Z7: 9.2114728e+08 | AA7: 7.907949e+08 | AB7: 2.9451931e+08 | AC7: 2.5092602e+08 | AD7: 8.1760237e+08
B8: Prepayments and Sundry Receivables | J8: 5863447 | K8: 24284162 | L8: 24779370 | M8: 2.1566836e+08 | N8: 618454.57 | O8: 2094825 | P8: 3757175.1 | Q8: 1.1976176e+08 | R8: 4.9342878e+08 | S8: 6147486.8 | T8: 8381173.8 | U8: 11930338 | V8: 13610850 | W8: 6.316281e+08 | X8: =430753438+195053203+2621600+1738005+628152+500000 -> 631294398 | Y8: 6132599.2 | Z8: 7298663.1 | AA8: 6209622.8 | AB8: 5.4085677e+08 | AC8: 5.714849e+08 | AD8: 2731571.5
B9: Financial Investments | J9: =J10+J11+J12+J13 -> 10000000 | K9: =K10+K11+K12+K13 -> 10000000 | L9: =L10+L11+L12+L13 -> 1.3078489e+08 | M9: =M10+M11+M12+M13 -> 1.3243854e+08 | N9: =N10+N11+N12+N13 -> 1.3243854e+08 | O9: =O10+O11+O12+O13 -> 1.928705e+08 | P9: =P10+P11+P12+P13 -> 2.338705e+08 | Q9: =Q10+Q11+Q12+Q13 -> 2.3544865e+08 | ... AD9: =AD10+AD11+AD12+AD13 -> 1.1395298e+08
B10: Government Securities | L10: 60000000 | M10: 60000000 | N10: 60000000 | O10: 60000000 | P10: 60000000 | Q10: 60000000 | R10: 60000000 | S10: 60000000 | T10: 60000000 | U10: 60000000 | V10: 60000000 | W10: 60000000 | Y10: 60000000 | Z10: 60000000 | AA10: 60000000 | AB10: 60000000 | AC10: 60000000 | AD10: 60000000
B11: Other Securities | L11: 10784886 | M11: 10855746 | N11: 10855747 | O11: 71287705 | P11: 71287705 | Q11: 71332526 | R11: 2764793.6 | S11: 2764793.6 | T11: 2764793.6 | U11: 2764793.6 | V11: 2764793.6 | W11: 2867694.4 | Y11: 2867694.4 | Z11: 2867694.4 | AA11: 2867694.4 | AB11: 2867694.4 | AC11: 2952981.5 | AD11: 2952981.5
B12: Balances with other SACCO Societies | J12: 10000000 | K12: 10000000 | L12: 50000000 | M12: 51582795 | N12: 51582795 | O12: 51582795 | P12: 51582795 | Q12: 53116127 | R12: 0 | S12: 0 | T12: 50000000 | U12: 50000000 | V12: 60000000 | W12: 50000000 | X12: 51000000 | Y12: 51511250 | Z12: 51511250 | AA12: 70000000 | AB12: 0 | AC12: 0 | AD12: 0
B13: Investments in companies | L13: 10000000 | M13: 10000000 | N13: 10000000 | O13: 10000000 | P13: 51000000 | Q13: 51000000 | R13: 51000000 | S13: 51000000 | T13: 51000000 | U13: 51000000 | V13: 41000000 | W13: 51000000 | Y13: 51000000 | Z13: 51000000 | AA13: 51000000 | AB13: 51000000 | AC13: 51000000 | AD13: 51000000
B14: Net Loan Portfolio | J14: =J15-J16 -> 67566895 | K14: =K15-K16 -> 5.5293772e+08 | L14: =L15-L16 -> 5.9571784e+08 | M14: =M15-M16 -> 6.3966133e+08 | N14: =N15-N16 -> 7.068788e+08 | O14: =O15-O16 -> 8.0472316e+08 | P14: =P15-P16 -> 9.1367836e+08 | Q14: =Q15-Q16 -> 1.0367631e+09 | ... AD14: =AD15-AD16 -> 3.2002342e+09
B15: Gross Loan Portfolio | J15: 67566895 | K15: 5.5293772e+08 | L15: 6.0713821e+08 | M15: 654081705 | N15: 7.2585877e+08 | O15: 8.2786399e+08 | P15: 9.4205761e+08 | Q15: 1.0602147e+09 | R15: 1.1788905e+09 | S15: 1.31237e+09 | T15: 1.4622987e+09 | U15: 1.6238722e+09 | V15: 1.795915e+09 | W15: 1.9658763e+09 | X15: 1965911975 | Y15: 2156775721 | Z15: 2.3521872e+09 | AA15: 2.5945021e+09 | AB15: 2.8057196e+09 | AC15: 3.031349e+09 | AD15: 3.2831912e+09
B16: Allowance for Loan Loss | J16: 0 | L16: 11420371 | M16: 14420371 | N16: 18979978 | O16: 23140824 | P16: 28379254 | Q16: 23451622 | R16: 26672724 | S16: 32820242 | T16: 36575624 | U16: 40075391 | V16: 43791359 | W16: 46239386 | X16: 46239386 | Y16: 54050756 | Z16: 58714104 | AA16: 61762371 | AB16: 69572162 | AC16: 76315224 | AD16: 82956980
B17: Account Receivables | J17: =J18+J19+J20 -> 0 | K17: =K18+K19+K20 -> 0 | L17: =L18+L19+L20 -> 628152.18 | M17: =M18+M19+M20 -> 628152.18 | N17: =N18+N19+N20 -> 628152.18 | O17: =O18+O19+O20 -> 628152.18 | P17: =P18+P19+P20 -> 628152.18 | Q17: =Q18+Q19+Q20 -> 628152.18 | ... AD17: =AD18+AD19+AD20 -> 628152.18
B18: Tax Recoverable | J18: 0 | L18: 628152.18 | M18: 628152.18 | N18: 628152.18 | O18: 628152.18 | P18: 628152.18 | Q18: 628152.18 | R18: 628152.18 | S18: 628152.18 | T18: 628152.18 | U18: 628152.18 | V18: 628152.18 | W18: 628152.18 | X18: 0 | Y18: 628152.18 | Z18: 628152.18 | AA18: 628152.18 | AB18: 628152.18 | AC18: 628152.18 | AD18: 628152.18
B19: Deferred Tax Assets | J19: 0 | L19: 0 | M19: 0 | N19: 0 | O19: 0 | P19: 0 | Q19: 0 | R19: 0 | S19: 0 | T19: 0 | U19: 0 | V19: 0 | W19: 0 | X19: 0 | Y19: 0 | Z19: 0 | AA19: 0 | AB19: 0 | AC19: 0 | AD19: 0
B20: Retirement Benefit Assets | J20: 0 | L20: 0 | M20: 0 | N20: 0 | O20: 0 | P20: 0 | Q20: 0 | R20: 0 | S20: 0 | T20: 0 | U20: 0 | V20: 0 | W20: 0 | X20: 0 | Y20: 0 | Z20: 0 | AA20: 0 | AB20: 0 | AC20: 0 | AD20: 0
B21: Property and Equipment and Other Assets | J21: =J22+J23+J24+J25+J26 -> 0 | W21: =W22+W23+W24+W25+W26 -> 0 | X21: =X22+X23+X24+X25+X26 -> 0 | Y21: =Y22+Y23+Y24+Y25+Y26 -> 0 | Z21: =Z22+Z23+Z24+Z25+Z26 -> 0 | AA21: =AA22+AA23+AA24+AA25+AA26 -> 2552000 | AB21: =AB22+AB23+AB24+AB25+AB26 -> 6902000 | AC21: =AC22+AC23+AC24+AC25+AC26 -> 7027000 | AD21: =AD22+AD23+AD24+AD25+AD26 -> 7027000
B22: Investment Properties | J22: 0 | L22: 0 | M22: 0 | N22: 0 | O22: 0 | P22: 0 | Q22: 0 | R22: 0 | S22: 0 | T22: 0 | U22: 0 | V22: 0 | W22: 0 | Y22: 0 | Z22: 0 | AA22: 0 | AB22: 0 | AC22: 0 | AD22: 4475000
B23: Property and Equipment | J23: 0 | L23: 0 | M23: 0 | N23: 0 | O23: 0 | P23: 0 | Q23: 0 | R23: 0 | S23: 0 | T23: 0 | U23: 0 | V23: 0 | W23: 0 | Y23: 0 | Z23: 0 | AA23: 0 | AB23: 4350000 | AC23: 4475000 | AD23: 0
B24: Prepaid lease rentals | J24: 0 | L24: 0 | M24: 0 | N24: 0 | O24: 0 | P24: 0 | Q24: 0 | R24: 0 | S24: 0 | T24: 0 | U24: 0 | V24: 0 | W24: 0 | Y24: 0 | Z24: 0 | AA24: 0 | AB24: 0 | AC24: 0 | AD24: 0
B25: Intangible Assets | J25: 0 | L25: 0 | M25: 0 | N25: 0 | O25: 0 | P25: 0 | Q25: 0 | R25: 0 | S25: 0 | T25: 0 | U25: 0 | V25: 0 | W25: 0 | Y25: 0 | Z25: 0 | AA25: 2552000 | AB25: 2552000 | AC25: 2552000 | AD25: 2552000
B26: Other Assets | J26: 0 | L26: 0 | M26: 0 | N26: 0 | O26: 0 | P26: 0 | Q26: 0 | R26: 0 | S26: 0 | T26: 0 | U26: 0 | V26: 0 | W26: 0 | Y26: 0 | Z26: 0 | AA26: 0 | AB26: 0 | AC26: 0 | AD26: 0
B27: Total Assets | J27: =J5+J8+J9+J14+J17+J21 -> 459363957 | K27: =K5+K8+K9+K14+K17+K21 -> 1.1708681e+09 | L27: =L5+L8+L9+L14+L17+L21 -> 1.2819615e+09 | M27: =M5+M8+M9+M14+M17+M21 -> 1.4032197e+09 | N27: =N5+N8+N9+N14+N17+N21 -> 1.515489e+09 | O27: =O5+O8+O9+O14+O17+O21 -> 1.6506892e+09 | P27: =P5+P8+P9+P14+P17+P21 -> 1.8382284e+09 | Q27: =Q5+Q8+Q9+Q14+Q17+Q21 -> 2.0979925e+09 | ... AD27: =AD5+AD8+AD9+AD14+AD17+AD21 -> 4.1446316e+09
B28: Savings Deposits | K28: 319521.55 | L28: 13983820 | M28: 49599559 | N28: 54281773 | O28: 75270723 | P28: 1.4092141e+08 | Q28: 2.573535e+08 | R28: 1.5415079e+08 | S28: 1.4814507e+08 | T28: 1.7932285e+08 | U28: 1.9141829e+08 | V28: 1.8570586e+08 | W28: 1.9540497e+08 | X28: 195438509 | Y28: 1.8637761e+08 | Z28: 2.1125221e+08 | AA28: 2.4384265e+08 | AB28: 2.3917689e+08 | AC28: 2.3691099e+08 | AD28: 2.6955472e+08
B29: Short Term Deposits | L29: 10205 | M29: 12955 | N29: 19136 | O29: 20236 | P29: 49312 | Q29: 119512 | R29: 19512 | S29: 19512 | T29: 19512 | U29: 19512 | V29: 9512 | W29: 9512 | Y29: 9512 | Z29: 9512 | AA29: 9512 | AB29: 9512 | AC29: 9512 | AD29: 9512
B30: Non withdrawable Deposits | J30: 291131418 | K30: 926612134 | L30: 1.0137507e+09 | M30: 1.103747e+09 | N30: 1.050628e+09 | O30: 1.1557788e+09 | P30: 1.2593688e+09 | Q30: 1.3679773e+09 | R30: 1.4954133e+09 | S30: 1.6289172e+09 | T30: 1.7111129e+09 | U30: 1.8455846e+09 | V30: 1.9464446e+09 | W30: 2.0914307e+09 | X30: 2091506898 | Y30: 2.2312789e+09 | Z30: 2.3698231e+09 | AA30: 2.3117227e+09 | AB30: 2.4667379e+09 | AC30: 2.6122539e+09 | AD30: 2.7663758e+09
B31: Total Deposit Liabilities | J31: =J28+J29+J30 -> 291131418 | K31: =K28+K29+K30 -> 9.2693166e+08 | L31: =L28+L29+L30 -> 1.0277447e+09 | M31: =M28+M29+M30 -> 1.1533595e+09 | N31: =N28+N29+N30 -> 1.1049289e+09 | O31: =O28+O29+O30 -> 1.2310698e+09 | P31: =P28+P29+P30 -> 1.4003395e+09 | Q31: =Q28+Q29+Q30 -> 1.6254503e+09 | ... AD31: =AD28+AD29+AD30 -> 3.03594e+09
B32: Accounts Payable Other Liabilities | J32: =J33+J34+J35+J36+J37+J38 -> 117409937 | K32: =K33+K34+K35+K36+K37+K38 -> 95695469 | L32: =L33+L34+L35+L36+L37+L38 -> 99271776 | M32: =M33+M34+M35+M36+M37+M38 -> 85051193 | N32: =N33+N34+N35+N36+N37+N38 -> 83997975 | O32: =O33+O34+O35+O36+O37+O38 -> 88767715 | P32: =P33+P34+P35+P36+P37+P38 -> 93678348 | Q32: =Q33+Q34+Q35+Q36+Q37+Q38 -> 99278714 | ... AD32: =AD33+AD34+AD35+AD36+AD37+AD38 -> 1.7135978e+08
B33: Tax Payable | L33: 5893585.2 | M33: 5981502.2 | N33: 388478.63 | O33: 438731.05 | P33: 429410.19 | Q33: 667283.09 | R33: 795224.09 | S33: 810965.19 | T33: 885780.39 | U33: 860287.79 | V33: 879071.59 | W33: 916346.79 | Y33: 12378272 | Z33: 16133050 | AA33: 1312211 | AB33: 1096107.9 | AC33: 1171225.8 | AD33: 1425818
B34: Dividends Payable | J34: 2463184 | K34: =16452616+3074654 -> 19527270 | L34: 18769641 | M34: 57 | N34: 57 | O34: 57 | P34: 57 | Q34: 57 | R34: 57 | S34: 57 | T34: 57 | U34: 57 | V34: 57 | W34: 57 | X34: =19514754+52611583 -> 72126337 | Y34: 72126394 | Z34: 68520074 | AA34: 57 | AB34: 8390.35 | AC34: 57 | AD34: 57
B35: Deferred Tax Liability | L35: 0 | M35: 0 | N35: 0 | O35: 0 | P35: 0 | Q35: 0 | R35: 0 | S35: 0 | T35: 0 | U35: 0 | V35: 0 | W35: 0 | Y35: 0 | Z35: 0 | AA35: 0 | AB35: 0 | AC35: 0 | AD35: 0
B36: Retirement Benefits Liability | J36: 8735358 | L36: 0 | M36: 0 | N36: 0 | O36: 0 | P36: 0 | Q36: 0 | R36: 0 | S36: 0 | T36: 0 | U36: 0 | V36: 0 | W36: 0 | Y36: 0 | Z36: 0 | AA36: 0 | AB36: 0 | AC36: 0 | AD36: 0
B37: Other Liabilities | J37: =10378923+5832472 -> 16211395 | K37: =35636830+10531369 -> 46168199 | L37: 44608550 | M37: 49069634 | N37: 53609440 | O37: 58328927 | P37: 63248881 | Q37: 68611374 | R37: 76451239 | S37: 84690972 | T37: 92021462 | U37: 97818028 | V37: 93821000 | W37: 1.0549287e+08 | X37: =25147127+93295271 -> 118442398 | Y37: 1.1128224e+08 | Z37: 1.1695203e+08 | AA37: 1.2140631e+08 | AB37: 1.2341994e+08 | AC37: 1.2984475e+08 | AD37: 1.399339e+08
B38: External Borrowings | J38: 90000000 | K38: 30000000 | L38: 30000000 | M38: 30000000 | N38: 30000000 | O38: 30000000 | P38: 30000000 | Q38: 30000000 | R38: 30000000 | S38: 30000000 | T38: 30000000 | U38: 30000000 | V38: 30000000 | W38: 30000000 | X38: 30000000 | Y38: 30000000 | Z38: 30000000 | AA38: 30000000 | AB38: 30000000 | AC38: 30000000 | AD38: 30000000
B39: Total Liabilities | J39: =J31+J32 -> 408541355 | K39: =K31+K32 -> 1.0226271e+09 | L39: =L31+L32 -> 1.1270165e+09 | M39: =M31+M32 -> 1.2384107e+09 | N39: =N31+N32 -> 1.1889269e+09 | O39: =O31+O32 -> 1.3198375e+09 | P39: =P31+P32 -> 1.4940178e+09 | Q39: =Q31+Q32 -> 1.724729e+09 | ... AD39: =AD31+AD32 -> 3.2072998e+09
B40: Share Capital | J40: 43186838 | K40: 73760486 | L40: 73765486 | M40: 73796626 | N40: 225824998 | O40: 226402490 | P40: 232021774 | Q40: 2.3209907e+08 | R40: 2.3232325e+08 | S40: 2.3247503e+08 | T40: 2.8673854e+08 | U40: 2.9506328e+08 | V40: 3.3168816e+08 | W40: 3.37595e+08 | X40: 337595002 | Y40: 3.3826777e+08 | Z40: 3.3970426e+08 | AA40: 5.397673e+08 | AB40: 5.4092581e+08 | AC40: 5.5288937e+08 | AD40: 5.5391011e+08
B41: Capital Grants | L41: 31750000 | M41: 31750000 | N41: 31750000 | O41: 31750000 | P41: 31750000 | Q41: 31750000 | R41: 31750000 | S41: 31750000 | T41: 31750000 | U41: 31750000 | V41: 31750000 | W41: 31750000 | X41: 31750000 | Y41: 31750000 | Z41: 31750000 | AA41: 31750000 | AB41: 31750000 | AC41: 31750000 | AD41: 31750000
B42: Retained Earnings | J42: 5615976 | K42: =K43+K44 -> 32981843 | L42: =L43+L44 -> 39775842 | M42: =M43+M44 -> 49608677 | N42: =N43+N44 -> 59333428 | O42: =O43+O44 -> 63045553 | P42: =P43+P44 -> 70785145 | Q42: =Q43+Q44 -> 1.0076071e+08 | R42: =R43+R44 -> 1.2116468e+08 | ... AD42: =AD43+AD44 -> 3.1630583e+08
B43: Prior Year Retained Earnings | K43: 5615975 | L43: 33076843 | M43: 33076843 | N43: 33076843 | O43: 33076843 | P43: 33076843 | Q43: 33076843 | R43: 33076843 | S43: 33076843 | T43: 33076843 | U43: 33076843 | V43: 33076843 | W43: 33076843 | X43: 33076843 | Y43: 1.164109e+08 | Z43: 1.1641209e+08 | AA43: 1.1641209e+08 | AB43: 1.1641209e+08 | AC43: 1.1641209e+08 | AD43: 1.1641209e+08
B44: Current Year Surplus | K44: 27365868 | L44: 6698999.3 | M44: 16531834 | N44: 26256585 | O44: 29968710 | P44: 37708302 | Q44: 67683868 | R44: 88087836 | S44: 1.0268293e+08 | T44: 1.2573047e+08 | U44: 1.4673587e+08 | V44: 1.6832903e+08 | W44: 1.9285483e+08 | X44: =116410903-X43 -> 83334060 | Y44: 20369938 | Z44: 56281693 | AA44: 89346782 | AB44: 1.1462619e+08 | AC44: 1.5820104e+08 | AD44: 1.9989374e+08
B45: Other Equity Accounts | J45: =J46+J47+J48+J49+J50 -> 2019789 | K45: =K46+K47+K48+K49+K50 -> 41498670 | L45: =L46+L47+L48+L49+L50 -> 9653670.2 | M45: =M46+M47+M48+M49+M50 -> 9653670.2 | N45: =N46+N47+N48+N49+N50 -> 9653670.2 | O45: =O46+O47+O48+O49+O50 -> 9653670.2 | P45: =P46+P47+P48+P49+P50 -> 9653670.2 | Q45: =Q46+Q47+Q48+Q49+Q50 -> 9653670.2 | ... AD45: =AD46+AD47+AD48+AD49+AD50 -> 35365874
B46: Statutory Reserve | J46: 2019789 | K46: 9748670 | L46: 9653670.2 | M46: 9653670.2 | N46: 9653670.2 | O46: 9653670.2 | P46: 9653670.2 | Q46: 9653670.2 | R46: 9653670.2 | S46: 9653670.2 | T46: 9653670.2 | U46: 9653670.2 | V46: 9653670.2 | W46: 9653670.2 | X46: 35365874 | Y46: 35365875 | Z46: 35365874 | AA46: 35365874 | AB46: 35365874 | AC46: 35365874 | AD46: 35365874
B47: Other Reserves | K47: 31750000 | L47: 0 | M47: 0 | N47: 0 | O47: 0 | P47: 0 | Q47: 0 | R47: 0 | S47: 0 | T47: 0 | U47: 0 | V47: 0 | W47: 0 | X47: 0 | Y47: 0 | Z47: 0 | AA47: 0 | AB47: 0 | AC47: 0 | AD47: 0
B48: Revaluation Reserves | L48: 0 | M48: 0 | N48: 0 | O48: 0 | P48: 0 | Q48: 0 | R48: 0 | S48: 0 | T48: 0 | U48: 0 | V48: 0 | W48: 0 | X48: 0 | Y48: 0 | Z48: 0 | AA48: 0 | AB48: 0 | AC48: 0 | AD48: 0
B49: Proposed Dividends | L49: 0 | M49: 0 | N49: 0 | O49: 0 | P49: 0 | Q49: 0 | R49: 0 | S49: 0 | T49: 0 | U49: 0 | V49: 0 | W49: 0 | X49: 0 | Y49: 0 | Z49: 0 | AA49: 0 | AB49: 0 | AC49: 0 | AD49: 0
B50: Adjustment To Equity | L50: 0 | M50: 0 | N50: 0 | O50: 0 | P50: 0 | Q50: 0 | R50: 0 | S50: 0 | T50: 0 | U50: 0 | V50: 0 | W50: 0 | X50: 0 | Y50: 0 | Z50: 0 | AA50: 0 | AB50: 0 | AC50: 0 | AD50: 0
B51: Total Equity | J51: =J42+J45+J40 -> 50822603 | K51: =K40+K41+K42+K45 -> 148240999 | L51: =L40+L41+L42+L45 -> 1.54945e+08 | M51: =M40+M41+M42+M45 -> 1.6480897e+08 | N51: =N40+N41+N42+N45 -> 3.265621e+08 | O51: =O40+O41+O42+O45 -> 3.3085171e+08 | P51: =P40+P41+P42+P45 -> 3.4421059e+08 | Q51: =Q40+Q41+Q42+Q45 -> 3.7426345e+08 | R51: =R40+R41+R42+R45 -> 3.948916e+08 | ... AD51: =AD40+AD41+AD42+AD45 -> 9.3733182e+08
B52: Total Liabilities and Equity | J52: =J39+J51 -> 459363958 | K52: =K39+K51 -> 1.1708681e+09 | L52: =L39+L51 -> 1.2819615e+09 | M52: =M39+M51 -> 1.4032197e+09 | N52: =N39+N51 -> 1.515489e+09 | O52: =O39+O51 -> 1.6506892e+09 | P52: =P39+P51 -> 1.8382284e+09 | Q52: =Q39+Q51 -> 2.0989925e+09 | ... AD52: =AD39+AD51 -> 4.1446316e+09
X53: =X27-X52 -> 0 | Y53: =Y27-Y52 -> -0.090000153 | Z53: =Z27-Z52 -> 0 | AA53: =AA27-AA52 -> 0 | AB53: =AB27-AB52 -> 0 | AC53: =AC27-AC52 -> 0.0099992752 | AD53: =AD27-AD52 -> 0
J54: =J27-J52 -> -1 | K54: =K52-K27 -> -2
B55: Suspense (Balancing Figure capital side)
B56: Adjustment to Equity
B57: Sacco Name | J57: Base Year
B58: AUDITED YEAR TO | C58: 2013 | D58: 2014 | E58: Audit 2015 | F58: Audit 2016 | G58: Audit 2017 | H58: Audited 2018 | I58: Audited 2019 | J58: Audited 2020 | K58: Audited 2021
B59: Financial Income | J59: =J60+J63 -> 26073627 | K59: =K60+K63 -> 75147891 | L59: =L60+L63 -> 9844121.8 | M59: =M60+M63 -> 23307862 | N59: =N60+N63 -> 38162899 | O59: =O60+O63 -> 51641985 | P59: =P60+P63 -> 67868387 | Q59: =Q60+Q63 -> 94717717 | ... AD59: =AD60+AD63 -> 2.5405281e+08
B60: Financial Income from Loans Portfolio | J60: =J61+J62 -> 2051377 | K60: =K61+K62 -> 30031682 | L60: =L61+L62 -> 6387480 | M60: =M61+M62 -> 13288121 | N60: =N61+N62 -> 20599493 | O60: =O61+O62 -> 29474824 | P60: =P61+P62 -> 39346655 | Q60: =Q61+Q62 -> 49903313 | ... AD60: =AD61+AD62 -> 2.0235244e+08
B61: Interest on Loan Portfolio | J61: 2051377 | K61: 30031682 | L61: 5791010 | M61: 12004631 | N61: 18456061 | O61: 26231070 | P61: 34864959 | Q61: 44097122 | R61: 56341071 | S61: 69144624 | T61: 83776983 | U61: 99957291 | V61: 1.1823479e+08 | W61: 1.3945648e+08 | X61: 132133329 | Y61: 20982250 | Z61: 47460924 | AA61: 76825974 | AB61: 1.0878539e+08 | AC61: 1.4374326e+08 | AD61: 1.8222278e+08
B62: Fees and Commission on Loan Portfolio | L62: 596470 | M62: 1283490 | N62: 2143432 | O62: 3243754.1 | P62: 4481696.4 | Q62: 5806191.4 | R62: 6965561.4 | S62: 8437111.4 | T62: 10131981 | U62: 11920448 | V62: 13832098 | W62: 15795552 | Y62: 2438030 | Z62: 5633317.6 | AA62: 9284765.6 | AB62: 12293486 | AC62: 15558702 | AD62: 20129664
B63: Financial Income From Investments | J63: =J64+J65+J66+J67 -> 24022250 | K63: =K64+K65+K66+K67 -> 45116209 | L63: =L64+L65+L66+L67 -> 3456641.8 | M63: =M64+M65+M66+M67 -> 10019741 | N63: =N64+N65+N66+N67 -> 17563406 | O63: =O64+O65+O66+O67 -> 22167160 | P63: =P64+P65+P66+P67 -> 28521731 | Q63: =Q64+Q65+Q66+Q67 -> 44814404 | ... AD63: =AD64+AD65+AD66+AD67 -> 51700363
B64: Government Securities | L64: 0 | M64: 1119420 | N64: 1119420 | O64: 1119420 | P64: 3518640 | Q64: 3518640 | R64: 3518640 | S64: 4638060 | T64: 4638060 | U64: 4638060 | V64: 7037280 | W64: 7037280 | Y64: 0 | Z64: 1119420 | AA64: 1119420 | AB64: 1119420 | AC64: 3518640 | AD64: 3518640
B65: Deposits with Banks and other Financial Institutions | J65: 18745805 | K65: 34607803 | L65: 2331101.8 | M65: 6234757.1 | N65: 9575500.2 | O65: 12591019 | P65: 15174580 | Q65: 23425989 | R65: 28154801 | S65: 30749390 | T65: 34887219 | U65: 39018794 | V65: 41613383 | W65: 51969196 | X65: =7037280+2163910+1676036+12940607+4926592+30368219+1671180 -> 60783824 | Y65: 2922991.6 | Z65: 8588362.2 | AA65: 11248526 | AB65: 12968800 | AC65: 21083025 | AD65: 29386888
B66: Other Investments | L66: 0 | M66: 0 | N66: 0 | O66: 0 | P66: 0 | Q66: 0 | R66: 5137125 | S66: 5137125 | T66: 5137125 | U66: 5137125 | V66: 5137125 | W66: 5137125 | X66: 5137125 | Y66: 0 | Z66: 0 | AA66: 0 | AB66: 0 | AC66: 0 | AD66: 0
B67: Other Operating Income | J67: 5276445 | K67: 10508406 | L67: 1125540 | M67: 2665564 | N67: 6868486 | O67: 8456721 | P67: 9828511 | Q67: 17869775 | R67: 18632190 | S67: 21771010 | T67: 29666206 | U67: 32791448 | V67: 35518602 | W67: 34455928 | X67: =61518939-5137125 -> 56381814 | Y67: 2574546.5 | Z67: 6802625.5 | AA67: 9875035 | AB67: 12589158 | AC67: 15878356 | AD67: 18794834
B68: Financial Expense | J68: =J69+J70+J71+J72+J73+J74 -> 13028923 | K68: =K69+K70+K71+K72+K73+K74 -> 20967322 | L68: =L69+L70+L71+L72+L73+L74 -> 37465.9 | M68: =M69+M70+M71+M72+M73+M74 -> 80100.1 | N68: =N69+N70+N71+N72+N73+N74 -> 144751.8 | O68: =O69+O70+O71+O72+O73+O74 -> 195361.8 | P68: =P69+P70+P71+P72+P73+P74 -> 1609627.8 | Q68: =Q69+Q70+Q71+Q72+Q73+Q74 -> 1677369.9 | ... AD68: =AD69+AD70+AD71+AD72+AD73+AD74 -> 145581.8
B69: Interest Expense on Deposits | J69: 13028923 | K69: 17052616 | L69: 0 | M69: 0 | N69: 0 | O69: 0 | P69: 0 | Q69: 0 | R69: 0 | S69: 0 | T69: 0 | U69: 0 | V69: 0 | W69: 0 | X69: 52611583 | Y69: 0 | Z69: 0 | AA69: 0 | AB69: 0 | AC69: 0 | AD69: 0
B70: Cost of External Borrowings | L70: 0 | M70: 0 | N70: 0 | O70: 0 | P70: 0 | Q70: 0 | R70: 0 | S70: 0 | T70: 0 | U70: 0 | V70: 0 | W70: 0 | X70: 600000 | Y70: 0 | Z70: 0 | AA70: 0 | AB70: 0 | AC70: 0 | AD70: 0
B71: Dividend Expenses | L71: 0 | M71: 0 | N71: 0 | O71: 0 | P71: 0 | Q71: 0 | R71: 0 | S71: 0 | T71: 0 | U71: 0 | V71: 0 | W71: 0 | Y71: 0 | Z71: 0 | AA71: 0 | AB71: 0 | AC71: 0 | AD71: 0
B72: Other Financial Expense | K72: =55354+3859352 -> 3914706 | L72: 0 | M72: 0 | N72: 0 | O72: 0 | P72: 0 | Q72: 0 | R72: 0 | S72: 0 | T72: 0 | U72: 0 | V72: 0 | W72: 0 | X72: 423521 | Y72: 0 | Z72: 0 | AA72: 0 | AB72: 0 | AC72: 0 | AD72: 0
B73: Fees and Commission Expense | L73: 0 | M73: 0 | N73: 0 | O73: 0 | P73: 1609627.8 | Q73: 1677369.9 | R73: 1692345.5 | S73: 1717195.3 | T73: 1739215.1 | U73: 1752415.1 | V73: 2093085.1 | W73: 1817521.1 | Y73: 11604 | Z73: 44684 | AA73: 72932.3 | AB73: 110290.3 | AC73: 132029.8 | AD73: 145581.8
B74: Other Expense | L74: 37465.9 | M74: 80100.1 | N74: 144751.8 | O74: 195361.8 | P74: 0 | Q74: 0 | R74: 0 | S74: 0 | T74: 0 | U74: 0 | V74: 0 | W74: 0 | Y74: 0 | Z74: 0 | AA74: 0 | AB74: 0 | AC74: 0 | AD74: 0
B75: Net Financial Income | J75: =J59-J68 -> 13044704 | K75: =K59-K68 -> 54180569 | L75: =L59-L68 -> 9806655.9 | M75: =M59-M68 -> 23227762 | N75: =N59-N68 -> 38018147 | O75: =O59-O68 -> 51446623 | P75: =P59-P68 -> 66258759 | Q75: =Q59-Q68 -> 93040347 | ... AD75: =AD59-AD68 -> 2.5390722e+08
B76: Allowance For Loan Loss | J76: =J77 -> 0 | K76: =K77 -> 7744702 | L76: =L77 -> 3000000 | M76: =M77 -> 6000000 | N76: =N77 -> 10559607 | O76: =O77 -> 14720453 | P76: =P77 -> 19958883 | Q76: =Q77 -> 15031250 | ... AD76: =AD77 -> 36717594
B77: Provsion for Loan Losses | K77: 7744702 | L77: 3000000 | M77: 6000000 | N77: 10559607 | O77: 14720453 | P77: 19958883 | Q77: 15031250 | R77: 18252352 | S77: 24399870 | T77: 28155252 | U77: 31655020 | V77: 35370988 | W77: 37819015 | X77: 37819015 | Y77: 7811369.4 | Z77: 12474718 | AA77: 15522985 | AB77: 23332776 | AC77: 30075838 | AD77: 36717594
B78: Value of Loans Recovered | L78: 0 | M78: 0 | N78: 0 | O78: 0 | P78: 0 | Q78: 0 | R78: 0 | S78: 0 | T78: 0 | U78: 0 | V78: 0 | W78: 0 | Y78: 0 | Z78: 0 | AA78: 0 | AB78: 0 | AC78: 0 | AD78: 0
B79: Operating Expenses | J79: =J80+J81+J82+J83+J84 -> 782036 | K79: =K80+K81+K82+K83+K84 -> 3168454 | L79: =L80+L81+L82+L83+L84 -> 107656.67 | M79: =M80+M81+M82+M83+M84 -> 695927.34 | N79: =N80+N81+N82+N83+N84 -> 1201955 | O79: =O80+O81+O82+O83+O84 -> 6757459.7 | P79: =P80+P81+P82+P83+P84 -> 8591573.8 | Q79: =Q80+Q81+Q82+Q83+Q84 -> 10325229 | ... AD79: =AD80+AD81+AD82+AD83+AD84 -> 17295890
B80: Personnel Expenses | L80: 0 | M80: 10200 | N80: 10200 | O80: 10200 | P80: 223650 | Q80: 249650 | R80: 254650 | S80: 254650 | T80: 254650 | U80: 254650 | V80: 254650 | W80: 254650 | X80: =173450+81200+33800 -> 288450 | Y80: 0 | Z80: 0 | AA80: 0 | AB80: 0 | AC80: 0 | AD80: 69600
B81: Governance Expenses | L81: 0 | M81: 4000 | N81: 68600 | O81: 72600 | P81: 72600 | Q81: 80100 | R81: 80100 | S81: 80100 | T81: 80100 | U81: 80100 | V81: 80100 | W81: 906100 | X81: 906100 | Y81: 0 | Z81: 8000 | AA81: 276000 | AB81: 276000 | AC81: 288000 | AD81: 288000
B82: Marketing Expenses | L82: 0 | M82: 0 | N82: 0 | O82: 0 | P82: 0 | Q82: 0 | R82: 0 | S82: 0 | T82: 0 | U82: 0 | V82: 0 | W82: 0 | X82: 327290 | Y82: 0 | Z82: 0 | AA82: 0 | AB82: 0 | AC82: 0 | AD82: 0
B83: Depreciation and Amortization Charges | L83: 0 | M83: 0 | N83: 0 | O83: 0 | P83: 0 | Q83: 0 | R83: 0 | S83: 0 | T83: 0 | U83: 0 | V83: 0 | W83: 0 | X83: 0 | Y83: 0 | Z83: 0 | AA83: 0 | AB83: 0 | AC83: 0 | AD83: 0
B84: Administrative Expenses | J84: =64035+718001 -> 782036 | K84: 3168454 | L84: 107656.67 | M84: 681727.34 | N84: 1123155 | O84: 6674659.7 | P84: 8295323.8 | Q84: 9995478.7 | R84: 10382105 | S84: 10742572 | T84: 12277886 | U84: 12985113 | V84: 15245427 | W84: 20199447 | X84: =13760772-327290-288450 -> 13145032 | Y84: 724906.8 | Z84: 795555 | AA84: 3135021.5 | AB84: 9410998.2 | AC84: 11085076 | AD84: 16938290
B85: Net Operating Income | J85: =J75-J79-J76 -> 12262668 | K85: =K75-K79-K76 -> 43267413 | L85: =L75-L79-L76 -> 6698999.2 | M85: =M75-M79-M76 -> 16531835 | N85: =N75-N79-N76 -> 26256585 | O85: =O75-O79-O76 -> 29968710 | P85: =P75-P79-P76 -> 37708302 | Q85: =Q75-Q79-Q76 -> 67683868 | ... AD85: =AD75-AD79-AD76 -> 1.9989374e+08
B86: Net Non Operating Income | J86: =J87-J88 -> 0 | W86: =W87+W88 -> 0 | X86: =X87+X88 -> 0 | Y86: =Y87+Y88 -> 0 | Z86: =Z87+Z88 -> 0 | AA86: =AA87+AA88 -> 0 | AB86: =AB87+AB88 -> 0 | AC86: =AC87+AC88 -> 0 | AD86: =AD87+AD88 -> 0
B87: Non Operating Income | L87: 0 | M87: 0 | N87: 0 | O87: 0 | P87: 0 | Q87: 0 | R87: 0 | S87: 0 | T87: 0 | U87: 0 | V87: 0 | W87: 0 | Y87: 0 | Z87: 0 | AA87: 0 | AB87: 0 | AC87: 0 | AD87: 0
B88: Non Operating Expense | L88: 0 | M88: 0 | N88: 0 | O88: 0 | P88: 0 | Q88: 0 | R88: 0 | S88: 0 | T88: 0 | U88: 0 | V88: 0 | W88: 0 | Y88: 0 | Z88: 0 | AA88: 0 | AB88: 0 | AC88: 0 | AD88: 0
B89: Net Income before tax | J89: =J85+J86 -> 12262668 | K89: =K85+K86 -> 43267413 | L89: =L85+L86 -> 6698999.2 | M89: =M85+M86 -> 16531835 | N89: =N85+N86 -> 26256585 | O89: =O85+O86 -> 29968710 | P89: =P85+P86 -> 37708302 | Q89: =Q85+Q86 -> 67683868 | ... AD89: =AD85+AD86 -> 1.9989374e+08
B90: Taxes | J90: 2163718 | K90: 4623009.4 | L90: 0 | M90: 0 | N90: 0 | O90: 0 | P90: 0 | Q90: 0 | R90: 0 | S90: 0 | T90: 0 | U90: 0 | V90: 0 | W90: 0 | X90: 19754082 | Y90: 0 | Z90: 0 | AA90: 0 | AB90: 0 | AC90: 0 | AD90: 0
B91: Net Income After Tax Before Donations | J91: =J89-J90 -> 10098950 | K91: =K89-K90 -> 38644404 | L91: =L89-L90 -> 6698999.2 | M91: =M89-M90 -> 16531835 | N91: =N89-N90 -> 26256585 | O91: =O89-O90 -> 29968710 | P91: =P89-P90 -> 37708302 | Q91: =Q89-Q90 -> 67683868 | ... AD91: =AD89-AD90 -> 1.9989374e+08
B92: Donations | J92: 0 | L92: 0 | M92: 0 | N92: 0 | O92: 0 | P92: 0 | Q92: 0 | R92: 0 | S92: 0 | T92: 0 | U92: 0 | V92: 0 | W92: 0 | Y92: 0 | Z92: 0 | AA92: 0 | AB92: 0 | AC92: 0 | AD92: 0
B93: Net Income | J93: =J91-J92 -> 10098950 | K93: =K91-K92 -> 38644404 | L93: =L91-L92 -> 6698999.2 | M93: =M91-M92 -> 16531835 | N93: =N91-N92 -> 26256585 | O93: =O91-O92 -> 29968710 | P93: =P91-P92 -> 37708302 | Q93: =Q91-Q92 -> 67683868 | ... AD93: =AD91-AD92 -> 1.9989374e+08

Sheet GDP
A1: Share of Financial Sector Total Assets to National GDP
A2: Year | B2: 2017 | D2: 2018 | F2: 2019 | H2: 2020
A3: Nominal GDP(Millions) | B3: 8144373 | D3: 8904984 | F3: 9740400 | H3: 10266381
A4: Industry/Indicator | B4: Total Assets KShs B) | C4: Share of GDP | D4: Total Assets KShs B) | E4: Share of GDP | F4: Total Assets KShs B) | G4: Share of GDP | H4: Total Assets KShs B) | I4: Share of GDP
A5: Banks excl MFB | B5: 4002.74 | C5: 49.15 | D5: 4408.59 | E5: 49.51 | F5: 4832.3 | G5: 49.61 | H5: 5420.1 | I5: 52.79
A6: Microfinance Banks | B6: 67.6 | C6: 0.83 | D6: 70.75 | E6: 0.79 | F6: 76.35 | G6: 0.78 | H6: 74.88 | I6: 0.73
A7: Insurance | B7: 590.95 | C7: 7.26 | D7: 637.41 | E7: 7.14 | F7: 705.84 | G7: 7.25 | H7: 761.34 | I7: 7.42
A8: Pension | B8: 1081.1 | C8: 13.27 | D8: 1166.34 | E8: 13.1 | F8: 1298.19 | G8: 13.33 | H8: 1398.95 | I8: 13.63
A9: SACCO's | B9: 442.9 | C9: 5.44 | D9: 493.82 | E9: 5.55 | F9: 556.71 | G9: 5.72 | H9: 627.68 | I9: 6.11

Sheet Sheet2
A1: KEY FINANCIAL SECTOR PERFORMANCE INDICATORS
B2: DT-SACCOS | E2: COMMERCIAL BANKS | H2: MICROFINANCE BANKS
A3: PARAMETER | B3: 2018 | C3: 2019 | D3: 2020 | E3: 2018 | F3: 2019 | G3: 2020 | H3: 2018 | I3: 2019 | J3: 2020
A4: No of Institutions | B4: 174 | C4: 172 | D4: 175 | E4: 40 | F4: 39 | G4: 39 | H4: 13 | I4: 14 | J4: 14
A5: No of branches | B5: 504 | C5: 526 | D5: 537 | E5: 1505 | F5: 1490 | G5: 1502 | H5: 118 | I5: 123 | J5: 120
A6: Total Asset (KShs B) | B6: 495.25 | C6: 556.71 | D6: 627.68 | E6: 4446.1 | F6: 4832.3 | G6: 5405.75 | H6: 70.75 | I6: 76.35 | J6: 74.88
A7: Gross Loans (KShs B) | B7: 374.28 | C7: 419.55 | D7: 473.74 | E7: 2567.3 | F7: 2774.6 | G7: 3006.1 | H7: 49.36 | I7: 50.45 | J7: 48.85
A8: Customer deposits | B8: 341.91 | C8: 380.44 | D8: 430.11 | E8: 3332.4 | F8: 3554.4 | G8: 4011.32 | H8: 40.96 | I8: 43.94 | J8: 49.36
A9: NPL | B9: 0.063 | C9: 0.0615 | D9: 0.0839 | E9: 0.1203 | F9: 0.1201 | G9: 0.145 | H9: 0.2004 | I9: 0.195 | J9: 0.266

Sheet Sheet4
A1: PARAMETER | B1: 2018 | C1: YtY % change | D1: 2019 | E1: YtY % change | F1: 2020
A2: No of DTS | B2: 174 | D2: 172 | F2: 175
A3: Total Assets | B3: 495.25 | C3: 0.1241 | D3: 556.71 | E3: 0.1275 | F3: 627.68
A4: Total Deposits | B4: 341.91 | C4: 0.1127 | D4: 380.44 | E4: 0.1341 | F4: 431.46
A5: Gross Loans | B5: 374.29 | C5: 0.1209 | D5: 419.55 | E5: 0.1316 | F5: 474.77
A6: Capital & Reserves | B6: 83.76 | C6: 0.1647 | D6: 97.55 | E6: 0.1818 | F6: 115.28
A7: Core Capital | B7: 74.37 | C7: 0.0649 | D7: 79.2 | E7: 0.2341 | F7: 97.74

Sheet FSI
A1: FINANCIAL SOUNDNESS INDICATORS | B1: Prescribed Minimum | C1: 2016 | D1: 2017 | E1: 2018 | F1: 2019 | G1: 2020
A2: CAPITAL ADEQUACY | B2: No of DTS | C2: 175 | D2: 174 | E2: 172 | F2: 172 | G2: 175
A3: Core Capital | B3: KShs 10 M | C3: 54.94 | D3: 64.25 | E3: 74.37 | F3: 79.2 | G3: 97.74
A4: Core Capital/Total Assets | B4: 0.1 | C4: 0.1396 | D4: 0.1453 | E4: 0.1502 | F4: 0.1423 | G4: 0.1557
A5: Core Capital/Total Deposits | B5: 0.08 | C5: 0.2016 | D5: 0.2105 | E5: 0.2175 | F5: 0.2082 | G5: 0.2265
A6: Institutional Capital/Total Assets | B6: 0.08 | C6: 0.0771 | D6: 0.0818 | E6: 0.085 | F6: 0.1063 | G6: 0.1139
A7: ASSET QUALITY
A8: Non-performing loans to Gross Loans | C8: 0.0523 | D8: 0.0614 | E8: 0.063 | F8: 0.0615 | G8: 0.0839
A9: NPL net of provisions to Core capital | C9: 0.0763 | D9: 0.099 | E9: 0.0927 | F9: 0.085 | G9: 0.1018
A10: Earning Assets to Total Assets | C10: 0.8071 | D10: 0.785 | E10: 0.7768 | F10: 0.769 | G10: 0.7962
A11: EARNING RATING
A12: Return on Assets | C12: 0.0245 | D12: 0.0269 | E12: 0.024 | F12: 0.026 | G12: 0.0265
A13: Cost Income ratio | C13: 0.628 | D13: 0.661 | E13: 0.621 | F13: 0.5767 | G13: 0.5672
A14: Operating Expense/Total Assets | C14: 0.0544 | D14: 0.0529 | E14: 0.0462 | F14: 0.0475 | G14: 0.045
A15: LIQUIDITY
A16: Liquid Assets/Short term Liabilities | C16: 0.4995 | D16: 0.541 | E16: 0.5268 | F16: 0.5092 | G16: 0.485
A17: Liquid Assets/Total Deposits | C17: 0.1805 | D17: 0.1717 | E17: 0.1705 | F17: 0.17 | G17: 0.2099
A18: Gross Loans/Total Deposits | C18: 1.0839 | D18: 0.1049 | E18: 1.0947 | F18: 1.1028 | G18: 1.1004

Sheet Financials
B2: DEFENCE SACCO FINANCIALS | I2: Base
B3: Year | C3: 2013 | D3: 2014 | E3: Audit 2015 | F3: Audit 2016 | G3: Audit 2017 | H3: Audit 2018 | I3: Audited 2020 | J3: Audited 2021 | K3: 44562 | L3: 44593 | M3: 44621 | N3: 44652 | O3: 44682 | P3: 44713 | Q3: 44743 | R3: 44774 | S3: 44805 | T3: 44835 | U3: 44866 | V3: 44896 | W3: Audited-2022 | X3: 44949 | Y3: 44980 | Z3: 45008 | AA3: 45039 | AB3: 45069 | AC3: 45100 | AD3: 45130 | AE3: 45161 | AF3: 45192
A4: 1 | B4: Membership | C4: 10344 | D4: 10824 | E4: 11521
A5: 2 | B5: Total Assets | C5: =Trend!C27 -> 0 | D5: =Trend!D27 -> 0 | E5: =Trend!E27 -> 0 | F5: =Trend!F27 -> 0 | G5: =Trend!G27 -> 0 | H5: =Trend!H27 -> 0 | I5: =Trend!J27 -> 459363957 | J5: =Trend!K27 -> 1.1708681e+09 | K5: =Trend!L27 -> 1.2819615e+09 | L5: =Trend!M27 -> 1.4032197e+09 | M5: =Trend!N27 -> 1.515489e+09 | N5: =Trend!O27 -> 1.6506892e+09 | O5: =Trend!P27 -> 1.8382284e+09 | P5: =Trend!Q27 -> 2.0979925e+09 | ... AC5: =Trend!AD27 -> 4.1446316e+09
A6: 3 | B6: Total Deposits | C6: =Trend!C31 -> 0 | D6: =Trend!D31 -> 0 | E6: =Trend!E31 -> 0 | F6: =Trend!F31 -> 0 | G6: =Trend!G31 -> 0 | H6: =Trend!H31 -> 0 | I6: =Trend!J31 -> 291131418 | J6: =Trend!K31 -> 9.2693166e+08 | K6: =Trend!L31 -> 1.0277447e+09 | L6: =Trend!M31 -> 1.1533595e+09 | M6: =Trend!N31 -> 1.1049289e+09 | N6: =Trend!O31 -> 1.2310698e+09 | O6: =Trend!P31 -> 1.4003395e+09 | P6: =Trend!Q31 -> 1.6254503e+09 | ... AC6: =Trend!AD31 -> 3.03594e+09
A7: 3.1 | B7: Deposits-Members(BOSA) | C7: =Trend!C30 -> 0 | D7: =Trend!D30 -> 0 | E7: =Trend!E30 -> 0 | F7: =Trend!F30 -> 0 | G7: =Trend!G30 -> 0 | H7: =Trend!H30 -> 0 | I7: =Trend!J30 -> 291131418 | J7: =Trend!K30 -> 926612134 | K7: =Trend!L30 -> 1.0137507e+09 | L7: =Trend!M30 -> 1.103747e+09 | M7: =Trend!N30 -> 1.050628e+09 | N7: =Trend!O30 -> 1.1557788e+09 | O7: =Trend!P30 -> 1.2593688e+09 | P7: =Trend!Q30 -> 1.3679773e+09 | ... AC7: =Trend!AD30 -> 2.7663758e+09
A8: 3.2 | B8: Deposits-Customers(FOSA) | C8: =Trend!C28 -> 0 | D8: =Trend!D28 -> 0 | E8: =Trend!E28 -> 0 | F8: =Trend!F28 -> 0 | G8: =Trend!G28 -> 0 | H8: =Trend!H28 -> 0 | I8: =Trend!J28 -> 0 | J8: =Trend!K28 -> 319521.55 | K8: =Trend!L28 -> 13983820 | L8: =Trend!M28 -> 49599559 | M8: =Trend!N28 -> 54281773 | N8: =Trend!O28 -> 75270723 | O8: =Trend!P28 -> 1.4092141e+08 | P8: =Trend!Q28 -> 2.573535e+08 | ... AC8: =Trend!AD28 -> 2.6955472e+08
A9: 4 | B9: External Borrowing | C9: =Trend!C38 -> 0 | D9: =Trend!D38 -> 0 | E9: =Trend!E38 -> 0 | F9: =Trend!F38 -> 0 | G9: =Trend!G38 -> 0 | H9: =Trend!H38 -> 0 | I9: =Trend!J38 -> 90000000 | J9: =Trend!K38 -> 30000000 | K9: =Trend!L38 -> 30000000 | L9: =Trend!M38 -> 30000000 | M9: =Trend!N38 -> 30000000 | N9: =Trend!O38 -> 30000000 | O9: =Trend!P38 -> 30000000 | P9: =Trend!Q38 -> 30000000 | ... AC9: =Trend!AD38 -> 30000000
A10: 4.1 | B10: Short term Liabilities | C10: =Trend!C33+Trend!C34+Trend!C35+Trend!C37 -> 0 | D10: =Trend!D33+Trend!D34+Trend!D35+Trend!D37 -> 0 | E10: =Trend!E33+Trend!E34+Trend!E35+Trend!E37 -> 0 | F10: =Trend!F33+Trend!F34+Trend!F35+Trend!F37 -> 0 | G10: =Trend!G33+Trend!G34+Trend!G35+Trend!G37 -> 0 | H10: =Trend!H33+Trend!H34+Trend!H35+Trend!H37 -> 0 | I10: =Trend!J33+Trend!J34+Trend!J35+Trend!J37 -> 18674579 | J10: =Trend!K33+Trend!K34+Trend!K35+Trend!K37 -> 65695469 | K10: =Trend!L33+Trend!L34+Trend!L35+Trend!L37 -> 69271776 | L10: =Trend!M33+Trend!M34+Trend!M35+Trend!M37 -> 55051193 | M10: =Trend!N33+Trend!N34+Trend!N35+Trend!N37 -> 53997975 | N10: =Trend!O33+Trend!O34+Trend!O35+Trend!O37 -> 58767715 | O10: =Trend!P33+Trend!P34+Trend!P35+Trend!P37 -> 63678348 | P10: =Trend!Q33+Trend!Q34+Trend!Q35+Trend!Q37 -> 69278714 | ... AC10: =Trend!AD33+Trend!AD34+Trend!AD35+Trend!AD37 -> 1.4135978e+08
A12: 5 | B12: Share capital and Reserves
A13: 5.1 | B13: Core Capital | C13: =C16-C28 -> 0 | D13: =D16-D28 -> 0 | E13: =E16-E28 -> 0 | F13: =F16-F28 -> 0 | G13: =G16-G28 -> 0 | H13: =H16-H28 -> 0 | I13: =I16-I28 -> 50822603 | J13: =J16-J28 -> 148240999 | ... AC13: =AC16-AC28 -> 8.5458182e+08
A14: 5.2 | B14: Institutional Capital | C14: =C13-C17 -> 0 | D14: =D13-D17 -> 0 | E14: =E13-E17 -> 0 | F14: =F13-F17 -> 0 | G14: =G13-G17 -> 0 | H14: =H13-H17 -> 0 | I14: =I13-I17 -> 7635765 | J14: =J13-J17 -> 74480513 | ... AC14: =AC13-AC17 -> 3.0067171e+08
A16: 5.3 | B16: Total Capital | C16: =SUM(C17:C20) -> 0 | D16: =SUM(D17:D20) -> 0 | E16: =SUM(E17:E20) -> 0 | F16: =SUM(F17:F20) -> 0 | G16: =SUM(G17:G20) -> 0 | H16: =SUM(H17:H20) -> 0 | I16: =SUM(I17:I20) -> 50822603 | J16: =SUM(J17:J20) -> 148240999 | ... AC16: =SUM(AC17:AC20) -> 9.0558182e+08
A17: 5.3.1 | B17: Members Share Capital | C17: =Trend!C40 -> 0 | D17: =Trend!D40 -> 0 | E17: =Trend!E40 -> 0 | F17: =Trend!F40 -> 0 | G17: =Trend!G40 -> 0 | H17: =Trend!H40 -> 0 | I17: =Trend!J40 -> 43186838 | J17: =Trend!K40 -> 73760486 | K17: =Trend!L40 -> 73765486 | L17: =Trend!M40 -> 73796626 | M17: =Trend!N40 -> 225824998 | N17: =Trend!O40 -> 226402490 | O17: =Trend!P40 -> 232021774 | P17: =Trend!Q40 -> 2.3209907e+08 | ... AC17: =Trend!AD40 -> 5.5391011e+08
A18: 5.3.3 | B18: Retained Earnings | C18: =Trend!C42 -> 0 | D18: =Trend!D42 -> 0 | E18: =Trend!E42 -> 0 | F18: =Trend!F42 -> 0 | G18: =Trend!G42 -> 0 | H18: =Trend!H42 -> 0 | I18: =Trend!J42 -> 5615976 | J18: =Trend!K42 -> 32981843 | K18: =Trend!L42 -> 39775842 | L18: =Trend!M42 -> 49608677 | M18: =Trend!N42 -> 59333428 | N18: =Trend!O42 -> 63045553 | O18: =Trend!P42 -> 70785145 | P18: =Trend!Q42 -> 1.0076071e+08 | ... AC18: =Trend!AD42 -> 3.1630583e+08
A19: 5.3.5 | B19: Statutory Reserves | C19: =Trend!C46 -> 0 | D19: =Trend!D46 -> 0 | E19: =Trend!E46 -> 0 | F19: =Trend!F46 -> 0 | G19: =Trend!G46 -> 0 | H19: =Trend!H46 -> 0 | I19: =Trend!J46 -> 2019789 | J19: =Trend!K46 -> 9748670 | K19: =Trend!L46 -> 9653670.2 | L19: =Trend!M46 -> 9653670.2 | M19: =Trend!N46 -> 9653670.2 | N19: =Trend!O46 -> 9653670.2 | O19: =Trend!P46 -> 9653670.2 | P19: =Trend!Q46 -> 9653670.2 | ... AC19: =Trend!AD46 -> 35365874
A20: 5.3.6 | B20: Capital Reserve | C20: =Trend!C47 -> 0 | D20: =Trend!D47 -> 0 | E20: =Trend!E47 -> 0 | F20: =Trend!F47 -> 0 | G20: =Trend!G47 -> 0 | H20: =Trend!H47 -> 0 | I20: =Trend!J47 -> 0 | J20: =Trend!K47 -> 31750000 | K20: =Trend!L47 -> 0 | L20: =Trend!M47 -> 0 | M20: =Trend!N47 -> 0 | N20: =Trend!O47 -> 0 | O20: =Trend!P47 -> 0 | P20: =Trend!Q47 -> 0 | ... AC20: =Trend!AD47 -> 0
A21: Capital grant | W21: 31750000
A22: 5.3.7 | B22: Supplementary Capital & reserves
A23: a | B23: Proposed Dividends | C23: =Trend!C69+Trend!C70 -> 0 | D23: =Trend!D69+Trend!D70 -> 0 | E23: =Trend!E69+Trend!E70 -> 0 | F23: =Trend!F69+Trend!F70 -> 0 | G23: =Trend!G69+Trend!G70 -> 0 | H23: =Trend!H69+Trend!H70 -> 0 | I23: =Trend!J69+Trend!J70 -> 13028923 | J23: =Trend!K69+Trend!K70 -> 17052616 | K23: =Trend!L69+Trend!L70 -> 0 | L23: =Trend!M69+Trend!M70 -> 0 | M23: =Trend!N69+Trend!N70 -> 0 | N23: =Trend!O69+Trend!O70 -> 0 | O23: =Trend!P69+Trend!P70 -> 0 | P23: =Trend!Q69+Trend!Q70 -> 0 | ... AC23: =Trend!AD69+Trend!AD70 -> 0
A24: b
A26: 6 | B26: Investments | C26: =SUM(C27:C28) -> 0 | D26: =SUM(D27:D28) -> 0 | E26: =SUM(E27:E28) -> 0 | F26: =SUM(F27:F28) -> 0 | G26: =SUM(G27:G28) -> 0 | H26: =SUM(H27:H28) -> 0 | I26: =SUM(I27:I28) -> 10000000 | J26: =SUM(J27:J28) -> 10000000 | ... AC26: =SUM(AC27:AC28) -> 51000000
A27: 6.1 | B27: Investments in Coop bank, CIC, Kuscco, Kerussu & Codic | C27: =Trend!C12 -> 0 | D27: =Trend!D12 -> 0 | E27: =Trend!E12 -> 0 | F27: =Trend!F12 -> 0 | G27: =Trend!G12 -> 0 | H27: =Trend!H12 -> 0 | I27: =Trend!J12 -> 10000000 | J27: =Trend!K12 -> 10000000 | K27: =Trend!L12 -> 50000000 | L27: =Trend!M12 -> 51582795 | M27: =Trend!N12 -> 51582795 | N27: =Trend!O12 -> 51582795 | O27: =Trend!P12 -> 51582795 | P27: =Trend!Q12 -> 53116127 | ... AC27: =Trend!AD12 -> 0
A28: 6.2 | B28: Equity Investments (at cost) | C28: =Trend!C13 -> 0 | D28: =Trend!D13 -> 0 | E28: =Trend!E13 -> 0 | F28: =Trend!F13 -> 0 | G28: =Trend!G13 -> 0 | H28: =Trend!H13 -> 0 | I28: =Trend!J13 -> 0 | J28: =Trend!K13 -> 0 | K28: =Trend!L13 -> 10000000 | L28: =Trend!M13 -> 10000000 | M28: =Trend!N13 -> 10000000 | N28: =Trend!O13 -> 10000000 | O28: =Trend!P13 -> 51000000 | P28: =Trend!Q13 -> 51000000 | ... AC28: =Trend!AD13 -> 51000000
A29: 6.3 | B29: Deposits in KUSCCO CFP
A31: 7 | B31: Net Loans & advances | C31: =C32-C33 -> 0 | D31: =D32-D33 -> 0 | E31: =E32-E33 -> 0 | F31: =F32-F33 -> 0 | G31: =G32-G33 -> 0 | H31: =H32-H33 -> 0 | I31: =I32-I33 -> 67566895 | J31: =J32-J33 -> 5.5293772e+08 | ... AC31: =AC32-AC33 -> 3.2002342e+09
A32: 7.1 | B32: Gross Loans & advances | C32: =+Trend!C15 -> 0 | D32: =+Trend!D15 -> 0 | E32: =+Trend!E15 -> 0 | F32: =+Trend!F15 -> 0 | G32: =+Trend!G15 -> 0 | H32: =+Trend!H15 -> 0 | I32: =+Trend!J15 -> 67566895 | J32: =+Trend!K15 -> 5.5293772e+08 | K32: =+Trend!L15 -> 6.0713821e+08 | L32: =+Trend!M15 -> 654081705 | M32: =+Trend!N15 -> 7.2585877e+08 | N32: =+Trend!O15 -> 8.2786399e+08 | O32: =+Trend!P15 -> 9.4205761e+08 | P32: =+Trend!Q15 -> 1.0602147e+09 | ... AC32: =+Trend!AD15 -> 3.2831912e+09
A33: 7.3 | B33: Allowance for loan losses | C33: =+Trend!C16 -> 0 | D33: =+Trend!D16 -> 0 | E33: =+Trend!E16 -> 0 | F33: =+Trend!F16 -> 0 | G33: =+Trend!G16 -> 0 | H33: =+Trend!H16 -> 0 | I33: =+Trend!J16 -> 0 | J33: =+Trend!K16 -> 0 | K33: =+Trend!L16 -> 11420371 | L33: =+Trend!M16 -> 14420371 | M33: =+Trend!N16 -> 18979978 | N33: =+Trend!O16 -> 23140824 | O33: =+Trend!P16 -> 28379254 | P33: =+Trend!Q16 -> 23451622 | ... AC33: =+Trend!AD16 -> 82956980
A34: 7.4 | B34: Non Performing Loans NPL30 | F34: 15659839 | G34: =9488181.59+650188.65+8950044.59 -> 19088415 | H34: =9488181.59+650188.65+8950044.59 -> 19088415
A35: 7.5666667 | B35: Non Performing Loans A/L NPL30
A36: 7.7166667 | B36: Required loan loss provision
A37: 7.8666667 | B37: Cash and Cash equipments | C37: =Trend!C5 -> 0 | D37: =Trend!D5 -> 0 | E37: =Trend!E5 -> 0 | F37: =Trend!F5 -> 0 | G37: =Trend!G5 -> 0 | H37: =Trend!H5 -> 0 | I37: =Trend!J5 -> 375933615 | J37: =Trend!K5 -> 583646239 | K37: =Trend!L5 -> 5.3005126e+08 | L37: =Trend!M5 -> 4.1482331e+08 | M37: =Trend!N5 -> 6.7492501e+08 | N37: =Trend!O5 -> 6.5037254e+08 | O37: =Trend!P5 -> 6.8629423e+08 | P37: =Trend!Q5 -> 7.0539082e+08 | ... AC37: =Trend!AD5 -> 8.2005767e+08
A39: 8 | B39: Non-Earning Assets | C39: =Trend!C8+Trend!C21 -> 0 | D39: =Trend!D8+Trend!D21 -> 0 | E39: =Trend!E8+Trend!E21 -> 0 | F39: =Trend!F8+Trend!F21 -> 0 | G39: =Trend!G8+Trend!G21 -> 0 | H39: =Trend!H8+Trend!H21 -> 0 | I39: =Trend!J8+Trend!J21 -> 5863447 | J39: =Trend!K8+Trend!K21 -> 24284162 | K39: =Trend!L8+Trend!L21 -> 24779370 | L39: =Trend!M8+Trend!M21 -> 2.1566836e+08 | M39: =Trend!N8+Trend!N21 -> 618454.57 | N39: =Trend!O8+Trend!O21 -> 2094825 | O39: =Trend!P8+Trend!P21 -> 3757175.1 | P39: =Trend!Q8+Trend!Q21 -> 1.1976176e+08 | ... AC39: =Trend!AD8+Trend!AD21 -> 9758571.4
A40: 8.1 | B40: Property and Equipment | C40: =Trend!C23 -> 0 | D40: =Trend!D23 -> 0 | E40: =Trend!E23 -> 0 | F40: =Trend!F23 -> 0 | G40: =Trend!G23 -> 0 | H40: =Trend!H23 -> 0 | I40: =Trend!J23 -> 0 | J40: =Trend!K23 -> 0 | K40: =Trend!L23 -> 0 | L40: =Trend!M23 -> 0 | M40: =Trend!N23 -> 0 | N40: =Trend!O23 -> 0 | O40: =Trend!P23 -> 0 | P40: =Trend!Q23 -> 0 | ... AC40: =Trend!AD23 -> 0
A41: 8.2 | B41: Land and Building
A43: 9 | B43: Turnover | C43: =C44+C45+C46 -> 0 | D43: =D44+D45+D46 -> 0 | E43: =E44+E45+E46 -> 0 | F43: =F44+F45+F46 -> 0 | G43: =G44+G45+G46 -> 0 | H43: =H44+H45+H46 -> 0 | I43: =I44+I45+I46 -> 26073627 | J43: =J44+J45+J46 -> 75147891 | ... AC43: =AC44+AC45+AC46 -> 2.5405281e+08
A44: 9.1 | B44: Loan Interest | C44: =Trend!C61 -> 0 | D44: =Trend!D61 -> 0 | E44: =Trend!E61 -> 0 | F44: =Trend!F61 -> 0 | G44: =Trend!G61 -> 0 | H44: =Trend!H61 -> 0 | I44: =Trend!J61 -> 2051377 | J44: =Trend!K61 -> 30031682 | K44: =Trend!L61 -> 5791010 | L44: =Trend!M61 -> 12004631 | M44: =Trend!N61 -> 18456061 | N44: =Trend!O61 -> 26231070 | O44: =Trend!P61 -> 34864959 | P44: =Trend!Q61 -> 44097122 | ... AC44: =Trend!AD61 -> 1.8222278e+08
B45: Income from investments | C45: =Trend!C62 -> 0 | D45: =Trend!D62 -> 0 | E45: =Trend!E62 -> 0 | F45: =Trend!F62 -> 0 | G45: =Trend!G62 -> 0 | H45: =Trend!H62 -> 0 | I45: =Trend!J62 -> 0 | J45: =Trend!K62 -> 0 | K45: =Trend!L62 -> 596470 | L45: =Trend!M62 -> 1283490 | M45: =Trend!N62 -> 2143432 | N45: =Trend!O62 -> 3243754.1 | O45: =Trend!P62 -> 4481696.4 | P45: =Trend!Q62 -> 5806191.4 | ... AC45: =Trend!AD62 -> 20129664
A46: 9.2 | B46: Fees & Commissions | C46: =Trend!C63 -> 0 | D46: =Trend!D63 -> 0 | E46: =Trend!E63 -> 0 | F46: =Trend!F63 -> 0 | G46: =Trend!G63 -> 0 | H46: =Trend!H63 -> 0 | I46: =Trend!J63 -> 24022250 | J46: =Trend!K63 -> 45116209 | K46: =Trend!L63 -> 3456641.8 | L46: =Trend!M63 -> 10019741 | M46: =Trend!N63 -> 17563406 | N46: =Trend!O63 -> 22167160 | O46: =Trend!P63 -> 28521731 | P46: =Trend!Q63 -> 44814404 | ... AC46: =Trend!AD63 -> 51700363
B47: Average yield on loans | C47: =C44/C32 -> #DIV/0! | D47: =D44/D32 -> #DIV/0! | E47: =E44/E32 -> #DIV/0! | F47: =F44/F32 -> #DIV/0! | G47: =G44/G32 -> #DIV/0! | H47: =H44/H32 -> #DIV/0! | I47: =I44/I32 -> 0.030360682 | J47: =J44/J32 -> 0.054312955 | ... AC47: =AC44/AC32 -> 0.055501726
A49: 10 | B49: Total Expenses (FinCosts + OpEx) | C49: =SUM(C50:C56) -> 0 | D49: =SUM(D50:D56) -> 0 | E49: =SUM(E50:E56) -> 0 | F49: =SUM(F50:F56) -> 0 | G49: =SUM(G50:G56) -> 0 | H49: =SUM(H50:H56) -> 0 | I49: =SUM(I50:I56) -> 14592995 | J49: =SUM(J50:J56) -> 35048932 | ... AC49: =SUM(AC50:AC56) -> 70809356
A50: 10.1 | B50: Financial Exp. (Interest on deposits) | C50: =Trend!C69 -> 0 | D50: =Trend!D69 -> 0 | E50: =Trend!E69 -> 0 | F50: =Trend!F69 -> 0 | G50: =Trend!G69 -> 0 | H50: =Trend!H69 -> 0 | I50: =Trend!J69 -> 13028923 | J50: =Trend!K69 -> 17052616 | K50: =Trend!L69 -> 0 | L50: =Trend!M69 -> 0 | M50: =Trend!N69 -> 0 | N50: =Trend!O69 -> 0 | O50: =Trend!P69 -> 0 | P50: =Trend!Q69 -> 0 | ... AC50: =Trend!AD69 -> 0
A51: 10.2 | B51: Financial Exp. (Dividends) | C51: =Trend!C71 -> 0 | D51: =Trend!D71 -> 0 | E51: =Trend!E71 -> 0 | F51: =Trend!F71 -> 0 | G51: =Trend!G71 -> 0 | H51: =Trend!H71 -> 0 | I51: =Trend!J71 -> 0 | J51: =Trend!K71 -> 0 | K51: =Trend!L71 -> 0 | L51: =Trend!M71 -> 0 | M51: =Trend!N71 -> 0 | N51: =Trend!O71 -> 0 | O51: =Trend!P71 -> 0 | P51: =Trend!Q71 -> 0 | ... AC51: =Trend!AD71 -> 0
A52: 10.3 | B52: Financial Exp. (Interest on bank loans) | C52: =Trend!C70 -> 0 | D52: =Trend!D70 -> 0 | E52: =Trend!E70 -> 0 | F52: =Trend!F70 -> 0 | G52: =Trend!G70 -> 0 | H52: =Trend!H70 -> 0 | I52: =Trend!J70 -> 0 | J52: =Trend!K70 -> 0 | K52: =Trend!L70 -> 0 | L52: =Trend!M70 -> 0 | M52: =Trend!N70 -> 0 | N52: =Trend!O70 -> 0 | O52: =Trend!P70 -> 0 | P52: =Trend!Q70 -> 0 | ... AC52: =Trend!AD70 -> 0
A53: 10.4 | B53: Other Financial Expenses | C53: =Trend!C72+Trend!C73+Trend!C74 -> 0 | D53: =Trend!D72+Trend!D73+Trend!D74 -> 0 | E53: =Trend!E72+Trend!E73+Trend!E74 -> 0 | F53: =Trend!F72+Trend!F73+Trend!F74 -> 0 | G53: =Trend!G72+Trend!G73+Trend!G74 -> 0 | H53: =Trend!H72+Trend!H73+Trend!H74 -> 0 | I53: =Trend!J72+Trend!J73+Trend!J74 -> 0 | J53: =Trend!K72+Trend!K73+Trend!K74 -> 3914706 | K53: =Trend!L72+Trend!L73+Trend!L74 -> 37465.9 | L53: =Trend!M72+Trend!M73+Trend!M74 -> 80100.1 | M53: =Trend!N72+Trend!N73+Trend!N74 -> 144751.8 | N53: =Trend!O72+Trend!O73+Trend!O74 -> 195361.8 | O53: =Trend!P72+Trend!P73+Trend!P74 -> 1609627.8 | P53: =Trend!Q72+Trend!Q73+Trend!Q74 -> 1677369.9 | ... AC53: =Trend!AD72+Trend!AD73+Trend!AD74 -> 145581.8
A54: 10.5 | B54: Administrative Expenses | C54: =Trend!C84+Trend!C83+Trend!C82+Trend!C80 -> 0 | D54: =Trend!D84+Trend!D83+Trend!D82+Trend!D80 -> 0 | E54: =Trend!E84+Trend!E83+Trend!E82+Trend!E80 -> 0 | F54: =Trend!F84+Trend!F83+Trend!F82+Trend!F80 -> 0 | G54: =Trend!G84+Trend!G83+Trend!G82+Trend!G80 -> 0 | H54: =Trend!H84+Trend!H83+Trend!H82+Trend!H80 -> 0 | I54: =Trend!J84+Trend!J83+Trend!J82+Trend!J80 -> 782036 | J54: =Trend!K84+Trend!K83+Trend!K82+Trend!K80 -> 3168454 | K54: =Trend!L84+Trend!L83+Trend!L82+Trend!L80 -> 107656.67 | L54: =Trend!M84+Trend!M83+Trend!M82+Trend!M80 -> 691927.34 | M54: =Trend!N84+Trend!N83+Trend!N82+Trend!N80 -> 1133355 | N54: =Trend!O84+Trend!O83+Trend!O82+Trend!O80 -> 6684859.7 | O54: =Trend!P84+Trend!P83+Trend!P82+Trend!P80 -> 8518973.8 | P54: =Trend!Q84+Trend!Q83+Trend!Q82+Trend!Q80 -> 10245129 | ... AC54: =Trend!AD84+Trend!AD83+Trend!AD82+Trend!AD80 -> 17007890
A55: 10.6 | B55: Governance Expenses | C55: =Trend!C81 -> 0 | D55: =Trend!D81 -> 0 | E55: =Trend!E81 -> 0 | F55: =Trend!F81 -> 0 | G55: =Trend!G84 -> 0 | H55: =Trend!H84 -> 0 | I55: =Trend!J84 -> 782036 | J55: =Trend!K84 -> 3168454 | K55: =Trend!L84 -> 107656.67 | L55: =Trend!M84 -> 681727.34 | M55: =Trend!N84 -> 1123155 | N55: =Trend!O84 -> 6674659.7 | O55: =Trend!P84 -> 8295323.8 | P55: =Trend!Q84 -> 9995478.7 | ... AC55: =Trend!AD84 -> 16938290
B56: LLP | C56: =Trend!C76 -> 0 | D56: =Trend!D76 -> 0 | E56: =Trend!E76 -> 0 | F56: =Trend!F76 -> 0 | G56: =Trend!G76 -> 0 | H56: =Trend!H76 -> 0 | I56: =Trend!J76 -> 0 | J56: =Trend!K76 -> 7744702 | K56: =Trend!L76 -> 3000000 | L56: =Trend!M76 -> 6000000 | M56: =Trend!N76 -> 10559607 | N56: =Trend!O76 -> 14720453 | O56: =Trend!P76 -> 19958883 | P56: =Trend!Q76 -> 15031250 | ... AC56: =Trend!AD76 -> 36717594
B58: Net Surplus | C58: =Trend!C93 -> 0 | D58: =Trend!D93 -> 0 | E58: =Trend!E93 -> 0 | F58: =Trend!F93 -> 0 | G58: =Trend!G93 -> 0 | H58: =Trend!H93 -> 0 | I58: =Trend!J93 -> 10098950 | J58: =Trend!K93 -> 38644404 | K58: =Trend!L93 -> 6698999.2 | L58: =Trend!M93 -> 16531835 | M58: =Trend!N93 -> 26256585 | N58: =Trend!O93 -> 29968710 | O58: =Trend!P93 -> 37708302 | P58: =Trend!Q93 -> 67683868 | ... AC58: =Trend!AD93 -> 1.9989374e+08
B59: Total Income | F59: =Trend!F59+Trend!F78+Trend!F87 -> 0 | G59: =Trend!G59+Trend!G78+Trend!G87 -> 0 | H59: =Trend!H59+Trend!H78+Trend!H87 -> 0 | I59: =Trend!J59+Trend!J78+Trend!J87 -> 26073627 | J59: =Trend!K59+Trend!K78+Trend!K87 -> 75147891 | K59: =Trend!L59+Trend!L78+Trend!L87 -> 9844121.8 | L59: =Trend!M59+Trend!M78+Trend!M87 -> 23307862 | M59: =Trend!N59+Trend!N78+Trend!N87 -> 38162899 | N59: =Trend!O59+Trend!O78+Trend!O87 -> 51641985 | O59: =Trend!P59+Trend!P78+Trend!P87 -> 67868387 | P59: =Trend!Q59+Trend!Q78+Trend!Q87 -> 94717717 | ... AC59: =Trend!AD59+Trend!AD78+Trend!AD87 -> 2.5405281e+08
B60: Total Expenses | F60: =Trend!F90+Trend!F79+Trend!F88+Trend!F77+Trend!F68 -> 0 | G60: =Trend!G90+Trend!G79+Trend!G88+Trend!G77+Trend!G68 -> 0 | H60: =Trend!H90+Trend!H79+Trend!H88+Trend!H77+Trend!H68 -> 0 | I60: =Trend!J90+Trend!J79+Trend!J88+Trend!J77+Trend!J68 -> 15974677 | J60: =Trend!K90+Trend!K79+Trend!K88+Trend!K77+Trend!K68 -> 36503487 | K60: =Trend!L90+Trend!L79+Trend!L88+Trend!L77+Trend!L68 -> 3145122.6 | L60: =Trend!M90+Trend!M79+Trend!M88+Trend!M77+Trend!M68 -> 6776027.4 | M60: =Trend!N90+Trend!N79+Trend!N88+Trend!N77+Trend!N68 -> 11906314 | N60: =Trend!O90+Trend!O79+Trend!O88+Trend!O77+Trend!O68 -> 21673274 | O60: =Trend!P90+Trend!P79+Trend!P88+Trend!P77+Trend!P68 -> 30160084 | P60: =Trend!Q90+Trend!Q79+Trend!Q88+Trend!Q77+Trend!Q68 -> 27033849 | ... AC60: =Trend!AD90+Trend!AD79+Trend!AD88+Trend!AD77+Trend!AD68 -> 54159066
B61: Liquid Assets | F61: =Trend!F5+Trend!F10+Trend!F11+Trend!F12 -> 0 | G61: =Trend!G5+Trend!G10+Trend!G11 -> 0 | H61: =Trend!H5+Trend!H10+Trend!H11 -> 0 | I61: =Trend!J5+Trend!J10+Trend!J11 -> 375933615 | J61: =Trend!K5+Trend!K10+Trend!K11 -> 583646239 | K61: =Trend!L5+Trend!L10+Trend!L11 -> 6.0083615e+08 | L61: =Trend!M5+Trend!M10+Trend!M11 -> 4.8567905e+08 | M61: =Trend!N5+Trend!N10+Trend!N11 -> 7.4578076e+08 | N61: =Trend!O5+Trend!O10+Trend!O11 -> 7.8166025e+08 | O61: =Trend!P5+Trend!P10+Trend!P11 -> 8.1758193e+08 | P61: =Trend!Q5+Trend!Q10+Trend!Q11 -> 8.3672334e+08 | ... AC61: =Trend!AD5+Trend!AD10+Trend!AD11 -> 8.8301066e+08
B62: Short Term Liabilities + Deposits | F62: =F6+F10 -> 0 | G62: =Trend!G28+Trend!G29+Trend!G33+Trend!G34+Trend!G35+Trend!G36+Trend!G37 -> 0 | H62: =Trend!H28+Trend!H29+Trend!H33+Trend!H34+Trend!H35+Trend!H36+Trend!H37 -> 0 | I62: =Trend!J28+Trend!J29+Trend!J33+Trend!J34+Trend!J35+Trend!J36+Trend!J37 -> 27409937 | J62: =Trend!K28+Trend!K29+Trend!K33+Trend!K34+Trend!K35+Trend!K36+Trend!K37 -> 66014991 | K62: =Trend!L28+Trend!L29+Trend!L33+Trend!L34+Trend!L35+Trend!L36+Trend!L37 -> 83265801 | L62: =Trend!M28+Trend!M29+Trend!M33+Trend!M34+Trend!M35+Trend!M36+Trend!M37 -> 1.0466371e+08 | M62: =Trend!N28+Trend!N29+Trend!N33+Trend!N34+Trend!N35+Trend!N36+Trend!N37 -> 1.0829888e+08 | N62: =Trend!O28+Trend!O29+Trend!O33+Trend!O34+Trend!O35+Trend!O36+Trend!O37 -> 1.3405867e+08 | O62: =Trend!P28+Trend!P29+Trend!P33+Trend!P34+Trend!P35+Trend!P36+Trend!P37 -> 2.0464907e+08 | P62: =Trend!Q28+Trend!Q29+Trend!Q33+Trend!Q34+Trend!Q35+Trend!Q36+Trend!Q37 -> 3.2675173e+08 | ... AC62: =Trend!AD28+Trend!AD29+Trend!AD33+Trend!AD34+Trend!AD35+Trend!AD36+Trend!AD37 -> 4.1092402e+08
B63: Average Assets | G63: =(G5+F6)/2 -> 0 | H63: =(H5+G6)/2 -> 0 | I63: =(I5+H6)/2 -> 2.2968198e+08 | J63: =(J5+I6)/2 -> 7.3099977e+08 | K63: =(K5+J6)/2 -> 1.1044466e+09 | L63: =(L5+K6)/2 -> 1.2154822e+09 | M63: =(M5+L6)/2 -> 1.3344242e+09 | N63: =(N5+M6)/2 -> 1.377809e+09 | ... AC63: =(AC5+AB6)/2 -> 3.496903e+09
B64: core Capital | G64: =(Trend!G40+Trend!G41+Trend!G43+Trend!G44+Trend!G46+Trend!G47)-Trend!G13 -> 0 | H64: =(Trend!H40+Trend!H41+Trend!H43+Trend!H44+Trend!H46+Trend!H47)-Trend!H13 -> 0 | I64: =(Trend!J40+Trend!J41+Trend!J43+Trend!J44+Trend!J46+Trend!J47)-Trend!J13 -> 45206627 | J64: =(Trend!K40+Trend!K41+Trend!K43+Trend!K44+Trend!K46+Trend!K47)-Trend!K13 -> 148240999 | K64: =(Trend!L40+Trend!L41+Trend!L43+Trend!L44+Trend!L46+Trend!L47)-Trend!L13 -> 1.44945e+08 | L64: =(Trend!M40+Trend!M41+Trend!M43+Trend!M44+Trend!M46+Trend!M47)-Trend!M13 -> 1.5480897e+08 | M64: =(Trend!N40+Trend!N41+Trend!N43+Trend!N44+Trend!N46+Trend!N47)-Trend!N13 -> 3.165621e+08 | N64: =(Trend!O40+Trend!O41+Trend!O43+Trend!O44+Trend!O46+Trend!O47)-Trend!O13 -> 3.2085171e+08 | O64: =(Trend!P40+Trend!P41+Trend!P43+Trend!P44+Trend!P46+Trend!P47)-Trend!P13 -> 2.9321059e+08 | P64: =(Trend!Q40+Trend!Q41+Trend!Q43+Trend!Q44+Trend!Q46+Trend!Q47)-Trend!Q13 -> 3.2326345e+08 | ... AC64: =(Trend!AD40+Trend!AD41+Trend!AD43+Trend!AD44+Trend!AD46+Trend!AD47)-Trend!AD13 -> 8.8633182e+08
B65: Institutional Capital | G65: =G64-Trend!G40 -> 0 | H65: =H64-Trend!H40 -> 0 | I65: =I64-Trend!J40 -> 2019789 | J65: =J64-Trend!K40 -> 74480513 | K65: =K64-Trend!L40 -> 71179512 | L65: =L64-Trend!M40 -> 81012347 | M65: =M64-Trend!N40 -> 90737098 | N65: =N64-Trend!O40 -> 94449223 | O65: =O64-Trend!P40 -> 61188815 | P65: =P64-Trend!Q40 -> 91164381 | ... AC65: =AC64-Trend!AD40 -> 3.3242171e+08
B66: Average Gross Loans | H66: =(H32+G32)/2 -> 0 | I66: =(I32+H32)/2 -> 33783448 | J66: =(J32+I32)/2 -> 3.1025231e+08 | K66: =(K32+J32)/2 -> 5.8003797e+08 | L66: =(L32+K32)/2 -> 6.3060996e+08 | M66: =(M32+L32)/2 -> 6.8997024e+08 | N66: =(N32+M32)/2 -> 7.7686138e+08 | O66: =(O32+N32)/2 -> 8.849608e+08 | ... AC66: =(AC32+AB32)/2 -> 3.1572701e+09

Sheet Prudential Ratios
B2: DEFENCE SACCO
B3: FINANCIAL SOUNDNESS INDICATORS | C3: Prude. Std | D3: Ref. # | E3: 2013 | F3: 2014 | G3: 2015 | H3: Audit 2016 | I3: Audit 2017 | J3: AUDIT 2018 | K3: Audited 2020 | L3: Audited 2021 | M3: 44562 | N3: 44593 | O3: 44621 | P3: 44682 | Q3: 44713 | R3: 44743 | S3: 44652 | T3: 44774 | U3: 44805 | V3: 44835 | W3: 44866 | X3: 44896 | Y3: Audited-2022 | Z3: 44949 | AA3: 44980 | AB3: 45008 | AC3: 45039 | AD3: 45069 | AE3: 45100 | AF3: 45130 | AG3: 45161 | AH3: 45192 | AI3: 45222
A4: 1 | B4: CAPITAL ADEQUACY REQUIREMENTS
A5: 1.1 | B5: Core capital | C5: ≥ Ksh.10M | D5: 9.a | E5: =Financials!C13/1000000 -> 0 | F5: =Financials!D13/1000000 -> 0 | G5: =Financials!E13/1000000 -> 0 | H5: =Financials!F13/1000000 -> 0 | I5: =Financials!G13/1000000 -> 0 | J5: =Financials!H13/1000000 -> 0 | K5: =Financials!I13/1000000 -> 50.822603 | L5: =Financials!J13/1000000 -> 148.241 | ... O5: =Financials!M13/1000000 -> 284.8121 | P5: =Financials!O13/1000000 -> 261.46059 | Q5: =Financials!P13/1000000 -> 291.51345 | R5: =Financials!Q13/1000000 -> 312.1416 | S5: =Financials!N13/1000000 -> 289.10171 | T5: =Financials!R13/1000000 -> 326.88847 | U5: =Financials!S13/1000000 -> 404.19952 | V5: =Financials!T13/1000000 -> 433.52966 | W5: =Financials!U13/1000000 -> 501.7477 | X5: =Financials!V13/1000000 -> 522.18035 | Y5: =Financials!W13/1000000 -> 489.37178 | Z5: =Financials!X13/1000000 -> 459.41448 | AA5: =Financials!Y13/1000000 -> 496.76393 | ... AE5: =Financials!AC13/1000000 -> 854.58182
A6: 1.2 | B6: Core capital /Total Assets | C6: ≥ 10% | D6: 9.b | E6: =Financials!C13/Financials!C5 -> #DIV/0! | F6: =Financials!D13/Financials!D5 -> #DIV/0! | G6: =Financials!E13/Financials!E5 -> #DIV/0! | H6: =Financials!F13/Financials!F5 -> #DIV/0! | I6: =Financials!G13/Financials!G5 -> #DIV/0! | J6: =Financials!H13/Financials!H5 -> #DIV/0! | K6: =Financials!I13/Financials!I5 -> 0.1106369 | L6: =Financials!J13/Financials!J5 -> 0.12660777 | ... O6: =Financials!M13/Financials!M5 -> 0.18793413 | P6: =Financials!O13/Financials!O5 -> 0.14223509 | Q6: =Financials!P13/Financials!P5 -> 0.13894876 | R6: =Financials!Q13/Financials!Q5 -> 0.14506597 | S6: =Financials!N13/Financials!N5 -> 0.17514001 | T6: =Financials!R13/Financials!R5 -> 0.14198824 | U6: =Financials!S13/Financials!S5 -> 0.16165963 | V6: =Financials!T13/Financials!T5 -> 0.16164535 | W6: =Financials!U13/Financials!U5 -> 0.17721098 | X6: =Financials!V13/Financials!V5 -> 0.17244005 | Y6: =Financials!W13/Financials!W5 -> 0.16158158 | Z6: =Financials!X13/Financials!X5 -> 0.14421521 | AA6: =Financials!Y13/Financials!Y5 -> 0.14644283 | ... AE6: =Financials!AC13/Financials!AC5 -> 0.20619006
A7: 1.3 | B7: Core capital /Total Deposits | C7: ≥ 8% | D7: 9.d | E7: =Financials!C13/Financials!C6 -> #DIV/0! | F7: =Financials!D13/Financials!D6 -> #DIV/0! | G7: =Financials!E13/Financials!E6 -> #DIV/0! | H7: =Financials!F13/Financials!F6 -> #DIV/0! | I7: =Financials!G13/Financials!G6 -> #DIV/0! | J7: =Financials!H13/Financials!H6 -> #DIV/0! | K7: =Financials!I13/Financials!I6 -> 0.17456928 | L7: =Financials!J13/Financials!J6 -> 0.15992657 | ... O7: =Financials!M13/Financials!M6 -> 0.25776509 | P7: =Financials!O13/Financials!O6 -> 0.18671229 | Q7: =Financials!P13/Financials!P6 -> 0.1793432 | R7: =Financials!Q13/Financials!Q6 -> 0.18922448 | S7: =Financials!N13/Financials!N6 -> 0.2348378 | T7: =Financials!R13/Financials!R6 -> 0.18394678 | U7: =Financials!S13/Financials!S6 -> 0.21381068 | V7: =Financials!T13/Financials!T6 -> 0.21282519 | W7: =Financials!U13/Financials!U6 -> 0.23532367 | X7: =Financials!V13/Financials!V6 -> 0.22834093 | Y7: =Financials!W13/Financials!W6 -> 0.2139849 | Z7: =Financials!X13/Financials!X6 -> 0.19002397 | AA7: =Financials!Y13/Financials!Y6 -> 0.19246323 | ... AE7: =Financials!AC13/Financials!AC6 -> 0.28148838
A8: 1.4 | B8: Share Capital/Total Assets | C8: ≤2% | D8: 9.c | E8: =Financials!C17/Financials!C5 -> #DIV/0! | F8: =Financials!D17/Financials!D5 -> #DIV/0! | G8: =Financials!E17/Financials!E5 -> #DIV/0! | H8: =Financials!F17/Financials!F5 -> #DIV/0! | I8: =Financials!G17/Financials!G5 -> #DIV/0! | J8: =Financials!H17/Financials!H5 -> #DIV/0! | K8: =Financials!I17/Financials!I5 -> 0.094014424 | L8: =Financials!J17/Financials!J5 -> 0.062996408 | ... O8: =Financials!M17/Financials!M5 -> 0.14901131 | P8: =Financials!O17/Financials!O5 -> 0.12622032 | Q8: =Financials!P17/Financials!P5 -> 0.11062913 | R8: =Financials!Q17/Financials!Q5 -> 0.10797086 | S8: =Financials!N17/Financials!N5 -> 0.13715634 | T8: =Financials!R17/Financials!R5 -> 0.10097853 | U8: =Financials!S17/Financials!S5 -> 0.1146811 | V8: =Financials!T17/Financials!T5 -> 0.11001694 | W8: =Financials!U17/Financials!U5 -> 0.11714809 | X8: =Financials!V17/Financials!V5 -> 0.11148428 | Y8: =Financials!W17/Financials!W5 -> 0.11146767 | Z8: =Financials!X17/Financials!X5 -> 0.10618594 | AA8: =Financials!Y17/Financials!Y5 -> 0.10014264 | ... AE8: =Financials!AC17/Financials!AC5 -> 0.1336452
A9: 1.5 | B9: Institutional Capital/Total Assets | C9: ≥ 8% | D9: 9.c | E9: =Financials!C14/Financials!C5 -> #DIV/0! | F9: =Financials!D14/Financials!D5 -> #DIV/0! | G9: =Financials!E14/Financials!E5 -> #DIV/0! | H9: =Financials!F14/Financials!F5 -> #DIV/0! | I9: =Financials!G14/Financials!G5 -> #DIV/0! | J9: =Financials!H14/Financials!H5 -> #DIV/0! | K9: =Financials!I14/Financials!I5 -> 0.016622473 | L9: =Financials!J14/Financials!J5 -> 0.063611359 | ... O9: =Financials!M14/Financials!M5 -> 0.038922816 | P9: =Financials!O14/Financials!O5 -> 0.016014775 | Q9: =Financials!P14/Financials!P5 -> 0.028319635 | R9: =Financials!Q14/Financials!Q5 -> 0.037095108 | S9: =Financials!N14/Financials!N5 -> 0.037983664 | T9: =Financials!R14/Financials!R5 -> 0.041009701 | U9: =Financials!S14/Financials!S5 -> 0.046978529 | V9: =Financials!T14/Financials!T5 -> 0.051628409 | W9: =Financials!U14/Financials!U5 -> 0.060062893 | X9: =Financials!V14/Financials!V5 -> 0.060955773 | Y9: =Financials!W14/Financials!W5 -> 0.050113906 | Z9: =Financials!X14/Financials!X5 -> 0.038029274 | AA9: =Financials!Y14/Financials!Y5 -> 0.046300183 | ... AE9: =Financials!AC14/Financials!AC5 -> 0.072544857
A10: 2 | B10: ASSET MIX AND QUALITY
A11: 2.1 | B11: Non Earning Assets
A12: 2.1.1 | B12: Non earning Assets/Total assets | C12: ≤ 10% | D12: 48.1 | E12: =Financials!C39/Financials!C5 -> #DIV/0! | F12: =Financials!D39/Financials!D5 -> #DIV/0! | G12: =Financials!E39/Financials!E5 -> #DIV/0! | H12: =Financials!F39/Financials!F5 -> #DIV/0! | I12: =Financials!G39/Financials!G5 -> #DIV/0! | J12: =Financials!H39/Financials!H5 -> #DIV/0! | K12: =Financials!I39/Financials!I5 -> 0.012764273 | L12: =Financials!J39/Financials!J5 -> 0.020740305 | ... O12: =Financials!M39/Financials!M5 -> 0.00040808913 | P12: =Financials!O39/Financials!O5 -> 0.0020439109 | Q12: =Financials!P39/Financials!P5 -> 0.057083981 | R12: =Financials!Q39/Financials!Q5 -> 0.22931812 | S12: =Financials!N39/Financials!N5 -> 0.0012690609 | T12: =Financials!R39/Financials!R5 -> 0.0026702404 | U12: =Financials!S39/Financials!S5 -> 0.0033520511 | V12: =Financials!T39/Financials!T5 -> 0.0044483317 | W12: =Financials!U39/Financials!U5 -> 0.0048071812 | X12: =Financials!V39/Financials!V5 -> 0.20858308 | Y12: =Financials!W39/Financials!W5 -> 0.20844182 | Z12: =Financials!X39/Financials!X5 -> 0.0019250897 | AA12: =Financials!Y39/Financials!Y5 -> 0.0021515992 | ... AE12: =Financials!AC39/Financials!AC5 -> 0.0023545088
A13: 2.1.2 | B13: Property and Equipment/Total Assets | C13: ≤ 5% | D13: 48.1 | E13: =Financials!C40/Financials!C5 -> #DIV/0! | F13: =Financials!D40/Financials!D5 -> #DIV/0! | G13: =Financials!E40/Financials!E5 -> #DIV/0! | H13: =Financials!F40/Financials!F5 -> #DIV/0! | I13: =Financials!G40/Financials!G5 -> #DIV/0! | J13: =Financials!H40/Financials!H5 -> #DIV/0! | K13: =Financials!I40/Financials!I5 -> 0 | L13: =Financials!J40/Financials!J5 -> 0 | ... O13: =Financials!M40/Financials!M5 -> 0 | P13: =Financials!O40/Financials!O5 -> 0 | Q13: =Financials!P40/Financials!P5 -> 0 | R13: =Financials!Q40/Financials!Q5 -> 0 | S13: =Financials!N40/Financials!N5 -> 0 | T13: =Financials!R40/Financials!R5 -> 0 | U13: =Financials!S40/Financials!S5 -> 0 | V13: =Financials!T40/Financials!T5 -> 0 | W13: =Financials!U40/Financials!U5 -> 0 | X13: =Financials!V40/Financials!V5 -> 0 | Y13: =Financials!W40/Financials!W5 -> 0 | Z13: =Financials!X40/Financials!X5 -> 0 | AA13: =Financials!Y40/Financials!Y5 -> 0 | ... AE13: =Financials!AC40/Financials!AC5 -> 0
A14: 2.1.3 | B14: Non Performing loans/Gross Loans | C14: ≤ 6% | D14: 41 | E14: =Financials!C34/Financials!C32 -> #DIV/0! | F14: =Financials!D34/Financials!D32 -> #DIV/0! | G14: =Financials!E34/Financials!E32 -> #DIV/0! | H14: =Financials!F34/Financials!F32 -> #DIV/0! | I14: =Financials!G34/Financials!G32 -> #DIV/0! | J14: =Financials!H34/Financials!H32 -> #DIV/0! | K14: =Financials!I34/Financials!I32 -> 0 | L14: =Financials!J34/Financials!J32 -> 0 | ... O14: =Financials!M34/Financials!M32 -> 0 | P14: =Financials!O34/Financials!O32 -> 0 | Q14: =Financials!P34/Financials!P32 -> 0 | R14: =Financials!Q34/Financials!Q32 -> 0 | S14: =Financials!N34/Financials!N32 -> 0 | T14: =Financials!R34/Financials!R32 -> 0 | U14: =Financials!S34/Financials!S32 -> 0 | V14: =Financials!T34/Financials!T32 -> 0 | W14: =Financials!U34/Financials!U32 -> 0 | X14: =Financials!V34/Financials!V32 -> 0 | Y14: =Financials!W34/Financials!W32 -> 0 | Z14: =Financials!X34/Financials!X32 -> 0 | AA14: =Financials!Y34/Financials!Y32 -> 0 | ... AE14: =Financials!AC34/Financials!AC32 -> 0
A15: 2.2 | B15: Earning Assets
A16: 2.2.1 | B16: Equities & Investments/Deposits | C16: ≤ 5% | D16: 48.4 | E16: =Financials!C26/Financials!C6 -> #DIV/0! | F16: =Financials!D26/Financials!D6 -> #DIV/0! | G16: =Financials!E26/Financials!E6 -> #DIV/0! | H16: =Financials!F26/Financials!F6 -> #DIV/0! | I16: =Financials!G26/Financials!G6 -> #DIV/0! | J16: =Financials!H26/Financials!H6 -> #DIV/0! | K16: =Financials!I26/Financials!I6 -> 0.034348749 | L16: =Financials!J26/Financials!J6 -> 0.010788282 | ... O16: =Financials!M26/Financials!M6 -> 0.055734623 | P16: =Financials!O26/Financials!O6 -> 0.073255662 | Q16: =Financials!P26/Financials!P6 -> 0.064053713 | R16: =Financials!Q26/Financials!Q6 -> 0.030916893 | S16: =Financials!N26/Financials!N6 -> 0.050023806 | T16: =Financials!R26/Financials!R6 -> 0.028698736 | U16: =Financials!S26/Financials!S6 -> 0.053426284 | V16: =Financials!T26/Financials!T6 -> 0.049582175 | W16: =Financials!U26/Financials!U6 -> 0.047369805 | X16: =Financials!V26/Financials!V6 -> 0.044165648 | Y16: =Financials!W26/Financials!W6 -> 0.022300489 | Z16: =Financials!X26/Financials!X6 -> 0.042400915 | AA16: =Financials!Y26/Financials!Y6 -> 0.039716343 | ... AE16: =Financials!AC26/Financials!AC6 -> 0.016798751
A17: 2.2.2 | B17: Equities & Investments/Core Capital | C17: ≤ 40% | D17: 48.4 | E17: =Financials!C26/Financials!C13 -> #DIV/0! | F17: =Financials!D26/Financials!D13 -> #DIV/0! | G17: =Financials!E26/Financials!E13 -> #DIV/0! | H17: =Financials!F26/Financials!F13 -> #DIV/0! | I17: =Financials!G26/Financials!G13 -> #DIV/0! | J17: =Financials!H26/Financials!H13 -> #DIV/0! | K17: =Financials!I26/Financials!I13 -> 0.19676285 | L17: =Financials!J26/Financials!J13 -> 0.067457721 | ... O17: =Financials!M26/Financials!M13 -> 0.21622254 | P17: =Financials!O26/Financials!O13 -> 0.39234515 | Q17: =Financials!P26/Financials!P13 -> 0.35715719 | R17: =Financials!Q26/Financials!Q13 -> 0.16338738 | S17: =Financials!N26/Financials!N13 -> 0.21301429 | T17: =Financials!R26/Financials!R13 -> 0.15601652 | U17: =Financials!S26/Financials!S13 -> 0.24987659 | V17: =Financials!T26/Financials!T13 -> 0.23297137 | W17: =Financials!U26/Financials!U13 -> 0.20129639 | X17: =Financials!V26/Financials!V13 -> 0.19341976 | Y17: =Financials!W26/Financials!W13 -> 0.10421525 | Z17: =Financials!X26/Financials!X13 -> 0.22313456 | AA17: =Financials!Y26/Financials!Y13 -> 0.20635808 | ... AE17: =Financials!AC26/Financials!AC13 -> 0.059678312
A18: 2.2.3 | B18: Net Loans & advances /Total assets | C18: NPR | E18: =Financials!C31/Financials!C5 -> #DIV/0! | F18: =Financials!D31/Financials!D5 -> #DIV/0! | G18: =Financials!E31/Financials!E5 -> #DIV/0! | H18: =Financials!F31/Financials!F5 -> #DIV/0! | I18: =Financials!G31/Financials!G5 -> #DIV/0! | J18: =Financials!H31/Financials!H5 -> #DIV/0! | K18: =Financials!I31/Financials!I5 -> 0.14708793 | L18: =Financials!J31/Financials!J5 -> 0.47224595 | ... O18: =Financials!M31/Financials!M5 -> 0.46643612 | P18: =Financials!O31/Financials!O5 -> 0.49704289 | Q18: =Financials!P31/Financials!P5 -> 0.49416912 | R18: =Financials!Q31/Financials!Q5 -> 0.53548642 | S18: =Financials!N31/Financials!N5 -> 0.48750738 | T18: =Financials!R31/Financials!R5 -> 0.55578899 | U18: =Financials!S31/Financials!S5 -> 0.57021805 | V18: =Financials!T31/Financials!T5 -> 0.5905326 | W18: =Financials!U31/Financials!U5 -> 0.61882805 | X18: =Financials!V31/Financials!V5 -> 0.6339233 | Y18: =Financials!W31/Financials!W5 -> 0.63384066 | Z18: =Financials!X31/Financials!X5 -> 0.66006828 | AA18: =Financials!Y31/Financials!Y5 -> 0.67610121 | ... AE18: =Financials!AC31/Financials!AC5 -> 0.77213961
A19: 3 | B19: FUNDING MIX
A20: 3.1 | B20: Total Deposits/Total Assets | C20: NPR | E20: =Financials!C6/Financials!C5 -> #DIV/0! | F20: =Financials!D6/Financials!D5 -> #DIV/0! | G20: =Financials!E6/Financials!E5 -> #DIV/0! | H20: =Financials!F6/Financials!F5 -> #DIV/0! | I20: =Financials!G6/Financials!G5 -> #DIV/0! | J20: =Financials!H6/Financials!H5 -> #DIV/0! | K20: =Financials!I6/Financials!I5 -> 0.6337707 | L20: =Financials!J6/Financials!J5 -> 0.79166187 | ... O20: =Financials!M6/Financials!M5 -> 0.72909069 | P20: =Financials!O6/Financials!O5 -> 0.76178753 | Q20: =Financials!P6/Financials!P5 -> 0.7747646 | R20: =Financials!Q6/Financials!Q5 -> 0.76663426 | S20: =Financials!N6/Financials!N5 -> 0.74579137 | T20: =Financials!R6/Financials!R5 -> 0.77189845 | U20: =Financials!S6/Financials!S5 -> 0.75608772 | V20: =Financials!T6/Financials!T5 -> 0.75952172 | W20: =Financials!U6/Financials!U5 -> 0.75305211 | X20: =Financials!V6/Financials!V5 -> 0.7551868 | Y20: =Financials!W6/Financials!W5 -> 0.7551074 | Z20: =Financials!X6/Financials!X5 -> 0.75893169 | AA20: =Financials!Y6/Financials!Y5 -> 0.76088728 | ... AE20: =Financials!AC6/Financials!AC5 -> 0.73249936
A21: 3.1.1 | B21: BOSA Deposits/Total Assets | C21: NPR | E21: =Financials!C7/Financials!C5 -> #DIV/0! | F21: =Financials!D7/Financials!D5 -> #DIV/0! | G21: =Financials!E7/Financials!E5 -> #DIV/0! | H21: =Financials!F7/Financials!F5 -> #DIV/0! | I21: =Financials!G7/Financials!G5 -> #DIV/0! | J21: =Financials!H7/Financials!H5 -> #DIV/0! | K21: =Financials!I7/Financials!I5 -> 0.6337707 | L21: =Financials!J7/Financials!J5 -> 0.79138898 | ... O21: =Financials!M7/Financials!M5 -> 0.69326007 | P21: =Financials!O7/Financials!O5 -> 0.68509917 | Q21: =Financials!P7/Financials!P5 -> 0.65204108 | R21: =Financials!Q7/Financials!Q5 -> 0.69498452 | S21: =Financials!N7/Financials!N5 -> 0.70017954 | T21: =Financials!R7/Financials!R5 -> 0.70754124 | U21: =Financials!S7/Financials!S5 -> 0.68435973 | V21: =Financials!T7/Financials!T5 -> 0.68814245 | W21: =Financials!U7/Financials!U5 -> 0.68745978 | X21: =Financials!V7/Financials!V5 -> 0.69065491 | Y21: =Financials!W7/Financials!W5 -> 0.69057719 | Z21: =Financials!X7/Financials!X5 -> 0.70042274 | AA21: =Financials!Y7/Financials!Y5 -> 0.69860868 | ... AE21: =Financials!AC7/Financials!AC5 -> 0.66745999
A22: 3.1.2 | B22: FOSA Deposits/Total Assets | C22: NPR | E22: =Financials!C8/Financials!C5 -> #DIV/0! | F22: =Financials!D8/Financials!D5 -> #DIV/0! | G22: =Financials!E8/Financials!E5 -> #DIV/0! | H22: =Financials!F8/Financials!F5 -> #DIV/0! | I22: =Financials!G8/Financials!G5 -> #DIV/0! | J22: =Financials!H8/Financials!H5 -> #DIV/0! | K22: =Financials!I8/Financials!I5 -> 0 | L22: =Financials!J8/Financials!J5 -> 0.00027289286 | ... O22: =Financials!M8/Financials!M5 -> 0.035817993 | P22: =Financials!O8/Financials!O5 -> 0.076661535 | Q22: =Financials!P8/Financials!P5 -> 0.12266655 | R22: =Financials!Q8/Financials!Q5 -> 0.071640673 | S22: =Financials!N8/Financials!N5 -> 0.045599574 | T22: =Financials!R8/Financials!R5 -> 0.064348728 | U22: =Financials!S8/Financials!S5 -> 0.071720186 | V22: =Financials!T8/Financials!T5 -> 0.071371995 | W22: =Financials!U8/Financials!U5 -> 0.065588976 | X22: =Financials!V8/Financials!V5 -> 0.064528745 | Y22: =Financials!W8/Financials!W5 -> 0.064530209 | Z22: =Financials!X8/Financials!X5 -> 0.058505963 | AA22: =Financials!Y8/Financials!Y5 -> 0.0622758 | ... AE22: =Financials!AC8/Financials!AC5 -> 0.065037077
A23: 3.2 | B23: External Borrowing/Total assets | C23: ≤ 25% | D23: 35.1 | E23: =Financials!C9/Financials!C5 -> #DIV/0! | F23: =Financials!D9/Financials!D5 -> #DIV/0! | G23: =Financials!E9/Financials!E5 -> #DIV/0! | H23: =Financials!F9/Financials!F5 -> #DIV/0! | I23: =Financials!G9/Financials!G5 -> #DIV/0! | J23: =Financials!H9/Financials!H5 -> #DIV/0! | K23: =Financials!I9/Financials!I5 -> 0.19592308 | L23: =Financials!J9/Financials!J5 -> 0.025622014 | ... O23: =Financials!M9/Financials!M5 -> 0.019795591 | P23: =Financials!O9/Financials!O5 -> 0.016320061 | Q23: =Financials!P9/Financials!P5 -> 0.014299384 | R23: =Financials!Q9/Financials!Q5 -> 0.013942323 | S23: =Financials!N9/Financials!N5 -> 0.018174227 | T23: =Financials!R9/Financials!R5 -> 0.013030888 | U23: =Financials!S9/Financials!S5 -> 0.011998502 | V23: =Financials!T9/Financials!T5 -> 0.011185764 | W23: =Financials!U9/Financials!U5 -> 0.010595623 | X23: =Financials!V9/Financials!V5 -> 0.0099069251 | Y23: =Financials!W9/Financials!W5 -> 0.0099054494 | Z23: =Financials!X9/Financials!X5 -> 0.0094173268 | AA23: =Financials!Y9/Financials!Y5 -> 0.0088438081 | ... AE23: =Financials!AC9/Financials!AC5 -> 0.007238279
A24: 4 | B24: GROWTH RATIOS
A25: 4.1 | B25: Total Assets | C25: NPR | E25: =Financials!C5/Financials!#REF!-1 -> #REF! | F25: =Financials!D5/Financials!C5-1 -> #DIV/0! | G25: =Financials!E5/Financials!D5-1 -> #DIV/0! | H25: =Financials!F5/Financials!E5-1 -> #DIV/0! | I25: =Financials!G5/Financials!F5-1 -> #DIV/0! | J25: =Financials!H5/Financials!G5-1 -> #DIV/0! | K25: =Financials!I5/Financials!H5-1 -> #DIV/0! | L25: =Financials!J5/Financials!H5-1 -> #DIV/0! | M25: =Financials!K5/Financials!I5-1 -> 1.7907316 | N25: =Financials!L5/Financials!J5-1 -> 0.19844384 | O25: =Financials!M5/Financials!K5-1 -> 0.18216417 | P25: =Financials!O5/Financials!M5-1 -> 0.21296061 | Q25: =Financials!P5/Financials!N5-1 -> 0.27097971 | R25: =Financials!Q5/Financials!O5-1 -> 0.170541 | S25: =Financials!N5/Financials!L5-1 -> 0.17635833 | T25: =Financials!R5/Financials!P5-1 -> 0.097345327 | U25: =Financials!S5/Financials!Q5-1 -> 0.16200532 | V25: =Financials!T5/Financials!R5-1 -> 0.16495287 | W25: =Financials!U5/Financials!S5-1 -> 0.13240174 | X25: =Financials!V5/Financials!T5-1 -> 0.12908536 | Y25: =Financials!W5/Financials!U5-1 -> 0.069676166 | Z25: =Financials!X5/Financials!V5-1 -> 0.051989087 | AA25: =Financials!Y5/Financials!W5-1 -> 0.12004347 | ... AE25: =Financials!AC5/Financials!AA5-1 -> 0.12031341
A26: 4.2 | B26: Total Deposits | C26: NPR | E26: =Financials!C6/Financials!#REF!-1 -> #REF! | F26: =Financials!D6/Financials!C6-1 -> #DIV/0! | G26: =Financials!E6/Financials!D6-1 -> #DIV/0! | H26: =Financials!F6/Financials!E6-1 -> #DIV/0! | I26: =Financials!G6/Financials!F6-1 -> #DIV/0! | J26: =Financials!H6/Financials!G6-1 -> #DIV/0! | K26: =Financials!I6/Financials!H6-1 -> #DIV/0! | L26: =Financials!J6/Financials!H6-1 -> #DIV/0! | M26: =Financials!K6/Financials!I6-1 -> 2.5301746 | N26: =Financials!L6/Financials!J6-1 -> 0.24427677 | O26: =Financials!M6/Financials!K6-1 -> 0.075100511 | P26: =Financials!O6/Financials!M6-1 -> 0.2673571 | Q26: =Financials!P6/Financials!N6-1 -> 0.32035596 | R26: =Financials!Q6/Financials!O6-1 -> 0.17798835 | S26: =Financials!N6/Financials!L6-1 -> 0.067377278 | T26: =Financials!R6/Financials!P6-1 -> 0.093285822 | U26: =Financials!S6/Financials!Q6-1 -> 0.14601968 | V26: =Financials!T6/Financials!R6-1 -> 0.14627386 | W26: =Financials!U6/Financials!S6-1 -> 0.12785527 | X26: =Financials!V6/Financials!T6-1 -> 0.12264118 | Y26: =Financials!W6/Financials!U6-1 -> 0.072595616 | Z26: =Financials!X6/Financials!V6-1 -> 0.057205791 | AA26: =Financials!Y6/Financials!W6-1 -> 0.12861671 | ... AE26: =Financials!AC6/Financials!AA6-1 -> 0.12196045
A27: 4.2.1 | B27: FOSA Deposits | C27: NPR | E27: =Financials!C8/Financials!#REF!-1 -> #REF! | F27: =Financials!D8/Financials!C8-1 -> #DIV/0! | G27: =Financials!E8/Financials!D8-1 -> #DIV/0! | H27: =Financials!F8/Financials!E8-1 -> #DIV/0! | I27: =Financials!G8/Financials!F8-1 -> #DIV/0! | J27: =Financials!H8/Financials!G8-1 -> #DIV/0! | K27: =Financials!I8/Financials!H8-1 -> #DIV/0! | L27: =Financials!J8/Financials!H8-1 -> #DIV/0! | M27: =Financials!K8/Financials!I8-1 -> #DIV/0! | N27: =Financials!L8/Financials!J8-1 -> 154.23072 | O27: =Financials!M8/Financials!K8-1 -> 2.8817557 | P27: =Financials!O8/Financials!M8-1 -> 1.5961092 | Q27: =Financials!P8/Financials!N8-1 -> 2.4190385 | R27: =Financials!Q8/Financials!O8-1 -> 0.093877713 | S27: =Financials!N8/Financials!L8-1 -> 0.51756839 | T27: =Financials!R8/Financials!P8-1 -> -0.42435183 | U27: =Financials!S8/Financials!Q8-1 -> 0.16329503 | V27: =Financials!T8/Financials!R8-1 -> 0.29210029 | W27: =Financials!U8/Financials!S8-1 -> 0.035595055 | X27: =Financials!V8/Financials!T8-1 -> 0.020827023 | Y27: =Financials!W8/Financials!U8-1 -> 0.052408971 | Z27: =Financials!X8/Financials!V8-1 -> -0.046198176 | AA27: =Financials!Y8/Financials!W8-1 -> 0.080913954 | ... AE27: =Financials!AC8/Financials!AA8-1 -> 0.12700989
A28: 4.2.2 | B28: BOSA Deposits | C28: NPR | E28: =Financials!C7/Financials!#REF!-1 -> #REF! | F28: =Financials!D7/Financials!C7-1 -> #DIV/0! | G28: =Financials!E7/Financials!D7-1 -> #DIV/0! | H28: =Financials!F7/Financials!E7-1 -> #DIV/0! | I28: =Financials!G7/Financials!F7-1 -> #DIV/0! | J28: =Financials!H7/Financials!G7-1 -> #DIV/0! | K28: =Financials!I7/Financials!H7-1 -> #DIV/0! | L28: =Financials!J7/Financials!H7-1 -> #DIV/0! | M28: =Financials!K7/Financials!I7-1 -> 2.4821069 | N28: =Financials!L7/Financials!J7-1 -> 0.191164 | O28: =Financials!M7/Financials!K7-1 -> 0.03637706 | P28: =Financials!O7/Financials!M7-1 -> 0.19868191 | Q28: =Financials!P7/Financials!N7-1 -> 0.18359783 | R28: =Financials!Q7/Financials!O7-1 -> 0.18743084 | S28: =Financials!N7/Financials!L7-1 -> 0.047141039 | T28: =Financials!R7/Financials!P7-1 -> 0.19074871 | U28: =Financials!S7/Financials!Q7-1 -> 0.14424081 | V28: =Financials!T7/Financials!R7-1 -> 0.13301314 | W28: =Financials!U7/Financials!S7-1 -> 0.13753135 | X28: =Financials!V7/Financials!T7-1 -> 0.13320774 | Y28: =Financials!W7/Financials!U7-1 -> 0.07452682 | Z28: =Financials!X7/Financials!V7-1 -> 0.066867212 | AA28: =Financials!Y7/Financials!W7-1 -> 0.13306969 | ... AE28: =Financials!AC7/Financials!AA7-1 -> 0.12147132
A29: 4.3 | B29: Net Loans & advances | C29: NPR | E29: =Financials!C31/Financials!#REF!-1 -> #REF! | F29: =Financials!D31/Financials!C31-1 -> #DIV/0! | G29: =Financials!E31/Financials!D31-1 -> #DIV/0! | H29: =Financials!F31/Financials!E31-1 -> #DIV/0! | I29: =Financials!G31/Financials!F31-1 -> #DIV/0! | J29: =Financials!H31/Financials!G31-1 -> #DIV/0! | K29: =Financials!I31/Financials!H31-1 -> #DIV/0! | L29: =Financials!J31/Financials!H31-1 -> #DIV/0! | M29: =Financials!K31/Financials!I31-1 -> 7.8167117 | N29: =Financials!L31/Financials!J31-1 -> 0.15684155 | O29: =Financials!M31/Financials!K31-1 -> 0.18660002 | P29: =Financials!O31/Financials!M31-1 -> 0.29255307 | Q29: =Financials!P31/Financials!N31-1 -> 0.28834751 | R29: =Financials!Q31/Financials!O31-1 -> 0.26107589 | S29: =Financials!N31/Financials!L31-1 -> 0.25804566 | T29: =Financials!R31/Financials!P31-1 -> 0.2341776 | U29: =Financials!S31/Financials!Q31-1 -> 0.23737295 | V29: =Financials!T31/Financials!R31-1 -> 0.23777666 | W29: =Financials!U31/Financials!S31-1 -> 0.22893683 | X29: =Financials!V31/Financials!T31-1 -> 0.21204742 | Y29: =Financials!W31/Financials!U31-1 -> 0.095626232 | Z29: =Financials!X31/Financials!V31-1 -> 0.095376408 | AA29: =Financials!Y31/Financials!W31-1 -> 0.19472099 | ... AE29: =Financials!AC31/Financials!AA31-1 -> 0.16961323
A30: 4.4 | B30: Core capital | C30: NPR | E30: =Financials!C13/Financials!#REF!-1 -> #REF! | F30: =Financials!D13/Financials!C13-1 -> #DIV/0! | G30: =Financials!E13/Financials!D13-1 -> #DIV/0! | H30: =Financials!F13/Financials!E13-1 -> #DIV/0! | I30: =Financials!G13/Financials!F13-1 -> #DIV/0! | J30: =Financials!H13/Financials!G13-1 -> #DIV/0! | K30: =Financials!I13/Financials!H13-1 -> #DIV/0! | L30: =Financials!J13/Financials!H13-1 -> #DIV/0! | M30: =Financials!K13/Financials!I13-1 -> 1.227257 | N30: =Financials!L13/Financials!J13-1 -> -0.16987221 | O30: =Financials!M13/Financials!K13-1 -> 1.5161191 | P30: =Financials!O13/Financials!M13-1 -> -0.081989169 | Q30: =Financials!P13/Financials!N13-1 -> 0.0083421905 | R30: =Financials!Q13/Financials!O13-1 -> 0.19383807 | S30: =Financials!N13/Financials!L13-1 -> 1.349294 | T30: =Financials!R13/Financials!P13-1 -> 0.12134951 | U30: =Financials!S13/Financials!Q13-1 -> 0.29492358 | V30: =Financials!T13/Financials!R13-1 -> 0.32623112 | W30: =Financials!U13/Financials!S13-1 -> 0.24133668 | X30: =Financials!V13/Financials!T13-1 -> 0.20448586 | Y30: =Financials!W13/Financials!U13-1 -> -0.024665618 | Z30: =Financials!X13/Financials!V13-1 -> -0.12019959 | AA30: =Financials!Y13/Financials!W13-1 -> 0.015105379 | ... AE30: =Financials!AC13/Financials!AA13-1 -> 0.12990606
A31: 4.5 | B31: Total Gross Income | C31: NPR | E31: =Financials!C43/Financials!#REF!-1 -> #REF! | F31: =Financials!D43/Financials!C43-1 -> #DIV/0! | G31: =Financials!E43/Financials!D43-1 -> #DIV/0! | H31: =Financials!F43/Financials!E43-1 -> #DIV/0! | I31: =Financials!G43/Financials!F43-1 -> #DIV/0! | J31: =Financials!H43/Financials!G43-1 -> #DIV/0! | K31: =Financials!I43/Financials!H43-1 -> #DIV/0! | L31: =Financials!J43/Financials!H43-1 -> #DIV/0! | M31: =Financials!K43/Financials!I43-1 -> -0.62244908 | N31: =Financials!L43/Financials!J43-1 -> -0.68984011 | O31: =Financials!M43/Financials!K43-1 -> 2.8767195 | P31: =Financials!O43/Financials!M43-1 -> 0.77838655 | Q31: =Financials!P43/Financials!N43-1 -> 0.83412233 | R31: =Financials!Q43/Financials!O43-1 -> 0.74970107 | S31: =Financials!N43/Financials!L43-1 -> 1.2156466 | T31: =Financials!R43/Financials!P43-1 -> 0.47678095 | U31: =Financials!S43/Financials!Q43-1 -> 0.41674477 | V31: =Financials!T43/Financials!R43-1 -> 0.38309174 | W31: =Financials!U43/Financials!S43-1 -> 0.3158373 | X31: =Financials!V43/Financials!T43-1 -> 0.31214418 | Y31: =Financials!W43/Financials!U43-1 -> 0.14935324 | Z31: =Financials!X43/Financials!V43-1 -> -0.88608375 | AA31: =Financials!Y43/Financials!W43-1 -> -0.72643563 | ... AE31: =Financials!AC43/Financials!AA43-1 -> 0.71940474
A32: 4.6 | B32: Membership | C32: NPR | E32: =Financials!C4/Financials!#REF!-1 -> #REF! | F32: =Financials!D4/Financials!C4-1 -> 0.046403712 | G32: =Financials!E4/Financials!D4-1 -> 0.064393939 | H32: =Financials!F4/Financials!E4-1 -> -1 | I32: =Financials!G4/Financials!F4-1 -> #DIV/0! | J32: =Financials!H4/Financials!G4-1 -> #DIV/0! | K32: =Financials!I4/Financials!H4-1 -> #DIV/0! | L32: =Financials!J4/Financials!H4-1 -> #DIV/0! | M32: =Financials!K4/Financials!I4-1 -> #DIV/0! | N32: =Financials!L4/Financials!J4-1 -> #DIV/0! | O32: =Financials!M4/Financials!K4-1 -> #DIV/0! | P32: =Financials!O4/Financials!M4-1 -> #DIV/0! | Q32: =Financials!P4/Financials!N4-1 -> #DIV/0! | R32: =Financials!Q4/Financials!O4-1 -> #DIV/0! | S32: =Financials!N4/Financials!L4-1 -> #DIV/0! | T32: =Financials!R4/Financials!P4-1 -> #DIV/0! | U32: =Financials!S4/Financials!Q4-1 -> #DIV/0! | V32: =Financials!T4/Financials!R4-1 -> #DIV/0! | W32: =Financials!U4/Financials!S4-1 -> #DIV/0! | X32: =Financials!V4/Financials!T4-1 -> #DIV/0! | Y32: =Financials!W4/Financials!U4-1 -> #DIV/0!
A33: 5 | B33: Efficiency Ratios
A34: 5.1 | B34: FinCost-Deposits/Average Deposits | C34: NPR | E34: =Financials!C50/((Financials!C6+Financials!#REF!)/2) -> #REF! | F34: =Financials!D50/((Financials!D6+Financials!C6)/2) -> #DIV/0! | G34: =Financials!E50/((Financials!E6+Financials!D6)/2) -> #DIV/0! | H34: =Financials!F50/((Financials!F6+Financials!E6)/2) -> #DIV/0! | I34: =Financials!G50/((Financials!G6+Financials!F6)/2) -> #DIV/0! | J34: =Financials!H50/((Financials!H6+Financials!G6)/2) -> #DIV/0! | K34: =Financials!I50/((Financials!I6+Financials!H6)/2) -> 0.089505441 | L34: =Financials!J50/((Financials!J6+Financials!H6)/2) -> 0.036793686 | M34: =Financials!K50/((Financials!K6+Financials!I6)/2) -> 0 | N34: =Financials!L50/((Financials!L6+Financials!J6)/2) -> 0 | O34: =Financials!M50/((Financials!M6+Financials!K6)/2) -> 0 | P34: =Financials!O50/((Financials!O6+Financials!M6)/2) -> 0 | Q34: =Financials!P50/((Financials!P6+Financials!N6)/2) -> 0 | R34: =Financials!Q50/((Financials!Q6+Financials!O6)/2) -> 0 | S34: =Financials!N50/((Financials!N6+Financials!L6)/2) -> 0 | T34: =Financials!R50/((Financials!R6+Financials!P6)/2) -> 0 | U34: =Financials!S50/((Financials!S6+Financials!Q6)/2) -> 0 | V34: =Financials!T50/((Financials!T6+Financials!R6)/2) -> 0 | W34: =Financials!U50/((Financials!U6+Financials!S6)/2) -> 0 | X34: =Financials!V50/((Financials!V6+Financials!T6)/2) -> 0 | Y34: =Financials!W50/((Financials!W6+Financials!U6)/2) -> 0.023810966 | Z34: =Financials!X50/((Financials!X6+Financials!V6)/2) -> 0 | AA34: =Financials!Y50/((Financials!Y6+Financials!W6)/2) -> 0 | ... AE34: =Financials!AC50/((Financials!AC6+Financials!AA6)/2) -> 0
A35: 5.2 | B35: FinCost-Shares/Average Share capital | C35: NPR | E35: =Financials!C51/((Financials!C17+Financials!#REF!)/2) -> #REF! | F35: =Financials!D51/((Financials!D17+Financials!C17)/2) -> #DIV/0! | G35: =Financials!E51/((Financials!E17+Financials!D17)/2) -> #DIV/0! | H35: =Financials!F51/((Financials!F17+Financials!E17)/2) -> #DIV/0! | I35: =Financials!G51/((Financials!G17+Financials!F17)/2) -> #DIV/0! | J35: =Financials!H51/((Financials!H17+Financials!G17)/2) -> #DIV/0! | K35: =Financials!I51/((Financials!I17+Financials!H17)/2) -> 0 | L35: =Financials!J51/((Financials!J17+Financials!H17)/2) -> 0 | M35: =Financials!K51/((Financials!K17+Financials!I17)/2) -> 0 | N35: =Financials!L51/((Financials!L17+Financials!J17)/2) -> 0 | O35: =Financials!M51/((Financials!M17+Financials!K17)/2) -> 0 | P35: =Financials!O51/((Financials!O17+Financials!M17)/2) -> 0 | Q35: =Financials!P51/((Financials!P17+Financials!N17)/2) -> 0 | R35: =Financials!Q51/((Financials!Q17+Financials!O17)/2) -> 0 | S35: =Financials!N51/((Financials!N17+Financials!L17)/2) -> 0 | T35: =Financials!R51/((Financials!R17+Financials!P17)/2) -> 0 | U35: =Financials!S51/((Financials!S17+Financials!Q17)/2) -> 0 | V35: =Financials!T51/((Financials!T17+Financials!R17)/2) -> 0 | W35: =Financials!U51/((Financials!U17+Financials!S17)/2) -> 0 | X35: =Financials!V51/((Financials!V17+Financials!T17)/2) -> 0 | Y35: =Financials!W51/((Financials!W17+Financials!U17)/2) -> 0 | Z35: =Financials!X51/((Financials!X17+Financials!V17)/2) -> 0 | AA35: =Financials!Y51/((Financials!Y17+Financials!W17)/2) -> 0 | ... AE35: =Financials!AC51/((Financials!AC17+Financials!AA17)/2) -> 0
A36: 5.3 | B36: FinCost-Ext Loans/Average Ext Loans | C36: NPR | E36: =Financials!C52/((Financials!C9+Financials!#REF!)/2) -> #REF! | F36: =Financials!D52/((Financials!D9+Financials!C9)/2) -> #DIV/0! | G36: =Financials!E52/((Financials!E9+Financials!D9)/2) -> #DIV/0! | H36: =Financials!F52/((Financials!F9+Financials!E9)/2) -> #DIV/0! | I36: =Financials!G52/((Financials!G9+Financials!F9)/2) -> #DIV/0! | J36: =Financials!H52/((Financials!H9+Financials!G9)/2) -> #DIV/0! | K36: =Financials!I52/((Financials!I9+Financials!H9)/2) -> 0 | L36: =Financials!J52/((Financials!J9+Financials!H9)/2) -> 0 | M36: =Financials!K52/((Financials!K9+Financials!I9)/2) -> 0 | N36: =Financials!L52/((Financials!L9+Financials!J9)/2) -> 0 | O36: =Financials!M52/((Financials!M9+Financials!K9)/2) -> 0 | P36: =Financials!O52/((Financials!O9+Financials!M9)/2) -> 0 | Q36: =Financials!P52/((Financials!P9+Financials!N9)/2) -> 0 | R36: =Financials!Q52/((Financials!Q9+Financials!O9)/2) -> 0 | S36: =Financials!N52/((Financials!N9+Financials!L9)/2) -> 0 | T36: =Financials!R52/((Financials!R9+Financials!P9)/2) -> 0 | U36: =Financials!S52/((Financials!S9+Financials!Q9)/2) -> 0 | V36: =Financials!T52/((Financials!T9+Financials!R9)/2) -> 0 | W36: =Financials!U52/((Financials!U9+Financials!S9)/2) -> 0 | X36: =Financials!V52/((Financials!V9+Financials!T9)/2) -> 0 | Y36: =Financials!W52/((Financials!W9+Financials!U9)/2) -> 0.02 | Z36: =Financials!X52/((Financials!X9+Financials!V9)/2) -> 0 | AA36: =Financials!Y52/((Financials!Y9+Financials!W9)/2) -> 0 | ... AE36: =Financials!AC52/((Financials!AC9+Financials!AA9)/2) -> 0
A37: 5.4 | B37: OpEx/Average Total Assets | C37: NPR | E37: =(Financials!C54+Financials!C55)/((Financials!C5+Financials!#REF!)/2) -> #REF! | F37: =(Financials!D54+Financials!D55)/((Financials!D5+Financials!C5)/2) -> #DIV/0! | G37: =(Financials!E54+Financials!E55)/((Financials!E5+Financials!D5)/2) -> #DIV/0! | H37: =(Financials!F54+Financials!F55)/((Financials!F5+Financials!E5)/2) -> #DIV/0! | I37: =(Financials!G54+Financials!G55)/((Financials!G5+Financials!F5)/2) -> #DIV/0! | J37: =(Financials!H54+Financials!H55)/((Financials!H5+Financials!G5)/2) -> #DIV/0! | K37: =(Financials!I54+Financials!I55)/((Financials!I5+Financials!H5)/2) -> 0.0068097289 | L37: =(Financials!J54+Financials!J55)/((Financials!J5+Financials!H5)/2) -> 0.01082429 | M37: =(Financials!K54+Financials!K55)/((Financials!K5+Financials!I5)/2) -> 0.00024729822 | N37: =(Financials!L54+Financials!L55)/((Financials!L5+Financials!J5)/2) -> 0.0010672943 | O37: =(Financials!M54+Financials!M55)/((Financials!M5+Financials!K5)/2) -> 0.0016132618 | P37: =(Financials!O54+Financials!O55)/((Financials!O5+Financials!M5)/2) -> 0.01002726 | Q37: =(Financials!P54+Financials!P55)/((Financials!P5+Financials!N5)/2) -> 0.010798787 | R37: =(Financials!Q54+Financials!Q55)/((Financials!Q5+Financials!O5)/2) -> 0.010535901 | S37: =(Financials!N54+Financials!N55)/((Financials!N5+Financials!L5)/2) -> 0.0087491277 | T37: =(Financials!R54+Financials!R55)/((Financials!R5+Financials!P5)/2) -> 0.0098812428 | U37: =(Financials!S54+Financials!S55)/((Financials!S5+Financials!Q5)/2) -> 0.010666484 | V37: =(Financials!T54+Financials!T55)/((Financials!T5+Financials!R5)/2) -> 0.010523198 | W37: =(Financials!U54+Financials!U55)/((Financials!U5+Financials!S5)/2) -> 0.011533161 | X37: =(Financials!V54+Financials!V55)/((Financials!V5+Financials!T5)/2) -> 0.014239008 | Y37: =(Financials!W54+Financials!W55)/((Financials!W5+Financials!U5)/2) -> 0.0091828782 | Z37: =(Financials!X54+Financials!X55)/((Financials!X5+Financials!V5)/2) -> 0.00046664299 | AA37: =(Financials!Y54+Financials!Y55)/((Financials!Y5+Financials!W5)/2) -> 0.00049560807 | ... AE37: =(Financials!AC54+Financials!AC55)/((Financials!AC5+Financials!AA5)/2) -> 0.008655147
A38: 5.5 | B38: Avge yield on Net loans | C38: NPR | E38: =Financials!C44/((Financials!C31+Financials!#REF!)/2) -> #REF! | F38: =Financials!D44/((Financials!D31+Financials!C31)/2) -> #DIV/0! | G38: =Financials!E44/((Financials!E31+Financials!D31)/2) -> #DIV/0! | H38: =Financials!F44/((Financials!F31+Financials!E31)/2) -> #DIV/0! | I38: =Financials!G44/((Financials!G31+Financials!F31)/2) -> #DIV/0! | J38: =Financials!H44/((Financials!H31+Financials!G31)/2) -> #DIV/0! | K38: =Financials!I44/((Financials!I31+Financials!H31)/2) -> 0.060721364 | L38: =Financials!J44/((Financials!J31+Financials!H31)/2) -> 0.10862591 | M38: =Financials!K44/((Financials!K31+Financials!I31)/2) -> 0.017461611 | N38: =Financials!L44/((Financials!L31+Financials!J31)/2) -> 0.020131881 | O38: =Financials!M44/((Financials!M31+Financials!K31)/2) -> 0.028337339 | P38: =Financials!O44/((Financials!O31+Financials!M31)/2) -> 0.04302836 | Q38: =Financials!P44/((Financials!P31+Financials!N31)/2) -> 0.047892969 | R38: =Financials!Q44/((Financials!Q31+Financials!O31)/2) -> 0.054543954 | S38: =Financials!N44/((Financials!N31+Financials!L31)/2) -> 0.036321451 | T38: =Financials!R44/((Financials!R31+Financials!P31)/2) -> 0.059702319 | U38: =Financials!S44/((Financials!S31+Financials!Q31)/2) -> 0.064995272 | V38: =Financials!T44/((Financials!T31+Financials!R31)/2) -> 0.069818505 | W38: =Financials!U44/((Financials!U31+Financials!S31)/2) -> 0.074411889 | X38: =Financials!V44/((Financials!V31+Financials!T31)/2) -> 0.079611316 | Y38: =Financials!W44/((Financials!W31+Financials!U31)/2) -> 0.071972039 | Z38: =Financials!X44/((Financials!X31+Financials!V31)/2) -> 0.010432801 | AA38: =Financials!Y44/((Financials!Y31+Financials!W31)/2) -> 0.022529923 | ... AE38: =Financials!AC44/((Financials!AC31+Financials!AA31)/2) -> 0.061391868
A39: 6 | B39: Liquidity Ratio
A40: 6.1 | B40: Liquid Assets - ST Liabilities/ Deposits | C40: 0.15 | D40: 13.2 | E40: =Financials!C37/(Financials!C10+Financials!C8+Financials!C7+Financials!C9) -> #DIV/0! | F40: =Financials!D37/(Financials!D10+Financials!D8+Financials!D7+Financials!D9) -> #DIV/0! | G40: =(Financials!E37-Financials!E10)/Financials!E6 -> #DIV/0! | H40: =Financials!F37/(Financials!F10+Financials!F6) -> #DIV/0! | I40: =Financials!G37/(Financials!G10+Financials!G6) -> #DIV/0! | J40: =Financials!H37/(Financials!H10+Financials!H6) -> #DIV/0! | K40: =Financials!I37/(Financials!I10+Financials!I6) -> 1.2134485 | L40: =Financials!J37/(Financials!J10+Financials!J6) -> 0.58798135 | M40: =Financials!K37/(Financials!K10+Financials!K6) -> 0.48317528 | N40: =Financials!L37/(Financials!L10+Financials!L6) -> 0.34328006 | O40: =Financials!M37/(Financials!M10+Financials!M6) -> 0.58237067 | P40: =Financials!O37/(Financials!O10+Financials!O6) -> 0.4687745 | Q40: =Financials!P37/(Financials!P10+Financials!P6) -> 0.41622632 | R40: =Financials!Q37/(Financials!Q10+Financials!Q6) -> 0.22682153 | S40: =Financials!N37/(Financials!N10+Financials!N6) -> 0.50422829 | T40: =Financials!R37/(Financials!R10+Financials!R6) -> 0.4843444 | U40: =Financials!S37/(Financials!S10+Financials!S6) -> 0.45468988 | V40: =Financials!T37/(Financials!T10+Financials!T6) -> 0.431643 | W40: =Financials!U37/(Financials!U10+Financials!U6) -> 0.40470902 | X40: =Financials!V37/(Financials!V10+Financials!V6) -> 0.13054357 | Y40: =Financials!W37/(Financials!W10+Financials!W6) -> 0.17221655 | Z40: =Financials!X37/(Financials!X10+Financials!X6) -> 0.34848637 | AA40: =Financials!Y37/(Financials!Y10+Financials!Y6) -> 0.33256489 | ... AE40: =Financials!AC37/(Financials!AC10+Financials!AC6) -> 0.25809893
A41: 7 | B41: Loan Loss Provisions Ratios
A42: 7.1 | B42: Actual LLP / Required LLP | C42: 1 | D42: 44.1 | E42: =Financials!C33/Financials!C36 -> #DIV/0! | F42: =Financials!D33/Financials!D36 -> #DIV/0! | G42: =(Financials!E37-Financials!E10)/Financials!E6 -> #DIV/0! | H42: =Financials!F33/Financials!F36 -> #DIV/0! | I42: =Financials!G33/Financials!G36 -> #DIV/0! | J42: =Financials!H33/Financials!H36 -> #DIV/0! | K42: =Financials!I33/Financials!I36 -> #DIV/0! | L42: =Financials!J33/Financials!J36 -> #DIV/0! | M42: =Financials!K33/Financials!K36 -> #DIV/0! | N42: =Financials!L33/Financials!L36 -> #DIV/0! | O42: =Financials!M33/Financials!M36 -> #DIV/0! | P42: =Financials!O33/Financials!O36 -> #DIV/0! | Q42: =Financials!P33/Financials!P36 -> #DIV/0! | R42: =Financials!Q33/Financials!Q36 -> #DIV/0! | S42: =Financials!N33/Financials!N36 -> #DIV/0! | T42: =Financials!R33/Financials!R36 -> #DIV/0! | U42: =Financials!S33/Financials!S36 -> #DIV/0! | V42: =Financials!T33/Financials!T36 -> #DIV/0! | W42: =Financials!U33/Financials!U36 -> #DIV/0! | X42: =Financials!V33/Financials!V36 -> #DIV/0! | Y42: =Financials!W33/Financials!W36 -> #DIV/0!
B43: Earnings
B44: ROA | E44: =Trend!C85/((Financials!C5+Financials!#REF!)/2) -> #REF! | F44: =Trend!D85/((Financials!D5+Financials!C5)/2) -> #DIV/0! | G44: =Trend!E85/((Financials!E5+Financials!D5)/2) -> #DIV/0! | H44: =Trend!F85/((Financials!F5+Financials!E5)/2) -> #DIV/0! | I44: =Trend!G85/((Financials!G5+Financials!F5)/2) -> #DIV/0! | J44: =Trend!H85/((Financials!H5+Financials!G5)/2) -> #DIV/0! | K44: =Trend!J85/((Financials!I5+Financials!H5)/2) -> 0.05338977 | L44: =Trend!K85/((Financials!J5+Financials!H5)/2) -> 0.073906552 | M44: =Trend!L85/((Financials!K5+Financials!I5)/2) -> 0.007694138 | N44: =Trend!M85/((Financials!L5+Financials!J5)/2) -> 0.01284481 | O44: =Trend!N85/((Financials!M5+Financials!K5)/2) -> 0.018771796 | P44: =Trend!P85/((Financials!O5+Financials!M5)/2) -> 0.022487466 | Q44: =Trend!Q85/((Financials!P5+Financials!N5)/2) -> 0.036110758 | R44: =Trend!R85/((Financials!Q5+Financials!O5)/2) -> 0.044154856 | S44: =Trend!O85/((Financials!N5+Financials!L5)/2) -> 0.01962646 | T44: =Trend!S85/((Financials!R5+Financials!P5)/2) -> 0.046671783 | U44: =Trend!T85/((Financials!S5+Financials!Q5)/2) -> 0.05405398 | V44: =Trend!U85/((Financials!T5+Financials!R5)/2) -> 0.058880378 | W44: =Trend!V85/((Financials!U5+Financials!S5)/2) -> 0.063143079 | X44: =Trend!W85/((Financials!V5+Financials!T5)/2) -> 0.0675479 | Y44: =Trend!X85/((Financials!W5+Financials!U5)/2) -> 0.050619543 | Z44: =Trend!Y85/((Financials!X5+Financials!V5)/2) -> 0.0065563524 | AA44: =Trend!Z85/((Financials!Y5+Financials!W5)/2) -> 0.017530944 | ... AE44: =Trend!AD85/((Financials!AC5+Financials!AA5)/2) -> 0.050966256
B45: C/I Ratio | E45: =Trend!C79/Trend!C75 -> #DIV/0! | F45: =Trend!D79/Trend!D75 -> #DIV/0! | G45: =Trend!E79/Trend!E75 -> #DIV/0! | H45: =Trend!F79/Trend!F75 -> #DIV/0! | I45: =Trend!G79/Trend!G75 -> #DIV/0! | J45: =Trend!H79/Trend!H75 -> #DIV/0! | K45: =Trend!J79/Trend!J75 -> 0.05995046 | L45: =Trend!K79/Trend!K75 -> 0.058479526 | M45: =Trend!L79/Trend!L75 -> 0.010977919 | N45: =Trend!M79/Trend!M75 -> 0.029961016 | O45: =Trend!N79/Trend!N75 -> 0.031615297 | P45: =Trend!P79/Trend!P75 -> 0.12966699 | Q45: =Trend!Q79/Trend!Q75 -> 0.11097582 | R45: =Trend!R79/Trend!R75 -> 0.091552413 | S45: =Trend!O79/Trend!O75 -> 0.13134895 | T45: =Trend!S79/Trend!S75 -> 0.080177421 | U45: =Trend!T79/Trend!T75 -> 0.075752315 | V45: =Trend!U79/Trend!U75 -> 0.069478958 | W45: =Trend!V79/Trend!V75 -> 0.071051456 | X45: =Trend!W79/Trend!W75 -> 0.084751238 | Y45: =Trend!X79/Trend!X75 -> 0.073041832 | Z45: =Trend!Y79/Trend!Y75 -> 0.025077888 | AA45: =Trend!Z79/Trend!Z75 -> 0.011551975 | ... AE45: =Trend!AD79/Trend!AD75 -> 0.068118937
B46: OE Ratio | E46: =Trend!C79/((Financials!C5+Financials!#REF!)/2) -> #REF! | F46: =Trend!D79/((Financials!D5+Financials!C5)/2) -> #DIV/0! | G46: =Trend!E79/((Financials!E5+Financials!D5)/2) -> #DIV/0! | H46: =Trend!F79/((Financials!F5+Financials!E5)/2) -> #DIV/0! | I46: =Trend!G79/((Financials!G5+Financials!F5)/2) -> #DIV/0! | J46: =Trend!H79/((Financials!H5+Financials!G5)/2) -> #DIV/0! | K46: =Trend!J79/((Financials!I5+Financials!H5)/2) -> 0.0034048644 | L46: =Trend!K79/((Financials!J5+Financials!H5)/2) -> 0.0054121449 | M46: =Trend!L79/((Financials!K5+Financials!I5)/2) -> 0.00012364911 | N46: =Trend!M79/((Financials!L5+Financials!J5)/2) -> 0.00054071764 | O46: =Trend!N79/((Financials!M5+Financials!K5)/2) -> 0.00085932175 | P46: =Trend!P79/((Financials!O5+Financials!M5)/2) -> 0.0051236123 | Q46: =Trend!Q79/((Financials!P5+Financials!N5)/2) -> 0.0055087253 | R46: =Trend!R79/((Financials!Q5+Financials!O5)/2) -> 0.0053719242 | S46: =Trend!O79/((Financials!N5+Financials!L5)/2) -> 0.0044254494 | T46: =Trend!S79/((Financials!R5+Financials!P5)/2) -> 0.0050349009 | U46: =Trend!T79/((Financials!S5+Financials!Q5)/2) -> 0.0054224181 | V46: =Trend!U79/((Financials!T5+Financials!R5)/2) -> 0.0053448321 | W46: =Trend!V79/((Financials!U5+Financials!S5)/2) -> 0.0058443892 | X46: =Trend!W79/((Financials!V5+Financials!T5)/2) -> 0.0074814639 | Y46: =Trend!X79/((Financials!W5+Financials!U5)/2) -> 0.0050057638 | Z46: =Trend!Y79/((Financials!X5+Financials!V5)/2) -> 0.00023332149 | AA46: =Trend!Z79/((Financials!Y5+Financials!W5)/2) -> 0.00025029592 | ... AE46: =Trend!AD79/((Financials!AC5+Financials!AA5)/2) -> 0.0044098768

Sheet CAELS
E2: Audit 2013 | F2: Audit 2014 | G2: Audit 2015 | H2: Audit 2016 | I2: Audit 2017 | J2: AUDIT 2018 | K2: 43466 | L2: Audited 2021 | M2: 44562 | N2: 44593 | O2: 44621 | P2: 44652 | Q2: 44682 | R2: 44713 | S2: 44743 | T2: 44774 | U2: 44805 | V2: 44835 | W2: 44866 | X2: 44896 | Y2: AUDITED-2022 | Z2: 44949 | AA2: 44980 | AB2: 45008 | AC2: 45039 | AD2: 45069 | AE2: 45100 | AF2: 45130 | AG2: 45161 | AH2: 45192
A3: INDICATORS | B3: CAPITAL ADEQUACY | C3: CORE CAPITAL | D3: 10M | E3: =Financials!C13/1000000 -> 0 | F3: =Financials!D13/1000000 -> 0 | G3: =Financials!E13/1000000 -> 0 | H3: =Financials!F13/1000000 -> 0 | I3: =Financials!G13/1000000 -> 0 | J3: =Financials!H13/1000000 -> 0 | K3: =Financials!I13/1000000 -> 50.822603 | L3: =Financials!J13/1000000 -> 148.241 | ... AE3: =Financials!AC13/1000000 -> 854.58182
C4: CCA | D4: Min 10% | E4: =Financials!C13/Financials!C5 -> #DIV/0! | F4: =Financials!D13/Financials!D5 -> #DIV/0! | G4: =Financials!E13/Financials!E5 -> #DIV/0! | H4: =Financials!F13/Financials!F5 -> #DIV/0! | I4: =Financials!G13/Financials!G5 -> #DIV/0! | J4: =Financials!H13/Financials!H5 -> #DIV/0! | K4: =Financials!I13/Financials!I5 -> 0.1106369 | L4: =Financials!J13/Financials!J5 -> 0.12660777 | ... AE4: =Financials!AC13/Financials!AC5 -> 0.20619006
C5: ICA | D5: Min 8% | E5: =Financials!C14/Financials!C5 -> #DIV/0! | F5: =Financials!D14/Financials!D5 -> #DIV/0! | G5: =Financials!E14/Financials!E5 -> #DIV/0! | H5: =Financials!F14/Financials!F5 -> #DIV/0! | I5: =Financials!G14/Financials!G5 -> #DIV/0! | J5: =Financials!H14/Financials!H5 -> #DIV/0! | K5: =Financials!I14/Financials!I5 -> 0.016622473 | L5: =Financials!J14/Financials!J5 -> 0.063611359 | ... AE5: =Financials!AC14/Financials!AC5 -> 0.072544857
C6: CCD | D6: Min 8% | E6: =Financials!C13/Financials!C6 -> #DIV/0! | F6: =Financials!D13/Financials!D6 -> #DIV/0! | G6: =Financials!E13/Financials!E6 -> #DIV/0! | H6: =Financials!F13/Financials!F6 -> #DIV/0! | I6: =Financials!G13/Financials!G6 -> #DIV/0! | J6: =Financials!H13/Financials!H6 -> #DIV/0! | K6: =Financials!I13/Financials!I6 -> 0.17456928 | L6: =Financials!J13/Financials!J6 -> 0.15992657 | ... AE6: =Financials!AC13/Financials!AC6 -> 0.28148838
C7: Adjusted CCA | E7: =(Financials!C13-Financials!C34)/Financials!C5 -> #DIV/0! | F7: =(Financials!D13-Financials!D34)/Financials!D5 -> #DIV/0! | G7: =(Financials!E13-Financials!E34)/Financials!E5 -> #DIV/0! | H7: =(Financials!F13-Financials!F34)/Financials!F5 -> #DIV/0! | I7: =(Financials!G13-Financials!G34)/Financials!G5 -> #DIV/0! | J7: =(Financials!H13-Financials!H34)/Financials!H5 -> #DIV/0! | K7: =(Financials!I13-Financials!I34)/Financials!I5 -> 0.1106369 | L7: =(Financials!J13-Financials!J34)/Financials!J5 -> 0.12660777 | ... AE7: =(Financials!AC13-Financials!AC34)/Financials!AC5 -> 0.20619006
B9: ASSET QUALITY | C9: NPL30 | E9: =Financials!C35/Financials!C32 -> #DIV/0! | F9: =Financials!D35/Financials!D32 -> #DIV/0! | G9: =Financials!E35/Financials!E32 -> #DIV/0! | H9: =Financials!F34/Financials!F32 -> #DIV/0! | I9: =Financials!G34/Financials!G32 -> #DIV/0!
C10: A/L NPL30 | E10: =Financials!C34/Financials!C32 -> #DIV/0! | F10: =Financials!D34/Financials!D32 -> #DIV/0! | G10: =Financials!E34/Financials!E32 -> #DIV/0! | H10: =Financials!F34/Financials!F32 -> #DIV/0! | I10: =Financials!G34/Financials!G32 -> #DIV/0!
B12: EARNINGS | C12: ROA | E12: =Trend!C93/((Financials!C5+Financials!#REF!)/2) -> #REF! | F12: =Trend!D93/((Financials!D5+Financials!#REF!)/2) -> #REF! | G12: =Trend!E93/((Financials!E5+Financials!#REF!)/2) -> #REF! | H12: =Trend!F93/((Financials!F5+Financials!E5)/2) -> #DIV/0! | I12: =Trend!G93/((Financials!G5+Financials!F5)/2) -> #DIV/0! | J12: =Trend!H93/((Financials!H5+Financials!G5)/2) -> #DIV/0! | K12: =Trend!J93/((Financials!I5+Financials!H5)/2) -> 0.043969275 | L12: =Trend!K93/((Financials!J5+Financials!I5)/2) -> 0.047409696 | M12: =Trend!L93/((Financials!K5+Financials!J5)/2) -> 0.0054622622 | N12: =Trend!M93/((Financials!L5+Financials!K5)/2) -> 0.012313385 | O12: =Trend!N93/((Financials!M5+Financials!L5)/2) -> 0.017991919 | P12: =Trend!O93/((Financials!N5+Financials!M5)/2) -> 0.018930527 | Q12: =Trend!P93/((Financials!O5+Financials!N5)/2) -> 0.021616046 | R12: =Trend!Q93/((Financials!P5+Financials!O5)/2) -> 0.03439028 | ... AE12: =Trend!AD93/((Financials!AC5+Financials!AB5)/2) -> 0.049666493
C13: C/I ratio | E13: =Trend!C79/(Trend!C75-Trend!C76) -> #DIV/0! | F13: =Trend!D79/(Trend!D75-Trend!D76) -> #DIV/0! | G13: =Trend!E79/(Trend!E75-Trend!E76) -> #DIV/0! | H13: =Trend!F79/(Trend!F75-Trend!F76) -> #DIV/0! | I13: =Trend!G79/(Trend!G75-Trend!G76) -> #DIV/0! | J13: =Trend!H79/(Trend!H75-Trend!H76) -> #DIV/0! | K13: =Trend!J79/(Trend!J75-Trend!J76) -> 0.05995046 | L13: =Trend!K79/(Trend!K75-Trend!K76) -> 0.068232903 | M13: =Trend!L79/(Trend!L75-Trend!L76) -> 0.015816382 | N13: =Trend!M79/(Trend!M75-Trend!M76) -> 0.040395691 | O13: =Trend!N79/(Trend!N75-Trend!N76) -> 0.043773449 | P13: =Trend!O79/(Trend!O75-Trend!O76) -> 0.18399576 | Q13: =Trend!P79/(Trend!P75-Trend!P76) -> 0.18556365 | R13: =Trend!Q79/(Trend!Q75-Trend!Q76) -> 0.13235929 | ... AE13: =Trend!AD79/(Trend!AD75-Trend!AD76) -> 0.079634973
C14: OE ratio | E14: =Trend!C79/((Financials!C5+Financials!#REF!)/2) -> #REF! | F14: =Trend!D79/((Financials!D5+Financials!#REF!)/2) -> #REF! | G14: =Trend!E79/((Financials!E5+Financials!#REF!)/2) -> #REF! | H14: =Trend!F79/((Financials!F5+Financials!E5)/2) -> #DIV/0! | I14: =Trend!G79/((Financials!G5+Financials!F5)/2) -> #DIV/0! | J14: =Trend!H79/((Financials!H5+Financials!G5)/2) -> #DIV/0! | K14: =Trend!J79/((Financials!I5+Financials!H5)/2) -> 0.0034048644 | L14: =Trend!K79/((Financials!J5+Financials!I5)/2) -> 0.0038871202 | M14: =Trend!L79/((Financials!K5+Financials!J5)/2) -> 8.7781612e-05 | N14: =Trend!M79/((Financials!L5+Financials!K5)/2) -> 0.00051834665 | O14: =Trend!N79/((Financials!M5+Financials!L5)/2) -> 0.00082362109 | P14: =Trend!O79/((Financials!N5+Financials!M5)/2) -> 0.0042685278 | Q14: =Trend!P79/((Financials!O5+Financials!N5)/2) -> 0.0049250655 | R14: =Trend!Q79/((Financials!P5+Financials!O5)/2) -> 0.0052462649 | ... AE14: =Trend!AD79/((Financials!AC5+Financials!AB5)/2) -> 0.0042974143
B16: LIQUIDITY | C16: W NLIQ ratio | D16: Min 15% | E16: =(Trend!C5+Trend!C13)/(Financials!C10+Trend!C28+Trend!C29) -> #DIV/0! | F16: =(Trend!D5+Trend!D13)/(Financials!D10+Trend!D28+Trend!D29) -> #DIV/0! | G16: =Financials!E37/(Financials!E10+Financials!E8+Financials!E7) -> #DIV/0! | H16: =Financials!F37/(Financials!F10+Financials!F8+Financials!F7) -> #DIV/0! | I16: =Financials!G37/(Financials!G10+Financials!G8+Financials!G7) -> #DIV/0! | J16: =Financials!H37/(Financials!H10+Financials!H8+Financials!H7) -> #DIV/0! | K16: =Financials!I37/(Financials!I10+Financials!I8+Financials!I7) -> 1.2134485 | L16: =Financials!J37/(Financials!J10+Financials!J8+Financials!J7) -> 0.58798135 | M16: =Financials!K37/(Financials!K10+Financials!K8+Financials!K7) -> 0.48317978 | N16: =Financials!L37/(Financials!L10+Financials!L8+Financials!L7) -> 0.34328374 | ... AE16: =Financials!AC37/(Financials!AC10+Financials!AC8+Financials!AC7) -> 0.2580997
C17: T NLIQ ratio | E17: =(Trend!C5+Trend!C13+Trend!C12)/Financials!C6 -> #DIV/0! | F17: =(Trend!D5+Trend!D13+Trend!D12)/Financials!D6 -> #DIV/0! | G17: =(Trend!E5+Trend!E10+Trend!E12)/Financials!E6 -> #DIV/0! | H17: =(Trend!F5+Trend!F10+Trend!F12)/Financials!F6 -> #DIV/0! | I17: =(Trend!G5+Trend!G10+Trend!G12)/Financials!G6 -> #DIV/0! | J17: =(Trend!H5+Trend!H10+Trend!H12)/Financials!H6 -> #DIV/0! | K17: =(Trend!J5+Trend!J10+Trend!J12)/Financials!I6 -> 1.3256337 | L17: =(Trend!K5+Trend!K10+Trend!K12)/Financials!J6 -> 0.6404423 | M17: =(Trend!L5+Trend!L10+Trend!L12)/Financials!K6 -> 0.6227726 | N17: =(Trend!M5+Trend!M10+Trend!M12)/Financials!L6 -> 0.45641111 | O17: =(Trend!N5+Trend!N10+Trend!N12)/Financials!M6 -> 0.71181758 | P17: =(Trend!O5+Trend!O10+Trend!O12)/Financials!N6 -> 0.61893758 | Q17: =(Trend!P5+Trend!P10+Trend!P12)/Financials!O6 -> 0.569774 | R17: =(Trend!Q5+Trend!Q10+Trend!Q12)/Financials!P6 -> 0.50355704 | ... AE17: =(Trend!AD5+Trend!AD10+Trend!AD12)/Financials!AC6 -> 0.2898798
C18: EB ratio | D18: Max 25% | E18: =Financials!C9/Financials!C5 -> #DIV/0! | F18: =Financials!D9/Financials!D5 -> #DIV/0! | G18: =Financials!E9/Financials!E5 -> #DIV/0! | H18: =Financials!F9/Financials!F5 -> #DIV/0! | I18: =Financials!G9/Financials!G5 -> #DIV/0! | J18: =Financials!H9/Financials!H5 -> #DIV/0! | K18: =Financials!I9/Financials!I5 -> 0.19592308 | L18: =Financials!J9/Financials!J5 -> 0.025622014 | ... AE18: =Financials!AC9/Financials!AC5 -> 0.007238279
C19: LIQ to TA ratio | E19: =(Trend!C5+Trend!C13)/Trend!C27 -> #DIV/0! | F19: =(Trend!D5+Trend!D13)/Trend!D27 -> #DIV/0! | G19: =Financials!E37/Financials!E5 -> #DIV/0! | H19: =Financials!F37/Financials!F5 -> #DIV/0! | I19: =Financials!G37/Financials!G5 -> #DIV/0! | J19: =Financials!H37/Financials!H5 -> #DIV/0! | K19: =Financials!I37/Financials!I5 -> 0.81837856 | L19: =Financials!J37/Financials!J5 -> 0.49847308 | M19: =Financials!K37/Financials!K5 -> 0.41346894 | N19: =Financials!L37/Financials!L5 -> 0.29562249 | ... AE19: =Financials!AC37/Financials!AC5 -> 0.19786021
B21: STRUCTURE OF ASSETS | C21: LB ratio | D21: Max 5% | E21: =Financials!C41/Financials!C5 -> #DIV/0! | F21: =Financials!D41/Financials!D5 -> #DIV/0! | G21: =Financials!E41/Financials!E5 -> #DIV/0! | H21: =Financials!F41/Financials!F5 -> #DIV/0! | I21: =Financials!G41/Financials!G5 -> #DIV/0! | J21: =Financials!H41/Financials!H5 -> #DIV/0! | K21: =Financials!I41/Financials!I5 -> 0 | L21: =Financials!J41/Financials!J5 -> 0 | ... AE21: =Financials!AC41/Financials!AC5 -> 0
C22: FICC | D22: Max 40% | E22: =Financials!C26/Financials!C13 -> #DIV/0! | F22: =Financials!D26/Financials!D13 -> #DIV/0! | G22: =Financials!E26/Financials!E13 -> #DIV/0! | H22: =Financials!F26/Financials!F13 -> #DIV/0! | I22: =Financials!G26/Financials!G13 -> #DIV/0! | J22: =Financials!H26/Financials!H13 -> #DIV/0! | K22: =Financials!I26/Financials!I13 -> 0.19676285 | L22: =Financials!J26/Financials!J13 -> 0.067457721 | ... AE22: =Financials!AC26/Financials!AC13 -> 0.059678312
C23: FITD | D23: Max 5% | E23: =Financials!C26/Financials!C6 -> #DIV/0! | F23: =Financials!D26/Financials!D6 -> #DIV/0! | G23: =Financials!E26/Financials!E6 -> #DIV/0! | H23: =Financials!F26/Financials!F6 -> #DIV/0! | I23: =Financials!G26/Financials!G6 -> #DIV/0! | J23: =Financials!H26/Financials!H6 -> #DIV/0! | K23: =Financials!I26/Financials!I6 -> 0.034348749 | L23: =Financials!J26/Financials!J6 -> 0.010788282 | ... AE23: =Financials!AC26/Financials!AC6 -> 0.016798751
C24: Gross Loans/TA | E24: =Financials!C32/Financials!C5 -> #DIV/0! | F24: =Financials!D32/Financials!D5 -> #DIV/0! | G24: =Financials!E32/Financials!E5 -> #DIV/0! | H24: =Financials!F32/Financials!F5 -> #DIV/0! | I24: =Financials!G32/Financials!G5 -> #DIV/0! | J24: =Financials!H32/Financials!H5 -> #DIV/0! | K24: =Financials!I32/Financials!I5 -> 0.14708793 | L24: =Financials!J32/Financials!J5 -> 0.47224595 | ... AE24: =Financials!AC32/Financials!AC5 -> 0.79215513
C25: NEA | D25: Max 10% | E25: =Financials!C39/Financials!C5 -> #DIV/0! | F25: =Financials!D39/Financials!D5 -> #DIV/0! | G25: =Financials!E39/Financials!E5 -> #DIV/0! | H25: =Financials!F39/Financials!F5 -> #DIV/0! | I25: =Financials!G39/Financials!G5 -> #DIV/0! | J25: =Financials!H39/Financials!H5 -> #DIV/0! | K25: =Financials!I39/Financials!I5 -> 0.012764273 | L25: =Financials!J39/Financials!J5 -> 0.020740305 | ... AE25: =Financials!AC39/Financials!AC5 -> 0.0023545088
A28: RATING PARAMETERS | B28: CAPITAL | C28: CORE CAPITAL | D28: 10M | E28: =IF(E3>10,1,5) -> 5 | F28: =IF(F3>10,1,5) -> 5 | G28: =IF(G3>10,1,5) -> 5 | H28: =IF(H3>10,1,5) -> 5 | I28: =IF(I3>10,1,5) -> 5 | J28: =IF(J3>10,1,5) -> 5 | K28: =IF(K3>10,1,5) -> 1 | L28: =IF(L3>10,1,5) -> 1 | ... AE28: =IF(AE3>10,1,5) -> 1
C29: CCA | D29: Min 10% | E29: =IF(E4>20%,1,IF(E4>15,2,IF(E4>12,3,IF(E4>10,4,5)))) -> #DIV/0! | F29: =IF(F4>20%,1,IF(F4>15,2,IF(F4>12,3,IF(F4>10,4,5)))) -> #DIV/0! | G29: =IF(G4>20%,1,IF(G4>15,2,IF(G4>12,3,IF(G4>10,4,5)))) -> #DIV/0! | H29: =IF(H4>20%,1,IF(H4>15,2,IF(H4>12,3,IF(H4>10,4,5)))) -> #DIV/0! | I29: =IF(I4>20%,1,IF(I4>15,2,IF(I4>12,3,IF(I4>10,4,5)))) -> #DIV/0! | J29: =IF(J4>20%,1,IF(J4>15,2,IF(J4>12,3,IF(J4>10,4,5)))) -> #DIV/0! | K29: =IF(K4>20%,1,IF(K4>15,2,IF(K4>12,3,IF(K4>10,4,5)))) -> 5 | L29: =IF(L4>20%,1,IF(L4>15,2,IF(L4>12,3,IF(L4>10,4,5)))) -> 5 | ... AE29: =IF(AE4>20%,1,IF(AE4>15,2,IF(AE4>12,3,IF(AE4>10,4,5)))) -> 1
C30: ICA | D30: Min 8% | E30: =IF(E5>15,1,IF(E5>12,2,IF(E5>10,3,IF(E5>8,4,5)))) -> #DIV/0! | F30: =IF(F5>15,1,IF(F5>12,2,IF(F5>10,3,IF(F5>8,4,5)))) -> #DIV/0! | G30: =IF(G5>15,1,IF(G5>12,2,IF(G5>10,3,IF(G5>8,4,5)))) -> #DIV/0! | H30: =IF(H5>15,1,IF(H5>12,2,IF(H5>10,3,IF(H5>8,4,5)))) -> #DIV/0! | I30: =IF(I5>15,1,IF(I5>12,2,IF(I5>10,3,IF(I5>8,4,5)))) -> #DIV/0! | J30: =IF(J5>15,1,IF(J5>12,2,IF(J5>10,3,IF(J5>8,4,5)))) -> #DIV/0! | K30: =IF(K5>15,1,IF(K5>12,2,IF(K5>10,3,IF(K5>8,4,5)))) -> 5 | L30: =IF(L5>15,1,IF(L5>12,2,IF(L5>10,3,IF(L5>8,4,5)))) -> 5 | ... AE30: =IF(AE5>15,1,IF(AE5>12,2,IF(AE5>10,3,IF(AE5>8,4,5)))) -> 5
C31: CCD | D31: Min 8% | E31: =IF(E6>20%,1,IF(E6>12%,2,IF(E6>10%,3,IF(E6>8%,4,5)))) -> #DIV/0! | F31: =IF(F6>20%,1,IF(F6>12%,2,IF(F6>10%,3,IF(F6>8%,4,5)))) -> #DIV/0! | G31: =IF(G6>20%,1,IF(G6>12%,2,IF(G6>10%,3,IF(G6>8%,4,5)))) -> #DIV/0! | H31: =IF(H6>20%,1,IF(H6>12%,2,IF(H6>10%,3,IF(H6>8%,4,5)))) -> #DIV/0! | I31: =IF(I6>20%,1,IF(I6>12%,2,IF(I6>10%,3,IF(I6>8%,4,5)))) -> #DIV/0! | J31: =IF(J6>20%,1,IF(J6>12%,2,IF(J6>10%,3,IF(J6>8%,4,5)))) -> #DIV/0! | K31: =IF(K6>20%,1,IF(K6>12%,2,IF(K6>10%,3,IF(K6>8%,4,5)))) -> 2 | L31: =IF(L6>20%,1,IF(L6>12%,2,IF(L6>10%,3,IF(L6>8%,4,5)))) -> 2 | ... AE31: =IF(AE6>20%,1,IF(AE6>12%,2,IF(AE6>10%,3,IF(AE6>8%,4,5)))) -> 1
C32: Adjusted CCA | E32: =IF(E7>20%,1,IF(E7>15%,2,IF(E7>12%,3,IF(E7>10%,4,5)))) -> #DIV/0! | F32: =IF(F7>20%,1,IF(F7>15%,2,IF(F7>12%,3,IF(F7>10%,4,5)))) -> #DIV/0! | G32: =IF(G7>20%,1,IF(G7>15%,2,IF(G7>12%,3,IF(G7>10%,4,5)))) -> #DIV/0! | H32: =IF(H7>20%,1,IF(H7>15%,2,IF(H7>12%,3,IF(H7>10%,4,5)))) -> #DIV/0! | I32: =IF(I7>20%,1,IF(I7>15%,2,IF(I7>12%,3,IF(I7>10%,4,5)))) -> #DIV/0! | J32: =IF(J7>20%,1,IF(J7>15%,2,IF(J7>12%,3,IF(J7>10%,4,5)))) -> #DIV/0! | K32: =IF(K7>20%,1,IF(K7>15%,2,IF(K7>12%,3,IF(K7>10%,4,5)))) -> 4 | L32: =IF(L7>20%,1,IF(L7>15%,2,IF(L7>12%,3,IF(L7>10%,4,5)))) -> 3 | ... AE32: =IF(AE7>20%,1,IF(AE7>15%,2,IF(AE7>12%,3,IF(AE7>10%,4,5)))) -> 1
B34: ASSET QUALITY | C34: NPL30 | E34: =IF(E9<4,1,IF(E9<8,2,IF(E9<12,3,IF(E9<15,4,5)))) -> #DIV/0! | F34: =IF(F9<4,1,IF(F9<8,2,IF(F9<12,3,IF(F9<15,4,5)))) -> #DIV/0! | G34: =IF(G9<4,1,IF(G9<8,2,IF(G9<12,3,IF(G9<15,4,5)))) -> #DIV/0! | H34: =IF(H9<4,1,IF(H9<8,2,IF(H9<12,3,IF(H9<15,4,5)))) -> #DIV/0! | I34: =IF(I9<4,1,IF(I9<8,2,IF(I9<12,3,IF(I9<15,4,5)))) -> #DIV/0! | J34: =IF(J9<4,1,IF(J9<8,2,IF(J9<12,3,IF(J9<15,4,5)))) -> 1 | K34: =IF(K9<4,1,IF(K9<8,2,IF(K9<12,3,IF(K9<15,4,5)))) -> 1 | L34: =IF(L9<4,1,IF(L9<8,2,IF(L9<12,3,IF(L9<15,4,5)))) -> 1 | ... AE34: =IF(AE9<4,1,IF(AE9<8,2,IF(AE9<12,3,IF(AE9<15,4,5)))) -> 1
C35: A/L NPL30 | E35: =IF(E10<4,1,IF(E10<8,2,IF(E10<12,3,IF(E10<15,4,5)))) -> #DIV/0! | F35: =IF(F10<4,1,IF(F10<8,2,IF(F10<12,3,IF(F10<15,4,5)))) -> #DIV/0! | G35: =IF(G10<4,1,IF(G10<8,2,IF(G10<12,3,IF(G10<15,4,5)))) -> #DIV/0! | H35: =IF(H10<4,1,IF(H10<8,2,IF(H10<12,3,IF(H10<15,4,5)))) -> #DIV/0! | I35: =IF(I10<4,1,IF(I10<8,2,IF(I10<12,3,IF(I10<15,4,5)))) -> #DIV/0! | J35: =IF(J10<4,1,IF(J10<8,2,IF(J10<12,3,IF(J10<15,4,5)))) -> 1 | K35: =IF(K10<4,1,IF(K10<8,2,IF(K10<12,3,IF(K10<15,4,5)))) -> 1 | L35: =IF(L10<4,1,IF(L10<8,2,IF(L10<12,3,IF(L10<15,4,5)))) -> 1 | ... AE35: =IF(AE10<4,1,IF(AE10<8,2,IF(AE10<12,3,IF(AE10<15,4,5)))) -> 1
B37: EARNINGS | C37: ROA | E37: =IF(E16>6,1,IF(E16>4,2,IF(E16>2,3,IF(E16>0,4,5)))) -> #DIV/0! | F37: =IF(F16>6,1,IF(F16>4,2,IF(F16>2,3,IF(F16>0,4,5)))) -> #DIV/0! | G37: =IF(G16>6,1,IF(G16>4,2,IF(G16>2,3,IF(G16>0,4,5)))) -> #DIV/0! | H37: =IF(H16>6,1,IF(H16>4,2,IF(H16>2,3,IF(H16>0,4,5)))) -> #DIV/0! | I37: =IF(I16>6,1,IF(I16>4,2,IF(I16>2,3,IF(I16>0,4,5)))) -> #DIV/0! | J37: =IF(J16>6,1,IF(J16>4,2,IF(J16>2,3,IF(J16>0,4,5)))) -> #DIV/0! | K37: =IF(K16>6,1,IF(K16>4,2,IF(K16>2,3,IF(K16>0,4,5)))) -> 4 | L37: =IF(L16>6,1,IF(L16>4,2,IF(L16>2,3,IF(L16>0,4,5)))) -> 4 | ... AE37: =IF(AE16>6,1,IF(AE16>4,2,IF(AE16>2,3,IF(AE16>0,4,5)))) -> 4
C38: C/I ratio | E38: =IF(E13<60,1,IF(E13<70,2,IF(E13<80,3,IF(E13<90,4,5)))) -> #DIV/0! | F38: =IF(F13<60,1,IF(F13<70,2,IF(F13<80,3,IF(F13<90,4,5)))) -> #DIV/0! | G38: =IF(G13<60,1,IF(G13<70,2,IF(G13<80,3,IF(G13<90,4,5)))) -> #DIV/0! | H38: =IF(H13<60,1,IF(H13<70,2,IF(H13<80,3,IF(H13<90,4,5)))) -> #DIV/0! | I38: =IF(I13<60,1,IF(I13<70,2,IF(I13<80,3,IF(I13<90,4,5)))) -> #DIV/0! | J38: =IF(J13<60,1,IF(J13<70,2,IF(J13<80,3,IF(J13<90,4,5)))) -> #DIV/0! | K38: =IF(K13<60,1,IF(K13<70,2,IF(K13<80,3,IF(K13<90,4,5)))) -> 1 | L38: =IF(L13<60,1,IF(L13<70,2,IF(L13<80,3,IF(L13<90,4,5)))) -> 1 | ... AE38: =IF(AE13<60,1,IF(AE13<70,2,IF(AE13<80,3,IF(AE13<90,4,5)))) -> 1
C39: OE ratio | E39: =IF(E14>10,5,IF(E14>8,4,IF(E14>6,3,IF(E14>4,2,1)))) -> #REF! | F39: =IF(F14>10,5,IF(F14>8,4,IF(F14>6,3,IF(F14>4,2,1)))) -> #REF! | G39: =IF(G14>10,5,IF(G14>8,4,IF(G14>6,3,IF(G14>4,2,1)))) -> #REF! | H39: =IF(H14>10,5,IF(H14>8,4,IF(H14>6,3,IF(H14>4,2,1)))) -> #DIV/0! | I39: =IF(I14>10,5,IF(I14>8,4,IF(I14>6,3,IF(I14>4,2,1)))) -> #DIV/0! | J39: =IF(J14>10,5,IF(J14>8,4,IF(J14>6,3,IF(J14>4,2,1)))) -> #DIV/0! | K39: =IF(K14>10,5,IF(K14>8,4,IF(K14>6,3,IF(K14>4,2,1)))) -> 1 | L39: =IF(L14>10,5,IF(L14>8,4,IF(L14>6,3,IF(L14>4,2,1)))) -> 1 | ... AE39: =IF(AE14>10,5,IF(AE14>8,4,IF(AE14>6,3,IF(AE14>4,2,1)))) -> 1
B41: LIQUIDITY | C41: W NLIQ ratio | D41: Min 15% | E41: =IF(E16>30,1,IF(E16>25,2,IF(E16>20,3,IF(E16>15,4,5)))) -> #DIV/0! | F41: =IF(F16>30,1,IF(F16>25,2,IF(F16>20,3,IF(F16>15,4,5)))) -> #DIV/0! | G41: =IF(G16>30,1,IF(G16>25,2,IF(G16>20,3,IF(G16>15,4,5)))) -> #DIV/0! | H41: =IF(H16>30,1,IF(H16>25,2,IF(H16>20,3,IF(H16>15,4,5)))) -> #DIV/0! | I41: =IF(I16>30,1,IF(I16>25,2,IF(I16>20,3,IF(I16>15,4,5)))) -> #DIV/0! | J41: =IF(J16>30,1,IF(J16>25,2,IF(J16>20,3,IF(J16>15,4,5)))) -> #DIV/0! | K41: =IF(K16>30,1,IF(K16>25,2,IF(K16>20,3,IF(K16>15,4,5)))) -> 5 | L41: =IF(L16>30,1,IF(L16>25,2,IF(L16>20,3,IF(L16>15,4,5)))) -> 5 | ... AE41: =IF(AE16>30,1,IF(AE16>25,2,IF(AE16>20,3,IF(AE16>15,4,5)))) -> 5
C42: T NLIQ ratio | E42: =IF(E17>30,1,IF(E17>25,2,IF(E17>20,3,IF(E17>15,4,5)))) -> #DIV/0! | F42: =IF(F17>30,1,IF(F17>25,2,IF(F17>20,3,IF(F17>15,4,5)))) -> #DIV/0! | G42: =IF(G17>30,1,IF(G17>25,2,IF(G17>20,3,IF(G17>15,4,5)))) -> #DIV/0! | H42: =IF(H17>30,1,IF(H17>25,2,IF(H17>20,3,IF(H17>15,4,5)))) -> #DIV/0! | I42: =IF(I17>30,1,IF(I17>25,2,IF(I17>20,3,IF(I17>15,4,5)))) -> #DIV/0! | J42: =IF(J17>30,1,IF(J17>25,2,IF(J17>20,3,IF(J17>15,4,5)))) -> #DIV/0! | K42: =IF(K17>30,1,IF(K17>25,2,IF(K17>20,3,IF(K17>15,4,5)))) -> 5 | L42: =IF(L17>30,1,IF(L17>25,2,IF(L17>20,3,IF(L17>15,4,5)))) -> 5 | ... AE42: =IF(AE17>30,1,IF(AE17>25,2,IF(AE17>20,3,IF(AE17>15,4,5)))) -> 5
C43: EB ratio | D43: Max 25% | E43: =IF(E18<15,1,IF(E18<18,2,IF(E18<22,3,IF(E18<25,4,5)))) -> #DIV/0! | F43: =IF(F18<15,1,IF(F18<18,2,IF(F18<22,3,IF(F18<25,4,5)))) -> #DIV/0! | G43: =IF(G18<15,1,IF(G18<18,2,IF(G18<22,3,IF(G18<25,4,5)))) -> #DIV/0! | H43: =IF(H18<15,1,IF(H18<18,2,IF(H18<22,3,IF(H18<25,4,5)))) -> #DIV/0! | I43: =IF(I18<15,1,IF(I18<18,2,IF(I18<22,3,IF(I18<25,4,5)))) -> #DIV/0! | J43: =IF(J18<15,1,IF(J18<18,2,IF(J18<22,3,IF(J18<25,4,5)))) -> #DIV/0! | K43: =IF(K18<15,1,IF(K18<18,2,IF(K18<22,3,IF(K18<25,4,5)))) -> 1 | L43: =IF(L18<15,1,IF(L18<18,2,IF(L18<22,3,IF(L18<25,4,5)))) -> 1 | ... AE43: =IF(AE18<15,1,IF(AE18<18,2,IF(AE18<22,3,IF(AE18<25,4,5)))) -> 1
C44: LIQ to TA ratio | E44: =IF(E19>15,1,IF(E19>12,2,IF(E19>9,3,IF(E19>6,4,5)))) -> #DIV/0! | F44: =IF(F19>15,1,IF(F19>12,2,IF(F19>9,3,IF(F19>6,4,5)))) -> #DIV/0! | G44: =IF(G19>15,1,IF(G19>12,2,IF(G19>9,3,IF(G19>6,4,5)))) -> #DIV/0! | H44: =IF(H19>15,1,IF(H19>12,2,IF(H19>9,3,IF(H19>6,4,5)))) -> #DIV/0! | I44: =IF(I19>15,1,IF(I19>12,2,IF(I19>9,3,IF(I19>6,4,5)))) -> #DIV/0! | J44: =IF(J19>15,1,IF(J19>12,2,IF(J19>9,3,IF(J19>6,4,5)))) -> #DIV/0! | K44: =IF(K19>15,1,IF(K19>12,2,IF(K19>9,3,IF(K19>6,4,5)))) -> 5 | L44: =IF(L19>15,1,IF(L19>12,2,IF(L19>9,3,IF(L19>6,4,5)))) -> 5 | ... AE44: =IF(AE19>15,1,IF(AE19>12,2,IF(AE19>9,3,IF(AE19>6,4,5)))) -> 5
B46: STRUCTURE OF ASSETS | C46: LB ratio | D46: Max 5% | E46: =IF(E21<2,1,IF(E21<3,2,IF(E21<4,3,IF(E21<5,4,5)))) -> #DIV/0! | F46: =IF(F21<2,1,IF(F21<3,2,IF(F21<4,3,IF(F21<5,4,5)))) -> #DIV/0! | G46: =IF(G21<2,1,IF(G21<3,2,IF(G21<4,3,IF(G21<5,4,5)))) -> #DIV/0! | H46: =IF(H21<2,1,IF(H21<3,2,IF(H21<4,3,IF(H21<5,4,5)))) -> #DIV/0! | I46: =IF(I21<2,1,IF(I21<3,2,IF(I21<4,3,IF(I21<5,4,5)))) -> #DIV/0! | J46: =IF(J21<2,1,IF(J21<3,2,IF(J21<4,3,IF(J21<5,4,5)))) -> #DIV/0! | K46: =IF(K21<2,1,IF(K21<3,2,IF(K21<4,3,IF(K21<5,4,5)))) -> 1 | L46: =IF(L21<2,1,IF(L21<3,2,IF(L21<4,3,IF(L21<5,4,5)))) -> 1 | ... AE46: =IF(AE21<2,1,IF(AE21<3,2,IF(AE21<4,3,IF(AE21<5,4,5)))) -> 1
C47: FICC | D47: Max 40% | E47: =IF(E22<20,1,IF(E22<25,2,IF(E22<30,3,IF(E22<40,4,5)))) -> #DIV/0! | F47: =IF(F22<20,1,IF(F22<25,2,IF(F22<30,3,IF(F22<40,4,5)))) -> #DIV/0! | G47: =IF(G22<20,1,IF(G22<25,2,IF(G22<30,3,IF(G22<40,4,5)))) -> #DIV/0! | H47: =IF(H22<20,1,IF(H22<25,2,IF(H22<30,3,IF(H22<40,4,5)))) -> #DIV/0! | I47: =IF(I22<20,1,IF(I22<25,2,IF(I22<30,3,IF(I22<40,4,5)))) -> #DIV/0! | J47: =IF(J22<20,1,IF(J22<25,2,IF(J22<30,3,IF(J22<40,4,5)))) -> #DIV/0! | K47: =IF(K22<20,1,IF(K22<25,2,IF(K22<30,3,IF(K22<40,4,5)))) -> 1 | L47: =IF(L22<20,1,IF(L22<25,2,IF(L22<30,3,IF(L22<40,4,5)))) -> 1 | ... AE47: =IF(AE22<20,1,IF(AE22<25,2,IF(AE22<30,3,IF(AE22<40,4,5)))) -> 1
C48: FITD | D48: Max 5% | E48: =IF(E22<2,1,IF(E22<3,2,IF(E22<4,3,IF(E22<5,4,5)))) -> #DIV/0! | F48: =IF(F22<2,1,IF(F22<3,2,IF(F22<4,3,IF(F22<5,4,5)))) -> #DIV/0! | G48: =IF(G22<2,1,IF(G22<3,2,IF(G22<4,3,IF(G22<5,4,5)))) -> #DIV/0! | H48: =IF(H22<2,1,IF(H22<3,2,IF(H22<4,3,IF(H22<5,4,5)))) -> #DIV/0! | I48: =IF(I22<2,1,IF(I22<3,2,IF(I22<4,3,IF(I22<5,4,5)))) -> #DIV/0! | J48: =IF(J22<2,1,IF(J22<3,2,IF(J22<4,3,IF(J22<5,4,5)))) -> #DIV/0! | K48: =IF(K22<2,1,IF(K22<3,2,IF(K22<4,3,IF(K22<5,4,5)))) -> 1 | L48: =IF(L22<2,1,IF(L22<3,2,IF(L22<4,3,IF(L22<5,4,5)))) -> 1 | ... AE48: =IF(AE22<2,1,IF(AE22<3,2,IF(AE22<4,3,IF(AE22<5,4,5)))) -> 1
C49: NEA | D49: Max 10% | E49: =IF(E25<6,1,IF(E25<7,2,IF(E25<8,3,IF(E25<10,4,5)))) -> #DIV/0! | F49: =IF(F25<6,1,IF(F25<7,2,IF(F25<8,3,IF(F25<10,4,5)))) -> #DIV/0! | G49: =IF(G25<6,1,IF(G25<7,2,IF(G25<8,3,IF(G25<10,4,5)))) -> #DIV/0! | H49: =IF(H25<6,1,IF(H25<7,2,IF(H25<8,3,IF(H25<10,4,5)))) -> #DIV/0! | I49: =IF(I25<6,1,IF(I25<7,2,IF(I25<8,3,IF(I25<10,4,5)))) -> #DIV/0! | J49: =IF(J25<6,1,IF(J25<7,2,IF(J25<8,3,IF(J25<10,4,5)))) -> #DIV/0! | K49: =IF(K25<6,1,IF(K25<7,2,IF(K25<8,3,IF(K25<10,4,5)))) -> 1 | L49: =IF(L25<6,1,IF(L25<7,2,IF(L25<8,3,IF(L25<10,4,5)))) -> 1 | ... AE49: =IF(AE25<6,1,IF(AE25<7,2,IF(AE25<8,3,IF(AE25<10,4,5)))) -> 1
A54: INDICATOR WEIGHTS | B54: CAPITAL | C54: CORE CAPITAL | E54: 0.01 | F54: 0.01 | G54: 0.01 | H54: 0.01 | I54: 0.01 | J54: 0.01 | K54: 0.01 | L54: 0.01 | M54: 0.01 | N54: 0.01 | O54: 0.01 | P54: 0.01 | Q54: 0.01 | R54: 0.01 | S54: 0.01 | T54: 0.01 | U54: 0.01 | V54: 0.01 | W54: 0.01 | X54: 0.01 | Y54: 0.01 | Z54: 0.01 | AA54: 0.01 | AB54: 0.01 | AC54: 0.01 | AD54: 0.01 | AE54: 0.01
C55: CCA (Min 10%) | E55: 0.2 | F55: 0.2 | G55: 0.2 | H55: 0.2 | I55: 0.2 | J55: 0.2 | K55: 0.2 | L55: 0.2 | M55: 0.2 | N55: 0.2 | O55: 0.2 | P55: 0.2 | Q55: 0.2 | R55: 0.2 | S55: 0.2 | T55: 0.2 | U55: 0.2 | V55: 0.2 | W55: 0.2 | X55: 0.2 | Y55: 0.2 | Z55: 0.2 | AA55: 0.2 | AB55: 0.2 | AC55: 0.2 | AD55: 0.2 | AE55: 0.2
C56: ICA (Min 8%) | E56: 0.2 | F56: 0.2 | G56: 0.2 | H56: 0.2 | I56: 0.2 | J56: 0.2 | K56: 0.2 | L56: 0.2 | M56: 0.2 | N56: 0.2 | O56: 0.2 | P56: 0.2 | Q56: 0.2 | R56: 0.2 | S56: 0.2 | T56: 0.2 | U56: 0.2 | V56: 0.2 | W56: 0.2 | X56: 0.2 | Y56: 0.2 | Z56: 0.2 | AA56: 0.2 | AB56: 0.2 | AC56: 0.2 | AD56: 0.2 | AE56: 0.2
C57: CCD (Min 8%) | E57: 0.2 | F57: 0.2 | G57: 0.2 | H57: 0.2 | I57: 0.2 | J57: 0.2 | K57: 0.2 | L57: 0.2 | M57: 0.2 | N57: 0.2 | O57: 0.2 | P57: 0.2 | Q57: 0.2 | R57: 0.2 | S57: 0.2 | T57: 0.2 | U57: 0.2 | V57: 0.2 | W57: 0.2 | X57: 0.2 | Y57: 0.2 | Z57: 0.2 | AA57: 0.2 | AB57: 0.2 | AC57: 0.2 | AD57: 0.2 | AE57: 0.2
C58: Adjusted CCA | E58: 0.39 | F58: 0.39 | G58: 0.39 | H58: 0.39 | I58: 0.39 | J58: 0.39 | K58: 0.39 | L58: 0.39 | M58: 0.39 | N58: 0.39 | O58: 0.39 | P58: 0.39 | Q58: 0.39 | R58: 0.39 | S58: 0.39 | T58: 0.39 | U58: 0.39 | V58: 0.39 | W58: 0.39 | X58: 0.39 | Y58: 0.39 | Z58: 0.39 | AA58: 0.39 | AB58: 0.39 | AC58: 0.39 | AD58: 0.39 | AE58: 0.39
B59: ASSET QUALITY | C59: NPL30 | E59: 0.7 | F59: 0.7 | G59: 0.7 | H59: 0.7 | I59: 0.7 | J59: 0.7 | K59: 0.7 | L59: 0.7 | M59: 0.7 | N59: 0.7 | O59: 0.7 | P59: 0.7 | Q59: 0.7 | R59: 0.7 | S59: 0.7 | T59: 0.7 | U59: 0.7 | V59: 0.7 | W59: 0.7 | X59: 0.7 | Y59: 0.7 | Z59: 0.7 | AA59: 0.7 | AB59: 0.7 | AC59: 0.7 | AD59: 0.7 | AE59: 0.7
C60: A/L NPL30 | E60: 0.3 | F60: 0.3 | G60: 0.3 | H60: 0.3 | I60: 0.3 | J60: 0.3 | K60: 0.3 | L60: 0.3 | M60: 0.3 | N60: 0.3 | O60: 0.3 | P60: 0.3 | Q60: 0.3 | R60: 0.3 | S60: 0.3 | T60: 0.3 | U60: 0.3 | V60: 0.3 | W60: 0.3 | X60: 0.3 | Y60: 0.3 | Z60: 0.3 | AA60: 0.3 | AB60: 0.3 | AC60: 0.3 | AD60: 0.3 | AE60: 0.3
B61: EARNINGS | C61: ROA | E61: 0.5 | F61: 0.5 | G61: 0.5 | H61: 0.5 | I61: 0.5 | J61: 0.5 | K61: 0.5 | L61: 0.5 | M61: 0.5 | N61: 0.5 | O61: 0.5 | P61: 0.5 | Q61: 0.5 | R61: 0.5 | S61: 0.5 | T61: 0.5 | U61: 0.5 | V61: 0.5 | W61: 0.5 | X61: 0.5 | Y61: 0.5 | Z61: 0.5 | AA61: 0.5 | AB61: 0.5 | AC61: 0.5 | AD61: 0.5 | AE61: 0.5
C62: C/I ratio | E62: 0.25 | F62: 0.25 | G62: 0.25 | H62: 0.25 | I62: 0.25 | J62: 0.25 | K62: 0.25 | L62: 0.25 | M62: 0.25 | N62: 0.25 | O62: 0.25 | P62: 0.25 | Q62: 0.25 | R62: 0.25 | S62: 0.25 | T62: 0.25 | U62: 0.25 | V62: 0.25 | W62: 0.25 | X62: 0.25 | Y62: 0.25 | Z62: 0.25 | AA62: 0.25 | AB62: 0.25 | AC62: 0.25 | AD62: 0.25 | AE62: 0.25
C63: OE ratio | E63: 0.25 | F63: 0.25 | G63: 0.25 | H63: 0.25 | I63: 0.25 | J63: 0.25 | K63: 0.25 | L63: 0.25 | M63: 0.25 | N63: 0.25 | O63: 0.25 | P63: 0.25 | Q63: 0.25 | R63: 0.25 | S63: 0.25 | T63: 0.25 | U63: 0.25 | V63: 0.25 | W63: 0.25 | X63: 0.25 | Y63: 0.25 | Z63: 0.25 | AA63: 0.25 | AB63: 0.25 | AC63: 0.25 | AD63: 0.25 | AE63: 0.25
B64: LIQUIDITY | C64: W NLIQ ratio | E64: 0.4 | F64: 0.4 | G64: 0.4 | H64: 0.4 | I64: 0.4 | J64: 0.4 | K64: 0.4 | L64: 0.4 | M64: 0.4 | N64: 0.4 | O64: 0.4 | P64: 0.4 | Q64: 0.4 | R64: 0.4 | S64: 0.4 | T64: 0.4 | U64: 0.4 | V64: 0.4 | W64: 0.4 | X64: 0.4 | Y64: 0.4 | Z64: 0.4 | AA64: 0.4 | AB64: 0.4 | AC64: 0.4 | AD64: 0.4 | AE64: 0.4
C65: T NLIQ ratio | E65: 0.2 | F65: 0.2 | G65: 0.2 | H65: 0.2 | I65: 0.2 | J65: 0.2 | K65: 0.2 | L65: 0.2 | M65: 0.2 | N65: 0.2 | O65: 0.2 | P65: 0.2 | Q65: 0.2 | R65: 0.2 | S65: 0.2 | T65: 0.2 | U65: 0.2 | V65: 0.2 | W65: 0.2 | X65: 0.2 | Y65: 0.2 | Z65: 0.2 | AA65: 0.2 | AB65: 0.2 | AC65: 0.2 | AD65: 0.2 | AE65: 0.2
C66: EB ratio | E66: 0.2 | F66: 0.2 | G66: 0.2 | H66: 0.2 | I66: 0.2 | J66: 0.2 | K66: 0.2 | L66: 0.2 | M66: 0.2 | N66: 0.2 | O66: 0.2 | P66: 0.2 | Q66: 0.2 | R66: 0.2 | S66: 0.2 | T66: 0.2 | U66: 0.2 | V66: 0.2 | W66: 0.2 | X66: 0.2 | Y66: 0.2 | Z66: 0.2 | AA66: 0.2 | AB66: 0.2 | AC66: 0.2 | AD66: 0.2 | AE66: 0.2
C67: LIQ to TA ratio | E67: 0.2 | F67: 0.2 | G67: 0.2 | H67: 0.2 | I67: 0.2 | J67: 0.2 | K67: 0.2 | L67: 0.2 | M67: 0.2 | N67: 0.2 | O67: 0.2 | P67: 0.2 | Q67: 0.2 | R67: 0.2 | S67: 0.2 | T67: 0.2 | U67: 0.2 | V67: 0.2 | W67: 0.2 | X67: 0.2 | Y67: 0.2 | Z67: 0.2 | AA67: 0.2 | AB67: 0.2 | AC67: 0.2 | AD67: 0.2 | AE67: 0.2
B68: STRUCTURE OF ASSETS | C68: LB ratio (Max 5%) | E68: 0.25 | F68: 0.25 | G68: 0.25 | H68: 0.25 | I68: 0.25 | J68: 0.25 | K68: 0.25 | L68: 0.25 | M68: 0.25 | N68: 0.25 | O68: 0.25 | P68: 0.25 | Q68: 0.25 | R68: 0.25 | S68: 0.25 | T68: 0.25 | U68: 0.25 | V68: 0.25 | W68: 0.25 | X68: 0.25 | Y68: 0.25 | Z68: 0.25 | AA68: 0.25 | AB68: 0.25 | AC68: 0.25 | AD68: 0.25 | AE68: 0.25
C69: FICC (Max 40%) | E69: 0.25 | F69: 0.25 | G69: 0.25 | H69: 0.25 | I69: 0.25 | J69: 0.25 | K69: 0.25 | L69: 0.25 | M69: 0.25 | N69: 0.25 | O69: 0.25 | P69: 0.25 | Q69: 0.25 | R69: 0.25 | S69: 0.25 | T69: 0.25 | U69: 0.25 | V69: 0.25 | W69: 0.25 | X69: 0.25 | Y69: 0.25 | Z69: 0.25 | AA69: 0.25 | AB69: 0.25 | AC69: 0.25 | AD69: 0.25 | AE69: 0.25
C70: FITD (Max 5%) | E70: 0.25 | F70: 0.25 | G70: 0.25 | H70: 0.25 | I70: 0.25 | J70: 0.25 | K70: 0.25 | L70: 0.25 | M70: 0.25 | N70: 0.25 | O70: 0.25 | P70: 0.25 | Q70: 0.25 | R70: 0.25 | S70: 0.25 | T70: 0.25 | U70: 0.25 | V70: 0.25 | W70: 0.25 | X70: 0.25 | Y70: 0.25 | Z70: 0.25 | AA70: 0.25 | AB70: 0.25 | AC70: 0.25 | AD70: 0.25 | AE70: 0.25
C71: NEA (Max 10%) | E71: 0.25 | F71: 0.25 | G71: 0.25 | H71: 0.25 | I71: 0.25 | J71: 0.25 | K71: 0.25 | L71: 0.25 | M71: 0.25 | N71: 0.25 | O71: 0.25 | P71: 0.25 | Q71: 0.25 | R71: 0.25 | S71: 0.25 | T71: 0.25 | U71: 0.25 | V71: 0.25 | W71: 0.25 | X71: 0.25 | Y71: 0.25 | Z71: 0.25 | AA71: 0.25 | AB71: 0.25 | AC71: 0.25 | AD71: 0.25 | AE71: 0.25
A73: COMPONENT RATINGS | B73: CAPITAL | E73: =IF(MAX(#REF!)-E79>1,MAX(#REF!)-1,E79) -> #REF! | F73: =IF(MAX(#REF!)-F79>1,MAX(#REF!)-1,F79) -> #REF! | G73: =IF(MAX(#REF!)-G79>1,MAX(#REF!)-1,G79) -> #REF! | H73: =IF(MAX(#REF!)-H79>1,MAX(#REF!)-1,H79) -> #REF! | I73: =IF(MAX(#REF!)-I79>1,MAX(#REF!)-1,I79) -> #REF! | J73: =IF(MAX(#REF!)-J79>1,MAX(#REF!)-1,J79) -> #REF! | K73: =IF(MAX(#REF!)-K79>1,MAX(#REF!)-1,K79) -> #REF! | L73: =IF(MAX(#REF!)-L79>1,MAX(#REF!)-1,L79) -> #REF! | ... AE73: =IF(MAX(#REF!)-AE79>1,MAX(#REF!)-1,AE79) -> #REF!
B74: ASSET QUALITY | E74: =IF(MAX(E33:E34)-E80>1,MAX(E33:E34)-1,E80) -> #DIV/0! | F74: =IF(MAX(F33:F34)-F80>1,MAX(F33:F34)-1,F80) -> #DIV/0! | G74: =IF(MAX(G33:G34)-G80>1,MAX(G33:G34)-1,G80) -> #DIV/0! | H74: =IF(MAX(H33:H34)-H80>1,MAX(H33:H34)-1,H80) -> #DIV/0! | I74: =IF(MAX(I33:I34)-I80>1,MAX(I33:I34)-1,I80) -> #DIV/0! | J74: =IF(MAX(J33:J34)-J80>1,MAX(J33:J34)-1,J80) -> 1 | K74: =IF(MAX(K33:K34)-K80>1,MAX(K33:K34)-1,K80) -> 1 | L74: =IF(MAX(L33:L34)-L80>1,MAX(L33:L34)-1,L80) -> 1 | ... AE74: =IF(MAX(AE33:AE34)-AE80>1,MAX(AE33:AE34)-1,AE80) -> 1
B75: EARNINGS | E75: =IF(MAX(E37:E39)-E81>1,MAX(E37:E39)-1,E81) -> #DIV/0! | F75: =IF(MAX(F37:F39)-F81>1,MAX(F37:F39)-1,F81) -> #DIV/0! | G75: =IF(MAX(G37:G39)-G81>1,MAX(G37:G39)-1,G81) -> #DIV/0! | H75: =IF(MAX(H37:H39)-H81>1,MAX(H37:H39)-1,H81) -> #DIV/0! | I75: =IF(MAX(I37:I39)-I81>1,MAX(I37:I39)-1,I81) -> #DIV/0! | J75: =IF(MAX(J37:J39)-J81>1,MAX(J37:J39)-1,J81) -> #DIV/0! | K75: =IF(MAX(K37:K39)-K81>1,MAX(K37:K39)-1,K81) -> 3 | L75: =IF(MAX(L37:L39)-L81>1,MAX(L37:L39)-1,L81) -> 3 | ... AE75: =IF(MAX(AE37:AE39)-AE81>1,MAX(AE37:AE39)-1,AE81) -> 3
B76: LIQUIDITY | E76: =IF(MAX(E43:E44)-E82>1,MAX(E43:E44),E82) -> #DIV/0! | F76: =IF(MAX(F43:F44)-F82>1,MAX(F43:F44),F82) -> #DIV/0! | G76: =IF(MAX(G43:G44)-G82>1,MAX(G43:G44),G82) -> #DIV/0! | H76: =IF(MAX(H43:H44)-H82>1,MAX(H43:H44),H82) -> #DIV/0! | I76: =IF(MAX(I43:I44)-I82>1,MAX(I43:I44),I82) -> #DIV/0! | J76: =IF(MAX(J43:J44)-J82>1,MAX(J43:J44),J82) -> #DIV/0! | K76: =IF(MAX(K43:K44)-K82>1,MAX(K43:K44),K82) -> 4 | L76: =IF(MAX(L43:L44)-L82>1,MAX(L43:L44),L82) -> 4 | ... AE76: =IF(MAX(AE43:AE44)-AE82>1,MAX(AE43:AE44),AE82) -> 4
B77: STRUCTURE | E77: =IF(MAX(E46:E49)-E83>1,MAX(E46:E49)-1,E83) -> #DIV/0! | F77: =IF(MAX(F46:F49)-F83>1,MAX(F46:F49)-1,F83) -> #DIV/0! | G77: =IF(MAX(G46:G49)-G83>1,MAX(G46:G49)-1,G83) -> #DIV/0! | H77: =IF(MAX(H46:H49)-H83>1,MAX(H46:H49)-1,H83) -> #DIV/0! | I77: =IF(MAX(I46:I49)-I83>1,MAX(I46:I49)-1,I83) -> #DIV/0! | J77: =IF(MAX(J46:J49)-J83>1,MAX(J46:J49)-1,J83) -> #DIV/0! | K77: =IF(MAX(K46:K49)-K83>1,MAX(K46:K49)-1,K83) -> 1 | L77: =IF(MAX(L46:L49)-L83>1,MAX(L46:L49)-1,L83) -> 1 | ... AE77: =IF(MAX(AE46:AE49)-AE83>1,MAX(AE46:AE49)-1,AE83) -> 1
A79: CONDITIONAL COMPONENT RATINGS | B79: CAPITAL | E79: =ROUND(SUMPRODUCT(E28:E32,E54:E58),0) -> #DIV/0! | F79: =ROUND(SUMPRODUCT(F28:F32,F54:F58),0) -> #DIV/0! | G79: =ROUND(SUMPRODUCT(G28:G32,G54:G58),0) -> #DIV/0! | H79: =ROUND(SUMPRODUCT(H28:H32,H54:H58),0) -> #DIV/0! | I79: =ROUND(SUMPRODUCT(I28:I32,I54:I58),0) -> #DIV/0! | J79: =ROUND(SUMPRODUCT(J28:J32,J54:J58),0) -> #DIV/0! | K79: =ROUND(SUMPRODUCT(K28:K32,K54:K58),0) -> 4 | L79: =ROUND(SUMPRODUCT(L28:L32,L54:L58),0) -> 4 | ... AE79: =ROUND(SUMPRODUCT(AE28:AE32,AE54:AE58),0) -> 2
B80: ASSET QUALITY | E80: =ROUND(SUMPRODUCT(E34:E35,E59:E60),0) -> #DIV/0! | F80: =ROUND(SUMPRODUCT(F34:F35,F59:F60),0) -> #DIV/0! | G80: =ROUND(SUMPRODUCT(G34:G35,G59:G60),0) -> #DIV/0! | H80: =ROUND(SUMPRODUCT(H34:H35,H59:H60),0) -> #DIV/0! | I80: =ROUND(SUMPRODUCT(I34:I35,I59:I60),0) -> #DIV/0! | J80: =ROUND(SUMPRODUCT(J34:J35,J59:J60),0) -> 1 | K80: =ROUND(SUMPRODUCT(K34:K35,K59:K60),0) -> 1 | L80: =ROUND(SUMPRODUCT(L34:L35,L59:L60),0) -> 1 | ... AE80: =ROUND(SUMPRODUCT(AE34:AE35,AE59:AE60),0) -> 1
B81: EARNINGS | E81: =ROUND(SUMPRODUCT(E37:E39,E61:E63),0) -> #DIV/0! | F81: =ROUND(SUMPRODUCT(F37:F39,F61:F63),0) -> #DIV/0! | G81: =ROUND(SUMPRODUCT(G37:G39,G61:G63),0) -> #DIV/0! | H81: =ROUND(SUMPRODUCT(H37:H39,H61:H63),0) -> #DIV/0! | I81: =ROUND(SUMPRODUCT(I37:I39,I61:I63),0) -> #DIV/0! | J81: =ROUND(SUMPRODUCT(J37:J39,J61:J63),0) -> #DIV/0! | K81: =ROUND(SUMPRODUCT(K37:K39,K61:K63),0) -> 3 | L81: =ROUND(SUMPRODUCT(L37:L39,L61:L63),0) -> 3 | ... AE81: =ROUND(SUMPRODUCT(AE37:AE39,AE61:AE63),0) -> 3
B82: LIQUIDITY | E82: =ROUND(SUMPRODUCT(E41:E44,E64:E67),0) -> #DIV/0! | F82: =ROUND(SUMPRODUCT(F41:F44,F64:F67),0) -> #DIV/0! | G82: =ROUND(SUMPRODUCT(G41:G44,G64:G67),0) -> #DIV/0! | H82: =ROUND(SUMPRODUCT(H41:H44,H64:H67),0) -> #DIV/0! | I82: =ROUND(SUMPRODUCT(I41:I44,I64:I67),0) -> #DIV/0! | J82: =ROUND(SUMPRODUCT(J41:J44,J64:J67),0) -> #DIV/0! | K82: =ROUND(SUMPRODUCT(K41:K44,K64:K67),0) -> 4 | L82: =ROUND(SUMPRODUCT(L41:L44,L64:L67),0) -> 4 | ... AE82: =ROUND(SUMPRODUCT(AE41:AE44,AE64:AE67),0) -> 4
B83: STRUCTURE | E83: =ROUND(SUMPRODUCT(E46:E49,E68:E71),0) -> #DIV/0! | F83: =ROUND(SUMPRODUCT(F46:F49,F68:F71),0) -> #DIV/0! | G83: =ROUND(SUMPRODUCT(G46:G49,G68:G71),0) -> #DIV/0! | H83: =ROUND(SUMPRODUCT(H46:H49,H68:H71),0) -> #DIV/0! | I83: =ROUND(SUMPRODUCT(I46:I49,I68:I71),0) -> #DIV/0! | J83: =ROUND(SUMPRODUCT(J46:J49,J68:J71),0) -> #DIV/0! | K83: =ROUND(SUMPRODUCT(K46:K49,K68:K71),0) -> 1 | L83: =ROUND(SUMPRODUCT(L46:L49,L68:L71),0) -> 1 | ... AE83: =ROUND(SUMPRODUCT(AE46:AE49,AE68:AE71),0) -> 1
A85: COMPOSITE RATINGS | B85: CONDITION RATING | E85: =AVERAGE(E79:E83) -> #DIV/0! | F85: =AVERAGE(F79:F83) -> #DIV/0! | G85: =AVERAGE(G79:G83) -> #DIV/0! | I85: =AVERAGE(I79:I83) -> #DIV/0! | J85: =AVERAGE(J79:J83) -> #DIV/0! | K85: =AVERAGE(K79:K83) -> 2.6 | L85: =AVERAGE(L79:L83) -> 2.6 | M85: =AVERAGE(M79:M83) -> 2.8 | N85: =AVERAGE(N79:N83) -> 2.8 | O85: =AVERAGE(O79:O83) -> 2.4 | P85: =AVERAGE(P79:P83) -> 2.4 | ... AE85: =AVERAGE(AE79:AE83) -> 2.2
B86: AVERAGE OF COMP RATINGS | E86: =AVERAGE(E73:E77) -> #REF! | F86: =AVERAGE(F73:F77) -> #REF! | G86: =AVERAGE(G73:G77) -> #REF! | I86: =AVERAGE(I73:I77) -> #REF! | J86: =AVERAGE(J73:J77) -> #REF! | K86: =AVERAGE(K73:K77) -> #REF! | L86: =AVERAGE(L73:L77) -> #REF! | M86: =AVERAGE(M73:M77) -> #REF! | N86: =AVERAGE(N73:N77) -> #REF! | O86: =AVERAGE(O73:O77) -> #REF! | P86: =AVERAGE(P73:P77) -> #REF! | ... AE86: =AVERAGE(AE73:AE77) -> #REF!
B87: COMPLIANCE RATING SOFT | E87: =IF(MAX(E73:E77)-E86>1,MAX(E73:E77)-1,E86) -> #REF! | F87: =IF(MAX(F73:F77)-F86>1,MAX(F73:F77)-1,F86) -> #REF! | G87: =IF(MAX(G73:G77)-G86>1,MAX(G73:G77)-1,G86) -> #REF! | I87: =IF(MAX(I73:I77)-I86>1,MAX(I73:I77)-1,I86) -> #REF! | J87: =IF(MAX(J73:J77)-J86>1,MAX(J73:J77)-1,J86) -> #REF! | K87: =IF(MAX(K73:K77)-K86>1,MAX(K73:K77)-1,K86) -> #REF! | L87: =IF(MAX(L73:L77)-L86>1,MAX(L73:L77)-1,L86) -> #REF! | M87: =IF(MAX(M73:M77)-M86>1,MAX(M73:M77)-1,M86) -> #REF! | N87: =IF(MAX(N73:N77)-N86>1,MAX(N73:N77)-1,N86) -> #REF! | O87: =IF(MAX(O73:O77)-O86>1,MAX(O73:O77)-1,O86) -> #REF! | P87: =IF(MAX(P73:P77)-P86>1,MAX(P73:P77)-1,P86) -> #REF! | ... AE87: =IF(MAX(AE73:AE77)-AE86>1,MAX(AE73:AE77)-1,AE86) -> #REF!
B88: FINAL RATING | C88: In the Law only | E88: =IF(MAX(E28,E29,E30,E31,E41,E43,E46,E47,E48,E49)-E85>1,MAX(E28,E29,E30,E31,E41,E43,E46,E47,E48,E49)-1,E85) -> #DIV/0! | F88: =IF(MAX(F28,F29,F30,F31,F41,F43,F46,F47,F48,F49)-F85>1,MAX(F28,F29,F30,F31,F41,F43,F46,F47,F48,F49)-1,F85) -> #DIV/0! | G88: =IF(MAX(G28,G29,G30,G31,G41,G43,G46,G47,G48,G49)-G85>1,MAX(G28,G29,G30,G31,G41,G43,G46,G47,G48,G49)-1,G85) -> #DIV/0! | I88: =IF(MAX(I28,I29,I30,I31,I41,I43,I46,I47,I48,I49)-I85>1,MAX(I28,I29,I30,I31,I41,I43,I46,I47,I48,I49)-1,I85) -> #DIV/0! | J88: =IF(MAX(J28,J29,J30,J31,J41,J43,J46,J47,J48,J49)-J85>1,MAX(J28,J29,J30,J31,J41,J43,J46,J47,J48,J49)-1,J85) -> #DIV/0! | K88: =IF(MAX(K28,K29,K30,K31,K41,K43,K46,K47,K48,K49)-K85>1,MAX(K28,K29,K30,K31,K41,K43,K46,K47,K48,K49)-1,K85) -> 4 | L88: =IF(MAX(L28,L29,L30,L31,L41,L43,L46,L47,L48,L49)-L85>1,MAX(L28,L29,L30,L31,L41,L43,L46,L47,L48,L49)-1,L85) -> 4 | M88: =IF(MAX(M28,M29,M30,M31,M41,M43,M46,M47,M48,M49)-M85>1,MAX(M28,M29,M30,M31,M41,M43,M46,M47,M48,M49)-1,M85) -> 4 | N88: =IF(MAX(N28,N29,N30,N31,N41,N43,N46,N47,N48,N49)-N85>1,MAX(N28,N29,N30,N31,N41,N43,N46,N47,N48,N49)-1,N85) -> 4 | O88: =IF(MAX(O28,O29,O30,O31,O41,O43,O46,O47,O48,O49)-O85>1,MAX(O28,O29,O30,O31,O41,O43,O46,O47,O48,O49)-1,O85) -> 4 | P88: =IF(MAX(P28,P29,P30,P31,P41,P43,P46,P47,P48,P49)-P85>1,MAX(P28,P29,P30,P31,P41,P43,P46,P47,P48,P49)-1,P85) -> 4 | ... AE88: =IF(MAX(AE28,AE29,AE30,AE31,AE41,AE43,AE46,AE47,AE48,AE49)-AE85>1,MAX(AE28,AE29,AE30,AE31,AE41,AE43,AE46,AE47,AE48,AE49)-1,AE85) -> 4

Sheet FORM 4
B1: FORM 4 SASRA2/004
B2: RISK CLASSIFICATION OF ASSETS AND PROVISIONING
B3: SACCO SOCIETY CS NUMBER | F3: 9231
B4: FINANCIAL YEAR | F4: 2019
B5: START DATE: | F5: 1/1/2019
B6: END DATE: | F6: 31/12/2019
B7: PORTFOLIO AGEING REPORT
C8: 43525 | G8: 43617 | K8: 43709
A9: NO. | B9: CLASSIFICATION | C9: NO. OF A/Cs | D9: OUTSTANDING LOAN PORTFOLIO(Kshs) | E9: REQUIRED PROVISION | F9: REQUIRED PROVISION AMOUNT(Kshs) | G9: NO. OF A/Cs | H9: OUTSTANDING LOAN PORTFOLIO(Kshs) | I9: REQUIRED PROVISION | J9: REQUIRED PROVISION AMOUNT(Kshs) | K9: NO. OF A/Cs | L9: OUTSTANDING LOAN PORTFOLIO(Kshs) | M9: REQUIRED PROVISION | N9: REQUIRED PROVISION AMOUNT(Kshs)
A10: 1 | B10: Performing | C10: 2556 | D10: 1.5929252e+08 | E10: 0.01 | F10: =D10*E10 -> 1592925.2 | I10: 0.01 | J10: =H10*I10 -> 0 | M10: 0.01 | N10: =L10*M10 -> 0
A11: 2 | B11: Watch | C11: 96 | D11: 10220980 | E11: 0.05 | F11: =D11*E11 -> 511049.01 | I11: 0.05 | J11: =H11*I11 -> 0 | M11: 0.05 | N11: =L11*M11 -> 0
A12: 3 | B12: Substandard | C12: 281 | D12: 9007217.3 | E12: 0.25 | F12: =D12*E12 -> 2251804.3 | I12: 0.25 | J12: =H12*I12 -> 0 | M12: 0.25 | N12: =L12*M12 -> 0
A13: 4 | B13: Doubtful | C13: 72 | D13: 3973123.9 | E13: 0.5 | F13: =D13*E13 -> 1986561.9 | I13: 0.5 | J13: =H13*I13 -> 0 | M13: 0.5 | N13: =L13*M13 -> 0
A14: 5 | B14: Loss | C14: 334 | D14: 8335591.8 | E14: 1 | F14: =D14*E14 -> 8335591.8 | I14: 1 | J14: =H14*I14 -> 0 | M14: 1 | N14: =L14*M14 -> 0
B15: subtotal | C15: =SUM(C10:C14) -> 3339 | D15: =SUM(D10:D14) -> 1.9082944e+08 | F15: =SUM(F10:F14) -> 14677932 | G15: =SUM(G10:G14) -> 0 | H15: =SUM(H10:H14) -> 0 | J15: =SUM(J10:J14) -> 0 | K15: =SUM(K10:K14) -> 0 | L15: =SUM(L10:L14) -> 0 | N15: =SUM(N10:N14) -> 0
B16: Reschedule/Renegotiated loans
A17: 1 | B17: Performing | C17: 0 | D17: 0 | E17: 0.01 | F17: =D17*E17 -> 0 | G17: 0 | H17: 0 | I17: 0.01 | J17: =H17*I17 -> 0 | K17: 0 | L17: 0 | M17: 0.01 | N17: =L17*M17 -> 0
A18: 2 | B18: Watch | C18: 0 | D18: 0 | E18: 0.05 | F18: =D18*E18 -> 0 | G18: 0 | H18: 0 | I18: 0.05 | J18: =H18*I18 -> 0 | K18: 0 | L18: 0 | M18: 0.05 | N18: =L18*M18 -> 0
A19: 3 | B19: Substandard | C19: 0 | D19: 0 | E19: 0.25 | F19: =D19*E19 -> 0 | G19: 0 | H19: 0 | I19: 0.25 | J19: =H19*I19 -> 0 | K19: 0 | L19: 0 | M19: 0.25 | N19: =L19*M19 -> 0
A20: 4 | B20: Doubtful | C20: 0 | D20: 0 | E20: 0.5 | F20: =D20*E20 -> 0 | G20: 0 | H20: 0 | I20: 0.5 | J20: =H20*I20 -> 0 | K20: 0 | L20: 0 | M20: 0.5 | N20: =L20*M20 -> 0
A21: 5 | B21: Loss | C21: 0 | D21: 0 | E21: 1 | F21: =D21*E21 -> 0 | G21: 0 | H21: 0 | I21: 1 | J21: =H21*I21 -> 0 | K21: 0 | L21: 0 | M21: 1 | N21: =L21*M21 -> 0
B22: subtotal | C22: =SUM(C16:C21) -> 0 | D22: =SUM(D16:D21) -> 0 | F22: =SUM(F16:F21) -> 0 | G22: =SUM(G16:G21) -> 0 | H22: =SUM(H16:H21) -> 0 | J22: =SUM(J16:J21) -> 0 | K22: =SUM(K16:K21) -> 0 | L22: =SUM(L16:L21) -> 0 | N22: =SUM(N16:N21) -> 0
B23: GRAND TOTAL | C23: =C15+C22 -> 3339 | D23: =D15+D22 -> 1.9082944e+08 | F23: =F15+F22 -> 14677932 | G23: =G15+G22 -> 0 | H23: =H15+H22 -> 0 | J23: =J15+J22 -> 0 | K23: =K15+K22 -> 0 | L23: =L15+L22 -> 0 | N23: =N15+N22 -> 0
B24: NPL | D24: =SUM(D12:D14) -> 21315933 | H24: =SUM(H12:H14) -> 0 | L24: =SUM(L12:L14) -> 0
B25: PAR | D25: =D24/D23 -> 0.11170149 | H25: =H24/H23 -> #DIV/0! | L25: =L24/L23 -> #DIV/0!
B26: provision for loan loss | D26: =F23-D28 -> 190476.31 | N26: =N23-Trend!#REF! -> #REF!
A27: Note: This return should be received on or before the 15th day of the month following end of every quarter
B28: Allowance for Loan Loss 2018 Audited accts | D28: 14487456
B29: AUTHORIZATION:
B30: We declare that this return, to the best of our knowledge and belief is correct.
B31: ……………………………………………………….... sign ………………….……………. date……………………………
B32: Name of Authorizing Officer
B33: ………………………………………………………... sign……………………………… date…………………………….
B34: Name of Countersigning Officer
