Workbook

Sheet SFP
B1: FORM 6 SASRA2/006
B2: STATEMENT OF FINANCIAL POSITION
B3: NAME OF SACCO SOCIETY: ECO PILLAR (KAPENGURIA TEACHERS)
B4: FINANCIAL YEAR
B5: START DATE:
B6: END DATE: | C6: AUDITED 2012 | D6: AUDITED 2013 | E6: Audited 2014 | F6: 42005 | G6: 42036 | H6: 42064 | I6: 42095 | J6: 42125 | K6: 42156 | L6: 42186 | M6: 42217 | N6: 42248 | O6: 42278 | P6: 42309 | Q6: 42339 | R6: Audited 2015 | S6: 42385 | T6: 42416 | U6: 42445 | V6: 42476 | W6: 42506 | X6: 42537 | Y6: 42567 | Z6: 42598 | AA6: 42629 | AB6: 42659 | AC6: 42690 | AD6: 42720 | AE6: 42736 | AF6: 42767 | AG6: 42795 | AH6: 42826 | AI6: 42856 | AJ6: 42887 | AK6: 42917 | AL6: 42948 | AM6: 42979 | AN6: 43009 | AO6: 43040 | AP6: 43070 | AQ6: Audited 2017 | AR6: 43101 | AS6: 43132 | AT6: 43160 | AU6: 43191 | AV6: 43221 | AW6: 43252 | AX6: 43282 | AY6: 43313 | AZ6: 43344 | BA6: 43374 | BB6: 43405 | BC6: 43435 | BD6: Aud-18 | BE6: 43466 | BF6: 43497 | BG6: 43525 | BH6: 43556 | BI6: 43586 | BJ6: 43617 | BK6: 43647 | BL6: 43678 | BM6: 43709 | BN6: 43739 | BO6: 43770 | BP6: 43800 | BQ6: Audited 2019 | BR6: 43831 | BS6: 43862 | BT6: 43891 | BU6: 43922 | BV6: 43952 | BW6: 43983 | BX6: 44013 | BY6: 44044 | BZ6: 44075 | CA6: 44105 | CB6: 44136 | CC6: 44166 | CD6: Audited 2020 | CE6: Audited 2021 | CF6: 44562 | CG6: 44593 | CH6: 44621 | CI6: 44652 | CJ6: 44682 | CK6: 44713 | CL6: 44743 | CM6: 44774 | CN6: 44805 | CO6: 44835 | CP6: 44866 | CQ6: 44896 | CR6: Dec 2022 Audited
A9: Ref No | B9: ASSETS
A10: 1 | B10: Cash & Cash Equivalent | C10: 37828323 | D10: 34544013 | E10: =SUM(E11:E12) -> 50299714 | F10: =SUM(F11:F12) -> 30898512 | G10: =SUM(G11:G12) -> 22594248 | H10: =SUM(H11:H12) -> 35458880 | I10: =SUM(I11:I12) -> 20508258 | J10: =SUM(J11:J12) -> 20541709 | K10: =SUM(K11:K12) -> 43473322 | L10: =SUM(L11:L12) -> 42233129 | ... CS10: =SUM(CS11:CS12) -> 0
A11: 1.1 | B11: Cash in hand(both local and foreign notes and coins) | E11: 7625036 | F11: 3785161.8 | G11: 7230893.8 | H11: 4355078.8 | I11: 5144903.8 | J11: 5178354.8 | K11: 4160419.8 | L11: 6998399.8 | M11: 15994075 | N11: 3164275.6 | O11: 6423052.6 | P11: 3251961.6 | Q11: 4783446.6 | R11: 7608696.6 | S11: 2185543.6 | T11: 566332.6 | U11: 1001426.6 | V11: 9687698.6 | W11: 2781993.6 | X11: 1167787.6 | Y11: 2836908.1 | Z11: 4903050 | AA11: 4482292.1 | AB11: 3047252.1 | AC11: 2369022.1 | AD11: 1993390.6 | AE11: 528036.1 | AF11: 6863519 | AG11: 4677222.1 | AH11: 3964643.1 | AI11: 4512542.1 | AJ11: 4109589.1 | AK11: 584739.1 | AL11: 1698185.5 | AM11: 2070296.1 | AN11: 2504803.1 | AO11: 2799938.9 | AP11: 3402526.1 | AQ11: 4473703 | AR11: 6815420.1 | AS11: 6943416.1 | AT11: 13048606 | AU11: 7558427 | AV11: 1764446.1 | AW11: 5022559.1 | AX11: 3616157.1 | AY11: 3237226.1 | AZ11: 3494679.1 | BA11: 3494679.1 | BB11: 1532967.4 | BC11: 15339910 | BD11: 17628340 | BE11: 3274500.1 | BF11: 10562660 | BG11: 8593830.1 | BH11: 6419700.1 | BI11: 6841160.1 | BJ11: 2002753.1 | BK11: 1336383.1 | BL11: 8756273.1 | BM11: 7694259.1 | BN11: 3781798.1 | BO11: 1629208.1 | BP11: 6219857.1 | BQ11: 10763824 | BR11: 4904382.1 | BS11: 5181862.1 | BT11: 663127.1 | BU11: 12508795 | BV11: 13260191 | BW11: 4899632.1 | BY11: 2551507.1 | BZ11: 9690616.1 | CA11: 2217402.1 | CB11: 2407666.1 | CC11: 617294.1 | CD11: =236504.1+380790+121895+6691847 -> 7431036.1 | CE11: =1876540+817640+121895+6444611 -> 9260686 | CF11: 2475953.1 | CG11: 13692810 | CH11: 5126391.1 | CI11: 763491.1 | CJ11: 4489306.1 | CK11: 8469153.1 | CL11: 5375585.1 | CM11: 3250325 | CN11: 962457 | CO11: 4444441 | CP11: 9185977 | CQ11: 774907
A12: 1.2 | B12: Cash at bank:(placement with financial institutions) | E12: 42674678 | F12: 27113350 | G12: 15363354 | H12: 31103802 | I12: 15363354 | J12: 15363354 | K12: 39312902 | L12: 35234729 | M12: 18425266 | N12: 56814495 | O12: 49957979 | P12: 29855363 | Q12: 35209919 | R12: 26083051 | S12: 37215014 | T12: 66129085 | U12: 65495563 | V12: 51970884 | W12: 93212764 | X12: 1.0241091e+08 | Y12: 1.0342108e+08 | Z12: 97528841 | AA12: 93432544 | AB12: 91594018 | AC12: 87153169 | AD12: 83782379 | AE12: 72216620 | AF12: 72879899 | AG12: 58343777 | AH12: 50957558 | AI12: 49268376 | AJ12: 59285199 | AK12: 50185029 | AL12: 50611375 | AM12: 46694402 | AN12: 64859617 | AO12: 69741486 | AP12: 82226406 | AQ12: 81155229 | AR12: 76918650 | AS12: 74755893 | AT12: 68058401 | AU12: 76415145 | AV12: 77406355 | AW12: 84669941 | AX12: 95527132 | AY12: 91815429 | AZ12: 90351487 | BA12: 90351487 | BB12: 94152297 | BC12: 97747448 | BD12: =51788836.75+41890172.55+7593.95+1976172.3-203757.85 -> 95459018 | BE12: 90076615 | BF12: 98632213 | BG12: 97521622 | BH12: 88504167 | BI12: 92167657 | BJ12: 97543488 | BK12: 94960184 | BL12: 89820042 | BM12: 1.0546745e+08 | BN12: 36806920 | BO12: 47180723 | BP12: 73068801 | BQ12: =67009876.6+321520.75+53309.7+7593+1133092.1-559.3 -> 68524833 | BR12: 33918458 | BS12: 27880363 | BT12: 41649350 | BU12: 33520607 | BV12: 52101459 | BW12: 77586120 | BY12: 57351045 | BZ12: 64680985 | CA12: 67984533 | CB12: 69703285 | CC12: 1.0237802e+08 | CD12: =61392673.3+429347.45+302307.25+7593.95+2454+46517+19632.6+32748871.25+-2415.4 -> 94946981 | CE12: =145762949-9260686 -> 136502263 | CF12: 1.0391534e+08 | CG12: 1.0199325e+08 | CH12: 93482430 | CI12: 1.0116455e+08 | CJ12: 1.1228537e+08 | CK12: 94222387 | CL12: 114804223 | CM12: 1.1751479e+08 | CN12: 1.7857995e+08 | CO12: 1.8890064e+08 | CP12: 2.1890064e+08 | CQ12: 1.8423676e+08
A13: 2 | B13: Prepayments & Sundry Receivables | C13: 21679003 | D13: 10068961 | E13: =10139889+134820232+129744+113867562 -> 258957427 | F13: 13679940 | G13: 101733797 | H13: 1.0937328e+08 | I13: 2.7706016e+08 | J13: 13679940 | K13: 2.6344487e+08 | L13: 2.6319353e+08 | M13: 2.7113116e+08 | O13: 2.7060451e+08 | P13: 2.9575405e+08 | Q13: 2.8244385e+08 | R13: 1.4405243e+08 | S13: 260187916 | T13: 3.3101983e+08 | U13: 3.233589e+08 | V13: 3.248621e+08 | W13: 2.8413293e+08 | X13: 2.5327936e+08 | Y13: 2.5163007e+08 | Z13: 2.4259642e+08 | AA13: 2.427855e+08 | AB13: 2.5756745e+08 | AC13: 2.4756366e+08 | AD13: 2.655252e+08 | AE13: 2.4676051e+08 | AF13: 2.5345305e+08 | AG13: 2.5561828e+08 | AH13: 2.5075067e+08 | AI13: 2.9654479e+08 | AJ13: 2.9102322e+08 | AK13: 2.9202652e+08 | AL13: 2.7255358e+08 | AM13: 2.6949753e+08 | AN13: 2.7270549e+08 | AO13: 2.3434263e+08 | AP13: 2.537381e+08 | AQ13: 244383762 | AR13: 2.2308901e+08 | AS13: 2.3037669e+08 | AT13: 2.5084187e+08 | AU13: 2.5125782e+08 | AV13: 2.749258e+08 | AX13: 2.785692e+08 | AY13: 2.946085e+08 | AZ13: 2.9359313e+08 | BA13: 2.9359313e+08 | BB13: 2.8625008e+08 | BC13: 2.2535988e+08 | BD13: 2.4282255e+08 | BE13: 1.4289018e+08 | BF13: 1.3467452e+08 | BG13: 1.3564782e+08 | BH13: 1.4221476e+08 | BI13: 1.3897491e+08 | BJ13: 1.5653713e+08 | BK13: 1.4820193e+08 | BL13: 1.2913807e+08 | BM13: 1.4756285e+08 | BN13: 2.0706101e+08 | BO13: 1.9650484e+08 | BP13: 2.4238557e+08 | BQ13: 2.7377833e+08 | BR13: 2.3168512e+08 | BS13: 2.5182354e+08 | BT13: 2.4092401e+08 | BU13: 2.6802922e+08 | BV13: 2.8250484e+08 | BW13: 2.5862592e+08 | BY13: 2.7288854e+08 | BZ13: 2.5904977e+08 | CA13: 2.4666889e+08 | CB13: 2.4050605e+08 | CC13: 2.2402078e+08 | CD13: 2.9475628e+08 | CE13: 287019357 | CF13: 2.2027759e+08 | CG13: 2.1184673e+08 | CH13: 2.9783031e+08 | CI13: 2.9324579e+08 | CJ13: 2.6400454e+08 | CK13: 2.8027957e+08 | CL13: 2.6552673e+08 | CM13: 2.6114129e+08 | CN13: 2.0684292e+08 | CO13: 1.964148e+08 | CP13: 1.8575727e+08 | CQ13: 2.4677593e+08
A14: 3 | B14: Financial Investments | C14: =SUM(C15:C18) -> 34475098 | D14: =SUM(D15:D18) -> 40570790 | E14: =SUM(E15:E18) -> 35208138 | F14: =SUM(F15:F18) -> 0 | G14: =SUM(G15:G18) -> 0 | H14: =SUM(H15:H18) -> 0 | I14: =SUM(I15:I18) -> 28462661 | J14: =SUM(J15:J18) -> 28462661 | ... CS14: =SUM(CS15:CS18) -> 0
A15: 3.1 | B15: Government Securities - Treasury Bills/bonds, | N15: 0 | S15: 0 | T15: 0 | U15: 0 | V15: 0 | X15: 0 | Y15: 0 | Z15: 0 | AB15: 0 | AC15: 0 | AD15: 0 | AE15: 0 | AF15: 0 | AG15: 0 | AH15: 0 | AI15: 0 | AJ15: 0 | AK15: 0 | AL15: 0 | AM15: 0 | AN15: 0 | AO15: 0 | AP15: 0 | AR15: 0 | AS15: 0 | AT15: 0 | AU15: 0 | AV15: 0 | AX15: 0 | AY15: 0 | AZ15: 0 | BA15: 0 | BB15: 0 | BC15: 0 | BD15: 0 | BE15: 0 | BF15: 0 | BG15: 0 | BH15: 0 | BI15: 0 | BJ15: 0 | BK15: 0 | BL15: 0 | BM15: 0 | BN15: 0 | BO15: 0 | BP15: 0 | BR15: 0 | BS15: 0 | BT15: 0 | BU15: 0 | BV15: 0 | BW15: 0 | BY15: 0 | BZ15: 0 | CA15: 0 | CB15: 0 | CC15: 0 | CF15: 0 | CG15: 0 | CH15: 0 | CI15: 0 | CJ15: 0 | CK15: 0 | CL15: 0 | CM15: 0 | CN15: 0 | CO15: 0 | CP15: 0 | CQ15: 0
A16: 3.2 | B16: Other Securities - Commercial papers/Bonds | E16: =11000+76528 -> 87528 | N16: 0 | S16: 0 | T16: 0 | U16: 0 | V16: 0 | X16: 0 | Y16: 0 | Z16: 0 | AB16: 0 | AC16: 0 | AD16: 0 | AE16: 0 | AF16: 0 | AG16: 0 | AH16: 0 | AI16: 0 | AJ16: 0 | AK16: 0 | AL16: 0 | AM16: 0 | AN16: 0 | AO16: 0 | AP16: 0 | AR16: 0 | AS16: 0 | AT16: 0 | AU16: 0 | AV16: 0 | AX16: 0 | AY16: 0 | AZ16: 0 | BA16: 0 | BB16: 0 | BC16: 0 | BD16: 0 | BE16: 0 | BF16: 0 | BG16: 0 | BH16: 0 | BI16: 0 | BJ16: 0 | BK16: 0 | BL16: 0 | BM16: 0 | BN16: 0 | BO16: 0 | BP16: 0 | BR16: 0 | BS16: 0 | BT16: 0 | BU16: 0 | BV16: 0 | BW16: 0 | BY16: 0 | BZ16: 0 | CA16: 0 | CB16: 0 | CC16: 0 | CF16: 0 | CG16: 0 | CH16: 0 | CI16: 0 | CJ16: 0 | CK16: 0 | CL16: 0 | CM16: 0 | CN16: 0 | CO16: 0 | CP16: 0 | CQ16: 0
A17: 3.3a | B17: Balances with other SACCO Societies | C17: 30347798 | D17: 32511490 | N17: 0 | S17: 0 | T17: 0 | U17: 0 | V17: 0 | X17: 0 | Y17: 0 | Z17: 0 | AB17: 0 | AC17: 0 | AD17: 0 | AE17: 0 | AF17: 0 | AG17: 0 | AH17: 0 | AI17: 0 | AJ17: 0 | AK17: 0 | AL17: 0 | AM17: 0 | AN17: 0 | AO17: 0 | AP17: 0 | AQ17: 19297893 | AR17: 0 | AS17: 0 | AT17: 0 | AU17: 0 | AV17: 0 | AX17: 0 | AY17: 0 | AZ17: 0 | BA17: 0 | BB17: 0 | BC17: 0 | BD17: 14708554 | BE17: 0 | BF17: 0 | BG17: 0 | BH17: 0 | BI17: 0 | BJ17: 0 | BK17: 0 | BL17: 0 | BM17: 0 | BN17: 0 | BO17: 0 | BP17: 0 | BQ17: 14442915 | BR17: 0 | BS17: 0 | BT17: 0 | BU17: 0 | BV17: 0 | BW17: 0 | BY17: 0 | BZ17: 0 | CA17: 0 | CB17: 0 | CC17: 0 | CD17: 14442918 | CE17: =11000+76528 -> 87528 | CF17: 0 | CG17: 0 | CH17: 0 | CI17: 0 | CJ17: 0 | CK17: 0 | CL17: 0 | CM17: 0 | CN17: 0 | CO17: 0 | CP17: 0 | CQ17: 0
A18: 3.3b | B18: Investments in companies - shares/stocks | C18: =3994772+11000+45000+76528 -> 4127300 | D18: =3942000+3984772+11000+45000+76528 -> 8059300 | E18: =6000000+9579348+3984772+15511490+45000 -> 35120610 | I18: 28462661 | J18: 28462661 | K18: 28462661 | L18: 28462661 | M18: 28462661 | N18: 28462661 | O18: 28462661 | P18: 28462661 | Q18: 28462661 | R18: 33641898 | S18: 28462661 | T18: 28462661 | U18: 28462661 | V18: 28462661 | W18: 22273509 | X18: 22273509 | Y18: 22273509 | Z18: 22273509 | AA18: 22273509 | AB18: 22273509 | AC18: 22273509 | AD18: 22273509 | AE18: 32448819 | AF18: 32448819 | AG18: 32448819 | AH18: 32448819 | AI18: 32448819 | AJ18: 32448819 | AK18: 34881096 | AL18: 34881096 | AM18: 34881096 | AN18: 34881096 | AO18: 34093974 | AP18: 34093974 | AQ18: 87528 | AR18: 34093974 | AS18: 34093974 | AT18: 34093974 | AU18: 34093974 | AV18: 34116047 | AW18: 34116047 | AX18: 34116047 | AY18: 34116047 | AZ18: 34116047 | BA18: 34116047 | BB18: 34116047 | BC18: 34116047 | BD18: =12011625+45000+6781017.6+11000+76528+482323+113186777 -> 1.3259427e+08 | BE18: 34116047 | BF18: 34116047 | BG18: 34529146 | BH18: 35575057 | BI18: 35775057 | BJ18: 38735057 | BK18: 38763252 | BL18: 36263252 | BM18: 34863252 | BN18: 34898176 | BO18: 34898176 | BP18: 34898176 | BQ18: 1.3364357e+08 | BR18: 34899711 | BS18: 35450236 | BT18: 35450733 | BU18: 35450733 | BV18: 35450733 | BW18: 35952324 | BY18: 39469709 | BZ18: 39506671 | CA18: 39506671 | CB18: 30613452 | CC18: 36618314 | CD18: 1.3536218e+08 | CE18: =135372831+14442917-87528 -> 149728220 | CF18: 36628968 | CG18: 36628968 | CH18: 36648066 | CI18: 36648066 | CJ18: 37196808 | CK18: 36398696 | CL18: 36398696 | CM18: 36399080 | CN18: 36399269 | CO18: 36399269 | CP18: 36399659 | CQ18: 23456744
A19: 4 | B19: Net Loan Portfolio | C19: =C20-C21 -> 3.0242896e+08 | D19: =D20-D21 -> 1.9123114e+08 | E19: =E20-E21 -> 237111555 | F19: =F20-F21 -> 2.4111051e+08 | G19: =G20-G21 -> 2.4155344e+08 | H19: =H20-H21 -> 2.3122683e+08 | I19: =I20-I21 -> 2.3341683e+08 | J19: =J20-J21 -> 2.3940967e+08 | ... CS19: =CS20-CS21 -> 0
B20: Gross Loan Portfolio | C20: 305479221 | D20: 1.9513381e+08 | E20: =180386268+66741713 -> 247127981 | F20: 2.4311463e+08 | G20: 2.4387353e+08 | H20: 2.3323095e+08 | I20: 2.4141379e+08 | J20: 2.4141379e+08 | K20: 2.4185374e+08 | L20: 2.4981319e+08 | M20: 2.5086799e+08 | N20: 2.8515109e+08 | O20: 3.1510298e+08 | P20: 3.15778e+08 | Q20: 3.2968773e+08 | R20: 258801812 | S20: 3.3932498e+08 | T20: 2.5311014e+08 | U20: 261440035 | V20: 2.7277301e+08 | W20: 2.5322397e+08 | X20: 2.5263731e+08 | Y20: 251123467 | Z20: 2.6447442e+08 | AA20: 2.6481779e+08 | AB20: 2.6339101e+08 | AC20: 2.6529082e+08 | AD20: 2.706052e+08 | AE20: 2.6730061e+08 | AF20: 2.7428541e+08 | AG20: 2.9225437e+08 | AH20: 2.9922121e+08 | AI20: 2.9429869e+08 | AJ20: 2.9880763e+08 | AK20: 3.0263226e+08 | AL20: 3.2077988e+08 | AM20: 3.2372741e+08 | AN20: 3.2059876e+08 | AO20: 3.4132997e+08 | AP20: 3.3460069e+08 | AQ20: 334089794 | AR20: 3.4105815e+08 | AS20: 3.4745152e+08 | AT20: 3.3593149e+08 | AU20: 3.3880095e+08 | AV20: 3.3187692e+08 | AW20: 3.2816436e+08 | AX20: 3.3303477e+08 | AY20: 3.1455427e+08 | AZ20: 3.1148918e+08 | BA20: 3.1148918e+08 | BB20: 3.2140363e+08 | BC20: 3.1844843e+08 | BD20: 318461829 | BE20: 3.4815466e+08 | BF20: 3.5454538e+08 | BG20: 3.484768e+08 | BH20: 3.4680111e+08 | BI20: 3.5584433e+08 | BJ20: 3.4870585e+08 | BK20: 3.5215567e+08 | BL20: 3.8123742e+08 | BM20: 3.6609873e+08 | BN20: 3.8274941e+08 | BO20: 3.9274699e+08 | BP20: 4.0621646e+08 | BQ20: 4.0604441e+08 | BR20: 4.0823919e+08 | BS20: 4.0164629e+08 | BT20: 3.9711314e+08 | BU20: 3.8384055e+08 | BV20: 3.9584636e+08 | BW20: 4.0442843e+08 | BY20: 4.2910041e+08 | BZ20: 4.3984774e+08 | CA20: 4.5990353e+08 | CB20: 4.5859292e+08 | CC20: 4.7110886e+08 | CD20: 4.7111686e+08 | CE20: 529871512 | CF20: 5.2931815e+08 | CG20: 5.31518e+08 | CH20: 5.339991e+08 | CI20: 5.3776946e+08 | CJ20: 5.3503708e+08 | CK20: 5.3438795e+08 | CL20: 5.3563081e+08 | CM20: 5.3824604e+08 | CN20: 5.3955404e+08 | CO20: 5.4255458e+08 | CP20: 5.447509e+08 | CQ20: 6.1787486e+08
B21: Allowance for Loan Loss | C21: 3050258.2 | D21: 3902676.2 | E21: 10016426 | F21: 2004119.4 | G21: 2320087 | H21: 2004119.4 | I21: 7996958.1 | J21: 2004119.4 | K21: 2547249.6 | L21: 2160622.9 | M21: 2720125.4 | N21: 3892150.5 | O21: 4393500.3 | P21: 5271719.2 | Q21: 7122341.1 | R21: 7504736 | S21: 2010478.7 | T21: 1010297.2 | U21: 2065128.3 | V21: 2370230.1 | W21: 1213077.3 | X21: 996699.5 | Y21: 1099590.1 | Z21: 2054575.7 | AA21: 1356716.5 | AB21: 11922708 | AC21: 10596215 | AD21: 18317843 | AE21: 11235789 | AF21: 12369785 | AG21: 11924753 | AH21: 12394568 | AI21: 11095883 | AJ21: 13741671 | AK21: 13340487 | AL21: 10375125 | AM21: 13645903 | AN21: 14379390 | AO21: 9825396.4 | AP21: 13788864 | AQ21: 13277969 | AR21: 13245897 | AS21: 11245365 | AT21: 12757388 | AU21: 13526987 | AV21: 14369785 | AW21: 10502228 | AX21: 11868566 | AY21: 9807410.6 | AZ21: 9609968.1 | BA21: 9609968.1 | BB21: 10509439 | BC21: 12013231 | BD21: 16777969 | BE21: 9625368.9 | BF21: 10225012 | BG21: 10867106 | BH21: 10735257 | BI21: 9298227.3 | BJ21: 9879712.9 | BK21: 9507885.7 | BL21: 9703533.6 | BM21: 9824517.5 | BN21: 10001064 | BO21: 10778845 | BP21: 22777969 | BQ21: 22777969 | BR21: 10523347 | BS21: 11311511 | BT21: 10722159 | BU21: 8260963.2 | BV21: 9145689.2 | BW21: 10699318 | BY21: 10257200 | BZ21: 10239570 | CA21: 10413070 | CB21: 11552130 | CC21: 29769969 | CD21: 29777969 | CE21: 36777969 | CF21: 6915696.2 | CG21: 6959043.4 | CH21: 6655279.3 | CI21: 7103146.2 | CJ21: 7315798.8 | CK21: 7178230.4 | CL21: 7595142 | CM21: 7494352.8 | CN21: 7730461 | CO21: 7725468.1 | CP21: 7825319.1 | CQ21: 7500000
A22: 5 | B22: Accounts Receivables | C22: 0 | E22: =SUM(E23:E25) -> 0 | F22: =SUM(F23:F25) -> 0 | G22: =SUM(G23:G25) -> 0 | H22: =SUM(H23:H25) -> 0 | I22: =SUM(I23:I25) -> 0 | J22: =SUM(J23:J25) -> 0 | K22: =SUM(K23:K25) -> 0 | L22: =SUM(L23:L25) -> 0 | ... CS22: =SUM(CS23:CS25) -> 0
A23: 5.1 | B23: Tax Recoverable | S23: 0 | T23: 0 | U23: 0 | V23: 0 | W23: 0 | X23: 0 | Y23: 0 | Z23: 0 | AB23: 0 | AC23: 0 | AD23: 0 | AE23: 0 | AF23: 0 | AG23: 0 | AH23: 0 | AI23: 0 | AJ23: 0 | AK23: 0 | AL23: 0 | AM23: 0 | AN23: 0 | AO23: 0 | AP23: 0 | AR23: 0 | AS23: 0 | AT23: 0 | AU23: 0 | AV23: 0 | AW23: 0 | AX23: 0 | AY23: 0 | AZ23: 0 | BA23: 0 | BB23: 0 | BC23: 0 | BD23: 0 | BE23: 0 | BF23: 0 | BG23: 0 | BH23: 0 | BI23: 0 | BJ23: 0 | BK23: 0 | BL23: 0 | BM23: 0 | BN23: 0 | BO23: 0 | BP23: 0 | BR23: 0 | BS23: 0 | BT23: 0 | BU23: 0 | BV23: 0 | BW23: 0 | BY23: 0 | BZ23: 0 | CA23: 0 | CB23: 0 | CC23: 0 | CF23: 0 | CG23: 0 | CH23: 0 | CI23: 0 | CJ23: 0 | CK23: 0 | CL23: 0 | CM23: 0 | CN23: 0 | CO23: 0 | CP23: 0 | CQ23: 0
A24: 5.2 | B24: Deferred Tax Assets | S24: 0 | T24: 0 | U24: 0 | V24: 0 | W24: 0 | X24: 0 | Y24: 0 | Z24: 0 | AB24: 0 | AC24: 0 | AD24: 0 | AE24: 0 | AF24: 0 | AG24: 0 | AH24: 0 | AI24: 0 | AJ24: 0 | AK24: 0 | AL24: 0 | AM24: 0 | AN24: 0 | AO24: 0 | AP24: 0 | AR24: 0 | AS24: 0 | AT24: 0 | AU24: 0 | AV24: 0 | AW24: 0 | AX24: 0 | AY24: 0 | AZ24: 0 | BA24: 0 | BB24: 0 | BC24: 0 | BD24: 0 | BE24: 0 | BF24: 0 | BG24: 0 | BH24: 0 | BI24: 0 | BJ24: 0 | BK24: 0 | BL24: 0 | BM24: 0 | BN24: 0 | BO24: 0 | BP24: 0 | BR24: 0 | BS24: 0 | BT24: 0 | BU24: 0 | BV24: 0 | BW24: 0 | BY24: 0 | BZ24: 0 | CA24: 0 | CB24: 0 | CC24: 0 | CF24: 0 | CG24: 0 | CH24: 0 | CI24: 0 | CJ24: 0 | CK24: 0 | CL24: 0 | CM24: 0 | CN24: 0 | CO24: 0 | CP24: 0 | CQ24: 0
A25: 5.3 | B25: Retirement Benefit Assets | S25: 0 | T25: 0 | U25: 0 | V25: 0 | W25: 0 | X25: 0 | Y25: 0 | Z25: 0 | AB25: 0 | AC25: 0 | AD25: 0 | AE25: 0 | AF25: 0 | AG25: 0 | AH25: 0 | AI25: 0 | AJ25: 0 | AK25: 0 | AL25: 0 | AM25: 0 | AN25: 0 | AO25: 0 | AP25: 0 | AR25: 0 | AS25: 0 | AT25: 0 | AU25: 0 | AV25: 0 | AW25: 0 | AX25: 0 | AY25: 0 | AZ25: 0 | BA25: 0 | BB25: 0 | BC25: 0 | BD25: 0 | BE25: 0 | BF25: 0 | BG25: 0 | BH25: 0 | BI25: 0 | BJ25: 0 | BK25: 0 | BL25: 0 | BM25: 0 | BN25: 0 | BO25: 0 | BP25: 0 | BR25: 0 | BS25: 0 | BT25: 0 | BU25: 0 | BV25: 0 | BW25: 0 | BY25: 0 | BZ25: 0 | CA25: 0 | CB25: 0 | CC25: 0 | CF25: 0 | CG25: 0 | CH25: 0 | CI25: 0 | CJ25: 0 | CK25: 0 | CL25: 0 | CM25: 0 | CN25: 0 | CO25: 0 | CP25: 0 | CQ25: 0
A26: 6 | B26: Property & Equipment & Other assets | C26: =SUM(C27:C31) -> 1.1680019e+08 | D26: =SUM(D27:D31) -> 2.6580812e+08 | E26: =SUM(E27:E31) -> 19672436 | F26: =SUM(F27:F31) -> 1.7844756e+08 | G26: =SUM(G27:G31) -> 1.7206346e+08 | H26: =SUM(H27:H31) -> 1.6531798e+08 | I26: =SUM(I27:I31) -> 19672436 | J26: =SUM(J27:J31) -> 19672436 | ... CS26: =SUM(CS27:CS31) -> 0
A27: 6.1 | B27: Investment Properties | F27: 23570790 | G27: 23570790 | H27: 16825313 | Q27: 0 | S27: 0 | T27: 0 | U27: 0 | V27: 0 | W27: 1.0718678e+08 | X27: 1.0718678e+08 | Y27: 1.0718678e+08 | Z27: 1.0718678e+08 | AA27: 1.0718678e+08 | AB27: 1.0718678e+08 | AC27: 1.0718678e+08 | AD27: 1.0718678e+08 | AE27: 1.0718678e+08 | AF27: 1.0718678e+08 | AG27: 1.0718678e+08 | AH27: 1.0718678e+08 | AI27: 1.0718678e+08 | AJ27: 1.0718678e+08 | AK27: 1.0718678e+08 | AL27: 1.0718678e+08 | AM27: 1.0718678e+08 | AN27: 1.0718678e+08 | AO27: 1.0718678e+08 | AP27: 1.0718678e+08 | AQ27: 41547728 | AR27: 1.1318678e+08 | AS27: 1.1318678e+08 | AT27: 1.1318678e+08 | AU27: 1.1318678e+08 | AV27: 1.1318678e+08 | AW27: 1.1318678e+08 | AX27: 1.1318678e+08 | AY27: 1.1318678e+08 | AZ27: 1.1318678e+08 | BA27: 1.1318678e+08 | BB27: 1.1318678e+08 | BC27: 1.1318678e+08 | BE27: 1.1318678e+08 | BF27: 1.1318678e+08 | BG27: 1.1318678e+08 | BH27: 1.1318678e+08 | BI27: 1.1318678e+08 | BJ27: 1.1318678e+08 | BK27: 1.1318678e+08 | BL27: 1.1318678e+08 | BM27: 1.1318678e+08 | BN27: 1.1318678e+08 | BO27: 1.1318678e+08 | BP27: 1.1318678e+08 | BR27: 1.1318678e+08 | BS27: 1.1318678e+08 | BT27: 1.1318678e+08 | BU27: 1.1318678e+08 | BV27: 1.1318678e+08 | BW27: 1.1318678e+08 | BY27: 1.1318678e+08 | BZ27: 1.1318678e+08 | CA27: 1.1318678e+08 | CB27: 1.1318678e+08 | CC27: 1.1318678e+08 | CF27: 1.1318678e+08 | CG27: 1.1318678e+08 | CH27: 1.1318678e+08 | CI27: 1.1318678e+08 | CJ27: 1.1318678e+08 | CK27: 1.1318678e+08 | CL27: 1.1318678e+08 | CM27: 1.1318678e+08 | CN27: 1.1318678e+08 | CO27: 1.1318678e+08 | CP27: 1.1318678e+08 | CQ27: 1.1318678e+08
A28: 6.2 | B28: Property & Equipment | C28: 1.1586468e+08 | D28: 6580532 | E28: =7375517+1934506+752103+114750+4949165+4546395 -> 19672436 | F28: 21344950 | G28: 19672436 | H28: 19672436 | I28: 19672436 | J28: 19672436 | K28: 19672436 | L28: 19672436 | M28: 19672436 | N28: 39853019 | O28: 39853019 | P28: 39853019 | Q28: 39853019 | R28: 19460785 | S28: 39853019 | T28: 39853019 | U28: 39853019 | V28: 30053019 | W28: 56865513 | X28: 56877263 | Y28: 56877263 | Z28: 56877263 | AA28: 56877263 | AB28: 56877263 | AC28: 64241230 | AD28: 64241230 | AE28: 64306230 | AF28: 64306230 | AG28: 64306230 | AH28: 64306230 | AI28: 64306230 | AJ28: 64306230 | AK28: 64306230 | AL28: 64349730 | AM28: 64349730 | AN28: 64349730 | AO28: 64349730 | AP28: 64349730 | AQ28: 10334868 | AR28: 75440365 | AS28: 65640365 | AT28: 65640365 | AU28: 65640365 | AV28: 65640365 | AW28: 65640365 | AX28: 66473165 | AY28: 66473165 | AZ28: 66473165 | BA28: 66473165 | BB28: 66433165 | BC28: 66433165 | BD28: 50224362 | BE28: 66433165 | BF28: 66433165 | BG28: 66433165 | BH28: 66433165 | BI28: 66563665 | BJ28: 66563665 | BK28: 66563665 | BL28: 66563665 | BM28: 66747665 | BN28: 66747665 | BO28: 66747665 | BP28: 66747665 | BQ28: 48670717 | BR28: 66797865 | BS28: 66797865 | BT28: 66797865 | BU28: 66797865 | BV28: 66860865 | BW28: 66785865 | BY28: 66745865 | BZ28: 66745865 | CA28: 63005865 | CB28: 63005865 | CC28: 63005865 | CD28: 46450359 | CE28: 51204736 | CF28: 69203921 | CG28: 69203921 | CH28: 69649922 | CI28: 69649922 | CJ28: 69701426 | CK28: 70119896 | CL28: 70119896 | CM28: 70119896 | CN28: 70119896 | CO28: 70119896 | CP28: 70119896 | CQ28: 49997050
A29: 6.3 | B29: Prepaid Lease rentals | Q29: 0 | S29: 0 | T29: 0 | U29: 0 | V29: 0 | W29: 0 | X29: 0 | Y29: 0 | Z29: 0 | AA29: 0 | AB29: 0 | AC29: 0 | AD29: 0 | AE29: 0 | AF29: 0 | AG29: 0 | AH29: 0 | AI29: 0 | AJ29: 0 | AK29: 0 | AL29: 0 | AM29: 0 | AN29: 0 | AO29: 0 | AP29: 0 | AR29: 0 | AS29: 0 | AT29: 0 | AU29: 0 | AV29: 0 | AW29: 0 | AX29: 0 | AY29: 0 | AZ29: 0 | BA29: 0 | BB29: 0 | BC29: 0 | BE29: 0 | BF29: 0 | BG29: 0 | BH29: 0 | BI29: 0 | BJ29: 0 | BK29: 0 | BL29: 0 | BM29: 0 | BN29: 0 | BO29: 0 | BP29: 0 | BR29: 0 | BS29: 0 | BT29: 0 | BU29: 0 | BV29: 0 | BW29: 0 | BY29: 0 | BZ29: 0 | CA29: 0 | CB29: 0 | CC29: 0 | CD29: 0 | CF29: 0 | CG29: 0 | CH29: 0 | CI29: 0 | CJ29: 0 | CK29: 0 | CL29: 0 | CM29: 0 | CN29: 0 | CO29: 0 | CP29: 0 | CQ29: 0
A30: 6.4 | B30: Intangible Assets | Q30: 0 | R30: 6536600 | S30: 0 | T30: 0 | U30: 0 | V30: 9800000 | W30: 9800000 | X30: 9800000 | Y30: 9800000 | Z30: 9800000 | AA30: 9800000 | AB30: 9800000 | AC30: 9800000 | AD30: 9800000 | AE30: 9800000 | AF30: 9800000 | AG30: 9800000 | AH30: 9800000 | AI30: 9800000 | AJ30: 9800000 | AK30: 9800000 | AL30: 9800000 | AM30: 9800000 | AN30: 9800000 | AO30: 9800000 | AP30: 9800000 | AQ30: 2906753 | AR30: 9800000 | AS30: 9800000 | AT30: 9800000 | AU30: 9800000 | AV30: 9800000 | AW30: 9800000 | AX30: 9800000 | AY30: 9800000 | AZ30: 9800000 | BA30: 9800000 | BB30: 16300000 | BC30: 16300000 | BD30: 6271482 | BE30: 16300000 | BF30: 16300000 | BG30: 16300000 | BH30: 16300000 | BI30: 16300000 | BJ30: 16300000 | BK30: 16300000 | BL30: 16300000 | BM30: 16300000 | BN30: 16300000 | BO30: 16300000 | BP30: 16300000 | BQ30: 4181197.1 | BR30: 16300000 | BS30: 17518000 | BT30: 17518000 | BU30: 17518000 | BV30: 17518000 | BW30: 17518000 | BY30: 17518000 | BZ30: 17518000 | CA30: 17518000 | CB30: 17518000 | CC30: 17518000 | CD30: 3599645 | CE30: 2699734 | CF30: 17648000 | CG30: 17648000 | CH30: 17648000 | CI30: 25734000 | CJ30: 25734000 | CK30: 25734000 | CL30: 25734000 | CM30: 25734000 | CN30: 25734000 | CO30: 25734000 | CP30: 25734000 | CQ30: 8186800.5
A31: 6.5 | B31: Other Assets | C31: 935514 | D31: 2.5922759e+08 | F31: 1.3353182e+08 | G31: 128820232 | H31: 128820232 | Q31: 0 | R31: =-[1]tb!$AG$247 -> 2.4643446e+08 | S31: 0 | T31: 0 | U31: 0 | V31: 0 | X31: 0 | Y31: 0 | Z31: 0 | AA31: 0 | AB31: 0 | AC31: 0 | AD31: 0 | AE31: 0 | AF31: 0 | AG31: 0 | AH31: 0 | AI31: 0 | AJ31: 0 | AK31: 0 | AL31: 0 | AM31: 0 | AN31: 0 | AO31: 0 | AP31: 0 | AQ31: 181803025 | AR31: 0 | AS31: 0 | AT31: 0 | AU31: 0 | AV31: 0 | AW31: 0 | AX31: 0 | AY31: 0 | AZ31: 0 | BA31: 0 | BB31: 0 | BC31: 1.2333862e+08 | BD31: 162923025 | BE31: 179803025 | BF31: 1.7187951e+08 | BG31: 1.6193181e+08 | BH31: 1.6226426e+08 | BI31: 1.6286405e+08 | BJ31: 1.5496093e+08 | BK31: 1.6076275e+08 | BL31: 1.5582198e+08 | BM31: 1.5669856e+08 | BN31: 1.5713847e+08 | BO31: 1.5252955e+08 | BP31: 150078175 | BQ31: 147578175 | BR31: 147578175 | BS31: 1.480705e+08 | BT31: 1.4794333e+08 | BU31: 1.497057e+08 | BV31: 1.4887041e+08 | BW31: 1.4687095e+08 | BY31: 1.4131487e+08 | BZ31: 1.4150222e+08 | CA31: 1.4131487e+08 | CB31: 1.4131487e+08 | CC31: 136928175 | CD31: 136928175 | CE31: 125428175 | CF31: 125563675 | CG31: 1.2499451e+08 | CH31: 125428175 | CI31: 125428175 | CJ31: 125428175 | CK31: 125428175 | CL31: 125468165 | CM31: 125428175 | CN31: 125428175 | CO31: 125428175 | CP31: 125428175 | CQ31: 113428175
B32: Total Assets | C32: =C26+C22+C19+C14+C13+C12-C53 -> 4.7538325e+08 | D32: =D26+D22+D19+D14+D13+D12 -> 5.07679e+08 | E32: =E10+E13+E14+E19+E22+E26 -> 601249270 | F32: =F10+F13+F14+F19+F22+F26 -> 4.6413652e+08 | G32: =G10+G13+G14+G19+G22+G26 -> 5.3794494e+08 | H32: =H10+H13+H14+H19+H22+H26 -> 5.4137697e+08 | I32: =I10+I13+I14+I19+I22+I26 -> 5.7912035e+08 | J32: =J10+J13+J14+J19+J22+J26 -> 3.2176642e+08 | K32: =K10+K13+K14+K19+K22+K26 -> 5.9435978e+08 | L32: =L10+L13+L14+L19+L22+L26 -> 6.0121432e+08 | ... CS32: =CS10+CS13+CS14+CS19+CS22+CS26 -> 0
A33: 7 | B33: Savings Deposits - Withdrawable deposits - FOSA) | C33: 16847165 | D33: 15401823 | E33: 18011508 | F33: 20656216 | G33: 17777237 | H33: 19926587 | I33: 27383127 | J33: 27383127 | K33: 25101091 | L33: 28751608 | M33: 26984489 | N33: 27507276 | O33: 34473158 | P33: 31556816 | Q33: 45111728 | R33: 48905597 | S33: 36126277 | T33: 34203886 | U33: 33569332 | V33: 43819425 | W33: 35174165 | X33: 37948670 | Y33: 36342998 | Z33: 36221018 | AA33: 40466132 | AB33: 42890344 | AC33: 40596096 | AD33: 51474886 | AE33: 33977753 | AF33: 41618645 | AG33: 41520260 | AH33: 39202512 | AI33: 38912549 | AJ33: 38611538 | AK33: 37183079 | AL33: 43740054 | AM33: 37163676 | AN33: 43030844 | AO33: 43089757 | AP33: 48364100 | AQ33: 48614100 | AR33: 41484423 | AS33: 41152387 | AT33: 42420543 | AU33: 42833833 | AV33: 43567265 | AW33: 38606432 | AX33: 43364745 | AY33: 41551977 | AZ33: 46057619 | BA33: 46057619 | BB33: 49219511 | BC33: 59511516 | BD33: 59788680 | BE33: 41972123 | BF33: 38940664 | BG33: 39653550 | BH33: 35059336 | BI33: 39505387 | BJ33: 38208789 | BK33: 33842063 | BL33: 42319800 | BM33: 41359495 | BN33: 48922568 | BO33: 43202579 | BP33: 47860435 | BQ33: =47070016.5+777427.4+225612 -> 48073056 | BR33: 44748933 | BS33: 46574289 | BT33: 40815256 | BU33: 56929135 | BV33: 56499684 | BW33: 50546955 | BY33: 57786254 | BZ33: 58787360 | CA33: 60620769 | CB33: 53783141 | CC33: 59663422 | CD33: =57986049.75+1286436.15+379636.15 -> 59652122 | CE33: 61809136 | CF33: 66839945 | CG33: 68651395 | CH33: 60208655 | CI33: 69111451 | CJ33: 54546341 | CK33: 54139961 | CL33: 50894442 | CM33: 50219990 | CN33: 52158523 | CO33: 45871120 | CP33: 58609992 | CQ33: 49429332
A34: 8 | B34: Short Term Deposits (e.g Fixed deposits, special savings) | F34: 1460576.8 | G34: 1341781.2 | H34: 1362011.3 | I34: 2171729.8 | J34: 2171729.8 | K34: 2218536.9 | L34: 2289868 | M34: 2520988.1 | N34: -15000 | O34: -15000 | S34: 0 | T34: 0 | U34: 0 | V34: 0 | W34: -15000 | X34: 0 | Y34: 0 | Z34: 0 | AB34: 0 | AC34: 0 | AD34: 0 | AE34: 0 | AF34: 0 | AG34: 0 | AH34: 0 | AI34: 0 | AJ34: 0 | AK34: 0 | AL34: 0 | AM34: 0 | AN34: 0 | AO34: 250000 | AP34: 250000 | AR34: 151000 | AS34: 0 | AT34: 151000 | AU34: 151000 | AV34: 151000 | AW34: 331000 | AX34: 331000 | AY34: 181000 | AZ34: 181000 | BA34: 181000 | BB34: 181000 | BC34: 181000 | BE34: 481000 | BF34: 382000 | BG34: 542000 | BH34: 492000 | BI34: 462000 | BJ34: 456000 | BK34: 683200 | BL34: 871200 | BM34: 832200 | BN34: 1006200 | BO34: 4005678.2 | BP34: 4005678.2 | BQ34: 4035678.2 | BR34: 4005678.2 | BS34: 4005678.2 | BT34: 1201200 | BU34: 1001300 | BV34: 1001300 | BW34: 1600272 | BY34: 2880450 | BZ34: 2870450 | CA34: 2322748.2 | CB34: 2322748.2 | CC34: 2102648.2 | CD34: =2102648.15+11300 -> 2113948.1 | CE34: =1422951+11300+3185793+2141712 -> 6761756 | CF34: 1672951.4 | CG34: 2874292.9 | CH34: 3900000 | CI34: 5140200.6 | CJ34: 5170200.6 | CK34: 5976795.2 | CL34: 12498352 | CM34: 11649727 | CN34: 7931570.4 | CO34: 7973170.4 | CP34: 7764995.6 | CQ34: 7469495.6
A35: 9 | B35: Non withdrawable deposits (BOSA member deposits) | C35: 3.7322967e+08 | D35: 3.8929794e+08 | E35: 415784125 | F35: 4.2352297e+08 | G35: 4.2268456e+08 | H35: 4.2642651e+08 | I35: 4.289255e+08 | J35: 4.289255e+08 | K35: 4.3485987e+08 | L35: 4.3820851e+08 | M35: 4.4016168e+08 | N35: 4.4628222e+08 | O35: 4.4564725e+08 | P35: 4.5197172e+08 | Q35: 4.5448169e+08 | R35: 4.4464562e+08 | S35: 4.6056628e+08 | T35: 4.6735761e+08 | U35: 4.7073249e+08 | V35: 4.7586137e+08 | W35: 4.8474955e+08 | X35: 4.893117e+08 | Y35: 4.9081224e+08 | Z35: 4.9164507e+08 | AA35: 4.8718085e+08 | AB35: 4.9171624e+08 | AC35: 4.9576986e+08 | AD35: 4.9634275e+08 | AE35: 5.027937e+08 | AF35: 5.0762425e+08 | AG35: 5.1087213e+08 | AH35: 5.1590025e+08 | AI35: 5.2143816e+08 | AJ35: 5.2725932e+08 | AK35: 5.2679731e+08 | AL35: 5.2213041e+08 | AM35: 5.2565868e+08 | AN35: 5.3625553e+08 | AO35: 5.40706e+08 | AP35: 5.4880044e+08 | AQ35: 548800441 | AR35: 5.4982232e+08 | AS35: 5.5757936e+08 | AT35: 5.6292242e+08 | AU35: 5.6761539e+08 | AV35: 5.7454559e+08 | AW35: 5.8508916e+08 | AX35: 5.8644593e+08 | AY35: 5.9241989e+08 | AZ35: 5.79735e+08 | BA35: 5.79735e+08 | BB35: 5.9000451e+08 | BC35: 5.9673947e+08 | BD35: 592342053 | BE35: 5.9959149e+08 | BF35: 5.9957934e+08 | BG35: 6.0477158e+08 | BH35: 6.1072066e+08 | BI35: 6.177616e+08 | BJ35: 6.2358725e+08 | BK35: 6.2949253e+08 | BL35: 6.2899733e+08 | BM35: 6.3679566e+08 | BN35: 6.4260625e+08 | BO35: 6.4949111e+08 | BP35: 6.5656202e+08 | BQ35: 6.5656202e+08 | BR35: 6.5788018e+08 | BS35: 6.629484e+08 | BT35: 6.6947452e+08 | BU35: 6.7941792e+08 | BV35: 6.8644596e+08 | BW35: 6.9115963e+08 | BY35: 6.9469359e+08 | BZ35: 6.9706176e+08 | CA35: 6.9977605e+08 | CB35: 7.0657558e+08 | CC35: 7.1349988e+08 | CD35: 7.1349988e+08 | CE35: 756058831 | CF35: 7.6069962e+08 | CG35: 7.6037185e+08 | CH35: 7.6934195e+08 | CI35: 7.7904268e+08 | CJ35: 7.8122735e+08 | CK35: 7.8324855e+08 | CL35: 7.8430685e+08 | CM35: 7.8301662e+08 | CN35: 7.9170544e+08 | CO35: 7.9190649e+08 | CP35: 7.9573398e+08 | CQ35: 8.0202415e+08
B36: Total Deposit liabilities | C36: =SUM(C33:C35) -> 3.9007683e+08 | D36: =SUM(D33:D35) -> 4.0469976e+08 | E36: =SUM(E33:E35) -> 433795633 | F36: =SUM(F33:F35) -> 4.4563976e+08 | G36: =SUM(G33:G35) -> 4.4180358e+08 | H36: =SUM(H33:H35) -> 4.4771511e+08 | I36: =SUM(I33:I35) -> 4.5848036e+08 | J36: =SUM(J33:J35) -> 4.5848036e+08 | ... CS36: =SUM(CS33:CS35) -> 0
A37: 10 | B37: Accounts Payable & Other Liabilities | C37: =C38+C39+C40+C41+C42+C43 -> 5851152.5 | D37: =D38+D39+D40+D41+D42+D43 -> 57286691 | E37: =SUM(E38:E43) -> 82474599 | F37: =SUM(F38:F43) -> 40426054 | G37: =SUM(G38:G43) -> 40426054 | H37: =SUM(H38:H43) -> 38300198 | I37: =SUM(I38:I43) -> 38300198 | J37: =SUM(J38:J43) -> 38300198 | K37: =SUM(K38:K43) -> 38300198 | L37: =SUM(L38:L43) -> 36965198 | ... CS37: =SUM(CS38:CS43) -> 0
A38: 10.1 | B38: Tax Payable | E38: =154735+199232 -> 353967 | R38: 413375.8 | S38: 0 | T38: 0 | U38: 0 | V38: 0 | X38: 0 | Y38: 0 | Z38: 0 | AA38: 0 | AB38: 0 | AC38: 0 | AD38: 0 | AE38: 0 | AF38: 0 | AG38: 0 | AH38: 0 | AI38: 0 | AJ38: 0 | AK38: 0 | AL38: 0 | AM38: 0 | AN38: 0 | AO38: 0 | AP38: 0 | AQ38: 729864 | AR38: 0 | AS38: 0 | AT38: 0 | AU38: 0 | AV38: 0 | AW38: 0 | AX38: 0 | AY38: 0 | AZ38: 0 | BA38: 0 | BB38: 10997 | BC38: 10997 | BD38: 962618 | BE38: 0 | BF38: 0 | BG38: 0 | BH38: 0 | BI38: 0 | BJ38: 0 | BK38: 0 | BL38: 0 | BM38: 0 | BN38: 0 | BO38: 0 | BP38: 32500000 | BQ38: 1459727 | BR38: 0 | BS38: 0 | BT38: 0 | BU38: 0 | BV38: 0 | BW38: 0 | BY38: 0 | BZ38: 984632 | CA38: 0 | CB38: 0 | CC38: 0 | CD38: 1910136 | CE38: 2671948 | CF38: 2671948 | CG38: 2671948 | CH38: 2497948 | CI38: 0 | CJ38: 0 | CK38: 0 | CL38: 0 | CM38: 0 | CN38: 547392 | CO38: 0 | CP38: 0 | CQ38: 1703939.4
A39: 10.2 | B39: Dividends Payable | C39: 5851152.5 | D39: 20234988 | E39: =26342838+2078921 -> 28421759 | S39: 0 | T39: 0 | U39: 0 | V39: 0 | X39: 0 | Y39: 0 | Z39: 0 | AA39: 0 | AB39: 0 | AC39: 0 | AD39: 0 | AE39: 0 | AF39: 0 | AG39: 0 | AH39: 0 | AI39: 0 | AJ39: 0 | AK39: 0 | AL39: 0 | AM39: 0 | AN39: 0 | AO39: 0 | AP39: 0 | AQ39: 31000000 | AR39: 0 | AS39: 0 | AT39: 0 | AU39: 0 | AV39: 0 | AW39: 0 | AX39: 0 | AY39: 0 | AZ39: 0 | BA39: 0 | BB39: 0 | BC39: 0 | BD39: 20740000 | BE39: 0 | BF39: 0 | BG39: 0 | BH39: 0 | BI39: 0 | BJ39: 0 | BK39: 0 | BL39: 0 | BM39: 0 | BN39: 0 | BO39: 0 | BP39: 0 | BQ39: 32500000 | BR39: 0 | BS39: 0 | BT39: 0 | BU39: 0 | BV39: 0 | BW39: 0 | BY39: 0 | BZ39: 0 | CA39: 0 | CB39: 0 | CC39: 0 | CD39: 40000000 | CE39: 48700000 | CF39: 0 | CG39: 0 | CH39: 0 | CI39: 0 | CJ39: 0 | CK39: 0 | CL39: 0 | CM39: 0 | CN39: 0 | CO39: 0 | CP39: 0 | CQ39: 0
A40: 10.3 | B40: Deferred Tax Liability | D40: =50000+5000+106681.95 -> 161681.95 | S40: 0 | T40: 0 | U40: 0 | V40: 0 | X40: 0 | Y40: 0 | Z40: 0 | AA40: 0 | AB40: 0 | AC40: 0 | AD40: 0 | AE40: 0 | AF40: 0 | AG40: 0 | AH40: 0 | AI40: 0 | AJ40: 0 | AK40: 0 | AL40: 0 | AM40: 0 | AN40: 0 | AO40: 0 | AP40: 0 | AR40: 0 | AS40: 0 | AT40: 0 | AU40: 0 | AV40: 0 | AW40: 0 | AX40: 0 | AY40: 0 | AZ40: 0 | BA40: 0 | BB40: 0 | BC40: 0 | BE40: 0 | BF40: 0 | BG40: 0 | BH40: 0 | BI40: 0 | BJ40: 0 | BK40: 0 | BL40: 0 | BM40: 0 | BN40: 0 | BO40: 0 | BP40: 0 | BR40: 0 | BS40: 0 | BT40: 0 | BU40: 0 | BV40: 0 | BW40: 0 | BY40: 0 | BZ40: 0 | CA40: 0 | CB40: 0 | CC40: 0 | CD40: 0 | CF40: 0 | CG40: 0 | CH40: 0 | CI40: 0 | CJ40: 0 | CK40: 0 | CL40: 0 | CM40: 0 | CN40: 0 | CO40: 0 | CP40: 0 | CQ40: 0
A41: 10.4 | B41: Retirement Benefits Liability | S41: 0 | T41: 0 | U41: 0 | V41: 0 | X41: 0 | Y41: 0 | Z41: 0 | AA41: 0 | AB41: 0 | AC41: 0 | AD41: 0 | AE41: 0 | AF41: 0 | AG41: 0 | AH41: 0 | AI41: 0 | AJ41: 0 | AK41: 0 | AL41: 0 | AM41: 0 | AN41: 0 | AO41: 0 | AP41: 0 | AR41: 0 | AS41: 0 | AT41: 0 | AU41: 0 | AV41: 0 | AW41: 0 | AX41: 0 | AY41: 0 | AZ41: 0 | BA41: 0 | BB41: 0 | BC41: 0 | BE41: 0 | BF41: 0 | BG41: 0 | BH41: 0 | BI41: 0 | BJ41: 0 | BK41: 0 | BL41: 0 | BM41: 0 | BN41: 0 | BO41: 0 | BP41: 0 | BR41: 0 | BS41: 0 | BT41: 0 | BU41: 0 | BV41: 0 | BW41: 0 | BY41: 0 | BZ41: 0 | CA41: 0 | CB41: 0 | CC41: 0 | CD41: 0 | CF41: 0 | CG41: 0 | CH41: 0 | CI41: 0 | CJ41: 0 | CK41: 0 | CL41: 0 | CM41: 0 | CN41: 0 | CO41: 0 | CP41: 0 | CQ41: 0
A42: 10.5 | B42: Other Liabilities | D42: 9893489.9 | E42: =-44908+120928+17920+36519+400+190220+550017+663040+11738702 -> 13272838 | R42: 30277534 | S42: 0 | T42: 0 | U42: 0 | V42: 0 | W42: 24682064 | X42: 0 | Y42: 0 | Z42: 0 | AB42: 0 | AC42: 0 | AD42: 0 | AE42: 0 | AF42: 0 | AG42: 0 | AH42: 0 | AI42: 0 | AJ42: 0 | AK42: 0 | AL42: 0 | AM42: 0 | AN42: 0 | AO42: 0 | AP42: 0 | AQ42: 949074 | AR42: 0 | AS42: 0 | AT42: 0 | AU42: 0 | AV42: 0 | AW42: 0 | AX42: 0 | AY42: 0 | AZ42: 0 | BA42: 0 | BB42: 0 | BC42: 0 | BD42: 801000 | BE42: 0 | BF42: 0 | BG42: 0 | BH42: 0 | BI42: 0 | BJ42: 0 | BK42: 0 | BL42: 0 | BM42: 0 | BN42: 0 | BO42: 0 | BP42: 0 | BQ42: =2002520.2+1000000 -> 3002520.2 | BR42: 0 | BS42: 0 | BT42: 0 | BU42: 0 | BV42: 0 | BW42: 0 | BY42: 0 | BZ42: 0 | CB42: 0 | CC42: 4756198.7 | CD42: =3374770.05+1300000 -> 4674770 | CE42: 2862127 | CF42: 0 | CG42: 0 | CH42: 2678740 | CI42: 0 | CJ42: 0 | CK42: 0 | CL42: 0 | CM42: 0 | CN42: 752536 | CO42: 3199986 | CP42: 3950793 | CQ42: 58773709
A43: 10.6 | B43: External Borrowings | D43: =12020122.1+14976409 -> 26996531 | E43: 40426035 | F43: 40426054 | G43: 40426054 | H43: 38300198 | I43: 38300198 | J43: 38300198 | K43: 38300198 | L43: 36965198 | M43: 36965198 | N43: 1.2688953e+08 | O43: 1.2555453e+08 | P43: 1.1919507e+08 | Q43: 1.0847283e+08 | R43: 1.153782e+08 | S43: 1.0847283e+08 | T43: 1.0428943e+08 | U43: 1.0066002e+08 | V43: 1.005839e+08 | W43: 121943271 | X43: 1.1816201e+08 | Y43: 1.1359408e+08 | Z43: 1.0790484e+08 | AA43: 1.0183942e+08 | AB43: 96246358 | AC43: 91158395 | AD43: 92300663 | AE43: 87539876 | AF43: 92833800 | AG43: 92833800 | AH43: 87394860 | AI43: 1.2230693e+08 | AJ43: 1.2011537e+08 | AK43: 1.1809437e+08 | AL43: 1.1718397e+08 | AM43: 1.1328937e+08 | AN43: 1.1151629e+08 | AO43: 1.2008333e+08 | AP43: 123249999 | AQ43: 123249999 | AR43: 123249999 | AS43: 1.2037824e+08 | AT43: 115999999 | AU43: 1.1236913e+08 | AV43: 1.0932559e+08 | AW43: 109639140 | AX43: 1.3183333e+08 | AY43: 1.2375e+08 | AZ43: 1.185e+08 | BA43: 1.185e+08 | BB43: 1.08e+08 | BC43: 172750000 | BD43: 1.7275e+08 | BE43: 166753350 | BF43: 1.6034925e+08 | BG43: 1.4822186e+08 | BH43: 1.4333333e+08 | BI43: 1.4333333e+08 | BJ43: 1.4333333e+08 | BK43: 142750000 | BL43: 1.3558333e+08 | BM43: 1.3558333e+08 | BN43: 1.2841667e+08 | BO43: 1.2483333e+08 | BP43: 1.5625e+08 | BQ43: 1.5625e+08 | BR43: 1.5208333e+08 | BS43: 1.5208333e+08 | BT43: 1.4791667e+08 | BU43: 1.4025e+08 | BV43: 1.8115532e+08 | BW43: 1.7926667e+08 | BY43: 1.7521667e+08 | BZ43: 1.7091667e+08 | CA43: 1.6958333e+08 | CB43: 1.6531622e+08 | CC43: 1.5925e+08 | CD43: 1.5925e+08 | CE43: 157249999 | CF43: 1.5725e+08 | CG43: 1.5023933e+08 | CH43: 218200000 | CI43: 2.1543e+08 | CJ43: 2.0971253e+08 | CK43: 2.0542633e+08 | CL43: 2.014503e+08 | CM43: 1.9747015e+08 | CN43: 1.943604e+08 | CO43: 1.922003e+08 | CP43: 1.89278e+08 | CQ43: 1.85778e+08
B44: Total Liabilities | C44: =C37+C36 -> 3.9592799e+08 | D44: =D36+D37 -> 4.6198645e+08 | E44: =E36+E37 -> 516270232 | F44: =F36+F37 -> 4.8606582e+08 | G44: =G36+G37 -> 4.8222964e+08 | H44: =H36+H37 -> 4.8601531e+08 | I44: =I36+I37 -> 4.9678056e+08 | J44: =J36+J37 -> 4.9678056e+08 | K44: =K36+K37 -> 5.004797e+08 | ... CS44: =CS36+CS37 -> 0
A45: 11 | B45: Share Capital (Members share capital per Bylaws) | C45: 5118000 | D45: 30772490 | E45: =31910489+31730 -> 31942219 | F45: 34811389 | G45: 34811389 | H45: 34811389 | I45: 34811389 | J45: 34811389 | K45: 35528603 | L45: 35528603 | M45: 35528603 | N45: 32874923 | O45: 32969011 | P45: 33085810 | Q45: 33215877 | R45: 33215877 | S45: 33459943 | T45: 33675110 | U45: 33832810 | V45: 33820810 | W45: 79399826 | X45: 79401866 | Y45: 80886446 | Z45: 80897436 | AA45: 80977976 | AB45: 81048702 | AC45: 81132585 | AD45: 81133736 | AE45: 81277076 | AF45: 81344608 | AG45: 81422555 | AH45: 81568628 | AI45: 81600064 | AJ45: 81616224 | AK45: 81648224 | AL45: 81677769 | AM45: 81643483 | AN45: 81665903 | AO45: 81689196 | AP45: 81732677 | AQ45: 81732676 | AR45: 81727592 | AS45: 81701572 | AT45: 81697126 | AU45: 81731166 | AV45: 81630846 | AW45: 81712416 | AX45: 81734976 | AY45: 81756066 | AZ45: 88703998 | BA45: 88703998 | BB45: 91068114 | BC45: 91363015 | BD45: 91363015 | BE45: 91780623 | BF45: 92019927 | BG45: 92254246 | BH45: 92486024 | BI45: 92711663 | BJ45: 92844320 | BK45: 92287164 | BL45: 92465690 | BM45: 92604774 | BN45: 92724110 | BO45: 92886414 | BP45: 93050795 | BQ45: 93070825 | BR45: 93070825 | BS45: 95804514 | BT45: 93751469 | BU45: 93240389 | BV45: 93225117 | BW45: 93226617 | BY45: 93187147 | BZ45: 93180877 | CA45: 93181732 | CB45: 93132732 | CC45: 93132732 | CD45: 93132732 | CE45: 96195922 | CF45: 96473287 | CG45: 96600690 | CH45: 96861669 | CI45: 97145701 | CJ45: 97415665 | CK45: 97833741 | CL45: 97862717 | CM45: 98067817 | CN45: 98308803 | CO45: 98526064 | CP45: 98648139 | CQ45: 98863322
A46: 12 | B46: Capital Grants | Q46: 0 | S46: 0 | T46: 0 | U46: 0 | V46: 0 | X46: 0 | Y46: 0 | Z46: 0 | AA46: 0 | AB46: 0 | AC46: 0 | AD46: 0 | AE46: 0 | AF46: 0 | AG46: 0 | AH46: 0 | AI46: 0 | AJ46: 0 | AK46: 0 | AL46: 0 | AM46: 0 | AN46: 0 | AO46: 0 | AP46: 0 | AR46: 0 | AS46: 0 | AT46: 0 | AU46: 0 | AX46: 0 | AY46: 0 | AZ46: 0 | BA46: 0 | BB46: 0 | BC46: 0 | BD46: 0 | BE46: 0 | BF46: 0 | BG46: 0 | BH46: 0 | BI46: 0 | BJ46: 0 | BK46: 0 | BL46: 0 | BM46: 0 | BN46: 0 | BO46: 0 | BP46: 0 | BR46: 0 | BS46: 0 | BT46: 0 | BU46: 0 | BV46: 0 | BW46: 0 | BY46: 0 | BZ46: 0 | CA46: 0 | CB46: 0 | CC46: 0 | CF46: 0 | CG46: 0 | CH46: 0 | CI46: 0 | CJ46: 0 | CK46: 0 | CL46: 0 | CM46: 0 | CN46: 0 | CO46: 0 | CP46: 0 | CQ46: 0
A47: 13 | B47: Retained Earnings | C47: =C48+C49 -> 0 | D47: =D48+D49 -> 28882818 | E47: =E49+E48 -> 37860904 | F47: =F49+F48 -> 83273.8 | G47: =G49+G48 -> -390773.93 | H47: =H49+H48 -> -1112049.8 | I47: =I49+I48 -> 22673145 | J47: =J49+J48 -> 0 | K47: =K49+K48 -> 32556188 | L47: =L49+L48 -> 33228737 | ... CS47: =CS49+CS48 -> 0
A48: 13.1 | B48: Prior Years' Retained Earnings | D48: 15899403 | E48: 36232623 | I48: 37860903 | K48: 37860903 | L48: 37860903 | M48: 37860903 | N48: 37860903 | O48: 37860903 | P48: 37860903 | Q48: 37860903 | R48: 41222483 | S48: 35665805 | T48: 43591339 | U48: 43591339 | V48: 37860903 | W48: 43591339 | X48: 43591339 | Y48: 43591339 | Z48: 43591339 | AA48: 43591339 | AB48: 43591339 | AC48: 43591339 | AD48: 43591339 | AE48: 43591339 | AF48: 43591339 | AG48: 43984320 | AH48: 43984320 | AI48: 43984320 | AJ48: 43984320 | AK48: 43984320 | AL48: 43984320 | AM48: 43984320 | AN48: 43984320 | AO48: 43984320 | AP48: 43984320 | AQ48: 43984320 | AR48: 49184320 | AS48: 43984320 | AT48: 49558898 | AU48: 49558898 | AV48: 49558898 | AW48: 49558898 | AX48: 49558898 | AY48: 49558898 | AZ48: 49558898 | BA48: 49558898 | BB48: 49558898 | BC48: 49558898 | BD48: 49558898 | BE48: 58488619 | BF48: 58488619 | BG48: 57208619 | BH48: 57208619 | BI48: 57208619 | BJ48: 57208619 | BK48: 57208619 | BL48: 57208619 | BM48: 57208619 | BN48: 57208619 | BO48: 57208619 | BP48: 57208619 | BQ48: 57208619 | BR48: 64912351 | BS48: 64912351 | BT48: 64912351 | BU48: 64912351 | BV48: 64912351 | BW48: 64912351 | BY48: 64912351 | BZ48: 64912351 | CA48: 64912351 | CB48: 64912351 | CC48: 64912351 | CD48: 64912351 | CE48: 75303797 | CF48: 87861276 | CG48: 87861276 | CH48: 87861276 | CI48: 87861276 | CJ48: 87861276 | CK48: 87861276 | CL48: 87861276 | CM48: 87861276 | CN48: 87861276 | CO48: 87861276 | CP48: 87861276 | CQ48: 87861276
A49: 13.2 | B49: Current Year's Surplus | D49: =16229269.08-3245853.82 -> 12983415 | E49: =4634002-926800-2078921 -> 1628281 | F49: 83273.8 | G49: -390773.93 | H49: -1112049.8 | I49: -15187758 | K49: -5304714.5 | L49: -4632165.9 | M49: -4956824.1 | N49: -1375713.5 | O49: -1795753.2 | P49: 2108067.5 | Q49: 2005799.8 | R49: 2368855.9 | S49: -1848072.1 | T49: 234815.3 | U49: 1735386 | V49: 2052936.9 | W49: 1715461 | X49: -1187999.6 | Y49: 1039146.9 | Z49: 5247182.2 | AA49: 7891345.3 | AB49: 5543757.2 | AC49: 3976430.7 | AD49: 6958582.5 | AE49: 413771.4 | AF49: 1786553.1 | AG49: 1571296.8 | AH49: 1139278.3 | AI49: 1422959 | AJ49: 3694109.8 | AK49: 2657876.5 | AL49: 4869593.5 | AM49: 4399964.5 | AN49: 6643730.4 | AO49: 8558881.8 | AP49: 12657410 | AQ49: 494578 | AR49: 2494467.9 | AS49: 6608816.8 | AT49: 4017014.7 | AU49: 7432088.7 | AV49: 7795823.6 | AW49: 6966289.4 | AX49: 9218492.5 | AY49: 8450339.8 | AZ49: 9243125.5 | BA49: 9243125.5 | BB49: 12802704 | BC49: 5503971 | BD49: 7649720.8 | BE49: 0 | BF49: 10403172 | BG49: 8141009.1 | BH49: 6702756.6 | BI49: 7229005.5 | BJ49: 12758466 | BK49: 9639842.2 | BL49: 12601432 | BM49: 18773343 | BN49: 19311273 | BO49: 20387722 | BP49: 13766160 | BQ49: 7703731.4 | BR49: 5301186.8 | BS49: 7884906.3 | BT49: 10230174 | BU49: 9919119.3 | BV49: 10572971 | BW49: 11232422 | BY49: 17171020 | BZ49: 24453004 | CA49: 28859289 | CB49: 31542526 | CC49: 10829515 | CD49: 8647446.6 | CE49: 12557478 | CF49: 6401449.2 | CG49: 13037530 | CH49: 12222952 | CI49: 9656096.5 | CJ49: 10076166 | CK49: 12040593 | CL49: 14795901 | CM49: 15989365 | CN49: 16040881 | CO49: 27866282 | CP49: 39527337 | CQ49: 13732233
A50: 14 | B50: Other Equity Accounts | C50: =C51+C52+C53+C54+C55 -> 7313333.3 | D50: =D51+D52+D53+D54+D55 -> 10559187 | E50: =SUM(E51:E55) -> 15175915 | F50: =SUM(F51:F55) -> 20969294 | G50: =SUM(G51:G55) -> 21294694 | H50: =SUM(H51:H55) -> 21662324 | I50: =SUM(I51:I55) -> 24855254 | J50: =SUM(J51:J55) -> 24855254 | K50: =SUM(K51:K55) -> 25795296 | L50: =SUM(L51:L55) -> 26241800 | ... CS50: =SUM(CS51:CS55) -> 0
B51: Statutory Reserve | C51: 3504457.3 | D51: 6750311.1 | E51: 11367039 | F51: 8587761.9 | G51: 8587761.9 | H51: 8587761.9 | I51: 11367039 | J51: 11367039 | K51: 11367039 | L51: 11367039 | M51: 11367039 | N51: 11367039 | O51: 11367039 | P51: 11367039 | Q51: 11367039 | R51: 12799648 | S51: 11367039 | T51: 12799648 | U51: 11367039 | V51: 11367039 | W51: 12799648 | X51: 12799648 | Y51: 12799648 | Z51: 12799648 | AA51: 12799648 | AB51: 12799648 | AC51: 12799648 | AD51: 12799648 | AE51: 12799648 | AF51: 12799648 | AG51: 12897894 | AH51: 12897894 | AI51: 12897894 | AJ51: 12897894 | AK51: 12897894 | AL51: 12897894 | AM51: 12897894 | AN51: 12897894 | AO51: 12897894 | AP51: 12897894 | AQ51: 14171538 | AR51: 12897894 | AS51: 12897894 | AT51: 14291539 | AU51: 14291539 | AV51: 14291539 | AW51: 14291539 | AX51: 14291539 | AY51: 14291539 | AZ51: 14291539 | BA51: 14291539 | BB51: 14291539 | BC51: 14291539 | BD51: 16203969 | BE51: 16523969 | BF51: 16523969 | BG51: 16203969 | BH51: 16203969 | BI51: 16203969 | BJ51: 16203969 | BK51: 16203969 | BL51: 16203969 | BM51: 16203969 | BN51: 16203969 | BO51: 16203969 | BP51: 18515873 | BQ51: 18379902 | BR51: 18379902 | BS51: 18379902 | BT51: 18379902 | BU51: 18379902 | BV51: 18379902 | BW51: 18379902 | BY51: 18379902 | BZ51: 18379902 | CA51: 18379902 | CB51: 18379902 | CC51: 20868763 | CD51: 20866763 | CE51: 24867132 | CF51: 24867133 | CG51: 24867133 | CH51: 24867133 | CI51: 24867133 | CJ51: 24867133 | CK51: 24867133 | CL51: 24867133 | CM51: 24867133 | CN51: 24867133 | CO51: 24867133 | CP51: 24867133 | CQ51: 24867133
B52: Other Reserves (provide notes on these reserves) | C52: 3808876 | D52: 3808876 | E52: 3808876 | F52: 12381532 | G52: 12706932 | H52: 13074562 | I52: 13488215 | J52: 13488215 | K52: 14428257 | L52: 14874761 | M52: 15401383 | N52: 19933055 | O52: 19949569 | P52: 20537920 | Q52: 20802420 | R52: 3808876 | S52: 21408542 | T52: 21978930 | U52: 22058066 | V52: 19872763 | W52: 24224061 | X52: 24608982 | Y52: 24983592 | Z52: 25279179 | AA52: 25552239 | AB52: 25978179 | AC52: 26257609 | AD52: 22488233 | AE52: 26918648 | AF52: 27255078 | AG52: 27608474 | AH52: 24153595 | AI52: 24707456 | AJ52: 25047017 | AK52: 24999090 | AL52: 25001490 | AM52: 25523958 | AN52: 26512368 | AO52: 2559725 | AP52: 3672500 | AQ52: 9775722 | AR52: 6144435 | AS52: 6700691 | AT52: 6785552 | AU52: 7243434 | AV52: 13480371 | AW52: 4467909.7 | AX52: 5675769.7 | AY52: 6024289.7 | AZ52: 6623309.7 | BA52: 6623309.7 | BB52: 7728255.7 | BC52: 8346634.7 | BD52: =3808876+8346634.7 -> 12155511 | BE52: 9018424.7 | BF52: 13418312 | BG52: 4757033.2 | BH52: 4757033.2 | BI52: 4803801.1 | BJ52: 55192.1 | BK52: 615342.1 | BL52: 1132562.1 | BM52: 5433628.1 | BN52: 2269502.1 | BO52: 2725654.9 | BP52: 6603936.6 | BQ52: =3808876+2795060.6 -> 6603936.6 | BR52: 6603936.6 | BS52: 3650561.1 | BT52: 3842639.4 | BU52: 8247165.3 | BV52: 4261349 | BW52: 4829885.7 | BY52: 5642149.7 | BZ52: 9942076.6 | CA52: 3257305.6 | CB52: 3938395.6 | CC52: 6596606.5 | CD52: =2787430.45+3808879 -> 6596309.5 | CE52: 3808876 | CF52: 6565067.6 | CG52: 6578467.6 | CH52: 7703569.6 | CI52: 8232538.6 | CJ52: 8871030 | CK52: 9653999 | CL52: 10112768 | CM52: 14383944 | CN52: 14543070 | CO52: 15185300 | CP52: 15396335 | CQ52: 16032365
B53: Revaluation Reserves (Not part of core capital) | S53: 0 | T53: 0 | U53: 0 | V53: 0 | X53: 0 | Y53: 0 | Z53: 0 | AA53: 0 | AB53: 0 | AC53: 0 | AD53: 0 | AE53: 0 | AF53: 0 | AG53: 0 | AH53: 0 | AI53: 0 | AJ53: 0 | AK53: 0 | AL53: 0 | AM53: 0 | AN53: 0 | AO53: 0 | AP53: 0 | AR53: 0 | AS53: 0 | AT53: 0 | AU53: 0 | AV53: 0 | AW53: 0 | AX53: 0 | AY53: 0 | AZ53: 0 | BA53: 0 | BB53: 0 | BC53: 0 | BE53: 0 | BF53: 0 | BG53: 0 | BH53: 0 | BI53: 0 | BJ53: 0 | BK53: 0 | BL53: 0 | BM53: 0 | BN53: 0 | BO53: 0 | BP53: 0 | BR53: 0 | BS53: 0 | BT53: 0 | BU53: 0 | BV53: 0 | BW53: 0 | BY53: 0 | BZ53: 0 | CA53: 0 | CB53: 0 | CC53: 0 | CD53: 0 | CE53: 6177236 | CF53: 0 | CG53: 0 | CH53: 0 | CI53: 0 | CJ53: 0 | CK53: 0 | CL53: 0 | CM53: 0 | CN53: 0 | CO53: 0 | CP53: 0 | CQ53: 0
B54: Proposed Dividends | R54: 2078921 | S54: 0 | T54: 0 | U54: 0 | V54: 0 | X54: 0 | Y54: 0 | Z54: 0 | AA54: 0 | AB54: 0 | AC54: 0 | AD54: 0 | AE54: 0 | AF54: 0 | AG54: 0 | AH54: 0 | AI54: 0 | AJ54: 0 | AK54: 0 | AL54: 0 | AM54: 0 | AN54: 0 | AO54: 0 | AP54: 0 | AQ54: 3300000 | AR54: 0 | AS54: 0 | AT54: 0 | AU54: 0 | AV54: 0 | AW54: 0 | AX54: 0 | AY54: 0 | AZ54: 0 | BA54: 0 | BB54: 0 | BC54: 0 | BE54: 0 | BF54: 0 | BG54: 0 | BH54: 0 | BI54: 0 | BJ54: 0 | BK54: 0 | BL54: 0 | BM54: 0 | BN54: 0 | BO54: 0 | BP54: 0 | BR54: 0 | BS54: 0 | BT54: 0 | BU54: 0 | BV54: 0 | BW54: 0 | BY54: 0 | BZ54: 0 | CA54: 0 | CB54: 0 | CC54: 0 | CD54: 0 | CF54: 0 | CG54: 0 | CH54: 0 | CI54: 0 | CJ54: 0 | CK54: 0 | CL54: 0 | CM54: 0 | CN54: 0 | CO54: 0 | CP54: 0 | CQ54: 0
B55: Adjustment to Equity | S55: 0 | T55: 0 | U55: 0 | V55: 0 | X55: 0 | Y55: 0 | Z55: 0 | AA55: 0 | AB55: 0 | AC55: 0 | AD55: 0 | AE55: 0 | AF55: 0 | AG55: 0 | AH55: 0 | AI55: 0 | AJ55: 0 | AK55: 0 | AL55: 0 | AM55: 0 | AN55: 0 | AO55: 0 | AP55: 0 | AR55: 0 | AS55: 0 | AT55: 0 | AU55: 0 | AV55: 0 | AW55: 0 | AX55: 0 | AY55: 0 | AZ55: 0 | BA55: 0 | BB55: 0 | BC55: 0 | BD55: 0 | BE55: 0 | BF55: 0 | BG55: 0 | BH55: 0 | BI55: 0 | BJ55: 0 | BK55: 0 | BL55: 0 | BM55: 0 | BN55: 0 | BO55: 0 | BP55: 0 | BR55: 0 | BS55: 0 | BT55: 0 | BU55: 0 | BV55: 0 | BW55: 0 | BY55: 0 | BZ55: 0 | CA55: 0 | CB55: 0 | CC55: 0 | CD55: 0 | CF55: 0 | CG55: 0 | CH55: 0 | CI55: 0 | CJ55: 0 | CK55: 0 | CL55: 0 | CM55: 0 | CN55: 0 | CO55: 0 | CP55: 0 | CQ55: 3883058.2
B56: Total Equity | C56: =C45+C46+C48+C49+C51+C52+C53+C54+C55 -> 12431333 | D56: =D45+D46+D47+D50 -> 70214495 | E56: =E45+E46+E47+E50 -> 84979038 | F56: =F45+F46+F47+F50 -> 55863957 | G56: =G45+G46+G47+G50 -> 55715309 | H56: =H45+H46+H47+H50 -> 55361663 | I56: =I45+I46+I47+I50 -> 82339788 | J56: =J45+J46+J47+J50 -> 59666643 | K56: =K45+K46+K47+K50 -> 93880087 | ... CS56: =CS45+CS46+CS47+CS50 -> 0
B57: Total Liabilities and Equity | C57: =C44+C56 -> 4.0835932e+08 | D57: =D44+D56 -> 5.3220095e+08 | E57: =E44+E56 -> 601249270 | F57: =F44+F56 -> 5.4192978e+08 | G57: =G44+G56 -> 5.3794494e+08 | H57: =H44+H56 -> 5.4137697e+08 | I57: =I44+I56 -> 5.7912035e+08 | J57: =J44+J56 -> 5.564472e+08 | ... CS57: =CS44+CS56 -> 0
B58: Note: This return should be received within 15 days after end of the month. | C58: =C57-C32 -> -67023936 | D58: =D57-D32 -> 24521943 | E58: =E57-E32 -> 0 | F58: =F57-F32 -> 77793255 | G58: =G57-G32 -> 0.019999981 | H58: =H57-H32 -> 0 | I58: =I57-I32 -> 0 | J58: =J57-J32 -> 2.3468078e+08 | ... Z58: =Z57-Z32 -> 0
BD59: =BD57-BD32 -> 0.45000005 | CB59: =CB57-CB32 -> 14606836
B60: AUTHORIZATION:
B61: We declare that this return, to the best of our knowledge and belief is correct.
B62: …………………………………………………..sign……………………………..date…………………….. | AK62: =AL57-AL32 -> 0
B63: name of authorizing officer
B64: …………………………………………………..sign……………………………..date……………………..
B65: name of countersigning officer
BX100: / | BY100: //

Sheet SCI
A1: FORM 7 SASRA/007
A2: STATEMENT OF COMPREHENSIVE INCOME
A3: NAME OF SACCO SOCIETY: ECO-PILLAR | O3: =(R10-E10)/E10 -> 0.22539948
A4: FINANCIAL YEAR | AZ4: =31928/3 -> 10642.667
A5: START DATE:
A6: END DATE:
A8: Ref No. | C8: AUDITED 2012 | D8: AUDITED 2013 | E8: Audited 2014 | F8: 42005 | G8: 42036 | H8: 42064 | I8: 42095 | J8: 42125 | K8: 42156 | L8: 42186 | M8: 42217 | N8: 42248 | O8: 42278 | P8: 42309 | Q8: 42339 | R8: Audit 2015 | S8: 42385 | T8: 42416 | U8: 42445 | V8: 42476 | W8: 42506 | X8: 42537 | Y8: 42567 | Z8: 42598 | AA8: 42629 | AB8: 42659 | AC8: 42690 | AD8: 42720 | AE8: 42736 | AF8: 42767 | AG8: 42795 | AH8: 42826 | AI8: 42856 | AJ8: 42887 | AK8: 42917 | AL8: 42948 | AM8: 42979 | AN8: 43009 | AO8: 43040 | AP8: 43070 | AQ8: Audited 2017 | AR8: 43101 | AS8: 43132 | AT8: 43160 | AU8: 43191 | AV8: 43221 | AW8: 43252 | AX8: 43282 | AY8: 43313 | AZ8: 43344 | BA8: 43374 | BB8: 43405 | BC8: 43435 | BD8: Aud-18 | BE8: 43466 | BF8: 43497 | BG8: 43525 | BH8: 43556 | BI8: 43586 | BJ8: 43617 | BK8: 43647 | BL8: 43678 | BM8: 43709 | BN8: 43739 | BO8: 43770 | BP8: 43800 | BQ8: Audited -19 | BR8: 43831 | BS8: 43862 | BT8: 43891 | BU8: 43922 | BV8: 43952 | BW8: 43983 | BX8: 44013 | BY8: 44044 | BZ8: 44075 | CA8: 44105 | CB8: 44136 | CC8: 44166 | CD8: Audited 2020 | CE8: Audited 2021 | CF8: 44562 | CG8: 44593 | CH8: 44621 | CI8: 44652 | CJ8: 44682 | CK8: 44713 | CL8: 44743 | CM8: 44774 | CN8: 44805 | CO8: 44835 | CP8: 44866 | CQ8: 44896 | CR8: Dec 2022 Audited
A10: 1 | B10: Financial Income | C10: =C11+C14 -> 45324711 | D10: =D11+D14 -> 45274899 | E10: =E11+E14 -> 67694492 | F10: =F11+F14 -> 6107686.8 | G10: =G11+G14 -> 10515264 | H10: =H11+H14 -> 14520010 | I10: =I11+I14 -> 19445843 | J10: =J11+J14 -> 28051245 | ... CR10: =CR11+CR14 -> 0
A11: 2 | B11: Financial Income from Loans Portfolio | C11: =C12+C13 -> 44986975 | D11: =D12+D13 -> 44247378 | E11: =SUM(E12:E13) -> 66366282 | F11: =SUM(F12:F13) -> 5788629.3 | G11: =SUM(G12:G13) -> 9889522.2 | H11: =SUM(H12:H13) -> 13574744 | I11: =SUM(I12:I13) -> 18194118 | J11: =SUM(J12:J13) -> 25996301 | K11: =SUM(K12:K13) -> 31493424 | L11: =SUM(L12:L13) -> 36232691 | ... CR11: =SUM(CR12:CR13) -> 0
A12: 2.1 | B12: Interest on Loan Portfolio | C12: 44346813 | D12: 43848893 | E12: =32739537+32356032 -> 65095569 | F12: 5293412.2 | G12: 8814618.7 | H12: 11941258 | I12: 15976794 | J12: 22773179 | K12: 27786423 | L12: 31965435 | M12: 34301413 | N12: 45441103 | O12: 49657572 | P12: 58085052 | Q12: 68498850 | R12: 80105335 | S12: 6240484.5 | T12: 9191283.5 | U12: 19865408 | V12: 26331597 | W12: 32790874 | X12: 36012061 | Y12: 42911257 | Z12: 44403802 | AA12: 51348502 | AB12: 56432183 | AC12: 59911894 | AD12: 68603616 | AE12: 8340896.4 | AF12: 11346978 | AG12: 16772741 | AH12: 22533644 | AI12: 29220521 | AJ12: 39968899 | AK12: 44231306 | AL12: 50819365 | AM12: 59581625 | AN12: 69449227 | AO12: 75848224 | AP12: 82516332 | AQ12: 82516332 | AR12: 8805333.2 | AS12: 17804492 | AT12: 23367416 | AU12: 31714268 | AV12: 40040279 | AW12: 49076826 | AX12: 55700743 | AY12: 62869798 | AZ12: 69961556 | BA12: 69961556 | BB12: 87604925 | BC12: 98040908 | BD12: 98521727 | BE12: 9463908 | BF12: 20608412 | BG12: 27884516 | BH12: 34642879 | BI12: 39516341 | BJ12: 52060033 | BK12: 58249943 | BL12: 69491514 | BM12: 81181260 | BN12: 86756322 | BO12: 94053168 | BP12: 1.1263499e+08 | BQ12: 1.1263499e+08 | BR12: 14539248 | BS12: 23327466 | BT12: 33316997 | BU12: 35778819 | BV12: 45263111 | BW12: 53090883 | BY12: 71863730 | BZ12: 81505966 | CA12: 93911601 | CB12: 1.0396758e+08 | CC12: 1.157573e+08 | CD12: 1.157573e+08 | CE12: 123851259 | CF12: 15038865 | CG12: 28143854 | CH12: 33929528 | CI12: 40082943 | CJ12: 48970279 | CK12: 55839194 | CL12: 65226230 | CM12: 72870868 | CN12: 81562087 | CO12: 98526541 | CP12: 1.2773453e+08 | CQ12: 1.3642388e+08
A13: 2.2 | B13: Fees & Commission on Loan Portfolio | C13: 640162.06 | D13: 398485.5 | E13: 1270713 | F13: 495217.05 | G13: 1074903.5 | H13: 1633485.9 | I13: 2217323.9 | J13: 3223122.1 | K13: 3707001.4 | L13: 4267256.1 | M13: 5304368.1 | N13: 2868188 | O13: 3041503.6 | P13: 3332466.5 | Q13: 3926584.1 | R13: 2451398.7 | S13: 391158 | T13: 575348 | U13: 755467.9 | V13: 3980742.3 | W13: 4961777.1 | X13: 5474023.7 | Y13: 5997308.3 | Z13: 6706225.2 | AA13: 7285245.7 | AB13: 7866097.2 | AC13: 8354035.2 | AD13: 8769113.2 | AE13: 628376 | AF13: 723569.5 | AG13: 2380936.9 | AH13: 4130600.2 | AI13: 4918751.9 | AJ13: 5588518.4 | AK13: 5692394.8 | AL13: 6673249.6 | AM13: 7627231.6 | AN13: 7934004.1 | AO13: 8613850 | AP13: 11458304 | AQ13: 11517170 | AR13: 545627.5 | AS13: 1044731.3 | AT13: 2548667.5 | AU13: 3939722.2 | AV13: 4907707.4 | AW13: 5523410.8 | AX13: 6044592.2 | AY13: 6918273.8 | AZ13: 7994676.6 | BA13: 7994676.6 | BB13: 9944911.6 | BC13: 9862884.8 | BE13: 3388162.8 | BF13: 2847760.4 | BG13: 3592766.8 | BH13: 4768859.1 | BI13: 5715067.9 | BJ13: 6315782.6 | BK13: 7008611.3 | BL13: 8506045 | BM13: 9212470.3 | BN13: 10188364 | BO13: 11422172 | BP13: 12059443 | BR13: 845976.2 | BS13: 1598571.7 | BT13: 2390109.1 | BU13: 5271418.3 | BV13: 6465918.2 | BW13: 7530483.4 | BY13: 12554228 | BZ13: 14003169 | CA13: 14981978 | CB13: 15993606 | CC13: 17109702 | CF13: 2017645.9 | CG13: 3212177.5 | CH13: 5312494 | CI13: 9997249.9 | CJ13: 12509357 | CK13: 14800532 | CL13: 17174592 | CM13: 18471614 | CN13: 20884364 | CO13: 26053688 | CP13: 24491131 | CQ13: 25619577
A14: 3 | B14: Financial Income from Investments in: | C14: =SUM(C16:C18) -> 337736.05 | D14: =SUM(D16:D18) -> 1027520.1 | E14: =SUM(E15:E18) -> 1328210 | F14: =SUM(F15:F18) -> 319057.5 | G14: =SUM(G15:G18) -> 625742 | H14: =SUM(H15:H18) -> 945266 | I14: =SUM(I15:I18) -> 1251725 | J14: =SUM(J15:J18) -> 2054943.6 | K14: =SUM(K15:K18) -> 2277488.6 | L14: =SUM(L15:L18) -> 2496039.6 | ... CR14: =SUM(CR15:CR18) -> 0
A15: 3.1 | B15: Government Securities | N15: 0 | O15: 0 | P15: 0 | Q15: 0 | S15: 0 | T15: 0 | U15: 0 | W15: 0 | X15: 0 | Y15: 0 | Z15: 0 | AA15: 0 | AB15: 0 | AC15: 0 | AD15: 0 | AE15: 0 | AF15: 0 | AG15: 0 | AH15: 0 | AI15: 0 | AJ15: 0 | AK15: 0 | AL15: 0 | AM15: 0 | AN15: 0 | AO15: 0 | AP15: 0 | AR15: 0 | AS15: 0 | AT15: 0 | AU15: 0 | AV15: 0 | AW15: 0 | AX15: 0 | AY15: 0 | AZ15: 0 | BB15: 0 | BC15: 0 | BE15: 0 | BF15: 0 | BG15: 0 | BH15: 0 | BI15: 0 | BJ15: 0 | BK15: 0 | BL15: 0 | BM15: 0 | BN15: 0 | BO15: 0 | BP15: 0 | BR15: 0 | BS15: 0 | BT15: 0 | BU15: 0 | BV15: 0 | BW15: 0 | BY15: 0 | BZ15: 0 | CA15: 0 | CB15: 0 | CC15: 0 | CF15: 0 | CG15: 0 | CH15: 0 | CI15: 0 | CJ15: 0 | CK15: 0 | CL15: 0 | CM15: 0 | CN15: 0 | CO15: 0 | CP15: 0 | CQ15: 0
A16: 3.2 | B16: Deposit with Banks and Other Financial Inst. | N16: 0 | O16: 0 | P16: 0 | Q16: 0 | S16: 0 | T16: 0 | U16: 0 | W16: 0 | X16: 0 | Y16: 0 | Z16: 0 | AA16: 0 | AB16: 0 | AC16: 0 | AD16: 0 | AE16: 0 | AF16: 0 | AG16: 0 | AH16: 0 | AI16: 0 | AJ16: 0 | AK16: 0 | AL16: 0 | AM16: 0 | AN16: 0 | AO16: 0 | AP16: 0 | AQ16: 1467012 | AR16: 0 | AS16: 0 | AT16: 0 | AU16: 0 | AV16: 0 | AW16: 0 | AX16: 0 | AY16: 0 | AZ16: 0 | BB16: 0 | BC16: 0 | BE16: 0 | BF16: 0 | BG16: 0 | BH16: 0 | BI16: 0 | BJ16: 0 | BK16: 0 | BL16: 0 | BM16: 0 | BN16: 0 | BO16: 0 | BP16: 0 | BR16: 0 | BS16: 0 | BT16: 0 | BU16: 0 | BV16: 0 | BW16: 0 | BY16: 0 | BZ16: 0 | CA16: 0 | CB16: 0 | CC16: 0 | CF16: 0 | CG16: 0 | CH16: 0 | CI16: 0 | CJ16: 0 | CK16: 0 | CL16: 0 | CM16: 0 | CN16: 0 | CO16: 0 | CP16: 0 | CQ16: 0
A17: 3.3 | B17: Other Investments - dividend & Interest incomes from investments | C17: 337736.05 | D17: 1027520.1 | N17: 0 | O17: 0 | P17: 0 | Q17: 0 | S17: 0 | T17: 0 | U17: 0 | V17: 424462 | W17: 424462 | X17: 440244 | Y17: 895808.35 | Z17: 895808.35 | AA17: 895808.35 | AB17: 895808.35 | AC17: 895808.35 | AD17: 895808.35 | AE17: 0 | AF17: 0 | AG17: 0 | AH17: 0 | AI17: 0 | AJ17: 1026160 | AK17: 1467012 | AL17: 1867012 | AM17: 1467012 | AN17: 1467012 | AO17: 1467012 | AP17: 1467012 | AR17: 0 | AS17: 0 | AT17: 0 | AU17: 0 | AV17: 0 | AW17: 896 | AX17: 569886.5 | AY17: 587922.2 | AZ17: 587922.2 | BA17: 587922.2 | BB17: 587922.2 | BC17: 587922.2 | BE17: 0 | BF17: 2443.75 | BG17: 2443.75 | BH17: 0 | BI17: 0 | BJ17: 0 | BK17: 523123.2 | BL17: 523123.2 | BM17: 523123.2 | BN17: 523123.2 | BO17: 523123.2 | BP17: 523123.2 | BR17: 0 | BS17: 0 | BT17: 0 | BU17: 1080094.1 | BV17: 1080094.1 | BW17: 1584430.1 | BY17: 1584430.1 | BZ17: 1584430.1 | CA17: 1584430.1 | CB17: 1584430.1 | CC17: 1584430.1 | CF17: 680734 | CG17: 380734 | CH17: 382566.8 | CI17: 382566.8 | CJ17: 382566.8 | CK17: 1567106.4 | CL17: 1567106.4 | CM17: 1567106.4 | CN17: 1567106.4 | CO17: 3385932.2 | CP17: 3385932.2 | CQ17: 3592164.2
A18: 3.4 | B18: Other Operating Income- Salary processing fees, transaction fees, membership fees | E18: 1328210 | F18: 319057.5 | G18: 625742 | H18: 945266 | I18: 1251725 | J18: 2054943.6 | K18: 2277488.6 | L18: 2496039.6 | M18: 2873568.6 | N18: 5590391.9 | O18: 6122572.9 | P18: 6319675.9 | Q18: 7123546.9 | R18: 396062 | S18: 688684 | T18: 1175683.1 | U18: 1566079.1 | V18: 328800 | W18: 490815 | X18: 639471 | Y18: 1215751 | Z18: 1448701 | AA18: 1524851 | AB18: 1712711 | AC18: 1862561 | AD18: 2622501 | AE18: 826983.36 | AF18: 887325.45 | AG18: 812495 | AH18: 1226105.6 | AI18: 1439799.6 | AJ18: 2436674.6 | AK18: 2452674.6 | AL18: 2725284.6 | AM18: 2576934.6 | AN18: 2587334.6 | AO18: 2692971 | AP18: 3398751 | AQ18: 3398751 | AR18: 141210 | AS18: 700280 | AT18: 474544 | AU18: 651919 | AV18: 1206224 | AW18: 1724286.6 | AX18: 2084924.6 | AY18: 2453562.3 | AZ18: 2574276.3 | BA18: 2574276.3 | BB18: 3168625.9 | BC18: 3576864.9 | BD18: 18017613 | BE18: 370131 | BF18: 671035.65 | BG18: 901180.65 | BH18: 1475080.6 | BI18: 1999306.1 | BJ18: 2619777.3 | BK18: 2275420.9 | BL18: 2536508.7 | BM18: 2884154.1 | BN18: 3076695.7 | BO18: 3381902.4 | BP18: 3667631.4 | BQ18: 17783000 | BR18: 382658.77 | BS18: 663591.77 | BT18: 731881.77 | BU18: 1293236.8 | BV18: 1754791.8 | BW18: 2343091.8 | BY18: 2826595.5 | BZ18: 3873055.5 | CA18: 4381456 | CB18: 4423370.5 | CC18: 4903124.4 | CD18: 23597256 | CE18: 35619130 | CF18: 0 | CG18: 0 | CH18: 0 | CI18: 0 | CJ18: 0 | CK18: 0 | CL18: 0 | CM18: 3201170 | CN18: 3571120 | CO18: 6458005 | CP18: 2888995 | CQ18: 4163956.2
A19: 4 | B19: Financial Expense | C19: =SUM(C20:C25) -> 13012501 | D19: =SUM(D20:D25) -> 9863205.4 | E19: =E20+E21+E22+E23+E24+E25 -> 27897903 | F19: =F20+F21+F22+F23+F24+F25 -> 1335000 | G19: =G20+G21+G22+G23+G24+G25 -> 1335000 | H19: =H20+H21+H22+H23+H24+H25 -> 1335000 | I19: =I20+I21+I22+I23+I24+I25 -> 9913510.1 | J19: =J20+J21+J22+J23+J24+J25 -> 12106280 | K19: =K20+K21+K22+K23+K24+K25 -> 14380796 | L19: =L20+L21+L22+L23+L24+L25 -> 16672298 | ... CR19: =CR20+CR21+CR22+CR23+CR24+CR25 -> 0
A20: 4.2 | B20: Interest Expense on Deposits | C20: 5851152.5 | D20: 6070496.4 | E20: 24947048 | I20: 8578510.1 | J20: 10771280 | K20: 13045796 | L20: 15337298 | M20: 16606467 | N20: 20082700 | O20: 22280900 | P20: 24858444 | Q20: 27268901 | R20: 15562597 | S20: 1655641.9 | T20: 1363126 | U20: 4118909.3 | V20: 5551715.9 | W20: 7069264.2 | X20: 8562954.7 | Y20: 10020750 | Z20: 11471718 | AA20: 12788497 | AB20: 14341727 | AC20: 18178228 | AD20: 17371996 | AE20: 2780236.3 | AF20: 0 | AG20: 0 | AH20: 5394570.3 | AI20: 9342433.8 | AJ20: 11278942 | AK20: 13828429 | AL20: 14967738 | AM20: 16952493 | AN20: 21137406 | AO20: 21312828 | AP20: 23598419 | AQ20: 29700000 | AR20: 2474200.5 | AS20: 5018214.2 | AT20: 7599452.7 | AU20: 10217077 | AV20: 12687882 | AW20: 15797407 | AX20: 18473047 | AY20: 21327116 | AZ20: 23479268 | BA20: 23479268 | BB20: 29205223 | BC20: 36997847 | BD20: 20740000 | BE20: 0 | BF20: 3497546.2 | BG20: 5291751.3 | BH20: 7125074.2 | BI20: 9006856.7 | BJ20: 10912777 | BK20: 12852139 | BL20: 14676604 | BM20: 16715886 | BN20: 18742682 | BO20: 22732189 | BP20: 32500000 | BQ20: 32500000 | BR20: 2739854.4 | BS20: 5524570 | BT20: 8368431.4 | BU20: 11323632 | BV20: 14300957 | BW20: 17278991 | BY20: 23156453 | BZ20: 26139816 | CA20: 31259297 | CB20: 35623186 | CC20: 40000000 | CD20: 40000000 | CE20: 47000000 | CF20: 680734 | CG20: 380734 | CH20: 382566.8 | CI20: 382566.8 | CJ20: 382566.8 | CK20: 1567106.4 | CL20: 1567106.4 | CM20: 31500900 | CN20: 35626745 | CO20: 44495324 | CP20: 51059597 | CQ20: 50400000
A21: 4.3 | B21: Cost of External Borrowings | C21: =2187682+4876654.2 -> 7064336.2 | D21: =3371543+378751 -> 3750294 | E21: 1335000 | F21: 1335000 | G21: 1335000 | H21: 1335000 | I21: 1335000 | J21: 1335000 | K21: 1335000 | L21: 1335000 | M21: 1335000 | N21: 1335000 | O21: 1335000 | P21: 0 | Q21: 1335000 | R21: 13249143 | S21: 1335000 | T21: 0 | U21: 2726252 | V21: 4343744.9 | W21: 6456798.9 | X21: 7748158.6 | Y21: 8979578.6 | Z21: 1335000 | AA21: 1335000 | AB21: 1335000 | AC21: 1335000 | AD21: 1335000 | AE21: 1335000 | AF21: 1335000 | AG21: 2770280 | AH21: 3770280 | AI21: 4272396.4 | AJ21: 5070280 | AK21: 5896536 | AL21: 6932410.4 | AM21: 7570389.6 | AN21: 8930285.4 | AO21: 9589535.7 | AP21: 9589535.7 | AQ21: 9592536 | AR21: 0 | AS21: 1246379 | AT21: 1350000 | AU21: 1350000 | AV21: 3261479 | AW21: 4861479 | AX21: 4861479 | AY21: 5961479 | AZ21: 6451479 | BA21: 6451479 | BB21: 7508389.6 | BC21: 7508389.6 | BD21: 7512889 | BE21: 1925360.2 | BF21: 1925360.4 | BG21: 2240125.7 | BH21: 2865321.2 | BI21: 3400899.5 | BJ21: 5301799.1 | BK21: 5301799.1 | BL21: 7363625.6 | BM21: 7363625.6 | BN21: 9276280.1 | BO21: 9276280.1 | BP21: 10610116 | BQ21: 10610116 | BR21: 1570137 | BS21: 1570137 | BT21: 2201413.3 | BU21: 3201413.3 | BV21: 5664581 | BW21: 6689016.5 | BY21: 8711019.9 | BZ21: 9700575.9 | CA21: 10147494 | CB21: 10147494 | CC21: 11784115 | CD21: 11784115 | CE21: 10402628 | CF21: 1254347 | CG21: 1875459.6 | CH21: 2141451 | CI21: 3141451 | CJ21: 3846930.5 | CK21: 5298862.5 | CL21: 6529555.3 | CM21: 7329455.3 | CN21: 8539260.5 | CO21: 9739260.5 | CP21: 10846900 | CQ21: 14501682
A22: 4.4 | B22: Dividend Expenses (on member shares) | Q22: 0 | S22: 0 | T22: 0 | U22: 0 | V22: 0 | X22: 0 | Y22: 0 | Z22: 0 | AA22: 0 | AB22: 0 | AC22: 0 | AD22: 0 | AE22: 0 | AF22: 0 | AG22: 0 | AH22: 0 | AI22: 0 | AJ22: 0 | AK22: 0 | AL22: 0 | AM22: 0 | AN22: 0 | AO22: 0 | AP22: 0 | AR22: 0 | AS22: 0 | AT22: 0 | AU22: 0 | AV22: 0 | AX22: 0 | AY22: 0 | AZ22: 0 | BA22: 0 | BB22: 0 | BC22: 0 | BE22: 0 | BF22: 0 | BG22: 0 | BH22: 0 | BI22: 0 | BJ22: 0 | BK22: 0 | BL22: 0 | BM22: 0 | BN22: 0 | BO22: 0 | BP22: 0 | BR22: 0 | BS22: 0 | BT22: 0 | BU22: 0 | BV22: 0 | BW22: 0 | BY22: 0 | BZ22: 0 | CA22: 0 | CB22: 0 | CC22: 0 | CF22: 0 | CG22: 0 | CH22: 0 | CI22: 0 | CJ22: 0 | CK22: 0 | CL22: 0 | CM22: 0 | CN22: 0 | CO22: 0 | CP22: 0 | CQ22: 0
A23: 4.5 | B23: Other Financial Expense | E23: 568105 | S23: 0 | T23: 0 | U23: 0 | V23: 0 | X23: 0 | Y23: 0 | Z23: 0 | AA23: 0 | AB23: 0 | AC23: 0 | AD23: 0 | AE23: 0 | AF23: 0 | AG23: 1432000 | AH23: 1432000 | AI23: 1432000 | AJ23: 1432000 | AK23: 1432000 | AL23: 1432000 | AM23: 1432000 | AN23: 1432000 | AO23: 2369867.9 | AP23: 2369867.9 | AR23: 0 | AS23: 0 | AT23: 0 | AU23: 0 | AV23: 0 | AX23: 0 | AY23: 0 | AZ23: 379698.56 | BA23: 379698.56 | BB23: 0 | BC23: 0 | BE23: 19104 | BF23: 67606 | BG23: 83956 | BH23: 84755.45 | BI23: 0 | BJ23: 0 | BK23: 1354821.4 | BL23: 1420353.4 | BM23: 2370834.6 | BN23: 1576376.6 | BO23: 1697236.6 | BP23: 0 | BR23: 0 | BS23: 167421.59 | BT23: 534638.94 | BU23: 0 | BV23: 794589.51 | BW23: 794589.51 | BY23: 1120674.2 | BZ23: 1704092.8 | CA23: 1958147.7 | CB23: 2161992.2 | CC23: 2721608.2 | CD23: 1799552 | CF23: 0 | CG23: 0 | CH23: 0 | CI23: 628719.99 | CJ23: 859263.54 | CK23: 419823.17 | CL23: 484091.81 | CM23: 558497.6 | CN23: 562300.2 | CO23: 562300.2 | CP23: 570350.8 | CQ23: 0
A24: 4.6 | B24: Fees & Commission Expense | C24: 97012.1 | D24: 42415 | S24: 0 | T24: 0 | U24: 0 | V24: 0 | X24: 0 | Y24: 0 | Z24: 0 | AA24: 1 | AB24: 0 | AC24: 0 | AD24: 0 | AE24: 0 | AF24: 0 | AG24: 0 | AH24: 0 | AI24: 0 | AJ24: 0 | AK24: 0 | AL24: 0 | AM24: 0 | AN24: 0 | AO24: 0 | AP24: 0 | AR24: 0 | AS24: 0 | AT24: 0 | AU24: 0 | AV24: 0 | AX24: 0 | AY24: 0 | AZ24: 0 | BA24: 0 | BB24: 0 | BC24: 0 | BD24: 0 | BE24: 0 | BF24: 0 | BG24: 0 | BH24: 0 | BI24: 0 | BJ24: 0 | BK24: 0 | BL24: 0 | BM24: 0 | BN24: 0 | BO24: 0 | BP24: 0 | BR24: 0 | BS24: 0 | BT24: 0 | BU24: 0 | BV24: 0 | BW24: 0 | BY24: 0 | BZ24: 0 | CA24: 0 | CB24: 0 | CC24: 0 | CF24: 0 | CG24: 0 | CH24: 0 | CI24: 0 | CJ24: 0 | CK24: 0 | CL24: 0 | CM24: 0 | CN24: 0 | CO24: 0 | CP24: 0 | CQ24: 0
A25: 4.7 | B25: Other Expense | E25: =912500+135250 -> 1047750 | AK25: 0 | AL25: 0 | AO25: 0 | AP25: 0 | AR25: 0 | AS25: 0 | AT25: 0 | AU25: 0 | AV25: 0 | AX25: 0 | AY25: 0 | AZ25: 0 | BA25: 0 | BB25: 0 | BC25: 0 | BD25: 0 | BE25: 0 | BF25: 0 | BG25: 0 | BH25: 0 | BI25: 0 | BJ25: 0 | BK25: 0 | BL25: 0 | BM25: 0 | BN25: 0 | BO25: 0 | BP25: 0 | BR25: 0 | BS25: 0 | BT25: 0 | BU25: 0 | BV25: 0 | BW25: 0 | BY25: 0 | BZ25: 0 | CA25: 0 | CB25: 0 | CC25: 0 | CD25: 1910136 | CF25: 0 | CG25: 0 | CH25: 0 | CI25: 0 | CJ25: 0 | CK25: 0 | CL25: 0 | CM25: 0 | CN25: 0 | CO25: 0 | CP25: 0 | CQ25: 0
A26: 5 | B26: Net Financial Income/(Loss) | C26: =C10-C19 -> 32312211 | D26: =D10-D19 -> 35411693 | E26: =E10-E19 -> 39796589 | F26: =F10-F19 -> 4772686.8 | G26: =G10-G19 -> 9180264.2 | H26: =H10-H19 -> 13185010 | I26: =I10-I19 -> 9532332.7 | J26: =J10-J19 -> 15944965 | ... CR26: =CR10-CR19 -> 0
A27: 6 | B27: Allowance for Loan Loss | C27: =C28-C29 -> 0 | D27: =D28-D29 -> 852418.02 | E27: =E28-E29 -> 6113750 | F27: =F28-F29 -> 2004119.4 | G27: =G28-G29 -> 2320087 | H27: =H28-H29 -> 3800123 | I27: =I28-I29 -> 7996958.1 | J27: =J28-J29 -> 7808518.7 | ... CR27: =CR28-CR29 -> 0
A28: 6.1 | B28: Provision for Loan Losses | D28: 852418.02 | E28: 6113750 | F28: 31788444 | G28: 35574259 | H28: 37229273 | I28: 35191294 | J28: 36008201 | K28: 25650895 | L28: 25565318 | M28: 25565318 | N28: 26684223 | O28: 35042555 | P28: 35144795 | Q28: 27229957 | R28: 1690285 | S28: 31295425 | T28: 7826079.6 | U28: 6634379.5 | V28: 5990682.4 | W28: 7195090.7 | X28: 8136285.8 | Y28: 9901946.3 | Z28: 12479945 | AA28: 11512086 | AB28: 11922708 | AC28: 10596215 | AD28: 18317842 | AE28: 11236789 | AF28: 12369785 | AG28: 11924753 | AH28: 12394567 | AI28: 11095883 | AJ28: 13741671 | AK28: 13340487 | AL28: 10375126 | AM28: 13645903 | AN28: 14379390 | AO28: 9825396.4 | AP28: 13788864 | AQ28: 3973233 | AR28: 13245897 | AS28: 11245365 | AT28: 12757388 | AU28: 13526987 | AV28: 14369785 | AW28: 10502228 | AX28: 11868566 | AY28: 9807410.6 | AZ28: 9609968.1 | BA28: 9609968.1 | BB28: 10509439 | BC28: 12013231 | BD28: 3500000 | BE28: 9625368.9 | BF28: 10225012 | BG28: 10867106 | BH28: 10735257 | BI28: 9298227.3 | BJ28: 9879712.9 | BK28: 9507885.7 | BL28: 9703533.6 | BM28: 9824517.5 | BN28: 10001064 | BO28: 10778845 | BP28: 11034851 | BQ28: 6000000 | BR28: 10526347 | BS28: 11311511 | BT28: 10722159 | BU28: 8260963.2 | BV28: 10260370 | BW28: 10699318 | BY28: 10257200 | BZ28: 10146692 | CA28: 10413070 | CB28: 11552130 | CC28: 8329276.5 | CD28: 7000000 | CE28: 7000000 | CF28: 6915696.2 | CG28: 6959043.4 | CH28: 6655279.3 | CI28: 7103146.2 | CJ28: 7315798.9 | CK28: 7178230.4 | CL28: 7595142 | CM28: 7494352.8 | CN28: 7730461 | CO28: 7725468.1 | CP28: 7825319.1 | CQ28: 7500000
A29: 6.2 | B29: Value of Loans Recovered | F29: 29784325 | G29: 33254172 | H29: 33429150 | I29: 27194336 | J29: 28199682 | K29: 23103646 | L29: 23404696 | M29: 23404696 | N29: 22792072 | O29: 30649054 | P29: 29873076 | Q29: 20107616 | S29: 29284946 | T29: 6815782.4 | U29: 4569251.2 | V29: 3620452.3 | W29: 5982013.4 | X29: 7139586.3 | Y29: 8802356.2 | Z29: 10425369 | AA29: 10155370 | AB29: 6349865.2 | AC29: 6389707.6 | AD29: 12319867 | AE29: 9920369.6 | AF29: 10526379 | AG29: 9863269.4 | AH29: 11479087 | AI29: 10235987 | AJ29: 12389964 | AK29: 12325370 | AL29: 9026967.1 | AM29: 12125370 | AN29: 12550237 | AO29: 8239489.7 | AP29: 12349212 | AQ29: 0 | AR29: 12362429 | AS29: 10163279 | AT29: 11428697 | AU29: 12247893 | AV29: 13246589 | AW29: 9233125.9 | AX29: 10800269 | AY29: 8137500 | AZ29: 8246398.4 | BA29: 8246398.4 | BB29: 9352689.4 | BC29: 10152357 | BE29: 8245149.2 | BF29: 9094251.4 | BG29: 9214522.2 | BH29: 8254126.4 | BI29: 8150236.4 | BJ29: 8245362.1 | BK29: 8213456.2 | BL29: 8239569.3 | BM29: 8249165.3 | BN29: 8715345.6 | BO29: 9256135.7 | BP29: 3450000 | BR29: 8246796.3 | BS29: 10213456 | BT29: 9287360.9 | BU29: 7340694 | BV29: 9145689.2 | BW29: 9356290.2 | BY29: 7925633.1 | BZ29: 9146237 | CA29: 9134856.3 | CB29: 10135630 | CC29: 0 | CF29: 5203146.2 | CG29: 5124989.2 | CH29: 5112479.3 | CI29: 5346983.3 | CJ29: 6154237 | CK29: 5924156.4 | CL29: 6123587.3 | CM29: 6232550.2 | CN29: 6320450.2 | CO29: 6505450.2 | CP29: 6400455.2 | CQ29: 0
A30: 7 | B30: Operating Expenses | C30: =C31+C32+C33+C34+C35 -> 14729924 | D30: =D31+D32+D33+D34+D35 -> 23782929 | E30: =SUM(E31:E35) -> 28899075 | F30: =SUM(F31:F35) -> 2685293.5 | G30: =SUM(G31:G35) -> 7250951.1 | H30: =SUM(H31:H35) -> 10496937 | I30: =SUM(I31:I35) -> 16723133 | J30: =SUM(J31:J35) -> 17981726 | K30: =SUM(K31:K35) -> 22147582 | L30: =SUM(L31:L35) -> 24527976 | ... CR30: =SUM(CR31:CR35) -> 0
A31: 7.1 | B31: Personnel Expenses | C31: 5434455 | D31: 7065720.4 | E31: =3537698+1282293+960960+53200+2313830+1812660 -> 9960641 | F31: 250647.58 | G31: 1647087.7 | H31: 1920033.6 | I31: 2265954.6 | J31: 2265954.6 | K31: 4021991.5 | L31: 4609287.5 | M31: 5177287.5 | N31: 9466252.9 | O31: 10459187 | P31: 11428658 | Q31: 12759714 | R31: 18827351 | S31: 1117127 | T31: 2254970 | U31: 3376527 | V31: 4441940 | W31: 6340550 | X31: 8786218 | Y31: 10432809 | Z31: 11855632 | AA31: 13295668 | AB31: 14878301 | AC31: 16757699 | AD31: 18957066 | AE31: 1236782.1 | AF31: 2052326.6 | AG31: 4291914 | AH31: 5304952 | AI31: 6757568 | AJ31: 8946309 | AK31: 10762763 | AL31: 12119377 | AM31: 15835392 | AN31: 16329416 | AO31: 17758581 | AP31: 20196229 | AQ31: 20296229 | AR31: 2111580 | AS31: 2448580 | AT31: 5297015 | AU31: 6772103.6 | AV31: 9615117.6 | AW31: 13762690 | AX31: 15054121 | AY31: 17353694 | AZ31: 19535377 | BA31: 19535377 | BB31: 24258159 | BC31: 27489033 | BD31: 21067433 | BE31: 2668499.1 | BF31: 3892858.1 | BG31: 5672374.4 | BH31: 9213306.5 | BI31: 11196575 | BJ31: 13057625 | BK31: 14888992 | BL31: 17590287 | BM31: 19607519 | BN31: 21522692 | BO31: 23275040 | BP31: 23672845 | BQ31: 24413005 | BR31: 1967820 | BS31: 3960896.9 | BT31: 5827391.9 | BU31: 7723011.9 | BV31: 8988999.3 | BW31: 10979019 | BY31: 15878253 | BZ31: 18074347 | CA31: 20981323 | CB31: 22867705 | CC31: 26053125 | CD31: 26053125 | CE31: 27260039 | CF31: 1797524 | CG31: 3358948 | CH31: 5213208.6 | CI31: 8060223.6 | CJ31: 10319548 | CK31: 12770811 | CL31: 15133254 | CM31: 17672338 | CN31: 21740896 | CO31: 23951116 | CP31: 27272528 | CQ31: 29117254
A32: 7.2 | B32: Governance Expenses | C32: 4867500 | D32: 7971760 | E32: =1609680+1861820+635050+2039900+2230510 -> 8376960 | F32: 897750 | G32: 3402850 | H32: 4482360 | I32: 8226380 | J32: 8429690 | K32: 9284870 | L32: 10080970 | M32: 10729070 | N32: 11316070 | O32: 11677970 | P32: 12177720 | Q32: 14646538 | R32: 10676538 | S32: 1458130 | T32: 3028530 | U32: 3985330 | V32: 6606938 | W32: 8010658 | X32: 8727868 | Y32: 9416488 | Z32: 10179508 | AA32: 11880378 | AB32: 11503238 | AC32: 12457678 | AD32: 14281378 | AE32: 780300 | AF32: 921600 | AG32: 2844090 | AH32: 4478500 | AI32: 4983920 | AJ32: 7330350 | AK32: 7834400 | AL32: 8435200 | AM32: 10048120 | AN32: 10619320 | AO32: 11413750 | AP32: 9157115.5 | AQ32: 9157115 | AR32: 507200 | AS32: 891100 | AT32: 3123290 | AU32: 3832990 | AV32: 4461040 | AW32: 4871190 | AX32: 5455890 | AY32: 6240090 | AZ32: 6915640 | BA32: 6915640 | BB32: 8356320 | BC32: 9865770 | BD32: 10214070 | BE32: 771650 | BF32: 935350 | BG32: 3445750 | BH32: 4147532 | BI32: 5816910 | BJ32: 6016710 | BK32: 9129665 | BL32: 9944665 | BM32: 10320965 | BN32: 10397155 | BO32: 10843665 | BP32: 11391654 | BQ32: 10986055 | BR32: 355500 | BS32: 1552100 | BT32: 1665870 | BU32: 2464670 | BV32: 3826870 | BW32: 4926270 | BY32: 5311070 | BZ32: 5697570 | CA32: 6403490 | CB32: 6738590 | CC32: 6725205 | CD32: 6725205 | CE32: 8828680 | CF32: 280080 | CG32: 674900 | CH32: 3491570 | CI32: 5026710 | CJ32: 5639010 | CK32: 5965110 | CL32: 6525410 | CM32: 6797110 | CN32: 6953700 | CO32: 7641552 | CP32: 7792490 | CQ32: 7301702
A33: 7.3 | B33: Marketing Expenses | C33: 117250 | D33: 28900 | E33: 499960 | F33: 12500 | G33: 28000 | H33: 81000 | I33: 175040 | J33: 181790 | K33: 188290 | L33: 197290 | M33: 218890 | N33: 326390 | O33: 459390 | P33: 666790 | Q33: 840290 | R33: 319490 | S33: 101800 | T33: 190800 | U33: 246800 | V33: 280800 | W33: 336800 | X33: 457400 | Y33: 511600 | Z33: 569600 | AA33: 761300 | AB33: 817400 | AC33: 823400 | AD33: 826400 | AE33: 234850 | AF33: 567800 | AG33: 140300 | AH33: 154300 | AI33: 478800 | AJ33: 524400 | AK33: 585800 | AL33: 690800 | AM33: 867600 | AN33: 1113350 | AO33: 1291450 | AP33: 1380100 | AQ33: 1380100 | AR33: 55500 | AS33: 143400 | AT33: 452410 | AU33: 784470 | AV33: 1187450 | AW33: 1559012 | AX33: 1822862 | AY33: 1961812 | AZ33: 2030712 | BA33: 2030712 | BB33: 2852932 | BC33: 2906232 | BE33: 249500 | BF33: 547100 | BG33: 697940 | BH33: 942820 | BI33: 995120 | BJ33: 1031920 | BK33: 1013370 | BL33: 1228738 | BM33: 1273938 | BN33: 1363590 | BO33: 1417490 | BP33: 1455940 | BQ33: 1455940 | BR33: 34600 | BS33: 188300 | BT33: 213500 | BU33: 215500 | BV33: 314050 | BW33: 399700 | BY33: 427550 | BZ33: 429550 | CA33: 632050 | CB33: 640550 | CC33: 645550 | CD33: 645550 | CE33: 1844935 | CF33: 604900 | CG33: 376350 | CH33: 390750 | CI33: 584050 | CJ33: 611050 | CK33: 890150 | CL33: 927750 | CM33: 1013250 | CN33: 1056250 | CO33: 1066250 | CP33: 1080250 | CQ33: 845050
A34: 7.4 | B34: Depreciation and Amortization Charges | C34: 816443.3 | D34: 1227389.5 | E34: 3121778 | F34: 98608.47 | G34: 98608.47 | H34: 147912.68 | I34: 98608.47 | J34: 123260.59 | K34: 147912.71 | L34: 172564.83 | M34: 197216.94 | N34: 2168886.2 | O34: 2409873.6 | P34: 2650861 | Q34: 2891848.3 | R34: 6546278.2 | S34: 375000 | T34: 545523 | U34: 818284.5 | V34: 1091046 | W34: 1363807.5 | X34: 1636569 | Y34: 1909330.5 | Z34: 2182092 | AA34: 2454853.5 | AB34: 2727615.4 | AC34: 3000376.9 | AD34: 3878022.4 | AE34: 575369.69 | AF34: 725489.23 | AG34: 856936.36 | AH34: 1142581.8 | AI34: 1371098.2 | AJ34: 1645317.8 | AK34: 1919537.4 | AL34: 2193757.1 | AM34: 2467976.7 | AN34: 2714774.4 | AO34: 2961572 | AP34: 3230805.9 | AQ34: 5037036 | AR34: 268356.85 | AS34: 436713.7 | AT34: 655070.55 | AU34: 873427.4 | AV34: 1091784.2 | AW34: 1310141.1 | AX34: 1528497.9 | AY34: 1746854.8 | AZ34: 1965211.6 | BA34: 1965211.6 | BB34: 2823810.7 | BC34: 3080520.8 | BD34: 2451033.6 | BE34: 342520 | BF34: 0 | BG34: 1396576.1 | BH34: 1862101.5 | BI34: 2327626.9 | BJ34: 2793152.3 | BK34: 3258677.7 | BL34: 3724203 | BM34: 4189728 | BN34: 4655253.3 | BO34: 5078458.2 | BP34: 4252572 | BQ34: =1868145.6+2090284.95 -> 3958430.5 | BR34: 354381 | BS34: 769500 | BT34: 852333.36 | BU34: 1065416.7 | BV34: 1331770.9 | BW34: 1598125.1 | BY34: 2130833.3 | BZ34: 2397187.5 | CA34: 2663541.7 | CB34: 2929895.8 | CC34: 3271901 | CD34: 1472349 | CE34: =1443678+899911 -> 2343589 | CF34: 398241.23 | CG34: 796482.46 | CH34: 889236.25 | CI34: 1185648.3 | CJ34: 1482060.4 | CK34: 1778472.5 | CL34: 2074884.6 | CM34: 2371296.6 | CN34: 3624446.6 | CO34: 4027163 | CP34: 4429879.3 | CQ34: 0
A35: 7.5 | B35: Administrative Expenses | C35: 3494275.8 | D35: =7469159.3+20000 -> 7489159.3 | E35: =391080+1501639+145180+495510+653942+73000+125633+735370+1083362+302880+14148+85470+85470+333700+913352 -> 6939736 | F35: 1425787.4 | G35: 2074404.9 | H35: 3865630.5 | I35: 5957150 | J35: 6981030.8 | K35: 8504517.3 | L35: 9467863.9 | M35: 11011619 | N35: 6687946.5 | O35: 7601580.5 | P35: 8574933.5 | Q35: 10678549 | R35: =12204200+1175924-319490 -> 13060634 | S35: 1115221 | T35: 2314253 | U35: 3114338 | V35: 4326250 | W35: 6161511 | X35: 6837931 | Y35: 7610832 | Z35: 8559228 | AA35: 9290648 | AB35: 10186918 | AC35: 10288978 | AD35: 11284618 | AE35: 1123526.4 | AF35: 3725698.4 | AG35: 3997872 | AH35: 4158407 | AI35: 4658002 | AJ35: 7746837 | AK35: 7910927 | AL35: 9095877 | AM35: 10158334 | AN35: 10688143 | AO35: 11779683 | AP35: 15221265 | AQ35: 12664929 | AR35: 697397 | AS35: 1674213 | AT35: 2567684 | AU35: 3764658 | AV35: 4930438 | AW35: 5928108 | AX35: 6917460 | AY35: 8118260 | AZ35: 9754350 | BA35: 9754350 | BB35: 12342097 | BC35: 16855942 | BD35: 37393873 | BE35: 1142219 | BF35: 1729898 | BG35: 3758840.6 | BH35: 5462020.6 | BI35: 6109730.6 | BJ35: 7488792.6 | BK35: 9323722.8 | BL35: 11043318 | BM35: 11609817 | BN35: 12413485 | BO35: 13149575 | BP35: 22651163 | BQ35: 29610992 | BR35: 1164853 | BS35: 2873743 | BT35: 5110436 | BU35: 6590536 | BV35: 7654546 | BW35: 9307728 | BY35: 12590543 | BZ35: 11370022 | CA35: 10676618 | CB35: 11900552 | CC35: 28994258 | CD35: =33447664.15-CD33 -> 32802114 | CE35: =36141657-1844935 -> 34296722 | CF35: 1912770 | CG35: 2588925 | CH35: 4236657 | CI35: 5915751 | CJ35: 9733016 | CK35: 10743735 | CL35: 11385913 | CM35: 11616743 | CN35: 12030187 | CO35: 13854890 | CP35: 14496391 | CQ35: 38214661
A36: 8 | B36: Net Operating Income | C36: =C26-C27-C30 -> 17582286 | D36: =D26-D27-D30 -> 10776346 | E36: =E26-E27-E30 -> 4783764 | F36: =F26-F27-F30 -> 83273.84 | G36: =G26-G27-G30 -> -390773.93 | H36: =H26-H27-H30 -> -1112049.8 | I36: =I26-I27-I30 -> -15187758 | J36: =J26-J27-J30 -> -9845279.7 | ... CQ36: =CQ26-CQ27-CQ30 -> 21919230
A37: 9 | B37: Net Non- Operating Income/ (Expense) | C37: =C38-C39 -> 0 | D37: =D38-D39 -> 0 | E37: =E38-E39 -> 0 | F37: =F38-F39 -> 0 | G37: =G38-G39 -> 0 | H37: =H38-H39 -> 0 | I37: =I38-I39 -> 0 | J37: =J38-J39 -> 0 | ... CQ37: =CQ38-CQ39 -> -5683058.2
A38: 9.1 | B38: Non- Operating Income | S38: 0 | T38: 0 | U38: 0 | V38: 0 | W38: 0 | X38: 0 | Y38: 0 | Z38: 0 | AA38: 1 | AB38: 0 | AC38: 0 | AD38: 0 | AE38: 0 | AF38: 0 | AG38: 0 | AH38: 0 | AI38: 0 | AJ38: 0 | AK38: 0 | AL38: 0 | AM38: 0 | AN38: 0 | AO38: 0 | AP38: 0 | AR38: 0 | AS38: 0 | AT38: 0 | AU38: 0 | AV38: 0 | AW38: 0 | AX38: 0 | AY38: 0 | AZ38: 0 | BA38: 0 | BB38: 0 | BC38: 0 | BD38: 0 | BE38: 0 | BF38: 0 | BG38: 0 | BH38: 0 | BI38: 0 | BJ38: 0 | BK38: 0 | BL38: 0 | BM38: 0 | BN38: 0 | BO38: 0 | BP38: 0 | BR38: 0 | BS38: 0 | BT38: 0 | BU38: 0 | BV38: 0 | BW38: 0 | BY38: 0 | BZ38: 0 | CA38: 0 | CB38: 0 | CC38: 0 | CF38: 0 | CG38: 0 | CH38: 0 | CI38: 0 | CJ38: 0 | CK38: 0 | CL38: 0 | CM38: 0 | CN38: 0 | CO38: 0 | CP38: 0 | CQ38: 0
A39: 9.2 | B39: Non- Operating Expense | S39: 0 | T39: 0 | U39: 0 | V39: 0 | W39: 0 | X39: 0 | Y39: 0 | Z39: 0 | AA39: 1 | AB39: 0 | AC39: 0 | AD39: 0 | AE39: 0 | AF39: 0 | AG39: 0 | AH39: 0 | AI39: 0 | AJ39: 0 | AK39: 0 | AL39: 0 | AM39: 0 | AN39: 0 | AO39: 0 | AP39: 0 | AR39: 0 | AS39: 0 | AT39: 0 | AU39: 0 | AV39: 0 | AW39: 0 | AX39: 0 | AY39: 0 | AZ39: 0 | BA39: 0 | BB39: 0 | BC39: 0 | BD39: 0 | BE39: 0 | BF39: 0 | BG39: 0 | BH39: 0 | BI39: 0 | BJ39: 0 | BK39: 0 | BL39: 0 | BM39: 0 | BN39: 0 | BO39: 0 | BP39: 0 | BR39: 0 | BS39: 0 | BT39: 0 | BU39: 0 | BV39: 0 | BW39: 0 | BY39: 0 | BZ39: 0 | CA39: 0 | CB39: 0 | CC39: 0 | CF39: 0 | CG39: 0 | CH39: 0 | CI39: 0 | CJ39: 0 | CK39: 0 | CL39: 0 | CM39: 0 | CN39: 0 | CO39: 0 | CP39: 0 | CQ39: 5683058.2
A40: 10 | B40: Net Income (Before Taxes and Donations) | C40: =C36+C37 -> 17582286 | D40: =D36+D37 -> 10776346 | E40: =E36+E37 -> 4783764 | F40: =F36+F37 -> 83273.84 | G40: =G36+G37 -> -390773.93 | H40: =H36+H37 -> -1112049.8 | I40: =I36+I37 -> -15187758 | J40: =J36+J37 -> -9845279.7 | ... CR40: =CR36+CR37 -> 0
A41: 11 | B41: Taxes (Incomes taxes & Other payable to KRA) | C41: 35 | E41: 199232 | R41: 59409.3 | AE41: 0 | AF41: 0 | AG41: 0 | AH41: 0 | AI41: 0 | AJ41: 0 | AK41: 0 | AL41: 0 | AM41: 0 | AN41: 0 | AO41: 0 | AP41: 0 | AQ41: 729864 | AR41: 0 | AS41: 0 | AT41: 0 | AU41: 0 | AV41: 0 | AW41: 0 | AX41: 0 | AY41: 0 | AZ41: 0 | BA41: 0 | BB41: 0 | BC41: 0 | BD41: 962618 | BE41: 0 | BF41: 0 | BG41: 0 | BH41: 0 | BI41: 0 | BJ41: 0 | BK41: 0 | BL41: 0 | BM41: 0 | BN41: 0 | BO41: 0 | BP41: 999887 | BQ41: 1459727 | BS41: 0 | BT41: 0 | BU41: 0 | BV41: 0 | BW41: 0 | BY41: 0 | BZ41: 0 | CA41: 0 | CB41: 0 | CC41: 0 | CE41: 2671948 | CF41: 0 | CG41: 0 | CH41: 0 | CI41: 0 | CJ41: 0 | CK41: 0 | CL41: 0 | CM41: 0 | CN41: 0 | CO41: 0 | CP41: 0 | CQ41: 2503939.4
A42: 12 | B42: Net Income (After Taxes before Donations) | C42: =C40-C41 -> 17582251 | D42: =D40-D41 -> 10776346 | E42: =E40-E41 -> 4584532 | F42: =F40-F41 -> 83273.84 | G42: =G40-G41 -> -390773.93 | H42: =H40-H41 -> -1112049.8 | I42: =I40-I41 -> -15187758 | J42: =J40-J41 -> -9845279.7 | ... CR42: =CR40-CR41 -> 0
A43: 13 | B43: Donations | C43: 0 | E43: 36000 | AE43: 0 | AF43: 0 | AG43: 0 | AH43: 0 | AI43: 0 | AJ43: 0 | AK43: 0 | AL43: 0 | AM43: 0 | AN43: 0 | AO43: 0 | AP43: 0 | AR43: 0 | AS43: 0 | AT43: 0 | AU43: 0 | AV43: 0 | AW43: 0 | AX43: 0 | AY43: 0 | AZ43: 0 | BA43: 0 | BB43: 0 | BC43: 0 | BE43: 0 | BF43: 0 | BG43: 0 | BH43: 0 | BI43: 0 | BJ43: 0 | BK43: 0 | BL43: 0 | BM43: 0 | BN43: 0 | BO43: 0 | BP43: 0 | BS43: 0 | BT43: 0 | BU43: 0 | BV43: 0 | BW43: 0 | BY43: 0 | BZ43: 0 | CA43: 0 | CB43: 0 | CC43: 0 | CF43: 0 | CG43: 0 | CH43: 0 | CI43: 0 | CJ43: 0 | CK43: 0 | CL43: 0 | CM43: 0 | CN43: 0 | CO43: 0 | CP43: 0 | CQ43: 0
A44: 14 | B44: Net Income/(After Taxes and Donations) | C44: =C42-C43 -> 17582251 | D44: =D42-D43 -> 10776346 | E44: =E42+E43 -> 4620532 | F44: =F42+F43 -> 83273.84 | G44: =G42+G43 -> -390773.93 | H44: =H42+H43 -> -1112049.8 | I44: =I42+I43 -> -15187758 | J44: =J42+J43 -> -9845279.7 | K44: =K42+K43 -> -5304714.5 | L44: =L42+L43 -> -4632165.9 | ... CR44: =CR42+CR43 -> 0
B45: Note: This return should be received within 15 days after end of the month. | BR45: =BQ44-BR44 -> 4122537.6
C46: =C19+C30 -> 27742425 | D46: =D19+D30 -> 33646135 | E46: =E19+E30 -> 56796978 | F46: =F19+F30 -> 4020293.5 | G46: =G19+G30 -> 8585951.1 | H46: =H19+H30 -> 11831937 | I46: =I19+I30 -> 26636643 | J46: =J19+J30 -> 30088006 | ... BA46: =BA19+BA30 -> 70511736
B47: AUTHORIZATION:
B48: We declare that this return, to the best of our knowledge and belief is correct.
B49: …………………………………………………..sign……………………………..date……………………..
B50: Name of Authorizing Officer
B51: …………………………………………………..sign……………………………..date……………………..
B52: Name of Countersigning Officer

Sheet PRUDENTIALS
B2: Eco-Pillar Sacco Ltd Financial Performance & Projections
B4: FINANCIAL SOUNDNESS INDICATORS | C4: Prudential Std | D4: Audited 2012 | E4: Audited 2013 | F4: Audited 14 | G4: 42005 | H4: 42036 | I4: 42064 | J4: 42095 | K4: 42125 | L4: 42156 | M4: 42186 | N4: 42217 | O4: 42248 | P4: 42278 | Q4: 42309 | R4: 42339 | S4: Audited 2015 | T4: 42385 | U4: 42416 | V4: 42445 | W4: 42476 | X4: 42506 | Y4: 42537 | Z4: 42567 | AA4: 42598 | AB4: 42629 | AC4: 42659 | AD4: 42690 | AE4: 42720 | AF4: 42751 | AG4: 42782 | AH4: 42810 | AI4: 42841 | AJ4: 42871 | AK4: 42902 | AL4: 42932 | AM4: 42963 | AN4: 42994 | AO4: 43024 | AP4: 43055 | AQ4: Audited 2017 | AR4: Audited 2017 | AS4: 43101 | AT4: 43132 | AU4: 43160 | AV4: 43191 | AW4: 43221 | AX4: 43252 | AY4: 43282 | AZ4: 43313 | BA4: 43344 | BB4: 43374 | BC4: 43405 | BD4: 43435 | BE4: Aud-18 | BF4: 43466 | BG4: 43497 | BH4: 43525 | BI4: 43556 | BJ4: 43586 | BK4: 43617 | BL4: 43647 | BM4: 43678 | BN4: 43709 | BO4: 43739 | BP4: 43770 | BQ4: 43800 | BR4: Audited 2019 | BS4: 43831 | BT4: 43862 | BU4: 43891 | BV4: 43922 | BW4: 43952 | BX4: 43983 | BY4: 44013 | BZ4: 44044 | CA4: 44075 | CB4: 44105 | CC4: 44136 | CD4: 44166 | CE4: Aud-20
A5: 1 | B5: CAPITAL ADEQUACY REQUIREMENTS
A6: 1.1 | B6: Core capital | C6: ≥ Ksh.10M | D6: =FINANCIALS!D12/1000000 -> -17.916464 | E6: =FINANCIALS!E12/1000000 -> 37.703005 | F6: =FINANCIALS!F12/1000000 -> 84.979038 | G6: =FINANCIALS!G12/1000000 -> 55.863957 | H6: =FINANCIALS!H12/1000000 -> 55.715309 | I6: =FINANCIALS!I12/1000000 -> 55.361663 | J6: =FINANCIALS!J12/1000000 -> 82.339788 | K6: =FINANCIALS!K12/1000000 -> 59.666643 | ... CC6: =FINANCIALS!CC12/1000000 -> 214.56412 | CD6: =FINANCIALS!CC12/1000000 -> 214.56412 | CE6: =FINANCIALS!CD12/1000000 -> 196.33967
A7: 1.2 | B7: Core capital /Total Assets | C7: ≥ 10% | D7: =FINANCIALS!D12/FINANCIALS!D4 -> -0.037688463 | E7: =FINANCIALS!E12/FINANCIALS!E4 -> 0.074265441 | F7: =FINANCIALS!F12/FINANCIALS!F4 -> 0.14133745 | G7: =FINANCIALS!G12/FINANCIALS!G4 -> 0.12036105 | H7: =FINANCIALS!H12/FINANCIALS!H4 -> 0.10357065 | I7: =FINANCIALS!I12/FINANCIALS!I4 -> 0.10226084 | J7: =FINANCIALS!J12/FINANCIALS!J4 -> 0.14218079 | K7: =FINANCIALS!K12/FINANCIALS!K4 -> 0.18543465 | ... CB7: =FINANCIALS!CB12/FINANCIALS!CB4 -> 0.18342788 | CC7: =FINANCIALS!CB12/FINANCIALS!CB4 -> 0.18342788 | CD7: =FINANCIALS!CC12/FINANCIALS!CC4 -> 0.19067336 | CE7: =FINANCIALS!CD12/FINANCIALS!CD4 -> 0.17289325
A8: 1.3 | B8: Core capital /Total Deposits | C8: ≥ 8% | D8: =FINANCIALS!D12/FINANCIALS!D5 -> -0.045930603 | E8: =FINANCIALS!E12/FINANCIALS!E5 -> 0.093162904 | F8: =FINANCIALS!F12/FINANCIALS!F5 -> 0.19589648 | G8: =FINANCIALS!G12/FINANCIALS!G5 -> 0.12535676 | H8: =FINANCIALS!H12/FINANCIALS!H5 -> 0.12610878 | I8: =FINANCIALS!I12/FINANCIALS!I5 -> 0.12365377 | J8: =FINANCIALS!J12/FINANCIALS!J5 -> 0.17959283 | K8: =FINANCIALS!K12/FINANCIALS!K5 -> 0.13014002 | ... BQ8: =FINANCIALS!BQ12/FINANCIALS!BQ5 -> 0.26699305 | BS8: =FINANCIALS!BR12/FINANCIALS!BR5 -> 0.2378031 | BT8: =FINANCIALS!BS12/FINANCIALS!BS5 -> 0.26224979 | BU8: =FINANCIALS!BT12/FINANCIALS!BT5 -> 0.2674376 | BV8: =FINANCIALS!BU12/FINANCIALS!BU5 -> 0.2748047 | BW8: =FINANCIALS!BV12/FINANCIALS!BV5 -> 0.25864723 | BX8: =FINANCIALS!BW12/FINANCIALS!BW5 -> 0.25797569 | BY8: =FINANCIALS!BX12/FINANCIALS!BX5 -> 0.25258921 | BZ8: =FINANCIALS!BY12/FINANCIALS!BY5 -> #DIV/0! | ... CD8: =FINANCIALS!CC12/FINANCIALS!CC5 -> 0.28132861 | CE8: =FINANCIALS!CC12/FINANCIALS!CC5 -> 0.28132861
A9: 1.4 | B9: Institutional/Total Assets | C9: ≥ 8% | D9: =FINANCIALS!D13/FINANCIALS!D4 -> 0.015384078 | E9: =FINANCIALS!E13/FINANCIALS!E4 -> 0.077690834 | F9: =FINANCIALS!F13/FINANCIALS!F4 -> 0.088211033 | G9: =FINANCIALS!G13/FINANCIALS!G4 -> 0.045358568 | H9: =FINANCIALS!H13/FINANCIALS!H4 -> 0.038858847 | I9: =FINANCIALS!I13/FINANCIALS!I4 -> 0.037959269 | J9: =FINANCIALS!J13/FINANCIALS!J4 -> 0.082069986 | K9: =FINANCIALS!K13/FINANCIALS!K4 -> 0.077246266 | ... CB9: =FINANCIALS!CB13/FINANCIALS!CB4 -> 0.10175353 | CC9: =FINANCIALS!CB13/FINANCIALS!CB4 -> 0.10175353 | CD9: =FINANCIALS!CB13/FINANCIALS!CB4 -> 0.10175353 | CE9: =FINANCIALS!CC13/FINANCIALS!CC4 -> 0.10791054
A11: 2 | B11: ASSET MIX AND QUALITY
A12: 2.1 | B12: Non Earning Assets
A13: 2.1.1 | B13: Non earning Assets/Total assets | C13: ≤ 10% | D13: =FINANCIALS!D33/FINANCIALS!D4 -> 0.29130011 | E13: =FINANCIALS!E33/FINANCIALS!E4 -> 0.54340849 | F13: =FINANCIALS!F33/FINANCIALS!F4 -> 0.46341821 | G13: =FINANCIALS!G33/FINANCIALS!G4 -> 0.4139461 | H13: =FINANCIALS!H33/FINANCIALS!H4 -> 0.50896892 | I13: =FINANCIALS!I33/FINANCIALS!I4 -> 0.5073937 | J13: =FINANCIALS!J33/FINANCIALS!J4 -> 0.51238503 | K13: =FINANCIALS!K33/FINANCIALS!K4 -> 0.103654 | ... CE13: =FINANCIALS!CE33/FINANCIALS!CE4 -> 0.40989731
A14: 2.1.2 | B14: Property and Equipment/TA | C14: ≤ 5% | D14: =FINANCIALS!D34/FINANCIALS!D4 -> 0.24372898 | E14: =FINANCIALS!E34/FINANCIALS!E4 -> 0.012961994 | F14: =FINANCIALS!F34/FINANCIALS!F4 -> 0.032719268 | G14: =FINANCIALS!G34/FINANCIALS!G4 -> 0.045988515 | H14: =FINANCIALS!H34/FINANCIALS!H4 -> 0.036569608 | I14: =FINANCIALS!I34/FINANCIALS!I4 -> 0.036337778 | J14: =FINANCIALS!J34/FINANCIALS!J4 -> 0.033969513 | K14: =FINANCIALS!K34/FINANCIALS!K4 -> 0.061138872 | ... CE14: =FINANCIALS!CE34/FINANCIALS!CE4 -> 0.039523594
A16: 2.2 | B16: Earning Assets
A17: 2.2.1 | B17: Non-Govt Securities/Deposits | C17: ≤ 5% | D17: =FINANCIALS!D25/FINANCIALS!D5 -> 0.088380275 | E17: =FINANCIALS!E25/FINANCIALS!E5 -> 0.10024911 | F17: =FINANCIALS!F25/FINANCIALS!F5 -> 0.080961188 | G17: =FINANCIALS!G25/FINANCIALS!G5 -> 0 | H17: =FINANCIALS!H25/FINANCIALS!H5 -> 0 | I17: =FINANCIALS!I25/FINANCIALS!I5 -> 0 | J17: =FINANCIALS!J25/FINANCIALS!J5 -> 0.062080437 | K17: =FINANCIALS!K25/FINANCIALS!K5 -> 0.062080437 | ... CE17: =FINANCIALS!CE25/FINANCIALS!CE5 -> 0.19323059
A18: 2.2.2 | B18: Non-Govt Securities/Core Capital | C18: ≤ 40% | D18: =FINANCIALS!D25/FINANCIALS!D12 -> -1.9242132 | E18: =FINANCIALS!E25/FINANCIALS!E12 -> 1.0760625 | F18: =FINANCIALS!F25/FINANCIALS!F12 -> 0.41328557 | G18: =FINANCIALS!G25/FINANCIALS!G12 -> 0 | H18: =FINANCIALS!H25/FINANCIALS!H12 -> 0 | I18: =FINANCIALS!I25/FINANCIALS!I12 -> 0 | J18: =FINANCIALS!J25/FINANCIALS!J12 -> 0.34567324 | K18: =FINANCIALS!K25/FINANCIALS!K12 -> 0.47702803 | ... CE18: =FINANCIALS!CE25/FINANCIALS!CE12 -> 0.84671404
A19: 2.2.3 | B19: Gross Loans & advances /Total assets | D19: =FINANCIALS!D30/FINANCIALS!D4 -> 0.63617925 | E19: =FINANCIALS!E30/FINANCIALS!E4 -> 0.37667726 | F19: =FINANCIALS!F30/FINANCIALS!F4 -> 0.39436481 | G19: =FINANCIALS!G30/FINANCIALS!G4 -> 0.51948187 | H19: =FINANCIALS!H30/FINANCIALS!H4 -> 0.44903004 | I19: =FINANCIALS!I30/FINANCIALS!I4 -> 0.42710872 | J19: =FINANCIALS!J30/FINANCIALS!J4 -> 0.40305411 | K19: =FINANCIALS!K30/FINANCIALS!K4 -> 0.74404804 | ... CA19: =FINANCIALS!CA30/FINANCIALS!CA4 -> 0.37635767 | CB19: =FINANCIALS!CA30/FINANCIALS!CA4 -> 0.37635767 | CC19: =FINANCIALS!CB30/FINANCIALS!CB4 -> 0.3939811 | CD19: =FINANCIALS!CC30/FINANCIALS!CC4 -> 0.3972648 | CE19: =FINANCIALS!CD30/FINANCIALS!CD4 -> 0.38863524
A21: 3 | B21: FUNDING MIX | D21: Audited 2012
A22: 3.1 | B22: Total Deposits/Total Assets | D22: =D23+D24 -> 0.82055232 | E22: =E23+E24 -> 0.79715678 | F22: =F23+F24 -> 0.72149049 | G22: =G23+G24 -> 0.95700116 | H22: =H23+H24 -> 0.81878602 | I22: =I23+I24 -> 0.82447744 | J22: =J23+J24 -> 0.78793403 | K22: =K23+K24 -> 1.4181363 | ... CE22: =CE23+CE24 -> 0.65963999
A23: 3.1.1 | B23: BOSA Deposits/Total Assets | D23: =FINANCIALS!D6/FINANCIALS!D4 -> 0.7851132 | E23: =FINANCIALS!E6/FINANCIALS!E4 -> 0.76681906 | F23: =FINANCIALS!F6/FINANCIALS!F4 -> 0.69153369 | G23: =FINANCIALS!G6/FINANCIALS!G4 -> 0.91249654 | H23: =FINANCIALS!H6/FINANCIALS!H4 -> 0.78573945 | I23: =FINANCIALS!I6/FINANCIALS!I4 -> 0.78767021 | J23: =FINANCIALS!J6/FINANCIALS!J4 -> 0.74065003 | K23: =FINANCIALS!K6/FINANCIALS!K4 -> 1.3330338 | ... CE23: =FINANCIALS!CE6/FINANCIALS!CE4 -> 0.60710143
A24: 3.1.2 | B24: FOSA Deposits/Total Assets | D24: =FINANCIALS!D7/FINANCIALS!D4 -> 0.035439122 | E24: =FINANCIALS!E7/FINANCIALS!E4 -> 0.030337719 | F24: =FINANCIALS!F7/FINANCIALS!F4 -> 0.029956806 | G24: =FINANCIALS!G7/FINANCIALS!G4 -> 0.044504613 | H24: =FINANCIALS!H7/FINANCIALS!H4 -> 0.033046572 | I24: =FINANCIALS!I7/FINANCIALS!I4 -> 0.036807231 | J24: =FINANCIALS!J7/FINANCIALS!J4 -> 0.047284001 | K24: =FINANCIALS!K7/FINANCIALS!K4 -> 0.085102502 | ... CD24: =FINANCIALS!CD7/FINANCIALS!CD4 -> 0.052538557 | CE24: =FINANCIALS!CD7/FINANCIALS!CD4 -> 0.052538557
A25: 3.2 | B25: External Borrowing/Total assets | C25: ≤ 25% | D25: =FINANCIALS!D9/FINANCIALS!D4 -> 0 | E25: =FINANCIALS!E9/FINANCIALS!E4 -> 0.053176379 | F25: =FINANCIALS!F9/FINANCIALS!F4 -> 0.06723673 | G25: =FINANCIALS!G9/FINANCIALS!G4 -> 0.08709949 | H25: =FINANCIALS!H9/FINANCIALS!H4 -> 0.075149055 | I25: =FINANCIALS!I9/FINANCIALS!I4 -> 0.070745894 | J25: =FINANCIALS!J9/FINANCIALS!J4 -> 0.066135128 | K25: =FINANCIALS!K9/FINANCIALS!K4 -> 0.11903106 | ... CC25: =FINANCIALS!CC9/FINANCIALS!CC4 -> 0.14690899 | CD25: =FINANCIALS!CC9/FINANCIALS!CC4 -> 0.14690899 | CE25: =FINANCIALS!CD9/FINANCIALS!CD4 -> 0.14023274
A26: 3.3 | B26: Core capital/total assets | C26: ≥ 10% | D26: =FINANCIALS!D12/FINANCIALS!D4 -> -0.037688463 | E26: =FINANCIALS!E12/FINANCIALS!E4 -> 0.074265441 | F26: =FINANCIALS!F12/FINANCIALS!F4 -> 0.14133745 | G26: =FINANCIALS!G12/FINANCIALS!G4 -> 0.12036105 | H26: =FINANCIALS!H12/FINANCIALS!H4 -> 0.10357065 | I26: =FINANCIALS!I12/FINANCIALS!I4 -> 0.10226084 | J26: =FINANCIALS!J12/FINANCIALS!J4 -> 0.14218079 | K26: =FINANCIALS!K12/FINANCIALS!K4 -> 0.18543465 | ... CD26: =FINANCIALS!CD12/FINANCIALS!CD4 -> 0.17289325 | CE26: =FINANCIALS!CD12/FINANCIALS!CD4 -> 0.17289325
A28: 4 | B28: GROWTH RATIOS | D28: Audited 2012
A29: 4.1 | B29: Total Assets
A30: 4.2 | B30: Total Deposits
A31: 4.2.1 | B31: BOSA Deposits
A32: 4.2.2 | B32: FOSA Deposits
A33: 4.3 | B33: Total Loans & advances
A34: 4.4 | B34: Core capital
A35: 4.5 | B35: Turnover
A36: 4.6 | B36: Expenses
A38: 5 | B38: Efficiency Ratios | D38: Audited 2012
A39: 5.4 | B39: OpEx/Average Total Assets
A40: 5.4 | B40: Opex/Turnover
A41: 5.4 | B41: Avge yield on Net loans
A42: 5.4 | B42: Avge yield on Gross loans

Sheet FINANCIALS
C1: Eco Pillar Sacco Ltd Financial Performance & Projections | I1: =(S4-F4)/F4 -> 0.22264597
C2: Year | D2: Audited 2012 | E2: 2013 AUDITED | F2: Audited 2014 | G2: 42005 | H2: 42036 | I2: 42064 | J2: 42095 | K2: 42125 | L2: 42156 | M2: 42186 | N2: 42217 | O2: 42248 | P2: 42278 | Q2: 42309 | R2: 42339 | S2: Audited 2015 | T2: 42385 | U2: 42416 | V2: 42445 | W2: 42476 | X2: 42506 | Y2: 42537 | Z2: 42567 | AA2: 42598 | AB2: 42629 | AC2: 42659 | AD2: 42690 | AE2: 42720 | AF2: 42736 | AG2: 42767 | AH2: 42795 | AI2: 42826 | AJ2: 42856 | AK2: 42887 | AL2: 42917 | AM2: 42948 | AN2: 42979 | AO2: 43009 | AP2: 43040 | AQ2: 43070 | AR2: Audited 2017 | AS2: 43101 | AT2: 43132 | AU2: 43160 | AV2: 43191 | AW2: 43221 | AX2: 43252 | AY2: 43282 | AZ2: 43313 | BA2: 43344 | BB2: 43374 | BC2: 43405 | BD2: 43435 | BE2: Aud-18 | BF2: 43466 | BG2: 43497 | BH2: 43525 | BI2: 43556 | BJ2: 43586 | BK2: 43617 | BL2: 43647 | BM2: 43678 | BN2: 43709 | BO2: 43739 | BP2: 43770 | BQ2: 43800 | BR2: Audited 2019 | BS2: 43831 | BT2: 43862 | BU2: 43891 | BV2: 43922 | BW2: 43952 | BX2: 43983 | BY2: 44013 | BZ2: 44044 | CA2: 44075 | CB2: 44105 | CC2: 44136 | CD2: 44166 | CE2: Audited 2020 | CF2: Audited 2021
B3: 1 | C3: Membership
B4: 2 | C4: Total Assets | D4: =SFP!C32 -> 4.7538325e+08 | E4: =SFP!D32 -> 5.07679e+08 | F4: =SFP!E32 -> 601249270 | G4: =SFP!F32 -> 4.6413652e+08 | H4: =SFP!G32 -> 5.3794494e+08 | I4: =SFP!H32 -> 5.4137697e+08 | J4: =SFP!I32 -> 5.7912035e+08 | K4: =SFP!J32 -> 3.2176642e+08 | ... CF4: =SFP!CE32 -> 1255024242
B5: 3 | C5: Total Deposits | D5: =D6+D7+D8 -> 3.9007683e+08 | E5: =E6+E7+E8 -> 4.0469976e+08 | F5: =F6+F7+F8 -> 433795633 | G5: =G6+G7+G8 -> 4.4563976e+08 | H5: =H6+H7+H8 -> 4.4180358e+08 | I5: =I6+I7+I8 -> 4.4771511e+08 | J5: =J6+J7+J8 -> 4.5848036e+08 | K5: =K6+K7+K8 -> 4.5848036e+08 | ... CF5: =CF6+CF7+CF8 -> 824629723
B6: 3.1 | C6: Deposits-Members(BOSA) | D6: =SFP!C35 -> 3.7322967e+08 | E6: =SFP!D35 -> 3.8929794e+08 | F6: =SFP!E35 -> 415784125 | G6: =SFP!F35 -> 4.2352297e+08 | H6: =SFP!G35 -> 4.2268456e+08 | I6: =SFP!H35 -> 4.2642651e+08 | J6: =SFP!I35 -> 4.289255e+08 | K6: =SFP!J35 -> 4.289255e+08 | ... CF6: =SFP!CE35 -> 756058831
B7: 3.2 | C7: Deposits-Customers(FOSA) | D7: =SFP!C33 -> 16847165 | E7: =SFP!D33 -> 15401823 | F7: =SFP!E33 -> 18011508 | G7: =SFP!F33 -> 20656216 | H7: =SFP!G33 -> 17777237 | I7: =SFP!H33 -> 19926587 | J7: =SFP!I33 -> 27383127 | K7: =SFP!J33 -> 27383127 | ... CF7: =SFP!CE33 -> 61809136
C8: Short term | D8: =SFP!C34 -> 0 | E8: =SFP!D34 -> 0 | F8: =SFP!E34 -> 0 | G8: =SFP!F34 -> 1460576.8 | H8: =SFP!G34 -> 1341781.2 | I8: =SFP!H34 -> 1362011.3 | J8: =SFP!I34 -> 2171729.8 | K8: =SFP!J34 -> 2171729.8 | ... CF8: =SFP!CE34 -> 6761756
B9: 4 | C9: External Borrowing | D9: =SFP!C43 -> 0 | E9: =SFP!D43 -> 26996531 | F9: =SFP!E43 -> 40426035 | G9: =SFP!F43 -> 40426054 | H9: =SFP!G43 -> 40426054 | I9: =SFP!H43 -> 38300198 | J9: =SFP!I43 -> 38300198 | K9: =SFP!J43 -> 38300198 | ... CF9: =SFP!CE43 -> 157249999
B11: 5 | C11: Share capital and Reserves
B12: 5.1 | C12: Core Capital | D12: =D15-D27 -> -17916464 | E12: =E15-E27 -> 37703005 | F12: =F15-F27 -> 84979038 | G12: =G15-G27 -> 55863957 | H12: =H15-H27 -> 55715309 | I12: =I15-I27 -> 55361663 | J12: =J15-J27 -> 82339788 | K12: =K15-K27 -> 59666643 | ... CF12: =CF15-CF27 -> 2.1540187e+08
B13: 5.2 | C13: Institutional Capital | D13: =D15-D16 -> 7313333.3 | E13: =E15-E16 -> 39442006 | F13: =F15-F16 -> 53036819 | G13: =G15-G16 -> 21052568 | H13: =H15-H16 -> 20903920 | I13: =I15-I16 -> 20550274 | J13: =J15-J16 -> 47528399 | K13: =K15-K16 -> 24855254 | ... CF13: =CF15-CF16 -> 1.1929347e+08
B15: 5.3 | C15: Total Capital | D15: =SUM(D16:D20) -> 12431333 | E15: =SUM(E16:E20) -> 70214495 | F15: =SUM(F16:F20) -> 84979038 | G15: =SUM(G16:G20) -> 55863957 | H15: =SUM(H16:H20) -> 55715309 | I15: =SUM(I16:I20) -> 55361663 | J15: =SUM(J16:J20) -> 82339788 | K15: =SUM(K16:K20) -> 59666643 | ... CF15: =SUM(CF16:CF20) -> 2.154894e+08
B16: 5.3.1 | C16: Members Share Capital | D16: =SFP!C45 -> 5118000 | E16: =SFP!D45 -> 30772490 | F16: =SFP!E45 -> 31942219 | G16: =SFP!F45 -> 34811389 | H16: =SFP!G45 -> 34811389 | I16: =SFP!H45 -> 34811389 | J16: =SFP!I45 -> 34811389 | K16: =SFP!J45 -> 34811389 | ... CF16: =SFP!CE45 -> 96195922
B17: 5.3.2 | C17: Entrance Fees
B18: 5.3.3 | C18: Retained Earnings | D18: =SFP!C47 -> 0 | E18: =SFP!D47 -> 28882818 | F18: =SFP!E47 -> 37860904 | G18: =SFP!F47 -> 83273.8 | H18: =SFP!G47 -> -390773.93 | I18: =SFP!H47 -> -1112049.8 | J18: =SFP!I47 -> 22673145 | K18: =SFP!J47 -> 0 | ... CF18: =SFP!CE47 -> 87861275
B19: 5.3.5 | C19: Statutory Reserves | D19: =SFP!C51 -> 3504457.3 | E19: =SFP!D51 -> 6750311.1 | F19: =SFP!E51 -> 11367039 | G19: =SFP!F51 -> 8587761.9 | H19: =SFP!G51 -> 8587761.9 | I19: =SFP!H51 -> 8587761.9 | J19: =SFP!I51 -> 11367039 | K19: =SFP!J51 -> 11367039 | ... CF19: =SFP!CE51 -> 24867132
B20: 5.3.6 | C20: Capital Reserves | D20: =SFP!C52 -> 3808876 | E20: =SFP!D52 -> 3808876 | F20: =SFP!E52 -> 3808876 | G20: =SFP!F52 -> 12381532 | H20: =SFP!G52 -> 12706932 | I20: =SFP!H52 -> 13074562 | J20: =SFP!I52 -> 13488215 | K20: =SFP!J52 -> 13488215 | ... BR20: =SFP!BQ52 -> 6603936.6 | BS20: =SFP!BS52 -> 3650561.1 | BT20: =SFP!BT52 -> 3842639.4 | BU20: =SFP!BU52 -> 8247165.3 | BV20: =SFP!BV52 -> 4261349 | BW20: =SFP!BW52 -> 4829885.7 | BX20: =SFP!BX52 -> 0 | BY20: =SFP!BY52 -> 5642149.7 | BZ20: =SFP!BZ52 -> 9942076.6 | ... CF20: =SFP!CF52 -> 6565067.6
B21: 5.3.7 | C21: Supplementary Capital & reserves
B22: a | C22: Proposed Dividends | D22: =SFP!C53 -> 0 | E22: =SFP!D53 -> 0 | F22: =SFP!E53 -> 0 | G22: =SFP!F53 -> 0 | H22: =SFP!G53 -> 0 | I22: =SFP!H53 -> 0 | J22: =SFP!I53 -> 0 | K22: =SFP!J53 -> 0 | ... AB22: =SFP!AA53 -> 0
B23: b | C23: Risk Mgt Fund
B25: 6 | C25: Investments | D25: =SUM(D26:D28) -> 34475098 | E25: =SUM(E26:E28) -> 40570790 | F25: =SUM(F26:F28) -> 35120610 | G25: =SUM(G26:G28) -> 0 | H25: =SUM(H26:H28) -> 0 | I25: =SUM(I26:I28) -> 0 | J25: =SUM(J26:J28) -> 28462661 | K25: =SUM(K26:K28) -> 28462661 | ... CF25: =SUM(CF26:CF28) -> 149815748
B26: 6.1 | C26: Quoted - Mumias, Safaricom, Co-op Bank | D26: =SFP!C18 -> 4127300 | E26: =SFP!D18 -> 8059300 | F26: =SFP!E18 -> 35120610 | G26: =SFP!F18 -> 0 | H26: =SFP!G18 -> 0 | I26: =SFP!H18 -> 0 | J26: =SFP!I18 -> 28462661 | K26: =SFP!J18 -> 28462661 | ... CF26: =SFP!CE18 -> 149728220
B27: 6.2 | C27: Unquoted Shares - Co-op Bank, CIC, KNFC, CODIC | D27: =SFP!C17 -> 30347798 | E27: =SFP!D17 -> 32511490 | F27: =SFP!E17 -> 0 | G27: =SFP!F17 -> 0 | H27: =SFP!G17 -> 0 | I27: =SFP!H17 -> 0 | J27: =SFP!I17 -> 0 | K27: =SFP!J17 -> 0 | ... CF27: =SFP!CE17 -> 87528
B28: 6.3 | C28: Equity investments
B29: 7 | C29: Net Loans & Advances | D29: =D30-D31 -> -3050258.2 | E29: =E30-E31 -> -3902676.2 | F29: =F30-F31 -> -10016426 | G29: =G30-G31 -> -2004119.4 | H29: =H30-H31 -> -2320087 | I29: =I30-I31 -> -2004119.4 | J29: =J30-J31 -> -7996958.1 | K29: =K30-K31 -> -2004119.4 | ... CF29: =CF30-CF31 -> -36777969
B30: 7.1 | C30: Gross Loans & advances | D30: =SFP!C19 -> 3.0242896e+08 | E30: =SFP!D19 -> 1.9123114e+08 | F30: =SFP!E19 -> 237111555 | G30: =SFP!F19 -> 2.4111051e+08 | H30: =SFP!G19 -> 2.4155344e+08 | I30: =SFP!H19 -> 2.3122683e+08 | J30: =SFP!I19 -> 2.3341683e+08 | K30: =SFP!J19 -> 2.3940967e+08 | ... CF30: =SFP!CE19 -> 493093543
B31: 7.2 | C31: Allowance for loan losses | D31: =SFP!C20 -> 305479221 | E31: =SFP!D20 -> 1.9513381e+08 | F31: =SFP!E20 -> 247127981 | G31: =SFP!F20 -> 2.4311463e+08 | H31: =SFP!G20 -> 2.4387353e+08 | I31: =SFP!H20 -> 2.3323095e+08 | J31: =SFP!I20 -> 2.4141379e+08 | K31: =SFP!J20 -> 2.4141379e+08 | ... CF31: =SFP!CE20 -> 529871512
B33: 8 | C33: Non-Earning Assets | D33: =SFP!C13+SFP!C22+SFP!C26 -> 1.3847919e+08 | E33: =SFP!D13+SFP!D22+SFP!D26 -> 2.7587708e+08 | F33: =SFP!E13+SFP!E22+SFP!E26 -> 278629863 | G33: =SFP!F13+SFP!F22+SFP!F26 -> 1.921275e+08 | H33: =SFP!G13+SFP!G22+SFP!G26 -> 2.7379726e+08 | I33: =SFP!H13+SFP!H22+SFP!H26 -> 2.7469126e+08 | J33: =SFP!I13+SFP!I22+SFP!I26 -> 2.9673259e+08 | K33: =SFP!J13+SFP!J22+SFP!J26 -> 33352376 | ... CF33: =SFP!CE13+SFP!CE22+SFP!CE26 -> 466352002
B34: 8.1 | C34: Property and Equipment | D34: =SFP!C28 -> 1.1586468e+08 | E34: =SFP!D28 -> 6580532 | F34: =SFP!E28 -> 19672436 | G34: =SFP!F28 -> 21344950 | H34: =SFP!G28 -> 19672436 | I34: =SFP!H28 -> 19672436 | J34: =SFP!I28 -> 19672436 | K34: =SFP!J28 -> 19672436 | ... CF34: =SFP!CE28 -> 51204736
B36: 9 | C36: Turnover | D36: =+D37+D38+D39 -> 45324711 | E36: =+E37+E38+E39 -> 45274899 | F36: =+F37+F38+F39 -> 67694492 | G36: =+G37+G38+G39 -> 6107686.8 | H36: =+H37+H38+H39 -> 10515264 | I36: =+I37+I38+I39 -> 14520010 | J36: =+J37+J38+J39 -> 19445843 | K36: =+K37+K38+K39 -> 28051245 | ... CF36: =+CF37+CF38+CF39 -> 159470389
B37: 9.1 | C37: Loan Interest | D37: =SCI!C12 -> 44346813 | E37: =SCI!D12 -> 43848893 | F37: =SCI!E12 -> 65095569 | G37: =SCI!F12 -> 5293412.2 | H37: =SCI!G12 -> 8814618.7 | I37: =SCI!H12 -> 11941258 | J37: =SCI!I12 -> 15976794 | K37: =SCI!J12 -> 22773179 | ... CF37: =SCI!CE12 -> 123851259
B38: 9.2 | C38: Income from investments | D38: =SCI!C14 -> 337736.05 | E38: =SCI!D14 -> 1027520.1 | F38: =SCI!E14 -> 1328210 | G38: =SCI!F14 -> 319057.5 | H38: =SCI!G14 -> 625742 | I38: =SCI!H14 -> 945266 | J38: =SCI!I14 -> 1251725 | K38: =SCI!J14 -> 2054943.6 | ... CF38: =SCI!CE14 -> 35619130
B39: 9.3 | C39: Fees & Commissions | D39: =SCI!C13 -> 640162.06 | E39: =SCI!D13 -> 398485.5 | F39: =SCI!E13 -> 1270713 | G39: =SCI!F13 -> 495217.05 | H39: =SCI!G13 -> 1074903.5 | I39: =SCI!H13 -> 1633485.9 | J39: =SCI!I13 -> 2217323.9 | K39: =SCI!J13 -> 3223122.1 | ... CF39: =SCI!CE13 -> 0
B41: 10 | C41: Fianacial and Operating costs | D41: =+D42+D43+D44+D45 -> 27645413 | E41: =+E42+E43+E44+E45 -> 33603720 | F41: =+F42+F43+F44+F45 -> 55181123 | G41: =+G42+G43+G44+G45 -> 4020293.5 | H41: =+H42+H43+H44+H45 -> 8585951.1 | I41: =+I42+I43+I44+I45 -> 11831937 | J41: =+J42+J43+J44+J45 -> 26636643 | K41: =+K42+K43+K44+K45 -> 30088006 | ... CF41: =+CF42+CF43+CF44+CF45 -> 131976593
B42: 10.1 | C42: Interest expense on deposits | D42: =SCI!C20 -> 5851152.5 | E42: =SCI!D20 -> 6070496.4 | F42: =SCI!E20 -> 24947048 | G42: =SCI!F20 -> 0 | H42: =SCI!G20 -> 0 | I42: =SCI!H20 -> 0 | J42: =SCI!I20 -> 8578510.1 | K42: =SCI!J20 -> 10771280 | ... CF42: =SCI!CE20 -> 47000000
B43: 10.2 | C43: Dividend expense on share capital | D43: =SCI!C22 -> 0 | E43: =SCI!D22 -> 0 | F43: =SCI!E22 -> 0 | G43: =SCI!F22 -> 0 | H43: =SCI!G22 -> 0 | I43: =SCI!H22 -> 0 | J43: =SCI!I22 -> 0 | K43: =SCI!J22 -> 0 | ... AB43: =SCI!AA22 -> 0
B44: 10.3 | C44: Interest expense on borrowed funds | D44: =SCI!C21 -> 7064336.2 | E44: =SCI!D21 -> 3750294 | F44: =SCI!E21 -> 1335000 | G44: =SCI!F21 -> 1335000 | H44: =SCI!G21 -> 1335000 | I44: =SCI!H21 -> 1335000 | J44: =SCI!I21 -> 1335000 | K44: =SCI!J21 -> 1335000 | ... CF44: =SCI!CE21 -> 10402628
B45: 10.4 | C45: Opperating expenses | D45: =SCI!C30 -> 14729924 | E45: =SCI!D30 -> 23782929 | F45: =SCI!E30 -> 28899075 | G45: =SCI!F30 -> 2685293.5 | H45: =SCI!G30 -> 7250951.1 | I45: =SCI!H30 -> 10496937 | J45: =SCI!I30 -> 16723133 | K45: =SCI!J30 -> 17981726 | ... CF45: =SCI!CE30 -> 74573965
BG63: ;/l | BH63: :"/;//

Sheet FORM 4
O2: RISK CLASSIFICATION OF ASSETS AND PROVISIONING
B3: RISK CLASSIFICATION OF ASSETS AND PROVISIONING | H3: RISK CLASSIFICATION OF ASSETS AND PROVISIONING | O3: SACCO SOCIETY CS NUMBER | S3: 2690
B4: SACCO SOCIETY CS NUMBER | F4: 2690 | H4: SACCO SOCIETY CS NUMBER | L4: 2690 | O4: FINANCIAL YEAR | S4: 2016
B5: FINANCIAL YEAR | F5: 2016 | H5: FINANCIAL YEAR | L5: 2016 | O5: START DATE: | S5: 42370
B6: START DATE: | F6: 42370 | H6: START DATE: | L6: 42370 | O6: END DATE: | S6: 30/6/2018
B7: END DATE: | F7: 31/3/2016 | H7: END DATE: | L7: 30/6/2016 | O7: PORTFOLIO AGEING REPORT
B8: PORTFOLIO AGEING REPORT | H8: PORTFOLIO AGEING REPORT | P8: A | Q8: B | R8: C | S8: D
C9: A | D9: B | E9: C | F9: D | I9: A | J9: B | K9: C | L9: D | O9: CLASSIFICATION | P9: NO. OF A/Cs | Q9: OUTSTANDING LOAN PORTFOLIO(Kshs) | R9: REQUIRED PROVISION | S9: REQUIRED PROVISION AMOUNT(Kshs)
B10: CLASSIFICATION | C10: NO. OF A/Cs | D10: OUTSTANDING LOAN PORTFOLIO(Kshs) | E10: REQUIRED PROVISION | F10: REQUIRED PROVISION AMOUNT(Kshs) | H10: CLASSIFICATION | I10: NO. OF A/Cs | J10: OUTSTANDING LOAN PORTFOLIO(Kshs) | K10: REQUIRED PROVISION | L10: REQUIRED PROVISION AMOUNT(Kshs) | O10: Performing | P10: 3222 | Q10: 2.9442779e+08 | R10: 0.01 | S10: =Q10*R10 -> 2944277.9
B11: Performing | D11: 2.4069847e+08 | E11: 0.01 | F11: =D11*E11 -> 2406984.7 | H11: Performing | J11: 2.0883553e+08 | K11: 0.01 | L11: =J11*K11 -> 2088355.3 | O11: Watch | P11: 404 | Q11: 27566931 | R11: 0.05 | S11: =Q11*R11 -> 1378346.6
B12: Watch | D12: 6121965.7 | E12: 0.05 | F12: =D12*E12 -> 306098.29 | H12: Watch | J12: 34350561 | K12: 0.05 | L12: =J12*K12 -> 1717528 | O12: Substandard | P12: 63 | Q12: 2635490 | R12: 0.25 | S12: =Q12*R12 -> 658872.49
B13: Substandard | D13: 13684297 | E13: 0.25 | F13: =D13*E13 -> 3421074.3 | H13: Substandard | J13: 6042444.8 | K13: 0.25 | L13: =J13*K13 -> 1510611.2 | O13: Doubtful | P13: 131 | Q13: 7050782 | R13: 0.5 | S13: =Q13*R13 -> 3525391
B14: Doubtful | D14: 870151 | E14: 0.5 | F14: =D14*E14 -> 435075.5 | H14: Doubtful | J14: 4869289.2 | K14: 0.5 | L14: =J14*K14 -> 2434644.6 | O14: Loss | P14: 118 | Q14: 4250500.3 | R14: 1 | S14: =Q14*R14 -> 4250500.3
B15: Loss | D15: 65146.7 | E15: 1 | F15: =D15*E15 -> 65146.7 | H15: Loss | J15: 385146.7 | K15: 1 | L15: =J15*K15 -> 385146.7 | O15: subtotal | P15: =SUM(P10:P14) -> 3938 | Q15: =SUM(Q10:Q14) -> 3.3593149e+08 | S15: =SUM(S10:S14) -> 12757388
B16: subtotal | C16: =SUM(C11:C15) -> 0 | D16: =SUM(D11:D15) -> 2.6144004e+08 | F16: =SUM(F11:F15) -> 6634379.5 | H16: subtotal | I16: =SUM(I11:I15) -> 0 | J16: =SUM(J11:J15) -> 2.5448297e+08 | L16: =SUM(L11:L15) -> 8136285.8 | O16: Reschedule/Renegotiated loans
B17: Reschedule/Renegotiated loans | H17: Reschedule/Renegotiated loans | O17: Performing | P17: 0 | R17: 0.01 | S17: =Q17*R17 -> 0
B18: Performing | C18: 0 | E18: 0.01 | F18: =D18*E18 -> 0 | H18: Performing | I18: 0 | K18: 0.01 | L18: =J18*K18 -> 0 | O18: Watch | P18: 0 | R18: 0.05 | S18: =Q18*R18 -> 0
B19: Watch | C19: 0 | E19: 0.05 | F19: =D19*E19 -> 0 | H19: Watch | I19: 0 | K19: 0.05 | L19: =J19*K19 -> 0 | O19: Substandard | P19: 0 | Q19: 0 | R19: 0.25 | S19: =Q19*R19 -> 0
B20: Substandard | C20: 0 | D20: 0 | E20: 0.25 | F20: =D20*E20 -> 0 | H20: Substandard | I20: 0 | J20: 0 | K20: 0.25 | L20: =J20*K20 -> 0 | O20: Doubtful | P20: 0 | Q20: 0 | R20: 0.5 | S20: =Q20*R20 -> 0
B21: Doubtful | C21: 0 | D21: 0 | E21: 0.5 | F21: =D21*E21 -> 0 | H21: Doubtful | I21: 0 | J21: 0 | K21: 0.5 | L21: =J21*K21 -> 0 | O21: Loss | P21: 0 | Q21: 0 | R21: 1 | S21: =Q21*R21 -> 0
B22: Loss | C22: 0 | D22: 0 | E22: 1 | F22: =D22*E22 -> 0 | H22: Loss | I22: 0 | J22: 0 | K22: 1 | L22: =J22*K22 -> 0 | O22: subtotal | P22: =SUM(P16:P21) -> 0 | Q22: =SUM(Q16:Q21) -> 0 | S22: =SUM(S16:S21) -> 0
B23: subtotal | C23: =SUM(C17:C22) -> 0 | D23: =SUM(D17:D22) -> 0 | F23: =SUM(F17:F22) -> 0 | H23: subtotal | I23: =SUM(I17:I22) -> 0 | J23: =SUM(J17:J22) -> 0 | L23: =SUM(L17:L22) -> 0 | O23: GRAND TOTAL | P23: =P15+P22 -> 3938 | Q23: =Q15+Q22 -> 3.3593149e+08 | S23: =S15+S22 -> 12757388
B24: GRAND TOTAL | C24: =C16+C23 -> 0 | D24: =D16+D23 -> 2.6144004e+08 | F24: =F16+F23 -> 6634379.5 | H24: GRAND TOTAL | I24: =I16+I23 -> 0 | J24: =J16+J23 -> 2.5448297e+08 | L24: =L16+L23 -> 8136285.8
Q25: =Q12+Q13+Q14 -> 13936772
D26: =D13+D14+D15 -> 14619595 | J26: =J13+J14+J15 -> 11296881 | P26: NPL | Q26: =Q25/Q23 -> 0.041486948
C27: NPL | D27: =D26/D24 -> 0.055919495 | I27: NPL | J27: =J26/J24 -> 0.0443915
P28: 42795
I29: 42795 | O29: RISK CLASSIFICATION OF ASSETS AND PROVISIONING
B30: RISK CLASSIFICATION OF ASSETS AND PROVISIONING | H30: RISK CLASSIFICATION OF ASSETS AND PROVISIONING | O30: SACCO SOCIETY CS NUMBER | S30: 2690
B31: SACCO SOCIETY CS NUMBER | F31: 2690 | H31: SACCO SOCIETY CS NUMBER | L31: 2690 | O31: FINANCIAL YEAR | S31: 2017
B32: FINANCIAL YEAR | F32: 2016 | H32: FINANCIAL YEAR | L32: 2017 | O32: START DATE: | S32: 43101
B33: START DATE: | F33: 1/1/2016 | H33: START DATE: | L33: 1/1/2017 | O33: END DATE: | S33: 30/3/2018
B34: END DATE: | F34: 30/9/2016 | H34: END DATE: | L34: 30/3/2017 | O34: PORTFOLIO AGEING REPORT
B35: PORTFOLIO AGEING REPORT | H35: PORTFOLIO AGEING REPORT | P35: A | Q35: B | R35: C | S35: D
C36: A | D36: B | E36: C | F36: D | I36: A | J36: B | K36: C | L36: D | O36: CLASSIFICATION | P36: NO. OF A/Cs | Q36: OUTSTANDING LOAN PORTFOLIO(Kshs) | R36: REQUIRED PROVISION | S36: REQUIRED PROVISION AMOUNT(Kshs)
B37: CLASSIFICATION | C37: NO. OF A/Cs | D37: OUTSTANDING LOAN PORTFOLIO(Kshs) | E37: REQUIRED PROVISION | F37: REQUIRED PROVISION AMOUNT(Kshs) | H37: CLASSIFICATION | I37: NO. OF A/Cs | J37: OUTSTANDING LOAN PORTFOLIO(Kshs) | K37: REQUIRED PROVISION | L37: REQUIRED PROVISION AMOUNT(Kshs) | O37: Performing | P37: 2650 | Q37: 2.6427151e+08 | R37: 0.01 | S37: =Q37*R37 -> 2642715.1
B38: Performing | C38: 2730 | D38: 2.4053309e+08 | E38: 0.01 | F38: =D38*E38 -> 2405330.9 | H38: Performing | I38: 2650 | J38: 2.6427151e+08 | K38: 0.01 | L38: =J38*K38 -> 2642715.1 | O38: Watch | P38: 78 | Q38: 10262123 | R38: 0.05 | S38: =Q38*R38 -> 513106.17
B39: Watch | C39: 145 | D39: 7306925.5 | E39: 0.05 | F39: =D39*E39 -> 365346.27 | H39: Watch | I39: 78 | J39: 10262123 | K39: 0.05 | L39: =J39*K39 -> 513106.17 | O39: Substandard | P39: 58 | Q39: 6806907.7 | R39: 0.25 | S39: =Q39*R39 -> 1701726.9
B40: Substandard | C40: 113 | D40: 7113724.1 | E40: 0.25 | F40: =D40*E40 -> 1778431 | H40: Substandard | I40: 58 | J40: 6806907.7 | K40: 0.25 | L40: =J40*K40 -> 1701726.9 | N40: =SUM(J40+J41+J42) -> 18697147 | O40: Doubtful | P40: 108 | Q40: 9646069.6 | R40: 0.5 | S40: =Q40*R40 -> 4823034.8
B41: Doubtful | C41: 175 | D41: 5802149.2 | E41: 0.5 | F41: =D41*E41 -> 2901074.6 | H41: Doubtful | I41: 108 | J41: 9646069.6 | K41: 0.5 | L41: =J41*K41 -> 4823034.8 | N41: =N40/J43 -> 0.063762568 | O41: Loss | P41: 122 | Q41: 2244170.1 | R41: 1 | S41: =Q41*R41 -> 2244170.1
B42: Loss | C42: 94 | D42: 4061903.2 | E42: 1 | F42: =D42*E42 -> 4061903.2 | H42: Loss | I42: 122 | J42: 2244170.1 | K42: 1 | L42: =J42*K42 -> 2244170.1 | O42: subtotal | Q42: =SUM(Q37:Q41) -> 2.9323078e+08 | S42: =SUM(S37:S41) -> 11924753
B43: subtotal | C43: =SUM(C38:C42) -> 3257 | D43: =SUM(D38:D42) -> 2.6481779e+08 | F43: =SUM(F38:F42) -> 11512086 | H43: subtotal | J43: =SUM(J38:J42) -> 2.9323078e+08 | L43: =SUM(L38:L42) -> 11924753 | O43: Reschedule/Renegotiated loans
B44: Reschedule/Renegotiated loans | H44: Reschedule/Renegotiated loans | O44: Performing | P44: 0 | R44: 0.01 | S44: =Q44*R44 -> 0
B45: Performing | C45: 0 | E45: 0.01 | F45: =D45*E45 -> 0 | H45: Performing | I45: 0 | K45: 0.01 | L45: =J45*K45 -> 0 | O45: Watch | P45: 0 | R45: 0.05 | S45: =Q45*R45 -> 0
B46: Watch | C46: 0 | E46: 0.05 | F46: =D46*E46 -> 0 | H46: Watch | I46: 0 | K46: 0.05 | L46: =J46*K46 -> 0 | O46: Substandard | P46: 0 | Q46: 0 | R46: 0.25 | S46: =Q46*R46 -> 0
B47: Substandard | C47: 0 | D47: 0 | E47: 0.25 | F47: =D47*E47 -> 0 | H47: Substandard | I47: 0 | J47: 0 | K47: 0.25 | L47: =J47*K47 -> 0 | O47: Doubtful | P47: 0 | Q47: 0 | R47: 0.5 | S47: =Q47*R47 -> 0
B48: Doubtful | C48: 0 | D48: 0 | E48: 0.5 | F48: =D48*E48 -> 0 | H48: Doubtful | I48: 0 | J48: 0 | K48: 0.5 | L48: =J48*K48 -> 0 | O48: Loss | P48: 0 | Q48: 0 | R48: 1 | S48: =Q48*R48 -> 0
B49: Loss | C49: 0 | D49: 0 | E49: 1 | F49: =D49*E49 -> 0 | H49: Loss | I49: 0 | J49: 0 | K49: 1 | L49: =J49*K49 -> 0 | O49: subtotal | P49: =SUM(P43:P48) -> 0 | Q49: =SUM(Q43:Q48) -> 0 | S49: =SUM(S43:S48) -> 0
B50: subtotal | C50: =SUM(C44:C49) -> 0 | D50: =SUM(D44:D49) -> 0 | F50: =SUM(F44:F49) -> 0 | H50: subtotal | I50: =SUM(I44:I49) -> 0 | J50: =SUM(J44:J49) -> 0 | L50: =SUM(L44:L49) -> 0 | O50: GRAND TOTAL | P50: =P42+P49 -> 0 | Q50: =Q42+Q49 -> 2.9323078e+08 | S50: =S42+S49 -> 11924753
B51: GRAND TOTAL | C51: =C43+C50 -> 3257 | D51: =D43+D50 -> 2.6481779e+08 | F51: =F43+F50 -> 11512086 | H51: GRAND TOTAL | I51: =I43+I50 -> 0 | J51: =J43+J50 -> 2.9323078e+08 | L51: =L43+L50 -> 11924753
D53: =D40+D41+D42 -> 16977777
C54: NPL | D54: =D53/D51 -> 0.064111164 | P54: 42979
C55: 42887 | I55: 42979 | O55: RISK CLASSIFICATION OF ASSETS AND PROVISIONING
B56: RISK CLASSIFICATION OF ASSETS AND PROVISIONING | H56: RISK CLASSIFICATION OF ASSETS AND PROVISIONING | O56: SACCO SOCIETY CS NUMBER | S56: 2690
B57: SACCO SOCIETY CS NUMBER | F57: 2690 | H57: SACCO SOCIETY CS NUMBER | L57: 2690 | O57: FINANCIAL YEAR | S57: 2017
B58: FINANCIAL YEAR | F58: 2016 | H58: FINANCIAL YEAR | L58: 2017 | O58: START DATE: | S58: 1/1/2017
B59: START DATE: | F59: 1/1/2016 | H59: START DATE: | L59: 1/1/2017 | O59: END DATE: | S59: 30/6/2017
B60: END DATE: | F60: 30/9/2016 | H60: END DATE: | L60: 30/6/2017 | O60: PORTFOLIO AGEING REPORT
B61: PORTFOLIO AGEING REPORT | H61: PORTFOLIO AGEING REPORT | P61: A | Q61: B | R61: C | S61: D
C62: A | D62: B | E62: C | F62: D | I62: A | J62: B | K62: C | L62: D | O62: CLASSIFICATION | P62: NO. OF A/Cs | Q62: OUTSTANDING LOAN PORTFOLIO(Kshs) | R62: REQUIRED PROVISION | S62: REQUIRED PROVISION AMOUNT(Kshs)
B63: CLASSIFICATION | C63: NO. OF A/Cs | D63: OUTSTANDING LOAN PORTFOLIO(Kshs) | E63: REQUIRED PROVISION | F63: REQUIRED PROVISION AMOUNT(Kshs) | H63: CLASSIFICATION | I63: NO. OF A/Cs | J63: OUTSTANDING LOAN PORTFOLIO(Kshs) | K63: REQUIRED PROVISION | L63: REQUIRED PROVISION AMOUNT(Kshs) | O63: Performing | P63: 2830 | Q63: 2.6692221e+08 | R63: 0.01 | S63: =Q63*R63 -> 2669222.1
B64: Performing | E64: 0.01 | F64: =D64*E64 -> 0 | H64: Performing | I64: 2830 | J64: 2.6692221e+08 | K64: 0.01 | L64: =J64*K64 -> 2669222.1 | O64: Watch | P64: 136 | Q64: 12218659 | R64: 0.05 | S64: =Q64*R64 -> 610932.97
B65: Watch | E65: 0.05 | F65: =D65*E65 -> 0 | H65: Watch | I65: 136 | J65: 12218659 | K65: 0.05 | L65: =J65*K65 -> 610932.97 | O65: Substandard | P65: 70 | Q65: 8624095.5 | R65: 0.25 | S65: =Q65*R65 -> 2156023.9
B66: Substandard | E66: 0.25 | F66: =D66*E66 -> 0 | H66: Substandard | I66: 70 | J66: 8624095.5 | K66: 0.25 | L66: =J66*K66 -> 2156023.9 | M66: =SUM(J66+J67+J68) -> 19242868 | O66: Doubtful | P66: 43 | Q66: 4626561.2 | R66: 0.5 | S66: =Q66*R66 -> 2313280.6
B67: Doubtful | E67: 0.5 | F67: =D67*E67 -> 0 | H67: Doubtful | I67: 43 | J67: 4626561.2 | K67: 0.5 | L67: =J67*K67 -> 2313280.6 | M67: =M66/J69 -> 0.064490337 | O67: Loss | P67: 96 | Q67: 5992211.4 | R67: 1 | S67: =Q67*R67 -> 5992211.4
B68: Loss | E68: 1 | F68: =D68*E68 -> 0 | H68: Loss | I68: 96 | J68: 5992211.4 | K68: 1 | L68: =J68*K68 -> 5992211.4 | O68: subtotal | Q68: =SUM(Q63:Q67) -> 2.9838374e+08 | S68: =SUM(S63:S67) -> 13741671
B69: subtotal | D69: =SUM(D64:D68) -> 0 | F69: =SUM(F64:F68) -> 0 | H69: subtotal | J69: =SUM(J64:J68) -> 2.9838374e+08 | L69: =SUM(L64:L68) -> 13741671 | O69: Reschedule/Renegotiated loans
B70: Reschedule/Renegotiated loans | H70: Reschedule/Renegotiated loans | O70: Performing | P70: 0 | R70: 0.01 | S70: =Q70*R70 -> 0
B71: Performing | C71: 0 | E71: 0.01 | F71: =D71*E71 -> 0 | H71: Performing | I71: 0 | K71: 0.01 | L71: =J71*K71 -> 0 | O71: Watch | P71: 0 | R71: 0.05 | S71: =Q71*R71 -> 0
B72: Watch | C72: 0 | E72: 0.05 | F72: =D72*E72 -> 0 | H72: Watch | I72: 0 | K72: 0.05 | L72: =J72*K72 -> 0 | O72: Substandard | P72: 0 | Q72: 0 | R72: 0.25 | S72: =Q72*R72 -> 0
B73: Substandard | C73: 0 | D73: 0 | E73: 0.25 | F73: =D73*E73 -> 0 | H73: Substandard | I73: 0 | J73: 0 | K73: 0.25 | L73: =J73*K73 -> 0 | O73: Doubtful | P73: 0 | Q73: 0 | R73: 0.5 | S73: =Q73*R73 -> 0
B74: Doubtful | C74: 0 | D74: 0 | E74: 0.5 | F74: =D74*E74 -> 0 | H74: Doubtful | I74: 0 | J74: 0 | K74: 0.5 | L74: =J74*K74 -> 0 | O74: Loss | P74: 0 | Q74: 0 | R74: 1 | S74: =Q74*R74 -> 0
B75: Loss | C75: 0 | D75: 0 | E75: 1 | F75: =D75*E75 -> 0 | H75: Loss | I75: 0 | J75: 0 | K75: 1 | L75: =J75*K75 -> 0 | O75: subtotal | P75: =SUM(P69:P74) -> 0 | Q75: =SUM(Q69:Q74) -> 0 | S75: =SUM(S69:S74) -> 0
B76: subtotal | C76: =SUM(C70:C75) -> 0 | D76: =SUM(D70:D75) -> 0 | F76: =SUM(F70:F75) -> 0 | H76: subtotal | I76: =SUM(I70:I75) -> 0 | J76: =SUM(J70:J75) -> 0 | L76: =SUM(L70:L75) -> 0 | O76: GRAND TOTAL | P76: =P68+P75 -> 0 | Q76: =Q68+Q75 -> 2.9838374e+08 | S76: =S68+S75 -> 13741671
B77: GRAND TOTAL | C77: =C69+C76 -> 0 | D77: =D69+D76 -> 0 | F77: =F69+F76 -> 0 | H77: GRAND TOTAL | I77: =I69+I76 -> 0 | J77: =J69+J76 -> 2.9838374e+08 | L77: =L69+L76 -> 13741671
P79: 43070
I80: 43070 | P80: A | Q80: B | R80: C | S80: D
I81: A | J81: B | K81: C | L81: D | O81: CLASSIFICATION | P81: NO. OF A/Cs | Q81: OUTSTANDING LOAN PORTFOLIO(Kshs) | R81: REQUIRED PROVISION | S81: REQUIRED PROVISION AMOUNT(Kshs)
H82: CLASSIFICATION | I82: NO. OF A/Cs | J82: OUTSTANDING LOAN PORTFOLIO(Kshs) | K82: REQUIRED PROVISION | L82: REQUIRED PROVISION AMOUNT(Kshs) | O82: Performing | P82: 3034 | Q82: 2.9959183e+08 | R82: 0.01 | S82: =Q82*R82 -> 2995918.3
H83: Performing | I83: 3034 | J83: 2.9959183e+08 | K83: 0.01 | L83: =J83*K83 -> 2995918.3 | O83: Watch | P83: 113 | Q83: 12056692 | R83: 0.05 | S83: =Q83*R83 -> 602834.61
H84: Watch | I84: 113 | J84: 12056692 | K84: 0.05 | L84: =J84*K84 -> 602834.61 | O84: Substandard | P84: 96 | Q84: 10737465 | R84: 0.25 | S84: =Q84*R84 -> 2684366.2
H85: Substandard | I85: 96 | J85: 10737465 | K85: 0.25 | L85: =J85*K85 -> 2684366.2 | O85: Doubtful | P85: 302 | Q85: 8396120.2 | R85: 0.5 | S85: =Q85*R85 -> 4198060.1
H86: Doubtful | I86: 302 | J86: 8396120.2 | K86: 0.5 | L86: =J86*K86 -> 4198060.1 | O86: Loss | P86: 68 | Q86: 3307684.3 | R86: 1 | S86: =Q86*R86 -> 3307684.3
H87: Loss | I87: 68 | J87: 3307684.3 | K87: 1 | L87: =J87*K87 -> 3307684.3 | N87: =J85+J86+J87 -> 22441269 | O87: subtotal | P87: =SUM(P82:P86) -> 3613 | Q87: =SUM(Q82:Q86) -> 3.3408979e+08 | S87: =SUM(S82:S86) -> 13788864
H88: subtotal | I88: =SUM(I83:I87) -> 3613 | J88: =SUM(J83:J87) -> 3.3408979e+08 | L88: =SUM(L83:L87) -> 13788864 | N88: =N87/J88 -> 0.06717137 | O88: Reschedule/Renegotiated loans
H89: Reschedule/Renegotiated loans | O89: Performing | P89: 0 | R89: 0.01 | S89: =Q89*R89 -> 0
H90: Performing | I90: 0 | K90: 0.01 | L90: =J90*K90 -> 0 | O90: Watch | P90: 0 | R90: 0.05 | S90: =Q90*R90 -> 0
H91: Watch | I91: 0 | K91: 0.05 | L91: =J91*K91 -> 0 | O91: Substandard | P91: 0 | R91: 0.25 | S91: =Q91*R91 -> 0
H92: Substandard | I92: 0 | K92: 0.25 | L92: =J92*K92 -> 0 | O92: Doubtful | P92: 0 | R92: 0.5 | S92: =Q92*R92 -> 0
H93: Doubtful | I93: 0 | K93: 0.5 | L93: =J93*K93 -> 0 | O93: Loss | P93: 0 | R93: 1 | S93: =Q93*R93 -> 0
H94: Loss | I94: 0 | K94: 1 | L94: =J94*K94 -> 0 | O94: subtotal | P94: =SUM(P88:P93) -> 0 | Q94: =SUM(Q88:Q93) -> 0 | S94: =SUM(S88:S93) -> 0
H95: subtotal | I95: =SUM(I89:I94) -> 0 | J95: =SUM(J89:J94) -> 0 | L95: =SUM(L89:L94) -> 0 | O95: GRAND TOTAL | P95: =P87+P94 -> 3613 | Q95: =Q87+Q94 -> 3.3408979e+08 | S95: =S87+S94 -> 13788864
H96: GRAND TOTAL | I96: =I88+I95 -> 3613 | J96: =J88+J95 -> 3.3408979e+08 | L96: =L88+L95 -> 13788864
O98: CLASSIFICATION | P98: NO. OF A/Cs | Q98: OUTSTANDING LOAN PORTFOLIO(Kshs) | R98: REQUIRED PROVISION | S98: REQUIRED PROVISION AMOUNT(Kshs)
O99: Performing | P99: 3185 | Q99: 2.943548e+08 | R99: 0.01 | S99: =Q99*R99 -> 2943548
O100: Watch | P100: 178 | Q100: 9221046.2 | R100: 0.05 | S100: =Q100*R100 -> 461052.31
O101: Substandard | P101: 169 | Q101: 7447461.9 | R101: 0.25 | S101: =Q101*R101 -> 1861865.5
O102: Doubtful | P102: 117 | Q102: 1356716.6 | R102: 0.5 | S102: =Q102*R102 -> 678358.31
O103: Loss | P103: 148 | Q103: 6068407.3 | R103: 1 | S103: =Q103*R103 -> 6068407.3
Q104: =SUM(Q99:Q103) -> 3.1844843e+08 | S104: =SUM(S99:S103) -> 12013231
...

Sheet FORM 3
B1: FORM 3 SASRA2/003
B2: STATEMENT OF DEPOSIT RETURN
B3: SACCO SOCIETY CS NUMBER | E3: 2690
B4: FINANCIAL YEAR | E4: 2014
B5: START DATE: | E5: 1/1/2014
B6: END DATE: | E6: 31/12/2014
A8: NO. | B8: RANGE | C8: TYPE OF DEPOSIT | D8: NO. OF A/Cs | E8: AMOUNT IN Kshs'000'
A9: 1 | B9: less than 50,000 | C9: non withdraw-able | D9: 594 | E9: 7783.6
C10: savings | D10: 3990 | E10: -354413.1
C11: term | D11: 0 | E11: 0
A12: 2 | B12: 50,000 to 100,000 | C12: non withdraw-able | D12: 262 | E12: 20033.81
C13: savings | D13: 65 | E13: 4449.9
C14: term | D14: 0 | E14: 0
A16: 3 | B16: 100,000 to 300,000 | C16: non withdraw-able | D16: 1742 | E16: 346689.28
C17: savings | D17: 61 | E17: 10435.7
C18: term | D18: 0 | E18: 0
A19: 4 | B19: 300,000 to 1,000,000 | C19: non withdraw-able | D19: 113 | E19: 41934.19
C20: savings | D20: 24 | E20: 11106.12
C21: term | D21: 0 | E21: 0
A23: 5 | B23: Over 1,000,000 | C23: non withdraw-able | D23: 3 | E23: 6298.24
C24: savings | D24: 2 | E24: 11196.38
C25: term | D25: 0 | E25: 0
C26: TOTAL | D26: =SUM(D9:D25) -> 6856 | E26: =SUM(E9:E25) -> 105514.12

Sheet CAELS
A1: ECO-PILLAR SACCO CAELS
D3: 2012 Audited | E3: 2013 Audited | F3: Audited 2014 | G3: 42005 | H3: 42036 | I3: 42064 | J3: 42095 | K3: 42125 | L3: 42156 | M3: 42186 | N3: 42217 | O3: 42248 | P3: 42278 | Q3: 42309 | R3: 42339 | S3: Audited 2015 | T3: 42385 | U3: 42416 | V3: 42445 | W3: 42476 | X3: 42506 | Y3: 42537 | Z3: 42567 | AA3: 42598 | AB3: 42629 | AC3: 42659 | AD3: 42690 | AE3: 42720 | AF3: 42736 | AG3: 42767 | AH3: 42795 | AI3: 42826 | AJ3: 42856 | AK3: 42887 | AL3: 42917 | AM3: 42948 | AN3: 42979 | AO3: 43009 | AP3: 43040 | AQ3: 43070 | AR3: Audited 2017 | AS3: 43101 | AT3: 43132 | AU3: 43160 | AV3: 43191 | AW3: 43221 | AX3: 43252 | AY3: 43282 | AZ3: 43313 | BA3: 43344 | BB3: 43374 | BC3: 43405 | BD3: 43435 | BE3: Aud-18 | BF3: 43466 | BG3: 43497 | BH3: 43525 | BI3: 43556 | BJ3: 43586 | BK3: 43617 | BL3: 43647 | BM3: 43678 | BN3: 43709 | BO3: 43739 | BP3: 43770 | BQ3: 43800 | BR3: Audited 2019 | BS3: 43831 | BT3: 43862 | BU3: 43891 | BV3: 43922 | BW3: 43952 | BX3: 43983 | BY3: 44013 | BZ3: 44044 | CA3: 44075 | CB3: 44105 | CC3: 44136 | CD3: 44166 | CE3: Audited 2020 | CF3: Audited 2021 | CH3: 43831 | CI3: 43862 | CJ3: 43891 | CK3: 43922 | CL3: 43952 | CM3: 43983 | CN3: 44013 | CO3: 44044 | CP3: 44075 | CQ3: 44105
A4: CAPITAL ADEQUACY | B4: Core Capital | C4: 10 M | D4: =FINANCIALS!D12 -> -17916464 | E4: =FINANCIALS!E12 -> 37703005 | F4: =FINANCIALS!F12 -> 84979038 | G4: =FINANCIALS!G12 -> 55863957 | H4: =FINANCIALS!H12 -> 55715309 | I4: =FINANCIALS!I12 -> 55361663 | J4: =FINANCIALS!J12 -> 82339788 | K4: =FINANCIALS!K12 -> 59666643 | ... CQ4: =FINANCIALS!CQ12 -> 0
B5: CCA | C5: Min 10% | D5: =FINANCIALS!D12/FINANCIALS!D4 -> -0.037688463 | E5: =FINANCIALS!E12/FINANCIALS!E4 -> 0.074265441 | F5: =FINANCIALS!F12/FINANCIALS!F4 -> 0.14133745 | G5: =FINANCIALS!G12/FINANCIALS!G4 -> 0.12036105 | H5: =FINANCIALS!H12/FINANCIALS!H4 -> 0.10357065 | I5: =FINANCIALS!I12/FINANCIALS!I4 -> 0.10226084 | J5: =FINANCIALS!J12/FINANCIALS!J4 -> 0.14218079 | K5: =FINANCIALS!K12/FINANCIALS!K4 -> 0.18543465 | ... CQ5: =FINANCIALS!CQ12/FINANCIALS!CQ4 -> #DIV/0!
B6: CCD | C6: Min 8% | D6: =FINANCIALS!D12/FINANCIALS!D5 -> -0.045930603 | E6: =FINANCIALS!E12/FINANCIALS!E5 -> 0.093162904 | F6: =FINANCIALS!F12/FINANCIALS!F5 -> 0.19589648 | G6: =FINANCIALS!G12/FINANCIALS!G5 -> 0.12535676 | H6: =FINANCIALS!H12/FINANCIALS!H5 -> 0.12610878 | I6: =FINANCIALS!I12/FINANCIALS!I5 -> 0.12365377 | J6: =FINANCIALS!J12/FINANCIALS!J5 -> 0.17959283 | K6: =FINANCIALS!K12/FINANCIALS!K5 -> 0.13014002 | ... CQ6: =FINANCIALS!CQ12/FINANCIALS!CQ5 -> #DIV/0!
B7: ICA | C7: Min 8% | D7: =(FINANCIALS!D12-FINANCIALS!D16)/FINANCIALS!D4 -> -0.048454514 | E7: =(FINANCIALS!E12-FINANCIALS!E16)/FINANCIALS!E4 -> 0.013651373 | F7: =(FINANCIALS!F12-FINANCIALS!F16)/FINANCIALS!F4 -> 0.088211033 | G7: =(FINANCIALS!G12-FINANCIALS!G16)/FINANCIALS!G4 -> 0.045358568 | H7: =(FINANCIALS!H12-FINANCIALS!H16)/FINANCIALS!H4 -> 0.038858847 | I7: =(FINANCIALS!I12-FINANCIALS!I16)/FINANCIALS!I4 -> 0.037959269 | J7: =(FINANCIALS!J12-FINANCIALS!J16)/FINANCIALS!J4 -> 0.082069986 | K7: =(FINANCIALS!K12-FINANCIALS!K16)/FINANCIALS!K4 -> 0.077246266 | ... CQ7: =(FINANCIALS!CQ12-FINANCIALS!CQ16)/FINANCIALS!CQ4 -> #DIV/0!
A9: ASSET QUALITY | B9: A/LNPL30
B10: NPL30 | I10: ='FORM 4'!#REF! -> #REF! | J10: ='FORM 4'!#REF! -> #REF! | K10: ='FORM 4'!#REF! -> #REF! | L10: ='FORM 4'!#REF! -> #REF! | M10: ='FORM 4'!#REF! -> #REF! | N10: ='FORM 4'!#REF! -> #REF! | O10: ='FORM 4'!#REF! -> #REF! | P10: ='FORM 4'!#REF! -> #REF! | ... R10: ='FORM 4'!#REF! -> #REF! | S10: =(21463086+1782189+608263)/258801812 -> 0.092169131 | T10: =(21463086+1782189+608263)/258801812 -> 0.092169131 | U10: =(21463086+1782189+608263)/258801812 -> 0.092169131 | V10: =(21463086+1782189+608263)/258801812 -> 0.092169131 | W10: =(21463086+1782189+608263)/258801812 -> 0.092169131 | X10: =(21463086+1782189+608263)/258801812 -> 0.092169131 | Y10: =(21463086+1782189+608263)/258801812 -> 0.092169131 | Z10: =(21463086+1782189+608263)/258801812 -> 0.092169131 | ... AP10: =(21463086+1782189+608263)/258801812 -> 0.092169131 | AQ10: =SUM('[2]Portfolio Analysis'!$D$12+'[2]Portfolio Analysis'!$D$13+'[2]Portfolio Analysis'!$D$14)/334089794.1 -> 0.06717137 | AR10: =(21463086+1782189+608263)/258801812 -> 0.092169131 | AS10: 0 | AT10: 0 | AU10: =SUM('[3]Portfolio Analysis'!$D$12+'[3]Portfolio Analysis'!$D$13+'[3]Portfolio Analysis'!$D$14)/'[3]Portfolio Analysis'!$D$15 -> 0.041486948 | AV10: 0 | AW10: 0 | AX10: =SUM('[4]Portfolio Analysis'!$D$12+'[4]Portfolio Analysis'!$D$13+'[4]Portfolio Analysis'!$D$14)/'[4]Portfolio Analysis'!$D$15 -> 0.038179034 | AY10: 0 | AZ10: 0 | BA10: =SUM('[5]Portfolio Analysis'!$D$12+'[5]Portfolio Analysis'!$D$13+'[5]Portfolio Analysis'!$D$14)/311489176.3 -> 0.026947409 | BB10: =SUM('[5]Portfolio Analysis'!$D$12+'[5]Portfolio Analysis'!$D$13+'[5]Portfolio Analysis'!$D$14)/311489176.3 -> 0.026947409 | BC10: =SUM('[5]Portfolio Analysis'!$D$12+'[5]Portfolio Analysis'!$D$13+'[5]Portfolio Analysis'!$D$14)/311489176.3 -> 0.026947409 | BD10: =SUM('[5]Portfolio Analysis'!$D$12+'[5]Portfolio Analysis'!$D$13+'[5]Portfolio Analysis'!$D$14)/311489176.3 -> 0.026947409 | BE10: =SUM('[5]Portfolio Analysis'!$D$12+'[5]Portfolio Analysis'!$D$13+'[5]Portfolio Analysis'!$D$14)/311489176.3 -> 0.026947409 | BF10: =SUM('[5]Portfolio Analysis'!$D$12+'[5]Portfolio Analysis'!$D$13+'[5]Portfolio Analysis'!$D$14)/311489176.3 -> 0.026947409 | BG10: =SUM('[5]Portfolio Analysis'!$D$12+'[5]Portfolio Analysis'!$D$13+'[5]Portfolio Analysis'!$D$14)/311489176.3 -> 0.026947409 | BH10: =SUM('[5]Portfolio Analysis'!$D$12+'[5]Portfolio Analysis'!$D$13+'[5]Portfolio Analysis'!$D$14)/311489176.3 -> 0.026947409 | ... CB10: =SUM('[5]Portfolio Analysis'!$D$12+'[5]Portfolio Analysis'!$D$13+'[5]Portfolio Analysis'!$D$14)/311489176.3 -> 0.026947409 | CC10: 24.06 | CD10: 25.06 | CE10: 26.06 | CF10: 27.06 | CG10: 28.06
A12: EARNINGS | B12: ROA | D12: =SCI!C40/SFP!C32 -> 0.036985498 | E12: =SCI!D40/SFP!D32 -> 0.021226692 | F12: =SCI!E40/SFP!E32 -> 0.0079563739 | G12: =SCI!F40/SFP!F32 -> 0.00017941669 | H12: =SCI!G40/SFP!G32 -> -0.00072641993 | I12: =SCI!H40/SFP!H32 -> -0.0020541137 | J12: =SCI!I40/SFP!I32 -> -0.026225565 | K12: =SCI!J40/SFP!J32 -> -0.030597599 | ... BR12: =SCI!BQ40/SFP!BQ32 -> 0.010032218 | BS12: =SCI!BR40/SFP!#REF! -> #REF! | BT12: =SCI!BS40/SFP!BR32 -> 0.00753105 | BU12: =SCI!BT40/SFP!BS32 -> 0.0096854278 | BV12: =SCI!BU40/SFP!BT32 -> 0.0094420668 | BW12: =SCI!BV40/SFP!BU32 -> 0.009860018 | BX12: =SCI!BW40/SFP!BV32 -> 0.010060801 | BY12: =SCI!BY40/SFP!BX32 -> #DIV/0! | BZ12: =SCI!BZ40/SFP!BY32 -> 0.021642325 | CA12: =SCI!CA40/SFP!CA32 -> 0.02529534 | CB12: =SCI!CB40/SFP!CB32 -> 0.028030407 | CC12: =SCI!CC40/SFP!CC32 -> 0.0095362798 | CD12: =SCI!CD40/SFP!CD32 -> 0.0077960918 | CE12: =SCI!CE40/SFP!CE32 -> 0.016329403 | CF12: =SCI!CF40/SFP!CF32 -> 0.0075093521 | CG12: =SCI!CG40/SFP!CG32 -> 0.016354973
B13: Cost Income ratio | D13: =SCI!C30/SCI!C26 -> 0.45586247 | E13: =SCI!D30/SCI!D26 -> 0.67161232 | F13: =SCI!E30/SCI!E26 -> 0.72616965 | G13: =SCI!F30/SCI!F26 -> 0.5626377 | H13: =SCI!G30/SCI!G26 -> 0.78984122 | I13: =SCI!H30/SCI!H26 -> 0.79612658 | J13: =SCI!I30/SCI!I26 -> 1.7543589 | K13: =SCI!J30/SCI!J26 -> 1.1277369 | ... BX13: =SCI!BW30/SCI!BW26 -> 0.68392507 | BY13: =SCI!BY30/SCI!BY26 -> 0.65074686 | BZ13: =SCI!BZ30/SCI!BZ26 -> 0.59866601 | CA13: =SCI!CA30/SCI!CA26 -> 0.57846419 | CB13: =SCI!CB30/SCI!CB26 -> 0.57764505 | CC13: =SCI!CC30/SCI!CC26 -> 0.77420088 | CD13: =SCI!CD30/SCI!CD26 -> 0.8072709 | CE13: =SCI!CE30/SCI!CE26 -> 0.73063193 | CF13: =SCI!CF30/SCI!CF26 -> 0.316002 | CG13: =SCI!CG30/SCI!CG26 -> 0.26443196
B14: Operating Expense ratio | D14: =SCI!C30/SFP!C32 -> 0.030985366 | E14: =SCI!D30/SFP!D32 -> 0.046846391 | F14: =SCI!E30/SFP!E32 -> 0.048065048 | G14: =SCI!F30/SFP!F32 -> 0.0057855682 | H14: =SCI!G30/SFP!G32 -> 0.013478984 | I14: =SCI!H30/SFP!H32 -> 0.01938933 | J14: =SCI!I30/SFP!I32 -> 0.028876784 | K14: =SCI!J30/SFP!J32 -> 0.055884408 | ... BR14: =SCI!BQ30/SFP!BQ32 -> 0.064916276 | BS14: =SCI!BR30/SFP!#REF! -> #REF! | BT14: =SCI!BS30/SFP!BR32 -> 0.0089251786 | BU14: =SCI!BT30/SFP!BS32 -> 0.012941642 | BV14: =SCI!BU30/SFP!BT32 -> 0.017190594 | BW14: =SCI!BV30/SFP!BU32 -> 0.020625098 | BX14: =SCI!BW30/SFP!BV32 -> 0.024372561 | BY14: =SCI!BY30/SFP!BX32 -> #DIV/0! | BZ14: =SCI!BZ30/SFP!BY32 -> 0.033604479 | CA14: =SCI!CA30/SFP!CA32 -> 0.03624968 | CB14: =SCI!CB30/SFP!CB32 -> 0.040058138 | CC14: =SCI!CC30/SFP!CC32 -> 0.05784549 | CD14: =SCI!CD30/SFP!CD32 -> 0.057603039 | CE14: =SCI!CE30/SFP!CE32 -> 0.059420338 | CF14: =SCI!CF30/SFP!CF32 -> 0.0041224339 | CG14: =SCI!CG30/SFP!CG32 -> 0.0064227232
A16: LIQUIDITY | B16: MIN LIQ ratio | C16: Min 15% | D16: =SFP!C10/(SFP!#REF!+SFP!C33+SFP!#REF!-SFP!C42) -> #REF! | E16: =SFP!D10/(SFP!#REF!+SFP!D33+SFP!#REF!-SFP!D42) -> #REF! | F16: =SFP!E10/(SFP!E33+SFP!E34+SFP!E37-SFP!E43) -> 0.83749007 | G16: =SFP!F10/(SFP!F33+SFP!F34+SFP!F37-SFP!F43) -> 1.3970611 | H16: =SFP!G10/(SFP!G33+SFP!G34+SFP!G37-SFP!G43) -> 1.1817682 | I16: =SFP!H10/(SFP!H33+SFP!H34+SFP!H37-SFP!H43) -> 1.6656278 | J16: =SFP!I10/(SFP!I33+SFP!I34+SFP!I37-SFP!I43) -> 0.69390483 | K16: =SFP!J10/(SFP!J33+SFP!J34+SFP!J37-SFP!J43) -> 0.69503666 | L16: =SFP!K10/(SFP!K33+SFP!K34+SFP!K37-SFP!K43) -> 1.5912853 | M16: =SFP!L10/(SFP!L33+SFP!L34+SFP!L37-SFP!L43) -> 1.3605387 | ... BR16: =SFP!BQ10/(SFP!BQ33+SFP!BQ34+SFP!BQ37-SFP!BQ43) -> 0.89017383 | BS16: =SFP!#REF!/(SFP!#REF!+SFP!#REF!+SFP!#REF!-SFP!#REF!) -> #REF! | BT16: =SFP!BR10/(SFP!BR33+SFP!BR34+SFP!BR37-SFP!BR43) -> 0.79629063 | BU16: =SFP!BS10/(SFP!BS33+SFP!BS34+SFP!BS37-SFP!BS43) -> 0.65366245 | BV16: =SFP!BT10/(SFP!BT33+SFP!BT34+SFP!BT37-SFP!BT43) -> 1.0070454 | BW16: =SFP!BU10/(SFP!BU33+SFP!BU34+SFP!BU37-SFP!BU43) -> 0.79456337 | BX16: =SFP!BV10/(SFP!BV33+SFP!BV34+SFP!BV37-SFP!BV43) -> 1.1367049 | BY16: =SFP!BX10/(SFP!BX33+SFP!BX34+SFP!BX37-SFP!BX43) -> #DIV/0! | BZ16: =SFP!BY10/(SFP!BY33+SFP!BY34+SFP!BY37-SFP!BY43) -> 0.9874041 | CA16: =SFP!CA10/(SFP!CA33+SFP!CA34+SFP!CA37-SFP!#REF!) -> #REF! | CB16: =SFP!CB10/(SFP!CB33+SFP!CB34+SFP!CB37-SFP!CB43) -> 1.2852653 | CC16: =SFP!CC10/(SFP!CC33+SFP!CC34+SFP!CC37-SFP!CC43) -> 1.5482832 | CD16: =SFP!CD10/(SFP!CD33+SFP!CD34+SFP!CD37-SFP!CD43) -> 0.94487397 | CE16: =SFP!CE10/(SFP!CE33+SFP!CE34+SFP!CE37-SFP!CE43) -> 1.1869467 | CF16: =SFP!CF10/(SFP!CF33+SFP!CF34+SFP!CF37-SFP!CF43) -> 1.4945779 | CG16: =SFP!CG10/(SFP!CG33+SFP!CG34+SFP!CG37-SFP!CG43) -> 1.559161
B17: Technical LIQ ratio | D17: =SFP!C10/(SFP!C35+SFP!#REF!-SFP!C42) -> #REF! | E17: =SFP!D10/(SFP!D35+SFP!#REF!-SFP!D42) -> #REF! | F17: =SFP!E10/(SFP!E36+SFP!E37-SFP!E43) -> 0.10570627 | G17: =SFP!F10/(SFP!F36+SFP!F37-SFP!F43) -> 0.069335177 | H17: =SFP!G10/(SFP!G36+SFP!G37-SFP!G43) -> 0.051140934 | I17: =SFP!H10/(SFP!H36+SFP!H37-SFP!H43) -> 0.07919965 | J17: =SFP!I10/(SFP!I36+SFP!I37-SFP!I43) -> 0.044730941 | K17: =SFP!J10/(SFP!J36+SFP!J37-SFP!J43) -> 0.044803901 | L17: =SFP!K10/(SFP!K36+SFP!K37-SFP!K43) -> 0.094061554 | M17: =SFP!L10/(SFP!L36+SFP!L37-SFP!L43) -> 0.090001343 | ... BR17: =SFP!BQ10/(SFP!BQ36+SFP!BQ37-SFP!BQ43) -> 0.10633738 | BS17: =SFP!#REF!/(SFP!#REF!+SFP!#REF!-SFP!#REF!) -> #REF! | BT17: =SFP!BR10/(SFP!BR36+SFP!BR37-SFP!BR43) -> 0.054940459 | BU17: =SFP!BS10/(SFP!BS36+SFP!BS37-SFP!BS43) -> 0.046336245 | BV17: =SFP!BT10/(SFP!BT36+SFP!BT37-SFP!BT43) -> 0.059470154 | BW17: =SFP!BU10/(SFP!BU36+SFP!BU37-SFP!BU43) -> 0.062425584 | BX17: =SFP!BV10/(SFP!BV36+SFP!BV37-SFP!BV43) -> 0.087857946 | BY17: =SFP!BX10/(SFP!BX36+SFP!BX37-SFP!BX43) -> #DIV/0! | BZ17: =SFP!BY10/(SFP!BY36+SFP!BY37-SFP!BY43) -> 0.079303285 | CA17: =SFP!CA10/(SFP!CA36+SFP!CA37-SFP!#REF!) -> #REF! | CB17: =SFP!CB10/(SFP!CB36+SFP!CB37-SFP!CB43) -> 0.094549236 | CC17: =SFP!CC10/(SFP!CC36+SFP!CC37-SFP!CC43) -> 0.13204152 | CD17: =SFP!CD10/(SFP!CD36+SFP!CD37-SFP!CD43) -> 0.12457007 | CE17: =SFP!CE10/(SFP!CE36+SFP!CE37-SFP!CE43) -> 0.16585386 | CF17: =SFP!CF10/(SFP!CF36+SFP!CF37-SFP!CF43) -> 0.12789191 | CG17: =SFP!CG10/(SFP!CG36+SFP!CG37-SFP!CG43) -> 0.13861765
B18: External Borrowing ratio | C18: Max 25% | D18: =SFP!C43/SFP!C32 -> 0 | E18: =SFP!D43/SFP!D32 -> 0.053176379 | F18: =SFP!E43/SFP!E32 -> 0.06723673 | G18: =SFP!F43/SFP!F32 -> 0.08709949 | H18: =SFP!G43/SFP!G32 -> 0.075149055 | I18: =SFP!H43/SFP!H32 -> 0.070745894 | J18: =SFP!I43/SFP!I32 -> 0.066135128 | K18: =SFP!J43/SFP!J32 -> 0.11903106 | ... BR18: =SFP!BQ43/SFP!BQ32 -> 0.14402913 | BS18: =SFP!#REF!/SFP!#REF! -> #REF! | BT18: =SFP!BR43/SFP!BR32 -> 0.14525819 | BU18: =SFP!BS43/SFP!BS32 -> 0.14398505 | BV18: =SFP!BT43/SFP!BT32 -> 0.14080273 | BW18: =SFP!BU43/SFP!BU32 -> 0.13079395 | BX18: =SFP!BV43/SFP!BV32 -> 0.16225955 | BY18: =SFP!BX43/SFP!BX32 -> #DIV/0! | BZ18: =SFP!BY43/SFP!BY32 -> 0.1550769 | CA18: =SFP!#REF!/SFP!CA32 -> #REF! | CB18: =SFP!CB43/SFP!CB32 -> 0.14690899 | CC18: =SFP!CC43/SFP!CC32 -> 0.14023274 | CD18: =SFP!CD43/SFP!CD32 -> 0.13550234 | CE18: =SFP!CE43/SFP!CE32 -> 0.12529638 | CF18: =SFP!CF43/SFP!CF32 -> 0.12981892 | CG18: =SFP!CG43/SFP!CG32 -> 0.12378072
B19: Liquid Assets to TA ratio | D19: =SFP!C10/SFP!C32 -> 0.07957437 | E19: =SFP!D10/SFP!D32 -> 0.06804302 | F19: =SFP!E10/SFP!E32 -> 0.08365867 | G19: =SFP!F10/SFP!F32 -> 0.066572034 | H19: =SFP!G10/SFP!G32 -> 0.042001042 | I19: =SFP!H10/SFP!H32 -> 0.065497578 | J19: =SFP!I10/SFP!I32 -> 0.035412774 | K19: =SFP!J10/SFP!J32 -> 0.063840438 | ... AM19: =SFP!AL10/SFP!AL32 -> 0.061433295
A21: STRUCTURE | B21: Non-earning Asset ratio | C21: Max 10% | D21: =(SFP!C13+SFP!C22+SFP!C26-SFP!C27)/SFP!C32 -> 0.29130011 | E21: =(SFP!D13+SFP!D22+SFP!D26-SFP!D27)/SFP!D32 -> 0.54340849 | F21: =(SFP!E13+SFP!E22+SFP!E26-SFP!E27)/SFP!E32 -> 0.46341821 | G21: =(SFP!F13+SFP!F22+SFP!F26-SFP!F27)/SFP!F32 -> 0.36316192 | H21: =(SFP!G13+SFP!G22+SFP!G26-SFP!G27)/SFP!G32 -> 0.46515255 | I21: =(SFP!H13+SFP!H22+SFP!H26-SFP!H27)/SFP!H32 -> 0.47631496 | J21: =(SFP!I13+SFP!I22+SFP!I26-SFP!I27)/SFP!I32 -> 0.51238503 | K21: =(SFP!J13+SFP!J22+SFP!J26-SFP!J27)/SFP!J32 -> 0.103654 | ... BR21: =(SFP!BQ13+SFP!BQ22+SFP!BQ26-SFP!BQ27)/SFP!BQ32 -> 0.43711888 | BS21: =(SFP!#REF!+SFP!#REF!+SFP!#REF!-SFP!#REF!)/SFP!#REF! -> #REF! | BT21: =(SFP!BR13+SFP!BR22+SFP!BR26-SFP!BR27)/SFP!BR32 -> 0.44161146 | BU21: =(SFP!BS13+SFP!BS22+SFP!BS26-SFP!BS27)/SFP!BS32 -> 0.45842622 | BV21: =(SFP!BT13+SFP!BT22+SFP!BT26-SFP!BT27)/SFP!BT32 -> 0.45042581 | BW21: =(SFP!BU13+SFP!BU22+SFP!BU26-SFP!BU27)/SFP!BU32 -> 0.46820111 | BX21: =(SFP!BV13+SFP!BV22+SFP!BV26-SFP!BV27)/SFP!BV32 -> 0.46195736 | BY21: =(SFP!BY13+SFP!BX22+SFP!BX26-SFP!BX27)/SFP!BX32 -> #DIV/0! | BZ21: =(SFP!BZ13+SFP!BY22+SFP!BY26-SFP!BY27)/SFP!BY32 -> 0.42892431 | CA21: =(SFP!CA13+SFP!CA22+SFP!CA26-SFP!CA27)/SFP!CA32 -> 0.41064976 | CB21: =(SFP!CB13+SFP!CB22+SFP!CB26-SFP!CB27)/SFP!CB32 -> 0.41086476 | CC21: =(SFP!CC13+SFP!CC22+SFP!CC26-SFP!CC27)/SFP!CC32 -> 0.38875318 | CD21: =(SFP!CD13+SFP!CD22+SFP!CD26-SFP!CD27)/SFP!CD32 -> 0.40989731 | CE21: =(SFP!CE13+SFP!CE22+SFP!CE26-SFP!CE27)/SFP!CE32 -> 0.37158804 | CF21: =(SFP!CF13+SFP!CF22+SFP!CF26-SFP!CF27)/SFP!CF32 -> 0.3572131 | CG21: =(SFP!CG13+SFP!CG22+SFP!CG26-SFP!CG27)/SFP!CG32 -> 0.34907666
B22: Land and Building ratio | C22: Max 5% | D22: =SFP!C28/SFP!C32 -> 0.24372898 | E22: =SFP!D28/SFP!D32 -> 0.012961994 | F22: =SFP!E28/SFP!E32 -> 0.032719268 | G22: =SFP!F28/SFP!F32 -> 0.045988515 | H22: =SFP!G28/SFP!G32 -> 0.036569608 | I22: =SFP!H28/SFP!H32 -> 0.036337778 | J22: =SFP!I28/SFP!I32 -> 0.033969513 | K22: =SFP!J28/SFP!J32 -> 0.061138872 | ... BR22: =SFP!BQ28/SFP!BQ32 -> 0.044864005 | BS22: =SFP!#REF!/SFP!#REF! -> #REF! | BT22: =SFP!BR28/SFP!BR32 -> 0.063800131 | BU22: =SFP!BS28/SFP!BS32 -> 0.063240946 | BV22: =SFP!BT28/SFP!BT32 -> 0.063585272 | BW22: =SFP!BU28/SFP!BU32 -> 0.062294166 | BX22: =SFP!BV28/SFP!BV32 -> 0.05988681 | BY22: =SFP!BX28/SFP!BX32 -> #DIV/0! | BZ22: =SFP!BY28/SFP!BY32 -> 0.059073958 | CA22: =SFP!CA28/SFP!CA32 -> 0.05522502 | CB22: =SFP!CB28/SFP!CB32 -> 0.055990444 | CC22: =SFP!CC28/SFP!CC32 -> 0.055481854 | CD22: =SFP!CD28/SFP!CD32 -> 0.039523594 | CE22: =SFP!CE28/SFP!CE32 -> 0.040799798 | CF22: =SFP!CF28/SFP!CF32 -> 0.057131816 | CG22: =SFP!CG28/SFP!CG32 -> 0.057016435
B23: Non-Government Investment to Deposit ratio | C23: Max 5% | D23: =SFP!C18/SFP!C35 -> 0.011058338 | E23: =SFP!D18/SFP!D35 -> 0.020702139 | F23: =SFP!E18/SFP!E36 -> 0.080961188 | G23: =SFP!F18/SFP!F36 -> 0 | H23: =SFP!G18/SFP!G36 -> 0 | I23: =SFP!H18/SFP!H36 -> 0 | J23: =SFP!I18/SFP!I36 -> 0.062080437 | K23: =SFP!J18/SFP!J36 -> 0.062080437 | L23: =SFP!K18/SFP!K36 -> 0.061583565 | M23: =SFP!L18/SFP!L36 -> 0.060655647 | ... BR23: =SFP!BQ18/SFP!BQ36 -> 0.18858345 | BS23: =SFP!#REF!/SFP!#REF! -> #REF! | BT23: =SFP!BR18/SFP!BR36 -> 0.049388611 | BU23: =SFP!BS18/SFP!BS36 -> 0.049683009 | BV23: =SFP!BT18/SFP!BT36 -> 0.049825978 | BW23: =SFP!BU18/SFP!BU36 -> 0.048078677 | BX23: =SFP!BV18/SFP!BV36 -> 0.047652233 | BY23: =SFP!BX18/SFP!BX36 -> #DIV/0! | BZ23: =SFP!BY18/SFP!BY36 -> 0.052252825 | CA23: =SFP!CA18/SFP!CA36 -> 0.051797112 | CB23: =SFP!CB18/SFP!CB36 -> 0.040139237 | CC23: =SFP!CC18/SFP!CC36 -> 0.047233229 | CD23: =SFP!CD18/SFP!CD36 -> 0.17460096 | CE23: =SFP!CE18/SFP!CE36 -> 0.18157024 | CF23: =SFP!CF18/SFP!CF36 -> 0.044173197 | CG23: =SFP!CG18/SFP!CG36 -> 0.044030624
B24: Non-Government Investment to Core Capital ratio | C24: Max 40% | D24: =SFP!C18/FINANCIALS!D12 -> -0.23036353 | E24: =SFP!D18/FINANCIALS!E12 -> 0.2137575 | F24: =SFP!E18/FINANCIALS!F12 -> 0.41328557 | G24: =SFP!F18/FINANCIALS!G12 -> 0 | H24: =SFP!G18/FINANCIALS!H12 -> 0 | I24: =SFP!H18/FINANCIALS!I12 -> 0 | J24: =SFP!I18/FINANCIALS!J12 -> 0.34567324 | K24: =SFP!J18/FINANCIALS!K12 -> 0.47702803 | ... BR24: =SFP!BQ18/FINANCIALS!BR12 -> 0.79302352 | BS24: =SFP!#REF!/FINANCIALS!BS12 -> #REF! | BT24: =SFP!BR18/FINANCIALS!BT12 -> 0.18288923 | BU24: =SFP!BS18/FINANCIALS!BU12 -> 0.1813116 | BV24: =SFP!BT18/FINANCIALS!BV12 -> 0.18588514 | BW24: =SFP!BU18/FINANCIALS!BW12 -> 0.18471598 | BX24: =SFP!BV18/FINANCIALS!BX12 -> 0.18881752 | BY24: =SFP!BX18/FINANCIALS!BY12 -> 0 | BZ24: =SFP!BY18/FINANCIALS!BZ12 -> 0.19386623 | CA24: =SFP!CA18/FINANCIALS!CA12 -> 0.19348617 | CB24: =SFP!CB18/FINANCIALS!CB12 -> 0.1462857 | CC24: =SFP!CC18/FINANCIALS!CD12 -> 0.18650492 | CD24: =SFP!CD18/FINANCIALS!CE12 -> 0.76508117 | CE24: =SFP!CE18/FINANCIALS!CF12 -> 0.69511105 | CF24: =SFP!CF18/FINANCIALS!CG12 -> #DIV/0! | CG24: =SFP!CG18/FINANCIALS!CH12 -> #DIV/0!
B25: Gross loans/TA | D25: =FINANCIALS!D30/FINANCIALS!D4 -> 0.63617925 | E25: =FINANCIALS!E30/FINANCIALS!E4 -> 0.37667726 | F25: =FINANCIALS!F30/FINANCIALS!F4 -> 0.39436481 | G25: =FINANCIALS!G30/FINANCIALS!G4 -> 0.51948187 | H25: =FINANCIALS!H30/FINANCIALS!H4 -> 0.44903004 | I25: =FINANCIALS!I30/FINANCIALS!I4 -> 0.42710872 | J25: =FINANCIALS!J30/FINANCIALS!J4 -> 0.40305411 | K25: =FINANCIALS!K30/FINANCIALS!K4 -> 0.74404804 | ... CB25: =FINANCIALS!CB30/FINANCIALS!CB4 -> 0.3939811 | CC25: =FINANCIALS!CD30/FINANCIALS!CD4 -> 0.38863524 | CD25: =FINANCIALS!CE30/FINANCIALS!CE4 -> 0.3755256 | CE25: =FINANCIALS!CF30/FINANCIALS!CF4 -> 0.39289563 | CF25: =FINANCIALS!CG30/FINANCIALS!CG4 -> #DIV/0! | CG25: =FINANCIALS!CH30/FINANCIALS!CH4 -> #DIV/0!

Sheet march 2018
C1: 43160 | J1: 43252
B2: A | C2: B | D2: C | E2: D | I2: A | J2: B | K2: C | L2: D
A3: CLASSIFICATION | B3: NO. OF A/Cs | C3: OUTSTANDING LOAN PORTFOLIO(Kshs) | D3: REQUIRED PROVISION | E3: REQUIRED PROVISION AMOUNT(Kshs) | H3: CLASSIFICATION | I3: NO. OF A/Cs | J3: OUTSTANDING LOAN PORTFOLIO(Kshs) | K3: REQUIRED PROVISION | L3: REQUIRED PROVISION AMOUNT(Kshs)
A4: Performing | B4: 3222 | C4: 2.9442779e+08 | D4: 0.01 | E4: =C4*D4 -> 2944277.9 | H4: Performing | I4: 3222 | J4: 2.9442779e+08 | K4: 0.01 | L4: =J4*K4 -> 2944277.9
A5: Watch | B5: 404 | C5: 27566931 | D5: 0.05 | E5: =C5*D5 -> 1378346.6 | H5: Watch | I5: 404 | J5: 27566931 | K5: 0.05 | L5: =J5*K5 -> 1378346.6
A6: Substandard | B6: 63 | C6: 2635490 | D6: 0.25 | E6: =C6*D6 -> 658872.49 | H6: Substandard | I6: 63 | J6: 2635490 | K6: 0.25 | L6: =J6*K6 -> 658872.49
A7: Doubtful | B7: 131 | C7: 7050782 | D7: 0.5 | E7: =C7*D7 -> 3525391 | H7: Doubtful | I7: 131 | J7: 7050782 | K7: 0.5 | L7: =J7*K7 -> 3525391
A8: Loss | B8: 118 | C8: 4250500.3 | D8: 1 | E8: =C8*D8 -> 4250500.3 | H8: Loss | I8: 118 | J8: 4250500.3 | K8: 1 | L8: =J8*K8 -> 4250500.3
A9: subtotal | B9: =SUM(B4:B8) -> 3938 | C9: =SUM(C4:C8) -> 3.3593149e+08 | E9: =SUM(E4:E8) -> 12757388 | H9: subtotal | I9: =SUM(I4:I8) -> 3938 | J9: =SUM(J4:J8) -> 3.3593149e+08 | L9: =SUM(L4:L8) -> 12757388
A10: Reschedule/Renegotiated loans | H10: Reschedule/Renegotiated loans
A11: Performing | B11: 0 | D11: 0.01 | E11: =C11*D11 -> 0 | H11: Performing | I11: 0 | K11: 0.01 | L11: =J11*K11 -> 0
A12: Watch | B12: 0 | D12: 0.05 | E12: =C12*D12 -> 0 | H12: Watch | I12: 0 | K12: 0.05 | L12: =J12*K12 -> 0
A13: Substandard | B13: 0 | D13: 0.25 | E13: =C13*D13 -> 0 | H13: Substandard | I13: 0 | K13: 0.25 | L13: =J13*K13 -> 0
A14: Doubtful | B14: 0 | D14: 0.5 | E14: =C14*D14 -> 0 | H14: Doubtful | I14: 0 | K14: 0.5 | L14: =J14*K14 -> 0
A15: Loss | B15: 0 | D15: 1 | E15: =C15*D15 -> 0 | H15: Loss | I15: 0 | K15: 1 | L15: =J15*K15 -> 0
A16: subtotal | B16: =SUM(B10:B15) -> 0 | C16: =SUM(C10:C15) -> 0 | E16: =SUM(E10:E15) -> 0 | H16: subtotal | I16: =SUM(I10:I15) -> 0 | J16: =SUM(J10:J15) -> 0 | L16: =SUM(L10:L15) -> 0
A17: GRAND TOTAL | B17: =B9+B16 -> 3938 | C17: =C9+C16 -> 3.3593149e+08 | E17: =E9+E16 -> 12757388 | H17: GRAND TOTAL | I17: =I9+I16 -> 3938 | J17: =J9+J16 -> 3.3593149e+08 | L17: =L9+L16 -> 12757388
B18: PAR | C18: =SUM(C6:C8) -> 13936772
C19: =C18/C9 -> 0.041486948

Sheet F4 2020
O1: FORM 4 SASRA2/004
C2: FORM 4 SASRA2/004 | O2: RISK CLASSIFICATION OF ASSETS AND PROVISIONING
C3: RISK CLASSIFICATION OF ASSETS AND PROVISIONING | O3: SACCO SOCIETY CS NUMBER | S3: 2690
C4: SACCO SOCIETY CS NUMBER | G4: 2690 | O4: FINANCIAL YEAR | S4: 2020
C5: FINANCIAL YEAR | G5: 2020 | O5: START DATE: | S5: 1/1/2020
C6: START DATE: | G6: 1/1/2020 | O6: END DATE: | S6: 30/6/2020
C7: END DATE: | G7: 31/3/2020 | O7: PORTFOLIO AGEING REPORT
C8: PORTFOLIO AGEING REPORT | P8: A | Q8: B | R8: C | S8: D
D9: A | E9: B | F9: C | G9: D | N9: NO. | O9: CLASSIFICATION | P9: NO. OF A/Cs | Q9: OUTSTANDING LOAN PORTFOLIO(Kshs) | R9: REQUIRED PROVISION | S9: REQUIRED PROVISION AMOUNT(Kshs)
B10: NO. | C10: CLASSIFICATION | D10: NO. OF A/Cs | E10: OUTSTANDING LOAN PORTFOLIO(Kshs) | F10: REQUIRED PROVISION | G10: REQUIRED PROVISION AMOUNT(Kshs) | N10: 1 | O10: Performing | P10: 3273 | Q10: 3.9114656e+08 | R10: 0.01 | S10: 3911465.6
B11: 1 | C11: Performing | D11: 3407 | E11: 3.8612438e+08 | F11: 0.01 | G11: 3861243.8 | N11: 2 | O11: Watch | P11: 70 | Q11: 5611577.4 | R11: 0.05 | S11: 280578.87
B12: 2 | C12: Watch | D12: 101 | E12: 2775685.2 | F12: 0.05 | G12: 138784.26 | N12: 3 | O12: Substandard | P12: 76 | Q12: 43245.17 | R12: 0.25 | S12: 10811.292
B13: 3 | C13: Substandard | D13: 23 | E13: 493191.68 | F13: 0.25 | G13: 123297.92 | N13: 4 | O13: Doubtful | P13: 67 | Q13: 2261162.7 | R13: 0.5 | S13: 1130581.4
B14: 4 | C14: Doubtful | D14: 57 | E14: 2242105.8 | F14: 0.5 | G14: 1121052.9 | J14: =SUM(E13:E15)/E16 -> 0.020681959 | N14: 5 | O14: Loss | P14: 138 | Q14: 5365881 | R14: 1 | S14: 5365881
B15: 5 | C15: Loss | D15: 120 | E15: 5477780.3 | F15: 1 | G15: 5477780.3 | O15: subtotal | P15: 3624 | Q15: 4.0442843e+08 | S15: 10699318 | U15: =SUM(Q12:Q14)/Q15 -> 0.018965751
C16: subtotal | D16: 3708 | E16: 3.9711314e+08 | G16: 10722159 | O16: Reschedule/Renegotiated loans
C17: Reschedule/Renegotiated loans | N17: 1 | O17: Performing | P17: 0 | R17: 0.01 | S17: 0
B18: 1 | C18: Performing | D18: 0 | F18: 0.01 | G18: 0 | N18: 2 | O18: Watch | P18: 0 | R18: 0.05 | S18: 0
B19: 2 | C19: Watch | D19: 0 | F19: 0.05 | G19: 0 | N19: 3 | O19: Substandard | P19: 0 | R19: 0.25 | S19: 0
B20: 3 | C20: Substandard | D20: 0 | F20: 0.25 | G20: 0 | N20: 4 | O20: Doubtful | P20: 0 | R20: 0.5 | S20: 0
B21: 4 | C21: Doubtful | D21: 0 | F21: 0.5 | G21: 0 | N21: 5 | O21: Loss | P21: 0 | R21: 1 | S21: 0
B22: 5 | C22: Loss | D22: 0 | F22: 1 | G22: 0 | O22: subtotal | P22: 0 | Q22: 0 | S22: 0
C23: subtotal | D23: 0 | E23: 0 | G23: 0 | O23: GRAND TOTAL | P23: 3624 | Q23: 4.0442843e+08 | S23: 10699318
C24: GRAND TOTAL | D24: 3708 | E24: 3.9711314e+08 | G24: 10722159
N25: Note: This return should be received on or before the 15th day of the month following end of every quarter
B26: Note: This return should be received on or before the 15th day of the month following end of every quarter
C30: FORM 4 SASRA2/004
C31: RISK CLASSIFICATION OF ASSETS AND PROVISIONING
C32: SACCO SOCIETY CS NUMBER | G32: 2690
C33: FINANCIAL YEAR | G33: 2020
C34: START DATE: | G34: 1/1/2020
C35: END DATE: | G35: 30/9/2020
C36: PORTFOLIO AGEING REPORT
D37: A | E37: B | F37: C | G37: D
B38: NO. | C38: CLASSIFICATION | D38: NO. OF A/Cs | E38: OUTSTANDING LOAN PORTFOLIO(Kshs) | F38: REQUIRED PROVISION | G38: REQUIRED PROVISION AMOUNT(Kshs)
B39: 1 | C39: Performing | D39: 3237 | E39: 4.0821548e+08 | F39: 0.01 | G39: 4082154.8
B40: 2 | C40: Watch | D40: 213 | E40: 24513171 | F40: 0.05 | G40: 1225658.6
B41: 3 | C41: Substandard | D41: 32 | E41: 2624294.6 | F41: 0.25 | G41: 656073.64 | I41: =SUM(E41:E43)/E44 -> 0.016185348
B42: 4 | C42: Doubtful | D42: 8 | E42: 623978.52 | F42: 0.5 | G42: 311989.26
B43: 5 | C43: Loss | D43: 103 | E43: 3870815.7 | F43: 1 | G43: 3870815.7
C44: subtotal | D44: 3593 | E44: 4.3984774e+08 | G44: 10146692
C45: Reschedule/Renegotiated loans
B46: 1 | C46: Performing | D46: 0 | F46: 0.01 | G46: 0
B47: 2 | C47: Watch | D47: 0 | F47: 0.05 | G47: 0
B48: 3 | C48: Substandard | D48: 0 | F48: 0.25 | G48: 0
B49: 4 | C49: Doubtful | D49: 0 | F49: 0.5 | G49: 0
B50: 5 | C50: Loss | D50: 0 | F50: 1 | G50: 0
C51: subtotal | D51: 0 | E51: 0 | G51: 0
C52: GRAND TOTAL | D52: 3593 | E52: 4.3984774e+08 | G52: 10146692
B54: Note: This return should be received on or before the 15th day of the month following end of every quarter
