Workbook
Name BALANCE1_LDA01: '[1]Financial Statements'!$E$112
Name BALANCE1_LDA12: '[1]Financial Statements'!$E$123
Name BALANCE2_LDA01: '[1]Financial Statements'!$F$112
Name BALANCE2_LDA12: '[1]Financial Statements'!$F$123
Name BALANCE3_LDA01: '[1]Financial Statements'!$G$112
Name BALANCE3_LDA12: '[1]Financial Statements'!$G$123
Name BALANCE4_LDA01: '[1]Financial Statements'!$H$112
Name BALANCE4_LDA12: '[1]Financial Statements'!$H$123
Name BALANCE5_LDA01: '[1]Financial Statements'!$I$112
Name BALANCE5_LDA12: '[1]Financial Statements'!$I$123
Name BALANCE6_LDA01: '[1]Financial Statements'!$J$112
Name BALANCE6_LDA12: '[1]Financial Statements'!$J$123
Name NotApplicable: 'Prudential Ratios'!#REF!
Name PEARLS1_LA002: '[1]Financial Statements'!$E$280
Name PEARLS1_LE008: '[1]Financial Statements'!$E$275
Name PEARLS1_LE009: '[1]Financial Statements'!$E$276
Name PEARLS1_LR001: '[1]Financial Statements'!$E$282
Name PEARLS1_LR005: '[1]Financial Statements'!$E$286
Name PEARLS1_LR006: '[1]Financial Statements'!$E$287
Name PEARLS1_LR007: '[1]Financial Statements'!$E$288
Name PEARLS1_LR009: '[1]Financial Statements'!$E$290
Name PEARLS1_LS001: '[1]Financial Statements'!$E$298
Name PEARLS1_LS005: '[1]Financial Statements'!$E$302
Name PEARLS1_LS011: '[1]Financial Statements'!$E$308
Name PEARLS2_LA002: '[1]Financial Statements'!$F$280
Name PEARLS2_LE008: '[1]Financial Statements'!$F$275
Name PEARLS2_LE009: '[1]Financial Statements'!$F$276
Name PEARLS2_LR001: '[1]Financial Statements'!$F$282
Name PEARLS2_LR005: '[1]Financial Statements'!$F$286
Name PEARLS2_LR006: '[1]Financial Statements'!$F$287
Name PEARLS2_LR007: '[1]Financial Statements'!$F$288
Name PEARLS2_LR009: '[1]Financial Statements'!$F$290
Name PEARLS2_LS001: '[1]Financial Statements'!$F$298
Name PEARLS2_LS005: '[1]Financial Statements'!$F$302
Name PEARLS2_LS010: '[1]Financial Statements'!$F$307
Name PEARLS2_LS011: '[1]Financial Statements'!$F$308
Name PEARLS3_LA002: '[1]Financial Statements'!$G$280
Name PEARLS3_LE008: '[1]Financial Statements'!$G$275
Name PEARLS3_LE009: '[1]Financial Statements'!$G$276
Name PEARLS3_LR001: '[1]Financial Statements'!$G$282
Name PEARLS3_LR005: '[1]Financial Statements'!$G$286
Name PEARLS3_LR006: '[1]Financial Statements'!$G$287
Name PEARLS3_LR007: '[1]Financial Statements'!$G$288
Name PEARLS3_LR009: '[1]Financial Statements'!$G$290
Name PEARLS3_LS001: '[1]Financial Statements'!$G$298
Name PEARLS3_LS005: '[1]Financial Statements'!$G$302
Name PEARLS3_LS010: '[1]Financial Statements'!$G$307
Name PEARLS3_LS011: '[1]Financial Statements'!$G$308
Name PEARLS4_LA002: '[1]Financial Statements'!$H$280
Name PEARLS4_LE008: '[1]Financial Statements'!$H$275
Name PEARLS4_LE009: '[1]Financial Statements'!$H$276
Name PEARLS4_LR001: '[1]Financial Statements'!$H$282
Name PEARLS4_LR005: '[1]Financial Statements'!$H$286
Name PEARLS4_LR006: '[1]Financial Statements'!$H$287
Name PEARLS4_LR007: '[1]Financial Statements'!$H$288
Name PEARLS4_LR009: '[1]Financial Statements'!$H$290
Name PEARLS4_LS001: '[1]Financial Statements'!$H$298
Name PEARLS4_LS005: '[1]Financial Statements'!$H$302
Name PEARLS4_LS010: '[1]Financial Statements'!$H$307
Name PEARLS4_LS011: '[1]Financial Statements'!$H$308

Sheet SFP
A1: Good Faith Sacco
A2: STATEMENT OF FINANCIAL POSITION
B3: january | C3: february | D3: march | E3: april | F3: may | G3: june | H3: july | I3: august | J3: september | K3: october | L3: november | M3: december | N3: audited 2021 | O3: 44562 | P3: 44593 | Q3: 44621 | R3: 44652 | S3: 44682 | T3: 44713 | U3: 44743 | V3: 44774 | W3: 44805 | X3: 44835 | Y3: 44866 | Z3: 44896 | AA3: Aud-22 | AB3: 44927 | AC3: 44958 | AD3: 44986 | AE3: 45017 | AF3: 45047 | AG3: 45078 | AH3: 45108 | AI3: 45139 | AJ3: 45170 | AK3: 45200 | AL3: 45231
A4: Cash & Cash Equivalent | B4: =SUM(B5:B6) -> 10823133 | C4: =SUM(C5:C6) -> 8750063.1 | D4: =SUM(D5:D6) -> 10397052 | E4: =SUM(E5:E6) -> 10542543 | F4: =SUM(F5:F6) -> 12327490 | G4: =SUM(G5:G6) -> 11429195 | H4: =SUM(H5:H6) -> 9501091.5 | I4: =SUM(I5:I6) -> 13459098 | ... AL4: =SUM(AL5:AL6) -> 0
A5: Cash in hand | B5: 270074.95 | C5: 909061.4 | D5: 747078.4 | E5: 1590778.9 | F5: 1700729.4 | G5: 944263 | H5: 1155344.8 | I5: 2734725.8 | J5: 2518022.8 | K5: 2266156.3 | L5: 1847953.2 | M5: 551659.2 | N5: 551659 | O5: 544653.07 | P5: 1303878.1 | Q5: 409311 | R5: 920579.73 | S5: 1338303.2 | T5: 1064859.7 | U5: 955694.93 | V5: 883448.93 | W5: 738220.73 | X5: 640273.04 | Y5: 892872.18 | Z5: 448188.18 | AA5: 448188 | AB5: 1165957.2 | AC5: 692816.18 | AD5: 659541.18 | AE5: 398668.13 | AF5: 1133997.3 | AG5: 1425037.5 | AH5: 485825.47 | AI5: 1073171.5 | AJ5: 1461075.5
A6: Cash at bank | B6: 10553058 | C6: 7841001.7 | D6: 9649973.9 | E6: 8951763.8 | F6: 10626760 | G6: 10484932 | H6: 8345746.7 | I6: 10724372 | J6: 11700851 | K6: 12901566 | L6: 14476391 | M6: 16350762 | N6: =7133257+12666140-551659 -> 19247738 | O6: 18780203 | P6: 18169313 | Q6: 19532993 | R6: 17162926 | S6: 16465262 | T6: 18473091 | U6: 16577093 | V6: 17835842 | W6: 18758842 | X6: 18558065 | Y6: 16429288 | Z6: 16972807 | AA6: 20436771 | AB6: 16359668 | AC6: 16073835 | AD6: 14439712 | AE6: 14534238 | AF6: 11202985 | AG6: 12507565 | AH6: 15047902 | AI6: 13466298 | AJ6: 13246120
A7: Prepayments & Sundry Receivables | B7: 1465559 | C7: 1465559 | D7: 1165559 | E7: 965559 | F7: 965559 | G7: 765559 | H7: 765559 | I7: 565559 | J7: 565559 | K7: 565559 | L7: 565559 | M7: 365559 | N7: 624332 | O7: 365559 | P7: 365559 | Q7: 365559 | R7: 365559 | S7: 365559 | T7: 365559 | U7: 365559 | V7: 365559 | W7: 365559 | X7: 365559 | Y7: 365559 | Z7: 669559 | AA7: 1011462 | AB7: 672609 | AC7: 672609 | AD7: 179609 | AE7: 365559 | AF7: 365559 | AG7: 365559 | AH7: 365559 | AI7: 365559 | AJ7: 365559
A8: Financial Investments | B8: =SUM(B9:B12) -> 2405123.6 | C8: =SUM(C9:C12) -> 2450123.6 | D8: =SUM(D9:D12) -> 2450123.6 | E8: =SUM(E9:E12) -> 2540123.6 | F8: =SUM(F9:F12) -> 2585123.6 | G8: =SUM(G9:G12) -> 2642769.5 | H8: =SUM(H9:H12) -> 2687769.5 | I8: =SUM(I9:I12) -> 2738029.6 | ... AL8: =SUM(AL9:AL12) -> 0
A9: Government Securities - Treasury Bills/bonds, | B9: 0 | C9: 0 | D9: 0 | E9: 0 | F9: 0 | G9: 0 | H9: 0 | I9: 0 | J9: 0 | K9: 0 | L9: 0 | M9: 0 | O9: 0 | P9: 0 | Q9: 0 | R9: 0 | S9: 0 | T9: 0 | U9: 0 | V9: 0 | W9: 0 | X9: 0 | Y9: 0 | Z9: 0 | AB9: 0 | AC9: 0 | AD9: 0 | AE9: 0 | AF9: 0 | AG9: 0 | AH9: 0 | AI9: 0 | AJ9: 0
A10: Other Securities - Commercial papers/Bonds | B10: 0 | C10: 0 | D10: 0 | E10: 0 | F10: 0 | G10: 0 | H10: 0 | I10: 0 | J10: 0 | K10: 0 | L10: 0 | M10: 0 | O10: 0 | P10: 0 | Q10: 0 | R10: 0 | S10: 0 | T10: 0 | U10: 0 | V10: 0 | W10: 0 | X10: 0 | Y10: 0 | Z10: 0 | AB10: 0 | AC10: 0 | AD10: 0 | AE10: 0 | AF10: 0 | AG10: 0 | AH10: 0 | AI10: 0 | AJ10: 0
A11: Balances with other SACCO Societies | B11: 2405123.6 | C11: 2450123.6 | D11: 2450123.6 | E11: 2540123.6 | F11: 2585123.6 | G11: 2642769.5 | H11: 2687769.5 | I11: 2738029.6 | J11: 2783029.6 | K11: 2783029.6 | L11: 2878715.4 | M11: 2923715.4 | N11: 25330 | O11: 2968715.4 | P11: 3018140.4 | Q11: 3063380.4 | R11: 3108380.4 | S11: 3159808 | T11: 3204808 | U11: 3249808 | V11: 3294808 | W11: 3339808 | X11: 3384808 | Y11: 3398724.9 | Z11: 3488724.9 | AA11: 24550 | AB11: 3488724.9 | AC11: 3541215.9 | AD11: 3585435.9 | AE11: 3594735.9 | AF11: 3602583.1 | AG11: 3603983.1 | AH11: 3603983.1 | AI11: 3603983.1 | AJ11: 3621987.5
A12: Investments in companies - shares/stocks | B12: 0 | C12: 0 | D12: 0 | E12: 0 | F12: 0 | G12: 0 | H12: 0 | I12: 0 | J12: 0 | K12: 0 | L12: 0 | M12: 0 | O12: 0 | P12: 0 | Q12: 0 | R12: 0 | S12: 0 | T12: 0 | U12: 0 | V12: 0 | W12: 0 | X12: 0 | Y12: 0 | Z12: 0 | AB12: 0 | AC12: 0 | AD12: 0 | AE12: 0 | AF12: 0 | AG12: 0 | AH12: 0 | AI12: 0 | AJ12: 0
A13: Net Loan Portfolio | B13: =B14-B15 -> 41776740 | C13: =C14-C15 -> 43679590 | D13: =D14-D15 -> 41525224 | E13: =E14-E15 -> 40111713 | F13: =F14-F15 -> 38802511 | G13: =G14-G15 -> 39916357 | H13: =H14-H15 -> 42300311 | I13: =I14-I15 -> 39065164 | ... AL13: =AL14-AL15 -> 0
A14: Gross Loan Portfolio | B14: 52223619 | C14: 54516104 | D14: 52561211 | E14: 51822542 | F14: 49942174 | G14: 50586146 | H14: 52944159 | I14: 49455696 | J14: 49024214 | K14: 48386796 | L14: 47894556 | M14: 47572950 | N14: 47572950 | O14: 44732530 | P14: 45138817 | Q14: 45321718 | R14: 48156126 | S14: 47977386 | T14: 46258005 | U14: 48713392 | V14: 48309250 | W14: 47976714 | X14: 49307156 | Y14: 52164577 | Z14: 52516192 | AA14: 52516192 | AB14: 52759708 | AC14: 53790705 | AD14: 56606717 | AE14: 55731228 | AF14: 57596435 | AG14: 56572467 | AH14: 55582511 | AI14: 57952306 | AJ14: 57949937
A15: Allowance for Loan Loss | B15: 10446879 | C15: 10836514 | D15: 11035987 | E15: 11710829 | F15: 11139663 | G15: 10669789 | H15: 10643848 | I15: 10390532 | J15: 10301576 | K15: 10317484 | L15: 10296465 | M15: 10093638 | N15: 10320803 | O15: 10089263 | P15: 9616092.4 | Q15: 10164983 | R15: 10161601 | S15: 10188655 | T15: 10246206 | U15: 10425852 | V15: 10400118 | W15: 10426582 | X15: 9837821.3 | Y15: 8705526.4 | Z15: 8427355.8 | AA15: 8427355.8 | AB15: 8401659.3 | AC15: 8445750.8 | AD15: 8526110.5 | AE15: 8594309.5 | AF15: 8525452.4 | AG15: 8855031.3 | AH15: 8502500.5 | AI15: 8417397.2 | AJ15: 8749466.4
A16: Accounts Receivables | B16: =SUM(B17:B19) -> 0 | C16: =SUM(C17:C19) -> 0 | D16: =SUM(D17:D19) -> 0 | E16: =SUM(E17:E19) -> 0 | F16: =SUM(F17:F19) -> 0 | G16: =SUM(G17:G19) -> 0 | H16: =SUM(H17:H19) -> 0 | I16: =SUM(I17:I19) -> 0 | J16: =SUM(J17:J19) -> 0 | L16: =SUM(L17:L19) -> 0 | M16: =SUM(M17:M19) -> 0 | O16: 0 | P16: 0 | Q16: 0 | R16: 0 | S16: 0 | T16: 0 | U16: 0 | V16: 0 | W16: 0 | X16: 0 | Y16: 0 | Z16: 0 | AB16: 0 | AC16: 0 | AD16: 0 | AE16: 0 | AF16: 0 | AG16: 0
A17: Tax Recoverable | B17: 0 | C17: 0 | D17: 0 | E17: 0 | F17: 0 | G17: 0 | H17: 0 | I17: 0 | J17: 0 | K17: 0 | L17: 0 | M17: 0 | O17: 0 | P17: 0 | Q17: 0 | R17: 0 | S17: 0 | T17: 0 | U17: 0 | V17: 0 | W17: 0 | X17: 0 | Y17: 0 | Z17: 0 | AB17: 0 | AC17: 0 | AD17: 0 | AE17: 0 | AF17: 0 | AG17: 0 | AH17: 0 | AI17: 0 | AJ17: 0
A18: Deferred Tax Assets | B18: 0 | C18: 0 | D18: 0 | E18: 0 | F18: 0 | G18: 0 | H18: 0 | I18: 0 | J18: 0 | K18: 0 | L18: 0 | M18: 0 | O18: 0 | P18: 0 | Q18: 0 | R18: 0 | S18: 0 | T18: 0 | U18: 0 | V18: 0 | W18: 0 | X18: 0 | Y18: 0 | Z18: 0 | AB18: 0 | AC18: 0 | AD18: 0 | AE18: 0 | AF18: 0 | AG18: 0 | AH18: 0 | AI18: 0 | AJ18: 0
A19: Retirement Benefit Assets | B19: 0 | C19: 0 | D19: 0 | E19: 0 | F19: 0 | G19: 0 | H19: 0 | I19: 0 | J19: 0 | K19: 0 | L19: 0 | M19: 0 | O19: 0 | P19: 0 | Q19: 0 | R19: 0 | S19: 0 | T19: 0 | U19: 0 | V19: 0 | W19: 0 | X19: 0 | Y19: 0 | Z19: 0 | AB19: 0 | AC19: 0 | AD19: 0 | AE19: 0 | AF19: 0 | AG19: 0 | AH19: 0 | AI19: 0 | AJ19: 0
A20: Property & Equipment & Other assets | B20: =SUM(B21:B25) -> 6676533.7 | C20: =SUM(C21:C25) -> 6668047 | D20: =SUM(D21:D25) -> 7659560.3 | E20: =SUM(E21:E25) -> 7651073.6 | F20: =SUM(F21:F25) -> 8242450.1 | G20: =SUM(G21:G25) -> 8233963.4 | H20: =SUM(H21:H25) -> 8225476.7 | I20: =SUM(I21:I25) -> 8216990 | ... AL20: =SUM(AL21:AL25) -> 0
A21: Investment Properties | B21: 5950000 | C21: 5950000 | D21: 6950000 | E21: 6950000 | F21: 7600000 | G21: 7600000 | H21: 7600000 | I21: 7600000 | J21: 7600000 | K21: 7950000 | L21: 7950000 | M21: 7950000 | N21: 7950000 | O21: 7950000 | P21: 7950000 | Q21: 7950000 | R21: 7950000 | S21: 7950000 | T21: 7950000 | U21: 7950000 | V21: 7950000 | W21: 7950000 | X21: 7950000 | Y21: 7950000 | Z21: 7000000 | AA21: 7000000 | AB21: 7000000 | AC21: 7000000 | AD21: 7000000 | AE21: 7000000 | AF21: 8080000 | AG21: 8080000 | AH21: 8080000 | AI21: 8080000 | AJ21: 8080000
A22: Property & Equipment | B22: 488059.71 | C22: 479573.01 | D22: 471086.31 | E22: 462599.61 | F22: 454112.91 | G22: 445626.21 | H22: 437139.51 | I22: 428652.81 | J22: 420166.11 | K22: 411679.41 | L22: 403192.71 | M22: 394706.01 | N22: 394706 | O22: 388274.46 | P22: 381842.91 | Q22: 443542.91 | R22: 437179.81 | S22: 430748.26 | T22: 424316.71 | U22: 452585.16 | V22: 446153.61 | W22: 439722.06 | X22: 433290.51 | Y22: 438558.96 | Z22: 432127.41 | AA22: 432128 | AB22: 425178.11 | AC22: 418228.81 | AD22: 411279.51 | AE22: 404330.21 | AF22: 397380.91 | AG22: 401831.61 | AH22: 394882.31 | AI22: 387933.01 | AJ22: 387983.71
A23: Prepaid Lease rentals | B23: 0 | C23: 0 | D23: 0 | E23: 0 | F23: 0 | G23: 0 | H23: 0 | I23: 0 | J23: 0 | K23: 0 | L23: 0 | M23: 0 | O23: 0 | P23: 0 | Q23: 0 | R23: 0 | S23: 0 | T23: 0 | U23: 0 | V23: 0 | W23: 0 | X23: 0 | Y23: 0 | Z23: 0 | AB23: 0 | AC23: 0 | AD23: 0 | AE23: 0 | AF23: 0 | AG23: 0 | AH23: 0 | AI23: 0 | AJ23: 0
A24: Intangible Assets | B24: 0 | C24: 0 | D24: 0 | E24: 0 | F24: 0 | G24: 0 | H24: 0 | I24: 0 | J24: 0 | K24: 0 | L24: 0 | M24: 0 | O24: 0 | P24: 0 | Q24: 0 | R24: 0 | S24: 0 | T24: 0 | U24: 1191013.3 | V24: 1170826.7 | W24: 1150640 | X24: 1130453.3 | Y24: 1110266.6 | Z24: 1090080 | AA24: 1090080 | AB24: 1069893.3 | AC24: 1049706.6 | AD24: 1029520 | AE24: 1009333.3 | AF24: 989146.63 | AG24: 968959.96 | AH24: 948773.29 | AI24: 928586.62 | AJ24: 908399.95
A25: Other Assets | B25: 238474.03 | C25: 238474.03 | D25: 238474.03 | E25: 238474.03 | F25: 188337.16 | G25: 188337.16 | H25: 188337.16 | I25: 188337.16 | J25: 188337.16 | K25: 188337.16 | L25: 188337.16 | M25: 188337.16 | O25: 230116.63 | P25: 230116.63 | Q25: 230116.63 | R25: 230116.63 | S25: 230116.63 | T25: 232116.63 | U25: 232116.63 | V25: 254797.63 | W25: 254797.63 | X25: 285797.63 | Y25: 285797.63 | Z25: 285797.63 | AB25: 285797.63 | AC25: 290354.63 | AD25: 290354.63 | AE25: 290354.63 | AF25: 290354.63 | AG25: 290354.63 | AH25: 290354.63 | AI25: 290354.63 | AJ25: 300534.63
A26: Total Assets | B26: =SUM(B4,B7,B8,B13,B16,B20) -> 63147089 | C26: =SUM(C4,C7,C8,C13,C16,C20) -> 63013383 | D26: =SUM(D4,D7,D8,D13,D16,D20) -> 63197519 | E26: =SUM(E4,E7,E8,E13,E16,E20) -> 61811012 | F26: =SUM(F4,F7,F8,F13,F16,F20) -> 62923133 | G26: =SUM(G4,G7,G8,G13,G16,G20) -> 62987844 | H26: =SUM(H4,H7,H8,H13,H16,H20) -> 63480208 | I26: =SUM(I4,I7,I8,I13,I16,I20) -> 64044840 | ... AL26: =SUM(AL4,AL7,AL8,AL13,AL16,AL20) -> 0
A27: Savings Deposits - Withdrawable deposits - FOSA) | B27: 4599353.5 | C27: 4238526.7 | D27: 4146261.2 | E27: 3817660.7 | F27: 4514703.7 | G27: 3756857.4 | H27: 3617001.1 | I27: 3856212.5 | J27: 3925535.7 | K27: 4119820.3 | L27: 4587062.8 | M27: 4653140.8 | N27: 4653141 | O27: 3935431.5 | P27: 3849470.6 | Q27: 4423456.3 | R27: 4175564.3 | S27: 4110530.6 | T27: 4369860.2 | U27: 4329166.6 | V27: 4426303.5 | W27: 4392049.3 | X27: 4717944.7 | Y27: 4982786.7 | Z27: 4229106.2 | AA27: 4229106 | AB27: 4245395.6 | AC27: 4513600.3 | AD27: 4424851.7 | AE27: 4536657.6 | AF27: 4412550.2 | AG27: 4534392.6 | AH27: 4521018.5 | AI27: 4800350.8 | AJ27: 3945078.1
A28: Short Term Deposits (e.g Fixed deposits, special savings) | B28: 1005900 | C28: 753000 | D28: 1253000 | E28: 1103000 | F28: 603000 | G28: 603000 | H28: 603000 | I28: 603000 | J28: 603000 | K28: 603000 | L28: 603000 | M28: 603000 | N28: 603000 | O28: 603000 | P28: 603000 | Q28: 603000 | R28: 783000 | S28: 1023000 | T28: 1023000 | U28: 1023000 | V28: 1023000 | W28: 1023000 | X28: 1023000 | Y28: 843000 | Z28: 903000 | AA28: 903000 | AB28: 903000 | AC28: 903000 | AD28: 903000 | AE28: 903000 | AF28: 903000 | AG28: 953000 | AH28: 953000 | AI28: 953000 | AJ28: 953000
A29: Non withdrawable deposits (BOSA member deposits) | B29: 42639605 | C29: 42952605 | D29: 42653632 | E29: 42623959 | F29: 42728068 | G29: 42804788 | H29: 43115098 | I29: 43237357 | J29: 43124824 | K29: 43263702 | L29: 43301366 | M29: 43532509 | N29: 42324690 | O29: 43749290 | P29: 44226218 | Q29: 44596225 | R29: 45728426 | S29: 45636162 | T29: 45447393 | U29: 45938107 | V29: 46191633 | W29: 46463927 | X29: 46814110 | Y29: 47211862 | Z29: 47770133 | AA29: 46509568 | AB29: 47997585 | AC29: 47963376 | AD29: 48224995 | AE29: 48066329 | AF29: 48413332 | AG29: 48731864 | AH29: 49400250 | AI29: 49722132 | AJ29: 50283934
A30: Total Deposit liabilities | B30: =SUM(B27:B29) -> 48244858 | C30: =SUM(C27:C29) -> 47944132 | D30: =SUM(D27:D29) -> 48052893 | E30: =SUM(E27:E29) -> 47544620 | F30: =SUM(F27:F29) -> 47845771 | G30: =SUM(G27:G29) -> 47164645 | H30: =SUM(H27:H29) -> 47335100 | I30: =SUM(I27:I29) -> 47696569 | ... AL30: =SUM(AL27:AL29) -> 0
A31: Accounts Payable & Other Liabilities | B31: =SUM(B32:B37) -> 742171.29 | C31: =SUM(C32:C37) -> 705460.01 | D31: =SUM(D32:D37) -> 1484749.5 | E31: =SUM(E32:E37) -> 1232363.1 | F31: =SUM(F32:F37) -> 1127691.4 | G31: =SUM(G32:G37) -> 980421.08 | H31: =SUM(H32:H37) -> 992968.92 | I31: =SUM(I32:I37) -> 533866.29 | ... AL31: =SUM(AL32:AL37) -> 0
A32: Tax Payable | B32: 39429.76 | C32: 40557.71 | D32: 60576.9 | E32: -14576.36 | F32: 5441.82 | G32: 7521.93 | H32: 20830.67 | I32: 7701.33 | J32: 20198.52 | K32: 16843.42 | L32: 13565.9 | M32: 16787.32 | N32: 39290 | O32: 0 | P32: 0 | Q32: 1477066 | R32: 1229024.7 | S32: 735146.25 | T32: 541793.71 | U32: 32750.63 | V32: 40642.13 | W32: 41449.75 | X32: 40167.06 | Y32: 14488.2 | Z32: 10880.66 | AA32: 52697 | AB32: 4910.8 | AC32: 15734.69 | AD32: 78636.05 | AE32: 9004.67 | AF32: 26459.62 | AG32: -4591.78 | AH32: 1544.73 | AI32: 8179.03 | AJ32: 5590.45
A33: Dividends Payable | B33: 742848.18 | C33: 745699.95 | D33: 1368787.3 | E33: 1274202.3 | F33: 1150551.9 | G33: 1014630.4 | H33: 1012189.5 | I33: 568796.19 | J33: 568796.19 | K33: 568796.19 | L33: 568796.19 | M33: 0 | N33: 846494 | O33: 0 | P33: 0 | Q33: 0 | R33: 0 | S33: 0 | T33: 0 | U33: 0 | V33: 0 | W33: 0 | X33: 0 | Y33: 0 | Z33: 0 | AA33: 2111329 | AB33: 10880.66 | AC33: 10880.66 | AD33: 2061448.9 | AE33: 1170443.1 | AF33: 808622.83 | AG33: 727779.75 | AH33: 763.1 | AI33: 1095.65 | AJ33: 1095.65
A34: Deferred Tax Liability | B34: 0 | C34: 0 | D34: 0 | E34: 0 | F34: 0 | G34: 0 | H34: 0 | I34: 0 | J34: 0 | K34: 0 | L34: 0 | M34: 0 | O34: 0 | P34: 0 | Q34: 0 | R34: 0 | S34: 0 | T34: 0 | U34: 0 | V34: 0 | W34: 0 | X34: 0 | Y34: 0 | Z34: 0 | AB34: 0 | AC34: 0 | AD34: 0 | AE34: 0 | AF34: 0 | AG34: 0 | AH34: 0 | AI34: 0 | AJ34: 0
A35: Retirement Benefits Liability | B35: 0 | C35: 0 | D35: 0 | E35: 0 | F35: 0 | G35: 0 | H35: 0 | I35: 0 | J35: 0 | K35: 0 | L35: 0 | M35: 0 | O35: -44769.75 | P35: -43714.65 | Q35: 41883.79 | R35: 42654.79 | S35: -19195.54 | T35: -29325.33 | U35: -36210.77 | V35: -36766.15 | W35: -36870.34 | X35: -36790.34 | Y35: -31582.77 | Z35: -33697.74 | AB35: 0 | AC35: 0 | AD35: 0 | AE35: 0 | AF35: 0 | AG35: 0 | AH35: 30 | AI35: 30 | AJ35: 0
A36: Other Liabilities | B36: -40106.65 | C36: -80797.65 | D36: 55385.35 | E36: -27262.81 | F36: -28302.25 | G36: -41731.22 | H36: -40051.24 | I36: -42631.23 | J36: -41041.38 | K36: -44161.29 | L36: -43755.23 | M36: -45969.73 | N36: =1207819+513572+150000+104013 -> 1975404 | O36: 0 | P36: 0 | Q36: 0 | R36: 0 | S36: 0 | T36: 0 | U36: 0 | V36: 0 | W36: 0 | X36: 0 | Y36: 0 | Z36: 0 | AA36: 1375626 | AB36: -26672.66 | AC36: -25448.66 | AD36: 56510.83 | AE36: 60978.19 | AF36: 48022.55 | AG36: 50721.91 | AH36: 51543.27 | AI36: 58806.94 | AJ36: 56639.52
A37: External Borrowings | B37: 0 | C37: 0 | D37: 0 | E37: 0 | F37: 0 | G37: 0 | H37: 0 | I37: 0 | J37: 0 | K37: 0 | L37: 0 | M37: 0 | AB37: 0 | AC37: 0 | AD37: 0 | AE37: 0 | AF37: 0 | AG37: 0 | AH37: 0 | AI37: 0 | AJ37: 0
A38: Total Liabilities | B38: =B31+B30 -> 48987029 | C38: =C31+C30 -> 48649592 | D38: =D31+D30 -> 49537643 | E38: =E31+E30 -> 48776983 | F38: =F31+F30 -> 48973463 | G38: =G31+G30 -> 48145066 | H38: =H31+H30 -> 48328068 | I38: =I31+I30 -> 48230435 | ... AL38: =AL31+AL30 -> 0
A39: Share Capital (Members share capital per Bylaws) | B39: 10034849 | C39: 10040665 | D39: 10040750 | E39: 10039165 | F39: 10039165 | G39: 10048405 | H39: 10049978 | I39: 10090837 | J39: 10103837 | K39: 10111672 | L39: 10119672 | M39: 10271434 | N39: 10271434 | O39: 10306473 | P39: 10311674 | Q39: 10325674 | R39: 10343674 | S39: 10367162 | T39: 10391265 | U39: 10567742 | V39: 10611107 | W39: 10637625 | X39: 10658391 | Y39: 10694612 | Z39: 10720832 | AA39: 10720832 | AB39: 10747916 | AC39: 10784394 | AD39: 10819950 | AE39: 10892237 | AF39: 10942839 | AG39: 10976047 | AH39: 11168593 | AI39: 11208521 | AJ39: 11242231
A40: Capital Grants | B40: 0 | C40: 0 | D40: 0 | E40: 0 | F40: 0 | G40: 0 | H40: 0 | I40: 0 | J40: 0 | K40: 0 | L40: 0 | M40: 0 | N40: 3469552 | O40: 0 | P40: 0 | Q40: 0 | R40: 0 | S40: 0 | T40: 0 | U40: 0 | V40: 0 | W40: 0 | X40: 0 | Y40: 0 | Z40: 0 | AB40: 0 | AC40: 0 | AD40: 0 | AE40: 0 | AF40: 0 | AG40: 0 | AH40: 0 | AI40: 0 | AJ40: 0
A41: Retained Earnings | B41: =B43+B42 -> 762124.57 | C41: =C43+C42 -> 960040.06 | D41: =D43+D42 -> 125226.09 | E41: =E43+E42 -> -499036.09 | F41: =F43+F42 -> 416605.5 | G41: =G43+G42 -> 1300472.9 | H41: =H43+H42 -> 1608260.8 | I41: =I43+I42 -> 2229666.7 | ... AL41: =AL43+AL42 -> 0
A42: Prior Years' Retained Earnings | B42: 716731.06 | C42: 716731.06 | D42: -135784.55 | E42: -135784 | F42: -135784 | G42: -135784 | H42: -135784 | I42: -135784 | J42: -135784 | K42: -135784 | L42: -135784 | M42: -135784 | N42: -135784 | O42: 3679248.7 | P42: 3677293.1 | Q42: 1337278 | R42: 1337278 | S42: 1337275.9 | T42: 1337275.9 | U42: 1337275.9 | V42: 1337275.9 | W42: 1337275.9 | X42: 1337275.9 | Y42: 1337275.9 | Z42: 1337275.9 | AA42: 1337278 | AB42: 5668282.8 | AC42: 5668282.8 | AD42: 2863650.6 | AE42: 2863650.6 | AF42: 2863650.6 | AG42: 2863650.6 | AH42: 2863650.6 | AI42: 2863650.6 | AJ42: 2863650.6
A43: Current Year's Surplus | B43: 45393.51 | C43: 243309 | D43: 261010.64 | E43: -363252.09 | F43: 552389.5 | G43: 1436256.9 | H43: 1744044.8 | I43: 2365450.7 | J43: 2835337 | K43: 3137850.7 | L43: 3400416.4 | M43: 3815032.7 | N43: =1337278-N42 -> 1473062 | O43: 140940.7 | P43: 798386.21 | Q43: 315209.89 | R43: 521944.09 | S43: 544390.5 | T43: 653759.52 | U43: 852773.12 | V43: 1312466.6 | W43: 1483903 | X43: 2452688.9 | Y43: 4050927.2 | Z43: 4331004.8 | AA43: 1526374 | AB43: 68196.04 | AC43: 43518.02 | AD43: 476809.8 | AE43: 465631.52 | AF43: 948306.48 | AG43: 761656.38 | AH43: 1570691.1 | AI43: 2348821.7 | AJ43: 2454705.1
A44: Other Equity Accounts | B44: =SUM(B45:B49) -> 3363086 | C44: =SUM(C45:C49) -> 3363086 | D44: =SUM(D45:D49) -> 3493900 | E44: =SUM(E45:E49) -> 3493900 | F44: =SUM(F45:F49) -> 3493900 | G44: =SUM(G45:G49) -> 3493900 | H44: =SUM(H45:H49) -> 3493900 | I44: =SUM(I45:I49) -> 3493900 | ... AB44: =SUM(AB45:AB49) -> 5206382 | AE44: =SUM(AE45:AE49) -> 5766206 | AF44: =SUM(AF45:AF49) -> 5766206 | AG44: =SUM(AG45:AG49) -> 5766206 | AH44: =SUM(AH45:AH49) -> 5766206 | AI44: =SUM(AI45:AI49) -> 5766206 | AJ44: =SUM(AJ45:AJ49) -> 5766206 | AK44: =SUM(AK45:AK49) -> 0 | AL44: =SUM(AL45:AL49) -> 0
A45: Statutory Reserve | B45: 2836046 | C45: 2836046 | D45: 2966860 | E45: 2966860 | F45: 2966860 | G45: 2966860 | H45: 2966860 | I45: 2966860 | J45: 2966860 | K45: 2966860 | L45: 2966860 | M45: 2966860 | O45: 2966860 | P45: 2966860 | Q45: 3469552 | R45: 3469552 | S45: 3469552 | T45: 3469552 | U45: 3469552 | V45: 3469552 | W45: 3469552 | X45: 3469552 | Y45: 3469552 | Z45: 3469552 | AA45: 4030156 | AB45: 3469552 | AC45: 3469552 | AD45: 4030156 | AE45: 4030156 | AF45: 4030156 | AG45: 4030156 | AH45: 4030156 | AI45: 4030156 | AJ45: 4030156
A46: Other Reserves (provide notes on these reserves) | B46: 200000 | C46: 200000 | D46: 200000 | E46: 200000 | F46: 200000 | G46: 200000 | H46: 200000 | I46: 200000 | J46: 200000 | K46: 200000 | L46: 200000 | M46: 200000 | N46: 200000 | O46: 200000 | P46: 200000 | Q46: 200000 | R46: 200000 | S46: 200000 | T46: 200000 | U46: 200000 | V46: 200000 | W46: 200000 | X46: 200000 | Y46: 200000 | Z46: 200000 | AA46: 200000 | AB46: 200000 | AC46: 200000 | AD46: 200000 | AE46: 200000 | AF46: 200000 | AG46: 200000 | AH46: 200000 | AI46: 200000 | AJ46: 200000
A47: Revaluation Reserves (Not part of core capital) | B47: 327040 | C47: 327040 | D47: 327040 | E47: 327040 | F47: 327040 | G47: 327040 | H47: 327040 | I47: 327040 | J47: 327040 | K47: 327040 | L47: 327040 | M47: 327040 | N47: 325630 | O47: 327040 | P47: 325390 | Q47: 325630 | R47: 325630 | S47: 325630 | T47: 325630 | U47: 1536830 | V47: 1536830 | W47: 1536830 | X47: 1536830 | Y47: 1536830 | Z47: 1536830 | AA47: 1536050 | AB47: 1536830 | AC47: 1536830 | AD47: 1536050 | AE47: 1536050 | AF47: 1536050 | AG47: 1536050 | AH47: 1536050 | AI47: 1536050 | AJ47: 1536050
A48: Proposed Dividends | B48: 0 | C48: 0 | D48: 0 | E48: 0 | F48: 0 | G48: 0 | H48: 0 | I48: 0 | J48: 0 | K48: 0 | L48: 0 | M48: 0 | O48: 0 | P48: 0 | Q48: 0 | R48: 0 | S48: 0 | T48: 0 | U48: 0 | V48: 0 | W48: 0 | X48: 0 | Y48: 0 | Z48: 0 | AB48: 0 | AC48: 0 | AD48: 0 | AE48: 0 | AF48: 0 | AG48: 0 | AH48: 0 | AI48: 0 | AJ48: 0
A49: Adjustment to Equity | B49: 0 | C49: 0 | D49: 0 | E49: 0 | F49: 0 | G49: 0 | H49: 0 | I49: 0 | J49: 0 | K49: 0 | L49: 0 | M49: 0 | O49: 0 | P49: 0 | Q49: 0 | R49: 0 | S49: 0 | T49: 0 | U49: 0 | V49: 0 | W49: 0 | X49: 0 | Y49: 0 | Z49: 0 | AB49: 0 | AC49: 0 | AD49: 0 | AE49: 0 | AF49: 0 | AG49: 0 | AH49: 0 | AI49: 0 | AJ49: 0
A50: Total Equity | B50: =SUM(B39,B40,B41,B44) -> 14160060 | C50: =SUM(C39,C40,C41,C44) -> 14363791 | D50: =SUM(D39,D40,D41,D44) -> 13659876 | E50: =SUM(E39,E40,E41,E44) -> 13034029 | F50: =SUM(F39,F40,F41,F44) -> 13949670 | G50: =SUM(G39,G40,G41,G44) -> 14842778 | H50: =SUM(H39,H40,H41,H44) -> 15152139 | I50: =SUM(I39,I40,I41,I44) -> 15814404 | ... AL50: =SUM(AL39,AL40,AL41,AL44) -> 0
A51: Total Liabilities and Equity | B51: =SUM(B38,B50) -> 63147089 | C51: =SUM(C38,C50) -> 63013383 | D51: =SUM(D38,D50) -> 63197519 | E51: =SUM(E38,E50) -> 61811012 | F51: =SUM(F38,F50) -> 62923133 | G51: =SUM(G38,G50) -> 62987844 | H51: =SUM(H38,H50) -> 63480208 | I51: =SUM(I38,I50) -> 64044840 | ... AL51: =SUM(AL38,AL50) -> 0
B52: =B26-B51 -> -0.07 | C52: =C26-C51 -> -0.019999996 | D52: =D26-D51 -> 0 | E52: =E26-E51 -> 0 | F52: =F26-F51 -> 0 | G52: =G26-G51 -> 0 | O52: =SUM(O39,#REF!) -> #REF! | P52: =SUM(P39,#REF!) -> #REF! | AA52: =AA51-AA26 -> 0.75 | AB52: =AB51-AB26 -> 0 | AC52: =AC51-AC26 -> -5206382 | AD52: =AD51-AD26 -> -5766206 | AE52: =AE51-AE26 -> 0 | AF52: =AF51-AF26 -> 0 | AG52: =AG51-AG26 -> 0 | AH52: =AH51-AH26 -> 0 | AI52: =AI51-AI26 -> 0

Sheet SCI
A1: ELIMU SACCO SOCIETY
A2: STATEMENT OF COMPREHENSIVE INCOME | B2: Jan | C2: Feb | D2: Mar | E2: Apr | F2: May | G2: Jun | H2: Jul | I2: Aug | J2: Sep | K2: Oct | L2: Nov | M2: Dec | N2: Aud-21 | O2: 44562 | P2: 44593 | Q2: 44621 | R2: 44652 | S2: 44682 | T2: 44713 | U2: 44743 | V2: 44774 | W2: 44805 | X2: 44835 | Y2: 44866 | Z2: 44896 | AA2: Aud-22 | AB2: 44927 | AC2: 44958 | AD2: 44986 | AE2: 45017 | AF2: 45047 | AG2: 45078 | AH2: 45108 | AI2: 45139 | AJ2: 45170 | AK2: 45200
A3: Financial Income | B3: =B4+B7 -> 627685.11 | C3: =C4+C7 -> 1484673.6 | D3: =D4+D7 -> 2163427.8 | E3: =E4+E7 -> 2671685.7 | F3: =F4+F7 -> 3324884.3 | G3: =G4+G7 -> 3889010.8 | H3: =H4+H7 -> 4604034.8 | I3: =I4+I7 -> 5334046.8 | ... AK3: =AK4+AK7 -> 0
A4: Financial Income from Loans Portfolio | B4: =SUM(B5:B6) -> 588407.36 | C4: =SUM(C5:C6) -> 1405691.9 | D4: =SUM(D5:D6) -> 2057061.3 | E4: =SUM(E5:E6) -> 2533705.3 | F4: =SUM(F5:F6) -> 3160522.5 | G4: =SUM(G5:G6) -> 3712003 | H4: =SUM(H5:H6) -> 4370844.7 | I4: =SUM(I5:I6) -> 5066122.8 | ... AK4: =SUM(AK5:AK6) -> 0
A5: Interest on Loan Portfolio | B5: 417187.46 | C5: 891941.19 | D5: 1413892.6 | E5: 1839805.4 | F5: 2437105.8 | G5: 2837543.4 | H5: 3202792.8 | I5: 3871962.8 | J5: 4415056.7 | K5: 4415056.7 | L5: 5329709.2 | M5: 5776188.4 | N5: 5776188 | O5: 442271.21 | P5: 801751.26 | Q5: 1092433.6 | R5: 1516779.6 | S5: 1957729.6 | T5: 2435134.8 | U5: 2810794.3 | V5: 3303691 | W5: 3665321.3 | X5: 4095515.9 | Y5: 4532050.8 | Z5: 4883184.6 | AA5: 4883185 | AB5: 558194.7 | AC5: 913081.28 | AD5: 1466053.9 | AE5: 1937205.9 | AF5: 2535553.9 | AG5: 3012247.1 | AH5: 3519438.1 | AI5: 4103345.1 | AJ5: 4731922
A6: Fees & Commission on Loan Portfolio | B6: 171219.9 | C6: 513750.7 | D6: 643168.7 | E6: 693899.9 | F6: 723416.7 | G6: 874459.6 | H6: 1168051.9 | I6: 1194160 | J6: 1403108.7 | K6: 1403108.7 | L6: 1666745.5 | M6: 1810114.9 | N6: 2090720 | O6: 22592.8 | P6: 248432 | Q6: 330295.6 | R6: 651590.3 | S6: 773469.9 | T6: 838634.1 | U6: 1286143.6 | V6: 1487575.1 | W6: 1622555.5 | X6: 1899854.6 | Y6: 2347579.9 | Z6: 2483711.3 | AA6: 2747426 | AB6: 198991.8 | AC6: 464958.8 | AD6: 946506.8 | AE6: 1067109.3 | AF6: 1522600.4 | AG6: 1610543.9 | AH6: 1811161.3 | AI6: 2270832 | AJ6: 2587262.1
A7: Financial Income from Investments in: | B7: =SUM(B8:B11) -> 39277.75 | C7: =SUM(C8:C11) -> 78981.71 | D7: =SUM(D8:D11) -> 106366.54 | E7: =SUM(E8:E11) -> 137980.38 | F7: =SUM(F8:F11) -> 164361.87 | G7: =SUM(G8:G11) -> 177007.82 | H7: =SUM(H8:H11) -> 233190.14 | I7: =SUM(I8:I11) -> 267923.91 | ... AK7: =SUM(AK8:AK11) -> 0
A8: Government Securities | B8: 0 | C8: 0 | D8: 0 | E8: 0 | F8: 0 | G8: 0 | H8: 0 | I8: 0 | J8: 0 | K8: 0 | L8: 0 | M8: 0 | O8: 0 | P8: 0 | Q8: 0 | R8: 0 | S8: 0 | T8: 0 | U8: 0 | V8: 0 | W8: 0 | X8: 0 | Y8: 0 | Z8: 0 | AB8: 0 | AC8: 0 | AD8: 0 | AE8: 0 | AF8: 0 | AG8: 0 | AH8: 0 | AI8: 0 | AJ8: 0
A9: Deposit with Banks and Other Financial Inst. | B9: 39277.75 | C9: 78981.71 | D9: 106366.54 | E9: 137980.38 | F9: 164361.87 | G9: 164361.87 | H9: 220544.19 | I9: 249996 | J9: 279129.68 | K9: 279129.68 | L9: 337782.41 | M9: 367874.97 | N9: 479435 | O9: 32194.8 | P9: 32194.8 | Q9: 93760.34 | R9: 126201.94 | S9: 126573.71 | T9: 164955.12 | U9: 198698.68 | V9: 234080.42 | W9: 270218.53 | X9: 308072.07 | Y9: 308072.07 | Z9: 421702.48 | AB9: 0 | AC9: 94822.57 | AD9: 215108.67 | AE9: 278522.24 | AF9: 278522.24 | AG9: 413408.49 | AH9: 459676.44 | AI9: 510117.63 | AJ9: 563884.95
A10: Other Investments - dividend & Interest incomes from investments | B10: 0 | C10: 0 | D10: 0 | E10: 0 | F10: 0 | G10: 12645.95 | H10: 12645.95 | I10: 17927.91 | J10: 23057.91 | K10: 23057.91 | L10: 28743.66 | M10: 154610.58 | O10: 0 | P10: 6075 | Q10: 6075 | R10: 6075 | S10: 12502.65 | T10: 12502.65 | U10: 12502.65 | V10: 12502.65 | W10: 12502.65 | X10: 12502.65 | Y10: 26419.5 | Z10: 26995 | AB10: 0 | AC10: 7491 | AD10: 18014.22 | AE10: 18014.22 | AF10: 25861.47 | AG10: 25861.47 | AH10: 25861.47 | AI10: 25861.47 | AJ10: 33865.82
A11: Other Operating Income- Salary processing fees, transaction fees, membership fees | O11: 8794 | P11: 15690 | Q11: 30866.25 | R11: 51974.16 | S11: 108954.89 | T11: 189351.85 | U11: 209254.75 | V11: 271793.71 | W11: 288301.27 | X11: 302279.92 | Y11: 325430.02 | Z11: 366250.56 | AA11: 551233 | AB11: 29964.64 | AC11: 65319.09 | AD11: 120770.64 | AE11: 353376.74 | AF11: 414685.97 | AG11: 443272.79 | AH11: 504789.31 | AI11: 543909.62 | AJ11: 577894.74
A12: Financial Expense | B12: =B13+B14+B15+B16+B18+B17 -> 47066.65 | C12: =C13+C14+C15+C16+C18+C17 -> 56473.15 | D12: =D13+D14+D15+D16+D18+D17 -> 63238.15 | E12: =E13+E14+E15+E16+E18+E17 -> 76174.64 | F12: =F13+F14+F15+F16+F18+F17 -> 85204.94 | G12: =G13+G14+G15+G16+G18+G17 -> 87912.14 | H12: =H13+H14+H15+H16+H18+H17 -> 100493.64 | I12: =I13+I14+I15+I16+I18+I17 -> 115953.64 | ... AL12: =AL13+AL14+AL15+AL16+AL18+AL17 -> 0
A13: Interest Expense on Deposits | B13: 46666.65 | C13: 55518.15 | D13: 55518.15 | E13: 58143.15 | F13: 63976.45 | G13: 63976.45 | H13: 63976.45 | I13: 63976.45 | J13: 63976.45 | K13: 63976.45 | L13: 63976.45 | M13: 63976.45 | N13: 910470 | O13: 0 | P13: 42000 | Q13: 42000 | R13: 42000 | S13: 42000 | T13: 42000 | U13: 42000 | V13: 42000 | W13: 42000 | X13: 42000 | Y13: 48300 | Z13: 56700 | AA13: 1451987 | AB13: 0 | AC13: 42000 | AD13: 42000 | AE13: 42000 | AF13: 42000 | AG13: 52500 | AH13: 52500 | AI13: 52500 | AJ13: 52500
A14: Cost of External Borrowings | B14: 0 | C14: 0 | D14: 0 | E14: 0 | F14: 0 | G14: 0 | H14: 0 | I14: 0 | J14: 0 | K14: 0 | L14: 0 | M14: 0 | O14: 0 | P14: 0 | Q14: 0 | R14: 0 | S14: 0 | T14: 0 | U14: 0 | V14: 0 | W14: 0 | X14: 0 | Y14: 0 | Z14: 0 | AB14: 0 | AC14: 0 | AD14: 0 | AE14: 0 | AF14: 0 | AG14: 0 | AH14: 0 | AI14: 0 | AJ14: 0
A15: Dividend Expenses (on member shares) | B15: 0 | C15: 0 | D15: 0 | E15: 0 | F15: 0 | G15: 0 | H15: 0 | I15: 0 | J15: 0 | K15: 0 | L15: 0 | M15: 0 | O15: 0 | P15: 0 | Q15: 0 | R15: 0 | S15: 0 | T15: 1900 | U15: 1900 | V15: 1900 | W15: 1900 | X15: 1900 | Y15: 1900 | Z15: 1900 | AB15: 237.5 | AC15: 237.5 | AD15: 237.5 | AE15: 237.5 | AF15: 237.5 | AG15: 237.5 | AH15: 237.5 | AI15: 237.5 | AJ15: 237.5
A16: Other Financial Expense | B16: 0 | C16: 0 | D16: 0 | E16: 6221.19 | F16: 6221.19 | G16: 6221.19 | H16: 6221.19 | I16: 8741.19 | J16: 10961.19 | K16: 10961.19 | L16: 11621.19 | M16: 13181.19 | O16: 0 | P16: 2346 | Q16: 2346 | R16: 6856 | S16: 7816 | T16: 9662.87 | U16: 9662.87 | V16: 12702.87 | W16: 13302.87 | X16: 13302.87 | Y16: 13302.87 | Z16: 21738.87 | AB16: 0 | AC16: 0 | AD16: 10044 | AE16: 12148 | AF16: 12148 | AG16: 12148 | AH16: 18496 | AI16: 21790 | AJ16: 21790
A17: Fees & Commission Expense | B17: 0 | C17: 955 | D17: 0 | E17: 0 | F17: 0 | G17: 0 | H17: 0 | I17: 0 | J17: 0 | K17: 0 | L17: 0 | M17: 0 | O17: 0 | P17: 0 | Q17: 0 | R17: 0 | S17: 0 | T17: 0 | U17: 0 | V17: 0 | W17: 0 | X17: 0 | Y17: 0 | Z17: 0 | AB17: 0 | AC17: 0 | AD17: 0 | AE17: 0 | AF17: 0 | AG17: 0 | AH17: 0 | AI17: 0 | AJ17: 0
A18: Other Expense | B18: 400 | C18: 0 | D18: 7720 | E18: 11810.3 | F18: 15007.3 | G18: 17714.5 | H18: 30296 | I18: 43236 | J18: 47935 | K18: 47935 | L18: 53511.1 | M18: 122064.1 | O18: 4405.1 | P18: 6190.1 | Q18: 12880.2 | R18: 85855.2 | S18: 97573.9 | T18: 112261.9 | U18: 117969.9 | V18: 128784.9 | W18: 131889.9 | X18: 134469.9 | Y18: 138219.9 | Z18: 228755.9 | AB18: 3255 | AC18: 7155 | AD18: 14550 | AE18: 24855 | AF18: 114379 | AG18: 120909 | AH18: 128272 | AI18: 137167 | AJ18: 144522
A19: Net Financial Income/(Loss) | B19: =B3-B12 -> 580618.46 | C19: =C3-C12 -> 1428200.4 | D19: =D3-D12 -> 2100189.7 | E19: =E3-E12 -> 2595511.1 | F19: =F3-F12 -> 3239679.4 | G19: =G3-G12 -> 3801098.6 | H19: =H3-H12 -> 4503541.2 | I19: =I3-I12 -> 5218093.1 | ... AL19: =AL3-AL12 -> 0
A20: Allowance for Loan Loss | B20: =B21-B22 -> 126075.8 | C20: =C21-C22 -> 515710.6 | D20: =D21-D22 -> 715183.9 | E20: =E21-E22 -> 1390025.4 | F20: =F21-F22 -> 818860.2 | G20: =G21-G22 -> 348986.4 | H20: =H21-H22 -> 323044.7 | I20: =I21-I22 -> 69729.4 | ... AL20: =AL21-AL22 -> 0
A21: Provision for Loan Losses | B21: 126075.8 | C21: 515710.6 | D21: 715183.9 | E21: 1390025.4 | F21: 818860.2 | G21: 348986.4 | H21: 323044.7 | I21: 69729.4 | J21: 0 | K21: 0 | L21: 0 | M21: 0 | O21: 0 | P21: 0 | Q21: 0 | R21: 0 | S21: 0 | T21: 0 | U21: 105049 | V21: 79314.4 | W21: 105778.1 | X21: 0 | Y21: 0 | Z21: 0 | AA21: -1893447 | AB21: 0 | AC21: 18395.1 | AD21: 98754.7 | AE21: 166953.7 | AF21: 98096.6 | AG21: 427675.6 | AH21: 75144.7 | AI21: 0 | AJ21: 322110.7
A22: Value of Loans Recovered | B22: 0 | C22: 0 | D22: 0 | E22: 0 | F22: 0 | G22: 0 | H22: 0 | I22: 0 | J22: 19227.9 | K22: 19227.9 | L22: 24337.9 | M22: 227164.8 | O22: 4375.5 | P22: 477546.4 | Q22: 155820.4 | R22: 159202.4 | S22: 132148.4 | T22: 74597 | U22: 0 | V22: 0 | W22: 0 | X22: 482982.3 | Y22: 1615276.6 | Z22: 1893447.8 | AB22: 25694.4 | AC22: 0 | AD22: 0 | AE22: 0 | AF22: 0 | AG22: 0 | AH22: 0 | AI22: 9958.5 | AJ22: 0
A23: Operating Expenses | B23: =SUM(B24:B28) -> 442148.7 | C23: =SUM(C24:C28) -> 715050.4 | D23: =SUM(D24:D28) -> 1185101.1 | E23: =SUM(E24:E28) -> 1651413.8 | F23: =SUM(F24:F28) -> 1944607.5 | G23: =SUM(G24:G28) -> 2279713.8 | H23: =SUM(H24:H28) -> 2741526.5 | I23: =SUM(I24:I28) -> 3034876 | ... AL23: =SUM(AL24:AL28) -> 0
A24: Personnel Expenses | B24: 66800 | C24: 142000 | D24: 232330 | E24: 396810 | F24: 472010 | G24: 616994.6 | H24: 731794.6 | I24: 836994.6 | J24: 973394.6 | K24: 973394.6 | L24: 1189794.6 | M24: 1304594.6 | N24: 1441163 | O24: 121800 | P24: 227400 | Q24: 350500 | R24: 487050 | S24: 592250 | T24: 716050 | U24: 854450 | V24: 970650 | W24: 1088350 | X24: 1214150 | Y24: 1345950 | Z24: 1462400 | AA24: 1590073 | AB24: 139350 | AC24: 452180 | AD24: 588430 | AE24: 724680 | AF24: 860930 | AG24: 997210 | AH24: 1128860 | AI24: 1260510 | AJ24: 1402100
A25: Governance Expenses | B25: 27945 | C25: 71015 | D25: 127225 | E25: 160510 | F25: 208890 | G25: 287605 | H25: 329450 | I25: 353590 | J25: 421670 | K25: 421670 | L25: 515170 | M25: 561180 | N25: 561580 | O25: 23100 | P25: 56550 | Q25: 143390 | R25: 397060 | S25: 454810 | T25: 548565 | U25: 708845 | V25: 772755 | W25: 822530 | X25: 853610 | Y25: 918695 | Z25: 974800 | AA25: 1001200 | AB25: 46460 | AC25: 106725 | AD25: 186565 | AE25: 478520 | AF25: 563305 | AG25: 668125 | AH25: 727315 | AI25: 800495 | AJ25: 866045
A26: Marketing Expenses | B26: 3300 | C26: 8300 | D26: 13300 | E26: 19000 | F26: 19000 | G26: 23000 | H26: 28000 | I26: 34000 | J26: 68975 | K26: 68975 | L26: 91885 | M26: 94245 | N26: 94245 | O26: 15060 | P26: 27410 | Q26: 29410 | R26: 33410 | S26: 39770 | T26: 42770 | U26: 52275 | V26: 57275 | W26: 78777 | X26: 97782 | Y26: 106382 | Z26: 114382 | AA26: 114382 | AB26: 14000 | AC26: 18600 | AD26: 34415 | AE26: 51415 | AF26: 64045 | AG26: 73495 | AH26: 81175 | AI26: 91175 | AJ26: 99175
A27: Depreciation and Amortization Charges | B27: 8486.7 | C27: 16973.4 | D27: 25460.1 | E27: 33946.8 | F27: 42433.5 | G27: 50920.2 | H27: 59406.9 | I27: 67893.6 | J27: 76380.3 | K27: 76380.3 | L27: 93353.7 | M27: 101840.4 | N27: 101840 | O27: 6431.55 | P27: 12863.1 | Q27: 12863.1 | R27: 25726.2 | S27: 32157.75 | T27: 38589.3 | U27: 65207.52 | V27: 91825.74 | W27: 118443.96 | X27: 145062.18 | Y27: 171680.4 | Z27: 198298.62 | AA27: 198299 | AB27: 27135.97 | AC27: 54271.94 | AD27: 81407.91 | AE27: 108543.88 | AF27: 135679.85 | AG27: 162815.82 | AH27: 189951.79 | AI27: 217087.76 | AJ27: 244223.73
A28: Administrative Expenses | B28: 335617 | C28: 476762 | D28: 786786 | E28: 1041147 | F28: 1202274 | G28: 1301194 | H28: 1592875 | I28: 1742397.8 | J28: 1921711.8 | K28: 1921711.8 | L28: 2289939.8 | M28: 2604418.8 | N28: 2684296 | O28: 198491 | P28: 408544 | Q28: 800652 | R28: 911922 | S28: 1300611 | T28: 1544617 | U28: 1702261.6 | V28: 1834968.6 | W28: 1967024.6 | X28: 2141241.5 | Y28: 2354471.5 | Z28: 2680311.5 | AA28: 2863633 | AB28: 514211 | AC28: 802590.23 | AD28: 1233240.2 | AE28: 1574243.7 | AF28: 1933096.5 | AG28: 2223561.5 | AH28: 2343283.5 | AI28: 2529240.5 | AJ28: 2882420.5
A29: Net Operating Income | B29: =B19-B20-B23 -> 12393.96 | C29: =C19-C20-C23 -> 197439.45 | D29: =D19-D20-D23 -> 199904.68 | E29: =E19-E20-E23 -> -445928.12 | F29: =F19-F20-F23 -> 476211.7 | G29: =G19-G20-G23 -> 1172398.4 | H29: =H19-H20-H23 -> 1438970 | I29: =I19-I20-I23 -> 2113487.8 | ... AL29: =AL19-AL20-AL23 -> 0
A30: Net Non- Operating Income/ (Expense) | B30: =B31-B32 -> 0 | C30: =C31-C32 -> 0 | D30: =D31-D32 -> 0 | E30: =E31-E32 -> 0 | F30: =F31-F32 -> 0 | G30: =G31-G32 -> 0 | H30: =H31-H32 -> 0 | I30: =I31-I32 -> 0 | ... AL30: =AL31-AL32 -> 0
A31: Non- Operating Income | B31: 0 | C31: 0 | D31: 0 | E31: 0 | F31: 0 | G31: 0 | H31: 0 | I31: 0 | J31: 0 | K31: 0 | L31: 0 | M31: 0 | O31: 0 | P31: 0 | Q31: 0 | R31: 0 | S31: 0 | T31: 0 | U31: 0 | V31: 0 | W31: 0 | X31: 0 | Y31: 0 | Z31: 0 | AB31: 0 | AC31: 0 | AD31: 0 | AE31: 0 | AF31: 0 | AG31: 0 | AH31: 0 | AI31: 0 | AJ31: 0
A32: Non- Operating Expense | B32: 0 | C32: 0 | D32: 0 | E32: 0 | F32: 0 | G32: 0 | H32: 0 | I32: 0 | J32: 0 | K32: 0 | L32: 0 | M32: 0 | O32: 0 | P32: 0 | Q32: 0 | R32: 0 | S32: 0 | T32: 5000 | U32: 5000 | V32: 5000 | W32: 5000 | X32: 5000 | Y32: 5000 | Z32: 5000 | AB32: 0 | AC32: 0 | AD32: 0 | AE32: 5000 | AF32: 5000 | AG32: 5000 | AH32: 5000 | AI32: 5000 | AJ32: 5000
A33: Net Income (Before Taxes and Donations) | B33: =B29+B30 -> 12393.96 | C33: =C29+C30 -> 197439.45 | D33: =D29+D30 -> 199904.68 | E33: =E29+E30 -> -445928.12 | F33: =F29+F30 -> 476211.7 | G33: =G29+G30 -> 1172398.4 | H33: =H29+H30 -> 1438970 | I33: =I29+I30 -> 2113487.8 | ... AL33: =AL29+AL30 -> 0
A34: Taxes (Incomes taxes & Other payable to KRA) | B34: 0 | C34: 0 | D34: 0 | E34: 0 | F34: 20395.6 | G34: 20395.6 | H34: 20395.6 | I34: 20395.6 | J34: 20395.6 | K34: 20395.6 | L34: 20395.6 | M34: 20395.6 | N34: 39290 | O34: 0 | P34: 0 | Q34: 0 | R34: 0 | S34: 0 | T34: 0 | U34: 0 | V34: 0 | W34: 0 | X34: 0 | Y34: 0 | Z34: 0 | AB34: 0 | AC34: 0 | AD34: 0 | AE34: 0 | AF34: 0 | AG34: 0 | AH34: 0 | AI34: 0 | AJ34: 0
A35: Net Income (After Taxes before Donations) | B35: =B33-B34 -> 12393.96 | C35: =C33-C34 -> 197439.45 | D35: =D33-D34 -> 199904.68 | E35: =E33-E34 -> -445928.12 | F35: =F33-F34 -> 455816.1 | G35: =G33-G34 -> 1152002.8 | H35: =H33-H34 -> 1418574.4 | I35: =I33-I34 -> 2093092.2 | ... AL35: =AL33-AL34 -> 0
A36: Donations | B36: 0 | C36: 0 | D36: 0 | E36: 0 | F36: 0 | G36: 0 | H36: 0 | I36: 0 | J36: 0 | K36: 0 | L36: 0 | M36: 0 | O36: 0 | P36: 0 | Q36: 0 | R36: 0 | S36: 0 | T36: 0 | U36: 0 | V36: 0 | W36: 0 | X36: 0 | Y36: 0 | Z36: 0 | AB36: 0 | AC36: 0 | AD36: 0 | AE36: 0 | AF36: 0 | AG36: 0 | AH36: 0 | AI36: 0 | AJ36: 0
A37: Net Income/(After Taxes and Donations) | B37: =B35-B36 -> 12393.96 | C37: =C35-C36 -> 197439.45 | D37: =D35-D36 -> 199904.68 | E37: =E35-E36 -> -445928.12 | F37: =F35-F36 -> 455816.1 | G37: =G35-G36 -> 1152002.8 | H37: =H35-H36 -> 1418574.4 | I37: =I35-I36 -> 2093092.2 | ... AL37: =AL35-AL36 -> 0
N40: =N35-2513459 -> 0
N47: =8178719+1271421+6894369 -> 16344509
N48: =N47/47572951 -> 0.34356727

Sheet Financials
B2: ELIMU SACCO SOCIETY
B3: Year | C3: january | D3: february | E3: march | F3: april | G3: may | H3: june | I3: july | J3: august | K3: september | L3: october | M3: november | N3: december | O3: audited 2021 | P3: 44562 | Q3: 44593 | R3: 44621 | S3: 44652 | T3: 44682 | U3: 44713 | V3: 44743 | W3: 44774 | X3: 44805 | Y3: 44835 | Z3: 44866 | AA3: 44896 | AB3: Aud-22 | AC3: 44927 | AD3: 44958 | AE3: 44986 | AF3: 45017 | AG3: 45047 | AH3: 45078 | AI3: 45108 | AJ3: 45139 | AK3: 45170 | AL3: 45200
A4: 1 | B4: Membership
A5: 2 | B5: Total Assets | C5: =SFP!B26 -> 63147089 | D5: =SFP!C26 -> 63013383 | E5: =SFP!D26 -> 63197519 | F5: =SFP!E26 -> 61811012 | G5: =SFP!F26 -> 62923133 | H5: =SFP!G26 -> 62987844 | I5: =SFP!H26 -> 63480208 | J5: =SFP!I26 -> 64044840 | ... AK5: =SFP!AJ26 -> 77572131
A6: 3 | B6: Total Deposits | C6: =SFP!B30 -> 48244858 | D6: =SFP!C30 -> 47944132 | E6: =SFP!D30 -> 48052893 | F6: =SFP!E30 -> 47544620 | G6: =SFP!F30 -> 47845771 | H6: =SFP!G30 -> 47164645 | I6: =SFP!H30 -> 47335100 | J6: =SFP!I30 -> 47696569 | ... AK6: =SFP!AJ30 -> 55182012
A7: 3.1 | B7: Deposits-Members(BOSA) | C7: =SFP!B29 -> 42639605 | D7: =SFP!C29 -> 42952605 | E7: =SFP!D29 -> 42653632 | F7: =SFP!E29 -> 42623959 | G7: =SFP!F29 -> 42728068 | H7: =SFP!G29 -> 42804788 | I7: =SFP!H29 -> 43115098 | J7: =SFP!I29 -> 43237357 | ... AK7: =SFP!AJ29 -> 50283934
A8: 3.2 | B8: Deposits-Customers(FOSA) | C8: =SFP!B27 -> 4599353.5 | D8: =SFP!C27 -> 4238526.7 | E8: =SFP!D27 -> 4146261.2 | F8: =SFP!E27 -> 3817660.7 | G8: =SFP!F27 -> 4514703.7 | H8: =SFP!G27 -> 3756857.4 | I8: =SFP!H27 -> 3617001.1 | J8: =SFP!I27 -> 3856212.5 | ... AK8: =SFP!AJ27 -> 3945078.1
A9: 4 | B9: External Borrowing | C9: =SFP!B37 -> 0 | D9: =SFP!C37 -> 0 | E9: =SFP!D37 -> 0 | F9: =SFP!E37 -> 0 | G9: =SFP!F37 -> 0 | H9: =SFP!G37 -> 0 | I9: =SFP!H37 -> 0 | J9: =SFP!I37 -> 0 | ... O9: =SFP!N37 -> 0 | P9: =SFP!O38 -> 48242952 | Q9: =SFP!P38 -> 48634974 | R9: =SFP!Q38 -> 51141631 | S9: =SFP!R38 -> 51958670 | T9: =SFP!S38 -> 51485643 | U9: =SFP!T38 -> 51352722 | V9: =SFP!U38 -> 51286814 | W9: =SFP!V38 -> 51644812 | ... AK9: =SFP!AJ38 -> 55245338
A10: 4.1 | B10: Short term Liabilities | C10: =SFP!B32+SFP!B33+SFP!B34+SFP!B35+SFP!B36 -> 742171.29 | D10: =SFP!C32+SFP!C33+SFP!C34+SFP!C35+SFP!C36 -> 705460.01 | E10: =SFP!D32+SFP!D33+SFP!D34+SFP!D35+SFP!D36 -> 1484749.5 | F10: =SFP!E32+SFP!E33+SFP!E34+SFP!E35+SFP!E36 -> 1232363.1 | G10: =SFP!F32+SFP!F33+SFP!F34+SFP!F35+SFP!F36 -> 1127691.4 | H10: =SFP!G32+SFP!G33+SFP!G34+SFP!G35+SFP!G36 -> 980421.08 | I10: =SFP!H32+SFP!H33+SFP!H34+SFP!H35+SFP!H36 -> 992968.92 | J10: =SFP!I32+SFP!I33+SFP!I34+SFP!I35+SFP!I36 -> 533866.29 | ... AK10: =SFP!AJ32+SFP!AJ33+SFP!AJ34+SFP!AJ35+SFP!AJ36 -> 63325.62
A13: 5 | B13: Share capital and Reserves | C13: =C18+C20+C21 -> 13070895 | D13: =D18+D20+D21 -> 13076711 | E13: =E18+E20+E21 -> 13207610 | F13: =F18+F20+F21 -> 13206025 | G13: =G18+G20+G21 -> 13206025 | H13: =H18+H20+H21 -> 13215265 | I13: =I18+I20+I21 -> 13216838 | J13: =J18+J20+J21 -> 13257697 | ... AK13: =AK18+AK20+AK21 -> 0
A14: 5.1 | B14: Core Capital | C14: =C17 -> 13833020 | D14: =D17 -> 14036751 | E14: =E17 -> 13332836 | F14: =F17 -> 12706989 | G14: =G17 -> 13622630 | H14: =H17 -> 14515738 | I14: =I17 -> 14825099 | J14: =J17 -> 15487364 | ... AK14: =AK17 -> 2454705.1
A15: 5.2 | B15: Institutional Capital | C15: =C14-C18 -> 3798170.6 | D15: =D14-D18 -> 3996086.1 | E15: =E14-E18 -> 3292086.1 | F15: =F14-F18 -> 2667823.9 | G15: =G14-G18 -> 3583465.5 | H15: =H14-H18 -> 4467332.9 | I15: =I14-I18 -> 4775120.8 | J15: =J14-J18 -> 5396526.7 | ... N15: =N14-N18 -> 6846108.7 | O15: =3469552+200000+1337278 -> 5006830 | P15: =P14-P18 -> 6987049.4 | Q15: =Q14-Q18 -> 7642539.3 | R15: =R14-R18 -> 5322039.9 | S15: =S14-S18 -> 5528774.1 | T15: =T14-T18 -> 5551218.4 | U15: =U14-U18 -> 5660587.4 | V15: =V14-V18 -> 5859601 | W15: =W14-W18 -> 6319294.4 | ... AK15: =AK14-AK18 -> 2454705.1
A17: 5.3 | B17: Total Capital | C17: =SUM(C18:C21) -> 13833020 | D17: =SUM(D18:D21) -> 14036751 | E17: =SUM(E18:E21) -> 13332836 | F17: =SUM(F18:F21) -> 12706989 | G17: =SUM(G18:G21) -> 13622630 | H17: =SUM(H18:H21) -> 14515738 | I17: =SUM(I18:I21) -> 14825099 | J17: =SUM(J18:J21) -> 15487364 | ... AK17: =SUM(AK18:AK21) -> 2454705.1
A18: 5.3.1 | B18: Members Share Capital | C18: =SFP!B39 -> 10034849 | D18: =SFP!C39 -> 10040665 | E18: =SFP!D39 -> 10040750 | F18: =SFP!E39 -> 10039165 | G18: =SFP!F39 -> 10039165 | H18: =SFP!G39 -> 10048405 | I18: =SFP!H39 -> 10049978 | J18: =SFP!I39 -> 10090837 | ... AG18: =SFP!AF39 -> 10942839 | AH18: =SFP!AG40 -> 0 | AI18: =SFP!AH40 -> 0 | AJ18: =SFP!AI40 -> 0 | AK18: =SFP!AJ40 -> 0
A19: 5.3.3 | B19: Retained Earnings | C19: =SFP!B41 -> 762124.57 | D19: =SFP!C41 -> 960040.06 | E19: =SFP!D41 -> 125226.09 | F19: =SFP!E41 -> -499036.09 | G19: =SFP!F41 -> 416605.5 | H19: =SFP!G41 -> 1300472.9 | I19: =SFP!H41 -> 1608260.8 | J19: =SFP!I41 -> 2229666.7 | ... AG19: =SFP!AF41 -> 3811957.1 | AH19: =SFP!AG43 -> 761656.38 | AI19: =SFP!AH43 -> 1570691.1 | AJ19: =SFP!AI43 -> 2348821.7 | AK19: =SFP!AJ43 -> 2454705.1
A20: 5.3.5 | B20: Statutory Reserves | C20: =SFP!B45 -> 2836046 | D20: =SFP!C45 -> 2836046 | E20: =SFP!D45 -> 2966860 | F20: =SFP!E45 -> 2966860 | G20: =SFP!F45 -> 2966860 | H20: =SFP!G45 -> 2966860 | I20: =SFP!H45 -> 2966860 | J20: =SFP!I45 -> 2966860 | ... AG20: =SFP!AF45 -> 4030156 | AH20: =SFP!AG48 -> 0 | AI20: =SFP!AH48 -> 0 | AJ20: =SFP!AI48 -> 0 | AK20: =SFP!AJ48 -> 0
A21: 5.3.6 | B21: Capital Reserve | C21: =SFP!B46 -> 200000 | D21: =SFP!C46 -> 200000 | E21: =SFP!D46 -> 200000 | F21: =SFP!E46 -> 200000 | G21: =SFP!F46 -> 200000 | H21: =SFP!G46 -> 200000 | I21: =SFP!H46 -> 200000 | J21: =SFP!I46 -> 200000 | ... AG21: =SFP!AF46 -> 200000 | AH21: =SFP!AG49 -> 0 | AI21: =SFP!AH49 -> 0 | AJ21: =SFP!AI49 -> 0 | AK21: =SFP!AJ49 -> 0
A22: 5.3.7 | B22: Supplementary Capital & reserves
A23: a | B23: Proposed Dividends | C23: =SFP!B48 -> 0 | D23: =SFP!C48 -> 0 | E23: =SFP!D48 -> 0 | F23: =SFP!E48 -> 0 | G23: =SFP!F48 -> 0 | H23: =SFP!G48 -> 0 | I23: =SFP!H48 -> 0 | J23: =SFP!I48 -> 0 | ... AG23: =SFP!AF48 -> 0 | AH23: =SFP!AG51 -> 75360727 | AI23: =SFP!AH51 -> 76297290 | AJ23: =SFP!AI51 -> 77730794 | AK23: =SFP!AJ51 -> 77572131
A24: b
A26: 6 | B26: Investments | C26: =C27+C28+C29 -> 2405123.6 | D26: =D27+D28+D29 -> 2450123.6 | E26: =E27+E28+E29 -> 2450123.6 | F26: =F27+F28+F29 -> 2540123.6 | G26: =G27+G28+G29 -> 2585123.6 | H26: =H27+H28+H29 -> 2642769.5 | I26: =I27+I28+I29 -> 2687769.5 | J26: =J27+J28+J29 -> 2738029.6 | ... AK26: =AK27+AK28+AK29 -> 3621987.5
A27: 6.1 | B27: Investments in Coop bank, CIC, Kuscco, Kerussu & Codic | C27: =SFP!B12 -> 0 | D27: =SFP!C12 -> 0 | E27: =SFP!D12 -> 0 | F27: =SFP!E12 -> 0 | G27: =SFP!F12 -> 0 | H27: =SFP!G12 -> 0 | I27: =SFP!H12 -> 0 | J27: =SFP!I12 -> 0 | ... AK27: =SFP!AJ12 -> 0
A28: 6.2 | B28: Equity Investments (at cost)
A29: 6.3 | B29: Deposits in KUSCCO CFP | C29: =SFP!B11 -> 2405123.6 | D29: =SFP!C11 -> 2450123.6 | E29: =SFP!D11 -> 2450123.6 | F29: =SFP!E11 -> 2540123.6 | G29: =SFP!F11 -> 2585123.6 | H29: =SFP!G11 -> 2642769.5 | I29: =SFP!H11 -> 2687769.5 | J29: =SFP!I11 -> 2738029.6 | ... AK29: =SFP!AJ11 -> 3621987.5
A31: 7 | B31: Net Loans & advances | C31: =C32-C33 -> 41776740 | D31: =D32-D33 -> 43679590 | E31: =E32-E33 -> 41525224 | F31: =F32-F33 -> 40111713 | G31: =G32-G33 -> 38802511 | H31: =H32-H33 -> 39916357 | I31: =I32-I33 -> 42300311 | J31: =J32-J33 -> 39065164 | ... AK31: =AK32-AK33 -> 49200471
A32: 7.1 | B32: Gross Loans & advances | C32: =SFP!B14 -> 52223619 | D32: =SFP!C14 -> 54516104 | E32: =SFP!D14 -> 52561211 | F32: =SFP!E14 -> 51822542 | G32: =SFP!F14 -> 49942174 | H32: =SFP!G14 -> 50586146 | I32: =SFP!H14 -> 52944159 | J32: =SFP!I14 -> 49455696 | ... AK32: =SFP!AJ14 -> 57949937
A33: 7.3 | B33: Allowance for loan losses | C33: =SFP!B15 -> 10446879 | D33: =SFP!C15 -> 10836514 | E33: =SFP!D15 -> 11035987 | F33: =SFP!E15 -> 11710829 | G33: =SFP!F15 -> 11139663 | H33: =SFP!G15 -> 10669789 | I33: =SFP!H15 -> 10643848 | J33: =SFP!I15 -> 10390532 | ... AK33: =SFP!AJ15 -> 8749466.4
A34: 7.4 | B34: Non Performing Loans
A35: 7.5 | B35: Required loan loss provision
A36: 7.6 | B36: Cash and Cash equipments | C36: =SFP!B4 -> 10823133 | D36: =SFP!C4 -> 8750063.1 | E36: =SFP!D4 -> 10397052 | F36: =SFP!E4 -> 10542543 | G36: =SFP!F4 -> 12327490 | H36: =SFP!G4 -> 11429195 | I36: =SFP!H4 -> 9501091.5 | J36: =SFP!I4 -> 13459098 | ... AK36: =SFP!AJ4 -> 14707195
A38: 8 | B38: Non-Earning Assets | C38: =SFP!B7+SFP!B16+SFP!B22+SFP!B23+SFP!B24+SFP!B25 -> 2192092.7 | D38: =SFP!C7+SFP!C16+SFP!C22+SFP!C23+SFP!C24+SFP!C25 -> 2183606 | E38: =SFP!D7+SFP!D16+SFP!D22+SFP!D23+SFP!D24+SFP!D25 -> 1875119.3 | F38: =SFP!E7+SFP!E16+SFP!E22+SFP!E23+SFP!E24+SFP!E25 -> 1666632.6 | G38: =SFP!F7+SFP!F16+SFP!F22+SFP!F23+SFP!F24+SFP!F25 -> 1608009.1 | H38: =SFP!G7+SFP!G16+SFP!G22+SFP!G23+SFP!G24+SFP!G25 -> 1399522.4 | I38: =SFP!H7+SFP!H16+SFP!H22+SFP!H23+SFP!H24+SFP!H25 -> 1391035.7 | J38: =SFP!I7+SFP!I16+SFP!I22+SFP!I23+SFP!I24+SFP!I25 -> 1182549 | ... AK38: =SFP!AJ7+SFP!AJ16+SFP!AJ22+SFP!AJ23+SFP!AJ24+SFP!AJ25 -> 1962477.3
A39: 8.1 | B39: Property and Equipment | C39: =SFP!B22 -> 488059.71 | D39: =SFP!C22 -> 479573.01 | E39: =SFP!D22 -> 471086.31 | F39: =SFP!E22 -> 462599.61 | G39: =SFP!F22 -> 454112.91 | H39: =SFP!G22 -> 445626.21 | I39: =SFP!H22 -> 437139.51 | J39: =SFP!I22 -> 428652.81 | ... AK39: =SFP!AJ22 -> 387983.71
A41: 9 | B41: Turnover | C41: =C42+C43+C44 -> 627685.11 | D41: =D42+D43+D44 -> 1484673.6 | E41: =E42+E43+E44 -> 2163427.8 | F41: =F42+F43+F44 -> 2671685.7 | G41: =G42+G43+G44 -> 3324884.3 | H41: =H42+H43+H44 -> 3889010.8 | I41: =I42+I43+I44 -> 4604034.8 | J41: =J42+J43+J44 -> 5334046.8 | ... AK41: =AK42+AK43+AK44 -> 0
A42: 9.1 | B42: Loan Interest | C42: =SCI!B5 -> 417187.46 | D42: =SCI!C5 -> 891941.19 | E42: =SCI!D5 -> 1413892.6 | F42: =SCI!E5 -> 1839805.4 | G42: =SCI!F5 -> 2437105.8 | H42: =SCI!G5 -> 2837543.4 | I42: =SCI!H5 -> 3202792.8 | J42: =SCI!I5 -> 3871962.8 | ... N42: =SCI!M5 -> 5776188.4 | O42: =SCI!O5 -> 442271.21 | P42: =SCI!P5 -> 801751.26 | Q42: =SCI!Q5 -> 1092433.6 | R42: =SCI!R5 -> 1516779.6 | S42: =SCI!S5 -> 1957729.6 | T42: =SCI!T5 -> 2435134.8 | U42: =SCI!U5 -> 2810794.3 | V42: =SCI!V5 -> 3303691 | ... AK42: =SCI!AK5 -> 0
B43: Income from investments | C43: =SCI!B7 -> 39277.75 | D43: =SCI!C7 -> 78981.71 | E43: =SCI!D7 -> 106366.54 | F43: =SCI!E7 -> 137980.38 | G43: =SCI!F7 -> 164361.87 | H43: =SCI!G7 -> 177007.82 | I43: =SCI!H7 -> 233190.14 | J43: =SCI!I7 -> 267923.91 | ... N43: =SCI!M7 -> 522485.55 | O43: =SCI!O7 -> 40988.8 | P43: =SCI!P7 -> 53959.8 | Q43: =SCI!Q7 -> 130701.59 | R43: =SCI!R7 -> 184251.1 | S43: =SCI!S7 -> 248031.25 | T43: =SCI!T7 -> 366809.62 | U43: =SCI!U7 -> 420456.08 | V43: =SCI!V7 -> 518376.78 | ... AK43: =SCI!AK7 -> 0
A44: 9.2 | B44: Fees & Commissions | C44: =SCI!B6 -> 171219.9 | D44: =SCI!C6 -> 513750.7 | E44: =SCI!D6 -> 643168.7 | F44: =SCI!E6 -> 693899.9 | G44: =SCI!F6 -> 723416.7 | H44: =SCI!G6 -> 874459.6 | I44: =SCI!H6 -> 1168051.9 | J44: =SCI!I6 -> 1194160 | ... N44: =SCI!M6 -> 1810114.9 | O44: =SCI!O6 -> 22592.8 | P44: =SCI!P6 -> 248432 | Q44: =SCI!Q6 -> 330295.6 | R44: =SCI!R6 -> 651590.3 | S44: =SCI!S6 -> 773469.9 | T44: =SCI!T6 -> 838634.1 | U44: =SCI!U6 -> 1286143.6 | V44: =SCI!V6 -> 1487575.1 | ... AK44: =SCI!AK6 -> 0
B45: Average yield on loans | C45: =C42/C32 -> 0.0079884823 | D45: =D42/D32 -> 0.016361059 | E45: =E42/E32 -> 0.026899924 | F45: =F42/F32 -> 0.03550203 | G45: =G42/G32 -> 0.048798552 | H45: =H42/H32 -> 0.05609329 | I45: =I42/I32 -> 0.060493789 | J45: =J42/J32 -> 0.078291545 | ... AK45: =AK42/AK32 -> 0
A47: 10 | B47: Total Expenses (FinCosts + OpEx) | C47: =SUM(C48:C53) -> #REF! | D47: =SUM(D48:D53) -> #REF! | E47: =SUM(E48:E53) -> #REF! | F47: =SUM(F48:F53) -> #REF! | G47: =SUM(G48:G53) -> #REF! | H47: =SUM(H48:H53) -> #REF! | I47: =SUM(I48:I53) -> #REF! | J47: =SUM(J48:J53) -> #REF! | ... AK47: =SUM(AK48:AK53) -> #REF!
A48: 10.1 | B48: Financial Exp. (Interest on deposits) | C48: =SCI!B13 -> 46666.65 | D48: =SCI!C13 -> 55518.15 | E48: =SCI!D13 -> 55518.15 | F48: =SCI!E13 -> 58143.15 | G48: =SCI!F13 -> 63976.45 | H48: =SCI!G13 -> 63976.45 | I48: =SCI!H13 -> 63976.45 | J48: =SCI!I13 -> 63976.45 | ... N48: =SCI!M13 -> 63976.45 | O48: =SCI!O13 -> 0 | P48: =SCI!P13 -> 42000 | Q48: =SCI!Q13 -> 42000 | R48: =SCI!R13 -> 42000 | S48: =SCI!S13 -> 42000 | T48: =SCI!T13 -> 42000 | U48: =SCI!U13 -> 42000 | V48: =SCI!V13 -> 42000 | ... AK48: =SCI!AK13 -> 0
A49: 10.2 | B49: Financial Exp. (Dividends) | C49: =SCI!B15 -> 0 | D49: =SCI!C15 -> 0 | E49: =SCI!D15 -> 0 | F49: =SCI!E15 -> 0 | G49: =SCI!F15 -> 0 | H49: =SCI!G15 -> 0 | I49: =SCI!H15 -> 0 | J49: =SCI!I15 -> 0 | ... N49: =SCI!M15 -> 0 | O49: =SCI!O15 -> 0 | P49: =SCI!P15 -> 0 | Q49: =SCI!Q15 -> 0 | R49: =SCI!R15 -> 0 | S49: =SCI!S15 -> 0 | T49: =SCI!T15 -> 1900 | U49: =SCI!U15 -> 1900 | V49: =SCI!V15 -> 1900 | ... AK49: =SCI!AK15 -> 0
A50: 10.3 | B50: Financial Exp. (Interest on bank loans) | C50: =SCI!B14 -> 0 | D50: =SCI!C14 -> 0 | E50: =SCI!D14 -> 0 | F50: =SCI!E14 -> 0 | G50: =SCI!F14 -> 0 | H50: =SCI!G14 -> 0 | I50: =SCI!H14 -> 0 | J50: =SCI!I14 -> 0 | ... N50: =SCI!M14 -> 0 | O50: =SCI!O14 -> 0 | P50: =SCI!P14 -> 0 | Q50: =SCI!Q14 -> 0 | R50: =SCI!R14 -> 0 | S50: =SCI!S14 -> 0 | T50: =SCI!T14 -> 0 | U50: =SCI!U14 -> 0 | V50: =SCI!V14 -> 0 | ... AK50: =SCI!AK14 -> 0
A51: 10.4 | B51: Other Financial Expenses | C51: =SCI!B16+SCI!B18+SCI!#REF! -> #REF! | D51: =SCI!C16+SCI!C18+SCI!#REF! -> #REF! | E51: =SCI!D16+SCI!D18+SCI!#REF! -> #REF! | F51: =SCI!E16+SCI!E18+SCI!#REF! -> #REF! | G51: =SCI!F16+SCI!F18+SCI!#REF! -> #REF! | H51: =SCI!G16+SCI!G18+SCI!#REF! -> #REF! | I51: =SCI!H16+SCI!H18+SCI!#REF! -> #REF! | J51: =SCI!I16+SCI!I18+SCI!#REF! -> #REF! | ... N51: =SCI!M16+SCI!M18+SCI!#REF! -> #REF! | O51: =SCI!O16+SCI!O18+SCI!#REF! -> #REF! | P51: =SCI!P16+SCI!P18+SCI!#REF! -> #REF! | Q51: =SCI!Q16+SCI!Q18+SCI!#REF! -> #REF! | R51: =SCI!R16+SCI!R18+SCI!#REF! -> #REF! | S51: =SCI!S16+SCI!S18+SCI!#REF! -> #REF! | T51: =SCI!T16+SCI!T18+SCI!#REF! -> #REF! | U51: =SCI!U16+SCI!U18+SCI!#REF! -> #REF! | V51: =SCI!V16+SCI!V18+SCI!#REF! -> #REF! | ... AK51: =SCI!AK16+SCI!AK18+SCI!#REF! -> #REF!
A52: 10.5 | B52: Administrative Expenses | C52: =SCI!B28 -> 335617 | D52: =SCI!C28 -> 476762 | E52: =SCI!D28 -> 786786 | F52: =SCI!E28 -> 1041147 | G52: =SCI!F28 -> 1202274 | H52: =SCI!G28 -> 1301194 | I52: =SCI!H28 -> 1592875 | J52: =SCI!I28 -> 1742397.8 | ... N52: =SCI!M28 -> 2604418.8 | O52: =SCI!O28 -> 198491 | P52: =SCI!P28 -> 408544 | Q52: =SCI!Q28 -> 800652 | R52: =SCI!R28 -> 911922 | S52: =SCI!S28 -> 1300611 | T52: =SCI!T28 -> 1544617 | U52: =SCI!U28 -> 1702261.6 | V52: =SCI!V28 -> 1834968.6 | ... AK52: =SCI!AK28 -> 0
A53: 10.6 | B53: Governance Expenses | C53: =SCI!B25 -> 27945 | D53: =SCI!C25 -> 71015 | E53: =SCI!D25 -> 127225 | F53: =SCI!E25 -> 160510 | G53: =SCI!F25 -> 208890 | H53: =SCI!G25 -> 287605 | I53: =SCI!H25 -> 329450 | J53: =SCI!I25 -> 353590 | ... N53: =SCI!M25 -> 561180 | O53: =SCI!O25 -> 23100 | P53: =SCI!P25 -> 56550 | Q53: =SCI!Q25 -> 143390 | R53: =SCI!R25 -> 397060 | S53: =SCI!S25 -> 454810 | T53: =SCI!T25 -> 548565 | U53: =SCI!U25 -> 708845 | V53: =SCI!V25 -> 772755 | ... AK53: =SCI!AK25 -> 0
B54: LLP
B56: Net Surplus | C56: =SCI!B37 -> 12393.96 | D56: =SCI!C37 -> 197439.45 | E56: =SCI!D37 -> 199904.68 | F56: =SCI!E37 -> -445928.12 | G56: =SCI!F37 -> 455816.1 | H56: =SCI!G37 -> 1152002.8 | I56: =SCI!H37 -> 1418574.4 | J56: =SCI!I37 -> 2093092.2 | ... N56: =SCI!M37 -> 3450057.6 | O56: =SCI!O37 -> 140940.66 | P56: =SCI!P37 -> 798386.26 | Q56: =SCI!Q37 -> 315209.9 | R56: =SCI!R37 -> 521944.05 | S56: =SCI!S37 -> 544390.5 | T56: =SCI!T37 -> 653759.48 | U56: =SCI!U37 -> 852773.1 | V56: =SCI!V37 -> 1312466.5 | ... AK56: =SCI!AK37 -> 0
B57: Liquid Assets | C57: =SFP!B4+SFP!B9+SFP!B10 -> 10823133 | D57: =SFP!C4+SFP!C9+SFP!C10 -> 8750063.1 | E57: =SFP!D4+SFP!D9+SFP!D10 -> 10397052 | F57: =SFP!E4+SFP!E9+SFP!E10 -> 10542543 | G57: =SFP!F4+SFP!F9+SFP!F10 -> 12327490 | H57: =SFP!G4+SFP!G9+SFP!G10 -> 11429195 | I57: =SFP!H4+SFP!H9+SFP!H10 -> 9501091.5 | J57: =SFP!I4+SFP!I9+SFP!I10 -> 13459098 | ... AK57: =SFP!AJ4+SFP!AJ9+SFP!AJ10 -> 14707195
B58: Short term Liabilities + deposits | C58: =SFP!B27+SFP!B28+SFP!B32+SFP!B33+SFP!B34+SFP!B35+SFP!B36 -> 6347424.8 | D58: =SFP!C27+SFP!C28+SFP!C32+SFP!C33+SFP!C34+SFP!C35+SFP!C36 -> 5696986.7 | E58: =SFP!D27+SFP!D28+SFP!D32+SFP!D33+SFP!D34+SFP!D35+SFP!D36 -> 6884010.7 | F58: =SFP!E27+SFP!E28+SFP!E32+SFP!E33+SFP!E34+SFP!E35+SFP!E36 -> 6153023.8 | G58: =SFP!F27+SFP!F28+SFP!F32+SFP!F33+SFP!F34+SFP!F35+SFP!F36 -> 6245395.2 | H58: =SFP!G27+SFP!G28+SFP!G32+SFP!G33+SFP!G34+SFP!G35+SFP!G36 -> 5340278.5 | I58: =SFP!H27+SFP!H28+SFP!H32+SFP!H33+SFP!H34+SFP!H35+SFP!H36 -> 5212970 | J58: =SFP!I27+SFP!I28+SFP!I32+SFP!I33+SFP!I34+SFP!I35+SFP!I36 -> 4993078.8 | ... AK58: =SFP!AJ27+SFP!AJ28+SFP!AJ32+SFP!AJ33+SFP!AJ34+SFP!AJ35+SFP!AJ36 -> 4961403.8
C59: =(SFP!B39+SFP!B40+SFP!B42+(0.5*SFP!B43)+SFP!B45+SFP!B46) -> 13810323 | D59: =(SFP!C39+SFP!C40+SFP!C42+(0.5*SFP!C43)+SFP!C45+SFP!C46) -> 13915096 | E59: =(SFP!D39+SFP!D40+SFP!D42+(0.5*SFP!D43)+SFP!D45+SFP!D46) -> 13202331 | F59: =(SFP!E39+SFP!E40+SFP!E42+(0.5*SFP!E43)+SFP!E45+SFP!E46) -> 12888615 | G59: =(SFP!F39+SFP!F40+SFP!F42+(0.5*SFP!F43)+SFP!F45+SFP!F46) -> 13346436 | H59: =(SFP!G39+SFP!G40+SFP!G42+(0.5*SFP!G43)+SFP!G45+SFP!G46) -> 13797609 | I59: =(SFP!H39+SFP!H40+SFP!H42+(0.5*SFP!H43)+SFP!H45+SFP!H46) -> 13953077 | J59: =(SFP!I39+SFP!I40+SFP!I42+(0.5*SFP!I43)+SFP!I45+SFP!I46) -> 14304639 | ... O59: =(SFP!N39+SFP!N40+SFP!N42+(0.5*SFP!N43)+SFP!N45+SFP!N46) -> 14541733 | P59: =(SFP!O40+SFP!O42+SFP!O45+(0.5*SFP!O46)+SFP!O48+SFP!O49) -> 6746108.7 | Q59: =(SFP!P40+SFP!P42+SFP!P45+(0.5*SFP!P46)+SFP!P48+SFP!P49) -> 6744153.1 | R59: =(SFP!Q40+SFP!Q42+SFP!Q45+(0.5*SFP!Q46)+SFP!Q48+SFP!Q49) -> 4906830 | S59: =(SFP!R40+SFP!R42+SFP!R45+(0.5*SFP!R46)+SFP!R48+SFP!R49) -> 4906830 | T59: =(SFP!S40+SFP!S42+SFP!S45+(0.5*SFP!S46)+SFP!S48+SFP!S49) -> 4906827.9 | U59: =(SFP!T40+SFP!T42+SFP!T45+(0.5*SFP!T46)+SFP!T48+SFP!T49) -> 4906827.9 | V59: =(SFP!U40+SFP!U42+SFP!U45+(0.5*SFP!U46)+SFP!U48+SFP!U49) -> 4906827.9 | W59: =(SFP!V40+SFP!V42+SFP!V45+(0.5*SFP!V46)+SFP!V48+SFP!V49) -> 4906827.9 | ... AK59: =(SFP!AJ40+SFP!AJ42+SFP!AJ45+(0.5*SFP!AJ46)+SFP!AJ48+SFP!AJ49) -> 6993806.6

Sheet Prudential Ratios
A1: Good Faith SACCO SOCIETY LTD
A2: Sacco Financial Performance
A4: FINANCIAL SOUNDNESS INDICATORS | B4: Prude. Std | C4: january | D4: february | E4: march | F4: april | G4: may | H4: june | I4: july | J4: august | K4: september | L4: october | M4: november | N4: december | O4: audited 2021 | P4: 44562 | Q4: 44593 | R4: 44621 | S4: 44652 | T4: 44682 | U4: 44713 | V4: 44743 | W4: 44774 | X4: 44805 | Y4: 44835 | Z4: 44866 | AA4: 44896 | AB4: Aud-22 | AC4: 44927 | AD4: 44958 | AE4: 44986 | AF4: 45017 | AG4: 45047 | AH4: 45078 | AI4: 45108 | AJ4: 45139 | AK4: 45170
A5: CAPITAL ADEQUACY REQUIREMENTS
A6: Core capital | B6: ≥ Ksh.10M | C6: =Financials!C14/1000000 -> 13.83302 | D6: =Financials!D14/1000000 -> 14.036751 | E6: =Financials!E14/1000000 -> 13.332837 | F6: =Financials!F14/1000000 -> 12.706989 | G6: =Financials!G14/1000000 -> 13.62263 | H6: =Financials!H14/1000000 -> 14.515738 | I6: =Financials!I14/1000000 -> 14.825099 | J6: =Financials!J14/1000000 -> 15.487364 | ... AK6: =Financials!AK14/1000000 -> 2.4547051
A7: Core capital /Total Assets | B7: ≥ 10% | C7: =Financials!C14/Financials!C5 -> 0.21906029 | D7: =Financials!D14/Financials!D5 -> 0.22275825 | E7: =Financials!E14/Financials!E5 -> 0.21097088 | F7: =Financials!F14/Financials!F5 -> 0.20557807 | G7: =Financials!G14/Financials!G5 -> 0.21649638 | H7: =Financials!H14/Financials!H5 -> 0.230453 | I7: =Financials!I14/Financials!I5 -> 0.23353892 | J7: =Financials!J14/Financials!J5 -> 0.24182064 | ... AK7: =Financials!AK14/Financials!AK5 -> 0.031644162
A8: Core capital /Total Deposits | B8: ≥ 8% | C8: =Financials!C14/Financials!C6 -> 0.28672526 | D8: =Financials!D14/Financials!D6 -> 0.29277308 | E8: =Financials!E14/Financials!E6 -> 0.27746168 | F8: =Financials!F14/Financials!F6 -> 0.26726449 | G8: =Financials!G14/Financials!G6 -> 0.28471963 | H8: =Financials!H14/Financials!H6 -> 0.30776735 | I8: =Financials!I14/Financials!I6 -> 0.31319463 | J8: =Financials!J14/Financials!J6 -> 0.32470604 | ... AK8: =Financials!AK14/Financials!AK6 -> 0.044483791
A9: Share Capital/Total Assets | B9: ≤2% | C9: =Financials!C18/Financials!C5 -> 0.1589123 | D9: =Financials!D18/Financials!D5 -> 0.15934178 | E9: =Financials!E18/Financials!E5 -> 0.15887887 | F9: =Financials!F18/Financials!F5 -> 0.16241709 | G9: =Financials!G18/Financials!G5 -> 0.15954649 | H9: =Financials!H18/Financials!H5 -> 0.15952927 | I9: =Financials!I18/Financials!I5 -> 0.15831672 | J9: =Financials!J18/Financials!J5 -> 0.15755895 | ... AK9: =Financials!AK18/Financials!AK5 -> 0
A10: Institutional Capital/Total Assets | B10: ≥ 8% | C10: =Financials!C15/Financials!C5 -> 0.060147991 | D10: =Financials!D15/Financials!D5 -> 0.063416466 | E10: =Financials!E15/Financials!E5 -> 0.052092014 | F10: =Financials!F15/Financials!F5 -> 0.043160981 | G10: =Financials!G15/Financials!G5 -> 0.05694989 | H10: =Financials!H15/Financials!H5 -> 0.070923731 | I10: =Financials!I15/Financials!I5 -> 0.075222199 | J10: =Financials!J15/Financials!J5 -> 0.084261694 | ... AK10: =Financials!AK15/Financials!AK5 -> 0.031644162
A12: ASSET MIX AND QUALITY
A13: Non Earning Assets
A14: Non earning Assets/Total assets | B14: ≤ 10% | C14: =Financials!C38/Financials!C5 -> 0.034714074 | D14: =Financials!D38/Financials!D5 -> 0.034653052 | E14: =Financials!E38/Financials!E5 -> 0.029670774 | F14: =Financials!F38/Financials!F5 -> 0.026963361 | G14: =Financials!G38/Financials!G5 -> 0.025555134 | H14: =Financials!H38/Financials!H5 -> 0.022218928 | I14: =Financials!I38/Financials!I5 -> 0.021912904 | J14: =Financials!J38/Financials!J5 -> 0.018464391 | ... AK14: =Financials!AK38/Financials!AK5 -> 0.025298742
A15: Property and Equipment/Total Assets | B15: ≤ 5% | C15: =Financials!C39/Financials!C5 -> 0.0077289344 | D15: =Financials!D39/Financials!D5 -> 0.0076106533 | E15: =Financials!E39/Financials!E5 -> 0.0074541899 | F15: =Financials!F39/Financials!F5 -> 0.0074840971 | G15: =Financials!G39/Financials!G5 -> 0.0072169469 | H15: =Financials!H39/Financials!H5 -> 0.007074797 | I15: =Financials!I39/Financials!I5 -> 0.0068862331 | J15: =Financials!J39/Financials!J5 -> 0.0066930109 | ... AK15: =Financials!AK39/Financials!AK5 -> 0.0050015864
A16: Non Performing loans/Gross Loans | B16: ≤ 6% | C16: =Financials!C34/Financials!C32 -> 0 | D16: =Financials!D34/Financials!D32 -> 0 | E16: =Financials!E34/Financials!E32 -> 0 | F16: =Financials!F34/Financials!F32 -> 0 | G16: =Financials!G34/Financials!G32 -> 0 | H16: =Financials!H34/Financials!H32 -> 0 | I16: =Financials!I34/Financials!I32 -> 0 | J16: =Financials!J34/Financials!J32 -> 0 | ... AK16: =Financials!AK34/Financials!AK32 -> 0
A18: Earning Assets
A19: Equities & Investments/Deposits | B19: ≤ 5% | C19: =Financials!C26/Financials!C6 -> 0.049852434 | D19: =Financials!D26/Financials!D6 -> 0.051103722 | E19: =Financials!E26/Financials!E6 -> 0.050988056 | F19: =Financials!F26/Financials!F6 -> 0.0534261 | G19: =Financials!G26/Financials!G6 -> 0.054030346 | H19: =Financials!H26/Financials!H6 -> 0.056032851 | I19: =Financials!I26/Financials!I6 -> 0.056781745 | J19: =Financials!J26/Financials!J6 -> 0.057405169 | ... AK19: =Financials!AK26/Financials!AK6 -> 0.065637103
A20: Equities & Investments/Core Capital | B20: ≤ 40% | C20: =Financials!C26/Financials!C14 -> 0.1738683 | D20: =Financials!D26/Financials!D14 -> 0.17455062 | E20: =Financials!E26/Financials!E14 -> 0.18376612 | F20: =Financials!F26/Financials!F14 -> 0.19989973 | G20: =Financials!G26/Financials!G14 -> 0.18976685 | H20: =Financials!H26/Financials!H14 -> 0.18206237 | I20: =Financials!I26/Financials!I14 -> 0.18129859 | J20: =Financials!J26/Financials!J14 -> 0.17679119 | ... AK20: =Financials!AK26/Financials!AK14 -> 1.4755286
A21: Net Loans & advances /Total assets | B21: NPR | C21: =Financials!C31/Financials!C5 -> 0.66157824 | D21: =Financials!D31/Financials!D5 -> 0.69317958 | E21: =Financials!E31/Financials!E5 -> 0.65707047 | F21: =Financials!F31/Financials!F5 -> 0.64894121 | G21: =Financials!G31/Financials!G5 -> 0.61666527 | H21: =Financials!H31/Financials!H5 -> 0.63371524 | I21: =Financials!I31/Financials!I5 -> 0.66635432 | J21: =Financials!J31/Financials!J5 -> 0.60996583 | ... AK21: =Financials!AK31/Financials!AK5 -> 0.63425447
A22: NPL
A23: FUNDING MIX
A24: Total Deposits/Total Assets | B24: NPR | C24: =Financials!C6/Financials!C5 -> 0.76400764 | D24: =Financials!D6/Financials!D5 -> 0.76085634 | E24: =Financials!E6/Financials!E5 -> 0.76036044 | F24: =Financials!F6/Financials!F5 -> 0.76919336 | G24: =Financials!G6/Financials!G5 -> 0.76038444 | H24: =Financials!H6/Financials!H5 -> 0.74878964 | I24: =Financials!I6/Financials!I5 -> 0.74566706 | J24: =Financials!J6/Financials!J5 -> 0.74473712 | ... AK24: =Financials!AK6/Financials!AK5 -> 0.71136389
A25: BOSA Deposits/Total Assets | B25: NPR | C25: =Financials!C7/Financials!C5 -> 0.6752426 | D25: =Financials!D7/Financials!D5 -> 0.68164259 | E25: =Financials!E7/Financials!E5 -> 0.67492573 | F25: =Financials!F7/Financials!F5 -> 0.6895852 | G25: =Financials!G7/Financials!G5 -> 0.67905181 | H25: =Financials!H7/Financials!H5 -> 0.6795722 | I25: =Financials!I7/Financials!I5 -> 0.67918963 | J25: =Financials!J7/Financials!J5 -> 0.6751107 | ... AK25: =Financials!AK7/Financials!AK5 -> 0.64822165
A26: FOSA Deposits/Total Assets | B26: NPR | C26: =Financials!C8/Financials!C5 -> 0.072835558 | D26: =Financials!D8/Financials!D5 -> 0.067263913 | E26: =Financials!E8/Financials!E5 -> 0.065607974 | F26: =Financials!F8/Financials!F5 -> 0.06176344 | G26: =Financials!G8/Financials!G5 -> 0.071749506 | H26: =Financials!H8/Financials!H5 -> 0.059644166 | I26: =Financials!I8/Financials!I5 -> 0.056978407 | J26: =Financials!J8/Financials!J5 -> 0.060211135 | ... AK26: =Financials!AK8/Financials!AK5 -> 0.050856901
A27: External Borrowing/Total assets | B27: ≤ 25% | C27: =Financials!C9/Financials!C5 -> 0 | D27: =Financials!D9/Financials!D5 -> 0 | E27: =Financials!E9/Financials!E5 -> 0 | F27: =Financials!F9/Financials!F5 -> 0 | G27: =Financials!G9/Financials!G5 -> 0 | H27: =Financials!H9/Financials!H5 -> 0 | I27: =Financials!I9/Financials!I5 -> 0 | J27: =Financials!J9/Financials!J5 -> 0 | ... AK27: =Financials!AK9/Financials!AK5 -> 0.71218023
A29: GROWTH RATIOS
A30: Total Assets | B30: NPR | C30: =Financials!C5/Financials!#REF!-1 -> #REF! | D30: =Financials!D5/Financials!#REF!-1 -> #REF! | E30: =Financials!E5/Financials!#REF!-1 -> #REF! | F30: =Financials!F5/Financials!#REF!-1 -> #REF! | G30: =Financials!G5/Financials!#REF!-1 -> #REF! | H30: =Financials!H5/Financials!#REF!-1 -> #REF! | I30: =Financials!I5/Financials!#REF!-1 -> #REF! | J30: =Financials!J5/Financials!#REF!-1 -> #REF! | ... AK30: =Financials!AK5/Financials!#REF!-1 -> #REF!
A31: Total Deposits | B31: NPR | C31: =Financials!C6/Financials!#REF!-1 -> #REF! | D31: =Financials!D6/Financials!#REF!-1 -> #REF! | E31: =Financials!E6/Financials!#REF!-1 -> #REF! | F31: =Financials!F6/Financials!#REF!-1 -> #REF! | G31: =Financials!G6/Financials!#REF!-1 -> #REF! | H31: =Financials!H6/Financials!#REF!-1 -> #REF! | I31: =Financials!I6/Financials!#REF!-1 -> #REF! | J31: =Financials!J6/Financials!#REF!-1 -> #REF! | ... AK31: =Financials!AK6/Financials!#REF!-1 -> #REF!
A32: FOSA Deposits | B32: NPR | C32: =Financials!C7/Financials!#REF!-1 -> #REF! | D32: =Financials!D7/Financials!#REF!-1 -> #REF! | E32: =Financials!E7/Financials!#REF!-1 -> #REF! | F32: =Financials!F7/Financials!#REF!-1 -> #REF! | G32: =Financials!G7/Financials!#REF!-1 -> #REF! | H32: =Financials!H7/Financials!#REF!-1 -> #REF! | I32: =Financials!I7/Financials!#REF!-1 -> #REF! | J32: =Financials!J7/Financials!#REF!-1 -> #REF! | ... AK32: =Financials!AK7/Financials!#REF!-1 -> #REF!
A33: BOSA Deposits | B33: NPR | C33: =Financials!C8/Financials!#REF!-1 -> #REF! | D33: =Financials!D8/Financials!#REF!-1 -> #REF! | E33: =Financials!E8/Financials!#REF!-1 -> #REF! | F33: =Financials!F8/Financials!#REF!-1 -> #REF! | G33: =Financials!G8/Financials!#REF!-1 -> #REF! | H33: =Financials!H8/Financials!#REF!-1 -> #REF! | I33: =Financials!I8/Financials!#REF!-1 -> #REF! | J33: =Financials!J8/Financials!#REF!-1 -> #REF! | ... AK33: =Financials!AK8/Financials!#REF!-1 -> #REF!
A34: Net Loans & advances | B34: NPR | C34: =Financials!C9/Financials!#REF!-1 -> #REF! | D34: =Financials!D9/Financials!#REF!-1 -> #REF! | E34: =Financials!E9/Financials!#REF!-1 -> #REF! | F34: =Financials!F9/Financials!#REF!-1 -> #REF! | G34: =Financials!G9/Financials!#REF!-1 -> #REF! | H34: =Financials!H9/Financials!#REF!-1 -> #REF! | I34: =Financials!I9/Financials!#REF!-1 -> #REF! | J34: =Financials!J9/Financials!#REF!-1 -> #REF! | ... AK34: =Financials!AK9/Financials!#REF!-1 -> #REF!
A35: Core capital | B35: NPR | C35: =Financials!C10/Financials!#REF!-1 -> #REF! | D35: =Financials!D10/Financials!#REF!-1 -> #REF! | E35: =Financials!E10/Financials!#REF!-1 -> #REF! | F35: =Financials!F10/Financials!#REF!-1 -> #REF! | G35: =Financials!G10/Financials!#REF!-1 -> #REF! | H35: =Financials!H10/Financials!#REF!-1 -> #REF! | I35: =Financials!I10/Financials!#REF!-1 -> #REF! | J35: =Financials!J10/Financials!#REF!-1 -> #REF! | ... AK35: =Financials!AK10/Financials!#REF!-1 -> #REF!
A36: Total Gross Income | B36: NPR | C36: =Financials!C11/Financials!#REF!-1 -> #REF! | D36: =Financials!D11/Financials!#REF!-1 -> #REF! | E36: =Financials!E11/Financials!#REF!-1 -> #REF! | F36: =Financials!F11/Financials!#REF!-1 -> #REF! | G36: =Financials!G11/Financials!#REF!-1 -> #REF! | H36: =Financials!H11/Financials!#REF!-1 -> #REF! | I36: =Financials!I11/Financials!#REF!-1 -> #REF! | J36: =Financials!J11/Financials!#REF!-1 -> #REF! | ... AK36: =Financials!AK11/Financials!#REF!-1 -> #REF!
A37: Membership | B37: NPR | C37: =Financials!C12/Financials!#REF!-1 -> #REF! | D37: =Financials!D12/Financials!#REF!-1 -> #REF! | E37: =Financials!E12/Financials!#REF!-1 -> #REF! | F37: =Financials!F12/Financials!#REF!-1 -> #REF! | G37: =Financials!G12/Financials!#REF!-1 -> #REF! | H37: =Financials!H12/Financials!#REF!-1 -> #REF! | I37: =Financials!I12/Financials!#REF!-1 -> #REF! | J37: =Financials!J12/Financials!#REF!-1 -> #REF! | ... AK37: =Financials!AK12/Financials!#REF!-1 -> #REF!
A39: Efficiency Ratios
A40: FinCost-Deposits/Average Deposits | B40: NPR | C40: =Financials!C48/((Financials!C6+Financials!#REF!)/2) -> #REF! | D40: =Financials!D48/((Financials!D6+Financials!#REF!)/2) -> #REF! | E40: =Financials!E48/((Financials!E6+Financials!#REF!)/2) -> #REF! | F40: =Financials!F48/((Financials!F6+Financials!#REF!)/2) -> #REF! | G40: =Financials!G48/((Financials!G6+Financials!#REF!)/2) -> #REF! | H40: =Financials!H48/((Financials!H6+Financials!#REF!)/2) -> #REF! | I40: =Financials!I48/((Financials!I6+Financials!#REF!)/2) -> #REF! | J40: =Financials!J48/((Financials!J6+Financials!#REF!)/2) -> #REF! | ... AK40: =Financials!AK48/((Financials!AK6+Financials!#REF!)/2) -> #REF!
A41: FinCost-Shares/Average Share capital | B41: NPR | C41: =Financials!C49/((Financials!C7+Financials!#REF!)/2) -> #REF! | D41: =Financials!D49/((Financials!D7+Financials!#REF!)/2) -> #REF! | E41: =Financials!E49/((Financials!E7+Financials!#REF!)/2) -> #REF! | F41: =Financials!F49/((Financials!F7+Financials!#REF!)/2) -> #REF! | G41: =Financials!G49/((Financials!G7+Financials!#REF!)/2) -> #REF! | H41: =Financials!H49/((Financials!H7+Financials!#REF!)/2) -> #REF! | I41: =Financials!I49/((Financials!I7+Financials!#REF!)/2) -> #REF! | J41: =Financials!J49/((Financials!J7+Financials!#REF!)/2) -> #REF! | ... AK41: =Financials!AK49/((Financials!AK7+Financials!#REF!)/2) -> #REF!
A42: FinCost-Ext Loans/Average Ext Loans | B42: NPR | C42: =Financials!C50/((Financials!C8+Financials!#REF!)/2) -> #REF! | D42: =Financials!D50/((Financials!D8+Financials!#REF!)/2) -> #REF! | E42: =Financials!E50/((Financials!E8+Financials!#REF!)/2) -> #REF! | F42: =Financials!F50/((Financials!F8+Financials!#REF!)/2) -> #REF! | G42: =Financials!G50/((Financials!G8+Financials!#REF!)/2) -> #REF! | H42: =Financials!H50/((Financials!H8+Financials!#REF!)/2) -> #REF! | I42: =Financials!I50/((Financials!I8+Financials!#REF!)/2) -> #REF! | J42: =Financials!J50/((Financials!J8+Financials!#REF!)/2) -> #REF! | ... AK42: =Financials!AK50/((Financials!AK8+Financials!#REF!)/2) -> #REF!
A43: OpEx/Average Total Assets | B43: NPR | C43: =Financials!C51/((Financials!C9+Financials!#REF!)/2) -> #REF! | D43: =Financials!D51/((Financials!D9+Financials!#REF!)/2) -> #REF! | E43: =Financials!E51/((Financials!E9+Financials!#REF!)/2) -> #REF! | F43: =Financials!F51/((Financials!F9+Financials!#REF!)/2) -> #REF! | G43: =Financials!G51/((Financials!G9+Financials!#REF!)/2) -> #REF! | H43: =Financials!H51/((Financials!H9+Financials!#REF!)/2) -> #REF! | I43: =Financials!I51/((Financials!I9+Financials!#REF!)/2) -> #REF! | J43: =Financials!J51/((Financials!J9+Financials!#REF!)/2) -> #REF! | ... AK43: =Financials!AK51/((Financials!AK9+Financials!#REF!)/2) -> #REF!
A44: Avge yield on Net loans | B44: NPR | C44: =Financials!C52/((Financials!C10+Financials!#REF!)/2) -> #REF! | D44: =Financials!D52/((Financials!D10+Financials!#REF!)/2) -> #REF! | E44: =Financials!E52/((Financials!E10+Financials!#REF!)/2) -> #REF! | F44: =Financials!F52/((Financials!F10+Financials!#REF!)/2) -> #REF! | G44: =Financials!G52/((Financials!G10+Financials!#REF!)/2) -> #REF! | H44: =Financials!H52/((Financials!H10+Financials!#REF!)/2) -> #REF! | I44: =Financials!I52/((Financials!I10+Financials!#REF!)/2) -> #REF! | J44: =Financials!J52/((Financials!J10+Financials!#REF!)/2) -> #REF! | ... AK44: =Financials!AK52/((Financials!AK10+Financials!#REF!)/2) -> #REF!
A46: Liquidity Ratio
A47: minimum Liquidity | B47: 0.15 | C47: =SFP!B4/(SFP!B29+SFP!B31-SFP!B37) -> 0.2494857 | D47: =SFP!C4/(SFP!C29+SFP!C31-SFP!C37) -> 0.2004226 | E47: =SFP!D4/(SFP!D29+SFP!D31-SFP!D37) -> 0.23555581 | F47: =SFP!E4/(SFP!E29+SFP!E31-SFP!E37) -> 0.24038821 | G47: =SFP!F4/(SFP!F29+SFP!F31-SFP!F37) -> 0.2810917 | H47: =SFP!G4/(SFP!G29+SFP!G31-SFP!G37) -> 0.26102868 | I47: =SFP!H4/(SFP!H29+SFP!H31-SFP!H37) -> 0.21540485 | J47: =SFP!I4/(SFP!I29+SFP!I31-SFP!I37) -> 0.30748736 | ... AK47: =SFP!AJ4/(SFP!AJ29+SFP!AJ31-SFP!AJ37) -> 0.29211511
A48: technical Liquidity | C48: =SFP!B4/(SFP!B30+SFP!B31-SFP!B37) -> 0.22093874 | D48: =SFP!C4/(SFP!C30+SFP!C31-SFP!C37) -> 0.17985892 | E48: =SFP!D4/(SFP!D30+SFP!D31-SFP!D37) -> 0.20988185 | F48: =SFP!E4/(SFP!E30+SFP!E31-SFP!E37) -> 0.21613765 | G48: =SFP!F4/(SFP!F30+SFP!F31-SFP!F37) -> 0.25171775 | H48: =SFP!G4/(SFP!G30+SFP!G31-SFP!G37) -> 0.23739079 | I48: =SFP!H4/(SFP!H30+SFP!H31-SFP!H37) -> 0.19659572 | J48: =SFP!I4/(SFP!I30+SFP!I31-SFP!I37) -> 0.27905818 | ... AK48: =SFP!AJ4/(SFP!AJ30+SFP!AJ31-SFP!AJ37) -> 0.26621604
A49: Loan Loss Provisions Ratios
A50: Actual LLP / Required LLP | B50: 1
A52: Loan interest/Net Loans | C52: =SCI!B5/SFP!#REF! -> #REF! | D52: =SCI!C5/SFP!#REF! -> #REF! | E52: =SCI!D5/SFP!#REF! -> #REF! | F52: =SCI!E5/SFP!#REF! -> #REF! | G52: =SCI!F5/SFP!#REF! -> #REF! | H52: =SCI!G5/SFP!#REF! -> #REF! | I52: =SCI!H5/SFP!#REF! -> #REF! | J52: =SCI!I5/SFP!#REF! -> #REF! | ... AK52: =SCI!AJ5/SFP!#REF! -> #REF!
A54: RETURN ON ASSETS | C54: =SCI!B33/((SFP!#REF!+SFP!#REF!)/2) -> #REF! | D54: =SCI!C33/((SFP!#REF!+SFP!#REF!)/2) -> #REF! | E54: =SCI!D33/((SFP!#REF!+SFP!#REF!)/2) -> #REF! | F54: =SCI!E33/((SFP!#REF!+SFP!#REF!)/2) -> #REF! | G54: =SCI!F33/((SFP!#REF!+SFP!#REF!)/2) -> #REF! | H54: =SCI!G33/((SFP!#REF!+SFP!#REF!)/2) -> #REF! | I54: =SCI!H33/((SFP!#REF!+SFP!#REF!)/2) -> #REF! | J54: =SCI!I33/((SFP!#REF!+SFP!#REF!)/2) -> #REF! | ... AK54: =SCI!AJ33/((SFP!#REF!+SFP!#REF!)/2) -> #REF!
A55: COST INCOME RATIO | C55: =SCI!B23/SCI!B19 -> 0.76151334 | D55: =SCI!C23/SCI!C19 -> 0.5006653 | E55: =SCI!D23/SCI!D19 -> 0.56428289 | F55: =SCI!E23/SCI!E19 -> 0.63625766 | G55: =SCI!F23/SCI!F19 -> 0.60024689 | H55: =SCI!G23/SCI!G19 -> 0.59975129 | I55: =SCI!H23/SCI!H19 -> 0.60874907 | J55: =SCI!I23/SCI!I19 -> 0.58160632 | ... AK55: =SCI!AJ23/SCI!AJ19 -> 0.66386059
A56: OPERATING EXPENSE RATIO | C56: =SCI!B23/SFP!#REF! -> #REF! | D56: =SCI!C23/SFP!#REF! -> #REF! | E56: =SCI!D23/SFP!#REF! -> #REF! | F56: =SCI!E23/SFP!#REF! -> #REF! | G56: =SCI!F23/SFP!#REF! -> #REF! | H56: =SCI!G23/SFP!#REF! -> #REF! | I56: =SCI!H23/SFP!#REF! -> #REF! | J56: =SCI!I23/SFP!#REF! -> #REF! | ... AK56: =SCI!AJ23/SFP!#REF! -> #REF!
A57: LIQUID ASSETS/TOTAL ASSETS | C57: =(Financials!C36+Financials!C29)/Financials!C5 -> 0.20948323 | D57: =(Financials!D36+Financials!D29)/Financials!D5 -> 0.17774298 | E57: =(Financials!E36+Financials!E29)/Financials!E5 -> 0.20328608 | F57: =(Financials!F36+Financials!F29)/Financials!F5 -> 0.21165592 | G57: =(Financials!G36+Financials!G29)/Financials!G5 -> 0.23699731 | H57: =(Financials!H36+Financials!H29)/Financials!H5 -> 0.22340763 | I57: =(Financials!I36+Financials!I29)/Financials!I5 -> 0.19201042 | J57: =(Financials!J36+Financials!J29)/Financials!J5 -> 0.25290292 | ... AK57: =(Financials!AK36+Financials!AK29)/Financials!AK5 -> 0.23628567
A58: ALLOWANCE FOR LOAN LOSS/NON PERFORMING L0ANS
A59: GROSS LOANS/TOTAL ASSETS | C59: =Financials!C32/Financials!C5 -> 0.82701547 | D59: =Financials!D32/Financials!D5 -> 0.86515121 | E59: =Financials!E32/Financials!E5 -> 0.83169737 | F59: =Financials!F32/Financials!F5 -> 0.83840307 | G59: =Financials!G32/Financials!G5 -> 0.79370132 | H59: =Financials!H32/Financials!H5 -> 0.80310966 | I59: =Financials!I32/Financials!I5 -> 0.83402623 | J59: =Financials!J32/Financials!J5 -> 0.77220423 | ... AK59: =Financials!AK32/Financials!AK5 -> 0.74704583

Sheet form4 
B1: FORM 4 SASRA2/004
B2: RISK CLASSIFICATION OF ASSETS AND PROVISIONING
B3: SACCO SOCIETY CS NUMBER | F3: 2032
B4: FINANCIAL YEAR | F4: 2016
B5: START DATE: | F5: 1/1/2018
B6: END DATE: | F6: 31/3/2018
B7: PORTFOLIO AGEING REPORT
C8: A | D8: B | E8: C | F8: D
A9: NO. | B9: CLASSIFICATION | C9: NO. OF A/Cs | D9: OUTSTANDING LOAN PORTFOLIO(Kshs) | E9: REQUIRED PROVISION | F9: REQUIRED PROVISION AMOUNT(Kshs)
A10: 1 | B10: Performing | C10: 7828 | D10: 4.0796422e+08 | E10: 0.01 | F10: =D10*E10 -> 4079642.2
A11: 2 | B11: Watch | C11: 857 | D11: 1.0609857e+08 | E11: 0.05 | F11: =D11*E11 -> 5304928.5
A12: 3 | B12: Substandard | C12: 353 | D12: 40541696 | E12: 0.25 | F12: =D12*E12 -> 10135424
A13: 4 | B13: Doubtful | C13: 146 | D13: 16738133 | E13: 0.5 | F13: =D13*E13 -> 8369066.6
A14: 5 | B14: Loss | C14: 95 | D14: 19768434 | E14: 1 | F14: =D14*E14 -> 19768434 | G14: =SUM(D12:D14) -> 77048264
B15: subtotal | C15: =SUM(C10:C14) -> 9279 | D15: =SUM(D10:D14) -> 5.9111105e+08 | F15: =SUM(F10:F14) -> 47657496
B16: Reschedule/Renegotiated loans
A17: 1 | B17: Performing | C17: 0 | D17: 0 | E17: 0.01 | F17: =D17*E17 -> 0
A18: 2 | B18: Watch | C18: 0 | E18: 0.05 | F18: =D18*E18 -> 0
A19: 3 | B19: Substandard | E19: 0.25 | F19: =D19*E19 -> 0
A20: 4 | B20: Doubtful | C20: 0 | D20: 0 | E20: 0.5 | F20: =D20*E20 -> 0
A21: 5 | B21: Loss | C21: 0 | D21: 0 | E21: 1 | F21: =D21*E21 -> 0
B22: subtotal | C22: =SUM(C16:C21) -> 0 | D22: =SUM(D16:D21) -> 0 | F22: =SUM(F16:F21) -> 0
B23: GRAND TOTAL | C23: =C15+C22 -> 9279 | D23: =D15+D22 -> 5.9111105e+08 | F23: =F15+F22 -> 47657496
A25: Note: This return should be received on or before the 15th day of the month following end of every quarter
B28: FORM 4 SASRA2/004
B29: RISK CLASSIFICATION OF ASSETS AND PROVISIONING
B30: SACCO SOCIETY CS NUMBER | F30: 2032
B31: FINANCIAL YEAR | F31: 2016
B32: START DATE: | F32: 1/1/2018
B33: END DATE: | F33: 31/6/2018
B34: PORTFOLIO AGEING REPORT
C35: A | D35: B | E35: C | F35: D
A36: NO. | B36: CLASSIFICATION | C36: NO. OF A/Cs | D36: OUTSTANDING LOAN PORTFOLIO(Kshs) | E36: REQUIRED PROVISION | F36: REQUIRED PROVISION AMOUNT(Kshs)
A37: 1 | B37: Performing | C37: 7269 | D37: 3.9579531e+08 | E37: 0.01 | F37: =D37*E37 -> 3957953.1
A38: 2 | B38: Watch | C38: 1041 | D38: 97770529 | E38: 0.05 | F38: =D38*E38 -> 4888526.4
A39: 3 | B39: Substandard | C39: 772 | D39: 51701232 | E39: 0.25 | F39: =D39*E39 -> 12925308
A40: 4 | B40: Doubtful | C40: 377 | D40: 28331436 | E40: 0.5 | F40: =D40*E40 -> 14165718
A41: 5 | B41: Loss | C41: 639 | D41: 26413438 | E41: 1 | F41: =D41*E41 -> 26413438 | G41: =SUM(D39:D41) -> 1.064461e+08
B42: subtotal | C42: =SUM(C37:C41) -> 10098 | D42: =SUM(D37:D41) -> 6.0001195e+08 | F42: =SUM(F37:F41) -> 62350943
B43: Reschedule/Renegotiated loans
A44: 1 | B44: Performing | C44: 0 | D44: 0 | E44: 0.01 | F44: =D44*E44 -> 0
A45: 2 | B45: Watch | C45: 0 | E45: 0.05 | F45: =D45*E45 -> 0
A46: 3 | B46: Substandard | E46: 0.25 | F46: =D46*E46 -> 0 | G46: =SUM(D39:D41) -> 1.064461e+08
A47: 4 | B47: Doubtful | C47: 0 | D47: 0 | E47: 0.5 | F47: =D47*E47 -> 0 | G47: =G46/D42 -> 0.17740664
A48: 5 | B48: Loss | C48: 0 | D48: 0 | E48: 1 | F48: =D48*E48 -> 0
B49: subtotal | C49: =SUM(C43:C48) -> 0 | D49: =SUM(D43:D48) -> 0 | F49: =SUM(F43:F48) -> 0
B50: GRAND TOTAL | C50: =C42+C49 -> 10098 | D50: =D42+D49 -> 6.0001195e+08 | F50: =F42+F49 -> 62350943
A52: Note: This return should be received on or before the 15th day of the month following end of every quarter
B54: FORM 4 SASRA2/004
B55: RISK CLASSIFICATION OF ASSETS AND PROVISIONING
B56: SACCO SOCIETY CS NUMBER | F56: 2032
B57: FINANCIAL YEAR | F57: 2018
B58: START DATE: | F58: 1/1/2018
B59: END DATE: | F59: 30/9/2018
B60: PORTFOLIO AGEING REPORT
C61: A | D61: B | E61: C | F61: D
B62: CLASSIFICATION | C62: NO. OF A/Cs | D62: OUTSTANDING LOAN PORTFOLIO(Kshs) | E62: REQUIRED PROVISION | F62: REQUIRED PROVISION AMOUNT(Kshs)
B63: Performing | C63: 6517 | D63: 3.7477319e+08 | E63: 0.01 | F63: =D63*E63 -> 3747731.9
B64: Watch | C64: 1404 | D64: 1.5133837e+08 | E64: 0.05 | F64: =D64*E64 -> 7566918.7
B65: Substandard | C65: 685 | D65: 60509701 | E65: 0.25 | F65: =D65*E65 -> 15127425
B66: Doubtful | C66: 335 | D66: 25541760 | E66: 0.5 | F66: =D66*E66 -> 12770880
B67: Loss | C67: 543 | D67: 22647916 | E67: 1 | F67: =D67*E67 -> 22647916
B68: subtotal | C68: =SUM(C63:C67) -> 9484 | D68: =SUM(D63:D67) -> 6.3481094e+08 | F68: =SUM(F63:F67) -> 61860872
B69: Reschedule/Renegotiated loans
B70: Performing | C70: 0 | D70: 0 | E70: 0.01 | F70: =D70*E70 -> 0
B71: Watch | C71: 0 | E71: 0.05 | F71: =D71*E71 -> 0
B72: Substandard | E72: 0.25 | F72: =D72*E72 -> 0
B73: Doubtful | C73: 0 | D73: 0 | E73: 0.5 | F73: =D73*E73 -> 0
B74: Loss | C74: 0 | D74: 0 | E74: 1 | F74: =D74*E74 -> 0
B75: subtotal | C75: =SUM(C69:C74) -> 0 | D75: =SUM(D69:D74) -> 0 | F75: =SUM(F69:F74) -> 0
B76: GRAND TOTAL | C76: =C68+C75 -> 9484 | D76: =D68+D75 -> 6.3481094e+08 | F76: =F68+F75 -> 61860872

Sheet Sacco Performance
A1: ELIMU SACCO SOCIETY LIMITED
A2: PERFORMANCE AND COMPLIANCE REPORT AS AT : 30th September , 2018
B3: Prud Std | C3: Audited | D3: Returns | H3: Aggregate for all Licensed Saccos
C4: 2017 | D4: 43177 | E4: 43269 | F4: Validated July 2018 | G4: 43361
A5: A. CAPITAL ADEQUACY
A6: Core Capital | B6: ≥10M | C6: =C33 -> #REF! | D6: =D33 -> 13915096 | E6: =E33 -> 13346436 | F6: =F33 -> 2.2099178e+08 | G6: =G33 -> 14304639 | H6: =H33 -> 68610901181
A7: Core Capital/Total Assets | B7: ≥10% | C7: =C33/C29 -> #REF! | D7: =D33/D29 -> 0.012788119 | E7: =E33/E29 -> 0.012677157 | F7: =F33/F29 -> 0.20503177 | G7: =G33/G29 -> 0.013106769 | H7: =H33/H29 -> 0.14576061
A8: Institutional Capital/Total Assets | B8: ≥8% | C8: =C34/C29 -> #REF! | D8: =D34/D29 -> 0.003560643 | E8: =E34/E29 -> 0.0031414223 | F8: =F34/F29 -> 0.095871936 | G8: =G34/G29 -> 0.0039068307 | H8: =H34/H29 -> 0.080885761
A9: B. ASSET QUALITY
A10: NPL (Substandard+Doubtful+Loss) | B10: <5% | C10: =C35/C32 -> 0.15518115 | D10: =D35/D32 -> 0 | E10: =E35/E32 -> 0.17740664 | F10: =F35/F32 -> 0.24924475 | G10: =G35/G32 -> 0 | H10: =H35/H32 -> 0.073088911
A11: Non-Earning Assets | B11: <10% | C11: =C36/C29 -> 0.19600848 | D11: =D36/D29 -> 0.22705784 | E11: =E36/E29 -> 0.18079154 | F11: =F36/F29 -> 0.20917825 | G11: =G36/G29 -> 0.21814514 | H11: =H36/H29 -> 0.12029808
A12: Equity investments/Deposits | B12: <5% | C12: =C38/C31 -> 0.18442583 | D12: =D38/D31 -> 0.1891277 | E12: =E38/E31 -> 0.18474351 | F12: =F38/F31 -> 0.1839376 | G12: =G38/G31 -> 0.18073695 | H12: =H38/H31 -> 0.041108343
A13: Equity investments/Core capital | B13: <40% | C13: =C38/C33 -> #REF! | D13: =D38/D33 -> 10.792609 | E13: =E38/E33 -> 11.252457 | F13: =F38/F33 -> 0.67957365 | G13: =G38/G33 -> 10.498706 | H13: =H38/H33 -> 0.19682259
A14: C. EARNINGS RATING
A15: Yield on Gross Loans | C15: =C44/C32 -> 0.22818323 | D15: =D44/D32 -> 0.077318822 | E15: =E44/E32 -> 0.15889458 | F15: =F44/F32 -> 0.18194977 | G15: =G44/G32 -> 0.22085733 | H15: =H44/H32 -> 0.094781906
A16: Total Expense/Total Income | C16: =C47/C43 -> 0.9138699 | D16: =D47/D43 -> 0.70485127 | E16: =E47/E43 -> 0.76136421 | F16: =F47/F43 -> 0.78869343 | G16: =G47/G43 -> 0.68993115 | H16: =H47/H43 -> 0.71962332
A17: Net Income/Average Assets (ROA) | C17: =C48/C30 -> 0.003791183 | D17: =D48/D30 -> 0.0097610884 | E17: =E48/E30 -> 0.016868344 | F17: =F48/F30 -> 0.022524417 | G17: =G48/G30 -> 0.033879707 | H17: =H48/H30 -> 0.02537129
A18: Operating Expenses/Financial Income (OPEX) | C18: =C46/C43 -> 0.7258397 | D18: =D46/D43 -> 0.69047378 | E18: =E46/E43 -> 0.73917345 | F18: =F46/F43 -> 0.70969989 | G18: =G46/G43 -> 0.66759028 | H18: =H46/H43 -> 0.34015828
A19: D. LIQUIDITY
A20: Liquid Assets/Short-term Liabilities | B20: >15% | C20: =C40/C41 -> 1.6100339 | D20: =D40/D41 -> 1.8231656 | E20: =E40/E41 -> 2.8116034 | F20: =F40/F41 -> 2.4337011 | G20: =G40/G41 -> 1.8877413 | H20: =H40/H41 -> 0.48530882
A21: External Borrowing/Total Assets | B21: <25% | C21: =C42/C29 -> 0 | D21: =D42/D29 -> 0 | E21: =E42/E29 -> 0 | F21: =F42/F29 -> 0 | G21: =G42/G29 -> 0 | H21: =H42/H29 -> 0.096313502
A22: Liquid Assets/Total Assets | C22: =C40/C29 -> 0.14699391 | D22: =D40/D29 -> 0.15140203 | E22: =E40/E29 -> 0.1588437 | F22: =F40/F29 -> 0.14013085 | G22: =G40/G29 -> 0.11447686 | H22: =H40/H29 -> 0.089910796
A23: E. STRUCTURE/SENSITIVITY TO RISK
A24: Gross loans /Total Assets | B24: 70-80 | C24: =C32/C29 -> 0.55689684 | D24: =D32/D29 -> 0.52756552 | E24: =E32/E29 -> 0.56992337 | F24: =F32/F29 -> 0.56614222 | G24: =G32/G29 -> 0.58165192 | H24: =H32/H29 -> 0.76593828
A25: Gross loans/Deposits | B25: >100% | C25: =C32/C31 -> 0.74803016 | D25: =D32/D31 -> 0.72293367 | E25: =E32/E31 -> 0.73810209 | F25: =F32/F31 -> 0.74737464 | G25: =G32/G31 -> 0.7639742 | H25: =H32/H31 -> 1.0975103
A26: Financial Investments/Total Assets | C26: =C39/C31 -> 0.20252188 | D26: =D39/D31 -> 0.19891937 | E26: =E39/E31 -> 0.18933826 | F26: =F39/F31 -> 0.18889199 | G26: =G39/G31 -> 0.18635655 | H26: =H39/H31 -> 0.063036125
A27: Dividends+Interest on Deposits/Total Income | C27: =C45/C43 -> 0.18406516 | D27: =D45/D43 -> 0 | E27: =E45/E43 -> 0 | F27: =F45/F43 -> 0.0018601715 | G27: =G45/G43 -> 0 | H27: =H45/H43 -> 0.30223696
A28: F. KEY FINANCIAL STATISTICS
A29: Total Assets | C29: 1041432343 | D29: 1088126951 | E29: 1052794079 | F29: 1.0778417e+09 | G29: 1091393186 | H29: 470709475259
A30: Average Assets | C30: 1.0415699e+09 | D30: 1.0543316e+09 | E30: 1023665177 | F30: 1.0596111e+09 | G30: 1046817819 | H30: 445555825332
A31: Total Deposits | C31: 775330209 | D31: 794067676 | E31: 812911867 | F31: 8.1647361e+08 | G31: 830932439 | H31: 328502062217
A32: Gross Loans | C32: 579970379 | D32: 574058263 | E32: 600011946 | F32: 6.1021167e+08 | G32: 634810944 | H32: 360534406503
A33: Core Capital | C33: =SFP!#REF!+SFP!#REF!+SFP!#REF!+(0.5*SFP!#REF!)+SFP!#REF!+SFP!#REF! -> #REF! | D33: =Financials!D59 -> 13915096 | E33: =Financials!G59 -> 13346436 | F33: 2.2099178e+08 | G33: =Financials!J59 -> 14304639 | H33: 68610901181
A34: Institutional Capital | C34: =C33-SFP!#REF! -> #REF! | D34: =D33-SFP!C39 -> 3874431.6 | E34: =E33-SFP!F39 -> 3307270.8 | F34: 1.0333477e+08 | G34: =G33-SFP!D39 -> 4263888.4 | H34: 38073694210
A35: Non-performing Loans | C35: 90000468 | D35: =Financials!D34 -> 0 | E35: 1.064461e+08 | F35: 152092052 | G35: =Financials!J34 -> 0 | H35: 26351067235
A36: Non-Earning Assets | C36: 204129574 | D36: 247067758 | E36: 190336258 | F36: 2.2546103e+08 | G36: 238082118 | H36: 56625446555
A37: Property and Equipment | C37: 64759978 | D37: 64759978 | E37: 67783475 | F37: 75924160 | G37: 91766559 | H37: 17662274541
A38: Equity Investments | C38: 142990915 | D38: 150180192 | E38: 150180192 | F38: 1.5018019e+08 | G38: 150180192 | H38: 13504175449
A39: Financial Investments | C39: 157021333 | D39: 157955444 | E39: 153915320 | F39: 1.5422532e+08 | G39: 154849705 | H39: 20707496977
A40: Liquid Assets | C40: 153084208 | D40: 164744634 | E40: 167229703 | F40: 1.5103887e+08 | G40: 124939267 | H40: 4.2321864e+10
A41: Short-term Liabilities) | C41: 95081359 | D41: 90361862 | E41: 59478411 | F41: 62061389 | G41: 66184528 | H41: 8.7206046e+10
A42: External Borrowing | C42: 0 | D42: 0 | E42: 0 | F42: 0 | G42: 0 | H42: 4.5335678e+10
A43: Total Income | C43: 162985758 | D43: 45032970 | E43: 97502294 | F43: 1.1295021e+08 | G43: 1.4340648e+08 | H43: 5.518931e+10
A44: Net Financial Income/Loss | C44: 132339514 | D44: 44385509 | E44: 95338643 | F44: 1.1102787e+08 | G44: 1.4020265e+08 | H44: 3.4172138e+10
A45: Dividends+Interest on Deposits | C45: 30000000 | D45: 0 | E45: 0 | F45: 210106.76 | G45: 0 | H45: 1.6680249e+10
A46: Operating Expenses | C46: 118301534 | D46: 31094085 | E46: 72071107 | F46: 80160751 | G46: 95736770 | H46: 1.8773101e+10
A47: Total Expenses | C47: 148947778 | D47: 31741546 | E47: 74234757 | F47: 89083088 | G47: 98940596 | H47: 3.9715514e+10
A48: Net Income | C48: 3948782 | D48: 10291424 | E48: 17267537 | F48: 23867122 | G48: 35465881 | H48: 1.1304326e+10
A49: G. AREAS OF IMPROVEMENT/REGULATORY CONCERNS
A50: High NPL ratio at 17.1%
A51: High Non -earning assets ratio at 21.8%
A52: Non compliance with equity investments to total deposits and core capital ratios
A53: Gross loans to Total assets ratio below the industry standards
A54: Prepared by:
A56: Checked by:
A58: Approved by:
A60: DISCLAIMER: This report is prepared based on information submitted by the Sacco as at the stated date and may change upon verification by the Authority.

Sheet Sheet2
A2: VALIDATED JULY
A3: TB | D3: VALIDATED
A4: =SUM(A5:A6) -> 1.5103887e+08 | D4: =D5+D9 -> 1.1295021e+08
A5: 4845494.6 | D5: =SUM(D6:D7) -> 82211672
A6: 1.4619337e+08 | D6: 68900450
D7: 13311222
A8: 87068294
D9: =SUM(D10:D13) -> 30738538
A10: =SUM(A11:A14) -> 1.5422532e+08
D11: 6596616.2
D12: 9977330.8
A13: 4045128.4 | D13: 14164591
A14: 1.5018019e+08
D15: =D16+D17+D18+D19+D21+D22 -> 1922336.9
A16: =A17-A18 -> 5.4711644e+08 | D16: 210106.76
A17: 6.0681559e+08 | D17: 230221.13
A18: 59699148
D19: 1166669
A20: =SUM(A21:A23) -> 0 | D20: 852788.38
D21: 315340
D24: =D4-D15 -> 1.1102787e+08
A25: =SUM(A26:A30) -> 1.3839274e+08
D26: =D27-D28 -> 7000000
A27: 75924160 | D27: 7000000
A28: 47992406
A29: 14476174
D30: =SUM(D31:D35) -> 80160751
D31: 31647160
A32: =SUM(A4,A8,A10,A16,A20,A25) -> 1.0778417e+09 | D32: 13968033
D33: 4684294
D35: 29861264
A36: 62054614
D37: =D24-D26-D30 -> 23867122
A38: 7.5441899e+08
A39: =SUM(A36:A38) -> 8.1647361e+08 | D39: =D40-D41 -> 0
A41: =SUM(A42:A47) -> 6775.4
A43: 6775.4 | D43: =D37+D39 -> 23867122
D47: =D43-D45 -> 23867122
A48: =SUM(A39,A41) -> 8.1648038e+08
D50: =D47-D48 -> 23867122
A51: 1.1765702e+08
A54: =A56+A55 -> 49798258
A55: 25931136
A56: 23867122
A58: =SUM(A59:A63) -> 81373362
A59: 32938419
A60: 32531651
A61: 15903291
A64: =SUM(A51,A52,A54,A58) -> 2.4882864e+08
A66: =SUM(A48,A64) -> 1.065309e+09
A67: =A32-A66 -> 12532648
