Workbook
Name BALANCE1_LDA01: '[1]Financial Statements'!$E$112
Name BALANCE1_LDA12: '[1]Financial Statements'!$E$123
Name BALANCE2_LDA01: '[1]Financial Statements'!$F$112
Name BALANCE2_LDA12: '[1]Financial Statements'!$F$123
Name BALANCE3_LDA01: '[1]Financial Statements'!$G$112
Name BALANCE3_LDA12: '[1]Financial Statements'!$G$123
Name BALANCE4_LDA01: '[1]Financial Statements'!$H$112
Name BALANCE4_LDA12: '[1]Financial Statements'!$H$123
Name BALANCE5_LDA01: '[1]Financial Statements'!$I$112
Name BALANCE5_LDA12: '[1]Financial Statements'!$I$123
Name BALANCE6_LDA01: '[1]Financial Statements'!$J$112
Name BALANCE6_LDA12: '[1]Financial Statements'!$J$123
Name NotApplicable: CAELS!$B$25
Name PEARLS1_LA002: '[1]Financial Statements'!$E$280
Name PEARLS1_LE008: '[1]Financial Statements'!$E$275
Name PEARLS1_LE009: '[1]Financial Statements'!$E$276
Name PEARLS1_LR001: '[1]Financial Statements'!$E$282
Name PEARLS1_LR005: '[1]Financial Statements'!$E$286
Name PEARLS1_LR006: '[1]Financial Statements'!$E$287
Name PEARLS1_LR007: '[1]Financial Statements'!$E$288
Name PEARLS1_LR009: '[1]Financial Statements'!$E$290
Name PEARLS1_LS001: '[1]Financial Statements'!$E$298
Name PEARLS1_LS005: '[1]Financial Statements'!$E$302
Name PEARLS1_LS011: '[1]Financial Statements'!$E$308
Name PEARLS2_LA002: '[1]Financial Statements'!$F$280
Name PEARLS2_LE008: '[1]Financial Statements'!$F$275
Name PEARLS2_LE009: '[1]Financial Statements'!$F$276
Name PEARLS2_LR001: '[1]Financial Statements'!$F$282
Name PEARLS2_LR005: '[1]Financial Statements'!$F$286
Name PEARLS2_LR006: '[1]Financial Statements'!$F$287
Name PEARLS2_LR007: '[1]Financial Statements'!$F$288
Name PEARLS2_LR009: '[1]Financial Statements'!$F$290
Name PEARLS2_LS001: '[1]Financial Statements'!$F$298
Name PEARLS2_LS005: '[1]Financial Statements'!$F$302
Name PEARLS2_LS010: '[1]Financial Statements'!$F$307
Name PEARLS2_LS011: '[1]Financial Statements'!$F$308
Name PEARLS3_LA002: '[1]Financial Statements'!$G$280
Name PEARLS3_LE008: '[1]Financial Statements'!$G$275
Name PEARLS3_LE009: '[1]Financial Statements'!$G$276
Name PEARLS3_LR001: '[1]Financial Statements'!$G$282
Name PEARLS3_LR005: '[1]Financial Statements'!$G$286
Name PEARLS3_LR006: '[1]Financial Statements'!$G$287
Name PEARLS3_LR007: '[1]Financial Statements'!$G$288
Name PEARLS3_LR009: '[1]Financial Statements'!$G$290
Name PEARLS3_LS001: '[1]Financial Statements'!$G$298
Name PEARLS3_LS005: '[1]Financial Statements'!$G$302
Name PEARLS3_LS010: '[1]Financial Statements'!$G$307
Name PEARLS3_LS011: '[1]Financial Statements'!$G$308
Name PEARLS4_LA002: '[1]Financial Statements'!$H$280
Name PEARLS4_LE008: '[1]Financial Statements'!$H$275
Name PEARLS4_LE009: '[1]Financial Statements'!$H$276
Name PEARLS4_LR001: '[1]Financial Statements'!$H$282
Name PEARLS4_LR005: '[1]Financial Statements'!$H$286
Name PEARLS4_LR006: '[1]Financial Statements'!$H$287
Name PEARLS4_LR007: '[1]Financial Statements'!$H$288
Name PEARLS4_LR009: '[1]Financial Statements'!$H$290
Name PEARLS4_LS001: '[1]Financial Statements'!$H$298
Name PEARLS4_LS005: '[1]Financial Statements'!$H$302
Name PEARLS4_LS010: '[1]Financial Statements'!$H$307
Name PEARLS4_LS011: '[1]Financial Statements'!$H$308

Sheet Financials
B2: INVEST AND GROW FINANCIALS
B3: Year | C3: Audited 2017 | D3: Audited 2018 | E3: 43466 | F3: 43497 | G3: 43525 | H3: 43556 | I3: 43586 | J3: 43617 | K3: 43647 | L3: 43678 | M3: 43709 | N3: 43739 | O3: 43770 | P3: 43800 | Q3: AUDITED 2019 | R3: 43831 | S3: 43862 | T3: 43891 | U3: 43922 | V3: 43952 | W3: 43983 | X3: 44013 | Y3: 44044 | Z3: 44075 | AA3: 44105 | AB3: 44136 | AC3: 44166 | AD3: AUDITED 2020 | AE3: 44197 | AF3: 44228 | AG3: 44256 | AH3: 44287 | AI3: 44317 | AJ3: 44348 | AK3: 44378 | AL3: 44409 | AM3: 44440 | AN3: 44470 | AO3: 44501 | AP3: 44531 | AQ3: Audited 2021 | AR3: 44562 | AS3: 44593 | AT3: 44621 | AU3: 44652 | AV3: 44682 | AW3: 44713 | AX3: 44743 | AY3: 44774 | AZ3: 44805 | BA3: 44835 | BB3: 44866 | BC3: 44896 | BD3: Audited 2022
A4: 1 | B4: Membership | AQ4: 32447 | BD4: 33724
A5: 2 | B5: Total Assets | C5: =SFP!U27 -> 8106353615 | D5: =SFP!V27 -> 8715310718 | E5: =SFP!W27 -> 8960270626 | F5: =SFP!X27 -> 8958482401 | G5: =SFP!Y27 -> 9048315222 | H5: =SFP!Z27 -> 8549803719 | I5: =SFP!AA27 -> 8553114064 | J5: =SFP!AB27 -> 8706983540 | ... BD5: =SFP!BV27 -> 12958024000
A6: 3 | B6: Total Deposits | C6: =SFP!U32 -> 4484295483 | D6: =SFP!V32 -> 4962987100 | E6: =SFP!W32 -> 4979841046 | F6: =SFP!X32 -> 5035187526 | G6: =SFP!Y32 -> 5144194841 | H6: =SFP!Z32 -> 5165409133 | I6: =SFP!AA32 -> 5144139209 | J6: =SFP!AB32 -> 5173463255 | ... BD6: =SFP!BV32 -> 7044649000
A7: 3.1 | B7: Deposits-Members(BOSA) | C7: =SFP!U31 -> 4085665384 | D7: =SFP!V31 -> 4454006657 | E7: =SFP!W31 -> 4412161292 | F7: =SFP!X31 -> 4456600587 | G7: =SFP!Y31 -> 4489078500 | H7: =SFP!Z31 -> 4535050198 | I7: =SFP!AA31 -> 4556535041 | J7: =SFP!AB31 -> 4602930363 | ... BD7: =SFP!BV31 -> 5967690000
A8: 3.2 | B8: Deposits-Customers(FOSA) | C8: =SFP!U29 -> 272121207 | D8: =SFP!V29 -> 358299491 | E8: =SFP!W29 -> 420539519 | F8: =SFP!X29 -> 436535669 | G8: =SFP!Y29 -> 491265589 | H8: =SFP!Z29 -> 461506696 | I8: =SFP!AA29 -> 421211633 | J8: =SFP!AB29 -> 408643393 | ... BD8: =SFP!BV29 -> 913891000
A9: 4 | B9: External Borrowing | C9: =SFP!U39 -> 375000000 | D9: =SFP!V39 -> 275000000 | E9: =SFP!W39 -> 266666667 | F9: =SFP!X39 -> 200265525 | G9: =SFP!Y39 -> 95392958 | H9: =SFP!Z39 -> 91941390 | I9: =SFP!AA39 -> 0 | J9: =SFP!AB39 -> 0 | ... BD9: =SFP!BV39 -> 0
A10: 4.1 | B10: Short term Liabilities | C10: =(SFP!U34+SFP!U35+SFP!U38) -> 554554538 | D10: =(SFP!V34+SFP!V35+SFP!V38) -> 588706903 | E10: =(SFP!W34+SFP!W35+SFP!W38) -> 7.1367817e+08 | F10: =(SFP!X34+SFP!X35+SFP!X38) -> 7.7168466e+08 | G10: =(SFP!Y34+SFP!Y35+SFP!Y38) -> 830973117 | H10: =(SFP!Z34+SFP!Z35+SFP!Z38) -> 274944616 | I10: =(SFP!AA34+SFP!AA35+SFP!AA38) -> 3.3458643e+08 | J10: =(SFP!AB34+SFP!AB35+SFP!AB38) -> 396968427 | ... BD10: =(SFP!BV34+SFP!BV35+SFP!BV38) -> 814693000
A12: 5 | B12: Share capital and Reserves | C12: =SFP!U42 -> 382449866 | D12: =SFP!V42 -> 421922225 | E12: =SFP!W42 -> 671803630 | F12: =SFP!X42 -> 675549493 | G12: =SFP!Y42 -> 682351864 | H12: =SFP!Z42 -> 694996501 | I12: =SFP!AA42 -> 699865703 | J12: =SFP!AB42 -> 704056427 | ... BD12: =SFP!BV42 -> 1305241000
A13: 5.1 | B13: Core Capital | C13: =C16-C27 -> 2354877200 | D13: =D16-D27 -> 2112253899 | E13: =E16-E27 -> 2260453672 | F13: =F16-F27 -> 2296490354 | G13: =G16-G27 -> 2316883115 | H13: =H16-H27 -> 2350463995 | I13: =I16-I27 -> 2401164231 | J13: =J16-J27 -> 2419093562 | ... BD13: =BD16-BD27 -> 4484427000
A14: 5.2 | B14: Institutional Capital | C14: =(C13-C12) -> 1972427334 | D14: =(D13-D12) -> 1690331674 | E14: =(E13-E12) -> 1588650042 | F14: =(F13-F12) -> 1620940861 | G14: =(G13-G12) -> 1634531251 | H14: =(H13-H12) -> 1655467494 | I14: =(I13-I12) -> 1701298528 | J14: =(J13-J12) -> 1715037135 | ... BD14: =(BD13-BD12) -> 3179186000
A16: 5.3 | B16: Total Capital | C16: =SUM(C17:C20) -> 2354877200 | D16: =SUM(D17:D20) -> 2593223115 | E16: =SUM(E17:E20) -> 2716051604 | F16: =SUM(F17:F20) -> 2725964420 | G16: =SUM(G17:G20) -> 2746357181 | H16: =SUM(H17:H20) -> 2779938061 | I16: =SUM(I17:I20) -> 2830638297 | J16: =SUM(J17:J20) -> 2886567629 | ... BD16: =SUM(BD17:BD20) -> 4484427000
A17: 5.3.1 | B17: Members Share Capital | C17: =SFP!U42 -> 382449866 | D17: =SFP!V42 -> 421922225 | E17: =SFP!W42 -> 671803630 | F17: =SFP!X42 -> 675549493 | G17: =SFP!Y42 -> 682351864 | H17: =SFP!Z42 -> 694996501 | I17: =SFP!AA42 -> 699865703 | J17: =SFP!AB42 -> 704056427 | ... BD17: =SFP!BV42 -> 1305241000
A18: 5.3.3 | B18: Retained Earnings | C18: =SFP!U44 -> 1244145530 | D18: =SFP!V44 -> 1354697707 | E18: =SFP!W44 -> 1433879611 | F18: =SFP!X44 -> 1407719966 | G18: =SFP!Y44 -> 1421155356 | H18: =SFP!Z44 -> 1442012599 | I18: =SFP!AA44 -> 1487770133 | J18: =SFP!AB44 -> 1539468741 | ... BD18: =SFP!BV44 -> 1974689000
A19: 5.3.5 | B19: Statutory Reserves | C19: =SFP!U48 -> 450731709 | D19: =SFP!V48 -> 0 | E19: =SFP!W48 -> 494856977 | F19: =SFP!X48 -> 528921206 | G19: =SFP!Y48 -> 528921206 | H19: =SFP!Z48 -> 528921206 | I19: =SFP!AA48 -> 528921206 | J19: =SFP!AB48 -> 528921206 | ... BD19: =SFP!BV48 -> 984947000
A20: 5.3.6 | B20: Capital Reserve | C20: =SFP!U49 -> 277550095 | D20: =SFP!V49 -> 816603183 | E20: =SFP!W49 -> 115511386 | F20: =SFP!X49 -> 113773755 | G20: =SFP!Y49 -> 113928755 | H20: =SFP!Z49 -> 114007755 | I20: =SFP!AA49 -> 114081255 | J20: =SFP!AB49 -> 114121255 | ... BD20: =SFP!BV49 -> 219550000
A21: 5.3.7 | B21: Supplementary Capital & reserves
A22: a | B22: Proposed Dividends
A23: b
A25: 6 | B25: Investments | C25: =SUM(C26:C28) -> 438411690 | D25: =SUM(D26:D28) -> 480969216 | E25: =SUM(E26:E28) -> 504037257 | F25: =SUM(F26:F28) -> 478357566 | G25: =SUM(G26:G28) -> 478801741 | H25: =SUM(H26:H28) -> 479245916 | I25: =SUM(I26:I28) -> 483490091 | J25: =SUM(J26:J28) -> 521934267 | ... BD25: =SUM(BD26:BD28) -> 1541829000
A26: 6.1 | B26: Investments in Coop bank, CIC, Kuscco, Kerussu & Codic | C26: =SFP!U12 -> 0 | D26: =SFP!V12 -> 0 | E26: =SFP!W12 -> 0 | F26: =SFP!X12 -> 0 | G26: =SFP!Y12 -> 0 | H26: =SFP!Z12 -> 0 | I26: =SFP!AA12 -> 0 | J26: =SFP!AB12 -> 0 | ... BD26: =SFP!BV12 -> 625541000
A27: 6.2 | B27: Equity Investments (at cost) | C27: =SFP!U13 -> 0 | D27: =SFP!V13 -> 480969216 | E27: =SFP!W13 -> 455597932 | F27: =SFP!X13 -> 429474066 | G27: =SFP!Y13 -> 429474066 | H27: =SFP!Z13 -> 429474066 | I27: =SFP!AA13 -> 429474066 | J27: =SFP!AB13 -> 467474067 | ... BD27: =SFP!BV13 -> 0
A28: 6.3 | B28: Deposits in KUSCCO CFP | C28: =SFP!U11 -> 438411690 | D28: =SFP!V11 -> 0 | E28: =SFP!W11 -> 48439325 | F28: =SFP!X11 -> 48883500 | G28: =SFP!Y11 -> 49327675 | H28: =SFP!Z11 -> 49771850 | I28: =SFP!AA11 -> 54016025 | J28: =SFP!AB11 -> 54460200 | ... BD28: =SFP!BV11 -> 916288000
A30: 7 | B30: Net Loans & advances | C30: =C31-C32 -> 6527159792 | D30: =D31-D32 -> 6735591075 | E30: =E31-E32 -> 6723378302 | F30: =F31-F32 -> 6701926883 | G30: =G31-G32 -> 6625163637 | H30: =H31-H32 -> 6469028018 | I30: =I31-I32 -> 6388246711 | J30: =J31-J32 -> 6355553649 | ... BD30: =BD31-BD32 -> 9122098000
A31: 7.1 | B31: Gross Loans & advances | C31: =SFP!U15 -> 6677545533 | D31: =SFP!V15 -> 7151001513 | E31: =SFP!W15 -> 7136929610 | F31: =SFP!X15 -> 7117337321 | G31: =SFP!Y15 -> 7040574075 | H31: =SFP!Z15 -> 6884438456 | I31: =SFP!AA15 -> 6803657149 | J31: =SFP!AB15 -> 6770964087 | ... BD31: =SFP!BV15 -> 9515329000
A32: 7.3 | B32: Allowance for loan losses | C32: =SFP!U16 -> 150385741 | D32: =SFP!V16 -> 415410438 | E32: =SFP!W16 -> 413551308 | F32: =SFP!X16 -> 415410438 | G32: =SFP!Y16 -> 415410438 | H32: =SFP!Z16 -> 415410438 | I32: =SFP!AA16 -> 415410438 | J32: =SFP!AB16 -> 415410438 | ... BD32: =SFP!BV16 -> 393231000
A33: 7.4 | B33: Non Performing Loans (A/L NPL30
A34: 7.5666667 | B34: Non Performing Loans NPL30
A35: 7.7166667 | B35: Required loan loss provision
A36: 7.8666667 | B36: Cash and Cash equipments | C36: =SFP!U4 -> 429143643 | D36: =SFP!V4 -> 750100001 | E36: =SFP!W4 -> 812532694 | F36: =SFP!X4 -> 938755546 | G36: =SFP!Y4 -> 1105837097 | H36: =SFP!Z4 -> 799400736 | I36: =SFP!AA4 -> 883354226 | J36: =SFP!AB4 -> 1024877296 | ... BD36: =SFP!BV4 -> 1471320000
A38: 8 | B38: Non-Earning Assets | C38: =SFP!U7+SFP!U17+SFP!U21-SFP!U22 -> 365513490 | D38: =SFP!V7+SFP!V17+SFP!V21-SFP!V22 -> 363650426 | E38: =SFP!W7+SFP!W17+SFP!W21-SFP!W22 -> 535322373 | F38: =SFP!X7+SFP!X17+SFP!X21-SFP!X22 -> 454442406 | G38: =SFP!Y7+SFP!Y17+SFP!Y21-SFP!Y22 -> 453512747 | H38: =SFP!Z7+SFP!Z17+SFP!Z21-SFP!Z22 -> 417129049 | I38: =SFP!AA7+SFP!AA17+SFP!AA21-SFP!AA22 -> 413023036 | J38: =SFP!AB7+SFP!AB17+SFP!AB21-SFP!AB22 -> 419618328 | ... W38: =SFP!AO7+SFP!AO17+SFP!AO21-SFP!AO22 -> 314284713 | X38: =SFP!AQ7+SFP!AP17+SFP!AP21-SFP!AP22 -> 444754612 | Y38: =SFP!AR7+SFP!AQ17+SFP!AQ21-SFP!AQ22 -> 500888407 | Z38: =SFP!AS7+SFP!AR17+SFP!AR21-SFP!AR22 -> 494777306 | AA38: =SFP!AT7+SFP!AS17+SFP!AS21-SFP!AS22 -> 524507513 | AB38: =SFP!AU7+SFP!AT17+SFP!AT21-SFP!AT22 -> 481977030 | AC38: =SFP!#REF!+SFP!AU17+SFP!AU21-SFP!AU22 -> #REF! | AD38: =SFP!AV7+SFP!AV17+SFP!AV21-SFP!AV22 -> 570700 | AE38: =SFP!AW7+SFP!AW17+SFP!AW21-SFP!AW22 -> 625922229 | AF38: =SFP!AX7+SFP!AX17+SFP!AX21-SFP!AX22 -> 520573369 | AG38: =SFP!AY7+SFP!AY17+SFP!AY21-SFP!AY22 -> 523234323 | AH38: =SFP!AZ7+SFP!AZ17+SFP!AZ21-SFP!AZ22 -> 479381954 | AI38: =SFP!BA7+SFP!BA17+SFP!BA21-SFP!BA22 -> 477346147 | AJ38: =SFP!BB7+SFP!BB17+SFP!BB21-SFP!BB22 -> 385026122 | AK38: =SFP!BC7+SFP!BC17+SFP!BC21-SFP!BC22 -> 335073363 | ... BD38: =SFP!BV7+SFP!BV17+SFP!BV21-SFP!BV22 -> 514977000
A39: 8.1 | B39: Property and Equipment | C39: =SFP!U23 -> 36326430 | D39: =SFP!V23 -> 32449324 | E39: =SFP!W23 -> 31896736 | F39: =SFP!X23 -> 32507453 | G39: =SFP!Y23 -> 32000246 | H39: =SFP!Z23 -> 31493038 | I39: =SFP!AA23 -> 32562424 | J39: =SFP!AB23 -> 32085699 | ... BD39: =SFP!BV23 -> 133616000
A40: 8.2 | B40: Land and Building
A42: 9 | B42: Turnover | C42: =SUM(C43:C45) -> 1341798042 | D42: =SUM(D43:D45) -> 1367622498 | E42: =SUM(E43:E45) -> 123283534 | F42: =SUM(F43:F45) -> 237196091 | G42: =SUM(G43:G45) -> 357021027 | H42: =SUM(H43:H45) -> 473117791 | I42: =SUM(I43:I45) -> 604661545 | J42: =SUM(J43:J45) -> 741828590 | ... BD42: =SUM(BD43:BD45) -> 1763187000
A43: 9.1 | B43: Loan Interest | C43: =SCI!T5 -> 1239848635 | D43: =SCI!U5 -> 1246870335 | E43: =SCI!V5 -> 116892118 | F43: =SCI!W5 -> 226319507 | G43: =SCI!X5 -> 338628579 | H43: =SCI!Y5 -> 441339573 | I43: =SCI!Z5 -> 552042078 | J43: =SCI!AA5 -> 659271924 | ... BD43: =SCI!BU5 -> 1424256000
B44: Income from investments | C44: =SCI!T7 -> 101949407 | D44: =SCI!U7 -> 120752163 | E44: =SCI!V7 -> 422941 | F44: =SCI!W7 -> 4908109 | G44: =SCI!X7 -> 16349047 | H44: =SCI!Y7 -> 29734817 | I44: =SCI!Z7 -> 50576066 | J44: =SCI!AA7 -> 79685544 | ... BD44: =SCI!BU7 -> 338931000
A45: 9.2 | B45: Fees & Commissions | C45: =SCI!T6 -> 0 | D45: =SCI!U6 -> 0 | E45: =SCI!V6 -> 5968475 | F45: =SCI!W6 -> 5968475 | G45: =SCI!X6 -> 2043401 | H45: =SCI!Y6 -> 2043401 | I45: =SCI!Z6 -> 2043401 | J45: =SCI!AA6 -> 2871122 | ... BD45: =SCI!BU6 -> 0
B46: Average yield on loans | C46: =SCI!T5/SFP!U15 -> 0.18567431 | D46: =SCI!U5/SFP!V15 -> 0.17436304 | E46: =SCI!V5/SFP!W15 -> 0.016378488 | F46: =SCI!W5/SFP!X15 -> 0.031798339 | G46: =SCI!X5/SFP!Y15 -> 0.048096728 | H46: =SCI!Y5/SFP!Z15 -> 0.064106837 | I46: =SCI!Z5/SFP!AA15 -> 0.081139021 | J46: =SCI!AA5/SFP!AB15 -> 0.097367512 | ... BD46: =SCI!BU5/SFP!BV15 -> 0.14968016
A48: 10 | B48: Total Expenses (FinCosts + OpEx) | C48: =SUM(C49:C55) -> 814507555 | D48: =SUM(D49:D55) -> 863458557 | E48: =SUM(E49:E55) -> 83314316 | F48: =SUM(F49:F55) -> 1.6574666e+08 | G48: =SUM(G49:G55) -> 261177070 | H48: =SUM(H49:H55) -> 3.5222661e+08 | I48: =SUM(I49:I55) -> 4.3357931e+08 | J48: =SUM(J49:J55) -> 5.1426315e+08 | ... BD48: =SUM(BD49:BD55) -> 1175350000
A49: 10.1 | B49: Financial Exp. (Interest on deposits) | C49: =SCI!T13 -> 506653751 | D49: =SCI!U13 -> 551167389 | E49: =SCI!V13 -> 54389865 | F49: =SCI!W13 -> 1.0868116e+08 | G49: =SCI!X13 -> 163712365 | H49: =SCI!Y13 -> 2.2066618e+08 | I49: =SCI!Z13 -> 2.7661498e+08 | J49: =SCI!AA13 -> 3.3462256e+08 | ... BD49: =SCI!BU13 -> 751693000
A50: 10.2 | B50: Financial Exp. (Dividends) | C50: =SCI!T15 -> 0 | D50: =SCI!U15 -> 0 | E50: =SCI!V15 -> 5799241 | F50: =SCI!W15 -> 11666498 | G50: =SCI!X15 -> 17683355 | H50: =SCI!Y15 -> 23856748 | I50: =SCI!Z15 -> 30036363 | J50: =SCI!AA15 -> 36270458 | ... BD50: =SCI!BU15 -> 0
A51: 10.3 | B51: Financial Exp. (Interest on bank loans) | C51: =SCI!T14 -> 61841796 | D51: =SCI!U14 -> 45261304 | E51: =SCI!V14 -> 3036301 | F51: =SCI!W14 -> 7912785 | G51: =SCI!X14 -> 9999689 | H51: =SCI!Y14 -> 9999689 | I51: =SCI!Z14 -> 11383625 | J51: =SCI!AA14 -> 11383627 | ... BD51: =SCI!BU14 -> 0
A52: 10.4 | B52: Other Financial Expenses
A53: 10.5 | B53: Administrative Expenses | C53: =SCI!T28 -> 106447541 | D53: =SCI!U28 -> 103826250 | E53: =SCI!V28 -> 3640084 | F53: =SCI!W28 -> 7150828 | G53: =SCI!X28 -> 10850760 | H53: =SCI!Y28 -> 13294215 | I53: =SCI!Z28 -> 15818957 | J53: =SCI!AA28 -> 18519596 | ... BD53: =SCI!BU28 -> 151315000
A54: 10.6 | B54: Governance Expenses | C54: =SCI!T25 -> 43709999 | D54: =SCI!U25 -> 58102205 | E54: =SCI!V25 -> 7395865 | F54: =SCI!W25 -> 13477375 | G54: =SCI!X25 -> 33249915 | H54: =SCI!Y25 -> 43457386 | I54: =SCI!Z25 -> 48705332 | J54: =SCI!AA25 -> 53087339 | ... BD54: =SCI!BU25 -> 96032000
B55: Other operating expenses | C55: =SCI!T24+SCI!T26+SCI!T27 -> 95854468 | D55: =SCI!U24+SCI!U26+SCI!U27 -> 105101409 | E55: =SCI!V24+SCI!V26+SCI!V27 -> 9052960 | F55: =SCI!W24+SCI!W26+SCI!W27 -> 16858019 | G55: =SCI!X24+SCI!X26+SCI!X27 -> 25680986 | H55: =SCI!Y24+SCI!Y26+SCI!Y27 -> 40952398 | I55: =SCI!Z24+SCI!Z26+SCI!Z27 -> 51020059 | J55: =SCI!AA24+SCI!AA26+SCI!AA27 -> 60379568 | ... BD55: =SCI!BU24+SCI!BU26+SCI!BU27 -> 176310000

Sheet CAELS
B1: INVEST & GROW (IG)CAELS
E2: Audited 2017 | F2: Audited 2018 | G2: 43466 | H2: 43497 | I2: 43525 | J2: 43556 | K2: 43586 | L2: 43617 | M2: 43647 | N2: 43678 | O2: 43709 | P2: 43739 | Q2: 43770 | R2: 43800 | S2: Audited 2019 | T2: 43831 | U2: 43862 | V2: 43891 | W2: 43922 | X2: 43952 | Y2: 43983 | Z2: 44013 | AA2: 44044 | AB2: 44075 | AC2: 44105 | AD2: 44136 | AE2: 44166 | AF2: Audited 2020 | AG2: 44197 | AH2: 44228 | AI2: 44256 | AJ2: 44287 | AK2: 44317 | AL2: 44348 | AM2: 44378 | AN2: 44409 | AO2: 44440 | AP2: 44470 | AQ2: 44501 | AR2: 44531 | AS2: Audited 2021 | AT2: 44562 | AU2: 44593 | AV2: 44621 | AW2: 44652 | AX2: 44682 | AY2: 44713 | AZ2: 44743 | BA2: 44774 | BB2: 44805 | BC2: 44835 | BD2: 44866 | BE2: 44896 | BF2: Aud-22
A4: INDICATORS | B4: Capital adequacy | C4: CORE CAPITAL | D4: 10M | E4: =Financials!C13/1000000 -> 2354.8772 | F4: =Financials!D13/1000000 -> 2112.2539 | G4: =Financials!E13/1000000 -> 2260.4537 | H4: =Financials!F13/1000000 -> 2296.4904 | I4: =Financials!G13/1000000 -> 2316.8831 | J4: =Financials!H13/1000000 -> 2350.464 | K4: =Financials!I13/1000000 -> 2401.1642 | L4: =Financials!J13/1000000 -> 2419.0936 | ... BF4: =Financials!BD13/1000000 -> 4484.427
C5: CCA | D5: Min 10% | E5: =Financials!C13/Financials!C5 -> 0.29049771 | F5: =Financials!D13/Financials!D5 -> 0.24236128 | G5: =Financials!E13/Financials!E5 -> 0.25227516 | H5: =Financials!F13/Financials!F5 -> 0.25634815 | I5: =Financials!G13/Financials!G5 -> 0.25605685 | J5: =Financials!H13/Financials!H5 -> 0.27491438 | K5: =Financials!I13/Financials!I5 -> 0.28073567 | L5: =Financials!J13/Financials!J5 -> 0.27783371 | ... BF5: =Financials!BD13/Financials!BD5 -> 0.34607337
C6: ICA | D6: Min 8% | E6: =Financials!C14/Financials!C5 -> 0.24331869 | F6: =Financials!D14/Financials!D5 -> 0.19394967 | G6: =Financials!E14/Financials!E5 -> 0.17729934 | H6: =Financials!F14/Financials!F5 -> 0.18093922 | I6: =Financials!G14/Financials!G5 -> 0.18064482 | J6: =Financials!H14/Financials!H5 -> 0.19362637 | K6: =Financials!I14/Financials!I5 -> 0.19890984 | L6: =Financials!J14/Financials!J5 -> 0.19697259 | ... BF6: =Financials!BD14/Financials!BD5 -> 0.24534497
C7: CCD | D7: Min 8% | E7: =Financials!C13/Financials!C6 -> 0.52513872 | F7: =Financials!D13/Financials!D6 -> 0.42560133 | G7: =Financials!E13/Financials!E6 -> 0.45392085 | H7: =Financials!F13/Financials!F6 -> 0.45608835 | I7: =Financials!G13/Financials!G6 -> 0.4503879 | J7: =Financials!H13/Financials!H6 -> 0.45503927 | K7: =Financials!I13/Financials!I6 -> 0.46677668 | L7: =Financials!J13/Financials!J6 -> 0.46759655 | ... BF7: =Financials!BD13/Financials!BD6 -> 0.6365721
C8: Adjusted CCA | E8: =(Financials!C13-Financials!C33)/Financials!C5 -> 0.29049771 | F8: =(Financials!D13-Financials!D33)/Financials!D5 -> 0.24236128 | G8: =(Financials!E13-Financials!E33)/Financials!E5 -> 0.25227516 | H8: =(Financials!F13-Financials!F33)/Financials!F5 -> 0.25634815 | I8: =(Financials!G13-Financials!G33)/Financials!G5 -> 0.25605685 | J8: =(Financials!H13-Financials!H33)/Financials!H5 -> 0.27491438 | K8: =(Financials!I13-Financials!I33)/Financials!I5 -> 0.28073567 | L8: =(Financials!J13-Financials!J33)/Financials!J5 -> 0.27783371 | ... BF8: =(Financials!BD13-Financials!BD33)/Financials!BD5 -> 0.34607337
B10: ASSET QUALITY | C10: NPL30 | I10: ='Form 4'!D28 -> 0.06980849 | L10: ='Form 4'!M28 -> 0.065020366 | O10: ='Form 4'!D54 -> 0.076137488 | R10: ='Form 4'!M54 -> 0.072045972 | BE10: 0.05 | BF10: 0.05
C11: A/L NPL30
B13: EARNINGS | C13: ROA | E13: =SCI!T37/SFP!U27 -> 0.060280468 | F13: =SCI!U37/SFP!V27 -> 0.038168181 | G13: =SCI!V37/SFP!W27 -> 0.0029391629 | H13: =SCI!W37/SFP!X27 -> 0.0059186653 | I13: =SCI!X37/SFP!Y27 -> 0.007344754 | J13: =SCI!Y37/SFP!Z27 -> 0.010212503 | K13: =SCI!Z37/SFP!AA27 -> 0.01555836 | L13: =SCI!AA37/SFP!AB27 -> 0.021221016 | ... BF13: =SCI!BU37/SFP!BV27 -> 0.053190286
C14: C/I ratio | E14: =SCI!T23/SCI!T19 -> 0.31813166 | F14: =SCI!U29/SCI!U23 -> 1.3202692 | G14: =SCI!V29/SCI!V23 -> 1.3109569 | H14: =SCI!W29/SCI!W23 -> 1.4144466 | I14: =SCI!X29/SCI!X23 -> 0.95236554 | J14: =SCI!Y29/SCI!Y23 -> 0.89366754 | K14: =SCI!Z29/SCI!Z23 -> 1.1517 | L14: =SCI!AA29/SCI!AA23 -> 1.3999237 | M14: =SCI!AB29/SCI!AB23 -> 1.2170551 | ... BF14: =SCI!BU29/SCI!BU23 -> 1.6268845
C15: OE ratio | E15: =SCI!T23/SFP!U27 -> 0.030348048 | F15: =SCI!U23/SFP!V27 -> 0.030639167 | G15: =SCI!V23/SFP!W27 -> 0.002241998 | H15: =SCI!W23/SFP!X27 -> 0.0041844389 | I15: =SCI!X23/SFP!Y27 -> 0.0077121165 | J15: =SCI!Y23/SFP!Z27 -> 0.011427631 | K15: =SCI!Z23/SFP!AA27 -> 0.013509039 | L15: =SCI!AA23/SFP!AB27 -> 0.015158694 | ... BF15: =SCI!BU23/SFP!BV27 -> 0.032694568
B17: LIQUIDITY | C17: W NLIQ ratio | D17: Min 15% | E17: =(SFP!U4+SFP!U11)/(SFP!U29+SFP!U30+SFP!U33-SFP!U39) -> 0.88648678 | F17: =(SFP!V4+SFP!V11)/(SFP!V29+SFP!V30+SFP!V33-SFP!V39) -> 0.68307476 | G17: =(SFP!W4+SFP!W11)/(SFP!W29+SFP!W30+SFP!W33-SFP!W39) -> 0.67192156 | H17: =(SFP!X4+SFP!X11)/(SFP!X29+SFP!X30+SFP!X33-SFP!X39) -> 0.73143732 | I17: =(SFP!Y4+SFP!Y11)/(SFP!Y29+SFP!Y30+SFP!Y33-SFP!Y39) -> 0.77731846 | J17: =(SFP!Z4+SFP!Z11)/(SFP!Z29+SFP!Z30+SFP!Z33-SFP!Z39) -> 0.93799763 | K17: =(SFP!AA4+SFP!AA11)/(SFP!AA29+SFP!AA30+SFP!AA33-SFP!AA39) -> 1.0164604 | L17: =(SFP!AB4+SFP!AB11)/(SFP!AB29+SFP!AB30+SFP!AB33-SFP!AB39) -> 1.1155928 | ... BF17: =(SFP!BV4+SFP!BV11)/(SFP!BV29+SFP!BV30+SFP!BV33-SFP!BV39) -> 1.2621814
C18: T NLIQ ratio | E18: =(SFP!U4+SFP!U11)/(SFP!U32+SFP!U33-SFP!U39) -> 0.17130771 | F18: =(SFP!V4+SFP!V11)/(SFP!V32+SFP!V33-SFP!V39) -> 0.13510132 | G18: =(SFP!W4+SFP!W11)/(SFP!W32+SFP!W33-SFP!W39) -> 0.15121966 | H18: =(SFP!X4+SFP!X11)/(SFP!X32+SFP!X33-SFP!X39) -> 0.17008107 | I18: =(SFP!Y4+SFP!Y11)/(SFP!Y32+SFP!Y33-SFP!Y39) -> 0.19332758 | J18: =(SFP!Z4+SFP!Z11)/(SFP!Z32+SFP!Z33-SFP!Z39) -> 0.15608775 | K18: =(SFP!AA4+SFP!AA11)/(SFP!AA32+SFP!AA33-SFP!AA39) -> 0.17109275 | L18: =(SFP!AB4+SFP!AB11)/(SFP!AB32+SFP!AB33-SFP!AB39) -> 0.19376191 | ... BF18: =(SFP!BV4+SFP!BV11)/(SFP!BV32+SFP!BV33-SFP!BV39) -> 0.30379235
C19: EB ratio | D19: Max 25% | E19: =Financials!C9/Financials!C5 -> 0.04626001 | F19: =Financials!D9/Financials!D5 -> 0.031553666 | G19: =Financials!E9/Financials!E5 -> 0.029761006 | H19: =Financials!F9/Financials!F5 -> 0.022354849 | I19: =Financials!G9/Financials!G5 -> 0.010542621 | J19: =Financials!H9/Financials!H5 -> 0.010753626 | K19: =Financials!I9/Financials!I5 -> 0 | L19: =Financials!J9/Financials!J5 -> 0 | ... BF19: =Financials!BD9/Financials!BD5 -> 0
C20: LIQ to TA ratio | E20: =(SFP!U4+SFP!U11)/SFP!U27 -> 0.10702165 | F20: =(SFP!V4+SFP!V11)/SFP!V27 -> 0.086066926 | G20: =(SFP!W4+SFP!W11)/SFP!W27 -> 0.096087725 | H20: =(SFP!X4+SFP!X11)/SFP!X27 -> 0.11024625 | I20: =(SFP!Y4+SFP!Y11)/SFP!Y27 -> 0.12766628 | J20: =(SFP!Z4+SFP!Z11)/SFP!Z27 -> 0.099320711 | K20: =(SFP!AA4+SFP!AA11)/SFP!AA27 -> 0.10959403 | L20: =(SFP!AB4+SFP!AB11)/SFP!AB27 -> 0.12396228 | ... BF20: =(SFP!BV4+SFP!BV11)/SFP!BV27 -> 0.18425711
B22: STRUCTURE OF ASSETS | C22: LB ratio | D22: Max 5% | E22: =Financials!C40/Financials!C5 -> 0 | F22: =Financials!D40/Financials!D5 -> 0 | G22: =Financials!E40/Financials!E5 -> 0 | H22: =Financials!F40/Financials!F5 -> 0 | I22: =Financials!G40/Financials!G5 -> 0 | J22: =Financials!H40/Financials!H5 -> 0 | K22: =Financials!I40/Financials!I5 -> 0 | L22: =Financials!J40/Financials!J5 -> 0 | ... BF22: =Financials!BD40/Financials!BD5 -> 0
C23: FICC | D23: Max 40% | E23: =Financials!C25/Financials!C13 -> 0.18617178 | F23: =Financials!D25/Financials!D13 -> 0.22770426 | G23: =Financials!E25/Financials!E13 -> 0.22298057 | H23: =Financials!F25/Financials!F13 -> 0.2082994 | I23: =Financials!G25/Financials!G13 -> 0.2066577 | J23: =Financials!H25/Financials!H13 -> 0.20389417 | K23: =Financials!I25/Financials!I13 -> 0.20135653 | L23: =Financials!J25/Financials!J13 -> 0.21575613 | ... BF23: =Financials!BD25/Financials!BD13 -> 0.34381851
C24: FITD | D24: Max 5% | E24: =Financials!C25/Financials!C6 -> 0.097766013 | F24: =Financials!D25/Financials!D6 -> 0.096911236 | G24: =Financials!E25/Financials!E6 -> 0.10121553 | H24: =Financials!F25/Financials!F6 -> 0.09500293 | I24: =Financials!G25/Financials!G6 -> 0.093076129 | J24: =Financials!H25/Financials!H6 -> 0.092779856 | K24: =Financials!I25/Financials!I6 -> 0.093988532 | L24: =Financials!J25/Financials!J6 -> 0.10088682 | ... BF24: =Financials!BD25/Financials!BD6 -> 0.21886527
C25: NEA | D25: Max 10% | E25: =Financials!C38/Financials!C5 -> 0.045089754 | F25: =Financials!D38/Financials!D5 -> 0.041725469 | G25: =Financials!E38/Financials!E5 -> 0.059743996 | H25: =Financials!F38/Financials!F5 -> 0.050727611 | I25: =Financials!G38/Financials!G5 -> 0.050121236 | J25: =Financials!H38/Financials!H5 -> 0.048788143 | K25: =Financials!I38/Financials!I5 -> 0.0482892 | L25: =Financials!J38/Financials!J5 -> 0.048193307 | ... BF25: =Financials!BD38/Financials!BD5 -> 0.039741939
C26: LOANS/TA | E26: =SFP!U14/SFP!U27 -> 0.80519061 | F26: =SFP!V14/SFP!V27 -> 0.77284578 | G26: =SFP!W14/SFP!W27 -> 0.75035438 | H26: =SFP!X14/SFP!X27 -> 0.74810962 | I26: =SFP!Y14/SFP!Y27 -> 0.73219859 | J26: =SFP!Z14/SFP!Z27 -> 0.75662883 | K26: =SFP!AA14/SFP!AA27 -> 0.74689133 | L26: =SFP!AB14/SFP!AB27 -> 0.72993748 | ... BF26: =SFP!BV14/SFP!BV27 -> 0.70397292
A28: RATING PARAMETERS | B28: CAPITAL | C28: CORE CAPITAL | D28: 10M | E28: =IF(E4>10,1,5) -> 1 | F28: =IF(F4>10,1,5) -> 1 | G28: =IF(G4>10,1,5) -> 1 | H28: =IF(H4>10,1,5) -> 1 | I28: =IF(I4>10,1,5) -> 1 | J28: =IF(J4>10,1,5) -> 1 | K28: =IF(K4>10,1,5) -> 1 | L28: =IF(L4>10,1,5) -> 1 | ... BF28: =IF(BF4>10,1,5) -> 1
C29: CCA | D29: Min 10% | E29: =IF(E5>20%,1,IF(E5>15,2,IF(E5>12,3,IF(E5>10,4,5)))) -> 1 | F29: =IF(F5>20%,1,IF(F5>15,2,IF(F5>12,3,IF(F5>10,4,5)))) -> 1 | G29: =IF(G5>20%,1,IF(G5>15,2,IF(G5>12,3,IF(G5>10,4,5)))) -> 1 | H29: =IF(H5>20%,1,IF(H5>15,2,IF(H5>12,3,IF(H5>10,4,5)))) -> 1 | I29: =IF(I5>20%,1,IF(I5>15,2,IF(I5>12,3,IF(I5>10,4,5)))) -> 1 | J29: =IF(J5>20%,1,IF(J5>15,2,IF(J5>12,3,IF(J5>10,4,5)))) -> 1 | K29: =IF(K5>20%,1,IF(K5>15,2,IF(K5>12,3,IF(K5>10,4,5)))) -> 1 | L29: =IF(L5>20%,1,IF(L5>15,2,IF(L5>12,3,IF(L5>10,4,5)))) -> 1 | ... BF29: =IF(BF5>20%,1,IF(BF5>15,2,IF(BF5>12,3,IF(BF5>10,4,5)))) -> 1
C30: ICA | D30: Min 8% | E30: =IF(E6>15,1,IF(E6>12,2,IF(E6>10,3,IF(E6>8,4,5)))) -> 5 | F30: =IF(F6>15,1,IF(F6>12,2,IF(F6>10,3,IF(F6>8,4,5)))) -> 5 | G30: =IF(G6>15,1,IF(G6>12,2,IF(G6>10,3,IF(G6>8,4,5)))) -> 5 | H30: =IF(H6>15,1,IF(H6>12,2,IF(H6>10,3,IF(H6>8,4,5)))) -> 5 | I30: =IF(I6>15,1,IF(I6>12,2,IF(I6>10,3,IF(I6>8,4,5)))) -> 5 | J30: =IF(J6>15,1,IF(J6>12,2,IF(J6>10,3,IF(J6>8,4,5)))) -> 5 | K30: =IF(K6>15,1,IF(K6>12,2,IF(K6>10,3,IF(K6>8,4,5)))) -> 5 | L30: =IF(L6>15,1,IF(L6>12,2,IF(L6>10,3,IF(L6>8,4,5)))) -> 5 | ... BF30: =IF(BF6>15,1,IF(BF6>12,2,IF(BF6>10,3,IF(BF6>8,4,5)))) -> 5
C31: CCD | D31: Min 8% | E31: =IF(E7>20%,1,IF(E7>12%,2,IF(E7>10%,3,IF(E7>8%,4,5)))) -> 1 | F31: =IF(F7>20%,1,IF(F7>12%,2,IF(F7>10%,3,IF(F7>8%,4,5)))) -> 1 | G31: =IF(G7>20%,1,IF(G7>12%,2,IF(G7>10%,3,IF(G7>8%,4,5)))) -> 1 | H31: =IF(H7>20%,1,IF(H7>12%,2,IF(H7>10%,3,IF(H7>8%,4,5)))) -> 1 | I31: =IF(I7>20%,1,IF(I7>12%,2,IF(I7>10%,3,IF(I7>8%,4,5)))) -> 1 | J31: =IF(J7>20%,1,IF(J7>12%,2,IF(J7>10%,3,IF(J7>8%,4,5)))) -> 1 | K31: =IF(K7>20%,1,IF(K7>12%,2,IF(K7>10%,3,IF(K7>8%,4,5)))) -> 1 | L31: =IF(L7>20%,1,IF(L7>12%,2,IF(L7>10%,3,IF(L7>8%,4,5)))) -> 1 | ... BF31: =IF(BF7>20%,1,IF(BF7>12%,2,IF(BF7>10%,3,IF(BF7>8%,4,5)))) -> 1
C32: Adjusted CCA | E32: =IF(E8>20%,1,IF(E8>15%,2,IF(E8>12%,3,IF(E8>10%,4,5)))) -> 1 | F32: =IF(F8>20%,1,IF(F8>15%,2,IF(F8>12%,3,IF(F8>10%,4,5)))) -> 1 | G32: =IF(G8>20%,1,IF(G8>15%,2,IF(G8>12%,3,IF(G8>10%,4,5)))) -> 1 | H32: =IF(H8>20%,1,IF(H8>15%,2,IF(H8>12%,3,IF(H8>10%,4,5)))) -> 1 | I32: =IF(I8>20%,1,IF(I8>15%,2,IF(I8>12%,3,IF(I8>10%,4,5)))) -> 1 | J32: =IF(J8>20%,1,IF(J8>15%,2,IF(J8>12%,3,IF(J8>10%,4,5)))) -> 1 | K32: =IF(K8>20%,1,IF(K8>15%,2,IF(K8>12%,3,IF(K8>10%,4,5)))) -> 1 | L32: =IF(L8>20%,1,IF(L8>15%,2,IF(L8>12%,3,IF(L8>10%,4,5)))) -> 1 | ... BF32: =IF(BF8>20%,1,IF(BF8>15%,2,IF(BF8>12%,3,IF(BF8>10%,4,5)))) -> 1
B34: ASSET QUALITY | C34: NPL30 | E34: =IF(E10<4,1,IF(E10<8,2,IF(E10<12,3,IF(E10<15,4,5)))) -> 1 | F34: =IF(F10<4,1,IF(F10<8,2,IF(F10<12,3,IF(F10<15,4,5)))) -> 1 | G34: =IF(G10<4,1,IF(G10<8,2,IF(G10<12,3,IF(G10<15,4,5)))) -> 1 | H34: =IF(H10<4,1,IF(H10<8,2,IF(H10<12,3,IF(H10<15,4,5)))) -> 1 | I34: =IF(I10<4,1,IF(I10<8,2,IF(I10<12,3,IF(I10<15,4,5)))) -> 1 | J34: =IF(J10<4,1,IF(J10<8,2,IF(J10<12,3,IF(J10<15,4,5)))) -> 1 | K34: =IF(K10<4,1,IF(K10<8,2,IF(K10<12,3,IF(K10<15,4,5)))) -> 1 | L34: =IF(L10<4,1,IF(L10<8,2,IF(L10<12,3,IF(L10<15,4,5)))) -> 1 | ... BF34: =IF(BF10<4,1,IF(BF10<8,2,IF(BF10<12,3,IF(BF10<15,4,5)))) -> 1
C35: A/L NPL30
B37: EARNINGS | C37: ROA | E37: =IF(E17>6,1,IF(E17>4,2,IF(E17>2,3,IF(E17>0,4,5)))) -> 4 | F37: =IF(F17>6,1,IF(F17>4,2,IF(F17>2,3,IF(F17>0,4,5)))) -> 4 | G37: =IF(G17>6,1,IF(G17>4,2,IF(G17>2,3,IF(G17>0,4,5)))) -> 4 | H37: =IF(H17>6,1,IF(H17>4,2,IF(H17>2,3,IF(H17>0,4,5)))) -> 4 | I37: =IF(I17>6,1,IF(I17>4,2,IF(I17>2,3,IF(I17>0,4,5)))) -> 4 | J37: =IF(J17>6,1,IF(J17>4,2,IF(J17>2,3,IF(J17>0,4,5)))) -> 4 | K37: =IF(K17>6,1,IF(K17>4,2,IF(K17>2,3,IF(K17>0,4,5)))) -> 4 | L37: =IF(L17>6,1,IF(L17>4,2,IF(L17>2,3,IF(L17>0,4,5)))) -> 4 | ... BF37: =IF(BF17>6,1,IF(BF17>4,2,IF(BF17>2,3,IF(BF17>0,4,5)))) -> 4
C38: C/I ratio | E38: =IF(E14<60,1,IF(E14<70,2,IF(E14<80,3,IF(E14<90,4,5)))) -> 1 | F38: =IF(F14<60,1,IF(F14<70,2,IF(F14<80,3,IF(F14<90,4,5)))) -> 1 | G38: =IF(G14<60,1,IF(G14<70,2,IF(G14<80,3,IF(G14<90,4,5)))) -> 1 | H38: =IF(H14<60,1,IF(H14<70,2,IF(H14<80,3,IF(H14<90,4,5)))) -> 1 | I38: =IF(I14<60,1,IF(I14<70,2,IF(I14<80,3,IF(I14<90,4,5)))) -> 1 | J38: =IF(J14<60,1,IF(J14<70,2,IF(J14<80,3,IF(J14<90,4,5)))) -> 1 | K38: =IF(K14<60,1,IF(K14<70,2,IF(K14<80,3,IF(K14<90,4,5)))) -> 1 | L38: =IF(L14<60,1,IF(L14<70,2,IF(L14<80,3,IF(L14<90,4,5)))) -> 1 | ... BF38: =IF(BF14<60,1,IF(BF14<70,2,IF(BF14<80,3,IF(BF14<90,4,5)))) -> 1
C39: OE ratio | E39: =IF(E15<4,1,IF(E15<6,2,IF(E15<8,3,IF(E15<10,4,5)))) -> 1 | F39: =IF(F15<4,1,IF(F15<6,2,IF(F15<8,3,IF(F15<10,4,5)))) -> 1 | G39: =IF(G15<4,1,IF(G15<6,2,IF(G15<8,3,IF(G15<10,4,5)))) -> 1 | H39: =IF(H15<4,1,IF(H15<6,2,IF(H15<8,3,IF(H15<10,4,5)))) -> 1 | I39: =IF(I15<4,1,IF(I15<6,2,IF(I15<8,3,IF(I15<10,4,5)))) -> 1 | J39: =IF(J15<4,1,IF(J15<6,2,IF(J15<8,3,IF(J15<10,4,5)))) -> 1 | K39: =IF(K15<4,1,IF(K15<6,2,IF(K15<8,3,IF(K15<10,4,5)))) -> 1 | L39: =IF(L15<4,1,IF(L15<6,2,IF(L15<8,3,IF(L15<10,4,5)))) -> 1 | ... BF39: =IF(BF15<4,1,IF(BF15<6,2,IF(BF15<8,3,IF(BF15<10,4,5)))) -> 1
B41: LIQUIDITY | C41: W NLIQ ratio | D41: Min 15% | E41: =IF(E17>30,1,IF(E17>25,2,IF(E17>20,3,IF(E17>15,4,5)))) -> 5 | F41: =IF(F17>30,1,IF(F17>25,2,IF(F17>20,3,IF(F17>15,4,5)))) -> 5 | G41: =IF(G17>30,1,IF(G17>25,2,IF(G17>20,3,IF(G17>15,4,5)))) -> 5 | H41: =IF(H17>30,1,IF(H17>25,2,IF(H17>20,3,IF(H17>15,4,5)))) -> 5 | I41: =IF(I17>30,1,IF(I17>25,2,IF(I17>20,3,IF(I17>15,4,5)))) -> 5 | J41: =IF(J17>30,1,IF(J17>25,2,IF(J17>20,3,IF(J17>15,4,5)))) -> 5 | K41: =IF(K17>30,1,IF(K17>25,2,IF(K17>20,3,IF(K17>15,4,5)))) -> 5 | L41: =IF(L17>30,1,IF(L17>25,2,IF(L17>20,3,IF(L17>15,4,5)))) -> 5 | ... BF41: =IF(BF17>30,1,IF(BF17>25,2,IF(BF17>20,3,IF(BF17>15,4,5)))) -> 5
C42: T NLIQ ratio | E42: =IF(E18>30,1,IF(E18>25,2,IF(E18>20,3,IF(E18>15,4,5)))) -> 5 | F42: =IF(F18>30,1,IF(F18>25,2,IF(F18>20,3,IF(F18>15,4,5)))) -> 5 | G42: =IF(G18>30,1,IF(G18>25,2,IF(G18>20,3,IF(G18>15,4,5)))) -> 5 | H42: =IF(H18>30,1,IF(H18>25,2,IF(H18>20,3,IF(H18>15,4,5)))) -> 5 | I42: =IF(I18>30,1,IF(I18>25,2,IF(I18>20,3,IF(I18>15,4,5)))) -> 5 | J42: =IF(J18>30,1,IF(J18>25,2,IF(J18>20,3,IF(J18>15,4,5)))) -> 5 | K42: =IF(K18>30,1,IF(K18>25,2,IF(K18>20,3,IF(K18>15,4,5)))) -> 5 | L42: =IF(L18>30,1,IF(L18>25,2,IF(L18>20,3,IF(L18>15,4,5)))) -> 5 | ... BF42: =IF(BF18>30,1,IF(BF18>25,2,IF(BF18>20,3,IF(BF18>15,4,5)))) -> 5
C43: EB ratio | D43: Max 25% | E43: =IF(E19<15,1,IF(E19<18,2,IF(E19<22,3,IF(E19<25,4,5)))) -> 1 | F43: =IF(F19<15,1,IF(F19<18,2,IF(F19<22,3,IF(F19<25,4,5)))) -> 1 | G43: =IF(G19<15,1,IF(G19<18,2,IF(G19<22,3,IF(G19<25,4,5)))) -> 1 | H43: =IF(H19<15,1,IF(H19<18,2,IF(H19<22,3,IF(H19<25,4,5)))) -> 1 | I43: =IF(I19<15,1,IF(I19<18,2,IF(I19<22,3,IF(I19<25,4,5)))) -> 1 | J43: =IF(J19<15,1,IF(J19<18,2,IF(J19<22,3,IF(J19<25,4,5)))) -> 1 | K43: =IF(K19<15,1,IF(K19<18,2,IF(K19<22,3,IF(K19<25,4,5)))) -> 1 | L43: =IF(L19<15,1,IF(L19<18,2,IF(L19<22,3,IF(L19<25,4,5)))) -> 1 | ... BF43: =IF(BF19<15,1,IF(BF19<18,2,IF(BF19<22,3,IF(BF19<25,4,5)))) -> 1
C44: LIQ to TA ratio | E44: =IF(E20>15,1,IF(E20>12,2,IF(E20>9,3,IF(E20>6,4,5)))) -> 5 | F44: =IF(F20>15,1,IF(F20>12,2,IF(F20>9,3,IF(F20>6,4,5)))) -> 5 | G44: =IF(G20>15,1,IF(G20>12,2,IF(G20>9,3,IF(G20>6,4,5)))) -> 5 | H44: =IF(H20>15,1,IF(H20>12,2,IF(H20>9,3,IF(H20>6,4,5)))) -> 5 | I44: =IF(I20>15,1,IF(I20>12,2,IF(I20>9,3,IF(I20>6,4,5)))) -> 5 | J44: =IF(J20>15,1,IF(J20>12,2,IF(J20>9,3,IF(J20>6,4,5)))) -> 5 | K44: =IF(K20>15,1,IF(K20>12,2,IF(K20>9,3,IF(K20>6,4,5)))) -> 5 | L44: =IF(L20>15,1,IF(L20>12,2,IF(L20>9,3,IF(L20>6,4,5)))) -> 5 | ... BF44: =IF(BF20>15,1,IF(BF20>12,2,IF(BF20>9,3,IF(BF20>6,4,5)))) -> 5
B46: STRUCTURE OF ASSETS | C46: LB ratio | D46: Max 5% | E46: =IF(E22<2,1,IF(E22<3,2,IF(E22<4,3,IF(E22<5,4,5)))) -> 1 | F46: =IF(F22<2,1,IF(F22<3,2,IF(F22<4,3,IF(F22<5,4,5)))) -> 1 | G46: =IF(G22<2,1,IF(G22<3,2,IF(G22<4,3,IF(G22<5,4,5)))) -> 1 | H46: =IF(H22<2,1,IF(H22<3,2,IF(H22<4,3,IF(H22<5,4,5)))) -> 1 | I46: =IF(I22<2,1,IF(I22<3,2,IF(I22<4,3,IF(I22<5,4,5)))) -> 1 | J46: =IF(J22<2,1,IF(J22<3,2,IF(J22<4,3,IF(J22<5,4,5)))) -> 1 | K46: =IF(K22<2,1,IF(K22<3,2,IF(K22<4,3,IF(K22<5,4,5)))) -> 1 | L46: =IF(L22<2,1,IF(L22<3,2,IF(L22<4,3,IF(L22<5,4,5)))) -> 1 | ... BF46: =IF(BF22<2,1,IF(BF22<3,2,IF(BF22<4,3,IF(BF22<5,4,5)))) -> 1
C47: FICC | D47: Max 40% | E47: =IF(E23<20,1,IF(E23<25,2,IF(E23<30,3,IF(E23<40,4,5)))) -> 1 | F47: =IF(F23<20,1,IF(F23<25,2,IF(F23<30,3,IF(F23<40,4,5)))) -> 1 | G47: =IF(G23<20,1,IF(G23<25,2,IF(G23<30,3,IF(G23<40,4,5)))) -> 1 | H47: =IF(H23<20,1,IF(H23<25,2,IF(H23<30,3,IF(H23<40,4,5)))) -> 1 | I47: =IF(I23<20,1,IF(I23<25,2,IF(I23<30,3,IF(I23<40,4,5)))) -> 1 | J47: =IF(J23<20,1,IF(J23<25,2,IF(J23<30,3,IF(J23<40,4,5)))) -> 1 | K47: =IF(K23<20,1,IF(K23<25,2,IF(K23<30,3,IF(K23<40,4,5)))) -> 1 | L47: =IF(L23<20,1,IF(L23<25,2,IF(L23<30,3,IF(L23<40,4,5)))) -> 1 | ... BF47: =IF(BF23<20,1,IF(BF23<25,2,IF(BF23<30,3,IF(BF23<40,4,5)))) -> 1
C48: FITD | D48: Max 5% | E48: =IF(E23<2,1,IF(E23<3,2,IF(E23<4,3,IF(E23<5,4,5)))) -> 1 | F48: =IF(F23<2,1,IF(F23<3,2,IF(F23<4,3,IF(F23<5,4,5)))) -> 1 | G48: =IF(G23<2,1,IF(G23<3,2,IF(G23<4,3,IF(G23<5,4,5)))) -> 1 | H48: =IF(H23<2,1,IF(H23<3,2,IF(H23<4,3,IF(H23<5,4,5)))) -> 1 | I48: =IF(I23<2,1,IF(I23<3,2,IF(I23<4,3,IF(I23<5,4,5)))) -> 1 | J48: =IF(J23<2,1,IF(J23<3,2,IF(J23<4,3,IF(J23<5,4,5)))) -> 1 | K48: =IF(K23<2,1,IF(K23<3,2,IF(K23<4,3,IF(K23<5,4,5)))) -> 1 | L48: =IF(L23<2,1,IF(L23<3,2,IF(L23<4,3,IF(L23<5,4,5)))) -> 1 | ... BF48: =IF(BF23<2,1,IF(BF23<3,2,IF(BF23<4,3,IF(BF23<5,4,5)))) -> 1
C49: NEA | D49: Max 10% | E49: =IF(E25<6,1,IF(E25<7,2,IF(E25<8,3,IF(E25<10,4,5)))) -> 1 | F49: =IF(F25<6,1,IF(F25<7,2,IF(F25<8,3,IF(F25<10,4,5)))) -> 1 | G49: =IF(G25<6,1,IF(G25<7,2,IF(G25<8,3,IF(G25<10,4,5)))) -> 1 | H49: =IF(H25<6,1,IF(H25<7,2,IF(H25<8,3,IF(H25<10,4,5)))) -> 1 | I49: =IF(I25<6,1,IF(I25<7,2,IF(I25<8,3,IF(I25<10,4,5)))) -> 1 | J49: =IF(J25<6,1,IF(J25<7,2,IF(J25<8,3,IF(J25<10,4,5)))) -> 1 | K49: =IF(K25<6,1,IF(K25<7,2,IF(K25<8,3,IF(K25<10,4,5)))) -> 1 | L49: =IF(L25<6,1,IF(L25<7,2,IF(L25<8,3,IF(L25<10,4,5)))) -> 1 | ... BF49: =IF(BF25<6,1,IF(BF25<7,2,IF(BF25<8,3,IF(BF25<10,4,5)))) -> 1
A52: INDICATOR WEIGHTS | B52: CAPITAL | C52: CORE CAPITAL | E52: 0.01 | F52: 0.01 | G52: 0.01 | H52: 0.01 | I52: 0.01 | J52: 0.01 | K52: 0.01 | L52: 0.01 | M52: 0.01 | N52: 0.01 | O52: 0.01 | P52: 0.01 | Q52: 0.01 | R52: 0.01 | S52: 0.01 | T52: 0.01 | U52: 0.01 | V52: 0.01 | W52: 0.01 | X52: 0.01 | Y52: 0.01 | Z52: 0.01 | AA52: 0.01 | AB52: 0.01 | AC52: 0.01 | AD52: 0.01 | AE52: 0.01 | AF52: 0.01 | AG52: 0.01 | AH52: 0.01 | AI52: 0.01 | AJ52: 0.01 | AK52: 0.01 | AL52: 0.01 | AM52: 0.01 | AN52: 0.01 | AO52: 0.01 | AP52: 0.01 | AQ52: 0.01 | AR52: 0.01 | AS52: 0.01 | AT52: 0.01 | AU52: 0.01 | AV52: 0.01 | AW52: 0.01 | AX52: 0.01 | AY52: 0.01 | AZ52: 0.01 | BA52: 0.01 | BB52: 0.01 | BC52: 0.01 | BD52: 0.01 | BE52: 0.01 | BF52: 0.01
C53: CCA (Min 10%) | E53: 0.2 | F53: 0.2 | G53: 0.2 | H53: 0.2 | I53: 0.2 | J53: 0.2 | K53: 0.2 | L53: 0.2 | M53: 0.2 | N53: 0.2 | O53: 0.2 | P53: 0.2 | Q53: 0.2 | R53: 0.2 | S53: 0.2 | T53: 0.2 | U53: 0.2 | V53: 0.2 | W53: 0.2 | X53: 0.2 | Y53: 0.2 | Z53: 0.2 | AA53: 0.2 | AB53: 0.2 | AC53: 0.2 | AD53: 0.2 | AE53: 0.2 | AF53: 0.2 | AG53: 0.2 | AH53: 0.2 | AI53: 0.2 | AJ53: 0.2 | AK53: 0.2 | AL53: 0.2 | AM53: 0.2 | AN53: 0.2 | AO53: 0.2 | AP53: 0.2 | AQ53: 0.2 | AR53: 0.2 | AS53: 0.2 | AT53: 0.2 | AU53: 0.2 | AV53: 0.2 | AW53: 0.2 | AX53: 0.2 | AY53: 0.2 | AZ53: 0.2 | BA53: 0.2 | BB53: 0.2 | BC53: 0.2 | BD53: 0.2 | BE53: 0.2 | BF53: 0.2
C54: ICA (Min 8%) | E54: 0.2 | F54: 0.2 | G54: 0.2 | H54: 0.2 | I54: 0.2 | J54: 0.2 | K54: 0.2 | L54: 0.2 | M54: 0.2 | N54: 0.2 | O54: 0.2 | P54: 0.2 | Q54: 0.2 | R54: 0.2 | S54: 0.2 | T54: 0.2 | U54: 0.2 | V54: 0.2 | W54: 0.2 | X54: 0.2 | Y54: 0.2 | Z54: 0.2 | AA54: 0.2 | AB54: 0.2 | AC54: 0.2 | AD54: 0.2 | AE54: 0.2 | AF54: 0.2 | AG54: 0.2 | AH54: 0.2 | AI54: 0.2 | AJ54: 0.2 | AK54: 0.2 | AL54: 0.2 | AM54: 0.2 | AN54: 0.2 | AO54: 0.2 | AP54: 0.2 | AQ54: 0.2 | AR54: 0.2 | AS54: 0.2 | AT54: 0.2 | AU54: 0.2 | AV54: 0.2 | AW54: 0.2 | AX54: 0.2 | AY54: 0.2 | AZ54: 0.2 | BA54: 0.2 | BB54: 0.2 | BC54: 0.2 | BD54: 0.2 | BE54: 0.2 | BF54: 0.2
C55: CCD (Min 8%) | E55: 0.2 | F55: 0.2 | G55: 0.2 | H55: 0.2 | I55: 0.2 | J55: 0.2 | K55: 0.2 | L55: 0.2 | M55: 0.2 | N55: 0.2 | O55: 0.2 | P55: 0.2 | Q55: 0.2 | R55: 0.2 | S55: 0.2 | T55: 0.2 | U55: 0.2 | V55: 0.2 | W55: 0.2 | X55: 0.2 | Y55: 0.2 | Z55: 0.2 | AA55: 0.2 | AB55: 0.2 | AC55: 0.2 | AD55: 0.2 | AE55: 0.2 | AF55: 0.2 | AG55: 0.2 | AH55: 0.2 | AI55: 0.2 | AJ55: 0.2 | AK55: 0.2 | AL55: 0.2 | AM55: 0.2 | AN55: 0.2 | AO55: 0.2 | AP55: 0.2 | AQ55: 0.2 | AR55: 0.2 | AS55: 0.2 | AT55: 0.2 | AU55: 0.2 | AV55: 0.2 | AW55: 0.2 | AX55: 0.2 | AY55: 0.2 | AZ55: 0.2 | BA55: 0.2 | BB55: 0.2 | BC55: 0.2 | BD55: 0.2 | BE55: 0.2 | BF55: 0.2
C56: Adjusted CCA | E56: 0.39 | F56: 0.39 | G56: 0.39 | H56: 0.39 | I56: 0.39 | J56: 0.39 | K56: 0.39 | L56: 0.39 | M56: 0.39 | N56: 0.39 | O56: 0.39 | P56: 0.39 | Q56: 0.39 | R56: 0.39 | S56: 0.39 | T56: 0.39 | U56: 0.39 | V56: 0.39 | W56: 0.39 | X56: 0.39 | Y56: 0.39 | Z56: 0.39 | AA56: 0.39 | AB56: 0.39 | AC56: 0.39 | AD56: 0.39 | AE56: 0.39 | AF56: 0.39 | AG56: 0.39 | AH56: 0.39 | AI56: 0.39 | AJ56: 0.39 | AK56: 0.39 | AL56: 0.39 | AM56: 0.39 | AN56: 0.39 | AO56: 0.39 | AP56: 0.39 | AQ56: 0.39 | AR56: 0.39 | AS56: 0.39 | AT56: 0.39 | AU56: 0.39 | AV56: 0.39 | AW56: 0.39 | AX56: 0.39 | AY56: 0.39 | AZ56: 0.39 | BA56: 0.39 | BB56: 0.39 | BC56: 0.39 | BD56: 0.39 | BE56: 0.39 | BF56: 0.39
B57: ASSET QUALITY | C57: NPL30 | E57: 0.7 | F57: 0.7 | G57: 0.7 | H57: 0.7 | I57: 0.7 | J57: 0.7 | K57: 0.7 | L57: 0.7 | M57: 0.7 | N57: 0.7 | O57: 0.7 | P57: 0.7 | Q57: 0.7 | R57: 0.7 | S57: 0.7 | T57: 0.7 | U57: 0.7 | V57: 0.7 | W57: 0.7 | X57: 0.7 | Y57: 0.7 | Z57: 0.7 | AA57: 0.7 | AB57: 0.7 | AC57: 0.7 | AD57: 0.7 | AE57: 0.7 | AF57: 0.7 | AG57: 0.7 | AH57: 0.7 | AI57: 0.7 | AJ57: 0.7 | AK57: 0.7 | AL57: 0.7 | AM57: 0.7 | AN57: 0.7 | AO57: 0.7 | AP57: 0.7 | AQ57: 0.7 | AR57: 0.7 | AS57: 0.7 | AT57: 0.7 | AU57: 0.7 | AV57: 0.7 | AW57: 0.7 | AX57: 0.7 | AY57: 0.7 | AZ57: 0.7 | BA57: 0.7 | BB57: 0.7 | BC57: 0.7 | BD57: 0.7 | BE57: 0.7 | BF57: 0.7
C58: A/L NPL30 | E58: 0.3 | F58: 0.3 | G58: 0.3 | H58: 0.3 | I58: 0.3 | J58: 0.3 | K58: 0.3 | L58: 0.3 | M58: 0.3 | N58: 0.3 | O58: 0.3 | P58: 0.3 | Q58: 0.3 | R58: 0.3 | S58: 0.3 | T58: 0.3 | U58: 0.3 | V58: 0.3 | W58: 0.3 | X58: 0.3 | Y58: 0.3 | Z58: 0.3 | AA58: 0.3 | AB58: 0.3 | AC58: 0.3 | AD58: 0.3 | AE58: 0.3 | AF58: 0.3 | AG58: 0.3 | AH58: 0.3 | AI58: 0.3 | AJ58: 0.3 | AK58: 0.3 | AL58: 0.3 | AM58: 0.3 | AN58: 0.3 | AO58: 0.3 | AP58: 0.3 | AQ58: 0.3 | AR58: 0.3 | AS58: 0.3 | AT58: 0.3 | AU58: 0.3 | AV58: 0.3 | AW58: 0.3 | AX58: 0.3 | AY58: 0.3 | AZ58: 0.3 | BA58: 0.3 | BB58: 0.3 | BC58: 0.3 | BD58: 0.3 | BE58: 0.3 | BF58: 0.3
B59: EARNINGS | C59: ROA | E59: 0.5 | F59: 0.5 | G59: 0.5 | H59: 0.5 | I59: 0.5 | J59: 0.5 | K59: 0.5 | L59: 0.5 | M59: 0.5 | N59: 0.5 | O59: 0.5 | P59: 0.5 | Q59: 0.5 | R59: 0.5 | S59: 0.5 | T59: 0.5 | U59: 0.5 | V59: 0.5 | W59: 0.5 | X59: 0.5 | Y59: 0.5 | Z59: 0.5 | AA59: 0.5 | AB59: 0.5 | AC59: 0.5 | AD59: 0.5 | AE59: 0.5 | AF59: 0.5 | AG59: 0.5 | AH59: 0.5 | AI59: 0.5 | AJ59: 0.5 | AK59: 0.5 | AL59: 0.5 | AM59: 0.5 | AN59: 0.5 | AO59: 0.5 | AP59: 0.5 | AQ59: 0.5 | AR59: 0.5 | AS59: 0.5 | AT59: 0.5 | AU59: 0.5 | AV59: 0.5 | AW59: 0.5 | AX59: 0.5 | AY59: 0.5 | AZ59: 0.5 | BA59: 0.5 | BB59: 0.5 | BC59: 0.5 | BD59: 0.5 | BE59: 0.5 | BF59: 0.5
C60: C/I ratio | E60: 0.25 | F60: 0.25 | G60: 0.25 | H60: 0.25 | I60: 0.25 | J60: 0.25 | K60: 0.25 | L60: 0.25 | M60: 0.25 | N60: 0.25 | O60: 0.25 | P60: 0.25 | Q60: 0.25 | R60: 0.25 | S60: 0.25 | T60: 0.25 | U60: 0.25 | V60: 0.25 | W60: 0.25 | X60: 0.25 | Y60: 0.25 | Z60: 0.25 | AA60: 0.25 | AB60: 0.25 | AC60: 0.25 | AD60: 0.25 | AE60: 0.25 | AF60: 0.25 | AG60: 0.25 | AH60: 0.25 | AI60: 0.25 | AJ60: 0.25 | AK60: 0.25 | AL60: 0.25 | AM60: 0.25 | AN60: 0.25 | AO60: 0.25 | AP60: 0.25 | AQ60: 0.25 | AR60: 0.25 | AS60: 0.25 | AT60: 0.25 | AU60: 0.25 | AV60: 0.25 | AW60: 0.25 | AX60: 0.25 | AY60: 0.25 | AZ60: 0.25 | BA60: 0.25 | BB60: 0.25 | BC60: 0.25 | BD60: 0.25 | BE60: 0.25 | BF60: 0.25
C61: OE ratio | E61: 0.25 | F61: 0.25 | G61: 0.25 | H61: 0.25 | I61: 0.25 | J61: 0.25 | K61: 0.25 | L61: 0.25 | M61: 0.25 | N61: 0.25 | O61: 0.25 | P61: 0.25 | Q61: 0.25 | R61: 0.25 | S61: 0.25 | T61: 0.25 | U61: 0.25 | V61: 0.25 | W61: 0.25 | X61: 0.25 | Y61: 0.25 | Z61: 0.25 | AA61: 0.25 | AB61: 0.25 | AC61: 0.25 | AD61: 0.25 | AE61: 0.25 | AF61: 0.25 | AG61: 0.25 | AH61: 0.25 | AI61: 0.25 | AJ61: 0.25 | AK61: 0.25 | AL61: 0.25 | AM61: 0.25 | AN61: 0.25 | AO61: 0.25 | AP61: 0.25 | AQ61: 0.25 | AR61: 0.25 | AS61: 0.25 | AT61: 0.25 | AU61: 0.25 | AV61: 0.25 | AW61: 0.25 | AX61: 0.25 | AY61: 0.25 | AZ61: 0.25 | BA61: 0.25 | BB61: 0.25 | BC61: 0.25 | BD61: 0.25 | BE61: 0.25 | BF61: 0.25
B62: LIQUIDITY | C62: W NLIQ ratio | E62: 0.4 | F62: 0.4 | G62: 0.4 | H62: 0.4 | I62: 0.4 | J62: 0.4 | K62: 0.4 | L62: 0.4 | M62: 0.4 | N62: 0.4 | O62: 0.4 | P62: 0.4 | Q62: 0.4 | R62: 0.4 | S62: 0.4 | T62: 0.4 | U62: 0.4 | V62: 0.4 | W62: 0.4 | X62: 0.4 | Y62: 0.4 | Z62: 0.4 | AA62: 0.4 | AB62: 0.4 | AC62: 0.4 | AD62: 0.4 | AE62: 0.4 | AF62: 0.4 | AG62: 0.4 | AH62: 0.4 | AI62: 0.4 | AJ62: 0.4 | AK62: 0.4 | AL62: 0.4 | AM62: 0.4 | AN62: 0.4 | AO62: 0.4 | AP62: 0.4 | AQ62: 0.4 | AR62: 0.4 | AS62: 0.4 | AT62: 0.4 | AU62: 0.4 | AV62: 0.4 | AW62: 0.4 | AX62: 0.4 | AY62: 0.4 | AZ62: 0.4 | BA62: 0.4 | BB62: 0.4 | BC62: 0.4 | BD62: 0.4 | BE62: 0.4 | BF62: 0.4
C63: T NLIQ ratio | E63: 0.2 | F63: 0.2 | G63: 0.2 | H63: 0.2 | I63: 0.2 | J63: 0.2 | K63: 0.2 | L63: 0.2 | M63: 0.2 | N63: 0.2 | O63: 0.2 | P63: 0.2 | Q63: 0.2 | R63: 0.2 | S63: 0.2 | T63: 0.2 | U63: 0.2 | V63: 0.2 | W63: 0.2 | X63: 0.2 | Y63: 0.2 | Z63: 0.2 | AA63: 0.2 | AB63: 0.2 | AC63: 0.2 | AD63: 0.2 | AE63: 0.2 | AF63: 0.2 | AG63: 0.2 | AH63: 0.2 | AI63: 0.2 | AJ63: 0.2 | AK63: 0.2 | AL63: 0.2 | AM63: 0.2 | AN63: 0.2 | AO63: 0.2 | AP63: 0.2 | AQ63: 0.2 | AR63: 0.2 | AS63: 0.2 | AT63: 0.2 | AU63: 0.2 | AV63: 0.2 | AW63: 0.2 | AX63: 0.2 | AY63: 0.2 | AZ63: 0.2 | BA63: 0.2 | BB63: 0.2 | BC63: 0.2 | BD63: 0.2 | BE63: 0.2 | BF63: 0.2
C64: EB ratio | E64: 0.2 | F64: 0.2 | G64: 0.2 | H64: 0.2 | I64: 0.2 | J64: 0.2 | K64: 0.2 | L64: 0.2 | M64: 0.2 | N64: 0.2 | O64: 0.2 | P64: 0.2 | Q64: 0.2 | R64: 0.2 | S64: 0.2 | T64: 0.2 | U64: 0.2 | V64: 0.2 | W64: 0.2 | X64: 0.2 | Y64: 0.2 | Z64: 0.2 | AA64: 0.2 | AB64: 0.2 | AC64: 0.2 | AD64: 0.2 | AE64: 0.2 | AF64: 0.2 | AG64: 0.2 | AH64: 0.2 | AI64: 0.2 | AJ64: 0.2 | AK64: 0.2 | AL64: 0.2 | AM64: 0.2 | AN64: 0.2 | AO64: 0.2 | AP64: 0.2 | AQ64: 0.2 | AR64: 0.2 | AS64: 0.2 | AT64: 0.2 | AU64: 0.2 | AV64: 0.2 | AW64: 0.2 | AX64: 0.2 | AY64: 0.2 | AZ64: 0.2 | BA64: 0.2 | BB64: 0.2 | BC64: 0.2 | BD64: 0.2 | BE64: 0.2 | BF64: 0.2
C65: LIQ to TA ratio | E65: 0.2 | F65: 0.2 | G65: 0.2 | H65: 0.2 | I65: 0.2 | J65: 0.2 | K65: 0.2 | L65: 0.2 | M65: 0.2 | N65: 0.2 | O65: 0.2 | P65: 0.2 | Q65: 0.2 | R65: 0.2 | S65: 0.2 | T65: 0.2 | U65: 0.2 | V65: 0.2 | W65: 0.2 | X65: 0.2 | Y65: 0.2 | Z65: 0.2 | AA65: 0.2 | AB65: 0.2 | AC65: 0.2 | AD65: 0.2 | AE65: 0.2 | AF65: 0.2 | AG65: 0.2 | AH65: 0.2 | AI65: 0.2 | AJ65: 0.2 | AK65: 0.2 | AL65: 0.2 | AM65: 0.2 | AN65: 0.2 | AO65: 0.2 | AP65: 0.2 | AQ65: 0.2 | AR65: 0.2 | AS65: 0.2 | AT65: 0.2 | AU65: 0.2 | AV65: 0.2 | AW65: 0.2 | AX65: 0.2 | AY65: 0.2 | AZ65: 0.2 | BA65: 0.2 | BB65: 0.2 | BC65: 0.2 | BD65: 0.2 | BE65: 0.2 | BF65: 0.2
B66: STRUCTURE OF ASSETS | C66: LB ratio (Max 5%) | E66: 0.25 | F66: 0.25 | G66: 0.25 | H66: 0.25 | I66: 0.25 | J66: 0.25 | K66: 0.25 | L66: 0.25 | M66: 0.25 | N66: 0.25 | O66: 0.25 | P66: 0.25 | Q66: 0.25 | R66: 0.25 | S66: 0.25 | T66: 0.25 | U66: 0.25 | V66: 0.25 | W66: 0.25 | X66: 0.25 | Y66: 0.25 | Z66: 0.25 | AA66: 0.25 | AB66: 0.25 | AC66: 0.25 | AD66: 0.25 | AE66: 0.25 | AF66: 0.25 | AG66: 0.25 | AH66: 0.25 | AI66: 0.25 | AJ66: 0.25 | AK66: 0.25 | AL66: 0.25 | AM66: 0.25 | AN66: 0.25 | AO66: 0.25 | AP66: 0.25 | AQ66: 0.25 | AR66: 0.25 | AS66: 0.25 | AT66: 0.25 | AU66: 0.25 | AV66: 0.25 | AW66: 0.25 | AX66: 0.25 | AY66: 0.25 | AZ66: 0.25 | BA66: 0.25 | BB66: 0.25 | BC66: 0.25 | BD66: 0.25 | BE66: 0.25 | BF66: 0.25
C67: FICC (Max 40%) | E67: 0.25 | F67: 0.25 | G67: 0.25 | H67: 0.25 | I67: 0.25 | J67: 0.25 | K67: 0.25 | L67: 0.25 | M67: 0.25 | N67: 0.25 | O67: 0.25 | P67: 0.25 | Q67: 0.25 | R67: 0.25 | S67: 0.25 | T67: 0.25 | U67: 0.25 | V67: 0.25 | W67: 0.25 | X67: 0.25 | Y67: 0.25 | Z67: 0.25 | AA67: 0.25 | AB67: 0.25 | AC67: 0.25 | AD67: 0.25 | AE67: 0.25 | AF67: 0.25 | AG67: 0.25 | AH67: 0.25 | AI67: 0.25 | AJ67: 0.25 | AK67: 0.25 | AL67: 0.25 | AM67: 0.25 | AN67: 0.25 | AO67: 0.25 | AP67: 0.25 | AQ67: 0.25 | AR67: 0.25 | AS67: 0.25 | AT67: 0.25 | AU67: 0.25 | AV67: 0.25 | AW67: 0.25 | AX67: 0.25 | AY67: 0.25 | AZ67: 0.25 | BA67: 0.25 | BB67: 0.25 | BC67: 0.25 | BD67: 0.25 | BE67: 0.25 | BF67: 0.25
C68: FITD (Max 5%) | E68: 0.25 | F68: 0.25 | G68: 0.25 | H68: 0.25 | I68: 0.25 | J68: 0.25 | K68: 0.25 | L68: 0.25 | M68: 0.25 | N68: 0.25 | O68: 0.25 | P68: 0.25 | Q68: 0.25 | R68: 0.25 | S68: 0.25 | T68: 0.25 | U68: 0.25 | V68: 0.25 | W68: 0.25 | X68: 0.25 | Y68: 0.25 | Z68: 0.25 | AA68: 0.25 | AB68: 0.25 | AC68: 0.25 | AD68: 0.25 | AE68: 0.25 | AF68: 0.25 | AG68: 0.25 | AH68: 0.25 | AI68: 0.25 | AJ68: 0.25 | AK68: 0.25 | AL68: 0.25 | AM68: 0.25 | AN68: 0.25 | AO68: 0.25 | AP68: 0.25 | AQ68: 0.25 | AR68: 0.25 | AS68: 0.25 | AT68: 0.25 | AU68: 0.25 | AV68: 0.25 | AW68: 0.25 | AX68: 0.25 | AY68: 0.25 | AZ68: 0.25 | BA68: 0.25 | BB68: 0.25 | BC68: 0.25 | BD68: 0.25 | BE68: 0.25 | BF68: 0.25
C69: NEA (Max 10%) | E69: 0.25 | F69: 0.25 | G69: 0.25 | H69: 0.25 | I69: 0.25 | J69: 0.25 | K69: 0.25 | L69: 0.25 | M69: 0.25 | N69: 0.25 | O69: 0.25 | P69: 0.25 | Q69: 0.25 | R69: 0.25 | S69: 0.25 | T69: 0.25 | U69: 0.25 | V69: 0.25 | W69: 0.25 | X69: 0.25 | Y69: 0.25 | Z69: 0.25 | AA69: 0.25 | AB69: 0.25 | AC69: 0.25 | AD69: 0.25 | AE69: 0.25 | AF69: 0.25 | AG69: 0.25 | AH69: 0.25 | AI69: 0.25 | AJ69: 0.25 | AK69: 0.25 | AL69: 0.25 | AM69: 0.25 | AN69: 0.25 | AO69: 0.25 | AP69: 0.25 | AQ69: 0.25 | AR69: 0.25 | AS69: 0.25 | AT69: 0.25 | AU69: 0.25 | AV69: 0.25 | AW69: 0.25 | AX69: 0.25 | AY69: 0.25 | AZ69: 0.25 | BA69: 0.25 | BB69: 0.25 | BC69: 0.25 | BD69: 0.25 | BE69: 0.25 | BF69: 0.25
A71: COMPONENT RATINGS | B71: CAPITAL
B72: ASSET QUALITY | E72: =IF(MAX(E33:E34)-E78>1,MAX(E33:E34)-1,E78) -> 1 | F72: =IF(MAX(F33:F34)-F78>1,MAX(F33:F34)-1,F78) -> 1 | G72: =IF(MAX(G33:G34)-G78>1,MAX(G33:G34)-1,G78) -> 1 | H72: =IF(MAX(H33:H34)-H78>1,MAX(H33:H34)-1,H78) -> 1 | I72: =IF(MAX(I33:I34)-I78>1,MAX(I33:I34)-1,I78) -> 1 | J72: =IF(MAX(J33:J34)-J78>1,MAX(J33:J34)-1,J78) -> 1 | K72: =IF(MAX(K33:K34)-K78>1,MAX(K33:K34)-1,K78) -> 1 | L72: =IF(MAX(L33:L34)-L78>1,MAX(L33:L34)-1,L78) -> 1 | ... BF72: =IF(MAX(BF33:BF34)-BF78>1,MAX(BF33:BF34)-1,BF78) -> 1
B73: EARNINGS | E73: =IF(MAX(E37:E39)-E79>1,MAX(E37:E39)-1,E79) -> 3 | F73: =IF(MAX(F37:F39)-F79>1,MAX(F37:F39)-1,F79) -> 3 | G73: =IF(MAX(G37:G39)-G79>1,MAX(G37:G39)-1,G79) -> 3 | H73: =IF(MAX(H37:H39)-H79>1,MAX(H37:H39)-1,H79) -> 3 | I73: =IF(MAX(I37:I39)-I79>1,MAX(I37:I39)-1,I79) -> 3 | J73: =IF(MAX(J37:J39)-J79>1,MAX(J37:J39)-1,J79) -> 3 | K73: =IF(MAX(K37:K39)-K79>1,MAX(K37:K39)-1,K79) -> 3 | L73: =IF(MAX(L37:L39)-L79>1,MAX(L37:L39)-1,L79) -> 3 | ... BF73: =IF(MAX(BF37:BF39)-BF79>1,MAX(BF37:BF39)-1,BF79) -> 3
B74: LIQUIDITY | E74: =IF(MAX(E43:E44)-E80>1,MAX(E43:E44),E80) -> 4 | F74: =IF(MAX(F43:F44)-F80>1,MAX(F43:F44),F80) -> 4 | G74: =IF(MAX(G43:G44)-G80>1,MAX(G43:G44),G80) -> 4 | H74: =IF(MAX(H43:H44)-H80>1,MAX(H43:H44),H80) -> 4 | I74: =IF(MAX(I43:I44)-I80>1,MAX(I43:I44),I80) -> 4 | J74: =IF(MAX(J43:J44)-J80>1,MAX(J43:J44),J80) -> 4 | K74: =IF(MAX(K43:K44)-K80>1,MAX(K43:K44),K80) -> 4 | L74: =IF(MAX(L43:L44)-L80>1,MAX(L43:L44),L80) -> 4 | ... BF74: =IF(MAX(BF43:BF44)-BF80>1,MAX(BF43:BF44),BF80) -> 4
B75: STRUCTURE | E75: =IF(MAX(E46:E49)-E81>1,MAX(E46:E49)-1,E81) -> 1 | F75: =IF(MAX(F46:F49)-F81>1,MAX(F46:F49)-1,F81) -> 1 | G75: =IF(MAX(G46:G49)-G81>1,MAX(G46:G49)-1,G81) -> 1 | H75: =IF(MAX(H46:H49)-H81>1,MAX(H46:H49)-1,H81) -> 1 | I75: =IF(MAX(I46:I49)-I81>1,MAX(I46:I49)-1,I81) -> 1 | J75: =IF(MAX(J46:J49)-J81>1,MAX(J46:J49)-1,J81) -> 1 | K75: =IF(MAX(K46:K49)-K81>1,MAX(K46:K49)-1,K81) -> 1 | L75: =IF(MAX(L46:L49)-L81>1,MAX(L46:L49)-1,L81) -> 1 | ... BF75: =IF(MAX(BF46:BF49)-BF81>1,MAX(BF46:BF49)-1,BF81) -> 1
A77: CONDITIONAL COMPONENT RATINGS | B77: CAPITAL | E77: =ROUND(SUMPRODUCT(E28:E32,E52:E56),0) -> 2 | F77: =ROUND(SUMPRODUCT(F28:F32,F52:F56),0) -> 2 | G77: =ROUND(SUMPRODUCT(G28:G32,G52:G56),0) -> 2 | H77: =ROUND(SUMPRODUCT(H28:H32,H52:H56),0) -> 2 | I77: =ROUND(SUMPRODUCT(I28:I32,I52:I56),0) -> 2 | J77: =ROUND(SUMPRODUCT(J28:J32,J52:J56),0) -> 2 | K77: =ROUND(SUMPRODUCT(K28:K32,K52:K56),0) -> 2 | L77: =ROUND(SUMPRODUCT(L28:L32,L52:L56),0) -> 2 | ... BF77: =ROUND(SUMPRODUCT(BF28:BF32,BF52:BF56),0) -> 2
B78: ASSET QUALITY | E78: =ROUND(SUMPRODUCT(E34:E35,E57:E58),0) -> 1 | F78: =ROUND(SUMPRODUCT(F34:F35,F57:F58),0) -> 1 | G78: =ROUND(SUMPRODUCT(G34:G35,G57:G58),0) -> 1 | H78: =ROUND(SUMPRODUCT(H34:H35,H57:H58),0) -> 1 | I78: =ROUND(SUMPRODUCT(I34:I35,I57:I58),0) -> 1 | J78: =ROUND(SUMPRODUCT(J34:J35,J57:J58),0) -> 1 | K78: =ROUND(SUMPRODUCT(K34:K35,K57:K58),0) -> 1 | L78: =ROUND(SUMPRODUCT(L34:L35,L57:L58),0) -> 1 | ... BF78: =ROUND(SUMPRODUCT(BF34:BF35,BF57:BF58),0) -> 1
B79: EARNINGS | E79: =ROUND(SUMPRODUCT(E37:E39,E59:E61),0) -> 3 | F79: =ROUND(SUMPRODUCT(F37:F39,F59:F61),0) -> 3 | G79: =ROUND(SUMPRODUCT(G37:G39,G59:G61),0) -> 3 | H79: =ROUND(SUMPRODUCT(H37:H39,H59:H61),0) -> 3 | I79: =ROUND(SUMPRODUCT(I37:I39,I59:I61),0) -> 3 | J79: =ROUND(SUMPRODUCT(J37:J39,J59:J61),0) -> 3 | K79: =ROUND(SUMPRODUCT(K37:K39,K59:K61),0) -> 3 | L79: =ROUND(SUMPRODUCT(L37:L39,L59:L61),0) -> 3 | ... BF79: =ROUND(SUMPRODUCT(BF37:BF39,BF59:BF61),0) -> 3
B80: LIQUIDITY | E80: =ROUND(SUMPRODUCT(E41:E44,E62:E65),0) -> 4 | F80: =ROUND(SUMPRODUCT(F41:F44,F62:F65),0) -> 4 | G80: =ROUND(SUMPRODUCT(G41:G44,G62:G65),0) -> 4 | H80: =ROUND(SUMPRODUCT(H41:H44,H62:H65),0) -> 4 | I80: =ROUND(SUMPRODUCT(I41:I44,I62:I65),0) -> 4 | J80: =ROUND(SUMPRODUCT(J41:J44,J62:J65),0) -> 4 | K80: =ROUND(SUMPRODUCT(K41:K44,K62:K65),0) -> 4 | L80: =ROUND(SUMPRODUCT(L41:L44,L62:L65),0) -> 4 | ... BF80: =ROUND(SUMPRODUCT(BF41:BF44,BF62:BF65),0) -> 4
B81: STRUCTURE | E81: =ROUND(SUMPRODUCT(E46:E49,E66:E69),0) -> 1 | F81: =ROUND(SUMPRODUCT(F46:F49,F66:F69),0) -> 1 | G81: =ROUND(SUMPRODUCT(G46:G49,G66:G69),0) -> 1 | H81: =ROUND(SUMPRODUCT(H46:H49,H66:H69),0) -> 1 | I81: =ROUND(SUMPRODUCT(I46:I49,I66:I69),0) -> 1 | J81: =ROUND(SUMPRODUCT(J46:J49,J66:J69),0) -> 1 | K81: =ROUND(SUMPRODUCT(K46:K49,K66:K69),0) -> 1 | L81: =ROUND(SUMPRODUCT(L46:L49,L66:L69),0) -> 1 | ... BF81: =ROUND(SUMPRODUCT(BF46:BF49,BF66:BF69),0) -> 1
A83: COMPOSITE RATINGS | B83: CONDITION RATING | E83: =AVERAGE(E77:E81) -> 2.2 | F83: =AVERAGE(F77:F81) -> 2.2 | G83: =AVERAGE(G77:G81) -> 2.2 | H83: =AVERAGE(H77:H81) -> 2.2 | I83: =AVERAGE(I77:I81) -> 2.2 | J83: =AVERAGE(J77:J81) -> 2.2 | K83: =AVERAGE(K77:K81) -> 2.2 | L83: =AVERAGE(L77:L81) -> 2.2 | ... BF83: =AVERAGE(BF77:BF81) -> 2.2
B84: AVERAGE OF COMP RATINGS | E84: =AVERAGE(E71:E75) -> 2.25 | F84: =AVERAGE(F71:F75) -> 2.25 | G84: =AVERAGE(G71:G75) -> 2.25 | H84: =AVERAGE(H71:H75) -> 2.25 | I84: =AVERAGE(I71:I75) -> 2.25 | J84: =AVERAGE(J71:J75) -> 2.25 | K84: =AVERAGE(K71:K75) -> 2.25 | L84: =AVERAGE(L71:L75) -> 2.25 | ... BF84: =AVERAGE(BF71:BF75) -> 2.25
B85: COMPLIANCE RATING SOFT | E85: =IF(MAX(E71:E75)-E84>1,MAX(E71:E75)-1,E84) -> 3 | F85: =IF(MAX(F71:F75)-F84>1,MAX(F71:F75)-1,F84) -> 3 | G85: =IF(MAX(G71:G75)-G84>1,MAX(G71:G75)-1,G84) -> 3 | H85: =IF(MAX(H71:H75)-H84>1,MAX(H71:H75)-1,H84) -> 3 | I85: =IF(MAX(I71:I75)-I84>1,MAX(I71:I75)-1,I84) -> 3 | J85: =IF(MAX(J71:J75)-J84>1,MAX(J71:J75)-1,J84) -> 3 | K85: =IF(MAX(K71:K75)-K84>1,MAX(K71:K75)-1,K84) -> 3 | L85: =IF(MAX(L71:L75)-L84>1,MAX(L71:L75)-1,L84) -> 3 | ... BF85: =IF(MAX(BF71:BF75)-BF84>1,MAX(BF71:BF75)-1,BF84) -> 3
B86: FINAL RATING | C86: In the Law only | E86: =IF(MAX(E28,E29,E30,E31,E41,E43,E46,E47,E48,E49)-E83>1,MAX(E28,E29,E30,E31,E41,E43,E46,E47,E48,E49)-1,E83) -> 4 | F86: =IF(MAX(F28,F29,F30,F31,F41,F43,F46,F47,F48,F49)-F83>1,MAX(F28,F29,F30,F31,F41,F43,F46,F47,F48,F49)-1,F83) -> 4 | G86: =IF(MAX(G28,G29,G30,G31,G41,G43,G46,G47,G48,G49)-G83>1,MAX(G28,G29,G30,G31,G41,G43,G46,G47,G48,G49)-1,G83) -> 4 | H86: =IF(MAX(H28,H29,H30,H31,H41,H43,H46,H47,H48,H49)-H83>1,MAX(H28,H29,H30,H31,H41,H43,H46,H47,H48,H49)-1,H83) -> 4 | I86: =IF(MAX(I28,I29,I30,I31,I41,I43,I46,I47,I48,I49)-I83>1,MAX(I28,I29,I30,I31,I41,I43,I46,I47,I48,I49)-1,I83) -> 4 | J86: =IF(MAX(J28,J29,J30,J31,J41,J43,J46,J47,J48,J49)-J83>1,MAX(J28,J29,J30,J31,J41,J43,J46,J47,J48,J49)-1,J83) -> 4 | K86: =IF(MAX(K28,K29,K30,K31,K41,K43,K46,K47,K48,K49)-K83>1,MAX(K28,K29,K30,K31,K41,K43,K46,K47,K48,K49)-1,K83) -> 4 | L86: =IF(MAX(L28,L29,L30,L31,L41,L43,L46,L47,L48,L49)-L83>1,MAX(L28,L29,L30,L31,L41,L43,L46,L47,L48,L49)-1,L83) -> 4 | ... BF86: =IF(MAX(BF28,BF29,BF30,BF31,BF41,BF43,BF46,BF47,BF48,BF49)-BF83>1,MAX(BF28,BF29,BF30,BF31,BF41,BF43,BF46,BF47,BF48,BF49)-1,BF83) -> 4

Sheet Prudential Ratios
A1: IG SACCO SOCIETY LTD
A2: Afya Sacco Financial Performance
A4: FINANCIAL SOUNDNESS INDICATORS | B4: Prude. Std | C4: Ref. # | D4: Audited 2017 | E4: 43101 | F4: 43132 | G4: 43160 | H4: 43191 | I4: 43221 | J4: 43252 | K4: 43282 | L4: 43313 | M4: 43344 | N4: 43374 | O4: 43405 | P4: 43435 | Q4: Audited 2018
A5: CAPITAL ADEQUACY REQUIREMENTS | AE5: 43831 | AF5: 43862 | AG5: 43891 | AH5: 43922 | AI5: 43952 | AJ5: 43983 | AK5: 44013 | AL5: 44044 | AM5: 44075 | AN5: 44105 | AO5: 44136 | AP5: 44166 | AQ5: Audited 2020 | AR5: 44197 | AS5: 44228 | AT5: 44256 | AU5: 44287 | AV5: 44317 | AW5: 44348 | AX5: 44378 | AY5: 44409 | AZ5: 44440 | BA5: 44470 | BB5: 44501 | BC5: 44531 | BD5: Audited 2021 | BE5: 44562 | BF5: 44593 | BG5: 44621 | BH5: 44652 | BI5: 44682 | BJ5: 44713 | BK5: 44743 | BL5: 44774
A6: Core capital | B6: ≥ Ksh.10M | C6: 9.a | D6: =CAELS!E4 -> 2354.8772 | E6: =CAELS!#REF! -> #REF! | F6: =CAELS!#REF! -> #REF! | G6: =CAELS!#REF! -> #REF! | H6: =CAELS!#REF! -> #REF! | I6: =CAELS!#REF! -> #REF! | J6: =CAELS!#REF! -> #REF! | K6: =CAELS!#REF! -> #REF! | L6: =CAELS!#REF! -> #REF! | ... P6: =CAELS!#REF! -> #REF! | Q6: =CAELS!F4 -> 2112.2539 | R6: =CAELS!G4 -> 2260.4537 | S6: =CAELS!H4 -> 2296.4904 | T6: =CAELS!I4 -> 2316.8831 | U6: =CAELS!J4 -> 2350.464 | V6: =CAELS!K4 -> 2401.1642 | W6: =CAELS!L4 -> 2419.0936 | X6: =CAELS!M4 -> 2415.9595 | ... BQ6: =CAELS!BF4 -> 4484.427 | BR6: =CAELS!#REF! -> #REF! | BS6: =CAELS!BG4 -> 0 | BT6: =CAELS!BH4 -> 0 | BU6: =CAELS!BI4 -> 0 | BV6: =CAELS!BJ4 -> 0 | BW6: =CAELS!BK4 -> 0 | BX6: =CAELS!BL4 -> 0 | BY6: =CAELS!BM4 -> 0 | BZ6: =CAELS!BN4 -> 0
A7: Core capital /Total Assets | B7: ≥ 10% | C7: 9.b | D7: =CAELS!E5 -> 0.29049771 | E7: =CAELS!#REF! -> #REF! | F7: =CAELS!#REF! -> #REF! | G7: =CAELS!#REF! -> #REF! | H7: =CAELS!#REF! -> #REF! | I7: =CAELS!#REF! -> #REF! | J7: =CAELS!#REF! -> #REF! | K7: =CAELS!#REF! -> #REF! | L7: =CAELS!#REF! -> #REF! | ... P7: =CAELS!#REF! -> #REF! | Q7: =CAELS!F5 -> 0.24236128 | R7: =CAELS!G5 -> 0.25227516 | S7: =CAELS!H5 -> 0.25634815 | T7: =CAELS!I5 -> 0.25605685 | U7: =CAELS!J5 -> 0.27491438 | V7: =CAELS!K5 -> 0.28073567 | W7: =CAELS!L5 -> 0.27783371 | X7: =CAELS!M5 -> 0.27461853 | ... BQ7: =CAELS!BF5 -> 0.34607337 | BR7: =CAELS!#REF! -> #REF! | BS7: =CAELS!BG5 -> 0 | BT7: =CAELS!BH5 -> 0 | BU7: =CAELS!BI5 -> 0 | BV7: =CAELS!BJ5 -> 0 | BW7: =CAELS!BK5 -> 0 | BX7: =CAELS!BL5 -> 0 | BY7: =CAELS!BM5 -> 0 | BZ7: =CAELS!BN5 -> 0
A8: Core capital /Total Deposits | B8: ≥ 8% | C8: 9.d | D8: =CAELS!E6 -> 0.24331869 | E8: =CAELS!#REF! -> #REF! | F8: =CAELS!#REF! -> #REF! | G8: =CAELS!#REF! -> #REF! | H8: =CAELS!#REF! -> #REF! | I8: =CAELS!#REF! -> #REF! | J8: =CAELS!#REF! -> #REF! | K8: =CAELS!#REF! -> #REF! | L8: =CAELS!#REF! -> #REF! | ... P8: =CAELS!#REF! -> #REF! | Q8: =CAELS!F6 -> 0.19394967 | R8: =CAELS!G6 -> 0.17729934 | S8: =CAELS!H6 -> 0.18093922 | T8: =CAELS!I6 -> 0.18064482 | U8: =CAELS!J6 -> 0.19362637 | V8: =CAELS!K6 -> 0.19890984 | W8: =CAELS!L6 -> 0.19697259 | X8: =CAELS!M6 -> 0.19425579 | ... BQ8: =CAELS!BF6 -> 0.24534497 | BR8: =CAELS!#REF! -> #REF! | BS8: =CAELS!BG6 -> 0 | BT8: =CAELS!BH6 -> 0 | BU8: =CAELS!BI6 -> 0 | BV8: =CAELS!BJ6 -> 0 | BW8: =CAELS!BK6 -> 0 | BX8: =CAELS!BL6 -> 0 | BY8: =CAELS!BM6 -> 0 | BZ8: =CAELS!BN6 -> 0
A9: Share Capital/Total Assets | B9: ≤2% | C9: 9.c | D9: =CAELS!E7 -> 0.52513872 | E9: =CAELS!#REF! -> #REF! | F9: =CAELS!#REF! -> #REF! | G9: =CAELS!#REF! -> #REF! | H9: =CAELS!#REF! -> #REF! | I9: =CAELS!#REF! -> #REF! | J9: =CAELS!#REF! -> #REF! | K9: =CAELS!#REF! -> #REF! | L9: =CAELS!#REF! -> #REF! | ... P9: =CAELS!#REF! -> #REF! | Q9: =CAELS!F7 -> 0.42560133 | R9: =CAELS!G7 -> 0.45392085 | S9: =CAELS!H7 -> 0.45608835 | T9: =CAELS!I7 -> 0.4503879 | U9: =CAELS!J7 -> 0.45503927 | V9: =CAELS!K7 -> 0.46677668 | W9: =CAELS!L7 -> 0.46759655 | X9: =CAELS!M7 -> 0.46642965 | ... BQ9: =CAELS!BF7 -> 0.6365721 | BR9: =CAELS!#REF! -> #REF! | BS9: =CAELS!BG7 -> 0 | BT9: =CAELS!BH7 -> 0 | BU9: =CAELS!BI7 -> 0 | BV9: =CAELS!BJ7 -> 0 | BW9: =CAELS!BK7 -> 0 | BX9: =CAELS!BL7 -> 0 | BY9: =CAELS!BM7 -> 0 | BZ9: =CAELS!BN7 -> 0
A10: Institutional Capital/Total Assets | B10: ≥ 8% | C10: 9.c | D10: =CAELS!E8 -> 0.29049771 | E10: =CAELS!#REF! -> #REF! | F10: =CAELS!#REF! -> #REF! | G10: =CAELS!#REF! -> #REF! | H10: =CAELS!#REF! -> #REF! | I10: =CAELS!#REF! -> #REF! | J10: =CAELS!#REF! -> #REF! | K10: =CAELS!#REF! -> #REF! | L10: =CAELS!#REF! -> #REF! | ... P10: =CAELS!#REF! -> #REF! | Q10: =CAELS!F8 -> 0.24236128 | R10: =CAELS!G8 -> 0.25227516 | S10: =CAELS!H8 -> 0.25634815 | T10: =CAELS!I8 -> 0.25605685 | U10: =CAELS!J8 -> 0.27491438 | V10: =CAELS!K8 -> 0.28073567 | W10: =CAELS!L8 -> 0.27783371 | X10: =CAELS!M8 -> 0.27461853 | ... BQ10: =CAELS!BF8 -> 0.34607337 | BR10: =CAELS!#REF! -> #REF! | BS10: =CAELS!BG8 -> 0 | BT10: =CAELS!BH8 -> 0 | BU10: =CAELS!BI8 -> 0 | BV10: =CAELS!BJ8 -> 0 | BW10: =CAELS!BK8 -> 0 | BX10: =CAELS!BL8 -> 0 | BY10: =CAELS!BM8 -> 0 | BZ10: =CAELS!BN8 -> 0
A12: ASSET MIX AND QUALITY
A13: Non Earning Assets
A14: Non earning Assets/Total assets | B14: ≤ 10% | C14: 48.1 | D14: =CAELS!E25 -> 0.045089754 | E14: =CAELS!#REF! -> #REF! | F14: =CAELS!#REF! -> #REF! | G14: =CAELS!#REF! -> #REF! | H14: =CAELS!#REF! -> #REF! | I14: =CAELS!#REF! -> #REF! | J14: =CAELS!#REF! -> #REF! | K14: =CAELS!#REF! -> #REF! | L14: =CAELS!#REF! -> #REF! | ... P14: =CAELS!#REF! -> #REF! | Q14: =CAELS!F25 -> 0.041725469 | R14: =CAELS!G25 -> 0.059743996 | S14: =CAELS!H25 -> 0.050727611 | T14: =CAELS!I25 -> 0.050121236 | U14: =CAELS!J25 -> 0.048788143 | V14: =CAELS!K25 -> 0.0482892 | W14: =CAELS!L25 -> 0.048193307 | X14: =CAELS!M25 -> 0.053723507 | ... BQ14: =CAELS!BF25 -> 0.039741939 | BR14: =CAELS!#REF! -> #REF! | BS14: =CAELS!BG25 -> 0 | BT14: =CAELS!BH25 -> 0 | BU14: =CAELS!BI25 -> 0 | BV14: =CAELS!BJ25 -> 0 | BW14: =CAELS!BK25 -> 0 | BX14: =CAELS!BL25 -> 0 | BY14: =CAELS!BM25 -> 0 | BZ14: =CAELS!BN25 -> 0
A15: Property and Equipment/Total Assets | B15: ≤ 5% | C15: 48.1 | D15: =CAELS!E22 -> 0 | E15: =CAELS!#REF! -> #REF! | F15: =CAELS!#REF! -> #REF! | G15: =CAELS!#REF! -> #REF! | H15: =CAELS!#REF! -> #REF! | I15: =CAELS!#REF! -> #REF! | J15: =CAELS!#REF! -> #REF! | K15: =CAELS!#REF! -> #REF! | L15: =CAELS!#REF! -> #REF! | ... P15: =CAELS!#REF! -> #REF! | Q15: =CAELS!F22 -> 0 | R15: =CAELS!G22 -> 0 | S15: =CAELS!H22 -> 0 | T15: =CAELS!I22 -> 0 | U15: =CAELS!J22 -> 0 | V15: =CAELS!K22 -> 0 | W15: =CAELS!L22 -> 0 | X15: =CAELS!M22 -> 0 | ... BQ15: =CAELS!BF22 -> 0 | BR15: =CAELS!#REF! -> #REF! | BS15: =CAELS!BG22 -> 0 | BT15: =CAELS!BH22 -> 0 | BU15: =CAELS!BI22 -> 0 | BV15: =CAELS!BJ22 -> 0 | BW15: =CAELS!BK22 -> 0 | BX15: =CAELS!BL22 -> 0 | BY15: =CAELS!BM22 -> 0 | BZ15: =CAELS!BN22 -> 0
A16: Non Performing loans/Gross Loans | B16: ≤ 6% | C16: 41
A18: Earning Assets
A19: Equities & Investments/Deposits | B19: ≤ 5% | C19: 48.4 | D19: =CAELS!E22 -> 0 | E19: =CAELS!#REF! -> #REF! | F19: =CAELS!#REF! -> #REF! | G19: =CAELS!#REF! -> #REF! | H19: =CAELS!#REF! -> #REF! | I19: =CAELS!#REF! -> #REF! | J19: =CAELS!#REF! -> #REF! | K19: =CAELS!#REF! -> #REF! | L19: =CAELS!#REF! -> #REF! | ... P19: =CAELS!#REF! -> #REF! | Q19: =CAELS!F22 -> 0 | R19: =CAELS!G22 -> 0 | S19: =CAELS!H22 -> 0 | T19: =CAELS!I22 -> 0 | U19: =CAELS!J22 -> 0 | V19: =CAELS!K22 -> 0 | W19: =CAELS!L22 -> 0 | X19: =CAELS!M22 -> 0 | ... BQ19: =CAELS!BF22 -> 0 | BR19: =CAELS!#REF! -> #REF! | BS19: =CAELS!BG22 -> 0 | BT19: =CAELS!BH22 -> 0 | BU19: =CAELS!BI22 -> 0 | BV19: =CAELS!BJ22 -> 0 | BW19: =CAELS!BK22 -> 0 | BX19: =CAELS!BL22 -> 0 | BY19: =CAELS!BM22 -> 0 | BZ19: =CAELS!BN22 -> 0
A20: Equities & Investments/Core Capital | B20: ≤ 40% | C20: 48.4 | D20: =CAELS!E23 -> 0.18617178 | E20: =CAELS!#REF! -> #REF! | F20: =CAELS!#REF! -> #REF! | G20: =CAELS!#REF! -> #REF! | H20: =CAELS!#REF! -> #REF! | I20: =CAELS!#REF! -> #REF! | J20: =CAELS!#REF! -> #REF! | K20: =CAELS!#REF! -> #REF! | L20: =CAELS!#REF! -> #REF! | ... P20: =CAELS!#REF! -> #REF! | Q20: =CAELS!F23 -> 0.22770426 | R20: =CAELS!G23 -> 0.22298057 | S20: =CAELS!H23 -> 0.2082994 | T20: =CAELS!I23 -> 0.2066577 | U20: =CAELS!J23 -> 0.20389417 | V20: =CAELS!K23 -> 0.20135653 | W20: =CAELS!L23 -> 0.21575613 | X20: =CAELS!M23 -> 0.2183598 | ... BQ20: =CAELS!BF23 -> 0.34381851 | BR20: =CAELS!#REF! -> #REF! | BS20: =CAELS!BG23 -> 0 | BT20: =CAELS!BH23 -> 0 | BU20: =CAELS!BI23 -> 0 | BV20: =CAELS!BJ23 -> 0 | BW20: =CAELS!BK23 -> 0 | BX20: =CAELS!BL23 -> 0 | BY20: =CAELS!BM23 -> 0 | BZ20: =CAELS!BN23 -> 0
A21: Net Loans & advances /Total assets | B21: NPR | D21: =CAELS!E26 -> 0.80519061 | E21: =CAELS!#REF! -> #REF! | F21: =CAELS!#REF! -> #REF! | G21: =CAELS!#REF! -> #REF! | H21: =CAELS!#REF! -> #REF! | I21: =CAELS!#REF! -> #REF! | J21: =CAELS!#REF! -> #REF! | K21: =CAELS!#REF! -> #REF! | L21: =CAELS!#REF! -> #REF! | ... P21: =CAELS!#REF! -> #REF! | Q21: =CAELS!F26 -> 0.77284578 | R21: =CAELS!G26 -> 0.75035438 | S21: =CAELS!H26 -> 0.74810962 | T21: =CAELS!I26 -> 0.73219859 | U21: =CAELS!J26 -> 0.75662883 | V21: =CAELS!K26 -> 0.74689133 | W21: =CAELS!L26 -> 0.72993748 | X21: =CAELS!M26 -> 0.72144756 | ... BQ21: =CAELS!BF26 -> 0.70397292 | BR21: =CAELS!#REF! -> #REF! | BS21: =CAELS!BG26 -> 0 | BT21: =CAELS!BH26 -> 0 | BU21: =CAELS!BI26 -> 0 | BV21: =CAELS!BJ26 -> 0 | BW21: =CAELS!BK26 -> 0 | BX21: =CAELS!BL26 -> 0 | BY21: =CAELS!BM26 -> 0 | BZ21: =CAELS!BN26 -> 0
A23: FUNDING MIX
A24: Total Deposits/Total Assets | B24: NPR | D24: =Financials!C6/Financials!C5 -> 0.55318281 | E24: =Financials!#REF!/Financials!#REF! -> #REF! | F24: =Financials!#REF!/Financials!#REF! -> #REF! | G24: =Financials!#REF!/Financials!#REF! -> #REF! | H24: =Financials!#REF!/Financials!#REF! -> #REF! | I24: =Financials!#REF!/Financials!#REF! -> #REF! | J24: =Financials!#REF!/Financials!#REF! -> #REF! | K24: =Financials!#REF!/Financials!#REF! -> #REF! | L24: =Financials!#REF!/Financials!#REF! -> #REF! | ... P24: =Financials!#REF!/Financials!#REF! -> #REF! | Q24: =Financials!D6/Financials!D5 -> 0.56945613 | R24: =Financials!E6/Financials!E5 -> 0.55576904 | S24: =Financials!F6/Financials!F5 -> 0.56205809 | T24: =Financials!G6/Financials!G5 -> 0.56852516 | U24: =Financials!H6/Financials!H5 -> 0.60415529 | V24: =Financials!I6/Financials!I5 -> 0.60143466 | W24: =Financials!J6/Financials!J5 -> 0.594174 | X24: =Financials!K6/Financials!K5 -> 0.58876731 | ... BQ24: =Financials!BD6/Financials!BD5 -> 0.54365149 | BR24: =Financials!#REF!/Financials!#REF! -> #REF! | BS24: =Financials!#REF!/Financials!#REF! -> #REF! | BT24: =Financials!#REF!/Financials!#REF! -> #REF! | BU24: =Financials!BE6/Financials!BE5 -> #DIV/0! | BV24: =Financials!BF6/Financials!BF5 -> #DIV/0! | BW24: =Financials!BG6/Financials!BG5 -> #DIV/0! | BX24: =Financials!BH6/Financials!BH5 -> #DIV/0! | BY24: =Financials!BI6/Financials!BI5 -> #DIV/0! | BZ24: =Financials!BJ6/Financials!BJ5 -> #DIV/0!
A25: BOSA Deposits/Total Assets | B25: NPR | D25: =Financials!C7/Financials!C5 -> 0.50400779 | E25: =Financials!#REF!/Financials!#REF! -> #REF! | F25: =Financials!#REF!/Financials!#REF! -> #REF! | G25: =Financials!#REF!/Financials!#REF! -> #REF! | H25: =Financials!#REF!/Financials!#REF! -> #REF! | I25: =Financials!#REF!/Financials!#REF! -> #REF! | J25: =Financials!#REF!/Financials!#REF! -> #REF! | K25: =Financials!#REF!/Financials!#REF! -> #REF! | L25: =Financials!#REF!/Financials!#REF! -> #REF! | ... P25: =Financials!#REF!/Financials!#REF! -> #REF! | Q25: =Financials!D7/Financials!D5 -> 0.51105541 | R25: =Financials!E7/Financials!E5 -> 0.49241384 | S25: =Financials!F7/Financials!F5 -> 0.49747272 | T25: =Financials!G7/Financials!G5 -> 0.49612313 | U25: =Financials!H7/Financials!H5 -> 0.5304274 | V25: =Financials!I7/Financials!I5 -> 0.53273404 | W25: =Financials!J7/Financials!J5 -> 0.52864811 | X25: =Financials!K7/Financials!K5 -> 0.52553383 | ... BQ25: =Financials!BD7/Financials!BD5 -> 0.46054013 | BR25: =Financials!#REF!/Financials!#REF! -> #REF! | BS25: =Financials!#REF!/Financials!#REF! -> #REF! | BT25: =Financials!#REF!/Financials!#REF! -> #REF! | BU25: =Financials!BE7/Financials!BE5 -> #DIV/0! | BV25: =Financials!BF7/Financials!BF5 -> #DIV/0! | BW25: =Financials!BG7/Financials!BG5 -> #DIV/0! | BX25: =Financials!BH7/Financials!BH5 -> #DIV/0! | BY25: =Financials!BI7/Financials!BI5 -> #DIV/0! | BZ25: =Financials!BJ7/Financials!BJ5 -> #DIV/0!
A26: FOSA Deposits/Total Assets | B26: NPR | D26: =Financials!C8/Financials!C5 -> 0.033568879 | E26: =Financials!#REF!/Financials!#REF! -> #REF! | F26: =Financials!#REF!/Financials!#REF! -> #REF! | G26: =Financials!#REF!/Financials!#REF! -> #REF! | H26: =Financials!#REF!/Financials!#REF! -> #REF! | I26: =Financials!#REF!/Financials!#REF! -> #REF! | J26: =Financials!#REF!/Financials!#REF! -> #REF! | K26: =Financials!#REF!/Financials!#REF! -> #REF! | L26: =Financials!#REF!/Financials!#REF! -> #REF! | ... P26: =Financials!#REF!/Financials!#REF! -> #REF! | Q26: =Financials!D8/Financials!D5 -> 0.041111499 | R26: =Financials!E8/Financials!E5 -> 0.046933797 | S26: =Financials!F8/Financials!F5 -> 0.048728752 | T26: =Financials!G8/Financials!G5 -> 0.054293598 | U26: =Financials!H8/Financials!H5 -> 0.053978631 | V26: =Financials!I8/Financials!I5 -> 0.049246582 | W26: =Financials!J8/Financials!J5 -> 0.046932832 | X26: =Financials!K8/Financials!K5 -> 0.044796852 | ... BQ26: =Financials!BD8/Financials!BD5 -> 0.070527034 | BR26: =Financials!#REF!/Financials!#REF! -> #REF! | BS26: =Financials!#REF!/Financials!#REF! -> #REF! | BT26: =Financials!#REF!/Financials!#REF! -> #REF! | BU26: =Financials!BE8/Financials!BE5 -> #DIV/0! | BV26: =Financials!BF8/Financials!BF5 -> #DIV/0! | BW26: =Financials!BG8/Financials!BG5 -> #DIV/0! | BX26: =Financials!BH8/Financials!BH5 -> #DIV/0! | BY26: =Financials!BI8/Financials!BI5 -> #DIV/0! | BZ26: =Financials!BJ8/Financials!BJ5 -> #DIV/0!
A27: External Borrowing/Total assets | B27: ≤ 25% | C27: 35.1 | D27: =Financials!C9/Financials!C5 -> 0.04626001 | E27: =Financials!#REF!/Financials!#REF! -> #REF! | F27: =Financials!#REF!/Financials!#REF! -> #REF! | G27: =Financials!#REF!/Financials!#REF! -> #REF! | H27: =Financials!#REF!/Financials!#REF! -> #REF! | I27: =Financials!#REF!/Financials!#REF! -> #REF! | J27: =Financials!#REF!/Financials!#REF! -> #REF! | K27: =Financials!#REF!/Financials!#REF! -> #REF! | L27: =Financials!#REF!/Financials!#REF! -> #REF! | ... P27: =Financials!#REF!/Financials!#REF! -> #REF! | Q27: =Financials!D9/Financials!D5 -> 0.031553666 | R27: =Financials!E9/Financials!E5 -> 0.029761006 | S27: =Financials!F9/Financials!F5 -> 0.022354849 | T27: =Financials!G9/Financials!G5 -> 0.010542621 | U27: =Financials!H9/Financials!H5 -> 0.010753626 | V27: =Financials!I9/Financials!I5 -> 0 | W27: =Financials!J9/Financials!J5 -> 0 | X27: =Financials!K9/Financials!K5 -> 0 | ... BQ27: =Financials!BD9/Financials!BD5 -> 0 | BR27: =Financials!#REF!/Financials!#REF! -> #REF! | BS27: =Financials!#REF!/Financials!#REF! -> #REF! | BT27: =Financials!#REF!/Financials!#REF! -> #REF! | BU27: =Financials!BE9/Financials!BE5 -> #DIV/0! | BV27: =Financials!BF9/Financials!BF5 -> #DIV/0! | BW27: =Financials!BG9/Financials!BG5 -> #DIV/0! | BX27: =Financials!BH9/Financials!BH5 -> #DIV/0! | BY27: =Financials!BI9/Financials!BI5 -> #DIV/0! | BZ27: =Financials!BJ9/Financials!BJ5 -> #DIV/0!
A29: GROWTH RATIOS
A30: Total Assets | B30: NPR | D30: =(SFP!#REF!-SFP!U27)/SFP!U27 -> #REF! | E30: =(SFP!#REF!-SFP!#REF!)/SFP!#REF! -> #REF! | F30: =(SFP!#REF!-SFP!#REF!)/SFP!#REF! -> #REF! | G30: =(SFP!#REF!-SFP!#REF!)/SFP!#REF! -> #REF! | H30: =(SFP!#REF!-SFP!#REF!)/SFP!#REF! -> #REF! | I30: =(SFP!#REF!-SFP!#REF!)/SFP!#REF! -> #REF! | J30: =(SFP!#REF!-SFP!#REF!)/SFP!#REF! -> #REF! | K30: =(SFP!#REF!-SFP!#REF!)/SFP!#REF! -> #REF! | L30: =(SFP!#REF!-SFP!#REF!)/SFP!#REF! -> #REF! | ... O30: =(SFP!#REF!-SFP!#REF!)/SFP!#REF! -> #REF! | P30: =(SFP!V34-SFP!#REF!)/SFP!#REF! -> #REF! | Q30: =(SFP!W34-SFP!V27)/SFP!V27 -> -1 | R30: =(SFP!X34-SFP!W27)/SFP!W27 -> -1 | S30: =(SFP!Y34-SFP!X27)/SFP!X27 -> -1 | T30: =(SFP!Z34-SFP!Y27)/SFP!Y27 -> -1 | U30: =(SFP!AA34-SFP!Z27)/SFP!Z27 -> -1 | V30: =(SFP!AB34-SFP!AA27)/SFP!AA27 -> -1 | W30: =(SFP!AC34-SFP!AB27)/SFP!AB27 -> -1 | X30: =(SFP!AD34-SFP!AC27)/SFP!AC27 -> -1 | ... BZ30: =(SFP!CF34-SFP!CE27)/SFP!CE27 -> #DIV/0!
A31: Total Deposits | B31: NPR | D31: =(SFP!#REF!-SFP!U32)/SFP!U32 -> #REF! | E31: =(SFP!#REF!-SFP!#REF!)/SFP!#REF! -> #REF! | F31: =(SFP!#REF!-SFP!#REF!)/SFP!#REF! -> #REF! | G31: =(SFP!#REF!-SFP!#REF!)/SFP!#REF! -> #REF! | H31: =(SFP!#REF!-SFP!#REF!)/SFP!#REF! -> #REF! | I31: =(SFP!#REF!-SFP!#REF!)/SFP!#REF! -> #REF! | J31: =(SFP!#REF!-SFP!#REF!)/SFP!#REF! -> #REF! | K31: =(SFP!#REF!-SFP!#REF!)/SFP!#REF! -> #REF! | L31: =(SFP!#REF!-SFP!#REF!)/SFP!#REF! -> #REF! | ... O31: =(SFP!#REF!-SFP!#REF!)/SFP!#REF! -> #REF! | P31: =(SFP!V44-SFP!#REF!)/SFP!#REF! -> #REF! | Q31: =(SFP!W44-SFP!V32)/SFP!V32 -> -0.71108536 | R31: =(SFP!X44-SFP!W32)/SFP!W32 -> -0.71731629 | S31: =(SFP!Y44-SFP!X32)/SFP!X32 -> -0.71775523 | T31: =(SFP!Z44-SFP!Y32)/SFP!Y32 -> -0.71968157 | U31: =(SFP!AA44-SFP!Z32)/SFP!Z32 -> -0.71197439 | V31: =(SFP!AB44-SFP!AA32)/SFP!AA32 -> -0.70073346 | W31: =(SFP!AC44-SFP!AB32)/SFP!AB32 -> -0.70261148 | X31: =(SFP!AD44-SFP!AC32)/SFP!AC32 -> -0.69249043 | ... BZ31: =(SFP!CF44-SFP!CE32)/SFP!CE32 -> #DIV/0!
A32: FOSA Deposits | B32: NPR | D32: =(SFP!#REF!-SFP!U29)/SFP!U29 -> #REF! | E32: =(SFP!#REF!-SFP!#REF!)/SFP!#REF! -> #REF! | F32: =(SFP!#REF!-SFP!#REF!)/SFP!#REF! -> #REF! | G32: =(SFP!#REF!-SFP!#REF!)/SFP!#REF! -> #REF! | H32: =(SFP!#REF!-SFP!#REF!)/SFP!#REF! -> #REF! | I32: =(SFP!#REF!-SFP!#REF!)/SFP!#REF! -> #REF! | J32: =(SFP!#REF!-SFP!#REF!)/SFP!#REF! -> #REF! | K32: =(SFP!#REF!-SFP!#REF!)/SFP!#REF! -> #REF! | L32: =(SFP!#REF!-SFP!#REF!)/SFP!#REF! -> #REF! | ... O32: =(SFP!#REF!-SFP!#REF!)/SFP!#REF! -> #REF! | P32: =(SFP!V39-SFP!#REF!)/SFP!#REF! -> #REF! | Q32: =(SFP!W39-SFP!V29)/SFP!V29 -> -0.25574366 | R32: =(SFP!X39-SFP!W29)/SFP!W29 -> -0.52378905 | S32: =(SFP!Y39-SFP!X29)/SFP!X29 -> -0.78147729 | T32: =(SFP!Z39-SFP!Y29)/SFP!Y29 -> -0.81284789 | U32: =(SFP!AA39-SFP!Z29)/SFP!Z29 -> -1 | V32: =(SFP!AB39-SFP!AA29)/SFP!AA29 -> -1 | W32: =(SFP!AC39-SFP!AB29)/SFP!AB29 -> -1 | X32: =(SFP!AD39-SFP!AC29)/SFP!AC29 -> -1 | ... BZ32: =(SFP!CF39-SFP!CE29)/SFP!CE29 -> #DIV/0!
A33: BOSA Deposits | B33: NPR | D33: =(SFP!#REF!-SFP!U31)/SFP!U31 -> #REF! | E33: =(SFP!#REF!-SFP!#REF!)/SFP!#REF! -> #REF! | F33: =(SFP!#REF!-SFP!#REF!)/SFP!#REF! -> #REF! | G33: =(SFP!#REF!-SFP!#REF!)/SFP!#REF! -> #REF! | H33: =(SFP!#REF!-SFP!#REF!)/SFP!#REF! -> #REF! | I33: =(SFP!#REF!-SFP!#REF!)/SFP!#REF! -> #REF! | J33: =(SFP!#REF!-SFP!#REF!)/SFP!#REF! -> #REF! | K33: =(SFP!#REF!-SFP!#REF!)/SFP!#REF! -> #REF! | L33: =(SFP!#REF!-SFP!#REF!)/SFP!#REF! -> #REF! | ... O33: =(SFP!#REF!-SFP!#REF!)/SFP!#REF! -> #REF! | P33: =(SFP!V42-SFP!#REF!)/SFP!#REF! -> #REF! | Q33: =(SFP!W42-SFP!V31)/SFP!V31 -> -0.8491687 | R33: =(SFP!X42-SFP!W31)/SFP!W31 -> -0.84688921 | S33: =(SFP!Y42-SFP!X31)/SFP!X31 -> -0.84688961 | T33: =(SFP!Z42-SFP!Y31)/SFP!Y31 -> -0.84518059 | U33: =(SFP!AA42-SFP!Z31)/SFP!Z31 -> -0.84567631 | V33: =(SFP!AB42-SFP!AA31)/SFP!AA31 -> -0.84548425 | W33: =(SFP!AC42-SFP!AB31)/SFP!AB31 -> -0.84640392 | X33: =(SFP!AD42-SFP!AC31)/SFP!AC31 -> -0.82944919 | ... BZ33: =(SFP!CF42-SFP!CE31)/SFP!CE31 -> #DIV/0!
A34: Net Loans & advances | B34: NPR | D34: =(SFP!#REF!-SFP!U14)/SFP!U14 -> #REF! | E34: =(SFP!#REF!-SFP!#REF!)/SFP!#REF! -> #REF! | F34: =(SFP!#REF!-SFP!#REF!)/SFP!#REF! -> #REF! | G34: =(SFP!#REF!-SFP!#REF!)/SFP!#REF! -> #REF! | H34: =(SFP!#REF!-SFP!#REF!)/SFP!#REF! -> #REF! | I34: =(SFP!#REF!-SFP!#REF!)/SFP!#REF! -> #REF! | J34: =(SFP!#REF!-SFP!#REF!)/SFP!#REF! -> #REF! | K34: =(SFP!#REF!-SFP!#REF!)/SFP!#REF! -> #REF! | L34: =(SFP!#REF!-SFP!#REF!)/SFP!#REF! -> #REF! | ... O34: =(SFP!#REF!-SFP!#REF!)/SFP!#REF! -> #REF! | P34: =(SFP!V17-SFP!#REF!)/SFP!#REF! -> #REF! | Q34: =(SFP!W17-SFP!V14)/SFP!V14 -> -1 | R34: =(SFP!X17-SFP!W14)/SFP!W14 -> -1 | S34: =(SFP!Y17-SFP!X14)/SFP!X14 -> -1 | T34: =(SFP!Z17-SFP!Y14)/SFP!Y14 -> -1 | U34: =(SFP!AA17-SFP!Z14)/SFP!Z14 -> -1 | V34: =(SFP!AB17-SFP!AA14)/SFP!AA14 -> -1 | W34: =(SFP!AC17-SFP!AB14)/SFP!AB14 -> -1 | X34: =(SFP!AD17-SFP!AC14)/SFP!AC14 -> -1 | ... BZ34: =(SFP!CF17-SFP!CE14)/SFP!CE14 -> #DIV/0!
A35: Core capital | B35: NPR
A36: Total Gross Income | B36: NPR
A37: Membership | B37: NPR
A39: Efficiency Ratios
A40: FinCost-Deposits/Average Deposits | B40: NPR | D40: =(SCI!T13/(SFP!U31+SFP!#REF!)/SFP!U27) -> #REF! | E40: =(SCI!#REF!/(SFP!#REF!+SFP!#REF!)/SFP!#REF!) -> #REF! | F40: =(SCI!#REF!/(SFP!#REF!+SFP!#REF!)/SFP!#REF!) -> #REF! | G40: =(SCI!#REF!/(SFP!#REF!+SFP!#REF!)/SFP!#REF!) -> #REF! | H40: =(SCI!#REF!/(SFP!#REF!+SFP!#REF!)/SFP!#REF!) -> #REF! | I40: =(SCI!#REF!/(SFP!#REF!+SFP!#REF!)/SFP!#REF!) -> #REF! | J40: =(SCI!#REF!/(SFP!#REF!+SFP!#REF!)/SFP!#REF!) -> #REF! | K40: =(SCI!#REF!/(SFP!#REF!+SFP!#REF!)/SFP!#REF!) -> #REF! | L40: =(SCI!#REF!/(SFP!#REF!+SFP!#REF!)/SFP!#REF!) -> #REF! | ... O40: =(SCI!#REF!/(SFP!#REF!+SFP!#REF!)/SFP!#REF!) -> #REF! | P40: =(SCI!#REF!/(SFP!#REF!+SFP!V42)/SFP!#REF!) -> #REF! | Q40: =(SCI!U13/(SFP!V31+SFP!W42)/SFP!V27) -> 1.2337811e-11 | R40: =(SCI!V13/(SFP!W31+SFP!X42)/SFP!W27) -> 1.1930934e-12 | S40: =(SCI!W13/(SFP!X31+SFP!Y42)/SFP!X27) -> 2.360724e-12 | T40: =(SCI!X13/(SFP!Y31+SFP!Z42)/SFP!Y27) -> 3.4901371e-12 | U40: =(SCI!Y13/(SFP!Z31+SFP!AA42)/SFP!Z27) -> 4.9302611e-12 | V40: =(SCI!Z13/(SFP!AA31+SFP!AB42)/SFP!AA27) -> 6.1477593e-12 | W40: =(SCI!AA13/(SFP!AB31+SFP!AC42)/SFP!AB27) -> 7.2376791e-12 | X40: =(SCI!AB13/(SFP!AC31+SFP!AD42)/SFP!AC27) -> 8.4691285e-12 | ... BZ40: =(SCI!CD13/(SFP!CE31+SFP!CF42)/SFP!CE27) -> #DIV/0!
A41: FinCost-Shares/Average Share capital | B41: NPR | D41: =(SCI!T15/(SFP!U42+SFP!#REF!)/SFP!U27) -> #REF! | E41: =(SCI!#REF!/(SFP!#REF!+SFP!#REF!)/SFP!#REF!) -> #REF! | F41: =(SCI!#REF!/(SFP!#REF!+SFP!#REF!)/SFP!#REF!) -> #REF! | G41: =(SCI!#REF!/(SFP!#REF!+SFP!#REF!)/SFP!#REF!) -> #REF! | H41: =(SCI!#REF!/(SFP!#REF!+SFP!#REF!)/SFP!#REF!) -> #REF! | I41: =(SCI!#REF!/(SFP!#REF!+SFP!#REF!)/SFP!#REF!) -> #REF! | J41: =(SCI!#REF!/(SFP!#REF!+SFP!#REF!)/SFP!#REF!) -> #REF! | K41: =(SCI!#REF!/(SFP!#REF!+SFP!#REF!)/SFP!#REF!) -> #REF! | L41: =(SCI!#REF!/(SFP!#REF!+SFP!#REF!)/SFP!#REF!) -> #REF! | ... O41: =(SCI!#REF!/(SFP!#REF!+SFP!#REF!)/SFP!#REF!) -> #REF! | P41: =(SCI!#REF!/(SFP!#REF!+SFP!V42)/SFP!#REF!) -> #REF! | Q41: =(SCI!U15/(SFP!V42+SFP!W42)/SFP!V27) -> 0 | R41: =(SCI!V15/(SFP!W42+SFP!X42)/SFP!W27) -> 4.8036195e-13 | S41: =(SCI!W15/(SFP!X42+SFP!Y42)/SFP!X27) -> 9.5904248e-13 | T41: =(SCI!X15/(SFP!Y42+SFP!Z42)/SFP!Y27) -> 1.4189044e-12 | U41: =(SCI!Y15/(SFP!Z42+SFP!AA42)/SFP!Z27) -> 2.000432e-12 | V41: =(SCI!Z15/(SFP!AA42+SFP!AB42)/SFP!AA27) -> 2.5013822e-12 | W41: =(SCI!AA15/(SFP!AB42+SFP!AC42)/SFP!AB27) -> 2.9521837e-12 | X41: =(SCI!AB15/(SFP!AC42+SFP!AD42)/SFP!AC27) -> 4.3884261e-12 | ... BZ41: =(SCI!CD15/(SFP!CE42+SFP!CF42)/SFP!CE27) -> #DIV/0!
A42: FinCost-Ext Loans/Average Ext Loans | B42: NPR | D42: =(SCI!T14/(SFP!U39+SFP!#REF!)/SFP!U27) -> #REF! | E42: =(SCI!#REF!/(SFP!#REF!+SFP!#REF!)/SFP!#REF!) -> #REF! | F42: =(SCI!#REF!/(SFP!#REF!+SFP!#REF!)/SFP!#REF!) -> #REF! | G42: =(SCI!#REF!/(SFP!#REF!+SFP!#REF!)/SFP!#REF!) -> #REF! | H42: =(SCI!#REF!/(SFP!#REF!+SFP!#REF!)/SFP!#REF!) -> #REF! | I42: =(SCI!#REF!/(SFP!#REF!+SFP!#REF!)/SFP!#REF!) -> #REF! | J42: =(SCI!#REF!/(SFP!#REF!+SFP!#REF!)/SFP!#REF!) -> #REF! | K42: =(SCI!#REF!/(SFP!#REF!+SFP!#REF!)/SFP!#REF!) -> #REF! | L42: =(SCI!#REF!/(SFP!#REF!+SFP!#REF!)/SFP!#REF!) -> #REF! | ... O42: =(SCI!#REF!/(SFP!#REF!+SFP!#REF!)/SFP!#REF!) -> #REF! | P42: =(SCI!#REF!/(SFP!#REF!+SFP!V53)/SFP!#REF!) -> #REF! | Q42: =(SCI!U14/(SFP!V39+SFP!W53)/SFP!V27) -> 1.5857023e-12 | R42: =(SCI!V14/(SFP!W39+SFP!X53)/SFP!W27) -> 1.0530188e-13 | S42: =(SCI!W14/(SFP!X39+SFP!Y53)/SFP!X27) -> 2.7793185e-13 | T42: =(SCI!X14/(SFP!Y39+SFP!Z53)/SFP!Y27) -> 3.5502046e-13 | U42: =(SCI!Y14/(SFP!Z39+SFP!AA53)/SFP!Z27) -> 3.693807e-13 | V42: =(SCI!Z14/(SFP!AA39+SFP!AB53)/SFP!AA27) -> 4.243301e-13 | W42: =(SCI!AA14/(SFP!AB39+SFP!AC53)/SFP!AB27) -> 4.1373121e-13 | X42: =(SCI!AB14/(SFP!AC39+SFP!AD53)/SFP!AC27) -> 3.928136e-13 | ... BZ42: =(SCI!CD14/(SFP!CE39+SFP!CF53)/SFP!CE27) -> #DIV/0!
A43: OpEx/Average Total Assets | B43: NPR | D43: =SCI!T23/SFP!U27 -> 0.030348048 | E43: =SCI!#REF!/SFP!#REF! -> #REF! | F43: =SCI!#REF!/SFP!#REF! -> #REF! | G43: =SCI!#REF!/SFP!#REF! -> #REF! | H43: =SCI!#REF!/SFP!#REF! -> #REF! | I43: =SCI!#REF!/SFP!#REF! -> #REF! | J43: =SCI!#REF!/SFP!#REF! -> #REF! | K43: =SCI!#REF!/SFP!#REF! -> #REF! | L43: =SCI!#REF!/SFP!#REF! -> #REF! | ... P43: =SCI!#REF!/SFP!#REF! -> #REF! | Q43: =SCI!U23/SFP!V27 -> 0.030639167 | R43: =SCI!V23/SFP!W27 -> 0.002241998 | S43: =SCI!W23/SFP!X27 -> 0.0041844389 | T43: =SCI!X23/SFP!Y27 -> 0.0077121165 | U43: =SCI!Y23/SFP!Z27 -> 0.011427631 | V43: =SCI!Z23/SFP!AA27 -> 0.013509039 | W43: =SCI!AA23/SFP!AB27 -> 0.015158694 | X43: =SCI!AB23/SFP!AC27 -> 0.017169133 | ... BZ43: =SCI!CD23/SFP!CE27 -> #DIV/0!
A44: Avge yield on Net loans | B44: NPR | D44: =SCI!T5/SFP!U15 -> 0.18567431 | E44: =SCI!#REF!/SFP!#REF! -> #REF! | F44: =SCI!#REF!/SFP!#REF! -> #REF! | G44: =SCI!#REF!/SFP!#REF! -> #REF! | H44: =SCI!#REF!/SFP!#REF! -> #REF! | I44: =SCI!#REF!/SFP!#REF! -> #REF! | J44: =SCI!#REF!/SFP!#REF! -> #REF! | K44: =SCI!#REF!/SFP!#REF! -> #REF! | L44: =SCI!#REF!/SFP!#REF! -> #REF! | ... P44: =SCI!#REF!/SFP!#REF! -> #REF! | Q44: =SCI!U5/SFP!V15 -> 0.17436304 | R44: =SCI!V5/SFP!W15 -> 0.016378488 | S44: =SCI!W5/SFP!X15 -> 0.031798339 | T44: =SCI!X5/SFP!Y15 -> 0.048096728 | U44: =SCI!Y5/SFP!Z15 -> 0.064106837 | V44: =SCI!Z5/SFP!AA15 -> 0.081139021 | W44: =SCI!AA5/SFP!AB15 -> 0.097367512 | X44: =SCI!AB5/SFP!AC15 -> 0.11322251 | ... BZ44: =SCI!CD5/SFP!CE15 -> #DIV/0!
A46: Liquidity Ratio
A47: Liquid Assets - ST Liabilities/ Deposits | B47: 0.15 | C47: 13.2 | D47: =CAELS!E17 -> 0.88648678 | E47: =CAELS!#REF! -> #REF! | F47: =CAELS!#REF! -> #REF! | G47: =CAELS!#REF! -> #REF! | H47: =CAELS!#REF! -> #REF! | I47: =CAELS!#REF! -> #REF! | J47: =CAELS!#REF! -> #REF! | K47: =CAELS!#REF! -> #REF! | L47: =CAELS!#REF! -> #REF! | ... P47: =CAELS!#REF! -> #REF! | Q47: =CAELS!F17 -> 0.68307476 | R47: =CAELS!G17 -> 0.67192156 | S47: =CAELS!H17 -> 0.73143732 | T47: =CAELS!I17 -> 0.77731846 | U47: =CAELS!J17 -> 0.93799763 | V47: =CAELS!K17 -> 1.0164604 | W47: =CAELS!L17 -> 1.1155928 | X47: =CAELS!M17 -> 1.1047511 | ... BQ47: =CAELS!BF17 -> 1.2621814 | BR47: =CAELS!#REF! -> #REF! | BS47: =CAELS!BG17 -> 0 | BT47: =CAELS!BH17 -> 0 | BU47: =CAELS!BI17 -> 0 | BV47: =CAELS!BJ17 -> 0 | BW47: =CAELS!BK17 -> 0 | BX47: =CAELS!BL17 -> 0 | BY47: =CAELS!BM17 -> 0 | BZ47: =CAELS!BN17 -> 0
A49: Loan Loss Provisions Ratios
A50: Actual LLP / Required LLP | B50: 1 | C50: 44.1

Sheet SFP
D2: AUDITED 2012 | E2: AUDITED 2013 | F2: AUDITED 2014 | G2: AUDITED 2015 | H2: AUDITED 2016 | I2: 42736 | J2: 42767 | K2: 42795 | L2: 42826 | M2: 42856 | N2: 42887 | O2: 42917 | P2: 42948 | Q2: 42979 | R2: 43009 | S2: 43040 | T2: 43070 | U2: Audited 2017 | V2: Audited 2018 | W2: 43466 | X2: 43497 | Y2: 43525 | Z2: 43556 | AA2: 43586 | AB2: 43617 | AC2: 43647 | AD2: 43678 | AE2: 43709 | AF2: 43739 | AG2: 43770 | AH2: 43800 | AI2: AUDITED 2019 | AJ2: 43831 | AK2: 43862 | AL2: 43891 | AM2: 43922 | AN2: 43952 | AO2: 43983 | AP2: 44013 | AQ2: 44044 | AR2: 44075 | AS2: 44105 | AT2: 44136 | AU2: 44166 | AV2: AUDITED 2020 | AW2: 44197 | AX2: 44228 | AY2: 44256 | AZ2: 44287 | BA2: 44317 | BB2: 44348 | BC2: 44378 | BD2: 44409 | BE2: 44440 | BF2: 44470 | BG2: 44501 | BH2: 44531 | BI2: Audited 2021 | BJ2: 44562 | BK2: 44593 | BL2: 44621 | BM2: 44652 | BN2: 44682 | BO2: 44713 | BP2: 44743 | BQ2: 44774 | BR2: 44805 | BS2: 44835 | BT2: 44866 | BU2: 44896 | BV2: Aud-22
C3: ASSETS
C4: Cash & Cash Equivalent | E4: =E5+E6 -> 251415764 | F4: =F5+F6 -> 506353666 | G4: =G5+G6 -> 600085716 | H4: =SUM(H5:H6) -> 430361711 | I4: =I5+I6 -> 772073007 | J4: =SUM(J5:J6) -> 466197322 | K4: =SUM(K5:K6) -> 578519252 | L4: =SUM(L5:L6) -> 196138306 | M4: 533884763 | N4: =N6+N5 -> 565458087 | O4: =O5+O6 -> 5.4041392e+08 | P4: =P5+P6 -> 415428324 | Q4: =SUM(Q5:Q6) -> 424784669 | R4: =SUM(R5:R6) -> 495349195 | S4: =SUM(S5:S6) -> 461384207 | T4: =SUM(T5:T6) -> 428362327 | U4: =SUM(U5:U6) -> 429143643 | V4: =SUM(V5:V6) -> 750100001 | W4: =SUM(W5:W6) -> 812532694 | X4: =SUM(X5:X6) -> 938755546 | ... BV4: =SUM(BV5:BV6) -> 1471320000
C5: Cash in hand(both local and foreign notes and coins) | E5: 2765634 | F5: 7781196 | G5: 3102499 | H5: 50485741 | I5: 14974358 | J5: 42270592 | K5: 54436519 | L5: 85926301 | M5: 66172685 | N5: 62028942 | O5: 45628746 | P5: 72937675 | Q5: 71374676 | R5: 56323585 | S5: 77565594 | T5: 38304025 | U5: 38303025 | V5: =31520634+3741159 -> 35261793 | W5: 28966692 | X5: 44967440 | Y5: 38665187 | Z5: 47637170 | AA5: 46519443 | AB5: 39798525 | AC5: 48354042 | AD5: 38988829 | AE5: 47667713 | AF5: 49725917 | AG5: 37814563 | AH5: 25694745 | AI5: 25694745 | AJ5: 42761631 | AK5: 35344059 | AL5: 49446758 | AM5: 43420976 | AN5: 44824873 | AO5: 35988248 | AQ5: 45346181 | AR5: 48287191 | AS5: 46905769 | AT5: 39556463 | AU5: 49273415 | AV5: 49274 | AW5: 46785060 | AX5: 52141939 | AY5: 44055092 | AZ5: 44642427 | BA5: 47182871 | BB5: 55143720 | BC5: 39856153 | BD5: 40651235 | BE5: 43480892 | BF5: 40192454 | BG5: 35985303 | BH5: 33483026 | BI5: =33483026+65322471 -> 98805497 | BJ5: 20294160 | BK5: 20147295 | BL5: 19889995 | BM5: 22750220 | BN5: 21340726 | BO5: 22295724 | BP5: 22295724 | BQ5: 50968531 | BR5: 42162678 | BS5: 38921880 | BT5: 41628848 | BU5: 20699919 | BV5: 20700000
C6: Cash at bank:(placement with financial institutions) | E6: 248650130 | F6: 498572470 | G6: 596983217 | H6: =430361711-H5 -> 379875970 | I6: 757098649 | J6: 423926730 | K6: 524082733 | L6: 110212005 | M6: 467712079 | N6: 503429145 | O6: 4.9478517e+08 | P6: 342490649 | Q6: 353409993 | R6: 439025610 | S6: 383818613 | T6: 390058302 | U6: =429143643-U5 -> 390840618 | V6: =750100001-V5 -> 714838208 | W6: 783566002 | X6: 893788106 | Y6: 1067171910 | Z6: 751763566 | AA6: 836834783 | AB6: 985078771 | AC6: 1017032577 | AD6: 1294976060 | AE6: 1311843513 | AF6: 1421534931 | AG6: 1407223559 | AH6: 1579008045 | AI6: =406166616+7178472+310142936+4072076+23703572+2500000 -> 753763672 | AJ6: 1688947896 | AK6: 1843236791 | AL6: 1689028512 | AM6: 1796436178 | AN6: 1765974008 | AO6: 2068494739 | AQ6: 1909035317 | AR6: 1926747314 | AS6: 1919425757 | AT6: 1949926930 | AU6: 2032837294 | AV6: =135082+46970+81862+4412+14115+1120269+425039+205242 -> 2032991 | AW6: 2001436167 | AX6: 1986315125 | AY6: 1766582888 | AZ6: 1788421374 | BA6: 1753244822 | BB6: 2001615219 | BC6: 2206797067 | BD6: 2043786436 | BE6: 2159648848 | BF6: 2082909932 | BG6: 2229022152 | BH6: 2311231478 | BI6: =30413280+1928068+13924449+2199643210+434842750 -> 2680751757 | BJ6: 2475151403 | BK6: 2269561674 | BL6: 2123864861 | BM6: 1955716253 | BN6: 1737471984 | BO6: 2094162164 | BP6: 1996948053 | BQ6: 1860167074 | BR6: 1802275457 | BS6: 1514663447 | BT6: 1485178171 | BU6: 1450619039 | BV6: =1367086000+34225000+49309000 -> 1450620000
C7: Prepayments & Sundry Receivables | E7: 253037438 | F7: 306215412 | G7: 348678521 | H7: =226108867+1054131 -> 227162998 | I7: 468632472 | J7: 263096680 | K7: 348607111 | L7: 374355514 | M7: 177269961 | N7: 179664680 | O7: 2.3564966e+08 | P7: 342250228 | Q7: 359226784 | R7: 367007522 | S7: 242482867 | T7: 334583598 | U7: 311194383 | V7: 305537203 | W7: 487967383 | X7: 406711231 | Y7: 410958550 | Z7: 375316592 | AA7: 368164846 | AB7: 375522811 | AC7: 427808018 | AD7: 316986787 | AE7: 4.8704232e+08 | AF7: 469026330 | AG7: 308987338 | AH7: 370173406 | AI7: =266548041+8730000+6837833+43337116+5368939 -> 330821929 | AJ7: 420690700 | AK7: 382257709 | AL7: 432462411 | AM7: 490337504 | AN7: 416270372 | AO7: 275351487 | AQ7: 444754612 | AR7: 461762438 | AS7: 455966861 | AT7: 486506590 | AU7: 430802380 | AV7: =326279+43214+5630+17203 -> 392326 | AW7: 478143449 | AX7: 377902069 | AY7: 376935366 | AZ7: 335758408 | BA7: 329973434 | BB7: 235265395 | BC7: 186233907 | BD7: 257923357 | BE7: 166952207 | BF7: 252222550 | BG7: 325830656 | BH7: 438992436 | BI7: 4.1744086e+08 | BJ7: 369180938 | BK7: 347615402 | BL7: 368931913 | BM7: 305793411 | BN7: 273376407 | BO7: -29976490 | BP7: 218744957 | BQ7: 235582649 | BR7: 213622955 | BS7: 231962583 | BT7: 252245426 | BU7: 349295372 | BV7: 345509000
C8: Financial Investments | E8: =SUM(E9:E13) -> 78543113 | F8: =SUM(F9:F13) -> 89261478 | G8: =SUM(G9:G13) -> 89848180 | H8: =SUM(H9:H13) -> 383823525 | I8: =SUM(I9:I13) -> 98672164 | J8: =J11+J13 -> 384705526 | K8: =K11+K13 -> 385146526 | L8: =L11+L13 -> 385587526 | M8: =SUM(M9:M13) -> 346028526 | N8: =SUM(N9:N13) -> 386488576 | O8: =SUM(O9:O13) -> 386932751 | P8: =SUM(P9:P13) -> 387376926 | Q8: =SUM(Q9:Q13) -> 387821101 | R8: =SUM(R9:R13) -> 388265276 | S8: 388709451 | T8: =SUM(T9:T13) -> 389153626 | U8: =SUM(U9:U13) -> 438411690 | V8: =SUM(V9:V13) -> 480969216 | W8: =SUM(W9:W13) -> 504037257 | X8: =SUM(X9:X13) -> 478357566 | Y8: =SUM(Y9:Y13) -> 478801741 | Z8: =SUM(Z9:Z13) -> 479245916 | AA8: =SUM(AA9:AA13) -> 483490091 | ... BV8: =SUM(BV9:BV13) -> 1541829000
C9: Government Securities - Treasury Bills/bonds, | F9: 0 | G9: 0 | I9: 0 | O9: 0 | Q9: 0 | R9: 0 | T9: 0 | AJ9: 0 | AK9: 0 | AW9: 0 | AX9: 0 | AY9: 0 | AZ9: 0 | BA9: 0 | BB9: 0 | BC9: 0 | BD9: 0 | BE9: 0 | BF9: 0 | BG9: 0 | BH9: 0 | BI9: 0 | BJ9: 0 | BK9: 0 | BL9: 0 | BM9: 0 | BN9: 0 | BO9: 0 | BP9: 0 | BQ9: 0 | BR9: 0 | BS9: 0 | BT9: 0 | BU9: 0 | BV9: 0
C10: Other Securities - Commercial papers/Bonds | F10: 0 | G10: 0 | I10: 0 | O10: 0 | Q10: 0 | R10: 0 | T10: 0 | AJ10: 0 | AK10: 0 | AW10: 0 | AX10: 0 | AY10: 0 | AZ10: 0 | BA10: 0 | BB10: 0 | BC10: 0 | BD10: 0 | BE10: 0 | BF10: 0 | BG10: 0 | BH10: 0 | BI10: 0 | BJ10: 0 | BK10: 0 | BL10: 0 | BM10: 0 | BN10: 0 | BO10: 0 | BP10: 0 | BQ10: 0 | BR10: 0 | BS10: 0 | BT10: 0 | BU10: 0 | BV10: 0
C11: Balances in NACCOS (E.g Jungu Kuu, ESS, Savings,Money Market,Coop FD, CFP) | E11: 28483894 | F11: 29202259 | G11: 29788961 | H11: 57238712 | I11: 33608047 | J11: 58120712 | K11: 58561712 | L11: 59002712 | M11: 9443712 | N11: 39903762 | O11: 40347937 | P11: 40792112 | Q11: 41236287 | R11: 41680462 | S11: 42124637 | T11: 42568812 | U11: =42813758+395597932 -> 438411690 | W11: 48439325 | X11: 48883500 | Y11: 49327675 | Z11: 49771850 | AA11: 54016025 | AB11: 54460200 | AC11: 54904375 | AD11: 105348550 | AE11: 105792725 | AF11: 106236900 | AG11: 106681075 | AH11: 107125250 | AI11: =548449536+103607021+210000000+107287208+2665050 -> 972008815 | AJ11: 110396433 | AK11: 110840608 | AL11: 111284783 | AM11: 111728958 | AN11: 212173133 | AO11: 212617308 | AQ11: 316672325 | AR11: 317116500 | AS11: 317560675 | AT11: 318004850 | AU11: 272221775 | AV11: =264227+7994 -> 272221 | AW11: 261605992 | AX11: 262050167 | AY11: 262494342 | AZ11: 312938517 | BA11: 313382692 | BB11: 313826867 | BC11: 414271042 | BD11: 433066050 | BE11: 433510225 | BF11: 433954400 | BG11: 434398575 | BH11: 434842750 | BI11: 0 | BJ11: 444256725 | BK11: 433596525 | BL11: 434040700 | BM11: 484040700 | BN11: 704769713 | BO11: 705213888 | BP11: 705658063 | BQ11: 706102238 | BR11: 706546412 | BS11: 906990587 | BT11: 915399500 | BU11: 916287850 | BV11: 916288000
C12: Equity Investments in NACCOs(Shares in- CIC, KUSCCO, COOP BANK,CAK, KERUSSU) | AI12: =13970107+213366733+292859084+29342443 -> 549538367 | AJ12: 549538366 | AK12: 549538366 | AL12: 559538366 | AM12: 559538366 | AN12: 559538366 | AO12: 559538366 | AQ12: 603074365 | AR12: 603074365 | AS12: 603074365 | AT12: 603074365 | AU12: 603074365 | AV12: =10433+506433 -> 516866 | AW12: 496509279 | AX12: 496509279 | AY12: 496509279 | AZ12: 4.9650928e+08 | BA12: 516866176 | BB12: 526866176 | BC12: 566364976 | BD12: 566364976 | BE12: 566364976 | BF12: 566364976 | BG12: 576364976 | BH12: 577206451 | BI12: =10875463+566330988 -> 577206451 | BJ12: 577206451 | BK12: 626321450 | BL12: 626321450 | BM12: 636321450 | BN12: 636321450 | BO12: 636321450 | BP12: 636321450 | BQ12: 646321450 | BR12: 646321450 | BS12: 646321450 | BT12: 646321450 | BU12: 646321450 | BV12: =614666000+10875000 -> 625541000
C13: Equity Investments in companies - shares/stocks | E13: 50059219 | F13: 60059219 | G13: 60059219 | H13: 326584813 | I13: 65064117 | J13: 326584814 | K13: 326584814 | L13: 326584814 | M13: 336584814 | N13: 346584814 | O13: 346584814 | P13: 346584814 | Q13: 346584814 | R13: 346584814 | S13: 346584814 | T13: 346584814 | V13: =47995150+3500000+429474066 -> 480969216 | W13: 455597932 | X13: 429474066 | Y13: 429474066 | Z13: 429474066 | AA13: 429474066 | AB13: 467474067 | AC13: 472644066 | AD13: 472644066 | AE13: 472644066 | AF13: 510385066 | AG13: 520385066 | AH13: 520385066 | AW13: 0 | AX13: 0 | AY13: 0 | AZ13: 0 | BA13: 0 | BB13: 0 | BC13: 0 | BD13: 0 | BE13: 0 | BF13: 0 | BG13: 0 | BH13: 0 | BI13: 0 | BL13: 0 | BM13: 0 | BN13: 0 | BO13: 0 | BP13: 0 | BQ13: 0 | BR13: 0
C14: Net Loan Portfolio | E14: =E15-E16 -> 4321931459 | F14: =F15-F16 -> 5568210509 | G14: =G15-G16 -> 7255037324 | H14: =H15-H16 -> 5883235568 | I14: =I15-I16 -> 9627426227 | J14: =J15-J16 -> 6053436393 | K14: =K15-K16 -> 5901058721 | L14: =L15-L16 -> 5912832534 | M14: 5853540115 | N14: =N15-N16 -> 5976850461 | O14: =O15-O16 -> 5.9433478e+09 | P14: =P15-P16 -> 6081908086 | Q14: =Q15-Q16 -> 6185567700 | R14: =R15-R16 -> 6252187024 | S14: =S15-S16 -> 6439596490 | T14: =T15-T16 -> 6409998565 | U14: =U15-U16 -> 6527159792 | ... BV14: =BV15-BV16 -> 9122098000
C15: Gross Loan Portfolio | E15: 4409358584 | F15: =4409358584+3740894610+789564218-3243537236 -> 5696280176 | G15: 7401435447 | H15: 6019992881 | I15: 9899194653 | J15: 6250165112 | K15: 6103005896 | L15: 6082146799 | M15: 6033714016 | N15: 6171941850 | O15: 6.1103761e+09 | P15: 6259303284 | Q15: 6383829356 | R15: 6448277504 | S15: 6645432127 | T15: 6677544533 | U15: 6677545533 | V15: 7151001513 | W15: 7136929610 | X15: 7117337321 | Y15: 7040574075 | Z15: 6884438456 | AA15: 6803657149 | AB15: 6770964087 | AC15: 6762353379 | AD15: 6809455710 | AE15: 6760058286 | AF15: 6783625125 | AG15: 6803155329 | AH15: 6805841374 | AI15: 6805841374 | AJ15: 6848465939 | AK15: 6821066296 | AL15: 6704742205 | AM15: 6655440429 | AN15: 6616637952 | AO15: 6603562072 | AQ15: 6732689976 | AR15: 6867846697 | AS15: 7003597287 | AT15: 7120495675 | AU15: 7229275042 | AV15: =6805841+5783969-5315744 -> 7274066 | AW15: 7297723771 | AX15: 7.1606588e+09 | AY15: 7229581575 | AZ15: 7308003887 | BA15: 7368192747 | BB15: 7446866860 | BC15: 7540941445 | BD15: 7588117975 | BE15: 7675939066 | BF15: 7814271733 | BG15: 7.8348211e+09 | BH15: 7941611446 | BI15: 7.9416114e+09 | BJ15: 7972031193 | BK15: 7867778659 | BL15: 8051864876 | BM15: 8195838726 | BN15: 8286754921 | BO15: 8370380038 | BP15: 8438093132 | BQ15: 8585165858 | BR15: 8825044494 | BS15: 9034235212 | BT15: 9259219948 | BU15: 9515328520 | BV15: 9515329000
C16: Allowance for Loan Loss | E16: 87427125 | F16: 128069667 | G16: 146398123 | H16: 136757313 | I16: 271768426 | J16: 196728719 | K16: 201947175 | L16: 169314265 | M16: 180173901 | N16: 195091389 | O16: 1.6702826e+08 | P16: 177395198 | Q16: 198261656 | R16: 196090480 | S16: 205835637 | T16: 267545968 | U16: 150385741 | V16: 415410438 | W16: 413551308 | X16: 415410438 | Y16: 415410438 | Z16: 415410438 | AA16: 415410438 | AB16: 415410438 | AC16: 415410438 | AD16: 415410438 | AE16: 4.4607551e+08 | AF16: 441935994 | AG16: 4.5049452e+08 | AH16: 465108277 | AI16: 437475353 | AJ16: 459450633 | AK16: 456220055 | AL16: 444500457 | AM16: 4.7734908e+08 | AN16: 4.7495686e+08 | AO16: 505174440 | AQ16: 510392621 | AR16: 611403552 | AS16: 538952020 | AT16: 495826123 | AU16: 497196092 | AV16: 541988 | AW16: 563891972 | AX16: 4.8839229e+08 | AY16: 481781220 | AZ16: 5.0692427e+08 | BA16: 468986921 | BB16: 463979943 | BC16: 454151055 | BD16: 452556998 | BE16: 443669891 | BF16: 470692764 | BG16: 4.9142202e+08 | BH16: 502784098 | BI16: 4.9463471e+08 | BJ16: 493329672 | BK16: 410628096 | BL16: 458321657 | BM16: 424714642 | BN16: 440742677 | BO16: 430451945 | BP16: 419962968 | BQ16: 458679291 | BR16: 437407406 | BS16: 435843947 | BT16: 436956219 | BU16: 473127093 | BV16: 393231000
C17: Accounts Receivables | E17: =SUM(E18:E20) -> 0 | F17: =SUM(F18:F20) -> 0 | G17: =SUM(G18:G20) -> 0 | H17: =SUM(H18:H20) -> 0 | I17: =SUM(I18:I20) -> 0 | J17: =SUM(J18:J20) -> 0 | K17: =SUM(K18:K20) -> 0 | L17: =SUM(L18:L20) -> 0 | ... O17: =SUM(O18:O20) -> 0 | P17: 0 | Q17: =SUM(Q18:Q20) -> 0 | R17: =SUM(R18:R20) -> 0 | S17: =SUM(S18:S20) -> 0 | T17: =SUM(T18:T20) -> 0 | U17: =SUM(U18:U20) -> 0 | V17: =SUM(V18:V20) -> 9971113 | W17: =SUM(W18:W20) -> 0 | X17: =SUM(X18:X20) -> 0 | ... BR17: =SUM(BR18:BR20) -> 0 | BS17: 0 | BT17: 0 | BU17: 0 | BV17: 0
C18: Tax Recoverable | R18: 0 | T18: 0 | U18: 0 | V18: 9971113 | AI18: 16055744 | AV18: 14457 | AW18: 0 | AX18: 0 | AY18: 0 | AZ18: 0 | BA18: 0 | BB18: 0 | BC18: 0 | BD18: 0 | BE18: 0 | BF18: 0 | BG18: 0 | BH18: 0 | BI18: 0 | BJ18: 0 | BK18: 0 | BL18: 0 | BM18: 0 | BN18: 0 | BO18: 0 | BP18: 0 | BQ18: 0 | BR18: 0 | BS18: 0 | BT18: 0 | BU18: 0 | BV18: 0
C19: Deferred Tax Assets | R19: 0 | T19: 0 | U19: 0 | AW19: 0 | AX19: 0 | AY19: 0 | AZ19: 0 | BA19: 0 | BB19: 0 | BC19: 0 | BD19: 0 | BE19: 0 | BF19: 0 | BG19: 0 | BH19: 0 | BI19: 0 | BJ19: 0 | BK19: 0 | BL19: 0 | BM19: 0 | BN19: 0 | BO19: 0 | BP19: 0 | BQ19: 0 | BR19: 0 | BS19: 0 | BT19: 0 | BU19: 0 | BV19: 0
C20: Retirement Benefit Assets | R20: 0 | T20: 0 | U20: 0 | AW20: 0 | AX20: 0 | AY20: 0 | AZ20: 0 | BA20: 0 | BB20: 0 | BC20: 0 | BD20: 0 | BE20: 0 | BF20: 0 | BG20: 0 | BH20: 0 | BI20: 0 | BJ20: 0 | BK20: 0 | BL20: 0 | BM20: 0 | BN20: 0 | BO20: 0 | BP20: 0 | BQ20: 0 | BR20: 0 | BS20: 0 | BT20: 0 | BU20: 0 | BV20: 0
C21: Property & Equipment & Other assets | E21: =SUM(E22:E26) -> 153841662 | F21: =SUM(F22:F26) -> 236400962 | G21: =SUM(G22:G26) -> 256977836 | H21: =SUM(H22:H26) -> 408164396 | I21: =SUM(I22:I26) -> 260367284 | J21: =SUM(J22:J26) -> 406285097 | K21: =SUM(K22:K26) -> 405345449 | L21: =SUM(L22:L26) -> 405089487 | M21: =SUM(M22:M26) -> 404134301 | N21: =N22+N23+N24+N25+N26 -> 403196176 | O21: =SUM(O22:O26) -> 4.0224058e+08 | P21: =SUM(P22:P26) -> 401284989 | Q21: =SUM(Q22:Q26) -> 400329394 | R21: =SUM(R22:R26) -> 399475781 | S21: =SUM(S22:S26) -> 399263128 | T21: =SUM(T22:T26) -> 399672198 | U21: =SUM(U22:U26) -> 400444107 | V21: =SUM(V22:V26) -> 433142110 | ... BV21: =SUM(BV22:BV26) -> 477268000
C22: Investment Properties | H22: 346125000 | J22: 346125000 | K22: 346125000 | L22: 346125000 | M22: 346125000 | N22: 346125000 | O22: 3.46125e+08 | P22: 346125000 | Q22: 346125000 | R22: 346125000 | S22: 346125000 | T22: 346125000 | U22: =346125000 -> 346125000 | V22: 385000000 | W22: 385000000 | X22: 385000000 | Y22: 385000000 | Z22: 385000000 | AA22: 385000000 | AB22: 385000000 | AC22: 385000000 | AD22: 385000000 | AE22: 385000000 | AF22: 385000000 | AG22: 385000000 | AH22: 385000000 | AI22: 400000000 | AJ22: 400000000 | AK22: 400000000 | AL22: 400000000 | AM22: 400000000 | AN22: 400000000 | AO22: 400000000 | AQ22: 400000000 | AR22: 400000000 | AS22: 400000000 | AT22: 400000000 | AU22: 403497059 | AV22: 304000 | AW22: 304000000 | AX22: 304000000 | AY22: 304000000 | AZ22: 304000000 | BA22: 304000000 | BB22: 304000000 | BC22: 304000000 | BD22: 304000000 | BE22: 304000000 | BF22: 304000000 | BG22: 304000000 | BH22: 305775000 | BI22: 305775000 | BJ22: 305775000 | BK22: 305775000 | BL22: 305775000 | BM22: 305775000 | BN22: 305775000 | BO22: 307800000 | BP22: 307800000 | BQ22: 307800000 | BR22: 307800000 | BS22: 307800000 | BT22: 307800000 | BU22: 307800000 | BV22: 307800000
C23: Property & Equipment | E23: 63627455 | F23: =106212110+109354009 -> 215566119 | G23: 232116211 | H23: 40338451 | I23: 235641326 | J23: 39211214 | K23: 38647596 | L23: 38767665 | M23: 38188509 | N23: 37626414 | O23: 37046851 | P23: 36467288 | Q23: 35887725 | R23: 35410142 | S23: 35573519 | T23: 36358621 | U23: 36326430 | V23: 32449324 | W23: 31896736 | X23: 32507453 | Y23: 32000246 | Z23: 31493038 | AA23: 32562424 | AB23: 32085699 | AC23: 31615018 | AD23: 31123306 | AE23: 30818436 | AF23: 30263500 | AG23: 30280027 | AH23: 29907812 | AI23: =34491857 -> 34491857 | AJ23: 28837877 | AK23: 28406139 | AL23: 30055457 | AM23: 29733651 | AN23: 29222411 | AO23: 28783987 | AQ23: 29045904 | AR23: 28500732 | AS23: 27955561 | AT23: 41657993 | AU23: 41150633 | AV23: 137151 | AW23: 136607232 | AX23: 131696263 | AY23: 135520431 | AZ23: 134977030 | BA23: 136348677 | BB23: 135813414 | BC23: 135224223 | BD23: 134635032 | BE23: 134045841 | BF23: 133739668 | BG23: 133904344 | BH23: 136937775 | BI23: 1.3693777e+08 | BJ23: 136410265 | BK23: 135882755 | BL23: 135355245 | BM23: 134827735 | BN23: 134300226 | BO23: 131747716 | BP23: 131220206 | BQ23: 130692696 | BR23: 131587359 | BS23: 131023383 | BT23: 133599380 | BU23: 133616256 | BV23: 133616000
C24: Prepaid Lease rentals | E24: 5542003 | F24: 2288053 | G24: 2711423 | H24: 486718 | I24: 3412875 | J24: 485388 | K24: 484723 | L24: 484058 | M24: 483393 | N24: 482729 | O24: 482063.58 | P24: 481399 | Q24: 480734 | R24: 480069 | S24: 479404 | T24: 478739 | U24: 478739 | W24: 0 | X24: 0 | Y24: 0 | Z24: 0 | AA24: 0 | AB24: 0 | AC24: 0 | AD24: 0 | AE24: 0 | AF24: 0 | AI24: 17394635 | AJ24: 0 | AK24: 0 | AL24: 0 | AM24: 0 | AN24: 0 | AO24: 0 | AQ24: 0 | AR24: 0 | AS24: 0 | AT24: 0 | AU24: 0 | AV24: 15398 | AW24: 0 | AX24: 0 | AY24: 0 | AZ24: 0 | BA24: 0 | BB24: 0 | BC24: 0 | BD24: 0 | BE24: 0 | BF24: 0 | BG24: 0 | BH24: 0 | BI24: 13402191 | BJ24: 0 | BK24: 0 | BL24: 0 | BM24: 0 | BN24: 0 | BO24: 0 | BP24: 0 | BQ24: 0 | BR24: 0 | BS24: 0 | BT24: 0 | BU24: 0 | BV24: 11406000
C25: Intangible Assets | E25: 83286564 | F25: 16165334 | G25: 20214575 | H25: 18017553 | I25: 17825974 | J25: 17266821 | K25: 16891456 | L25: 16516090 | M25: 16140725 | N25: 15765359 | O25: 15389993 | P25: 15014628 | Q25: 14639262 | R25: 14263896 | S25: 13888530 | T25: 13513165 | U25: 13270064 | V25: 11257548 | W25: 11023016 | X25: 10788484 | Y25: 10553951 | Z25: 10319419 | AA25: 12295766 | AB25: 12009818 | AC25: 13210120 | AD25: 12887922 | AE25: 12565724 | AF25: 12243526 | AG25: 11921328 | AH25: 11599130 | AI25: 11599129 | AJ25: 11357481 | AK25: 11115833 | AL25: 10874184 | AM25: 10632536 | AN25: 10390887 | AO25: 10149239 | AQ25: 10080065 | AR25: 10309713 | AS25: 10045362 | AT25: 9516657 | AU25: 9432563 | AV25: 9433 | AW25: 9236051 | AX25: 9039540 | AY25: 8843029 | AZ25: 8646516 | BA25: 11024036 | BB25: 13947313 | BC25: 13615233 | BD25: 13283156 | BE25: 12951077 | BF25: 12951077 | BG25: 11744148 | BH25: 11396632 | BI25: 11396631 | BJ25: 11159201 | BK25: 10921771 | BL25: 10684342 | BM25: 10446911 | BN25: 10209482 | BO25: 9972050 | BP25: 9734621 | BQ25: 9497191 | BR25: 9884029 | BS25: 9630593 | BT25: 13027786 | BU25: 13027786 | BV25: 13028000
C26: Other Assets | E26: 1385640 | F26: 2381456 | G26: 1935627 | H26: 3196674 | I26: 3487109 | J26: 3196674 | K26: 3196674 | L26: 3196674 | M26: 3196674 | N26: 3196674 | O26: 3196674 | P26: 3196674 | Q26: 3196673 | R26: 3196674 | S26: 3196675 | T26: 3196673 | U26: =4243874 -> 4243874 | V26: =4435238 -> 4435238 | W26: 4435238 | X26: 4435238 | Y26: 0 | Z26: 0 | AA26: 0 | AB26: 0 | AC26: 0 | AD26: 0 | AE26: 0 | AF26: 0 | AI26: 5097677 | AJ26: 5097677 | AK26: 5097677 | AL26: 0 | AM26: 0 | AN26: 0 | AO26: 0 | AQ26: 0 | AR26: 0 | AS26: 0 | AT26: 0 | AU26: 1935497 | AV26: =1935 -> 1935 | AW26: 1935497 | AX26: 1935497 | AY26: 1935497 | AZ26: 0 | BA26: 0 | BB26: 0 | BC26: 0 | BD26: 0 | BE26: 0 | BF26: 0 | BG26: 0 | BH26: 1966211 | BI26: 1966211 | BJ26: 0 | BK26: 0 | BL26: 0 | BM26: 0 | BN26: 0 | BO26: 0 | BP26: 0 | BQ26: 0 | BR26: 0 | BS26: 0 | BT26: 0 | BU26: 2318602 | BV26: =2319000+9099000 -> 11418000
C27: Total Assets | E27: =E21+E17+E14+E8+E7+E4 -> 5058769436 | F27: =F21+F17+F14+F8+F7+F4 -> 6706442027 | G27: =G21+G17+G14+G8+G7+G4 -> 8550627577 | H27: =SUM(H4,H7,H8,H14,H17,H21) -> 7332748198 | I27: =I21+I17+I14+I8+I7+I4 -> 11227171154 | J27: =SUM(J4,J7,J8,J14,J17,J21) -> 7573721018 | K27: =SUM(K4,K7,K8,K14,K17,K21) -> 7618677059 | L27: =SUM(L4,L7,L8,L14,L17,L21) -> 7274003367 | M27: =SUM(M4,M7,M8,M14,M17,M21) -> 7314857666 | N27: =N4+N7+N8+N14+N21 -> 7511657980 | O27: =O21+O17+O14+O8+O7+O4 -> 7.5085847e+09 | P27: =P4+P7+P8+P14+P17+P21 -> 7628248553 | Q27: =Q4+Q7+Q8+Q14+Q17+Q21 -> 7757729648 | R27: =SUM(R4,R7,R8,R14,R17,R21) -> 7902284798 | S27: =SUM(S4,S7,S8,S14,S17,S21) -> 7931436143 | T27: =SUM(T4,T7,T8,T14,T17,T21) -> 7961770314 | U27: =SUM(U4,U7,U8,U14,U17,U21) -> 8106353615 | V27: =SUM(V4,V7,V8,V14,V17,V21) -> 8715310718 | W27: =SUM(W4,W7,W8,W14,W17,W21) -> 8960270626 | X27: =SUM(X4,X7,X8,X14,X17,X21) -> 8958482401 | Y27: =SUM(Y4,Y7,Y8,Y14,Y17,Y21) -> 9048315222 | ... BV27: =SUM(BV4,BV7,BV8,BV14,BV17,BV21) -> 12958024000
C28: LIABILITIES
C29: Savings Deposits - Withdrawable deposits - FOSA) | E29: 365046466 | F29: 375412943 | G29: 512838792 | H29: 293114101 | I29: 669647217 | J29: 404514804 | K29: 409826694 | L29: 334421800 | M29: 311000555 | N29: 369832814 | O29: 2.6859204e+08 | P29: 256936418 | Q29: 297935795 | R29: 294469689 | S29: 305373640 | T29: 256126960 | U29: 272121207 | V29: 358299491 | W29: 420539519 | X29: 436535669 | Y29: 491265589 | Z29: 461506696 | AA29: 421211633 | AB29: 408643393 | AC29: 394100806 | AD29: 549096046 | AE29: 605230464 | AF29: 606930650 | AG29: 373155183 | AH29: 479423926 | AI29: 479423926 | AJ29: 581806290 | AK29: 543775832 | AL29: 865829357 | AM29: 794599641 | AN29: 624454504 | AO29: 634894039 | AQ29: 711768547 | AR29: 760488230 | AS29: 736244281 | AT29: 739120872 | AU29: 788925324 | AV29: 788925 | AW29: 690233341 | AX29: 1122776019 | AY29: 820457445 | AZ29: 766083550 | BA29: 701979787 | BB29: 764644248 | BC29: 979433173 | BD29: 888376284 | BE29: 853007493 | BF29: 810987981 | BG29: 843035567 | BH29: 839236589 | BI29: 839236589 | BJ29: 843041059 | BK29: 1257139856 | BL29: 1112122326 | BM29: 983861183 | BN29: 915067611 | BO29: 898385198 | BP29: 954382871 | BQ29: 915322466 | BR29: 889638483 | BS29: 853181762 | BT29: 922876820 | BU29: 913891059 | BV29: 913891000
C30: Short Term Deposits (e.g Fixed deposits, special savings) | E30: 528880389 | F30: 467492944 | G30: 540527915 | H30: 69413927 | I30: 687345997 | J30: 130253527 | K30: 136549627 | L30: 130647627 | M30: 79691885 | N30: 139285327 | O30: 82051427 | P30: 132544530 | Q30: 134633730 | R30: 137820391 | S30: 132814422 | T30: 129056692 | U30: 126508892 | V30: 150680952 | W30: 147140235 | X30: 142051270 | Y30: 163850752 | Z30: 168852239 | AA30: 166392535 | AB30: 161889499 | AC30: 162196433 | AD30: 158135752 | AE30: 152309530 | AF30: 151303503 | AG30: 137331903 | AH30: 131354346 | AI30: 131354346 | AJ30: 126854212 | AK30: 130608003 | AL30: 133224222 | AM30: 137070606 | AN30: 136224053 | AO30: 145903588 | AQ30: 150971372 | AR30: 153244885 | AS30: 157613336 | AT30: 161293696 | AU30: 146735889 | AV30: 146737 | AW30: 138889418 | AX30: 146279312 | AY30: 140084646 | AZ30: 137118959 | BA30: 137705575 | BB30: 139726852 | BC30: 171555962 | BD30: 173837156 | BE30: 172805903 | BF30: 172297933 | BG30: 175231499 | BH30: 164322810 | BI30: 164322810 | BJ30: 151090074 | BK30: 148442852 | BL30: 154866106 | BM30: 158608453 | BN30: 162807460 | BO30: 170014882 | BP30: 169218142 | BQ30: 162607694 | BR30: 163342868 | BS30: 164959920 | BT30: 132029045 | BU30: 163067835 | BV30: 163068000
C31: Non withdrawable deposits (BOSA member deposits) | E31: 2255901167 | F31: 2888506869 | G31: 3724504078 | H31: 3791936129 | I31: 4693715976 | J31: 3801493564 | K31: 3708137788 | L31: 3831554335 | M31: 3865857096 | N31: 3879484635 | O31: 3.9246165e+09 | P31: 3957621544 | Q31: 4002543148 | R31: 4045294279 | S31: 4008892470 | T31: 4085665384 | U31: 4085665384 | V31: 4454006657 | W31: 4412161292 | X31: 4456600587 | Y31: 4489078500 | Z31: 4535050198 | AA31: 4556535041 | AB31: 4602930363 | AC31: 4623389706 | AD31: 4586505949 | AE31: 4623512337 | AF31: 4670409980 | AG31: 4670299015 | AH31: 4718751110 | AI31: 4718751110 | AJ31: 4661067125 | AK31: 4685056569 | AL31: 4731042974 | AM31: 4789569089 | AN31: 4839195666 | AO31: 4879367128 | AQ31: 4939565750 | AR31: 4972198718 | AS31: 5012032513 | AT31: 5047530654 | AU31: 5051756877 | AV31: 5051756 | AW31: 5090529263 | AX31: 5048320510 | AY31: 5085588035 | AZ31: 5111680118 | BA31: 5155398544 | BB31: 5204538093 | BC31: 5225184760 | BD31: 5254730048 | BE31: 5308695746 | BF31: 5360122380 | BG31: 5415306577 | BH31: 5444572137 | BI31: 5444572137 | BJ31: 5407733539 | BK31: 5466555851 | BL31: 5517370386 | BM31: 5565337341 | BN31: 5628109010 | BO31: 5663861868 | BP31: 5699668347 | BQ31: 5742741145 | BR31: 5798774560 | BS31: 5862798650 | BT31: 5917566869 | BU31: 5967689614 | BV31: 5967690000
C32: Total Deposit liabilities | E32: =SUM(E29:E31) -> 3149828022 | F32: =SUM(F29:F31) -> 3731412756 | G32: =SUM(G29:G31) -> 4777870785 | H32: =SUM(H29:H31) -> 4154464157 | I32: =SUM(I29:I31) -> 6050709190 | J32: =SUM(J29:J31) -> 4336261895 | K32: =SUM(K29:K31) -> 4254514109 | L32: =SUM(L29:L31) -> 4296623762 | ... BV32: =SUM(BV29:BV31) -> 7044649000
C33: Accounts Payable & Other Liabilities | E33: =SUM(E34:E39) -> 1460675878 | F33: =SUM(F34:F39) -> 2188528151 | G33: =SUM(G34:G39) -> 2615610418 | H33: =SUM(H34:H39) -> 1031650169 | I33: =SUM(I34:I39) -> 3352986654 | J33: =SUM(J34:J39) -> 1140710267 | K33: =SUM(K34:K39) -> 1182425645 | L33: =SUM(L34:L39) -> 707375068 | ... BV33: =SUM(BV34:BV39) -> 814693000
C34: Tax Payable | E34: 3399264 | F34: 1672106 | G34: 1956947 | I34: 19244069 | O34: 0 | P34: 0 | R34: 0 | S34: 0 | T34: 0 | U34: 389584 | AJ34: 0 | AK34: 0 | AL34: 0 | AM34: 0 | AN34: 0 | AO34: 0 | AQ34: 0 | AR34: 0 | AS34: 0 | AT34: 0 | AU34: 0 | AW34: 0 | AX34: 0 | AY34: 0 | AZ34: 0 | BA34: 0 | BB34: 0 | BC34: 0 | BD34: 0 | BE34: 0 | BF34: 0 | BG34: 0 | BH34: 0 | BI34: 1405641.6 | BJ34: 0 | BK34: 0 | BL34: 0 | BM34: 0 | BN34: 0 | BO34: 0 | BP34: 0 | BQ34: 0 | BR34: 0 | BS34: 0 | BT34: 0 | BU34: 0
C35: Dividends Payable | F35: 0 | G35: 0 | H35: 455032335 | I35: 0 | O35: 0 | P35: 0 | R35: 0 | S35: 0 | T35: 0 | U35: 490279846 | V35: 534480799 | AI35: 566250133 | AJ35: 0 | AK35: 0 | AL35: 0 | AM35: 0 | AN35: 0 | AO35: 0 | AQ35: 0 | AR35: 0 | AS35: 0 | AT35: 0 | AU35: 0 | AV35: 606211 | AW35: 0 | AX35: 0 | AY35: 0 | AZ35: 0 | BA35: 0 | BB35: 0 | BC35: 0 | BD35: 0 | BE35: 0 | BF35: 0 | BG35: 0 | BH35: 0 | BI35: 653348656 | BJ35: 0 | BK35: 0 | BL35: 0 | BM35: 0 | BN35: 0 | BO35: 0 | BP35: 0 | BQ35: 0 | BR35: 0 | BS35: 0 | BT35: 0 | BU35: 0 | BV35: 728058000
C36: Deferred Tax Liability | G36: 0 | I36: 0 | O36: 0 | P36: 0 | R36: 0 | S36: 0 | T36: 0 | V36: 435500 | AJ36: 0 | AK36: 0 | AL36: 0 | AM36: 0 | AN36: 0 | AO36: 0 | AQ36: 0 | AR36: 0 | AS36: 0 | AT36: 0 | AU36: 0 | AW36: 0 | AX36: 0 | AY36: 0 | AZ36: 0 | BA36: 0 | BB36: 0 | BC36: 0 | BD36: 0 | BE36: 0 | BF36: 0 | BG36: 0 | BH36: 0 | BI36: 0 | BJ36: 0 | BK36: 0 | BL36: 0 | BM36: 0 | BN36: 0 | BO36: 0 | BP36: 0 | BQ36: 0 | BR36: 0 | BS36: 0 | BT36: 0 | BU36: 0
C37: Retirement Benefits Liability | E37: 35476735 | F37: 46489975 | G37: 66318217 | I37: 89567647 | J37: 20877147 | K37: 20877147 | L37: 20877147 | M37: 20877147 | N37: 20877147 | O37: 20877147 | P37: 20877147 | Q37: 20877147 | R37: 20877147 | S37: 20877147 | T37: 20877147 | U37: 25459772 | W37: 0 | X37: 0 | Y37: 0 | Z37: 0 | AA37: 0 | AB37: 0 | AC37: 0 | AD37: 0 | AE37: 0 | AF37: 0 | AH37: 3221000 | AI37: 221000 | AJ37: 3221000 | AK37: 0 | AL37: 0 | AM37: 0 | AN37: 0 | AO37: 0 | AQ37: 0 | AR37: 0 | AS37: 0 | AT37: 0 | AU37: 0 | AW37: 0 | AX37: 0 | AY37: 0 | AZ37: 0 | BA37: 0 | BB37: 0 | BC37: 0 | BD37: 0 | BE37: 0 | BF37: 0 | BG37: 0 | BH37: 0 | BI37: 0 | BJ37: 0 | BK37: 0 | BL37: 0 | BM37: 0 | BN37: 0 | BO37: 0 | BP37: 0 | BQ37: 0 | BR37: 0 | BS37: 0 | BT37: 0 | BU37: 0
C38: Other Liabilities | E38: 344792845 | F38: =334719630+39928399 -> 374648029 | G38: 492507640 | H38: =80740687+20877147 -> 101617834 | I38: 675238554 | J38: 661499787 | K38: 711548498 | L38: 244831254 | M38: 2.9358652e+08 | N38: 338167286 | O38: 3.9235737e+08 | P38: 4.1288351e+08 | Q38: 4.5033752e+08 | R38: 5.1354668e+08 | S38: 5.2979148e+08 | T38: 5.9232419e+08 | U38: =63885108 -> 63885108 | V38: =54226104 -> 54226104 | W38: 7.1367817e+08 | X38: 7.7168466e+08 | Y38: 830973117 | Z38: 274944616 | AA38: 3.3458643e+08 | AB38: 396968427 | AC38: 457769145 | AD38: 4.6418174e+08 | AE38: 5.0803999e+08 | AF38: 5.7347707e+08 | AG38: 6.3703994e+08 | AH38: 6.9455313e+08 | AI38: =39963397+4957913+3244626+19186589 -> 67352525 | AJ38: 7.6058689e+08 | AK38: 771066042 | AL38: 211218029 | AM38: 275437399 | AN38: 3.3662338e+08 | AO38: 401762937 | AQ38: 4.2461658e+08 | AR38: 5.5214259e+08 | AS38: 6.0572395e+08 | AT38: 7.1203782e+08 | AU38: 7.7424984e+08 | AV38: =38467+2803+4764+18262 -> 64296 | AW38: 865252465 | AX38: 163088006 | AY38: 2.3537297e+08 | AZ38: 3.0714029e+08 | BA38: 310887955 | BB38: 4.5598395e+08 | BC38: 5.3003855e+08 | BD38: 529262344 | BE38: 6.0692148e+08 | BF38: 6.870576e+08 | BG38: 7.9566603e+08 | BH38: 7.328079e+08 | BI38: =60980649+17072949 -> 78053598 | BJ38: 9.8812839e+08 | BK38: 2.3627477e+08 | BL38: 366968862 | BM38: 4.5399399e+08 | BN38: 4.0860394e+08 | BO38: 4.8748268e+08 | BP38: 5.6744645e+08 | BQ38: 554916152 | BR38: 5.0778657e+08 | BS38: 579134756 | BT38: 6.6530028e+08 | BU38: 7.3948464e+08 | BV38: =71023000+15612000 -> 86635000
C39: External Borrowings | E39: 1077007034 | F39: 1765718041 | G39: 2054827614 | H39: 475000000 | I39: 2568936384 | J39: 458333333 | K39: 450000000 | L39: 441666667 | M39: 433333333 | N39: 425000000 | O39: 4.1666667e+08 | P39: 408333333 | Q39: 400000000 | R39: 391666667 | S39: 383333333 | T39: 375000000 | U39: 375000000 | V39: 275000000 | W39: 266666667 | X39: 200265525 | Y39: 95392958 | Z39: 91941390 | AA39: 0 | AB39: 0 | AC39: 0 | AD39: 0 | AE39: 0 | AF39: 0 | AJ39: 0 | AK39: 0 | AL39: 0 | AM39: 0 | AN39: 0 | AO39: 0 | AQ39: 0 | AR39: 0 | AS39: 0 | AT39: 0 | AU39: 0 | AW39: 0 | AX39: 0 | AY39: 0 | AZ39: 0 | BA39: 0 | BB39: 0 | BC39: 0 | BD39: 0 | BE39: 0 | BF39: 0 | BG39: 0 | BH39: 0 | BJ39: 0 | BK39: 0 | BL39: 0 | BM39: 0 | BN39: 0 | BO39: 0 | BP39: 0 | BQ39: 0 | BR39: 0 | BS39: 0 | BT39: 0 | BU39: 0
C40: Total Liabilities | E40: =E32+E33 -> 4610503900 | F40: =F32+F33 -> 5919940907 | G40: =G32+G33 -> 7393481203 | H40: =SUM(H32,H33) -> 5186114326 | I40: =I32+I33 -> 9403695844 | J40: =SUM(J32,J33) -> 5476972162 | K40: =SUM(K32,K33) -> 5436939754 | L40: =SUM(L32,L33) -> 5003998830 | M40: =SUM(M32,M33) -> 5.0043465e+09 | N40: =SUM(N32,N33) -> 5172647209 | O40: =O32+O33 -> 5.1051612e+09 | P40: =P32+P33 -> 5.1891965e+09 | Q40: =Q32+Q33 -> 5.3063273e+09 | R40: =SUM(R32,R33) -> 5.4036749e+09 | S40: =SUM(S32,S33) -> 5.3810825e+09 | T40: =SUM(T32,T33) -> 5.4590504e+09 | U40: =SUM(U32,U33) -> 5439309793 | V40: =SUM(V32,V33) -> 5827129503 | W40: =SUM(W32,W33) -> 5.9601859e+09 | X40: =SUM(X32,X33) -> 6.0071377e+09 | Y40: =SUM(Y32,Y33) -> 6070560916 | ... BV40: =SUM(BV32,BV33) -> 7859342000
C41: EQUITY
C42: Share Capital (Members share capital per Bylaws) | E42: 200701861 | F42: 354553357 | G42: 506915782 | H42: =363268505+85068747 -> 448337252 | I42: 572548724 | J42: 362116694 | K42: 369261188 | L42: 369640072 | M42: 370248612 | N42: 371189189 | O42: 3.7106241e+08 | P42: 372690154 | Q42: 374526545 | R42: 377213578 | S42: 379916219 | T42: 382449866 | U42: 382449866 | V42: 421922225 | W42: 671803630 | X42: 675549493 | Y42: 682351864 | Z42: 694996501 | AA42: 699865703 | AB42: 704056427 | AC42: 706992079 | AD42: 788522873 | AE42: 792152555 | AF42: 798811574 | AG42: 803417610 | AH42: 808927628 | AI42: =712566664+96360965 -> 808927629 | AJ42: 889478087 | AK42: 895362245 | AL42: 903681549 | AM42: 908325219 | AN42: 913266833 | AO42: 917391488 | AQ42: 927537895 | AR42: 933059620 | AS42: 939209221 | AT42: 945621922 | AU42: 951548799 | AV42: =855296+96253 -> 951549 | AW42: 956552872 | AX42: 1052526620 | AY42: 1068575644 | AZ42: 1077139670 | BA42: 1084948139 | BB42: 1090053803 | BC42: 1099912990 | BD42: 1108761516 | BE42: 1116734817 | BF42: 1124039832 | BG42: 1131591525 | BH42: 1138732170 | BI42: =1021550973+117181197 -> 1138732170 | BJ42: 1227167486 | BK42: 1233529981 | BL42: 1243165993 | BM42: 1249880974 | BN42: 1256607095 | BO42: 1262839984 | BP42: 1268441681 | BQ42: 1274290526 | BR42: 1281308853 | BS42: 1287614159 | BT42: 1291670944 | BU42: 1305240952 | BV42: =1188205000+117036000 -> 1305241000
C43: Capital Grants | O43: 0 | P43: 0 | Q43: 0 | R43: 0 | S43: 0 | T43: 0 | AA43: 0 | AJ43: 0 | AK43: 0 | AL43: 0 | AM43: 0 | AN43: 0 | AO43: 0 | AQ43: 0 | AR43: 0 | AS43: 0 | AT43: 0 | AU43: 0 | AW43: 0 | AX43: 0 | AY43: 0 | AZ43: 0 | BA43: 0 | BB43: 0 | BC43: 0 | BD43: 0 | BE43: 0 | BF43: 0 | BG43: 0 | BH43: 0 | BI43: 0 | BJ43: 0 | BK43: 0 | BL43: 0 | BM43: 0 | BN43: 0 | BO43: 0 | BP43: 0 | BQ43: 0 | BR43: 0 | BS43: 0 | BT43: 0 | BU43: 0
C44: Retained Earnings | E44: =E45+E46 -> 122033640 | F44: =F45+F46 -> 231411145 | G44: =G45+G46 -> 363313672 | H44: =H46+H45 -> 998644776 | I44: =I45+I46 -> 824732856 | J44: =J46+J45 -> 1114886711 | K44: =K46+K45 -> 1075582467 | L44: =L46+L45 -> 1150889352 | M44: =M46+M45 -> 1175760829 | N44: =N46+N45 -> 1198539602 | O44: =O45+O46 -> 1.2576227e+09 | P44: =P45+P46 -> 1286115583 | Q44: =Q46+Q45 -> 1291934473 | R44: =R46+R45 -> 1331145940 | S44: =S46+S45 -> 1374982701 | T44: =T46+T45 -> 1318553143 | U44: =U46+U45 -> 1244145530 | V44: =V46+V45 -> 1354697707 | W44: =W46+W45 -> 1433879611 | X44: =X46+X45 -> 1407719966 | ... BV44: =BV46+BV45 -> 1974689000
C45: Prior Years' Retained Earnings | E45: 87411123 | F45: 122033640 | G45: 231411145 | H45: 851712029 | I45: 754979893 | J45: 1061726214 | K45: 998644776 | L45: 998644776 | M45: 998644776 | N45: 998644776 | O45: 998644776 | P45: 998644776 | Q45: 998644776 | R45: 998644776 | S45: 998644776 | T45: 998644776 | U45: 998644776 | V45: 1128111767 | W45: 1407543917 | X45: 1354697707 | Y45: 1354697707 | Z45: 1354697707 | AA45: 1354697707 | AB45: 1354697707 | AC45: 1354697707 | AD45: 1354697707 | AE45: 1354697707 | AF45: 1354697707 | AG45: 1354697707 | AH45: 1354697707 | AI45: 1354697707 | AJ45: 1691664735 | AK45: 1690135345 | AL45: 1690135345 | AM45: 1690135345 | AN45: 1690135345 | AO45: 1690135345 | AQ45: 1690135345 | AR45: 1690135345 | AS45: 1690135345 | AT45: 1690135345 | AU45: 1690135345 | AV45: 1690135 | AW45: 1863087733 | AX45: 1863087733 | AY45: 1863087733 | AZ45: 1863087733 | BA45: 1863087733 | BB45: 1863087733 | BC45: 1863087733 | BD45: 1863087733 | BE45: 1863087733 | BF45: 1863087733 | BG45: 1863087733 | BH45: 1863087733 | BI45: 1863087733 | BJ45: 1956805622 | BK45: 1956805622 | BL45: 1956805622 | BM45: 1956805622 | BN45: 1956805622 | BO45: 1956805622 | BP45: 1956805622 | BQ45: 1956805622 | BR45: 1956805622 | BS45: 1956805622 | BT45: 1956805622 | BU45: 1956805622 | BV45: 1956805000
C46: Current Year's Surplus | E46: 34622517 | F46: 109377505 | G46: 131902527 | H46: 146932747 | I46: 69752963 | J46: 53160497 | K46: 76937691 | L46: 152244576 | M46: 177116053 | N46: 199894826 | O46: 2.589779e+08 | P46: 287470807 | Q46: 293289697 | R46: 332501164 | S46: 376337925 | T46: 319908367 | U46: =1244145530-U45 -> 245500754 | V46: 226585940 | W46: 26335694 | X46: 53022259 | Y46: 66457649 | Z46: 87314892 | AA46: 133072426 | AB46: 184771034 | AC46: 183830863 | AD46: 238105615 | AE46: 211355515 | AF46: 242608753 | AG46: 249546852 | AH46: 235699667 | AI46: =474738488-2800000+74551614-99729815-111322649 -> 335437638 | AJ46: 12311538 | AK46: 95318918 | AL46: 71860581 | AM46: 80409081 | AN46: 87301947 | AO46: 58427698 | AQ46: 165308764 | AR46: 3283962 | AS46: 107838356 | AT46: 171158392 | AU46: 157584838 | AV46: =368214-5000-79271+1722+27633-139845 -> 173453 | AW46: -8421938 | AX46: 11484587 | AY46: 34816896 | AZ46: 57222810 | BA46: 149352071 | BB46: 121831290 | BC46: 143134916 | BD46: 158832192 | BE46: 168103840 | BF46: 176636717 | BG46: 183171136 | BH46: 54513163 | BI46: 93717889 | BJ46: 3744084 | BK46: 50177949 | BL46: -8901661 | BM46: -38747926 | BN46: 29296284 | BO46: 47415426 | BP46: 81748957 | BQ46: 99104662 | BR46: 263356557 | BS46: 275277276 | BT46: 306371288 | BU46: 377144957 | BV46: 17884000
C47: Other Equity Accounts | E47: =SUM(E48:E52) -> 125530034 | F47: =SUM(F48:F52) -> 200536617 | G47: =SUM(G48:G52) -> 286916920 | H47: =SUM(H48:H52) -> 699651844 | I47: =SUM(I48:I52) -> 426193730 | J47: =SUM(J48:J52) -> 619745451 | K47: =SUM(K48:K52) -> 736893650 | L47: =SUM(L48:L52) -> 749475113 | ... O47: =SUM(O48:O52) -> 7.7473847e+08 | P47: =SUM(P48:P51) -> 7.8024634e+08 | Q47: =SUM(Q48:Q52) -> 7.8494129e+08 | R47: =SUM(R48:R52) -> 7.9025043e+08 | S47: =SUM(S48:S52) -> 7.9545473e+08 | T47: =SUM(T48:T52) -> 8.0171693e+08 | U47: =SUM(U48:U52) -> 1040448423 | V47: =SUM(V48:V52) -> 1111561263 | W47: =SUM(W48:W52) -> 8.944015e+08 | X47: =SUM(X48:X52) -> 8.6807523e+08 | ... BV47: =SUM(BV48:BV52) -> 1818750000
C48: Statutory Reserve | E48: 69785929 | F48: 113085206 | G48: 169505693 | H48: 393846829 | I48: 294450183 | J48: 347999297 | K48: 347999297 | L48: 347999297 | M48: 347999297 | N48: 347999297 | O48: 347999297 | P48: 347999297 | Q48: 347999297 | R48: 347999297 | S48: 347999297 | T48: 347999297 | U48: 450731709 | W48: 494856977 | X48: 528921206 | Y48: 528921206 | Z48: 528921206 | AA48: 528921206 | AB48: 528921206 | AC48: 528921206 | AD48: 528921221 | AE48: 528921221 | AF48: 528921221 | AG48: 528921221 | AH48: 528921221 | AI48: 628651036 | AJ48: 629050281 | AK48: 628651036 | AL48: 628651036 | AM48: 628651036 | AN48: 628651036 | AO48: 628651036 | AQ48: 628651036 | AR48: 628651036 | AS48: 628651036 | AT48: 628651036 | AU48: 628651036 | AV48: 707922 | AW48: 707922660 | AX48: 707922660 | AY48: 707922660 | AZ48: 707922660 | BA48: 707922660 | BB48: 707922660 | BC48: 707922660 | BD48: 707922660 | BE48: 707922660 | BF48: 707922660 | BG48: 707922660 | BH48: 847099120 | BI48: 8.4709912e+08 | BJ48: 847099120 | BK48: 847099120 | BL48: 847099120 | BM48: 847099120 | BN48: 847099120 | BO48: 847099120 | BP48: 847099120 | BQ48: 847099120 | BR48: 847099120 | BS48: 847099120 | BT48: 847099120 | BU48: 847099120 | BV48: 984947000
C49: Other Reserves (provide notes on these reserves) | E49: 4527843 | F49: 4527843 | G49: 4527843 | H49: 49067834 | I49: 4527843 | J49: 69108591 | K49: 182101663 | L49: 190666379 | M49: 201655559 | N49: 202363685 | O49: 2.0380858e+08 | P49: 205155527 | Q49: 205633952 | R49: 2.0659463e+08 | S49: 207390380 | T49: 209207450 | U49: =95916272+704694515-U48-U51 -> 277550095 | V49: =618248091+102184539+96170553 -> 816603183 | W49: 115511386 | X49: 113773755 | Y49: 113928755 | Z49: 114007755 | AA49: 114081255 | AB49: 114121255 | AC49: 114161755 | AD49: 114204255 | AE49: 114239255 | AF49: 114302255 | AG49: 114341117 | AH49: 114127437 | AI49: =11942898+27632925 -> 39575823 | AJ49: 39621323 | AK49: 39672423 | AL49: 39723923 | AM49: 39747423 | AN49: 39776923 | AO49: 39831422 | AQ49: 39888923 | AR49: 39924423 | AS49: 39956923 | AT49: 39978923 | AU49: 39996623 | AV49: =146659+10642 -> 157301 | AW49: 10685682 | AX49: 10733182 | AY49: 10794682 | AZ49: 10896182 | BA49: 10951682 | BB49: 11043182 | BC49: 11130182 | BD49: 11210682 | BE49: 11262182 | BF49: 11321682 | BG49: 11375682 | BH49: 267546287 | BI49: 2.2019217e+08 | BJ49: 228441061 | BK49: 228496061 | BL49: 228575061 | BM49: 231630061 | BN49: 228671061 | BO49: 2.2871806e+08 | BP49: 228754561 | BQ49: 228811061 | BR49: 228857561 | BS49: 228921561 | BT49: 228921561 | BU49: 242372588 | BV49: 219550000
C50: Revaluation Reserves (Not part of core capital) | E50: 19103964 | F50: 19103964 | G50: 19103964 | H50: 194791701 | I50: 19103964 | J50: 194791701 | K50: 194791701 | L50: 194791701 | M50: 194791701 | N50: 194791701 | O50: 194791701 | P50: 194791701 | Q50: 194791701 | R50: 194791701 | S50: 194791701 | T50: 194791701 | U50: =239837636 -> 239837636 | V50: =213713770 -> 213713770 | W50: 278233897 | X50: 213713771 | Y50: 213713771 | Z50: 213713771 | AA50: 213713771 | AB50: 213713771 | AC50: 213713771 | AD50: 213713771 | AE50: 213713771 | AF50: 213713771 | AG50: 213713771 | AH50: 213713771 | AI50: 242867069 | AJ50: 242867069 | AK50: 242867069 | AL50: 242867069 | AM50: 242867069 | AN50: 242867069 | AO50: 242867069 | AQ50: 242867069 | AR50: 242867069 | AS50: 242867069 | AT50: 242867069 | AU50: 242867069 | AW50: 146658880 | AX50: 146658880 | AY50: 1.4665888e+08 | AZ50: 1.4665888e+08 | BA50: 1.4665888e+08 | BB50: 1.4665888e+08 | BC50: 1.4665888e+08 | BD50: 1.4665888e+08 | BE50: 1.4665888e+08 | BF50: 146658881 | BG50: 1.4665888e+08 | BH50: 147500355 | BI50: 1.4750036e+08 | BJ50: 147500355 | BK50: 147500355 | BL50: 147500355 | BM50: 147500355 | BN50: 147500355 | BO50: 147500355 | BP50: 147500355 | BQ50: 147500355 | BR50: 147500355 | BS50: 147500355 | BT50: 147500355 | BU50: 147500355 | BV50: =126720000+79896000 -> 206616000
C51: Proposed Dividends | E51: 32112298 | F51: 63819604 | G51: 93779420 | H51: 61945480 | I51: 108111740 | J51: 7845862 | K51: 12000989 | L51: 16017736 | M51: 20055133 | N51: 24127297 | O51: 28138900 | P51: 32299813 | Q51: 36516338 | R51: 40864804 | S51: 45273349 | T51: 49718484 | U51: 72328983 | V51: 81244310 | W51: 5799241.5 | X51: 11666498 | Y51: 17683354 | Z51: 23856748 | AA51: 30036362 | AB51: 36270458 | AC51: 57737686 | AD51: 55915859 | AE51: 63184934 | AF51: 70928821 | AG51: 78489450 | AH51: 86235607 | AI51: 111322649 | AJ51: 8114816.3 | AK51: 8169941 | AL51: 24698134 | AM51: 33107606 | AN51: 41578390 | AO51: 50079256 | AQ51: 58994848 | AR51: 76245523 | AS51: 85307591 | AT51: 94517667 | AU51: 1.0385156e+08 | AV51: 139845 | AW51: 8700150 | AX51: 20978914 | AY51: 31316691 | AZ51: 42022314 | BA51: 42335508 | BB51: 63874326 | BC51: 75093182 | BD51: 86591723 | BE51: 98022502 | BF51: 1.0978063e+08 | BG51: 1.2160192e+08 | BH51: 191240847 | BI51: 1.9124084e+08 | BJ51: 17384873 | BK51: 34950016 | BL51: 52834555 | BM51: 70826589 | BN51: 89009671 | BO51: 1.073414e+08 | BP51: 1.2578713e+08 | BQ51: 144419593 | BR51: 1.6336688e+08 | BS51: 182412007 | BT51: 2.0128539e+08 | BU51: 2.2189096e+08 | BV51: 407637000
C52: Adjustment to Equity | P52: 0 | R52: 0 | S52: 0 | T52: 0 | AJ52: 0 | AK52: 0 | AW52: 0 | AX52: 0 | AY52: 0 | AZ52: 0 | BA52: 0 | BB52: 0 | BC52: 0 | BD52: 0 | BE52: 0 | BF52: 0 | BG52: 0 | BH52: 0 | BI52: 0 | BJ52: 0 | BK52: 0 | BL52: 0 | BM52: 0 | BN52: 0 | BO52: 0 | BP52: 0 | BQ52: 0 | BR52: 0 | BS52: 0 | BT52: 0 | BU52: 0
C53: Total Equity | E53: =E42+E44+E47 -> 448265535 | F53: =F42+F44+F47 -> 786501119 | G53: =G42+G44+G47 -> 1157146374 | H53: =SUM(H42,H43,H44,H47) -> 2146633872 | I53: =I42+I44+I47 -> 1823475310 | J53: =SUM(J42,J43,J44,J47) -> 2096748856 | K53: =SUM(K42,K43,K44,K47) -> 2181737305 | L53: =SUM(L42,L43,L44,L47) -> 2270004537 | M53: =SUM(M42,M43,M44,M47) -> 2.3105111e+09 | N53: =SUM(N42,N43,N44,N47) -> 2339010771 | O53: =O42+O44+O47 -> 2.4034236e+09 | P53: =P42+P44+P47 -> 2.4390521e+09 | Q53: =Q42+Q43+Q44+Q47 -> 2.4514023e+09 | R53: =SUM(R42,R43,R44,R47) -> 2.4986099e+09 | S53: =SUM(S42,S43,S44,S47) -> 2.5503536e+09 | T53: =SUM(T42,T43,T44,T47) -> 2.5027199e+09 | U53: =SUM(U42,U43,U44,U47) -> 2667043819 | V53: =SUM(V42,V43,V44,V47) -> 2888181195 | W53: =SUM(W42,W43,W44,W47) -> 3.0000847e+09 | X53: =SUM(X42,X43,X44,X47) -> 2.9513447e+09 | Y53: =SUM(Y42,Y43,Y44,Y47) -> 2977754306 | ... BV53: =SUM(BV42,BV43,BV44,BV47) -> 5098680000
C54: Total Liabilities and Equity | E54: =E40+E53 -> 5058769435 | F54: =F40+F53 -> 6706442026 | G54: =G40+G53 -> 8550627577 | H54: =SUM(H40,H53) -> 7332748198 | I54: =I40+I53 -> 11227171154 | J54: =SUM(J40,J53) -> 7573721018 | K54: =SUM(K40,K53) -> 7618677059 | L54: =SUM(L40,L53) -> 7274003367 | M54: =SUM(M40,M53) -> 7.3148577e+09 | N54: =SUM(N40,N53) -> 7511657980 | O54: =O40+O53 -> 7.5085847e+09 | P54: =P40+P53 -> 7.6282486e+09 | Q54: =Q40+Q53 -> 7757729648 | R54: =SUM(R40,R53) -> 7902284798 | S54: =SUM(S40,S53) -> 7931436143 | T54: =SUM(T40,T53) -> 7961770314 | U54: =SUM(U40,U53) -> 8106353612 | V54: =SUM(V40,V53) -> 8715310698 | W54: =SUM(W40,W53) -> 8960270626 | X54: =SUM(X40,X53) -> 8958482401 | Y54: =SUM(Y40,Y53) -> 9048315222 | ... BH54: =SUM(BH40,BH53) -> 1.1690659e+10 | BI54: =BI40+BI53 -> 1.168251e+10 | BJ54: =BJ40+BJ53 -> 11818135664 | BK54: =BK40+BK53 -> 11606972435 | BL54: =BL40+BL53 -> 11618406725 | BM54: =BM40+BM53 -> 11626795764 | BN54: =BN40+BN53 -> 11669577232 | BO54: =BO40+BO53 -> 11817464595 | BP54: =BP40+BP53 -> 12046853238 | ... BV54: =BV40+BV53 -> 12958022000
D55: =D54-D27 -> 0 | E55: =E54-E27 -> -1 | F55: =F54-F27 -> -1 | G55: =G54-G27 -> 0 | H55: =H54-H27 -> 0 | I55: =I54-I27 -> 0 | J55: =J54-J27 -> 0 | N55: =N54-N27 -> 0 | O55: =O54-O27 -> 0 | P55: =P54-P27 -> -0.11000061 | Q55: =Q54-Q27 -> 0 | R55: =R54-R27 -> 0 | S55: =S54-S27 -> 0 | T55: =T54-T27 -> 0 | U55: =U54-U27 -> -3 | V55: =V27-V54 -> 20 | W55: =W27-W54 -> 0 | X55: =X27-X54 -> 0 | Y55: =Y27-Y54 -> 0 | Z55: =Z27-Z54 -> 0 | AA55: =AA27-AA54 -> 0 | AB55: =AB27-AB54 -> 0 | AC55: =AC27-AC54 -> 0 | ... AV55: =AV27-AV54 -> 0 | BI55: =BI54-BI27 -> -8149389.7 | BJ55: =BJ54-BJ27 -> 0 | BK55: =BK54-BK27 -> 0 | BL55: =BL54-BL27 -> 0 | BM55: =BM54-BM27 -> 0 | BN55: =BN54-BN27 -> 0 | BO55: =BO54-BO27 -> 0 | BP55: =BP54-BP27 -> 0 | ... BR55: =BR54-BR27 -> 0

Sheet SCI
C2: AUDITED 2012 | D2: AUDITED 2013 | E2: AUDITED 2014 | F2: AUDITED 2015 | G2: AUDITED 2016 | H2: 42736 | I2: 42768 | J2: 42800 | K2: 42832 | L2: 42864 | M2: 42896 | N2: 42928 | O2: 42960 | P2: 42992 | Q2: 43024 | R2: 43056 | S2: 43088 | T2: AUDITED 2017 | U2: Audited 2018 | V2: 43466 | W2: 43497 | X2: 43525 | Y2: 43556 | Z2: 43586 | AA2: 43617 | AB2: 43647 | AC2: 43678 | AD2: 43709 | AE2: 43739 | AF2: 43770 | AG2: 43800 | AH2: AUDITED 2019 | AI2: 43831 | AJ2: 43862 | AK2: 43891 | AL2: 43922 | AM2: 43952 | AN2: 43983 | AO2: 44013 | AP2: 44044 | AQ2: 44075 | AR2: 44105 | AS2: 44136 | AT2: 44166 | AU2: AUDITED 2020 | AV2: 44197 | AW2: 44228 | AX2: 44256 | AY2: 44287 | AZ2: 44317 | BA2: 44348 | BB2: 44378 | BC2: 44409 | BD2: 44440 | BE2: 44470 | BF2: 44501 | BG2: 44531 | BH2: Audited 2021 | BI2: 44562 | BJ2: 44593 | BK2: 44621 | BL2: 44652 | BM2: 44682 | BN2: 44713 | BO2: 44743 | BP2: 44774 | BQ2: 44805 | BR2: 44835 | BS2: 44866 | BT2: 44896
B3: Financial Income | D3: =D4+D7 -> 676832181 | E3: =E4+E7 -> 946830578 | F3: =F4+F7 -> 1227499577 | G3: =G4+G7 -> 1143452459 | H3: =H4+H7 -> 193744293 | I3: =I4+I7 -> 203564866 | J3: =J4+J7 -> 303028686 | K3: =K4+K7 -> 430167093 | ... BU3: =BU4+BU7 -> 1763187000
B4: Financial Income from Loans Portfolio | D4: =D5+D6 -> 610694891 | E4: =E5+E6 -> 789564218 | F4: =F5+F6 -> 1126129366 | G4: =SUM(G5:G6) -> 1046558453 | H4: =H5+H6 -> 181126619 | I4: =SUM(I5:I6) -> 197803153 | J4: =SUM(J5:J6) -> 293247468 | K4: =SUM(K5:K6) -> 407702281 | L4: =SUM(L5:L6) -> 505905780 | M4: =SUM(M5:M6) -> 602538848 | N4: =SUM(N5:N6) -> 7.0196992e+08 | O4: =SUM(O5:O6) -> 808241658 | P4: =SUM(P5:P6) -> 919325902 | ... BU4: =SUM(BU5:BU6) -> 1424256000
B5: Interest on Loan Portfolio | D5: 610694891 | E5: 789564218 | F5: 1126129366 | G5: 1046558453 | H5: 178321845 | I5: 195596456 | J5: 290110440 | K5: 403571533 | L5: 500875916 | M5: 596698871 | N5: 6.9524448e+08 | O5: 800190668 | P5: 910539022 | Q5: 1014161815 | R5: 1122793037 | S5: 1223575415 | T5: 1239848635 | U5: 1246870335 | V5: 116892118 | W5: 226319507 | X5: 338628579 | Y5: 441339573 | Z5: 552042078 | AA5: 659271924 | AB5: 765650636 | AC5: 874103598 | AD5: 969262585 | AE5: 1078663805 | AF5: 1174408219 | AG5: 1262228351 | AH5: =1268904530 -> 1268904530 | AI5: 161567247 | AJ5: 318027791 | AK5: 337777581 | AL5: 426420881 | AM5: 516263765 | AN5: 604741119 | AP5: 803140139 | AQ5: 900812162 | AR5: 1000975635 | AS5: 1105609467 | AT5: 1217860781 | AU5: =573908+122403+521550 -> 1217861 | AV5: 98795883 | AW5: 210901581 | AX5: 316261645 | AY5: 423936541 | AZ5: 532784944 | BA5: 640048000 | BB5: 760281663 | BC5: 863048218 | BD5: 976419816 | BE5: 1089934217 | BF5: 1205697536 | BG5: 1313648179 | BH5: 1.3136482e+09 | BI5: 106476900 | BJ5: 247096178 | BK5: 361377808 | BL5: 477295869 | BM5: 593072534 | BN5: 701560174 | BO5: 814798007 | BP5: 941955189 | BQ5: 1059712465 | BR5: 1177275594 | BS5: 1306005477 | BT5: 1424256218 | BU5: 1424256000
B6: Fees & Commission on Loan Portfolio | D6: 0 | H6: 2804774 | I6: 2206697 | J6: 3137028 | K6: 4130748 | L6: 5029864 | M6: 5839977 | N6: 6725443.3 | O6: 8050990 | P6: 8786880 | Q6: 8987630 | R6: 9927030 | S6: 10792130 | V6: 5968475 | W6: 5968475 | X6: 2043401 | Y6: 2043401 | Z6: 2043401 | AA6: 2871122 | AB6: 2871122 | AC6: 4357604 | AD6: 4622386 | AE6: 4622386 | AF6: 4622386 | AG6: 4622386 | AI6: 2725147 | AJ6: 6426148 | AK6: 0 | AL6: 0 | AM6: 0 | AN6: 0 | AP6: 0 | AQ6: 0 | AR6: 0 | AS6: 0 | AT6: 0 | AV6: 0 | AW6: 0 | AX6: 0 | AY6: 0 | AZ6: 0 | BA6: 0 | BB6: 0 | BC6: 0 | BD6: 0 | BE6: 0 | BF6: 0 | BG6: 0 | BI6: 0 | BJ6: 0 | BK6: 0 | BL6: 0 | BM6: 0 | BN6: 0 | BO6: 0 | BP6: 0 | BQ6: 0 | BR6: 0 | BS6: 0 | BT6: 0
B7: Financial Income from Investments in: | D7: =SUM(D8:D11) -> 66137290 | E7: =SUM(E8:E11) -> 157266360 | F7: =SUM(F8:F11) -> 101370211 | G7: =SUM(G8:G11) -> 96894006 | H7: =SUM(H8:H11) -> 12617674 | I7: =SUM(I8:I11) -> 5761713 | J7: =SUM(J8:J11) -> 9781218 | K7: =SUM(K8:K11) -> 22464812 | ... BU7: =SUM(BU8:BU11) -> 338931000
B8: Government Securities | H8: 0 | P8: 0 | Q8: 0 | R8: 0 | S8: 0 | AI8: 0 | AJ8: 0 | AK8: 0 | AL8: 0 | AM8: 0 | AN8: 0 | AP8: 0 | AQ8: 0 | AR8: 0 | AS8: 0 | AT8: 0 | AV8: 0 | AW8: 0 | AX8: 0 | AY8: 0 | AZ8: 0 | BA8: 0 | BB8: 0 | BC8: 0 | BD8: 0 | BE8: 0 | BF8: 0 | BG8: 0 | BI8: 0 | BJ8: 0 | BK8: 0 | BL8: 0 | BM8: 0 | BN8: 0 | BO8: 0 | BP8: 0 | BQ8: 0 | BR8: 0 | BS8: 0 | BT8: 0
B9: Deposit with Banks and Other Financial Inst. | D9: 23928427 | E9: =8412541+584000 -> 8996541 | F9: 9845327 | H9: 1312043 | P9: 0 | Q9: 0 | R9: 0 | S9: 0 | AI9: 0 | AJ9: 0 | AK9: 0 | AL9: 0 | AM9: 0 | AN9: 0 | AP9: 0 | AQ9: 0 | AR9: 0 | AS9: 0 | AT9: 0 | AV9: 0 | AW9: 0 | AX9: 0 | AY9: 0 | AZ9: 0 | BA9: 0 | BB9: 0 | BC9: 0 | BD9: 0 | BE9: 0 | BF9: 0 | BG9: 0 | BH9: 2.1931509e+08 | BI9: 0 | BJ9: 0 | BK9: 0 | BL9: 0 | BM9: 0 | BN9: 0 | BO9: 0 | BP9: 0 | BQ9: 0 | BR9: 0 | BS9: 0 | BT9: 0 | BU9: 203981000
B10: Other Investments - dividend & Interest incomes from investments | E10: 15781910 | F10: 16915086 | G10: 9824350 | H10: 0 | K10: 2996468 | L10: 4996468 | M10: 17219555 | N10: 19133923 | O10: 21668115 | P10: 20745545 | Q10: 24268575 | R10: 24268575 | S10: 27919090 | T10: 16644442 | U10: =30435654+25113162 -> 55548816 | V10: 0 | W10: 0 | X10: 0 | Y10: 367552 | Z10: 14193338 | AA10: 37394287 | AB10: 43107114 | AC10: 43685588 | AD10: 52633008 | AE10: 53252174 | AF10: 58091809 | AG10: 76734831 | AH10: =53874180 -> 53874180 | AI10: 0 | AJ10: 0 | AK10: 5100938 | AL10: 21029541 | AM10: 50434991 | AN10: 50983303 | AP10: 58743416 | AQ10: 58743416 | AR10: 74398073 | AS10: 97844606 | AT10: 117568888 | AU10: =78028+39540 -> 117568 | AV10: 2465709 | AW10: 2465709 | AX10: 7799042 | AY10: 42223694 | AZ10: 42223694 | BA10: 94441389 | BB10: 94441389 | BC10: 107827534 | BD10: 109649046 | BE10: 111548301 | BF10: 113422223 | BG10: 259886079 | BH10: 40570986 | BI10: 0 | BJ10: 8920460 | BK10: 8920460 | BL10: 8920460 | BM10: 33431705 | BN10: 77811306 | BO10: 116370936 | BP10: 116370936 | BQ10: 160601945 | BR10: 160756249 | BS10: 172052116 | BT10: 252543026
B11: Other Operating Income- Salary processing fees, transaction fees, membership fees | D11: 42208863 | E11: 132487909 | F11: 74609798 | G11: 87069656 | H11: 11305631 | I11: 5761713 | J11: 9781218 | K11: 19468344 | L11: 28473369 | M11: 34122394 | N11: 37987353 | O11: 44351364 | P11: 49001608 | Q11: 54138927 | R11: 64232516 | S11: 63355107 | T11: =85304965 -> 85304965 | U11: =90316509-25113162 -> 65203347 | V11: 422941 | W11: 4908109 | X11: 16349047 | Y11: 29367265 | Z11: 36382728 | AA11: 42291257 | AB11: 47468640 | AC11: 55953229 | AD11: 57643909 | AE11: 64942782 | AF11: 60312391 | AG11: 65235244 | AH11: =104322145 -> 104322145 | AI11: 6758574 | AJ11: 13817611 | AK11: 23762695 | AL11: 59700961 | AM11: 39120293 | AN11: 40560308 | AP11: 49990620 | AQ11: 54824111 | AR11: 64620743 | AS11: 71255195 | AT11: 74601546 | AU11: =34339+19358+15379+2492+221+2813 -> 74602 | AV11: 5467550 | AW11: 14691123 | AX11: 22574373 | AY11: 30551886 | AZ11: 38551286 | BA11: 45248276 | BB11: 51381406 | BC11: 54820780 | BD11: 61008203 | BE11: 66075337 | BF11: 76958006 | BG11: 84726379 | BH11: =62703159+21946347+76873 -> 84726379 | BI11: 6358787 | BJ11: 16758010 | BK11: 24631984 | BL11: 32365955 | BM11: 40388329 | BN11: 46995246 | BO11: 49910318 | BP11: 60079348 | BQ11: 65920841 | BR11: 75068413 | BS11: 81383321 | BT11: 86387636 | BU11: 134950000
B12: Financial Expense | C12: =SUM(C13:C18) -> 0 | D12: =SUM(D13:D18) -> 402074127 | E12: =SUM(E13:E18) -> 478287881 | F12: =SUM(F13:F18) -> 619005052 | G12: =G13+G14+G15+G16+G17+G18 -> 503292195 | H12: =SUM(H13:H18) -> 82300867 | I12: =I13+I14+I15+I16+I17+I18 -> 108336631 | J12: =J13+J14+J15+J16+J17+J18 -> 164649494 | K12: =K13+K14+K15+K16+K17+K18 -> 230707154 | L12: =L13+L14+L15+L16+L17+L18 -> 2.8841367e+08 | M12: =M13+M14+M15+M16+M17+M18 -> 351928134 | N12: =N13+N14+N15+N16+N17+N18 -> 4.1224302e+08 | O12: =O13+O14+O15+O16+O17+O18 -> 4.742617e+08 | P12: =P13+P14+P15+P16+P17+P18 -> 5.4396708e+08 | ... BU12: =BU13+BU14+BU15+BU16+BU17+BU18 -> 751693000
B13: Interest Expense on Deposits | D13: 274653200 | E13: =283203148+41141974 -> 324345122 | F13: 436386278 | G13: =455032335+7760428 -> 462792763 | H13: 47493255 | I13: 83475796 | J13: 126442851 | K13: 174149650 | L13: 2.2006201e+08 | M13: 264787224 | N13: 3.132318e+08 | O13: 3.6046062e+08 | P13: 4.095364e+08 | Q13: 4.6098706e+08 | R13: 5.0216227e+08 | S13: 5.5795178e+08 | T13: =490279846+16373905 -> 506653751 | U13: =16686590+534480799 -> 551167389 | V13: 54389865 | W13: 1.0868116e+08 | X13: 163712365 | Y13: 2.2066618e+08 | Z13: 2.7661498e+08 | AA13: 3.3462256e+08 | AB13: 4.0322674e+08 | AC13: 4.5485056e+08 | AD13: 5.1336982e+08 | AE13: 5.7390804e+08 | AF13: 6.257004e+08 | AG13: 6.8809525e+08 | AH13: =12179875+566250133 -> 578430008 | AI13: 40984623 | AJ13: 82318515 | AK13: 1.7198538e+08 | AL13: 2.31036e+08 | AM13: 2.9135564e+08 | AN13: 352493379 | AP13: 4.1624712e+08 | AQ13: 5.3885709e+08 | AR13: 6.0352088e+08 | AS13: 6.7599896e+08 | AT13: 7.3807967e+08 | AU13: =606211+17358 -> 623569 | AV13: 60512433 | AW13: 1.2998175e+08 | AX13: 1.9637812e+08 | AY13: 2.6395007e+08 | AZ13: 2.6763824e+08 | BA13: 404345440 | BB13: 4.795653e+08 | BC13: 550124844 | BD13: 6.2334501e+08 | BE13: 7.0085071e+08 | BF13: 7.7854004e+08 | BG13: 6.7286367e+08 | BH13: =19515018+653348656 -> 672863674 | BI13: 55970447 | BJ13: 1.1172423e+08 | BK13: 237755340 | BL13: 3.1863621e+08 | BM13: 3.5859588e+08 | BN13: 4.3302029e+08 | BO13: 5.0861711e+08 | BP13: 5.8927733e+08 | BQ13: 5.3855079e+08 | BR13: 6.1250713e+08 | BS13: 672030497 | BT13: 7.3975749e+08 | BU13: 751693000
B14: Cost of External Borrowings | D14: 125309827 | E14: =145777691+7434856 -> 153212547 | F14: 180297605 | G14: =503292195-G13 -> 40499432 | H14: 22604631 | I14: 11682507 | J14: 16624290 | K14: 21978631 | L14: 27060822 | M14: 32213334 | N14: 37103745 | O14: 42061623 | P14: 48040667 | Q14: 52643408 | R14: 57371622 | S14: 61841795 | T14: =1760060+60081736 -> 61841796 | U14: =553882+44707422 -> 45261304 | V14: 3036301 | W14: 7912785 | X14: 9999689 | Y14: 9999689 | Z14: 11383625 | AA14: 11383627 | AB14: 11383627 | AC14: 11383627 | AD14: 11383627 | AE14: 11383627 | AF14: 11383627 | AG14: 11383627 | AH14: 11383627 | AI14: 0 | AJ14: 0 | AK14: 0 | AL14: 0 | AM14: 0 | AN14: 0 | AP14: 0 | AQ14: 0 | AR14: 0 | AS14: 0 | AT14: 0 | AV14: 0 | AW14: 0 | AX14: 0 | AY14: 0 | AZ14: 0 | BA14: 0 | BB14: 0 | BC14: 0 | BD14: 0 | BE14: 0 | BF14: 0 | BG14: 0 | BI14: 0 | BJ14: 0 | BK14: 0 | BL14: 0 | BM14: 0 | BN14: 0 | BO14: 0 | BP14: 0 | BQ14: 0 | BR14: 0 | BS14: 0 | BT14: 0
B15: Dividend Expenses (on member shares) | H15: 12000000 | I15: 7845862 | J15: 12000989 | K15: 16017736 | L15: 20055133 | M15: 24127297 | N15: 28138900 | O15: 32299813 | P15: 36516338 | Q15: 40864804 | R15: 45273349 | S15: 49718483 | V15: 5799241 | W15: 11666498 | X15: 17683355 | Y15: 23856748 | Z15: 30036363 | AA15: 36270458 | AB15: 57737686 | AC15: 55915859 | AD15: 63184934 | AE15: 70928821 | AF15: 78489450 | AG15: 86235607 | AI15: 4089203 | AJ15: 8178623 | AK15: 24698133 | AL15: 33107607 | AM15: 41578390 | AN15: 50079255 | AP15: 58994484 | AQ15: 76245523 | AR15: 85307592 | AS15: 94517667 | AT15: 1.0385156e+08 | AV15: 8700151 | AW15: 20978913 | AX15: 31316691 | AY15: 42022314 | AZ15: 42335507 | BA15: 63874326 | BB15: 75093182 | BC15: 86591723 | BD15: 98022503 | BE15: 109780628 | BF15: 121601922 | BG15: 191240845 | BI15: 17384873 | BJ15: 34950016 | BK15: 52834555 | BL15: 70826589 | BM15: 89009669 | BN15: 107341399 | BO15: 125787133 | BP15: 144419593 | BQ15: 163366879 | BR15: 182412006 | BS15: 201285389 | BT15: 221890962
B16: Other Financial Expense | D16: 1304560 | F16: 1384622 | H16: 98654 | P16: 0 | Q16: 0 | R16: 0 | S16: 0 | U16: 2621710 | V16: 0 | W16: 0 | X16: 0 | Y16: 0 | Z16: 0 | AA16: 0 | AB16: 0 | AC16: 0 | AD16: 0 | AE16: 0 | AH16: =18589967 -> 18589967 | AI16: 808221 | AJ16: 1006042 | AK16: 0 | AL16: 0 | AM16: 0 | AN16: 0 | AP16: 0 | AQ16: 0 | AR16: 0 | AS16: 0 | AT16: 0 | AU16: =3497 -> 3497 | AV16: 0 | AW16: 0 | AX16: 0 | AY16: 0 | AZ16: 0 | BA16: 0 | BB16: 0 | BC16: 0 | BD16: 0 | BE16: 0 | BF16: 0 | BG16: 0 | BI16: 0 | BJ16: 0 | BK16: 0 | BL16: 0 | BM16: 0 | BN16: 0 | BO16: 0 | BP16: 0 | BQ16: 0 | BR16: 0 | BS16: 0 | BT16: 0
B17: Fees & Commission Expense | D17: 806540 | E17: 730212 | F17: 936547 | H17: 104327 | I17: 1595388 | J17: 2392023 | K17: 3202974 | L17: 4002073 | M17: 4766366 | N17: 5479326.2 | O17: 6529708 | P17: 6913706 | Q17: 7758743 | R17: 8520442 | S17: 9374086 | V17: 818250 | W17: 1602578 | X17: 2334587 | Y17: 3329836 | Z17: 4154591 | AA17: 4996955 | AB17: 5829917 | AC17: 6754209 | AD17: 6754209 | AE17: 7718718 | AF17: 8473968 | AG17: 8797903 | AI17: 706839 | AJ17: 988329 | AK17: 2566719 | AL17: 3264937 | AM17: 3503536 | AN17: 4064576 | AP17: 5242652 | AQ17: 6337788 | AR17: 6460009 | AS17: 6058704 | AT17: 7718338 | AV17: 769323 | AW17: 1371323 | AX17: 1371323 | AY17: 2335500 | AZ17: 2911097 | BA17: 3508049 | BB17: 4665477 | BC17: 5446113 | BD17: 6175443 | BE17: 6258199 | BF17: 6047217 | BG17: 7212501 | BI17: 670274 | BJ17: 1365286 | BK17: 2133698 | BL17: 2426198 | BM17: 3101920 | BN17: 4412610 | BO17: 5328164 | BP17: 4824262 | BQ17: 4868826 | BR17: 6011436 | BS17: 6097152 | BT17: 6688462
B18: Other Expense | I18: 3737078 | J18: 7189341 | K18: 15358163 | L18: 17233635 | M18: 26033913 | N18: 28289254 | O18: 32909932 | P18: 42959968 | Q18: 45070910 | R18: 47464509 | S18: 61556414 | V18: 12815273 | W18: 16824590 | X18: 27051721 | Y18: 30246448 | Z18: 33855213 | AA18: 37797449 | AB18: 46043040 | AC18: 47241421 | AD18: 62382928 | AE18: 65429103 | AF18: 67693100 | AG18: 87459200 | AI18: 0 | AJ18: 0 | AV18: 0 | AW18: 0 | AX18: 0 | AY18: 0 | AZ18: 0 | BA18: 0 | BB18: 0 | BC18: 0 | BD18: 0 | BE18: 0 | BF18: 0 | BG18: 0 | BI18: 0 | BJ18: 0 | BK18: 0 | BL18: 0 | BM18: 0 | BN18: 0 | BO18: 0 | BP18: 0 | BQ18: 0 | BR18: 0 | BS18: 0 | BT18: 0
B19: Net Financial Income/(Loss) | D19: =D3-D12 -> 274758054 | E19: =E3-E12 -> 468542697 | F19: =F3-F12 -> 608494525 | G19: =G3-G12 -> 640160264 | H19: =H3-H12 -> 111443426 | I19: =I3-I12 -> 95228235 | J19: =J3-J12 -> 138379192 | K19: =K3-K12 -> 199459939 | ... BU19: =BU3-BU12 -> 1011494000
B20: Allowance for Loan Loss | D20: =D21+D22 -> 36806523 | E20: =E21+E22 -> 40642542 | F20: =F21+F22 -> 18328456 | G20: =G21-G22 -> 66035226 | H20: =H21+H22 -> 1987245 | I20: =I21-I22 -> 10903573 | J20: =J21-J22 -> 16122028 | K20: =K21-K22 -> -16510882 | L20: =L21-L22 -> -5651246 | M20: =M21-M22 -> 9266242 | N20: =N21-N22 -> -18796890 | O20: =O21-O22 -> -8429948 | P20: =P21-P22 -> 12436509 | ... BU20: =BU21-BU22 -> -101404000
B21: Provision for Loan Losses | D21: 36806523 | E21: 40642542 | F21: 18328456 | G21: 66035226 | H21: 1987245 | I21: 10903573 | J21: 16122028 | K21: -16510882 | L21: -5651246 | M21: 9266242 | N21: -18796890 | O21: -8429948 | P21: 12436509 | Q21: 10265333 | R21: 20010490 | S21: 81720821 | T21: =13628428 -> 13628428 | U21: 148990933 | V21: 0 | W21: 0 | X21: 0 | Y21: 0 | Z21: 0 | AA21: 0 | AB21: 0 | AC21: 0 | AD21: 30665069 | AE21: 26525556 | AF21: 35084078 | AG21: 49697840 | AH21: 22064915 | AI21: 9778427 | AJ21: 18245749 | AK21: 7024907 | AL21: 39873533 | AM21: 37481310 | AN21: 67698889 | AP21: 72917070 | AQ21: 173928001 | AR21: 101476469 | AS21: 58350572 | AT21: 104513273 | AU21: 104513 | AV21: 16696078 | AW21: 0 | AX21: 0 | AY21: 0 | AZ21: 0 | BA21: 0 | BB21: 0 | BC21: 0 | BD21: 0 | BE21: 0 | BF21: 0 | BG21: 0 | BH21: 541988824 | BI21: 0 | BJ21: 0 | BK21: 0 | BL21: 0 | BM21: 0 | BN21: 0 | BO21: 0 | BP21: 0 | BQ21: 0 | BR21: 0 | BS21: 0 | BT21: 0 | BU21: -101404000
B22: Value of Loans Recovered | I22: 0 | Q22: 0 | R22: 0 | S22: 0 | V22: 0 | W22: 0 | X22: 0 | Y22: 0 | Z22: 0 | AA22: 0 | AB22: 0 | AC22: 0 | AD22: 0 | AE22: 0 | AI22: 0 | AJ22: 0 | AK22: 0 | AL22: 0 | AM22: 0 | AN22: 0 | AP22: 0 | AQ22: 0 | AR22: 0 | AS22: 0 | AT22: 0 | AV22: 0 | AW22: 0 | AX22: 0 | AY22: 0 | AZ22: 0 | BA22: 0 | BB22: 0 | BC22: 0 | BD22: 0 | BE22: 0 | BF22: 0 | BG22: 0 | BI22: 0 | BJ22: 0 | BK22: 0 | BL22: 0 | BM22: 0 | BN22: 0 | BO22: 0 | BP22: 0 | BQ22: 0 | BR22: 0 | BS22: 0 | BT22: 0
B23: Operating Expenses | D23: =SUM(D24:D28) -> 202791555 | E23: =SUM(E24:E28) -> 206012139 | F23: =SUM(F24:F28) -> 301548982 | G23: =SUM(G24:G28) -> 224824612 | H23: =SUM(H24:H28) -> 37500031 | I23: =SUM(I24:I28) -> 31164165 | J23: =SUM(J24:J28) -> 45319473 | K23: =SUM(K24:K28) -> 63726245 | ... BU23: =SUM(BU24:BU28) -> 423657000
B24: Personnel Expenses | D24: 97671925 | E24: 105681103 | F24: 184493557 | G24: 57781248 | H24: 26419186 | I24: 8816158 | J24: 13036709 | K24: 17261115 | L24: 25814697 | M24: 30734994 | N24: 35632272 | O24: 39984697 | P24: 44487961 | Q24: 49700905 | R24: 54399657 | S24: 62489155 | T24: =68094770 -> 68094770 | U24: 76662549 | V24: 6713106 | W24: 12561889 | X24: 19014721 | Y24: 31854031 | Z24: 39545848 | AA24: 46690091 | AB24: 53715627 | AC24: 59399927 | AD24: 67023808 | AE24: 74384328 | AF24: 81022361 | AG24: 90230431 | AH24: 91848011 | AI24: 23475514 | AJ24: 46946676 | AK24: 17599873 | AL24: 34317677 | AM24: 41624371 | AN24: 45631546 | AP24: 57063583 | AQ24: 62702314 | AR24: 70699556 | AS24: 78183551 | AT24: 86363895 | AU24: =30447+9980+2691+2011+6000+4303+982+11957+10425+6205+3193+408+3762 -> 92364 | AV24: 5064945 | AW24: 12341880 | AX24: 18908077 | AY24: 37221654 | AZ24: 43999211 | BA24: 49412239 | BB24: 56393780 | BC24: 63366451 | BD24: 71101272 | BE24: 80452114 | BF24: 89525370 | BG24: 120222573 | BH24: 1.2022237e+08 | BI24: 6641482 | BJ24: 13228297 | BK24: 23631838 | BL24: 48338977 | BM24: 57692089 | BN24: 68160247 | BO24: 77233464 | BP24: 83967265 | BQ24: 90092911 | BR24: 97339224 | BS24: 104360774 | BT24: 114683097 | BU24: 136094000
B25: Governance Expenses | D25: 13566600 | E25: 14672808 | F25: 17845321 | G25: 40827606 | H25: 985300 | I25: 13555729 | J25: 19133395 | K25: 30223955 | L25: 32210640 | M25: 36157566 | N25: 38568996 | O25: 41795926 | P25: 49889678 | Q25: 52559148 | R25: 56144063 | S25: 61349928 | T25: =43709999 -> 43709999 | U25: 58102205 | V25: 7395865 | W25: 13477375 | X25: 33249915 | Y25: 43457386 | Z25: 48705332 | AA25: 53087339 | AB25: 60772179 | AC25: 63211269 | AD25: 72805009 | AE25: 77613541 | AF25: 81718851 | AG25: 87321631 | AH25: =59659971 -> 59659971 | AI25: 570000 | AJ25: 1186023 | AK25: 24653069 | AL25: 26087399 | AM25: 27771749 | AN25: 29169299 | AP25: 33640760 | AQ25: 39215580 | AR25: 42443175 | AS25: 51354028 | AT25: 58325128 | AU25: =21026+20006+3550+1663+868 -> 47113 | AV25: 4905455 | AW25: 22473259 | AX25: 27167531 | AY25: 36728305 | AZ25: 39895027 | BA25: 43583447 | BB25: 46461917 | BC25: 49061632 | BD25: 52188357 | BE25: 57242407 | BF25: 61068675 | BG25: 74088340 | BH25: 59688740 | BI25: 10931781 | BJ25: 25190392 | BK25: 40172247 | BL25: 46316427 | BM25: 49091094 | BN25: 55948543 | BO25: 63062103 | BP25: 68688039 | BQ25: 74833812 | BR25: 80007647 | BS25: 96776733 | BT25: 106099718 | BU25: 96032000
B26: Marketing Expenses | D26: 8333350 | E26: 11827454 | F26: 14836218 | G26: 17441689 | H26: 945321 | I26: 1976860 | J26: 3089860 | K26: 4618886 | L26: 5776746 | M26: 6960226 | N26: 8602226 | O26: 9668506 | P26: 10945356 | Q26: 12238106 | R26: 13505222 | S26: 15647811 | T26: =15647811 -> 15647811 | U26: 17858434 | V26: 1621900 | W26: 2810900 | X26: 4438420 | Y26: 6127908 | Z26: 7325108 | AA26: 8700961 | AB26: 9938131 | AC26: 10906891 | AD26: 11894646 | AE26: 13735646 | AF26: 15016646 | AG26: 18157536 | AH26: 18157536 | AI26: 625000 | AJ26: 885300 | AK26: 4711716 | AL26: 5239216 | AM26: 6379216 | AN26: 7679036 | AP26: 9688992 | AQ26: 12220472 | AR26: 13510972 | AS26: 16211354 | AT26: 17646354 | AU26: =6892+10755 -> 17647 | AV26: 907680 | AW26: 4570820 | AX26: 6100756 | AY26: 7010756 | AZ26: 8904856 | BA26: 10208496 | BB26: 11813496 | BC26: 14457316 | BD26: 16142027 | BE26: 17993927 | BF26: 19870427 | BG26: 22863827 | BH26: 13193068 | BI26: 2285190 | BJ26: 4040840 | BK26: 5961540 | BL26: 7663190 | BM26: 9296940 | BN26: 11608340 | BO26: 13548590 | BP26: 15605840 | BQ26: 17916069 | BR26: 19917919 | BS26: 21641519 | BT26: 25868569 | BU26: 25869000
B27: Depreciation and Amortization Charges | D27: 22457890 | E27: 26473936 | F27: 33998254 | G27: 14282307 | H27: 3187206 | I27: 1879298 | J27: 2818947 | K27: 2818947 | L27: 4698245 | M27: 5733561 | N27: 6689154.9 | O27: 7644748 | P27: 8600342 | Q27: 9582772 | R27: 10762721 | S27: 12203651 | T27: =12111887 -> 12111887 | U27: 10580426 | V27: 717954 | W27: 1485230 | X27: 2227845 | Y27: 2970459 | Z27: 4149103 | AA27: 4988516 | AB27: 6086455 | AC27: 6967065 | AD27: 7894213 | AE27: 8771348 | AF27: 9818377 | AG27: 10745927 | AH27: 12881694 | AI27: 2631006 | AJ27: 5168874 | AK27: 2246040 | AL27: 3011559 | AM27: 3764449 | AN27: 4527741 | AP27: 6377386 | AQ27: 7285709 | AR27: 8095232 | AS27: 10970795 | AT27: 10801199 | AU27: =7657+1996+3144 -> 12797 | AV27: 739912 | AW27: 1479825 | AX27: 2219737 | AY27: 2959650 | AZ27: 3699562 | BA27: 5527619 | BB27: 6448888 | BC27: 7370158 | BD27: 8291428 | BE27: 9212698 | BF27: 11376542 | BG27: 13193068 | BH27: 22863827 | BI27: 764946 | BJ27: 1529892 | BK27: 2294838 | BL27: 3059784 | BM27: 3824729 | BN27: 4589675 | BO27: 5354621 | BP27: 6119567 | BQ27: 6539349 | BR27: 8174187 | BS27: 12345030 | BT27: 14346902 | BU27: 14347000
B28: Administrative Expenses | D28: 60761790 | E28: 47356838 | F28: 50375632 | G28: 94491762 | H28: 5963018 | I28: 4936120 | J28: 7240562 | K28: 8803342 | L28: 10996813 | M28: 13205248 | N28: 17174507 | O28: 21864701 | P28: 25456430 | Q28: 27384599 | R28: 29268890 | S28: 31879455 | T28: =106447541 -> 106447541 | U28: =106447960-2621710 -> 103826250 | V28: 3640084 | W28: 7150828 | X28: 10850760 | Y28: 13294215 | Z28: 15818957 | AA28: 18519596 | AB28: 20533250 | AC28: 23363571 | AD28: 25448107 | AE28: 28473661 | AF28: 33487100 | AG28: 34996195 | AH28: =115231781 -> 115231781 | AI28: 5932542 | AJ28: 9486275 | AK28: 39294795 | AL28: 50804378 | AM28: 65058444 | AN28: 76513313 | AP28: 86392997 | AQ28: 94303253 | AR28: 100642205 | AS28: 111905244 | AT28: 125146960 | AU28: =21867+13548+11205+11154+8920+7050+6339+6133+5545+5307+4468+3000+2794+1629+806+2409 -> 112174 | AV28: 16855103 | AW28: 23376051 | AX28: 28355927 | AY28: 47261063 | AZ28: 54824357 | BA28: 77446759 | BB28: 82527505 | BC28: 90446103 | BD28: 103707182 | BE28: 109130459 | BF28: 124876441 | BG28: 152162572 | BH28: 1.2590077e+08 | BI28: 14442610 | BJ28: 30567747 | BK28: 39047857 | BL28: 60062831 | BM28: 66983967 | BN28: 93870197 | BO28: 100399119 | BP28: 106398913 | BQ28: 126710055 | BR28: 131453434 | BS28: 138532532 | BT28: 156706726 | BU28: 151315000
B29: Net Operating Income | D29: =D19-D20-D23 -> 35159976 | E29: =E19-E20-E23 -> 221888016 | F29: =F19-F20-F23 -> 288617087 | G29: =G19-G20-G23 -> 349300426 | H29: =H19-H20-H23 -> 71956150 | I29: =I19-I20-I23 -> 53160497 | J29: =J19-J20-J23 -> 76937691 | K29: =K19-K20-K23 -> 152244576 | ... BU29: =BU19-BU20-BU23 -> 689241000
B30: Net Non- Operating Income/ (Expense) | D30: =D31-D32 -> 0 | E30: =E31-E32 -> 0 | F30: =F31-F32 -> 0 | G30: =G31-G32 -> 0 | H30: =H31-H32 -> 0 | I30: =I31-I32 -> 0 | J30: =J31-J32 -> 0 | K30: =K31-K32 -> 0 | ... BU30: =BU31-BU32 -> 0
B31: Non- Operating Income | P31: 0 | Q31: 0 | S31: 0 | U31: 0 | AV31: 0 | AW31: 0 | AX31: 0 | AY31: 0 | AZ31: 0 | BA31: 0 | BB31: 0 | BC31: 0 | BD31: 0 | BE31: 0 | BF31: 0 | BG31: 0 | BH31: 0 | BI31: 0 | BJ31: 0 | BK31: 0 | BL31: 0 | BM31: 0 | BN31: 0 | BO31: 0 | BP31: 0 | BQ31: 0 | BR31: 0 | BS31: 0 | BT31: 0
B32: Non- Operating Expense | P32: 0 | Q32: 0 | S32: 0 | U32: 0 | AV32: 0 | AW32: 0 | AX32: 0 | AY32: 0 | AZ32: 0 | BA32: 0 | BB32: 0 | BC32: 0 | BD32: 0 | BE32: 0 | BF32: 0 | BG32: 0 | BH32: 0 | BI32: 0 | BJ32: 0 | BK32: 0 | BL32: 0 | BM32: 0 | BN32: 0 | BO32: 0 | BP32: 0 | BQ32: 0 | BR32: 0 | BS32: 0 | BT32: 0
B33: Net Income (Before Taxes and Donations) | D33: =D29+D30 -> 35159976 | E33: =E29+E30 -> 221888016 | F33: =F29+F30 -> 288617087 | G33: =G29+G30 -> 349300426 | H33: =H29+H30 -> 71956150 | I33: =I29+I30 -> 53160497 | J33: =J29+J30 -> 76937691 | K33: =K29+K30 -> 152244576 | ... BU33: =BU29+BU30 -> 689241000
B34: Taxes (Incomes taxes & Other payable to KRA) | D34: 3999264 | E34: 4042106 | F34: 6184653 | G34: 21494280 | H34: 2103187 | T34: =25007266 -> 25007266 | U34: 19903737 | AH34: 24114857 | AI34: 1621799 | AJ34: 3500940 | AU34: 28143 | AV34: 0 | AW34: 0 | AX34: 0 | AY34: 0 | AZ34: 0 | BA34: 0 | BB34: 0 | BC34: 0 | BD34: 0 | BE34: 0 | BF34: 0 | BG34: 0 | BH34: 47874205 | BI34: 0 | BJ34: 0 | BK34: 0 | BL34: 0 | BM34: 0 | BN34: 0 | BO34: 0 | BP34: 0 | BQ34: 0 | BR34: 0 | BS34: 0 | BT34: 0
B35: Net Income (After Taxes before Donations) | D35: =D33-D34 -> 31160712 | E35: =E33-E34 -> 217845910 | F35: =F33-F34 -> 282432434 | G35: =G33-G34 -> 327806146 | H35: =H33-H34 -> 69852963 | I35: =I33-I34 -> 53160497 | J35: =J33-J34 -> 76937691 | K35: =K33-K34 -> 152244576 | ... BU35: =BU33-BU34 -> 689241000
B36: Donations | D36: 240000 | F36: 330000 | H36: 100000 | AV36: 0 | AW36: 0 | AX36: 0 | AY36: 0 | AZ36: 0 | BA36: 0 | BB36: 0 | BC36: 0 | BD36: 0 | BE36: 0 | BF36: 0 | BG36: 0 | BH36: 0 | BI36: 0 | BJ36: 0 | BK36: 0 | BL36: 0 | BM36: 0 | BN36: 0 | BO36: 0 | BP36: 0 | BQ36: 0 | BR36: 0 | BS36: 0 | BT36: 0
B37: Net Income/(After Taxes and Donations) | D37: =D35-D36 -> 30920712 | E37: =E35-E36 -> 217845910 | F37: =F35-F36 -> 282102434 | G37: =G35+G36 -> 327806146 | H37: =H35-H36 -> 69752963 | I37: =I35+I36 -> 53160497 | J37: =J35+J36 -> 76937691 | K37: =K35+K36 -> 152244576 | L37: =L35+L36 -> 1.7711605e+08 | M37: =M35+M36 -> 199894826 | N37: =N35+N36 -> 2.589779e+08 | O37: =O35+O36 -> 2.8747081e+08 | P37: =P35+P36 -> 293289697 | ... BU37: =BU35+BU36 -> 689241000
BU38: =BU37-689241000 -> 0
BU40: =67.8+49.5+110.3+55.3+12+11+2.7 -> 308.6

Sheet Form 4
B4: RISK CLASSIFICATION OF ASSETS AND PROVISIONING | K4: RISK CLASSIFICATION OF ASSETS AND PROVISIONING
B5: SACCO SOCIETY CS NUMBER | F5: 2738 | K5: SACCO SOCIETY CS NUMBER | O5: 2738
B6: FINANCIAL YEAR | F6: 2019 | K6: FINANCIAL YEAR | O6: 2019
B7: START DATE: | F7: 1/1/2019 | K7: START DATE: | O7: 1/1/2019
B8: END DATE: | F8: 31/3/2019 | K8: END DATE: | O8: 30/6/2019
B9: PORTFOLIO AGEING REPORT | K9: PORTFOLIO AGEING REPORT
C10: A | D10: B | E10: C | F10: D | L10: A | M10: B | N10: C | O10: D
A11: NO. | B11: CLASSIFICATION | C11: NO. OF A/Cs | D11: OUTSTANDING LOAN PORTFOLIO(Kshs) | E11: REQUIRED PROVISION | F11: REQUIRED PROVISION AMOUNT(Kshs) | J11: NO. | K11: CLASSIFICATION | L11: NO. OF A/Cs | M11: OUTSTANDING LOAN PORTFOLIO(Kshs) | N11: REQUIRED PROVISION | O11: REQUIRED PROVISION AMOUNT(Kshs)
A12: 1 | B12: Performing | C12: 39313 | D12: 6.4701408e+09 | E12: 0.01 | F12: =D12*E12 -> 64701408 | J12: 1 | K12: Performing | L12: 33990 | M12: 6.2422556e+09 | N12: 0.01 | O12: =M12*N12 -> 62422556
A13: 2 | B13: Watch | C13: 477 | D13: 78941396 | E13: 0.05 | F13: =D13*E13 -> 3947069.8 | J13: 2 | K13: Watch | L13: 790 | M13: 88457902 | N13: 0.05 | O13: =M13*N13 -> 4422895.1
A14: 3 | B14: Substandard | C14: 792 | D14: 1.2330688e+08 | E14: 0.25 | F14: =D14*E14 -> 30826721 | J14: 3 | K14: Substandard | L14: 364 | M14: 55170030 | N14: 0.25 | O14: =M14*N14 -> 13792507
A15: 4 | B15: Doubtful | C15: 1182 | D15: 1.7546175e+08 | E15: 0.5 | F15: =D15*E15 -> 87730876 | J15: 4 | K15: Doubtful | L15: 704 | M15: 1.3610175e+08 | N15: 0.5 | O15: =M15*N15 -> 68050876
A16: 5 | B16: Loss | C16: 981 | D16: 1.9272321e+08 | E16: 1 | F16: =D16*E16 -> 1.9272321e+08 | J16: 5 | K16: Loss | L16: 1285 | M16: 2.4897878e+08 | N16: 1 | O16: =M16*N16 -> 2.4897878e+08
B17: subtotal | C17: =SUM(C12:C16) -> 42745 | D17: =SUM(D12:D16) -> 7.0405741e+09 | F17: =SUM(F12:F16) -> 3.7992928e+08 | K17: subtotal | L17: =SUM(L12:L16) -> 37133 | M17: =SUM(M12:M16) -> 6.7709641e+09 | O17: =SUM(O12:O16) -> 3.9766762e+08
B18: Reschedule/Renegotiated loans | K18: Reschedule/Renegotiated loans
A19: 1 | B19: Performing | C19: 0 | E19: 0.01 | F19: =D19*E19 -> 0 | J19: 1 | K19: Performing | L19: 0 | N19: 0.01 | O19: =M19*N19 -> 0
A20: 2 | B20: Watch | C20: 0 | E20: 0.05 | F20: =D20*E20 -> 0 | J20: 2 | K20: Watch | L20: 0 | N20: 0.05 | O20: =M20*N20 -> 0
A21: 3 | B21: Substandard | C21: 0 | E21: 0.25 | F21: =D21*E21 -> 0 | J21: 3 | K21: Substandard | L21: 0 | N21: 0.25 | O21: =M21*N21 -> 0
A22: 4 | B22: Doubtful | C22: 0 | E22: 0.5 | F22: =D22*E22 -> 0 | J22: 4 | K22: Doubtful | L22: 0 | N22: 0.5 | O22: =M22*N22 -> 0
A23: 5 | B23: Loss | C23: 0 | E23: 1 | F23: =D23*E23 -> 0 | J23: 5 | K23: Loss | L23: 0 | N23: 1 | O23: =M23*N23 -> 0
B24: subtotal | C24: =SUM(C18:C23) -> 0 | D24: =SUM(D18:D23) -> 0 | F24: =SUM(F18:F23) -> 0 | K24: subtotal | L24: =SUM(L18:L23) -> 0 | M24: =SUM(M18:M23) -> 0 | O24: =SUM(O18:O23) -> 0
B25: GRAND TOTAL | C25: =C17+C24 -> 42745 | D25: =D17+D24 -> 7.0405741e+09 | F25: =F17+F24 -> 3.7992928e+08 | K25: GRAND TOTAL | L25: =L17+L24 -> 37133 | M25: =M17+M24 -> 6.7709641e+09 | O25: =O17+O24 -> 3.9766762e+08
D27: =D14+D15+D16 -> 4.9149184e+08 | M27: =M14+M15+M16 -> 4.4025057e+08
D28: =D27/D25 -> 0.06980849 | M28: =M27/M25 -> 0.065020366
B30: RISK CLASSIFICATION OF ASSETS AND PROVISIONING | K30: RISK CLASSIFICATION OF ASSETS AND PROVISIONING
B31: SACCO SOCIETY CS NUMBER | F31: 2738 | K31: SACCO SOCIETY CS NUMBER | O31: 2738
B32: FINANCIAL YEAR | F32: 2019 | K32: FINANCIAL YEAR | O32: 2019
B33: START DATE: | F33: 1/1/2019 | K33: START DATE: | O33: 1/1/2019
B34: END DATE: | F34: 30/9/2019 | K34: END DATE: | O34: 31/12/2019
B35: PORTFOLIO AGEING REPORT | K35: PORTFOLIO AGEING REPORT
C36: A | D36: B | E36: C | F36: D | L36: A | M36: B | N36: C | O36: D
A37: NO. | B37: CLASSIFICATION | C37: NO. OF A/Cs | D37: OUTSTANDING LOAN PORTFOLIO(Kshs) | E37: REQUIRED PROVISION | F37: REQUIRED PROVISION AMOUNT(Kshs) | J37: NO. | K37: CLASSIFICATION | L37: NO. OF A/Cs | M37: OUTSTANDING LOAN PORTFOLIO(Kshs) | N37: REQUIRED PROVISION | O37: REQUIRED PROVISION AMOUNT(Kshs)
A38: 1 | B38: Performing | C38: 32415 | D38: 6.1290383e+09 | E38: 0.01 | F38: =D38*E38 -> 61290383 | J38: 1 | K38: Performing | M38: 5.9966473e+09 | N38: 0.01 | O38: =M38*N38 -> 59966473
A39: 2 | B39: Watch | C39: 1116 | D39: 1.1632609e+08 | E39: 0.05 | F39: =D39*E39 -> 5816304.3 | J39: 2 | K39: Watch | M39: 318860630 | N39: 0.05 | O39: =M39*N39 -> 15943032
A40: 3 | B40: Substandard | C40: 796 | D40: 96064119 | E40: 0.25 | F40: =D40*E40 -> 24016030 | J40: 3 | K40: Substandard | M40: 43839021 | N40: 0.25 | O40: =M40*N40 -> 10959755
A41: 4 | B41: Doubtful | C41: 800 | D41: 1.273539e+08 | E41: 0.5 | F41: =D41*E41 -> 63676948 | J41: 4 | K41: Doubtful | M41: 1.3651084e+08 | N41: 0.5 | O41: =M41*N41 -> 68255420
A42: 5 | B42: Loss | C42: 1618 | D42: 2.9127584e+08 | E42: 1 | F42: =D42*E42 -> 2.9127584e+08 | J42: 5 | K42: Loss | M42: 3.099836e+08 | N42: 1 | O42: =M42*N42 -> 3.099836e+08
B43: subtotal | C43: =SUM(C38:C42) -> 36745 | D43: =SUM(D38:D42) -> 6.7600583e+09 | F43: =SUM(F38:F42) -> 4.4607551e+08 | K43: subtotal | L43: =SUM(L38:L42) -> 0 | M43: =SUM(M38:M42) -> 6.8058414e+09 | O43: =SUM(O38:O42) -> 4.6510828e+08
B44: Reschedule/Renegotiated loans | K44: Reschedule/Renegotiated loans
A45: 1 | B45: Performing | C45: 0 | E45: 0.01 | F45: =D45*E45 -> 0 | J45: 1 | K45: Performing | L45: 0 | N45: 0.01 | O45: =M45*N45 -> 0
A46: 2 | B46: Watch | C46: 0 | E46: 0.05 | F46: =D46*E46 -> 0 | J46: 2 | K46: Watch | L46: 0 | N46: 0.05 | O46: =M46*N46 -> 0
A47: 3 | B47: Substandard | C47: 0 | E47: 0.25 | F47: =D47*E47 -> 0 | J47: 3 | K47: Substandard | L47: 0 | N47: 0.25 | O47: =M47*N47 -> 0
A48: 4 | B48: Doubtful | C48: 0 | E48: 0.5 | F48: =D48*E48 -> 0 | J48: 4 | K48: Doubtful | L48: 0 | N48: 0.5 | O48: =M48*N48 -> 0
A49: 5 | B49: Loss | C49: 0 | E49: 1 | F49: =D49*E49 -> 0 | J49: 5 | K49: Loss | L49: 0 | N49: 1 | O49: =M49*N49 -> 0
B50: subtotal | C50: =SUM(C44:C49) -> 0 | D50: =SUM(D44:D49) -> 0 | F50: =SUM(F44:F49) -> 0 | K50: subtotal | L50: =SUM(L44:L49) -> 0 | M50: =SUM(M44:M49) -> 0 | O50: =SUM(O44:O49) -> 0
B51: GRAND TOTAL | C51: =C43+C50 -> 36745 | D51: =D43+D50 -> 6.7600583e+09 | F51: =F43+F50 -> 4.4607551e+08 | K51: GRAND TOTAL | L51: =L43+L50 -> 0 | M51: =M43+M50 -> 6.8058414e+09 | O51: =O43+O50 -> 4.6510828e+08
D53: =D40+D41+D42 -> 5.1469386e+08 | M53: =M40+M41+M42 -> 4.9033346e+08
D54: =D53/D51 -> 0.076137488 | M54: =M53/M51 -> 0.072045972
M58: Aud-2022
K59: RISK CLASSIFICATION OF ASSETS AND PROVISIONING
L60: A | M60: B | N60: C | O60: D
J61: NO. | K61: CLASSIFICATION | L61: NO. OF A/Cs | M61: OUTSTANDING LOAN PORTFOLIO(Kshs) | N61: REQUIRED PROVISION | O61: REQUIRED PROVISION AMOUNT(Kshs)
J62: 1 | K62: Performing | M62: 8788508000 | N62: 0.01 | O62: =M62*N62 -> 87885080
J63: 2 | K63: Watch | M63: 222498000 | N63: 0.05 | O63: =M63*N63 -> 11124900
J64: 3 | K64: Substandard | M64: 137553000 | N64: 0.25 | O64: =M64*N64 -> 34388250
J65: 4 | K65: Doubtful | M65: 54082000 | N65: 0.5 | O65: =M65*N65 -> 27041000
J66: 5 | K66: Loss | M66: 312688000 | N66: 1 | O66: =M66*N66 -> 312688000
K67: subtotal | L67: =SUM(L62:L66) -> 0 | M67: =SUM(M62:M66) -> 9515329000 | O67: =SUM(O62:O66) -> 473127230
K68: Reschedule/Renegotiated loans
J69: 1 | K69: Performing | L69: 0 | N69: 0.01 | O69: =M69*N69 -> 0
J70: 2 | K70: Watch | L70: 0 | N70: 0.05 | O70: =M70*N70 -> 0
J71: 3 | K71: Substandard | L71: 0 | N71: 0.25 | O71: =M71*N71 -> 0
J72: 4 | K72: Doubtful | L72: 0 | N72: 0.5 | O72: =M72*N72 -> 0
J73: 5 | K73: Loss | L73: 0 | N73: 1 | O73: =M73*N73 -> 0
K74: subtotal | L74: =SUM(L68:L73) -> 0 | M74: =SUM(M68:M73) -> 0 | O74: =SUM(O68:O73) -> 0
K75: GRAND TOTAL | L75: =L67+L74 -> 0 | M75: =M67+M74 -> 9515329000 | O75: =O67+O74 -> 473127230
M79: =M66+M65+M64 -> 504323000
M80: =M79/M75 -> 0.05300111

Sheet DEC REPORT
A1: INVEST & GROW (IG) SACCO SOCIETY LIMITED
A2: PERFORMANCE AND COMPLIANCE REPORT AS AT : 31st December , 2020
B3: Prudential Standard | C3: Audited | D3: Returns | F3: AUDITED 2020 | G3: Aggregate for all Licensed Saccos
C4: 2019 | D4: 30th September , 2020 | E4: 31st December , 2020
A5: A. CAPITAL ADEQUACY
A6: Core Capital | B6: ≥10M | C6: 2617751466 | D6: 2690338040 | E6: 2786049857 | F6: =F33 -> 3680360 | G6: 9.3691213e+10
A7: Core Capital/Total Assets | B7: ≥10% | C7: 0.27599343 | D7: 0.26763564 | E7: 0.26342377 | F7: =F33/F29 -> 0.35124206 | G7: 0.15861451
A8: Institutional Capital/Total Assets | B8: ≥8% | C8: 0.19070699 | D8: 0.17481459 | E8: 0.17345389 | F8: =F34/F29 -> 0.2604292 | G8: 0.092981557
A9: B. ASSET QUALITY
A10: NPL (Substandard+Doubtful+Loss) | B10: <5% | C10: 0 | D10: 0.097096672 | E10: 0.072182375 | F10: =F35/F32 -> 0.071737732 | G10: 0.081142074
A11: Non-Earning Assets | B11: <10% | C11: 0.043802668 | D11: 0.049797141 | E11: 0.045698486 | F11: =F36/F29 -> 0.054465825 | G11: 0.10306874
A12: Equity investments/Deposits | B12: <5% | C12: 0.10311199 | D12: 0.1024603 | E12: 0.10072361 | F12: =F38/F31 -> 0.086325358 | G12: 0.033654976
A13: Equity investments/Core capital | B13: <40% | C13: 0.20992763 | D13: 0.22416304 | E13: 0.21646216 | F13: =F38/F33 -> 0.14043898 | G13: 0.14556657
A14: C. EARNINGS RATING
A15: Yield on Gross Loans | C15: 0.18644345 | D15: 0.1311637 | E15: 0.16846237 | F15: =F48/F32 -> 0.16742507 | G15: 0.17277563
A16: Total Expense/Total Income | C16: 0.63498147 | D16: 0.82530017 | E16: 0.81411893 | F16: =F49/F44 -> 0.71890192 | G16: 0.69938821
A17: Net Income/Average Assets (ROA) | C17: 0.052168654 | D17: 0.00034173056 | E17: 0.015801202 | F17: =F50/F30 -> 7.755702e-05 | G17: 0.038235463
A18: Operating Expenses/Financial Income (OPEX) | C18: 0.20866009 | D18: 0.21266921 | E18: 0.21154392 | F18: =F47/F44 -> 0.20006298 | G18: 0.30079837
A19: D. LIQUIDITY
A20: Liquid Assets/Short-term Liabilities | B20: >15% | C20: 1.1490475 | D20: 1.347341 | E20: 1.2176719 | F20: =F40/F41 -> 1.4659018 | G20: 0.62089206
A21: External Borrowing/Total Assets | B21: <25% | C21: 0 | D21: 0 | E21: 0 | F21: =F42/F29 -> 0 | G21: 0.036253819
A22: Liquid Assets/Total Assets | C22: 0.08217946 | D22: 0.19647703 | E22: 0.19686563 | F22: =F40/F29 -> 0.22470479 | G22: 0.11763884
A23: E. STRUCTURE/SENSITIVITY TO RISK
A24: Gross loans /Total Assets | B24: 70-80 | C24: 0.71754997 | D24: 0.68321546 | E24: 0.68353511 | F24: =F32/F29 -> 0.69421414 | G24: 0.75577804
A25: Gross loans/Deposits | B25: >100% | C25: 1.2770061 | D25: 1.166824 | E25: 1.2074111 | F25: =F32/F31 -> 1.214892 | G25: 1.1016383
A26: Financial Investments/Total Assets | C26: 0.28549372 | D26: 0.15633733 | E26: 0.14618925 | F26: =F39/F29 -> 0.075307999 | G26: 0.066695359
A27: Dividends+Interest on Deposits/Total Income | C27: 0.40531824 | D27: 0.60638301 | E27: 0.59710113 | F27: =F46/F44 -> 0.44223779 | G27: 0.33833569
A28: F. KEY FINANCIAL STATISTICS | C28: 2015 | D28: 2016 | E28: 2017 | G28: AGGREGATE
A29: Total Assets | C29: 9484832591 | D29: 10052241398 | E29: 10576303931 | F29: =SFP!AV27 -> 10478130 | G29: 5.9068501e+11
A30: Average Assets | C30: 9.1000717e+09 | D30: 9.6097993e+09 | E30: 9972965241 | F30: =(F29+C29)/2 -> 4.7476554e+09 | G30: 5.7226818e+11
A31: Total Deposits | C31: 5329529382 | D31: 5885931833 | E31: 5987418090 | F31: =SFP!AV32 -> 5987418 | G31: 4.0523898e+11
A32: Gross Loans | C32: 6805841374 | D32: 6867846697 | E32: 7229275042 | F32: =SFP!AV15 -> 7274066 | G32: 4.4642676e+11
A33: Core Capital | C33: 2617751466 | D33: 2690338040 | E33: 2786049857 | F33: =Financials!AD13 -> 3680360 | G33: 9.3691213e+10
A34: Institutional Capital | C34: 1808823837 | D34: 1757278420 | E34: 1834501058 | F34: =Financials!AD14 -> 2728811 | G34: 5.4922811e+10
A35: Non-performing Loans | C35: 0 | D35: 6.6684506e+08 | E35: 5.2182624e+08 | F35: =66481+104376+350968 -> 521825 | G35: 3.6223993e+10
A36: Non-Earning Assets | C36: 415460971 | D36: 500572883 | E36: 483321073 | F36: =Financials!AD38 -> 570700 | G36: 6.0881157e+10
A37: Property and Equipment | C37: 46090986 | D37: 38810445 | E37: 50583196 | F37: =Financials!AD39 -> 137151 | G37: 1.7541925e+10
A38: Equity Investments | C38: 549538367 | D38: 603074365 | E38: 603074365 | F38: =SFP!AV12+SFP!AV13 -> 516866 | G38: 1.3638308e+10
A39: Financial Investments | C39: 1521547182 | D39: 920190865 | E39: 875296140 | F39: =SFP!AV8 -> 789087 | G39: 2.7027559e+10
A40: Liquid Assets | C40: 779458417 | D40: 1975034505 | E40: 2082110709 | F40: =SFP!AV4+SFP!AV11 -> 2354486 | G40: 6.9487501e+10
A41: Short-term Liabilities) | C41: 678351797 | D41: 1.4658757e+09 | E41: 1.709911e+09 | F41: =SFP!AV29+SFP!AV30+SFP!AV33-SFP!AV39 -> 1606169 | G41: 1.1191559e+11
A42: External Borrowing | C42: 0 | D42: 0 | E42: 0 | F42: =SFP!AV39 -> 0 | G42: 2.1414587e+10
A43: Average Gross Loans | C43: 6.9784214e+09 | D43: 6.8139525e+09 | E43: 7017558208 | F43: =(C32+F32)/2 -> 3406557720 | G43: 4.3344033e+11
A44: Total Income | C44: 1427100855 | D44: 1014379689 | E44: 1410031215 | F44: =SCI!AU3 -> 1410031 | G44: 8.9459919e+10
A45: Net Financial Income/Loss | C45: 818697253 | D45: 3.9293929e+08 | E45: 5.6038165e+08 | F45: =SCI!AU19 -> 782965 | G45: 5.3897612e+10
A46: Dividends+Interest on Deposits | C46: 578430008 | D46: 6.1510261e+08 | E46: 8.4193123e+08 | F46: =SCI!AU13 -> 623569 | G46: 3.0267483e+10
A47: Operating Expenses | C47: 297778993 | D47: 215727328 | E47: 298283536 | F47: =SCI!AU23 -> 282095 | G47: 2.6909398e+10
A48: Interest on Loan portfolio+Fees&Commission on Loan | C48: 1268904530 | D48: 900812162 | E48: 1217860781 | F48: =SCI!AU4 -> 1217861 | G48: 7.7131665e+10
A49: Total Expenses | C49: 906182595 | D49: 8.3716773e+08 | E49: 1.1479331e+09 | F49: =SCI!AU12+SCI!AU20+SCI!AU23 -> 1013674 | G49: 6.2567213e+10
A50: Net Income | C50: 474738488 | D50: 3283962.1 | E50: 1.5758484e+08 | F50: =SCI!AU37 -> 368214 | G50: 2.1880939e+10
A51: G. AREAS OF IMPROVEMENT/REGULATORY CONCERNS
A52: 1
A53: 2
A54: 3
A55: 4
A56: Prepared by:
A58: Checked by:
A60: Approved by:
A62: DISCLAIMER: This report is prepared based on information submitted by the Sacco as at the stated date and may change upon verification by the Authority.

Sheet Expenditure Analysis
C3: 2013 | D3: 2014 | E3: 2015 | F3: 2016 | G3: 2017 | H3: 43101 | I3: 43132 | J3: 43160 | K3: 43191 | L3: 43221 | M3: 43252 | N3: 43282 | O3: 43313 | P3: 43344
B4: FINANCIAL INCOME | C4: 676832181 | D4: 946830578 | E4: 1227499577 | F4: 1143452459 | G4: 1341798042 | H4: 111748333 | I4: 231152913 | J4: 350478980 | K4: 468699233 | L4: 582634997 | M4: 709048044 | N4: 822328328 | O4: 949281415 | P4: 1078093939
B6: OPERATING EXPENSES | C6: =SUM(C7:C11) -> 202791555 | D6: =SUM(D7:D11) -> 206012139 | E6: =SUM(E7:E11) -> 301548982 | F6: =SUM(F7:F11) -> 224824612 | G6: =SUM(G7:G11) -> 246012008 | H6: =SUM(H7:H11) -> 21167855 | I6: =SUM(I7:I11) -> 36719246 | J6: =SUM(J7:J11) -> 51888119 | ... P6: =SUM(P7:P11) -> 167498573
B7: Personnel Expenses | C7: 97671925 | D7: 105681103 | E7: 184493557 | F7: 57781248 | G7: =68094770 -> 68094770 | H7: 4444252 | I7: 8773301 | J7: 13392582 | K7: 17607423 | L7: 28810989 | M7: 38252636 | N7: 43409915 | O7: 50004706 | P7: 55009025
B8: Governance Expenses | C8: 13566600 | D8: 14672808 | E8: 17845321 | F8: 40827606 | G8: =43709999 -> 43709999 | H8: 10156455 | I8: 17049410 | J8: 23225674 | K8: 39888253 | L8: 41913308 | M8: 47501288 | N8: 50665568 | O8: 56827373 | P8: 65104149
B9: Marketing Expenses | C9: 8333350 | D9: 11827454 | E9: 14836218 | F9: 17441689 | G9: =15647811 -> 15647811 | H9: 2991016 | I9: 3946016 | J9: 5586456 | K9: 7406272 | L9: 8975272 | M9: 10265272 | N9: 11898252 | O9: 13228172 | P9: 14945944
B10: Depreciation and Amortization Charges | C10: 22457890 | D10: 26473936 | E10: 33998254 | F10: 14282307 | G10: =12111887 -> 12111887 | H10: 802006 | I10: 1604012 | J10: 2489236 | K10: 3351454 | L10: 4189318 | M10: 5027182 | N10: 5865045 | O10: 7052865 | P10: 8063848
B11: Administrative Expenses | C11: 60761790 | D11: 47356838 | E11: 50375632 | F11: 94491762 | G11: =106447541 -> 106447541 | H11: 2774126 | I11: 5346507 | J11: 7194171 | K11: 9394981 | L11: 12156837 | M11: 14600498 | N11: 17138169 | O11: 19315624 | P11: 24375607
B13: TOTAL EXPENSES | C13: 645911469 | D13: 728984668 | E13: 945397143 | F13: 815646313 | G13: 853143249 | H13: 79342187 | I13: 208247710 | J13: 2.6901753e+08 | K13: 3.7749145e+08 | L13: 4.5822405e+08 | M13: 5.8348929e+08 | N13: 6.7539951e+08 | O13: 8.0259499e+08 | P13: 9.0487673e+08
B15: % of Total Income
B16: Personnel Expenses | C16: =C7/C4 -> 0.14430745 | D16: =D7/D4 -> 0.11161564 | E16: =E7/E4 -> 0.1503003 | F16: =F7/F4 -> 0.05053227 | G16: =G7/G4 -> 0.050748897 | H16: =H7/H4 -> 0.039770186 | I16: =I7/I4 -> 0.037954534 | J16: =J7/J4 -> 0.038212226 | ... P16: =P7/P4 -> 0.051024334
B17: Governance Expenses | C17: =C8/C4 -> 0.02004426 | D17: =D8/D4 -> 0.015496762 | E17: =E8/E4 -> 0.014537945 | F17: =F8/F4 -> 0.035705556 | G17: =G8/G4 -> 0.032575691 | H17: =H8/H4 -> 0.090886859 | I17: =I8/I4 -> 0.073758145 | J17: =J8/J4 -> 0.066268379 | ... P17: =P8/P4 -> 0.060388197
B18: Marketing Expenses | C18: =C9/C4 -> 0.012312284 | D18: =D9/D4 -> 0.012491627 | E18: =E9/E4 -> 0.012086536 | F18: =F9/F4 -> 0.015253532 | G18: =G9/G4 -> 0.011661823 | H18: =H9/H4 -> 0.026765643 | I18: =I9/I4 -> 0.01707102 | J18: =J9/J4 -> 0.015939489 | ... P18: =P9/P4 -> 0.013863304
B19: Depreciation and Amortization Charges | C19: =C10/C4 -> 0.033180884 | D19: =D10/D4 -> 0.027960584 | E19: =E10/E4 -> 0.027697161 | F19: =F10/F4 -> 0.012490512 | G19: =G10/G4 -> 0.0090266095 | H19: =H10/H4 -> 0.0071768945 | I19: =I10/I4 -> 0.0069391814 | J19: =J10/J4 -> 0.0071023831 | ... P19: =P10/P4 -> 0.0074797267
B20: Administrative Expenses | C20: =C11/C4 -> 0.08977379 | D20: =D11/D4 -> 0.050016169 | E20: =E11/E4 -> 0.041039226 | F20: =F11/F4 -> 0.082637246 | G20: =G11/G4 -> 0.079332014 | H20: =H11/H4 -> 0.024824764 | I20: =I11/I4 -> 0.023129741 | J20: =J11/J4 -> 0.020526683 | ... P20: =P11/P4 -> 0.02260991
B22: % of Operating Expenses
B23: Personnel Expenses | C23: =C7/C6 -> 0.48163704 | D23: =D7/D6 -> 0.51298483 | E23: =E7/E6 -> 0.61181953 | F23: =F7/F6 -> 0.25700588 | G23: =G7/G6 -> 0.2767945 | H23: =H7/H6 -> 0.20995287 | I23: =I7/I6 -> 0.23892923 | J23: =J7/J6 -> 0.25810498 | ... P23: =P7/P6 -> 0.32841489
B24: Governance Expenses | C24: =C8/C6 -> 0.066899236 | D24: =D8/D6 -> 0.071223026 | E24: =E8/E6 -> 0.059178847 | F24: =F8/F6 -> 0.18159758 | G24: =G8/G6 -> 0.17767425 | H24: =H8/H6 -> 0.47980558 | I24: =I8/I6 -> 0.46431809 | J24: =J8/J6 -> 0.44761064 | ... P24: =P8/P6 -> 0.3886848
B25: Marketing Expenses | C25: =C9/C6 -> 0.041093181 | D25: =D9/D6 -> 0.057411442 | E25: =E9/E6 -> 0.049200027 | F25: =F9/F6 -> 0.077579091 | G25: =G9/G6 -> 0.063605883 | H25: =H9/H6 -> 0.14129991 | I25: =I9/I6 -> 0.10746452 | J25: =J9/J6 -> 0.10766349 | ... P25: =P9/P6 -> 0.089230277
B26: Depreciation and Amortization Charges | C26: =C10/C6 -> 0.11074371 | D26: =D10/D6 -> 0.12850668 | E26: =E10/E6 -> 0.11274538 | F26: =F10/F6 -> 0.063526439 | G26: =G10/G6 -> 0.04923291 | H26: =H10/H6 -> 0.03788792 | I26: =I10/I6 -> 0.043683141 | J26: =J10/J6 -> 0.04797314 | ... P26: =P10/P6 -> 0.048142786
B27: Administrative Expenses | C27: =C11/C6 -> 0.29962683 | D27: =D11/D6 -> 0.22987402 | E27: =E11/E6 -> 0.16705622 | F27: =F11/F6 -> 0.420291 | G27: =G11/G6 -> 0.43269246 | H27: =H11/H6 -> 0.13105371 | I27: =I11/I6 -> 0.14560503 | J27: =J11/J6 -> 0.13864775 | ... P27: =P11/P6 -> 0.14552725
B29: % of Total Expenses
B30: Personnel Expenses | C30: =C7/C13 -> 0.15121565 | D30: =D7/D13 -> 0.14497027 | E30: =E7/E13 -> 0.19514926 | F30: =F7/F13 -> 0.070841058 | G30: =G7/G13 -> 0.079816338 | H30: =H7/H13 -> 0.056013732 | I30: =I7/I13 -> 0.04212916 | J30: =J7/J13 -> 0.049783305 | ... P30: =P7/P13 -> 0.060791733
B31: Governance Expenses | C31: =C8/C13 -> 0.021003807 | D31: =D8/D13 -> 0.020127732 | E31: =E8/E13 -> 0.018876005 | F31: =F8/F13 -> 0.050055527 | G31: =G8/G13 -> 0.051234068 | H31: =H8/H13 -> 0.12800826 | I31: =I8/I13 -> 0.081870816 | J31: =J8/J13 -> 0.086335168 | ... P31: =P8/P13 -> 0.071948086
B32: Marketing Expenses | C32: =C9/C13 -> 0.012901691 | D32: =D9/D13 -> 0.016224558 | E32: =E9/E13 -> 0.015693106 | F32: =F9/F13 -> 0.021383888 | G32: =G9/G13 -> 0.018341364 | H32: =H9/H13 -> 0.037697675 | I32: =I9/I13 -> 0.018948665 | J32: =J9/J13 -> 0.020766141 | ... P32: =P9/P13 -> 0.016517105
B33: Depreciation and Amortization Charges | C33: =C10/C13 -> 0.034769301 | D33: =D10/D13 -> 0.036316177 | E33: =E10/E13 -> 0.035961875 | F33: =F10/F13 -> 0.017510417 | G33: =G10/G13 -> 0.01419678 | H33: =H10/H13 -> 0.010108191 | I33: =I10/I13 -> 0.0077024232 | J33: =J10/J13 -> 0.0092530623 | ... P33: =P10/P13 -> 0.0089115431
B34: Administrative Expenses | C34: =C11/C13 -> 0.09407139 | D34: =D11/D13 -> 0.064962735 | E34: =E11/E13 -> 0.053285154 | F34: =F11/F13 -> 0.11584894 | G34: =G11/G13 -> 0.12477101 | H34: =H11/H13 -> 0.034964073 | I34: =I11/I13 -> 0.025673785 | J34: =J11/J13 -> 0.026742387 | ... P34: =P11/P13 -> 0.026938042
