Workbook
Name BALANCE1_LDA01: '[1]Financial Statements'!$E$112
Name BALANCE1_LDA12: '[1]Financial Statements'!$E$123
Name BALANCE2_LDA01: '[1]Financial Statements'!$F$112
Name BALANCE2_LDA12: '[1]Financial Statements'!$F$123
Name BALANCE3_LDA01: '[1]Financial Statements'!$G$112
Name BALANCE3_LDA12: '[1]Financial Statements'!$G$123
Name BALANCE4_LDA01: '[1]Financial Statements'!$H$112
Name BALANCE4_LDA12: '[1]Financial Statements'!$H$123
Name BALANCE5_LDA01: '[1]Financial Statements'!$I$112
Name BALANCE5_LDA12: '[1]Financial Statements'!$I$123
Name BALANCE6_LDA01: '[1]Financial Statements'!$J$112
Name BALANCE6_LDA12: '[1]Financial Statements'!$J$123
Name PEARLS1_LA002: '[1]Financial Statements'!$E$280
Name PEARLS1_LE008: '[1]Financial Statements'!$E$275
Name PEARLS1_LE009: '[1]Financial Statements'!$E$276
Name PEARLS1_LR001: '[1]Financial Statements'!$E$282
Name PEARLS1_LR005: '[1]Financial Statements'!$E$286
Name PEARLS1_LR006: '[1]Financial Statements'!$E$287
Name PEARLS1_LR007: '[1]Financial Statements'!$E$288
Name PEARLS1_LR009: '[1]Financial Statements'!$E$290
Name PEARLS1_LS001: '[1]Financial Statements'!$E$298
Name PEARLS1_LS005: '[1]Financial Statements'!$E$302
Name PEARLS1_LS011: '[1]Financial Statements'!$E$308
Name PEARLS2_LA002: '[1]Financial Statements'!$F$280
Name PEARLS2_LE008: '[1]Financial Statements'!$F$275
Name PEARLS2_LE009: '[1]Financial Statements'!$F$276
Name PEARLS2_LR001: '[1]Financial Statements'!$F$282
Name PEARLS2_LR005: '[1]Financial Statements'!$F$286
Name PEARLS2_LR006: '[1]Financial Statements'!$F$287
Name PEARLS2_LR007: '[1]Financial Statements'!$F$288
Name PEARLS2_LR009: '[1]Financial Statements'!$F$290
Name PEARLS2_LS001: '[1]Financial Statements'!$F$298
Name PEARLS2_LS005: '[1]Financial Statements'!$F$302
Name PEARLS2_LS010: '[1]Financial Statements'!$F$307
Name PEARLS2_LS011: '[1]Financial Statements'!$F$308
Name PEARLS3_LA002: '[1]Financial Statements'!$G$280
Name PEARLS3_LE008: '[1]Financial Statements'!$G$275
Name PEARLS3_LE009: '[1]Financial Statements'!$G$276
Name PEARLS3_LR001: '[1]Financial Statements'!$G$282
Name PEARLS3_LR005: '[1]Financial Statements'!$G$286
Name PEARLS3_LR006: '[1]Financial Statements'!$G$287
Name PEARLS3_LR007: '[1]Financial Statements'!$G$288
Name PEARLS3_LR009: '[1]Financial Statements'!$G$290
Name PEARLS3_LS001: '[1]Financial Statements'!$G$298
Name PEARLS3_LS005: '[1]Financial Statements'!$G$302
Name PEARLS3_LS010: '[1]Financial Statements'!$G$307
Name PEARLS3_LS011: '[1]Financial Statements'!$G$308
Name PEARLS4_LA002: '[1]Financial Statements'!$H$280
Name PEARLS4_LE008: '[1]Financial Statements'!$H$275
Name PEARLS4_LE009: '[1]Financial Statements'!$H$276
Name PEARLS4_LR001: '[1]Financial Statements'!$H$282
Name PEARLS4_LR005: '[1]Financial Statements'!$H$286
Name PEARLS4_LR006: '[1]Financial Statements'!$H$287
Name PEARLS4_LR007: '[1]Financial Statements'!$H$288
Name PEARLS4_LR009: '[1]Financial Statements'!$H$290
Name PEARLS4_LS001: '[1]Financial Statements'!$H$298
Name PEARLS4_LS005: '[1]Financial Statements'!$H$302
Name PEARLS4_LS010: '[1]Financial Statements'!$H$307
Name PEARLS4_LS011: '[1]Financial Statements'!$H$308
Name PEARLS5_LA002: '[1]Financial Statements'!$I$280

Sheet Evolutive SFP
B3: 43831 | C3: 43862 | D3: 43891 | E3: 43922 | F3: 43952 | G3: 43983 | H3: 44013 | I3: 44044 | J3: 44075 | K3: 44105 | L3: 44136 | M3: 44166 | N3: AUDITED 2020 | O3: 44197 | P3: 44228 | Q3: 44256 | R3: 44287 | S3: 44317 | T3: 44348 | U3: 44378 | V3: 44409 | W3: 44440 | X3: 44470 | Y3: 44501 | Z3: 44531 | AA3: Audited 2021 | AB3: 44562 | AC3: 44593 | AD3: 44621 | AE3: 44652 | AF3: 44682 | AG3: 44713 | AH3: 44743 | AI3: 44774 | AJ3: 44805 | AK3: 44835 | AL3: 44866 | AM3: 44896 | AN3: Aud-22
A4: Cash & cash Equivalent | B4: =(B5+B6) -> 1.0101863e+09 | C4: =(C5+C6) -> 1.0585918e+09 | D4: =(D5+D6) -> 7.869912e+08 | E4: =(E5+E6) -> 5.3780551e+08 | F4: =(F5+F6) -> 6.7427165e+08 | G4: =(G5+G6) -> 8.8731409e+08 | H4: =(H5+H6) -> 9.8082857e+08 | I4: =(I5+I6) -> 9.8415191e+08 | ... AN4: =(AN5+AN6) -> 1954092000
A5: Cash In Hand | B5: 1.010153e+09 | C5: 21969.49 | D5: 35966.49 | E5: 29941.49 | F5: 31473.49 | G5: 160465.77 | H5: 148928.77 | I5: 196968.77 | J5: 208221.77 | K5: 241659.57 | L5: 219890.57 | M5: 1255040.3 | N5: 252000 | O5: 1583728.3 | P5: 1757108.3 | Q5: 1035713.6 | R5: 2389981.6 | S5: 6111924.6 | T5: 3088383.6 | U5: 6155297.6 | V5: 4862203.4 | W5: 4344987 | X5: 3175001 | Y5: 1957830 | Z5: 1303599.1 | AA5: 1000 | AB5: 913220.8 | AC5: 4023647 | AD5: 4471649.9 | AE5: 3896218 | AF5: 1220087.7 | AG5: 3743930.5 | AH5: 3687296.4 | AI5: 2451256.4 | AJ5: 2146417.1 | AK5: 5876491.1 | AL5: 4789067.1 | AM5: 2433359.4 | AN5: 82435000
A6: Cash at Bank | B6: 33343.49 | C6: 1.0585698e+09 | D6: 7.8695523e+08 | E6: 5.3777557e+08 | F6: 6.7424017e+08 | G6: 8.8715363e+08 | H6: 9.8067964e+08 | I6: 9.8395494e+08 | J6: 9.9408861e+08 | K6: 1082914258 | L6: 1.2203478e+09 | M6: 1.2425879e+09 | N6: =16333000+1113000+12103000+573000+1349000+1003000+17210000 -> 49684000 | O6: 1.3352814e+09 | P6: 1.4116783e+09 | Q6: 1.0427998e+09 | R6: 9.9210255e+08 | S6: 9.4874057e+08 | T6: 9.7306423e+08 | U6: 1.1811607e+09 | V6: 1.2052931e+09 | W6: 1.1854755e+09 | X6: 1.2554971e+09 | Y6: 1.302692e+09 | Z6: 1.3368233e+09 | AA6: =116148000+71416000+320222000+162000+343255000+336605000+150319000 -> 1338127000 | AB6: 1.3079433e+09 | AC6: 1.2284454e+09 | AD6: 1.3749216e+09 | AE6: 1.2992514e+09 | AF6: 1.3300062e+09 | AG6: 1.4736664e+09 | AH6: 1.4422755e+09 | AI6: 1.4491563e+09 | AJ6: 1.0706931e+09 | AK6: 1.1383077e+09 | AL6: 1.1606487e+09 | AM6: 1.1960837e+09 | AN6: 1871657000
A7: Prepayment and Sundry | B7: 1.3214172e+08 | C7: 1.4246224e+08 | D7: 0 | E7: 1.4458991e+08 | F7: 1.4390946e+08 | G7: 64235857 | H7: 69710925 | I7: 75746422 | J7: 82061838 | K7: 80631380 | L7: 80715944 | M7: 88025263 | N7: 90910000 | O7: 70956448 | P7: 1.4670054e+08 | Q7: 1.4076959e+08 | R7: 1.5874134e+08 | S7: 1.5564367e+08 | T7: 1.5872149e+08 | U7: 1.6416e+08 | V7: 1.6352983e+08 | W7: 1.719237e+08 | X7: 1.7311523e+08 | Y7: 1.6883048e+08 | Z7: 1.686447e+08 | AA7: 104846000 | AB7: 1.8176984e+08 | AC7: 1.9089697e+08 | AD7: 2.0224698e+08 | AE7: 2.1003406e+08 | AF7: 1.9992038e+08 | AG7: 2.0528994e+08 | AH7: 2.1426977e+08 | AI7: 2.0885843e+08 | AJ7: 2.0829975e+08 | AK7: 2.1228848e+08 | AL7: 223925472 | AM7: 2.0611555e+08 | AN7: 24210000
A8: Financial Investment | B8: =(B9+B10+B11+B13+B12) -> 1.4835578e+08 | C8: =(C9+C10+C11+C13+C12) -> 1.8635578e+08 | D8: =(D9+D10+D11+D13+D12) -> 1.9135578e+08 | E8: =(E9+E10+E11+E13+E12) -> 4.4135578e+08 | F8: =(F9+F10+F11+F13+F12) -> 4.4135578e+08 | G8: =(G9+G10+G11+G13+G12) -> 4.4938528e+08 | H8: =(H9+H10+H11+H13+H12) -> 4.5227775e+08 | I8: =(I9+I10+I11+I13+I12) -> 4.8627775e+08 | ... K8: =(K9+K10+K11+K13+K12) -> 3.8516373e+08 | L8: =(L9+L10+L11+L12+L13) -> 3.8516373e+08 | M8: =(M9+M10+M11+M13+M12) -> 4.6163073e+08 | N8: =(N9+N10+N11+N13+N12) -> 1653199000 | O8: =(O9+O10+O11+O13+O12) -> 4.3595943e+08 | P8: =(P9+P10+P11+P13+P12) -> 3.9176941e+08 | Q8: =(Q9+Q10+Q11+Q13+Q12) -> 6.5109522e+08 | R8: =(R9+R10+R11+R13+R12) -> 6.9909522e+08 | S8: =(S9+S10+S11+S13+S12) -> 6.9909522e+08 | T8: =(T9+T10+T11+T13+T12) -> 7.0892257e+08 | ... AN8: =(AN9+AN10+AN11+AN13+AN12) -> 241010000
A9: Government Security | B9: 129759730 | C9: 167759730 | D9: 172759730 | E9: 172759730 | F9: 172759730 | G9: 166759730 | H9: 166759730 | I9: 166759730 | J9: 141759730 | K9: 76759730 | L9: 76759730 | M9: 76759730 | N9: 76760000 | O9: 50759730 | P9: 5000000 | Q9: 210000000 | R9: 258000000 | S9: 258000000 | T9: 258000000 | U9: 258000000 | V9: 258000000 | W9: 258000000 | X9: 258000000 | Y9: 258000000 | Z9: 258000000 | AA9: 258000000 | AB9: 258000000 | AC9: 407000000 | AD9: 197000000 | AE9: 149000000 | AF9: 149000000 | AG9: 149000000 | AH9: 149000000 | AI9: 149000000 | AJ9: 564823940 | AK9: 564823940 | AL9: 576000000 | AM9: 623000000 | AN9: 220000000
A10: Other Securities | B10: 0 | C10: 0 | D10: 0 | E10: 0 | F10: 0 | G10: 0 | H10: 0 | I10: 0 | J10: 0 | K10: 0 | L10: 0 | M10: 0 | O10: 0 | P10: 0 | Q10: 0 | R10: 0 | S10: 0 | T10: 0 | U10: 0 | V10: 0 | W10: 0 | X10: 0 | Y10: 0 | Z10: 0 | AB10: 0 | AC10: 0 | AD10: 0 | AE10: 0 | AF10: 0 | AG10: 0 | AH10: 0 | AI10: 0 | AJ10: 0 | AK10: 0 | AL10: 0 | AM10: 0
A11: Balances in NACCOS (E.g Jungu Kuu, ESS, Savings,Money Market,Coop FD, CFP) | B11: 0 | C11: 0 | D11: 0 | E11: 250000000 | F11: 250000000 | G11: 264029491 | H11: 266921968 | I11: 300921968 | J11: 303399524 | K11: 289807943 | L11: 289807943 | M11: 366274944 | N11: 1560028000 | O11: 368789447 | P11: 370359160 | Q11: 424684965 | R11: 424684965 | S11: 424684965 | T11: 434512313 | U11: 300257150 | V11: 301898294 | W11: 307195170 | X11: 307195170 | Y11: 308919696 | Z11: 344430948 | AA11: 344431000 | AB11: 344430948 | AC11: 346871431 | AD11: 282584769 | AE11: 332584769 | AF11: 333480645 | AG11: 287759709 | AH11: 338909709 | AI11: 339826190 | AJ11: 344486816 | AK11: 346813266 | AL11: 347750902 | AM11: 352561426
A12: Equity Investments in NACCOs(Shares in- CIC, KUSCCO, COOP BANK,CAK, KERUSSU) | L12: 0 | M12: 0 | N12: =2079000+4720000+1575000+3415000 -> 11789000
A13: Equity Investments in companies - shares/stocks | B13: 18596054 | C13: 18596054 | D13: 18596054 | E13: 18596054 | F13: 18596054 | G13: 18596054 | H13: 18596054 | I13: 18596054 | J13: 18596054 | K13: 18596054 | L13: 18596054 | M13: 18596054 | N13: =2640000+1982000 -> 4622000 | O13: 16410254 | P13: 16410254 | Q13: 16410254 | R13: 16410254 | S13: 16410254 | T13: 16410254 | U13: 16410254 | V13: 16410254 | W13: 16410254 | X13: 16410254 | Y13: 16410254 | Z13: 16410254 | AA13: =17040000+2066000 -> 19106000 | AB13: 19105609 | AC13: 19105609 | AD13: 19105609 | AE13: 19105609 | AF13: 19105609 | AG13: 19105609 | AH13: 21105609 | AI13: 21105609 | AJ13: 21105609 | AK13: 21105609 | AL13: 21105609 | AM13: 21009425 | AN13: 21010000
A14: Net Loan Portfolio | B14: =(B15-B16) -> 5.2541832e+09 | C14: =(C15-C16) -> 5.165615e+09 | D14: =(D15-D16) -> 5.2067397e+09 | E14: =(E15-E16) -> 5.214632e+09 | F14: =(F15-F16) -> 5.1847667e+09 | G14: =(G15-G16) -> 5.1656339e+09 | H14: =(H15-H16) -> 5.2006949e+09 | I14: =(I15-I16) -> 5.2552086e+09 | ... AN14: =(AN15-AN16) -> 6927369000
A15: Gross Loan Portfolio | B15: 5.394204e+09 | C15: 5.3056358e+09 | D15: 5.3686268e+09 | E15: 5.3765191e+09 | F15: 5.3466538e+09 | G15: 5.327521e+09 | H15: 5.362582e+09 | I15: 5.4276033e+09 | J15: 5.5516486e+09 | K15: 5.6023668e+09 | L15: 5.6337173e+09 | M15: 5.6729643e+09 | N15: =5504745000+165551000 -> 5670296000 | O15: 5.6985851e+09 | P15: 5.741567e+09 | Q15: 5.7151278e+09 | R15: 5.7959051e+09 | S15: 5.8497818e+09 | T15: 5.8511896e+09 | U15: 5.9209457e+09 | V15: 6.063743e+09 | W15: 6.1594623e+09 | X15: 6.1956509e+09 | Y15: 6.2238862e+09 | Z15: 6.2750579e+09 | AA15: 6334627000 | AB15: 6.4057229e+09 | AC15: 6.4288761e+09 | AD15: 6.3608269e+09 | AE15: 6.447651e+09 | AF15: 6.5043329e+09 | AG15: 6.4816222e+09 | AH15: 6.6054459e+09 | AI15: 6.6927014e+09 | AJ15: 6.7769328e+09 | AK15: 6.8902866e+09 | AL15: 7.0239582e+09 | AM15: 7.0886847e+09 | AN15: 7258848000
A16: Allowance For Loan Loss | B16: 1.4002079e+08 | C16: 1.4002079e+08 | D16: 1.6188709e+08 | E16: 1.6188709e+08 | F16: 1.6188709e+08 | G16: 1.6188709e+08 | H16: 1.6188709e+08 | I16: 1.7239471e+08 | J16: 1.7239471e+08 | K16: 1.7239471e+08 | L16: 1.7239471e+08 | M16: 1.8488671e+08 | N16: 184886000 | O16: 2.7035547e+08 | P16: 3.934329e+08 | Q16: 2.3973918e+08 | R16: 2.4681637e+08 | S16: 2.5389355e+08 | T16: 2.5389355e+08 | U16: 2.5904846e+08 | V16: 2.714612e+08 | W16: 2.714612e+08 | X16: 2.8672624e+08 | Y16: 2.3923267e+08 | Z16: 2.5686472e+08 | AA16: 222885000 | AB16: 2.5546166e+08 | AC16: 2.5546166e+08 | AD16: 2.5546166e+08 | AE16: 2.5546166e+08 | AF16: 2.5546166e+08 | AG16: 2.5546166e+08 | AH16: 2.5546166e+08 | AI16: 2.5546166e+08 | AJ16: 2.5546166e+08 | AK16: 2.5546166e+08 | AL16: 2.5546166e+08 | AM16: 2.5546166e+08 | AN16: 331479000
A17: Accounts Recievables | B17: =(B18+B19+B20) -> -3692461.6 | C17: =(C18+C19+C20) -> -3441691.7 | D17: =(D18+D19+D20) -> 1.370186e+08 | E17: =(E18+E19+E20) -> 21406077 | F17: =(F18+F19+F20) -> 21540228 | G17: =(G18+G19+G20) -> 21622703 | H17: =(H18+H19+H20) -> 21624637 | I17: =(I18+I19+I20) -> 21703385 | ... AA17: =(AA18+AA19+AA20) -> 178000 | AB17: 178080 | AC17: 178080 | AD17: 178080 | AE17: 178080 | AF17: 178080 | AG17: 178080 | AH17: 178080 | AI17: 178080 | AJ17: 178080 | AK17: 178080 | AL17: 178080 | AM17: 178080
A18: Tax Recoverable | B18: -3727741.6 | C18: -3476971.7 | D18: -4027588.2 | E18: 21370797 | F18: 21504948 | G18: 21587423 | H18: 21589357 | I18: 21668105 | J18: 21577630 | K18: 21462789 | L18: 21517463 | M18: -3668660.4 | N18: 0 | O18: -806971.81 | P18: -16257.22 | Q18: 12221657 | R18: 38829.51 | S18: 1242022.7 | T18: 1764568.1 | U18: 2411821.3 | V18: 5055542.7 | W18: 5237080.5 | X18: 5555790.9 | Y18: 5586403.8 | Z18: 0 | AA18: 178000 | AB18: 0 | AC18: 0 | AD18: 0 | AE18: 0 | AF18: 0 | AG18: 178080 | AH18: 178080 | AI18: 178080 | AJ18: 178080 | AK18: 178080 | AL18: 178080 | AM18: 178080
A19: Deffered Tax Assets | B19: 35280 | C19: 35280 | D19: 35280 | E19: 35280 | F19: 35280 | G19: 35280 | H19: 35280 | I19: 35280 | J19: 35280 | K19: 35280 | L19: 35280 | M19: 35280 | N19: 203000 | O19: 203280 | P19: 203280 | Q19: 203280 | R19: 203280 | S19: 203280 | T19: 203280 | U19: 203280 | V19: 203280 | W19: 203280 | X19: 203280 | Y19: 203280 | Z19: 203280 | AB19: 178080 | AC19: 178080 | AD19: 178080 | AE19: 178080 | AF19: 178080 | AG19: 0 | AH19: 0 | AI19: 0 | AJ19: 0 | AK19: 0 | AL19: 0 | AM19: 0
A20: Retirement Benefit Assets | B20: 0 | C20: 0 | D20: 1.4101091e+08 | E20: 0 | F20: 0 | G20: 0 | H20: 0 | I20: 0 | J20: 0 | K20: 0 | L20: 0 | M20: 0 | N20: 0 | O20: 0 | P20: 0 | Q20: 0 | R20: 0 | S20: 0 | T20: 0 | U20: 0 | V20: 0 | W20: 0 | X20: 0 | Y20: 0 | Z20: 0 | AB20: 0 | AC20: 0 | AD20: 0 | AE20: 0 | AF20: 0
A21: Property&Equipments&Other Assets | B21: =(B22+B23+B24+B25+B26) -> 3.7778544e+08 | C21: =(C22+C23+C24+C25+C26) -> 3.799367e+08 | D21: =(D22+D23+D24+D25+D26) -> 3.8482724e+08 | E21: =(E22+E23+E24+E25+E26) -> 3.8685266e+08 | F21: =(F22+F23+F24+F25+F26) -> 3.8766205e+08 | G21: =(G22+G23+G24+G25+G26) -> 3.8713425e+08 | H21: =(H22+H23+H24+H25+H26) -> 3.8775507e+08 | I21: =(I22+I23+I24+I25+I26) -> 3.8835257e+08 | ... AN21: =(AN22+AN23+AN24+AN25+AN26) -> 395991000
A22: Investment Properties | B22: 0 | C22: 3.547409e+08 | D22: 0 | E22: 0 | F22: 0 | G22: 0 | H22: 0 | I22: 0 | J22: 0 | K22: 0 | L22: 0 | M22: 0 | N22: 0 | O22: 0 | P22: 0 | Q22: 0 | R22: 0 | S22: 0 | T22: 0 | U22: 0 | V22: 0 | W22: 0 | X22: 0 | Y22: 0 | Z22: 0 | AB22: 0 | AC22: 0 | AD22: 0 | AE22: 0 | AF22: 0 | AG22: 0 | AH22: 0 | AI22: 0 | AJ22: 0 | AK22: 0 | AL22: 0 | AM22: 0
A23: Property and Equipment | B23: 3.5479938e+08 | C23: 0 | D23: 3.5984937e+08 | E23: 3.6214789e+08 | F23: 3.6320642e+08 | G23: 3.6286959e+08 | H23: 3.6326091e+08 | I23: 3.6414576e+08 | J23: 3.2829728e+08 | K23: 3.3211655e+08 | L23: 3.3250428e+08 | M23: 3.492099e+08 | N23: 349209000 | O23: 3.4908543e+08 | P23: 3.487866e+08 | Q23: 3.4737702e+08 | R23: 3.4689648e+08 | S23: 3.463183e+08 | T23: 3.5333545e+08 | U23: 3.5438394e+08 | V23: 3.5236651e+08 | W23: 3.5193949e+08 | X23: 3.5136213e+08 | Y23: 3.5105313e+08 | Z23: 3.5132793e+08 | AA23: 352686000 | AB23: 3.5217774e+08 | AC23: 3.5166933e+08 | AD23: 3.5129753e+08 | AE23: 3.5034675e+08 | AF23: 3.5229715e+08 | AG23: 3.5120761e+08 | AH23: 3.5011212e+08 | AI23: 3.4900868e+08 | AJ23: 3.4834609e+08 | AK23: 3.47238e+08 | AL23: 3.4613662e+08 | AM23: 3.499129e+08 | AN23: 351329000
A24: Prepaid Lease Rentals | B24: 0 | C24: 0 | D24: 0 | E24: 0 | F24: 0 | G24: 0 | H24: 0 | I24: 0 | J24: 0 | K24: 0 | L24: 0 | M24: 0 | N24: 0 | O24: 0 | P24: 0 | Q24: 0 | R24: 0 | S24: 0 | T24: 0 | U24: 0 | V24: 0 | W24: 0 | X24: 0 | Y24: 0 | Z24: 0 | AB24: 0 | AC24: 0 | AD24: 0 | AE24: 0 | AF24: 0 | AG24: 0 | AH24: 0 | AI24: 0 | AJ24: 0 | AK24: 0 | AL24: 0 | AM24: 0
A25: Intangible Assets | B25: 22986061 | C25: 25195801 | D25: 24977872 | E25: 24704774 | F25: 24455633 | G25: 24264663 | H25: 24494159 | I25: 24206810 | J25: 29683436 | K25: 29773316 | L25: 29490118 | M25: 32771380 | N25: 32771000 | O25: 32546618 | P25: 32028424 | Q25: 31977927 | R25: 31922884 | S25: 31870306 | T25: 31815768 | U25: 31758964 | V25: 35069935 | W25: 39398730 | X25: 39296901 | Y25: 39362063 | Z25: 39303746 | AA25: 41154000 | AB25: 41652071 | AC25: 41493377 | AD25: 41323508 | AE25: 41159356 | AF25: 42446992 | AG25: 45790665 | AH25: 44785047 | AI25: 43745774 | AJ25: 42742281 | AK25: 42323570 | AL25: 41360038 | AM25: 44662431 | AN25: 44662000
A26: Other Assets | B26: 0 | C26: 0 | D26: 0 | E26: 0 | F26: 0 | G26: 0 | H26: 0 | I26: 0 | J26: 0 | K26: 0 | L26: 0 | M26: 0 | N26: 0 | O26: 0 | P26: 0 | Q26: 0 | R26: 0 | S26: 0 | T26: 0 | U26: 0 | V26: 0 | W26: 0 | X26: 0 | Y26: 0 | Z26: 0 | AB26: 0 | AC26: 0 | AD26: 0 | AE26: 0 | AF26: 0 | AG26: 0 | AH26: 0 | AI26: 0 | AJ26: 0 | AK26: 0 | AL26: 0 | AM26: 0
A27: Total Assets | B27: =(B21+B17+B14+B8+B7+B4) -> 6.91896e+09 | C27: =(C21+C17+C14+C8+C7+C4) -> 6.9295198e+09 | D27: =(D21+D17+D14+D8+D7+D4) -> 6.7069325e+09 | E27: =(E21+E17+E14+E8+E7+E4) -> 6.746642e+09 | F27: =(F21+F17+F14+F8+F7+F4) -> 6.8535059e+09 | G27: =(G21+G17+G14+G8+G7+G4) -> 6.9753261e+09 | H27: =(H21+H17+H14+H8+H7+H4) -> 7.1128919e+09 | I27: =(I21+I17+I14+I8+I7+I4) -> 7.2114407e+09 | ... AO27: =(AO21+AO17+AO14+AO8+AO7+AO4) -> 0
A28: Savings and Deposits | B28: 0 | C28: 0 | D28: 0 | E28: 0 | F28: 0 | G28: 0 | H28: 0 | I28: 0 | J28: 0 | K28: 0 | L28: 0 | M28: 64332 | N28: 5916911000 | O28: 968053.02 | P28: 1.9277926e+08 | Q28: 93474883 | R28: 81845472 | S28: 69739721 | T28: 69211526 | U28: 1.0386625e+08 | V28: 1.5482055e+08 | W28: 1.419525e+08 | X28: 1.2397897e+08 | Y28: 1.4311435e+08 | Z28: 1.2485343e+08 | AA28: 126447000 | AB28: 1.4926346e+08 | AC28: 1.4166661e+08 | AD28: 3.447683e+08 | AE28: 2.607424e+08 | AF28: 2.3884634e+08 | AG28: 2.4489044e+08 | AH28: 2.7654407e+08 | AI28: 2.5459203e+08 | AJ28: 2.2856712e+08 | AK28: 2.4457975e+08 | AL28: 2.4297308e+08 | AM28: 2.3655047e+08 | AN28: 330931000
A29: Short Terrm Deposits | B29: 55125212 | C29: 57687510 | D29: 60972993 | E29: 66344454 | F29: 70243155 | G29: 91522596 | H29: 91259010 | I29: 84437462 | J29: 90906172 | K29: 96133734 | L29: 96863484 | M29: 87694688 | O29: 92991143 | P29: 86014808 | Q29: 91141092 | R29: 94488018 | S29: 95995000 | T29: 96429405 | U29: 98704366 | V29: 1.0440746e+08 | W29: 1.0444308e+08 | X29: 1.0104332e+08 | Y29: 94490230 | Z29: 92485835 | AA29: =28142000+32183000+30567000+47000 -> 90939000 | AB29: 90373961 | AC29: 92665757 | AD29: 91130919 | AE29: 89318494 | AF29: 92232097 | AG29: 94753382 | AH29: 96432774 | AI29: 93433199 | AJ29: 94451326 | AK29: 97702518 | AL29: 96305855 | AM29: 94247370
A30: Non Withdrawable Deposits | B30: 5.3494077e+09 | C30: 5425374401 | D30: 5.4994885e+09 | E30: 5.5300382e+09 | F30: 5576806617 | G30: 5.6119058e+09 | H30: 5.6953443e+09 | I30: 5.749134e+09 | J30: 5.7856993e+09 | K30: 5.8599787e+09 | L30: 5.9079874e+09 | M30: 5.916898e+09 | N30: 88107000 | O30: 5.9714998e+09 | P30: 6.0437252e+09 | Q30: 6.1382567e+09 | R30: 6.1953535e+09 | S30: 6.1708658e+09 | T30: 6.1544773e+09 | U30: 6.2047627e+09 | V30: 6.2403096e+09 | W30: 6.2457152e+09 | X30: 6.2991952e+09 | Y30: 6.2823982e+09 | Z30: 6.3476863e+09 | AA30: 6347686000 | AB30: 6.4134089e+09 | AC30: 6.4418425e+09 | AD30: 6.5425059e+09 | AE30: 6.6105472e+09 | AF30: 6.6532933e+09 | AG30: 6.6496016e+09 | AH30: 6.7033456e+09 | AI30: 6.7443433e+09 | AJ30: 6.7836691e+09 | AK30: 6.8604398e+09 | AL30: 6.9494994e+09 | AM30: 7.0062215e+09 | AN30: 7006250000
A31: Total Deposit Liabilities | B31: =SUM(B28:B30) -> 5.4045329e+09 | C31: =SUM(C28:C30) -> 5.4830619e+09 | D31: =SUM(D28:D30) -> 5.5604615e+09 | E31: =SUM(E28:E30) -> 5.5963827e+09 | F31: =SUM(F28:F30) -> 5.6470498e+09 | G31: =SUM(G28:G30) -> 5.7034284e+09 | H31: =SUM(H28:H30) -> 5.7866033e+09 | I31: =SUM(I28:I30) -> 5.8335715e+09 | ... AN31: =SUM(AN28:AN30) -> 7337181000
A32: Tax Payable | B32: 10332188 | C32: 10332188 | D32: 10332188 | E32: 3039879.4 | F32: 3039879.4 | G32: 3039879.4 | H32: 3039879.4 | I32: 3039879.4 | J32: 3039879.4 | K32: 3039879.4 | L32: 3039879.4 | M32: 13064682 | N32: 12817000 | O32: 12817308 | P32: 12817308 | Q32: 12817308 | R32: -3451056.8 | S32: -3451056.8 | T32: -3451056.8 | U32: -3451056.8 | V32: -3451056.8 | W32: -3451056.8 | X32: -3451056.8 | Y32: -3451056.8 | Z32: 19083326 | AA32: 15379000 | AB32: 11325272 | AC32: 10820854 | AD32: 10456260 | AE32: -23040670 | AF32: -39949661 | AG32: -40657750 | AH32: 196942.33 | AI32: 103456.85 | AJ32: -210726.57 | AK32: -159557.23 | AL32: 157459.18 | AM32: 14319700 | AN32: 2240000
A33: Dividends Payable | B33: 0 | C33: 0 | D33: 0 | E33: 0 | F33: 0 | G33: 0 | H33: 0 | I33: 0 | J33: 0 | K33: 0 | L33: 0 | M33: 0 | N33: 0 | O33: 0 | P33: 0 | Q33: 0 | R33: 0 | S33: 0 | T33: 0 | U33: 0 | V33: 0 | W33: 0 | X33: 0 | Y33: 0 | Z33: 0 | AB33: 0 | AC33: 0 | AD33: 0 | AE33: 0 | AF33: 0 | AG33: 0 | AH33: 0 | AI33: 0 | AJ33: 0 | AK33: 0 | AL33: 0 | AM33: 0 | AN33: 762218000
A34: Deferred Tax Liability | B34: 0 | C34: 0 | D34: 0 | E34: 0 | F34: 0 | G34: 0 | H34: 0 | I34: 0 | J34: 0 | K34: 0 | L34: 0 | M34: 0 | N34: 0 | O34: 0 | P34: 0 | Q34: 0 | R34: 0 | S34: 0 | T34: 0 | U34: 0 | V34: 0 | W34: 0 | X34: 0 | Y34: 0 | Z34: 0 | AB34: 0 | AC34: 0 | AD34: 0 | AE34: 0 | AF34: 0 | AG34: 0 | AH34: 0 | AI34: 0 | AJ34: 0 | AK34: 0 | AL34: 0 | AM34: 0
A35: Retirement Benefits Liabilty | B35: 0 | C35: 0 | D35: 0 | E35: 0 | F35: 0 | G35: 0 | H35: 0 | I35: 0 | J35: 0 | K35: 0 | L35: 0 | M35: 0 | N35: 0 | O35: 0 | P35: 0 | Q35: 0 | R35: 0 | S35: 0 | T35: 0 | U35: 0 | V35: 0 | W35: 0 | X35: 0 | Y35: 0 | Z35: 0 | AB35: 0 | AC35: 0 | AD35: 0 | AE35: 0 | AF35: 0 | AG35: 0 | AH35: 0 | AI35: 0 | AJ35: 0 | AK35: 0 | AL35: 0 | AM35: 0
A36: Other Liabilities | B36: 7.1218939e+08 | C36: 6.0643112e+08 | D36: 3.0872809e+08 | E36: 3.0129029e+08 | F36: 3.3508129e+08 | G36: 3.7629147e+08 | H36: 4.0954176e+08 | I36: 4.5232466e+08 | J36: 4.7767995e+08 | K36: 5.0732925e+08 | L36: 5.468888e+08 | M36: 6.509614e+08 | N36: 562738000 | O36: 6.2440856e+08 | P36: 3.8386607e+08 | Q36: 3.106408e+08 | R36: 3.4210022e+08 | S36: 3.6687118e+08 | T36: 3.6800003e+08 | U36: 4.099255e+08 | V36: 4.6916319e+08 | W36: 5.3639067e+08 | X36: 5.8534089e+08 | Y36: 6.2272632e+08 | Z36: 7.6431255e+08 | AA36: =151848000+576222000 -> 728070000 | AB36: 7.8814388e+08 | AC36: 8.2954885e+08 | AD36: 3.0815161e+08 | AE36: 3.5121546e+08 | AF36: 3.8241967e+08 | AG36: 4.2216949e+08 | AH36: 4.2848511e+08 | AI36: 4.715406e+08 | AJ36: 5.3655065e+08 | AK36: 5.8583919e+08 | AL36: 6.4384857e+08 | AM36: 8.020594e+08 | AN36: 89935000
A37: External Borrowings | B37: 0 | C37: 13804980 | D37: 0 | E37: 0 | F37: 0 | G37: 0 | H37: 0 | I37: 0 | J37: 0 | K37: 0 | L37: -95628.4 | M37: 8044913.8 | O37: 14029968 | P37: 12367621 | Q37: 7653936.5 | R37: 5131884 | S37: 5016337.2 | T37: 5063251.8 | U37: 2542171.3 | V37: 2679824.5 | W37: 2770985.6 | X37: 2706446.5 | Y37: 50138.87 | Z37: 18644831 | AB37: 16642260 | AC37: 16422883 | AD37: 7999025.4 | AE37: 5206074.7 | AF37: 5054477.4 | AG37: 5033276.8 | AH37: 5079730.7 | AI37: 5074863 | AJ37: 5024366.3 | AK37: 4966674.5 | AL37: 2828503.2 | AM37: 39213462
A38: Total Liabilities | B38: =SUM(B31:B37) -> 6.1270545e+09 | C38: =SUM(C31:C37) -> 6.1136302e+09 | D38: =SUM(D31:D37) -> 5.8795218e+09 | E38: =SUM(E31:E37) -> 5.9007129e+09 | F38: =SUM(F31:F37) -> 5.9851709e+09 | G38: =SUM(G31:G37) -> 6.0827598e+09 | H38: =SUM(H31:H37) -> 6.199185e+09 | I38: =SUM(I31:I37) -> 6.288936e+09 | ... AN38: =SUM(AN31:AN37) -> 8191574000
A39: Share Capital | B39: 3.3896874e+08 | C39: 345632751 | D39: 3.4843312e+08 | E39: 3.524745e+08 | F39: 3.5511752e+08 | G39: 3.5851755e+08 | H39: 3.6270301e+08 | I39: 3.6591878e+08 | J39: 3.6881766e+08 | K39: 3.7418783e+08 | L39: 3.7827165e+08 | M39: 4.3274797e+08 | N39: 432735000 | O39: 4.3535137e+08 | P39: 4.3895028e+08 | Q39: 4.434157e+08 | R39: 4.497373e+08 | S39: 4.5338392e+08 | T39: 4.5767317e+08 | U39: 4.61847e+08 | V39: 4.6542189e+08 | W39: 4.7002729e+08 | X39: 4.7418366e+08 | Y39: 4.7946819e+08 | Z39: 4.8574187e+08 | AA39: 485742000 | AB39: 4.8925978e+08 | AC39: 4.9453395e+08 | AD39: 5.0580535e+08 | AE39: 5.1132762e+08 | AF39: 5.1730788e+08 | AG39: 5.229283e+08 | AH39: 5.288884e+08 | AI39: 5.3555807e+08 | AJ39: 5.4303538e+08 | AK39: 5.5419559e+08 | AL39: 5.627931e+08 | AM39: 5.7003526e+08 | AN39: 570035000
A40: Capital Grants | B40: 0 | C40: 0 | D40: 0 | E40: 0 | F40: 0 | G40: 0 | H40: 0 | I40: 0 | J40: 0 | K40: 0 | L40: 0 | M40: 0 | N40: 0 | O40: 0 | P40: 0 | Q40: 0 | R40: 0 | S40: 0 | T40: 0 | U40: 0 | V40: 0 | W40: 0 | X40: 0 | Y40: 0 | Z40: 0 | AA40: 0 | AB40: 0 | AC40: 0 | AD40: 0 | AE40: 0 | AF40: 0 | AG40: 0 | AH40: 0 | AI40: 0 | AJ40: 0 | AK40: 0 | AL40: 0 | AM40: 0
A41: Prior Year Retained Earnigs | B41: 1.4389978e+08 | C41: 1.4424767e+08 | D41: 1.4421888e+08 | E41: 1.4410894e+08 | F41: 1.4410883e+08 | G41: 1.4410883e+08 | H41: 1.4410883e+08 | I41: 1.4410883e+08 | J41: 1.4341243e+08 | K41: 1.435261e+08 | L41: 1.434741e+08 | M41: 1.4605558e+08 | N41: 154932000 | O41: 1.1716123e+08 | P41: 1.1866549e+08 | Q41: 1.1860358e+08 | R41: 1.1860358e+08 | S41: 1.1859333e+08 | T41: 1.1859333e+08 | U41: 118483746 | V41: 1.1846944e+08 | W41: 1.1843865e+08 | X41: 1.1824667e+08 | Y41: 1.1822687e+08 | Z41: 1.1847687e+08 | AA41: 118477000 | AB41: 1.3706386e+08 | AC41: 1.3642706e+08 | AD41: 1.3635327e+08 | AE41: 1.3674492e+08 | AF41: 1.4183943e+08 | AG41: 1.459391e+08 | AH41: 1.4592546e+08 | AI41: 1.4592546e+08 | AJ41: 1.4592546e+08 | AK41: 1.4596592e+08 | AL41: 1.4596592e+08 | AM41: 1.4596592e+08 | AN41: 72861000
A42: Current Year Surplus | B42: -2595393.7 | C42: 13971720 | D42: 18261707 | E42: 32893276 | F42: 51343483 | G42: 71169876 | H42: 86717528 | I42: 89353494 | J42: 1.0372004e+08 | K42: 1.1692171e+08 | L42: 1.2574752e+08 | M42: 38280842 | N42: =174512000-34903000-64910000-99839000-6980000-6400000 -> -38520000 | O42: -77843073 | P42: -71467527 | Q42: 21557751 | R42: 28838470 | S42: 37547016 | T42: 88368236 | U42: 1.0428261e+08 | V42: 1.0255548e+08 | W42: 1.2854885e+08 | X42: 1.316829e+08 | Y42: 2.1130151e+08 | Z42: 44314382 | AA42: =175176000-35035000-72861000-33978000-7007000-8527000 -> 17768000 | AB42: -82589.46 | AC42: 36127469 | AD42: 66430022 | AE42: 88345425 | AF42: 1.1574185e+08 | AG42: 1.4724918e+08 | AH42: 1.5666965e+08 | AI42: 1.7406948e+08 | AJ42: 2.0759098e+08 | AK42: 2.3781501e+08 | AL42: 2.6025636e+08 | AM42: 90561573 | AN42: =85505000-72861000 -> 12644000
A43: Statutory Reserves | B43: 99053600 | C43: 99053600 | D43: 99053600 | E43: 99145215 | F43: 99145215 | G43: 99145215 | H43: 99145215 | I43: 99145215 | J43: 99145215 | K43: 99145215 | L43: 99145215 | M43: 1.2843879e+08 | N43: 134048000 | O43: 1.3404753e+08 | P43: 1.3404753e+08 | Q43: 1.3404753e+08 | R43: 1.3404753e+08 | S43: 1.3404753e+08 | T43: 1.3404753e+08 | U43: 1.3404753e+08 | V43: 1.3404753e+08 | W43: 1.3404753e+08 | X43: 1.3404753e+08 | Y43: 1.3404753e+08 | Z43: 1.6684636e+08 | AA43: 169083000 | AB43: 1.6908289e+08 | AC43: 1.6908289e+08 | AD43: 1.6908289e+08 | AE43: 1.6908289e+08 | AF43: 1.6908289e+08 | AG43: 1.6908289e+08 | AH43: 1.6908289e+08 | AI43: 1.6908289e+08 | AJ43: 1.6908289e+08 | AK43: 1.6908289e+08 | AL43: 1.6908289e+08 | AM43: 2.2131034e+08 | AN43: 202727000
A44: Other Reserves | B44: 1.7644741e+08 | C44: 1.7688583e+08 | D44: 1.8134541e+08 | E44: 1.8120908e+08 | F44: 1.8252183e+08 | G44: 1.835268e+08 | H44: 1.8493425e+08 | I44: 1.8788027e+08 | J44: 1.9044278e+08 | K44: 1.9220537e+08 | L44: 1.9389659e+08 | M44: 2.015751e+08 | N44: =148778000+141684000 -> 290462000 | O44: 2.9150901e+08 | P44: 2.9317737e+08 | Q44: 2.9516149e+08 | R44: 2.9768628e+08 | S44: 3.0040664e+08 | T44: 3.0370101e+08 | U44: 3.0568984e+08 | V44: 3.1044876e+08 | W44: 3.1314756e+08 | X44: 3.1566289e+08 | Y44: 3.1919829e+08 | Z44: 3.1609716e+08 | AA44: 167766000 | AB44: 3.5585233e+08 | AC44: 3.5786142e+08 | AD44: 3.5971349e+08 | AE44: 3.6215778e+08 | AF44: 3.6456001e+08 | AG44: 3.6481456e+08 | AH44: 3.675587e+08 | AI44: 3.7074878e+08 | AJ44: 3.7450861e+08 | AK44: 3.7725424e+08 | AL44: 3.8058184e+08 | AM44: 3.7259689e+08 | AN44: =299930000+203354000 -> 503284000
A45: Revaluation Reserves | B45: 36098063 | C45: 36098063 | D45: 36098063 | E45: 36098063 | F45: 36098063 | G45: 36098063 | H45: 36098063 | I45: 36098063 | J45: 36098063 | K45: 36098063 | L45: 36098063 | M45: 36098063 | N45: 36098000 | O45: 36098063 | P45: 36098063 | Q45: 36098063 | R45: 36098063 | S45: 36098063 | T45: 36098063 | U45: 36098063 | V45: 36098063 | W45: 36098063 | X45: 36098063 | Y45: 36098063 | Z45: 36098063 | AA45: 38768000 | AB45: 36098063 | AC45: 36098063 | AD45: 36098063 | AE45: 36098063 | AF45: 36098063 | AG45: 36098063 | AH45: 36098063 | AI45: 36098063 | AJ45: 36098063 | AK45: 36098063 | AL45: 36098063 | AM45: 36098063
A46: Proposed Dividends | B46: 0 | C46: 0 | D46: 0 | E46: 0 | F46: 0 | G46: 0 | H46: 0 | I46: 0 | J46: 0 | K46: 0 | L46: 0 | M46: 0 | N46: =64910000+6400000 -> 71310000 | O46: 0 | P46: 0 | Q46: 0 | R46: 0 | S46: 0 | T46: 0 | U46: 0 | V46: 0 | W46: 0 | X46: 0 | Y46: 0 | Z46: 0 | AA46: =81388000 -> 81388000 | AB46: 0 | AC46: 0 | AD46: 0 | AE46: 0 | AF46: 0 | AG46: 0 | AH46: 0 | AI46: 0 | AJ46: 0 | AK46: 0 | AL46: 0 | AM46: 0
A47: Adjustment To Equity | B47: 0 | C47: 0 | D47: 0 | E47: 0 | F47: 0 | G47: 0 | H47: 0 | I47: 0 | J47: 0 | K47: 0 | L47: 0 | M47: 0 | N47: 0 | O47: 0 | P47: 0 | Q47: 0 | R47: 0 | S47: 0 | T47: 0 | U47: 0 | V47: 0 | W47: 0 | X47: 0 | Y47: 0 | Z47: 0 | AA47: 182756000 | AB47: 0 | AC47: 0 | AD47: 0 | AE47: 0 | AF47: 0 | AG47: 0 | AH47: 0 | AI47: 0 | AJ47: 0 | AK47: 0 | AL47: 0 | AM47: 0
A48: Total Equity | B48: =SUM(B39:B47) -> 7.9187219e+08 | C48: =SUM(C39:C47) -> 8.1588963e+08 | D48: =SUM(D39:D47) -> 8.2741079e+08 | E48: =SUM(E39:E47) -> 8.4592908e+08 | F48: =SUM(F39:F47) -> 8.6833495e+08 | G48: =SUM(G39:G47) -> 8.9256634e+08 | H48: =SUM(H39:H47) -> 9.137069e+08 | I48: =SUM(I39:I47) -> 9.2250466e+08 | ... AN48: =SUM(AN39:AN47) -> 1361551000
A49: Total Liabilities and Equity | B49: =SUM(B48+B38) -> 6.9189267e+09 | C49: =SUM(C48+C38) -> 6.9295198e+09 | D49: =SUM(D48+D38) -> 6.7069325e+09 | E49: =SUM(E48+E38) -> 6.746642e+09 | F49: =SUM(F48+F38) -> 6.8535059e+09 | G49: =SUM(G48+G38) -> 6.9753261e+09 | H49: =SUM(H48+H38) -> 7.1128919e+09 | I49: =SUM(I48+I38) -> 7.2114407e+09 | ... AN49: =SUM(AN48+AN38) -> 9553125000
AA50: =AA49-AA27 -> -2000
B51: =B49-B27 -> -33343.49 | C51: =C49-C27 -> -0.40000057 | D51: =D49-D27 -> 0 | E51: =E49-E27 -> 0 | F51: =F49-F27 -> 0 | G51: =G49-G27 -> 0 | H51: =H49-H27 -> 0 | I51: =I49-I27 -> 0 | ... N51: =N49-N27 -> 0 | AN51: =AN49-AN27 -> 10453000

Sheet Evolutitve SCI
B2: 43831 | C2: 43862 | D2: 43891 | E2: 43922 | F2: 43952 | G2: 43983 | H2: 44013 | I2: 44044 | J2: 44075 | K2: 44105 | L2: 44136 | M2: 44166 | N2: AUDITED 2020 | O2: 44197 | P2: 44228 | Q2: 44256 | R2: 44287 | S2: 44317 | T2: 44348 | U2: 44378 | V2: 44409 | W2: 44440 | X2: 44470 | Y2: 44501 | Z2: 44531 | AA2: Audited 2021 | AB2: 44562 | AC2: 44593 | AD2: 44621 | AE2: 44652 | AF2: 44682 | AG2: 44713 | AH2: 44743 | AI2: 44774 | AJ2: 44805 | AK2: 44835 | AL2: 44866 | AM2: 44896 | AN2: Aud-22
A3: Financial Income | B3: =B4+B7 -> 52306145 | C3: =C4+C7 -> 1.1536999e+08 | D3: =D4+D7 -> 1.9583627e+08 | E3: =E4+E7 -> 2.5886877e+08 | F3: =F4+F7 -> 3.3201075e+08 | G3: =G4+G7 -> 4.0716797e+08 | H3: =H4+H7 -> 9.5332453e+08 | I3: =I4+I7 -> 5.4696414e+08 | ... AN3: =AN4+AN7 -> 1162675000
A4: Financial Income From Loans Portfolio | B4: =SUM(B5:B6) -> 43406556 | C4: =SUM(C5:C6) -> 97662235 | D4: =SUM(D5:D6) -> 1.7249303e+08 | E4: =SUM(E5:E6) -> 2.2997502e+08 | F4: =SUM(F5:F6) -> 2.972804e+08 | G4: =SUM(G5:G6) -> 3.5556035e+08 | H4: =SUM(H5:H6) -> 8.3092834e+08 | I4: =SUM(I5:I6) -> 4.7885759e+08 | ... AN4: =SUM(AN5:AN6) -> 1026147000
A5: Interest from Loans Portfolio | B5: 38601227 | C5: 90310521 | D5: 1.5531162e+08 | E5: 2.0771087e+08 | F5: 2.7051616e+08 | G5: 3.2530323e+08 | H5: 7.6513805e+08 | I5: 4.4216336e+08 | J5: 5.0337658e+08 | K5: 5.6458979e+08 | L5: 6.239282e+08 | M5: 7.1884011e+08 | N5: 715367000 | O5: 36935438 | P5: 1.6673137e+08 | Q5: 2.1407774e+08 | R5: 2.5896048e+08 | S5: 3.1748233e+08 | T5: 3.9208572e+08 | U5: 4.5556344e+08 | V5: 5.2427204e+08 | W5: 5.9583431e+08 | X5: 6.638262e+08 | Y5: 7.4756162e+08 | Z5: 8.0859846e+08 | AA5: =835521*1000-AA6 -> 803226000 | AB5: 74525992 | AC5: 1.5000407e+08 | AD5: 2.3063693e+08 | AE5: 3.063592e+08 | AF5: 3.8828414e+08 | AG5: 4.7046956e+08 | AH5: 5.49043e+08 | AI5: 6.2680262e+08 | AJ5: 7.1433301e+08 | AK5: 8.008878e+08 | AL5: 8.8925939e+08 | AM5: 9.8298313e+08 | AN5: 1026147000
A6: Fees&Commision on Loan Portfolio | B6: 4805328.3 | C6: 7351713.5 | D6: 17181414 | E6: 22264157 | F6: 26764236 | G6: 30257122 | H6: 65790294 | I6: 36694228 | J6: 39031002 | K6: 41367776 | L6: 43714148 | M6: 46361591 | N6: =46362000+1364000+2300000 -> 50026000 | O6: 1634874.6 | P6: 3407779.8 | Q6: 5269207 | R6: 8382611.2 | S6: 11347975 | T6: 13749145 | U6: 15564610 | V6: 20332139 | W6: 24160161 | X6: 26920231 | Y6: 30276736 | Z6: 32914307 | AA6: =32295*1000 -> 32295000 | AB6: 2144530.7 | AC6: 4984721.8 | AD6: 7106502.7 | AE6: 10671649 | AF6: 14906003 | AG6: 18300244 | AH6: 21613307 | AI6: 27516536 | AJ6: 33768241 | AK6: 39951843 | AL6: 46278387 | AM6: 50479757
A7: Financial Income from Investments | B7: =SUM(B8:B11) -> 8899589.1 | C7: =SUM(C8:C11) -> 17707757 | D7: =SUM(D8:D11) -> 23343240 | E7: =SUM(E8:E11) -> 28893744 | F7: =SUM(F8:F11) -> 34730356 | G7: =SUM(G8:G11) -> 51607621 | H7: =SUM(H8:H11) -> 1.2239619e+08 | I7: =SUM(I8:I11) -> 68106553 | ... AN7: =SUM(AN8:AN11) -> 136528000
A8: Government Securities | B8: 2624927.4 | C8: 5634922.6 | D8: 5979263.5 | E8: 6014345.6 | F8: 6052570.1 | G8: 6071437 | H8: 12235590 | I8: 6150231.7 | J8: 6183508.1 | K8: 6216784.6 | L8: 6267339.8 | M8: 12831208 | O8: 21123.7 | P8: 38391.7 | Q8: 12141848 | R8: 14383597 | S8: 14402857 | T8: 14414647 | U8: 14484163 | V8: 14497211 | W8: 14526933 | X8: 14544884 | Y8: 14556828 | Z8: 14565289 | AB8: 0 | AC8: 9300509.8 | AD8: 13148313 | AE8: 13550834 | AF8: 13576161 | AG8: 13694747 | AH8: 13730071 | AI8: 13739094 | AJ8: 16995818 | AK8: 18304376 | AL8: 21629152 | AM8: 21850105
A9: Deposits with Banks & other Financial Institutions | B9: 6265195.7 | C9: 12056687 | D9: 16131981 | E9: 21021931 | F9: 25532240 | G9: 41802227 | H9: 1.0176454e+08 | I9: 57663248 | J9: 66483375 | K9: 75303503 | L9: 80426526 | M9: 1.0110281e+08 | N9: 113934000 | O9: 9007367.9 | P9: 17905092 | Q9: 27625198 | R9: 33447054 | S9: 39703030 | T9: 55587243 | U9: 65186353 | V9: 74729122 | W9: 87732121 | X9: 95890161 | Y9: 1.0625949e+08 | Z9: 1.2296866e+08 | AA9: =137534*1000 -> 137534000 | AB9: 9241872.1 | AC9: 17940010 | AD9: 28738515 | AE9: 36236792 | AF9: 44973648 | AG9: 59797487 | AH9: 58002044 | AI9: 67829839 | AJ9: 78136462 | AK9: 86484165 | AL9: 93748750 | AM9: 1.0901051e+08 | AN9: 118976000
A10: Other Investments | B10: 0 | C10: 0 | D10: 234080 | E10: 839312.1 | F10: 839312.1 | G10: 839312.1 | H10: 1678624.2 | I10: 839312.1 | J10: 839312.1 | K10: 839312.1 | L10: 839312.1 | M10: 839312.1 | N10: 0 | O10: 0 | P10: 98743 | Q10: 98743 | R10: 696939.3 | S10: 696939.3 | T10: 696939.3 | U10: 696939.3 | V10: 696939.3 | W10: 829863.3 | X10: 829863.3 | Y10: 829863.3 | Z10: 904908.3 | AB10: 0 | AC10: 0 | AD10: 0 | AE10: 0 | AF10: 159508.8 | AG10: 741943.1 | AH10: 741943.1 | AI10: 741943.1 | AJ10: 741943.1 | AK10: 741943.1 | AL10: 741943.1 | AM10: 741943.1
A11: Other Operating Income | B11: 9466.02 | C11: 16146.59 | D11: 997915.59 | E11: 1018155.9 | F11: 2306234.7 | G11: 2894644.7 | H11: 6717429.3 | I11: 3453761.9 | J11: 3556770.7 | K11: 3659779.5 | L11: 4546021.1 | M11: 6126845.1 | N11: =10421000-2300000-1364000 -> 6757000 | O11: 62028 | P11: 569006 | Q11: 1412021.9 | R11: 3547332.8 | S11: 3918766.6 | T11: 4184460.5 | U11: 5350088 | V11: 6593192.3 | W11: 6884237.1 | X11: 8809181 | Y11: 8956232.8 | Z11: 8813784.9 | AA11: =15711*1000 -> 15711000 | AB11: 651102.94 | AC11: 724652.32 | AD11: 3672962.6 | AE11: 3918571.4 | AF11: 4226784.8 | AG11: 5239683.9 | AH11: 5542343.2 | AI11: 5705811.3 | AJ11: 7433180 | AK11: 8350093.9 | AL11: 9333022.8 | AM11: 9531428.5 | AN11: 17552000
A12: Financial Expenses | B12: =SUM(B13:B18) -> 35841893 | C12: =SUM(C13:C18) -> 70623452 | D12: =SUM(D13:D18) -> 1.1108601e+08 | E12: =SUM(E13:E18) -> 1.483571e+08 | F12: =SUM(F13:F18) -> 1.9139303e+08 | G12: =SUM(G13:G18) -> 2.3492764e+08 | H12: =SUM(H13:H18) -> 5.509844e+08 | I12: =SUM(I13:I18) -> 3.1619005e+08 | ... AN12: =SUM(AN13:AN18) -> 601754000
A13: Interest Expense on Deposits | B13: 35916788 | C13: 70620497 | D13: 1.1108601e+08 | E13: 1.4869413e+08 | F13: 1.9139303e+08 | G13: 2.344911e+08 | H13: 5.4977442e+08 | I13: 3.1539068e+08 | J13: 3.5651565e+08 | K13: 3.9764062e+08 | L13: 4.3995638e+08 | M13: 485343088 | N13: 485441000 | O13: 27335989 | P13: 27692885 | Q13: 1.4617999e+08 | R13: 1.7928103e+08 | S13: 2.1753203e+08 | T13: 2.4564154e+08 | U13: 2.8436825e+08 | V13: 3.2720803e+08 | W13: 3.7235533e+08 | X13: 4.1349026e+08 | Y13: 4.630795e+08 | Z13: 5.0568202e+08 | AA13: =531044*1000 -> 531044000 | AB13: 41014531 | AC13: 86605494 | AD13: 1.3872804e+08 | AE13: 1.8155551e+08 | AF13: 2.2826598e+08 | AG13: 2.7825209e+08 | AH13: 3.1771244e+08 | AI13: 3.6358741e+08 | AJ13: 4.169386e+08 | AK13: 4.6751372e+08 | AL13: 5.1951708e+08 | AM13: 5.7509341e+08 | AN13: 601754000
A14: Cost of External Borrowings | B14: 0 | C14: 0 | D14: 0 | E14: 0 | F14: 0 | G14: 0 | H14: 0 | I14: 0 | J14: 0 | K14: 0 | L14: 0 | M14: 0 | N14: 0 | O14: 0 | P14: 0 | Q14: 0 | R14: 0 | S14: 0 | T14: 0 | U14: 0 | V14: 0 | W14: 0 | X14: 0 | Y14: 0 | Z14: 0 | AB14: 0 | AC14: 0 | AD14: 0 | AE14: 0 | AF14: 0 | AG14: 0 | AH14: 0 | AI14: 0 | AJ14: 0 | AK14: 0 | AL14: 0 | AM14: 0
A15: Dividend Expenses | B15: 0 | C15: 0 | D15: 0 | E15: 0 | F15: 0 | G15: 0 | H15: 0 | I15: 0 | J15: 0 | K15: 0 | L15: 0 | M15: 64912195 | N15: 0 | O15: 0 | P15: 0 | Q15: 0 | R15: 0 | S15: 0 | T15: 0 | U15: 0 | V15: 0 | W15: 0 | X15: 0 | Y15: 0 | Z15: 72861280 | AB15: 0 | AC15: 0 | AD15: 0 | AE15: 0 | AF15: 0 | AG15: 0 | AH15: 0 | AI15: 0 | AJ15: 0 | AK15: 0 | AL15: 0 | AM15: 85505289
A16: Other Financial Expense | B16: -74894.97 | C16: 2954.69 | D16: 0 | E16: -337024.44 | F16: 0 | G16: 436535.01 | H16: 1209982.4 | I16: 799362.39 | J16: 990812.79 | K16: 1182263.2 | L16: 1337061.9 | M16: 1553773.7 | N16: 0 | O16: 169639.25 | P16: 312982.15 | Q16: 559481.63 | R16: 719551.98 | S16: 874209.92 | T16: 1046852.2 | U16: 1199903.4 | V16: 1373085.4 | W16: 1504913.1 | X16: 1666506.2 | Y16: 1819899.6 | Z16: 1992512.7 | AB16: 118373.07 | AC16: 303431.21 | AD16: 511292.73 | AE16: 692487.51 | AF16: 878974.79 | AG16: 1066687.1 | AH16: 1202043 | AI16: 1349778.6 | AJ16: 1502232.7 | AK16: 1653649.9 | AL16: 1782796.4 | AM16: 1924310.9
A17: Fees & Commision Expense | B17: 0 | C17: 0 | D17: 0 | E17: 0 | F17: 0 | G17: 0 | H17: 0 | I17: 0 | J17: 0 | K17: 0 | L17: 0 | M17: 0 | N17: 0 | O17: 0 | P17: 0 | Q17: 0 | R17: 0 | S17: 0 | T17: 0 | U17: 0 | V17: 0 | W17: 0 | X17: 0 | Y17: 0 | Z17: 0 | AB17: 0 | AC17: 0 | AD17: 0 | AE17: 0 | AF17: 0 | AG17: 0 | AH17: 0 | AI17: 0 | AJ17: 0 | AK17: 0 | AL17: 0 | AM17: 0
A18: Other Expenses | B18: 0 | C18: 0 | D18: 0 | E18: 0 | F18: 0 | G18: 0 | H18: 0 | I18: 0 | J18: 0 | K18: 0 | L18: 0 | M18: 0 | N18: 0 | O18: 0 | P18: 0 | Q18: 0 | R18: 0 | S18: 0 | T18: 0 | U18: 0 | V18: 0 | W18: 0 | X18: 0 | Y18: 0 | Z18: 0 | AB18: 0 | AC18: 0 | AD18: 0 | AE18: 0 | AF18: 0 | AG18: 0 | AH18: 0 | AI18: 0 | AJ18: 0 | AK18: 0 | AL18: 0 | AM18: 62672939
A19: Net Financial Income | B19: =B3-B12 -> 16464252 | C19: =C3-C12 -> 44746540 | D19: =D3-D12 -> 84750265 | E19: =E3-E12 -> 1.1051166e+08 | F19: =F3-F12 -> 1.4061773e+08 | G19: =G3-G12 -> 1.7224033e+08 | H19: =H3-H12 -> 4.0234013e+08 | I19: =I3-I12 -> 2.3077409e+08 | ... AN19: =AN3-AN12 -> 560921000
A20: Allowance for Loan Loss | B20: =B21-B22 -> 8097355.9 | C20: =C21-C22 -> 8097355.9 | D20: =D21-D22 -> 29963659 | E20: =E21-E22 -> 29963659 | F20: =F21-F22 -> 29963659 | G20: =G21-G22 -> 29963659 | H20: =H21-H22 -> 59927318 | I20: =I21-I22 -> 40471280 | ... AN20: =AN21-AN22 -> 75680000
A21: Provision for Loan Losses | B21: 8097355.9 | C21: 8097355.9 | D21: 29963659 | E21: 29963659 | F21: 29963659 | G21: 29963659 | H21: 59927318 | I21: 40471280 | J21: 40471280 | K21: 40471280 | L21: 40471280 | M21: 52963275 | N21: 52963000 | O21: 85468766 | P21: 2.0854619e+08 | Q21: 54852479 | R21: 61929664 | S21: 69006848 | T21: 69006848 | U21: 74161752 | V21: 86574497 | W21: 86574497 | X21: 1.0183954e+08 | Y21: 54345968 | Z21: 71978013 | AA21: =37999*1000 -> 37999000 | AB21: 32576462 | AC21: 32576462 | AD21: 32576462 | AE21: 32576462 | AF21: 32576462 | AG21: 32576462 | AH21: 32576462 | AI21: 32576462 | AJ21: 32576462 | AK21: 32576462 | AL21: 32576462 | AM21: 32576462 | AN21: 75680000
A22: Value of Loans Recovered | B22: 0 | C22: 0 | D22: 0 | E22: 0 | F22: 0 | G22: 0 | H22: 0 | I22: 0 | J22: 0 | K22: 0 | L22: 0 | M22: 0 | N22: 0 | O22: 0 | P22: 0 | Q22: 0 | R22: 0 | S22: 0 | T22: 0 | U22: 0 | V22: 0 | W22: 0 | X22: 0 | Y22: 0 | Z22: 0 | AB22: 0 | AC22: 0 | AD22: 0 | AE22: 0 | AF22: 0 | AG22: 0 | AH22: 0 | AI22: 0 | AJ22: 0 | AK22: 0 | AL22: 0 | AM22: 0
A23: Operating Expeses | B23: =SUM(B24:B28) -> 10962290 | C23: =SUM(C24:C28) -> 22677464 | D23: =SUM(D24:D28) -> 36524899 | E23: =SUM(E24:E28) -> 47354729 | F23: =SUM(F24:F28) -> 58963797 | G23: =SUM(G24:G28) -> 70663335 | H23: =SUM(H24:H28) -> 1.6809083e+08 | I23: =SUM(I24:I28) -> 1.0049586e+08 | ... AN23: =SUM(AN24:AN28) -> 308034000
A24: Personel Expenses | B24: 7566742.5 | C24: 14935998 | D24: 22021168 | E24: 28928438 | F24: 35822844 | G24: 42826651 | H24: 99571304 | I24: 56721001 | J24: 65846904 | K24: 74972807 | L24: 80565064 | M24: 92315991 | N24: 0 | O24: 7367618.5 | P24: 14337990 | Q24: 22608881 | R24: 30947496 | S24: 39570440 | T24: 49938208 | U24: 59228699 | V24: 68272835 | W24: 77528728 | X24: 87012238 | Y24: 97030580 | Z24: 1.1204564e+08 | AA24: =112046*1000 -> 112046000 | AB24: 9366631.9 | AC24: 17756228 | AD24: 27754893 | AE24: 38553645 | AF24: 48745477 | AG24: 59348842 | AH24: 70833354 | AI24: 81776884 | AJ24: 92977517 | AK24: 1.0357181e+08 | AL24: 1.15256e+08 | AM24: 1.265911e+08 | AN24: 127549000
A25: Governance Expenses | B25: 657026 | C25: 1577277 | D25: 2878632 | E25: 3216939 | F25: 3758126 | G25: 4193370 | H25: 10603894 | I25: 5805233 | J25: 6438271 | K25: 7071309 | L25: 9083546 | M25: 18026583 | N25: 23485000 | O25: 353040 | P25: 732369 | Q25: 1419910 | R25: 1879860 | S25: 2821970 | T25: 3314720 | U25: 5455800 | V25: 7110742 | W25: 8035942 | X25: 9899777 | Y25: 11964613 | Z25: 20903487 | AA25: =7174*1000+16565*1000 -> 23739000 | AB25: 794988 | AC25: 1684348 | AD25: 3522245.7 | AE25: 5066488 | AF25: 6838060 | AG25: 7986578 | AH25: 11181078 | AI25: 12173541 | AJ25: 13636138 | AK25: 15000868 | AL25: 17795520 | AM25: 45346944 | AN25: 56947000
A26: Marketing Expenses | B26: 454203.51 | C26: 1668843.7 | D26: 4520654.6 | E26: 5675864.2 | F26: 7279396 | G26: 9144668.1 | H26: 22155182 | I26: 14255656 | J26: 16281045 | K26: 18306435 | L26: 19996023 | M26: 24839927 | N26: 0 | O26: 719413.22 | P26: 1369365 | Q26: 3841872.6 | R26: 4524009.1 | S26: 5425600.6 | T26: 6215024.8 | U26: 7576044.8 | V26: 8518428.9 | W26: 10223945 | X26: 11565980 | Y26: 12553604 | Z26: 17104098 | AB26: 65471.67 | AC26: 1819877.7 | AD26: 3646381.1 | AE26: 6416016.5 | AF26: 8938656.6 | AG26: 11534697 | AH26: 15007593 | AI26: 19103730 | AJ26: 22804135 | AK26: 27067498 | AL26: 31874855 | AM26: 39780697 | AN26: 9712000
A27: Depreciation and Amortization | B27: 648295.53 | C27: 1254723.7 | D27: 1927095.1 | E27: 2606455.5 | F27: 3330662.1 | G27: 4031459.2 | H27: 9574314.6 | I27: 5550797.9 | J27: 6289752.7 | K27: 7028707.5 | L27: 7795826.7 | M27: 8725551 | N27: =5331000+3395000 -> 8726000 | O27: 836153.1 | P27: 1508878.2 | Q27: 2143158 | R27: 2757733.6 | S27: 3392795.3 | T27: 4008164 | U27: 4667852 | V27: 5327459.5 | W27: 6018051.5 | X27: 6742231.4 | Y27: 7450056.6 | Z27: 8200619.6 | AA27: =1825*1000+7184*1000 -> 9009000 | AB27: 690109.39 | AC27: 1357215.6 | AD27: 2074815.6 | AE27: 3260289.2 | AF27: 5381727.4 | AG27: 7477764.2 | AH27: 9643999.4 | AI27: 11809712 | AJ27: 13915719 | AK27: 16110519 | AL27: 18231978 | AM27: 20701432 | AN27: 20702000
A28: Administrative Expenses | B28: 1636022.3 | C28: 3240621.8 | D28: 5177349.2 | E28: 6927032.2 | F28: 8772769.3 | G28: 10467187 | H28: 26186138 | I28: 18163171 | J28: 22789643 | K28: 27416115 | L28: 34465576 | M28: 47700503 | N28: =162236000-5331000-3395000 -> 153510000 | O28: 1570006.1 | P28: 4033976.2 | Q28: 7461236.1 | R28: 8540209.1 | S28: 11380993 | T28: 13178567 | U28: 15904687 | V28: 34180092 | W28: 39177370 | X28: 46921081 | Y28: 50927585 | Z28: 72459008 | AA28: =45208000+40406*1000-AA27 -> 76605000 | AB28: 1819520.4 | AC28: 4523440.7 | AD28: 7859067 | AE28: 14070721 | AF28: 18559049 | AG28: 22551370 | AH28: 33646094 | AI28: 45688846 | AJ28: 49266876 | AK28: 53210683 | AL28: 63499593 | AM28: 72658833 | AN28: 93124000
A29: Net Operating Income | B29: =B19-B20-B23 -> -2595393.6 | C29: =C19-C20-C23 -> 13971720 | D29: =D19-D20-D23 -> 18261707 | E29: =E19-E20-E23 -> 33193275 | F29: =F19-F20-F23 -> 51690269 | G29: =G19-G20-G23 -> 71613336 | H29: =H19-H20-H23 -> 1.7432198e+08 | I29: =I19-I20-I23 -> 89806954 | ... AN29: =AN19-AN20-AN23 -> 177207000
A30: Net Non operating Income/Expense | B30: =B31-B32 -> -35280 | C30: =C31-C32 -> -35280 | D30: =D31-D32 -> 0 | E30: =E31-E32 -> -35280 | F30: =F31-F32 -> -35280 | G30: =G31-G32 -> -35280 | H30: =H31-H32 -> -70560 | I30: =I31-I32 -> -35280 | ... AN30: =AN31-AN32 -> 0
A31: Non Operating Income | B31: 0 | C31: 0 | D31: 0 | E31: 0 | F31: 0 | G31: 0 | H31: 0 | I31: 0 | J31: 0 | K31: 0 | L31: 0 | M31: 0 | N31: 0 | O31: 0 | P31: 0 | Q31: 0 | R31: 0 | S31: 0 | T31: 0 | U31: 0 | V31: 0 | W31: 0 | X31: 0 | Y31: 0 | Z31: 0 | AB31: 0 | AC31: 0 | AD31: 0 | AE31: 0 | AF31: 0 | AG31: 0 | AH31: 0 | AI31: 0 | AJ31: 0 | AK31: 0 | AL31: 0 | AM31: 0
A32: Non Operating Expense | B32: 35280 | C32: 35280 | D32: 0 | E32: 35280 | F32: 35280 | G32: 35280 | H32: 70560 | I32: 35280 | J32: 35280 | K32: 35280 | L32: 35280 | M32: 35280 | N32: 0 | O32: 203280 | P32: 203280 | Q32: 203280 | R32: 203280 | S32: 203280 | T32: 203280 | U32: 203280 | V32: 203280 | W32: 203280 | X32: 203280 | Y32: 203280 | Z32: 203280 | AB32: 0 | AC32: 0 | AD32: 0 | AE32: 0 | AF32: 0 | AG32: 0 | AH32: 0 | AI32: 0 | AJ32: 0 | AK32: 0 | AL32: 0 | AM32: 0
A33: Net Income(Before Tax & Donations) | B33: =B29+B30 -> -2630673.6 | C33: =C29+C30 -> 13936440 | D33: =D29+D30 -> 18261707 | E33: =E29+E30 -> 33157995 | F33: =F29+F30 -> 51654989 | G33: =G29+G30 -> 71578056 | H33: =H29+H30 -> 1.7425142e+08 | I33: =I29+I30 -> 89771674 | ... AN33: =AN29+AN30 -> 177207000
A34: Taxes | B34: 0 | C34: 0 | D34: 0 | E34: 0 | F34: 0 | G34: 0 | H34: 0 | I34: 0 | J34: 0 | K34: 0 | L34: 0 | M34: 15983292 | N34: 0 | O34: 0 | P34: 0 | Q34: 0 | R34: 0 | S34: 0 | T34: 0 | U34: 0 | V34: 0 | W34: 0 | X34: 0 | Y34: 0 | Z34: 22503826 | AA34: =23147*1000 -> 23147000 | AB34: 0 | AC34: 0 | AD34: 0 | AE34: 0 | AF34: 0 | AG34: 0 | AH34: 0 | AI34: 0 | AJ34: 0 | AK34: 0 | AL34: 0 | AM34: 20982677
A35: Net Income(After Tax Before Donations) | B35: =B33-B34 -> -2630673.6 | C35: =C33-C34 -> 13936440 | D35: =D33-D34 -> 18261707 | E35: =E33-E34 -> 33157995 | F35: =F33-F34 -> 51654989 | G35: =G33-G34 -> 71578056 | H35: =H33-H34 -> 1.7425142e+08 | I35: =I33-I34 -> 89771674 | ... AN35: =AN33-AN34 -> 177207000
A36: Donations | B36: 0 | C36: 0 | D36: 0 | E36: 300000 | F36: 300000 | G36: 304560 | H36: 609120 | I36: 304560 | J36: 304560 | K36: 304560 | L36: -304560 | M36: -304560 | N36: 15736000 | AB36: -200000 | AC36: -200000 | AD36: -200000 | AE36: -200000 | AF36: -200000 | AG36: -200000 | AH36: -200000 | AI36: -200000 | AJ36: -200000 | AK36: -200000 | AL36: -200000 | AM36: -201210
A37: Net Income/(After Tax & Donations) | B37: =B35-B36 -> -2630673.6 | C37: =C35-C36 -> 13936440 | D37: =D35-D36 -> 18261707 | E37: =E35-E36 -> 32857995 | F37: =F35-F36 -> 51354989 | G37: =G35-G36 -> 71273496 | H37: =H35-H36 -> 1.736423e+08 | I37: =I35-I36 -> 89467114 | ... AN37: =AN35-AN36 -> 177207000
A39: Total Expenses | B39: =B12+B23 -> 46804182 | C39: =C12+C23 -> 93300915 | D39: =D12+D23 -> 1.4761091e+08 | E39: =E12+E23 -> 1.9571183e+08 | F39: =F12+F23 -> 2.5035682e+08 | G39: =G12+G23 -> 3.0559097e+08 | H39: =H12+H23 -> 7.1907523e+08 | I39: =I12+I23 -> 4.1668591e+08 | ... AF39: =AF12+AF23 -> 3.1760793e+08

Sheet FORM 4
D2: 43891
B3: CLASSIFICATION | C3: NO. OF A/Cs | D3: OUTSTANDING LOAN PORTFOLIO(Kshs) | E3: REQUIRED PROVISION | F3: REQUIRED PROVISION AMOUNT(Kshs)
B4: Performing | C4: 11812 | D4: 7.6526299e+09 | E4: 0.01 | F4: =D4*E4 -> 76526299
B5: Watch | C5: 3404 | D5: 2.188066e+09 | E5: 0.05 | F5: =D5*E5 -> 1.094033e+08
B6: Substandard | C6: 1506 | D6: 6.8259044e+08 | E6: 0.25 | F6: =D6*E6 -> 1.7064761e+08
B7: Doubtful | C7: 508 | D7: 1.4039815e+08 | E7: 0.5 | F7: =D7*E7 -> 70199075
B8: Loss | C8: 1206 | D8: 1.3261675e+08 | E8: 1 | F8: =D8*E8 -> 1.3261675e+08
B9: Sub-total | C9: =SUM(C4:C8) -> 18436 | D9: =SUM(D4:D8) -> 1.0796301e+10 | E9: 1.81 | F9: =SUM(F4:F8) -> 5.5939303e+08
C10: NPL | D10: =SUM(D6:D8) -> 9.5560534e+08
C11: PAR | D11: =D10/D9 -> 0.088512289
D14: 43983
B15: CLASSIFICATION | C15: NO. OF A/Cs | D15: OUTSTANDING LOAN PORTFOLIO(Kshs) | E15: REQUIRED PROVISION | F15: REQUIRED PROVISION AMOUNT(Kshs)
B16: Performing | C16: 5661 | D16: 3.5091131e+09 | E16: 0.01 | F16: =D16*E16 -> 35091131
B17: Watch | C17: 1712 | D17: 1.1514882e+09 | E17: 0.05 | F17: =D17*E17 -> 57574410 | H17: 11812
B18: Substandard | C18: 1187 | D18: 5.5435741e+08 | E18: 0.25 | F18: =D18*E18 -> 1.3858935e+08 | H18: 3404
B19: Doubtful | C19: 246 | D19: 62601627 | E19: 0.5 | F19: =D19*E19 -> 31300813 | H19: 1506
B20: Loss | C20: 670 | D20: 72780269 | E20: 1 | F20: =D20*E20 -> 72780269 | H20: 508
B21: Sub-total | C21: =SUM(C16:C20) -> 9476 | D21: =SUM(D16:D20) -> 5.3503406e+09 | E21: 1.81 | F21: =SUM(F16:F20) -> 3.3533598e+08 | H21: 1206
C22: NPL | D22: =SUM(D18:D20) -> 6.897393e+08 | H22: KIMISITU
C23: PAR | D23: =D22/D21 -> 0.12891503 | H23: 7.6526299e+09
H24: 2.188066e+09
H25: 6.8259044e+08
H26: 1.4039815e+08
D27: 44075 | H27: 1.3261675e+08
B28: CLASSIFICATION | C28: NO. OF A/Cs | D28: OUTSTANDING LOAN PORTFOLIO(Kshs) | E28: REQUIRED PROVISION | F28: REQUIRED PROVISION AMOUNT(Kshs)
B29: Performing | C29: 5914 | D29: 3.5082788e+09 | E29: 0.01 | F29: =D29*E29 -> 35082788
B30: Watch | C30: 2272 | D30: 1.3035993e+09 | E30: 0.05 | F30: =D30*E30 -> 65179965
B31: Substandard | C31: 1287 | D31: 6.4721095e+08 | E31: 0.25 | F31: =D31*E31 -> 1.6180274e+08
B32: Doubtful | C32: 210 | D32: 56010066 | E32: 0.5 | F32: =D32*E32 -> 28005033
B33: Loss | C33: 754 | D33: 80879265 | E33: 1 | F33: =D33*E33 -> 80879265
B34: Sub-total | C34: =SUM(C29:C33) -> 10437 | D34: =SUM(D29:D33) -> 5.5959784e+09 | E34: 1.81 | F34: =SUM(F29:F33) -> 3.7094979e+08
C35: NPL | D35: =SUM(D31:D33) -> 7.8410028e+08
C36: PAR | D36: =D35/D34 -> 0.14011853
D38: 44621
B39: CLASSIFICATION | C39: NO. OF A/Cs | D39: OUTSTANDING LOAN PORTFOLIO(Kshs) | E39: REQUIRED PROVISION | F39: REQUIRED PROVISION AMOUNT(Kshs)
B40: Performing | C40: 6895 | D40: 4.8188063e+09 | E40: 0.01 | F40: =D40*E40 -> 48188063
B41: Watch | C41: 1462 | D41: 1.0290779e+09 | E41: 0.05 | F41: =D41*E41 -> 51453897
B42: Substandard | C42: 664 | D42: 3.7026432e+08 | E42: 0.25 | F42: =D42*E42 -> 92566080
B43: Doubtful | C43: 198 | D43: 1.1730296e+08 | E43: 0.5 | F43: =D43*E43 -> 58651480
B44: Loss | C44: 645 | D44: 86302149 | E44: 1 | F44: =D44*E44 -> 86302149
B45: Sub-total | C45: =SUM(C40:C44) -> 9864 | D45: =SUM(D40:D44) -> 6.4217537e+09 | E45: 1.81 | F45: =SUM(F40:F44) -> 3.3716167e+08
C46: NPL | D46: =SUM(D42:D44) -> 5.7386943e+08
C47: PAR | D47: =D46/D45 -> 0.089363351

Sheet CAELS
A1: STIMA SACCO 2017 CAELS
D2: 43831 | E2: 43862 | F2: 43891 | G2: 43922 | H2: 43952 | I2: 43983 | J2: 44013 | K2: 44044 | L2: 44075 | M2: 44105 | N2: 44136 | O2: 44166 | P2: AUDITED 2020 | Q2: 44197 | R2: 44228 | S2: 44256 | T2: 44287 | U2: 44317 | V2: 44348 | W2: 44378 | X2: 44409 | Y2: 44440 | Z2: 44470 | AA2: 44501 | AB2: 44531 | AC2: Audited 2021 | AD2: 44562 | AE2: 44593 | AF2: 44621 | AG2: 44652 | AH2: 44682 | AI2: 44713 | AJ2: 44743 | AK2: 44774 | AL2: 44805 | AM2: 44835 | AN2: 44866 | AO2: 44896 | AP2: Aud-22
A3: CAPITAL ADEQUACY | B3: Core Capital | C3: 10 M | D3: =(('Evolutive SFP'!B39+'Evolutive SFP'!B40+'Evolutive SFP'!B41+'Evolutive SFP'!B42+'Evolutive SFP'!B43+'Evolutive SFP'!B44)-'Evolutive SFP'!B10)/1000000 -> 755.77413 | E3: =(('Evolutive SFP'!C39+'Evolutive SFP'!C40+'Evolutive SFP'!C41+'Evolutive SFP'!C42+'Evolutive SFP'!C43+'Evolutive SFP'!C44)-'Evolutive SFP'!C10)/1000000 -> 779.79157 | F3: =(('Evolutive SFP'!D39+'Evolutive SFP'!D40+'Evolutive SFP'!D41+'Evolutive SFP'!D42+'Evolutive SFP'!D43+'Evolutive SFP'!D44)-'Evolutive SFP'!D10)/1000000 -> 791.31272 | G3: =(('Evolutive SFP'!E39+'Evolutive SFP'!E40+'Evolutive SFP'!E41+'Evolutive SFP'!E42+'Evolutive SFP'!E43+'Evolutive SFP'!E44)-'Evolutive SFP'!E10)/1000000 -> 809.83102 | H3: =(('Evolutive SFP'!F39+'Evolutive SFP'!F40+'Evolutive SFP'!F41+'Evolutive SFP'!F42+'Evolutive SFP'!F43+'Evolutive SFP'!F44)-'Evolutive SFP'!F10)/1000000 -> 832.23689 | I3: =(('Evolutive SFP'!G39+'Evolutive SFP'!G40+'Evolutive SFP'!G41+'Evolutive SFP'!G42+'Evolutive SFP'!G43+'Evolutive SFP'!G44)-'Evolutive SFP'!G10)/1000000 -> 856.46827 | J3: =(('Evolutive SFP'!H39+'Evolutive SFP'!H40+'Evolutive SFP'!H41+'Evolutive SFP'!H42+'Evolutive SFP'!H43+'Evolutive SFP'!H44)-'Evolutive SFP'!H10)/1000000 -> 877.60884 | K3: =(('Evolutive SFP'!I39+'Evolutive SFP'!I40+'Evolutive SFP'!I41+'Evolutive SFP'!I42+'Evolutive SFP'!I43+'Evolutive SFP'!I44)-'Evolutive SFP'!I10)/1000000 -> 886.4066 | ... AT3: =(('Evolutive SFP'!AR39+'Evolutive SFP'!AR40+'Evolutive SFP'!AR41+'Evolutive SFP'!AR42+'Evolutive SFP'!AR43+'Evolutive SFP'!AR44)-'Evolutive SFP'!AR10)/1000000 -> 0
B4: CCA | C4: Min 10% | D4: =D3/(('Evolutive SFP'!B27)/1000000) -> 0.10923233 | E4: =E3/(('Evolutive SFP'!C27)/1000000) -> 0.11253183 | F4: =F3/(('Evolutive SFP'!D27)/1000000) -> 0.1179843 | G4: =G3/(('Evolutive SFP'!E27)/1000000) -> 0.12003468 | H4: =H3/(('Evolutive SFP'!F27)/1000000) -> 0.12143229 | I4: =I3/(('Evolutive SFP'!G27)/1000000) -> 0.12278541 | J4: =J3/(('Evolutive SFP'!H27)/1000000) -> 0.12338285 | K4: =K3/(('Evolutive SFP'!I27)/1000000) -> 0.12291671 | ... AT4: =AT3/(('Evolutive SFP'!AR27)/1000000) -> #DIV/0!
B5: CCD | C5: Min 8% | D5: =D3/('Evolutive SFP'!B31/1000000) -> 0.13984079 | E5: =E3/('Evolutive SFP'!C31/1000000) -> 0.14221827 | F5: =F3/('Evolutive SFP'!D31/1000000) -> 0.14231062 | G5: =G3/('Evolutive SFP'!E31/1000000) -> 0.14470615 | H5: =H3/('Evolutive SFP'!F31/1000000) -> 0.14737552 | I5: =I3/('Evolutive SFP'!G31/1000000) -> 0.15016727 | J5: =J3/('Evolutive SFP'!H31/1000000) -> 0.15166217 | K5: =K3/('Evolutive SFP'!I31/1000000) -> 0.15194921 | ... AT5: =AT3/('Evolutive SFP'!AR31/1000000) -> #DIV/0!
B6: ICA | C6: Min 8% | D6: =((D3*1000000)-'Evolutive SFP'!B39)/'Evolutive SFP'!B27 -> 0.060241046 | E6: =((E3*1000000)-'Evolutive SFP'!C39)/'Evolutive SFP'!C27 -> 0.062653521 | F6: =((F3*1000000)-'Evolutive SFP'!D39)/'Evolutive SFP'!D27 -> 0.066033108 | G6: =((G3*1000000)-'Evolutive SFP'!E39)/'Evolutive SFP'!E27 -> 0.067790246 | H6: =((H3*1000000)-'Evolutive SFP'!F39)/'Evolutive SFP'!F27 -> 0.069616831 | I6: =((I3*1000000)-'Evolutive SFP'!G39)/'Evolutive SFP'!G27 -> 0.071387448 | J6: =((J3*1000000)-'Evolutive SFP'!H39)/'Evolutive SFP'!H27 -> 0.072390505 | K6: =((K3*1000000)-'Evolutive SFP'!I39)/'Evolutive SFP'!I27 -> 0.072175289 | ... AT6: =((AT3*1000000)-'Evolutive SFP'!AR39)/'Evolutive SFP'!AR27 -> #DIV/0!
A7: ASSET QUALITY | B7: A/LNPL30
B8: NPL30 | D8: =('FORM 4'!#REF!+'FORM 4'!#REF!+'FORM 4'!#REF!)/'Evolutive SFP'!B15 -> #REF! | E8: =('FORM 4'!#REF!+'FORM 4'!#REF!+'FORM 4'!#REF!)/'Evolutive SFP'!C15 -> #REF! | F8: =('FORM 4'!#REF!+'FORM 4'!#REF!+'FORM 4'!#REF!)/'Evolutive SFP'!D15 -> #REF! | G8: =('FORM 4'!#REF!+'FORM 4'!#REF!+'FORM 4'!#REF!)/'Evolutive SFP'!E15 -> #REF! | H8: =('FORM 4'!#REF!+'FORM 4'!#REF!+'FORM 4'!#REF!)/'Evolutive SFP'!F15 -> #REF! | I8: =('FORM 4'!#REF!+'FORM 4'!#REF!+'FORM 4'!#REF!)/'Evolutive SFP'!G15 -> #REF! | J8: =('FORM 4'!#REF!+'FORM 4'!#REF!+'FORM 4'!#REF!)/'Evolutive SFP'!H15 -> #REF! | K8: =('FORM 4'!#REF!+'FORM 4'!#REF!+'FORM 4'!#REF!)/'Evolutive SFP'!I15 -> #REF! | ... AT8: =('FORM 4'!#REF!+'FORM 4'!#REF!+'FORM 4'!#REF!)/'Evolutive SFP'!AR15 -> #REF!
A9: EARNINGS | B9: ROA | D9: ='Evolutitve SCI'!B33/(('Evolutive SFP'!#REF!+'Evolutive SFP'!B27)/2) -> #REF! | E9: ='Evolutitve SCI'!C33/(('Evolutive SFP'!B27+'Evolutive SFP'!C27)/2) -> 0.0020127032 | F9: ='Evolutitve SCI'!D33/(('Evolutive SFP'!C27+'Evolutive SFP'!D27)/2) -> 0.0026783662 | G9: ='Evolutitve SCI'!E33/(('Evolutive SFP'!D27+'Evolutive SFP'!E27)/2) -> 0.0049292469 | H9: ='Evolutitve SCI'!F33/(('Evolutive SFP'!E27+'Evolutive SFP'!F27)/2) -> 0.0075962393 | I9: ='Evolutitve SCI'!G33/(('Evolutive SFP'!F27+'Evolutive SFP'!G27)/2) -> 0.010352003 | J9: ='Evolutitve SCI'!H33/(('Evolutive SFP'!G27+'Evolutive SFP'!H27)/2) -> 0.024737184 | K9: ='Evolutitve SCI'!I33/(('Evolutive SFP'!H27+'Evolutive SFP'!I27)/2) -> 0.012534151 | L9: ='Evolutitve SCI'!J33/(('Evolutive SFP'!I27+'Evolutive SFP'!J27)/2) -> 0.014308618 | ... AT9: ='Evolutitve SCI'!AR33/(('Evolutive SFP'!AQ27+'Evolutive SFP'!AR27)/2) -> #DIV/0!
B10: Cost Income ratio | D10: ='Evolutitve SCI'!B23/'Evolutitve SCI'!B19 -> 0.66582373 | E10: ='Evolutitve SCI'!C23/'Evolutitve SCI'!C19 -> 0.50679815 | F10: ='Evolutitve SCI'!D23/'Evolutitve SCI'!D19 -> 0.43097091 | G10: ='Evolutitve SCI'!E23/'Evolutitve SCI'!E19 -> 0.42850435 | H10: ='Evolutitve SCI'!F23/'Evolutitve SCI'!F19 -> 0.41931981 | I10: ='Evolutitve SCI'!G23/'Evolutitve SCI'!G19 -> 0.4102601 | J10: ='Evolutitve SCI'!H23/'Evolutitve SCI'!H19 -> 0.41778292 | K10: ='Evolutitve SCI'!I23/'Evolutitve SCI'!I19 -> 0.43547288 | ... AT10: ='Evolutitve SCI'!AR23/'Evolutitve SCI'!AR19 -> #DIV/0!
B11: Operating Expense ratio | D11: =('Evolutitve SCI'!B23+'Evolutitve SCI'!B12)/(('Evolutive SFP'!B27+'Evolutive SFP'!D27)/2) -> 0.0068698887 | E11: =('Evolutitve SCI'!C23+'Evolutitve SCI'!C12)/(('Evolutive SFP'!C27+'Evolutive SFP'!E27)/2) -> 0.013644313 | F11: =('Evolutitve SCI'!D23+'Evolutitve SCI'!D12)/(('Evolutive SFP'!D27+'Evolutive SFP'!F27)/2) -> 0.021770816 | G11: =('Evolutitve SCI'!E23+'Evolutitve SCI'!E12)/(('Evolutive SFP'!E27+'Evolutive SFP'!G27)/2) -> 0.02852533 | H11: =('Evolutitve SCI'!F23+'Evolutitve SCI'!F12)/(('Evolutive SFP'!F27+'Evolutive SFP'!H27)/2) -> 0.03585131 | I11: =('Evolutitve SCI'!G23+'Evolutitve SCI'!G12)/(('Evolutive SFP'!G27+'Evolutive SFP'!I27)/2) -> 0.04308113 | J11: =('Evolutitve SCI'!H23+'Evolutitve SCI'!H12)/(('Evolutive SFP'!H27+'Evolutive SFP'!J27)/2) -> 0.099789418 | K11: =('Evolutitve SCI'!I23+'Evolutitve SCI'!I12)/(('Evolutive SFP'!I27+'Evolutive SFP'!K27)/2) -> 0.057183066 | L11: =('Evolutitve SCI'!J23+'Evolutitve SCI'!J12)/(('Evolutive SFP'!J27+'Evolutive SFP'!#REF!)/2) -> #REF! | M11: =('Evolutitve SCI'!K23+'Evolutitve SCI'!K12)/(('Evolutive SFP'!K27+'Evolutive SFP'!#REF!)/2) -> #REF! | N11: =('Evolutitve SCI'!L23+'Evolutitve SCI'!L12)/(('Evolutive SFP'!L27+'Evolutive SFP'!#REF!)/2) -> #REF! | O11: =('Evolutitve SCI'!M23+'Evolutitve SCI'!M12)/(('Evolutive SFP'!M27+'Evolutive SFP'!#REF!)/2) -> #REF! | P11: =('Evolutitve SCI'!N23+'Evolutitve SCI'!N12)/(('Evolutive SFP'!N27+'Evolutive SFP'!#REF!)/2) -> #REF! | Q11: =('Evolutitve SCI'!O23+'Evolutitve SCI'!O12)/(('Evolutive SFP'!O27+'Evolutive SFP'!#REF!)/2) -> #REF! | R11: =('Evolutitve SCI'!P23+'Evolutitve SCI'!P12)/(('Evolutive SFP'!P27+'Evolutive SFP'!#REF!)/2) -> #REF! | S11: =('Evolutitve SCI'!Q23+'Evolutitve SCI'!Q12)/(('Evolutive SFP'!Q27+'Evolutive SFP'!#REF!)/2) -> #REF! | ... AT11: =('Evolutitve SCI'!AR23+'Evolutitve SCI'!AR12)/(('Evolutive SFP'!AR27+'Evolutive SFP'!#REF!)/2) -> #REF!
A12: LIQUIDITY | B12: MIN LIQ ratio | C12: Min 15% | D12: =('Evolutive SFP'!B4)/('Evolutive SFP'!B28+'Evolutive SFP'!B29+'Evolutive SFP'!B32+'Evolutive SFP'!B33+'Evolutive SFP'!B34+'Evolutive SFP'!B35+'Evolutive SFP'!B36) -> 1.2990298 | E12: =('Evolutive SFP'!C4)/('Evolutive SFP'!C28+'Evolutive SFP'!C29+'Evolutive SFP'!C32+'Evolutive SFP'!C33+'Evolutive SFP'!C34+'Evolutive SFP'!C35+'Evolutive SFP'!C36) -> 1.5695611 | F12: =('Evolutive SFP'!D4)/('Evolutive SFP'!D28+'Evolutive SFP'!D29+'Evolutive SFP'!D32+'Evolutive SFP'!D33+'Evolutive SFP'!D34+'Evolutive SFP'!D35+'Evolutive SFP'!D36) -> 2.0708482 | G12: =('Evolutive SFP'!E4)/('Evolutive SFP'!E28+'Evolutive SFP'!E29+'Evolutive SFP'!E32+'Evolutive SFP'!E33+'Evolutive SFP'!E34+'Evolutive SFP'!E35+'Evolutive SFP'!E36) -> 1.450883 | H12: =('Evolutive SFP'!F4)/('Evolutive SFP'!F28+'Evolutive SFP'!F29+'Evolutive SFP'!F32+'Evolutive SFP'!F33+'Evolutive SFP'!F34+'Evolutive SFP'!F35+'Evolutive SFP'!F36) -> 1.6511522 | I12: =('Evolutive SFP'!G4)/('Evolutive SFP'!G28+'Evolutive SFP'!G29+'Evolutive SFP'!G32+'Evolutive SFP'!G33+'Evolutive SFP'!G34+'Evolutive SFP'!G35+'Evolutive SFP'!G36) -> 1.8844784 | J12: =('Evolutive SFP'!H4)/('Evolutive SFP'!H28+'Evolutive SFP'!H29+'Evolutive SFP'!H32+'Evolutive SFP'!H33+'Evolutive SFP'!H34+'Evolutive SFP'!H35+'Evolutive SFP'!H36) -> 1.9467039 | K12: =('Evolutive SFP'!I4)/('Evolutive SFP'!I28+'Evolutive SFP'!I29+'Evolutive SFP'!I32+'Evolutive SFP'!I33+'Evolutive SFP'!I34+'Evolutive SFP'!I35+'Evolutive SFP'!I36) -> 1.823172 | ... AT12: =('Evolutive SFP'!AR4)/('Evolutive SFP'!AR28+'Evolutive SFP'!AR29+'Evolutive SFP'!AR32+'Evolutive SFP'!AR33+'Evolutive SFP'!AR34+'Evolutive SFP'!AR35+'Evolutive SFP'!AR36) -> #DIV/0!
B13: T/LIQ ratio | D13: ='Evolutive SFP'!B4/('Evolutive SFP'!B31+'Evolutive SFP'!B36) -> 0.16515158 | E13: ='Evolutive SFP'!C4/('Evolutive SFP'!C31+'Evolutive SFP'!C36) -> 0.17383907 | F13: ='Evolutive SFP'!D4/('Evolutive SFP'!D31+'Evolutive SFP'!D36) -> 0.13408856 | G13: ='Evolutive SFP'!E4/('Evolutive SFP'!E31+'Evolutive SFP'!E36) -> 0.091189443 | H13: ='Evolutive SFP'!F4/('Evolutive SFP'!F31+'Evolutive SFP'!F36) -> 0.11271429 | I13: ='Evolutive SFP'!G4/('Evolutive SFP'!G31+'Evolutive SFP'!G36) -> 0.14594654 | J13: ='Evolutive SFP'!H4/('Evolutive SFP'!H31+'Evolutive SFP'!H36) -> 0.15829658 | K13: ='Evolutive SFP'!I4/('Evolutive SFP'!I31+'Evolutive SFP'!I36) -> 0.15656509 | ... AT13: ='Evolutive SFP'!AR4/('Evolutive SFP'!AR31+'Evolutive SFP'!AR36) -> #DIV/0!
B14: EB ratio | C14: Max 25% | D14: ='Evolutive SFP'!B37/'Evolutive SFP'!B27 -> 0 | E14: ='Evolutive SFP'!C37/'Evolutive SFP'!C27 -> 0.0019921987 | F14: ='Evolutive SFP'!D37/'Evolutive SFP'!D27 -> 0 | G14: ='Evolutive SFP'!E37/'Evolutive SFP'!E27 -> 0 | H14: ='Evolutive SFP'!F37/'Evolutive SFP'!F27 -> 0 | I14: ='Evolutive SFP'!G37/'Evolutive SFP'!G27 -> 0 | J14: ='Evolutive SFP'!H37/'Evolutive SFP'!H27 -> 0 | K14: ='Evolutive SFP'!I37/'Evolutive SFP'!I27 -> 0 | ... AT14: ='Evolutive SFP'!AR37/'Evolutive SFP'!AR27 -> #DIV/0!
B15: LA to TA ratio | D15: ='Evolutive SFP'!B4/'Evolutive SFP'!B27 -> 0.14600263 | E15: ='Evolutive SFP'!C4/'Evolutive SFP'!C27 -> 0.15276553 | F15: ='Evolutive SFP'!D4/'Evolutive SFP'!D27 -> 0.11733996 | G15: ='Evolutive SFP'!E4/'Evolutive SFP'!E27 -> 0.079714548 | H15: ='Evolutive SFP'!F4/'Evolutive SFP'!F27 -> 0.098383464 | I15: ='Evolutive SFP'!G4/'Evolutive SFP'!G27 -> 0.12720754 | J15: ='Evolutive SFP'!H4/'Evolutive SFP'!H27 -> 0.13789449 | K15: ='Evolutive SFP'!I4/'Evolutive SFP'!I27 -> 0.13647092 | ... AT15: ='Evolutive SFP'!AR4/'Evolutive SFP'!AR27 -> #DIV/0!
A16: STRUCTURE | B16: NEA ratio | C16: Max 10% | D16: =('Evolutive SFP'!B7+'Evolutive SFP'!B21)/'Evolutive SFP'!B27 -> 0.073699972 | E16: =('Evolutive SFP'!C7+'Evolutive SFP'!C21)/'Evolutive SFP'!C27 -> 0.075387466 | F16: =('Evolutive SFP'!D7+'Evolutive SFP'!D21)/'Evolutive SFP'!D27 -> 0.057377533 | G16: =('Evolutive SFP'!E7+'Evolutive SFP'!E21)/'Evolutive SFP'!E27 -> 0.078771422 | H16: =('Evolutive SFP'!F7+'Evolutive SFP'!F21)/'Evolutive SFP'!F27 -> 0.077561983 | I16: =('Evolutive SFP'!G7+'Evolutive SFP'!G21)/'Evolutive SFP'!G27 -> 0.064709535 | J16: =('Evolutive SFP'!H7+'Evolutive SFP'!H21)/'Evolutive SFP'!H27 -> 0.06431505 | K16: =('Evolutive SFP'!I7+'Evolutive SFP'!I21)/'Evolutive SFP'!I27 -> 0.064355933 | ... AT16: =('Evolutive SFP'!AR7+'Evolutive SFP'!AR21)/'Evolutive SFP'!AR27 -> #DIV/0!
B17: LB ratio | C17: Max 5% | D17: ='Evolutive SFP'!B21/'Evolutive SFP'!B27 -> 0.054601477 | E17: ='Evolutive SFP'!C21/'Evolutive SFP'!C27 -> 0.054828719 | F17: ='Evolutive SFP'!D21/'Evolutive SFP'!D27 -> 0.057377533 | G17: ='Evolutive SFP'!E21/'Evolutive SFP'!E27 -> 0.057340032 | H17: ='Evolutive SFP'!F21/'Evolutive SFP'!F27 -> 0.056564051 | I17: ='Evolutive SFP'!G21/'Evolutive SFP'!G27 -> 0.055500523 | J17: ='Evolutive SFP'!H21/'Evolutive SFP'!H27 -> 0.054514406 | K17: ='Evolutive SFP'!I21/'Evolutive SFP'!I27 -> 0.053852287 | ... AT17: ='Evolutive SFP'!AR21/'Evolutive SFP'!AR27 -> #DIV/0!
B18: PI to Deposit ratio | C18: Max 5% | D18: ='Evolutive SFP'!B13/'Evolutive SFP'!B31 -> 0.0034408254 | E18: ='Evolutive SFP'!C13/'Evolutive SFP'!C31 -> 0.0033915456 | F18: ='Evolutive SFP'!D13/'Evolutive SFP'!D31 -> 0.0033443365 | G18: ='Evolutive SFP'!E13/'Evolutive SFP'!E31 -> 0.0033228704 | H18: ='Evolutive SFP'!F13/'Evolutive SFP'!F31 -> 0.0032930566 | I18: ='Evolutive SFP'!G13/'Evolutive SFP'!G31 -> 0.0032605046 | J18: ='Evolutive SFP'!H13/'Evolutive SFP'!H31 -> 0.003213639 | K18: ='Evolutive SFP'!I13/'Evolutive SFP'!I31 -> 0.0031877649 | ... AT18: ='Evolutive SFP'!AR13/'Evolutive SFP'!AR31 -> #DIV/0!
B19: PI to CC ratio | C19: Max 40% | D19: ='Evolutive SFP'!B13/(CAELS!D3*1000000) -> 0.024605307 | E19: ='Evolutive SFP'!C13/(CAELS!E3*1000000) -> 0.023847468 | F19: ='Evolutive SFP'!D13/(CAELS!F3*1000000) -> 0.023500259 | G19: ='Evolutive SFP'!E13/(CAELS!G3*1000000) -> 0.022962882 | H19: ='Evolutive SFP'!F13/(CAELS!H3*1000000) -> 0.022344665 | I19: ='Evolutive SFP'!G13/(CAELS!I3*1000000) -> 0.021712485 | J19: ='Evolutive SFP'!H13/(CAELS!J3*1000000) -> 0.021189457 | K19: ='Evolutive SFP'!I13/(CAELS!K3*1000000) -> 0.020979147 | ... AT19: ='Evolutive SFP'!AR13/(CAELS!AT3*1000000) -> #DIV/0!
B20: Gross loans/TA | D20: ='Evolutive SFP'!B15/'Evolutive SFP'!B27 -> 0.77962641 | E20: ='Evolutive SFP'!C15/'Evolutive SFP'!C27 -> 0.76565706 | F20: ='Evolutive SFP'!D15/'Evolutive SFP'!D27 -> 0.80045934 | G20: ='Evolutive SFP'!E15/'Evolutive SFP'!E27 -> 0.7969178 | H20: ='Evolutive SFP'!F15/'Evolutive SFP'!F27 -> 0.78013412 | I20: ='Evolutive SFP'!G15/'Evolutive SFP'!G27 -> 0.76376659 | J20: ='Evolutive SFP'!H15/'Evolutive SFP'!H27 -> 0.7539243 | K20: ='Evolutive SFP'!I15/'Evolutive SFP'!I27 -> 0.75263787 | ... AT20: ='Evolutive SFP'!AR15/'Evolutive SFP'!AR27 -> #DIV/0!
A21: FUNDING MIX | B21: Total Deposits/Total Assets | D21: ='Evolutive SFP'!B31/'Evolutive SFP'!B27 -> 0.78111926 | E21: ='Evolutive SFP'!C31/'Evolutive SFP'!C27 -> 0.79126145 | F21: ='Evolutive SFP'!D31/'Evolutive SFP'!D27 -> 0.82906179 | G21: ='Evolutive SFP'!E31/'Evolutive SFP'!E27 -> 0.8295064 | H21: ='Evolutive SFP'!F31/'Evolutive SFP'!F27 -> 0.82396512 | I21: ='Evolutive SFP'!G31/'Evolutive SFP'!G27 -> 0.8176576 | J21: ='Evolutive SFP'!H31/'Evolutive SFP'!H27 -> 0.81353737 | K21: ='Evolutive SFP'!I31/'Evolutive SFP'!I27 -> 0.80893288 | ... AT21: ='Evolutive SFP'!AR31/'Evolutive SFP'!AR27 -> #DIV/0!
B22: BOSA Deposits/Total Assets | D22: ='Evolutive SFP'!B30/'Evolutive SFP'!B27 -> 0.77315199 | E22: ='Evolutive SFP'!C30/'Evolutive SFP'!C27 -> 0.78293656 | F22: ='Evolutive SFP'!D30/'Evolutive SFP'!D27 -> 0.81997075 | G22: ='Evolutive SFP'!E30/'Evolutive SFP'!E27 -> 0.8196727 | H22: ='Evolutive SFP'!F30/'Evolutive SFP'!F27 -> 0.81371589 | I22: ='Evolutive SFP'!G30/'Evolutive SFP'!G27 -> 0.8045367 | J22: ='Evolutive SFP'!H30/'Evolutive SFP'!H27 -> 0.80070728 | K22: ='Evolutive SFP'!I30/'Evolutive SFP'!I27 -> 0.79722406 | ... AT22: ='Evolutive SFP'!AR30/'Evolutive SFP'!AR27 -> #DIV/0!
B23: FOSA Deposits/Total Assets | D23: =('Evolutive SFP'!B28+'Evolutive SFP'!B29)/'Evolutive SFP'!B27 -> 0.0079672684 | E23: =('Evolutive SFP'!C28+'Evolutive SFP'!C29)/'Evolutive SFP'!C27 -> 0.0083248928 | F23: =('Evolutive SFP'!D28+'Evolutive SFP'!D29)/'Evolutive SFP'!D27 -> 0.0090910402 | G23: =('Evolutive SFP'!E28+'Evolutive SFP'!E29)/'Evolutive SFP'!E27 -> 0.0098337001 | H23: =('Evolutive SFP'!F28+'Evolutive SFP'!F29)/'Evolutive SFP'!F27 -> 0.01024923 | I23: =('Evolutive SFP'!G28+'Evolutive SFP'!G29)/'Evolutive SFP'!G27 -> 0.013120906 | J23: =('Evolutive SFP'!H28+'Evolutive SFP'!H29)/'Evolutive SFP'!H27 -> 0.012830085 | K23: =('Evolutive SFP'!I28+'Evolutive SFP'!I29)/'Evolutive SFP'!I27 -> 0.01170882 | ... AT23: =('Evolutive SFP'!AR28+'Evolutive SFP'!AR29)/'Evolutive SFP'!AR27 -> #DIV/0!
A24: GROWTH RATIOS | B24: Total Assets | D24: =(Financials!C4-Financials!#REF!)/Financials!#REF! -> #REF! | E24: =(Financials!D4-Financials!C4)/Financials!C4 -> 0.0015262133 | F24: =(Financials!E4-Financials!D4)/Financials!D4 -> -0.032121603 | G24: =(Financials!F4-Financials!E4)/Financials!E4 -> 0.0059206507 | H24: =(Financials!G4-Financials!F4)/Financials!F4 -> 0.015839574 | I24: =(Financials!H4-Financials!G4)/Financials!G4 -> 0.017774877 | J24: =(Financials!I4-Financials!H4)/Financials!H4 -> 0.019721765 | K24: =(Financials!J4-Financials!I4)/Financials!I4 -> 0.013854959 | L24: =(Financials!K4-Financials!J4)/Financials!J4 -> 0.012136389 | ... AT24: =(Financials!AS4-Financials!AR4)/Financials!AR4 -> #DIV/0!
B25: Total Deposits | D25: =Financials!#REF!/Financials!C5-1 -> #REF! | E25: =Financials!#REF!/Financials!D5-1 -> #REF! | F25: =Financials!#REF!/Financials!E5-1 -> #REF! | G25: =Financials!#REF!/Financials!F5-1 -> #REF! | H25: =Financials!#REF!/Financials!G5-1 -> #REF! | I25: =Financials!#REF!/Financials!H5-1 -> #REF! | J25: =Financials!#REF!/Financials!I5-1 -> #REF! | K25: =Financials!#REF!/Financials!J5-1 -> #REF! | ... AT25: =Financials!#REF!/Financials!AS5-1 -> #REF!
B26: BOSA Deposits | D26: =Financials!#REF!/Financials!C6-1 -> #REF! | E26: =Financials!#REF!/Financials!D6-1 -> #REF! | F26: =Financials!#REF!/Financials!E6-1 -> #REF! | G26: =Financials!#REF!/Financials!F6-1 -> #REF! | H26: =Financials!#REF!/Financials!G6-1 -> #REF! | I26: =Financials!#REF!/Financials!H6-1 -> #REF! | J26: =Financials!#REF!/Financials!I6-1 -> #REF! | K26: =Financials!#REF!/Financials!J6-1 -> #REF! | ... AT26: =Financials!#REF!/Financials!AS6-1 -> #REF!
B27: FOSA Deposits | D27: =Financials!#REF!/Financials!C7-1 -> #REF! | E27: =Financials!#REF!/Financials!D7-1 -> #REF! | F27: =Financials!#REF!/Financials!E7-1 -> #REF! | G27: =Financials!#REF!/Financials!F7-1 -> #REF! | H27: =Financials!#REF!/Financials!G7-1 -> #REF! | I27: =Financials!#REF!/Financials!H7-1 -> #REF! | J27: =Financials!#REF!/Financials!I7-1 -> #REF! | K27: =Financials!#REF!/Financials!J7-1 -> #REF! | ... AT27: =Financials!#REF!/Financials!AS7-1 -> #REF!
B28: Total Loans & advances | D28: =Financials!#REF!/Financials!C31-1 -> #REF! | E28: =Financials!#REF!/Financials!D31-1 -> #REF! | F28: =Financials!#REF!/Financials!E31-1 -> #REF! | G28: =Financials!#REF!/Financials!F31-1 -> #REF! | H28: =Financials!#REF!/Financials!G31-1 -> #REF! | I28: =Financials!#REF!/Financials!H31-1 -> #REF! | J28: =Financials!#REF!/Financials!I31-1 -> #REF! | K28: =Financials!#REF!/Financials!J31-1 -> #REF! | ... AT28: =Financials!#REF!/Financials!AS31-1 -> #REF!
B29: Core capital | D29: =Financials!#REF!/Financials!C11-1 -> #REF! | E29: =Financials!#REF!/Financials!D11-1 -> #REF! | F29: =Financials!#REF!/Financials!E11-1 -> #REF! | G29: =Financials!#REF!/Financials!F11-1 -> #REF! | H29: =Financials!#REF!/Financials!G11-1 -> #REF! | I29: =Financials!#REF!/Financials!H11-1 -> #REF! | J29: =Financials!#REF!/Financials!I11-1 -> #REF! | K29: =Financials!#REF!/Financials!J11-1 -> #REF! | ... AT29: =Financials!#REF!/Financials!AS11-1 -> #REF!
B30: Turnover | D30: =Financials!#REF!/Financials!C37-1 -> #REF! | E30: =Financials!#REF!/Financials!D37-1 -> #REF! | F30: =Financials!#REF!/Financials!E37-1 -> #REF! | G30: =Financials!#REF!/Financials!F37-1 -> #REF! | H30: =Financials!#REF!/Financials!G37-1 -> #REF! | I30: =Financials!#REF!/Financials!H37-1 -> #REF! | J30: =Financials!#REF!/Financials!I37-1 -> #REF! | K30: =Financials!#REF!/Financials!J37-1 -> #REF! | ... AT30: =Financials!#REF!/Financials!AS37-1 -> #REF!
B31: Membership
B32: Expenses | D32: ='Evolutitve SCI'!#REF!/'Evolutitve SCI'!B39-1 -> #REF! | E32: ='Evolutitve SCI'!#REF!/'Evolutitve SCI'!C39-1 -> #REF! | F32: ='Evolutitve SCI'!#REF!/'Evolutitve SCI'!D39-1 -> #REF! | G32: ='Evolutitve SCI'!#REF!/'Evolutitve SCI'!E39-1 -> #REF! | H32: ='Evolutitve SCI'!#REF!/'Evolutitve SCI'!F39-1 -> #REF! | I32: ='Evolutitve SCI'!#REF!/'Evolutitve SCI'!G39-1 -> #REF! | J32: ='Evolutitve SCI'!#REF!/'Evolutitve SCI'!H39-1 -> #REF! | K32: ='Evolutitve SCI'!#REF!/'Evolutitve SCI'!I39-1 -> #REF! | ... AT32: ='Evolutitve SCI'!#REF!/'Evolutitve SCI'!AR39-1 -> #REF!
A33: Efficiency Ratios | B33: FinCost-Deposits/Avg Deposits | D33: =Financials!C44/('Evolutive SFP'!#REF!+'Evolutive SFP'!B30)/2 -> #REF! | E33: =Financials!D44/('Evolutive SFP'!B30+'Evolutive SFP'!C30)/2 -> 0.0032772566 | F33: =Financials!E44/('Evolutive SFP'!C30+'Evolutive SFP'!D30)/2 -> 0.0050840916 | G33: =Financials!F44/('Evolutive SFP'!D30+'Evolutive SFP'!E30)/2 -> 0.0067254519 | H33: =Financials!G44/('Evolutive SFP'!E30+'Evolutive SFP'!F30)/2 -> 0.0086159944 | I33: =Financials!H44/('Evolutive SFP'!F30+'Evolutive SFP'!G30)/2 -> 0.010498421 | J33: =Financials!I44/('Evolutive SFP'!G30+'Evolutive SFP'!H30)/2 -> 0.024364208 | K33: =Financials!J44/('Evolutive SFP'!H30+'Evolutive SFP'!I30)/2 -> 0.013814087 | L33: =Financials!K44/('Evolutive SFP'!I30+'Evolutive SFP'!J30)/2 -> 0.01549682 | ... AT33: =Financials!AS44/('Evolutive SFP'!AQ30+'Evolutive SFP'!AR30)/2 -> #DIV/0!
B34: FinCost-Shares/Avg Share capital | D34: =Financials!C45/('Evolutive SFP'!#REF!+'Evolutive SFP'!B39)/2 -> #REF! | E34: =Financials!D45/('Evolutive SFP'!B39+'Evolutive SFP'!C39)/2 -> 0 | F34: =Financials!E45/('Evolutive SFP'!C39+'Evolutive SFP'!D39)/2 -> 0 | G34: =Financials!F45/('Evolutive SFP'!D39+'Evolutive SFP'!E39)/2 -> 0 | H34: =Financials!G45/('Evolutive SFP'!E39+'Evolutive SFP'!F39)/2 -> 0 | I34: =Financials!H45/('Evolutive SFP'!F39+'Evolutive SFP'!G39)/2 -> 0 | J34: =Financials!I45/('Evolutive SFP'!G39+'Evolutive SFP'!H39)/2 -> 0 | K34: =Financials!J45/('Evolutive SFP'!H39+'Evolutive SFP'!I39)/2 -> 0 | L34: =Financials!K45/('Evolutive SFP'!I39+'Evolutive SFP'!J39)/2 -> 0 | ... AT34: =Financials!AS45/('Evolutive SFP'!AQ39+'Evolutive SFP'!AR39)/2 -> #DIV/0!
B35: FinCost-Ext Loans/Avg Ext Loans | D35: =Financials!C46/(Financials!#REF!+Financials!C31)/2 -> #REF! | E35: =Financials!D46/(Financials!C31+Financials!D31)/2 -> 0 | F35: =Financials!E46/(Financials!D31+Financials!E31)/2 -> 0 | G35: =Financials!F46/(Financials!E31+Financials!F31)/2 -> 0 | H35: =Financials!G46/(Financials!F31+Financials!G31)/2 -> 0 | I35: =Financials!H46/(Financials!G31+Financials!H31)/2 -> 0 | J35: =Financials!I46/(Financials!H31+Financials!I31)/2 -> 0 | K35: =Financials!J46/(Financials!I31+Financials!J31)/2 -> 0 | L35: =Financials!K46/(Financials!J31+Financials!K31)/2 -> 0 | ... AT35: =Financials!AS46/(Financials!AR31+Financials!AS31)/2 -> #DIV/0!
B36: OpEx/Average Total Assets | D36: =Financials!C47/(Financials!#REF!+Financials!C4)/2 -> #REF! | E36: =Financials!D47/(Financials!C4+Financials!D4)/2 -> 0.00081877087 | F36: =Financials!E47/(Financials!D4+Financials!E4)/2 -> 0.0013392376 | G36: =Financials!F47/(Financials!E4+Financials!F4)/2 -> 0.0017599311 | H36: =Financials!G47/(Financials!F4+Financials!G4)/2 -> 0.0021677631 | I36: =Financials!H47/(Financials!G4+Financials!H4)/2 -> 0.0025549278 | J36: =Financials!I47/(Financials!H4+Financials!I4)/2 -> 0.0059656527 | K36: =Financials!J47/(Financials!I4+Financials!J4)/2 -> 0.0035078723 | L36: =Financials!K47/(Financials!J4+Financials!K4)/2 -> 0.0040538372 | ... AT36: =Financials!AS47/(Financials!AR4+Financials!AS4)/2 -> #DIV/0!
B37: Opex/Turnover | D37: =Financials!C47/Financials!C37 -> 0.20957939 | E37: =Financials!D47/Financials!D37 -> 0.19656293 | F37: =Financials!E47/Financials!E37 -> 0.18650732 | G37: =Financials!F47/Financials!F37 -> 0.18292948 | H37: =Financials!G47/Financials!G37 -> 0.17759605 | I37: =Financials!H47/Financials!H37 -> 0.17354836 | J37: =Financials!I47/Financials!I37 -> 0.17632068 | K37: =Financials!J47/Financials!J37 -> 0.18373391 | ... AT37: =Financials!AS47/Financials!AS37 -> #DIV/0!
B38: Avge yield on Net loans | D38: =Financials!C38/('Evolutive SFP'!B14+'Evolutive SFP'!#REF!)/2 -> #REF! | E38: =Financials!D38/('Evolutive SFP'!C14+'Evolutive SFP'!B14)/2 -> 0.0043336022 | F38: =Financials!E38/('Evolutive SFP'!D14+'Evolutive SFP'!C14)/2 -> 0.0074868062 | G38: =Financials!F38/('Evolutive SFP'!E14+'Evolutive SFP'!D14)/2 -> 0.0099656203 | H38: =Financials!G38/('Evolutive SFP'!F14+'Evolutive SFP'!E14)/2 -> 0.013006337 | I38: =Financials!H38/('Evolutive SFP'!G14+'Evolutive SFP'!F14)/2 -> 0.015714523 | J38: =Financials!I38/('Evolutive SFP'!H14+'Evolutive SFP'!G14)/2 -> 0.036904967 | K38: =Financials!J38/('Evolutive SFP'!I14+'Evolutive SFP'!H14)/2 -> 0.021144197 | L38: =Financials!K38/('Evolutive SFP'!J14+'Evolutive SFP'!I14)/2 -> 0.023667232 | ... AT38: =Financials!AS38/('Evolutive SFP'!AR14+'Evolutive SFP'!AQ14)/2 -> #DIV/0!
B39: Avge yield on Gross loans | D39: =Financials!C37/('Evolutive SFP'!B15+'Evolutive SFP'!#REF!)/2 -> #REF! | E39: =Financials!D37/('Evolutive SFP'!C15+'Evolutive SFP'!B15)/2 -> 0.0053912018 | F39: =Financials!E37/('Evolutive SFP'!D15+'Evolutive SFP'!C15)/2 -> 0.0091732928 | G39: =Financials!F37/('Evolutive SFP'!E15+'Evolutive SFP'!D15)/2 -> 0.012045847 | H39: =Financials!G37/('Evolutive SFP'!F15+'Evolutive SFP'!E15)/2 -> 0.015480994 | I39: =Financials!H37/('Evolutive SFP'!G15+'Evolutive SFP'!F15)/2 -> 0.019072573 | J39: =Financials!I37/('Evolutive SFP'!H15+'Evolutive SFP'!G15)/2 -> 0.044589118 | K39: =Financials!J37/('Evolutive SFP'!I15+'Evolutive SFP'!H15)/2 -> 0.025345447 | L39: =Financials!K37/('Evolutive SFP'!J15+'Evolutive SFP'!I15)/2 -> 0.028210963 | ... AT39: =Financials!AS37/('Evolutive SFP'!AR15+'Evolutive SFP'!AQ15)/2 -> #DIV/0!
A41: ALL/Average Gross Loan portfolio

Sheet Financials
B1: STIMA Sacco Financial Performance
B2: Year | C2: 43831 | D2: 43862 | E2: 43891 | F2: 43922 | G2: 43952 | H2: 43983 | I2: 44013 | J2: 44044 | K2: 44075 | L2: 44105 | M2: 44136 | N2: 44166 | O2: Audited 2020 | P2: 44197 | Q2: 44228 | R2: 44256 | S2: 44287 | T2: 44317 | U2: 44348 | V2: 44378 | W2: 44409 | X2: 44440 | Y2: 44470 | Z2: 44501 | AA2: 44531 | AB2: Audited 2021 | AC2: 44562 | AD2: 44593 | AE2: 44621 | AF2: 44652 | AG2: 44682 | AH2: 44713 | AI2: 44743 | AJ2: 44774 | AK2: 44805 | AL2: 44835 | AM2: 44866 | AN2: 44896 | AO2: 44927
A3: 1 | B3: Membership
A4: 2 | B4: Total Assets | C4: ='Evolutive SFP'!B27 -> 6.91896e+09 | D4: ='Evolutive SFP'!C27 -> 6.9295198e+09 | E4: ='Evolutive SFP'!D27 -> 6.7069325e+09 | F4: ='Evolutive SFP'!E27 -> 6.746642e+09 | G4: ='Evolutive SFP'!F27 -> 6.8535059e+09 | H4: ='Evolutive SFP'!G27 -> 6.9753261e+09 | I4: ='Evolutive SFP'!H27 -> 7.1128919e+09 | J4: ='Evolutive SFP'!I27 -> 7.2114407e+09 | ... AO4: ='Evolutive SFP'!AN27 -> 9542672000
A5: 3 | B5: Total Deposits | C5: ='Evolutive SFP'!B31 -> 5.4045329e+09 | D5: ='Evolutive SFP'!C31 -> 5.4830619e+09 | E5: ='Evolutive SFP'!D31 -> 5.5604615e+09 | F5: ='Evolutive SFP'!E31 -> 5.5963827e+09 | G5: ='Evolutive SFP'!F31 -> 5.6470498e+09 | H5: ='Evolutive SFP'!G31 -> 5.7034284e+09 | I5: ='Evolutive SFP'!H31 -> 5.7866033e+09 | J5: ='Evolutive SFP'!I31 -> 5.8335715e+09 | ... AQ5: ='Evolutive SFP'!AP31 -> 0
A6: 3.1 | B6: Deposits-Members(BOSA) | C6: ='Evolutive SFP'!B30 -> 5.3494077e+09 | D6: ='Evolutive SFP'!C30 -> 5425374401 | E6: ='Evolutive SFP'!D30 -> 5.4994885e+09 | F6: ='Evolutive SFP'!E30 -> 5.5300382e+09 | G6: ='Evolutive SFP'!F30 -> 5576806617 | H6: ='Evolutive SFP'!G30 -> 5.6119058e+09 | I6: ='Evolutive SFP'!H30 -> 5.6953443e+09 | J6: ='Evolutive SFP'!I30 -> 5.749134e+09 | ... AQ6: ='Evolutive SFP'!AP30 -> 0
A7: 3.2 | B7: Deposits-Customers(FOSA) | C7: =('Evolutive SFP'!B28+'Evolutive SFP'!B29) -> 55125212 | D7: =('Evolutive SFP'!C28+'Evolutive SFP'!C29) -> 57687510 | E7: =('Evolutive SFP'!D28+'Evolutive SFP'!D29) -> 60972993 | F7: =('Evolutive SFP'!E28+'Evolutive SFP'!E29) -> 66344454 | G7: =('Evolutive SFP'!F28+'Evolutive SFP'!F29) -> 70243155 | H7: =('Evolutive SFP'!G28+'Evolutive SFP'!G29) -> 91522596 | I7: =('Evolutive SFP'!H28+'Evolutive SFP'!H29) -> 91259010 | J7: =('Evolutive SFP'!I28+'Evolutive SFP'!I29) -> 84437462 | ... AQ7: =('Evolutive SFP'!AP28+'Evolutive SFP'!AP29) -> 0
A8: 4 | B8: External Borrowing | C8: ='Evolutive SFP'!B37 -> 0 | D8: ='Evolutive SFP'!C37 -> 13804980 | E8: ='Evolutive SFP'!D37 -> 0 | F8: ='Evolutive SFP'!E37 -> 0 | G8: ='Evolutive SFP'!F37 -> 0 | H8: ='Evolutive SFP'!G37 -> 0 | I8: ='Evolutive SFP'!H37 -> 0 | J8: ='Evolutive SFP'!I37 -> 0 | ... AQ8: ='Evolutive SFP'!AP37 -> 0
B9: Short term Liabilities | C9: =SUM('Evolutive SFP'!B32:B36) -> 7.2252157e+08 | D9: =SUM('Evolutive SFP'!C32:C36) -> 6.1676331e+08 | E9: =SUM('Evolutive SFP'!D32:D36) -> 3.1906027e+08 | F9: =SUM('Evolutive SFP'!E32:E36) -> 3.0433017e+08 | G9: =SUM('Evolutive SFP'!F32:F36) -> 3.3812117e+08 | H9: =SUM('Evolutive SFP'!G32:G36) -> 3.7933135e+08 | I9: =SUM('Evolutive SFP'!H32:H36) -> 4.1258164e+08 | J9: =SUM('Evolutive SFP'!I32:I36) -> 4.5536454e+08 | ... AQ9: =SUM('Evolutive SFP'!AP32:AP36) -> 0
A10: 5 | B10: Share capital and Reserves
A11: 5.1 | B11: Core Capital | C11: =C14-C22-C27 -> 7.3717807e+08 | D11: =D14-D22-D27 -> 7.6119551e+08 | E11: =E14-E22-E27 -> 7.7271667e+08 | F11: =F14-F22-F27 -> 7.9123497e+08 | G11: =G14-G22-G27 -> 8.1364083e+08 | H11: =H14-H22-H27 -> 8.3787222e+08 | I11: =I14-I22-I27 -> 8.5901278e+08 | J11: =J14-J22-J27 -> 8.6781054e+08 | ... AA11: =AA14-AA22-AA27 -> 1.1150664e+09 | AB11: =AB14-AB27-AB22 -> 939730000 | AC11: =AC14-AC27-AC22 -> 1.1320707e+09 | AD11: =AD14-AD27-AD22 -> 1.1749272e+09 | AE11: =AE14-AE27-AE22 -> 1.2182794e+09 | AF11: =AF14-AF27-AF22 -> 1.248553e+09 | AG11: =AG14-AG27-AG22 -> 1.2894265e+09 | AH11: =AH14-AH27-AH22 -> 1.3309084e+09 | AI11: =AI14-AI27-AI22 -> 1.3470195e+09 | ... AQ11: =AQ14-AQ27-AQ22 -> 0
A12: 5.2 | B12: Institutional Capital | C12: =C11-C15 -> 3.9820934e+08 | D12: =D11-D15 -> 4.1556276e+08 | E12: =E11-E15 -> 4.2428355e+08 | F12: =F11-F15 -> 4.3876046e+08 | G12: =G11-G15 -> 4.5852331e+08 | H12: =H11-H15 -> 4.7935467e+08 | I12: =I11-I15 -> 4.9630978e+08 | J12: =J11-J15 -> 5.0189176e+08 | ... AQ12: =AQ11-AQ15 -> 0
A14: 5.3 | B14: Total Capital | C14: =C15+C16+C17+C18+C19+C20+C21 -> 7.5577413e+08 | D14: =D15+D16+D17+D18+D19+D20+D21 -> 7.7979157e+08 | E14: =E15+E16+E17+E18+E19+E20+E21 -> 7.9131272e+08 | F14: =F15+F16+F17+F18+F19+F20+F21 -> 8.0983102e+08 | G14: =G15+G16+G17+G18+G19+G20+G21 -> 8.3223689e+08 | H14: =H15+H16+H17+H18+H19+H20+H21 -> 8.5646827e+08 | I14: =I15+I16+I17+I18+I19+I20+I21 -> 8.7760884e+08 | J14: =J15+J16+J17+J18+J19+J20+J21 -> 8.864066e+08 | ... AQ14: =AQ15+AQ16+AQ17+AQ18+AQ19+AQ20+AQ21 -> 0
A15: 5.3.1 | B15: Members Share Capital | C15: ='Evolutive SFP'!B39 -> 3.3896874e+08 | D15: ='Evolutive SFP'!C39 -> 345632751 | E15: ='Evolutive SFP'!D39 -> 3.4843312e+08 | F15: ='Evolutive SFP'!E39 -> 3.524745e+08 | G15: ='Evolutive SFP'!F39 -> 3.5511752e+08 | H15: ='Evolutive SFP'!G39 -> 3.5851755e+08 | I15: ='Evolutive SFP'!H39 -> 3.6270301e+08 | J15: ='Evolutive SFP'!I39 -> 3.6591878e+08 | ... AQ15: ='Evolutive SFP'!AP39 -> 0
A16: 5.3.2 | B16: Entrance Fees
A17: 5.3.3 | B17: Retained Earnings | C17: ='Evolutive SFP'!B41 -> 1.4389978e+08 | D17: ='Evolutive SFP'!C41 -> 1.4424767e+08 | E17: ='Evolutive SFP'!D41 -> 1.4421888e+08 | F17: ='Evolutive SFP'!E41 -> 1.4410894e+08 | G17: ='Evolutive SFP'!F41 -> 1.4410883e+08 | H17: ='Evolutive SFP'!G41 -> 1.4410883e+08 | I17: ='Evolutive SFP'!H41 -> 1.4410883e+08 | J17: ='Evolutive SFP'!I41 -> 1.4410883e+08 | ... AQ17: ='Evolutive SFP'!AP41 -> 0
A18: 5.3.4 | B18: Appropriation Account | C18: ='Evolutive SFP'!B42 -> -2595393.7 | D18: ='Evolutive SFP'!C42 -> 13971720 | E18: ='Evolutive SFP'!D42 -> 18261707 | F18: ='Evolutive SFP'!E42 -> 32893276 | G18: ='Evolutive SFP'!F42 -> 51343483 | H18: ='Evolutive SFP'!G42 -> 71169876 | I18: ='Evolutive SFP'!H42 -> 86717528 | J18: ='Evolutive SFP'!I42 -> 89353494 | ... AQ18: ='Evolutive SFP'!AP42 -> 0
A19: 5.3.5 | B19: Statutory Reserves | C19: ='Evolutive SFP'!B43 -> 99053600 | D19: ='Evolutive SFP'!C43 -> 99053600 | E19: ='Evolutive SFP'!D43 -> 99053600 | F19: ='Evolutive SFP'!E43 -> 99145215 | G19: ='Evolutive SFP'!F43 -> 99145215 | H19: ='Evolutive SFP'!G43 -> 99145215 | I19: ='Evolutive SFP'!H43 -> 99145215 | J19: ='Evolutive SFP'!I43 -> 99145215 | ... AQ19: ='Evolutive SFP'!AP43 -> 0
A20: 5.3.6 | B20: Capital Reserves | C20: =('Evolutive SFP'!B44) -> 1.7644741e+08 | D20: =('Evolutive SFP'!C44) -> 1.7688583e+08 | E20: =('Evolutive SFP'!D44) -> 1.8134541e+08 | F20: =('Evolutive SFP'!E44) -> 1.8120908e+08 | G20: =('Evolutive SFP'!F44) -> 1.8252183e+08 | H20: =('Evolutive SFP'!G44) -> 1.835268e+08 | I20: =('Evolutive SFP'!H44) -> 1.8493425e+08 | J20: =('Evolutive SFP'!I44) -> 1.8788027e+08 | ... AQ20: =('Evolutive SFP'!AP44) -> 0
A21: 5.3.7 | B21: Supplementary Capital & reserves | C21: =C22+C23 -> 0 | D21: =D22+D23 -> 0 | E21: =E22+E23 -> 0 | F21: =F22+F23 -> 0 | G21: =G22+G23 -> 0 | H21: =H22+H23 -> 0 | I21: =I22+I23 -> 0 | J21: =J22+J23 -> 0 | ... AQ21: =AQ22+AQ23 -> 0
A22: a | B22: Proposed Dividends | C22: ='Evolutive SFP'!B46 -> 0 | D22: ='Evolutive SFP'!C46 -> 0 | E22: ='Evolutive SFP'!D46 -> 0 | F22: ='Evolutive SFP'!E46 -> 0 | G22: ='Evolutive SFP'!F46 -> 0 | H22: ='Evolutive SFP'!G46 -> 0 | I22: ='Evolutive SFP'!H46 -> 0 | J22: ='Evolutive SFP'!I46 -> 0 | ... AQ22: ='Evolutive SFP'!AP46 -> 0
A23: b | B23: Risk Mgt Fund
A25: 6 | B25: Investments | C25: =C26+C27+C28 -> 37192109 | D25: =D26+D27+D28 -> 37192109 | E25: =E26+E27+E28 -> 37192109 | F25: =F26+F27+F28 -> 2.8719211e+08 | G25: =G26+G27+G28 -> 2.8719211e+08 | H25: =H26+H27+H28 -> 3.012216e+08 | I25: =I26+I27+I28 -> 3.0411408e+08 | J25: =J26+J27+J28 -> 3.3811408e+08 | ... AQ25: =AQ26+AQ27+AQ28 -> 0
A26: 6.1 | B26: Shares in Kusco,CIC,Coop Bank | C26: ='Evolutive SFP'!B13 -> 18596054 | D26: ='Evolutive SFP'!C13 -> 18596054 | E26: ='Evolutive SFP'!D13 -> 18596054 | F26: ='Evolutive SFP'!E13 -> 18596054 | G26: ='Evolutive SFP'!F13 -> 18596054 | H26: ='Evolutive SFP'!G13 -> 18596054 | I26: ='Evolutive SFP'!H13 -> 18596054 | J26: ='Evolutive SFP'!I13 -> 18596054 | ... AQ26: ='Evolutive SFP'!AP13 -> 0
A27: 6.2 | B27: Equity Investments (at cost) | C27: ='Evolutive SFP'!B10+'Evolutive SFP'!B13 -> 18596054 | D27: ='Evolutive SFP'!C10+'Evolutive SFP'!C13 -> 18596054 | E27: ='Evolutive SFP'!D10+'Evolutive SFP'!D13 -> 18596054 | F27: ='Evolutive SFP'!E10+'Evolutive SFP'!E13 -> 18596054 | G27: ='Evolutive SFP'!F10+'Evolutive SFP'!F13 -> 18596054 | H27: ='Evolutive SFP'!G10+'Evolutive SFP'!G13 -> 18596054 | I27: ='Evolutive SFP'!H10+'Evolutive SFP'!H13 -> 18596054 | J27: ='Evolutive SFP'!I10+'Evolutive SFP'!I13 -> 18596054 | ... AQ27: ='Evolutive SFP'!AP10+'Evolutive SFP'!AP13 -> 0
A28: 6.3 | B28: Deposits in KUSCCO CFP | C28: ='Evolutive SFP'!B11 -> 0 | D28: ='Evolutive SFP'!C11 -> 0 | E28: ='Evolutive SFP'!D11 -> 0 | F28: ='Evolutive SFP'!E11 -> 250000000 | G28: ='Evolutive SFP'!F11 -> 250000000 | H28: ='Evolutive SFP'!G11 -> 264029491 | I28: ='Evolutive SFP'!H11 -> 266921968 | J28: ='Evolutive SFP'!I11 -> 300921968 | ... AQ28: ='Evolutive SFP'!AP11 -> 0
A30: 7 | B30: Net Loans & Advances | C30: ='Evolutive SFP'!B14 -> 5.2541832e+09 | D30: ='Evolutive SFP'!C14 -> 5.165615e+09 | E30: ='Evolutive SFP'!D14 -> 5.2067397e+09 | F30: ='Evolutive SFP'!E14 -> 5.214632e+09 | G30: ='Evolutive SFP'!F14 -> 5.1847667e+09 | H30: ='Evolutive SFP'!G14 -> 5.1656339e+09 | I30: ='Evolutive SFP'!H14 -> 5.2006949e+09 | J30: ='Evolutive SFP'!I14 -> 5.2552086e+09 | ... AQ30: ='Evolutive SFP'!AP14 -> 0
A31: 7.1 | B31: Gross Loans & advances | C31: ='Evolutive SFP'!B15 -> 5.394204e+09 | D31: ='Evolutive SFP'!C15 -> 5.3056358e+09 | E31: ='Evolutive SFP'!D15 -> 5.3686268e+09 | F31: ='Evolutive SFP'!E15 -> 5.3765191e+09 | G31: ='Evolutive SFP'!F15 -> 5.3466538e+09 | H31: ='Evolutive SFP'!G15 -> 5.327521e+09 | I31: ='Evolutive SFP'!H15 -> 5.362582e+09 | J31: ='Evolutive SFP'!I15 -> 5.4276033e+09 | ... AQ31: ='Evolutive SFP'!AP15 -> 0
A32: 7.2 | B32: Allowance for loan losses | C32: ='Evolutive SFP'!B16 -> 1.4002079e+08 | D32: ='Evolutive SFP'!C16 -> 1.4002079e+08 | E32: ='Evolutive SFP'!D16 -> 1.6188709e+08 | F32: ='Evolutive SFP'!E16 -> 1.6188709e+08 | G32: ='Evolutive SFP'!F16 -> 1.6188709e+08 | H32: ='Evolutive SFP'!G16 -> 1.6188709e+08 | I32: ='Evolutive SFP'!H16 -> 1.6188709e+08 | J32: ='Evolutive SFP'!I16 -> 1.7239471e+08 | ... AQ32: ='Evolutive SFP'!AP16 -> 0
A34: 8 | B34: Non-Earning Assets | C34: ='Evolutive SFP'!B21+'Evolutive SFP'!B7 -> 5.0992716e+08 | D34: ='Evolutive SFP'!C21+'Evolutive SFP'!C7 -> 5.2239894e+08 | E34: ='Evolutive SFP'!D21+'Evolutive SFP'!D7 -> 3.8482724e+08 | F34: ='Evolutive SFP'!E21+'Evolutive SFP'!E7 -> 5.3144258e+08 | G34: ='Evolutive SFP'!F21+'Evolutive SFP'!F7 -> 5.3157151e+08 | H34: ='Evolutive SFP'!G21+'Evolutive SFP'!G7 -> 4.5137011e+08 | I34: ='Evolutive SFP'!H21+'Evolutive SFP'!H7 -> 4.57466e+08 | J34: ='Evolutive SFP'!I21+'Evolutive SFP'!I7 -> 4.6409899e+08 | ... AQ34: ='Evolutive SFP'!AP21+'Evolutive SFP'!AP7 -> 0
A35: 8.1 | B35: Property and Equipment | C35: ='Evolutive SFP'!B23 -> 3.5479938e+08 | D35: ='Evolutive SFP'!C23 -> 0 | E35: ='Evolutive SFP'!D23 -> 3.5984937e+08 | F35: ='Evolutive SFP'!E23 -> 3.6214789e+08 | G35: ='Evolutive SFP'!F23 -> 3.6320642e+08 | H35: ='Evolutive SFP'!G23 -> 3.6286959e+08 | I35: ='Evolutive SFP'!H23 -> 3.6326091e+08 | J35: ='Evolutive SFP'!I23 -> 3.6414576e+08 | ... AQ35: ='Evolutive SFP'!AP23 -> 0
B36: Cash & Cash Equivalents
A37: 9 | B37: Turnover | C37: =C38+C39+C40+C41 -> 52306145 | D37: =D38+D39+D40+D41 -> 1.1536999e+08 | E37: =E38+E39+E40+E41 -> 1.9583627e+08 | F37: =F38+F39+F40+F41 -> 2.5886877e+08 | G37: =G38+G39+G40+G41 -> 3.3201075e+08 | H37: =H38+H39+H40+H41 -> 4.0716797e+08 | I37: =I38+I39+I40+I41 -> 9.5332453e+08 | J37: =J38+J39+J40+J41 -> 5.4696414e+08 | ... AQ37: =AQ38+AQ39+AQ40+AQ41 -> #DIV/0!
A38: 9.1 | B38: Loan Interest | C38: ='Evolutitve SCI'!B5 -> 38601227 | D38: ='Evolutitve SCI'!C5 -> 90310521 | E38: ='Evolutitve SCI'!D5 -> 1.5531162e+08 | F38: ='Evolutitve SCI'!E5 -> 2.0771087e+08 | G38: ='Evolutitve SCI'!F5 -> 2.7051616e+08 | H38: ='Evolutitve SCI'!G5 -> 3.2530323e+08 | I38: ='Evolutitve SCI'!H5 -> 7.6513805e+08 | J38: ='Evolutitve SCI'!I5 -> 4.4216336e+08 | ... AQ38: ='Evolutitve SCI'!AP5 -> 0
A39: 9.2 | B39: Income from investments | C39: ='Evolutitve SCI'!B7 -> 8899589.1 | D39: ='Evolutitve SCI'!C7 -> 17707757 | E39: ='Evolutitve SCI'!D7 -> 23343240 | F39: ='Evolutitve SCI'!E7 -> 28893744 | G39: ='Evolutitve SCI'!F7 -> 34730356 | H39: ='Evolutitve SCI'!G7 -> 51607621 | I39: ='Evolutitve SCI'!H7 -> 1.2239619e+08 | J39: ='Evolutitve SCI'!I7 -> 68106553 | ... AQ39: ='Evolutitve SCI'!AP7 -> 0
A40: 9.3 | B40: Fees & Commissions | C40: ='Evolutitve SCI'!B6 -> 4805328.3 | D40: ='Evolutitve SCI'!C6 -> 7351713.5 | E40: ='Evolutitve SCI'!D6 -> 17181414 | F40: ='Evolutitve SCI'!E6 -> 22264157 | G40: ='Evolutitve SCI'!F6 -> 26764236 | H40: ='Evolutitve SCI'!G6 -> 30257122 | I40: ='Evolutitve SCI'!H6 -> 65790294 | J40: ='Evolutitve SCI'!I6 -> 36694228 | ... AQ40: ='Evolutitve SCI'!AP6 -> 0
A41: 9.4 | B41: Average yield on loans | C41: =C38/C31 -> 0.0071560563 | D41: =D38/D31 -> 0.017021621 | E41: =E38/E31 -> 0.028929487 | F41: =F38/F31 -> 0.038632964 | G41: =G38/G31 -> 0.050595413 | H41: =H38/H31 -> 0.061060899 | I41: =I38/I31 -> 0.1426809 | J41: =J38/J31 -> 0.081465673 | ... AQ41: =AQ38/AQ31 -> #DIV/0!
A43: 10 | B43: Financial and Operating costs | C43: =SUM(C44:C47) -> 46804182 | D43: =SUM(D44:D47) -> 93300915 | E43: =SUM(E44:E47) -> 1.4761091e+08 | F43: =SUM(F44:F47) -> 1.9571183e+08 | G43: =SUM(G44:G47) -> 2.5035682e+08 | H43: =SUM(H44:H47) -> 3.0559097e+08 | I43: =SUM(I44:I47) -> 7.1907523e+08 | J43: =SUM(J44:J47) -> 4.1668591e+08 | ... AQ43: =SUM(AQ44:AQ47) -> 0
A44: 10.1 | B44: Interest expense on deposits | C44: ='Evolutitve SCI'!B13+'Evolutitve SCI'!B16 -> 35841893 | D44: ='Evolutitve SCI'!C13+'Evolutitve SCI'!C16 -> 70623452 | E44: ='Evolutitve SCI'!D13+'Evolutitve SCI'!D16 -> 1.1108601e+08 | F44: ='Evolutitve SCI'!E13+'Evolutitve SCI'!E16 -> 1.483571e+08 | G44: ='Evolutitve SCI'!F13+'Evolutitve SCI'!F16 -> 1.9139303e+08 | H44: ='Evolutitve SCI'!G13+'Evolutitve SCI'!G16 -> 2.3492764e+08 | I44: ='Evolutitve SCI'!H13+'Evolutitve SCI'!H16 -> 5.509844e+08 | J44: ='Evolutitve SCI'!I13+'Evolutitve SCI'!I16 -> 3.1619005e+08 | ... AQ44: ='Evolutitve SCI'!AP13+'Evolutitve SCI'!AP16 -> 0
A45: 10.2 | B45: Dividend expense on share capital | C45: ='Evolutitve SCI'!B15 -> 0 | D45: ='Evolutitve SCI'!C15 -> 0 | E45: ='Evolutitve SCI'!D15 -> 0 | F45: ='Evolutitve SCI'!E15 -> 0 | G45: ='Evolutitve SCI'!F15 -> 0 | H45: ='Evolutitve SCI'!G15 -> 0 | I45: ='Evolutitve SCI'!H15 -> 0 | J45: ='Evolutitve SCI'!I15 -> 0 | ... AQ45: ='Evolutitve SCI'!AP15 -> 0
A46: 10.3 | B46: Interest expense on borrowed funds | C46: ='Evolutitve SCI'!B14 -> 0 | D46: ='Evolutitve SCI'!C14 -> 0 | E46: ='Evolutitve SCI'!D14 -> 0 | F46: ='Evolutitve SCI'!E14 -> 0 | G46: ='Evolutitve SCI'!F14 -> 0 | H46: ='Evolutitve SCI'!G14 -> 0 | I46: ='Evolutitve SCI'!H14 -> 0 | J46: ='Evolutitve SCI'!I14 -> 0 | ... AQ46: ='Evolutitve SCI'!AP14 -> 0
A47: 10.4 | B47: Opperating expenses | C47: ='Evolutitve SCI'!B23 -> 10962290 | D47: ='Evolutitve SCI'!C23 -> 22677464 | E47: ='Evolutitve SCI'!D23 -> 36524899 | F47: ='Evolutitve SCI'!E23 -> 47354729 | G47: ='Evolutitve SCI'!F23 -> 58963797 | H47: ='Evolutitve SCI'!G23 -> 70663335 | I47: ='Evolutitve SCI'!H23 -> 1.6809083e+08 | J47: ='Evolutitve SCI'!I23 -> 1.0049586e+08 | ... AQ47: ='Evolutitve SCI'!AP23 -> 0
B50: Total Income
B51: Net Financial Income
B52: Net Income
B53: Div + Int on Deposits
B54: Total Expenses
B55: Liquid Assets
B56: Short term (Deposits + Liabilities)
B57: Operating Expenses
B58: Financial Investments
B59: Equity Investments
B60: Non-Earning Assets

Sheet CASH FLOW
A1: STATEMENT OF CASHFLOWS FOR THE YEAR ENDED 31ST DECEMBER 2015
B2: 2015 | C2: 2014
A3: Cash flows from operating activities
A4: Interest receipts
A5: Interest Payments
A6: Payment to employees and suppliers
A7: Other receipts
A8: (Increase)/Decrease in Operating assets | B8: =B4+B5+B6+B7 -> 0 | C8: =SUM(C4:C7) -> 0
A9: Net loans to members | B9: -21420750 | C9: -19341453
A10: Recievables and prepayments | B10: 3405679 | C10: 644537
A11: Short term investments
A12: Increase/(Decrease) in Operating liabilities | B12: =SUM(B9:B11) -> -18015071 | C12: =SUM(C9:C11) -> -18696916
A13: Deposits from members | B13: 37542318 | C13: 70912356
A14: Decrease/Increase Risk Fund | B14: -2636186 | C14: 17927
A15: Increase/decrease on Interest bearing Liabilities | B15: -7154210 | C15: -4536404
A16: Sundry creditors | B16: -312508 | C16: -2877539
A17: Net cashflow from operating activities before income taxes | B17: =B8+B12+B13+B14+B15+B16 -> 9424343 | C17: =C8+C12+C13+C14+C15+C16 -> 44819424
A18: Income tax paid
A19: Net Cash from Operating activities | B19: =B17+B18 -> 9424343 | C19: =C17+C18 -> 44819424
A21: Cashflow from investing activities
A22: Purchase of Property and equipment | B22: -987736 | C22: -4053993
A23: Purchase of intangible assets
A24: Purchase of financial assets
A25: Movement of other reserves-
A26: Issue of Bonus | B26: -286875 | C26: -534318
A27: Dividends Received
A28: Net Cash from investing activities | B28: =SUM(B22:B27) -> -1274611 | C28: =SUM(C22:C27) -> -4588311 | E28: =810794136-637456683 -> 173337453
A30: Cashflow from financing activities
A31: Share capital contributions | B31: 34941877 | C31: 17467705
A32: Contribution to sinking fund
A33: Repayments of long term borrowings
A34: Dividend paid | B34: -6887998 | C34: -6887998
A35: Honorarium paid | B35: 0 | C35: 0
A36: Net cash from financing activities | B36: =SUM(B31:B35) -> 28053879 | C36: =SUM(C31:C35) -> 10579707
A37: Net (Decrease)/Increase in cash and cash equivalent | B37: =B19+B28+B36 -> 36203611 | C37: =C19+C28+C36 -> 50810820
A38: Cash and cash equivalent at the beginning of the year | B38: 207318182 | C38: 134933687
A39: Cash and cash equivalent at the end of the year | B39: =SUM(B37:B38) -> 243521793 | C39: =SUM(C37:C38) -> 185744507

Sheet Prudential Ratios
A1: KIMISITU SACCO SOCIETY LTD
A2: KIMISITU Sacco Financial Performance
A4: FINANCIAL SOUNDNESS INDICATORS | B4: Prude. Std | C4: Ref. # | D4: 43831 | E4: 43862 | F4: 43891 | G4: 43922 | H4: 43952 | I4: 43983 | J4: 44013 | K4: 44044 | L4: 44075 | M4: 44105 | N4: 44136 | O4: 44166 | P4: Audited 2020 | Q4: 44197 | R4: 44228 | S4: 44256 | T4: 44287 | U4: 44317 | V4: 44348 | W4: 44378 | X4: 44409 | Y4: 44440 | Z4: 44470 | AA4: 44501 | AB4: 44531 | AC4: Audited 2021 | AD4: 44562 | AE4: 44593 | AF4: 44621 | AG4: 44652 | AH4: 44682 | AI4: 44713 | AJ4: 44743 | AK4: 44774 | AL4: 44805 | AM4: 44835 | AN4: 44866 | AO4: 44896 | AP4: 44927
A5: CAPITAL ADEQUACY REQUIREMENTS
A6: Core capital | B6: ≥ Ksh.10M | C6: 9.a | D6: =Financials!C11/1000000 -> 737.17807 | E6: =Financials!D11/1000000 -> 761.19551 | F6: =Financials!E11/1000000 -> 772.71667 | G6: =Financials!F11/1000000 -> 791.23497 | H6: =Financials!G11/1000000 -> 813.64083 | I6: =Financials!H11/1000000 -> 837.87222 | J6: =Financials!I11/1000000 -> 859.01278 | K6: =Financials!J11/1000000 -> 867.81054 | ... BD6: =Financials!BC11/1000000 -> 0
A7: Core capital /Total Assets | B7: ≥ 10% | C7: 9.b | D7: =Financials!C11/Financials!C4 -> 0.10654464 | E7: =Financials!D11/Financials!D4 -> 0.10984823 | F7: =Financials!E11/Financials!E4 -> 0.11521164 | G7: =Financials!F11/Financials!F4 -> 0.11727834 | H7: =Financials!G11/Financials!G4 -> 0.11871892 | I7: =Financials!H11/Financials!H4 -> 0.12011943 | J7: =Financials!I11/Financials!I4 -> 0.12076843 | K7: =Financials!J11/Financials!J4 -> 0.12033803 | ... BD7: =Financials!BC11/Financials!BC4 -> #DIV/0!
A8: Core capital /Total Deposits | B8: ≥ 8% | C8: 9.d | D8: =Financials!C11/Financials!C5 -> 0.13639996 | E8: =Financials!D11/Financials!D5 -> 0.13882672 | F8: =Financials!E11/Financials!E5 -> 0.13896628 | G8: =Financials!F11/Financials!F5 -> 0.14138328 | H8: =Financials!G11/Financials!G5 -> 0.14408246 | I8: =Financials!H11/Financials!H5 -> 0.14690677 | J8: =Financials!I11/Financials!I5 -> 0.14844854 | K8: =Financials!J11/Financials!J5 -> 0.14876145 | ... BD8: =Financials!BC11/Financials!BC5 -> #DIV/0!
A9: Share Capital/Total Assets | B9: ≤2% | C9: 9.c | D9: =Financials!C15/Financials!C4 -> 0.048991284 | E9: =Financials!D15/Financials!D4 -> 0.049878312 | F9: =Financials!E15/Financials!E4 -> 0.051951189 | G9: =Financials!F15/Financials!F4 -> 0.052244436 | H9: =Financials!G15/Financials!G4 -> 0.051815455 | I9: =Financials!H15/Financials!H4 -> 0.051397962 | J9: =Financials!I15/Financials!I4 -> 0.050992341 | K9: =Financials!J15/Financials!J4 -> 0.050741425 | ... BD9: =Financials!BC15/Financials!BC4 -> #DIV/0!
A10: Institutional Capital/Total Assets | B10: ≥ 8% | C10: 9.c | D10: =Financials!C12/Financials!C4 -> 0.057553351 | E10: =Financials!D12/Financials!D4 -> 0.059969922 | F10: =Financials!E12/Financials!E4 -> 0.063260446 | G10: =Financials!F12/Financials!F4 -> 0.065033904 | H10: =Financials!G12/Financials!G4 -> 0.066903468 | I10: =Financials!H12/Financials!H4 -> 0.068721471 | J10: =Financials!I12/Financials!I4 -> 0.069776089 | K10: =Financials!J12/Financials!J4 -> 0.069596601 | ... BD10: =Financials!BC12/Financials!BC4 -> #DIV/0!
A12: ASSET MIX AND QUALITY
A13: Non Earning Assets
A14: Non earning Assets/Total assets | B14: ≤ 10% | C14: 48.1 | D14: =('Evolutive SFP'!B7+'Evolutive SFP'!B17+'Evolutive SFP'!B21)/'Evolutive SFP'!B27 -> 0.073166299 | E14: =('Evolutive SFP'!C7+'Evolutive SFP'!C17+'Evolutive SFP'!C21)/'Evolutive SFP'!C27 -> 0.074890795 | F14: =('Evolutive SFP'!D7+'Evolutive SFP'!D17+'Evolutive SFP'!D21)/'Evolutive SFP'!D27 -> 0.077806931 | G14: =('Evolutive SFP'!E7+'Evolutive SFP'!E17+'Evolutive SFP'!E21)/'Evolutive SFP'!E27 -> 0.081944271 | H14: =('Evolutive SFP'!F7+'Evolutive SFP'!F17+'Evolutive SFP'!F21)/'Evolutive SFP'!F27 -> 0.080704934 | I14: =('Evolutive SFP'!G7+'Evolutive SFP'!G17+'Evolutive SFP'!G21)/'Evolutive SFP'!G27 -> 0.067809419 | J14: =('Evolutive SFP'!H7+'Evolutive SFP'!H17+'Evolutive SFP'!H21)/'Evolutive SFP'!H27 -> 0.067355254 | K14: =('Evolutive SFP'!I7+'Evolutive SFP'!I17+'Evolutive SFP'!I21)/'Evolutive SFP'!I27 -> 0.06736551 | ... BD14: =('Evolutive SFP'!BB7+'Evolutive SFP'!BB17+'Evolutive SFP'!BB21)/'Evolutive SFP'!BB27 -> #DIV/0!
A15: Property and Equipment/Total Assets | B15: ≤ 5% | C15: 48.1 | D15: =Financials!C35/Financials!C4 -> 0.051279293 | E15: =Financials!D35/Financials!D4 -> 0 | F15: =Financials!E35/Financials!E4 -> 0.053653345 | G15: =Financials!F35/Financials!F4 -> 0.053678244 | H15: =Financials!G35/Financials!G4 -> 0.052995712 | I15: =Financials!H35/Financials!H4 -> 0.052021881 | J15: =Financials!I35/Financials!I4 -> 0.051070777 | K15: =Financials!J35/Financials!J4 -> 0.050495564 | ... BD15: =Financials!BC35/Financials!BC4 -> #DIV/0!
A16: Non Performing loans/Gross Loans | B16: ≤ 6% | C16: 41 | D16: ='FORM 4'!#REF! -> #REF! | E16: ='FORM 4'!#REF! -> #REF! | F16: 0.04 | G16: ='FORM 4'!#REF! -> #REF! | H16: ='FORM 4'!#REF! -> #REF! | I16: 0.0501 | J16: ='FORM 4'!#REF! -> #REF! | K16: ='FORM 4'!#REF! -> #REF! | L16: ='FORM 4'!#REF! -> #REF! | M16: ='FORM 4'!#REF! -> #REF! | N16: ='FORM 4'!#REF! -> #REF! | O16: ='FORM 4'!#REF! -> #REF! | P16: ='FORM 4'!#REF! -> #REF! | Q16: ='FORM 4'!#REF! -> #REF! | ... BD16: ='FORM 4'!#REF! -> #REF!
A18: Earning Assets
A19: Equities & Investments/Deposits | B19: ≤ 5% | C19: 48.4 | D19: =Financials!C25/Financials!C5 -> 0.0068816509 | E19: =Financials!D25/Financials!D5 -> 0.0067830911 | F19: =Financials!E25/Financials!E5 -> 0.006688673 | G19: =Financials!F25/Financials!F5 -> 0.051317453 | H19: =Financials!G25/Financials!G5 -> 0.050857017 | I19: =Financials!H25/Financials!H5 -> 0.052814128 | J19: =Financials!I25/Financials!I5 -> 0.052554851 | K19: =Financials!J25/Financials!J5 -> 0.057960047 | ... BD19: =Financials!BC25/Financials!BC5 -> #DIV/0!
A20: Equities & Investments/Core Capital | B20: ≤ 40% | C20: 48.4 | D20: =Financials!C25/Financials!C11 -> 0.050452001 | E20: =Financials!D25/Financials!D11 -> 0.048860126 | F20: =Financials!E25/Financials!E11 -> 0.048131625 | G20: =Financials!F25/Financials!F11 -> 0.36296691 | H20: =Financials!G25/Financials!G11 -> 0.3529716 | I20: =Financials!H25/Financials!H11 -> 0.3595078 | J20: =Financials!I25/Financials!I11 -> 0.35402742 | K20: =Financials!J25/Financials!J11 -> 0.38961739 | ... BD20: =Financials!BC25/Financials!BC11 -> #DIV/0!
A21: Net Loans & advances /Total assets | B21: NPR | D21: =Financials!C30/Financials!C4 -> 0.75938915 | E21: =Financials!D30/Financials!D4 -> 0.74545064 | F21: =Financials!E30/Financials!E4 -> 0.77632206 | G21: =Financials!F30/Financials!F4 -> 0.77292259 | H21: =Financials!G30/Financials!G4 -> 0.75651306 | I21: =Financials!H30/Financials!H4 -> 0.74055805 | J21: =Financials!I30/Financials!I4 -> 0.73116462 | K21: =Financials!J30/Financials!J4 -> 0.72873215 | ... BD21: =Financials!BC30/Financials!BC4 -> #DIV/0!
A23: FUNDING MIX
A24: Total Deposits/Total Assets | B24: NPR | D24: =Financials!C5/Financials!C4 -> 0.78111926 | E24: =Financials!D5/Financials!D4 -> 0.79126145 | F24: =Financials!E5/Financials!E4 -> 0.82906179 | G24: =Financials!F5/Financials!F4 -> 0.8295064 | H24: =Financials!G5/Financials!G4 -> 0.82396512 | I24: =Financials!H5/Financials!H4 -> 0.8176576 | J24: =Financials!I5/Financials!I4 -> 0.81353737 | K24: =Financials!J5/Financials!J4 -> 0.80893288 | ... BD24: =Financials!BC5/Financials!BC4 -> #DIV/0!
A25: BOSA Deposits/Total Assets | B25: NPR | D25: =Financials!C6/Financials!C4 -> 0.77315199 | E25: =Financials!D6/Financials!D4 -> 0.78293656 | F25: =Financials!E6/Financials!E4 -> 0.81997075 | G25: =Financials!F6/Financials!F4 -> 0.8196727 | H25: =Financials!G6/Financials!G4 -> 0.81371589 | I25: =Financials!H6/Financials!H4 -> 0.8045367 | J25: =Financials!I6/Financials!I4 -> 0.80070728 | K25: =Financials!J6/Financials!J4 -> 0.79722406 | ... BD25: =Financials!BC6/Financials!BC4 -> #DIV/0!
A26: FOSA Deposits/Total Assets | B26: NPR | D26: =Financials!C7/Financials!C4 -> 0.0079672684 | E26: =Financials!D7/Financials!D4 -> 0.0083248928 | F26: =Financials!E7/Financials!E4 -> 0.0090910402 | G26: =Financials!F7/Financials!F4 -> 0.0098337001 | H26: =Financials!G7/Financials!G4 -> 0.01024923 | I26: =Financials!H7/Financials!H4 -> 0.013120906 | J26: =Financials!I7/Financials!I4 -> 0.012830085 | K26: =Financials!J7/Financials!J4 -> 0.01170882 | ... BD26: =Financials!BC7/Financials!BC4 -> #DIV/0!
A27: External Borrowing/Total assets | B27: ≤ 25% | C27: 35.1 | D27: =Financials!C8/Financials!C4 -> 0 | E27: =Financials!D8/Financials!D4 -> 0.0019921987 | F27: =Financials!E8/Financials!E4 -> 0 | G27: =Financials!F8/Financials!F4 -> 0 | H27: =Financials!G8/Financials!G4 -> 0 | I27: =Financials!H8/Financials!H4 -> 0 | J27: =Financials!I8/Financials!I4 -> 0 | K27: =Financials!J8/Financials!J4 -> 0 | ... BD27: =Financials!BC8/Financials!BC4 -> #DIV/0!
A29: GROWTH RATIOS
A30: Total Assets | B30: NPR | D30: 0.031257705 | E30: 0.0067457959 | F30: 0.019779457 | G30: -0.008526631 | H30: 0.0077077653 | I30: 0.0050623348 | J30: -0.0037644421 | K30: 0.002533208 | L30: 0.002533208 | M30: 0.002533208 | N30: 0.002533208 | O30: 0.002533208 | P30: 0.002533208 | Q30: 0.002533208 | R30: 0.002533208 | S30: 0.002533208 | T30: 0.002533208 | U30: 0.002533208 | V30: 0.002533208 | W30: 0.002533208 | X30: 0.002533208 | Y30: 0.002533208 | Z30: 0.002533208 | AA30: 0.002533208 | AB30: 0.002533208 | AC30: 0.002533208 | AD30: 0.002533208 | AE30: 0.002533208 | AF30: 0.002533208 | AG30: 0.002533208 | AH30: 0.002533208 | AI30: 0.002533208 | AJ30: 0.002533208 | AK30: 0.002533208 | AL30: 0.002533208 | AM30: 0.002533208 | AN30: 0.002533208 | AO30: 0.002533208 | AP30: 0.002533208 | AQ30: 0.002533208 | AR30: 0.002533208 | AS30: 0.002533208 | AT30: 0.002533208 | AU30: 0.002533208 | AV30: 0.002533208 | AW30: 0.002533208 | AX30: 0.002533208 | AY30: 0.002533208 | AZ30: 0.002533208 | BA30: 0.002533208 | BB30: 0.002533208 | BC30: 0.002533208 | BD30: 0.002533208
A31: Total Deposits | B31: NPR | D31: -0.035093983 | E31: 0.05281735 | F31: -0.0087600184 | G31: -0.0010638542 | H31: 0.0022941794 | I31: -0.00017928582 | J31: -0.021102955 | K31: -0.0015087471 | L31: -0.0015087471 | M31: -0.0015087471 | N31: -0.0015087471 | O31: -0.0015087471 | P31: -0.0015087471 | Q31: -0.0015087471 | R31: -0.0015087471 | S31: -0.0015087471 | T31: -0.0015087471 | U31: -0.0015087471 | V31: -0.0015087471 | W31: -0.0015087471 | X31: -0.0015087471 | Y31: -0.0015087471 | Z31: -0.0015087471 | AA31: -0.0015087471 | AB31: -0.0015087471 | AC31: -0.0015087471 | AD31: -0.0015087471 | AE31: -0.0015087471 | AF31: -0.0015087471 | AG31: -0.0015087471 | AH31: -0.0015087471 | AI31: -0.0015087471 | AJ31: -0.0015087471 | AK31: -0.0015087471 | AL31: -0.0015087471 | AM31: -0.0015087471 | AN31: -0.0015087471 | AO31: -0.0015087471 | AP31: -0.0015087471 | AQ31: -0.0015087471 | AR31: -0.0015087471 | AS31: -0.0015087471 | AT31: -0.0015087471 | AU31: -0.0015087471 | AV31: -0.0015087471 | AW31: -0.0015087471 | AX31: -0.0015087471 | AY31: -0.0015087471 | AZ31: -0.0015087471 | BA31: -0.0015087471 | BB31: -0.0015087471 | BC31: -0.0015087471 | BD31: -0.0015087471
A32: FOSA Deposits | B32: NPR | D32: -0.052971373 | E32: 0.067219696 | F32: -0.016154937 | G32: -0.0047446665 | H32: -0.00061806271 | I32: -0.0051613776 | J32: -0.041211834 | K32: -0.0057699176 | L32: -0.0057699176 | M32: -0.0057699176 | N32: -0.0057699176 | O32: -0.0057699176 | P32: -0.0057699176 | Q32: -0.0057699176 | R32: -0.0057699176 | S32: -0.0057699176 | T32: -0.0057699176 | U32: -0.0057699176 | V32: -0.0057699176 | W32: -0.0057699176 | X32: -0.0057699176 | Y32: -0.0057699176 | Z32: -0.0057699176 | AA32: -0.0057699176 | AB32: -0.0057699176 | AC32: -0.0057699176 | AD32: -0.0057699176 | AE32: -0.0057699176 | AF32: -0.0057699176 | AG32: -0.0057699176 | AH32: -0.0057699176 | AI32: -0.0057699176 | AJ32: -0.0057699176 | AK32: -0.0057699176 | AL32: -0.0057699176 | AM32: -0.0057699176 | AN32: -0.0057699176 | AO32: -0.0057699176 | AP32: -0.0057699176 | AQ32: -0.0057699176 | AR32: -0.0057699176 | AS32: -0.0057699176 | AT32: -0.0057699176 | AU32: -0.0057699176 | AV32: -0.0057699176 | AW32: -0.0057699176 | AX32: -0.0057699176 | AY32: -0.0057699176 | AZ32: -0.0057699176 | BA32: -0.0057699176 | BB32: -0.0057699176 | BC32: -0.0057699176 | BD32: -0.0057699176
A33: BOSA Deposits | B33: NPR | D33: 0.0098330654 | E33: 0.01887433 | F33: 0.0094950683 | G33: 0.0077917189 | H33: 0.0092135117 | I33: 0.011542584 | J33: 0.02542795 | K33: 0.0077105975 | L33: 0.0077105975 | M33: 0.0077105975 | N33: 0.0077105975 | O33: 0.0077105975 | P33: 0.0077105975 | Q33: 0.0077105975 | R33: 0.0077105975 | S33: 0.0077105975 | T33: 0.0077105975 | U33: 0.0077105975 | V33: 0.0077105975 | W33: 0.0077105975 | X33: 0.0077105975 | Y33: 0.0077105975 | Z33: 0.0077105975 | AA33: 0.0077105975 | AB33: 0.0077105975 | AC33: 0.0077105975 | AD33: 0.0077105975 | AE33: 0.0077105975 | AF33: 0.0077105975 | AG33: 0.0077105975 | AH33: 0.0077105975 | AI33: 0.0077105975 | AJ33: 0.0077105975 | AK33: 0.0077105975 | AL33: 0.0077105975 | AM33: 0.0077105975 | AN33: 0.0077105975 | AO33: 0.0077105975 | AP33: 0.0077105975 | AQ33: 0.0077105975 | AR33: 0.0077105975 | AS33: 0.0077105975 | AT33: 0.0077105975 | AU33: 0.0077105975 | AV33: 0.0077105975 | AW33: 0.0077105975 | AX33: 0.0077105975 | AY33: 0.0077105975 | AZ33: 0.0077105975 | BA33: 0.0077105975 | BB33: 0.0077105975 | BC33: 0.0077105975 | BD33: 0.0077105975
A34: Net Loans & advances | B34: NPR | D34: =('Evolutive SFP'!B14-'Evolutive SFP'!#REF!)/'Evolutive SFP'!#REF! -> #REF! | E34: =('Evolutive SFP'!C14-'Evolutive SFP'!B14)/'Evolutive SFP'!B14 -> -0.016856702 | F34: =('Evolutive SFP'!D14-'Evolutive SFP'!C14)/'Evolutive SFP'!C14 -> 0.0079612448 | G34: =('Evolutive SFP'!E14-'Evolutive SFP'!D14)/'Evolutive SFP'!D14 -> 0.0015157807 | H34: =('Evolutive SFP'!F14-'Evolutive SFP'!E14)/'Evolutive SFP'!E14 -> -0.005727208 | I34: =('Evolutive SFP'!G14-'Evolutive SFP'!F14)/'Evolutive SFP'!F14 -> -0.0036901916 | J34: =('Evolutive SFP'!H14-'Evolutive SFP'!G14)/'Evolutive SFP'!G14 -> 0.0067873502 | K34: =('Evolutive SFP'!I14-'Evolutive SFP'!H14)/'Evolutive SFP'!H14 -> 0.01048201 | L34: =('Evolutive SFP'!J14-'Evolutive SFP'!I14)/'Evolutive SFP'!I14 -> 0.023604256 | ... BD34: =('Evolutive SFP'!BB14-'Evolutive SFP'!BA14)/'Evolutive SFP'!BA14 -> #DIV/0!
A35: Core capital | B35: NPR | D35: =(Financials!C11-Financials!#REF!)/Financials!#REF! -> #REF! | E35: =(Financials!D11-Financials!C11)/Financials!C11 -> 0.032580243 | F35: =(Financials!E11-Financials!D11)/Financials!D11 -> 0.015135607 | G35: =(Financials!F11-Financials!E11)/Financials!E11 -> 0.023965181 | H35: =(Financials!G11-Financials!F11)/Financials!F11 -> 0.02831759 | I35: =(Financials!H11-Financials!G11)/Financials!G11 -> 0.02978143 | J35: =(Financials!I11-Financials!H11)/Financials!H11 -> 0.02523125 | K35: =(Financials!J11-Financials!I11)/Financials!I11 -> 0.010241707 | L35: =(Financials!K11-Financials!J11)/Financials!J11 -> 0.022045747 | ... BD35: =(Financials!BC11-Financials!BB11)/Financials!BB11 -> #DIV/0!
A36: Total Gross Income | B36: NPR | D36: =('Evolutitve SCI'!B3-'Evolutitve SCI'!#REF!)/'Evolutitve SCI'!#REF! -> #REF! | E36: =('Evolutitve SCI'!C3-'Evolutitve SCI'!B3)/'Evolutitve SCI'!B3 -> 1.205668 | F36: =('Evolutitve SCI'!D3-'Evolutitve SCI'!C3)/'Evolutitve SCI'!C3 -> 0.69746284 | G36: =('Evolutitve SCI'!E3-'Evolutitve SCI'!D3)/'Evolutitve SCI'!D3 -> 0.32186323 | H36: =('Evolutitve SCI'!F3-'Evolutitve SCI'!E3)/'Evolutitve SCI'!E3 -> 0.28254465 | I36: =('Evolutitve SCI'!G3-'Evolutitve SCI'!F3)/'Evolutitve SCI'!F3 -> 0.22636983 | J36: =('Evolutitve SCI'!H3-'Evolutitve SCI'!G3)/'Evolutitve SCI'!G3 -> 1.3413544 | K36: =('Evolutitve SCI'!I3-'Evolutitve SCI'!H3)/'Evolutitve SCI'!H3 -> -0.42625609 | L36: =('Evolutitve SCI'!J3-'Evolutitve SCI'!I3)/'Evolutitve SCI'!I3 -> 0.13256153 | ... BD36: =('Evolutitve SCI'!BB3-'Evolutitve SCI'!BA3)/'Evolutitve SCI'!BA3 -> #DIV/0!
A37: Membership | B37: NPR
A39: Efficiency Ratios
A40: FinCost-Deposits/Average Deposits | B40: NPR
A41: FinCost-Shares/Average Share capital | B41: NPR
A42: FinCost-Ext Loans/Average Ext Loans | B42: NPR
A43: OpEx/Average Total Assets | B43: NPR
A44: Avge yield on Net loans | B44: NPR
A46: Liquidity Ratio
A47: Liquid Assets - ST Liabilities/ Deposits | B47: 0.15 | C47: 13.2 | D47: =('Evolutive SFP'!B4+'Evolutive SFP'!B11)/('Evolutive SFP'!B28+'Evolutive SFP'!B29+'Evolutive SFP'!B32+'Evolutive SFP'!B33+'Evolutive SFP'!B34+'Evolutive SFP'!B35+'Evolutive SFP'!B36) -> 1.2990298 | E47: =('Evolutive SFP'!C4+'Evolutive SFP'!C11)/('Evolutive SFP'!C28+'Evolutive SFP'!C29+'Evolutive SFP'!C32+'Evolutive SFP'!C33+'Evolutive SFP'!C34+'Evolutive SFP'!C35+'Evolutive SFP'!C36) -> 1.5695611 | F47: =('Evolutive SFP'!D4+'Evolutive SFP'!D11)/('Evolutive SFP'!D28+'Evolutive SFP'!D29+'Evolutive SFP'!D32+'Evolutive SFP'!D33+'Evolutive SFP'!D34+'Evolutive SFP'!D35+'Evolutive SFP'!D36) -> 2.0708482 | G47: =('Evolutive SFP'!E4+'Evolutive SFP'!E11)/('Evolutive SFP'!E28+'Evolutive SFP'!E29+'Evolutive SFP'!E32+'Evolutive SFP'!E33+'Evolutive SFP'!E34+'Evolutive SFP'!E35+'Evolutive SFP'!E36) -> 2.1253289 | H47: =('Evolutive SFP'!F4+'Evolutive SFP'!F11)/('Evolutive SFP'!F28+'Evolutive SFP'!F29+'Evolutive SFP'!F32+'Evolutive SFP'!F33+'Evolutive SFP'!F34+'Evolutive SFP'!F35+'Evolutive SFP'!F36) -> 2.2633506 | I47: =('Evolutive SFP'!G4+'Evolutive SFP'!G11)/('Evolutive SFP'!G28+'Evolutive SFP'!G29+'Evolutive SFP'!G32+'Evolutive SFP'!G33+'Evolutive SFP'!G34+'Evolutive SFP'!G35+'Evolutive SFP'!G36) -> 2.4452244 | J47: =('Evolutive SFP'!H4+'Evolutive SFP'!H11)/('Evolutive SFP'!H28+'Evolutive SFP'!H29+'Evolutive SFP'!H32+'Evolutive SFP'!H33+'Evolutive SFP'!H34+'Evolutive SFP'!H35+'Evolutive SFP'!H36) -> 2.4764785 | K47: =('Evolutive SFP'!I4+'Evolutive SFP'!I11)/('Evolutive SFP'!I28+'Evolutive SFP'!I29+'Evolutive SFP'!I32+'Evolutive SFP'!I33+'Evolutive SFP'!I34+'Evolutive SFP'!I35+'Evolutive SFP'!I36) -> 2.3806394 | ... O47: =('Evolutive SFP'!M4+'Evolutive SFP'!M11)/('Evolutive SFP'!M28+'Evolutive SFP'!M29+'Evolutive SFP'!M32+'Evolutive SFP'!M33+'Evolutive SFP'!M34+'Evolutive SFP'!M35+'Evolutive SFP'!M36) -> 2.1417262 | P47: =('Evolutive SFP'!N4+'Evolutive SFP'!#REF!)/('Evolutive SFP'!N28+'Evolutive SFP'!N29+'Evolutive SFP'!N32+'Evolutive SFP'!N33+'Evolutive SFP'!N34+'Evolutive SFP'!N35+'Evolutive SFP'!N36) -> #REF! | Q47: =('Evolutive SFP'!O4+'Evolutive SFP'!#REF!)/('Evolutive SFP'!O28+'Evolutive SFP'!O29+'Evolutive SFP'!O32+'Evolutive SFP'!O33+'Evolutive SFP'!O34+'Evolutive SFP'!O35+'Evolutive SFP'!O36) -> #REF! | R47: =('Evolutive SFP'!P4+'Evolutive SFP'!#REF!)/('Evolutive SFP'!P28+'Evolutive SFP'!P29+'Evolutive SFP'!P32+'Evolutive SFP'!P33+'Evolutive SFP'!P34+'Evolutive SFP'!P35+'Evolutive SFP'!P36) -> #REF! | S47: =('Evolutive SFP'!Q4+'Evolutive SFP'!#REF!)/('Evolutive SFP'!Q28+'Evolutive SFP'!Q29+'Evolutive SFP'!Q32+'Evolutive SFP'!Q33+'Evolutive SFP'!Q34+'Evolutive SFP'!Q35+'Evolutive SFP'!Q36) -> #REF! | T47: =('Evolutive SFP'!R4+'Evolutive SFP'!#REF!)/('Evolutive SFP'!R28+'Evolutive SFP'!R29+'Evolutive SFP'!R32+'Evolutive SFP'!R33+'Evolutive SFP'!R34+'Evolutive SFP'!R35+'Evolutive SFP'!R36) -> #REF! | U47: =('Evolutive SFP'!S4+'Evolutive SFP'!#REF!)/('Evolutive SFP'!S28+'Evolutive SFP'!S29+'Evolutive SFP'!S32+'Evolutive SFP'!S33+'Evolutive SFP'!S34+'Evolutive SFP'!S35+'Evolutive SFP'!S36) -> #REF! | V47: =('Evolutive SFP'!T4+'Evolutive SFP'!#REF!)/('Evolutive SFP'!T28+'Evolutive SFP'!T29+'Evolutive SFP'!T32+'Evolutive SFP'!T33+'Evolutive SFP'!T34+'Evolutive SFP'!T35+'Evolutive SFP'!T36) -> #REF! | W47: =('Evolutive SFP'!U4+'Evolutive SFP'!#REF!)/('Evolutive SFP'!U28+'Evolutive SFP'!U29+'Evolutive SFP'!U32+'Evolutive SFP'!U33+'Evolutive SFP'!U34+'Evolutive SFP'!U35+'Evolutive SFP'!U36) -> #REF! | ... BD47: =('Evolutive SFP'!BB4+'Evolutive SFP'!#REF!)/('Evolutive SFP'!BB28+'Evolutive SFP'!BB29+'Evolutive SFP'!BB32+'Evolutive SFP'!BB33+'Evolutive SFP'!BB34+'Evolutive SFP'!BB35+'Evolutive SFP'!BB36) -> #REF!
A49: Loan Loss Provisions Ratios
A50: Actual LLP / Required LLP | B50: 1 | C50: 44.1
A53: Minimum Liquidity | D53: =('Evolutive SFP'!B4+'Evolutive SFP'!C11)/('Evolutive SFP'!B28+'Evolutive SFP'!B29+'Evolutive SFP'!B32+'Evolutive SFP'!B33+'Evolutive SFP'!B34+'Evolutive SFP'!B35+'Evolutive SFP'!B36) -> 1.2990298 | E53: =('Evolutive SFP'!C4+'Evolutive SFP'!D11)/('Evolutive SFP'!C28+'Evolutive SFP'!C29+'Evolutive SFP'!C32+'Evolutive SFP'!C33+'Evolutive SFP'!C34+'Evolutive SFP'!C35+'Evolutive SFP'!C36) -> 1.5695611 | F53: =('Evolutive SFP'!D4+'Evolutive SFP'!E11)/('Evolutive SFP'!D28+'Evolutive SFP'!D29+'Evolutive SFP'!D32+'Evolutive SFP'!D33+'Evolutive SFP'!D34+'Evolutive SFP'!D35+'Evolutive SFP'!D36) -> 2.7286853 | G53: =('Evolutive SFP'!E4+'Evolutive SFP'!F11)/('Evolutive SFP'!E28+'Evolutive SFP'!E29+'Evolutive SFP'!E32+'Evolutive SFP'!E33+'Evolutive SFP'!E34+'Evolutive SFP'!E35+'Evolutive SFP'!E36) -> 2.1253289 | H53: =('Evolutive SFP'!F4+'Evolutive SFP'!G11)/('Evolutive SFP'!F28+'Evolutive SFP'!F29+'Evolutive SFP'!F32+'Evolutive SFP'!F33+'Evolutive SFP'!F34+'Evolutive SFP'!F35+'Evolutive SFP'!F36) -> 2.297706 | I53: =('Evolutive SFP'!G4+'Evolutive SFP'!H11)/('Evolutive SFP'!G28+'Evolutive SFP'!G29+'Evolutive SFP'!G32+'Evolutive SFP'!G33+'Evolutive SFP'!G34+'Evolutive SFP'!G35+'Evolutive SFP'!G36) -> 2.4513675 | J53: =('Evolutive SFP'!H4+'Evolutive SFP'!I11)/('Evolutive SFP'!H28+'Evolutive SFP'!H29+'Evolutive SFP'!H32+'Evolutive SFP'!H33+'Evolutive SFP'!H34+'Evolutive SFP'!H35+'Evolutive SFP'!H36) -> 2.5439601 | K53: =('Evolutive SFP'!I4+'Evolutive SFP'!J11)/('Evolutive SFP'!I28+'Evolutive SFP'!I29+'Evolutive SFP'!I32+'Evolutive SFP'!I33+'Evolutive SFP'!I34+'Evolutive SFP'!I35+'Evolutive SFP'!I36) -> 2.3852291 | ... N53: =('Evolutive SFP'!L4+'Evolutive SFP'!M11)/('Evolutive SFP'!L28+'Evolutive SFP'!L29+'Evolutive SFP'!L32+'Evolutive SFP'!L33+'Evolutive SFP'!L34+'Evolutive SFP'!L35+'Evolutive SFP'!L36) -> 2.4534042 | O53: =('Evolutive SFP'!M4+'Evolutive SFP'!#REF!)/('Evolutive SFP'!M28+'Evolutive SFP'!M29+'Evolutive SFP'!M32+'Evolutive SFP'!M33+'Evolutive SFP'!M34+'Evolutive SFP'!M35+'Evolutive SFP'!M36) -> #REF! | P53: =('Evolutive SFP'!N4+'Evolutive SFP'!O11)/('Evolutive SFP'!N28+'Evolutive SFP'!N29+'Evolutive SFP'!N32+'Evolutive SFP'!N33+'Evolutive SFP'!N34+'Evolutive SFP'!N35+'Evolutive SFP'!N36) -> 0.064494053
A54: Technical Liquidity | D54: =('Evolutive SFP'!B4+'Evolutive SFP'!B11)/('Evolutive SFP'!B28+'Evolutive SFP'!B29+'Evolutive SFP'!B30+'Evolutive SFP'!B32+'Evolutive SFP'!B33+'Evolutive SFP'!B34+'Evolutive SFP'!B35+'Evolutive SFP'!B36) -> 0.16487308 | E54: =('Evolutive SFP'!C4+'Evolutive SFP'!C11)/('Evolutive SFP'!C28+'Evolutive SFP'!C29+'Evolutive SFP'!C30+'Evolutive SFP'!C32+'Evolutive SFP'!C33+'Evolutive SFP'!C34+'Evolutive SFP'!C35+'Evolutive SFP'!C36) -> 0.17354461 | F54: =('Evolutive SFP'!D4+'Evolutive SFP'!D11)/('Evolutive SFP'!D28+'Evolutive SFP'!D29+'Evolutive SFP'!D30+'Evolutive SFP'!D32+'Evolutive SFP'!D33+'Evolutive SFP'!D34+'Evolutive SFP'!D35+'Evolutive SFP'!D36) -> 0.13385293 | G54: =('Evolutive SFP'!E4+'Evolutive SFP'!E11)/('Evolutive SFP'!E28+'Evolutive SFP'!E29+'Evolutive SFP'!E30+'Evolutive SFP'!E32+'Evolutive SFP'!E33+'Evolutive SFP'!E34+'Evolutive SFP'!E35+'Evolutive SFP'!E36) -> 0.13351023 | H54: =('Evolutive SFP'!F4+'Evolutive SFP'!F11)/('Evolutive SFP'!F28+'Evolutive SFP'!F29+'Evolutive SFP'!F30+'Evolutive SFP'!F32+'Evolutive SFP'!F33+'Evolutive SFP'!F34+'Evolutive SFP'!F35+'Evolutive SFP'!F36) -> 0.15442694 | I54: =('Evolutive SFP'!G4+'Evolutive SFP'!G11)/('Evolutive SFP'!G28+'Evolutive SFP'!G29+'Evolutive SFP'!G30+'Evolutive SFP'!G32+'Evolutive SFP'!G33+'Evolutive SFP'!G34+'Evolutive SFP'!G35+'Evolutive SFP'!G36) -> 0.1892798 | J54: =('Evolutive SFP'!H4+'Evolutive SFP'!H11)/('Evolutive SFP'!H28+'Evolutive SFP'!H29+'Evolutive SFP'!H30+'Evolutive SFP'!H32+'Evolutive SFP'!H33+'Evolutive SFP'!H34+'Evolutive SFP'!H35+'Evolutive SFP'!H36) -> 0.20127655 | K54: =('Evolutive SFP'!I4+'Evolutive SFP'!I11)/('Evolutive SFP'!I28+'Evolutive SFP'!I29+'Evolutive SFP'!I30+'Evolutive SFP'!I32+'Evolutive SFP'!I33+'Evolutive SFP'!I34+'Evolutive SFP'!I35+'Evolutive SFP'!I36) -> 0.20433884 | ... O54: =('Evolutive SFP'!M4+'Evolutive SFP'!M11)/('Evolutive SFP'!M28+'Evolutive SFP'!M29+'Evolutive SFP'!M30+'Evolutive SFP'!M32+'Evolutive SFP'!M33+'Evolutive SFP'!M34+'Evolutive SFP'!M35+'Evolutive SFP'!M36) -> 0.24144465 | P54: =('Evolutive SFP'!N4+'Evolutive SFP'!#REF!)/('Evolutive SFP'!N28+'Evolutive SFP'!N29+'Evolutive SFP'!N30+'Evolutive SFP'!N32+'Evolutive SFP'!N33+'Evolutive SFP'!N34+'Evolutive SFP'!N35+'Evolutive SFP'!N36) -> #REF!
A55: Net Interest Margin | D55: =('Evolutitve SCI'!B5-'Evolutitve SCI'!B13)/'Evolutive SFP'!B27 -> 0.00038798314 | E55: =('Evolutitve SCI'!C5-'Evolutitve SCI'!C13)/'Evolutive SFP'!C27 -> 0.0028414703 | F55: =('Evolutitve SCI'!D5-'Evolutitve SCI'!D13)/'Evolutive SFP'!D27 -> 0.0065940145 | G55: =('Evolutitve SCI'!E5-'Evolutitve SCI'!E13)/'Evolutive SFP'!E27 -> 0.0087475723 | H55: =('Evolutitve SCI'!F5-'Evolutitve SCI'!F13)/'Evolutive SFP'!F27 -> 0.011544914 | I55: =('Evolutitve SCI'!G5-'Evolutitve SCI'!G13)/'Evolutive SFP'!G27 -> 0.01301905 | J55: =('Evolutitve SCI'!H5-'Evolutitve SCI'!H13)/'Evolutive SFP'!H27 -> 0.030277928 | K55: =('Evolutitve SCI'!I5-'Evolutitve SCI'!I13)/'Evolutive SFP'!I27 -> 0.017579382 | ... P55: =('Evolutitve SCI'!N5-'Evolutitve SCI'!N13)/'Evolutive SFP'!N27 -> 0.030010032
A56: ROA | D56: =('Evolutitve SCI'!B33)/(('Evolutive SFP'!B27+'Evolutive SFP'!#REF!)/2) -> #REF! | E56: =('Evolutitve SCI'!C33)/(('Evolutive SFP'!C27+'Evolutive SFP'!B27)/2) -> 0.0020127032 | F56: =('Evolutitve SCI'!D33)/(('Evolutive SFP'!D27+'Evolutive SFP'!C27)/2) -> 0.0026783662 | G56: =('Evolutitve SCI'!E33)/(('Evolutive SFP'!E27+'Evolutive SFP'!D27)/2) -> 0.0049292469 | H56: =('Evolutitve SCI'!F33)/(('Evolutive SFP'!F27+'Evolutive SFP'!E27)/2) -> 0.0075962393 | I56: =('Evolutitve SCI'!G33)/(('Evolutive SFP'!G27+'Evolutive SFP'!F27)/2) -> 0.010352003 | J56: =('Evolutitve SCI'!H33)/(('Evolutive SFP'!H27+'Evolutive SFP'!G27)/2) -> 0.024737184 | K56: =('Evolutitve SCI'!I33)/(('Evolutive SFP'!I27+'Evolutive SFP'!H27)/2) -> 0.012534151 | L56: =('Evolutitve SCI'!J33)/(('Evolutive SFP'!J27+'Evolutive SFP'!I27)/2) -> 0.014308618 | ... P56: =('Evolutitve SCI'!N33)/(('Evolutive SFP'!N27+'Evolutive SFP'!M27)/2) -> 0.021141317
A57: Assets Growth Ratio | D57: =('Evolutive SFP'!B27-'Evolutive SFP'!#REF!)/'Evolutive SFP'!#REF! -> #REF! | E57: =('Evolutive SFP'!C27-'Evolutive SFP'!B27)/'Evolutive SFP'!B27 -> 0.0015262133 | F57: =('Evolutive SFP'!D27-'Evolutive SFP'!C27)/'Evolutive SFP'!C27 -> -0.032121603 | G57: =('Evolutive SFP'!E27-'Evolutive SFP'!D27)/'Evolutive SFP'!D27 -> 0.0059206507 | H57: =('Evolutive SFP'!F27-'Evolutive SFP'!E27)/'Evolutive SFP'!E27 -> 0.015839574 | I57: =('Evolutive SFP'!G27-'Evolutive SFP'!F27)/'Evolutive SFP'!F27 -> 0.017774877 | J57: =('Evolutive SFP'!H27-'Evolutive SFP'!G27)/'Evolutive SFP'!G27 -> 0.019721765 | K57: =('Evolutive SFP'!I27-'Evolutive SFP'!H27)/'Evolutive SFP'!H27 -> 0.013854959 | L57: =('Evolutive SFP'!J27-'Evolutive SFP'!I27)/'Evolutive SFP'!I27 -> 0.012136389 | ... P57: =('Evolutive SFP'!N27-'Evolutive SFP'!M27)/'Evolutive SFP'!M27 -> 0.00022371764
A58: Deposits Growth Ratio | D58: =(Financials!C5-Financials!#REF!)/Financials!#REF! -> #REF! | E58: =(Financials!D5-Financials!C5)/Financials!C5 -> 0.01453021 | F58: =(Financials!E5-Financials!D5)/Financials!D5 -> 0.014116123 | G58: =(Financials!F5-Financials!E5)/Financials!E5 -> 0.0064601129 | H58: =(Financials!G5-Financials!F5)/Financials!F5 -> 0.0090535403 | I58: =(Financials!H5-Financials!G5)/Financials!G5 -> 0.0099837352 | J58: =(Financials!I5-Financials!H5)/Financials!H5 -> 0.014583314 | K58: =(Financials!J5-Financials!I5)/Financials!I5 -> 0.0081167097 | L58: =(Financials!K5-Financials!J5)/Financials!J5 -> 0.0073769599 | ... P58: =(Financials!O5-Financials!N5)/Financials!N5 -> 6.011994e-05
A59: BOSA Growth Ratio | D59: =(Financials!C6-Financials!#REF!)/Financials!#REF! -> #REF! | E59: =(Financials!D6-Financials!C6)/Financials!C6 -> 0.014200955 | F59: =(Financials!E6-Financials!D6)/Financials!D6 -> 0.013660641 | G59: =(Financials!F6-Financials!E6)/Financials!E6 -> 0.0055550164 | H59: =(Financials!G6-Financials!F6)/Financials!F6 -> 0.0084571522 | I59: =(Financials!H6-Financials!G6)/Financials!G6 -> 0.0062937826 | J59: =(Financials!I6-Financials!H6)/Financials!H6 -> 0.014868117 | K59: =(Financials!J6-Financials!I6)/Financials!I6 -> 0.0094445084 | L59: =(Financials!K6-Financials!J6)/Financials!J6 -> 0.0063601427 | ... P59: =(Financials!O6-Financials!N6)/Financials!N6 -> -0.98510926
A60: FOSA Growth Ratio | D60: =(Financials!C7-Financials!#REF!)/Financials!#REF! -> #REF! | E60: =(Financials!D7-Financials!C7)/Financials!C7 -> 0.046481413 | F60: =(Financials!E7-Financials!D7)/Financials!D7 -> 0.056953119 | G60: =(Financials!F7-Financials!E7)/Financials!E7 -> 0.088095733 | H60: =(Financials!G7-Financials!F7)/Financials!F7 -> 0.058764537 | I60: =(Financials!H7-Financials!G7)/Financials!G7 -> 0.30293971 | J60: =(Financials!I7-Financials!H7)/Financials!H7 -> -0.00288001 | K60: =(Financials!J7-Financials!I7)/Financials!I7 -> -0.074749308 | L60: =(Financials!K7-Financials!J7)/Financials!J7 -> 0.076609476 | ... P60: =(Financials!O7-Financials!N7)/Financials!N7 -> 66.422255
M63: =12.2-9.64 -> 2.56

Sheet Feedback report
A1: STIMA SACCO SOCIETY LIMITED CS/NO: 2207
A2: PERFORMANCE AND COMPLIANCE REPORT AS AT : 30TH JUNE , 2018
B3: Prudential Standard | C3: Audited | D3: Returns | F3: Validated | G3: Average for all Licensed Saccos
C4: 2017 | D4: 43160 | E4: 43252
A5: A. CAPITAL ADEQUACY
A6: Core Capital | B6: ≥10M | C6: =C33 -> 3575294000 | D6: =D33 -> 3.6383881e+09 | E6: =E33 -> 3.8508836e+09 | F6: =F33 -> 0 | G6: =G33 -> 6.9326568e+10
A7: Core Capital/Total Assets | B7: ≥10% | C7: =C33/C29 -> 0.12516247 | D7: =D33/D29 -> 0.12404378 | E7: =E33/E29 -> 0.12810105 | F7: =F33/F29 -> #DIV/0! | G7: =G33/G29 -> 0.15142619
A8: Institutional Capital/Total Assets | B8: ≥8% | C8: =C34/C29 -> 0.084655346 | D8: =D34/D29 -> 0.080427602 | E8: =E34/E29 -> 0.082116799 | F8: =F34/F29 -> #DIV/0! | G8: =G34/G29 -> 0.086793277
A9: B. ASSET QUALITY
A10: NPL (Substandard+Doubtful+Loss) | B10: <5% | C10: =C35/C32 -> 0.083758752 | D10: =D35/D32 -> 0.069905965 | E10: =E35/E32 -> 0.064128919 | F10: =F35/F32 -> #DIV/0! | G10: =G35/G32 -> 0.064216556
A11: Non-Earning Assets | B11: <10% | C11: =C36/C29 -> 0.078233551 | D11: =D36/D29 -> 0.07077156 | E11: =E36/E29 -> 0.073871285 | F11: =F36/F29 -> #DIV/0! | G11: =G36/G29 -> 0.21105592
A12: Equity investments/Deposits | B12: <5% | C12: =C38/C31 -> 0.039319754 | D12: =D38/D31 -> 0.035325792 | E12: =E38/E31 -> 0.037197617 | F12: =F38/F31 -> #DIV/0! | G12: =G38/G31 -> 0.041240427
A13: Equity investments/Core capital | B13: <40% | C13: =C38/C33 -> 0.24098997 | D13: =D38/D33 -> 0.22956689 | E13: =E38/E33 -> 0.22930111 | F13: =F38/F33 -> #DIV/0! | G13: =G38/G33 -> 0.19351903
A14: C. EARNINGS RATING
A15: Yield on Gross Loans | C15: =C41/C32 -> 0.076755322 | D15: =D41/D32 -> 0.019738298 | E15: =E41/E32 -> 0.038638319 | F15: =F41/F32 -> #DIV/0! | G15: =G41/G32 -> 0.060128916
A16: Total Expense/Total Income | C16: =C44/C40 -> 0.8602912 | D16: =D44/D40 -> 0.91284222 | E16: =E44/E40 -> 0.88209003 | F16: =F44/F40 -> #DIV/0! | G16: =G44/G40 -> 0.79898157
A17: Net Income/Average Assets | C17: =C42/C30 -> 0.021114194 | D17: =D42/D30 -> 0.0032004404 | E17: =E42/E30 -> 0.0085246189 | F17: =F42/F30 -> #DIV/0! | G17: =G42/G30 -> 0.014471496
A18: Operating Expenses/Net Income (OPEX) | C18: =C45/C42 -> 1.8241433 | D18: =D45/D42 -> 2.5388457 | E18: =E45/E42 -> 2.0792721 | F18: =F45/F42 -> #DIV/0! | G18: =G45/G42 -> 1.6778105
A19: D. LIQUIDITY
A20: Liquid Assets/Short-term Liabilities | B20: >15% | C20: =C46/C47 -> 0.33588266 | D20: =D46/D47 -> 0.44544133 | E20: =E46/E47 -> 0.45759283 | F20: =F46/F47 -> #DIV/0! | G20: =G46/G47 -> 0.53762833
A21: External Borrowing/Total Assets | B21: <25% | C21: =C48/C29 -> 0.015941271 | D21: =D48/D29 -> 0.014155771 | E21: =E48/E29 -> 0.012698777 | F21: =F48/F29 -> #DIV/0! | G21: =G48/G29 -> 0.048858222
A22: Liquid Assets/Total Assets | C22: =C46/C29 -> 0.089409238 | D22: =D46/D29 -> 0.11709895 | E22: =E46/E29 -> 0.11553873 | F22: =F46/F29 -> #DIV/0! | G22: =G46/G29 -> 0.10366677
A23: E. STRUCTURE/SENSITIVITY TO RISK
A24: Gross loans /Total Assets | B24: 70-80 | C24: =C32/C29 -> 0.81615737 | D24: =D32/D29 -> 0.80219752 | E24: =E32/E29 -> 0.80146237 | F24: =F32/F29 -> #DIV/0! | G24: =G32/G29 -> 0.75746736
A25: Gross loans/Deposits | B25: >100% | C25: =C32/C31 -> 1.0639265 | D25: =D32/D31 -> 0.99515095 | E25: =E32/E31 -> 1.0149377 | F25: =F32/F31 -> #DIV/0! | G25: =G32/G31 -> 1.0660128
A26: Financial Investments/Total Assets | C26: =C39/C29 -> 0.038223399 | D26: =D39/D29 -> 0.02937488 | E26: =E39/E29 -> 0.030250433 | F26: =F39/F29 -> #DIV/0! | G26: =G39/G29 -> 0.043658487
A27: Dividends+Interest on Deposits/Total Income | C27: =C43/C40 -> 0.95525793 | D27: =D43/D40 -> 0.54694558 | E27: =E43/E40 -> 0.54728259 | F27: =F43/F40 -> #DIV/0! | G27: =G43/G40 -> 0.27724023
A28: F. KEY FINANCIAL STATISTICS | C28: 2015 | D28: 2016 | E28: 2017 | G28: AGGREGATE
A29: Total Assets | C29: 28565225000 | D29: 2.9331483e+10 | E29: 3.0061295e+10 | G29: 4.5782417e+11
A30: Average Assets | C30: 26523579000 | D30: 2.8948354e+10 | E30: 2.931326e+10 | G30: 4.5005065e+11
A31: Total Deposits | C31: 21912904000 | D31: 2.3644295e+10 | E31: 2.3738399e+10 | G31: 3.253121e+11
A32: Gross Loans | C32: 23313719000 | D32: 2.3529643e+10 | E32: 2.4092997e+10 | G32: 3.4678687e+11
A33: Core Capital | C33: 3575294000 | D33: 3.6383881e+09 | E33: 3.8508836e+09 | G33: 6.9326568e+10
A34: Institutional Capital | C34: 2418199000 | D34: 2.3590608e+09 | E34: 2.4685373e+09 | G34: 3.973606e+10
A35: Non-performing Loans | C35: 1952728000 | D35: 1.6448624e+09 | E35: 1.5450578e+09 | G35: 2.2269458e+10
A36: Non-Earning Assets | C36: 2234759000 | D36: 2.0758348e+09 | E36: 2.2206665e+09 | G36: 9.66265e+10
A37: Property and Equipment | C37: 235465000 | D37: 2.3485688e+08 | E37: 2.2615095e+08 | G37: 1.5408701e+10
A38: Equity Investments | C38: 861610000 | D38: 8.3525346e+08 | E38: 8.8301186e+08 | G38: 1.341601e+10
A39: Financial Investments | C39: 1091860000 | D39: 8.616088e+08 | E39: 9.0936721e+08 | G39: 1.9987911e+10
A40: Total Income | C40: 4008509000 | D40: 1.0629858e+09 | E40: 2.119281e+09 | G40: 3.2399548e+10
... A48: External Borrowing | C48: 455366000 | D48: 4.1520974e+08 | E48: 3.8174169e+08 | G48: 2.2368475e+10
A49: G. AREAS OF IMPROVEMENT/REGULARTORY CONCERNS
A50: 1. The ratio of NPL is above the prescribed limit
A51: 2
A52: 3
A53: 4
A54: Prepared by: Daniel Mwatu
A56: Checked by:
A58: Approved by: Peter Njuguna
A60: DISCLAIMER: This report is prepared based on information submitted by the Sacco as at the stated date and may change upon verification by the Authority.
