Workbook
Name BALANCE1_LDA01: '[1]Financial Statements'!$E$112
Name BALANCE1_LDA12: '[1]Financial Statements'!$E$123
Name BALANCE2_LDA01: '[1]Financial Statements'!$F$112
Name BALANCE2_LDA12: '[1]Financial Statements'!$F$123
Name BALANCE3_LDA01: '[1]Financial Statements'!$G$112
Name BALANCE3_LDA12: '[1]Financial Statements'!$G$123
Name BALANCE4_LDA01: '[1]Financial Statements'!$H$112
Name BALANCE4_LDA12: '[1]Financial Statements'!$H$123
Name BALANCE5_LDA01: '[1]Financial Statements'!$I$112
Name BALANCE5_LDA12: '[1]Financial Statements'!$I$123
Name BALANCE6_LDA01: '[1]Financial Statements'!$J$112
Name BALANCE6_LDA12: '[1]Financial Statements'!$J$123
Name PEARLS1_LA002: '[1]Financial Statements'!$E$280
Name PEARLS1_LE008: '[1]Financial Statements'!$E$275
Name PEARLS1_LE009: '[1]Financial Statements'!$E$276
Name PEARLS1_LR001: '[1]Financial Statements'!$E$282
Name PEARLS1_LR005: '[1]Financial Statements'!$E$286
Name PEARLS1_LR006: '[1]Financial Statements'!$E$287
Name PEARLS1_LR007: '[1]Financial Statements'!$E$288
Name PEARLS1_LR009: '[1]Financial Statements'!$E$290
Name PEARLS1_LS001: '[1]Financial Statements'!$E$298
Name PEARLS1_LS005: '[1]Financial Statements'!$E$302
Name PEARLS1_LS011: '[1]Financial Statements'!$E$308
Name PEARLS2_LA002: '[1]Financial Statements'!$F$280
Name PEARLS2_LE008: '[1]Financial Statements'!$F$275
Name PEARLS2_LE009: '[1]Financial Statements'!$F$276
Name PEARLS2_LR001: '[1]Financial Statements'!$F$282
Name PEARLS2_LR005: '[1]Financial Statements'!$F$286
Name PEARLS2_LR006: '[1]Financial Statements'!$F$287
Name PEARLS2_LR007: '[1]Financial Statements'!$F$288
Name PEARLS2_LR009: '[1]Financial Statements'!$F$290
Name PEARLS2_LS001: '[1]Financial Statements'!$F$298
Name PEARLS2_LS005: '[1]Financial Statements'!$F$302
Name PEARLS2_LS010: '[1]Financial Statements'!$F$307
Name PEARLS2_LS011: '[1]Financial Statements'!$F$308
Name PEARLS3_LA002: '[1]Financial Statements'!$G$280
Name PEARLS3_LE008: '[1]Financial Statements'!$G$275
Name PEARLS3_LE009: '[1]Financial Statements'!$G$276
Name PEARLS3_LR001: '[1]Financial Statements'!$G$282
Name PEARLS3_LR005: '[1]Financial Statements'!$G$286
Name PEARLS3_LR006: '[1]Financial Statements'!$G$287
Name PEARLS3_LR007: '[1]Financial Statements'!$G$288
Name PEARLS3_LR009: '[1]Financial Statements'!$G$290
Name PEARLS3_LS001: '[1]Financial Statements'!$G$298
Name PEARLS3_LS005: '[1]Financial Statements'!$G$302
Name PEARLS3_LS010: '[1]Financial Statements'!$G$307
Name PEARLS3_LS011: '[1]Financial Statements'!$G$308
Name PEARLS4_LA002: '[1]Financial Statements'!$H$280
Name PEARLS4_LE008: '[1]Financial Statements'!$H$275
Name PEARLS4_LE009: '[1]Financial Statements'!$H$276
Name PEARLS4_LR001: '[1]Financial Statements'!$H$282
Name PEARLS4_LR005: '[1]Financial Statements'!$H$286
Name PEARLS4_LR006: '[1]Financial Statements'!$H$287
Name PEARLS4_LR007: '[1]Financial Statements'!$H$288
Name PEARLS4_LR009: '[1]Financial Statements'!$H$290
Name PEARLS4_LS001: '[1]Financial Statements'!$H$298
Name PEARLS4_LS005: '[1]Financial Statements'!$H$302
Name PEARLS4_LS010: '[1]Financial Statements'!$H$307
Name PEARLS4_LS011: '[1]Financial Statements'!$H$308
Name PEARLS5_LA002: '[1]Financial Statements'!$I$280

Sheet Evolutive SFP
B3: AUDITED 2011 | C3: AUDITED 2012 | D3: AUDITED 2013 | E3: AUDITED 2014 | F3: AUDITED 2015 | G3: AUDITED 2016 | H3: AUDITED 2017 | I3: 43101 | J3: 43132 | K3: 43160 | L3: 43191 | M3: 43221 | N3: 43252 | O3: 43282 | P3: 43313 | Q3: 43344 | R3: 43374 | S3: 43405 | T3: 43435 | U3: AUDITED 2018 | V3: 43466 | W3: 43497 | X3: 43525 | Y3: 43556 | Z3: 43586 | AA3: 43617 | AB3: 43647 | AC3: 43678 | AD3: 43709 | AE3: 43739 | AF3: 43770 | AG3: 43800 | AH3: AUDITED 2019 | AI3: 43831 | AJ3: 43862 | AK3: 43891 | AL3: 43922 | AM3: 43952 | AN3: 43983 | AO3: 44044 | AP3: 44075 | AQ3: 44105 | AR3: 44136 | AS3: 44166 | AT3: Audited 2020 | AU3: 44197 | AV3: 44228 | AW3: 44256 | AX3: 44287 | AY3: 44317 | AZ3: 44348 | BA3: 44378 | BB3: 44409 | BC3: 44440 | BD3: 44470 | BE3: 44501 | BF3: 44531 | BG3: Audited 2021 | BH3: 44562 | BI3: 44593 | BJ3: 44621 | BK3: 44652 | BL3: 44682 | BM3: 44713 | BN3: 44743 | BO3: 44774 | BP3: 44805 | BQ3: 44835 | BR3: 44866 | BS3: 44896 | BT3: Audited 2022 | BU3: 44927 | BV3: 44958 | BW3: 44986 | BX3: 45017 | BY3: 45047 | BZ3: 45078 | CA3: 45108 | CB3: 45139 | CC3: 45170
A4: Cash & cash Equivalent | B4: =(B5+B6) -> 4171061 | C4: =(C5+C6) -> 2005744 | D4: =(D5+D6) -> 8488741 | E4: =(E5+E6) -> 13617624 | F4: =(F5+F6) -> 37177 | G4: =(G5+G6) -> 11883011 | H4: =(H5+H6) -> 42565374 | I4: =(I5+I6) -> 5094394.7 | ... CC4: =(CC5+CC6) -> 8208949.6
A5: Cash In Hand | B5: 4171061 | C5: 57008 | D5: 332646 | E5: 1730565 | F5: 37177 | G5: 65515 | H5: =2605926+300000+45078 -> 2951004 | I5: 2100894.4 | J5: 2840718.9 | K5: 2948528.9 | L5: 3616298.9 | M5: 3715914.9 | N5: 3993690.9 | O5: 5662806.8 | P5: 5249447.9 | Q5: 3867987.9 | R5: 4106300.9 | S5: 3993895.9 | T5: 6081154.9 | U5: 2243873 | V5: 3051990.8 | W5: 1952496.8 | X5: 1595603.8 | Y5: 4392495.8 | Z5: 5063685.8 | AA5: 1991970.8 | AB5: 2091535.8 | AC5: 3503758.8 | AD5: 5119051.8 | AE5: 2816540.8 | AF5: 2707491.5 | AG5: 2893023.5 | AH5: =1302655+300000 -> 1602655 | AI5: 4472837.5 | AJ5: 2707137.4 | AK5: 3765246.4 | AL5: 5676413.3 | AM5: 3006496.4 | AN5: 5635720 | AO5: 1602603 | AP5: 3007278 | AQ5: 2304652 | AR5: 910635.01 | AS5: 1117021 | AT5: =350000+767021 -> 1117021 | AU5: 841826.01 | AV5: 788748 | AW5: 3515180 | AX5: 2921068 | AY5: 3590315 | AZ5: 1243230 | BA5: 1386686 | BB5: 663432 | BC5: 540291 | BD5: 2948963 | BE5: 1133778 | BF5: 3138609.6 | BG5: =2788610+350000 -> 3138610 | BH5: 3478146.6 | BI5: 2466128 | BJ5: 3902992 | BK5: 1762070 | BL5: 3494705 | BM5: 1524682 | BN5: 3230642 | BO5: 3653246 | BP5: 2222849 | BQ5: 3421109 | BR5: 1811561 | BS5: 1523834 | BU5: 2267414 | BV5: 3612357 | BW5: 2426230 | BX5: 2095832 | BY5: 1168771 | BZ5: 3055884 | CA5: 1218725 | CB5: 3040357 | CC5: 644681
A6: Cash at Bank | C6: 1948736 | D6: 8156095 | E6: =13617624-E5 -> 11887059 | G6: =11883011-G5 -> 11817496 | H6: 39614370 | I6: 2993500.4 | J6: 4154969.8 | K6: 4732580.9 | L6: 4322904.8 | M6: 3996510.4 | N6: 2946237.8 | O6: 9186720.9 | P6: 4517338.4 | Q6: 10717274 | R6: 3432788.3 | S6: 11499159 | T6: 4082318.4 | U6: 9929688 | V6: 8574049.7 | W6: 4121185.3 | X6: 13109253 | Y6: 7833877.6 | Z6: 7836180.2 | AA6: 12326245 | AB6: 10240519 | AC6: 6468864.8 | AD6: 6771801.4 | AE6: 10257214 | AF6: 7282896.5 | AG6: 5600758.1 | AH6: =544474+809141+3448869+1159907+2614052+92466 -> 8668909 | AI6: 9904371.9 | AJ6: 11880178 | AK6: 6479516.6 | AL6: 6369183.7 | AM6: 10755203 | AN6: 7080660.5 | AO6: 18440443 | AP6: 15155242 | AQ6: 15528568 | AR6: 19850371 | AS6: 12512192 | AT6: =244474+8683434+827268+2757016 -> 12512192 | AU6: 9248375.1 | AV6: 9376232.4 | AW6: 12224670 | AX6: 11607855 | AY6: 11533765 | AZ6: 16106893 | BA6: 13898816 | BB6: 16437043 | BC6: 8310209.3 | BD6: 12323350 | BE6: 18075658 | BF6: 14060782 | BG6: =17087703-BG5 -> 13949093 | BH6: 13919000 | BI6: 16253029 | BJ6: 14535557 | BK6: 11669398 | BL6: 11023327 | BM6: 16080812 | BN6: 12992833 | BO6: 14025631 | BP6: 14593393 | BQ6: 15621493 | BR6: 16752223 | BS6: 13821847 | BU6: 12781319 | BV6: 11864595 | BW6: 12346481 | BX6: 12123127 | BY6: 12496725 | BZ6: 11800794 | CA6: 11790408 | CB6: 11409835 | CC6: 7564268.6
A7: Prepayment and Sundry | B7: 2679219 | C7: 863066 | D7: 2510315 | E7: 4516636 | F7: 2688882 | G7: 9292482 | H7: 2280087 | I7: 354051.21 | J7: 342674.14 | K7: 357893.57 | L7: 303292.64 | M7: 393785.73 | N7: 3283807.1 | O7: 412895.66 | P7: 2375574.3 | Q7: -7330670.1 | R7: 458062.56 | S7: -6529366.6 | T7: 3412095.9 | U7: 3966017 | V7: 1371464.7 | W7: 550435.84 | X7: 2047954.6 | Y7: 394102.95 | Z7: 414766.83 | AA7: -5886338.7 | AB7: 172169.78 | AC7: 445819.29 | AD7: 459521.24 | AE7: 314946.33 | AF7: 535417.06 | AG7: 418535.32 | AH7: 2019383 | AI7: 307618.88 | AJ7: 360688.41 | AK7: 578196.16 | AL7: 604875.16 | AM7: 236812.78 | AN7: 632852.16 | AO7: 560108 | AP7: 572430 | AQ7: 585589 | AR7: 599132 | AS7: 867414.81 | AT7: 1866499 | AU7: 611529 | AV7: 626207 | AW7: 637392 | AX7: 637392 | AY7: 665954 | AZ7: 685382 | BA7: 699317 | BB7: 699317 | BC7: 718911 | BD7: 741143 | BE7: 729142 | BF7: 652111.11 | BG7: =164500+1418098 -> 1582598 | BH7: 620660 | BI7: 631010 | BJ7: 636933 | BK7: 636933 | BL7: 655349 | BM7: 164500 | BN7: 172811 | BO7: 180705 | BP7: 192103 | BQ7: 192103 | BR7: 210346 | BS7: 164500 | BU7: 175667 | BV7: 187995 | BW7: 187995 | BX7: 187995 | BY7: 223545 | BZ7: 223545 | CA7: 223545 | CB7: 223545 | CC7: 164500
A8: Financial Investment | B8: =(B9+B10+B11+B13+B12) -> 4301970 | C8: =(C9+C10+C11+C13+C12) -> 4689870 | D8: =(D9+D10+D11+D13+D12) -> 6970410 | E8: =(E9+E10+E11+E13+E12) -> 9680814 | F8: =(F9+F10+F11+F13+F12) -> 11873268 | G8: =(G9+G10+G11+G13+G12) -> 13123495 | H8: =(H9+H10+H11+H13+H12) -> 14112600 | I8: =(I9+I10+I11+I13+I12) -> 0 | ... CC8: =(CC9+CC10+CC11+CC13+CC12) -> 8633989.4
A9: Government Security | I9: 0 | J9: 0 | K9: 0 | L9: 0 | M9: 0 | N9: 0 | O9: 0 | P9: 0 | Q9: 0 | R9: 0 | S9: 0 | T9: 0 | V9: 0 | W9: 0 | X9: 0 | Y9: 0 | Z9: 0 | AA9: 0 | AB9: 0 | AC9: 0 | AD9: 0 | AE9: 0 | AF9: 0 | AG9: 0 | AI9: 0 | AJ9: 0 | AK9: 0 | AL9: 0 | AM9: 0 | AN9: 0 | AO9: 0 | AP9: 0 | AQ9: 0 | AR9: 0 | AS9: 0 | AU9: 0 | AV9: 0 | AW9: 0 | AX9: 0 | AY9: 0 | AZ9: 0 | BA9: 0 | BB9: 0 | BC9: 0 | BD9: 0 | BE9: 0 | BF9: 0 | BH9: 0 | BI9: 0 | BJ9: 0 | BK9: 0 | BL9: 0 | BM9: 0 | BN9: 0 | BO9: 0 | BP9: 0 | BQ9: 0 | BR9: 0 | BS9: 0 | BU9: 0 | BV9: 0 | BW9: 0 | BX9: 0 | BY9: 0 | BZ9: 0 | CA9: 0 | CB9: 0 | CC9: 0
A10: Other Securities | I10: 0 | J10: 0 | K10: 0 | L10: 0 | M10: 0 | N10: 0 | O10: 0 | P10: 0 | Q10: 0 | R10: 0 | S10: 0 | T10: 0 | V10: 0 | W10: 0 | X10: 0 | Y10: 0 | Z10: 0 | AA10: 0 | AB10: 0 | AC10: 0 | AD10: 0 | AE10: 0 | AF10: 0 | AG10: 0 | AI10: 0 | AJ10: 0 | AK10: 0 | AL10: 0 | AM10: 0 | AN10: 0 | AO10: 0 | AP10: 0 | AQ10: 0 | AR10: 0 | AS10: 0 | AU10: 0 | AV10: 0 | AW10: 0 | AX10: 0 | AY10: 0 | AZ10: 0 | BA10: 0 | BB10: 0 | BC10: 0 | BD10: 0 | BE10: 0 | BF10: 0 | BH10: 0 | BI10: 0 | BJ10: 0 | BK10: 0 | BL10: 0 | BM10: 0 | BN10: 0 | BO10: 0 | BP10: 0 | BQ10: 0 | BR10: 0 | BS10: 0 | BU10: 0 | BV10: 0 | BW10: 0 | BX10: 0 | BY10: 0 | BZ10: 0 | CA10: 0 | CB10: 0 | CC10: 0
A11: Balances in NACCOS (E.g Jungu Kuu, ESS, Savings,Money Market,Coop FD, CFP) | I11: 0 | J11: 0 | K11: 0 | L11: 0 | M11: 0 | N11: 0 | O11: 0 | P11: 0 | Q11: 0 | R11: 0 | S11: 0 | T11: 0 | U11: 15098011 | V11: 0 | W11: 0 | X11: 0 | Y11: 0 | Z11: 0 | AA11: 0 | AB11: 0 | AC11: 0 | AD11: 0 | AE11: 0 | AF11: 0 | AG11: 0 | AI11: 0 | AJ11: 0 | AK11: 0 | AL11: 0 | AM11: 0 | AN11: 0 | AO11: 0 | AP11: 0 | AQ11: 0 | AR11: 0 | AS11: 0 | AU11: 0 | AV11: 0 | AW11: 0 | AX11: 0 | AY11: 0 | AZ11: 0 | BA11: 0 | BB11: 0 | BC11: 0 | BD11: 0 | BE11: 0 | BF11: 0 | BH11: 0 | BI11: 0 | BJ11: 0 | BK11: 0 | BL11: 0 | BM11: 0 | BN11: 0 | BO11: 0 | BP11: 0 | BQ11: 0 | BR11: 0 | BS11: 0 | BU11: 0 | BV11: 0 | BW11: 0 | BX11: 0 | BY11: 0 | BZ11: 0 | CA11: 0 | CB11: 0 | CC11: 0
A12: Equity Investments in NACCOs(Shares in- CIC, KUSCCO, COOP BANK,CAK, KERUSSU) | B12: 1250000 | C12: 1520000 | D12: 3580540 | E12: 6070944 | F12: 7763398 | G12: =161100+8613625+2270870+1967900 -> 13013495 | H12: 14112600 | I12: 0 | J12: 0 | K12: 0 | L12: 0 | M12: 0 | N12: 0 | O12: 0 | P12: 0 | Q12: 0 | R12: 0 | S12: 0 | T12: 0 | U12: 0 | V12: 0 | W12: 0 | X12: 0 | Y12: 0 | Z12: 0 | AA12: 0 | AB12: 0 | AC12: 0 | AD12: 0 | AE12: 0 | AF12: 0 | AG12: 0 | AH12: 16146154 | AI12: 0 | AJ12: 0 | AK12: 0 | AL12: 0 | AM12: 0 | AN12: 0 | AO12: 6954009.4 | AP12: 6994009.4 | AQ12: 7034009.4 | AR12: 7074009.4 | AS12: 7114009.4 | AT12: =95000+66100+10000+2270870+4572039 -> 7014009 | AX12: 0 | AY12: 0 | BH12: 7834009.4 | BI12: 7874009.4 | BJ12: 7914009.4 | BK12: 7954009.4 | BL12: 7994009.4 | BM12: 8034009.4 | BN12: 8074009.4 | BO12: 8114009.4 | BP12: 8154009.4 | BQ12: 8194009.4 | BR12: 8234009.4 | BS12: 8274009.4 | BU12: 0 | BV12: 0 | BW12: 0 | BX12: 0 | BY12: 0 | BZ12: 0 | CA12: 0 | CB12: 0 | CC12: 0
A13: Equity Investments in companies - shares/stocks | B13: =4301970-B12 -> 3051970 | C13: =4689870-C12 -> 3169870 | D13: =6970410-D12 -> 3389870 | E13: =9680814-E12 -> 3609870 | F13: =161100+100000+10000+2270870+1567900 -> 4109870 | G13: =100000+10000 -> 110000 | AH13: 100000 | AT13: 100000 | AU13: 7154009.4 | AV13: 7194009.4 | AW13: 7234009.4 | AX13: 7274009.4 | AY13: 7514009.4 | AZ13: 7554009.4 | BA13: 7594009.4 | BB13: 7634009.4 | BC13: 7674009.4 | BD13: 7714009.4 | BE13: 7754009.4 | BF13: 7794009.4 | BG13: 7920080 | BT13: 0 | BU13: 8314009.4 | BV13: 8354009.4 | BW13: 8394009.4 | BX13: 8434009.4 | BY13: 8474009.4 | BZ13: 8514009.4 | CA13: 8553989.4 | CB13: 8593989.4 | CC13: 8633989.4
A14: Net Loan Portfolio | B14: =(B15-B16) -> 31524548 | C14: =(C15-C16) -> 36920493 | D14: =(D15-D16) -> 36085793 | E14: =(E15-E16) -> 34456354 | F14: =(F15-F16) -> 32589509 | G14: =(G15-G16) -> 28504566 | H14: =(H15-H16) -> 29086031 | I14: =(I15-I16) -> 34575531 | ... CD14: =(CD15-CD16) -> 0
A15: Gross Loan Portfolio | B15: 31524548 | C15: 36920493 | D15: 36085793 | E15: 34456354 | F15: 33389509 | G15: 29854566 | H15: =244076+209632+3631769+6187564+9770913+10967804 -> 31011758 | I15: 34575531 | J15: 33764918 | K15: 34798281 | L15: 33789021 | M15: 33733276 | N15: 32870616 | O15: 28885717 | P15: 30209044 | Q15: 33253484 | R15: 33151954 | S15: 32745821 | T15: 29862145 | U15: 29862147 | V15: 30995823 | W15: 33706035 | X15: 29395402 | Y15: 28721214 | Z15: 28162168 | AA15: 31706424 | AB15: 28304800 | AC15: 29946706 | AD15: 28715854 | AE15: 28645058 | AF15: 30717200 | AG15: 29988726 | AH15: =95098+298550+4019181+7599174+8825713+9151010 -> 29988726 | AI15: 32516881 | AJ15: 32613412 | AK15: 33997628 | AL15: 31247366 | AM15: 30958397 | AN15: 30678214 | AO15: 30545196 | AP15: 31716573 | AQ15: 32368564 | AR15: 32015043 | AS15: 33586812 | AT15: =114242+1722923+3952080+6913347+8515373+12368848 -> 33586813 | AU15: 36565988 | AV15: 36228626 | AW15: 32981570 | AX15: 32830265 | AY15: 32865277 | AZ15: 36734980 | BA15: 36367144 | BB15: 35006595 | BC15: 38888360 | BD15: 34801220 | BE15: 34158311 | BF15: 32943350 | BG15: =28704269+BG16 -> 32943349 | BH15: 32485709 | BI15: 32189804 | BJ15: 32363227 | BK15: 34461139 | BL15: 34226908 | BM15: 34400949 | BN15: 34103925 | BO15: 33606644 | BP15: 34468468 | BQ15: 33927412 | BR15: 35206291 | BS15: 35777040 | BU15: 36888220 | BV15: 36898782 | BW15: 38683835 | BX15: 35204596 | BY15: 35975078 | BZ15: 36203370 | CA15: 37794329 | CB15: 37181777 | CC15: 42574709
A16: Allowance For Loan Loss | F16: 800000 | G16: 1350000 | H16: 1925727 | I16: 0 | J16: 0 | K16: 0 | L16: 0 | M16: 0 | N16: 0 | O16: 0 | P16: 0 | Q16: 0 | R16: 0 | S16: 0 | T16: 0 | U16: 2960451 | V16: 0 | W16: 0 | X16: 0 | Y16: 0 | Z16: 0 | AA16: 0 | AB16: 0 | AC16: 0 | AD16: 0 | AE16: 0 | AF16: 0 | AG16: 0 | AH16: 3560451 | AI16: 0 | AJ16: 0 | AK16: 0 | AL16: 0 | AM16: 0 | AN16: 0 | AO16: 0 | AP16: 0 | AQ16: 3560451 | AR16: 3560451 | AS16: 3560451 | AT16: 3560451 | AU16: 3560451 | AV16: 3560451 | AW16: 4142551 | AX16: 4142551 | AY16: 4142551 | AZ16: 4142551 | BA16: 4142551 | BB16: 4142551 | BC16: 4142551 | BD16: 4142551 | BE16: 4142551 | BF16: 4142551 | BG16: 4239080 | BH16: 4142551 | BI16: 4142551 | BJ16: 4239080 | BK16: 4239080 | BL16: 4239080 | BM16: 4239080 | BN16: 4239080 | BO16: 4239080 | BP16: 4239080 | BQ16: 4239080 | BR16: 4239080 | BS16: 4239080 | BU16: 4239080 | BV16: 4239080 | BW16: 3698400 | BX16: 3698400 | BY16: 3698400 | BZ16: 3698400 | CA16: 3698400 | CB16: 3698400 | CC16: 3698400
A17: Accounts Recievables | B17: =(B18+B19+B20) -> 0 | C17: =(C18+C19+C20) -> 0 | D17: =(D18+D19+D20) -> 0 | E17: =(E18+E19+E20) -> 0 | F17: =(F18+F19+F20) -> 0 | G17: =(G18+G19+G20) -> 0 | H17: =(H18+H19+H20) -> 0 | I17: =(I18+I19+I20) -> 0 | ... CC17: =(CC18+CC19+CC20) -> 0
A18: Tax Recoverable | I18: 0 | J18: 0 | K18: 0 | L18: 0 | M18: 0 | N18: 0 | O18: 0 | P18: 0 | Q18: 0 | R18: 0 | S18: 0 | T18: 0 | U18: 0 | V18: 0 | W18: 0 | X18: 0 | Y18: 0 | Z18: 0 | AA18: 0 | AB18: 0 | AC18: 0 | AD18: 0 | AE18: 0 | AF18: 0 | AG18: 0 | AI18: 0 | AJ18: 0 | AK18: 0 | AL18: 0 | AM18: 0 | AN18: 0 | AO18: 0 | AP18: 0 | AQ18: 0 | AR18: 0 | AS18: 0 | AU18: 0 | AV18: 0 | AW18: 0 | AX18: 0 | AY18: 0 | AZ18: 0 | BA18: 0 | BB18: 0 | BC18: 0 | BH18: 0 | BI18: 0 | BJ18: 0 | BK18: 0 | BL18: 0 | BM18: 0 | BN18: 0 | BO18: 0 | BP18: 0 | BQ18: 0 | BR18: 0 | BS18: 0 | BU18: 0 | BV18: 0 | BW18: 0 | BX18: 0 | BY18: 0 | BZ18: 0 | CA18: 0 | CB18: 0 | CC18: 0
A19: Deffered Tax Assets | I19: 0 | J19: 0 | K19: 0 | L19: 0 | M19: 0 | N19: 0 | O19: 0 | P19: 0 | Q19: 0 | R19: 0 | S19: 0 | T19: 0 | U19: 0 | V19: 0 | W19: 0 | X19: 0 | Y19: 0 | Z19: 0 | AA19: 0 | AB19: 0 | AC19: 0 | AD19: 0 | AE19: 0 | AF19: 0 | AG19: 0 | AI19: 0 | AJ19: 0 | AK19: 0 | AL19: 0 | AM19: 0 | AN19: 0 | AO19: 0 | AP19: 0 | AQ19: 0 | AR19: 0 | AS19: 0 | AU19: 0 | AV19: 0 | AW19: 0 | AX19: 0 | AY19: 0 | AZ19: 0 | BA19: 0 | BB19: 0 | BC19: 0 | BH19: 0 | BI19: 0 | BJ19: 0 | BK19: 0 | BL19: 0 | BM19: 0 | BN19: 0 | BO19: 0 | BP19: 0 | BQ19: 0 | BR19: 0 | BS19: 0 | BU19: 0 | BV19: 0 | BW19: 0 | BX19: 0 | BY19: 0 | BZ19: 0 | CA19: 0 | CB19: 0 | CC19: 0
A20: Retirement Benefit Assets | I20: 0 | J20: 0 | K20: 0 | L20: 0 | M20: 0 | O20: 0 | P20: 0 | Q20: 0 | R20: 0 | S20: 0 | T20: 0 | U20: 0 | V20: 0 | W20: 0 | X20: 0 | Y20: 0 | Z20: 0 | AA20: 0 | AB20: 0 | AC20: 0 | AD20: 0 | AE20: 0 | AF20: 0 | AG20: 0 | AI20: 0 | AJ20: 0 | AK20: 0 | AL20: 0 | AM20: 0 | AN20: 0 | AO20: 0 | AP20: 0 | AQ20: 0 | AR20: 0 | AS20: 0 | AU20: 0 | AV20: 0 | AW20: 0 | AX20: 0 | AY20: 0 | AZ20: 0 | BA20: 0 | BB20: 0 | BC20: 0 | BH20: 0 | BI20: 0 | BJ20: 0 | BK20: 0 | BL20: 0 | BM20: 0 | BN20: 0 | BO20: 0 | BP20: 0 | BQ20: 0 | BR20: 0 | BS20: 0 | BU20: 0 | BV20: 0 | BW20: 0 | BX20: 0 | BY20: 0 | BZ20: 0 | CA20: 0 | CB20: 0 | CC20: 0
A21: Property&Equipments&Other Assets | B21: =(B22+B23+B24+B25+B26) -> 1733278 | C21: =(C22+C23+C24+C25+C26) -> 1653529 | D21: =(D22+D23+D24+D25+D26) -> 2207010 | E21: =(E22+E23+E24+E25+E26) -> 2317124 | F21: =(F22+F23+F24+F25+F26) -> 1896351 | G21: =(G22+G23+G24+G25+G26) -> 6240222 | H21: =(H22+H23+H24+H25+H26) -> 9597930 | I21: =(I22+I23+I24+I25+I26) -> 26288006 | ... CC21: =(CC22+CC23+CC24+CC25+CC26) -> 22056438
A22: Investment Properties | I22: 16378525 | J22: 16501280 | K22: 16551280 | L22: 16551280 | M22: 17019070 | N22: 17069070 | O22: 17172190 | P22: 17222190 | Q22: 17332900 | R22: 17382900 | S22: 17456691 | T22: 17506691 | V22: 17637656 | W22: 17687655 | X22: 17767655 | Y22: 17817655 | Z22: 17867655 | AA22: 18217655 | AB22: 18374121 | AC22: 18474121 | AD22: 18597631 | AE22: 18647631 | AF22: 18697631 | AG22: 18717631 | AI22: 13767631 | AJ22: 13960207 | AK22: 14010207 | AL22: 14060207 | AM22: 14110207 | AN22: 14194798 | AO22: 0 | AP22: 0 | AQ22: 0 | AR22: 0 | AS22: 0 | AU22: 0 | AV22: 0 | AW22: 0 | AX22: 0 | AY22: 0 | AZ22: 0 | BA22: 0 | BB22: 0 | BC22: 0 | BD22: 0 | BE22: 0 | BF22: 0 | BG22: 21049644 | BH22: 0 | BI22: 0 | BJ22: 0 | BK22: 0 | BL22: 0 | BM22: 0 | BN22: 0 | BO22: 0 | BP22: 0 | BQ22: 0 | BR22: 0 | BS22: 0 | BU22: 0 | BV22: 0 | BW22: 0 | BX22: 0 | BY22: 0 | BZ22: 0 | CA22: 21018454 | CB22: 21018454 | CC22: 21018454
A23: Property and Equipment | B23: 1610246 | C23: 1189141 | D23: 1332352 | E23: 1803019 | F23: 1749407 | G23: =5761062+376299 -> 6137361 | H23: =588430+8937497 -> 9525927 | I23: 9909480.8 | J23: 9765784.8 | K23: 9599442.8 | L23: 9599442.8 | M23: 9602687.8 | N23: 9621212.8 | O23: 11629408 | P23: 12631333 | Q23: 12810659 | R23: 12829289 | S23: 12831507 | T23: 12833131 | U23: =12126808+574661 -> 12701469 | V23: 12753070 | W23: 12759270 | X23: 13068270 | Y23: 13097008 | Z23: 13098758 | AA23: 13099108 | AB23: 15465635 | AC23: 15465635 | AD23: 15465635 | AE23: 16463885 | AF23: 16508035 | AG23: 16220775 | AH23: =676154+15542646 -> 16218800 | AI23: 16238775 | AJ23: 17608718 | AK23: 17632998 | AL23: 18632998 | AM23: 19669198 | AN23: 19823168 | AO23: 20957465 | AP23: 20957465 | AQ23: 21473465 | AR23: 21493465 | AS23: 21714448 | AT23: =623278+21066475 -> 21689753 | AU23: 21730448 | AV23: 21730448 | AW23: 21788448 | AX23: 21788448 | AY23: 21788448 | AZ23: 21788448 | BA23: 21788448 | BB23: 21788448 | BC23: 21788448 | BD23: 21788448 | BE23: 21788448 | BF23: 21665049 | BG23: 543019 | BH23: 21665049 | BI23: 21725081 | BJ23: 21727981 | BK23: 21727981 | BL23: 21727981 | BM23: 21727981 | BN23: 21727981 | BO23: 21727981 | BP23: 21727981 | BQ23: 21727981 | BR23: 21921981 | BS23: 21750380 | BU23: 21750380 | BV23: 21750380 | BW23: 21692317 | BX23: 21692317 | BY23: 21692317 | BZ23: 21692317 | CA23: 661760.4 | CB23: 681755.4 | CC23: 681755.4
A24: Prepaid Lease Rentals | I24: 0 | J24: 0 | K24: 0 | L24: 0 | M24: 0 | N24: 0 | O24: 0 | P24: 0 | Q24: 0 | R24: 0 | S24: 0 | T24: 0 | V24: 0 | W24: 0 | X24: 0 | Y24: 0 | Z24: 0 | AA24: 0 | AB24: 0 | AC24: 0 | AD24: 0 | AE24: 0 | AF24: 0 | AG24: 0 | AI24: 0 | AJ24: 0 | AK24: 0 | AL24: 0 | AM24: 0 | AN24: 0 | AO24: 0 | AP24: 0 | AQ24: 0 | AR24: 0 | AS24: 0 | AU24: 0 | AV24: 0 | AW24: 0 | AX24: 0 | AY24: 0 | AZ24: 0 | BA24: 0 | BB24: 0 | BC24: 0 | BD24: 0 | BE24: 0 | BF24: 0 | BH24: 0 | BI24: 0 | BJ24: 0 | BK24: 0 | BL24: 0 | BM24: 0 | BN24: 0 | BO24: 0 | BP24: 0 | BQ24: 0 | BR24: 0 | BS24: 0 | BU24: 0 | BV24: 0 | BW24: 0 | BX24: 0 | BY24: 0 | BZ24: 0 | CA24: 0 | CB24: 0 | CC24: 0
A25: Intangible Assets | C25: 326422 | D25: 299885 | E25: 209920 | F25: 146944 | G25: 102861 | H25: 72003 | I25: 0 | J25: 0 | K25: 0 | L25: 0 | M25: 0 | N25: 0 | O25: 0 | P25: 0 | Q25: 0 | R25: 0 | S25: 0 | T25: 0 | U25: 50402.1 | V25: 0 | W25: 0 | X25: 0 | Y25: 0 | Z25: 0 | AA25: 0 | AB25: 0 | AC25: 0 | AD25: 0 | AE25: 0 | AF25: 0 | AG25: 0 | AH25: 35281 | AI25: 0 | AJ25: 0 | AK25: 0 | AL25: 0 | AM25: 0 | AN25: 0 | AO25: 0 | AP25: 0 | AQ25: 0 | AR25: 0 | AS25: 0 | AU25: 0 | AV25: 0 | AW25: 0 | AX25: 0 | AY25: 0 | AZ25: 0 | BA25: 0 | BB25: 0 | BC25: 0 | BD25: 0 | BE25: 0 | BF25: 0 | BG25: 17288 | BH25: 0 | BI25: 0 | BJ25: 0 | BK25: 0 | BL25: 0 | BM25: 0 | BN25: 0 | BO25: 0 | BP25: 0 | BQ25: 0 | BR25: 0 | BS25: 0 | BU25: 0 | BV25: 0 | BW25: 0 | BX25: 0 | BY25: 0 | BZ25: 0 | CA25: 12102 | CB25: 12102 | CC25: 12102
A26: Other Assets | B26: 123032 | C26: 137966 | D26: 574773 | E26: 304185 | I26: 0 | J26: 0 | K26: 0 | L26: 0 | M26: 0 | N26: 0 | O26: 0 | P26: 0 | Q26: 0 | R26: 0 | S26: 0 | T26: 0 | V26: 0 | W26: 0 | X26: 0 | Y26: 0 | Z26: 0 | AA26: 0 | AB26: 0 | AC26: 0 | AD26: 0 | AE26: 0 | AF26: 0 | AG26: 0 | AI26: 0 | AJ26: 0 | AK26: 0 | AL26: 0 | AM26: 0 | AN26: 0 | AO26: 904842.6 | AP26: 1249387.8 | AQ26: 1208578.6 | AR26: 1075284.1 | AS26: 1013375.2 | AT26: 24697 | AU26: 1042547.2 | AV26: 1420576.2 | AW26: 1137207.8 | AX26: 1184653.5 | AY26: 812931.16 | AZ26: -6983355.1 | BA26: 795052.62 | BB26: 662064.16 | BC26: 846467.76 | BD26: 833587.76 | BE26: 473541.16 | BF26: 572316 | BH26: 573054.13 | BI26: 266011.12 | BJ26: 557994.3 | BK26: 820011.27 | BL26: 560528.77 | BM26: 222909.05 | BN26: 548994 | BO26: 559394 | BP26: 536807.45 | BQ26: 536987.75 | BR26: 568747.53 | BS26: 618464 | BU26: 591956.55 | BV26: 598547.55 | BW26: 521576.35 | BX26: 496956.29 | BY26: 502194.29 | BZ26: 507343.24 | CA26: 506575.24 | CB26: 487105.27 | CC26: 344126
A27: Total Assets | B27: =(B21+B17+B14+B8+B7+B4) -> 44410076 | C27: =(C21+C17+C14+C8+C7+C4) -> 46132702 | D27: =(D21+D17+D14+D8+D7+D4) -> 56262269 | E27: =(E21+E17+E14+E8+E7+E4) -> 64588552 | F27: =(F21+F17+F14+F8+F7+F4) -> 49085187 | G27: =(G21+G17+G14+G8+G7+G4) -> 69043776 | H27: =(H21+H17+H14+H8+H7+H4) -> 97642022 | I27: =(I21+I17+I14+I8+I7+I4) -> 66311983 | ... CC27: =(CC21+CC17+CC14+CC8+CC7+CC4) -> 77940186
A28: Savings and Deposits | B28: =990000+4500274+351704 -> 5841978 | C28: 2653947 | D28: =6014250+327188 -> 6341438 | E28: =5535219+364748 -> 5899967 | F28: 5271989 | G28: 11473284 | H28: 10112825 | I28: 5565483.4 | J28: 5498954.3 | K28: 5371536.1 | L28: 5400807.5 | M28: 5455184.6 | N28: 5520622.7 | O28: 7084385.9 | P28: 6590844.8 | Q28: 5628970.7 | R28: 5691367.9 | S28: 6002402.5 | T28: 10142094 | U28: 10680343 | V28: 9786846.9 | W28: 7052454.5 | X28: 11373016 | Y28: 8312811.2 | Z28: 8195703.1 | AA28: 7108323.1 | AB28: 8345786.9 | AC28: 6903334 | AD28: 7368454.6 | AE28: 8145216.7 | AF28: 7126454.4 | AG28: 8049085.5 | AH28: 8496850 | AI28: 9846861.8 | AJ28: 10952432 | AK28: 7487515.6 | AL28: 8818164.4 | AM28: 10399099 | AN28: 8507267 | AO28: 8903541.5 | AP28: 7918113.7 | AQ28: 7517876 | AR28: 9104854.2 | AS28: 7020972.5 | AT28: 7533678 | AU28: 6693158.2 | AV28: 5736169.2 | AW28: 6861768.3 | AX28: 7030776.9 | AY28: 6960556.3 | AZ28: 6262415.9 | BA28: 9745764.9 | BB28: 9428957.1 | BC28: 5928484.7 | BD28: 6842797.4 | BE28: 9198733.9 | BF28: 9462491 | BG28: 9462491 | BH28: 8629384.5 | BI28: 9431571.3 | BJ28: 8982236.3 | BK28: 8818689.9 | BL28: 8435070.9 | BM28: 10022393 | BN28: 8129915 | BO28: 7969492.5 | BP28: 7251560.9 | BQ28: 8261406.7 | BR28: 8114650.8 | BS28: 8802818 | BU28: 8329361.4 | BV28: 7913593.9 | BW28: 7511956 | BX28: 8073478.9 | BY28: 6918568.1 | BZ28: 7104839.7 | CA28: 6106546 | CB28: 6387619.1 | CC28: 5671158.4
A29: Short Terrm Deposits | I29: 561679.16 | J29: 956410.72 | K29: 1295332.7 | L29: 1622577.8 | M29: 1858109.4 | N29: 2544787 | O29: 3160275.5 | P29: 3143337.1 | Q29: 2915929.1 | R29: 3237983.6 | S29: 3562797.4 | T29: 480448.72 | V29: 936053.44 | W29: 824803.44 | X29: 1683487.3 | Y29: 2075890.9 | Z29: 2278353.3 | AA29: 2300071.3 | AB29: 2868594.2 | AC29: 2939817.1 | AD29: 3168302.2 | AE29: 3470478.5 | AF29: 3767390.8 | AG29: 447794.02 | AI29: 883553.23 | AJ29: 1196533.4 | AK29: 1456072 | AL29: 1901452 | AM29: 2134407 | AN29: 2487851 | AO29: 3229416.6 | AP29: 3485620.5 | AQ29: 3794574.5 | AR29: 4437220.8 | AS29: 512704.77 | AT29: 0 | AU29: 520991.92 | AV29: 927433.22 | AW29: 1844113.4 | AX29: 2401010.2 | AY29: 2735742.3 | AZ29: 2473207.8 | BA29: 2954285.8 | BB29: 3138063.5 | BC29: 2932850.3 | BD29: 3607978.1 | BE29: 4044725.4 | BF29: 386054.76 | BH29: 841120.4 | BI29: 1149223.4 | BJ29: 1424991.8 | BK29: 2122107.4 | BL29: 2435619.5 | BM29: 2752388.1 | BN29: 2959673.8 | BO29: 3272490 | BP29: 3607114.2 | BQ29: 3852247.1 | BR29: 4285933.4 | BS29: 367642.02 | BU29: 709595.59 | BV29: 1031997.1 | BW29: 1719348.9 | BX29: 2038824 | BY29: 2311067.1 | BZ29: 2493914.4 | CA29: 2766434.4 | CB29: 3006856.4 | CC29: 2944016.4
A30: Non Withdrawable Deposits | B30: 24860593 | C30: 29607983 | D30: 32984337 | E30: 34606608 | F30: 33623566 | G30: 36128593 | H30: 37576767 | I30: 37552128 | J30: 37893569 | K30: 38081672 | L30: 38286717 | M30: 38646303 | N30: 38815296 | O30: 39273754 | P30: 38628823 | Q30: 38662147 | R30: 38642403 | S30: 38519201 | T30: 39141848 | U30: 39141848 | V30: 39507482 | W30: 38796403 | X30: 39084608 | Y30: 39255914 | Z30: 39040292 | AA30: 38559038 | AB30: 39202952 | AC30: 39296828 | AD30: 39393936 | AE30: 39518110 | AF30: 39221601 | AG30: 39316438 | AH30: 39316438 | AI30: 39319865 | AJ30: 39445819 | AK30: 39673950 | AL30: 40064569 | AM30: 40137074 | AN30: 40546454 | AO30: 40731541 | AP30: 41031928 | AQ30: 41384370 | AR30: 41334696 | AS30: 41809421 | AT30: 41809421 | AU30: 41852139 | AV30: 42191489 | AW30: 41979586 | AX30: 42344451 | AY30: 42464929 | AZ30: 42211695 | BA30: 42747288 | BB30: 42938956 | BC30: 42177479 | BD30: 42191463 | BE30: 42294830 | BF30: 42157242 | BG30: 42157242 | BH30: 42293657 | BI30: 41935393 | BJ30: 41699911 | BK30: 41876442 | BL30: 42202629 | BM30: 42352986 | BN30: 42266788 | BO30: 42524871 | BP30: 42557524 | BQ30: 42857234 | BR30: 42767812 | BS30: 43161599 | BU30: 43831373 | BV30: 44146264 | BW30: 44202266 | BX30: 43072564 | BY30: 43279709 | BZ30: 44109508 | CA30: 43904872 | CB30: 43788834 | CC30: 43270702
A31: Total Deposit Liabilities | B31: =SUM(B28:B30) -> 30702571 | C31: =SUM(C28:C30) -> 32261930 | D31: =SUM(D28:D30) -> 39325775 | E31: =SUM(E28:E30) -> 40506575 | F31: =SUM(F28:F30) -> 38895555 | G31: =SUM(G28:G30) -> 47601877 | H31: =SUM(H28:H30) -> 47689592 | I31: =SUM(I28:I30) -> 43679291 | ... CC31: =SUM(CC28:CC30) -> 51885876
A32: Tax Payable | F32: 79999 | G32: 43968 | I32: 5411.2 | J32: 5339.7 | K32: 5401.7 | L32: 6229.2 | M32: 5583.7 | N32: 5111.2 | O32: 12668.7 | P32: 10506.2 | Q32: 7236.7 | R32: 19122.7 | S32: 23628.7 | T32: 33350.7 | U32: 51709 | V32: 23402.7 | W32: 15971.7 | X32: 80114.7 | Y32: 42386.7 | Z32: 34139.7 | AA32: 27007.7 | AB32: 22372.7 | AC32: 23052.7 | AD32: 18737.7 | AE32: 15281.7 | AF32: 23513.7 | AG32: 20447.7 | AH32: 64642 | AI32: 21417.7 | AJ32: 18860.7 | AK32: 22214.7 | AL32: 17473.7 | AM32: 15410.7 | AN32: 19080.7 | AO32: 15170.7 | AP32: 19131.7 | AQ32: 18882.7 | AR32: 15386.7 | AS32: 28694.7 | AT32: 28817 | AU32: 12853.7 | AV32: 20462.7 | AW32: 23558.7 | AX32: 21185.7 | AY32: 20468.7 | AZ32: 18004.7 | BA32: 27005.7 | BB32: 20179.7 | BC32: 15517.7 | BD32: 25243.7 | BE32: 16554.7 | BF32: 22971.7 | BG32: 2242 | BH32: 18155.7 | BI32: 15545.7 | BJ32: 20998.7 | BK32: 26503.7 | BL32: 20303.7 | BM32: 16854.7 | BN32: 21477.7 | BO32: 17453.7 | BP32: 20770.7 | BQ32: 14284.7 | BR32: 19919.7 | BS32: 20845.7 | BU32: 18435.7 | BV32: 15907.7 | BW32: 29533.7 | BX32: 26159.7 | BY32: 33189.7 | BZ32: 22749.7 | CA32: 30984.7 | CB32: 17719.7 | CC32: 14579.7
A33: Dividends Payable | C33: =2672099 -> 2672099 | D33: =2638747+200000+540001 -> 3378748 | G33: 2480651 | H33: 1503071 | I33: 0 | J33: 0 | K33: 0 | L33: 0 | M33: 0 | N33: 0 | O33: 0 | P33: 0 | Q33: 0 | R33: 0 | S33: 0 | T33: 0 | U33: 1957092.4 | V33: 0 | W33: 0 | X33: 0 | Y33: 0 | Z33: 0 | AA33: 0 | AB33: 0 | AC33: 0 | AD33: 0 | AE33: 0 | AF33: 0 | AG33: 0 | AH33: 2358986 | AI33: 0 | AJ33: 0 | AK33: 0 | AL33: 0 | AM33: 0 | AN33: 0 | AO33: 0 | AP33: 0 | AQ33: 0 | AR33: 0 | AS33: 0 | AT33: 3344754 | AU33: 0 | AV33: 0 | AW33: 0 | AX33: 0 | AY33: 0 | AZ33: 0 | BA33: 0 | BB33: 0 | BC33: 0 | BD33: 0 | BE33: 0 | BF33: 0 | BG33: 2951007 | BH33: 0 | BI33: 0 | BJ33: 0 | BK33: 0 | BL33: 0 | BM33: 0 | BN33: 0 | BO33: 0 | BP33: 0 | BQ33: 0 | BR33: 0 | BS33: 0 | BU33: 0 | BV33: 0 | BW33: 0 | BX33: 0 | BY33: 0 | BZ33: 0 | CA33: 0 | CB33: 0 | CC33: 0
A34: Deferred Tax Liability | I34: 0 | J34: 0 | K34: 0 | L34: 0 | M34: 0 | N34: 0 | O34: 0 | P34: 0 | Q34: 0 | R34: 0 | S34: 0 | T34: 0 | U34: 0 | V34: 0 | W34: 0 | X34: 0 | Y34: 0 | Z34: 0 | AA34: 0 | AB34: 0 | AC34: 0 | AD34: 0 | AE34: 0 | AF34: 0 | AG34: 0 | AI34: 0 | AJ34: 0 | AK34: 0 | AL34: 0 | AM34: 0 | AN34: 0 | AO34: 0 | AP34: 0 | AQ34: 0 | AR34: 0 | AS34: 0 | AT34: 0 | AU34: 0 | AV34: 0 | AW34: 0 | AX34: 0 | AY34: 0 | AZ34: 0 | BA34: 0 | BB34: 0 | BC34: 0 | BD34: 0 | BE34: 0 | BF34: 0 | BH34: 0 | BI34: 0 | BJ34: 0 | BK34: 0 | BL34: 0 | BM34: 0 | BN34: 0 | BO34: 0 | BP34: 0 | BQ34: 0 | BR34: 0 | BS34: 0 | BU34: 0 | BV34: 0 | BW34: 0 | BX34: 0 | BY34: 0 | BZ34: 0 | CA34: 0 | CB34: 0 | CC34: 0
A35: Retirement Benefits Liabilty | G35: 2167716 | I35: 0 | J35: 0 | K35: 0 | L35: 0 | M35: 0 | N35: 0 | O35: 0 | P35: 0 | Q35: 0 | R35: 0 | S35: 0 | T35: 0 | U35: 0 | V35: 0 | W35: 0 | X35: 0 | Y35: 0 | Z35: 0 | AA35: 0 | AB35: 0 | AC35: 0 | AD35: 0 | AE35: 0 | AF35: 0 | AG35: 0 | AI35: 0 | AJ35: 0 | AK35: 0 | AL35: 0 | AM35: 0 | AN35: 0 | AO35: 0 | AP35: 0 | AQ35: 0 | AR35: 0 | AS35: 0 | AT35: 0 | AU35: 0 | AV35: 0 | AW35: 0 | AX35: 0 | AY35: 0 | AZ35: 0 | BA35: 0 | BB35: 0 | BC35: 0 | BD35: 0 | BE35: 0 | BF35: 0 | BH35: 0 | BI35: 0 | BJ35: 0 | BK35: 0 | BL35: 0 | BM35: 0 | BN35: 0 | BO35: 0 | BP35: 0 | BQ35: 0 | BR35: 0 | BS35: 0 | BU35: 0 | BV35: 0 | BW35: 0 | BX35: 0 | BY35: 0 | BZ35: 0 | CA35: 0 | CB35: 0 | CC35: 0
A36: Other Liabilities | B36: 3470185 | C36: =1787148+321686 -> 2108834 | D36: =2600712+656204 -> 3256916 | E36: =5076866+150000+606579 -> 5833445 | F36: =1717414+3437605 -> 5155019 | H36: 350096 | I36: 2341274.1 | J36: 2617476.2 | K36: 3525343.3 | L36: 2242713.8 | M36: 1684888.4 | N36: 1573570.5 | O36: 1641539.9 | P36: 1624192.4 | Q36: 1695237.6 | R36: 1874551.4 | S36: 1930573.3 | T36: 1939943.5 | U36: 761254 | V36: 6264105 | W36: 6227222.1 | X36: 5659216.2 | Y36: 3231363 | Z36: 3097656 | AA36: 3143998.2 | AB36: 3042708.6 | AC36: 3472678.6 | AD36: 3044796.8 | AE36: 3323035.8 | AF36: 3386759.9 | AG36: 4124370.8 | AH36: 2022756 | AI36: 8237697.4 | AJ36: 8269920 | AK36: 7441499.5 | AL36: 5063911.8 | AM36: 4841286 | AN36: 4819427.3 | AO36: 4279100.8 | AP36: 3956450 | AQ36: 423017.86 | AR36: 372991.86 | AS36: 1049732 | AT36: 2247051 | AU36: 5365014.4 | AV36: 5541733.1 | AW36: 4049323.7 | AX36: 1294075.9 | AY36: 998203.13 | AZ36: 76321.6 | BA36: 173648.15 | BB36: 66432.08 | BC36: -36681.05 | BD36: 32028.05 | BE36: -58343.8 | BF36: 156344.25 | BG36: 1068513 | BH36: 4311541.7 | BI36: 4299392.9 | BJ36: 2992515.2 | BK36: -726678.24 | BL36: -794465.05 | BM36: -826567.04 | BN36: -866289.44 | BO36: -852790.2 | BP36: -1020657.2 | BQ36: -1003694.4 | BR36: -951943.4 | BS36: -740099.86 | BU36: 3826265.6 | BV36: 3869746.4 | BW36: 3738295.5 | BX36: -118074.66 | BY36: 220798.17 | BZ36: 94194.22 | CA36: -122479.65 | CB36: -110999.87 | CC36: 5553.27
A37: External Borrowings | B37: 3635383 | C37: 361622 | D37: 637835 | E37: 4500000 | F37: 2420583 | H37: 3576860 | I37: 3176106 | J37: 3015984.9 | K37: 2748772.3 | L37: 2489256.3 | M37: 2211045 | N37: 1911045.1 | O37: 1666964.5 | P37: 1666964.5 | Q37: 1102544.3 | R37: 802544.3 | S37: 516553.35 | T37: 216553.35 | U37: 216553.35 | V37: 0 | W37: 0 | X37: 0 | Y37: 0 | Z37: 0 | AA37: 0 | AB37: 0 | AC37: 0 | AD37: 0 | AE37: 0 | AF37: 0 | AG37: 0 | AI37: 0 | AJ37: 0 | AK37: 0 | AL37: 0 | AM37: 0 | AN37: 0 | AO37: 0 | AP37: 0 | AQ37: 0 | AR37: 0 | AS37: 0 | AU37: 0 | AV37: 0 | AW37: 0 | AX37: 0 | AY37: 0 | AZ37: 0 | BA37: 0 | BB37: 0 | BC37: 0 | BD37: 0 | BE37: 0 | BF37: 0 | BH37: 0 | BI37: 0 | BJ37: 0 | BK37: 0 | BL37: 0 | BM37: 0 | BN37: 0 | BO37: 0 | BP37: 0 | BQ37: 0 | BR37: 0 | BS37: 0 | BU37: 0 | BV37: 0 | BW37: 0 | BX37: 0 | BY37: 0 | BZ37: 0 | CA37: 0 | CB37: 0 | CC37: 0
A38: Total Liabilities | B38: =SUM(B31:B37) -> 37808139 | C38: =SUM(C31:C37) -> 37404485 | D38: =SUM(D31:D37) -> 46599274 | E38: =SUM(E31:E37) -> 50840020 | F38: =SUM(F31:F37) -> 46551156 | G38: =SUM(G31:G37) -> 52294212 | H38: =SUM(H31:H37) -> 53119619 | I38: =SUM(I31:I37) -> 49202082 | ... CC38: =SUM(CC31:CC37) -> 51906009
A39: Share Capital | B39: 5621296 | C39: =6905081+992000 -> 7897081 | D39: =6905021+1319000 -> 8224021 | E39: =8509483+1331000+824457 -> 10664940 | F39: =8509483+960817+1331500 -> 10801800 | G39: =9823239+187532 -> 10010771 | H39: =10010771+1185542+1335000 -> 12531313 | I39: 12531313 | J39: 12539557 | K39: 12546957 | L39: 12552757 | M39: 12560747 | N39: 12636693 | O39: 12651209 | P39: 12656809 | Q39: 12656809 | R39: 12662109 | S39: 12671009 | T39: 12684723 | U39: =10084216+2600506 -> 12684722 | V39: 12691760 | W39: 12691760 | X39: 12705860 | Y39: 12713659 | Z39: 12716660 | AA39: 12718660 | AB39: 12728260 | AC39: 12730560 | AD39: 12732560 | AE39: 12734860 | AF39: 12988600 | AG39: 12966352 | AH39: =10310909+1315943+1339500 -> 12966352 | AI39: 12971152 | AJ39: 12973152 | AK39: 12974152 | AL39: 12975652 | AM39: 12977152 | AN39: 12979008 | AO39: 13104844 | AP39: 13106344 | AQ39: 13108844 | AR39: 13110344 | AS39: 13112644 | AT39: =10433245+1339899+1339500 -> 13112644 | AU39: 13112644 | AV39: 13113644 | AW39: 13116144 | AX39: 13119624 | AY39: 13122624 | AZ39: 13240686 | BA39: 13245186 | BB39: 13245898 | BC39: 13245898 | BD39: 13249698 | BE39: 13251498 | BF39: 13305823 | BG39: 10604628 | BH39: 13307323 | BI39: 13308823 | BJ39: 13311623 | BK39: 13312123 | BL39: 13315623 | BM39: 13316123 | BN39: 13318623 | BO39: 13319246 | BP39: 13360452 | BQ39: 13360952 | BR39: 13360952 | BS39: 13384352 | BU39: 13385652 | BV39: 13386952 | BW39: 13387452 | BX39: 13388452 | BY39: 13388952 | BZ39: 13389452 | CA39: 13389952 | CB39: 13395279 | CC39: 13395279
A40: Capital Grants | I40: 0 | J40: 0 | K40: 0 | L40: 0 | M40: 0 | N40: 0 | O40: 0 | P40: 0 | Q40: 0 | R40: 0 | S40: 0 | T40: 0 | U40: 0 | V40: 0 | W40: 0 | X40: 0 | Y40: 0 | Z40: 0 | AA40: 0 | AB40: 0 | AC40: 0 | AD40: 0 | AE40: 0 | AF40: 0 | AG40: 0 | AI40: 0 | AJ40: 0 | AK40: 0 | AL40: 0 | AM40: 0 | AN40: 0 | AO40: 0 | AP40: 0 | AQ40: 0 | AR40: 0 | AS40: 0 | AU40: 0 | AV40: 0 | AW40: 0 | AX40: 0 | AY40: 0 | AZ40: 0 | BA40: 0 | BB40: 0 | BC40: 0 | BD40: 0 | BE40: 0 | BF40: 0 | BH40: 0 | BI40: 0 | BJ40: 0 | BK40: 0 | BL40: 0 | BM40: 0 | BN40: 0 | BO40: 0 | BP40: 0 | BQ40: 0 | BR40: 0 | BS40: 0 | BU40: 0 | BV40: 0 | BW40: 0 | BX40: 0 | BY40: 0 | BZ40: 0 | CA40: 0 | CB40: 0 | CC40: 0
A41: Prior Year Retained Earnigs | B41: 461312 | C41: 461314.45 | E41: 629358 | G41: 1392830 | H41: 1579427 | I41: 1579426.8 | J41: 1579426.8 | K41: 1748020.8 | L41: 1748020.8 | M41: 1748020.8 | N41: 1748020.8 | O41: 1748020.8 | P41: 1748020.8 | Q41: 1748020.8 | R41: 1748020.8 | S41: 1748020.8 | T41: 1748020.8 | U41: 1748020.8 | V41: 1748020.8 | W41: 1748020.8 | X41: 2256870.9 | Y41: 2256870.9 | Z41: 2256870.9 | AA41: 2256870.9 | AB41: 2256870.9 | AC41: 2256870.9 | AD41: 2256870.9 | AE41: 2256870.9 | AF41: 2256870.9 | AG41: 2256870.9 | AH41: 2279446 | AI41: 2256870.9 | AJ41: 2256870.9 | AK41: 2741685.9 | AL41: 2741685.9 | AM41: 2741685.9 | AN41: 2741685.9 | AO41: 2741685 | AP41: 2741685 | AQ41: 2741685 | AR41: 2741685 | AS41: 2741685 | AT41: 2741685 | AU41: 2741685.9 | AV41: 2741685.9 | AW41: 3253606.9 | AX41: 3253606.9 | AY41: 3253606.9 | AZ41: 3253606.9 | BA41: 3253606.9 | BB41: 3253606.9 | BC41: 3253606.9 | BD41: 3253606.9 | BE41: 3253606.9 | BF41: 3253606.9 | BG41: =4164333-BG42 -> 2008198 | BH41: 3253606.9 | BI41: 3253606.9 | BJ41: 4164332.9 | BK41: 4164332.9 | BL41: 4164332.9 | BM41: 4164332.9 | BN41: 4164332.9 | BO41: 4164332.9 | BP41: 4164332.9 | BQ41: 4164332.9 | BR41: 4164332.9 | BS41: 4164332.9 | BU41: 4164332.9 | BV41: 4164332.9 | BW41: 4427856.9 | BX41: 4427856.9 | BY41: 4164332.9 | BZ41: 4164332.9 | CA41: 4427856.9 | CB41: 4427856.9 | CC41: 4427856.9
A42: Current Year Surplus | C42: =291088-C41 -> -170226.45 | D42: 338270 | E42: 744861 | F42: 18611 | G42: 186597 | H42: =210743-42149 -> 168594 | I42: 55977.45 | J42: 320443.54 | K42: 679638.53 | L42: 847828.42 | M42: 1306029.5 | N42: 2044155.4 | O42: 2725587.9 | P42: 3150097.4 | Q42: 3249407.1 | R42: 3697877.8 | S42: 4038187.8 | T42: 4405220.3 | U42: 531426 | V42: 441050.57 | W42: 435110.81 | X42: 1022777.8 | Y42: 1249269.5 | Z42: 1705351.6 | AA42: 2222907.8 | AB42: 3063047.2 | AC42: 3563575.3 | AD42: 4027647.6 | AE42: 4563232.5 | AF42: 4559291.2 | AG42: 3539901.2 | AH42: =2741685-2279446 -> 462239 | AI42: 552509.1 | AJ42: 898564.59 | AK42: 1432954 | AL42: 1774386 | AM42: 2256452.2 | AN42: 2710890.5 | AO42: 3725619 | AP42: 4159363.6 | AQ42: 4719976.6 | AR42: 5106561.6 | AS42: 4855217.7 | AT42: =298736-59747 -> 238989 | AU42: 102035.83 | AV42: 298030.17 | AW42: 886096.07 | AX42: 1274680.8 | AY42: 1710290.1 | AZ42: 2089370 | BA42: 2878408.2 | BB42: 3294536.2 | BC42: 3745262.3 | BD42: 4443626.8 | BE42: 4607003.5 | BF42: 4577413.6 | BG42: 2156135 | BH42: 416559.37 | BI42: 507237.14 | BJ42: 1010049.6 | BK42: 1405986 | BL42: 1871658.4 | BM42: 2325296.2 | BN42: 2824639.1 | BO42: 3420479.6 | BP42: 3922478 | BQ42: 4082297.1 | BR42: 4911466.9 | BS42: 4736549.2 | BU42: 471915 | BV42: 705837 | BW42: 1426046.1 | BX42: 1515883.5 | BY42: 2406334.1 | BZ42: 2808582.9 | CA42: 3466033.4 | CB42: 3926066.4 | CC42: 4099752
A43: Statutory Reserves | B43: 474829 | C43: 495548 | D43: 765116 | E43: 1140476 | F43: 1334299 | G43: 1577238 | H43: 1619386 | I43: 1577237.2 | J43: 1577237.2 | K43: 1619386.2 | L43: 1619386.2 | M43: 1619386.2 | N43: 1619386.2 | O43: 1619386.2 | P43: 1619386.2 | Q43: 1619386.2 | R43: 1619386.2 | S43: 1619386.2 | T43: 1619386.2 | U43: 1752242 | V43: 1619386.2 | W43: 1619386.2 | X43: 1752242.2 | Y43: 1752242.2 | Z43: 1752242.2 | AA43: 1752242.2 | AB43: 1752242.2 | AC43: 1752242.2 | AD43: 1752242.2 | AE43: 1752242.2 | AF43: 1752242.2 | AG43: 1752242.2 | AH43: 1867801 | AI43: 1752242.2 | AJ43: 1752242.2 | AK43: 1867802.2 | AL43: 1867802.2 | AM43: 1867802.2 | AN43: 1867802.2 | AO43: 1867802.2 | AP43: 1867802.2 | AQ43: 1867802.2 | AR43: 1867802.2 | AS43: 1867802.2 | AT43: 1927549 | AU43: 1867802.2 | AV43: 1867802.2 | AW43: 1995782 | AX43: 1995782 | AY43: 1995782 | AZ43: 1995782 | BA43: 1995782 | BB43: 1995782 | BC43: 1995782 | BD43: 1995782 | BE43: 1995782 | BF43: 1995782 | BG43: 2427008 | BH43: 1995782 | BI43: 1995782 | BJ43: 2427009 | BK43: 2427009 | BL43: 2427009 | BM43: 2427009 | BN43: 2427009 | BO43: 2427009 | BP43: 2427009 | BQ43: 2427009 | BR43: 2427009 | BS43: 2427009 | BU43: 2427009 | BV43: 2427009 | BW43: 2745342 | BX43: 2745342 | BY43: 2745342 | BZ43: 2745342 | CA43: 2745342 | CB43: 2745342 | CC43: 2745342
A44: Other Reserves | B44: 44500 | C44: =44500 -> 44500 | D44: 44500 | E44: 44500 | F44: 44500 | G44: =841550+1073715+1330000 -> 3245265 | H44: =841550 -> 841550 | I44: 841550.38 | J44: 841550.38 | K44: 841550.38 | L44: 841550.38 | M44: 841550.38 | N44: 841550.38 | O44: 841550.38 | P44: 841550.38 | Q44: 841550.38 | R44: 841550.38 | S44: 841550.38 | T44: 841550.38 | U44: 841550 | V44: 841550.38 | W44: 841550.38 | X44: 841550.38 | Y44: 841550.38 | Z44: 841550.38 | AA44: 841550.38 | AB44: 841550.38 | AC44: 841550.38 | AD44: 841550.38 | AE44: 841550.38 | AF44: 841550.38 | AG44: 841550.38 | AH44: 841550 | AI44: 841550.38 | AJ44: 841550.38 | AK44: 841550.38 | AL44: 841550.38 | AM44: 841550.38 | AN44: 841550.38 | AO44: 841550.38 | AP44: 841550.38 | AQ44: 841550.38 | AR44: 841550.38 | AS44: 841550.38 | AT44: 841550 | AU44: 841550.38 | AV44: 841550.38 | AW44: 841550.38 | AX44: 841550.38 | AY44: 841550.38 | AZ44: 841550.38 | BA44: 841550.38 | BB44: 841550.38 | BC44: 841550.38 | BD44: 841550.38 | BE44: 841550.38 | BF44: 841550.38 | BG44: =841550+1339500+1361691 -> 3542741 | BH44: 841550.38 | BI44: 841550.38 | BJ44: 841550.38 | BK44: 841550.38 | BL44: 841550.38 | BM44: 841550.38 | BN44: 841550.38 | BO44: 841550.38 | BP44: 841550.38 | BQ44: 841550.38 | BR44: 841550.38 | BS44: 841550.38 | BU44: 841550.38 | BV44: 841550.38 | BW44: 841550.38 | BX44: 841550.38 | BY44: 841550.38 | BZ44: 841550.38 | CA44: 841550.38 | CB44: 841550.38 | CC44: 841550.38
A45: Revaluation Reserves | E45: 524396 | F45: 524396 | G45: 524396 | H45: 524396 | I45: 524395.75 | J45: 524395.75 | K45: 524395.75 | L45: 524395.75 | M45: 524395.75 | N45: 524395.75 | O45: 524395.75 | P45: 524395.75 | Q45: 524395.75 | R45: 524395.75 | S45: 524395.75 | T45: 524395.75 | U45: 524396 | V45: 524395.75 | W45: 524395.75 | X45: 524395.75 | Y45: 524395.75 | Z45: 524395.75 | AA45: 524395.75 | AB45: 524395.75 | AC45: 524395.75 | AD45: 524395.75 | AE45: 524395.75 | AF45: 524395.75 | AG45: 524395.75 | AH45: 524396 | AI45: 524395.75 | AJ45: 524395.75 | AK45: 524395.75 | AL45: 524395.75 | AM45: 524395.75 | AN45: 524395.75 | AO45: 524395.75 | AP45: 524395.75 | AQ45: 524395.75 | AR45: 524395.75 | AS45: 524395.75 | AT45: 524396 | AU45: 524395.75 | AV45: 524395.75 | AW45: 524395.75 | AX45: 524395.75 | AY45: 524395.75 | AZ45: 524395.75 | BA45: 524395.75 | BB45: 524395.75 | BC45: 524395.75 | BD45: 524395.75 | BE45: 524395.75 | BF45: 524395.75 | BG45: 524396 | BH45: 524395.75 | BI45: 524395.75 | BJ45: 524395.75 | BK45: 524395.75 | BL45: 524395.75 | BM45: 524395.75 | BN45: 524395.75 | BO45: 524395.75 | BP45: 524395.75 | BQ45: 524395.75 | BR45: 524395.75 | BS45: 524395.75 | BU45: 524395.75 | BV45: 524395.75 | BW45: 524395.75 | BX45: 524395.75 | BY45: 524395.75 | BZ45: 524395.75 | CA45: 524395.75 | CB45: 524395.75 | CC45: 524395.75
A46: Proposed Dividends | I46: 0 | J46: 0 | K46: 0 | L46: 0 | M46: 0 | N46: 0 | O46: 0 | P46: 0 | Q46: 0 | R46: 0 | S46: 0 | T46: 0 | U46: 0 | V46: 0 | W46: 0 | X46: 0 | Y46: 0 | Z46: 0 | AA46: 0 | AB46: 0 | AC46: 0 | AD46: 0 | AE46: 0 | AF46: 0 | AG46: 0 | AI46: 0 | AJ46: 0 | AK46: 0 | AL46: 0 | AM46: 0 | AN46: 0 | AO46: 0 | AP46: 0 | AQ46: 0 | AR46: 0 | AS46: 0 | AU46: 0 | AV46: 0 | AW46: 0 | AX46: 0 | AY46: 0 | AZ46: 0 | BA46: 0 | BB46: 0 | BC46: 0 | BD46: 0 | BE46: 0 | BF46: 0 | BH46: 0 | BI46: 0 | BJ46: 0 | BK46: 0 | BL46: 0 | BM46: 0 | BN46: 0 | BO46: 0 | BP46: 0 | BQ46: 0 | BR46: 0 | BS46: 0 | BU46: 0 | BV46: 0 | BW46: 0 | BX46: 0 | BY46: 0 | BZ46: 0 | CA46: 0 | CB46: 0 | CC46: 0
A47: Adjustment To Equity | I47: 0 | J47: 0 | K47: 0 | L47: 0 | M47: 0 | N47: 0 | O47: 0 | P47: 0 | Q47: 0 | R47: 0 | S47: 0 | T47: 0 | U47: 0 | V47: 0 | W47: 0 | X47: 0 | Y47: 0 | Z47: 0 | AA47: 0 | AB47: 0 | AC47: 0 | AD47: 0 | AE47: 0 | AF47: 0 | AG47: 0 | AI47: 0 | AJ47: 0 | AK47: 0 | AL47: 0 | AM47: 0 | AN47: 0 | AO47: 0 | AP47: 0 | AQ47: 0 | AR47: 0 | AS47: 0 | AU47: 0 | AV47: 0 | AW47: 0 | AX47: 0 | AY47: 0 | AZ47: 0 | BA47: 0 | BB47: 0 | BC47: 0 | BD47: 0 | BE47: 0 | BF47: 0 | BH47: 0 | BI47: 0 | BJ47: 0 | BK47: 0 | BL47: 0 | BM47: 0 | BN47: 0 | BO47: 0 | BP47: 0 | BQ47: 0 | BR47: 0 | BS47: 0 | BU47: 0 | BV47: 0 | BW47: 0 | BX47: 0 | BY47: 0 | BZ47: 0 | CA47: 0 | CB47: 0 | CC47: 0
A48: Total Equity | B48: =SUM(B39:B47) -> 6601937 | C48: =SUM(C39:C47) -> 8728217 | D48: =SUM(D39:D47) -> 9371907 | E48: =SUM(E39:E47) -> 13748531 | F48: =SUM(F39:F47) -> 12723606 | G48: =SUM(G39:G47) -> 16937097 | H48: =SUM(H39:H47) -> 17264666 | I48: =SUM(I39:I47) -> 17109901 | ... CC48: =SUM(CC39:CC47) -> 26034176
A49: Total Liabilities and Equity | B49: =SUM(B48+B38) -> 44410076 | C49: =SUM(C48+C38) -> 46132702 | D49: =SUM(D48+D38) -> 55971181 | E49: =SUM(E48+E38) -> 64588551 | F49: =SUM(F48+F38) -> 59274762 | G49: =SUM(G48+G38) -> 69231309 | H49: =SUM(H48+H38) -> 70384285 | I49: =SUM(I48+I38) -> 66311983 | ... CC49: =SUM(CC48+CC38) -> 77940186
B51: =B49-B27 -> 0 | C51: =C49-C27 -> 0 | D51: =D49-D27 -> -291088 | E51: =E49-E27 -> -1 | F51: =F49-F27 -> 10189575 | G51: =G49-G27 -> 187533 | H51: =H49-H27 -> -27257737 | I51: =I49-I27 -> 0 | ... CC51: =CC49-CC27 -> 0

Sheet Evolutitve SCI
B1: "000" | C1: "000" | D1: "000" | E1: "000" | F1: "000" | G1: "000" | H1: "000" | I1: "000" | AG1: "000"
B2: Audited 2011 | C2: Audited 2012 | D2: Audited 2013 | E2: Audited 2014 | F2: Audited 2015 | G2: Audited 2016 | H2: Audited 2017 | I2: 43101 | J2: 43132 | K2: 43160 | L2: 43191 | M2: 43221 | N2: 43252 | O2: 43282 | P2: 43313 | Q2: 43344 | R2: 43405 | S2: 43435 | T2: AUDITED 2018 | U2: 43466 | V2: 43497 | W2: 43525 | X2: 43556 | Y2: 43586 | Z2: 43617 | AA2: 43647 | AB2: 43678 | AC2: 43709 | AD2: 43739 | AE2: 43770 | AF2: 43800 | AG2: Audited 2019 | AH2: 43831 | AI2: 43862 | AJ2: 43891 | AK2: 43922 | AL2: 43952 | AM2: 43983 | AN2: 44044 | AO2: 44075 | AP2: 44105 | AQ2: 44136 | AR2: 44166 | AS2: Audited 2020 | AT2: 44197 | AU2: 44228 | AV2: 44256 | AW2: 44287 | AX2: 44317 | AY2: 44348 | AZ2: 44378 | BA2: 44409 | BB2: 44440 | BC2: 44470 | BD2: 44501 | BE2: 44531 | BF2: Audited 2021 | BG2: 44562 | BH2: 44593 | BI2: 44621 | BJ2: 44652 | BK2: 44682 | BL2: 44713 | BM2: 44743 | BN2: 44774 | BO2: 44805 | BP2: 44835 | BQ2: 44866 | BR2: 44896 | BS2: Audited 2022 | BT2: 44927 | BU2: 44958 | BV2: 44986 | BW2: 45017 | BX2: 45047 | BY2: 45078 | BZ2: 45108 | CA2: 45139 | CB2: 45170
A3: Financial Income | B3: =B4+B7 -> 4618217 | C3: =C4+C7 -> 5184217 | D3: =D4+D7 -> 7952957 | E3: =E4+E7 -> 8542749 | F3: =F4+F7 -> 8421094 | G3: =G4+G7 -> 8907817 | H3: =H4+H7 -> 8230050 | I3: =I4+I7 -> 232839.35 | ... CB3: =CB4+CB7 -> 8166071.4
A4: Financial Income From Loans Portfolio | B4: =SUM(B5:B6) -> 3294763 | C4: =SUM(C5:C6) -> 4288884 | D4: =SUM(D5:D6) -> 6035735 | E4: =SUM(E5:E6) -> 7524715 | F4: =SUM(F5:F6) -> 4986862 | G4: =SUM(G5:G6) -> 3743538 | H4: =SUM(H5:H6) -> 3567572 | I4: =SUM(I5:I6) -> 11651.35 | ... CB4: =SUM(CB5:CB6) -> 7206908.2
A5: Interest from Loans Portfolio | B5: =2885192+409571 -> 3294763 | C5: =2929622+1359262 -> 4288884 | D5: 3512831 | E5: 4843673 | F5: 4986862 | G5: 3743538 | H5: 3567572 | I5: 11651.35 | J5: 301453.9 | K5: 585768.16 | L5: 874257.55 | M5: 1148206.2 | N5: 1424737.3 | O5: 1935845.3 | P5: 2208519.6 | Q5: 2218615.1 | R5: 2795560.9 | S5: 3321955.7 | T5: 3321956 | U5: 285791.57 | V5: 304362.23 | W5: 825717.24 | X5: 1100922.9 | Y5: 1368129.2 | Z5: 1387377.9 | AA5: 1861531.9 | AB5: 2126795.3 | AC5: 2407641.4 | AD5: 2662890 | AE5: 2955324.9 | AF5: 3214668 | AG5: =2960343+254325 -> 3214668 | AH5: 292294.1 | AI5: 594618.59 | AJ5: 878858.52 | AK5: 1163295.3 | AL5: 1431499.5 | AM5: 1706433.5 | AN5: 2247354.5 | AO5: 2524122.9 | AP5: 2837829 | AQ5: 3125492.1 | AR5: 3390721.3 | AS5: =3124887+265833 -> 3390720 | AT5: 16718.83 | AU5: 297804.17 | AV5: 865337.64 | AW5: 1175347.7 | AX5: 1474867.3 | AY5: 1511971.8 | AZ5: 2130246.5 | BA5: 2468885 | BB5: 2526325.8 | BC5: 3152612 | BD5: 3471549.2 | BE5: 3814191.9 | BF5: 3859683 | BG5: 310141.87 | BH5: 610009.64 | BI5: 930395.63 | BJ5: 1259346 | BK5: 1594549.7 | BL5: 1918860.2 | BM5: 2273366.1 | BN5: 2613963.7 | BO5: 2958270.1 | BP5: 3291439.1 | BQ5: 3623793 | BR5: 3962796.8 | BS5: =3666592+408725 -> 4075317 | BT5: 345293 | BU5: 700748 | BV5: 1055101 | BW5: 1455961.4 | BX5: 1802684.2 | BY5: 2122977.2 | BZ5: 2693298 | CA5: 3112864 | CB5: 3173667.1
A6: Fees&Commision on Loan Portfolio | D6: 2522904 | E6: 2681042 | I6: 0 | J6: 0 | K6: 0 | L6: 0 | M6: 0 | N6: 0 | O6: 0 | P6: 0 | Q6: 0 | R6: 0 | S6: 0 | U6: 0 | V6: 0 | W6: 0 | X6: 0 | Y6: 0 | Z6: 0 | AA6: 0 | AB6: 0 | AC6: 0 | AD6: 0 | AE6: 0 | AF6: 0 | AH6: 0 | AI6: 0 | AJ6: 0 | AK6: 0 | AL6: 0 | AM6: 0 | AN6: 0 | AO6: 0 | AP6: 0 | AQ6: 0 | AR6: 0 | AS6: 0 | AT6: 0 | AU6: 0 | AV6: 0 | AW6: 0 | AX6: 0 | AY6: 0 | AZ6: 0 | BA6: 0 | BB6: 0 | BC6: 0 | BD6: 0 | BE6: 0 | BG6: 0 | BH6: 0 | BI6: 0 | BJ6: 0 | BK6: 0 | BL6: 0 | BM6: 0 | BN6: 0 | BO6: 0 | BP6: 0 | BQ6: 0 | BR6: 0 | BS6: =4004977 -> 4004977 | BT6: 0 | BU6: 0 | BV6: 0 | BW6: 0 | BX6: 0 | BY6: 0 | BZ6: 3189815 | CA6: 3527469 | CB6: 4033241
A7: Financial Income from Investments | B7: =SUM(B8:B11) -> 1323454 | C7: =SUM(C8:C11) -> 895333 | D7: =SUM(D8:D11) -> 1917222 | E7: =SUM(E8:E11) -> 1018034 | F7: =SUM(F8:F11) -> 3434232 | G7: =SUM(G8:G11) -> 5164279 | H7: =SUM(H8:H11) -> 4662478 | I7: =SUM(I8:I11) -> 221188 | ... CB7: =SUM(CB8:CB11) -> 959163.25
A8: Government Securities | I8: 0 | J8: 0 | K8: 0 | L8: 0 | M8: 0 | N8: 0 | O8: 0 | P8: 0 | Q8: 0 | R8: 0 | S8: 0 | U8: 0 | V8: 0 | W8: 0 | X8: 0 | Y8: 0 | Z8: 0 | AA8: 0 | AB8: 0 | AC8: 0 | AD8: 0 | AE8: 0 | AF8: 0 | AH8: 0 | AI8: 0 | AJ8: 0 | AK8: 0 | AL8: 0 | AM8: 0 | AN8: 0 | AO8: 0 | AP8: 0 | AQ8: 0 | AR8: 0 | AS8: 0 | AT8: 0 | AU8: 0 | AV8: 0 | AW8: 0 | AX8: 0 | AY8: 0 | AZ8: 0 | BA8: 0 | BB8: 0 | BC8: 0 | BD8: 0 | BE8: 0 | BG8: 0 | BH8: 0 | BI8: 0 | BJ8: 0 | BK8: 0 | BL8: 0 | BM8: 0 | BN8: 0 | BO8: 0 | BP8: 0 | BQ8: 0 | BR8: 0 | BT8: 0 | BU8: 0 | BV8: 0 | BW8: 0 | BX8: 0 | BY8: 0 | BZ8: 0 | CA8: 0 | CB8: 0
A9: Deposits with Banks & other Financial Institutions | H9: 282010 | I9: 36150 | J9: 81669 | K9: 127759 | L9: 181563.5 | M9: 233935 | N9: 279885 | O9: 377888 | P9: 480034 | Q9: 560013.5 | R9: 745427.5 | S9: 858937.5 | T9: 370004 | U9: 77890 | V9: 157282.5 | W9: 252618 | X9: 390914.25 | Y9: 487738.15 | Z9: 570827.65 | AA9: 662317.6 | AB9: 774057.6 | AC9: 859705.1 | AD9: 929055.1 | AE9: 1029089.6 | AF9: 1107864.6 | AG9: 293533 | AH9: 68700 | AI9: 143220 | AJ9: 249124 | AK9: 320091 | AL9: 386758.5 | AM9: 470638.4 | AN9: 619445.55 | AO9: 707428.55 | AP9: 794024.55 | AQ9: 850484.55 | AR9: 965764.55 | AS9: 62070 | AT9: 53160 | AU9: 135165 | AV9: 224910 | AW9: 319040.5 | AX9: 403499.2 | AY9: 499601.7 | AZ9: 603459.2 | BA9: 695526.7 | BB9: 777804.2 | BC9: 873282.5 | BD9: 939485 | BE9: 1030260 | BF9: =6283120-BF11 -> 2762988 | BG9: 64472.5 | BH9: 129107.5 | BI9: 217495 | BJ9: 327465 | BK9: 412556 | BL9: 483468 | BM9: 573743 | BN9: 646224 | BO9: 733738 | BP9: 792640 | BQ9: 870905 | BR9: 956635 | BS9: 287713 | BT9: 61302 | BU9: 120568 | BV9: 258831 | BW9: 367926 | BX9: 507961 | BY9: 608999 | BZ9: 0 | CA9: 0 | CB9: 0
A10: Other Investments | B10: 67805 | C10: 196592 | D10: 187787 | E10: 128575 | F10: 259249 | G10: 188122 | I10: 600 | J10: 12510 | K10: 23910 | L10: 34440 | M10: 45990 | N10: 57090 | O10: 79050 | P10: 90270 | Q10: 90870 | R10: 113250 | S10: 135330 | T10: 433128 | U10: 11160 | V10: 11550 | W10: 32550 | X10: 44104.07 | Y10: 53974.07 | Z10: 54394.07 | AA10: 74254.07 | AB10: 84754.07 | AC10: 94744.07 | AD10: 104254.07 | AE10: 113914.07 | AF10: 123064.07 | AH10: 9420 | AI10: 18750 | AJ10: 27600 | AK10: 37110 | AL10: 45720 | AM10: 54390 | AN10: 71040 | AO10: 78870 | AP10: 86670 | AQ10: 94140 | AR10: 102120 | AT10: 270 | AU10: 8250 | AV10: 23490 | AW10: 31200 | AX10: 39030 | AY10: 39560.32 | AZ10: 54200.32 | BA10: 61730.32 | BB10: 61970.32 | BC10: 76280.32 | BD10: 83540.32 | BE10: 90530.32 | BG10: 6840 | BH10: 13740 | BI10: 21360 | BJ10: 29310 | BK10: 37110 | BL10: 44880 | BM10: 52380 | BN10: 60480 | BO10: 68550 | BP10: 76380 | BQ10: 84840 | BR10: 92940 | BT10: 8640 | BU10: 17670 | BV10: 26310 | BW10: 34890 | BX10: 43620 | BY10: 51690 | BZ10: 673333.25 | CA10: 733273.25 | CB10: 778273.25
A11: Other Operating Income | B11: 1255649 | C11: =698741 -> 698741 | D11: 1729435 | E11: 889459 | F11: =3174983-F6 -> 3174983 | G11: 4976157 | H11: 4380468 | I11: 184438 | J11: 370159 | K11: 571354 | L11: 766958 | M11: 975012 | N11: 1193261 | O11: 1411815 | P11: 1660374.6 | Q11: 1881679.6 | R11: 2422437.6 | S11: 2659460.8 | T11: =5214289-433123 -> 4781166 | U11: 212633 | V11: 452982 | W11: 657761 | X11: 873148 | Y11: 1081540 | Z11: 1307047 | AA11: 1561150 | AB11: 1852080 | AC11: 2038071 | AD11: 2269137 | AE11: 2569224 | AF11: 2751429 | AG11: 5697204 | AH11: 226799 | AI11: 450979 | AJ11: 791196 | AK11: 867906 | AL11: 1097380 | AM11: 1322105 | AN11: 1835454 | AO11: 2113090 | AP11: 2392360 | AQ11: 2654450 | AR11: 3016123 | AS11: 5570903 | AT11: 145131 | AU11: 421096 | AV11: 671823 | AW11: 912785 | AX11: 1176275 | AY11: 1487045 | AZ11: 1826940 | BA11: 2099720 | BB11: 2409165 | BC11: 2723050 | BD11: 2975260 | BE11: 3222151 | BF11: 3520132 | BG11: 268760 | BH11: 534010 | BI11: 826766 | BJ11: 1155324 | BK11: 1422236 | BL11: 1711669 | BM11: 2011319 | BN11: 2302441 | BO11: 2686231 | BP11: 2871971 | BQ11: 3260876 | BR11: 3608331 | BS11: =1257889+592000+130400+120083 -> 2100372 | BT11: 294612 | BU11: 507131 | BV11: 937749 | BW11: 1060969 | BX11: 1449635 | BY11: 1676646 | BZ11: 158090 | CA11: 177840 | CB11: 180890
A12: Financial Expenses | B12: =SUM(B13:B18) -> 2292847 | C12: =SUM(C13:C18) -> 2761880 | D12: =SUM(D13:D18) -> 743203.78 | E12: =SUM(E13:E18) -> 2960790 | F12: =SUM(F13:F18) -> 2422107 | G12: =SUM(G13:G18) -> 2651211 | H12: =SUM(H13:H18) -> 2073568 | I12: =SUM(I13:I18) -> 4999.5 | ... CB12: =SUM(CB13:CB18) -> 58111
A13: Interest Expense on Deposits | B13: =1864544+184222 -> 2048766 | C13: =2220599+275212 -> 2495811 | D13: =191967 -> 191967 | E13: =2422463+75051 -> 2497514 | F13: =1717414+270545 -> 1987959 | G13: =321048+2167716 -> 2488764 | H13: =1503071+203637 -> 1706708 | I13: 4999.5 | J13: 12617 | K13: 13447.5 | L13: 27329.5 | M13: 37187.5 | N13: 47885 | O13: 61184 | P13: 72178.5 | Q13: 74034 | R13: 94756.5 | S13: 117900.5 | T13: =186488+1957092+233000+201684 -> 2578264 | U13: 15984 | V13: 19248 | W13: 23178 | X13: 43202 | Y13: 51132 | Z13: 71356 | AA13: 71456 | AB13: 83011 | AC13: 90167 | AD13: 96183 | AE13: 107927 | AF13: 115961 | AG13: =179592+2358986 -> 2538578 | AH13: 10728 | AI13: 19344 | AJ13: 30582 | AK13: 46108 | AL13: 49512 | AM13: 61687 | AN13: 74693.46 | AO13: 92137.42 | AP13: 102067.44 | AQ13: 106111.7 | AR13: 261531.35 | AS13: 2941600 | AT13: 12160 | AU13: 21874 | AV13: 37443.57 | AW13: 50199.4 | AX13: 51105.4 | AY13: 64807.42 | AZ13: 83150.42 | BA13: 91334.42 | BB13: 101801.1 | BC13: 115487.1 | BD13: 117629.1 | BE13: 143274.44 | BF13: 3154973 | BG13: 10104 | BH13: 12726 | BI13: 21672 | BJ13: 29976 | BK13: 45756 | BL13: 49566 | BM13: 64883 | BN13: 84315 | BO13: 97519 | BP13: 107089 | BQ13: 117307 | BR13: 135042.57 | BS13: 3021312 | BT13: 12550 | BU13: 22108 | BV13: 30403.92 | BW13: 38449.92 | BX13: 48007.92 | BY13: 55453.92 | BZ13: 0 | CA13: 0 | CB13: 0
A14: Cost of External Borrowings | B14: =178862+17556+47663 -> 244081 | C14: =50936+84651+130482 -> 266069 | D14: =35132+74114+3977+193986.78 -> 307209.78 | E14: 40009 | F14: 434148 | G14: 162447 | H14: 366860 | I14: 0 | J14: 39125.1 | K14: 71912.55 | L14: 71912.55 | M14: 134185.35 | N14: 134185.35 | O14: 190104.45 | P14: 190104.45 | Q14: 225684.5 | R14: 10957 | S14: 239693.6 | T14: 262484 | U14: 0 | V14: 0 | W14: 0 | X14: 0 | Y14: 0 | Z14: 0 | AA14: 0 | AB14: 44608 | AC14: 44608 | AD14: 44608 | AE14: 44608 | AF14: 44608 | AG14: 44608 | AH14: 0 | AI14: 0 | AJ14: 0 | AK14: 0 | AL14: 0 | AM14: 0 | AN14: 0 | AO14: 0 | AP14: 0 | AQ14: 0 | AR14: 0 | AS14: 0 | AT14: 0 | AU14: 0 | AV14: 0 | AW14: 0 | AX14: 0 | AY14: 0 | AZ14: 0 | BA14: 0 | BB14: 0 | BC14: 0 | BD14: 0 | BE14: 0 | BG14: 0 | BH14: 0 | BI14: 0 | BJ14: 0 | BK14: 0 | BL14: 0 | BM14: 0 | BN14: 0 | BO14: 0 | BP14: 0 | BQ14: 0 | BR14: 0 | BT14: 0 | BU14: 0 | BV14: 0 | BW14: 0 | BX14: 0 | BY14: 0 | BZ14: 0 | CA14: 0 | CB14: 0
A15: Dividend Expenses | I15: 0 | J15: 0 | K15: 0 | L15: 0 | M15: 0 | N15: 0 | O15: 0 | P15: 0 | Q15: 0 | R15: 0 | S15: 0 | U15: 0 | V15: 0 | W15: 0 | X15: 0 | Y15: 0 | Z15: 0 | AA15: 0 | AB15: 0 | AC15: 0 | AD15: 0 | AE15: 0 | AF15: 0 | AG15: =150000+133950+515545 -> 799495 | AH15: 0 | AI15: 0 | AJ15: 0 | AK15: 0 | AL15: 0 | AM15: 0 | AN15: 0 | AO15: 0 | AP15: 0 | AQ15: 0 | AR15: 0 | AS15: 0 | AT15: 0 | AU15: 0 | AV15: 0 | AW15: 0 | AX15: 0 | AY15: 0 | AZ15: 0 | BA15: 0 | BB15: 0 | BC15: 0 | BD15: 0 | BE15: 0 | BG15: 0 | BH15: 0 | BI15: 0 | BJ15: 0 | BK15: 0 | BL15: 0 | BM15: 0 | BN15: 0 | BO15: 0 | BP15: 0 | BQ15: 0 | BR15: 0 | BS15: 215684 | BT15: 0 | BU15: 0 | BV15: 0 | BW15: 0 | BX15: 0 | BY15: 0 | BZ15: 0 | CA15: 0 | CB15: 0
A16: Other Financial Expense | D16: =42757+149210 -> 191967 | I16: 0 | J16: 1146 | K16: 2065 | L16: 3101 | M16: 4205 | N16: 5332 | O16: 6359 | P16: 7442 | Q16: 8528 | R16: 239693.6 | S16: 198298.29 | U16: 0 | V16: 0 | W16: 0 | X16: 0 | Y16: 2517 | Z16: 2517 | AA16: 2517 | AB16: 0 | AC16: 0 | AD16: 0 | AE16: 0 | AF16: 0 | AH16: 0 | AI16: 0 | AJ16: 0 | AK16: 19122.81 | AL16: 19976.81 | AM16: 90795.03 | AN16: 94393.03 | AO16: 140042.03 | AP16: 140735.03 | AQ16: 141448.03 | AR16: 487889.43 | AS16: =150000+133950+521662 -> 805612 | AT16: 0 | AU16: 122573 | AV16: 123160 | AW16: 143160 | AX16: 144665 | AY16: 145688 | AZ16: 146422 | BA16: 146422 | BB16: 169319 | BC16: 190957 | BD16: 191826 | BE16: 396554.41 | BF16: 0 | BG16: 0 | BH16: 545 | BI16: 857 | BJ16: 20857 | BK16: 21827 | BL16: 21827 | BM16: 22265 | BN16: 22681 | BO16: 23281 | BP16: 296881 | BQ16: 297843 | BR16: 513527.18 | BS16: 0 | BT16: 0 | BU16: 649 | BV16: 649 | BW16: 649 | BX16: 2521 | BY16: 124321 | BZ16: 2521 | CA16: 2521 | CB16: 58111
A17: Fees & Commision Expense | I17: 0 | J17: 0 | K17: 0 | L17: 0 | M17: 0 | N17: 0 | O17: 0 | P17: 0 | Q17: 0 | R17: 0 | S17: 0 | U17: 0 | V17: 0 | W17: 0 | X17: 0 | Y17: 0 | Z17: 0 | AA17: 44608 | AB17: 68734.7 | AC17: 69403.7 | AD17: 69403.7 | AE17: 70832.7 | AF17: 372224.5 | AH17: 0 | AI17: 0 | AJ17: 0 | AK17: 0 | AL17: 0 | AM17: 0 | AN17: 0 | AO17: 0 | AP17: 0 | AQ17: 0 | AR17: 0 | AS17: 0 | AT17: 0 | AU17: 0 | AV17: 0 | AW17: 0 | AX17: 0 | AY17: 0 | AZ17: 0 | BA17: 0 | BB17: 0 | BC17: 0 | BD17: 0 | BE17: 0 | BG17: 0 | BH17: 0 | BI17: 0 | BJ17: 0 | BK17: 0 | BL17: 0 | BM17: 0 | BN17: 0 | BO17: 0 | BP17: 0 | BQ17: 0 | BR17: 0 | BT17: 0 | BU17: 0 | BV17: 0 | BW17: 0 | BX17: 0 | BY17: 0 | BZ17: 0 | CA17: 0 | CB17: 0
A18: Other Expenses | D18: 52060 | E18: =293758+129509 -> 423267 | I18: 0 | J18: 0 | K18: 0 | L18: 0 | M18: 0 | N18: 0 | O18: 0 | P18: 0 | Q18: 0 | R18: 0 | S18: 0 | U18: 0 | V18: 0 | W18: 0 | X18: 0 | Y18: 0 | Z18: 0 | AA18: 0 | AB18: 0 | AC18: 0 | AD18: 0 | AE18: 0 | AF18: 0 | AH18: 0 | AI18: 0 | AJ18: 0 | AK18: 0 | AL18: 0 | AM18: 0 | AN18: 0 | AO18: 0 | AP18: 0 | AQ18: 0 | AR18: 0 | AS18: 0 | AT18: 0 | AU18: 0 | AV18: 0 | AW18: 0 | AX18: 0 | AY18: 0 | AZ18: 0 | BA18: 0 | BB18: 0 | BC18: 0 | BD18: 0 | BE18: 0 | BG18: 0 | BH18: 0 | BI18: 0 | BJ18: 0 | BK18: 0 | BL18: 0 | BM18: 0 | BN18: 0 | BO18: 0 | BP18: 0 | BQ18: 0 | BR18: 0 | BT18: 0 | BU18: 0 | BV18: 0 | BW18: 0 | BX18: 0 | BY18: 0 | BZ18: 0 | CA18: 0 | CB18: 0
A19: Net Financial Income | B19: =B3-B12 -> 2325370 | C19: =C3-C12 -> 2422337 | D19: =D3-D12 -> 7209753.2 | E19: =E3-E12 -> 5581959 | F19: =F3-F12 -> 5998987 | G19: =G3-G12 -> 6256606 | H19: =H3-H12 -> 6156482 | I19: =I3-I12 -> 227839.85 | ... CB19: =CB3-CB12 -> 8107960.4
A20: Allowance for Loan Loss | B20: =B21-B22 -> 0 | C20: =C21-C22 -> 0 | D20: =D21-D22 -> 0 | E20: =E21-E22 -> 0 | F20: =F21-F22 -> 800000 | G20: =G21-G22 -> 550000 | H20: =H21-H22 -> 575767 | I20: =I21-I22 -> 0 | ... CB20: =CB21-CB22 -> 0
A21: Provision for Loan Losses | F21: 800000 | G21: 550000 | H21: 575767 | I21: 0 | J21: 0 | K21: 0 | L21: 0 | M21: 0 | N21: 0 | O21: 0 | P21: 0 | Q21: 0 | R21: 0 | S21: 0 | T21: 1034684 | U21: 0 | V21: 0 | W21: 0 | X21: 0 | Y21: 0 | Z21: 0 | AA21: 0 | AB21: 0 | AC21: 0 | AD21: 0 | AE21: 0 | AF21: 0 | AG21: 600000 | AH21: 0 | AI21: 0 | AJ21: 0 | AK21: 0 | AL21: 0 | AM21: 0 | AN21: 0 | AO21: 0 | AP21: 0 | AQ21: 0 | AR21: 0 | AS21: 582100 | AT21: 0 | AU21: 0 | AV21: 0 | AW21: 0 | AX21: 0 | AY21: 0 | AZ21: 0 | BA21: 0 | BB21: 0 | BF21: 96529 | BG21: 0 | BH21: 0 | BI21: 0 | BJ21: 0 | BK21: 0 | BL21: 0 | BM21: 0 | BN21: 0 | BO21: 0 | BP21: 0 | BQ21: 0 | BR21: 0 | BS21: 0 | BT21: 0 | BU21: 0 | BV21: 0 | BW21: 0 | BX21: 0 | BY21: 0 | BZ21: 0 | CA21: 0 | CB21: 0
A22: Value of Loans Recovered | I22: 0 | J22: 0 | K22: 0 | L22: 0 | M22: 0 | N22: 0 | O22: 0 | P22: 0 | Q22: 0 | R22: 0 | S22: 0 | U22: 0 | V22: 0 | W22: 0 | X22: 0 | Y22: 0 | Z22: 0 | AA22: 0 | AB22: 0 | AC22: 0 | AD22: 0 | AE22: 0 | AF22: 0 | AH22: 0 | AI22: 0 | AJ22: 0 | AK22: 0 | AL22: 0 | AM22: 0 | AN22: 0 | AO22: 0 | AP22: 0 | AQ22: 0 | AR22: 0 | AS22: 0 | AT22: 0 | AU22: 0 | AV22: 0 | AW22: 0 | AX22: 0 | AY22: 0 | AZ22: 0 | BA22: 0 | BB22: 0 | BG22: 0 | BH22: 0 | BI22: 0 | BJ22: 0 | BK22: 0 | BL22: 0 | BM22: 0 | BN22: 0 | BO22: 0 | BP22: 0 | BQ22: 0 | BR22: 0 | BT22: 0 | BU22: 0 | BV22: 0 | BW22: 0 | BX22: 0 | BY22: 0 | BZ22: 0 | CA22: 0 | CB22: 0
A23: Operating Expeses | B23: =SUM(B24:B28) -> 2188331 | C23: =SUM(C24:C28) -> 2142423 | D23: =SUM(D24:D28) -> 3280896 | E23: =SUM(E24:E28) -> 3663861 | F23: =SUM(F24:F28) -> 4191173 | G23: =SUM(G24:G28) -> 4447942 | H23: =SUM(H24:H28) -> 5369973 | I23: =SUM(I24:I28) -> 193026.22 | ... CB23: =SUM(CB24:CB28) -> 4008208.4
A24: Personel Expenses | B24: 191449 | C24: =1223055 -> 1223055 | D24: 1344891 | E24: 1357118 | F24: 1588884 | G24: 1675820 | H24: 1803481 | I24: 127475 | J24: 257903 | K24: 387932 | L24: 609382 | M24: 737262 | N24: 862873 | O24: 988307 | P24: 1123380 | Q24: 1267192 | R24: 1537503 | S24: 1703992 | T24: 1839286 | U24: 147224 | V24: 324430 | W24: 500926 | X24: 731175 | Y24: 887063 | Z24: 1032215 | AA24: 1139164 | AB24: 1281120 | AC24: 1408250 | AD24: 1416600 | AE24: 1794528.6 | AF24: 1966473.6 | AG24: 2137339 | AH24: 115904 | AI24: 206892 | AJ24: 315730 | AK24: 470266 | AL24: 588743 | AM24: 690251 | AN24: 895445 | AO24: 996940 | AP24: 1109467 | AQ24: 1221132 | AR24: 1338669 | AS24: 1588761 | AT24: 10272 | AU24: 124370 | AV24: 415912 | AW24: 588180 | AX24: 832337 | AY24: 837844 | AZ24: 1183667 | BA24: 1375140 | BB24: 1382736 | BC24: 1751440 | BD24: 1937943 | BE24: 2130920 | BF24: 2130920 | BG24: 178359 | BH24: 356267 | BI24: 540240 | BJ24: 717827 | BK24: 896702 | BL24: 1228531 | BM24: 1405884 | BN24: 1580555 | BO24: 1889750 | BP24: 2088932 | BQ24: 2288915 | BR24: 2501397 | BS24: =28246+138354+51429+82330+2201038 -> 2501397 | BT24: 201281 | BU24: 401355 | BV24: 612245 | BW24: 821390 | BX24: 1165258 | BY24: 1192178 | BZ24: 1588639 | CA24: 1797291 | CB24: 2007211
A25: Governance Expenses | B25: 508737 | C25: =265661 -> 265661 | D25: =516344+305261 -> 821605 | E25: =416562+416562 -> 833124 | F25: 870700 | G25: 1068794 | H25: 827193 | I25: 33891.22 | J25: 138714.26 | K25: 185135.58 | L25: 220795.58 | M25: 270568.82 | N25: 298168.82 | O25: 382937.42 | P25: 470457.62 | Q25: 525367.62 | R25: 952001.9 | S25: 981719.9 | T25: 796588 | U25: 31580 | V25: 78601.92 | W25: 227074.48 | X25: 269288.8 | Y25: 306501.84 | Z25: 335768.24 | AA25: 370518.24 | AB25: 426286.3 | AC25: 470408.96 | AD25: 488422.64 | AE25: 828644.82 | AF25: 864717.17 | AG25: 842346 | AH25: 35057 | AI25: 76982 | AJ25: 213555.49 | AK25: 261911.88 | AL25: 304029.44 | AM25: 358671.98 | AN25: 447826.76 | AO25: 495938.54 | AP25: 524022.54 | AQ25: 852579.32 | AR25: 894744.32 | AS25: 592227 | AT25: 70838 | AU25: 186952 | AV25: 250101 | AW25: 306117 | AX25: 345722 | AY25: 387223 | AZ25: 410425 | BA25: 506578 | BB25: 534018 | BC25: 581270 | BD25: 897492 | BE25: 960165 | BF25: 734300 | BG25: 112879 | BH25: 160431 | BI25: 195129 | BJ25: 309727 | BK25: 355225 | BL25: 385553 | BM25: 421039 | BN25: 436056 | BO25: 455578 | BP25: 476742 | BQ25: 518682 | BR25: 843489.8 | BS25: =74730+309390+215524+363700+184256 -> 1147600 | BT25: 20912 | BU25: 136427 | BV25: 167912 | BW25: 198642 | BX25: 222582 | BY25: 274598 | BZ25: 734532 | CA25: 854141 | CB25: 954804
A26: Marketing Expenses | C26: =15391 -> 15391 | F26: 66795 | G26: 50845 | H26: 88581 | I26: 31660 | J26: 63820 | K26: 97580 | L26: 153254 | M26: 208614 | N26: 239774 | O26: 323239 | P26: 392399 | Q26: 431299 | R26: 492713 | S26: 527373 | T26: 26107 | U26: 28840 | V26: 164880 | W26: 187160 | X26: 230654 | Y26: 285294 | Z26: 322534 | AA26: 400488 | AB26: 423728 | AC26: 466768 | AD26: 508808 | AE26: 544448 | AF26: 611288 | AG26: 73120 | AH26: 40240 | AI26: 197880 | AJ26: 220280 | AK26: 245392 | AL26: 271432 | AM26: 298537 | AN26: 391617 | AO26: 441943 | AP26: 498643 | AQ26: 532571 | AR26: 592227 | AS26: 30792 | AT26: 79312 | AU26: 183024 | AV26: 262150 | AW26: 309548 | AX26: 371760 | AY26: 411786 | AZ26: 454098 | BA26: 523810 | BB26: 555022 | BC26: 584834 | BD26: 625702 | BE26: 658228 | BF26: 23744 | BG26: 23240 | BH26: 417324 | BI26: 446780 | BJ26: 497050 | BK26: 599094 | BL26: 633178 | BM26: 669076 | BN26: 702488 | BO26: 730400 | BP26: 753640 | BQ26: 824411 | BR26: 857346 | BS26: 34594 | BT26: 40963 | BU26: 180326 | BV26: 210309 | BW26: 271108 | BX26: 359091 | BY26: 414554 | BZ26: 15956 | CA26: 15956 | CB26: 29656
A27: Depreciation and Amortization | B27: 1488145 | C27: =163186+66711 -> 229897 | E27: 104770 | F27: 124306 | G27: 145141 | H27: 166412 | I27: 0 | J27: 0 | K27: 0 | L27: 0 | M27: 0 | N27: 0 | O27: 0 | P27: 0 | Q27: 0 | R27: 0 | S27: 0 | T27: 149817 | U27: 0 | V27: 0 | W27: 0 | X27: 0 | Y27: 0 | Z27: 0 | AA27: 0 | AB27: 0 | AC27: 0 | AD27: 0 | AE27: 0 | AF27: 0 | AG27: 153572 | AH27: 0 | AI27: 0 | AJ27: 0 | AK27: 0 | AL27: 0 | AM27: 0 | AN27: 0 | AO27: 0 | AP27: 0 | AQ27: 0 | AR27: 0 | AS27: 138019 | AT27: 0 | AU27: 0 | AV27: 0 | AW27: 0 | AX27: 0 | AY27: 0 | AZ27: 0 | BA27: 0 | BB27: 0 | BC27: 0 | BD27: 0 | BE27: 0 | BF27: 120499 | BG27: 0 | BH27: 0 | BI27: 0 | BJ27: 0 | BK27: 0 | BL27: 0 | BM27: 0 | BN27: 0 | BO27: 0 | BP27: 0 | BQ27: 0 | BR27: 0 | BS27: 171593 | BT27: 0 | BU27: 0 | BV27: 0 | BW27: 0 | BX27: 0 | BY27: 0 | BZ27: 0 | CA27: 0 | CB27: 0
A28: Administrative Expenses | C28: =8734+11062+78670+2600+42241+115643+103738+9397+6500+12000+2234+15600 -> 408419 | D28: =1006155+43820+12365+52060 -> 1114400 | E28: =734848+634001 -> 1368849 | F28: 1540488 | G28: 1507342 | H28: 2484306 | I28: 0 | J28: 0 | K28: 0 | L28: 0 | M28: 0 | N28: 0 | O28: 0 | P28: 0 | Q28: 0 | R28: 0 | S28: 0 | T28: 1503028 | U28: 0 | V28: 0 | W28: 0 | X28: 0 | Y28: 0 | Z28: 0 | AA28: 0 | AB28: 0 | AC28: 0 | AD28: 0 | AE28: 0 | AF28: 0 | AG28: 1373905 | AH28: 0 | AI28: 0 | AJ28: 0 | AK28: 0 | AL28: 0 | AM28: 0 | AN28: 0 | AO28: 0 | AP28: 0 | AQ28: 0 | AR28: 0 | AS28: 1608989 | AT28: 0 | AU28: 0 | AV28: 0 | AW28: 0 | AX28: 0 | AY28: 0 | AZ28: 0 | BA28: 0 | BB28: 0 | BC28: 0 | BD28: 0 | BE28: 0 | BF28: 1663461 | BG28: 0 | BH28: 0 | BI28: 0 | BJ28: 0 | BK28: 0 | BL28: 0 | BM28: 0 | BN28: 0 | BO28: 0 | BP28: 0 | BQ28: 0 | BR28: 0 | BS28: =90933+35000+243600+134978+55688+20085+279488+75000+107669+139350+285353+27840+32164+135043 -> 1662191 | BT28: 0 | BU28: 0 | BV28: 0 | BW28: 0 | BX28: 0 | BY28: 0 | BZ28: 906854.92 | CA28: 955470.87 | CB28: 1016537.4
A29: Net Operating Income | B29: =B19-B20-B23 -> 137039 | C29: =C19-C20-C23 -> 279914 | D29: =D19-D20-D23 -> 3928857.2 | E29: =E19-E20-E23 -> 1918098 | F29: =F19-F20-F23 -> 1007814 | G29: =G19-G20-G23 -> 1258664 | H29: =H19-H20-H23 -> 210742 | I29: =I19-I20-I23 -> 34813.63 | ... CB29: =CB19-CB20-CB23 -> 4099752
A30: Net Non operating Income/Expense | B30: =B31-B32 -> 0 | C30: =C31-C32 -> 0 | D30: =D31-D32 -> 79200 | E30: =E31-E32 -> 0 | F30: =F31-F32 -> 0 | G30: =G31-G32 -> 0 | H30: =H31-H32 -> 0 | I30: =I31-I32 -> 0 | ... CB30: =CB31-CB32 -> 0
A31: Non Operating Income | D31: 79200 | I31: 0 | J31: 0 | K31: 0 | L31: 0 | M31: 0 | N31: 0 | O31: 0 | P31: 0 | Q31: 0 | R31: 0 | S31: 0 | U31: 0 | V31: 0 | W31: 0 | X31: 0 | Y31: 0 | Z31: 0 | AA31: 0 | AB31: 0 | AC31: 0 | AD31: 0 | AE31: 0 | AF31: 0 | AH31: 0 | AI31: 0 | AJ31: 0 | AK31: 0 | AL31: 0 | AM31: 0 | AN31: 0 | AO31: 0 | AP31: 0 | AQ31: 0 | AR31: 0 | AT31: 0 | AU31: 0 | AV31: 0 | AW31: 0 | AX31: 0 | AY31: 0 | AZ31: 0 | BA31: 0 | BB31: 0 | BG31: 0 | BH31: 0 | BI31: 0 | BJ31: 0 | BK31: 0 | BL31: 0 | BM31: 0 | BN31: 0 | BO31: 0 | BP31: 0 | BQ31: 0 | BR31: 0 | BT31: 0 | BU31: 0 | BV31: 0 | BW31: 0 | BX31: 0 | BY31: 0 | BZ31: 0 | CA31: 0 | CB31: 0
A32: Non Operating Expense | I32: 0 | J32: 0 | K32: 0 | L32: 0 | M32: 0 | N32: 0 | O32: 0 | P32: 0 | Q32: 0 | R32: 0 | S32: 0 | U32: 0 | V32: 0 | W32: 0 | X32: 0 | Y32: 0 | Z32: 0 | AA32: 0 | AB32: 0 | AC32: 0 | AD32: 0 | AE32: 0 | AF32: 0 | AH32: 0 | AI32: 0 | AJ32: 0 | AK32: 0 | AL32: 0 | AM32: 0 | AN32: 0 | AO32: 0 | AP32: 0 | AQ32: 0 | AR32: 0 | AT32: 0 | AU32: 0 | AV32: 0 | AW32: 0 | AX32: 0 | AY32: 0 | AZ32: 0 | BA32: 0 | BB32: 0 | BG32: 0 | BH32: 0 | BI32: 0 | BJ32: 0 | BK32: 0 | BL32: 0 | BM32: 0 | BN32: 0 | BO32: 0 | BP32: 0 | BQ32: 0 | BR32: 0 | BT32: 0 | BU32: 0 | BV32: 0 | BW32: 0 | BX32: 0 | BY32: 0 | BZ32: 0 | CA32: 0 | CB32: 0
A33: Net Income(Before Tax & Donations) | B33: =B29+B30 -> 137039 | C33: =C29+C30 -> 279914 | D33: =D29+D30 -> 4008057.2 | E33: =E29+E30 -> 1918098 | F33: =F29+F30 -> 1007814 | G33: =G29+G30 -> 1258664 | H33: =H29+H30 -> 210742 | I33: =I29+I30 -> 34813.63 | ... CB33: =CB29+CB30 -> 4099752
A34: Taxes | C34: 94708 | E34: 41297 | F34: 38702 | G34: 43968 | I34: 0 | J34: 0 | K34: 10000 | L34: 24000 | M34: 24000 | N34: 24000 | O34: 24000 | P34: 24000 | Q34: 24000 | R34: 24000 | S34: 24000 | T34: 51709 | U34: 0 | V34: 8840 | W34: 13840 | X34: 83840 | Y34: 83840 | Z34: 83840 | AA34: 13840 | AB34: 13840 | AC34: 13840 | AD34: 13840 | AE34: 13840 | AF34: 83840 | AG34: 64642 | AH34: 0 | AI34: 19642 | AJ34: 23612 | AK34: 28684 | AL34: 28684 | AM34: 28684 | AN34: 28684 | AO34: 28684 | AP34: 28684 | AQ34: 28684 | AR34: 98684 | AS34: 95961 | AT34: 0 | AU34: 21850 | AV34: 21850 | AW34: 21850 | AX34: 21850 | AY34: 21850 | AZ34: 21850 | BA34: 21850 | BB34: 21850 | BC34: 21850 | BD34: 21850 | BE34: 21850 | BF34: 62242 | BG34: 0 | BH34: 30092 | BI34: 32164 | BJ34: 32164 | BK34: 32164 | BL34: 32164 | BM34: 32164 | BN34: 32164 | BO34: 32164 | BP34: 32164 | BQ34: 32164 | BR34: 32164 | BS34: 122339 | BT34: 0 | BU34: 36000 | BV34: 36000 | BW34: 36000 | BX34: 36000 | BY34: 36000 | BZ34: 0 | CA34: 0 | CB34: 0
A35: Net Income(After Tax Before Donations) | B35: =B33-B34 -> 137039 | C35: =C33-C34 -> 185206 | D35: =D33-D34 -> 4008057.2 | E35: =E33-E34 -> 1876801 | F35: =F33-F34 -> 969112 | G35: =G33-G34 -> 1214696 | H35: =H33-H34 -> 210742 | I35: =I33-I34 -> 34813.63 | ... CB35: =CB33-CB34 -> 4099752
A36: Donations | I36: 0 | J36: 0 | K36: 0 | L36: 0 | M36: 0 | N36: 0 | O36: 0 | P36: 0 | Q36: 0 | R36: 0 | S36: 0 | U36: 0 | V36: 0 | W36: 0 | X36: 0 | Y36: 0 | Z36: 0 | AA36: 0 | AB36: 0 | AC36: 0 | AD36: 0 | AE36: 0 | AF36: 0 | AH36: 0 | AI36: 0 | AJ36: 0 | AK36: 0 | AL36: 0 | AM36: 0 | AN36: 0 | AO36: 0 | AP36: 0 | AQ36: 0 | AR36: 0 | AT36: 0 | AU36: 0 | AV36: 0 | AW36: 0 | AX36: 0 | AY36: 0 | AZ36: 0 | BA36: 0 | BB36: 0 | BG36: 0 | BH36: 0 | BI36: 0 | BJ36: 0 | BK36: 0 | BL36: 0 | BM36: 0 | BN36: 0 | BO36: 0 | BP36: 0 | BQ36: 0 | BR36: 0 | BX36: 0 | BY36: 0 | BZ36: 0 | CA36: 0 | CB36: 0
A37: Net Income/(After Tax & Donations) | B37: =B35-B36 -> 137039 | C37: =C35-C36 -> 185206 | D37: =D35-D36 -> 4008057.2 | E37: =E35-E36 -> 1876801 | F37: =F35-F36 -> 969112 | G37: =G35-G36 -> 1214696 | H37: =H35-H36 -> 210742 | I37: =I35-I36 -> 34813.63 | ... CB37: =CB35-CB36 -> 4099752
BT38: 0 | BU38: 0 | BV38: 0 | BW38: 0 | BX38: 0 | BY38: 0 | BZ38: 0
A39: Total Expenses | B39: =B12+B23 -> 4481178 | C39: =C12+C23 -> 4904303 | D39: =D12+D23 -> 4024099.8 | E39: =E12+E23 -> 6624651 | F39: =F12+F23 -> 6613280 | G39: =G12+G23 -> 7099153 | H39: =H12+H23 -> 7443541 | I39: =I12+I23 -> 198025.72 | ... CB39: =CB12+CB23 -> 4066319.4
AT44: =AT37-164292468.04 -> -1.6424977e+08

Sheet Dec 2019 report
A1: STIMA SACCO SOCIETY LIMITED
A2: PERFORMANCE AND COMPLIANCE REPORT AS AT : 31st December , 2019
B3: Prudential Standard | C3: Audited | D3: Returns | F3: Audited 2019 | G3: Aggregate for all Licensed Saccos
C4: 2018 | D4: 30th September , 2019 | E4: 31st December , 2019
A5: A. CAPITAL ADEQUACY
A6: Core Capital | B6: ≥10M | C6: 4057843000 | D6: 3.9340926e+09 | E6: 4.252452e+09 | F6: =F33 -> 18417388 | G6: 8.5755077e+10
A7: Core Capital/Total Assets | B7: ≥10% | C7: 0.12567652 | D7: 0.11408248 | E7: 0.11481094 | F7: =F6/F29 -> 0.25860051 | G7: 0.15609442
A8: Institutional Capital/Total Assets | B8: ≥8% | C8: 0.079393471 | D8: 0.064591681 | E8: 0.067244176 | F8: =F34/F29 -> 0.076538578 | G8: 0.091531093
A9: B. ASSET QUALITY
A10: NPL (Substandard+Doubtful+Loss) | B10: <5% | C10: 0 | D10: 0.054329847 | E10: 0.047637752 | F10: =F35/F32 -> 0 | G10: 0.07434801
A11: Non-Earning Assets | B11: <10% | C11: 0.035863732 | D11: 0.035724114 | E11: 0.037274684 | F11: =F36/F29 -> 0.25657966 | G11: 0.10558073
A12: Equity investments/Deposits | B12: <5% | C12: 0 | D12: 0.024842844 | E12: 0.023590605 | F12: =F38/F31 -> 0.33978324 | G12: 0.034793574
A13: Equity investments/Core capital | B13: <40% | C13: 0 | D13: 0.16950928 | E13: 0.1568204 | F13: =F38/F33 -> 0.88210956 | G13: 0.15319582
A14: C. EARNINGS RATING
A15: Yield on Gross Loans | C15: 0.15191121 | D15: 0.11822952 | E15: 0.1455451 | F15: =F48/F32 -> 0.10719588 | G15: 0.16355249
A16: Total Expense/Total Income | C16: 0.75439892 | D16: 0.75528666 | E16: 0.7186639 | F16: =F49/F44 -> 0.86503125 | G16: 0.70158636
A17: Net Income/Average Assets (ROA) | C17: 0.0278967 | D17: 0.020089744 | E17: 0.031914696 | F17: =F50/F30 -> 3.5711621e-05 | G17: 0.038444702
A18: Operating Expenses/Financial Income (OPEX) | C18: 0.25221239 | D18: 0.25235898 | E18: 0.24257735 | F18: =F47/F45 -> 0.78662186 | G18: 0.31925833
A19: D. LIQUIDITY
A20: Liquid Assets/Short-term Liabilities | B20: >15% | C20: 0.22714378 | D20: 0.72775006 | E20: 0.53145529 | F20: =F40/F41 -> 0.23505702 | G20: 0.5504023
A21: External Borrowing/Total Assets | B21: <25% | C21: 0.01020404 | D21: 0 | E21: 0 | F21: =F42/F29 -> 0 | G21: 0.03910423
A22: Liquid Assets/Total Assets | C22: 0.060313562 | D22: 0.18011196 | E22: 0.14005067 | F22: =F40/F29 -> 0.14422413 | G22: 0.11043073
A23: E. STRUCTURE/SENSITIVITY TO RISK
A24: Gross loans /Total Assets | B24: 70-80 | C24: 0.79999743 | D24: 0.7800437 | E24: 0.82085193 | F24: =F32/F29 -> 0.4210749 | G24: 0.75950448
A25: Gross loans/Deposits | B25: >100% | C25: 1.0373556 | D25: 1.0020925 | E25: 1.0755191 | F25: =F32/F31 -> 0.62720485 | G25: 1.1050835
A26: Financial Investments/Total Assets | C26: 0.18797701 | D26: 0.034489796 | E26: 0.033529934 | F26: =F38/F29 -> 0.22811398 | G26: 0.059615079
A27: Dividends+Interest on Deposits/Total Income | C27: 0.49156615 | D27: 0.49594541 | E27: 0.47078017 | F27: =F46/F44 -> 0.0048458487 | G27: 0.3152237
A28: F. KEY FINANCIAL STATISTICS | C28: 2015 | D28: 2016 | E28: 2017 | G28: AGGREGATE
A29: Total Assets | C29: 32287995000 | D29: 3.4484633e+10 | E29: 3.7038736e+10 | F29: ='Evolutive SFP'!AH27 -> 71219457 | G29: 5.4937953e+11
A30: Average Assets | C30: 30426610000 | D30: 3.2935177e+10 | E30: 3.4818536e+10 | F30: =(C29+F29)/2 -> 1.6179607e+10 | G30: 5.2175164e+11
A31: Total Deposits | C31: 24900152000 | D31: 2.6843352e+10 | E31: 2.8268507e+10 | F31: ='Evolutive SFP'!AH31 -> 47813288 | G31: 3.775789e+11
A32: Gross Loans | C32: 25830313000 | D32: 2.6899521e+10 | E32: 3.0403318e+10 | F32: ='Evolutive SFP'!AH15 -> 29988726 | G32: 4.1725622e+11
A33: Core Capital | C33: 4057843000 | D33: 3.9340926e+09 | E33: 4.252452e+09 | F33: =Financials!AS11 -> 18417388 | G33: 8.5755077e+10
A34: Institutional Capital | C34: 2563456000 | D34: 2.2274204e+09 | E34: 2.4906393e+09 | F34: =Financials!AS12 -> 5451036 | G34: 5.0285309e+10
A35: Non-performing Loans | C35: 0 | D35: 1.4614469e+09 | E35: 1.4483457e+09 | G35: 3.1022169e+10
A36: Non-Earning Assets | C36: 1157968000 | D36: 1.231933e+09 | E36: 1.3806072e+09 | F36: =Financials!AS34 -> 18273464 | G36: 5.8003891e+10
A37: Property and Equipment | C37: 320370000 | D37: 3.0385145e+08 | E37: 3.017075e+08 | F37: =Financials!AS35 -> 16218800 | G37: 1.780879e+10
A38: Equity Investments | C38: 0 | D38: 6.6686521e+08 | E38: 6.6687121e+08 | F38: ='Evolutive SFP'!AH12+'Evolutive SFP'!AH13 -> 16246154 | G38: 1.3137319e+10
A39: Financial Investments | C39: 4680656000 | D39: 9.2582174e+08 | E39: 9.4784119e+08 | F39: ='Evolutive SFP'!AH8 -> 16246154 | G39: 2.2509396e+10
A40: Liquid Assets | C40: 1947404000 | D40: 6.2110949e+09 | E40: 5.1872997e+09 | F40: ='Evolutive SFP'!AH4+'Evolutive SFP'!AH11+'Evolutive SFP'!AH10+'Evolutive SFP'!AH9 -> 10271564 | G40: 6.0668383e+10
A41: Short-term Liabilities) | C41: 8573442000 | D41: 8.5346539e+09 | E41: 9.7605571e+09 | F41: ='Evolutive SFP'!AH29+'Evolutive SFP'!AH30+'Evolutive SFP'!AH33+'Evolutive SFP'!AH34+'Evolutive SFP'!AH35+'Evolutive SFP'!AH36+'Evolutive SFP'!AH37 -> 43698180 | G41: 1.1022553e+11
A42: External Borrowing | C42: 329468000 | D42: 0 | E42: 0 | F42: ='Evolutive SFP'!AH37 -> 0 | G42: 2.1483063e+10
A43: Average Gross Loans | C43: 24572016000 | D43: 2.585491e+10 | E43: 2.8116816e+10 | F43: =(C43+F32)/2 -> 12301002363 | G43: 3.9427965e+11
A44: Total Income | C44: 4601812000 | D44: 3.6674475e+09 | E44: 5.2364454e+09 | F44: ='Evolutitve SCI'!AG3 -> 9205405 | G44: 8.0901352e+10
A45: Net Financial Income/Loss | C45: 2290844000 | D45: 1.8229867e+09 | E45: 2.7434442e+09 | F45: ='Evolutitve SCI'!AG19 -> 5822724 | G45: 4.8226248e+10
A46: Dividends+Interest on Deposits | C46: 2262095000 | D46: 1.8188538e+09 | E46: 2.4652146e+09 | F46: ='Evolutitve SCI'!AG14+'Evolutitve SCI'!AG16 -> 44608 | G46: 2.5502023e+10
A47: Operating Expenses | C47: 1160634000 | D47: 9.2551333e+08 | E47: 1.2702431e+09 | F47: ='Evolutitve SCI'!AG23 -> 4580282 | G47: 2.5828431e+10
A48: Interest on Loan portfolio+Fees&Commission on Loan | C48: 3923914000 | D48: 3.1803174e+09 | E48: 4425053884 | F48: ='Evolutitve SCI'!AG4 -> 3214668 | G48: 6.8243292e+10
A49: Total Expenses | C49: 3471602000 | D49: 2.7699742e+09 | E49: 3.7632443e+09 | F49: ='Evolutitve SCI'!AG23+'Evolutitve SCI'!AG12 -> 7962963 | G49: 5.6759285e+10
A50: Net Income | C50: 848802000 | D50: 6.6165929e+08 | E50: 1.111223e+09 | F50: ='Evolutitve SCI'!AG37 -> 577800 | G50: 2.0058586e+10
A51: G. AREAS OF IMPROVEMENT/REGULATORY CONCERNS
A52: 1
A53: 2
A54: 3
A55: 4
A56: Prepared by:
A58: Checked by:
A60: Approved by:
A62: DISCLAIMER: This report is prepared based on information submitted by the Sacco as at the stated date and may change upon verification by the Authority.

Sheet FORM 4
D1: 42795
B2: CLASSIFICATION | C2: NO. OF A/Cs | D2: OUTSTANDING LOAN PORTFOLIO(Kshs) | E2: REQUIRED PROVISION | F2: REQUIRED PROVISION AMOUNT(Kshs)
B3: Performing | C3: 56175 | D3: 1.993701e+10 | E3: 0 | F3: =D3*E3 -> 0
B4: Watch | C4: 342 | D4: 6.0964609e+08 | E4: 0.05 | F4: =D4*E4 -> 30482304
B5: Substandard | C5: 721 | D5: 5.3176756e+08 | E5: 0.25 | F5: =D5*E5 -> 1.3294189e+08
B6: Doubtful | C6: 182 | D6: 1.3302199e+08 | E6: 0.5 | F6: =D6*E6 -> 66510994
B7: Loss | C7: 285 | D7: 53640300 | E7: 1 | F7: =D7*E7 -> 53640300
B8: subtotal | C8: =SUM(C3:C7) -> 57705 | D8: =SUM(D3:D7) -> 2.1265086e+10 | F8: =SUM(F3:F7) -> 2.8357549e+08
D10: 42887
B11: CLASSIFICATION | C11: NO. OF A/Cs | D11: OUTSTANDING LOAN PORTFOLIO(Kshs) | E11: REQUIRED PROVISION | F11: REQUIRED PROVISION AMOUNT(Kshs)
B12: Performing | C12: 52931 | D12: 2.0932769e+10 | E12: 0.01 | F12: =D12*E12 -> 2.0932769e+08
B13: Watch | C13: 1072 | D13: 6.9302846e+08 | E13: 0.05 | F13: =D13*E13 -> 34651423
B14: Substandard | C14: 237 | D14: 2.1101418e+08 | E14: 0.25 | F14: =D14*E14 -> 52753546
B15: Doubtful | C15: 75 | D15: 31560414 | E15: 0.5 | F15: =D15*E15 -> 15780207
B16: Loss | C16: 16 | D16: 4449341.3 | E16: 1 | F16: =D16*E16 -> 4449341.3
B17: subtotal | C17: =SUM(C12:C16) -> 54331 | D17: =SUM(D12:D16) -> 2.1872821e+10 | E17: 1.81 | F17: =SUM(F12:F16) -> 3.169622e+08
C18: NPL | D18: =SUM(D14:D16) -> 2.4702394e+08
C19: PAR | D19: =D18/D17 -> 0.011293648
D21: 42979
B22: CLASSIFICATION | C22: NO. OF A/Cs | D22: OUTSTANDING LOAN PORTFOLIO(Kshs) | E22: REQUIRED PROVISION | F22: REQUIRED PROVISION AMOUNT(Kshs)
B23: Performing | C23: 48840 | D23: 19551006671 | E23: 0.01
B24: Watch | C24: 2088 | D24: 1.0437061e+09 | E24: 0.05 | F24: =D24*E24 -> 52185307
B25: Substandard | C25: 4389 | D25: 1.5125185e+09 | E25: 0.25 | F25: =D25*E25 -> 3.7812962e+08
B26: Doubtful | C26: 927 | D26: 4.2115024e+08 | E26: 0.5 | F26: =D26*E26 -> 2.1057512e+08
B27: Loss | C27: 1102 | D27: 229316298 | E27: 1 | F27: =D27*E27 -> 229316298
B28: subtotal | C28: =SUM(C23:C27) -> 57346 | D28: =SUM(D23:D27) -> 2.2757698e+10 | F28: =SUM(F23:F27) -> 8.7020635e+08
C29: NPL | D29: =SUM(D25:D27) -> 2.162985e+09
C30: PAR | D30: =D29/D28 -> 0.095044105
D32: 43070
B33: CLASSIFICATION | C33: NO. OF A/Cs | D33: OUTSTANDING LOAN PORTFOLIO(Kshs) | E33: REQUIRED PROVISION | F33: REQUIRED PROVISION AMOUNT(Kshs)
B34: Performing | C34: 50625 | D34: 2.0056569e+10 | E34: 0 | F34: =D34*E34 -> 0
B35: Watch | C35: 1985 | D35: 817339191 | E35: 0.05 | F35: =D35*E35 -> 40866960
B36: Substandard | C36: 4389 | D36: 1.2107046e+09 | E36: 0.25 | F36: =D36*E36 -> 3.0267616e+08
B37: Doubtful | C37: 1012 | D37: 6.4041824e+08 | E37: 0.5 | F37: =D37*E37 -> 3.2020912e+08
B38: Loss | C38: 1121 | D38: 4.8124864e+08 | E38: 1 | F38: =D38*E38 -> 4.8124864e+08
B39: subtotal | C39: =SUM(C34:C38) -> 59132 | D39: =SUM(D34:D38) -> 2.320628e+10 | E39: 1.81 | F39: =SUM(F34:F38) -> 1.1450009e+09
C40: NPL | D40: =SUM(D36:D38) -> 2.3323715e+09
C41: PAR | D41: =D40/D39 -> 0.10050605
D43: Audited 2017
B44: CLASSIFICATION | C44: NO. OF A/Cs | D44: OUTSTANDING LOAN PORTFOLIO(Kshs) | E44: REQUIRED PROVISION | F44: REQUIRED PROVISION AMOUNT(Kshs)
B45: Performing | E45: 0 | F45: =D45*E45 -> 0
B46: Watch | E46: 0.05 | F46: 6739000
B47: Substandard | E47: 0.25 | F47: 54183000 | H47: =SUM(D47:D49)/D50 -> #DIV/0!
B48: Doubtful | E48: 0.5 | F48: 33315000
B49: Loss | E49: 1 | F49: 11377000
B50: subtotal | C50: =SUM(C45:C49) -> 0 | D50: =SUM(D45:D49) -> 0 | E50: 1.81 | F50: =SUM(F45:F49) -> 105614000
D53: 43160
B54: CLASSIFICATION | C54: NO. OF A/Cs | D54: OUTSTANDING LOAN PORTFOLIO(Kshs) | E54: REQUIRED PROVISION | F54: REQUIRED PROVISION AMOUNT(Kshs)
B55: Performing | C55: 47697 | D55: 2.1205447e+10 | E55: 0 | F55: =D55*E55 -> 0
B56: Watch | C56: 26917 | D56: 6.7933412e+08 | E56: 0.05 | F56: =D56*E56 -> 33966706
B57: Substandard | C57: 3726 | D57: 1.003759e+09 | E57: 0.25 | F57: =D57*E57 -> 2.5093975e+08
B58: Doubtful | C58: 2799 | D58: 3.4918089e+08 | E58: 0.5 | F58: =D58*E58 -> 1.7459044e+08
B59: Loss | C59: 1768 | D59: 2.9192251e+08 | E59: 1 | F59: =D59*E59 -> 2.9192251e+08
B60: subtotal | C60: 82907 | D60: 2.3529643e+10 | F60: =SUM(F55:F59) -> 7.5141941e+08 | H60: NPL | I60: =(D57+D58+D59)/D60 -> 0.069905965
D62: 43252
B63: CLASSIFICATION | C63: NO. OF A/Cs | D63: OUTSTANDING LOAN PORTFOLIO(Kshs) | E63: REQUIRED PROVISION | F63: REQUIRED PROVISION AMOUNT(Kshs)
B64: Performing | C64: 49406 | D64: 2.1905084e+10 | E64: 0.01
B65: Watch | C65: 3346 | D65: 6.4285512e+08 | E65: 0.05 | F65: =D65*E65 -> 32142756
B66: Substandard | C66: 4337 | D66: 9.8318969e+08 | E66: 0.25 | F66: =D66*E66 -> 2.4579742e+08
B67: Doubtful | C67: 1945 | D67: 2.0661378e+08 | E67: 0.5 | F67: =D67*E67 -> 1.0330689e+08
B68: Loss | C68: 2419 | D68: 3.5525437e+08 | E68: 1 | F68: =D68*E68 -> 3.5525437e+08
B69: subtotal | C69: =SUM(C64:C68) -> 61453 | D69: =SUM(D64:D68) -> 2.4092997e+10 | F69: =SUM(F64:F68) -> 7.3650143e+08 | H69: NPL | I69: =(D66+D67+D68)/D69 -> 0.064128919
C70: NPL | D70: =SUM(D66:D68) -> 1.5450578e+09
C71: PAR | D71: =D70/D69 -> 0.064128919
D73: 43344
B74: CLASSIFICATION | C74: NO. OF A/Cs | D74: OUTSTANDING LOAN PORTFOLIO(Kshs) | E74: REQUIRED PROVISION | F74: REQUIRED PROVISION AMOUNT(Kshs)
B75: Performing | C75: 52325 | D75: 2.3771723e+10 | E75: 0.01
B76: Watch | C76: 3425 | D76: 5.7053399e+08 | E76: 0.05 | F76: =D76*E76 -> 28526700
B77: Substandard | C77: 3825 | D77: 2.9021825e+08 | E77: 0.25 | F77: =D77*E77 -> 72554563
B78: Doubtful | C78: 1852 | D78: 27072771 | E78: 0.5 | F78: =D78*E78 -> 13536386
B79: Loss | C79: 2325 | D79: 1.5075147e+08 | E79: 1 | F79: =D79*E79 -> 1.5075147e+08
B80: subtotal | C80: 63752 | D80: 2.4810299e+10 | F80: =SUM(F75:F79) -> 2.6536911e+08 | H80: NPL | I80: =(D77+D78+D79)/D80 -> 0.018864847
C81: NPL | D81: =SUM(D77:D79) -> 4.6804249e+08
C82: PAR | D82: =D81/D80 -> 0.018864847
D84: 43435
B85: CLASSIFICATION | C85: NO. OF A/Cs | D85: OUTSTANDING LOAN PORTFOLIO(Kshs) | E85: REQUIRED PROVISION | F85: REQUIRED PROVISION AMOUNT(Kshs)
B86: Performing | E86: 0 | F86: =D86*E86 -> 0
B87: Watch | E87: 0.05 | F87: =D87*E87 -> 0
B88: Substandard | E88: 0.25 | F88: =D88*E88 -> 0
B89: Doubtful | E89: 0.5 | F89: =D89*E89 -> 0
B90: Loss | E90: 1 | F90: =D90*E90 -> 0
B91: subtotal | E91: 1.81 | F91: =SUM(F86:F90) -> 0 | H91: NPL | I91: =(D88+D89+D90)/D91 -> #DIV/0!
C92: NPL | D92: =SUM(D88:D90) -> 0
C93: PAR | D93: =D92/D91 -> #DIV/0!
D95: Audited 2018
B96: CLASSIFICATION | C96: NO. OF A/Cs | D96: OUTSTANDING LOAN PORTFOLIO(Kshs) | E96: REQUIRED PROVISION | F96: REQUIRED PROVISION AMOUNT(Kshs)
B97: Performing | C97: 61808 | D97: 23864790000 | E97: 0 | F97: =D97*E97 -> 0
B98: Watch | C98: 2558 | D98: 543816000 | E98: 0.05 | F98: 6739000
B99: Substandard | C99: 3972 | D99: 838253000 | E99: 0.25 | F99: 54183000
B100: Doubtful | C100: 2510 | D100: 373254000 | E100: 0.5 | F100: 33315000
B101: Loss | C101: 2139 | D101: 210209000 | E101: 1 | F101: 11377000
B102: subtotal | C102: =SUM(C97:C101) -> 72987 | D102: =SUM(D97:D101) -> 25830322000 | E102: 1.81 | F102: =SUM(F97:F101) -> 105614000 | H102: NPL | I102: =(D99+D100+D101)/D102 -> 0.055040584
C103: NPL | D103: =SUM(D99:D101) -> 1421716000
C104: PAR | D104: =D103/D102 -> 0.055040584
D107: 44075
B108: CLASSIFICATION | C108: NO. OF A/Cs | D108: OUTSTANDING LOAN PORTFOLIO(Kshs) | E108: REQUIRED PROVISION | F108: REQUIRED PROVISION AMOUNT(Kshs)
B109: Performing | C109: 56618 | D109: 3.1475041e+10 | E109: 0.01 | F109: =D109*E109 -> 3.1475041e+08
B110: Watch | C110: 2064 | D110: 4.7265764e+08 | E110: 0.05 | F110: =D110*E110 -> 23632882
B111: Substandard | C111: 4931 | D111: 8.0013981e+08 | E111: 0.25 | F111: =D111*E111 -> 2.0003495e+08
B112: Doubtful | C112: 2310 | D112: 1.3164484e+08 | E112: 0.5 | F112: =D112*E112 -> 65822422
...

Sheet CAELS
A1: STIMA SACCO 2017 CAELS
D2: 2013 Audited | E2: 2014 Audited | F2: 2015 Audited | G2: 2016 Audited | H2: 42736 | I2: 42767 | J2: 42795 | K2: 42826 | L2: 42856 | M2: 42887 | N2: 42917 | O2: 42948 | P2: 42979 | Q2: 43009 | R2: 43040 | S2: 43070 | T2: Audited 2017 | U2: 43101 | V2: 43132 | W2: 43160 | X2: 43191 | Y2: 43221 | Z2: 43252 | AA2: 43282 | AB2: 43313 | AC2: 43344 | AD2: 43374 | AE2: 43405 | AF2: 43435 | AG2: Audited 2018 | AH2: 43466 | AI2: 43497 | AJ2: 43525 | AK2: 43556 | AL2: 43586 | AM2: 43617 | AN2: 43647 | AO2: 43678 | AP2: 43709 | AQ2: 43739 | AR2: 43770 | AS2: 43800 | AT2: Audited 2019 | AU2: 43831 | AV2: 43862 | AW2: 43891 | AX2: 43922 | AY2: 43952 | AZ2: 43983 | BA2: 44013 | BB2: 44044 | BC2: 44075 | BD2: 44105 | BE2: 44136 | BF2: 44166 | BG2: 44197 | BH2: 44228 | BI2: 44256 | BJ2: 44287 | BK2: 44317 | BL2: 44348 | BM2: 44378 | BN2: 44409 | BO2: 44440 | BP2: 44470 | BQ2: 44501 | BR2: 44531 | BS2: 44562 | BT2: 44593 | BU2: 44621 | BV2: 44652 | BW2: 44682 | BX2: 44713 | BY2: 44743 | BZ2: 44774 | CA2: 44805 | CB2: 44835 | CC2: 44866 | CD2: 44896 | CE2: Audited 2022 | CF2: 44927 | CG2: 44958 | CH2: 44986 | CI2: 45017 | CJ2: 45047 | CK2: 45078 | CL2: 45108 | CM2: 45139 | CN2: 45170
A3: CAPITAL ADEQUACY | B3: Core Capital | C3: 10 M | D3: =(('Evolutive SFP'!#REF!+'Evolutive SFP'!#REF!+'Evolutive SFP'!#REF!+'Evolutive SFP'!#REF!+'Evolutive SFP'!#REF!+'Evolutive SFP'!#REF!)-'Evolutive SFP'!#REF!)/1000000 -> #REF! | E3: =(('Evolutive SFP'!#REF!+'Evolutive SFP'!#REF!+'Evolutive SFP'!#REF!+'Evolutive SFP'!#REF!+'Evolutive SFP'!#REF!+'Evolutive SFP'!#REF!)-'Evolutive SFP'!#REF!)/1000000 -> #REF! | F3: =(('Evolutive SFP'!#REF!+'Evolutive SFP'!#REF!+'Evolutive SFP'!#REF!+'Evolutive SFP'!#REF!+'Evolutive SFP'!#REF!+'Evolutive SFP'!#REF!)-'Evolutive SFP'!#REF!)/1000000 -> #REF! | G3: =(('Evolutive SFP'!#REF!+'Evolutive SFP'!#REF!+'Evolutive SFP'!#REF!+'Evolutive SFP'!#REF!+'Evolutive SFP'!#REF!+'Evolutive SFP'!#REF!)-'Evolutive SFP'!#REF!)/1000000 -> #REF! | H3: =(('Evolutive SFP'!#REF!+'Evolutive SFP'!#REF!+'Evolutive SFP'!#REF!+'Evolutive SFP'!#REF!+'Evolutive SFP'!#REF!+'Evolutive SFP'!#REF!)-'Evolutive SFP'!#REF!)/1000000 -> #REF! | I3: =(('Evolutive SFP'!#REF!+'Evolutive SFP'!#REF!+'Evolutive SFP'!#REF!+'Evolutive SFP'!#REF!+'Evolutive SFP'!#REF!+'Evolutive SFP'!#REF!)-'Evolutive SFP'!#REF!)/1000000 -> #REF! | J3: =(('Evolutive SFP'!#REF!+'Evolutive SFP'!#REF!+'Evolutive SFP'!#REF!+'Evolutive SFP'!#REF!+'Evolutive SFP'!#REF!+'Evolutive SFP'!#REF!)-'Evolutive SFP'!#REF!)/1000000 -> #REF! | K3: =(('Evolutive SFP'!#REF!+'Evolutive SFP'!#REF!+'Evolutive SFP'!#REF!+'Evolutive SFP'!#REF!+'Evolutive SFP'!#REF!+'Evolutive SFP'!#REF!)-'Evolutive SFP'!#REF!)/1000000 -> #REF! | ... AS3: =(('Evolutive SFP'!#REF!+'Evolutive SFP'!#REF!+'Evolutive SFP'!#REF!+'Evolutive SFP'!#REF!+'Evolutive SFP'!#REF!+'Evolutive SFP'!#REF!)-'Evolutive SFP'!#REF!)/1000000 -> #REF! | AT3: =(('Evolutive SFP'!AH39+'Evolutive SFP'!AH40+'Evolutive SFP'!AH41+'Evolutive SFP'!AH42+'Evolutive SFP'!AH43+'Evolutive SFP'!AH44)-'Evolutive SFP'!AH10)/1000000 -> 18.417388 | AU3: =(('Evolutive SFP'!AI39+'Evolutive SFP'!AI40+'Evolutive SFP'!AI41+'Evolutive SFP'!AI42+'Evolutive SFP'!AI43+'Evolutive SFP'!AI44)-'Evolutive SFP'!AI10)/1000000 -> 18.374324 | AV3: =(('Evolutive SFP'!AJ39+'Evolutive SFP'!AJ40+'Evolutive SFP'!AJ41+'Evolutive SFP'!AJ42+'Evolutive SFP'!AJ43+'Evolutive SFP'!AJ44)-'Evolutive SFP'!AJ10)/1000000 -> 18.72238 | AW3: =(('Evolutive SFP'!AK39+'Evolutive SFP'!AK40+'Evolutive SFP'!AK41+'Evolutive SFP'!AK42+'Evolutive SFP'!AK43+'Evolutive SFP'!AK44)-'Evolutive SFP'!AK10)/1000000 -> 19.858144 | AX3: =(('Evolutive SFP'!AL39+'Evolutive SFP'!AL40+'Evolutive SFP'!AL41+'Evolutive SFP'!AL42+'Evolutive SFP'!AL43+'Evolutive SFP'!AL44)-'Evolutive SFP'!AL10)/1000000 -> 20.201076 | AY3: =(('Evolutive SFP'!AM39+'Evolutive SFP'!AM40+'Evolutive SFP'!AM41+'Evolutive SFP'!AM42+'Evolutive SFP'!AM43+'Evolutive SFP'!AM44)-'Evolutive SFP'!AM10)/1000000 -> 20.684643 | AZ3: =(('Evolutive SFP'!AN39+'Evolutive SFP'!AN40+'Evolutive SFP'!AN41+'Evolutive SFP'!AN42+'Evolutive SFP'!AN43+'Evolutive SFP'!AN44)-'Evolutive SFP'!AN10)/1000000 -> 21.140937 | BA3: =(('Evolutive SFP'!#REF!+'Evolutive SFP'!#REF!+'Evolutive SFP'!#REF!+'Evolutive SFP'!#REF!+'Evolutive SFP'!#REF!+'Evolutive SFP'!#REF!)-'Evolutive SFP'!#REF!)/1000000 -> #REF! | BB3: =(('Evolutive SFP'!AO39+'Evolutive SFP'!AO40+'Evolutive SFP'!AO41+'Evolutive SFP'!AO42+'Evolutive SFP'!AO43+'Evolutive SFP'!AO44)-'Evolutive SFP'!AO10)/1000000 -> 22.281501 | BC3: =(('Evolutive SFP'!AP39+'Evolutive SFP'!AP40+'Evolutive SFP'!AP41+'Evolutive SFP'!AP42+'Evolutive SFP'!AP43+'Evolutive SFP'!AP44)-'Evolutive SFP'!AP10)/1000000 -> 22.716745 | BD3: =(('Evolutive SFP'!AQ39+'Evolutive SFP'!AQ40+'Evolutive SFP'!AQ41+'Evolutive SFP'!AQ42+'Evolutive SFP'!AQ43+'Evolutive SFP'!AQ44)-'Evolutive SFP'!AQ10)/1000000 -> 23.279858 | BE3: =(('Evolutive SFP'!AR39+'Evolutive SFP'!AR40+'Evolutive SFP'!AR41+'Evolutive SFP'!AR42+'Evolutive SFP'!AR43+'Evolutive SFP'!AR44)-'Evolutive SFP'!AR10)/1000000 -> 23.667943 | BF3: =(('Evolutive SFP'!AS39+'Evolutive SFP'!AS40+'Evolutive SFP'!AS41+'Evolutive SFP'!AS42+'Evolutive SFP'!AS43+'Evolutive SFP'!AS44)-'Evolutive SFP'!AS10)/1000000 -> 23.4189 | BG3: =(('Evolutive SFP'!AT39+'Evolutive SFP'!AT40+'Evolutive SFP'!AT41+'Evolutive SFP'!AT42+'Evolutive SFP'!AT43+'Evolutive SFP'!AT44)-'Evolutive SFP'!AT10)/1000000 -> 18.862417 | BH3: =(('Evolutive SFP'!AU39+'Evolutive SFP'!AU40+'Evolutive SFP'!AU41+'Evolutive SFP'!AU42+'Evolutive SFP'!AU43+'Evolutive SFP'!AU44)-'Evolutive SFP'!AU10)/1000000 -> 18.665719 | BI3: =(('Evolutive SFP'!AV39+'Evolutive SFP'!AV40+'Evolutive SFP'!AV41+'Evolutive SFP'!AV42+'Evolutive SFP'!AV43+'Evolutive SFP'!AV44)-'Evolutive SFP'!AV10)/1000000 -> 18.862713 | ... CN3: =(('Evolutive SFP'!CA39+'Evolutive SFP'!CA40+'Evolutive SFP'!CA41+'Evolutive SFP'!CA42+'Evolutive SFP'!CA43+'Evolutive SFP'!CA44)-'Evolutive SFP'!CA10)/1000000 -> 24.870735
B4: CCA | C4: Min 10% | D4: =D3/(('Evolutive SFP'!#REF!)/1000000) -> #REF! | E4: =E3/(('Evolutive SFP'!#REF!)/1000000) -> #REF! | F4: =F3/(('Evolutive SFP'!#REF!)/1000000) -> #REF! | G4: =G3/(('Evolutive SFP'!#REF!)/1000000) -> #REF! | H4: =H3/(('Evolutive SFP'!#REF!)/1000000) -> #REF! | I4: =I3/(('Evolutive SFP'!#REF!)/1000000) -> #REF! | J4: =J3/(('Evolutive SFP'!#REF!)/1000000) -> #REF! | K4: =K3/(('Evolutive SFP'!#REF!)/1000000) -> #REF! | ... AS4: =AS3/(('Evolutive SFP'!#REF!)/1000000) -> #REF! | AT4: =AT3/(('Evolutive SFP'!AH27)/1000000) -> 0.25860051 | AU4: =AU3/(('Evolutive SFP'!AI27)/1000000) -> 0.23798437 | AV4: =AV3/(('Evolutive SFP'!AJ27)/1000000) -> 0.23660179 | AW4: =AW3/(('Evolutive SFP'!AK27)/1000000) -> 0.25970651 | AX4: =AX3/(('Evolutive SFP'!AL27)/1000000) -> 0.26375246 | AY4: =AY3/(('Evolutive SFP'!AM27)/1000000) -> 0.26270778 | AZ4: =AZ3/(('Evolutive SFP'!AN27)/1000000) -> 0.27087994 | BA4: =BA3/(('Evolutive SFP'!#REF!)/1000000) -> #REF! | BB4: =BB3/(('Evolutive SFP'!AO27)/1000000) -> 0.27864182 | BC4: =BC3/(('Evolutive SFP'!AP27)/1000000) -> 0.28519856 | BD4: =BD3/(('Evolutive SFP'!AQ27)/1000000) -> 0.30255989 | BE4: =BE3/(('Evolutive SFP'!AR27)/1000000) -> 0.29786926 | BF4: =BF3/(('Evolutive SFP'!AS27)/1000000) -> 0.31491906 | BG4: =BG3/(('Evolutive SFP'!AT27)/1000000) -> 0.25369579 | BH4: =BH3/(('Evolutive SFP'!AU27)/1000000) -> 0.25349227 | BI4: =BI3/(('Evolutive SFP'!AV27)/1000000) -> 0.25557709 | ... CN4: =CN3/(('Evolutive SFP'!CA27)/1000000) -> 0.31852281
B5: CCD | C5: Min 8% | D5: =D3/('Evolutive SFP'!#REF!/1000000) -> #REF! | E5: =E3/('Evolutive SFP'!#REF!/1000000) -> #REF! | F5: =F3/('Evolutive SFP'!#REF!/1000000) -> #REF! | G5: =G3/('Evolutive SFP'!#REF!/1000000) -> #REF! | H5: =H3/('Evolutive SFP'!#REF!/1000000) -> #REF! | I5: =I3/('Evolutive SFP'!#REF!/1000000) -> #REF! | J5: =J3/('Evolutive SFP'!#REF!/1000000) -> #REF! | K5: =K3/('Evolutive SFP'!#REF!/1000000) -> #REF! | ... AS5: =AS3/('Evolutive SFP'!#REF!/1000000) -> #REF! | AT5: =AT3/('Evolutive SFP'!AH31/1000000) -> 0.38519392 | AU5: =AU3/('Evolutive SFP'!AI31/1000000) -> 0.36711732 | AV5: =AV3/('Evolutive SFP'!AJ31/1000000) -> 0.3628735 | AW5: =AW3/('Evolutive SFP'!AK31/1000000) -> 0.4084564 | AX5: =AX3/('Evolutive SFP'!AL31/1000000) -> 0.39778282 | AY5: =AY3/('Evolutive SFP'!AM31/1000000) -> 0.3927172 | AZ5: =AZ3/('Evolutive SFP'!AN31/1000000) -> 0.41017253 | BA5: =BA3/('Evolutive SFP'!#REF!/1000000) -> #REF! | BB5: =BB3/('Evolutive SFP'!AO31/1000000) -> 0.42148325 | BC5: =BC3/('Evolutive SFP'!AP31/1000000) -> 0.43323083 | BD5: =BD3/('Evolutive SFP'!AQ31/1000000) -> 0.4417697 | BE5: =BE3/('Evolutive SFP'!AR31/1000000) -> 0.43129257 | BF5: =BF3/('Evolutive SFP'!AS31/1000000) -> 0.47461348 | BG5: =BG3/('Evolutive SFP'!AT31/1000000) -> 0.38227062 | BH5: =BH3/('Evolutive SFP'!AU31/1000000) -> 0.38041838 | BI5: =BI3/('Evolutive SFP'!AV31/1000000) -> 0.38609513 | ... CN5: =CN3/('Evolutive SFP'!CA31/1000000) -> 0.47123431
B6: ICA | C6: Min 8% | D6: =((D3*1000000)-'Evolutive SFP'!#REF!)/'Evolutive SFP'!#REF! -> #REF! | E6: =((E3*1000000)-'Evolutive SFP'!#REF!)/'Evolutive SFP'!#REF! -> #REF! | F6: =((F3*1000000)-'Evolutive SFP'!#REF!)/'Evolutive SFP'!#REF! -> #REF! | G6: =((G3*1000000)-'Evolutive SFP'!#REF!)/'Evolutive SFP'!#REF! -> #REF! | H6: =((H3*1000000)-'Evolutive SFP'!#REF!)/'Evolutive SFP'!#REF! -> #REF! | I6: =((I3*1000000)-'Evolutive SFP'!#REF!)/'Evolutive SFP'!#REF! -> #REF! | J6: =((J3*1000000)-'Evolutive SFP'!#REF!)/'Evolutive SFP'!#REF! -> #REF! | K6: =((K3*1000000)-'Evolutive SFP'!#REF!)/'Evolutive SFP'!#REF! -> #REF! | ... AS6: =((AS3*1000000)-'Evolutive SFP'!#REF!)/'Evolutive SFP'!#REF! -> #REF! | AT6: =((AT3*1000000)-'Evolutive SFP'!AH39)/'Evolutive SFP'!AH27 -> 0.076538578 | AU6: =((AU3*1000000)-'Evolutive SFP'!AI39)/'Evolutive SFP'!AI27 -> 0.069981925 | AV6: =((AV3*1000000)-'Evolutive SFP'!AJ39)/'Evolutive SFP'!AJ27 -> 0.072655166 | AW6: =((AW3*1000000)-'Evolutive SFP'!AK39)/'Evolutive SFP'!AK27 -> 0.090029441 | AX6: =((AX3*1000000)-'Evolutive SFP'!AL39)/'Evolutive SFP'!AL27 -> 0.094337721 | AY6: =((AY3*1000000)-'Evolutive SFP'!AM39)/'Evolutive SFP'!AM27 -> 0.097889908 | AZ6: =((AZ3*1000000)-'Evolutive SFP'!AN39)/'Evolutive SFP'!AN27 -> 0.10457923 | BA6: =((BA3*1000000)-'Evolutive SFP'!#REF!)/'Evolutive SFP'!#REF! -> #REF! | BB6: =((BB3*1000000)-'Evolutive SFP'!AO39)/'Evolutive SFP'!AO27 -> 0.11475889 | BC6: =((BC3*1000000)-'Evolutive SFP'!AP39)/'Evolutive SFP'!AP27 -> 0.12065428 | BD6: =((BD3*1000000)-'Evolutive SFP'!AQ39)/'Evolutive SFP'!AQ27 -> 0.13218899 | BE6: =((BE3*1000000)-'Evolutive SFP'!AR39)/'Evolutive SFP'!AR27 -> 0.13287104 | BF6: =((BF3*1000000)-'Evolutive SFP'!AS39)/'Evolutive SFP'!AS27 -> 0.13859047 | BG6: =((BG3*1000000)-'Evolutive SFP'!AT39)/'Evolutive SFP'!AT27 -> 0.077333312 | BH6: =((BH3*1000000)-'Evolutive SFP'!AU39)/'Evolutive SFP'!AU27 -> 0.075414262 | BI6: =((BI3*1000000)-'Evolutive SFP'!AV39)/'Evolutive SFP'!AV27 -> 0.077896019 | ... CN6: =((CN3*1000000)-'Evolutive SFP'!CA39)/'Evolutive SFP'!CA27 -> 0.14703591
A7: ASSET QUALITY | B7: A/LNPL30 | F7: 0.36 | G7: 0.52149977 | J7: ='Evolutive SFP'!#REF!/('FORM 4'!D5+'FORM 4'!D6+'FORM 4'!D7) -> #REF! | M7: ='Evolutive SFP'!#REF!/('FORM 4'!D14+'FORM 4'!D15+'FORM 4'!D16) -> #REF! | P7: ='Evolutive SFP'!#REF!/('FORM 4'!D25+'FORM 4'!D26+'FORM 4'!D27) -> #REF! | S7: ='Evolutive SFP'!#REF!/('FORM 4'!D36+'FORM 4'!D37+'FORM 4'!D38) -> #REF! | T7: ='Evolutive SFP'!#REF!/('FORM 4'!E36+'FORM 4'!E37+'FORM 4'!E38) -> #REF! | U7: ='Evolutive SFP'!#REF!/('FORM 4'!F36+'FORM 4'!F37+'FORM 4'!F38) -> #REF! | V7: ='Evolutive SFP'!#REF!/('FORM 4'!G36+'FORM 4'!G37+'FORM 4'!G38) -> #REF! | W7: ='Evolutive SFP'!#REF!/('FORM 4'!H36+'FORM 4'!H37+'FORM 4'!H38) -> #REF! | X7: ='Evolutive SFP'!#REF!/('FORM 4'!I36+'FORM 4'!I37+'FORM 4'!I38) -> #REF! | Y7: ='Evolutive SFP'!#REF!/('FORM 4'!J36+'FORM 4'!J37+'FORM 4'!J38) -> #REF! | Z7: ='Evolutive SFP'!#REF!/('FORM 4'!#REF!+'FORM 4'!#REF!+'FORM 4'!#REF!) -> #REF! | AA7: ='Evolutive SFP'!#REF!/('FORM 4'!K36+'FORM 4'!K37+'FORM 4'!K38) -> #REF! | AB7: ='Evolutive SFP'!#REF!/('FORM 4'!L36+'FORM 4'!L37+'FORM 4'!L38) -> #REF! | AC7: ='Evolutive SFP'!#REF!/('FORM 4'!M36+'FORM 4'!M37+'FORM 4'!M38) -> #REF! | AD7: ='Evolutive SFP'!#REF!/('FORM 4'!N36+'FORM 4'!N37+'FORM 4'!N38) -> #REF! | AE7: ='Evolutive SFP'!#REF!/('FORM 4'!O36+'FORM 4'!O37+'FORM 4'!O38) -> #REF! | AF7: ='Evolutive SFP'!#REF!/('FORM 4'!P36+'FORM 4'!P37+'FORM 4'!P38) -> #REF! | AG7: ='Evolutive SFP'!#REF!/('FORM 4'!Q36+'FORM 4'!Q37+'FORM 4'!Q38) -> #REF! | AH7: ='Evolutive SFP'!#REF!/('FORM 4'!R36+'FORM 4'!R37+'FORM 4'!R38) -> #REF! | ... AP7: ='Evolutive SFP'!#REF!/('FORM 4'!Z36+'FORM 4'!Z37+'FORM 4'!Z38) -> #REF!
B8: NPL30 | F8: 0.02 | G8: 0.051294614 | J8: =('FORM 4'!D5+'FORM 4'!D6+'FORM 4'!D7)/'Evolutive SFP'!#REF! -> #REF! | M8: =('FORM 4'!D14+'FORM 4'!D15+'FORM 4'!D16)/'Evolutive SFP'!#REF! -> #REF! | P8: =('FORM 4'!D25+'FORM 4'!D26+'FORM 4'!D27)/'Evolutive SFP'!#REF! -> #REF! | S8: =('FORM 4'!D36+'FORM 4'!D37+'FORM 4'!D38)/'Evolutive SFP'!#REF! -> #REF! | T8: =('FORM 4'!E36+'FORM 4'!E37+'FORM 4'!E38)/'Evolutive SFP'!#REF! -> #REF! | U8: =('FORM 4'!F36+'FORM 4'!F37+'FORM 4'!F38)/'Evolutive SFP'!#REF! -> #REF! | V8: =('FORM 4'!G36+'FORM 4'!G37+'FORM 4'!G38)/'Evolutive SFP'!#REF! -> #REF! | W8: =('FORM 4'!H36+'FORM 4'!H37+'FORM 4'!H38)/'Evolutive SFP'!#REF! -> #REF! | X8: =('FORM 4'!I36+'FORM 4'!I37+'FORM 4'!I38)/'Evolutive SFP'!#REF! -> #REF! | Y8: =('FORM 4'!J36+'FORM 4'!J37+'FORM 4'!J38)/'Evolutive SFP'!#REF! -> #REF! | Z8: =('FORM 4'!#REF!+'FORM 4'!#REF!+'FORM 4'!#REF!)/'Evolutive SFP'!#REF! -> #REF! | AA8: =('FORM 4'!K36+'FORM 4'!K37+'FORM 4'!K38)/'Evolutive SFP'!#REF! -> #REF! | AB8: =('FORM 4'!L36+'FORM 4'!L37+'FORM 4'!L38)/'Evolutive SFP'!#REF! -> #REF! | AC8: =('FORM 4'!M36+'FORM 4'!M37+'FORM 4'!M38)/'Evolutive SFP'!#REF! -> #REF! | AD8: =('FORM 4'!N36+'FORM 4'!N37+'FORM 4'!N38)/'Evolutive SFP'!#REF! -> #REF! | AE8: =('FORM 4'!O36+'FORM 4'!O37+'FORM 4'!O38)/'Evolutive SFP'!#REF! -> #REF! | AF8: =('FORM 4'!P36+'FORM 4'!P37+'FORM 4'!P38)/'Evolutive SFP'!#REF! -> #REF! | AG8: =('FORM 4'!Q36+'FORM 4'!Q37+'FORM 4'!Q38)/'Evolutive SFP'!#REF! -> #REF! | AH8: =('FORM 4'!R36+'FORM 4'!R37+'FORM 4'!R38)/'Evolutive SFP'!#REF! -> #REF! | ... AS8: =('FORM 4'!AC36+'FORM 4'!AC37+'FORM 4'!AC38)/'Evolutive SFP'!#REF! -> #REF! | AT8: =('FORM 4'!AD36+'FORM 4'!AD37+'FORM 4'!AD38)/'Evolutive SFP'!AH15 -> 0 | AU8: =('FORM 4'!AE36+'FORM 4'!AE37+'FORM 4'!AE38)/'Evolutive SFP'!AI15 -> 0 | AV8: =('FORM 4'!AF36+'FORM 4'!AF37+'FORM 4'!AF38)/'Evolutive SFP'!AJ15 -> 0 | AW8: =('FORM 4'!AG36+'FORM 4'!AG37+'FORM 4'!AG38)/'Evolutive SFP'!AK15 -> 0 | AX8: =('FORM 4'!AH36+'FORM 4'!AH37+'FORM 4'!AH38)/'Evolutive SFP'!AL15 -> 0 | AY8: =('FORM 4'!AI36+'FORM 4'!AI37+'FORM 4'!AI38)/'Evolutive SFP'!AM15 -> 0 | AZ8: =('FORM 4'!AJ36+'FORM 4'!AJ37+'FORM 4'!AJ38)/'Evolutive SFP'!AN15 -> 0 | BA8: =('FORM 4'!AK36+'FORM 4'!AK37+'FORM 4'!AK38)/'Evolutive SFP'!#REF! -> #REF! | BB8: =('FORM 4'!AL36+'FORM 4'!AL37+'FORM 4'!AL38)/'Evolutive SFP'!AO15 -> 0 | BC8: =('FORM 4'!AM36+'FORM 4'!AM37+'FORM 4'!AM38)/'Evolutive SFP'!AP15 -> 0 | BD8: =('FORM 4'!AN36+'FORM 4'!AN37+'FORM 4'!AN38)/'Evolutive SFP'!AQ15 -> 0 | BE8: =('FORM 4'!AO36+'FORM 4'!AO37+'FORM 4'!AO38)/'Evolutive SFP'!AR15 -> 0 | BF8: =('FORM 4'!AP36+'FORM 4'!AP37+'FORM 4'!AP38)/'Evolutive SFP'!AS15 -> 0 | BG8: =('FORM 4'!AQ36+'FORM 4'!AQ37+'FORM 4'!AQ38)/'Evolutive SFP'!AT15 -> 0 | BH8: =('FORM 4'!AR36+'FORM 4'!AR37+'FORM 4'!AR38)/'Evolutive SFP'!AU15 -> 0 | BI8: =('FORM 4'!AS36+'FORM 4'!AS37+'FORM 4'!AS38)/'Evolutive SFP'!AV15 -> 0 | ... CN8: =('FORM 4'!BX36+'FORM 4'!BX37+'FORM 4'!BX38)/'Evolutive SFP'!CA15 -> 0
A9: EARNINGS | B9: ROA | E9: ='Evolutitve SCI'!#REF!/(('Evolutive SFP'!#REF!+'Evolutive SFP'!#REF!)/2) -> #REF! | H9: ='Evolutitve SCI'!#REF!/(('Evolutive SFP'!#REF!+'Evolutive SFP'!#REF!)/2) -> #REF! | I9: ='Evolutitve SCI'!#REF!/(('Evolutive SFP'!#REF!+'Evolutive SFP'!#REF!)/2) -> #REF! | J9: ='Evolutitve SCI'!#REF!/(('Evolutive SFP'!#REF!+'Evolutive SFP'!#REF!)/2) -> #REF! | K9: ='Evolutitve SCI'!#REF!/(('Evolutive SFP'!#REF!+'Evolutive SFP'!#REF!)/2) -> #REF! | L9: ='Evolutitve SCI'!#REF!/(('Evolutive SFP'!#REF!+'Evolutive SFP'!#REF!)/2) -> #REF! | M9: ='Evolutitve SCI'!#REF!/(('Evolutive SFP'!#REF!+'Evolutive SFP'!#REF!)/2) -> #REF! | N9: ='Evolutitve SCI'!#REF!/(('Evolutive SFP'!#REF!+'Evolutive SFP'!#REF!)/2) -> #REF! | O9: ='Evolutitve SCI'!#REF!/(('Evolutive SFP'!#REF!+'Evolutive SFP'!#REF!)/2) -> #REF! | ... AS9: ='Evolutitve SCI'!#REF!/(('Evolutive SFP'!#REF!+'Evolutive SFP'!#REF!)/2) -> #REF! | AT9: ='Evolutitve SCI'!AG33/(('Evolutive SFP'!#REF!+'Evolutive SFP'!AH27)/2) -> #REF! | AU9: ='Evolutitve SCI'!AH33/(('Evolutive SFP'!AH27+'Evolutive SFP'!AI27)/2) -> 0.0053262894 | AV9: ='Evolutitve SCI'!AI33/(('Evolutive SFP'!AI27+'Evolutive SFP'!AJ27)/2) -> 0.0090376944 | AW9: ='Evolutitve SCI'!AJ33/(('Evolutive SFP'!AJ27+'Evolutive SFP'!AK27)/2) -> 0.014995823 | AX9: ='Evolutitve SCI'!AK33/(('Evolutive SFP'!AK27+'Evolutive SFP'!AL27)/2) -> 0.017583261 | AY9: ='Evolutitve SCI'!AL33/(('Evolutive SFP'!AL27+'Evolutive SFP'!AM27)/2) -> 0.022245467 | AZ9: ='Evolutitve SCI'!AM33/(('Evolutive SFP'!AM27+'Evolutive SFP'!AN27)/2) -> 0.026197248 | BA9: ='Evolutitve SCI'!#REF!/(('Evolutive SFP'!AN27+'Evolutive SFP'!#REF!)/2) -> #REF! | BB9: ='Evolutitve SCI'!AN33/(('Evolutive SFP'!#REF!+'Evolutive SFP'!AO27)/2) -> #REF! | BC9: ='Evolutitve SCI'!AO33/(('Evolutive SFP'!AO27+'Evolutive SFP'!AP27)/2) -> 0.040804042 | BD9: ='Evolutitve SCI'!AP33/(('Evolutive SFP'!AP27+'Evolutive SFP'!AQ27)/2) -> 0.047714678 | BE9: ='Evolutitve SCI'!AQ33/(('Evolutive SFP'!AQ27+'Evolutive SFP'!AR27)/2) -> 0.04949761 | BF9: ='Evolutitve SCI'!AR33/(('Evolutive SFP'!AR27+'Evolutive SFP'!AS27)/2) -> 0.050703539 | BG9: ='Evolutitve SCI'!AS33/(('Evolutive SFP'!AS27+'Evolutive SFP'!AT27)/2) -> 0.0098926302 | BH9: ='Evolutitve SCI'!AT33/(('Evolutive SFP'!AT27+'Evolutive SFP'!AU27)/2) -> 0.00057705695 | BI9: ='Evolutitve SCI'!AU33/(('Evolutive SFP'!AU27+'Evolutive SFP'!AV27)/2) -> 0.0030320699 | BJ9: ='Evolutitve SCI'!AV33/(('Evolutive SFP'!AV27+'Evolutive SFP'!AW27)/2) -> 0.0093416352 | ... CN9: ='Evolutitve SCI'!BZ33/(('Evolutive SFP'!BZ27+'Evolutive SFP'!CA27)/2) -> 0.044328246
B10: Cost Income ratio | D10: ='Evolutitve SCI'!#REF!/'Evolutitve SCI'!#REF! -> #REF! | E10: ='Evolutitve SCI'!#REF!/'Evolutitve SCI'!#REF! -> #REF! | F10: ='Evolutitve SCI'!#REF!/'Evolutitve SCI'!#REF! -> #REF! | G10: ='Evolutitve SCI'!#REF!/'Evolutitve SCI'!#REF! -> #REF! | H10: ='Evolutitve SCI'!#REF!/'Evolutitve SCI'!#REF! -> #REF! | I10: ='Evolutitve SCI'!#REF!/'Evolutitve SCI'!#REF! -> #REF! | J10: ='Evolutitve SCI'!#REF!/'Evolutitve SCI'!#REF! -> #REF! | K10: ='Evolutitve SCI'!#REF!/'Evolutitve SCI'!#REF! -> #REF! | ... AS10: ='Evolutitve SCI'!#REF!/'Evolutitve SCI'!#REF! -> #REF! | AT10: ='Evolutitve SCI'!AG23/'Evolutitve SCI'!AG19 -> 0.78662186 | AU10: ='Evolutitve SCI'!AH23/'Evolutitve SCI'!AH19 -> 0.32601169 | AV10: ='Evolutitve SCI'!AI23/'Evolutitve SCI'!AI19 -> 0.40544053 | AW10: ='Evolutitve SCI'!AJ23/'Evolutitve SCI'!AJ19 -> 0.3911736 | AX10: ='Evolutitve SCI'!AK23/'Evolutitve SCI'!AK19 -> 0.4207911 | AY10: ='Evolutitve SCI'!AL23/'Evolutitve SCI'!AL19 -> 0.40257852 | AZ10: ='Evolutitve SCI'!AM23/'Evolutitve SCI'!AM19 -> 0.39618535 | BA10: ='Evolutitve SCI'!#REF!/'Evolutitve SCI'!#REF! -> #REF! | BB10: ='Evolutitve SCI'!AN23/'Evolutitve SCI'!AN19 -> 0.37680507 | BC10: ='Evolutitve SCI'!AO23/'Evolutitve SCI'!AO19 -> 0.37270233 | BD10: ='Evolutitve SCI'!AP23/'Evolutitve SCI'!AP19 -> 0.36334408 | BE10: ='Evolutitve SCI'!AQ23/'Evolutitve SCI'!AQ19 -> 0.40238992 | BF10: ='Evolutitve SCI'!AR23/'Evolutitve SCI'!AR19 -> 0.42015032 | BG10: ='Evolutitve SCI'!AS23/'Evolutitve SCI'!AS19 -> 0.75027049 | BH10: ='Evolutitve SCI'!AT23/'Evolutitve SCI'!AT19 -> 0.78978995 | BI10: ='Evolutitve SCI'!AU23/'Evolutitve SCI'!AU19 -> 0.68863062 | ... CN10: ='Evolutitve SCI'!BZ23/'Evolutitve SCI'!BZ19 -> 0.48360765
B11: Operating Expense ratio | D11: =('Evolutitve SCI'!#REF!+'Evolutitve SCI'!#REF!)/(('Evolutive SFP'!#REF!+'Evolutive SFP'!#REF!)/2) -> #REF! | E11: =('Evolutitve SCI'!#REF!+'Evolutitve SCI'!#REF!)/(('Evolutive SFP'!#REF!+'Evolutive SFP'!#REF!)/2) -> #REF! | F11: =('Evolutitve SCI'!#REF!+'Evolutitve SCI'!#REF!)/(('Evolutive SFP'!#REF!+'Evolutive SFP'!#REF!)/2) -> #REF! | G11: =('Evolutitve SCI'!#REF!+'Evolutitve SCI'!#REF!)/(('Evolutive SFP'!#REF!+'Evolutive SFP'!#REF!)/2) -> #REF! | H11: =('Evolutitve SCI'!#REF!+'Evolutitve SCI'!#REF!)/(('Evolutive SFP'!#REF!+'Evolutive SFP'!#REF!)/2) -> #REF! | I11: =('Evolutitve SCI'!#REF!+'Evolutitve SCI'!#REF!)/(('Evolutive SFP'!#REF!+'Evolutive SFP'!#REF!)/2) -> #REF! | J11: =('Evolutitve SCI'!#REF!+'Evolutitve SCI'!#REF!)/(('Evolutive SFP'!#REF!+'Evolutive SFP'!#REF!)/2) -> #REF! | K11: =('Evolutitve SCI'!#REF!+'Evolutitve SCI'!#REF!)/(('Evolutive SFP'!#REF!+'Evolutive SFP'!#REF!)/2) -> #REF! | ... AQ11: =('Evolutitve SCI'!#REF!+'Evolutitve SCI'!#REF!)/(('Evolutive SFP'!#REF!+'Evolutive SFP'!#REF!)/2) -> #REF! | AR11: =('Evolutitve SCI'!#REF!+'Evolutitve SCI'!#REF!)/(('Evolutive SFP'!#REF!+'Evolutive SFP'!AH27)/2) -> #REF! | AS11: =('Evolutitve SCI'!#REF!+'Evolutitve SCI'!#REF!)/(('Evolutive SFP'!#REF!+'Evolutive SFP'!AI27)/2) -> #REF! | AT11: =('Evolutitve SCI'!AG23+'Evolutitve SCI'!AG12)/(('Evolutive SFP'!AH27+'Evolutive SFP'!AJ27)/2) -> 0.10592582 | AU11: =('Evolutitve SCI'!AH23+'Evolutitve SCI'!AH12)/(('Evolutive SFP'!AI27+'Evolutive SFP'!AK27)/2) -> 0.0026280535 | AV11: =('Evolutitve SCI'!AI23+'Evolutitve SCI'!AI12)/(('Evolutive SFP'!AJ27+'Evolutive SFP'!AL27)/2) -> 0.0064358277 | AW11: =('Evolutitve SCI'!AJ23+'Evolutitve SCI'!AJ12)/(('Evolutive SFP'!AK27+'Evolutive SFP'!AM27)/2) -> 0.01005344 | AX11: =('Evolutitve SCI'!AK23+'Evolutitve SCI'!AK12)/(('Evolutive SFP'!AL27+'Evolutive SFP'!AN27)/2) -> 0.013487126 | AY11: =('Evolutitve SCI'!AL23+'Evolutitve SCI'!AL12)/(('Evolutive SFP'!AM27+'Evolutive SFP'!#REF!)/2) -> #REF! | AZ11: =('Evolutitve SCI'!AM23+'Evolutitve SCI'!AM12)/(('Evolutive SFP'!AN27+'Evolutive SFP'!AO27)/2) -> 0.018985396 | BA11: =('Evolutitve SCI'!#REF!+'Evolutitve SCI'!#REF!)/(('Evolutive SFP'!#REF!+'Evolutive SFP'!AP27)/2) -> #REF! | BB11: =('Evolutitve SCI'!AN23+'Evolutitve SCI'!AN12)/(('Evolutive SFP'!AO27+'Evolutive SFP'!AQ27)/2) -> 0.024268738 | BC11: =('Evolutitve SCI'!AO23+'Evolutitve SCI'!AO12)/(('Evolutive SFP'!AP27+'Evolutive SFP'!#REF!)/2) -> #REF! | BD11: =('Evolutitve SCI'!AP23+'Evolutitve SCI'!AP12)/(('Evolutive SFP'!AQ27+'Evolutive SFP'!#REF!)/2) -> #REF! | BE11: =('Evolutitve SCI'!AQ23+'Evolutitve SCI'!AQ12)/(('Evolutive SFP'!AR27+'Evolutive SFP'!#REF!)/2) -> #REF! | BF11: =('Evolutitve SCI'!AR23+'Evolutitve SCI'!AR12)/(('Evolutive SFP'!AS27+'Evolutive SFP'!#REF!)/2) -> #REF! | BG11: =('Evolutitve SCI'!AS23+'Evolutitve SCI'!AS12)/(('Evolutive SFP'!AT27+'Evolutive SFP'!#REF!)/2) -> #REF! | BH11: =('Evolutitve SCI'!AT23+'Evolutitve SCI'!AT12)/(('Evolutive SFP'!AU27+'Evolutive SFP'!#REF!)/2) -> #REF! | BI11: =('Evolutitve SCI'!AU23+'Evolutitve SCI'!AU12)/(('Evolutive SFP'!AV27+'Evolutive SFP'!#REF!)/2) -> #REF! | BJ11: =('Evolutitve SCI'!AV23+'Evolutitve SCI'!AV12)/(('Evolutive SFP'!AW27+'Evolutive SFP'!#REF!)/2) -> #REF! | ... CN11: =('Evolutitve SCI'!BZ23+'Evolutitve SCI'!BZ12)/(('Evolutive SFP'!CA27+'Evolutive SFP'!#REF!)/2) -> #REF!
A12: LIQUIDITY | B12: MIN LIQ ratio | C12: Min 15% | D12: =('Evolutive SFP'!#REF!)/('Evolutive SFP'!#REF!+'Evolutive SFP'!#REF!+'Evolutive SFP'!#REF!+'Evolutive SFP'!#REF!+'Evolutive SFP'!#REF!+'Evolutive SFP'!#REF!+'Evolutive SFP'!#REF!) -> #REF! | E12: =('Evolutive SFP'!#REF!)/('Evolutive SFP'!#REF!+'Evolutive SFP'!#REF!+'Evolutive SFP'!#REF!+'Evolutive SFP'!#REF!+'Evolutive SFP'!#REF!+'Evolutive SFP'!#REF!+'Evolutive SFP'!#REF!) -> #REF! | F12: =('Evolutive SFP'!#REF!)/('Evolutive SFP'!#REF!+'Evolutive SFP'!#REF!+'Evolutive SFP'!#REF!+'Evolutive SFP'!#REF!+'Evolutive SFP'!#REF!+'Evolutive SFP'!#REF!+'Evolutive SFP'!#REF!) -> #REF! | G12: =('Evolutive SFP'!#REF!)/('Evolutive SFP'!#REF!+'Evolutive SFP'!#REF!+'Evolutive SFP'!#REF!+'Evolutive SFP'!#REF!+'Evolutive SFP'!#REF!+'Evolutive SFP'!#REF!+'Evolutive SFP'!#REF!) -> #REF! | H12: =('Evolutive SFP'!#REF!)/('Evolutive SFP'!#REF!+'Evolutive SFP'!#REF!+'Evolutive SFP'!#REF!+'Evolutive SFP'!#REF!+'Evolutive SFP'!#REF!+'Evolutive SFP'!#REF!+'Evolutive SFP'!#REF!) -> #REF! | I12: =('Evolutive SFP'!#REF!)/('Evolutive SFP'!#REF!+'Evolutive SFP'!#REF!+'Evolutive SFP'!#REF!+'Evolutive SFP'!#REF!+'Evolutive SFP'!#REF!+'Evolutive SFP'!#REF!+'Evolutive SFP'!#REF!) -> #REF! | J12: =('Evolutive SFP'!#REF!)/('Evolutive SFP'!#REF!+'Evolutive SFP'!#REF!+'Evolutive SFP'!#REF!+'Evolutive SFP'!#REF!+'Evolutive SFP'!#REF!+'Evolutive SFP'!#REF!+'Evolutive SFP'!#REF!) -> #REF! | K12: =('Evolutive SFP'!#REF!)/('Evolutive SFP'!#REF!+'Evolutive SFP'!#REF!+'Evolutive SFP'!#REF!+'Evolutive SFP'!#REF!+'Evolutive SFP'!#REF!+'Evolutive SFP'!#REF!+'Evolutive SFP'!#REF!) -> #REF! | ... AS12: =('Evolutive SFP'!#REF!)/('Evolutive SFP'!#REF!+'Evolutive SFP'!#REF!+'Evolutive SFP'!#REF!+'Evolutive SFP'!#REF!+'Evolutive SFP'!#REF!+'Evolutive SFP'!#REF!+'Evolutive SFP'!#REF!) -> #REF! | AT12: =('Evolutive SFP'!AH4)/('Evolutive SFP'!AH28+'Evolutive SFP'!AH29+'Evolutive SFP'!AH32+'Evolutive SFP'!AH33+'Evolutive SFP'!AH34+'Evolutive SFP'!AH35+'Evolutive SFP'!AH36) -> 0.79358559 | AU12: =('Evolutive SFP'!AI4)/('Evolutive SFP'!AI28+'Evolutive SFP'!AI29+'Evolutive SFP'!AI32+'Evolutive SFP'!AI33+'Evolutive SFP'!AI34+'Evolutive SFP'!AI35+'Evolutive SFP'!AI36) -> 0.75711243 | AV12: =('Evolutive SFP'!AJ4)/('Evolutive SFP'!AJ28+'Evolutive SFP'!AJ29+'Evolutive SFP'!AJ32+'Evolutive SFP'!AJ33+'Evolutive SFP'!AJ34+'Evolutive SFP'!AJ35+'Evolutive SFP'!AJ36) -> 0.71374384 | AW12: =('Evolutive SFP'!AK4)/('Evolutive SFP'!AK28+'Evolutive SFP'!AK29+'Evolutive SFP'!AK32+'Evolutive SFP'!AK33+'Evolutive SFP'!AK34+'Evolutive SFP'!AK35+'Evolutive SFP'!AK36) -> 0.62440266 | AX12: =('Evolutive SFP'!AL4)/('Evolutive SFP'!AL28+'Evolutive SFP'!AL29+'Evolutive SFP'!AL32+'Evolutive SFP'!AL33+'Evolutive SFP'!AL34+'Evolutive SFP'!AL35+'Evolutive SFP'!AL36) -> 0.76233122 | AY12: =('Evolutive SFP'!AM4)/('Evolutive SFP'!AM28+'Evolutive SFP'!AM29+'Evolutive SFP'!AM32+'Evolutive SFP'!AM33+'Evolutive SFP'!AM34+'Evolutive SFP'!AM35+'Evolutive SFP'!AM36) -> 0.79134784 | AZ12: =('Evolutive SFP'!AN4)/('Evolutive SFP'!AN28+'Evolutive SFP'!AN29+'Evolutive SFP'!AN32+'Evolutive SFP'!AN33+'Evolutive SFP'!AN34+'Evolutive SFP'!AN35+'Evolutive SFP'!AN36) -> 0.80312498 | BA12: =('Evolutive SFP'!#REF!)/('Evolutive SFP'!#REF!+'Evolutive SFP'!#REF!+'Evolutive SFP'!#REF!+'Evolutive SFP'!#REF!+'Evolutive SFP'!#REF!+'Evolutive SFP'!#REF!+'Evolutive SFP'!#REF!) -> #REF! | BB12: =('Evolutive SFP'!AO4)/('Evolutive SFP'!AO28+'Evolutive SFP'!AO29+'Evolutive SFP'!AO32+'Evolutive SFP'!AO33+'Evolutive SFP'!AO34+'Evolutive SFP'!AO35+'Evolutive SFP'!AO36) -> 1.2201112 | BC12: =('Evolutive SFP'!AP4)/('Evolutive SFP'!AP28+'Evolutive SFP'!AP29+'Evolutive SFP'!AP32+'Evolutive SFP'!AP33+'Evolutive SFP'!AP34+'Evolutive SFP'!AP35+'Evolutive SFP'!AP36) -> 1.1809706 | BD12: =('Evolutive SFP'!AQ4)/('Evolutive SFP'!AQ28+'Evolutive SFP'!AQ29+'Evolutive SFP'!AQ32+'Evolutive SFP'!AQ33+'Evolutive SFP'!AQ34+'Evolutive SFP'!AQ35+'Evolutive SFP'!AQ36) -> 1.5171591 | BE12: =('Evolutive SFP'!AR4)/('Evolutive SFP'!AR28+'Evolutive SFP'!AR29+'Evolutive SFP'!AR32+'Evolutive SFP'!AR33+'Evolutive SFP'!AR34+'Evolutive SFP'!AR35+'Evolutive SFP'!AR36) -> 1.4903324 | BF12: =('Evolutive SFP'!AS4)/('Evolutive SFP'!AS28+'Evolutive SFP'!AS29+'Evolutive SFP'!AS32+'Evolutive SFP'!AS33+'Evolutive SFP'!AS34+'Evolutive SFP'!AS35+'Evolutive SFP'!AS36) -> 1.5825648 | BG12: =('Evolutive SFP'!AT4)/('Evolutive SFP'!AT28+'Evolutive SFP'!AT29+'Evolutive SFP'!AT32+'Evolutive SFP'!AT33+'Evolutive SFP'!AT34+'Evolutive SFP'!AT35+'Evolutive SFP'!AT36) -> 1.0361033 | BH12: =('Evolutive SFP'!AU4)/('Evolutive SFP'!AU28+'Evolutive SFP'!AU29+'Evolutive SFP'!AU32+'Evolutive SFP'!AU33+'Evolutive SFP'!AU34+'Evolutive SFP'!AU35+'Evolutive SFP'!AU36) -> 0.80131723 | BI12: =('Evolutive SFP'!AV4)/('Evolutive SFP'!AV28+'Evolutive SFP'!AV29+'Evolutive SFP'!AV32+'Evolutive SFP'!AV33+'Evolutive SFP'!AV34+'Evolutive SFP'!AV35+'Evolutive SFP'!AV36) -> 0.83143695 | ... CN12: =('Evolutive SFP'!CA4)/('Evolutive SFP'!CA28+'Evolutive SFP'!CA29+'Evolutive SFP'!CA32+'Evolutive SFP'!CA33+'Evolutive SFP'!CA34+'Evolutive SFP'!CA35+'Evolutive SFP'!CA36) -> 1.4814274
B13: T/LIQ ratio | D13: =('Evolutive SFP'!#REF!+'Evolutive SFP'!#REF!)/('Evolutive SFP'!#REF!+'Evolutive SFP'!#REF!+'Evolutive SFP'!#REF!+'Evolutive SFP'!#REF!+'Evolutive SFP'!#REF!+'Evolutive SFP'!#REF!) -> #REF! | E13: =('Evolutive SFP'!#REF!+'Evolutive SFP'!#REF!)/('Evolutive SFP'!#REF!+'Evolutive SFP'!#REF!+'Evolutive SFP'!#REF!+'Evolutive SFP'!#REF!+'Evolutive SFP'!#REF!+'Evolutive SFP'!#REF!) -> #REF! | F13: =('Evolutive SFP'!#REF!+'Evolutive SFP'!#REF!)/('Evolutive SFP'!#REF!+'Evolutive SFP'!#REF!+'Evolutive SFP'!#REF!+'Evolutive SFP'!#REF!+'Evolutive SFP'!#REF!+'Evolutive SFP'!#REF!) -> #REF! | G13: =('Evolutive SFP'!#REF!+'Evolutive SFP'!#REF!)/('Evolutive SFP'!#REF!+'Evolutive SFP'!#REF!+'Evolutive SFP'!#REF!+'Evolutive SFP'!#REF!+'Evolutive SFP'!#REF!+'Evolutive SFP'!#REF!) -> #REF! | H13: =('Evolutive SFP'!#REF!+'Evolutive SFP'!#REF!)/('Evolutive SFP'!#REF!+'Evolutive SFP'!#REF!+'Evolutive SFP'!#REF!+'Evolutive SFP'!#REF!+'Evolutive SFP'!#REF!+'Evolutive SFP'!#REF!) -> #REF! | I13: =('Evolutive SFP'!#REF!+'Evolutive SFP'!#REF!)/('Evolutive SFP'!#REF!+'Evolutive SFP'!#REF!+'Evolutive SFP'!#REF!+'Evolutive SFP'!#REF!+'Evolutive SFP'!#REF!+'Evolutive SFP'!#REF!) -> #REF! | J13: =('Evolutive SFP'!#REF!+'Evolutive SFP'!#REF!)/('Evolutive SFP'!#REF!+'Evolutive SFP'!#REF!+'Evolutive SFP'!#REF!+'Evolutive SFP'!#REF!+'Evolutive SFP'!#REF!+'Evolutive SFP'!#REF!) -> #REF! | K13: =('Evolutive SFP'!#REF!+'Evolutive SFP'!#REF!)/('Evolutive SFP'!#REF!+'Evolutive SFP'!#REF!+'Evolutive SFP'!#REF!+'Evolutive SFP'!#REF!+'Evolutive SFP'!#REF!+'Evolutive SFP'!#REF!) -> #REF! | ... O13: =('Evolutive SFP'!#REF!+'Evolutive SFP'!#REF!)/('Evolutive SFP'!#REF!+'Evolutive SFP'!#REF!+'Evolutive SFP'!#REF!+'Evolutive SFP'!#REF!+'Evolutive SFP'!#REF!+'Evolutive SFP'!#REF!) -> #REF! | P13: ='Evolutive SFP'!#REF!/('Evolutive SFP'!#REF!+'Evolutive SFP'!#REF!) -> #REF! | Q13: ='Evolutive SFP'!#REF!/('Evolutive SFP'!#REF!+'Evolutive SFP'!#REF!) -> #REF! | R13: ='Evolutive SFP'!#REF!/('Evolutive SFP'!#REF!+'Evolutive SFP'!#REF!) -> #REF! | S13: ='Evolutive SFP'!#REF!/('Evolutive SFP'!#REF!+'Evolutive SFP'!#REF!) -> #REF! | T13: ='Evolutive SFP'!#REF!/('Evolutive SFP'!#REF!+'Evolutive SFP'!#REF!) -> #REF! | U13: ='Evolutive SFP'!#REF!/('Evolutive SFP'!#REF!+'Evolutive SFP'!#REF!) -> #REF! | V13: ='Evolutive SFP'!#REF!/('Evolutive SFP'!#REF!+'Evolutive SFP'!#REF!) -> #REF! | W13: ='Evolutive SFP'!#REF!/('Evolutive SFP'!#REF!+'Evolutive SFP'!#REF!) -> #REF! | ... AS13: ='Evolutive SFP'!#REF!/('Evolutive SFP'!#REF!+'Evolutive SFP'!#REF!) -> #REF! | AT13: ='Evolutive SFP'!AH4/('Evolutive SFP'!AH31+'Evolutive SFP'!AH36) -> 0.20610713 | AU13: ='Evolutive SFP'!AI4/('Evolutive SFP'!AI31+'Evolutive SFP'!AI36) -> 0.24665823 | AV13: ='Evolutive SFP'!AJ4/('Evolutive SFP'!AJ31+'Evolutive SFP'!AJ36) -> 0.24367138 | AW13: ='Evolutive SFP'!AK4/('Evolutive SFP'!AK31+'Evolutive SFP'!AK36) -> 0.18274953 | AX13: ='Evolutive SFP'!AL4/('Evolutive SFP'!AL31+'Evolutive SFP'!AL36) -> 0.215685 | AY13: ='Evolutive SFP'!AM4/('Evolutive SFP'!AM31+'Evolutive SFP'!AM36) -> 0.23928452 | AZ13: ='Evolutive SFP'!AN4/('Evolutive SFP'!AN31+'Evolutive SFP'!AN36) -> 0.22562376 | BA13: ='Evolutive SFP'!#REF!/('Evolutive SFP'!#REF!+'Evolutive SFP'!#REF!) -> #REF! | BB13: ='Evolutive SFP'!AO4/('Evolutive SFP'!AO31+'Evolutive SFP'!AO36) -> 0.35074875 | BC13: ='Evolutive SFP'!AP4/('Evolutive SFP'!AP31+'Evolutive SFP'!AP36) -> 0.32207554 | BD13: ='Evolutive SFP'!AQ4/('Evolutive SFP'!AQ31+'Evolutive SFP'!AQ36) -> 0.33571677 | BE13: ='Evolutive SFP'!AR4/('Evolutive SFP'!AR31+'Evolutive SFP'!AR36) -> 0.37576643 | BF13: ='Evolutive SFP'!AS4/('Evolutive SFP'!AS31+'Evolutive SFP'!AS36) -> 0.27045936 | BG13: ='Evolutive SFP'!AT4/('Evolutive SFP'!AT31+'Evolutive SFP'!AT36) -> 0.26418247 | BH13: ='Evolutive SFP'!AU4/('Evolutive SFP'!AU31+'Evolutive SFP'!AU36) -> 0.18537497 | BI13: ='Evolutive SFP'!AV4/('Evolutive SFP'!AV31+'Evolutive SFP'!AV36) -> 0.18686717 | ... CN13: ='Evolutive SFP'!CA4/('Evolutive SFP'!CA31+'Evolutive SFP'!CA36) -> 0.24706184
B14: EB ratio | C14: Max 25% | D14: ='Evolutive SFP'!#REF!/'Evolutive SFP'!#REF! -> #REF! | E14: ='Evolutive SFP'!#REF!/'Evolutive SFP'!#REF! -> #REF! | F14: ='Evolutive SFP'!#REF!/'Evolutive SFP'!#REF! -> #REF! | G14: ='Evolutive SFP'!#REF!/'Evolutive SFP'!#REF! -> #REF! | H14: ='Evolutive SFP'!#REF!/'Evolutive SFP'!#REF! -> #REF! | I14: ='Evolutive SFP'!#REF!/'Evolutive SFP'!#REF! -> #REF! | J14: ='Evolutive SFP'!#REF!/'Evolutive SFP'!#REF! -> #REF! | K14: ='Evolutive SFP'!#REF!/'Evolutive SFP'!#REF! -> #REF! | ... AS14: ='Evolutive SFP'!#REF!/'Evolutive SFP'!#REF! -> #REF! | AT14: ='Evolutive SFP'!AH37/'Evolutive SFP'!AH27 -> 0 | AU14: ='Evolutive SFP'!AI37/'Evolutive SFP'!AI27 -> 0 | AV14: ='Evolutive SFP'!AJ37/'Evolutive SFP'!AJ27 -> 0 | AW14: ='Evolutive SFP'!AK37/'Evolutive SFP'!AK27 -> 0 | AX14: ='Evolutive SFP'!AL37/'Evolutive SFP'!AL27 -> 0 | AY14: ='Evolutive SFP'!AM37/'Evolutive SFP'!AM27 -> 0 | AZ14: ='Evolutive SFP'!AN37/'Evolutive SFP'!AN27 -> 0 | BA14: ='Evolutive SFP'!#REF!/'Evolutive SFP'!#REF! -> #REF! | BB14: ='Evolutive SFP'!AO37/'Evolutive SFP'!AO27 -> 0 | BC14: ='Evolutive SFP'!AP37/'Evolutive SFP'!AP27 -> 0 | BD14: ='Evolutive SFP'!AQ37/'Evolutive SFP'!AQ27 -> 0 | BE14: ='Evolutive SFP'!AR37/'Evolutive SFP'!AR27 -> 0 | BF14: ='Evolutive SFP'!AS37/'Evolutive SFP'!AS27 -> 0 | BG14: ='Evolutive SFP'!AT37/'Evolutive SFP'!AT27 -> 0 | BH14: ='Evolutive SFP'!AU37/'Evolutive SFP'!AU27 -> 0 | BI14: ='Evolutive SFP'!AV37/'Evolutive SFP'!AV27 -> 0 | ... CN14: ='Evolutive SFP'!CA37/'Evolutive SFP'!CA27 -> 0
B15: LA to TA ratio | D15: ='Evolutive SFP'!#REF!/'Evolutive SFP'!#REF! -> #REF! | E15: ='Evolutive SFP'!#REF!/'Evolutive SFP'!#REF! -> #REF! | F15: ='Evolutive SFP'!#REF!/'Evolutive SFP'!#REF! -> #REF! | G15: ='Evolutive SFP'!#REF!/'Evolutive SFP'!#REF! -> #REF! | H15: ='Evolutive SFP'!#REF!/'Evolutive SFP'!#REF! -> #REF! | I15: ='Evolutive SFP'!#REF!/'Evolutive SFP'!#REF! -> #REF! | J15: ='Evolutive SFP'!#REF!/'Evolutive SFP'!#REF! -> #REF! | K15: ='Evolutive SFP'!#REF!/'Evolutive SFP'!#REF! -> #REF! | ... AS15: ='Evolutive SFP'!#REF!/'Evolutive SFP'!#REF! -> #REF! | AT15: ='Evolutive SFP'!AH4/'Evolutive SFP'!AH27 -> 0.14422413 | AU15: ='Evolutive SFP'!AI4/'Evolutive SFP'!AI27 -> 0.18621371 | AV15: ='Evolutive SFP'!AJ4/'Evolutive SFP'!AJ27 -> 0.18434541 | AW15: ='Evolutive SFP'!AK4/'Evolutive SFP'!AK27 -> 0.13398188 | AX15: ='Evolutive SFP'!AL4/'Evolutive SFP'!AL27 -> 0.15727162 | AY15: ='Evolutive SFP'!AM4/'Evolutive SFP'!AM27 -> 0.17478211 | AZ15: ='Evolutive SFP'!AN4/'Evolutive SFP'!AN27 -> 0.16293566 | BA15: ='Evolutive SFP'!#REF!/'Evolutive SFP'!#REF! -> #REF! | BB15: ='Evolutive SFP'!AO4/'Evolutive SFP'!AO27 -> 0.25064878 | BC15: ='Evolutive SFP'!AP4/'Evolutive SFP'!AP27 -> 0.2280223 | BD15: ='Evolutive SFP'!AQ4/'Evolutive SFP'!AQ27 -> 0.23177191 | BE15: ='Evolutive SFP'!AR4/'Evolutive SFP'!AR27 -> 0.26128445 | BF15: ='Evolutive SFP'!AS4/'Evolutive SFP'!AS27 -> 0.183275 | BG15: ='Evolutive SFP'!AT4/'Evolutive SFP'!AT27 -> 0.18331023 | BH15: ='Evolutive SFP'!AU4/'Evolutive SFP'!AU27 -> 0.13703132 | BI15: ='Evolutive SFP'!AV4/'Evolutive SFP'!AV27 -> 0.13772866 | ... CN15: ='Evolutive SFP'!CA4/'Evolutive SFP'!CA27 -> 0.1666097
A16: STRUCTURE | B16: NEA ratio | C16: Max 10% | D16: =('Evolutive SFP'!#REF!+'Evolutive SFP'!#REF!)/'Evolutive SFP'!#REF! -> #REF! | E16: =('Evolutive SFP'!#REF!+'Evolutive SFP'!#REF!)/'Evolutive SFP'!#REF! -> #REF! | F16: =('Evolutive SFP'!#REF!+'Evolutive SFP'!#REF!)/'Evolutive SFP'!#REF! -> #REF! | G16: =('Evolutive SFP'!#REF!+'Evolutive SFP'!#REF!)/'Evolutive SFP'!#REF! -> #REF! | H16: =('Evolutive SFP'!#REF!+'Evolutive SFP'!#REF!)/'Evolutive SFP'!#REF! -> #REF! | I16: =('Evolutive SFP'!#REF!+'Evolutive SFP'!#REF!)/'Evolutive SFP'!#REF! -> #REF! | J16: =('Evolutive SFP'!#REF!+'Evolutive SFP'!#REF!)/'Evolutive SFP'!#REF! -> #REF! | K16: =('Evolutive SFP'!#REF!+'Evolutive SFP'!#REF!)/'Evolutive SFP'!#REF! -> #REF! | ... AS16: =('Evolutive SFP'!#REF!+'Evolutive SFP'!#REF!)/'Evolutive SFP'!#REF! -> #REF! | AT16: =('Evolutive SFP'!AH7+'Evolutive SFP'!AH21)/'Evolutive SFP'!AH27 -> 0.25657966 | AU16: =('Evolutive SFP'!AI7+'Evolutive SFP'!AI21)/'Evolutive SFP'!AI27 -> 0.39262744 | AV16: =('Evolutive SFP'!AJ7+'Evolutive SFP'!AJ21)/'Evolutive SFP'!AJ27 -> 0.40350658 | AW16: =('Evolutive SFP'!AK7+'Evolutive SFP'!AK21)/'Evolutive SFP'!AK27 -> 0.42139423 | AX16: =('Evolutive SFP'!AL7+'Evolutive SFP'!AL21)/'Evolutive SFP'!AL27 -> 0.43475162 | AY16: =('Evolutive SFP'!AM7+'Evolutive SFP'!AM21)/'Evolutive SFP'!AM27 -> 0.43202705 | AZ16: =('Evolutive SFP'!AN7+'Evolutive SFP'!AN21)/'Evolutive SFP'!AN27 -> 0.44398276 | BA16: =('Evolutive SFP'!#REF!+'Evolutive SFP'!#REF!)/'Evolutive SFP'!#REF! -> #REF! | BB16: =('Evolutive SFP'!AO7+'Evolutive SFP'!AO21)/'Evolutive SFP'!AO27 -> 0.28040403 | BC16: =('Evolutive SFP'!AP7+'Evolutive SFP'!AP21)/'Evolutive SFP'!AP27 -> 0.28598369 | BD16: =('Evolutive SFP'!AQ7+'Evolutive SFP'!AQ21)/'Evolutive SFP'!AQ27 -> 0.302401 | BE16: =('Evolutive SFP'!AR7+'Evolutive SFP'!AR21)/'Evolutive SFP'!AR27 -> 0.2915758 | BF16: =('Evolutive SFP'!AS7+'Evolutive SFP'!AS21)/'Evolutive SFP'!AS27 -> 0.31729032 | BG16: =('Evolutive SFP'!AT7+'Evolutive SFP'!AT21)/'Evolutive SFP'!AT27 -> 0.31715911 | BH16: =('Evolutive SFP'!AU7+'Evolutive SFP'!AU21)/'Evolutive SFP'!AU27 -> 0.31757663 | BI16: =('Evolutive SFP'!AV7+'Evolutive SFP'!AV21)/'Evolutive SFP'!AV27 -> 0.32216551 | ... CN16: =('Evolutive SFP'!CA7+'Evolutive SFP'!CA21)/'Evolutive SFP'!CA27 -> 0.28716713
B17: LB ratio | C17: Max 5% | D17: ='Evolutive SFP'!#REF!/'Evolutive SFP'!#REF! -> #REF! | E17: ='Evolutive SFP'!#REF!/'Evolutive SFP'!#REF! -> #REF! | F17: ='Evolutive SFP'!#REF!/'Evolutive SFP'!#REF! -> #REF! | G17: ='Evolutive SFP'!#REF!/'Evolutive SFP'!#REF! -> #REF! | H17: ='Evolutive SFP'!#REF!/'Evolutive SFP'!#REF! -> #REF! | I17: ='Evolutive SFP'!#REF!/'Evolutive SFP'!#REF! -> #REF! | J17: ='Evolutive SFP'!#REF!/'Evolutive SFP'!#REF! -> #REF! | K17: ='Evolutive SFP'!#REF!/'Evolutive SFP'!#REF! -> #REF! | ... AS17: ='Evolutive SFP'!#REF!/'Evolutive SFP'!#REF! -> #REF! | AT17: ='Evolutive SFP'!AH21/'Evolutive SFP'!AH27 -> 0.22822529 | AU17: ='Evolutive SFP'!AI21/'Evolutive SFP'!AI27 -> 0.38864316 | AV17: ='Evolutive SFP'!AJ21/'Evolutive SFP'!AJ27 -> 0.39894843 | AW17: ='Evolutive SFP'!AK21/'Evolutive SFP'!AK27 -> 0.41383253 | AX17: ='Evolutive SFP'!AL21/'Evolutive SFP'!AL27 -> 0.42685415 | AY17: ='Evolutive SFP'!AM21/'Evolutive SFP'!AM27 -> 0.42901938 | AZ17: ='Evolutive SFP'!AN21/'Evolutive SFP'!AN27 -> 0.435874 | BA17: ='Evolutive SFP'!#REF!/'Evolutive SFP'!#REF! -> #REF! | BB17: ='Evolutive SFP'!AO21/'Evolutive SFP'!AO27 -> 0.27339959 | BC17: ='Evolutive SFP'!AP21/'Evolutive SFP'!AP27 -> 0.27879708 | BD17: ='Evolutive SFP'!AQ21/'Evolutive SFP'!AQ27 -> 0.29479031 | BE17: ='Evolutive SFP'!AR21/'Evolutive SFP'!AR27 -> 0.28403552 | BF17: ='Evolutive SFP'!AS21/'Evolutive SFP'!AS27 -> 0.305626 | BG17: ='Evolutive SFP'!AT21/'Evolutive SFP'!AT27 -> 0.29205507 | BH17: ='Evolutive SFP'!AU21/'Evolutive SFP'!AU27 -> 0.30927168 | BI17: ='Evolutive SFP'!AV21/'Evolutive SFP'!AV27 -> 0.31368083 | ... CN17: ='Evolutive SFP'!CA21/'Evolutive SFP'!CA27 -> 0.28430416
B18: PI to Deposit ratio | C18: Max 5% | D18: ='Evolutive SFP'!#REF!/'Evolutive SFP'!#REF! -> #REF! | E18: ='Evolutive SFP'!#REF!/'Evolutive SFP'!#REF! -> #REF! | F18: ='Evolutive SFP'!#REF!/'Evolutive SFP'!#REF! -> #REF! | G18: ='Evolutive SFP'!#REF!/'Evolutive SFP'!#REF! -> #REF! | H18: ='Evolutive SFP'!#REF!/'Evolutive SFP'!#REF! -> #REF! | I18: ='Evolutive SFP'!#REF!/'Evolutive SFP'!#REF! -> #REF! | J18: ='Evolutive SFP'!#REF!/'Evolutive SFP'!#REF! -> #REF! | K18: ='Evolutive SFP'!#REF!/'Evolutive SFP'!#REF! -> #REF! | ... AS18: ='Evolutive SFP'!#REF!/'Evolutive SFP'!#REF! -> #REF! | AT18: ='Evolutive SFP'!AH13/'Evolutive SFP'!AH31 -> 0.0020914688 | AU18: ='Evolutive SFP'!AI13/'Evolutive SFP'!AI31 -> 0 | AV18: ='Evolutive SFP'!AJ13/'Evolutive SFP'!AJ31 -> 0 | AW18: ='Evolutive SFP'!AK13/'Evolutive SFP'!AK31 -> 0 | AX18: ='Evolutive SFP'!AL13/'Evolutive SFP'!AL31 -> 0 | AY18: ='Evolutive SFP'!AM13/'Evolutive SFP'!AM31 -> 0 | AZ18: ='Evolutive SFP'!AN13/'Evolutive SFP'!AN31 -> 0 | BA18: ='Evolutive SFP'!#REF!/'Evolutive SFP'!#REF! -> #REF! | BB18: ='Evolutive SFP'!AO13/'Evolutive SFP'!AO31 -> 0 | BC18: ='Evolutive SFP'!AP13/'Evolutive SFP'!AP31 -> 0 | BD18: ='Evolutive SFP'!AQ13/'Evolutive SFP'!AQ31 -> 0 | BE18: ='Evolutive SFP'!AR13/'Evolutive SFP'!AR31 -> 0 | BF18: ='Evolutive SFP'!AS13/'Evolutive SFP'!AS31 -> 0 | BG18: ='Evolutive SFP'!AT13/'Evolutive SFP'!AT31 -> 0.0020266259 | BH18: ='Evolutive SFP'!AU13/'Evolutive SFP'!AU31 -> 0.14580294 | BI18: ='Evolutive SFP'!AV13/'Evolutive SFP'!AV31 -> 0.14725199 | ... CN18: ='Evolutive SFP'!CA13/'Evolutive SFP'!CA31 -> 0.16207536
B19: PI to CC ratio | C19: Max 40% | D19: ='Evolutive SFP'!#REF!/(CAELS!D3*1000000) -> #REF! | E19: ='Evolutive SFP'!#REF!/(CAELS!E3*1000000) -> #REF! | F19: ='Evolutive SFP'!#REF!/(CAELS!F3*1000000) -> #REF! | G19: ='Evolutive SFP'!#REF!/(CAELS!G3*1000000) -> #REF! | H19: ='Evolutive SFP'!#REF!/(CAELS!H3*1000000) -> #REF! | I19: ='Evolutive SFP'!#REF!/(CAELS!I3*1000000) -> #REF! | J19: ='Evolutive SFP'!#REF!/(CAELS!J3*1000000) -> #REF! | K19: ='Evolutive SFP'!#REF!/(CAELS!K3*1000000) -> #REF! | ... AS19: ='Evolutive SFP'!#REF!/(CAELS!AS3*1000000) -> #REF! | AT19: ='Evolutive SFP'!AH13/(CAELS!AT3*1000000) -> 0.0054296516 | AU19: ='Evolutive SFP'!AI13/(CAELS!AU3*1000000) -> 0 | AV19: ='Evolutive SFP'!AJ13/(CAELS!AV3*1000000) -> 0 | AW19: ='Evolutive SFP'!AK13/(CAELS!AW3*1000000) -> 0 | AX19: ='Evolutive SFP'!AL13/(CAELS!AX3*1000000) -> 0 | AY19: ='Evolutive SFP'!AM13/(CAELS!AY3*1000000) -> 0 | AZ19: ='Evolutive SFP'!AN13/(CAELS!AZ3*1000000) -> 0 | BA19: ='Evolutive SFP'!#REF!/(CAELS!BA3*1000000) -> #REF! | BB19: ='Evolutive SFP'!AO13/(CAELS!BB3*1000000) -> 0 | BC19: ='Evolutive SFP'!AP13/(CAELS!BC3*1000000) -> 0 | BD19: ='Evolutive SFP'!AQ13/(CAELS!BD3*1000000) -> 0 | BE19: ='Evolutive SFP'!AR13/(CAELS!BE3*1000000) -> 0 | BF19: ='Evolutive SFP'!AS13/(CAELS!BF3*1000000) -> 0 | BG19: ='Evolutive SFP'!AT13/(CAELS!BG3*1000000) -> 0.0053015475 | BH19: ='Evolutive SFP'!AU13/(CAELS!BH3*1000000) -> 0.38326997 | BI19: ='Evolutive SFP'!AV13/(CAELS!BI3*1000000) -> 0.38138784 | ... CN19: ='Evolutive SFP'!CA13/(CAELS!CN3*1000000) -> 0.34393794
B20: Gross loans/TA | D20: ='Evolutive SFP'!#REF!/'Evolutive SFP'!#REF! -> #REF! | E20: ='Evolutive SFP'!#REF!/'Evolutive SFP'!#REF! -> #REF! | F20: ='Evolutive SFP'!#REF!/'Evolutive SFP'!#REF! -> #REF! | G20: ='Evolutive SFP'!#REF!/'Evolutive SFP'!#REF! -> #REF! | H20: ='Evolutive SFP'!#REF!/'Evolutive SFP'!#REF! -> #REF! | I20: ='Evolutive SFP'!#REF!/'Evolutive SFP'!#REF! -> #REF! | J20: ='Evolutive SFP'!#REF!/'Evolutive SFP'!#REF! -> #REF! | K20: ='Evolutive SFP'!#REF!/'Evolutive SFP'!#REF! -> #REF! | ... AS20: ='Evolutive SFP'!#REF!/'Evolutive SFP'!#REF! -> #REF! | AT20: ='Evolutive SFP'!AH15/'Evolutive SFP'!AH27 -> 0.4210749 | AU20: ='Evolutive SFP'!AI15/'Evolutive SFP'!AI27 -> 0.42115885 | AV20: ='Evolutive SFP'!AJ15/'Evolutive SFP'!AJ27 -> 0.41214801 | AW20: ='Evolutive SFP'!AK15/'Evolutive SFP'!AK27 -> 0.44462388 | AX20: ='Evolutive SFP'!AL15/'Evolutive SFP'!AL27 -> 0.40797676 | AY20: ='Evolutive SFP'!AM15/'Evolutive SFP'!AM27 -> 0.39319084 | AZ20: ='Evolutive SFP'!AN15/'Evolutive SFP'!AN27 -> 0.39308158 | BA20: ='Evolutive SFP'!#REF!/'Evolutive SFP'!#REF! -> #REF! | BB20: ='Evolutive SFP'!AO15/'Evolutive SFP'!AO27 -> 0.38198366 | BC20: ='Evolutive SFP'!AP15/'Evolutive SFP'!AP27 -> 0.39818737 | BD20: ='Evolutive SFP'!AQ15/'Evolutive SFP'!AQ27 -> 0.42068251 | BE20: ='Evolutive SFP'!AR15/'Evolutive SFP'!AR27 -> 0.4029204 | BF20: ='Evolutive SFP'!AS15/'Evolutive SFP'!AS27 -> 0.4516492 | BG20: ='Evolutive SFP'!AT15/'Evolutive SFP'!AT27 -> 0.45173601 | BH20: ='Evolutive SFP'!AU15/'Evolutive SFP'!AU27 -> 0.49658926 | BI20: ='Evolutive SFP'!AV15/'Evolutive SFP'!AV27 -> 0.49087355 | ... CN20: ='Evolutive SFP'!CA15/'Evolutive SFP'!CA27 -> 0.48403699
A21: FUNDING MIX | B21: Total Deposits/Total Assets | D21: ='Evolutive SFP'!#REF!/'Evolutive SFP'!#REF! -> #REF! | E21: ='Evolutive SFP'!#REF!/'Evolutive SFP'!#REF! -> #REF! | F21: ='Evolutive SFP'!#REF!/'Evolutive SFP'!#REF! -> #REF! | G21: ='Evolutive SFP'!#REF!/'Evolutive SFP'!#REF! -> #REF! | H21: ='Evolutive SFP'!#REF!/'Evolutive SFP'!#REF! -> #REF! | I21: ='Evolutive SFP'!#REF!/'Evolutive SFP'!#REF! -> #REF! | J21: ='Evolutive SFP'!#REF!/'Evolutive SFP'!#REF! -> #REF! | K21: ='Evolutive SFP'!#REF!/'Evolutive SFP'!#REF! -> #REF! | ... AS21: ='Evolutive SFP'!#REF!/'Evolutive SFP'!#REF! -> #REF! | AT21: ='Evolutive SFP'!AH31/'Evolutive SFP'!AH27 -> 0.67135148 | AU21: ='Evolutive SFP'!AI31/'Evolutive SFP'!AI27 -> 0.64825154 | AV21: ='Evolutive SFP'!AJ31/'Evolutive SFP'!AJ27 -> 0.65202278 | AW21: ='Evolutive SFP'!AK31/'Evolutive SFP'!AK27 -> 0.63582431 | AX21: ='Evolutive SFP'!AL31/'Evolutive SFP'!AL27 -> 0.66305646 | AY21: ='Evolutive SFP'!AM31/'Evolutive SFP'!AM27 -> 0.66894901 | AZ21: ='Evolutive SFP'!AN31/'Evolutive SFP'!AN27 -> 0.66040489 | BA21: ='Evolutive SFP'!#REF!/'Evolutive SFP'!#REF! -> #REF! | BB21: ='Evolutive SFP'!AO31/'Evolutive SFP'!AO27 -> 0.66109822 | BC21: ='Evolutive SFP'!AP31/'Evolutive SFP'!AP27 -> 0.65830624 | BD21: ='Evolutive SFP'!AQ31/'Evolutive SFP'!AQ27 -> 0.6848815 | BE21: ='Evolutive SFP'!AR31/'Evolutive SFP'!AR27 -> 0.69064316 | BF21: ='Evolutive SFP'!AS31/'Evolutive SFP'!AS27 -> 0.66352743 | BG21: ='Evolutive SFP'!AT31/'Evolutive SFP'!AT27 -> 0.66365495 | BH21: ='Evolutive SFP'!AU31/'Evolutive SFP'!AU27 -> 0.66635126 | BI21: ='Evolutive SFP'!AV31/'Evolutive SFP'!AV27 -> 0.66195368 | ... CN21: ='Evolutive SFP'!CA31/'Evolutive SFP'!CA27 -> 0.67593297
B22: BOSA Deposits/Total Assets | D22: ='Evolutive SFP'!#REF!/'Evolutive SFP'!#REF! -> #REF! | E22: ='Evolutive SFP'!#REF!/'Evolutive SFP'!#REF! -> #REF! | F22: ='Evolutive SFP'!#REF!/'Evolutive SFP'!#REF! -> #REF! | G22: ='Evolutive SFP'!#REF!/'Evolutive SFP'!#REF! -> #REF! | H22: ='Evolutive SFP'!#REF!/'Evolutive SFP'!#REF! -> #REF! | I22: ='Evolutive SFP'!#REF!/'Evolutive SFP'!#REF! -> #REF! | J22: ='Evolutive SFP'!#REF!/'Evolutive SFP'!#REF! -> #REF! | K22: ='Evolutive SFP'!#REF!/'Evolutive SFP'!#REF! -> #REF! | ... AS22: ='Evolutive SFP'!#REF!/'Evolutive SFP'!#REF! -> #REF! | AT22: ='Evolutive SFP'!AH30/'Evolutive SFP'!AH27 -> 0.5520463 | AU22: ='Evolutive SFP'!AI30/'Evolutive SFP'!AI27 -> 0.50927114 | AV22: ='Evolutive SFP'!AJ30/'Evolutive SFP'!AJ27 -> 0.49849172 | AW22: ='Evolutive SFP'!AK30/'Evolutive SFP'!AK27 -> 0.51885931 | AX22: ='Evolutive SFP'!AL30/'Evolutive SFP'!AL27 -> 0.52309732 | AY22: ='Evolutive SFP'!AM30/'Evolutive SFP'!AM27 -> 0.50976571 | AZ22: ='Evolutive SFP'!AN30/'Evolutive SFP'!AN27 -> 0.51952386 | BA22: ='Evolutive SFP'!#REF!/'Evolutive SFP'!#REF! -> #REF! | BB22: ='Evolutive SFP'!AO30/'Evolutive SFP'!AO27 -> 0.50936923 | BC22: ='Evolutive SFP'!AP30/'Evolutive SFP'!AP27 -> 0.51513747 | BD22: ='Evolutive SFP'!AQ30/'Evolutive SFP'!AQ27 -> 0.53785768 | BE22: ='Evolutive SFP'!AR30/'Evolutive SFP'!AR27 -> 0.52021146 | BF22: ='Evolutive SFP'!AS30/'Evolutive SFP'!AS27 -> 0.56222043 | BG22: ='Evolutive SFP'!AT30/'Evolutive SFP'!AT27 -> 0.56232846 | BH22: ='Evolutive SFP'!AU30/'Evolutive SFP'!AU27 -> 0.56837853 | BI22: ='Evolutive SFP'!AV30/'Evolutive SFP'!AV27 -> 0.57166634 | ... CN22: ='Evolutive SFP'!CA30/'Evolutive SFP'!CA27 -> 0.56229553
B23: FOSA Deposits/Total Assets | D23: =('Evolutive SFP'!#REF!+'Evolutive SFP'!#REF!)/'Evolutive SFP'!#REF! -> #REF! | E23: =('Evolutive SFP'!#REF!+'Evolutive SFP'!#REF!)/'Evolutive SFP'!#REF! -> #REF! | F23: =('Evolutive SFP'!#REF!+'Evolutive SFP'!#REF!)/'Evolutive SFP'!#REF! -> #REF! | G23: =('Evolutive SFP'!#REF!+'Evolutive SFP'!#REF!)/'Evolutive SFP'!#REF! -> #REF! | H23: =('Evolutive SFP'!#REF!+'Evolutive SFP'!#REF!)/'Evolutive SFP'!#REF! -> #REF! | I23: =('Evolutive SFP'!#REF!+'Evolutive SFP'!#REF!)/'Evolutive SFP'!#REF! -> #REF! | J23: =('Evolutive SFP'!#REF!+'Evolutive SFP'!#REF!)/'Evolutive SFP'!#REF! -> #REF! | K23: =('Evolutive SFP'!#REF!+'Evolutive SFP'!#REF!)/'Evolutive SFP'!#REF! -> #REF! | ... AS23: =('Evolutive SFP'!#REF!+'Evolutive SFP'!#REF!)/'Evolutive SFP'!#REF! -> #REF! | AT23: =('Evolutive SFP'!AH28+'Evolutive SFP'!AH29)/'Evolutive SFP'!AH27 -> 0.11930518 | AU23: =('Evolutive SFP'!AI28+'Evolutive SFP'!AI29)/'Evolutive SFP'!AI27 -> 0.13898041 | AV23: =('Evolutive SFP'!AJ28+'Evolutive SFP'!AJ29)/'Evolutive SFP'!AJ27 -> 0.15353106 | AW23: =('Evolutive SFP'!AK28+'Evolutive SFP'!AK29)/'Evolutive SFP'!AK27 -> 0.116965 | AX23: =('Evolutive SFP'!AL28+'Evolutive SFP'!AL29)/'Evolutive SFP'!AL27 -> 0.13995914 | AY23: =('Evolutive SFP'!AM28+'Evolutive SFP'!AM29)/'Evolutive SFP'!AM27 -> 0.1591833 | AZ23: =('Evolutive SFP'!AN28+'Evolutive SFP'!AN29)/'Evolutive SFP'!AN27 -> 0.14088103 | BA23: =('Evolutive SFP'!#REF!+'Evolutive SFP'!#REF!)/'Evolutive SFP'!#REF! -> #REF! | BB23: =('Evolutive SFP'!AO28+'Evolutive SFP'!AO29)/'Evolutive SFP'!AO27 -> 0.15172899 | BC23: =('Evolutive SFP'!AP28+'Evolutive SFP'!AP29)/'Evolutive SFP'!AP27 -> 0.14316877 | BD23: =('Evolutive SFP'!AQ28+'Evolutive SFP'!AQ29)/'Evolutive SFP'!AQ27 -> 0.14702383 | BE23: =('Evolutive SFP'!AR28+'Evolutive SFP'!AR29)/'Evolutive SFP'!AR27 -> 0.1704317 | BF23: =('Evolutive SFP'!AS28+'Evolutive SFP'!AS29)/'Evolutive SFP'!AS27 -> 0.10130701 | BG23: =('Evolutive SFP'!AT28+'Evolutive SFP'!AT29)/'Evolutive SFP'!AT27 -> 0.10132648 | BH23: =('Evolutive SFP'!AU28+'Evolutive SFP'!AU29)/'Evolutive SFP'!AU27 -> 0.097972722 | BI23: =('Evolutive SFP'!AV28+'Evolutive SFP'!AV29)/'Evolutive SFP'!AV27 -> 0.090287339 | ... CN23: =('Evolutive SFP'!CA28+'Evolutive SFP'!CA29)/'Evolutive SFP'!CA27 -> 0.11363744
A24: GROWTH RATIOS | B24: Total Assets | E24: =(Financials!D4-Financials!C4)/Financials!C4 -> #REF! | H24: =(Financials!G4-Financials!D4)/Financials!D4 -> #REF! | I24: =(Financials!H4-Financials!G4)/Financials!G4 -> #REF! | J24: =(Financials!I4-Financials!H4)/Financials!H4 -> #REF! | K24: =(Financials!J4-Financials!I4)/Financials!I4 -> #REF! | L24: =(Financials!K4-Financials!J4)/Financials!J4 -> #REF! | M24: =(Financials!L4-Financials!K4)/Financials!K4 -> #REF! | N24: =(Financials!M4-Financials!L4)/Financials!L4 -> #REF! | O24: =(Financials!N4-Financials!M4)/Financials!M4 -> #REF! | P24: =(Financials!O4-Financials!N4)/Financials!N4 -> #REF! | ... CN24: =(Financials!CM4-Financials!CL4)/Financials!CL4 -> -0.0027762121
B25: Total Deposits | D25: =Financials!D5/Financials!C5-1 -> #REF! | E25: =Financials!G5/Financials!D5-1 -> #REF! | F25: =Financials!H5/Financials!G5-1 -> #REF! | G25: =Financials!H5/Financials!G5-1 -> #REF! | H25: =Financials!H5/Financials!G5-1 -> #REF! | I25: =Financials!I5/Financials!H5-1 -> #REF! | J25: =Financials!J5/Financials!I5-1 -> #REF! | K25: =Financials!K5/Financials!J5-1 -> #REF! | L25: =Financials!L5/Financials!K5-1 -> #REF! | M25: =Financials!M5/Financials!L5-1 -> #REF! | N25: =Financials!N5/Financials!M5-1 -> #REF! | O25: =Financials!O5/Financials!N5-1 -> #REF! | ... R25: =Financials!R5/Financials!Q5-1 -> #REF! | S25: =Financials!#REF!/Financials!R5-1 -> #REF! | T25: =Financials!#REF!/Financials!S5-1 -> #REF! | U25: =Financials!#REF!/Financials!T5-1 -> #REF! | V25: =Financials!#REF!/Financials!U5-1 -> #REF! | W25: =Financials!#REF!/Financials!V5-1 -> #REF! | X25: =Financials!#REF!/Financials!W5-1 -> #REF! | Y25: =Financials!#REF!/Financials!X5-1 -> #REF! | Z25: =Financials!#REF!/Financials!Y5-1 -> #REF! | ... CN25: =Financials!#REF!/Financials!CM5-1 -> #REF!
B26: BOSA Deposits | D26: =Financials!D6/Financials!C6-1 -> #REF! | E26: =Financials!G6/Financials!D6-1 -> #REF! | F26: =Financials!H6/Financials!G6-1 -> #REF! | G26: =Financials!H6/Financials!G6-1 -> #REF! | H26: =Financials!H6/Financials!G6-1 -> #REF! | I26: =Financials!I6/Financials!H6-1 -> #REF! | J26: =Financials!J6/Financials!I6-1 -> #REF! | K26: =Financials!K6/Financials!J6-1 -> #REF! | L26: =Financials!L6/Financials!K6-1 -> #REF! | M26: =Financials!M6/Financials!L6-1 -> #REF! | N26: =Financials!N6/Financials!M6-1 -> #REF! | O26: =Financials!O6/Financials!N6-1 -> #REF! | ... R26: =Financials!R6/Financials!Q6-1 -> #REF! | S26: =Financials!#REF!/Financials!R6-1 -> #REF! | T26: =Financials!#REF!/Financials!S6-1 -> #REF! | U26: =Financials!#REF!/Financials!T6-1 -> #REF! | V26: =Financials!#REF!/Financials!U6-1 -> #REF! | W26: =Financials!#REF!/Financials!V6-1 -> #REF! | X26: =Financials!#REF!/Financials!W6-1 -> #REF! | Y26: =Financials!#REF!/Financials!X6-1 -> #REF! | Z26: =Financials!#REF!/Financials!Y6-1 -> #REF! | ... CN26: =Financials!#REF!/Financials!CM6-1 -> #REF!
B27: FOSA Deposits | D27: =Financials!D7/Financials!C7-1 -> #REF! | E27: =Financials!G7/Financials!D7-1 -> #REF! | F27: =Financials!H7/Financials!G7-1 -> #REF! | G27: =Financials!H7/Financials!G7-1 -> #REF! | H27: =Financials!H7/Financials!G7-1 -> #REF! | I27: =Financials!I7/Financials!H7-1 -> #REF! | J27: =Financials!J7/Financials!I7-1 -> #REF! | K27: =Financials!K7/Financials!J7-1 -> #REF! | L27: =Financials!L7/Financials!K7-1 -> #REF! | M27: =Financials!M7/Financials!L7-1 -> #REF! | N27: =Financials!N7/Financials!M7-1 -> #REF! | O27: =Financials!O7/Financials!N7-1 -> #REF! | ... R27: =Financials!R7/Financials!Q7-1 -> #REF! | S27: =Financials!#REF!/Financials!R7-1 -> #REF! | T27: =Financials!#REF!/Financials!S7-1 -> #REF! | U27: =Financials!#REF!/Financials!T7-1 -> #REF! | V27: =Financials!#REF!/Financials!U7-1 -> #REF! | W27: =Financials!#REF!/Financials!V7-1 -> #REF! | X27: =Financials!#REF!/Financials!W7-1 -> #REF! | Y27: =Financials!#REF!/Financials!X7-1 -> #REF! | Z27: =Financials!#REF!/Financials!Y7-1 -> #REF! | ... CN27: =Financials!#REF!/Financials!CM7-1 -> #REF!
B28: Total Loans & advances | D28: =Financials!D31/Financials!C31-1 -> #REF! | E28: =Financials!G31/Financials!D31-1 -> #REF! | F28: =Financials!H31/Financials!G31-1 -> #REF! | G28: =Financials!H31/Financials!G31-1 -> #REF! | H28: =Financials!H31/Financials!G31-1 -> #REF! | I28: =Financials!I31/Financials!H31-1 -> #REF! | J28: =Financials!J31/Financials!I31-1 -> #REF! | K28: =Financials!K31/Financials!J31-1 -> #REF! | L28: =Financials!L31/Financials!K31-1 -> #REF! | M28: =Financials!M31/Financials!L31-1 -> #REF! | N28: =Financials!N31/Financials!M31-1 -> #REF! | O28: =Financials!O31/Financials!N31-1 -> #REF! | ... R28: =Financials!R31/Financials!Q31-1 -> #REF! | S28: =Financials!#REF!/Financials!R31-1 -> #REF! | T28: =Financials!#REF!/Financials!S31-1 -> #REF! | U28: =Financials!#REF!/Financials!T31-1 -> #REF! | V28: =Financials!#REF!/Financials!U31-1 -> #REF! | W28: =Financials!#REF!/Financials!V31-1 -> #REF! | X28: =Financials!#REF!/Financials!W31-1 -> #REF! | Y28: =Financials!#REF!/Financials!X31-1 -> #REF! | Z28: =Financials!#REF!/Financials!Y31-1 -> #REF! | ... CN28: =Financials!#REF!/Financials!CM31-1 -> #REF!
B29: Core capital | D29: =Financials!D11/Financials!C11-1 -> #REF! | E29: =Financials!G11/Financials!D11-1 -> #REF! | F29: =Financials!H11/Financials!G11-1 -> #REF! | G29: =Financials!H11/Financials!G11-1 -> #REF! | H29: =Financials!H11/Financials!G11-1 -> #REF! | I29: =Financials!I11/Financials!H11-1 -> #REF! | J29: =Financials!J11/Financials!I11-1 -> #REF! | K29: =Financials!K11/Financials!J11-1 -> #REF! | L29: =Financials!L11/Financials!K11-1 -> #REF! | M29: =Financials!M11/Financials!L11-1 -> #REF! | N29: =Financials!N11/Financials!M11-1 -> #REF! | O29: =Financials!O11/Financials!N11-1 -> #REF! | ... R29: =Financials!R11/Financials!Q11-1 -> #REF! | S29: =Financials!#REF!/Financials!R11-1 -> #REF! | T29: =Financials!#REF!/Financials!S11-1 -> #REF! | U29: =Financials!#REF!/Financials!T11-1 -> #REF! | V29: =Financials!#REF!/Financials!U11-1 -> #REF! | W29: =Financials!#REF!/Financials!V11-1 -> #REF! | X29: =Financials!#REF!/Financials!W11-1 -> #REF! | Y29: =Financials!#REF!/Financials!X11-1 -> #REF! | Z29: =Financials!#REF!/Financials!Y11-1 -> #REF! | ... CN29: =Financials!#REF!/Financials!CM11-1 -> #REF!
B30: Turnover | D30: =Financials!D37/Financials!C37-1 -> #REF! | E30: =Financials!G37/Financials!D37-1 -> #REF! | F30: =Financials!H37/Financials!G37-1 -> #REF! | G30: =Financials!H37/Financials!G37-1 -> #REF! | H30: =Financials!H37/Financials!G37-1 -> #REF! | I30: =Financials!I37/Financials!H37-1 -> #REF! | J30: =Financials!J37/Financials!I37-1 -> #REF! | K30: =Financials!K37/Financials!J37-1 -> #REF! | L30: =Financials!L37/Financials!K37-1 -> #REF! | M30: =Financials!M37/Financials!L37-1 -> #REF! | N30: =Financials!N37/Financials!M37-1 -> #REF! | O30: =Financials!O37/Financials!N37-1 -> #REF! | ... R30: =Financials!R37/Financials!Q37-1 -> #REF! | S30: =Financials!#REF!/Financials!R37-1 -> #REF! | T30: =Financials!#REF!/Financials!S37-1 -> #REF! | U30: =Financials!#REF!/Financials!T37-1 -> #REF! | V30: =Financials!#REF!/Financials!U37-1 -> #REF! | W30: =Financials!#REF!/Financials!V37-1 -> #REF! | X30: =Financials!#REF!/Financials!W37-1 -> #REF! | Y30: =Financials!#REF!/Financials!X37-1 -> #REF! | Z30: =Financials!#REF!/Financials!Y37-1 -> #REF! | ... CN30: =Financials!#REF!/Financials!CM37-1 -> #REF!
B31: Membership
B32: Expenses | D32: ='Evolutitve SCI'!#REF!/'Evolutitve SCI'!#REF!-1 -> #REF! | E32: ='Evolutitve SCI'!#REF!/'Evolutitve SCI'!#REF!-1 -> #REF! | F32: ='Evolutitve SCI'!#REF!/'Evolutitve SCI'!#REF!-1 -> #REF! | G32: ='Evolutitve SCI'!#REF!/'Evolutitve SCI'!#REF!-1 -> #REF! | H32: ='Evolutitve SCI'!#REF!/'Evolutitve SCI'!#REF!-1 -> #REF! | I32: ='Evolutitve SCI'!#REF!/'Evolutitve SCI'!#REF!-1 -> #REF! | J32: ='Evolutitve SCI'!#REF!/'Evolutitve SCI'!#REF!-1 -> #REF! | K32: ='Evolutitve SCI'!#REF!/'Evolutitve SCI'!#REF!-1 -> #REF! | ... AS32: ='Evolutitve SCI'!#REF!/'Evolutitve SCI'!#REF!-1 -> #REF! | AT32: ='Evolutitve SCI'!#REF!/'Evolutitve SCI'!AG39-1 -> #REF! | AU32: ='Evolutitve SCI'!#REF!/'Evolutitve SCI'!AH39-1 -> #REF! | AV32: ='Evolutitve SCI'!#REF!/'Evolutitve SCI'!AI39-1 -> #REF! | AW32: ='Evolutitve SCI'!#REF!/'Evolutitve SCI'!AJ39-1 -> #REF! | AX32: ='Evolutitve SCI'!#REF!/'Evolutitve SCI'!AK39-1 -> #REF! | AY32: ='Evolutitve SCI'!#REF!/'Evolutitve SCI'!AL39-1 -> #REF! | AZ32: ='Evolutitve SCI'!#REF!/'Evolutitve SCI'!AM39-1 -> #REF! | BA32: ='Evolutitve SCI'!#REF!/'Evolutitve SCI'!#REF!-1 -> #REF! | BB32: ='Evolutitve SCI'!#REF!/'Evolutitve SCI'!AN39-1 -> #REF! | BC32: ='Evolutitve SCI'!#REF!/'Evolutitve SCI'!AO39-1 -> #REF! | BD32: ='Evolutitve SCI'!#REF!/'Evolutitve SCI'!AP39-1 -> #REF! | BE32: ='Evolutitve SCI'!#REF!/'Evolutitve SCI'!AQ39-1 -> #REF! | BF32: ='Evolutitve SCI'!#REF!/'Evolutitve SCI'!AR39-1 -> #REF! | BG32: ='Evolutitve SCI'!#REF!/'Evolutitve SCI'!AS39-1 -> #REF! | BH32: ='Evolutitve SCI'!#REF!/'Evolutitve SCI'!AT39-1 -> #REF! | BI32: ='Evolutitve SCI'!#REF!/'Evolutitve SCI'!AU39-1 -> #REF! | ... CN32: ='Evolutitve SCI'!#REF!/'Evolutitve SCI'!BZ39-1 -> #REF!
A33: Efficiency Ratios | B33: FinCost-Deposits/Avg Deposits | E33: =Financials!D44/('Evolutive SFP'!#REF!+'Evolutive SFP'!#REF!)/2 -> #REF! | H33: =Financials!G44/('Evolutive SFP'!#REF!+'Evolutive SFP'!#REF!)/2 -> #REF! | I33: =Financials!H44/('Evolutive SFP'!#REF!+'Evolutive SFP'!#REF!)/2 -> #REF! | J33: =Financials!I44/('Evolutive SFP'!#REF!+'Evolutive SFP'!#REF!)/2 -> #REF! | K33: =Financials!J44/('Evolutive SFP'!#REF!+'Evolutive SFP'!#REF!)/2 -> #REF! | L33: =Financials!K44/('Evolutive SFP'!#REF!+'Evolutive SFP'!#REF!)/2 -> #REF! | M33: =Financials!L44/('Evolutive SFP'!#REF!+'Evolutive SFP'!#REF!)/2 -> #REF! | N33: =Financials!M44/('Evolutive SFP'!#REF!+'Evolutive SFP'!#REF!)/2 -> #REF! | O33: =Financials!N44/('Evolutive SFP'!#REF!+'Evolutive SFP'!#REF!)/2 -> #REF! | ... AS33: =Financials!AR44/('Evolutive SFP'!#REF!+'Evolutive SFP'!#REF!)/2 -> #REF! | AT33: =Financials!AS44/('Evolutive SFP'!#REF!+'Evolutive SFP'!AH30)/2 -> #REF! | AU33: =Financials!AT44/('Evolutive SFP'!AH30+'Evolutive SFP'!AI30)/2 -> 6.821277e-05 | AV33: =Financials!AU44/('Evolutive SFP'!AI30+'Evolutive SFP'!AJ30)/2 -> 0.00012279459 | AW33: =Financials!AV44/('Evolutive SFP'!AJ30+'Evolutive SFP'!AK30)/2 -> 0.00019326396 | AX33: =Financials!AW44/('Evolutive SFP'!AK30+'Evolutive SFP'!AL30)/2 -> 0.00040902948 | AY33: =Financials!AX44/('Evolutive SFP'!AL30+'Evolutive SFP'!AM30)/2 -> 0.00043321314 | AZ33: =Financials!AY44/('Evolutive SFP'!AM30+'Evolutive SFP'!AN30)/2 -> 0.00094493904 | BA33: =Financials!AZ44/('Evolutive SFP'!AN30+'Evolutive SFP'!#REF!)/2 -> #REF! | BB33: =Financials!BA44/('Evolutive SFP'!#REF!+'Evolutive SFP'!AO30)/2 -> #REF! | BC33: =Financials!BB44/('Evolutive SFP'!AO30+'Evolutive SFP'!AP30)/2 -> 0.0014198239 | BD33: =Financials!BC44/('Evolutive SFP'!AP30+'Evolutive SFP'!AQ30)/2 -> 0.0014730246 | BE33: =Financials!BD44/('Evolutive SFP'!AQ30+'Evolutive SFP'!AR30)/2 -> 0.0014963886 | BF33: =Financials!BE44/('Evolutive SFP'!AR30+'Evolutive SFP'!AS30)/2 -> 0.0045067577 | BG33: =Financials!BF44/('Evolutive SFP'!AS30+'Evolutive SFP'!AT30)/2 -> 0.022406505 | BH33: =Financials!BG44/('Evolutive SFP'!AT30+'Evolutive SFP'!AU30)/2 -> 7.2673758e-05 | BI33: =Financials!BH44/('Evolutive SFP'!AU30+'Evolutive SFP'!AV30)/2 -> 0.00085935724 | BJ33: =Financials!BI44/('Evolutive SFP'!AV30+'Evolutive SFP'!AW30)/2 -> 0.00095403065 | ... CN33: =Financials!CM44/('Evolutive SFP'!BZ30+'Evolutive SFP'!CA30)/2 -> 1.4321523e-05
B34: FinCost-Shares/Avg Share capital | E34: =Financials!D45/('Evolutive SFP'!#REF!+'Evolutive SFP'!#REF!)/2 -> #REF! | H34: =Financials!G45/('Evolutive SFP'!#REF!+'Evolutive SFP'!#REF!)/2 -> #REF! | I34: =Financials!H45/('Evolutive SFP'!#REF!+'Evolutive SFP'!#REF!)/2 -> #REF! | J34: =Financials!I45/('Evolutive SFP'!#REF!+'Evolutive SFP'!#REF!)/2 -> #REF! | K34: =Financials!J45/('Evolutive SFP'!#REF!+'Evolutive SFP'!#REF!)/2 -> #REF! | L34: =Financials!K45/('Evolutive SFP'!#REF!+'Evolutive SFP'!#REF!)/2 -> #REF! | M34: =Financials!L45/('Evolutive SFP'!#REF!+'Evolutive SFP'!#REF!)/2 -> #REF! | N34: =Financials!M45/('Evolutive SFP'!#REF!+'Evolutive SFP'!#REF!)/2 -> #REF! | O34: =Financials!N45/('Evolutive SFP'!#REF!+'Evolutive SFP'!#REF!)/2 -> #REF! | ... AS34: =Financials!AR45/('Evolutive SFP'!#REF!+'Evolutive SFP'!#REF!)/2 -> #REF! | AT34: =Financials!AS45/('Evolutive SFP'!#REF!+'Evolutive SFP'!AH39)/2 -> #REF! | AU34: =Financials!AT45/('Evolutive SFP'!AH39+'Evolutive SFP'!AI39)/2 -> 0 | AV34: =Financials!AU45/('Evolutive SFP'!AI39+'Evolutive SFP'!AJ39)/2 -> 0 | AW34: =Financials!AV45/('Evolutive SFP'!AJ39+'Evolutive SFP'!AK39)/2 -> 0 | AX34: =Financials!AW45/('Evolutive SFP'!AK39+'Evolutive SFP'!AL39)/2 -> 0 | AY34: =Financials!AX45/('Evolutive SFP'!AL39+'Evolutive SFP'!AM39)/2 -> 0 | AZ34: =Financials!AY45/('Evolutive SFP'!AM39+'Evolutive SFP'!AN39)/2 -> 0 | BA34: =Financials!AZ45/('Evolutive SFP'!AN39+'Evolutive SFP'!#REF!)/2 -> #REF! | BB34: =Financials!BA45/('Evolutive SFP'!#REF!+'Evolutive SFP'!AO39)/2 -> #REF! | BC34: =Financials!BB45/('Evolutive SFP'!AO39+'Evolutive SFP'!AP39)/2 -> 0 | BD34: =Financials!BC45/('Evolutive SFP'!AP39+'Evolutive SFP'!AQ39)/2 -> 0 | BE34: =Financials!BD45/('Evolutive SFP'!AQ39+'Evolutive SFP'!AR39)/2 -> 0 | BF34: =Financials!BE45/('Evolutive SFP'!AR39+'Evolutive SFP'!AS39)/2 -> 0 | BG34: =Financials!BF45/('Evolutive SFP'!AS39+'Evolutive SFP'!AT39)/2 -> 0 | BH34: =Financials!BG45/('Evolutive SFP'!AT39+'Evolutive SFP'!AU39)/2 -> 0 | BI34: =Financials!BH45/('Evolutive SFP'!AU39+'Evolutive SFP'!AV39)/2 -> 0 | BJ34: =Financials!BI45/('Evolutive SFP'!AV39+'Evolutive SFP'!AW39)/2 -> 0 | ... CN34: =Financials!CM45/('Evolutive SFP'!BZ39+'Evolutive SFP'!CA39)/2 -> 0
B35: FinCost-Ext Loans/Avg Ext Loans | E35: =Financials!D46/(Financials!C31+Financials!D31)/2 -> #REF! | H35: =Financials!G46/(Financials!D31+Financials!G31)/2 -> #REF! | I35: =Financials!H46/(Financials!G31+Financials!H31)/2 -> #REF! | J35: =Financials!I46/(Financials!H31+Financials!I31)/2 -> #REF! | K35: =Financials!J46/(Financials!I31+Financials!J31)/2 -> #REF! | L35: =Financials!K46/(Financials!J31+Financials!K31)/2 -> #REF! | M35: =Financials!L46/(Financials!K31+Financials!L31)/2 -> #REF! | N35: =Financials!M46/(Financials!L31+Financials!M31)/2 -> #REF! | O35: =Financials!N46/(Financials!M31+Financials!N31)/2 -> #REF! | P35: =Financials!O46/(Financials!N31+Financials!O31)/2 -> #REF! | ... CN35: =Financials!CM46/(Financials!CL31+Financials!CM31)/2 -> 0
B36: OpEx/Average Total Assets | E36: =Financials!D47/(Financials!C4+Financials!D4)/2 -> #REF! | H36: =Financials!G47/(Financials!D4+Financials!G4)/2 -> #REF! | I36: =Financials!H47/(Financials!G4+Financials!H4)/2 -> #REF! | J36: =Financials!I47/(Financials!H4+Financials!I4)/2 -> #REF! | K36: =Financials!J47/(Financials!I4+Financials!J4)/2 -> #REF! | L36: =Financials!K47/(Financials!J4+Financials!K4)/2 -> #REF! | M36: =Financials!L47/(Financials!K4+Financials!L4)/2 -> #REF! | N36: =Financials!M47/(Financials!L4+Financials!M4)/2 -> #REF! | O36: =Financials!N47/(Financials!M4+Financials!N4)/2 -> #REF! | P36: =Financials!O47/(Financials!N4+Financials!O4)/2 -> #REF! | ... CN36: =Financials!CM47/(Financials!CL4+Financials!CM4)/2 -> 0.010378484
B37: Opex/Turnover | E37: =Financials!D47/Financials!D37 -> #REF! | H37: =Financials!G47/Financials!G37 -> #REF! | I37: =Financials!H47/Financials!H37 -> #REF! | J37: =Financials!I47/Financials!I37 -> #REF! | K37: =Financials!J47/Financials!J37 -> #REF! | L37: =Financials!K47/Financials!K37 -> #REF! | M37: =Financials!L47/Financials!L37 -> #REF! | N37: =Financials!M47/Financials!M37 -> #REF! | O37: =Financials!N47/Financials!N37 -> #REF! | ... CN37: =Financials!CM47/Financials!CM37 -> 0.48342607
B38: Avge yield on Net loans | E38: =Financials!D38/('Evolutive SFP'!#REF!+'Evolutive SFP'!#REF!)/2 -> #REF! | H38: =Financials!G38/('Evolutive SFP'!#REF!+'Evolutive SFP'!#REF!)/2 -> #REF! | I38: =Financials!H38/('Evolutive SFP'!#REF!+'Evolutive SFP'!#REF!)/2 -> #REF! | J38: =Financials!I38/('Evolutive SFP'!#REF!+'Evolutive SFP'!#REF!)/2 -> #REF! | K38: =Financials!J38/('Evolutive SFP'!#REF!+'Evolutive SFP'!#REF!)/2 -> #REF! | L38: =Financials!K38/('Evolutive SFP'!#REF!+'Evolutive SFP'!#REF!)/2 -> #REF! | M38: =Financials!L38/('Evolutive SFP'!#REF!+'Evolutive SFP'!#REF!)/2 -> #REF! | N38: =Financials!M38/('Evolutive SFP'!#REF!+'Evolutive SFP'!#REF!)/2 -> #REF! | O38: =Financials!N38/('Evolutive SFP'!#REF!+'Evolutive SFP'!#REF!)/2 -> #REF! | ... AS38: =Financials!AR38/('Evolutive SFP'!#REF!+'Evolutive SFP'!#REF!)/2 -> #REF! | AT38: =Financials!AS38/('Evolutive SFP'!AH14+'Evolutive SFP'!#REF!)/2 -> #REF! | AU38: =Financials!AT38/('Evolutive SFP'!AI14+'Evolutive SFP'!AH14)/2 -> 0.0024793734 | AV38: =Financials!AU38/('Evolutive SFP'!AJ14+'Evolutive SFP'!AI14)/2 -> 0.0045648389 | AW38: =Financials!AV38/('Evolutive SFP'!AK14+'Evolutive SFP'!AJ14)/2 -> 0.0065969433 | AX38: =Financials!AW38/('Evolutive SFP'!AL14+'Evolutive SFP'!AK14)/2 -> 0.0089148239 | AY38: =Financials!AX38/('Evolutive SFP'!AM14+'Evolutive SFP'!AL14)/2 -> 0.011506165 | AZ38: =Financials!AY38/('Evolutive SFP'!AN14+'Evolutive SFP'!AM14)/2 -> 0.013842694 | BA38: =Financials!AZ38/('Evolutive SFP'!#REF!+'Evolutive SFP'!AN14)/2 -> #REF! | BB38: =Financials!BA38/('Evolutive SFP'!AO14+'Evolutive SFP'!#REF!)/2 -> #REF! | BC38: =Financials!BB38/('Evolutive SFP'!AP14+'Evolutive SFP'!AO14)/2 -> 0.020270247 | BD38: =Financials!BC38/('Evolutive SFP'!AQ14+'Evolutive SFP'!AP14)/2 -> 0.023443567 | BE38: =Financials!BD38/('Evolutive SFP'!AR14+'Evolutive SFP'!AQ14)/2 -> 0.027290818 | BF38: =Financials!BE38/('Evolutive SFP'!AS14+'Evolutive SFP'!AR14)/2 -> 0.028989963 | BG38: =Financials!BF38/('Evolutive SFP'!AT14+'Evolutive SFP'!AS14)/2 -> 0.028231193 | BH38: =Financials!BG38/('Evolutive SFP'!AU14+'Evolutive SFP'!AT14)/2 -> 0.00013262198 | BI38: =Financials!BH38/('Evolutive SFP'!AV14+'Evolutive SFP'!AU14)/2 -> 0.0022673012 | BJ38: =Financials!BI38/('Evolutive SFP'!AW14+'Evolutive SFP'!AV14)/2 -> 0.0070344426 | ... CN38: =Financials!CM38/('Evolutive SFP'!CA14+'Evolutive SFP'!BZ14)/2 -> 0.020219682
B39: Avge yield on Gross loans | E39: =Financials!D37/('Evolutive SFP'!#REF!+'Evolutive SFP'!#REF!)/2 -> #REF! | H39: =Financials!G37/('Evolutive SFP'!#REF!+'Evolutive SFP'!#REF!)/2 -> #REF! | I39: =Financials!H37/('Evolutive SFP'!#REF!+'Evolutive SFP'!#REF!)/2 -> #REF! | J39: =Financials!I37/('Evolutive SFP'!#REF!+'Evolutive SFP'!#REF!)/2 -> #REF! | K39: =Financials!J37/('Evolutive SFP'!#REF!+'Evolutive SFP'!#REF!)/2 -> #REF! | L39: =Financials!K37/('Evolutive SFP'!#REF!+'Evolutive SFP'!#REF!)/2 -> #REF! | M39: =Financials!L37/('Evolutive SFP'!#REF!+'Evolutive SFP'!#REF!)/2 -> #REF! | N39: =Financials!M37/('Evolutive SFP'!#REF!+'Evolutive SFP'!#REF!)/2 -> #REF! | O39: =Financials!N37/('Evolutive SFP'!#REF!+'Evolutive SFP'!#REF!)/2 -> #REF! | ... AS39: =Financials!AR37/('Evolutive SFP'!#REF!+'Evolutive SFP'!#REF!)/2 -> #REF! | AT39: =Financials!AS37/('Evolutive SFP'!AH15+'Evolutive SFP'!#REF!)/2 -> #REF! | AU39: =Financials!AT37/('Evolutive SFP'!AI15+'Evolutive SFP'!AH15)/2 -> 0.0047772763 | AV39: =Financials!AU37/('Evolutive SFP'!AJ15+'Evolutive SFP'!AI15)/2 -> 0.009270399 | AW39: =Financials!AV37/('Evolutive SFP'!AK15+'Evolutive SFP'!AJ15)/2 -> 0.014613032 | AX39: =Financials!AW37/('Evolutive SFP'!AL15+'Evolutive SFP'!AK15)/2 -> 0.018303338 | AY39: =Financials!AX37/('Evolutive SFP'!AM15+'Evolutive SFP'!AL15)/2 -> 0.023802924 | AZ39: =Financials!AY37/('Evolutive SFP'!AN15+'Evolutive SFP'!AM15)/2 -> 0.028826754 | BA39: =Financials!AZ37/('Evolutive SFP'!#REF!+'Evolutive SFP'!AN15)/2 -> #REF! | BB39: =Financials!BA37/('Evolutive SFP'!AO15+'Evolutive SFP'!#REF!)/2 -> #REF! | BC39: =Financials!BB37/('Evolutive SFP'!AP15+'Evolutive SFP'!AO15)/2 -> 0.043554106 | BD39: =Financials!BC37/('Evolutive SFP'!AQ15+'Evolutive SFP'!AP15)/2 -> 0.047677854 | BE39: =Financials!BD37/('Evolutive SFP'!AR15+'Evolutive SFP'!AQ15)/2 -> 0.052222662 | BF39: =Financials!BE37/('Evolutive SFP'!AS15+'Evolutive SFP'!AR15)/2 -> 0.056970408 | BG39: =Financials!BF37/('Evolutive SFP'!AT15+'Evolutive SFP'!AS15)/2 -> 0.067166936 | BH39: =Financials!BG37/('Evolutive SFP'!AU15+'Evolutive SFP'!AT15)/2 -> 0.0015343637 | BI39: =Financials!BH37/('Evolutive SFP'!AV15+'Evolutive SFP'!AU15)/2 -> 0.0059229325 | BJ39: =Financials!BI37/('Evolutive SFP'!AW15+'Evolutive SFP'!AV15)/2 -> 0.012899549 | ... CN39: =Financials!CM37/('Evolutive SFP'!CA15+'Evolutive SFP'!BZ15)/2 -> 0.0453699
A41: ALL/Average Gross Loan portfolio

Sheet Financials
B1: KORU Sacco Financial Performance
B2: Year | C2: 2013 Audited | D2: 2014 Audited | E2: 2015 Audited | F2: 2016 Audited | G2: 42736 | H2: 42767 | I2: 42795 | J2: 42826 | K2: 42856 | L2: 42887 | M2: 42917 | N2: 42948 | O2: 42979 | P2: 43009 | Q2: 43040 | R2: 43070 | S2: Audited 2017 | T2: 43101 | U2: 43132 | V2: 43160 | W2: 43191 | X2: 43221 | Y2: 43252 | Z2: 43282 | AA2: 43313 | AB2: 43344 | AC2: 43374 | AD2: 43405 | AE2: 43435 | AF2: Audited 2018 | AG2: 43466 | AH2: 43497 | AI2: 43525 | AJ2: 43556 | AK2: 43586 | AL2: 43617 | AM2: 43647 | AN2: 43678 | AO2: 43709 | AP2: 43739 | AQ2: 43770 | AR2: 43800 | AS2: Audited 2019 | AT2: 43831 | AU2: 43862 | AV2: 43891 | AW2: 43922 | AX2: 43952 | AY2: 43983 | AZ2: 44013 | BA2: 44044 | BB2: 44075 | BC2: 44105 | BD2: 44136 | BE2: 44166 | BF2: Audited 2020 | BG2: 44197 | BH2: 44228 | BI2: 44256 | BJ2: 44287 | BK2: 44317 | BL2: 44348 | BM2: 44378 | BN2: 44409 | BO2: 44440 | BP2: 44470 | BQ2: 44501 | BR2: 44531 | BS2: Audited 2021 | CF2: Audited 2022 | CG2: 44927 | CH2: 44958 | CI2: 44986 | CJ2: 45017 | CK2: 45047 | CL2: 45078 | CM2: 45108 | CN2: 45139 | CO2: 45170
A3: 1 | B3: Membership | D3: 39898 | E3: 55854
A4: 2 | B4: Total Assets | C4: ='Evolutive SFP'!#REF! -> #REF! | D4: ='Evolutive SFP'!#REF! -> #REF! | E4: ='Evolutive SFP'!#REF! -> #REF! | F4: ='Evolutive SFP'!#REF! -> #REF! | G4: ='Evolutive SFP'!#REF! -> #REF! | H4: ='Evolutive SFP'!#REF! -> #REF! | I4: ='Evolutive SFP'!#REF! -> #REF! | J4: ='Evolutive SFP'!#REF! -> #REF! | ... AR4: ='Evolutive SFP'!#REF! -> #REF! | AS4: ='Evolutive SFP'!AH27 -> 71219457 | AT4: ='Evolutive SFP'!AI27 -> 77208115 | AU4: ='Evolutive SFP'!AJ27 -> 79130341 | AV4: ='Evolutive SFP'!AK27 -> 76463792 | AW4: ='Evolutive SFP'!AL27 -> 76591043 | AX4: ='Evolutive SFP'!AM27 -> 78736314 | AY4: ='Evolutive SFP'!AN27 -> 78045413 | AZ4: ='Evolutive SFP'!#REF! -> #REF! | BA4: ='Evolutive SFP'!AO27 -> 79964668 | BB4: ='Evolutive SFP'!AP27 -> 79652385 | BC4: ='Evolutive SFP'!AQ27 -> 76942975 | BD4: ='Evolutive SFP'!AR27 -> 79457489 | BE4: ='Evolutive SFP'!AS27 -> 74364821 | BF4: ='Evolutive SFP'!AT27 -> 74350533 | BG4: ='Evolutive SFP'!AU27 -> 73634272 | BH4: ='Evolutive SFP'!AV27 -> 73804395 | ... CO4: ='Evolutive SFP'!CC27 -> 77940186
A5: 3 | B5: Total Deposits | C5: ='Evolutive SFP'!#REF! -> #REF! | D5: ='Evolutive SFP'!#REF! -> #REF! | E5: ='Evolutive SFP'!#REF! -> #REF! | F5: ='Evolutive SFP'!#REF! -> #REF! | G5: ='Evolutive SFP'!#REF! -> #REF! | H5: ='Evolutive SFP'!#REF! -> #REF! | I5: ='Evolutive SFP'!#REF! -> #REF! | J5: ='Evolutive SFP'!#REF! -> #REF! | ... AR5: ='Evolutive SFP'!#REF! -> #REF! | AS5: ='Evolutive SFP'!AH31 -> 47813288 | AT5: ='Evolutive SFP'!AI31 -> 50050280 | AU5: ='Evolutive SFP'!AJ31 -> 51594784 | AV5: ='Evolutive SFP'!AK31 -> 48617538 | AW5: ='Evolutive SFP'!AL31 -> 50784185 | AX5: ='Evolutive SFP'!AM31 -> 52670580 | AY5: ='Evolutive SFP'!AN31 -> 51541572 | AZ5: ='Evolutive SFP'!#REF! -> #REF! | BA5: ='Evolutive SFP'!AO31 -> 52864499 | BB5: ='Evolutive SFP'!AP31 -> 52435662 | BC5: ='Evolutive SFP'!AQ31 -> 52696820 | BD5: ='Evolutive SFP'!AR31 -> 54876771 | BE5: ='Evolutive SFP'!AS31 -> 49343099 | BF5: ='Evolutive SFP'!AT31 -> 49343099 | BG5: ='Evolutive SFP'!AU31 -> 49066289 | BH5: ='Evolutive SFP'!AV31 -> 48855091 | ... CO5: ='Evolutive SFP'!CC31 -> 51885876
A6: 3.1 | B6: Deposits-Members(BOSA) | C6: ='Evolutive SFP'!#REF! -> #REF! | D6: ='Evolutive SFP'!#REF! -> #REF! | E6: ='Evolutive SFP'!#REF! -> #REF! | F6: ='Evolutive SFP'!#REF! -> #REF! | G6: ='Evolutive SFP'!#REF! -> #REF! | H6: ='Evolutive SFP'!#REF! -> #REF! | I6: ='Evolutive SFP'!#REF! -> #REF! | J6: ='Evolutive SFP'!#REF! -> #REF! | ... AR6: ='Evolutive SFP'!#REF! -> #REF! | AS6: ='Evolutive SFP'!AH30 -> 39316438 | AT6: ='Evolutive SFP'!AI30 -> 39319865 | AU6: ='Evolutive SFP'!AJ30 -> 39445819 | AV6: ='Evolutive SFP'!AK30 -> 39673950 | AW6: ='Evolutive SFP'!AL30 -> 40064569 | AX6: ='Evolutive SFP'!AM30 -> 40137074 | AY6: ='Evolutive SFP'!AN30 -> 40546454 | AZ6: ='Evolutive SFP'!#REF! -> #REF! | BA6: ='Evolutive SFP'!AO30 -> 40731541 | BB6: ='Evolutive SFP'!AP30 -> 41031928 | BC6: ='Evolutive SFP'!AQ30 -> 41384370 | BD6: ='Evolutive SFP'!AR30 -> 41334696 | BE6: ='Evolutive SFP'!AS30 -> 41809421 | BF6: ='Evolutive SFP'!AT30 -> 41809421 | BG6: ='Evolutive SFP'!AU30 -> 41852139 | BH6: ='Evolutive SFP'!AV30 -> 42191489 | ... CO6: ='Evolutive SFP'!CC30 -> 43270702
A7: 3.2 | B7: Deposits-Customers(FOSA) | C7: =('Evolutive SFP'!#REF!+'Evolutive SFP'!#REF!) -> #REF! | D7: =('Evolutive SFP'!#REF!+'Evolutive SFP'!#REF!) -> #REF! | E7: =('Evolutive SFP'!#REF!+'Evolutive SFP'!#REF!) -> #REF! | F7: =('Evolutive SFP'!#REF!+'Evolutive SFP'!#REF!) -> #REF! | G7: =('Evolutive SFP'!#REF!+'Evolutive SFP'!#REF!) -> #REF! | H7: =('Evolutive SFP'!#REF!+'Evolutive SFP'!#REF!) -> #REF! | I7: =('Evolutive SFP'!#REF!+'Evolutive SFP'!#REF!) -> #REF! | J7: =('Evolutive SFP'!#REF!+'Evolutive SFP'!#REF!) -> #REF! | ... AR7: =('Evolutive SFP'!#REF!+'Evolutive SFP'!#REF!) -> #REF! | AS7: =('Evolutive SFP'!AH28+'Evolutive SFP'!AH29) -> 8496850 | AT7: =('Evolutive SFP'!AI28+'Evolutive SFP'!AI29) -> 10730415 | AU7: =('Evolutive SFP'!AJ28+'Evolutive SFP'!AJ29) -> 12148965 | AV7: =('Evolutive SFP'!AK28+'Evolutive SFP'!AK29) -> 8943587.6 | AW7: =('Evolutive SFP'!AL28+'Evolutive SFP'!AL29) -> 10719616 | AX7: =('Evolutive SFP'!AM28+'Evolutive SFP'!AM29) -> 12533506 | AY7: =('Evolutive SFP'!AN28+'Evolutive SFP'!AN29) -> 10995118 | AZ7: =('Evolutive SFP'!#REF!+'Evolutive SFP'!#REF!) -> #REF! | BA7: =('Evolutive SFP'!AO28+'Evolutive SFP'!AO29) -> 12132958 | BB7: =('Evolutive SFP'!AP28+'Evolutive SFP'!AP29) -> 11403734 | BC7: =('Evolutive SFP'!AQ28+'Evolutive SFP'!AQ29) -> 11312451 | BD7: =('Evolutive SFP'!AR28+'Evolutive SFP'!AR29) -> 13542075 | BE7: =('Evolutive SFP'!AS28+'Evolutive SFP'!AS29) -> 7533677.3 | BF7: =('Evolutive SFP'!AT28+'Evolutive SFP'!AT29) -> 7533678 | BG7: =('Evolutive SFP'!AU28+'Evolutive SFP'!AU29) -> 7214150.1 | BH7: =('Evolutive SFP'!AV28+'Evolutive SFP'!AV29) -> 6663602.5 | ... CO7: =('Evolutive SFP'!CC28+'Evolutive SFP'!CC29) -> 8615174.7
A8: 4 | B8: External Borrowing | C8: ='Evolutive SFP'!#REF! -> #REF! | D8: ='Evolutive SFP'!#REF! -> #REF! | E8: ='Evolutive SFP'!#REF! -> #REF! | F8: ='Evolutive SFP'!#REF! -> #REF! | G8: ='Evolutive SFP'!#REF! -> #REF! | H8: ='Evolutive SFP'!#REF! -> #REF! | I8: ='Evolutive SFP'!#REF! -> #REF! | J8: ='Evolutive SFP'!#REF! -> #REF! | ... AR8: ='Evolutive SFP'!#REF! -> #REF! | AS8: ='Evolutive SFP'!AH37 -> 0 | AT8: ='Evolutive SFP'!AI37 -> 0 | AU8: ='Evolutive SFP'!AJ37 -> 0 | AV8: ='Evolutive SFP'!AK37 -> 0 | AW8: ='Evolutive SFP'!AL37 -> 0 | AX8: ='Evolutive SFP'!AM37 -> 0 | AY8: ='Evolutive SFP'!AN37 -> 0 | AZ8: ='Evolutive SFP'!#REF! -> #REF! | BA8: ='Evolutive SFP'!AO37 -> 0 | BB8: ='Evolutive SFP'!AP37 -> 0 | BC8: ='Evolutive SFP'!AQ37 -> 0 | BD8: ='Evolutive SFP'!AR37 -> 0 | BE8: ='Evolutive SFP'!AS37 -> 0 | BF8: ='Evolutive SFP'!AT37 -> 0 | BG8: ='Evolutive SFP'!AU37 -> 0 | BH8: ='Evolutive SFP'!AV37 -> 0 | ... CO8: ='Evolutive SFP'!CC37 -> 0
B9: Short term Liabilities | D9: =SUM('Evolutive SFP'!#REF!) -> #REF! | E9: =SUM('Evolutive SFP'!#REF!) -> #REF! | F9: =SUM('Evolutive SFP'!#REF!) -> #REF! | G9: =SUM('Evolutive SFP'!#REF!) -> #REF! | H9: =SUM('Evolutive SFP'!#REF!) -> #REF! | I9: =SUM('Evolutive SFP'!#REF!) -> #REF! | J9: =SUM('Evolutive SFP'!#REF!) -> #REF! | K9: =SUM('Evolutive SFP'!#REF!) -> #REF! | ... AR9: =SUM('Evolutive SFP'!#REF!) -> #REF! | AS9: =SUM('Evolutive SFP'!AH32:AH36) -> 4446384 | AT9: =SUM('Evolutive SFP'!AI32:AI36) -> 8259115.1 | AU9: =SUM('Evolutive SFP'!AJ32:AJ36) -> 8288780.7 | AV9: =SUM('Evolutive SFP'!AK32:AK36) -> 7463714.2 | AW9: =SUM('Evolutive SFP'!AL32:AL36) -> 5081385.5 | AX9: =SUM('Evolutive SFP'!AM32:AM36) -> 4856696.7 | AY9: =SUM('Evolutive SFP'!AN32:AN36) -> 4838508 | AZ9: =SUM('Evolutive SFP'!#REF!) -> #REF! | BA9: =SUM('Evolutive SFP'!AO32:AO36) -> 4294271.5 | BB9: =SUM('Evolutive SFP'!AP32:AP36) -> 3975581.7 | BC9: =SUM('Evolutive SFP'!AQ32:AQ36) -> 441900.56 | BD9: =SUM('Evolutive SFP'!AR32:AR36) -> 388378.56 | BE9: =SUM('Evolutive SFP'!AS32:AS36) -> 1078426.7 | BF9: =SUM('Evolutive SFP'!AT32:AT36) -> 5620622 | BG9: =SUM('Evolutive SFP'!AU32:AU36) -> 5377868.1 | BH9: =SUM('Evolutive SFP'!AV32:AV36) -> 5562195.8 | ... CO9: =SUM('Evolutive SFP'!CC32:CC36) -> 20132.97
A10: 5 | B10: Share capital and Reserves
A11: 5.1 | B11: Core Capital | C11: =C14-C22-C26-C27 -> #REF! | D11: =D14-D22-D26-D27 -> #REF! | E11: =E14-E22-E26-E27 -> #REF! | F11: =F14-F22-F26-F27 -> #REF! | G11: =G14-G22-G26-G27 -> #REF! | H11: =H14-H22-H26-H27 -> #REF! | I11: =I14-I22-I26-I27 -> #REF! | J11: =J14-J22-J26-J27 -> #REF! | ... R11: =R14-R22-R26-R27 -> #REF! | S11: =S14-S22-S27 -> #REF! | T11: =T14-T22-T27 -> #REF! | U11: =U14-U22-U27 -> #REF! | V11: =V14-V22 -> #REF! | W11: =W14-W22 -> #REF! | X11: =X14-X22 -> #REF! | Y11: =Y14-Y22 -> #REF! | Z11: =Z14-Z22 -> #REF! | AA11: =AA14-AA22 -> #REF! | AB11: =AB14-AB22 -> #REF! | AC11: =AC14-AC22 -> #REF! | ... CO11: =CO14-CO22 -> 25509781
A12: 5.2 | B12: Institutional Capital | C12: =C11-C15 -> #REF! | D12: =D11-D15 -> #REF! | E12: =E11-E15 -> #REF! | F12: =F11-F15 -> #REF! | G12: =G11-G15 -> #REF! | H12: =H11-H15 -> #REF! | I12: =I11-I15 -> #REF! | J12: =J11-J15 -> #REF! | ... CO12: =CO11-CO15 -> 12114501
A14: 5.3 | B14: Total Capital | C14: =C15+C16+C17+C18+C19+C20+C21 -> #REF! | D14: =D15+D16+D17+D18+D19+D20+D21 -> #REF! | E14: =E15+E16+E17+E18+E19+E20+E21 -> #REF! | F14: =F15+F16+F17+F18+F19+F20+F21 -> #REF! | G14: =G15+G16+G17+G18+G19+G20+G21 -> #REF! | H14: =H15+H16+H17+H18+H19+H20+H21 -> #REF! | I14: =I15+I16+I17+I18+I19+I20+I21 -> #REF! | J14: =J15+J16+J17+J18+J19+J20+J21 -> #REF! | ... CO14: =CO15+CO16+CO17+CO18+CO19+CO20+CO21 -> 25509781
A15: 5.3.1 | B15: Members Share Capital | C15: ='Evolutive SFP'!#REF! -> #REF! | D15: ='Evolutive SFP'!#REF! -> #REF! | E15: ='Evolutive SFP'!#REF! -> #REF! | F15: ='Evolutive SFP'!#REF! -> #REF! | G15: ='Evolutive SFP'!#REF! -> #REF! | H15: ='Evolutive SFP'!#REF! -> #REF! | I15: ='Evolutive SFP'!#REF! -> #REF! | J15: ='Evolutive SFP'!#REF! -> #REF! | ... AR15: ='Evolutive SFP'!#REF! -> #REF! | AS15: ='Evolutive SFP'!AH39 -> 12966352 | AT15: ='Evolutive SFP'!AI39 -> 12971152 | AU15: ='Evolutive SFP'!AJ39 -> 12973152 | AV15: ='Evolutive SFP'!AK39 -> 12974152 | AW15: ='Evolutive SFP'!AL39 -> 12975652 | AX15: ='Evolutive SFP'!AM39 -> 12977152 | AY15: ='Evolutive SFP'!AN39 -> 12979008 | AZ15: ='Evolutive SFP'!#REF! -> #REF! | BA15: ='Evolutive SFP'!AO39 -> 13104844 | BB15: ='Evolutive SFP'!AP39 -> 13106344 | BC15: ='Evolutive SFP'!AQ39 -> 13108844 | BD15: ='Evolutive SFP'!AR39 -> 13110344 | BE15: ='Evolutive SFP'!AS39 -> 13112644 | BF15: ='Evolutive SFP'!AT39 -> 13112644 | BG15: ='Evolutive SFP'!AU39 -> 13112644 | BH15: ='Evolutive SFP'!AV39 -> 13113644 | ... CO15: ='Evolutive SFP'!CC39 -> 13395279
A16: 5.3.2 | B16: Entrance Fees
A17: 5.3.3 | B17: Retained Earnings | C17: ='Evolutive SFP'!#REF! -> #REF! | D17: ='Evolutive SFP'!#REF! -> #REF! | E17: ='Evolutive SFP'!#REF! -> #REF! | F17: ='Evolutive SFP'!#REF! -> #REF! | G17: ='Evolutive SFP'!#REF! -> #REF! | H17: ='Evolutive SFP'!#REF! -> #REF! | I17: ='Evolutive SFP'!#REF! -> #REF! | J17: ='Evolutive SFP'!#REF! -> #REF! | ... AR17: ='Evolutive SFP'!#REF! -> #REF! | AS17: ='Evolutive SFP'!AH41 -> 2279446 | AT17: ='Evolutive SFP'!AI41 -> 2256870.9 | AU17: ='Evolutive SFP'!AJ41 -> 2256870.9 | AV17: ='Evolutive SFP'!AK41 -> 2741685.9 | AW17: ='Evolutive SFP'!AL41 -> 2741685.9 | AX17: ='Evolutive SFP'!AM41 -> 2741685.9 | AY17: ='Evolutive SFP'!AN41 -> 2741685.9 | AZ17: ='Evolutive SFP'!#REF! -> #REF! | BA17: ='Evolutive SFP'!AO41 -> 2741685 | BB17: ='Evolutive SFP'!AP41 -> 2741685 | BC17: ='Evolutive SFP'!AQ41 -> 2741685 | BD17: ='Evolutive SFP'!AR41 -> 2741685 | BE17: ='Evolutive SFP'!AS41 -> 2741685 | BF17: ='Evolutive SFP'!AT41 -> 2741685 | BG17: ='Evolutive SFP'!AU41 -> 2741685.9 | BH17: ='Evolutive SFP'!AV41 -> 2741685.9 | ... CO17: ='Evolutive SFP'!CC41 -> 4427856.9
A18: 5.3.4 | B18: Appropriation Account | C18: ='Evolutive SFP'!#REF! -> #REF! | D18: ='Evolutive SFP'!#REF! -> #REF! | E18: ='Evolutive SFP'!#REF! -> #REF! | F18: ='Evolutive SFP'!#REF! -> #REF! | G18: ='Evolutive SFP'!#REF! -> #REF! | H18: ='Evolutive SFP'!#REF! -> #REF! | I18: ='Evolutive SFP'!#REF! -> #REF! | J18: ='Evolutive SFP'!#REF! -> #REF! | ... AR18: ='Evolutive SFP'!#REF! -> #REF! | AS18: ='Evolutive SFP'!AH42 -> 462239 | AT18: ='Evolutive SFP'!AI42 -> 552509.1 | AU18: ='Evolutive SFP'!AJ42 -> 898564.59 | AV18: ='Evolutive SFP'!AK42 -> 1432954 | AW18: ='Evolutive SFP'!AL42 -> 1774386 | AX18: ='Evolutive SFP'!AM42 -> 2256452.2 | AY18: ='Evolutive SFP'!AN42 -> 2710890.5 | AZ18: ='Evolutive SFP'!#REF! -> #REF! | BA18: ='Evolutive SFP'!AO42 -> 3725619 | BB18: ='Evolutive SFP'!AP42 -> 4159363.6 | BC18: ='Evolutive SFP'!AQ42 -> 4719976.6 | BD18: ='Evolutive SFP'!AR42 -> 5106561.6 | BE18: ='Evolutive SFP'!AS42 -> 4855217.7 | BF18: ='Evolutive SFP'!AT42 -> 238989 | BG18: ='Evolutive SFP'!AU42 -> 102035.83 | BH18: ='Evolutive SFP'!AV42 -> 298030.17 | ... CO18: ='Evolutive SFP'!CC42 -> 4099752
A19: 5.3.5 | B19: Statutory Reserves | C19: ='Evolutive SFP'!#REF! -> #REF! | D19: ='Evolutive SFP'!#REF! -> #REF! | E19: ='Evolutive SFP'!#REF! -> #REF! | F19: ='Evolutive SFP'!#REF! -> #REF! | G19: ='Evolutive SFP'!#REF! -> #REF! | H19: ='Evolutive SFP'!#REF! -> #REF! | I19: ='Evolutive SFP'!#REF! -> #REF! | J19: ='Evolutive SFP'!#REF! -> #REF! | ... AR19: ='Evolutive SFP'!#REF! -> #REF! | AS19: ='Evolutive SFP'!AH43 -> 1867801 | AT19: ='Evolutive SFP'!AI43 -> 1752242.2 | AU19: ='Evolutive SFP'!AJ43 -> 1752242.2 | AV19: ='Evolutive SFP'!AK43 -> 1867802.2 | AW19: ='Evolutive SFP'!AL43 -> 1867802.2 | AX19: ='Evolutive SFP'!AM43 -> 1867802.2 | AY19: ='Evolutive SFP'!AN43 -> 1867802.2 | AZ19: ='Evolutive SFP'!#REF! -> #REF! | BA19: ='Evolutive SFP'!AO43 -> 1867802.2 | BB19: ='Evolutive SFP'!AP43 -> 1867802.2 | BC19: ='Evolutive SFP'!AQ43 -> 1867802.2 | BD19: ='Evolutive SFP'!AR43 -> 1867802.2 | BE19: ='Evolutive SFP'!AS43 -> 1867802.2 | BF19: ='Evolutive SFP'!AT43 -> 1927549 | BG19: ='Evolutive SFP'!AU43 -> 1867802.2 | BH19: ='Evolutive SFP'!AV43 -> 1867802.2 | ... CO19: ='Evolutive SFP'!CC43 -> 2745342
A20: 5.3.6 | B20: Capital Reserves | C20: =('Evolutive SFP'!#REF!) -> #REF! | D20: =('Evolutive SFP'!#REF!) -> #REF! | E20: =('Evolutive SFP'!#REF!) -> #REF! | F20: =('Evolutive SFP'!#REF!) -> #REF! | G20: =('Evolutive SFP'!#REF!) -> #REF! | H20: =('Evolutive SFP'!#REF!) -> #REF! | I20: =('Evolutive SFP'!#REF!) -> #REF! | J20: =('Evolutive SFP'!#REF!) -> #REF! | ... AR20: =('Evolutive SFP'!#REF!) -> #REF! | AS20: =('Evolutive SFP'!AH44) -> 841550 | AT20: =('Evolutive SFP'!AI44) -> 841550.38 | AU20: =('Evolutive SFP'!AJ44) -> 841550.38 | AV20: =('Evolutive SFP'!AK44) -> 841550.38 | AW20: =('Evolutive SFP'!AL44) -> 841550.38 | AX20: =('Evolutive SFP'!AM44) -> 841550.38 | AY20: =('Evolutive SFP'!AN44) -> 841550.38 | AZ20: =('Evolutive SFP'!#REF!) -> #REF! | BA20: =('Evolutive SFP'!AO44) -> 841550.38 | BB20: =('Evolutive SFP'!AP44) -> 841550.38 | BC20: =('Evolutive SFP'!AQ44) -> 841550.38 | BD20: =('Evolutive SFP'!AR44) -> 841550.38 | BE20: =('Evolutive SFP'!AS44) -> 841550.38 | BF20: =('Evolutive SFP'!AT44) -> 841550 | BG20: =('Evolutive SFP'!AU44) -> 841550.38 | BH20: =('Evolutive SFP'!AV44) -> 841550.38 | ... CO20: =('Evolutive SFP'!CC44) -> 841550.38
A21: 5.3.7 | B21: Supplementary Capital & reserves | C21: =C22+C23 -> #REF! | D21: =D22+D23 -> #REF! | E21: =E22+E23 -> #REF! | F21: =F22+F23 -> #REF! | G21: =G22+G23 -> #REF! | H21: =H22+H23 -> #REF! | I21: =I22+I23 -> #REF! | J21: =J22+J23 -> #REF! | ... CO21: =CO22+CO23 -> 0
A22: a | B22: Proposed Dividends | C22: ='Evolutive SFP'!#REF! -> #REF! | D22: ='Evolutive SFP'!#REF! -> #REF! | E22: ='Evolutive SFP'!#REF! -> #REF! | F22: ='Evolutive SFP'!#REF! -> #REF! | G22: ='Evolutive SFP'!#REF! -> #REF! | H22: ='Evolutive SFP'!#REF! -> #REF! | I22: ='Evolutive SFP'!#REF! -> #REF! | J22: ='Evolutive SFP'!#REF! -> #REF! | ... AR22: ='Evolutive SFP'!#REF! -> #REF! | AS22: ='Evolutive SFP'!AH46 -> 0 | AT22: ='Evolutive SFP'!AI46 -> 0 | AU22: ='Evolutive SFP'!AJ46 -> 0 | AV22: ='Evolutive SFP'!AK46 -> 0 | AW22: ='Evolutive SFP'!AL46 -> 0 | AX22: ='Evolutive SFP'!AM46 -> 0 | AY22: ='Evolutive SFP'!AN46 -> 0 | AZ22: ='Evolutive SFP'!#REF! -> #REF! | BA22: ='Evolutive SFP'!AO46 -> 0 | BB22: ='Evolutive SFP'!AP46 -> 0 | BC22: ='Evolutive SFP'!AQ46 -> 0 | BD22: ='Evolutive SFP'!AR46 -> 0 | BE22: ='Evolutive SFP'!AS46 -> 0 | BF22: ='Evolutive SFP'!AT46 -> 0 | BG22: ='Evolutive SFP'!AU46 -> 0 | BH22: ='Evolutive SFP'!AV46 -> 0 | ... CO22: ='Evolutive SFP'!CC46 -> 0
A23: b | B23: Risk Mgt Fund
A25: 6 | B25: Investments | C25: =C26+C27+C28 -> #REF! | D25: =D26+D27+D28 -> #REF! | E25: =E26+E27+E28 -> #REF! | F25: =F26+F27+F28 -> #REF! | G25: =G26+G27+G28 -> #REF! | H25: =H26+H27+H28 -> #REF! | I25: =I26+I27+I28 -> #REF! | J25: =J26+J27+J28 -> #REF! | ... CO25: =CO26+CO27+CO28 -> 17267979
A26: 6.1 | B26: Shares in Kusco,CIC,Coop Bank | C26: ='Evolutive SFP'!#REF! -> #REF! | D26: ='Evolutive SFP'!#REF! -> #REF! | E26: ='Evolutive SFP'!#REF! -> #REF! | F26: ='Evolutive SFP'!#REF! -> #REF! | G26: ='Evolutive SFP'!#REF! -> #REF! | H26: ='Evolutive SFP'!#REF! -> #REF! | I26: ='Evolutive SFP'!#REF! -> #REF! | J26: ='Evolutive SFP'!#REF! -> #REF! | ... AR26: ='Evolutive SFP'!#REF! -> #REF! | AS26: ='Evolutive SFP'!AH13 -> 100000 | AT26: ='Evolutive SFP'!AI13 -> 0 | AU26: ='Evolutive SFP'!AJ13 -> 0 | AV26: ='Evolutive SFP'!AK13 -> 0 | AW26: ='Evolutive SFP'!AL13 -> 0 | AX26: ='Evolutive SFP'!AM13 -> 0 | AY26: ='Evolutive SFP'!AN13 -> 0 | AZ26: ='Evolutive SFP'!#REF! -> #REF! | BA26: ='Evolutive SFP'!AO13 -> 0 | BB26: ='Evolutive SFP'!AP13 -> 0 | BC26: ='Evolutive SFP'!AQ13 -> 0 | BD26: ='Evolutive SFP'!AR13 -> 0 | BE26: ='Evolutive SFP'!AS13 -> 0 | BF26: ='Evolutive SFP'!AT13 -> 100000 | BG26: ='Evolutive SFP'!AU13 -> 7154009.4 | BH26: ='Evolutive SFP'!AV13 -> 7194009.4 | ... CO26: ='Evolutive SFP'!CC13 -> 8633989.4
A27: 6.2 | B27: Equity Investments (at cost) | C27: ='Evolutive SFP'!#REF! -> #REF! | D27: ='Evolutive SFP'!#REF! -> #REF! | E27: ='Evolutive SFP'!#REF! -> #REF! | F27: ='Evolutive SFP'!#REF! -> #REF! | G27: ='Evolutive SFP'!#REF! -> #REF! | H27: ='Evolutive SFP'!#REF! -> #REF! | I27: ='Evolutive SFP'!#REF! -> #REF! | J27: ='Evolutive SFP'!#REF! -> #REF! | ... R27: ='Evolutive SFP'!#REF! -> #REF! | S27: ='Evolutive SFP'!#REF!+'Evolutive SFP'!#REF! -> #REF! | T27: ='Evolutive SFP'!#REF!+'Evolutive SFP'!#REF! -> #REF! | U27: ='Evolutive SFP'!#REF!+'Evolutive SFP'!#REF! -> #REF! | V27: ='Evolutive SFP'!#REF!+'Evolutive SFP'!#REF! -> #REF! | W27: ='Evolutive SFP'!#REF!+'Evolutive SFP'!#REF! -> #REF! | X27: ='Evolutive SFP'!#REF!+'Evolutive SFP'!#REF! -> #REF! | Y27: ='Evolutive SFP'!#REF!+'Evolutive SFP'!#REF! -> #REF! | Z27: ='Evolutive SFP'!#REF!+'Evolutive SFP'!#REF! -> #REF! | ... AR27: ='Evolutive SFP'!#REF!+'Evolutive SFP'!#REF! -> #REF! | AS27: ='Evolutive SFP'!AH10+'Evolutive SFP'!AH13 -> 100000 | AT27: ='Evolutive SFP'!AI10+'Evolutive SFP'!AI13 -> 0 | AU27: ='Evolutive SFP'!AJ10+'Evolutive SFP'!AJ13 -> 0 | AV27: ='Evolutive SFP'!AK10+'Evolutive SFP'!AK13 -> 0 | AW27: ='Evolutive SFP'!AL10+'Evolutive SFP'!AL13 -> 0 | AX27: ='Evolutive SFP'!AM10+'Evolutive SFP'!AM13 -> 0 | AY27: ='Evolutive SFP'!AN10+'Evolutive SFP'!AN13 -> 0 | AZ27: ='Evolutive SFP'!#REF!+'Evolutive SFP'!#REF! -> #REF! | BA27: ='Evolutive SFP'!AO10+'Evolutive SFP'!AO13 -> 0 | BB27: ='Evolutive SFP'!AP10+'Evolutive SFP'!AP13 -> 0 | BC27: ='Evolutive SFP'!AQ10+'Evolutive SFP'!AQ13 -> 0 | BD27: ='Evolutive SFP'!AR10+'Evolutive SFP'!AR13 -> 0 | BE27: ='Evolutive SFP'!AS10+'Evolutive SFP'!AS13 -> 0 | BF27: ='Evolutive SFP'!AT10+'Evolutive SFP'!AT13 -> 100000 | BG27: ='Evolutive SFP'!AU10+'Evolutive SFP'!AU13 -> 7154009.4 | BH27: ='Evolutive SFP'!AV10+'Evolutive SFP'!AV13 -> 7194009.4 | ... CO27: ='Evolutive SFP'!CC10+'Evolutive SFP'!CC13 -> 8633989.4
A28: 6.3 | B28: Deposits in KUSCCO CFP | C28: ='Evolutive SFP'!#REF! -> #REF! | D28: ='Evolutive SFP'!#REF! -> #REF! | E28: ='Evolutive SFP'!#REF! -> #REF! | F28: ='Evolutive SFP'!#REF! -> #REF! | G28: ='Evolutive SFP'!#REF! -> #REF! | H28: ='Evolutive SFP'!#REF! -> #REF! | I28: ='Evolutive SFP'!#REF! -> #REF! | J28: ='Evolutive SFP'!#REF! -> #REF! | ... AR28: ='Evolutive SFP'!#REF! -> #REF! | AS28: ='Evolutive SFP'!AH11 -> 0 | AT28: ='Evolutive SFP'!AI11 -> 0 | AU28: ='Evolutive SFP'!AJ11 -> 0 | AV28: ='Evolutive SFP'!AK11 -> 0 | AW28: ='Evolutive SFP'!AL11 -> 0 | AX28: ='Evolutive SFP'!AM11 -> 0 | AY28: ='Evolutive SFP'!AN11 -> 0 | AZ28: ='Evolutive SFP'!#REF! -> #REF! | BA28: ='Evolutive SFP'!AO11 -> 0 | BB28: ='Evolutive SFP'!AP11 -> 0 | BC28: ='Evolutive SFP'!AQ11 -> 0 | BD28: ='Evolutive SFP'!AR11 -> 0 | BE28: ='Evolutive SFP'!AS11 -> 0 | BF28: ='Evolutive SFP'!AT11 -> 0 | BG28: ='Evolutive SFP'!AU11 -> 0 | BH28: ='Evolutive SFP'!AV11 -> 0 | ... CO28: ='Evolutive SFP'!CC11 -> 0
A30: 7 | B30: Net Loans & Advances | C30: ='Evolutive SFP'!#REF! -> #REF! | D30: ='Evolutive SFP'!#REF! -> #REF! | E30: ='Evolutive SFP'!#REF! -> #REF! | F30: ='Evolutive SFP'!#REF! -> #REF! | G30: ='Evolutive SFP'!#REF! -> #REF! | H30: ='Evolutive SFP'!#REF! -> #REF! | I30: ='Evolutive SFP'!#REF! -> #REF! | J30: ='Evolutive SFP'!#REF! -> #REF! | ... AR30: ='Evolutive SFP'!#REF! -> #REF! | AS30: ='Evolutive SFP'!AH14 -> 26428275 | AT30: ='Evolutive SFP'!AI14 -> 32516881 | AU30: ='Evolutive SFP'!AJ14 -> 32613412 | AV30: ='Evolutive SFP'!AK14 -> 33997628 | AW30: ='Evolutive SFP'!AL14 -> 31247366 | AX30: ='Evolutive SFP'!AM14 -> 30958397 | AY30: ='Evolutive SFP'!AN14 -> 30678214 | AZ30: ='Evolutive SFP'!#REF! -> #REF! | BA30: ='Evolutive SFP'!AO14 -> 30545196 | BB30: ='Evolutive SFP'!AP14 -> 31716573 | BC30: ='Evolutive SFP'!AQ14 -> 28808113 | BD30: ='Evolutive SFP'!AR14 -> 28454592 | BE30: ='Evolutive SFP'!AS14 -> 30026361 | BF30: ='Evolutive SFP'!AT14 -> 30026362 | BG30: ='Evolutive SFP'!AU14 -> 33005537 | BH30: ='Evolutive SFP'!AV14 -> 32668175 | ... CO30: ='Evolutive SFP'!CC14 -> 38876309
A31: 7.1 | B31: Gross Loans & advances | C31: ='Evolutive SFP'!#REF! -> #REF! | D31: ='Evolutive SFP'!#REF! -> #REF! | E31: ='Evolutive SFP'!#REF! -> #REF! | F31: ='Evolutive SFP'!#REF! -> #REF! | G31: ='Evolutive SFP'!#REF! -> #REF! | H31: ='Evolutive SFP'!#REF! -> #REF! | I31: ='Evolutive SFP'!#REF! -> #REF! | J31: ='Evolutive SFP'!#REF! -> #REF! | ... AR31: ='Evolutive SFP'!#REF! -> #REF! | AS31: ='Evolutive SFP'!AH15 -> 29988726 | AT31: ='Evolutive SFP'!AI15 -> 32516881 | AU31: ='Evolutive SFP'!AJ15 -> 32613412 | AV31: ='Evolutive SFP'!AK15 -> 33997628 | AW31: ='Evolutive SFP'!AL15 -> 31247366 | AX31: ='Evolutive SFP'!AM15 -> 30958397 | AY31: ='Evolutive SFP'!AN15 -> 30678214 | AZ31: ='Evolutive SFP'!#REF! -> #REF! | BA31: ='Evolutive SFP'!AO15 -> 30545196 | BB31: ='Evolutive SFP'!AP15 -> 31716573 | BC31: ='Evolutive SFP'!AQ15 -> 32368564 | BD31: ='Evolutive SFP'!AR15 -> 32015043 | BE31: ='Evolutive SFP'!AS15 -> 33586812 | BF31: ='Evolutive SFP'!AT15 -> 33586813 | BG31: ='Evolutive SFP'!AU15 -> 36565988 | BH31: ='Evolutive SFP'!AV15 -> 36228626 | ... CO31: ='Evolutive SFP'!CC15 -> 42574709
A32: 7.2 | B32: Allowance for loan losses | C32: ='Evolutive SFP'!#REF! -> #REF! | D32: ='Evolutive SFP'!#REF! -> #REF! | E32: ='Evolutive SFP'!#REF! -> #REF! | F32: ='Evolutive SFP'!#REF! -> #REF! | G32: ='Evolutive SFP'!#REF! -> #REF! | H32: ='Evolutive SFP'!#REF! -> #REF! | I32: ='Evolutive SFP'!#REF! -> #REF! | J32: ='Evolutive SFP'!#REF! -> #REF! | ... AR32: ='Evolutive SFP'!#REF! -> #REF! | AS32: ='Evolutive SFP'!AH16 -> 3560451 | AT32: ='Evolutive SFP'!AI16 -> 0 | AU32: ='Evolutive SFP'!AJ16 -> 0 | AV32: ='Evolutive SFP'!AK16 -> 0 | AW32: ='Evolutive SFP'!AL16 -> 0 | AX32: ='Evolutive SFP'!AM16 -> 0 | AY32: ='Evolutive SFP'!AN16 -> 0 | AZ32: ='Evolutive SFP'!#REF! -> #REF! | BA32: ='Evolutive SFP'!AO16 -> 0 | BB32: ='Evolutive SFP'!AP16 -> 0 | BC32: ='Evolutive SFP'!AQ16 -> 3560451 | BD32: ='Evolutive SFP'!AR16 -> 3560451 | BE32: ='Evolutive SFP'!AS16 -> 3560451 | BF32: ='Evolutive SFP'!AT16 -> 3560451 | BG32: ='Evolutive SFP'!AU16 -> 3560451 | BH32: ='Evolutive SFP'!AV16 -> 3560451 | ... CO32: ='Evolutive SFP'!CC16 -> 3698400
A34: 8 | B34: Non-Earning Assets | C34: ='Evolutive SFP'!#REF!+'Evolutive SFP'!#REF! -> #REF! | D34: ='Evolutive SFP'!#REF!+'Evolutive SFP'!#REF! -> #REF! | E34: ='Evolutive SFP'!#REF!+'Evolutive SFP'!#REF! -> #REF! | F34: ='Evolutive SFP'!#REF!+'Evolutive SFP'!#REF! -> #REF! | G34: ='Evolutive SFP'!#REF!+'Evolutive SFP'!#REF! -> #REF! | H34: ='Evolutive SFP'!#REF!+'Evolutive SFP'!#REF! -> #REF! | I34: ='Evolutive SFP'!#REF!+'Evolutive SFP'!#REF! -> #REF! | J34: ='Evolutive SFP'!#REF!+'Evolutive SFP'!#REF! -> #REF! | ... AR34: ='Evolutive SFP'!#REF!+'Evolutive SFP'!#REF! -> #REF! | AS34: ='Evolutive SFP'!AH21+'Evolutive SFP'!AH7 -> 18273464 | AT34: ='Evolutive SFP'!AI21+'Evolutive SFP'!AI7 -> 30314025 | AU34: ='Evolutive SFP'!AJ21+'Evolutive SFP'!AJ7 -> 31929613 | AV34: ='Evolutive SFP'!AK21+'Evolutive SFP'!AK7 -> 32221401 | AW34: ='Evolutive SFP'!AL21+'Evolutive SFP'!AL7 -> 33298080 | AX34: ='Evolutive SFP'!AM21+'Evolutive SFP'!AM7 -> 34016218 | AY34: ='Evolutive SFP'!AN21+'Evolutive SFP'!AN7 -> 34650818 | AZ34: ='Evolutive SFP'!#REF!+'Evolutive SFP'!#REF! -> #REF! | BA34: ='Evolutive SFP'!AO21+'Evolutive SFP'!AO7 -> 22422415 | BB34: ='Evolutive SFP'!AP21+'Evolutive SFP'!AP7 -> 22779283 | BC34: ='Evolutive SFP'!AQ21+'Evolutive SFP'!AQ7 -> 23267632 | BD34: ='Evolutive SFP'!AR21+'Evolutive SFP'!AR7 -> 23167881 | BE34: ='Evolutive SFP'!AS21+'Evolutive SFP'!AS7 -> 23595238 | BF34: ='Evolutive SFP'!AT21+'Evolutive SFP'!AT7 -> 23580949 | BG34: ='Evolutive SFP'!AU21+'Evolutive SFP'!AU7 -> 23384524 | BH34: ='Evolutive SFP'!AV21+'Evolutive SFP'!AV7 -> 23777231 | ... CO34: ='Evolutive SFP'!CC21+'Evolutive SFP'!CC7 -> 22220938
A35: 8.1 | B35: Property and Equipment | C35: ='Evolutive SFP'!#REF! -> #REF! | D35: ='Evolutive SFP'!#REF! -> #REF! | E35: ='Evolutive SFP'!#REF! -> #REF! | F35: ='Evolutive SFP'!#REF! -> #REF! | G35: ='Evolutive SFP'!#REF! -> #REF! | H35: ='Evolutive SFP'!#REF! -> #REF! | I35: ='Evolutive SFP'!#REF! -> #REF! | J35: ='Evolutive SFP'!#REF! -> #REF! | ... AR35: ='Evolutive SFP'!#REF! -> #REF! | AS35: ='Evolutive SFP'!AH23 -> 16218800 | AT35: ='Evolutive SFP'!AI23 -> 16238775 | AU35: ='Evolutive SFP'!AJ23 -> 17608718 | AV35: ='Evolutive SFP'!AK23 -> 17632998 | AW35: ='Evolutive SFP'!AL23 -> 18632998 | AX35: ='Evolutive SFP'!AM23 -> 19669198 | AY35: ='Evolutive SFP'!AN23 -> 19823168 | AZ35: ='Evolutive SFP'!#REF! -> #REF! | BA35: ='Evolutive SFP'!AO23 -> 20957465 | BB35: ='Evolutive SFP'!AP23 -> 20957465 | BC35: ='Evolutive SFP'!AQ23 -> 21473465 | BD35: ='Evolutive SFP'!AR23 -> 21493465 | BE35: ='Evolutive SFP'!AS23 -> 21714448 | BF35: ='Evolutive SFP'!AT23 -> 21689753 | BG35: ='Evolutive SFP'!AU23 -> 21730448 | BH35: ='Evolutive SFP'!AV23 -> 21730448 | ... CO35: ='Evolutive SFP'!CC23 -> 681755.4
B36: Cash & Cash Equivalents | D36: ='Evolutive SFP'!#REF! -> #REF! | E36: ='Evolutive SFP'!#REF! -> #REF! | F36: ='Evolutive SFP'!#REF! -> #REF! | G36: ='Evolutive SFP'!#REF! -> #REF! | H36: ='Evolutive SFP'!#REF! -> #REF! | I36: ='Evolutive SFP'!#REF! -> #REF! | J36: ='Evolutive SFP'!#REF! -> #REF! | K36: ='Evolutive SFP'!#REF! -> #REF! | ... M36: ='Evolutive SFP'!#REF! -> #REF!
A37: 9 | B37: Turnover | C37: =C38+C39+C40+C41 -> #REF! | D37: =D38+D39+D40+D41 -> #REF! | E37: =E38+E39+E40+E41 -> #REF! | F37: =F38+F39+F40+F41 -> #REF! | G37: =G38+G39+G40+G41 -> #REF! | H37: =H38+H39+H40+H41 -> #REF! | I37: =I38+I39+I40+I41 -> #REF! | J37: =J38+J39+J40+J41 -> #REF! | ... CO37: =CO38+CO39+CO40+CO41 -> 8166071.5
A38: 9.1 | B38: Loan Interest | C38: ='Evolutitve SCI'!#REF! -> #REF! | D38: ='Evolutitve SCI'!#REF! -> #REF! | E38: ='Evolutitve SCI'!#REF! -> #REF! | F38: ='Evolutitve SCI'!#REF! -> #REF! | G38: ='Evolutitve SCI'!#REF! -> #REF! | H38: ='Evolutitve SCI'!#REF! -> #REF! | I38: ='Evolutitve SCI'!#REF! -> #REF! | J38: ='Evolutitve SCI'!#REF! -> #REF! | ... AR38: ='Evolutitve SCI'!#REF! -> #REF! | AS38: ='Evolutitve SCI'!AG5 -> 3214668 | AT38: ='Evolutitve SCI'!AH5 -> 292294.1 | AU38: ='Evolutitve SCI'!AI5 -> 594618.59 | AV38: ='Evolutitve SCI'!AJ5 -> 878858.52 | AW38: ='Evolutitve SCI'!AK5 -> 1163295.3 | AX38: ='Evolutitve SCI'!AL5 -> 1431499.5 | AY38: ='Evolutitve SCI'!AM5 -> 1706433.5 | AZ38: ='Evolutitve SCI'!#REF! -> #REF! | BA38: ='Evolutitve SCI'!AN5 -> 2247354.5 | BB38: ='Evolutitve SCI'!AO5 -> 2524122.9 | BC38: ='Evolutitve SCI'!AP5 -> 2837829 | BD38: ='Evolutitve SCI'!AQ5 -> 3125492.1 | BE38: ='Evolutitve SCI'!AR5 -> 3390721.3 | BF38: ='Evolutitve SCI'!AS5 -> 3390720 | BG38: ='Evolutitve SCI'!AT5 -> 16718.83 | BH38: ='Evolutitve SCI'!AU5 -> 297804.17 | ... CO38: ='Evolutitve SCI'!CB5 -> 3173667.1
A39: 9.2 | B39: Income from investments | C39: ='Evolutitve SCI'!#REF! -> #REF! | D39: ='Evolutitve SCI'!#REF! -> #REF! | E39: ='Evolutitve SCI'!#REF! -> #REF! | F39: ='Evolutitve SCI'!#REF! -> #REF! | G39: ='Evolutitve SCI'!#REF! -> #REF! | H39: ='Evolutitve SCI'!#REF! -> #REF! | I39: ='Evolutitve SCI'!#REF! -> #REF! | J39: ='Evolutitve SCI'!#REF! -> #REF! | ... AR39: ='Evolutitve SCI'!#REF! -> #REF! | AS39: ='Evolutitve SCI'!AG7 -> 5990737 | AT39: ='Evolutitve SCI'!AH7 -> 304919 | AU39: ='Evolutitve SCI'!AI7 -> 612949 | AV39: ='Evolutitve SCI'!AJ7 -> 1067920 | AW39: ='Evolutitve SCI'!AK7 -> 1225107 | AX39: ='Evolutitve SCI'!AL7 -> 1529858.5 | AY39: ='Evolutitve SCI'!AM7 -> 1847133.4 | AZ39: ='Evolutitve SCI'!#REF! -> #REF! | BA39: ='Evolutitve SCI'!AN7 -> 2525939.5 | BB39: ='Evolutitve SCI'!AO7 -> 2899388.5 | BC39: ='Evolutitve SCI'!AP7 -> 3273054.5 | BD39: ='Evolutitve SCI'!AQ7 -> 3599074.5 | BE39: ='Evolutitve SCI'!AR7 -> 4084007.5 | BF39: ='Evolutitve SCI'!AS7 -> 5632973 | BG39: ='Evolutitve SCI'!AT7 -> 198561 | BH39: ='Evolutitve SCI'!AU7 -> 564511 | ... CO39: ='Evolutitve SCI'!CB7 -> 959163.25
A40: 9.3 | B40: Fees & Commissions | C40: ='Evolutitve SCI'!#REF! -> #REF! | D40: ='Evolutitve SCI'!#REF! -> #REF! | E40: ='Evolutitve SCI'!#REF! -> #REF! | F40: ='Evolutitve SCI'!#REF! -> #REF! | G40: ='Evolutitve SCI'!#REF! -> #REF! | H40: ='Evolutitve SCI'!#REF! -> #REF! | I40: ='Evolutitve SCI'!#REF! -> #REF! | J40: ='Evolutitve SCI'!#REF! -> #REF! | ... AR40: ='Evolutitve SCI'!#REF! -> #REF! | AS40: ='Evolutitve SCI'!AG6 -> 0 | AT40: ='Evolutitve SCI'!AH6 -> 0 | AU40: ='Evolutitve SCI'!AI6 -> 0 | AV40: ='Evolutitve SCI'!AJ6 -> 0 | AW40: ='Evolutitve SCI'!AK6 -> 0 | AX40: ='Evolutitve SCI'!AL6 -> 0 | AY40: ='Evolutitve SCI'!AM6 -> 0 | AZ40: ='Evolutitve SCI'!#REF! -> #REF! | BA40: ='Evolutitve SCI'!AN6 -> 0 | BB40: ='Evolutitve SCI'!AO6 -> 0 | BC40: ='Evolutitve SCI'!AP6 -> 0 | BD40: ='Evolutitve SCI'!AQ6 -> 0 | BE40: ='Evolutitve SCI'!AR6 -> 0 | BF40: ='Evolutitve SCI'!AS6 -> 0 | BG40: ='Evolutitve SCI'!AT6 -> 0 | BH40: ='Evolutitve SCI'!AU6 -> 0 | ... CO40: ='Evolutitve SCI'!CB6 -> 4033241
A41: 9.4 | B41: Average yield on loans | S41: =S38/S31 -> #REF! | T41: =T38/T31 -> #REF! | U41: =U38/U31 -> #REF! | V41: =V38/V31 -> #REF! | W41: =W38/W31 -> #REF! | X41: =X38/X31 -> #REF! | Y41: =Y38/Y31 -> #REF! | Z41: =Z38/Z31 -> #REF! | ... CO41: =CO38/CO31 -> 0.074543484
A43: 10 | B43: Financial and Operating costs | C43: =SUM(C44:C47) -> #REF! | D43: =SUM(D44:D47) -> #REF! | E43: =SUM(E44:E47) -> #REF! | F43: =SUM(F44:F47) -> #REF! | G43: =SUM(G44:G47) -> #REF! | H43: =SUM(H44:H47) -> #REF! | I43: =SUM(I44:I47) -> #REF! | J43: =SUM(J44:J47) -> #REF! | ... CO43: =SUM(CO44:CO47) -> 4066319.4
A44: 10.1 | B44: Interest expense on deposits | C44: ='Evolutitve SCI'!#REF!+'Evolutitve SCI'!#REF! -> #REF! | D44: ='Evolutitve SCI'!#REF!+'Evolutitve SCI'!#REF! -> #REF! | E44: ='Evolutitve SCI'!#REF!+'Evolutitve SCI'!#REF! -> #REF! | F44: ='Evolutitve SCI'!#REF!+'Evolutitve SCI'!#REF! -> #REF! | G44: ='Evolutitve SCI'!#REF!+'Evolutitve SCI'!#REF! -> #REF! | H44: ='Evolutitve SCI'!#REF!+'Evolutitve SCI'!#REF! -> #REF! | I44: ='Evolutitve SCI'!#REF!+'Evolutitve SCI'!#REF! -> #REF! | J44: ='Evolutitve SCI'!#REF!+'Evolutitve SCI'!#REF! -> #REF! | ... AR44: ='Evolutitve SCI'!#REF!+'Evolutitve SCI'!#REF! -> #REF! | AS44: ='Evolutitve SCI'!AG13+'Evolutitve SCI'!AG16 -> 2538578 | AT44: ='Evolutitve SCI'!AH13+'Evolutitve SCI'!AH16 -> 10728 | AU44: ='Evolutitve SCI'!AI13+'Evolutitve SCI'!AI16 -> 19344 | AV44: ='Evolutitve SCI'!AJ13+'Evolutitve SCI'!AJ16 -> 30582 | AW44: ='Evolutitve SCI'!AK13+'Evolutitve SCI'!AK16 -> 65230.81 | AX44: ='Evolutitve SCI'!AL13+'Evolutitve SCI'!AL16 -> 69488.81 | AY44: ='Evolutitve SCI'!AM13+'Evolutitve SCI'!AM16 -> 152482.03 | AZ44: ='Evolutitve SCI'!#REF!+'Evolutitve SCI'!#REF! -> #REF! | BA44: ='Evolutitve SCI'!AN13+'Evolutitve SCI'!AN16 -> 169086.49 | BB44: ='Evolutitve SCI'!AO13+'Evolutitve SCI'!AO16 -> 232179.45 | BC44: ='Evolutitve SCI'!AP13+'Evolutitve SCI'!AP16 -> 242802.47 | BD44: ='Evolutitve SCI'!AQ13+'Evolutitve SCI'!AQ16 -> 247559.73 | BE44: ='Evolutitve SCI'!AR13+'Evolutitve SCI'!AR16 -> 749420.78 | BF44: ='Evolutitve SCI'!AS13+'Evolutitve SCI'!AS16 -> 3747212 | BG44: ='Evolutitve SCI'!AT13+'Evolutitve SCI'!AT16 -> 12160 | BH44: ='Evolutitve SCI'!AU13+'Evolutitve SCI'!AU16 -> 144447 | ... CO44: ='Evolutitve SCI'!CB13+'Evolutitve SCI'!CB16 -> 58111
A45: 10.2 | B45: Dividend expense on share capital | C45: ='Evolutitve SCI'!#REF! -> #REF! | D45: ='Evolutitve SCI'!#REF! -> #REF! | E45: ='Evolutitve SCI'!#REF! -> #REF! | F45: ='Evolutitve SCI'!#REF! -> #REF! | G45: ='Evolutitve SCI'!#REF! -> #REF! | H45: ='Evolutitve SCI'!#REF! -> #REF! | I45: ='Evolutitve SCI'!#REF! -> #REF! | J45: ='Evolutitve SCI'!#REF! -> #REF! | ... AR45: ='Evolutitve SCI'!#REF! -> #REF! | AS45: ='Evolutitve SCI'!AG15 -> 799495 | AT45: ='Evolutitve SCI'!AH15 -> 0 | AU45: ='Evolutitve SCI'!AI15 -> 0 | AV45: ='Evolutitve SCI'!AJ15 -> 0 | AW45: ='Evolutitve SCI'!AK15 -> 0 | AX45: ='Evolutitve SCI'!AL15 -> 0 | AY45: ='Evolutitve SCI'!AM15 -> 0 | AZ45: ='Evolutitve SCI'!#REF! -> #REF! | BA45: ='Evolutitve SCI'!AN15 -> 0 | BB45: ='Evolutitve SCI'!AO15 -> 0 | BC45: ='Evolutitve SCI'!AP15 -> 0 | BD45: ='Evolutitve SCI'!AQ15 -> 0 | BE45: ='Evolutitve SCI'!AR15 -> 0 | BF45: ='Evolutitve SCI'!AS15 -> 0 | BG45: ='Evolutitve SCI'!AT15 -> 0 | BH45: ='Evolutitve SCI'!AU15 -> 0 | ... CO45: ='Evolutitve SCI'!CB15 -> 0
A46: 10.3 | B46: Interest expense on borrowed funds | C46: ='Evolutitve SCI'!#REF! -> #REF! | D46: ='Evolutitve SCI'!#REF! -> #REF! | E46: ='Evolutitve SCI'!#REF! -> #REF! | F46: ='Evolutitve SCI'!#REF! -> #REF! | G46: ='Evolutitve SCI'!#REF! -> #REF! | H46: ='Evolutitve SCI'!#REF! -> #REF! | I46: ='Evolutitve SCI'!#REF! -> #REF! | J46: ='Evolutitve SCI'!#REF! -> #REF! | ... AR46: ='Evolutitve SCI'!#REF! -> #REF! | AS46: ='Evolutitve SCI'!AG14 -> 44608 | AT46: ='Evolutitve SCI'!AH14 -> 0 | AU46: ='Evolutitve SCI'!AI14 -> 0 | AV46: ='Evolutitve SCI'!AJ14 -> 0 | AW46: ='Evolutitve SCI'!AK14 -> 0 | AX46: ='Evolutitve SCI'!AL14 -> 0 | AY46: ='Evolutitve SCI'!AM14 -> 0 | AZ46: ='Evolutitve SCI'!#REF! -> #REF! | BA46: ='Evolutitve SCI'!AN14 -> 0 | BB46: ='Evolutitve SCI'!AO14 -> 0 | BC46: ='Evolutitve SCI'!AP14 -> 0 | BD46: ='Evolutitve SCI'!AQ14 -> 0 | BE46: ='Evolutitve SCI'!AR14 -> 0 | BF46: ='Evolutitve SCI'!AS14 -> 0 | BG46: ='Evolutitve SCI'!AT14 -> 0 | BH46: ='Evolutitve SCI'!AU14 -> 0 | ... CO46: ='Evolutitve SCI'!CB14 -> 0
A47: 10.4 | B47: Opperating expenses | C47: ='Evolutitve SCI'!#REF! -> #REF! | D47: ='Evolutitve SCI'!#REF! -> #REF! | E47: ='Evolutitve SCI'!#REF! -> #REF! | F47: ='Evolutitve SCI'!#REF! -> #REF! | G47: ='Evolutitve SCI'!#REF! -> #REF! | H47: ='Evolutitve SCI'!#REF! -> #REF! | I47: ='Evolutitve SCI'!#REF! -> #REF! | J47: ='Evolutitve SCI'!#REF! -> #REF! | ... AR47: ='Evolutitve SCI'!#REF! -> #REF! | AS47: ='Evolutitve SCI'!AG23 -> 4580282 | AT47: ='Evolutitve SCI'!AH23 -> 191201 | AU47: ='Evolutitve SCI'!AI23 -> 481754 | AV47: ='Evolutitve SCI'!AJ23 -> 749565.49 | AW47: ='Evolutitve SCI'!AK23 -> 977569.88 | AX47: ='Evolutitve SCI'!AL23 -> 1164204.4 | AY47: ='Evolutitve SCI'!AM23 -> 1347460 | AZ47: ='Evolutitve SCI'!#REF! -> #REF! | BA47: ='Evolutitve SCI'!AN23 -> 1734888.8 | BB47: ='Evolutitve SCI'!AO23 -> 1934821.5 | BC47: ='Evolutitve SCI'!AP23 -> 2132132.5 | BD47: ='Evolutitve SCI'!AQ23 -> 2606282.3 | BE47: ='Evolutitve SCI'!AR23 -> 2825640.3 | BF47: ='Evolutitve SCI'!AS23 -> 3958788 | BG47: ='Evolutitve SCI'!AT23 -> 160422 | BH47: ='Evolutitve SCI'!AU23 -> 494346 | ... CO47: ='Evolutitve SCI'!CB23 -> 4008208.4
B50: Total Income | C50: ='Evolutitve SCI'!#REF! -> #REF! | D50: ='Evolutitve SCI'!#REF! -> #REF! | E50: ='Evolutitve SCI'!#REF! -> #REF! | F50: ='Evolutitve SCI'!#REF! -> #REF! | G50: ='Evolutitve SCI'!#REF! -> #REF! | H50: ='Evolutitve SCI'!#REF! -> #REF! | I50: ='Evolutitve SCI'!#REF! -> #REF! | J50: ='Evolutitve SCI'!#REF! -> #REF! | ... AF50: ='Evolutitve SCI'!#REF! -> #REF!
B51: Net Financial Income | C51: ='Evolutitve SCI'!#REF! -> #REF! | D51: ='Evolutitve SCI'!#REF! -> #REF! | E51: ='Evolutitve SCI'!#REF! -> #REF! | F51: ='Evolutitve SCI'!#REF! -> #REF! | G51: ='Evolutitve SCI'!#REF! -> #REF! | H51: ='Evolutitve SCI'!#REF! -> #REF! | I51: ='Evolutitve SCI'!#REF! -> #REF! | J51: ='Evolutitve SCI'!#REF! -> #REF! | ... AF51: ='Evolutitve SCI'!#REF! -> #REF!
B52: Net Income | C52: ='Evolutitve SCI'!#REF! -> #REF! | D52: ='Evolutitve SCI'!#REF! -> #REF! | E52: ='Evolutitve SCI'!#REF! -> #REF! | F52: ='Evolutitve SCI'!#REF! -> #REF! | G52: ='Evolutitve SCI'!#REF! -> #REF! | H52: ='Evolutitve SCI'!#REF! -> #REF! | I52: ='Evolutitve SCI'!#REF! -> #REF! | J52: ='Evolutitve SCI'!#REF! -> #REF! | ... AF52: ='Evolutitve SCI'!#REF! -> #REF!
B53: Div + Int on Deposits | C53: ='Evolutitve SCI'!#REF!+'Evolutitve SCI'!#REF!+'Evolutitve SCI'!#REF! -> #REF! | D53: ='Evolutitve SCI'!#REF!+'Evolutitve SCI'!#REF!+'Evolutitve SCI'!#REF! -> #REF! | E53: ='Evolutitve SCI'!#REF!+'Evolutitve SCI'!#REF!+'Evolutitve SCI'!#REF! -> #REF! | F53: ='Evolutitve SCI'!#REF!+'Evolutitve SCI'!#REF!+'Evolutitve SCI'!#REF! -> #REF! | G53: ='Evolutitve SCI'!#REF!+'Evolutitve SCI'!#REF!+'Evolutitve SCI'!#REF! -> #REF! | H53: ='Evolutitve SCI'!#REF!+'Evolutitve SCI'!#REF!+'Evolutitve SCI'!#REF! -> #REF! | I53: ='Evolutitve SCI'!#REF!+'Evolutitve SCI'!#REF!+'Evolutitve SCI'!#REF! -> #REF! | J53: ='Evolutitve SCI'!#REF!+'Evolutitve SCI'!#REF!+'Evolutitve SCI'!#REF! -> #REF! | ... AF53: ='Evolutitve SCI'!#REF!+'Evolutitve SCI'!#REF!+'Evolutitve SCI'!#REF! -> #REF!
B54: Total Expenses | C54: ='Evolutitve SCI'!#REF!+'Evolutitve SCI'!#REF!+'Evolutitve SCI'!#REF!+'Evolutitve SCI'!#REF!+'Evolutitve SCI'!#REF!+'Evolutitve SCI'!#REF! -> #REF! | D54: ='Evolutitve SCI'!#REF!+'Evolutitve SCI'!#REF!+'Evolutitve SCI'!#REF!+'Evolutitve SCI'!#REF!+'Evolutitve SCI'!#REF!+'Evolutitve SCI'!#REF! -> #REF! | E54: ='Evolutitve SCI'!#REF!+'Evolutitve SCI'!#REF!+'Evolutitve SCI'!#REF!+'Evolutitve SCI'!#REF!+'Evolutitve SCI'!#REF!+'Evolutitve SCI'!#REF! -> #REF! | F54: ='Evolutitve SCI'!#REF!+'Evolutitve SCI'!#REF!+'Evolutitve SCI'!#REF!+'Evolutitve SCI'!#REF!+'Evolutitve SCI'!#REF!+'Evolutitve SCI'!#REF! -> #REF! | G54: ='Evolutitve SCI'!#REF!+'Evolutitve SCI'!#REF!+'Evolutitve SCI'!#REF!+'Evolutitve SCI'!#REF!+'Evolutitve SCI'!#REF!+'Evolutitve SCI'!#REF! -> #REF! | H54: ='Evolutitve SCI'!#REF!+'Evolutitve SCI'!#REF!+'Evolutitve SCI'!#REF!+'Evolutitve SCI'!#REF!+'Evolutitve SCI'!#REF!+'Evolutitve SCI'!#REF! -> #REF! | I54: ='Evolutitve SCI'!#REF!+'Evolutitve SCI'!#REF!+'Evolutitve SCI'!#REF!+'Evolutitve SCI'!#REF!+'Evolutitve SCI'!#REF!+'Evolutitve SCI'!#REF! -> #REF! | J54: ='Evolutitve SCI'!#REF!+'Evolutitve SCI'!#REF!+'Evolutitve SCI'!#REF!+'Evolutitve SCI'!#REF!+'Evolutitve SCI'!#REF!+'Evolutitve SCI'!#REF! -> #REF! | ... AF54: ='Evolutitve SCI'!#REF!+'Evolutitve SCI'!#REF!+'Evolutitve SCI'!#REF!+'Evolutitve SCI'!#REF!+'Evolutitve SCI'!#REF!+'Evolutitve SCI'!#REF! -> #REF!
B55: Liquid Assets | C55: ='Evolutive SFP'!#REF!+'Evolutive SFP'!#REF!+'Evolutive SFP'!#REF!+'Evolutive SFP'!#REF! -> #REF! | D55: ='Evolutive SFP'!#REF!+'Evolutive SFP'!#REF!+'Evolutive SFP'!#REF!+'Evolutive SFP'!#REF! -> #REF! | E55: ='Evolutive SFP'!#REF!+'Evolutive SFP'!#REF!+'Evolutive SFP'!#REF!+'Evolutive SFP'!#REF! -> #REF! | F55: ='Evolutive SFP'!#REF!+'Evolutive SFP'!#REF!+'Evolutive SFP'!#REF!+'Evolutive SFP'!#REF! -> #REF! | G55: ='Evolutive SFP'!#REF!+'Evolutive SFP'!#REF!+'Evolutive SFP'!#REF!+'Evolutive SFP'!#REF! -> #REF! | H55: ='Evolutive SFP'!#REF!+'Evolutive SFP'!#REF!+'Evolutive SFP'!#REF!+'Evolutive SFP'!#REF! -> #REF! | I55: ='Evolutive SFP'!#REF!+'Evolutive SFP'!#REF!+'Evolutive SFP'!#REF!+'Evolutive SFP'!#REF! -> #REF! | J55: ='Evolutive SFP'!#REF!+'Evolutive SFP'!#REF!+'Evolutive SFP'!#REF!+'Evolutive SFP'!#REF! -> #REF! | ... AF55: ='Evolutive SFP'!#REF!+'Evolutive SFP'!#REF!+'Evolutive SFP'!#REF!+'Evolutive SFP'!#REF! -> #REF!
