Workbook
Name BALANCE1_LDA01: '[1]Financial Statements'!$E$112
Name BALANCE1_LDA12: '[1]Financial Statements'!$E$123
Name BALANCE2_LDA01: '[1]Financial Statements'!$F$112
Name BALANCE2_LDA12: '[1]Financial Statements'!$F$123
Name BALANCE3_LDA01: '[1]Financial Statements'!$G$112
Name BALANCE3_LDA12: '[1]Financial Statements'!$G$123
Name BALANCE4_LDA01: '[1]Financial Statements'!$H$112
Name BALANCE4_LDA12: '[1]Financial Statements'!$H$123
Name BALANCE5_LDA01: '[1]Financial Statements'!$I$112
Name BALANCE5_LDA12: '[1]Financial Statements'!$I$123
Name BALANCE6_LDA01: '[1]Financial Statements'!$J$112
Name BALANCE6_LDA12: '[1]Financial Statements'!$J$123
Name NotApplicable: 'Prudential Ratios'!$B$76
Name PEARLS1_LA002: '[1]Financial Statements'!$E$280
Name PEARLS1_LE008: '[1]Financial Statements'!$E$275
Name PEARLS1_LE009: '[1]Financial Statements'!$E$276
Name PEARLS1_LR001: '[1]Financial Statements'!$E$282
Name PEARLS1_LR005: '[1]Financial Statements'!$E$286
Name PEARLS1_LR006: '[1]Financial Statements'!$E$287
Name PEARLS1_LR007: '[1]Financial Statements'!$E$288
Name PEARLS1_LR009: '[1]Financial Statements'!$E$290
Name PEARLS1_LS001: '[1]Financial Statements'!$E$298
Name PEARLS1_LS005: '[1]Financial Statements'!$E$302
Name PEARLS1_LS011: '[1]Financial Statements'!$E$308
Name PEARLS2_LA002: '[1]Financial Statements'!$F$280
Name PEARLS2_LE008: '[1]Financial Statements'!$F$275
Name PEARLS2_LE009: '[1]Financial Statements'!$F$276
Name PEARLS2_LR001: '[1]Financial Statements'!$F$282
Name PEARLS2_LR005: '[1]Financial Statements'!$F$286
Name PEARLS2_LR006: '[1]Financial Statements'!$F$287
Name PEARLS2_LR007: '[1]Financial Statements'!$F$288
Name PEARLS2_LR009: '[1]Financial Statements'!$F$290
Name PEARLS2_LS001: '[1]Financial Statements'!$F$298
Name PEARLS2_LS005: '[1]Financial Statements'!$F$302
Name PEARLS2_LS010: '[1]Financial Statements'!$F$307
Name PEARLS2_LS011: '[1]Financial Statements'!$F$308
Name PEARLS3_LA002: '[1]Financial Statements'!$G$280
Name PEARLS3_LE008: '[1]Financial Statements'!$G$275
Name PEARLS3_LE009: '[1]Financial Statements'!$G$276
Name PEARLS3_LR001: '[1]Financial Statements'!$G$282
Name PEARLS3_LR005: '[1]Financial Statements'!$G$286
Name PEARLS3_LR006: '[1]Financial Statements'!$G$287
Name PEARLS3_LR007: '[1]Financial Statements'!$G$288
Name PEARLS3_LR009: '[1]Financial Statements'!$G$290
Name PEARLS3_LS001: '[1]Financial Statements'!$G$298
Name PEARLS3_LS005: '[1]Financial Statements'!$G$302
Name PEARLS3_LS010: '[1]Financial Statements'!$G$307
Name PEARLS3_LS011: '[1]Financial Statements'!$G$308
Name PEARLS4_LA002: '[1]Financial Statements'!$H$280
Name PEARLS4_LE008: '[1]Financial Statements'!$H$275
Name PEARLS4_LE009: '[1]Financial Statements'!$H$276
Name PEARLS4_LR001: '[1]Financial Statements'!$H$282
Name PEARLS4_LR005: '[1]Financial Statements'!$H$286
Name PEARLS4_LR006: '[1]Financial Statements'!$H$287
Name PEARLS4_LR007: '[1]Financial Statements'!$H$288
Name PEARLS4_LR009: '[1]Financial Statements'!$H$290
Name PEARLS4_LS001: '[1]Financial Statements'!$H$298
Name PEARLS4_LS005: '[1]Financial Statements'!$H$302
Name PEARLS4_LS010: '[1]Financial Statements'!$H$307
Name PEARLS4_LS011: '[1]Financial Statements'!$H$308

Sheet compliance status
B2: audited2017 | C2: 43101 | D2: 43133 | E2: 43165 | F2: 43197 | G2: 43229 | H2: 43261 | I2: 43293 | J2: 43325 | K2: 43357 | L2: 43389 | M2: 43421 | N2: 43453
A3: CORE CAPITAL | B3: =IF('Prudential Ratios'!#REF!>10,"compliant","not compliant") -> #REF! | C3: =IF('Prudential Ratios'!#REF!>10,"compliant","not compliant") -> #REF! | D3: =IF('Prudential Ratios'!#REF!>10,"compliant","not compliant") -> #REF! | E3: =IF('Prudential Ratios'!#REF!>10,"compliant","not compliant") -> #REF! | F3: =IF('Prudential Ratios'!#REF!>10,"compliant","not compliant") -> #REF! | G3: =IF('Prudential Ratios'!#REF!>10,"compliant","not compliant") -> #REF! | H3: =IF('Prudential Ratios'!#REF!>10,"compliant","not compliant") -> #REF! | I3: =IF('Prudential Ratios'!#REF!>10,"compliant","not compliant") -> #REF! | ... N3: =IF('Prudential Ratios'!#REF!>10,"compliant","not compliant") -> #REF!
A4: CCA (Min 10%) | B4: =IF('Prudential Ratios'!#REF!>10%,"compliant","not compliant") -> #REF! | C4: =IF('Prudential Ratios'!#REF!>10%,"compliant","not compliant") -> #REF! | D4: =IF('Prudential Ratios'!#REF!>10%,"compliant","not compliant") -> #REF! | E4: =IF('Prudential Ratios'!#REF!>10%,"compliant","not compliant") -> #REF! | F4: =IF('Prudential Ratios'!#REF!>10%,"compliant","not compliant") -> #REF! | G4: =IF('Prudential Ratios'!#REF!>10%,"compliant","not compliant") -> #REF! | H4: =IF('Prudential Ratios'!#REF!>10%,"compliant","not compliant") -> #REF! | I4: =IF('Prudential Ratios'!#REF!>10%,"compliant","not compliant") -> #REF! | ... N4: =IF('Prudential Ratios'!#REF!>10%,"compliant","not compliant") -> #REF!
A5: ICA (Min 8%) | B5: =IF('Prudential Ratios'!#REF!>8%,"compliant","not compliant") -> #REF! | C5: =IF('Prudential Ratios'!#REF!>8%,"compliant","not compliant") -> #REF! | D5: =IF('Prudential Ratios'!#REF!>8%,"compliant","not compliant") -> #REF! | E5: =IF('Prudential Ratios'!#REF!>8%,"compliant","not compliant") -> #REF! | F5: =IF('Prudential Ratios'!#REF!>8%,"compliant","not compliant") -> #REF! | G5: =IF('Prudential Ratios'!#REF!>8%,"compliant","not compliant") -> #REF! | H5: =IF('Prudential Ratios'!#REF!>8%,"compliant","not compliant") -> #REF! | I5: =IF('Prudential Ratios'!#REF!>8%,"compliant","not compliant") -> #REF! | ... N5: =IF('Prudential Ratios'!#REF!>8%,"compliant","not compliant") -> #REF!
A6: CCD (Min 8%) | B6: =IF('Prudential Ratios'!#REF!>8%,"compliant","not compliant") -> #REF! | C6: =IF('Prudential Ratios'!#REF!>8%,"compliant","not compliant") -> #REF! | D6: =IF('Prudential Ratios'!#REF!>8%,"compliant","not compliant") -> #REF! | E6: =IF('Prudential Ratios'!#REF!>8%,"compliant","not compliant") -> #REF! | F6: =IF('Prudential Ratios'!#REF!>8%,"compliant","not compliant") -> #REF! | G6: =IF('Prudential Ratios'!#REF!>8%,"compliant","not compliant") -> #REF! | H6: =IF('Prudential Ratios'!#REF!>8%,"compliant","not compliant") -> #REF! | I6: =IF('Prudential Ratios'!#REF!>8%,"compliant","not compliant") -> #REF! | ... N6: =IF('Prudential Ratios'!#REF!>8%,"compliant","not compliant") -> #REF!
A7: NPL(5%)
A8: Liquidity(15%) | B8: =IF('Prudential Ratios'!#REF!>15%,"compliant","not compliant") -> #REF! | C8: =IF('Prudential Ratios'!#REF!>15%,"compliant","not compliant") -> #REF! | D8: =IF('Prudential Ratios'!#REF!>15%,"compliant","not compliant") -> #REF! | E8: =IF('Prudential Ratios'!#REF!>15%,"compliant","not compliant") -> #REF! | F8: =IF('Prudential Ratios'!#REF!>15%,"compliant","not compliant") -> #REF! | G8: =IF('Prudential Ratios'!#REF!>15%,"compliant","not compliant") -> #REF! | H8: =IF('Prudential Ratios'!#REF!>15%,"compliant","not compliant") -> #REF! | I8: =IF('Prudential Ratios'!#REF!>15%,"compliant","not compliant") -> #REF! | ... N8: =IF('Prudential Ratios'!#REF!>15%,"compliant","not compliant") -> #REF!
A9: NEA (Max 10%) | B9: =IF('Prudential Ratios'!#REF!<10%,"compliant","not compliant") -> #REF! | C9: =IF('Prudential Ratios'!#REF!<10%,"compliant","not compliant") -> #REF! | D9: =IF('Prudential Ratios'!#REF!<10%,"compliant","not compliant") -> #REF! | E9: =IF('Prudential Ratios'!#REF!<10%,"compliant","not compliant") -> #REF! | F9: =IF('Prudential Ratios'!#REF!<10%,"compliant","not compliant") -> #REF! | G9: =IF('Prudential Ratios'!#REF!<10%,"compliant","not compliant") -> #REF! | H9: =IF('Prudential Ratios'!#REF!<10%,"compliant","not compliant") -> #REF! | I9: =IF('Prudential Ratios'!#REF!<10%,"compliant","not compliant") -> #REF! | ... N9: =IF('Prudential Ratios'!#REF!<10%,"compliant","not compliant") -> #REF!
A10: LB ratio (Max 5%) | B10: =IF('Prudential Ratios'!#REF!<5%,"compliant","not compliant") -> #REF! | C10: =IF('Prudential Ratios'!#REF!<5%,"compliant","not compliant") -> #REF! | D10: =IF('Prudential Ratios'!#REF!<5%,"compliant","not compliant") -> #REF! | E10: =IF('Prudential Ratios'!#REF!<5%,"compliant","not compliant") -> #REF! | F10: =IF('Prudential Ratios'!#REF!<5%,"compliant","not compliant") -> #REF! | G10: =IF('Prudential Ratios'!#REF!<5%,"compliant","not compliant") -> #REF! | H10: =IF('Prudential Ratios'!#REF!<5%,"compliant","not compliant") -> #REF! | I10: =IF('Prudential Ratios'!#REF!<5%,"compliant","not compliant") -> #REF! | ... N10: =IF('Prudential Ratios'!#REF!<5%,"compliant","not compliant") -> #REF!
A11: FITD (Max 5%) | B11: =IF('Prudential Ratios'!#REF!<5%,"compliant","not compliant") -> #REF! | C11: =IF('Prudential Ratios'!#REF!<5%,"compliant","not compliant") -> #REF! | D11: =IF('Prudential Ratios'!#REF!<5%,"compliant","not compliant") -> #REF! | E11: =IF('Prudential Ratios'!#REF!<5%,"compliant","not compliant") -> #REF! | F11: =IF('Prudential Ratios'!#REF!<5%,"compliant","not compliant") -> #REF! | G11: =IF('Prudential Ratios'!#REF!<5%,"compliant","not compliant") -> #REF! | H11: =IF('Prudential Ratios'!#REF!<5%,"compliant","not compliant") -> #REF! | I11: =IF('Prudential Ratios'!#REF!<5%,"compliant","not compliant") -> #REF! | ... N11: =IF('Prudential Ratios'!#REF!<5%,"compliant","not compliant") -> #REF!
A12: FICC (Max 40%) | B12: =IF('Prudential Ratios'!#REF!<40%,"compliant","not compliant") -> #REF! | C12: =IF('Prudential Ratios'!#REF!<40%,"compliant","not compliant") -> #REF! | D12: =IF('Prudential Ratios'!#REF!<40%,"compliant","not compliant") -> #REF! | E12: =IF('Prudential Ratios'!#REF!<40%,"compliant","not compliant") -> #REF! | F12: =IF('Prudential Ratios'!#REF!<40%,"compliant","not compliant") -> #REF! | G12: =IF('Prudential Ratios'!#REF!<40%,"compliant","not compliant") -> #REF! | H12: =IF('Prudential Ratios'!#REF!<40%,"compliant","not compliant") -> #REF! | I12: =IF('Prudential Ratios'!#REF!<40%,"compliant","not compliant") -> #REF! | ... N12: =IF('Prudential Ratios'!#REF!<40%,"compliant","not compliant") -> #REF!
A13: EB ratio | B13: =IF('Prudential Ratios'!#REF!<25%,"compliant","not compliant") -> #REF! | C13: =IF('Prudential Ratios'!#REF!<25%,"compliant","not compliant") -> #REF! | D13: =IF('Prudential Ratios'!#REF!<25%,"compliant","not compliant") -> #REF! | E13: =IF('Prudential Ratios'!#REF!<25%,"compliant","not compliant") -> #REF! | F13: =IF('Prudential Ratios'!#REF!<25%,"compliant","not compliant") -> #REF! | G13: =IF('Prudential Ratios'!#REF!<25%,"compliant","not compliant") -> #REF! | H13: =IF('Prudential Ratios'!#REF!<25%,"compliant","not compliant") -> #REF! | I13: =IF('Prudential Ratios'!#REF!<25%,"compliant","not compliant") -> #REF! | ... N13: =IF('Prudential Ratios'!#REF!<25%,"compliant","not compliant") -> #REF!
A14: A=S+L | B14: =IF('SFP-2022'!#REF!='SFP-2022'!#REF!,"balancing","notbalancing") -> #REF! | C14: =IF('SFP-2022'!#REF!='SFP-2022'!#REF!,"balancing","notbalancing") -> #REF! | D14: =IF('SFP-2022'!#REF!='SFP-2022'!#REF!,"balancing","notbalancing") -> #REF! | E14: =IF('SFP-2022'!#REF!='SFP-2022'!#REF!,"balancing","notbalancing") -> #REF! | F14: =IF('SFP-2022'!#REF!='SFP-2022'!#REF!,"balancing","notbalancing") -> #REF! | G14: =IF('SFP-2022'!#REF!='SFP-2022'!#REF!,"balancing","notbalancing") -> #REF! | H14: =IF('SFP-2022'!#REF!='SFP-2022'!#REF!,"balancing","notbalancing") -> #REF! | I14: =IF('SFP-2022'!#REF!='SFP-2022'!#REF!,"balancing","notbalancing") -> #REF! | ... N14: =IF('SFP-2022'!#REF!='SFP-2022'!#REF!,"balancing","notbalancing") -> #REF!

Sheet Prudential Ratios
C1: KWETU SACCO SOCIETY LTD
C2: Sacco Financial Performance
C4: FINANCIAL SOUNDNESS INDICATORS | D4: Prude. Std | E4: Audited 2020 | F4: 44197 | G4: 44228 | H4: 44256 | I4: 44287 | J4: 44317 | K4: 44348 | L4: 44378 | M4: 44409 | N4: 44440 | O4: 44470 | P4: 44501 | Q4: 44531 | R4: Audited 2021 | S4: 44562 | T4: 44593 | U4: 44621 | V4: 44652 | W4: 44682 | X4: 44713 | Y4: 44743 | Z4: 44774 | AA4: 44805 | AB4: 44835 | AC4: 44866 | AD4: 44896 | AE4: Audited-2022 | AF4: 44949 | AG4: 44980 | AH4: 45008 | AI4: 45039 | AJ4: 45069 | AK4: 45100
B5: 1 | C5: CAPITAL ADEQUACY REQUIREMENTS
B6: 1.1 | C6: Core capital | D6: ≥ Ksh.10M | E6: =Financials!C14/1000000 -> 629.59023 | F6: =Financials!D14/1000000 -> 637.74636 | G6: =Financials!E14/1000000 -> 670.01584 | H6: =Financials!F14/1000000 -> 689.21991 | I6: =Financials!G14/1000000 -> 727.8007 | J6: =Financials!H14/1000000 -> 707.23569 | K6: =Financials!I14/1000000 -> 716.34862 | L6: =Financials!J14/1000000 -> 724.18982 | ... AK6: =Financials!AI14/1000000 -> 1198.318
B7: 1.2 | C7: Core capital /Total Assets | D7: ≥ 10% | E7: =Financials!C14/Financials!C5 -> 0.14376602 | F7: =Financials!D14/Financials!D5 -> 0.14528077 | G7: =Financials!E14/Financials!E5 -> 0.15149908 | H7: =Financials!F14/Financials!F5 -> 0.15561639 | I7: =Financials!G14/Financials!G5 -> 0.16282358 | J7: =Financials!H14/Financials!H5 -> 0.15929066 | K7: =Financials!I14/Financials!I5 -> 0.16085586 | L7: =Financials!J14/Financials!J5 -> 0.1580466 | ... AK7: =Financials!AI14/Financials!AI5 -> 0.2328877
B8: 1.3 | C8: Core capital /Total Deposits | D8: ≥ 8% | E8: =Financials!C14/Financials!C6 -> 0.26221751 | F8: =Financials!D14/Financials!D6 -> 0.26444542 | G8: =Financials!E14/Financials!E6 -> 0.27423695 | H8: =Financials!F14/Financials!F6 -> 0.28252581 | I8: =Financials!G14/Financials!G6 -> 0.29340121 | J8: =Financials!H14/Financials!H6 -> 0.28654143 | K8: =Financials!I14/Financials!I6 -> 0.28894288 | L8: =Financials!J14/Financials!J6 -> 0.27781485 | ... AK8: =Financials!AI14/Financials!AI6 -> 0.44084484
B9: 1.4 | C9: Share Capital/Total Assets | D9: ≤2% | E9: =Financials!C18/Financials!C5 -> 0.06447744 | F9: =Financials!D18/Financials!D5 -> 0.064535888 | G9: =Financials!E18/Financials!E5 -> 0.064304703 | H9: =Financials!F18/Financials!F5 -> 0.064477695 | I9: =Financials!G18/Financials!G5 -> 0.064149519 | J9: =Financials!H18/Financials!H5 -> 0.064808329 | K9: =Financials!I18/Financials!I5 -> 0.064940823 | L9: =Financials!J18/Financials!J5 -> 0.063402115 | ... AK9: =Financials!AI18/Financials!AI5 -> 0.079479255
B10: 1.5 | C10: Institutional Capital/Total Assets | D10: ≥ 8% | E10: =Financials!C15/Financials!C5 -> 0.079288584 | F10: =Financials!D15/Financials!D5 -> 0.080744884 | G10: =Financials!E15/Financials!E5 -> 0.087194377 | H10: =Financials!F15/Financials!F5 -> 0.09113869 | I10: =Financials!G15/Financials!G5 -> 0.098674062 | J10: =Financials!H15/Financials!H5 -> 0.094482328 | K10: =Financials!I15/Financials!I5 -> 0.095915038 | L10: =Financials!J15/Financials!J5 -> 0.094644481 | ... AK10: =Financials!AI15/Financials!AI5 -> 0.15340844
B12: 2 | C12: ASSET MIX AND QUALITY
B13: 2.1 | C13: Non Earning Assets
B14: 2.1.1 | C14: Non earning Assets/Total assets | D14: ≤ 10% | E14: =Financials!C38/Financials!C5 -> 0.27231684 | F14: =Financials!D38/Financials!D5 -> 0.27381193 | G14: =Financials!E38/Financials!E5 -> 0.27168583 | H14: =Financials!F38/Financials!F5 -> 0.27195813 | I14: =Financials!G38/Financials!G5 -> 0.26486552 | J14: =Financials!H38/Financials!H5 -> 0.27000834 | K14: =Financials!I38/Financials!I5 -> 0.26543324 | L14: =Financials!J38/Financials!J5 -> 0.25780748 | ... AK14: =Financials!AI38/Financials!AI5 -> 0.22392615
B15: 2.1.2 | C15: Property and Equipment/Total Assets | D15: ≤ 5% | E15: =Financials!C39/Financials!C5 -> 0.031560111 | F15: =Financials!D39/Financials!D5 -> 0.03132349 | G15: =Financials!E39/Financials!E5 -> 0.031069599 | H15: =Financials!F39/Financials!F5 -> 0.030932915 | I15: =Financials!G39/Financials!G5 -> 0.031384934 | J15: =Financials!H39/Financials!H5 -> 0.031646156 | K15: =Financials!I39/Financials!I5 -> 0.03159001 | L15: =Financials!J39/Financials!J5 -> 0.03072233 | ... AK15: =Financials!AI39/Financials!AI5 -> 0.031187136
B16: 2.1.3 | C16: Non Performing loans/Gross Loans | D16: ≤ 6%
B18: 2.2 | C18: Earning Assets
B19: 2.2.1 | C19: Equities & Investments/Deposits | D19: ≤ 5% | E19: =Financials!C26/Financials!C6 -> 0.35331811 | F19: =Financials!D26/Financials!D6 -> 0.34926009 | G19: =Financials!E26/Financials!E6 -> 0.3448504 | H19: =Financials!F26/Financials!F6 -> 0.34543073 | I19: =Financials!G26/Financials!G6 -> 0.33976311 | J19: =Financials!H26/Financials!H6 -> 0.34148828 | K19: =Financials!I26/Financials!I6 -> 0.34002568 | L19: =Financials!J26/Financials!J6 -> 0.32339045 | ... AK19: =Financials!AI26/Financials!AI6 -> 0.28311329
B20: 2.2.2 | C20: Equities & Investments/Core Capital | D20: ≤ 40% | E20: =Financials!C26/Financials!C14 -> 1.3474238 | F20: =Financials!D26/Financials!D14 -> 1.3207265 | G20: =Financials!E26/Financials!E14 -> 1.2574906 | H20: =Financials!F26/Financials!F14 -> 1.2226519 | I20: =Financials!G26/Financials!G14 -> 1.1580154 | J20: =Financials!H26/Financials!H14 -> 1.1917588 | K20: =Financials!I26/Financials!I14 -> 1.176792 | L20: =Financials!J26/Financials!J14 -> 1.1640503 | ... AK20: =Financials!AI26/Financials!AI14 -> 0.64220619
B21: 2.2.3 | C21: Net Loans & advances /Total assets | D21: NPR | E21: =Financials!C31/Financials!C5 -> 0.47658656 | F21: =Financials!D31/Financials!D5 -> 0.47787352 | G21: =Financials!E31/Financials!E5 -> 0.47921217 | H21: =Financials!F31/Financials!F5 -> 0.48191869 | I21: =Financials!G31/Financials!G5 -> 0.47989055 | J21: =Financials!H31/Financials!H5 -> 0.48221068 | K21: =Financials!I31/Financials!I5 -> 0.48725956 | L21: =Financials!J31/Financials!J5 -> 0.48320864 | ... AK21: =Financials!AI31/Financials!AI5 -> 0.55616217
B23: 3 | C23: FUNDING MIX
B24: 3.1 | C24: Total Deposits/Total Assets | D24: NPR | E24: =Financials!C6/Financials!C5 -> 0.54827012 | F24: =Financials!D6/Financials!D5 -> 0.54937903 | G24: =Financials!E6/Financials!E5 -> 0.55243861 | H24: =Financials!F6/Financials!F5 -> 0.55080414 | I24: =Financials!G6/Financials!G5 -> 0.55495198 | J24: =Financials!H6/Financials!H5 -> 0.55590795 | K24: =Financials!I6/Financials!I5 -> 0.55670471 | L24: =Financials!J6/Financials!J5 -> 0.56889183 | ... AK24: =Financials!AI6/Financials!AI5 -> 0.52827588
B25: 3.1.1 | C25: BOSA Deposits/Total Assets | D25: NPR | E25: =Financials!C7/Financials!C5 -> 0.54827012 | F25: =Financials!D7/Financials!D5 -> 0.54937903 | G25: =Financials!E7/Financials!E5 -> 0.55243861 | H25: =Financials!F7/Financials!F5 -> 0.55080414 | I25: =Financials!G7/Financials!G5 -> 0.55495198 | J25: =Financials!H7/Financials!H5 -> 0.55590795 | K25: =Financials!I7/Financials!I5 -> 0.55670471 | L25: =Financials!J7/Financials!J5 -> 0.56889183 | ... AK25: =Financials!AI7/Financials!AI5 -> 0.52827588
B26: 3.1.2 | C26: FOSA Deposits/Total Assets | D26: NPR | E26: =Financials!C8/Financials!C5 -> 0.12563503 | F26: =Financials!D8/Financials!D5 -> 0.074312766 | G26: =Financials!E8/Financials!E5 -> 0.077185346 | H26: =Financials!F8/Financials!F5 -> 0.073284241 | I26: =Financials!G8/Financials!G5 -> 0.080028241 | J26: =Financials!H8/Financials!H5 -> 0.074455919 | K26: =Financials!I8/Financials!I5 -> 0.07191886 | L26: =Financials!J8/Financials!J5 -> 0.091701426 | ... AK26: =Financials!AI8/Financials!AI5 -> 0.073962086
B27: 3.2 | C27: External Borrowing/Total assets | D27: ≤ 25% | E27: =Financials!C9/Financials!C5 -> 0.10637237 | F27: =Financials!D9/Financials!D5 -> 0.10365053 | G27: =Financials!E9/Financials!E5 -> 0.10043172 | H27: =Financials!F9/Financials!F5 -> 0.097840713 | I27: =Financials!G9/Financials!G5 -> 0.094521704 | J27: =Financials!H9/Financials!H5 -> 0.092719661 | K27: =Financials!I9/Financials!I5 -> 0.090007001 | L27: =Financials!J9/Financials!J5 -> 0.085113282 | ... AK27: =Financials!AI9/Financials!AI5 -> 0.082110965
B29: 4 | C29: GROWTH RATIOS
B30: 4.1 | C30: Total Assets | D30: NPR | F30: =Financials!D5/Financials!B5-1 -> #VALUE! | G30: =Financials!E5/Financials!D5-1 -> 0.0074771871 | H30: =Financials!F5/Financials!E5-1 -> 0.0014457338 | I30: =Financials!G5/Financials!F5-1 -> 0.0092358729 | J30: =Financials!H5/Financials!G5-1 -> -0.0067039718 | K30: =Financials!I5/Financials!H5-1 -> 0.0030294205 | L30: =Financials!J5/Financials!I5-1 -> 0.028915543 | M30: =Financials!K5/Financials!J5-1 -> 0.0055837948 | N30: =Financials!L5/Financials!K5-1 -> 0.0019569454 | ... AK30: =Financials!AI5/Financials!AH5-1 -> 0.0052249869
B31: 4.2 | C31: Total Deposits | D31: NPR | F31: =Financials!D6/Financials!B6-1 -> #VALUE! | G31: =Financials!E6/Financials!D6-1 -> 0.013087988 | H31: =Financials!F6/Financials!E6-1 -> -0.0015171974 | I31: =Financials!G6/Financials!F6-1 -> 0.016835937 | J31: =Financials!H6/Financials!G6-1 -> -0.004992898 | K31: =Financials!I6/Financials!H6-1 -> 0.004467022 | L31: =Financials!J6/Financials!I6-1 -> 0.051440076 | M31: =Financials!K6/Financials!J6-1 -> 0.0057482085 | N31: =Financials!L6/Financials!K6-1 -> 0.0011621312 | ... AK31: =Financials!AI6/Financials!AH6-1 -> 0.029730503
B32: 4.2.1 | C32: FOSA Deposits | D32: NPR | F32: =Financials!D8/Financials!B8-1 -> #VALUE! | G32: =Financials!E8/Financials!D8-1 -> 0.046421484 | H32: =Financials!F8/Financials!E8-1 -> -0.049169375 | I32: =Financials!G8/Financials!F8-1 -> 0.10211104 | J32: =Financials!H8/Financials!G8-1 -> -0.075866624 | K32: =Financials!I8/Financials!H8-1 -> -0.031148444 | L32: =Financials!J8/Financials!I8-1 -> 0.31193711 | M32: =Financials!K8/Financials!J8-1 -> -0.044282159 | N32: =Financials!L8/Financials!K8-1 -> -0.023522112 | ... AK32: =Financials!AI8/Financials!AH8-1 -> 0.11722684
B33: 4.2.2 | C33: BOSA Deposits | D33: NPR | F33: =Financials!D7/Financials!B7-1 -> #VALUE! | G33: =Financials!E7/Financials!D7-1 -> 0.013087988 | H33: =Financials!F7/Financials!E7-1 -> -0.0015171974 | I33: =Financials!G7/Financials!F7-1 -> 0.016835937 | J33: =Financials!H7/Financials!G7-1 -> -0.004992898 | K33: =Financials!I7/Financials!H7-1 -> 0.004467022 | L33: =Financials!J7/Financials!I7-1 -> 0.051440076 | M33: =Financials!K7/Financials!J7-1 -> 0.0057482085 | N33: =Financials!L7/Financials!K7-1 -> 0.0011621312 | ... AK33: =Financials!AI7/Financials!AH7-1 -> 0.029730503
B34: 4.3 | C34: Net Loans & advances | D34: NPR | F34: =Financials!D31/Financials!B31-1 -> #VALUE! | G34: =Financials!E31/Financials!D31-1 -> 0.01029939 | H34: =Financials!F31/Financials!E31-1 -> 0.0071017602 | I34: =Financials!G31/Financials!F31-1 -> 0.004988531 | J34: =Financials!H31/Financials!G31-1 -> -0.0019016746 | K34: =Financials!I31/Financials!H31-1 -> 0.013531405 | L34: =Financials!J31/Financials!I31-1 -> 0.020361482 | M34: =Financials!K31/Financials!J31-1 -> -0.0092507579 | N34: =Financials!L31/Financials!K31-1 -> 0.011612861 | ... AK34: =Financials!AI31/Financials!AH31-1 -> -0.029506738
B35: 4.4 | C35: Core capital | D35: NPR | F35: =Financials!D14/Financials!B14-1 -> #VALUE! | G35: =Financials!E14/Financials!D14-1 -> 0.050599237 | H35: =Financials!F14/Financials!E14-1 -> 0.028662116 | I35: =Financials!G14/Financials!F14-1 -> 0.055977481 | J35: =Financials!H14/Financials!G14-1 -> -0.028256374 | K35: =Financials!I14/Financials!H14-1 -> 0.01288528 | L35: =Financials!J14/Financials!I14-1 -> 0.010946062 | M35: =Financials!K14/Financials!J14-1 -> 0.022292771 | N35: =Financials!L14/Financials!K14-1 -> 0.012804155 | ... AK35: =Financials!AI14/Financials!AH14-1 -> 0.066256889
B36: 4.5 | C36: Total Gross Income | D36: NPR | F36: =Financials!D41/Financials!B41-1 -> #VALUE! | G36: =Financials!E41/Financials!D41-1 -> 0.099146334 | H36: =Financials!F41/Financials!E41-1 -> 0.020988053 | I36: =Financials!G41/Financials!F41-1 -> -0.062053427 | J36: =Financials!H41/Financials!G41-1 -> -0.095693316 | K36: =Financials!I41/Financials!H41-1 -> 0.019166248 | L36: =Financials!J41/Financials!I41-1 -> 0.0072405752 | M36: =Financials!K41/Financials!J41-1 -> 0.040751732 | N36: =Financials!L41/Financials!K41-1 -> 0.00892081 | ... AK36: =Financials!AI41/Financials!AH41-1 -> -0.038768986
B37: 4.6 | C37: Membership | D37: NPR
B39: 5 | C39: Efficiency Ratios
B40: 5.1 | C40: FinCost-Deposits/Average Deposits | D40: NPR | E40: =Financials!C48/((Financials!C6+Financials!A6)/2) -> 0.18416553 | F40: =Financials!D48/((Financials!D6+Financials!B6)/2) -> #VALUE! | G40: =Financials!E48/((Financials!E6+Financials!D6)/2) -> 0.0022826208 | H40: =Financials!F48/((Financials!F6+Financials!E6)/2) -> 0.0036078733 | I40: =Financials!G48/((Financials!G6+Financials!F6)/2) -> 0.027252862 | J40: =Financials!H48/((Financials!H6+Financials!G6)/2) -> 0.032661346 | K40: =Financials!I48/((Financials!I6+Financials!H6)/2) -> 0.036367464 | L40: =Financials!J48/((Financials!J6+Financials!I6)/2) -> 0.039238108 | M40: =Financials!K48/((Financials!K6+Financials!J6)/2) -> 0.041493454 | N40: =Financials!L48/((Financials!L6+Financials!K6)/2) -> 0.045098839 | ... AK40: =Financials!AI48/((Financials!AI6+Financials!AH6)/2) -> 0.041851975
B41: 5.2 | C41: FinCost-Shares/Average Share capital | D41: NPR | E41: =Financials!C49/((Financials!C18+Financials!A18)/2) -> #VALUE! | F41: =Financials!D49/((Financials!D18+Financials!B18)/2) -> #VALUE! | G41: =Financials!E49/((Financials!E18+Financials!D18)/2) -> 0 | H41: =Financials!F49/((Financials!F18+Financials!E18)/2) -> 0 | I41: =Financials!G49/((Financials!G18+Financials!F18)/2) -> 0 | J41: =Financials!H49/((Financials!H18+Financials!G18)/2) -> 0 | K41: =Financials!I49/((Financials!I18+Financials!H18)/2) -> 0 | L41: =Financials!J49/((Financials!J18+Financials!I18)/2) -> 0 | M41: =Financials!K49/((Financials!K18+Financials!J18)/2) -> 0 | N41: =Financials!L49/((Financials!L18+Financials!K18)/2) -> 0 | ... AK41: =Financials!AI49/((Financials!AI18+Financials!AH18)/2) -> 0
B42: 5.3 | C42: FinCost-Ext Loans/Average Ext Loans | D42: NPR | E42: =Financials!C50/((Financials!C9+Financials!A9)/2) -> 0 | F42: =Financials!D50/((Financials!D9+Financials!B9)/2) -> #VALUE! | G42: =Financials!E50/((Financials!E9+Financials!D9)/2) -> 0.022342732 | H42: =Financials!F50/((Financials!F9+Financials!E9)/2) -> 0.032888655 | I42: =Financials!G50/((Financials!G9+Financials!F9)/2) -> 0.044786464 | J42: =Financials!H50/((Financials!H9+Financials!G9)/2) -> 0.056653018 | K42: =Financials!I50/((Financials!I9+Financials!H9)/2) -> 0.069288449 | L42: =Financials!J50/((Financials!J9+Financials!I9)/2) -> 0.081976958 | M42: =Financials!K50/((Financials!K9+Financials!J9)/2) -> 0.095353948 | N42: =Financials!L50/((Financials!L9+Financials!K9)/2) -> 0.10919112 | ... AK42: =Financials!AI50/((Financials!AI9+Financials!AH9)/2) -> 0.06851627
B43: 5.4 | C43: OpEx/Average Total Assets | D43: NPR | E43: =(Financials!C52+Financials!C53)/((Financials!C5+Financials!A5)/2) -> 0.080372012 | F43: =(Financials!D52+Financials!D53)/((Financials!D5+Financials!B5)/2) -> #VALUE! | G43: =(Financials!E52+Financials!E53)/((Financials!E5+Financials!D5)/2) -> 0.0058310399 | H43: =(Financials!F52+Financials!F53)/((Financials!F5+Financials!E5)/2) -> 0.0094401883 | I43: =(Financials!G52+Financials!G53)/((Financials!G5+Financials!F5)/2) -> 0.012740571 | J43: =(Financials!H52+Financials!H53)/((Financials!H5+Financials!G5)/2) -> 0.014708069 | K43: =(Financials!I52+Financials!I53)/((Financials!I5+Financials!H5)/2) -> 0.016542346 | L43: =(Financials!J52+Financials!J53)/((Financials!J5+Financials!I5)/2) -> 0.018489481 | M43: =(Financials!K52+Financials!K53)/((Financials!K5+Financials!J5)/2) -> 0.019694143 | N43: =(Financials!L52+Financials!L53)/((Financials!L5+Financials!K5)/2) -> 0.021510843 | ... AK43: =(Financials!AI52+Financials!AI53)/((Financials!AI5+Financials!AH5)/2) -> 0.021005275
B44: 5.5 | C44: Avge yield on Net loans | D44: NPR | E44: =Financials!C42/((Financials!C31+Financials!A31)/2) -> 0.097304206 | F44: =Financials!D42/((Financials!D31+Financials!B31)/2) -> #VALUE! | G44: =Financials!E42/((Financials!E31+Financials!D31)/2) -> 0.048157238 | H44: =Financials!F42/((Financials!F31+Financials!E31)/2) -> 0.047742244 | I44: =Financials!G42/((Financials!G31+Financials!F31)/2) -> 0.047455546 | J44: =Financials!H42/((Financials!H31+Financials!G31)/2) -> 0.04738282 | K44: =Financials!I42/((Financials!I31+Financials!H31)/2) -> 0.047109232 | L44: =Financials!J42/((Financials!J31+Financials!I31)/2) -> 0.046323156 | M44: =Financials!K42/((Financials!K31+Financials!J31)/2) -> 0.046074073 | N44: =Financials!L42/((Financials!L31+Financials!K31)/2) -> 0.04602195 | ... AK44: =Financials!AI42/((Financials!AI31+Financials!AH31)/2) -> 0.052502872
B46: 6 | C46: Liquidity Ratio
B47: 6.1 | C47: minimum Liquidity | D47: 0.15 | E47: =('SFP-2022'!B4+'SFP-2022'!B11)/('SFP-2022'!#REF!+'SFP-2022'!B33+'SFP-2022'!B34+'SFP-2022'!B35+'SFP-2022'!B36+'SFP-2022'!B37) -> #REF! | F47: =('SFP-2022'!C4+'SFP-2022'!C11)/('SFP-2022'!#REF!+'SFP-2022'!C33+'SFP-2022'!C34+'SFP-2022'!C35+'SFP-2022'!C36+'SFP-2022'!C37) -> #REF! | G47: ='SFP-2022'!D4/('SFP-2022'!D28+'SFP-2022'!D37) -> 0.58941618 | H47: ='SFP-2022'!E4/('SFP-2022'!E28+'SFP-2022'!E37) -> 0.5827146 | I47: ='SFP-2022'!F4/('SFP-2022'!F28+'SFP-2022'!F37) -> 0.69405351 | J47: ='SFP-2022'!G4/('SFP-2022'!G28+'SFP-2022'!G37) -> 0.61783139 | K47: ='SFP-2022'!H4/('SFP-2022'!H28+'SFP-2022'!H37) -> 0.6296639 | L47: ='SFP-2022'!I4/('SFP-2022'!I28+'SFP-2022'!I37) -> 0.66839464 | M47: ='SFP-2022'!J4/('SFP-2022'!J28+'SFP-2022'!J37) -> 0.63491466 | N47: ='SFP-2022'!K4/('SFP-2022'!K28+'SFP-2022'!K37) -> 0.60259415 | ... AK47: ='SFP-2022'!AH4/('SFP-2022'!AH28+'SFP-2022'!AH37) -> 0.73228622
C48: TECHNICAL Liquidity | E48: =('SFP-2022'!B4+'SFP-2022'!B11)/('SFP-2022'!B31+'SFP-2022'!B33+'SFP-2022'!B34+'SFP-2022'!B35+'SFP-2022'!B36+'SFP-2022'!B37) -> 0.44072713 | F48: =('SFP-2022'!C4+'SFP-2022'!C11)/('SFP-2022'!C31+'SFP-2022'!C33+'SFP-2022'!C34+'SFP-2022'!C35+'SFP-2022'!C36+'SFP-2022'!C37) -> 0.43079737 | G48: =('SFP-2022'!D4+'SFP-2022'!D11)/('SFP-2022'!D31+'SFP-2022'!D33+'SFP-2022'!D34+'SFP-2022'!D35+'SFP-2022'!D36+'SFP-2022'!D37) -> 0.43344427 | H48: =('SFP-2022'!E4+'SFP-2022'!E11)/('SFP-2022'!E31+'SFP-2022'!E33+'SFP-2022'!E34+'SFP-2022'!E35+'SFP-2022'!E36+'SFP-2022'!E37) -> 0.42921403 | I48: =('SFP-2022'!F4+'SFP-2022'!F11)/('SFP-2022'!F31+'SFP-2022'!F33+'SFP-2022'!F34+'SFP-2022'!F35+'SFP-2022'!F36+'SFP-2022'!F37) -> 0.44691535 | J48: =('SFP-2022'!G4+'SFP-2022'!G11)/('SFP-2022'!G31+'SFP-2022'!G33+'SFP-2022'!G34+'SFP-2022'!G35+'SFP-2022'!G36+'SFP-2022'!G37) -> 0.43069803 | K48: =('SFP-2022'!H4+'SFP-2022'!H11)/('SFP-2022'!H31+'SFP-2022'!H33+'SFP-2022'!H34+'SFP-2022'!H35+'SFP-2022'!H36+'SFP-2022'!H37) -> 0.428631 | L48: =('SFP-2022'!I4+'SFP-2022'!I11)/('SFP-2022'!I31+'SFP-2022'!I33+'SFP-2022'!I34+'SFP-2022'!I35+'SFP-2022'!I36+'SFP-2022'!I37) -> 0.43931959 | ... AK48: =('SFP-2022'!AH4+'SFP-2022'!AH11)/('SFP-2022'!AH31+'SFP-2022'!AH33+'SFP-2022'!AH34+'SFP-2022'!AH35+'SFP-2022'!AH36+'SFP-2022'!AH37) -> 0.39947235
B49: 7 | C49: Loan Loss Provisions Ratios
B50: 7.1 | C50: Actual LLP / Required LLP | D50: 1
B51: 7.2 | C51: allowance for loan loss/NPL
C52: Loan interest/Net Loans | E52: ='SCI-2022'!B5/'SFP-2022'!B14 -> 0.21865339 | F52: ='SCI-2022'!C5/'SFP-2022'!C14 -> 0.016394011 | G52: ='SCI-2022'!D5/'SFP-2022'!D14 -> 0.032888148 | H52: ='SCI-2022'!E5/'SFP-2022'!E14 -> 0.048552606 | I52: ='SCI-2022'!F5/'SFP-2022'!F14 -> 0.065180308 | J52: ='SCI-2022'!G5/'SFP-2022'!G14 -> 0.081684933 | K52: ='SCI-2022'!H5/'SFP-2022'!H14 -> 0.09780057 | L52: ='SCI-2022'!I5/'SFP-2022'!I14 -> 0.1142076 | ... AK52: ='SCI-2022'!AH5/'SFP-2022'!AH14 -> 0.094443343
C53: Gross loans/Total assets | E53: =Financials!C32/Financials!C5 -> 0.49165381 | F53: =Financials!D32/Financials!D5 -> 0.49324322 | G53: =Financials!E32/Financials!E5 -> 0.4953214 | H53: =Financials!F32/Financials!F5 -> 0.49639253 | I53: =Financials!G32/Financials!G5 -> 0.49497242 | J53: =Financials!H32/Financials!H5 -> 0.49797374 | K53: =Financials!I32/Financials!I5 -> 0.50459775 | L53: =Financials!J32/Financials!J5 -> 0.5015678 | ... AK53: =Financials!AI32/Financials!AI5 -> 0.5736983
B54: 8 | C54: Earnings
B55: 8.1 | C55: ROA | E55: ='SCI-2022'!B33/('SFP-2022'!#REF!+'SFP-2022'!B27/2) -> #REF! | F55: ='SCI-2022'!C33/('SFP-2022'!A27+'SFP-2022'!C27/2) -> #VALUE! | G55: ='SCI-2022'!D33/('SFP-2022'!C27+'SFP-2022'!D27/2) -> 0.0017874322 | H55: ='SCI-2022'!E33/('SFP-2022'!D27+'SFP-2022'!E27/2) -> 0.0037483423 | I55: ='SCI-2022'!F33/('SFP-2022'!E27+'SFP-2022'!F27/2) -> 0.011588337 | J55: ='SCI-2022'!G33/('SFP-2022'!F27+'SFP-2022'!G27/2) -> 0.011548673 | K55: ='SCI-2022'!H33/('SFP-2022'!G27+'SFP-2022'!H27/2) -> 0.012149707 | L55: ='SCI-2022'!I33/('SFP-2022'!H27+'SFP-2022'!I27/2) -> 0.012754219 | M55: ='SCI-2022'!J33/('SFP-2022'!I27+'SFP-2022'!J27/2) -> 0.013294606 | N55: ='SCI-2022'!K33/('SFP-2022'!J27+'SFP-2022'!K27/2) -> 0.014123459 | ... AK55: ='SCI-2022'!AH33/('SFP-2022'!AG27+'SFP-2022'!AH27/2) -> 0.014986211
B56: 8.2 | C56: Cost Income Ratio | E56: ='SCI-2022'!B23/'SCI-2022'!B19 -> 0.70313143 | F56: ='SCI-2022'!C23/'SCI-2022'!C19 -> 0.79133968 | G56: ='SCI-2022'!D23/'SCI-2022'!D19 -> 0.73809658 | H56: ='SCI-2022'!E23/'SCI-2022'!E19 -> 0.76385029 | I56: ='SCI-2022'!F23/'SCI-2022'!F19 -> 0.56201554 | J56: ='SCI-2022'!G23/'SCI-2022'!G19 -> 0.59990835 | K56: ='SCI-2022'!H23/'SCI-2022'!H19 -> 0.60566817 | L56: ='SCI-2022'!I23/'SCI-2022'!I19 -> 0.61095265 | ... AK56: ='SCI-2022'!AH23/'SCI-2022'!AH19 -> 0.59457625
B57: 8.3 | C57: Operating Expense Ratio | E57: ='SCI-2022'!B23/'SFP-2022'!B27 -> 0.067155029 | F57: ='SCI-2022'!C23/'SFP-2022'!C27 -> 0.005507729 | G57: ='SCI-2022'!D23/'SFP-2022'!D27 -> 0.010870896 | H57: ='SCI-2022'!E23/'SFP-2022'!E27 -> 0.016796479 | I57: ='SCI-2022'!F23/'SFP-2022'!F27 -> 0.02257956 | J57: ='SCI-2022'!G23/'SFP-2022'!G27 -> 0.027443319 | K57: ='SCI-2022'!H23/'SFP-2022'!H27 -> 0.031808396 | L57: ='SCI-2022'!I23/'SFP-2022'!I27 -> 0.035697671 | ... AK57: ='SCI-2022'!AH23/'SFP-2022'!AH27 -> 0.035594681
C58: Liquid assets/total assets | E58: =(Financials!C36+Financials!C29)/Financials!C5 -> 0.2510966 | F58: =(Financials!D36+Financials!D29)/Financials!D5 -> 0.24831455 | G58: =(Financials!E36+Financials!E29)/Financials!E5 -> 0.249102 | H58: =(Financials!F36+Financials!F29)/Financials!F5 -> 0.24612317 | I58: =(Financials!G36+Financials!G29)/Financials!G5 -> 0.25524393 | J58: =(Financials!H36+Financials!H29)/Financials!H5 -> 0.24778097 | K58: =(Financials!I36+Financials!I29)/Financials!I5 -> 0.2473072 | L58: =(Financials!J36+Financials!J29)/Financials!J5 -> 0.25898388 | ... AK58: =(Financials!AI36+Financials!AI29)/Financials!AI5 -> 0.21991168
B76: 0

Sheet CAELS
B1: KWETU SACCO
B2: FINANCIAL SOUNDNESS INDICATORS | C2: Prude. Std | E2: 44197 | F2: 44228 | G2: 44256 | H2: 44287 | I2: 44317 | J2: 44348 | K2: 44378 | L2: 44409 | M2: 44440 | N2: 44470 | O2: 44501 | P2: 44531 | Q2: Audited 2021 | R2: 44562 | S2: 44593 | T2: 44621 | U2: 44652 | V2: 44682 | W2: 44713 | X2: 44743 | Y2: 44774 | Z2: 44805 | AA2: 44835 | AB2: 44866 | AC2: 44896 | AD2: Audited-2022 | AE2: 44949 | AF2: 44980 | AG2: 45008 | AH2: 45039 | AI2: 45069 | AJ2: 45100
B3: CAPITAL
B4: CORE CAPITAL | C4: ≥ Ksh.10M | E4: ='Prudential Ratios'!F6 -> 637.74636 | F4: ='Prudential Ratios'!G6 -> 670.01584 | G4: ='Prudential Ratios'!H6 -> 689.21991 | H4: ='Prudential Ratios'!I6 -> 727.8007 | I4: ='Prudential Ratios'!J6 -> 707.23569 | J4: ='Prudential Ratios'!K6 -> 716.34862 | K4: ='Prudential Ratios'!L6 -> 724.18982 | L4: ='Prudential Ratios'!M6 -> 740.33402 | ... AJ4: ='Prudential Ratios'!AK6 -> 1198.318
B5: CCA | C5: ≥ 10% | E5: ='Prudential Ratios'!F7 -> 0.14528077 | F5: ='Prudential Ratios'!G7 -> 0.15149908 | G5: ='Prudential Ratios'!H7 -> 0.15561639 | H5: ='Prudential Ratios'!I7 -> 0.16282358 | I5: ='Prudential Ratios'!J7 -> 0.15929066 | J5: ='Prudential Ratios'!K7 -> 0.16085586 | K5: ='Prudential Ratios'!L7 -> 0.1580466 | L5: ='Prudential Ratios'!M7 -> 0.16067273 | ... AJ5: ='Prudential Ratios'!AK7 -> 0.2328877
B6: ICA | C6: ≥ 8% | E6: ='Prudential Ratios'!F10 -> 0.080744884 | F6: ='Prudential Ratios'!G10 -> 0.087194377 | G6: ='Prudential Ratios'!H10 -> 0.09113869 | H6: ='Prudential Ratios'!I10 -> 0.098674062 | I6: ='Prudential Ratios'!J10 -> 0.094482328 | J6: ='Prudential Ratios'!K10 -> 0.095915038 | K6: ='Prudential Ratios'!L10 -> 0.094644481 | L6: ='Prudential Ratios'!M10 -> 0.097171832 | ... AJ6: ='Prudential Ratios'!AK10 -> 0.15340844
B7: CCD | C7: ≥ 8% | E7: ='Prudential Ratios'!F8 -> 0.26444542 | F7: ='Prudential Ratios'!G8 -> 0.27423695 | G7: ='Prudential Ratios'!H8 -> 0.28252581 | H7: ='Prudential Ratios'!I8 -> 0.29340121 | I7: ='Prudential Ratios'!J8 -> 0.28654143 | J7: ='Prudential Ratios'!K8 -> 0.28894288 | K7: ='Prudential Ratios'!L8 -> 0.27781485 | L7: ='Prudential Ratios'!M8 -> 0.2823849 | ... AJ7: ='Prudential Ratios'!AK8 -> 0.44084484
B8: Asset Quality
B9: NPL | C9: ≤ 6%
B10: Earnings
B11: ROA | E11: ='Prudential Ratios'!F55 -> #VALUE! | F11: ='Prudential Ratios'!G55 -> 0.0017874322 | G11: ='Prudential Ratios'!H55 -> 0.0037483423 | H11: ='Prudential Ratios'!I55 -> 0.011588337 | I11: ='Prudential Ratios'!J55 -> 0.011548673 | J11: ='Prudential Ratios'!K55 -> 0.012149707 | K11: ='Prudential Ratios'!L55 -> 0.012754219 | L11: ='Prudential Ratios'!M55 -> 0.013294606 | ... AJ11: ='Prudential Ratios'!AK55 -> 0.014986211
B12: CIR | E12: ='Prudential Ratios'!F56 -> 0.79133968 | F12: ='Prudential Ratios'!G56 -> 0.73809658 | G12: ='Prudential Ratios'!H56 -> 0.76385029 | H12: ='Prudential Ratios'!I56 -> 0.56201554 | I12: ='Prudential Ratios'!J56 -> 0.59990835 | J12: ='Prudential Ratios'!K56 -> 0.60566817 | K12: ='Prudential Ratios'!L56 -> 0.61095265 | L12: ='Prudential Ratios'!M56 -> 0.62006393 | ... AJ12: ='Prudential Ratios'!AK56 -> 0.59457625
B13: OER | E13: ='Prudential Ratios'!F57 -> 0.005507729 | F13: ='Prudential Ratios'!G57 -> 0.010870896 | G13: ='Prudential Ratios'!H57 -> 0.016796479 | H13: ='Prudential Ratios'!I57 -> 0.02257956 | I13: ='Prudential Ratios'!J57 -> 0.027443319 | J13: ='Prudential Ratios'!K57 -> 0.031808396 | K13: ='Prudential Ratios'!L57 -> 0.035697671 | L13: ='Prudential Ratios'!M57 -> 0.040267143 | ... AJ13: ='Prudential Ratios'!AK57 -> 0.035594681
B14: LIQUIDITY
B15: MIN LIQ | C15: 0.15 | E15: ='SFP-2022'!O4/('SFP-2022'!O30+'SFP-2022'!O29+'SFP-2022'!O37) -> 0.10102816 | F15: ='SFP-2022'!P4/('SFP-2022'!P30+'SFP-2022'!P29+'SFP-2022'!P37) -> 0.10838936 | G15: ='SFP-2022'!Q4/('SFP-2022'!Q30+'SFP-2022'!Q29+'SFP-2022'!Q37) -> 0.11472779 | H15: ='SFP-2022'!R4/('SFP-2022'!R30+'SFP-2022'!R29+'SFP-2022'!R37) -> 0.093479761 | I15: ='SFP-2022'!S4/('SFP-2022'!S30+'SFP-2022'!S29+'SFP-2022'!S37) -> 0.092817819 | J15: ='SFP-2022'!T4/('SFP-2022'!T30+'SFP-2022'!T29+'SFP-2022'!T37) -> 0.084539188 | K15: ='SFP-2022'!U4/('SFP-2022'!U30+'SFP-2022'!U29+'SFP-2022'!U37) -> 0.12296439 | L15: ='SFP-2022'!V4/('SFP-2022'!V30+'SFP-2022'!V29+'SFP-2022'!V37) -> 0.13015376 | ... P15: ='SFP-2022'!Z4/('SFP-2022'!Z30+'SFP-2022'!Z29+'SFP-2022'!Z37) -> 0.082986787 | Q15: ='SFP-2022'!O4/('SFP-2022'!O29+'SFP-2022'!O30+'SFP-2022'!O37) -> 0.10102816 | R15: ='SFP-2022'!P4/('SFP-2022'!P29+'SFP-2022'!P30+'SFP-2022'!P37) -> 0.10838936 | S15: ='SFP-2022'!Q4/('SFP-2022'!Q29+'SFP-2022'!Q30+'SFP-2022'!Q37) -> 0.11472779 | T15: ='SFP-2022'!R4/('SFP-2022'!R29+'SFP-2022'!R30+'SFP-2022'!R37) -> 0.093479761 | U15: ='SFP-2022'!S4/('SFP-2022'!S29+'SFP-2022'!S30+'SFP-2022'!S37) -> 0.092817819 | V15: ='SFP-2022'!T4/('SFP-2022'!T29+'SFP-2022'!T30+'SFP-2022'!T37) -> 0.084539188 | W15: ='SFP-2022'!U4/('SFP-2022'!U29+'SFP-2022'!U30+'SFP-2022'!U37) -> 0.12296439 | X15: ='SFP-2022'!V4/('SFP-2022'!V29+'SFP-2022'!V30+'SFP-2022'!V37) -> 0.13015376 | ... AJ15: ='SFP-2022'!AH4/('SFP-2022'!AH29+'SFP-2022'!AH30+'SFP-2022'!AH37) -> 0.14766321
B16: TEC LIQ | E16: ='Prudential Ratios'!F48 -> 0.43079737 | F16: ='Prudential Ratios'!G48 -> 0.43344427 | G16: ='Prudential Ratios'!H48 -> 0.42921403 | H16: ='Prudential Ratios'!I48 -> 0.44691535 | I16: ='Prudential Ratios'!J48 -> 0.43069803 | J16: ='Prudential Ratios'!K48 -> 0.428631 | K16: ='Prudential Ratios'!L48 -> 0.43931959 | L16: ='Prudential Ratios'!M48 -> 0.42665873 | ... AJ16: ='Prudential Ratios'!AK48 -> 0.39947235
B17: EB | C17: ≤ 25% | E17: ='Prudential Ratios'!F27 -> 0.10365053 | F17: ='Prudential Ratios'!G27 -> 0.10043172 | G17: ='Prudential Ratios'!H27 -> 0.097840713 | H17: ='Prudential Ratios'!I27 -> 0.094521704 | I17: ='Prudential Ratios'!J27 -> 0.092719661 | J17: ='Prudential Ratios'!K27 -> 0.090007001 | K17: ='Prudential Ratios'!L27 -> 0.085113282 | L17: ='Prudential Ratios'!M27 -> 0.082289537 | ... AJ17: ='Prudential Ratios'!AK27 -> 0.082110965
B18: LIQ/TA | E18: ='Prudential Ratios'!F58 -> 0.24831455 | F18: ='Prudential Ratios'!G58 -> 0.249102 | G18: ='Prudential Ratios'!H58 -> 0.24612317 | H18: ='Prudential Ratios'!I58 -> 0.25524393 | I18: ='Prudential Ratios'!J58 -> 0.24778097 | J18: ='Prudential Ratios'!K58 -> 0.2473072 | K18: ='Prudential Ratios'!L58 -> 0.25898388 | L18: ='Prudential Ratios'!M58 -> 0.2520009 | ... AJ18: ='Prudential Ratios'!AK58 -> 0.21991168
B19: STRUCTURE
B20: NEA | C20: ≤ 10% | E20: ='Prudential Ratios'!F14 -> 0.27381193 | F20: ='Prudential Ratios'!G14 -> 0.27168583 | G20: ='Prudential Ratios'!H14 -> 0.27195813 | H20: ='Prudential Ratios'!I14 -> 0.26486552 | I20: ='Prudential Ratios'!J14 -> 0.27000834 | J20: ='Prudential Ratios'!K14 -> 0.26543324 | K20: ='Prudential Ratios'!L14 -> 0.25780748 | L20: ='Prudential Ratios'!M14 -> 0.27191884 | ... AJ20: ='Prudential Ratios'!AK14 -> 0.22392615
B21: LB | C21: ≤ 5% | E21: ='Prudential Ratios'!F15 -> 0.03132349 | F21: ='Prudential Ratios'!G15 -> 0.031069599 | G21: ='Prudential Ratios'!H15 -> 0.030932915 | H21: ='Prudential Ratios'!I15 -> 0.031384934 | I21: ='Prudential Ratios'!J15 -> 0.031646156 | J21: ='Prudential Ratios'!K15 -> 0.03159001 | K21: ='Prudential Ratios'!L15 -> 0.03072233 | L21: ='Prudential Ratios'!M15 -> 0.030832037 | ... AJ21: ='Prudential Ratios'!AK15 -> 0.031187136
B22: FITD | C22: ≤ 5% | E22: ='Prudential Ratios'!F19 -> 0.34926009 | F22: ='Prudential Ratios'!G19 -> 0.3448504 | G22: ='Prudential Ratios'!H19 -> 0.34543073 | H22: ='Prudential Ratios'!I19 -> 0.33976311 | I22: ='Prudential Ratios'!J19 -> 0.34148828 | J22: ='Prudential Ratios'!K19 -> 0.34002568 | K22: ='Prudential Ratios'!L19 -> 0.32339045 | L22: ='Prudential Ratios'!M19 -> 0.32157778 | ... AJ22: ='Prudential Ratios'!AK19 -> 0.28311329
B23: FICC | C23: ≤ 40% | E23: ='Prudential Ratios'!F20 -> 1.3207265 | F23: ='Prudential Ratios'!G20 -> 1.2574906 | G23: ='Prudential Ratios'!H20 -> 1.2226519 | H23: ='Prudential Ratios'!I20 -> 1.1580154 | I23: ='Prudential Ratios'!J20 -> 1.1917588 | J23: ='Prudential Ratios'!K20 -> 1.176792 | K23: ='Prudential Ratios'!L20 -> 1.1640503 | L23: ='Prudential Ratios'!M20 -> 1.1387924 | ... AJ23: ='Prudential Ratios'!AK20 -> 0.64220619

Sheet Financials
B1: KWETU SACCO SOCIETY
B3: Year | C3: Audited 2020 | D3: 44197 | E3: 44228 | F3: 44256 | G3: 44287 | H3: 44317 | I3: 44348 | J3: 44378 | K3: 44409 | L3: 44440 | M3: 44470 | N3: 44501 | O3: 44531 | P3: Audited 2021 | Q3: 44562 | R3: 44593 | S3: 44621 | T3: 44652 | U3: 44682 | V3: 44713 | W3: 44743 | X3: 44774 | Y3: 44805 | Z3: 44835 | AA3: 44866 | AB3: 44896 | AC3: Audited-2022 | AD3: 44949 | AE3: 44980 | AF3: 45008 | AG3: 45039 | AH3: 45069 | AI3: 45100 | AJ3: 45130 | AK3: 45161
A4: 1 | B4: Membership
A5: 2 | B5: Total Assets | C5: ='SFP-2022'!B27 -> 4379269975 | D5: ='SFP-2022'!C27 -> 4.3897506e+09 | E5: ='SFP-2022'!D27 -> 4.4225736e+09 | F5: ='SFP-2022'!E27 -> 4.4289675e+09 | G5: ='SFP-2022'!F27 -> 4.4698728e+09 | H5: ='SFP-2022'!G27 -> 4.4399069e+09 | I5: ='SFP-2022'!H27 -> 4.4533573e+09 | J5: ='SFP-2022'!I27 -> 4.5821285e+09 | ... AI5: ='SFP-2022'!AH27 -> 5.145476e+09
A6: 3 | B6: Total Deposits | C6: ='SFP-2022'!B31 -> 2401022868 | D6: ='SFP-2022'!C31 -> 2.411637e+09 | E6: ='SFP-2022'!D31 -> 2.4432004e+09 | F6: ='SFP-2022'!E31 -> 2.4394936e+09 | G6: ='SFP-2022'!F31 -> 2.4805648e+09 | H6: ='SFP-2022'!G31 -> 2.4681796e+09 | I6: ='SFP-2022'!H31 -> 2.479205e+09 | J6: ='SFP-2022'!I31 -> 2.6067355e+09 | ... AI6: ='SFP-2022'!AH31 -> 2.7182308e+09
A7: 3.1 | B7: Deposits-Members(BOSA) | C7: ='SFP-2022'!B31 -> 2401022868 | D7: ='SFP-2022'!C31 -> 2.411637e+09 | E7: ='SFP-2022'!D31 -> 2.4432004e+09 | F7: ='SFP-2022'!E31 -> 2.4394936e+09 | G7: ='SFP-2022'!F31 -> 2.4805648e+09 | H7: ='SFP-2022'!G31 -> 2.4681796e+09 | I7: ='SFP-2022'!H31 -> 2.479205e+09 | J7: ='SFP-2022'!I31 -> 2.6067355e+09 | ... AI7: ='SFP-2022'!AH31 -> 2.7182308e+09
A8: 3.2 | B8: Deposits-Customers(FOSA) | C8: ='SFP-2022'!B28 -> 550189731 | D8: ='SFP-2022'!C28 -> 3.2621451e+08 | E8: ='SFP-2022'!D28 -> 3.4135787e+08 | F8: ='SFP-2022'!E28 -> 3.2457352e+08 | G8: ='SFP-2022'!F28 -> 3.5771606e+08 | H8: ='SFP-2022'!G28 -> 3.3057735e+08 | I8: ='SFP-2022'!H28 -> 3.2028038e+08 | J8: ='SFP-2022'!I28 -> 4.2018772e+08 | ... AI8: ='SFP-2022'!AH28 -> 3.8057014e+08
A9: 4 | B9: External Borrowing | C9: ='SFP-2022'!B38 -> 465833333 | D9: ='SFP-2022'!C38 -> 4.55e+08 | E9: ='SFP-2022'!D38 -> 4.4416667e+08 | F9: ='SFP-2022'!E38 -> 4.3333333e+08 | G9: ='SFP-2022'!F38 -> 4.225e+08 | H9: ='SFP-2022'!G38 -> 4.1166667e+08 | I9: ='SFP-2022'!H38 -> 4.0083333e+08 | J9: ='SFP-2022'!I38 -> 3.9e+08 | ... AI9: ='SFP-2022'!AH38 -> 4.225e+08
A10: 4.1 | B10: Short term Liabilities | C10: ='SFP-2022'!B33+'SFP-2022'!B34+'SFP-2022'!B35+'SFP-2022'!B36+'SFP-2022'!B37 -> 93989880 | D10: ='SFP-2022'!C33+'SFP-2022'!C34+'SFP-2022'!C35+'SFP-2022'!C36+'SFP-2022'!C37 -> 1.186453e+08 | E10: ='SFP-2022'!D33+'SFP-2022'!D34+'SFP-2022'!D35+'SFP-2022'!D36+'SFP-2022'!D37 -> 98468666 | F10: ='SFP-2022'!E33+'SFP-2022'!E34+'SFP-2022'!E35+'SFP-2022'!E36+'SFP-2022'!E37 -> 1.0019861e+08 | G10: ='SFP-2022'!F33+'SFP-2022'!F34+'SFP-2022'!F35+'SFP-2022'!F36+'SFP-2022'!F37 -> 72285368 | H10: ='SFP-2022'!G33+'SFP-2022'!G34+'SFP-2022'!G35+'SFP-2022'!G36+'SFP-2022'!G37 -> 86103015 | I10: ='SFP-2022'!H33+'SFP-2022'!H34+'SFP-2022'!H35+'SFP-2022'!H36+'SFP-2022'!H37 -> 90248352 | J10: ='SFP-2022'!I33+'SFP-2022'!I34+'SFP-2022'!I35+'SFP-2022'!I36+'SFP-2022'!I37 -> 94481239 | ... AI10: ='SFP-2022'!AH33+'SFP-2022'!AH34+'SFP-2022'!AH35+'SFP-2022'!AH36+'SFP-2022'!AH37 -> 1.143814e+08
A13: 5 | B13: Share capital and Reserves
A14: 5.1 | B14: Core Capital | C14: =C17 -> 629590233 | D14: =D17 -> 6.3774636e+08 | E14: =E17 -> 6.7001584e+08 | F14: =F17 -> 6.8921991e+08 | G14: =G17 -> 7.278007e+08 | H14: =H17 -> 7.0723569e+08 | I14: =I17 -> 7.1634862e+08 | J14: =J17 -> 7.2418982e+08 | ... AI14: =AI17 -> 1.198318e+09
A15: 5.2 | B15: Institutional Capital | C15: =C14-C18 -> 347226115 | D15: =D14-D18 -> 3.544499e+08 | E15: =E14-E18 -> 3.8562355e+08 | F15: =F14-F18 -> 4.0365029e+08 | G15: =G14-G18 -> 4.4106051e+08 | H15: =H14-H18 -> 4.1949274e+08 | I15: =I14-I18 -> 4.2714393e+08 | J15: =J14-J18 -> 4.3367318e+08 | ... AI15: =AI14-AI18 -> 7.8935945e+08
A17: 5.3 | B17: Total Capital | C17: =SUM(C18:C21) -> 629590233 | D17: =SUM(D18:D21) -> 6.3774636e+08 | E17: =SUM(E18:E21) -> 6.7001584e+08 | F17: =SUM(F18:F21) -> 6.8921991e+08 | G17: =SUM(G18:G21) -> 7.278007e+08 | H17: =SUM(H18:H21) -> 7.0723569e+08 | I17: =SUM(I18:I21) -> 7.1634862e+08 | J17: =SUM(J18:J21) -> 7.2418982e+08 | ... AI17: =SUM(AI18:AI21) -> 1.198318e+09
A18: 5.3.1 | B18: Members Share Capital | C18: ='SFP-2022'!B41 -> 282364118 | D18: ='SFP-2022'!C41 -> 2.8329645e+08 | E18: ='SFP-2022'!D41 -> 2.8439228e+08 | F18: ='SFP-2022'!E41 -> 2.8556961e+08 | G18: ='SFP-2022'!F41 -> 2.8674019e+08 | H18: ='SFP-2022'!G41 -> 2.8774295e+08 | I18: ='SFP-2022'!H41 -> 2.8920469e+08 | J18: ='SFP-2022'!I41 -> 2.9051664e+08 | ... AI18: ='SFP-2022'!AH41 -> 4.089586e+08
A19: 5.3.3 | B19: Retained Earnings | C19: ='SFP-2022'!B44 -> 198992818 | D19: ='SFP-2022'!C44 -> 2.0388238e+08 | E19: ='SFP-2022'!D44 -> 2.1379173e+08 | F19: ='SFP-2022'!E44 -> 2.2687078e+08 | G19: ='SFP-2022'!F44 -> 2.7921638e+08 | H19: ='SFP-2022'!G44 -> 2.7925144e+08 | I19: ='SFP-2022'!H44 -> 2.8298988e+08 | J19: ='SFP-2022'!I44 -> 2.8801265e+08 | ... AI19: ='SFP-2022'!AH44 -> 5.4506888e+08
A20: 5.3.5 | B20: Statutory Reserves | C20: ='SFP-2022'!B49 -> 101541864 | D20: ='SFP-2022'!C49 -> 1.0154186e+08 | E20: ='SFP-2022'!D49 -> 1.0154186e+08 | F20: ='SFP-2022'!E49 -> 1.0154186e+08 | G20: ='SFP-2022'!F49 -> 1.0154186e+08 | H20: ='SFP-2022'!G49 -> 1.0154186e+08 | I20: ='SFP-2022'!H49 -> 1.0154186e+08 | J20: ='SFP-2022'!I49 -> 1.0154186e+08 | ... AI20: ='SFP-2022'!AH49 -> 1.5253254e+08
A21: 5.3.6 | B21: Capital Reserve | C21: ='SFP-2022'!B50 -> 46691433 | D21: ='SFP-2022'!C50 -> 49025656 | E21: ='SFP-2022'!D50 -> 70289962 | F21: ='SFP-2022'!E50 -> 75237648 | G21: ='SFP-2022'!F50 -> 60302261 | H21: ='SFP-2022'!G50 -> 38699442 | I21: ='SFP-2022'!H50 -> 42612189 | J21: ='SFP-2022'!I50 -> 44118666 | ... AI21: ='SFP-2022'!AH50 -> 91758030
A22: 5.3.7 | B22: Supplementary Capital & reserves
A23: a | B23: Proposed Dividends | C23: ='SFP-2022'!B52 -> 22111655 | D23: ='SFP-2022'!C52 -> 7.0281558e+08 | E23: ='SFP-2022'!D52 -> 7.0281558e+08 | F23: ='SFP-2022'!E52 -> 7.0281558e+08 | G23: ='SFP-2022'!F52 -> 7.0281558e+08 | H23: ='SFP-2022'!G52 -> 7.0281558e+08 | I23: ='SFP-2022'!H52 -> 7.0281558e+08 | J23: ='SFP-2022'!I52 -> 7.0281558e+08 | ... AI23: ='SFP-2022'!AH52 -> 6.2813928e+08
A24: b
A26: 6 | B26: Investments | C26: =C27+C28+C29 -> 848324872 | D26: =D27+D28+D29 -> 8.4228853e+08 | E26: =E27+E28+E29 -> 8.4253864e+08 | F26: =F27+F28+F29 -> 8.4267606e+08 | G26: =G27+G28+G29 -> 8.428044e+08 | H26: =H27+H28+H29 -> 8.428544e+08 | I26: =I27+I28+I29 -> 8.4299336e+08 | J26: =J27+J28+J29 -> 8.4299336e+08 | ... AI26: =AI27+AI28+AI29 -> 7.6956727e+08
A27: 6.1 | B27: Investments in Coop bank, CIC, Kuscco, Kerussu & Codic | C27: ='SFP-2022'!B12 -> 0 | D27: ='SFP-2022'!C12 -> 0 | E27: ='SFP-2022'!D12 -> 0 | F27: ='SFP-2022'!E12 -> 0 | G27: ='SFP-2022'!F12 -> 0 | H27: ='SFP-2022'!G12 -> 0 | I27: ='SFP-2022'!H12 -> 0 | J27: ='SFP-2022'!I12 -> 0 | ... AI27: ='SFP-2022'!AH12 -> 0
A28: 6.2 | B28: Equity Investments (at cost) | C28: ='SFP-2022'!B13 -> 0 | D28: ='SFP-2022'!C13 -> 0 | E28: ='SFP-2022'!D13 -> 0 | F28: ='SFP-2022'!E13 -> 0 | G28: ='SFP-2022'!F13 -> 0 | H28: ='SFP-2022'!G13 -> 0 | I28: ='SFP-2022'!H13 -> 0 | J28: ='SFP-2022'!I13 -> 0 | ... AI28: ='SFP-2022'!AH13 -> 0
A29: 6.3 | B29: Deposits in KUSCCO CFP | C29: ='SFP-2022'!B11 -> 848324872 | D29: ='SFP-2022'!C11 -> 8.4228853e+08 | E29: ='SFP-2022'!D11 -> 8.4253864e+08 | F29: ='SFP-2022'!E11 -> 8.4267606e+08 | G29: ='SFP-2022'!F11 -> 8.428044e+08 | H29: ='SFP-2022'!G11 -> 8.428544e+08 | I29: ='SFP-2022'!H11 -> 8.4299336e+08 | J29: ='SFP-2022'!I11 -> 8.4299336e+08 | ... AI29: ='SFP-2022'!AH11 -> 7.6956727e+08
A31: 7 | B31: Net Loans & advances | C31: =C32-C33 -> 2087101217 | D31: =D32-D33 -> 2.0977456e+09 | E31: =E32-E33 -> 2.1193511e+09 | F31: =F32-F33 -> 2.1344022e+09 | G31: =G32-G33 -> 2.1450497e+09 | H31: =H32-H33 -> 2.1409706e+09 | I31: =I32-I33 -> 2.1699409e+09 | J31: =J32-J33 -> 2.2141241e+09 | ... AI31: =AI32-AI33 -> 2.8617191e+09
A32: 7.1 | B32: Gross Loans & advances | C32: ='SFP-2022'!B15 -> 2153084789 | D32: ='SFP-2022'!C15 -> 2.1652147e+09 | E32: ='SFP-2022'!D15 -> 2.1905953e+09 | F32: ='SFP-2022'!E15 -> 2.1985063e+09 | G32: ='SFP-2022'!F15 -> 2.2124638e+09 | H32: ='SFP-2022'!G15 -> 2.2109571e+09 | I32: ='SFP-2022'!H15 -> 2.247154e+09 | J32: ='SFP-2022'!I15 -> 2.2982481e+09 | ... AI32: ='SFP-2022'!AH15 -> 2.9519508e+09
A33: 7.3 | B33: Allowance for loan losses | C33: ='SFP-2022'!B16 -> 65983572 | D33: ='SFP-2022'!C16 -> 67469142 | E33: ='SFP-2022'!D16 -> 71244246 | F33: ='SFP-2022'!E16 -> 64104130 | G33: ='SFP-2022'!F16 -> 67414041 | H33: ='SFP-2022'!G16 -> 69986500 | I33: ='SFP-2022'!H16 -> 77213148 | J33: ='SFP-2022'!I16 -> 84124003 | ... AI33: ='SFP-2022'!AH16 -> 90231735
A34: 7.4 | B34: Non Performing Loans | C34: =(#REF!+#REF!+#REF!) -> #REF! | D34: =(#REF!+#REF!+#REF!) -> #REF! | E34: =(#REF!+#REF!+#REF!) -> #REF! | F34: =(#REF!+#REF!+#REF!) -> #REF! | G34: =(#REF!+#REF!+#REF!) -> #REF! | H34: =(#REF!+#REF!+#REF!) -> #REF! | I34: =(#REF!+#REF!+#REF!) -> #REF! | J34: =(#REF!+#REF!+#REF!) -> #REF! | ... AC34: =(#REF!+#REF!+#REF!) -> #REF!
A35: 7.5 | B35: Required loan loss provision | C35: =#REF! -> #REF! | D35: =#REF! -> #REF! | E35: =#REF! -> #REF! | F35: =#REF! -> #REF! | G35: =#REF! -> #REF! | H35: =#REF! -> #REF! | I35: =#REF! -> #REF! | J35: =#REF! -> #REF! | ... AC35: =#REF! -> #REF!
A36: 7.6 | B36: Cash and Cash equipments | C36: ='SFP-2022'!B4 -> 251294928 | D36: ='SFP-2022'!C4 -> 2.477504e+08 | E36: ='SFP-2022'!D4 -> 2.5913327e+08 | F36: ='SFP-2022'!E4 -> 2.4739548e+08 | G36: ='SFP-2022'!F4 -> 2.9810352e+08 | H36: ='SFP-2022'!G4 -> 2.5727008e+08 | I36: ='SFP-2022'!H4 -> 2.5835399e+08 | J36: ='SFP-2022'!I4 -> 3.4370407e+08 | ... AI36: ='SFP-2022'!AH4 -> 3.6198302e+08
A38: 8 | B38: Non-Earning Assets | C38: ='SFP-2022'!B7+'SFP-2022'!B17+'SFP-2022'!B23+'SFP-2022'!B24+'SFP-2022'!B25+'SFP-2022'!B26 -> 1192548958 | D38: ='SFP-2022'!C7+'SFP-2022'!C17+'SFP-2022'!C23+'SFP-2022'!C24+'SFP-2022'!C25+'SFP-2022'!C26 -> 1.2019661e+09 | E38: ='SFP-2022'!D7+'SFP-2022'!D17+'SFP-2022'!D23+'SFP-2022'!D24+'SFP-2022'!D25+'SFP-2022'!D26 -> 1.2015506e+09 | F38: ='SFP-2022'!E7+'SFP-2022'!E17+'SFP-2022'!E23+'SFP-2022'!E24+'SFP-2022'!E25+'SFP-2022'!E26 -> 1.2044937e+09 | G38: ='SFP-2022'!F7+'SFP-2022'!F17+'SFP-2022'!F23+'SFP-2022'!F24+'SFP-2022'!F25+'SFP-2022'!F26 -> 1.1839152e+09 | H38: ='SFP-2022'!G7+'SFP-2022'!G17+'SFP-2022'!G23+'SFP-2022'!G24+'SFP-2022'!G25+'SFP-2022'!G26 -> 1.1988119e+09 | I38: ='SFP-2022'!H7+'SFP-2022'!H17+'SFP-2022'!H23+'SFP-2022'!H24+'SFP-2022'!H25+'SFP-2022'!H26 -> 1.182069e+09 | J38: ='SFP-2022'!I7+'SFP-2022'!I17+'SFP-2022'!I23+'SFP-2022'!I24+'SFP-2022'!I25+'SFP-2022'!I26 -> 1.181307e+09 | ... AI38: ='SFP-2022'!AH7+'SFP-2022'!AH17+'SFP-2022'!AH23+'SFP-2022'!AH24+'SFP-2022'!AH25+'SFP-2022'!AH26 -> 1.1522066e+09
A39: 8.1 | B39: Property and Equipment | C39: ='SFP-2022'!B23 -> 138210245 | D39: ='SFP-2022'!C23 -> 1.3750231e+08 | E39: ='SFP-2022'!D23 -> 1.3740759e+08 | F39: ='SFP-2022'!E23 -> 1.3700087e+08 | G39: ='SFP-2022'!F23 -> 140286665 | H39: ='SFP-2022'!G23 -> 1.4050599e+08 | I39: ='SFP-2022'!H23 -> 1.406816e+08 | J39: ='SFP-2022'!I23 -> 1.4077366e+08 | ... AI39: ='SFP-2022'!AH23 -> 1.6047266e+08
A41: 9 | B41: Turnover | C41: =C42+C43+C44 -> 914955301 | D41: =D42+D43+D44 -> 2.1447394e+08 | E41: =E42+E43+E44 -> 2.3573825e+08 | F41: =F42+F43+F44 -> 2.4068594e+08 | G41: =G42+G43+G44 -> 2.2575055e+08 | H41: =H42+H43+H44 -> 2.0414773e+08 | I41: =I42+I43+I44 -> 2.0806048e+08 | J41: =J42+J43+J44 -> 2.0956695e+08 | ... AI41: =AI42+AI43+AI44 -> 3.0819699e+08
A42: 9.1 | B42: Loan Interest | C42: ='SFP-2022'!B49 -> 101541864 | D42: ='SFP-2022'!C49 -> 1.0154186e+08 | E42: ='SFP-2022'!D49 -> 1.0154186e+08 | F42: ='SFP-2022'!E49 -> 1.0154186e+08 | G42: ='SFP-2022'!F49 -> 1.0154186e+08 | H42: ='SFP-2022'!G49 -> 1.0154186e+08 | I42: ='SFP-2022'!H49 -> 1.0154186e+08 | J42: ='SFP-2022'!I49 -> 1.0154186e+08 | ... AI42: ='SFP-2022'!AH49 -> 1.5253254e+08
B43: Income from investments | C43: ='SFP-2022'!B50 -> 46691433 | D43: ='SFP-2022'!C50 -> 49025656 | E43: ='SFP-2022'!D50 -> 70289962 | F43: ='SFP-2022'!E50 -> 75237648 | G43: ='SFP-2022'!F50 -> 60302261 | H43: ='SFP-2022'!G50 -> 38699442 | I43: ='SFP-2022'!H50 -> 42612189 | J43: ='SFP-2022'!I50 -> 44118666 | ... AI43: ='SFP-2022'!AH50 -> 91758030
A44: 9.2 | B44: Fees & Commissions | C44: ='SFP-2022'!B51 -> 766722004 | D44: ='SFP-2022'!C51 -> 63906424 | E44: ='SFP-2022'!D51 -> 63906424 | F44: ='SFP-2022'!E51 -> 63906424 | G44: ='SFP-2022'!F51 -> 63906424 | H44: ='SFP-2022'!G51 -> 63906424 | I44: ='SFP-2022'!H51 -> 63906424 | J44: ='SFP-2022'!I51 -> 63906424 | ... AI44: ='SFP-2022'!AH51 -> 63906424
B45: Average yield on loans
A47: 10 | B47: Total Expenses (FinCosts + OpEx) | C47: =SUM(C48:C53) -> 397078190 | D47: =SUM(D48:D53) -> 21371654 | E47: =SUM(E48:E53) -> 41278304 | F47: =SUM(F48:F53) -> 65018075 | G47: =SUM(G48:G53) -> 1.4289587e+08 | H47: =SUM(H48:H53) -> 1.6996819e+08 | I47: =SUM(I48:I53) -> 1.9166807e+08 | J47: =SUM(J48:J53) -> 2.1572712e+08 | ... AI47: =SUM(AI48:AI53) -> 2.4941283e+08
A48: 10.1 | B48: Financial Exp. (Interest on deposits) | C48: ='SCI-2022'!B13 -> 221092820 | D48: ='SCI-2022'!C13 -> 4002490.3 | E48: ='SCI-2022'!D13 -> 5540876.4 | F48: ='SCI-2022'!E13 -> 8808070.7 | G48: ='SCI-2022'!F13 -> 67042836 | H48: ='SCI-2022'!G13 -> 80816326 | I48: ='SCI-2022'!H13 -> 89961915 | J48: ='SCI-2022'!I13 -> 99781340 | ... AI48: ='SCI-2022'!AH13 -> 1.1212104e+08
A49: 10.2 | B49: Financial Exp. (Dividends) | C49: ='SCI-2022'!B15 -> 0 | D49: ='SCI-2022'!C15 -> 0 | E49: ='SCI-2022'!D15 -> 0 | F49: ='SCI-2022'!E15 -> 0 | G49: ='SCI-2022'!F15 -> 0 | H49: ='SCI-2022'!G15 -> 0 | I49: ='SCI-2022'!H15 -> 0 | J49: ='SCI-2022'!I15 -> 0 | ... AI49: ='SCI-2022'!AH15 -> 0
A50: 10.3 | B50: Financial Exp. (Interest on bank loans) | C50: ='SCI-2022'!B14 -> 0 | D50: ='SCI-2022'!C14 -> 5081381.3 | E50: ='SCI-2022'!D14 -> 10044920 | F50: ='SCI-2022'!E14 -> 14429897 | G50: ='SCI-2022'!F14 -> 19164874 | H50: ='SCI-2022'!G14 -> 23629030 | I50: ='SCI-2022'!H14 -> 28148432 | J50: ='SCI-2022'!I14 -> 32415055 | ... AI50: ='SCI-2022'!AH14 -> 29490545
A51: 10.4 | B51: Other Financial Expenses | C51: ='SCI-2022'!B16+'SCI-2022'!B17+'SCI-2022'!B18 -> 0 | D51: ='SCI-2022'!C16+'SCI-2022'!C17+'SCI-2022'!C18 -> 0 | E51: ='SCI-2022'!D16+'SCI-2022'!D17+'SCI-2022'!D18 -> 0 | F51: ='SCI-2022'!E16+'SCI-2022'!E17+'SCI-2022'!E18 -> 0 | G51: ='SCI-2022'!F16+'SCI-2022'!F17+'SCI-2022'!F18 -> 0 | H51: ='SCI-2022'!G16+'SCI-2022'!G17+'SCI-2022'!G18 -> 0 | I51: ='SCI-2022'!H16+'SCI-2022'!H17+'SCI-2022'!H18 -> 0 | J51: ='SCI-2022'!I16+'SCI-2022'!I17+'SCI-2022'!I18 -> 0 | ... AI51: ='SCI-2022'!AH16+'SCI-2022'!AH17+'SCI-2022'!AH18 -> 0
A52: 10.5 | B52: Administrative Expenses | C52: ='SCI-2022'!B28 -> 128579268 | D52: ='SCI-2022'!C28 -> 9390351 | E52: ='SCI-2022'!D28 -> 19050524 | F52: ='SCI-2022'!E28 -> 31599899 | G52: ='SCI-2022'!F28 -> 41079134 | H52: ='SCI-2022'!G28 -> 46352491 | I52: ='SCI-2022'!H28 -> 51782286 | J52: ='SCI-2022'!I28 -> 58347040 | ... AI52: ='SCI-2022'!AH28 -> 85385671
A53: 10.6 | B53: Governance Expenses | C53: ='SCI-2022'!B25 -> 47406102 | D53: ='SCI-2022'!C25 -> 2897431.4 | E53: ='SCI-2022'!D25 -> 6641982.9 | F53: ='SCI-2022'!E25 -> 10180208 | G53: ='SCI-2022'!F25 -> 15609021 | H53: ='SCI-2022'!G25 -> 19170338 | I53: ='SCI-2022'!H25 -> 21775440 | J53: ='SCI-2022'!I25 -> 25183681 | ... AI53: ='SCI-2022'!AH25 -> 22415574
B54: LLP
B56: Net Surplus | C56: ='SCI-2022'!B37 -> 124167512 | D56: ='SCI-2022'!C37 -> 4889563.5 | E56: ='SCI-2022'!D37 -> 11798907 | F56: ='SCI-2022'!E37 -> 24877963 | G56: ='SCI-2022'!F37 -> 77223566 | H56: ='SCI-2022'!G37 -> 77258617 | I56: ='SCI-2022'!H37 -> 80997063 | J56: ='SCI-2022'!I37 -> 86019828 | ... AI56: ='SCI-2022'!AH37 -> 1.1526597e+08

Sheet form4
D3: RISK CLASSIFICATION OF ASSETS AND PROVISIONING | L3: RISK CLASSIFICATION OF ASSETS AND PROVISIONING
D4: SACCO SOCIETY CS NUMBER | L4: SACCO SOCIETY CS NUMBER
D5: FINANCIAL YEAR | L5: FINANCIAL YEAR
D6: START DATE: | L6: START DATE:
D7: END DATE: | L7: END DATE:
D8: PORTFOLIO AGEING REPORT | L8: PORTFOLIO AGEING REPORT
E9: A | F9: B | G9: C | H9: D | M9: A | N9: B | O9: C | P9: D
C10: NO. | D10: CLASSIFICATION | E10: NO. OF A/Cs | F10: OUTSTANDING LOAN PORTFOLIO(Kshs) | G10: REQUIRED PROVISION | H10: REQUIRED PROVISION AMOUNT(Kshs) | K10: NO. | L10: CLASSIFICATION | M10: NO. OF A/Cs | N10: OUTSTANDING LOAN PORTFOLIO(Kshs) | O10: REQUIRED PROVISION | P10: REQUIRED PROVISION AMOUNT(Kshs)
C11: 1 | D11: Performing | K11: 1 | L11: Performing
C12: 2 | D12: Watch | K12: 2 | L12: Watch
C13: 3 | D13: Substandard | K13: 3 | L13: Substandard
C14: 4 | D14: Doubtful | K14: 4 | L14: Doubtful
C15: 5 | D15: Loss | K15: 5 | L15: Loss
D16: subtotal | L16: subtotal | M16: =SUM(M11:M15) -> 0 | N16: =SUM(N11:N15) -> 0 | P16: =SUM(P11:P15) -> 0
D17: Reschedule/Renegotiated loans | L17: Reschedule/Renegotiated loans
C18: 1 | D18: Performing | K18: 1 | L18: Performing | M18: 0 | N18: 0 | O18: 0.01 | P18: =N18*O18 -> 0
C19: 2 | D19: Watch | K19: 2 | L19: Watch | M19: 0 | N19: 0 | O19: 0.05 | P19: =N19*O19 -> 0
C20: 3 | D20: Substandard | K20: 3 | L20: Substandard | M20: 0 | N20: 0 | O20: 0.25 | P20: =N20*O20 -> 0
C21: 4 | D21: Doubtful | K21: 4 | L21: Doubtful | M21: 0 | N21: 0 | O21: 0.5 | P21: =N21*O21 -> 0
C22: 5 | D22: Loss | K22: 5 | L22: Loss | M22: 0 | N22: 0 | O22: 1 | P22: =N22*O22 -> 0
D23: subtotal | E23: =SUM(E17:E22) -> 0 | F23: =SUM(F17:F22) -> 0 | H23: =SUM(H17:H22) -> 0 | L23: subtotal | M23: =SUM(M17:M22) -> 0 | N23: =SUM(N17:N22) -> 0 | P23: =SUM(P17:P22) -> 0
D24: GRAND TOTAL | E24: =E16+E23 -> 0 | F24: =F16+F23 -> 0 | H24: =H16+H23 -> 0 | L24: GRAND TOTAL | M24: =M16+M23 -> 0 | N24: =N16+N23 -> 0 | P24: =P16+P23 -> 0
F26: =F13+F14+F15 -> 0 | N26: =N13+N14+N15 -> 0
F27: =F26/F24 -> #DIV/0! | N27: =N26/N24 -> #DIV/0!
D30: RISK CLASSIFICATION OF ASSETS AND PROVISIONING
D31: SACCO SOCIETY CS NUMBER
D32: FINANCIAL YEAR
D33: START DATE:
D34: END DATE:
D35: PORTFOLIO AGEING REPORT
E36: A | F36: B | G36: C | H36: D
C37: NO. | D37: CLASSIFICATION | E37: NO. OF A/Cs | F37: OUTSTANDING LOAN PORTFOLIO(Kshs) | G37: REQUIRED PROVISION | H37: REQUIRED PROVISION AMOUNT(Kshs)
C38: 1 | D38: Performing
C39: 2 | D39: Watch
C40: 3 | D40: Substandard
C41: 4 | D41: Doubtful
C42: 5 | D42: Loss
D43: subtotal
D44: Reschedule/Renegotiated loans
C45: 1 | D45: Performing | H45: =F45*G45 -> 0
C46: 2 | D46: Watch | H46: =F46*G46 -> 0
C47: 3 | D47: Substandard | H47: =F47*G47 -> 0
C48: 4 | D48: Doubtful | H48: =F48*G48 -> 0
C49: 5 | D49: Loss | H49: =F49*G49 -> 0
D50: subtotal | E50: =SUM(E44:E49) -> 0 | F50: =SUM(F44:F49) -> 0 | H50: =SUM(H44:H49) -> 0
D51: GRAND TOTAL | E51: =E43+E50 -> 0 | F51: =F43+F50 -> 0 | H51: =H43+H50 -> 0
F53: =F40+F41+F42 -> 0
F54: =F53/F51 -> #DIV/0!
D56: RISK CLASSIFICATION OF ASSETS AND PROVISIONING
D57: SACCO SOCIETY CS NUMBER
D58: FINANCIAL YEAR
D59: START DATE:
D60: END DATE:
D61: PORTFOLIO AGEING REPORT
E62: A | F62: B | G62: C | H62: D
C63: NO. | D63: CLASSIFICATION | E63: NO. OF A/Cs | F63: OUTSTANDING LOAN PORTFOLIO(Kshs) | G63: REQUIRED PROVISION | H63: REQUIRED PROVISION AMOUNT(Kshs)
C64: 1 | D64: Performing
C65: 2 | D65: Watch
C66: 3 | D66: Substandard
C67: 4 | D67: Doubtful
C68: 5 | D68: Loss
D69: subtotal | E69: =SUM(E64:E68) -> 0 | F69: =SUM(F64:F68) -> 0 | H69: =SUM(H64:H68) -> 0
D70: Reschedule/Renegotiated loans
C71: 1 | D71: Performing | E71: 0 | F71: 0 | G71: 0.01 | H71: =F71*G71 -> 0
C72: 2 | D72: Watch | E72: 0 | F72: 0 | G72: 0.05 | H72: =F72*G72 -> 0
C73: 3 | D73: Substandard | E73: 0 | F73: 0 | G73: 0.25 | H73: =F73*G73 -> 0
C74: 4 | D74: Doubtful | E74: 0 | F74: 0 | G74: 0.5 | H74: =F74*G74 -> 0
C75: 5 | D75: Loss | E75: 0 | F75: 0 | G75: 1 | H75: =F75*G75 -> 0
D76: subtotal | E76: =SUM(E70:E75) -> 0 | F76: =SUM(F70:F75) -> 0 | H76: =SUM(H70:H75) -> 0
D77: GRAND TOTAL | E77: =E69+E76 -> 0 | F77: =F69+F76 -> 0 | H77: =H69+H76 -> 0
F79: =F66+F67+F68 -> 0
F80: =F79/F77 -> #DIV/0!

Sheet SFP-2022
A1: KWETU SACCO SOCIETY LTD
A2: STATEMENT OF FINANCIAL POSITION
B3: Audited 2020 | C3: 44197 | D3: 44228 | E3: 44256 | F3: 44287 | G3: 44317 | H3: 44348 | I3: 44378 | J3: 44409 | K3: 44440 | L3: 44470 | M3: 44501 | N3: 44531 | O3: AUDITED 2021 | P3: 44562 | Q3: 44593 | R3: 44621 | S3: 44652 | T3: 44682 | U3: 44713 | V3: 44743 | W3: 44774 | X3: 44805 | Y3: 44835 | Z3: 44866 | AA3: 44896 | AB3: Audited-22 | AC3: 44949 | AD3: 44980 | AE3: 45008 | AF3: 45039 | AG3: 45069 | AH3: 45100 | AI3: 45130 | AJ3: 45161 | AK3: 45192 | AL3: 45222
A4: Cash & Cash Equivalent | B4: =SUM(B5:B6) -> 251294928 | C4: =SUM(C5:C6) -> 2.477504e+08 | D4: =SUM(D5:D6) -> 2.5913327e+08 | E4: =SUM(E5:E6) -> 2.4739548e+08 | F4: =SUM(F5:F6) -> 2.9810352e+08 | G4: =SUM(G5:G6) -> 2.5727008e+08 | H4: =SUM(H5:H6) -> 2.5835399e+08 | I4: =SUM(I5:I6) -> 3.4370407e+08 | ... AH4: =SUM(AH5:AH6) -> 3.6198302e+08
A5: Cash in hand | B5: =14623898+23902605 -> 38526503 | C5: 32528616 | D5: 25335508 | E5: 18428547 | F5: 12460689 | G5: 45531114 | H5: 35558284 | I5: 26373154 | J5: 12476967 | K5: 47584095 | L5: 42570464 | M5: 36022000 | N5: 39816394 | O5: =5753282+21912855 -> 27666137 | P5: 32888431 | Q5: 23517965 | R5: 40496648 | S5: 46022747 | T5: 41374151 | U5: 52623479 | V5: 36421180 | W5: 31360313 | X5: 34000824 | Y5: 28637228 | Z5: 27662293 | AA5: 33257684 | AB5: =15230372+17362560 -> 32592932 | AC5: 27601432 | AD5: 17489748 | AE5: 45002038 | AF5: 25213498 | AG5: 27502421 | AH5: 22731417
A6: Cash at bank | B6: =251294928-B5 -> 212768425 | C6: 2.1522178e+08 | D6: 2.3379777e+08 | E6: 2.2896693e+08 | F6: 2.8564283e+08 | G6: 2.1173896e+08 | H6: 2.227957e+08 | I6: 3.1733092e+08 | J6: 3.055844e+08 | K6: 2.5312544e+08 | L6: 1.8040812e+08 | M6: 2.0332463e+08 | N6: 1.8439005e+08 | O6: =212893091-27666137 -> 185226954 | P6: 2.2886186e+08 | Q6: 2.5979991e+08 | R6: 1.9237364e+08 | S6: 1.8701894e+08 | T6: 1.615964e+08 | U6: 2.5128943e+08 | V6: 2.8518586e+08 | W6: 2.6265012e+08 | X6: 2.9407062e+08 | Y6: 2.3549603e+08 | Z6: 1.7760646e+08 | AA6: 1.9699832e+08 | AB6: =12903743+106983802+36217395+7373629+5937365+100586+1329838+14211017 -> 185057375 | AC6: 2.6122478e+08 | AD6: 2.4700314e+08 | AE6: 2.3337181e+08 | AF6: 2.7380339e+08 | AG6: 1.9783838e+08 | AH6: 3.392516e+08
A7: Prepayments & Sundry Receivables | B7: 65659257 | C7: 75087891 | D7: 76667654 | E7: 79744435 | F7: 57780653 | G7: 74358599 | H7: 58815661 | I7: 59806984 | J7: 1.3203329e+08 | K7: 1.3353619e+08 | L7: 1.6673873e+08 | M7: 1.4961383e+08 | N7: 1.3407878e+08 | O7: 136459664 | P7: 1.3663357e+08 | Q7: 1.4112411e+08 | R7: 1.4293937e+08 | S7: 1.4453977e+08 | T7: 1.3930261e+08 | U7: 1.4227755e+08 | V7: 70421877 | W7: 1.2093578e+08 | X7: 1.4623243e+08 | Y7: 1.496084e+08 | Z7: 1.6665143e+08 | AA7: 50340483 | AB7: =27912536+1381710+20385292+1308490+183574 -> 51171602 | AC7: 51546559 | AD7: 55408558 | AE7: 53601259 | AF7: -20444604 | AG7: 79309561 | AH7: 56744759
A8: Financial Investments | B8: =SUM(B9:B13) -> 848324872 | C8: =SUM(C9:C13) -> 8.4228853e+08 | D8: =SUM(D9:D13) -> 8.4253864e+08 | E8: =SUM(E9:E13) -> 8.4267606e+08 | F8: =SUM(F9:F13) -> 8.428044e+08 | G8: =SUM(G9:G13) -> 8.428544e+08 | H8: =SUM(H9:H13) -> 8.4299336e+08 | I8: =SUM(I9:I13) -> 8.4299336e+08 | ... AH8: =SUM(AH9:AH13) -> 7.6956727e+08
A9: Government Securities - Treasury Bills/bonds, | C9: 0 | D9: 0 | E9: 0 | F9: 0 | G9: 0 | H9: 0 | I9: 0 | J9: 0 | K9: 0 | L9: 0 | M9: 0 | N9: 0 | P9: 0 | Q9: 0 | R9: 0 | S9: 0 | T9: 0 | U9: 0 | V9: 0 | W9: 0 | X9: 0 | Y9: 0 | Z9: 0 | AA9: 0 | AB9: 0 | AC9: 0 | AD9: 0 | AE9: 0 | AF9: 0 | AG9: 0 | AH9: 0
A10: Other Securities - Commercial papers/Bonds | C10: 0 | D10: 0 | E10: 0 | F10: 0 | G10: 0 | H10: 0 | I10: 0 | J10: 0 | K10: 0 | L10: 0 | M10: 0 | N10: 0 | P10: 0 | Q10: 0 | R10: 0 | S10: 0 | T10: 0 | U10: 0 | V10: 0 | W10: 0 | X10: 0 | Y10: 0 | Z10: 0 | AA10: 0 | AB10: 0 | AC10: 0 | AD10: 0 | AE10: 0 | AF10: 0 | AG10: 0 | AH10: 0
A11: Balances in NACCOS (E.g Jungu Kuu, ESS, Savings,Money Market,Coop FD, CFP) | B11: 848324872 | C11: 8.4228853e+08 | D11: 8.4253864e+08 | E11: 8.4267606e+08 | F11: 8.428044e+08 | G11: 8.428544e+08 | H11: 8.4299336e+08 | I11: 8.4299336e+08 | J11: 8.4308674e+08 | K11: 8.4508674e+08 | L11: 8.4508674e+08 | M11: 8.4518224e+08 | N11: 9.1904483e+08 | O11: 927895776 | P11: 8.7839408e+08 | Q11: 8.7839408e+08 | R11: 8.7839408e+08 | S11: 8.7839408e+08 | T11: 8.7839408e+08 | U11: 8.7832525e+08 | V11: 8.7832525e+08 | W11: 8.7832525e+08 | X11: 7.7717525e+08 | Y11: 7.7717525e+08 | Z11: 7.7717525e+08 | AA11: 7.772083e+08 | AB11: 1586437 | AC11: 7.706709e+08 | AD11: 7.706709e+08 | AE11: 7.706709e+08 | AF11: 7.6956727e+08 | AG11: 7.6956727e+08 | AH11: 7.6956727e+08
A12: Equity Investments in NACCOs(Shares in- CIC, KUSCCO, COOP BANK,CAK, KERUSSU) | C12: 0 | D12: 0 | E12: 0 | F12: 0 | G12: 0 | H12: 0 | I12: 0 | J12: 0 | K12: 0 | L12: 0 | M12: 0 | N12: 0 | W12: 0 | X12: 0 | Y12: 0 | Z12: 0 | AA12: 0 | AB12: =3738508+706586638+17363209 -> 727688355 | AC12: 0 | AD12: 0 | AE12: 0 | AF12: 0 | AG12: 0 | AH12: 0
A13: Equity Investments in companies - shares/stocks | P13: 0 | Q13: 0 | R13: 0 | S13: 0 | T13: 0 | U13: 0 | V13: 0 | AB13: =260155+11850950+250000+40885950 -> 53247055
A14: Net Loan Portfolio | B14: =B15-B16 -> 2087101217 | C14: =C15-C16 -> 2.0977456e+09 | D14: =D15-D16 -> 2.1193511e+09 | E14: =E15-E16 -> 2.1344022e+09 | F14: =F15-F16 -> 2.1450497e+09 | G14: =G15-G16 -> 2.1409706e+09 | H14: =H15-H16 -> 2.1699409e+09 | I14: =I15-I16 -> 2.2141241e+09 | ... AH14: =AH15-AH16 -> 2.8617191e+09
A15: Gross Loan Portfolio | B15: 2153084789 | C15: 2.1652147e+09 | D15: 2.1905953e+09 | E15: 2.1985063e+09 | F15: 2.2124638e+09 | G15: 2.2109571e+09 | H15: 2.247154e+09 | I15: 2.2982481e+09 | J15: 2.2817658e+09 | K15: 2.3112402e+09 | L15: 2.3484129e+09 | M15: 2.3837482e+09 | N15: 2.3973787e+09 | O15: 2397378724 | P15: 2.3950174e+09 | Q15: 2.3993314e+09 | R15: 2.4601313e+09 | S15: 2.4820924e+09 | T15: 2.4506419e+09 | U15: 2.4455341e+09 | V15: 2.5231802e+09 | W15: 2.510259e+09 | X15: 2.5471861e+09 | Y15: 2.5795909e+09 | Z15: 2.6477768e+09 | AA15: 2.7202943e+09 | AB15: 2720294275 | AC15: 2.8201613e+09 | AD15: 2.8446898e+09 | AE15: 2.8989791e+09 | AF15: 3.0154808e+09 | AG15: 3.0389581e+09 | AH15: 2.9519508e+09
A16: Allowance for Loan Loss | B16: 65983572 | C16: 67469142 | D16: 71244246 | E16: 64104130 | F16: 67414041 | G16: 69986500 | H16: 77213148 | I16: 84124003 | J16: 88124003 | K16: 92124003 | L16: 96124003 | M16: 1.00124e+08 | N16: 69781491 | O16: 69781491 | P16: 70824673 | Q16: 72275431 | R16: 73714682 | S16: 76591118 | T16: 78701758 | U16: 78701758 | V16: 78701758 | W16: 78701758 | X16: 78701758 | Y16: 79951851 | Z16: 81201851 | AA16: 80612126 | AB16: 80612126 | AC16: 83657637 | AD16: 85419891 | AE16: 86448126 | AF16: 90231735 | AG16: 90231735 | AH16: 90231735
A17: Accounts Receivables | B17: =SUM(B18:B20) -> 0 | C17: =SUM(C18:C20) -> 0 | D17: =SUM(D18:D20) -> 0 | E17: =SUM(E18:E20) -> 0 | F17: =SUM(F18:F20) -> 0 | G17: =SUM(G18:G20) -> 0 | H17: =SUM(H18:H20) -> 0 | I17: =SUM(I18:I20) -> 0 | ... AH17: =SUM(AH18:AH20) -> 0
A18: Tax Recoverable | C18: 0 | D18: 0 | E18: 0 | F18: 0 | G18: 0 | H18: 0 | I18: 0 | J18: 0 | K18: 0 | L18: 0 | M18: 0 | N18: 0 | O18: 0 | P18: 0 | Q18: 0 | R18: 0 | S18: 0 | T18: 0 | U18: 0 | V18: 0 | W18: 0 | X18: 0 | Y18: 0 | Z18: 0 | AA18: 0 | AC18: 0 | AD18: 0 | AE18: 0 | AF18: 0 | AG18: 0 | AH18: 0
A19: Deferred Tax Assets | C19: 0 | D19: 0 | E19: 0 | F19: 0 | G19: 0 | H19: 0 | I19: 0 | J19: 0 | K19: 0 | L19: 0 | M19: 0 | N19: 0 | O19: 0 | P19: 0 | Q19: 0 | R19: 0 | S19: 0 | T19: 0 | U19: 0 | V19: 0 | W19: 0 | X19: 0 | Y19: 0 | Z19: 0 | AA19: 0 | AC19: 0 | AD19: 0 | AE19: 0 | AF19: 0 | AG19: 0 | AH19: 0
A20: Retirement Benefit Assets | C20: 0 | D20: 0 | E20: 0 | F20: 0 | G20: 0 | H20: 0 | I20: 0 | J20: 0 | K20: 0 | L20: 0 | M20: 0 | N20: 0 | O20: 0 | P20: 0 | Q20: 0 | R20: 0 | S20: 0 | T20: 0 | U20: 0 | V20: 0 | W20: 0 | X20: 0 | Y20: 0 | Z20: 0 | AA20: 0 | AC20: 0 | AD20: 0 | AE20: 0 | AF20: 0 | AG20: 0 | AH20: 0
A21: Property & Equipment & Other assets | B21: =SUM(B23:B26) -> 1126889701 | C21: =SUM(C23:C26) -> 1.1268782e+09 | D21: =SUM(D22:D26) -> 1.1248829e+09 | E21: =SUM(E22:E26) -> 1.1247493e+09 | F21: =SUM(F22:F26) -> 1.1261345e+09 | G21: =SUM(G22:G26) -> 1.1244533e+09 | H21: =SUM(H22:H26) -> 1.1232534e+09 | I21: =SUM(I22:I26) -> 1.1215e+09 | J21: =SUM(J22:J26) -> 1.120891e+09 | K21: =SUM(K22:K26) -> 1.1182825e+09 | ... AH21: =SUM(AH22:AH26) -> 1.0954619e+09
A22: Investment Properties | C22: 0 | D22: 0 | E22: 0 | F22: 0 | G22: 0 | H22: 0 | I22: 0 | J22: 0 | K22: 0 | L22: 0 | M22: 0 | N22: 0 | P22: 0 | Q22: 0 | R22: 0 | S22: 0 | T22: 0 | U22: 0 | V22: 0 | W22: 0 | X22: 0 | Y22: 0 | Z22: 0 | AA22: 0 | AC22: 0 | AD22: 0 | AE22: 0 | AF22: 0 | AG22: 0 | AH22: 0
A23: Property & Equipment | B23: 138210245 | C23: 1.3750231e+08 | D23: 1.3740759e+08 | E23: 1.3700087e+08 | F23: 140286665 | G23: 1.4050599e+08 | H23: 1.406816e+08 | I23: 1.4077366e+08 | J23: 1.4206522e+08 | K23: 1.4135728e+08 | L23: 1.4120934e+08 | M23: 1.4105325e+08 | N23: 1.412906e+08 | O23: 140958466 | P23: 1.4228098e+08 | Q23: 1.4473197e+08 | R23: 1.4507669e+08 | S23: 1.4443141e+08 | T23: 1.4404435e+08 | U23: 1.4374918e+08 | V23: 1.431039e+08 | W23: 1.4236449e+08 | X23: 1.4577296e+08 | Y23: 1.4540338e+08 | Z23: 1.4538559e+08 | AA23: 1.4795734e+08 | AB23: 146212040 | AC23: 1.5004361e+08 | AD23: 1.547066e+08 | AE23: 1.5498117e+08 | AF23: 1.5514801e+08 | AG23: 1.5888547e+08 | AH23: 1.6047266e+08
A24: Prepaid Lease rentals | C24: 0 | D24: 0 | E24: 0 | F24: 0 | G24: 0 | H24: 0 | I24: 0 | J24: 0 | K24: 0 | L24: 0 | M24: 0 | N24: 0 | P24: 0 | Q24: 0 | R24: 0 | S24: 0 | T24: 0 | U24: 0 | V24: 0 | W24: 0 | X24: 0 | Y24: 0 | Z24: 0 | AA24: 0 | AC24: 0 | AD24: 0 | AE24: 0 | AF24: 0 | AG24: 0 | AH24: 0
A25: Intangible Assets | B25: 11215165 | C25: 13411604 | D25: 13011062 | E25: 14860520 | F25: 14459979 | G25: 14059437 | H25: 14183896 | I25: 13783354 | J25: 13382812 | K25: 12982271 | L25: 12581729 | M25: 12181187 | N25: 12362450 | O25: 9857623 | P25: 13138934 | Q25: 13086434 | R25: 12644917 | S25: 15103401 | T25: 14661885 | U25: 14220369 | V25: 13778853 | W25: 13337337 | X25: 12895821 | Y25: 12454305 | Z25: 12012789 | AA25: 11571273 | AB25: 12405809 | AC25: 10751663 | AD25: 10339652 | AE25: 9927640.5 | AF25: 11240523 | AG25: 10828512 | AH25: 10416501
A26: Other Assets | B26: 977464291 | C26: 9.7596429e+08 | D26: 9.7446429e+08 | E26: 9.7288789e+08 | F26: 9.7138789e+08 | G26: 9.6988789e+08 | H26: 9.6838789e+08 | I26: 9.6694299e+08 | J26: 9.6544299e+08 | K26: 9.6394299e+08 | L26: 9.6249662e+08 | M26: 9.6099662e+08 | N26: 9.5652947e+08 | O26: 956529469 | P26: 9.5513572e+08 | Q26: 9.5359755e+08 | R26: 9.5140314e+08 | S26: 9.4990314e+08 | T26: 9.4840314e+08 | U26: 9.463465e+08 | V26: 9.448465e+08 | W26: 9.433465e+08 | X26: 9.4193834e+08 | Y26: 9.4043834e+08 | Z26: 9.3893834e+08 | AA26: 9.374369e+08 | AB26: 933436902 | AC26: 9.319369e+08 | AD26: 9.3057272e+08 | AE26: 9.2907272e+08 | AF26: 9.2757272e+08 | AG26: 9.2607272e+08 | AH26: 9.2457272e+08
A27: Total Assets | B27: =B4+B7+B8+B14+B17+B21 -> 4379269975 | C27: =C4+C7+C8+C14+C17+C21 -> 4.3897506e+09 | D27: =D4+D7+D8+D14+D17+D21 -> 4.4225736e+09 | E27: =E4+E7+E8+E14+E17+E21 -> 4.4289675e+09 | F27: =F4+F7+F8+F14+F17+F21 -> 4.4698728e+09 | G27: =G4+G7+G8+G14+G17+G21 -> 4.4399069e+09 | H27: =H4+H7+H8+H14+H17+H21 -> 4.4533573e+09 | I27: =I4+I7+I8+I14+I17+I21 -> 4.5821285e+09 | ... N27: =N4+N7+N8+N14+N17+N21 -> 4.7151098e+09 | O27: =O21+O17+O14+O8+O4+O7 -> 4712191322 | P27: =P21+P17+P14+P8+P4+P7 -> 4.7115263e+09 | Q27: =Q21+Q17+Q14+Q8+Q4+Q7 -> 4.741308e+09 | R27: =R21+R17+R14+R8+R4+R7 -> 4.7497451e+09 | S27: =S21+S17+S14+S8+S4+S7 -> 4.7709148e+09 | T27: =T21+T17+T14+T8+T4+T7 -> 4.6997167e+09 | U27: =U21+U17+U14+U8+U4+U7 -> 4.7956641e+09 | V27: =V21+V17+V14+V8+V4+V7 -> 4.8165618e+09 | ... AH27: =AH21+AH17+AH14+AH8+AH4+AH7 -> 5.145476e+09
A28: fosa | B28: 550189731 | C28: 3.2621451e+08 | D28: 3.4135787e+08 | E28: 3.2457352e+08 | F28: 3.5771606e+08 | G28: 3.3057735e+08 | H28: 3.2028038e+08 | I28: 4.2018772e+08 | J28: 4.015809e+08 | K28: 3.9213487e+08 | L28: 3.7425766e+08 | M28: 3.9094285e+08 | N28: 3.5209097e+08 | O28: 635197433 | P28: 3.6079784e+08 | Q28: 3.6946258e+08 | R28: 3.5643043e+08 | S28: 3.5464535e+08 | T28: 3.9032066e+08 | U28: 3.6227158e+08 | V28: 3.8989389e+08 | W28: 3.6905444e+08 | X28: 3.4755719e+08 | Y28: 3.6660077e+08 | Z28: 3.83946e+08 | AA28: 3.5633321e+08 | AB28: 675344114 | AC28: 3.5658381e+08 | AD28: 3.435556e+08 | AE28: 3.4072082e+08 | AF28: 3.5268034e+08 | AG28: 3.406382e+08 | AH28: 3.8057014e+08
A29: Short Term Deposits (e.g Fixed deposits, special savings) | C29: 1.9820934e+08 | D29: 1.9911836e+08 | E29: 1.988312e+08 | F29: 1.9933329e+08 | G29: 1.998347e+08 | H29: 2.0357023e+08 | I29: 2.208971e+08 | J29: 2.2537634e+08 | K29: 2.269992e+08 | L29: 2.3192183e+08 | M29: 2.3578025e+08 | N29: 2.4148333e+08 | P29: 2.4351412e+08 | Q29: 2.551177e+08 | R29: 2.6149194e+08 | S29: 2.6438837e+08 | T29: 2.7115161e+08 | U29: 2.7701476e+08 | V29: 2.7722568e+08 | W29: 2.7209119e+08 | X29: 2.6897241e+08 | Y29: 2.7010761e+08 | Z29: 2.6660725e+08 | AA29: 2.6511624e+08 | AB29: 0 | AC29: 2.5919441e+08 | AD29: 2.5564233e+08 | AE29: 2.5494376e+08 | AF29: 2.5334076e+08 | AG29: 2.5315475e+08 | AH29: 2.5613232e+08
A30: Non withdrawable deposits (BOSA member deposits) | B30: 1850833137 | C30: 1.8872131e+09 | D30: 1.9027242e+09 | E30: 1.9160889e+09 | F30: 1.9235154e+09 | G30: 1.9377675e+09 | H30: 1.9553544e+09 | I30: 1.9656507e+09 | J30: 1.9947623e+09 | K30: 2.0056322e+09 | L30: 1.9949716e+09 | M30: 1.9890441e+09 | N30: 2.0027792e+09 | O30: 1961156088 | P30: 2.0159762e+09 | Q30: 2.0265231e+09 | R30: 2.0432335e+09 | S30: 2.0608198e+09 | T30: 2.0759408e+09 | U30: 2.0858455e+09 | V30: 2.0832792e+09 | W30: 2.1021344e+09 | X30: 2.1113417e+09 | Y30: 2.0652722e+09 | Z30: 2.0544555e+09 | AA30: 2.0694441e+09 | AB30: 2015549412 | AC30: 2.0803822e+09 | AD30: 2.0995083e+09 | AE30: 2.0376485e+09 | AF30: 2.030826e+09 | AG30: 2.0459568e+09 | AH30: 2.0815284e+09
A31: Total Deposit liabilities | B31: =SUM(B28:B30) -> 2401022868 | C31: =SUM(C28:C30) -> 2.411637e+09 | D31: =SUM(D28:D30) -> 2.4432004e+09 | E31: =SUM(E28:E30) -> 2.4394936e+09 | F31: =SUM(F28:F30) -> 2.4805648e+09 | G31: =SUM(G28:G30) -> 2.4681796e+09 | H31: =SUM(H28:H30) -> 2.479205e+09 | I31: =SUM(I28:I30) -> 2.6067355e+09 | ... AH31: =SUM(AH28:AH30) -> 2.7182308e+09
A32: Accounts Payable & Other Liabilities | B32: =SUM(B33:B38) -> 559823213 | C32: =SUM(C33:C38) -> 5.736453e+08 | D32: =SUM(D33:D38) -> 5.4263533e+08 | E32: =SUM(E33:E38) -> 5.3353194e+08 | F32: =SUM(F33:F38) -> 4.9478537e+08 | G32: =SUM(G33:G38) -> 4.9776968e+08 | H32: =SUM(H33:H38) -> 4.9108168e+08 | I32: =SUM(I33:I38) -> 4.8448124e+08 | ... AH32: =SUM(AH33:AH38) -> 5.368814e+08
A33: Tax Payable | B33: 2989880 | C33: 190690.29 | D33: 182564.29 | E33: 215278.29 | F33: 490573.31 | G33: 272138.31 | H33: 224150.31 | I33: 445692.31 | J33: 401508.31 | K33: 206120.31 | L33: 224071.31 | M33: 213240.31 | N33: 222719.31 | P33: 200172.31 | Q33: 198177.31 | R33: 286301.91 | S33: 221700.05 | T33: 490092.51 | U33: 252413.51 | V33: 229025.51 | W33: 224151.51 | X33: 221877.51 | Y33: 219059.51 | Z33: 218781.51 | AA33: 228275.51 | AB33: 228276 | AC33: 222511.51 | AD33: 206739.51 | AE33: 225875.51 | AF33: 198627.51 | AG33: 227093.51 | AH33: 632504.26
A34: Dividends Payable | B34: 91000000 | C34: 0 | D34: 0 | E34: 0 | F34: 0 | G34: 0 | H34: 0 | I34: 0 | J34: 0 | K34: 0 | L34: 0 | M34: 0 | N34: 0 | P34: 0 | Q34: 0 | R34: 0 | S34: 0 | T34: 0 | U34: 0 | V34: 0 | W34: 0 | X34: 0 | Y34: 0 | Z34: 0 | AA34: 0 | AB34: 154556883 | AC34: 0 | AD34: 0 | AE34: 0 | AF34: 0 | AG34: 0 | AH34: 0
A35: Deferred Tax Liability | C35: 0 | D35: 0 | E35: 0 | F35: 0 | G35: 0 | H35: 0 | I35: 0 | J35: 0 | K35: 0 | L35: 0 | M35: 0 | N35: 0 | P35: 0 | Q35: 0 | R35: 0 | S35: 0 | T35: 0 | U35: 0 | V35: 0 | W35: 0 | X35: 0 | Y35: 0 | Z35: 0 | AA35: 0 | AC35: 0 | AD35: 0 | AE35: 0 | AF35: 0 | AG35: 0 | AH35: 0
A36: Retirement Benefits Liability | C36: 0 | D36: 0 | E36: 0 | F36: 0 | G36: 0 | H36: 0 | I36: 0 | J36: 0 | K36: 0 | L36: 0 | M36: 0 | N36: 0 | P36: 0 | Q36: 0 | R36: 0 | S36: 0 | T36: 0 | U36: 0 | V36: 0 | W36: 0 | X36: 0 | Y36: 0 | Z36: 0 | AA36: 0 | AC36: 0 | AD36: 0 | AE36: 0 | AF36: 0 | AG36: 0 | AH36: 0
A37: Other Liabilities | C37: 1.1845461e+08 | D37: 98286101 | E37: 99983331 | F37: 71794795 | G37: 85830877 | H37: 90024201 | I37: 94035547 | J37: 99370473 | K37: 1.0689011e+08 | L37: 1.1336146e+08 | M37: 1.2242599e+08 | N37: 1.4597042e+08 | O37: =141400000+4708687 -> 146108687 | P37: 1.5541722e+08 | Q37: 1.8783832e+08 | R37: 1.8640516e+08 | S37: 1.8553482e+08 | T37: 53812500 | U37: 1.0869189e+08 | V37: 1.1047285e+08 | W37: 1.2093032e+08 | X37: 1.3169677e+08 | Y37: 1.4082926e+08 | Z37: 1.5244857e+08 | AA37: 1.6333885e+08 | AB37: 5492264 | AC37: 2.0090313e+08 | AD37: 2.0833123e+08 | AE37: 2.1536425e+08 | AF37: 2.2538519e+08 | AG37: 2.2451989e+08 | AH37: 1.1374889e+08
A38: External Borrowings | B38: 465833333 | C38: 4.55e+08 | D38: 4.4416667e+08 | E38: 4.3333333e+08 | F38: 4.225e+08 | G38: 4.1166667e+08 | H38: 4.0083333e+08 | I38: 3.9e+08 | J38: 3.7916667e+08 | K38: 3.6833333e+08 | L38: 3.575e+08 | M38: 3.4666667e+08 | N38: 3.3583333e+08 | O38: 335833333 | P38: 3.25e+08 | Q38: 3.1416667e+08 | R38: 3.0333333e+08 | S38: 2.925e+08 | T38: 2.8166667e+08 | U38: 2.7083333e+08 | V38: 2.6e+08 | W38: 2.4916667e+08 | X38: 2.3833333e+08 | Y38: 2.275e+08 | Z38: 2.1666667e+08 | AA38: 2.0583333e+08 | AB38: 205833333 | AC38: 3.45e+08 | AD38: 3.2991906e+08 | AE38: 3.6658573e+08 | AF38: 4.0158573e+08 | AG38: 4.3833333e+08 | AH38: 4.225e+08
A39: Total Liabilities | B39: =B31+B32 -> 2960846081 | C39: =C31+C32 -> 2.9852823e+09 | D39: =D31+D32 -> 2.9858358e+09 | E39: =E31+E32 -> 2.9730256e+09 | F39: =F31+F32 -> 2.9753501e+09 | G39: =G31+G32 -> 2.9659492e+09 | H39: =H31+H32 -> 2.9702867e+09 | I39: =I31+I32 -> 3.0912167e+09 | ... AH39: =AH31+AH32 -> 3.2551122e+09
A40: EQUITY
A41: Share Capital (Members share capital per Bylaws) | B41: 282364118 | C41: 2.8329645e+08 | D41: 2.8439228e+08 | E41: 2.8556961e+08 | F41: 2.8674019e+08 | G41: 2.8774295e+08 | H41: 2.8920469e+08 | I41: 2.9051664e+08 | J41: 2.9259399e+08 | K41: 2.9399514e+08 | L41: 2.9537997e+08 | M41: 2.9794599e+08 | N41: 3.0039835e+08 | O41: 300398348 | P41: 3.0200904e+08 | Q41: 3.0359866e+08 | R41: 3.0590704e+08 | S41: 3.0654829e+08 | T41: 3.0919952e+08 | U41: 3.1045821e+08 | V41: 3.1144253e+08 | W41: 3.1340438e+08 | X41: 3.1516113e+08 | Y41: 3.1669679e+08 | Z41: 3.1810869e+08 | AA41: 3.1995617e+08 | AB41: 319956175 | AC41: 3.212447e+08 | AD41: 3.2334097e+08 | AE41: 4.0083175e+08 | AF41: 4.0263626e+08 | AG41: 4.0523736e+08 | AH41: 4.089586e+08
A42: Capital Grants | C42: 0 | D42: 0 | E42: 0 | F42: 0 | G42: 0 | H42: 0 | I42: 0 | J42: 0 | K42: 0 | L42: 0 | M42: 0 | N42: 0 | O42: 0 | P42: 0 | Q42: 0 | R42: 0 | S42: 0 | T42: 0 | U42: 0 | V42: 0 | W42: 0 | X42: 0 | Y42: 0 | Z42: 0 | AA42: 0 | AB42: 0 | AC42: 0 | AD42: 0 | AE42: 0 | AF42: 0 | AG42: 0 | AH42: 0
A44: Retained Earnings | B44: =B46+B45 -> 198992818 | C44: =C46+C45 -> 2.0388238e+08 | D44: =D46+D45 -> 2.1379173e+08 | E44: =E46+E45 -> 2.2687078e+08 | F44: =F46+F45 -> 2.7921638e+08 | G44: =G46+G45 -> 2.7925144e+08 | H44: =H46+H45 -> 2.8298988e+08 | I44: =I46+I45 -> 2.8801265e+08 | ... AH44: =AH46+AH45 -> 5.4506888e+08
A45: Prior Years' Retained Earnings | B45: 136371407 | C45: 1.9899282e+08 | D45: 2.0199282e+08 | E45: 2.0199282e+08 | F45: 2.0199282e+08 | G45: 2.0199282e+08 | H45: 2.0199282e+08 | I45: 2.0199282e+08 | J45: 2.0199282e+08 | K45: 2.0199282e+08 | L45: 2.0199282e+08 | M45: 2.0199282e+08 | N45: 1.5115932e+08 | O45: 198992818 | P45: 2.7532683e+08 | Q45: 2.7532683e+08 | R45: 2.7532683e+08 | S45: 2.7532683e+08 | T45: 2.7532683e+08 | U45: 2.7532683e+08 | V45: 2.7532683e+08 | W45: 2.7532683e+08 | X45: 2.7532683e+08 | Y45: 3.5912923e+08 | Z45: 3.5912923e+08 | AA45: 3.5917423e+08 | AB45: 275326828 | AC45: 4.2980291e+08 | AD45: 4.2980291e+08 | AE45: 4.2980291e+08 | AF45: 4.2980291e+08 | AG45: 4.2980291e+08 | AH45: 4.2980291e+08
A46: Current Year's Surplus | B46: =198992818-136371407 -> 62621411 | C46: 4889563.5 | D46: 11798907 | E46: 24877963 | F46: 77223566 | G46: 77258617 | H46: 80997063 | I46: 86019828 | J46: 91546464 | K46: 97678969 | L46: 1.0641192e+08 | M46: 1.1624522e+08 | N46: 1.2408599e+08 | O46: =272326828-198992818 -> 73334010 | P46: 5774641.5 | Q46: 11972515 | R46: 25223152 | S46: 34759559 | T46: 46456085 | U46: 1.0146947e+08 | V46: 1.0780418e+08 | W46: 1.147993e+08 | X46: 1.2044733e+08 | Y46: 1.2640468e+08 | Z46: 1.3965204e+08 | AA46: 1.4178663e+08 | AB46: 154476086 | AC46: 6477512.6 | AD46: 10830177 | AE46: 18190543 | AF46: 22658090 | AG46: 32093683 | AH46: 1.1526597e+08
A48: Other Equity Accounts | B48: =SUM(B49:B53) -> 937066956 | C48: =SUM(C49:C53) -> 9.1728952e+08 | D48: =SUM(D49:D53) -> 9.3855383e+08 | E48: =SUM(E49:E53) -> 9.4350152e+08 | F48: =SUM(F49:F53) -> 9.2856613e+08 | G48: =SUM(G49:G53) -> 9.0696331e+08 | H48: =SUM(H49:H53) -> 9.1087606e+08 | I48: =SUM(I49:I53) -> 9.1238253e+08 | ... AH48: =SUM(AH49:AH53) -> 9.3633628e+08
A49: Statutory Reserve | B49: 101541864 | C49: 1.0154186e+08 | D49: 1.0154186e+08 | E49: 1.0154186e+08 | F49: 1.0154186e+08 | G49: 1.0154186e+08 | H49: 1.0154186e+08 | I49: 1.0154186e+08 | J49: 1.0154186e+08 | K49: 1.0154186e+08 | L49: 1.0154186e+08 | M49: 1.0154186e+08 | N49: 1.2637537e+08 | O49: 126375367 | P49: 1.2637537e+08 | Q49: 1.2637537e+08 | R49: 1.2637537e+08 | S49: 1.2637537e+08 | T49: 1.2637537e+08 | U49: 1.2637537e+08 | V49: 1.2637537e+08 | W49: 1.2637537e+08 | X49: 1.2637537e+08 | Y49: 1.2637537e+08 | Z49: 1.2637537e+08 | AA49: 1.2637537e+08 | AB49: 152532538 | AC49: 1.5253254e+08 | AD49: 1.5253254e+08 | AE49: 1.5253254e+08 | AF49: 1.5253254e+08 | AG49: 1.5253254e+08 | AH49: 1.5253254e+08
A50: Other Reserves (provide notes on these reserves) | B50: 46691433 | C50: 49025656 | D50: 70289962 | E50: 75237648 | F50: 60302261 | G50: 38699442 | H50: 42612189 | I50: 44118666 | J50: 52658882 | K50: 54604575 | L50: 59095437 | M50: 62476959 | N50: 94263968 | O50: 68263968 | P50: 1.0140173e+08 | Q50: 70994988 | R50: 65999016 | S50: 70061596 | T50: 69243537 | U50: 77391603 | V50: 74779213 | W50: 80636797 | X50: 85403548 | Y50: 91133927 | Z50: 95815904 | AA50: 88282969 | AB50: =94282969 -> 94282969 | AC50: 95890112 | AD50: 99745662 | AE50: 1.0026618e+08 | AF50: 1.0365775e+08 | AG50: 1.0418843e+08 | AH50: 91758030
A51: Revaluation Reserves (Not part of core capital) | B51: =63906424+702815580 -> 766722004 | C51: 63906424 | D51: 63906424 | E51: 63906424 | F51: 63906424 | G51: 63906424 | H51: 63906424 | I51: 63906424 | J51: 63906424 | K51: 63906424 | L51: 63906424 | M51: 63906424 | N51: 63906424 | O51: =63906424+776540392 -> 840446816 | P51: 63906424 | Q51: 63906424 | R51: 63906424 | S51: 63906424 | T51: 63906424 | U51: 63906424 | V51: 63906424 | W51: 63906424 | X51: 63906424 | Y51: 63906424 | Z51: 63906424 | AA51: 63906424 | AB51: =63906424+628139283 -> 692045707 | AC51: 63906424 | AD51: 63906424 | AE51: 63906424 | AF51: 63906424 | AG51: 63906424 | AH51: 63906424
A52: Proposed Dividends | B52: 22111655 | C52: 7.0281558e+08 | D52: 7.0281558e+08 | E52: 7.0281558e+08 | F52: 7.0281558e+08 | G52: 7.0281558e+08 | H52: 7.0281558e+08 | I52: 7.0281558e+08 | J52: 7.0281558e+08 | K52: 7.0281558e+08 | L52: 7.0281558e+08 | M52: 7.0281558e+08 | N52: 7.7654039e+08 | O52: 26084450 | P52: 7.3582669e+08 | Q52: 7.3582669e+08 | R52: 7.3582669e+08 | S52: 7.3582669e+08 | T52: 7.3582669e+08 | U52: 7.3582669e+08 | V52: 7.3582669e+08 | W52: 7.3582669e+08 | X52: 7.3582669e+08 | Y52: 6.3467669e+08 | Z52: 6.3467669e+08 | AA52: 6.3467669e+08 | AB52: 37456070 | AC52: 6.2813928e+08 | AD52: 6.2813928e+08 | AE52: 6.2813928e+08 | AF52: 6.2813928e+08 | AG52: 6.2813928e+08 | AH52: 6.2813928e+08
A53: Adjustment to Equity | C53: 0 | D53: 0 | E53: 0 | F53: 0 | G53: 0 | H53: 0 | I53: 0 | J53: 0 | K53: 0 | L53: 0 | M53: 0 | N53: 0 | P53: 0 | Q53: 0 | R53: 0 | S53: 0 | T53: 0 | U53: 0 | V53: 0 | W53: 0 | X53: 0 | Y53: 0 | Z53: 0 | AA53: 0 | AC53: 0 | AD53: 0 | AE53: 0 | AF53: 0 | AG53: 0 | AH53: 0
A54: Total Equity | B54: =B41+B42+B44+B48 -> 1418423892 | C54: =C41+C42+C44+C48 -> 1.4044684e+09 | D54: =D41+D42+D44+D48 -> 1.4367378e+09 | E54: =E41+E42+E44+E48 -> 1.4559419e+09 | F54: =F41+F42+F44+F48 -> 1.4945227e+09 | G54: =G41+G42+G44+G48 -> 1.4739577e+09 | H54: =H41+H42+H44+H48 -> 1.4830706e+09 | I54: =I41+I42+I44+I48 -> 1.4909118e+09 | ... AH54: =AH41+AH42+AH44+AH48 -> 1.8903638e+09
A55: Total Liabilities and Equity | B55: =B39+B54 -> 4379269973 | C55: =C39+C54 -> 4.3897506e+09 | D55: =D39+D54 -> 4.4225736e+09 | E55: =E39+E54 -> 4.4289675e+09 | F55: =F39+F54 -> 4.4698728e+09 | G55: =G39+G54 -> 4.4399069e+09 | H55: =H39+H54 -> 4.4533573e+09 | I55: =I39+I54 -> 4.5821285e+09 | ... AH55: =AH39+AH54 -> 5.145476e+09
AC56: =AC55-AC27 -> 0 | AD56: =AD55-AD27 -> 0 | AE56: =AE55-AE27 -> 0 | AF56: =AF55-AF27 -> 0 | AG56: =AG55-AG27 -> 0 | AH56: =AH55-AH27 -> 0

Sheet Sheet2
O26: =419229770 -> 419229770 | R26: =1439501529 -> 1439501529
O27: 264941067 | R27: 1431173549
O28: =O26-O27 -> 154288703 | R28: =R26-R27 -> 8327980

Sheet SCI-2022
A1: KWETU SACCO SOCIETY LTD
A2: STATEMENT OF COMPREHENSIVE INCOME | B2: Audited 2020 | C2: 44197 | D2: 44228 | E2: 44256 | F2: 44287 | G2: 44317 | H2: 44348 | I2: 44378 | J2: 44409 | K2: 44440 | L2: 44470 | M2: 44501 | N2: 44531 | O2: Audited 2021 | P2: 44562 | Q2: 44593 | R2: 44621 | S2: 44652 | T2: 44682 | U2: 44713 | V2: 44743 | W2: 44774 | X2: 44805 | Y2: 44835 | Z2: 44866 | AA2: 44896 | AB2: Audited -22 | AC2: 44949 | AD2: 44980 | AE2: 45008 | AF2: 45039 | AG2: 45069 | AH2: 45100
A3: Financial Income | B3: =B4+B7 -> 639350336 | C3: =C4+C7 -> 39636563 | D3: =D4+D7 -> 80722715 | E3: =E4+E7 -> 1.2062755e+08 | F3: =F4+F7 -> 2.6578951e+08 | G3: =G4+G7 -> 3.0755268e+08 | H3: =H4+H7 -> 3.5199114e+08 | I3: =I4+I7 -> 3.9992797e+08 | ... AH3: =AH4+AH7 -> 4.4964874e+08
A4: Financial Income from Loans Portfolio | B4: =SUM(B5:B6) -> 456351764 | C4: =SUM(C5:C6) -> 38028979 | D4: =SUM(D5:D6) -> 76886254 | E4: =SUM(E5:E6) -> 1.1518746e+08 | F4: =SUM(F5:F6) -> 1.5784686e+08 | G4: =SUM(G5:G6) -> 1.9766831e+08 | H4: =SUM(H5:H6) -> 2.4048007e+08 | I4: =SUM(I5:I6) -> 2.8662319e+08 | ... AH4: =SUM(AH5:AH6) -> 3.0717532e+08
A5: Interest on Loan Portfolio | B5: 456351764 | C5: 34390464 | D5: 69701533 | E5: 1.0363079e+08 | F5: 1.39815e+08 | G5: 1.7488504e+08 | H5: 2.1222146e+08 | I5: 2.528698e+08 | J5: 2.9063364e+08 | K5: 3.2988188e+08 | L5: 3.7292359e+08 | M5: 4.1520161e+08 | N5: 4.5635176e+08 | O5: 456351764 | P5: 39601826 | Q5: 80376449 | R5: 1.24323e+08 | S5: 1.6456803e+08 | T5: 2.0239565e+08 | U5: 2.4258923e+08 | V5: 2.8472819e+08 | W5: 3.2710206e+08 | X5: 3.7006558e+08 | Y5: 4.1496744e+08 | Z5: 4.6079906e+08 | AA5: 5.061141e+08 | AB5: 506114104 | AC5: 45932038 | AD5: 88281181 | AE5: 1.3396639e+08 | AF5: 1.803288e+08 | AG5: 2.2608833e+08 | AH5: 2.7027032e+08
A6: Fees & Commission on Loan Portfolio | C6: 3638514.8 | D6: 7184720.5 | E6: 11556670 | F6: 18031856 | G6: 22783270 | H6: 28258610 | I6: 33753386 | J6: 38508416 | K6: 43666284 | L6: 49282930 | M6: 55135220 | N6: 60654214 | P6: 4475143.9 | Q6: 8820698.1 | R6: 15337772 | S6: 20720746 | T6: 27455293 | U6: 33015901 | V6: 38457791 | W6: 44686442 | X6: 51205492 | Y6: 57412086 | Z6: 64575015 | AA6: 71801844 | AB6: 63274958 | AC6: 7428163.4 | AD6: 12508721 | AE6: 18698208 | AF6: 23775542 | AG6: 29100554 | AH6: 36904998
A7: Financial Income from Investments in: | B7: =SUM(B8:B11) -> 182998572 | C7: =SUM(C8:C11) -> 1607583.8 | D7: =SUM(D8:D11) -> 3836460.7 | E7: =SUM(E8:E11) -> 5440086 | F7: =SUM(F8:F11) -> 1.0794265e+08 | G7: =SUM(G8:G11) -> 1.0988438e+08 | H7: =SUM(H8:H11) -> 1.1151107e+08 | I7: =SUM(I8:I11) -> 1.1330479e+08 | ... AH7: =SUM(AH8:AH11) -> 1.4247342e+08
A8: Government Securities | C8: 0 | D8: 0 | E8: 0 | F8: 0 | G8: 0 | H8: 0 | I8: 0 | J8: 0 | K8: 0 | L8: 0 | M8: 0 | N8: 0 | O8: 0 | P8: 0 | Q8: 0 | R8: 0 | S8: 0 | T8: 0 | U8: 0 | V8: 0 | W8: 0 | X8: 0 | Y8: 0 | Z8: 0 | AA8: 0 | AB8: 0 | AC8: 0 | AD8: 0 | AE8: 0 | AF8: 0 | AG8: 0 | AH8: 0
A9: Deposit with Banks and Other Financial Inst. | C9: 0 | D9: 0 | E9: 0 | F9: 0 | G9: 0 | H9: 0 | I9: 0 | J9: 0 | K9: 0 | L9: 0 | M9: 0 | N9: 0 | O9: 0 | P9: 0 | Q9: 0 | R9: 0 | S9: 0 | T9: 0 | U9: 0 | V9: 0 | W9: 0 | X9: 0 | Y9: 0 | Z9: 0 | AA9: 0 | AB9: 0 | AC9: 0 | AD9: 0 | AE9: 0 | AF9: 0 | AG9: 0 | AH9: 0
A10: Other Investments - dividend & Interest incomes from investments | C10: 727207.54 | D10: 2119185.4 | E10: 2871931.8 | F10: 1.0400492e+08 | G10: 1.0493063e+08 | H10: 1.0559774e+08 | I10: 1.0639355e+08 | J10: 1.0738699e+08 | K10: 1.0829445e+08 | L10: 1.0918022e+08 | M10: 1.0985556e+08 | N10: 1.1047191e+08 | P10: 1179881.1 | Q10: 1771999.7 | R10: 2497504.3 | S10: 2881541.8 | T10: 3171543.9 | U10: 1.0067489e+08 | V10: 1.0116112e+08 | W10: 1.0190965e+08 | X10: 1.0243013e+08 | Y10: 1.0319332e+08 | Z10: 1.0377288e+08 | AA10: 1.0402622e+08 | AB10: 104026224 | AC10: 781227.66 | AD10: 916871.77 | AE10: 916871.77 | AF10: 3708872.6 | AG10: 3839856.3 | AH10: 1.3298052e+08
A11: Other Operating Income- Salary processing fees, transaction fees, membership fees | B11: 182998572 | C11: 880376.26 | D11: 1717275.3 | E11: 2568154.2 | F11: 3937727.2 | G11: 4953750.9 | H11: 5913336.4 | I11: 6911232.7 | J11: 7842214.1 | K11: 8915647.2 | L11: 9807416.6 | M11: 10755715 | N11: 11790930 | O11: 182998572 | P11: 1057190.8 | Q11: 2054367.3 | R11: 3258819.3 | S11: 4305207.2 | T11: 6796692.2 | U11: 7804690.3 | V11: 8795448.8 | W11: 10258586 | X11: 11223464 | Y11: 12230897 | Z11: 13532517 | AA11: 14580858 | AB11: 23107744 | AC11: 1081375.1 | AD11: 2166386.9 | AE11: 5202389.8 | AF11: 6326725.4 | AG11: 7471357.5 | AH11: 9492901.7
A12: Financial Expense | B12: =B13+B14+B15+B16+B17+B18 -> 221092820 | C12: =C13+C14+C15+C16+C17+C18 -> 9083871.6 | D12: =D13+D14+D15+D16+D17+D18 -> 15585796 | E12: =E13+E14+E15+E16+E17+E18 -> 23237968 | F12: =F13+F14+F15+F16+F17+F18 -> 86207710 | G12: =G13+G14+G15+G16+G17+G18 -> 1.0444536e+08 | H12: =H13+H14+H15+H16+H17+H18 -> 1.1811035e+08 | I12: =I13+I14+I15+I16+I17+I18 -> 1.321964e+08 | ... AH12: =AH13+AH14+AH15+AH16+AH17+AH18 -> 1.4161158e+08
A13: Interest Expense on Deposits | B13: 221092820 | C13: 4002490.3 | D13: 5540876.4 | E13: 8808070.7 | F13: 67042836 | G13: 80816326 | H13: 89961915 | I13: 99781340 | J13: 1.0847333e+08 | K13: 1.1830521e+08 | L13: 1.2748297e+08 | M13: 1.3609691e+08 | N13: 1.6882557e+08 | O13: =149000000+19825573 -> 168825573 | P13: 10401675 | Q13: 18688921 | R13: 23252463 | S13: 31715258 | T13: 41370517 | U13: 99820851 | V13: 1.1391367e+08 | W13: 1.2655604e+08 | X13: 1.3919818e+08 | Y13: 1.5144446e+08 | Z13: 1.6375579e+08 | AA13: 1.7667981e+08 | AB13: =153200004+23479806 -> 176679810 | AC13: 8161166.5 | AD13: 17587014 | AE13: 26584124 | AF13: 34948667 | AG13: 45681206 | AH13: 1.1212104e+08
A14: Cost of External Borrowings | C14: 5081381.3 | D14: 10044920 | E14: 14429897 | F14: 19164874 | G14: 23629030 | H14: 28148432 | I14: 32415055 | J14: 36671539 | K14: 40810181 | L14: 44701277 | M14: 48604233 | N14: 52267247 | O14: 52267247 | P14: 3667271.7 | Q14: 7217001.3 | R14: 10317125 | S14: 13631995 | T14: 16725742 | U14: 19807179 | V14: 22674720 | W14: 25517095 | X14: 28241627 | Y14: 30764229 | Z14: 33256984 | AA14: 35554761 | AB14: 35554761 | AC14: 5865462.1 | AD14: 8003521.5 | AE14: 11469079 | AF14: 16517163 | AG14: 24369015 | AH14: 29490545
A15: Dividend Expenses (on member shares) | C15: 0 | D15: 0 | E15: 0 | F15: 0 | G15: 0 | H15: 0 | I15: 0 | J15: 0 | K15: 0 | L15: 0 | M15: 0 | N15: 0 | P15: 0 | Q15: 0 | R15: 0 | S15: 0 | T15: 0 | U15: 0 | V15: 0 | W15: 0 | X15: 0 | Y15: 0 | Z15: 0 | AA15: 0 | AB15: 0 | AC15: 0 | AD15: 0 | AE15: 0 | AF15: 0 | AG15: 0 | AH15: 0
A16: Other Financial Expense | C16: 0 | D16: 0 | E16: 0 | F16: 0 | G16: 0 | H16: 0 | I16: 0 | J16: 0 | K16: 0 | L16: 0 | M16: 0 | N16: 0 | P16: 0 | Q16: 0 | R16: 0 | S16: 0 | T16: 0 | U16: 0 | V16: 0 | W16: 0 | X16: 0 | Y16: 0 | Z16: 0 | AA16: 0 | AB16: 0 | AC16: 0 | AD16: 0 | AE16: 0 | AF16: 0 | AG16: 0 | AH16: 0
A17: Fees & Commission Expense | C17: 0 | D17: 0 | E17: 0 | F17: 0 | G17: 0 | H17: 0 | I17: 0 | J17: 0 | K17: 0 | L17: 0 | M17: 0 | N17: 0 | P17: 0 | Q17: 0 | R17: 0 | S17: 0 | T17: 0 | U17: 0 | V17: 0 | W17: 0 | X17: 0 | Y17: 0 | Z17: 0 | AA17: 0 | AB17: 0 | AC17: 0 | AD17: 0 | AE17: 0 | AF17: 0 | AG17: 0 | AH17: 0
A18: Other Expense | C18: 0 | D18: 0 | E18: 0 | F18: 0 | G18: 0 | H18: 0 | I18: 0 | J18: 0 | K18: 0 | L18: 0 | M18: 0 | N18: 0 | P18: 0 | Q18: 0 | R18: 0 | S18: 0 | T18: 0 | U18: 0 | V18: 0 | W18: 0 | X18: 0 | Y18: 0 | Z18: 0 | AA18: 0 | AB18: 0 | AC18: 0 | AD18: 0 | AE18: 0 | AF18: 0 | AG18: 0 | AH18: 0
A19: Net Financial Income/(Loss) | B19: =B3-B12 -> 418257516 | C19: =C3-C12 -> 30552691 | D19: =D3-D12 -> 65136918 | E19: =E3-E12 -> 97389579 | F19: =F3-F12 -> 1.795818e+08 | G19: =G3-G12 -> 2.0310733e+08 | H19: =H3-H12 -> 2.3388079e+08 | I19: =I3-I12 -> 2.6773158e+08 | ... AH19: =AH3-AH12 -> 3.0803716e+08
A20: Allowance for Loan Loss | B20: =B21-B22 -> 0 | C20: =C21-C22 -> 1485570.8 | D20: =D21-D22 -> 5260675 | E20: =E21-E22 -> -1879441.4 | F20: =F21-F22 -> 1430469.7 | G20: =G21-G22 -> 4002928.3 | H20: =H21-H22 -> 11229577 | I20: =I21-I22 -> 18140432 | ... AH20: =AH21-AH22 -> 9619608.9
A21: Provision for Loan Losses | C21: 1485570.8 | D21: 5260675 | E21: -1879441.4 | F21: 1430469.7 | G21: 4002928.3 | H21: 11229577 | I21: 18140432 | J21: 22140432 | K21: 26140432 | L21: 30140432 | M21: 34140432 | N21: 3797919.5 | O21: 3797919 | P21: 1043181.9 | Q21: 2493940.3 | R21: 3933191 | S21: 6809626.8 | T21: 8920266.9 | U21: 8920266.9 | V21: 8920266.9 | W21: 8920266.9 | X21: 8920266.9 | Y21: 10170360 | Z21: 11420360 | AA21: 10830635 | AB21: =10830635 -> 10830635 | AC21: 3045511.2 | AD21: 4807764.5 | AE21: 5835999.5 | AF21: 9619608.9 | AG21: 9619608.9 | AH21: 9619608.9
A22: Value of Loans Recovered | C22: 0 | D22: 0 | E22: 0 | F22: 0 | G22: 0 | H22: 0 | I22: 0 | J22: 0 | K22: 0 | L22: 0 | M22: 0 | N22: 0 | O22: 0 | P22: 0 | Q22: 0 | R22: 0 | S22: 0 | T22: 0 | U22: 0 | V22: 0 | W22: 0 | X22: 0 | Y22: 0 | Z22: 0 | AA22: 0 | AB22: 0 | AC22: 0 | AD22: 0 | AE22: 0 | AF22: 0 | AG22: 0 | AH22: 0
A23: Operating Expenses | B23: =SUM(B24:B28) -> 294090004 | C23: =SUM(C24:C28) -> 24177557 | D23: =SUM(D24:D28) -> 48077336 | E23: =SUM(E24:E28) -> 74391058 | F23: =SUM(F24:F28) -> 1.0092776e+08 | G23: =SUM(G24:G28) -> 1.2184578e+08 | H23: =SUM(H24:H28) -> 1.4165415e+08 | I23: =SUM(I24:I28) -> 1.6357132e+08 | ... AH23: =SUM(AH24:AH28) -> 1.8315158e+08
A24: Personnel Expenses | B24: 104355946 | C24: 6878923.2 | D24: 13104499 | E24: 19758280 | F24: 28119555 | G24: 37414374 | H24: 46102559 | I24: 54618184 | J24: 65595118 | K24: 75126351 | L24: 84664804 | M24: 93478548 | N24: 1.0435595e+08 | O24: 104355946 | P24: 9317337.4 | Q24: 18258496 | R24: 25674382 | S24: 35741030 | T24: 46892654 | U24: 60807176 | V24: 70268184 | W24: 80454205 | X24: 90368772 | Y24: 100257010 | Z24: 1.1081431e+08 | AA24: 1.2075505e+08 | AB24: 126755051 | AC24: 10373029 | AD24: 19901912 | AE24: 21604786 | AF24: 28369474 | AG24: 36886372 | AH24: 44039776
A25: Governance Expenses | B25: 47406102 | C25: 2897431.4 | D25: 6641982.9 | E25: 10180208 | F25: 15609021 | G25: 19170338 | H25: 21775440 | I25: 25183681 | J25: 27929972 | K25: 31044835 | L25: 36994813 | M25: 40078343 | N25: 49107563 | O25: 47406102 | P25: 2617681.4 | Q25: 5633975.2 | R25: 14461803 | S25: 17269187 | T25: 18548023 | U25: 20753201 | V25: 25064681 | W25: 28517991 | X25: 31979652 | Y25: 39363387 | Z25: 43152381 | AA25: 50179869 | AB25: 46288149 | AC25: 2272404 | AD25: 5839293.8 | AE25: 11457775 | AF25: 14561984 | AG25: 17971473 | AH25: 22415574
A26: Marketing Expenses | C26: 2402372 | D26: 4063372 | E26: 5027233 | F26: 5686133 | G26: 5866183 | H26: 6342993 | I26: 7163057 | J26: 8583499 | K26: 10008011 | L26: 12304620 | M26: 14548073 | N26: 15977602 | P26: 341250 | Q26: 3197763 | R26: 6446083 | S26: 8486613 | T26: 10257963 | U26: 12368138 | V26: 14760325 | W26: 16038005 | X26: 17659415 | Y26: 20462814 | Z26: 22797744 | AA26: 28964336 | AB26: =27498336 -> 27498336 | AC26: 1863927 | AD26: 4831984 | AE26: 6452593 | AF26: 8897264 | AG26: 11244785 | AH26: 14536765
A27: Depreciation and Amortization Charges | B27: 13748688 | C27: 2608479.2 | D27: 5216958.5 | E27: 7825437.7 | F27: 10433917 | G27: 13042396 | H27: 15650875 | I27: 18259355 | J27: 20867834 | K27: 23476313 | L27: 26084792 | M27: 28693272 | N27: 34748688 | O27: 13748688 | P27: 2746902.5 | Q27: 5104789 | R27: 7851691.5 | S27: 10598594 | T27: 13345496 | U27: 16092399 | V27: 18839301 | W27: 21586204 | X27: 24333106 | Y27: 27080009 | Z27: 29826911 | AA27: 32573814 | AB27: 15574582 | AC27: 2795632.2 | AD27: 5591264.4 | AE27: 8386896.6 | AF27: 11182529 | AG27: 13978161 | AH27: 16773793
A28: Administrative Expenses | B28: 128579268 | C28: 9390351 | D28: 19050524 | E28: 31599899 | F28: 41079134 | G28: 46352491 | H28: 51782286 | I28: 58347040 | J28: 62563064 | K28: 68167965 | L28: 72408519 | M28: 79063062 | N28: 86102286 | O28: =128579268-3797919 -> 124781349 | P28: 10404100 | Q28: 20456114 | R28: 28257209 | S28: 33463660 | T28: 37302429 | U28: 44046030 | V28: 50897215 | W28: 61567638 | X28: 73776315 | Y28: 81856788 | Z28: 88002949 | AA28: 99198128 | AB28: =164884819-(10830635+27498336) -> 126555848 | AC28: 14368160 | AD28: 26480229 | AE28: 48802065 | AF28: 67385155 | AG28: 74655794 | AH28: 85385671
A29: Net Operating Income | B29: =B19-B20-B23 -> 124167512 | C29: =C19-C20-C23 -> 4889563.5 | D29: =D19-D20-D23 -> 11798907 | E29: =E19-E20-E23 -> 24877963 | F29: =F19-F20-F23 -> 77223566 | G29: =G19-G20-G23 -> 77258617 | H29: =H19-H20-H23 -> 80997063 | I29: =I19-I20-I23 -> 86019828 | ... AH29: =AH19-AH20-AH23 -> 1.1526597e+08
A30: Net Non- Operating Income/ (Expense) | N30: =N31-N32 -> 0 | O30: =O31-O32 -> 0 | P30: =P31-P32 -> 0 | Q30: =Q31-Q32 -> 0 | R30: =R31-R32 -> 0 | S30: =S31-S32 -> 0 | T30: =T31-T32 -> 0 | U30: =U31-U32 -> 0 | ... AH30: =AH31-AH32 -> 0
A31: Non- Operating Income | C31: 0 | D31: 0 | E31: 0 | F31: 0 | G31: 0 | H31: 0 | I31: 0 | J31: 0 | K31: 0 | L31: 0 | M31: 0 | N31: 0 | P31: 0 | Q31: 0 | R31: 0 | S31: 0 | T31: 0 | U31: 0 | V31: 0 | W31: 0 | X31: 0 | Y31: 0 | Z31: 0 | AA31: 0 | AC31: 0 | AD31: 0 | AE31: 0 | AF31: 0 | AG31: 0 | AH31: 0
A32: Non- Operating Expense | C32: 0 | D32: 0 | E32: 0 | F32: 0 | G32: 0 | H32: 0 | I32: 0 | J32: 0 | K32: 0 | L32: 0 | M32: 0 | N32: 0 | P32: 0 | Q32: 0 | R32: 0 | S32: 0 | T32: 0 | U32: 0 | V32: 0 | W32: 0 | X32: 0 | Y32: 0 | Z32: 0 | AA32: 0 | AC32: 0 | AD32: 0 | AE32: 0 | AF32: 0 | AG32: 0 | AH32: 0
A33: Net Income (Before Taxes and Donations) | B33: =B29+B30 -> 124167512 | C33: =C29+C30 -> 4889563.5 | D33: =D29+D30 -> 11798907 | E33: =E29+E30 -> 24877963 | F33: =F29+F30 -> 77223566 | G33: =G29+G30 -> 77258617 | H33: =H29+H30 -> 80997063 | I33: =I29+I30 -> 86019828 | ... AH33: =AH29+AH30 -> 1.1526597e+08
A34: Taxes (Incomes taxes & Other payable to KRA) | C34: 0 | D34: 0 | E34: 0 | F34: 0 | G34: 0 | H34: 0 | I34: 0 | J34: 0 | K34: 0 | L34: 0 | M34: 0 | N34: 0 | P34: 0 | Q34: 0 | R34: 0 | S34: 0 | T34: 0 | U34: 0 | V34: 0 | W34: 0 | X34: 0 | Y34: 0 | Z34: 0 | AA34: 0 | AC34: 0 | AD34: 0 | AE34: 0 | AF34: 0 | AG34: 0 | AH34: 0
A35: Net Income (After Taxes before Donations) | B35: =B33-B34 -> 124167512 | C35: =C33-C34 -> 4889563.5 | D35: =D33-D34 -> 11798907 | E35: =E33-E34 -> 24877963 | F35: =F33-F34 -> 77223566 | G35: =G33-G34 -> 77258617 | H35: =H33-H34 -> 80997063 | I35: =I33-I34 -> 86019828 | ... AH35: =AH33-AH34 -> 1.1526597e+08
A36: Donations | C36: 0 | D36: 0 | E36: 0 | F36: 0 | G36: 0 | H36: 0 | I36: 0 | J36: 0 | K36: 0 | L36: 0 | M36: 0 | N36: 0 | P36: 0 | Q36: 0 | R36: 0 | S36: 0 | T36: 0 | U36: 0 | V36: 0 | W36: 0 | X36: 0 | Y36: 0 | Z36: 0 | AA36: 0 | AC36: 0 | AD36: 0 | AE36: 0 | AF36: 0 | AG36: 0 | AH36: 0
A37: Net Income/(After Taxes and Donations) | B37: =B35+B36 -> 124167512 | C37: =C35+C36 -> 4889563.5 | D37: =D35+D36 -> 11798907 | E37: =E35+E36 -> 24877963 | F37: =F35+F36 -> 77223566 | G37: =G35+G36 -> 77258617 | H37: =H35+H36 -> 80997063 | I37: =I35+I36 -> 86019828 | ... AH37: =AH35+AH36 -> 1.1526597e+08
C38: =C36+C37 -> 4889563.5

Sheet Sheet1
B2: Year | C2: AUDITED 2015 | D2: AUDITED 2016 | E2: AUDITED 2017 | F2: AUDITED 2018 | G2: 43466 | H2: 43497 | I2: 43525 | J2: 43556 | K2: 43586 | L2: 43617
A3: 2 | B3: Total Assets | C3: 4.6351889e+08 | D3: 4.5637093e+08 | E3: 4.3683362e+08 | F3: 590186392 | G3: 6.0231394e+08 | H3: 6.2625108e+08 | I3: 5.9828697e+08 | J3: 5.8907278e+08 | K3: 6.1710155e+08 | L3: 6.0417723e+08
A4: 3 | B4: Total Deposits | C4: 3.6391029e+08 | D4: 3.5281156e+08 | E4: 3.4681983e+08 | F4: 433315333 | G4: 4.3839535e+08 | H4: 4.542002e+08 | I4: 4.7118357e+08 | J4: 4.6306008e+08 | K4: 4.8617864e+08 | L4: 4.6622117e+08
A5: 3.1 | B5: Deposits-Members(BOSA) | C5: 2.4228165e+08 | D5: 2.4464437e+08 | E5: 2.4323434e+08 | F5: 365696388 | G5: 3.7313088e+08 | H5: 3.8056337e+08 | I5: 3.899621e+08 | J5: 3.9463998e+08 | K5: 3.9710517e+08 | L5: 4.0401425e+08
A6: 3.2 | B6: Deposits-Customers(FOSA) | C6: 4074376.9 | D6: 4984401.3 | E6: 5076228.9 | F6: 67618945 | G6: 14363008 | H6: 15611949 | I6: 13612359 | J6: 14419909 | K6: 14679037 | L6: 13096149
A7: 4 | B7: External Borrowing | C7: 782851.88 | D7: 782851.88 | E7: 782851.88 | F7: 0 | G7: 0 | H7: 0 | I7: 0 | J7: 0 | K7: 0 | L7: 0
A8: 4.1 | B8: Short term Liabilities | C8: 4642444.9 | D8: 27506534 | E8: 4912342.2 | F8: 58156529 | G8: 3901907.3 | H8: 4415903.4 | I8: -44130681 | J8: 10574287 | K8: 12876255 | L8: 10617410
A9: 5.1 | B9: Core Capital | C9: 94944699 | D9: 75269883 | E9: 78350880 | F9: 88729697 | G9: 1.5578813e+08 | H9: 1.6340642e+08 | I9: 1.6700553e+08 | J9: 1.1120986e+08 | K9: 1.138181e+08 | L9: 1.231101e+08
A10: 5.2 | B10: Institutional Capital | C10: 85006164 | D10: 65331348 | E10: 67704199 | F10: 65523502 | G10: 1.3199681e+08 | H10: 1.3957898e+08 | I10: 1.42917e+08 | J10: 87051631 | K10: 89639871 | L10: 98730332
A11: 5.3 | B11: Total Capital | C11: 94944699 | D11: 75269883 | E11: 78350880 | F11: 92958252 | G11: 1.6001668e+08 | H11: 1.6763498e+08 | I11: 1.7123408e+08 | J11: 1.1543841e+08 | K11: 1.1804665e+08 | L11: 1.2733866e+08
A12: 7 | B12: Net Loans & advances | C12: 2.9963107e+08 | D12: 3.0964314e+08 | E12: 3.1063977e+08 | F12: 467465209 | G12: 4.7291977e+08 | H12: 4.7868736e+08 | I12: 4.7578771e+08 | J12: 4.7958254e+08 | K12: 4.8126667e+08 | L12: 4.8527697e+08
A13: 7.1 | B13: Gross Loans & advances | C13: 3.0960349e+08 | D13: 3.1961557e+08 | E13: 3.2061219e+08 | F13: 478678153 | G13: 4.8413271e+08 | H13: 4.899003e+08 | I13: 4.8760561e+08 | J13: 4.9160208e+08 | K13: 4.9348786e+08 | L13: 4.9769982e+08
A14: 7.3 | B14: Allowance for loan losses | C14: 9972423.1 | D14: 9972423.1 | E14: 9972423.1 | F14: 11212944 | G14: 11212944 | H14: 11212944 | I14: 11817894 | J14: 12019544 | K14: 12221194 | L14: 12422844
... A19: 10 | B19: Total Expenses (FinCosts + OpEx) | C19: 22339455 | D19: 4546921.1 | E19: 5916993.1 | F19: 68345005 | G19: 18479434 | H19: 19450021 | I19: 21786998 | J19: 6653981.1 | K19: 12263359 | L19: 13807775
B21: CORE CAPITAL | C21: 94.944699 | D21: 75.269883 | E21: 78.35088 | F21: 88.729697 | G21: 155.78813 | H21: 163.40642 | I21: 167.00553 | J21: 111.20986 | K21: 113.8181 | L21: 123.1101
B22: CCA | C22: 0.20483458 | D22: 0.16493137 | E22: 0.17936092 | F22: 0.15034182 | G22: 0.25864938 | H22: 0.26092797 | I22: 0.2791395 | J22: 0.18878798 | K22: 0.18443982 | L22: 0.20376488
B23: ICA | C23: 0.18339309 | D23: 0.14315405 | E23: 0.15498853 | F23: 0.11102171 | G23: 0.21914952 | H23: 0.22288022 | I23: 0.23887701 | J23: 0.14777738 | K23: 0.14525951 | L23: 0.16341286
B24: CCD | C24: 0.26090139 | D24: 0.21334302 | E24: 0.22591234 | F24: 0.20476935 | G24: 0.3553599 | H24: 0.35976739 | I24: 0.35443835 | J24: 0.24016291 | K24: 0.23410757 | L24: 0.26405944
B25: Asset Quality
B26: NPL
B27: Earnings
B28: ROA | C28: 0.10366402 | D28: 0.0049791285 | E28: 0.0086990958 | F28: 0.021403287 | G28: 0.086521768 | H28: 0.092418745 | I28: 0.095308004 | J28: 0.025179366 | K28: 0.027427623 | L28: 0.036644694
B29: CIR | C29: 0.25741416 | D29: 0.47475461 | E29: 0.47309013 | F29: 0.59346691 | G29: 0.29062189 | H29: 0.28378981 | I29: 0.30491294 | J29: 0.3518848 | K29: 0.42614589 | L29: 0.38569897
B30: OER | C30: 0.050864587 | D30: 0.006821232 | E30: 0.012065152 | F30: 0.056671522 | G30: 0.054654004 | H30: 0.055574311 | I30: 0.067479629 | J30: 0.021463423 | K30: 0.030839954 | L30: 0.036261474
B31: MIN LIQ | C31: 0.28117848 | D31: 0.1804874 | E31: 0.14704211 | F31: 0.20525016 | G31: 0.26279967 | H31: 0.27638489 | I31: 0.26967942 | J31: 0.20183359 | K31: 0.21134839 | L31: 0.19694405
B32: TEC LIQ | C32: 0.18838483 | D32: 0.12915454 | E32: 0.10373806 | F32: 0.1770109 | G32: 0.2240215 | H32: 0.23200767 | I32: 0.21838892 | J32: 0.17267718 | K32: 0.17362602 | L32: 0.17125133
B33: EB | C33: 0.001688932 | D33: 0.0017153851 | E33: 0.0017921054 | F33: 0 | G33: 0 | H33: 0 | I33: 0 | J33: 0 | K33: 0 | L33: 0
B34: LIQ/TA | C34: 0.14978838 | D34: 0.10763133 | E34: 0.083528395 | F34: 0.14740407 | G34: 0.16450573 | H34: 0.16990382 | I34: 0.15588442 | J34: 0.13883827 | K34: 0.14041273 | L34: 0.13515776
B35: NEA | C35: 0.11800484 | D35: 0.12675515 | E35: 0.10067358 | F35: 0.053367462 | G35: 0.043302199 | H35: 0.058974292 | I35: 0.041797813 | J35: 0.039852185 | K35: 0.072852538 | L35: 0.054640365
B36: LB | C36: 0.01288188 | D36: 0.012663382 | E36: 0.013661078 | F36: 0.0051649463 | G36: 0.011631407 | H36: 0.01118682 | I36: 0.011457956 | J36: 0.010564849 | K36: 0.011089534 | L36: 0.010959528
B37: FITD | C37: 0.12176194 | D37: 0.11269646 | E37: 0.11464343 | F37: 0.0097586092 | G37: 0.0096455287 | H37: 0.0093098923 | I37: 0.0089743259 | J37: 0.009131763 | K37: 0.0086975334 | L37: 0.0090698477
B38: FICC | C38: 0.46669717 | D38: 0.52824067 | E38: 0.50746862 | F38: 0.047656592 | G38: 0.027142986 | H38: 0.025877532 | I38: 0.02531985 | J38: 0.038023203 | K38: 0.037151868 | L38: 0.03434775

Sheet DEC 2020
A1: MAGADI SACCO SOCIETY LIMITED
A2: PERFORMANCE AND COMPLIANCE REPORT AS AT : 31st December , 2020
B3: Prudential Standard | C3: Audited | D3: Returns | F3: AUDITED 2020 | G3: Aggregate for all Licensed Saccos
C4: 2019 | D4: 30th September , 2020 | E4: 31st December , 2020
A5: A. CAPITAL ADEQUACY
A6: Core Capital | B6: ≥10M | C6: =C33 -> 98409139 | D6: =D33 -> 1.5398554e+08 | E6: =E33 -> 1.7565742e+08 | F6: =F33 -> #REF! | G6: =G33 -> 9.281382e+10 | H6: =F6-C6 -> #REF!
A7: Core Capital/Total Assets | B7: ≥10% | C7: =C33/C29 -> 0.149196 | D7: =D33/D29 -> 0.21974079 | E7: =E33/E29 -> 0.23992254 | F7: =F33/F29 -> #REF! | G7: =G33/G29 -> 0.15852844
A8: Institutional Capital/Total Assets | B8: ≥8% | C8: =C34/C29 -> 0.11007419 | D8: =D34/D29 -> 0.18075965 | E8: =E34/E29 -> 0.2020382 | F8: =F34/F29 -> #REF! | G8: =G34/G29 -> 0.092879022
A9: B. ASSET QUALITY
A10: NPL (Substandard+Doubtful+Loss) | B10: <5% | C10: =C35/C32 -> 0 | D10: =D35/D32 -> 0.066804616 | E10: =E35/E32 -> 0.058669004 | F10: =F35/F32 -> #REF! | G10: =G35/G32 -> 0.081923116
A11: Non-Earning Assets | B11: <10% | C11: =C36/C29 -> 0.041460677 | D11: =D36/D29 -> 0.034504765 | E11: =E36/E29 -> 0.03147327 | F11: =F36/F29 -> #REF! | G11: =G36/G29 -> 0.10331964
A12: Equity investments/Deposits | B12: <5% | C12: =C38/C31 -> 0.0086859989 | D12: =D38/D31 -> 0.007972688 | E12: =E38/E31 -> 0.0078282924 | F12: =F38/F31 -> #REF! | G12: =G38/G31 -> 0.033894147
A13: Equity investments/Core capital | B13: <40% | C13: =C38/C33 -> 0.042969139 | D13: =D38/D33 -> 0.027460728 | E13: =E38/E33 -> 0.024072738 | F13: =F38/F33 -> #REF! | G13: =G38/G33 -> 0.14648774
A14: C. EARNINGS RATING
A15: Yield on Gross Loans | C15: =C48/C32 -> 0.18432223 | D15: =D48/D32 -> 0.1292034 | E15: =E48/E32 -> 0.17383407 | F15: =F48/F32 -> #REF! | G15: =G48/G32 -> 0.1744387
A16: Total Expense/Total Income | C16: =C49/C44 -> 0.81230275 | D16: =D49/D44 -> 0.33068826 | E16: =E49/E44 -> 0.33091343 | F16: =F49/F44 -> #REF! | G16: =G49/G44 -> 0.69938821
A17: Net Income/Average Assets (ROA) | C17: =C50/C30 -> 0.02237977 | D17: =D50/D30 -> 0.081626281 | E17: =E50/E30 -> 0.10964544 | F17: =F50/F30 -> #REF! | G17: =G50/G30 -> 0.038410442
A18: Operating Expenses/Financial Income (OPEX) | C18: =C47/C44 -> 0.32162796 | D18: =D47/D44 -> 0.28452022 | E18: =E47/E44 -> 0.28396284 | F18: =F47/F44 -> #REF! | G18: =G47/G44 -> 0.30079837
A19: D. LIQUIDITY
A20: Liquid Assets/Short-term Liabilities | B20: >15% | C20: =C40/C41 -> 0.59313783 | D20: =D40/D41 -> 1.4178168 | E20: =E40/E41 -> 2.0006732 | F20: =F40/F41 -> #REF! | G20: =G40/G41 -> 0.6151057
A21: External Borrowing/Total Assets | B21: <25% | C21: =C42/C29 -> 1.1611647e-05 | D21: =D42/D29 -> 0.011921445 | E21: =E42/E29 -> 0.010282182 | F21: =F42/F29 -> #REF! | G21: =G42/G29 -> 0.036576677
A22: Liquid Assets/Total Assets | C22: =C40/C29 -> 0.067680721 | D22: =D40/D29 -> 0.12936886 | E22: =E40/E29 -> 0.15742859 | F22: =F40/F29 -> #REF! | G22: =G40/G29 -> 0.11724056
A23: E. STRUCTURE/SENSITIVITY TO RISK
A24: Gross loans /Total Assets | B24: 70-80 | C24: =C32/C29 -> 0.82800207 | D24: =D32/D29 -> 0.86523081 | E24: =E32/E29 -> 0.83846194 | F24: =F32/F29 -> #REF! | G24: =G32/G29 -> 0.75523899
A25: Gross loans/Deposits | B25: >100% | C25: =C32/C31 -> 1.1218567 | D25: =D32/D31 -> 1.1431784 | E25: =E32/E31 -> 1.1364592 | F25: =F32/F31 -> #REF! | G25: =G32/G31 -> 1.1023021
A26: Financial Investments/Total Assets | C26: =C39/C31 -> 0.11977917 | D26: =D39/D31 -> 0.007972688 | E26: =E39/E31 -> 0.0078282924 | F26: =F39/F31 -> #REF! | G26: =G39/G31 -> 0.067272667
A27: Dividends+Interest on Deposits/Total Income | C27: =C46/C44 -> 0.48412627 | D27: =D46/D44 -> 0.012481243 | E27: =E46/E44 -> 0.0115585 | F27: =F46/F44 -> #REF! | G27: =G46/G44 -> 0.33833569
A28: F. KEY FINANCIAL STATISTICS | C28: 2015 | D28: 2016 | E28: 2017 | G28: AGGREGATE
A29: Total Assets | C29: 659596375 | D29: 7.0075991e+08 | E29: 7.321422e+08 | F29: ='SFP-2022'!#REF! -> #REF! | G29: 5.8547109e+11
A30: Average Assets | C30: 6.2488266e+08 | D30: 6.6920187e+08 | E30: 6.9562445e+08 | F30: =(C29+F29)/2 -> #REF! | G30: 5.6966122e+11
A31: Total Deposits | C31: 486824375 | D31: 5.3038009e+08 | E31: 5.4016313e+08 | F31: ='SFP-2022'!#REF! -> #REF! | G31: 4.0113376e+11
A32: Gross Loans | C32: 546147164 | D32: 6.0631906e+08 | E32: 6.1387337e+08 | F32: ='SFP-2022'!#REF! -> #REF! | G32: 4.421706e+11
A33: Core Capital | C33: 98409139 | D33: 1.5398554e+08 | E33: 1.7565742e+08 | F33: =Financials!#REF! -> #REF! | G33: 9.281382e+10
A34: Institutional Capital | C34: 72604536 | D34: 1.2666911e+08 | E34: 1.4792069e+08 | F34: =Financials!#REF! -> #REF! | G34: 5.4377982e+10
A35: Non-performing Loans | C35: 0 | D35: 40504912 | E35: 36015340 | F35: =16172116+14580201+5263023 -> 36015340 | G35: 3.6223993e+10
A36: Non-Earning Assets | C36: 27347312 | D36: 24179556 | E36: 23042909 | F36: =Financials!#REF! -> #REF! | G36: 6.0490663e+10
A37: Property and Equipment | C37: 5678927 | D37: 5703357.5 | E37: 5726554 | F37: =Financials!#REF! -> #REF! | G37: 1.7300265e+10
A38: Equity Investments | C38: 4228556 | D38: 4228554.9 | E38: 4228554.9 | F38: ='SFP-2022'!#REF!+'SFP-2022'!#REF! -> #REF! | G38: 1.3596086e+10
A39: Financial Investments | C39: 58311419 | D39: 4228554.9 | E39: 4228554.9 | F39: ='SFP-2022'!#REF! -> #REF! | G39: 2.6985337e+10
A40: Liquid Assets | C40: 44641958 | D40: 90656514 | E40: 1.1526011e+08 | F40: ='SFP-2022'!#REF!+'SFP-2022'!#REF! -> #REF! | G40: 6.8640959e+10
A41: Short-term Liabilities) | C41: 75264054 | D41: 63940921 | E41: 57610665 | F41: ='SFP-2022'!#REF!+'SFP-2022'!#REF!+'SFP-2022'!#REF!-'SFP-2022'!#REF! -> #REF! | G41: 1.1159213e+11
A42: External Borrowing | C42: 7659 | D42: 8354071 | E42: 7528019 | F42: ='SFP-2022'!#REF! -> #REF! | G42: 2.1414587e+10
A43: Average Gross Loans | C43: 5.1241266e+08 | D43: 5.768587e+08 | E43: 5.7996732e+08 | F43: =(C32+E32)/2 -> 5.8001027e+08 | G43: 4.3131225e+11
A44: Total Income | C44: 119501967 | D44: 93225263 | E44: 1.2531687e+08 | F44: ='SCI-2022'!#REF! -> #REF! | G44: 8.9459919e+10
A45: Net Financial Income/Loss | C45: 60865365 | D45: 88921235 | E45: 1.1943317e+08 | F45: ='SCI-2022'!#REF! -> #REF! | G45: 5.3897612e+10
A46: Dividends+Interest on Deposits | C46: 57854041 | D46: 1163567.2 | E46: 1448475.1 | F46: ='SCI-2022'!#REF! -> #REF! | G46: 3.0267483e+10
A47: Operating Expenses | C47: 38435174 | D47: 26524472 | E47: 35585335 | F47: ='SCI-2022'!#REF! -> #REF! | G47: 2.6909398e+10
A48: Interest on Loan portfolio+Fees&Commission on Loan | C48: 100667063 | D48: 78338482 | E48: 1.0671211e+08 | F48: ='SCI-2022'!#REF!+'SCI-2022'!#REF! -> #REF! | G48: 7.7131665e+10
A49: Total Expenses | C49: 97071776 | D49: 30828500 | E49: 41469037 | F49: ='SCI-2022'!#REF!+'SCI-2022'!#REF!+'SCI-2022'!#REF! -> #REF! | G49: 6.2567213e+10
A50: Net Income | C50: 13984730 | D50: 54624460 | E50: 76272050 | F50: ='SCI-2022'!#REF! -> #REF! | G50: 2.1880939e+10
A51: G. AREAS OF IMPROVEMENT/REGULATORY CONCERNS
A52: 1
A53: 2
A54: 3
A55: 4
A56: Prepared by:
A58: Checked by:
A60: Approved by:
A62: DISCLAIMER: This report is prepared based on information submitted by the Sacco as at the stated date and may change upon verification by the Authority.

Sheet DEC 2019 REPORT
A1: EGERTON SACCO SOCIETY LIMITED
A2: PERFORMANCE AND COMPLIANCE REPORT AS AT : 31st December , 2019
B3: Prudential Standard | C3: Audited | D3: Returns | F3: Audited 2019 | G3: Aggregate for all Licensed Saccos
C4: 2018 | D4: 30th September , 2019 | E4: 31st December , 2019
A5: A. CAPITAL ADEQUACY
A6: Core Capital | B6: ≥10M | C6: 92958252 | D6: 1.14416e+08 | E6: 1.2704881e+08 | F6: =F33 -> #REF! | G6: 8.5391581e+10
A7: Core Capital/Total Assets | B7: ≥10% | C7: 0.15751126 | D7: 0.17943559 | E7: 0.19275909 | F7: =F6/F29 -> #REF! | G7: 0.15597716
A8: Institutional Capital/Total Assets | B8: ≥8% | C8: 0.11818998 | D8: 0.13976271 | E8: 0.15360974 | F8: =F34/F29 -> #REF! | G8: 0.091529477
A9: B. ASSET QUALITY
A10: NPL (Substandard+Doubtful+Loss) | B10: <5% | C10: 0 | D10: 0.057997794 | E10: 0.049062417 | F10: =F35/F32 -> #REF! | G10: 0.073407957
A11: Non-Earning Assets | B11: <10% | C11: 0.05336904 | D11: 0.043135899 | E11: 0.041315651 | F11: =F36/F29 -> #REF! | G11: 0.10567687
A12: Equity investments/Deposits | B12: <5% | C12: 0 | D12: 0.0086297878 | E12: 0.0086830722 | F12: =F38/F31 -> #REF! | G12: 0.034924323
A13: Equity investments/Core capital | B13: <40% | C13: 0 | D13: 0.036957724 | E13: 0.033282917 | F13: =F38/F33 -> #REF! | G13: 0.15379721
A14: C. EARNINGS RATING
A15: Yield on Gross Loans | C15: 0.1927038 | D15: 0.13877868 | E15: 0.18737466 | F15: =F48/F32 -> #REF! | G15: 0.16090341
A16: Total Expense/Total Income | C16: 0.79311986 | D16: 0.35836605 | E16: 0.33974951 | F16: =F49/F44 -> #REF! | G16: 0.7077997
A17: Net Income/Average Assets (ROA) | C17: 0.027977038 | D17: 0.081818348 | E17: 0.11400955 | F17: =F50/F30 -> #REF! | G17: 0.036975972
A18: Operating Expenses/Financial Income (OPEX) | C18: 0.30200757 | D18: 0.31934513 | E18: 0.30463818 | F18: =F47/F45 -> #REF! | G18: 0.31992697
A19: D. LIQUIDITY
A20: Liquid Assets/Short-term Liabilities | B20: >15% | C20: 1.1755674 | D20: 1.0116662 | E20: 1.4570234 | F20: =F40/F41 -> #REF! | G20: 0.54995224
A21: External Borrowing/Total Assets | B21: <25% | C21: 0 | D21: 0 | E21: 0 | F21: =F42/F29 -> #REF! | G21: 0.039238045
A22: Liquid Assets/Total Assets | C22: 0.14737887 | D22: 0.12043218 | E22: 0.149349 | F22: =F40/F29 -> #REF! | G22: 0.11016896
A23: E. STRUCTURE/SENSITIVITY TO RISK
A24: Gross loans /Total Assets | B24: 70-80 | C24: 0.81108665 | D24: 0.85847035 | E24: 0.82848691 | F24: =F32/F29 -> #REF! | G24: 0.75892188
A25: Gross loans/Deposits | B25: >100% | C25: 1.1046878 | D25: 1.1171503 | E25: 1.1213025 | F25: =F32/F31 -> #REF! | G25: 1.1048812
A26: Financial Investments/Total Assets | C26: 0.0097586092 | D26: 0.0086297878 | E26: 0.0086830722 | F26: =F39/F29 -> #REF! | G26: 0.059782935
A27: Dividends+Interest on Deposits/Total Income | C27: 0.48814819 | D27: 0.012035001 | E27: 0.012230217 | F27: =F46/F44 -> #REF! | G27: 0.32108527
A28: F. KEY FINANCIAL STATISTICS | C28: 2015 | D28: 2016 | E28: 2017 | G28: AGGREGATE
A29: Total Assets | C29: 590168948 | D29: 6.3764384e+08 | E29: 6.5910669e+08 | F29: ='SFP-2022'!#REF! -> #REF! | G29: 5.4746207e+11
A30: Average Assets | C30: 5.6413338e+08 | D30: 6.1492399e+08 | E30: 6.4176168e+08 | F30: =(F29+C29)/2 -> #REF! | G30: 5.2079291e+11
A31: Total Deposits | C31: 433315333 | D31: 4.8999524e+08 | E31: 4.8698834e+08 | F31: ='SFP-2022'!#REF! -> #REF! | G31: 3.7604128e+11
A32: Gross Loans | C32: 478678153 | D32: 5.4739833e+08 | E32: 5.4606127e+08 | F32: ='SFP-2022'!#REF! -> #REF! | G32: 4.1548094e+11
A33: Core Capital | C33: 92958252 | D33: 1.14416e+08 | E33: 1.2704881e+08 | F33: =Financials!#REF! -> #REF! | G33: 8.5391581e+10
A34: Institutional Capital | C34: 69752057 | D34: 89118833 | E34: 1.0124521e+08 | F34: =Financials!#REF! -> #REF! | G34: 5.0108917e+10
A35: Non-performing Loans | C35: 0 | D35: 31747895 | E35: 26791086 | F35: =22604726+734025+3452334 -> 26791085 | G35: 3.0499607e+10
A36: Non-Earning Assets | C36: 31496750 | D36: 27505341 | E36: 27231422 | F36: =Financials!#REF! -> #REF! | G36: 5.7854076e+10
A37: Property and Equipment | C37: 7005759 | D37: 5982262.2 | E37: 5325780.8 | F37: =Financials!#REF! -> #REF! | G37: 1.7751024e+10
A38: Equity Investments | C38: 0 | D38: 4228554.9 | E38: 4228554.9 | F38: ='SFP-2022'!#REF!+'SFP-2022'!#REF! -> #REF! | G38: 1.3132987e+10
A39: Financial Investments | C39: 4228555 | D39: 4228554.9 | E39: 4228554.9 | F39: ='SFP-2022'!#REF! -> #REF! | G39: 2.2480852e+10
A40: Liquid Assets | C40: 86978434 | D40: 76792836 | E40: 98436927 | F40: ='SFP-2022'!#REF! -> #REF! | G40: 6.031333e+10
A41: Short-term Liabilities) | C41: 73988469 | D41: 75907286 | E41: 67560292 | F41: ='SFP-2022'!#REF!+'SFP-2022'!#REF!+'SFP-2022'!#REF!-'SFP-2022'!#REF! -> #REF! | G41: 1.0967012e+11
A42: External Borrowing | C42: 0 | D42: 0 | E42: 0 | F42: ='SFP-2022'!#REF! -> #REF! | G42: 2.1481341e+10
A43: Average Gross Loans | C43: 445483841 | D43: 5.0462708e+08 | E43: 5.1208838e+08 | F43: =(C32+F32)/2 -> #REF! | G43: 3.9339201e+11
A44: Total Income | C44: 110748089 | D44: 89428467 | E44: 1.1935697e+08 | F44: ='SCI-2022'!#REF! -> #REF! | G44: 7.9322865e+10
A45: Net Financial Income/Loss | C45: 56358341 | D45: 85938886 | E45: 1.1516619e+08 | F45: ='SCI-2022'!#REF! -> #REF! | G45: 4.6800236e+10
A46: Dividends+Interest on Deposits | C46: 54061479 | D46: 1076271.7 | E46: 1459761.6 | F46: ='SCI-2022'!#REF! -> #REF! | G46: 2.5469404e+10
A47: Operating Expenses | C47: 33446761 | D47: 28558545 | E47: 36360690 | F47: ='SCI-2022'!#REF! -> #REF! | G47: 2.5377524e+10
A48: Interest on Loan portfolio+Fees&Commission on Loan | C48: 92243098 | D48: 75967218 | E48: 1.0231804e+08 | F48: ='SCI-2022'!#REF! -> #REF! | G48: 6.6852299e+10
A49: Total Expenses | C49: 87836509 | D49: 32048126 | E49: 40551471 | F49: ='SCI-2022'!#REF!+'SCI-2022'!#REF! -> #REF! | G49: 5.61447e+10
A50: Net Income | C50: 15782781 | D50: 50312065 | E50: 73166962 | F50: ='SCI-2022'!#REF! -> #REF! | G50: 1.9256824e+10
A51: G. AREAS OF IMPROVEMENT/REGULATORY CONCERNS
A52: 1
A53: 2
A54: 3
A55: 4
A56: Prepared by:
A58: Checked by: Nelly Kulei
A60: Approved by: Peter Owira
A62: DISCLAIMER: This report is prepared based on information submitted by the Sacco as at the stated date and may change upon verification by the Authority.
C63: 22nd January 2020
