Workbook
Name BALANCE1_LDA01: '[1]Financial Statements'!$E$112
Name BALANCE1_LDA12: '[1]Financial Statements'!$E$123
Name BALANCE2_LDA01: '[1]Financial Statements'!$F$112
Name BALANCE2_LDA12: '[1]Financial Statements'!$F$123
Name BALANCE3_LDA01: '[1]Financial Statements'!$G$112
Name BALANCE3_LDA12: '[1]Financial Statements'!$G$123
Name BALANCE4_LDA01: '[1]Financial Statements'!$H$112
Name BALANCE4_LDA12: '[1]Financial Statements'!$H$123
Name BALANCE5_LDA01: '[1]Financial Statements'!$I$112
Name BALANCE5_LDA12: '[1]Financial Statements'!$I$123
Name BALANCE6_LDA01: '[1]Financial Statements'!$J$112
Name BALANCE6_LDA12: '[1]Financial Statements'!$J$123
Name PEARLS1_LA002: '[1]Financial Statements'!$E$280
Name PEARLS1_LE008: '[1]Financial Statements'!$E$275
Name PEARLS1_LE009: '[1]Financial Statements'!$E$276
Name PEARLS1_LR001: '[1]Financial Statements'!$E$282
Name PEARLS1_LR005: '[1]Financial Statements'!$E$286
Name PEARLS1_LR006: '[1]Financial Statements'!$E$287
Name PEARLS1_LR007: '[1]Financial Statements'!$E$288
Name PEARLS1_LR009: '[1]Financial Statements'!$E$290
Name PEARLS1_LS001: '[1]Financial Statements'!$E$298
Name PEARLS1_LS005: '[1]Financial Statements'!$E$302
Name PEARLS1_LS011: '[1]Financial Statements'!$E$308
Name PEARLS2_LA002: '[1]Financial Statements'!$F$280
Name PEARLS2_LE008: '[1]Financial Statements'!$F$275
Name PEARLS2_LE009: '[1]Financial Statements'!$F$276
Name PEARLS2_LR001: '[1]Financial Statements'!$F$282
Name PEARLS2_LR005: '[1]Financial Statements'!$F$286
Name PEARLS2_LR006: '[1]Financial Statements'!$F$287
Name PEARLS2_LR007: '[1]Financial Statements'!$F$288
Name PEARLS2_LR009: '[1]Financial Statements'!$F$290
Name PEARLS2_LS001: '[1]Financial Statements'!$F$298
Name PEARLS2_LS005: '[1]Financial Statements'!$F$302
Name PEARLS2_LS010: '[1]Financial Statements'!$F$307
Name PEARLS2_LS011: '[1]Financial Statements'!$F$308
Name PEARLS3_LA002: '[1]Financial Statements'!$G$280
Name PEARLS3_LE008: '[1]Financial Statements'!$G$275
Name PEARLS3_LE009: '[1]Financial Statements'!$G$276
Name PEARLS3_LR001: '[1]Financial Statements'!$G$282
Name PEARLS3_LR005: '[1]Financial Statements'!$G$286
Name PEARLS3_LR006: '[1]Financial Statements'!$G$287
Name PEARLS3_LR007: '[1]Financial Statements'!$G$288
Name PEARLS3_LR009: '[1]Financial Statements'!$G$290
Name PEARLS3_LS001: '[1]Financial Statements'!$G$298
Name PEARLS3_LS005: '[1]Financial Statements'!$G$302
Name PEARLS3_LS010: '[1]Financial Statements'!$G$307
Name PEARLS3_LS011: '[1]Financial Statements'!$G$308
Name PEARLS4_LA002: '[1]Financial Statements'!$H$280
Name PEARLS4_LE008: '[1]Financial Statements'!$H$275
Name PEARLS4_LE009: '[1]Financial Statements'!$H$276
Name PEARLS4_LR001: '[1]Financial Statements'!$H$282
Name PEARLS4_LR005: '[1]Financial Statements'!$H$286
Name PEARLS4_LR006: '[1]Financial Statements'!$H$287
Name PEARLS4_LR007: '[1]Financial Statements'!$H$288
Name PEARLS4_LR009: '[1]Financial Statements'!$H$290
Name PEARLS4_LS001: '[1]Financial Statements'!$H$298
Name PEARLS4_LS005: '[1]Financial Statements'!$H$302
Name PEARLS4_LS010: '[1]Financial Statements'!$H$307
Name PEARLS4_LS011: '[1]Financial Statements'!$H$308
Name PEARLS5_LA002: '[1]Financial Statements'!$I$280

Sheet Evolutive SFP
B3: AUDITED 2007 | C3: AUDITED 2008 | D3: AUDITED 2009 | E3: AUDITED 2010 | F3: AUDITED 2011 | G3: AUDITED 2012 | H3: AUDITED 2013 | I3: AUDITED 2014 | J3: 42005 | K3: 42036 | L3: 42064 | M3: 42095 | N3: 42125 | O3: 42156 | P3: 42186 | Q3: 42217 | R3: 42248 | S3: 42278 | T3: 42309 | U3: 42339 | V3: AUDITED 2015 | W3: 42370 | X3: 42401 | Y3: 42430 | Z3: 42461 | AA3: 42491 | AB3: 42522 | AC3: 42552 | AD3: 42583 | AE3: 42614 | AF3: 42644 | AG3: 42675 | AH3: 42705 | AI3: AUDITED 2016 | AJ3: 42736 | AK3: 42767 | AL3: 42795 | AM3: 42826 | AN3: 42856 | AO3: 42887 | AP3: 42917 | AQ3: 42948 | AR3: 42979 | AS3: 43009 | AT3: 43040 | AU3: 43070 | AV3: AUDITED 2017 | AW3: 43101 | AX3: 43132 | AY3: 43160 | AZ3: 43191 | BA3: 43221 | BB3: 43252 | BC3: 43282 | BD3: 43313 | BE3: 43344 | BF3: 43374 | BG3: 43405 | BH3: 43435 | BI3: AUDITED 2018 | BJ3: 43466 | BK3: 43497 | BL3: 43525 | BM3: 43556 | BN3: 43586 | BO3: 43617 | BP3: 43647 | BQ3: 43678 | BR3: 43709 | BS3: 43739 | BT3: 43770 | BU3: 43800 | BV3: AUDITED 2019 | BW3: 43831 | BX3: 43862 | BY3: 43891 | BZ3: 43922 | CA3: 43952 | CB3: 43983 | CC3: 44044 | CD3: 44075 | CE3: 44105 | CF3: 44136 | CG3: 44166 | CH3: Audited 2020 | CI3: 44197 | CJ3: 44228 | CK3: 44256 | CL3: 44287 | CM3: 44317 | CN3: 44348 | CO3: 44378 | CP3: 44409 | CQ3: 44440 | CR3: 44470 | CS3: 44501 | CT3: 44531 | CU3: AUDITED 2021 | CV3: AUDITED 2022 | CW3: 44927 | CX3: 44958 | CY3: 44986 | CZ3: 45017 | DA3: 45047 | DB3: 45078 | DC3: 45108 | DD3: 45139 | DE3: 45170
A4: Cash & cash Equivalent | B4: =(B5+B6) -> 9072837 | C4: =(C5+C6) -> 9652154 | D4: =(D5+D6) -> 11606332 | E4: =(E5+E6) -> 11999140 | F4: =(F5+F6) -> 11850442 | G4: =(G5+G6) -> 2.0963163e+08 | H4: =(H5+H6) -> 14295816 | I4: =(I5+I6) -> 93164187 | ... DE4: =(DE5+DE6) -> 2.0526233e+08
A5: Cash In Hand | B5: 2129508 | C5: 9652154 | D5: 11606332 | E5: 11999140 | F5: 11850442 | G5: 2.0963163e+08 | H5: =18750+39802 -> 58552 | I5: =1239424+9246254+36226+2337631+18452 -> 12877987 | J5: 3073882.1 | K5: 4646176.1 | L5: 2338283.1 | M5: 5020582.1 | N5: 3075818.1 | O5: 3258057.1 | P5: 866181.09 | Q5: 6631522.4 | R5: 3738090.8 | S5: 3782067.5 | T5: 4504077.8 | U5: 7426930.3 | V5: =9880+4051665 -> 4061545 | W5: 7907096.3 | X5: 9369994.3 | Y5: 9133012.3 | Z5: 7563564.3 | AA5: 9330171 | AB5: 21218903 | AC5: 14724428 | AD5: 10521856 | AE5: 14358579 | AF5: 10445879 | AG5: 8877148.4 | AH5: 5635660.2 | AI5: =10476+950850+1314529+955069 -> 3230924 | AJ5: 8133853.2 | AK5: 10776231 | AL5: 6887292.2 | AM5: 6554107 | AN5: 19436134 | AO5: 13185120 | AP5: 7499782.4 | AQ5: 9338495.4 | AR5: 7490234.6 | AS5: 10637681 | AT5: 8842445.9 | AU5: 8198740.8 | AV5: =3626919+2353+1065239+721786 -> 5416297 | AW5: 6861473.8 | AX5: 8049032.8 | AY5: 9808796.2 | AZ5: 9879877.2 | BA5: 22777270 | BB5: 7115197.2 | BC5: 10666300 | BD5: 9414093.5 | BE5: 7443120 | BF5: 9473993.8 | BG5: 14227305 | BH5: 9952482.6 | BI5: 3821043.6 | BJ5: 7753825.1 | BK5: 10373715 | BL5: 5788558.4 | BM5: 6894236.7 | BN5: 6137764 | BO5: 7940988.4 | BP5: 15061291 | BQ5: 8022872.6 | BR5: 8284175.1 | BS5: 7927205.1 | BT5: 9407027.5 | BU5: 7816909.2 | BV5: 5025922 | BW5: 8896704.1 | BX5: 8250773.4 | BY5: 6994773.8 | BZ5: 10231233 | CA5: 12925229 | CB5: 6039112.7 | CC5: 9491651.7 | CD5: 10354059 | CE5: 11543880 | CF5: 5854286 | CG5: 13064694 | CH5: 11627268 | CI5: 7344350.2 | CJ5: 6615362.3 | CK5: 7730487.1 | CL5: 11107950 | CM5: 13547426 | CN5: 10595249 | CO5: 11012328 | CP5: 6650639.6 | CQ5: 8883353.9 | CR5: 7896906.6 | CS5: 9786459.9 | CT5: 11604850 | CU5: =233362462-CU6 -> 11604851 | CV5: 0 | CW5: 18520446 | CX5: 13683271 | CY5: 15124040 | CZ5: 25630525 | DA5: 19899522 | DB5: 29281101 | DC5: 21504524 | DD5: 25489447 | DE5: 20865878
A6: Cash at Bank | B6: 6943329 | H6: =114295816-100000000-H5 -> 14237264 | I6: =93164187-12877987 -> 80286200 | J6: 94044947 | K6: 89952488 | L6: 93617578 | M6: 88592744 | N6: 87210682 | O6: 1.5175587e+08 | P6: 1.3057663e+08 | Q6: 1.064813e+08 | R6: 1.0785348e+08 | S6: 97690580 | T6: 71671948 | U6: 74669409 | V6: =69012969-V5 -> 64951424 | W6: 69041046 | X6: 64102302 | Y6: 47512557 | Z6: 44524367 | AA6: 42147811 | AB6: 157295064 | AC6: 1.3177994e+08 | AD6: 108049675 | AE6: 71957443 | AF6: 66846945 | AG6: 59581214 | AH6: 69687916 | AI6: =75323576-AI5 -> 72092652 | AJ6: 64161534 | AK6: 65942847 | AL6: 78192077 | AM6: 76257474 | AN6: 2.0021383e+08 | AO6: 1.5814187e+08 | AP6: 1.3179803e+08 | AQ6: 1.0797819e+08 | AR6: 99553409 | AS6: 89316298 | AT6: 81529537 | AU6: 82079655 | AV6: =90278396-5416297 -> 84862099 | AW6: 84985628 | AX6: 82808160 | AY6: 83744832 | AZ6: 76134736 | BA6: 1.7227249e+08 | BB6: 1.4301726e+08 | BC6: 1.1049705e+08 | BD6: 87185064 | BE6: 83103410 | BF6: 79858547 | BG6: 68602626 | BH6: 62214296 | BI6: 68345735 | BJ6: 77589941 | BK6: 53508070 | BL6: 51550108 | BM6: 45306980 | BN6: 43178937 | BO6: 49939682 | BP6: 1.4788614e+08 | BQ6: 1.3628562e+08 | BR6: 82582777 | BS6: 55983230 | BT6: 29984061 | BU6: 15966365 | BV6: =11371837.65+1294570.79+3299956.75+6187+795862.68+524195+688497.5+112815+150740+104785+78911+150000+178994 -> 18757352 | BW6: 20916391 | BX6: 22744819 | BY6: 25338049 | BZ6: 1.210785e+08 | CA6: 79666095 | CB6: 1.7889953e+08 | CC6: 73236977 | CD6: 2.153357e+08 | CE6: 87471702 | CF6: 24703877 | CG6: 30758136 | CH6: =43822830-11627268 -> 32195562 | CI6: 11483467 | CJ6: 32987253 | CK6: 42686986 | CL6: 58001777 | CM6: 50242431 | CN6: 45609153 | CO6: 51401396 | CP6: 42512510 | CQ6: 2.0487868e+08 | CR6: 3.1465648e+08 | CS6: 2.1673047e+08 | CT6: 2.0587439e+08 | CU6: =38177946+43996018+13700430+125883217 -> 221757611 | CV6: =18997845+484619+793570+10902544+1592223+71171+320190+5500+542803+300000+211749+160790+130314072+215461 -> 164912537 | CW6: 1.2725124e+08 | CX6: 1.2636003e+08 | CY6: 1.3271081e+08 | CZ6: 1.2701929e+08 | DA6: 1.1855572e+08 | DB6: 1.3535299e+08 | DC6: 2.8111174e+08 | DD6: 2.1120252e+08 | DE6: 1.8439645e+08
A7: Prepayment and Sundry | B7: =241235 -> 241235 | C7: 210238 | D7: 23363689 | E7: 21063691 | F7: 5577314 | G7: 1759918.6 | H7: 3482697 | I7: 7204334 | J7: 1310705 | K7: 2948933.1 | L7: 1441059.8 | M7: 1515755.8 | N7: 1717323 | O7: 28325030 | P7: 1214917 | Q7: 2035161 | R7: 1845830 | S7: 1409415.1 | T7: 1409415.1 | U7: 8752386 | V7: 24942726 | W7: 8213164.8 | X7: 6948220.4 | Y7: 23754253 | Z7: 18463213 | AA7: 21294198 | AB7: 13657950 | AC7: 13059154 | AD7: 12975869 | AE7: 23189672 | AF7: 22568136 | AG7: 23276423 | AH7: 5557216.8 | AI7: 5557217 | AJ7: 6689660 | AK7: 5850693 | AL7: 4823659.3 | AM7: 5733891.9 | AN7: 7700206.2 | AO7: 3904046.1 | AP7: 4095944.8 | AQ7: 6431976.1 | AR7: 2797303.2 | AS7: 3021493 | AT7: 3036333.1 | AU7: 2939722.3 | AV7: 3775087 | AW7: 4245869.5 | AX7: 4736502.8 | AY7: 4918009.9 | AZ7: 4748069.7 | BA7: 44583187 | BB7: =4045872.94+40000000 -> 44045873 | BC7: 33617176 | BD7: 23611042 | BE7: 15036260 | BF7: 15005012 | BG7: 5173387.5 | BH7: 6971773.9 | BI7: 6787025 | BJ7: 6739591.5 | BK7: 5064049.1 | BL7: 5241965.7 | BM7: 5172855.6 | BN7: 5064954.5 | BO7: 5957568.9 | BP7: 7292830.4 | BQ7: 8245290 | BR7: 9035168.2 | BS7: 9082646.4 | BT7: 9246945.2 | BU7: 12284230 | BW7: 12178438 | BX7: 10565509 | BY7: 10447542 | BZ7: 11809242 | CA7: 12059778 | CB7: 11951870 | CC7: 12889324 | CD7: 13074393 | CE7: 15885199 | CF7: 14929667 | CG7: 17415014 | CH7: 17053152 | CI7: 17668646 | CJ7: 17150062 | CK7: 17074630 | CL7: 18363109 | CM7: 18165302 | CN7: 18431218 | CO7: 19189432 | CP7: 18420830 | CQ7: 19626455 | CR7: 20512573 | CS7: 19943223 | CT7: 22171337 | CU7: 5979284 | CV7: 5029726 | CW7: 5070360 | CX7: 5080039.2 | CY7: 4750756.3 | CZ7: 4660863.5 | DA7: 3770981.9 | DB7: 4248424.8 | DC7: 3818805.4 | DD7: 5167046.8 | DE7: 5394188
A8: Financial Investment | B8: =(B9+B10+B11+B13+B12) -> 3099100 | C8: =(C9+C10+C11+C13+C12) -> 3153280 | D8: =(D9+D10+D11+D13+D12) -> 3153280 | E8: =(E9+E10+E11+E13+E12) -> 3187680 | F8: =(F9+F10+F11+F13+F12) -> 3213000 | G8: =(G9+G10+G11+G13+G12) -> 3837498 | H8: =(H9+H10+H11+H13+H12) -> 109136598 | I8: =(I9+I10+I11+I13+I12) -> 13336598 | ... CP8: =(CP9+CP10+CP11+CP13+CP12) -> 16940857 | CQ8: =(CQ9+CQ10+CQ11+CQ12+CQ13) -> 16940857 | CR8: =(CR9+CR10+CR11+CR12+CR13) -> 16940857 | CS8: =(CS9+CS10+CS11+CS12+CS13) -> 16940857 | CT8: =(CT9+CT10+CT11+CT12+CT13) -> 16940857 | CU8: =(CU9+CU10+CU11+CU12+CU13) -> 16940857 | CV8: =(CV9+CV10+CV11+CV12+CV13) -> 49524309 | CW8: =(CW9+CW10+CW11+CW12+CW13) -> 49524309 | CX8: =(CX9+CX10+CX11+CX12+CX13) -> 49524309 | ... DE8: =(DE9+DE10+DE11+DE12+DE13) -> 49524309
A9: Government Security | J9: 0 | K9: 0 | L9: 0 | M9: 0 | N9: 0 | O9: 0 | P9: 0 | Q9: 0 | R9: 0 | S9: 0 | T9: 0 | U9: 0 | W9: 0 | X9: 0 | Y9: 0 | Z9: 0 | AA9: 0 | AB9: 0 | AC9: 0 | AD9: 0 | AE9: 0 | AF9: 0 | AG9: 0 | AH9: 0 | AI9: 0 | AJ9: 0 | AK9: 0 | AL9: 0 | AM9: 0 | AN9: 0 | AO9: 0 | AP9: 0 | AQ9: 0 | AR9: 0 | AS9: 0 | AT9: 0 | AU9: 0 | AV9: 0 | AW9: 0 | AX9: 0 | AY9: 0 | AZ9: 0 | BA9: 0 | BB9: 0 | BC9: 0 | BD9: 0 | BE9: 0 | BF9: 0 | BG9: 0 | BH9: 0 | BJ9: 0 | BK9: 0 | BL9: 0 | BM9: 0 | BN9: 0 | BO9: 0 | BP9: 0 | BQ9: 0 | BR9: 0 | BS9: 0 | BT9: 0 | BU9: 0 | BW9: 0 | BX9: 0 | BY9: 0 | BZ9: 0 | CA9: 0 | CB9: 0 | CC9: 0 | CD9: 0 | CE9: 0 | CF9: 0 | CG9: 0 | CI9: 0 | CJ9: 0 | CK9: 0 | CL9: 0 | CM9: 0 | CN9: 0 | CO9: 0 | CP9: 0 | CQ9: 0 | CR9: 0 | CS9: 0 | CT9: 0 | CW9: 0 | CX9: 0 | CY9: 0 | CZ9: 0 | DA9: 0 | DB9: 0 | DC9: 0 | DD9: 0 | DE9: 0
A10: Other Securities | J10: 0 | K10: 0 | L10: 0 | M10: 0 | N10: 0 | O10: 0 | P10: 0 | Q10: 0 | R10: 0 | S10: 0 | T10: 0 | U10: 0 | W10: 0 | X10: 0 | Y10: 0 | Z10: 0 | AA10: 0 | AB10: 0 | AC10: 0 | AD10: 0 | AE10: 0 | AF10: 0 | AG10: 0 | AH10: 0 | AI10: 0 | AJ10: 0 | AK10: 0 | AL10: 0 | AM10: 0 | AN10: 0 | AO10: 0 | AP10: 0 | AQ10: 0 | AR10: 0 | AS10: 0 | AT10: 0 | AU10: 0 | AV10: 0 | AW10: 0 | AX10: 0 | AY10: 0 | AZ10: 0 | BA10: 0 | BB10: 0 | BC10: 0 | BD10: 0 | BE10: 0 | BF10: 0 | BG10: 0 | BH10: 0 | BJ10: 0 | BK10: 0 | BL10: 0 | BM10: 0 | BN10: 0 | BO10: 0 | BP10: 0 | BQ10: 0 | BR10: 0 | BS10: 0 | BT10: 0 | BU10: 0 | BW10: 0 | BX10: 0 | BY10: 0 | BZ10: 0 | CA10: 0 | CB10: 0 | CC10: 0 | CD10: 0 | CE10: 0 | CF10: 0 | CG10: 0 | CI10: 0 | CJ10: 0 | CK10: 0 | CL10: 0 | CM10: 0 | CN10: 0 | CO10: 0 | CP10: 0 | CQ10: 0 | CR10: 0 | CS10: 0 | CT10: 0 | CW10: 0 | CX10: 0 | CY10: 0 | CZ10: 0 | DA10: 0 | DB10: 0 | DC10: 0 | DD10: 0 | DE10: 0
A11: Balances in NACCOS (E.g Jungu Kuu, ESS, Savings,Money Market,Coop FD, CFP) | J11: 0 | K11: 0 | L11: 0 | M11: 0 | N11: 0 | O11: 0 | P11: 0 | Q11: 0 | R11: 0 | S11: 0 | T11: 0 | U11: 0 | W11: 0 | X11: 0 | Y11: 0 | Z11: 0 | AA11: 0 | AB11: 0 | AC11: 0 | AD11: 0 | AE11: 0 | AF11: 0 | AG11: 0 | AH11: 0 | AI11: 13277355 | AJ11: 0 | AK11: 0 | AL11: 0 | AM11: 0 | AN11: 0 | AO11: 0 | AP11: 0 | AQ11: 0 | AR11: 0 | AS11: 0 | AT11: 0 | AU11: 0 | AV11: 14314587 | AW11: 0 | AX11: 0 | AY11: 0 | AZ11: 0 | BA11: 0 | BB11: 0 | BC11: 0 | BD11: 0 | BE11: 0 | BF11: 0 | BG11: 0 | BH11: 0 | BJ11: 0 | BK11: 0 | BL11: 0 | BM11: 0 | BN11: 0 | BO11: 0 | BP11: 0 | BQ11: 0 | BR11: 0 | BS11: 0 | BT11: 0 | BU11: 0 | BW11: 0 | BX11: 0 | BY11: 0 | BZ11: 0 | CA11: 0 | CB11: 0 | CC11: 0 | CD11: 0 | CE11: 0 | CF11: 0 | CG11: 0 | CI11: 0 | CJ11: 0 | CK11: 0 | CL11: 0 | CM11: 0 | CN11: 0 | CO11: 0 | CP11: 0 | CQ11: 0 | CR11: 0 | CS11: 0 | CT11: 0 | CW11: 0 | CX11: 0 | CY11: 0 | CZ11: 0 | DA11: 0 | DB11: 0 | DC11: 0 | DD11: 0 | DE11: 0
A12: Equity Investments in NACCOs(Shares in- CIC, KUSCCO, COOP BANK,CAK, KERUSSU) | G12: 3837498 | H12: =100000000+9136598 -> 109136598 | I12: 13336598 | J12: 4832498 | K12: 4832498 | L12: 4832498 | M12: 4832498 | N12: 4832498 | O12: 4832498 | P12: 12823062 | Q12: 12823062 | R12: 12823062 | S12: 13308498 | T12: 13199798 | U12: 13308498 | W12: 13308498 | X12: 13272498 | Y12: 13272498 | Z12: 13272498 | AA12: 13277355 | AB12: 13277355 | AC12: 13277355 | AD12: 13277355 | AE12: 13277355 | AF12: 13277355 | AG12: 13277355 | AH12: 13277355 | AJ12: 13277355 | AK12: 13277355 | AL12: 13277355 | AM12: 13277355 | AN12: 13277355 | AO12: 13277355 | AP12: 13277355 | AQ12: 13277355 | AR12: 14314587 | AS12: 14314587 | AT12: 14314587 | AU12: 14314587 | AW12: 14314587 | AX12: 14314587 | AY12: 14314587 | AZ12: 14314587 | BA12: 14314587 | BB12: 14314587 | BC12: 34314587 | BD12: 34314587 | BE12: 34314587 | BF12: 34314587 | BG12: 34314587 | BH12: 34314587 | BI12: 94611870 | BJ12: 14314587 | BK12: 34314587 | BL12: 34264587 | BM12: 34264587 | BN12: 34264587 | BO12: 34264587 | BP12: 84264587 | BQ12: 84264587 | BR12: 84264587 | BS12: 84264587 | BT12: 84264587 | BU12: 84264587 | BW12: 64264587 | BX12: 64264587 | BY12: 64264587 | BZ12: 64264587 | CA12: 66264027 | CB12: 116264027 | CC12: 116264027 | CD12: 116940857 | CE12: 116940857 | CF12: 116940857 | CG12: 66940857 | CH12: 50000000 | CI12: 66940857 | CJ12: 46940857 | CK12: 46940857 | CW12: 0 | CX12: 0 | CY12: 0 | CZ12: 0 | DA12: 0 | DB12: 0 | DC12: 0 | DD12: 0 | DE12: 0
A13: Equity Investments in companies - shares/stocks | B13: 3099100 | C13: 3153280 | D13: 3153280 | E13: 3187680 | F13: 3213000 | V13: 13272498 | BV13: 11722912 | CH13: =125044646-58103789-50000000 -> 16940857 | CL13: 46940857 | CM13: 46940857 | CN13: 46940857 | CO13: 16940857 | CP13: 16940857 | CQ13: 16940857 | CR13: 16940857 | CS13: 16940857 | CT13: 16940857 | CU13: =73992051-CU22 -> 16940857 | CV13: 49524309 | CW13: 49524309 | CX13: 49524309 | CY13: 49524309 | CZ13: 49524309 | DA13: 49524309 | DB13: 49524309 | DC13: 49524309 | DD13: 49524309 | DE13: 49524309
A14: Net Loan Portfolio | B14: =(B15-B16) -> 49447375 | C14: =(C15-C16) -> 55470816 | D14: =(D15-D16) -> 55516677 | E14: =(E15-E16) -> 60516357 | F14: =(F15-F16) -> 70473718 | G14: =(G15-G16) -> 4079328.1 | H14: =(H15-H16) -> 80748696 | I14: =(I15-I16) -> 102052227 | ... DE14: =(DE15-DE16) -> 3.500674e+08
A15: Gross Loan Portfolio | B15: 53169220 | C15: 63674472 | D15: 72197161 | E15: 78490493 | F15: 79987012 | G15: 4079328.1 | H15: 80748696 | I15: 105659865 | J15: 92638072 | K15: 94271916 | L15: 97321100 | M15: 99708968 | N15: 1.0078959e+08 | O15: 60774670 | P15: 86671810 | Q15: 1.0003238e+08 | R15: 1.0811192e+08 | S15: 1.1667158e+08 | T15: 1.2987107e+08 | U15: 1.3888909e+08 | V15: 143895127 | W15: 1.4112429e+08 | X15: 145038005 | Y15: 145426284 | Z15: 1.4936527e+08 | AA15: 151757044 | AB15: 106119121 | AC15: 1.3892526e+08 | AD15: 154196845 | AE15: 162998012 | AF15: 168301782 | AG15: 170676237 | AH15: 173376620 | AI15: 173376620 | AJ15: 174327576 | AK15: 1.743573e+08 | AL15: 1.7396032e+08 | AM15: 1.737757e+08 | AN15: 1.1295082e+08 | AO15: 1.3461454e+08 | AP15: 1.6351659e+08 | AQ15: 1.7347583e+08 | AR15: 1.78145e+08 | AS15: 1.8181614e+08 | AT15: 1.8819663e+08 | AU15: 1.8343272e+08 | AV15: 183432718 | AW15: 1.8108397e+08 | AX15: 1.7891374e+08 | AY15: 1.7666565e+08 | AZ15: 1.8635001e+08 | BA15: 1.2103648e+08 | BB15: 1.4111859e+08 | BC15: 1.6320818e+08 | BD15: 1.944307e+08 | BE15: 2.0149485e+08 | BF15: 2.0152659e+08 | BG15: 2.1205298e+08 | BH15: 2.1556213e+08 | BI15: 215562132 | BJ15: 2.2036328e+08 | BK15: 2.2340304e+08 | BL15: 2.2857003e+08 | BM15: 2.3008694e+08 | BN15: 2.315006e+08 | BO15: 2.3257777e+08 | BP15: 2.1043968e+08 | BQ15: 2.2136321e+08 | BR15: 2.391268e+08 | BS15: 2.5474266e+08 | BT15: 2.5828705e+08 | BU15: 2.5704619e+08 | BV15: 257046189 | BW15: 2.6187878e+08 | BX15: 2.6513021e+08 | BY15: 2.6075478e+08 | BZ15: 2.1748328e+08 | CA15: 2.3165045e+08 | CB15: 1.8150484e+08 | CC15: 2.4022561e+08 | CD15: 2.6760297e+08 | CE15: 2.9827748e+08 | CF15: 3.1687263e+08 | CG15: 3.2818425e+08 | CH15: 328184248 | CI15: 3.3973494e+08 | CJ15: 3.357611e+08 | CK15: 3.2659681e+08 | CL15: 3.1369754e+08 | CM15: 3.1465328e+08 | CN15: 3.2033375e+08 | CO15: 3.419853e+08 | CP15: 3.528156e+08 | CQ15: 3.5504548e+08 | CR15: 2.4331791e+08 | CS15: 2.8182567e+08 | CT15: 2.7083649e+08 | CU15: 270836485 | CV15: 366357901 | CW15: 3.7787302e+08 | CX15: 3.8334447e+08 | CY15: 3.817687e+08 | CZ15: 3.7576055e+08 | DA15: 3.865305e+08 | DB15: 3.7870679e+08 | DC15: 3.3029772e+08 | DD15: 3.728836e+08 | DE15: 391328588
A16: Allowance For Loan Loss | B16: 3721845 | C16: 8203656 | D16: 16680484 | E16: 17974136 | F16: 9513294 | I16: 3607638 | J16: 1525420.1 | K16: -2457614 | L16: -4710331.1 | M16: -6224922.3 | N16: -8270916.8 | O16: 1819986 | P16: -41795250 | Q16: 2667629.1 | R16: -77564797 | S16: 3193905.9 | T16: 3338256.9 | U16: 3736596.3 | V16: 7344235 | W16: 5311572.9 | X16: 5067241 | Y16: 5028488.4 | Z16: 6090124.9 | AA16: 7701680 | AB16: 7227703 | AC16: 7948965.7 | AD16: 8700631 | AE16: 9887556 | AF16: 11305305 | AG16: 12212990 | AH16: 13505608 | AI16: 13505608 | AJ16: 14728312 | AK16: 15461939 | AL16: 16669390 | AM16: 18239457 | AN16: 16506665 | AO16: 18607033 | AP16: 19910086 | AQ16: 20536817 | AR16: 21154773 | AS16: 21541207 | AT16: 18637024 | AU16: 19450261 | AV16: 20450261 | AW16: 20780274 | AX16: 19141626 | AY16: 19978169 | AZ16: 20069891 | BA16: 18383270 | BB16: 19666720 | BC16: 20902182 | BD16: 21620474 | BE16: 22776647 | BF16: 23595547 | BG16: 24984065 | BH16: 27464068 | BI16: 27464068 | BJ16: 28980330 | BK16: 30204412 | BL16: 28568179 | BM16: 29109466 | BN16: 30517054 | BO16: 32395094 | BP16: 26212332 | BQ16: 29313639 | BR16: 29714131 | BS16: 30988944 | BT16: 33949049 | BU16: 28463507 | BV16: 28463507 | BW16: 28954455 | BX16: 34613448 | BY16: 36104841 | BZ16: 38924517 | CA16: 40195425 | CB16: 32301539 | CC16: 33517598 | CD16: 32976203 | CE16: 32340275 | CF16: 34341464 | CG16: 35406123 | CH16: 35406123 | CI16: 37754496 | CJ16: 41621690 | CK16: 43072777 | CL16: 43304904 | CM16: 47314570 | CN16: 51277948 | CO16: 55002071 | CP16: 62564410 | CQ16: 67891436 | CR16: 52631077 | CS16: 48046888 | CT16: 36416868 | CU16: 36416868 | CV16: 36416868 | CW16: 37327939 | CX16: 39901396 | CY16: 40966925 | CZ16: 43965964 | DA16: 50529402 | DB16: 50516941 | DC16: 34272450 | DD16: 38459878 | DE16: 41261191
A17: Accounts Recievables | B17: =(B18+B19+B20) -> 0 | C17: =(C18+C19+C20) -> 0 | D17: =(D18+D19+D20) -> 0 | E17: =(E18+E19+E20) -> 0 | F17: =(F18+F19+F20) -> 0 | G17: =(G18+G19+G20) -> 0 | H17: =(H18+H19+H20) -> 0 | I17: =(I18+I19+I20) -> 0 | ... DE17: =(DE18+DE19+DE20) -> 0
A18: Tax Recoverable | J18: 0 | K18: 0 | L18: 0 | M18: 0 | N18: 0 | O18: 0 | P18: 0 | Q18: 0 | R18: 0 | S18: 0 | T18: 0 | U18: 0 | W18: 0 | X18: 0 | Y18: 0 | Z18: 0 | AA18: 0 | AB18: 0 | AC18: 0 | AD18: 0 | AE18: 0 | AF18: 0 | AG18: 0 | AH18: 0 | AI18: 0 | AJ18: 0 | AK18: 0 | AL18: 0 | AM18: 0 | AN18: 0 | AO18: 0 | AP18: 0 | AQ18: 0 | AR18: 0 | AS18: 0 | AT18: 0 | AU18: 0 | AV18: 0 | AW18: 0 | AX18: 0 | AY18: 0 | AZ18: 0 | BA18: 0 | BB18: 0 | BC18: 0 | BD18: 0 | BE18: 0 | BF18: 0 | BG18: 0 | BH18: 0 | BJ18: 0 | BK18: 0 | BL18: 0 | BM18: 0 | BN18: 0 | BO18: 0 | BP18: 0 | BQ18: 0 | BR18: 0 | BS18: 0 | BT18: 0 | BU18: 0 | BW18: 0 | BX18: 0 | BY18: 0 | BZ18: 0 | CA18: 0 | CB18: 0 | CC18: 0 | CD18: 0 | CE18: 0 | CF18: 0 | CG18: 0 | CI18: 0 | CJ18: 0 | CK18: 0 | CL18: 0 | CM18: 0 | CN18: 0 | CO18: 0 | CP18: 0 | CW18: 0 | CX18: 0 | CY18: 0 | CZ18: 0 | DA18: 0 | DB18: 0 | DC18: 0 | DD18: 0 | DE18: 0
A19: Deffered Tax Assets | J19: 0 | K19: 0 | L19: 0 | M19: 0 | N19: 0 | O19: 0 | P19: 0 | Q19: 0 | R19: 0 | S19: 0 | T19: 0 | U19: 0 | W19: 0 | X19: 0 | Y19: 0 | Z19: 0 | AA19: 0 | AB19: 0 | AC19: 0 | AD19: 0 | AE19: 0 | AF19: 0 | AG19: 0 | AH19: 0 | AI19: 0 | AJ19: 0 | AK19: 0 | AL19: 0 | AM19: 0 | AN19: 0 | AO19: 0 | AP19: 0 | AQ19: 0 | AR19: 0 | AS19: 0 | AT19: 0 | AU19: 0 | AV19: 0 | AW19: 0 | AX19: 0 | AY19: 0 | AZ19: 0 | BA19: 0 | BB19: 0 | BC19: 0 | BD19: 0 | BE19: 0 | BF19: 0 | BG19: 0 | BH19: 0 | BJ19: 0 | BK19: 0 | BL19: 0 | BM19: 0 | BN19: 0 | BO19: 0 | BP19: 0 | BQ19: 0 | BR19: 0 | BS19: 0 | BT19: 0 | BU19: 0 | BW19: 0 | BX19: 0 | BY19: 0 | BZ19: 0 | CA19: 0 | CB19: 0 | CC19: 0 | CD19: 0 | CE19: 0 | CF19: 0 | CG19: 0 | CI19: 0 | CJ19: 0 | CK19: 0 | CL19: 0 | CM19: 0 | CN19: 0 | CO19: 0 | CP19: 0 | CW19: 0 | CX19: 0 | CY19: 0 | CZ19: 0 | DA19: 0 | DB19: 0 | DC19: 0 | DD19: 0 | DE19: 0
A20: Retirement Benefit Assets | J20: 0 | K20: 0 | L20: 0 | M20: 0 | N20: 0 | O20: 0 | P20: 0 | Q20: 0 | R20: 0 | S20: 0 | T20: 0 | U20: 0 | W20: 0 | X20: 0 | Y20: 0 | Z20: 0 | AA20: 0 | AB20: 0 | AC20: 0 | AD20: 0 | AE20: 0 | AF20: 0 | AG20: 0 | AH20: 0 | AI20: 0 | AJ20: 0 | AK20: 0 | AL20: 0 | AM20: 0 | AN20: 0 | AO20: 0 | AP20: 0 | AQ20: 0 | AR20: 0 | AS20: 0 | AT20: 0 | AU20: 0 | AV20: 0 | AW20: 0 | AX20: 0 | AY20: 0 | AZ20: 0 | BA20: 0 | BB20: 0 | BC20: 0 | BD20: 0 | BE20: 0 | BF20: 0 | BG20: 0 | BH20: 0 | BJ20: 0 | BK20: 0 | BL20: 0 | BM20: 0 | BN20: 0 | BO20: 0 | BP20: 0 | BQ20: 0 | BR20: 0 | BS20: 0 | BT20: 0 | BU20: 0 | BW20: 0 | BX20: 0 | BY20: 0 | BZ20: 0 | CA20: 0 | CB20: 0 | CC20: 0 | CD20: 0 | CE20: 0 | CF20: 0 | CG20: 0 | CI20: 0 | CJ20: 0 | CK20: 0 | CL20: 0 | CM20: 0 | CN20: 0 | CO20: 0 | CP20: 0 | CW20: 0 | CX20: 0 | CY20: 0 | CZ20: 0 | DA20: 0 | DB20: 0 | DC20: 0 | DD20: 0 | DE20: 0
A21: Property&Equipments&Other Assets | B21: =(B22+B23+B24+B25+B26) -> 39181612 | C21: =(C22+C23+C24+C25+C26) -> 38465275 | D21: =(D22+D23+D24+D25+D26) -> 37319422 | E21: =(E22+E23+E24+E25+E26) -> 36083711 | F21: =(F22+F23+F24+F25+F26) -> 35187188 | G21: =(G22+G23+G24+G25+G26) -> 34119364 | H21: =(H22+H23+H24+H25+H26) -> 35001409 | I21: =(I22+I23+I24+I25+I26) -> 68742772 | ... DE21: =(DE22+DE23+DE24+DE25+DE26) -> 72733533
A22: Investment Properties | J22: 0 | K22: 0 | L22: 0 | M22: 0 | N22: 0 | O22: 0 | P22: 0 | Q22: 0 | R22: 0 | S22: 0 | T22: 0 | U22: 0 | W22: 0 | X22: 0 | Y22: 0 | Z22: 0 | AA22: 0 | AB22: 0 | AC22: 0 | AD22: 0 | AE22: 0 | AF22: 0 | AG22: 0 | AH22: 0 | AI22: 0 | AJ22: 0 | AK22: 0 | AL22: 0 | AM22: 0 | AN22: 0 | AO22: 0 | AP22: 0 | AR22: 0 | AS22: 0 | AT22: 0 | AU22: 60556766 | AW22: 60463940 | AX22: 60371113 | AY22: 60278287 | AZ22: 60605767 | BA22: 61045315 | BB22: 61096684 | BC22: 60992722 | BD22: 60898054 | BE22: 60803386 | BF22: 60708718 | BG22: 60614050 | BH22: 60297283 | BJ22: 60204994 | BK22: 60112494 | BL22: 59994288 | BM22: 59902468 | BN22: 59810894 | BO22: 59719511 | BP22: 59628318 | BQ22: 59537315 | BR22: 59446502 | BS22: 59461027 | BT22: 59370353 | BU22: 59442985 | BV22: 143707572 | BW22: 59628202 | BX22: 60172154 | BY22: 60080018 | BZ22: 59988100 | CA22: 59896348 | CB22: 59803339 | CC22: 59617167 | CD22: 59523741 | CE22: 59431334 | CF22: 59338901 | CG22: 58103789 | CH22: 58103789 | CI22: 58016072 | CJ22: 57928539 | CK22: 57840640 | CL22: 57752924 | CM22: 57665208 | CN22: 57577491 | CO22: 57489775 | CP22: 57402059 | CQ22: 57314343 | CR22: 57226626 | CS22: 57138900 | CT22: 57051194 | CU22: 57051194 | CV22: 56024914 | CW22: 55941528 | CX22: 55858143 | CY22: 55774758 | CZ22: 55691373 | DA22: 55607987 | DB22: 55524601 | DC22: 55441216 | DD22: 55357813 | DE22: 55274428
A23: Property and Equipment | B23: 38899150 | C23: 38222790 | D23: 37083833 | E23: 35801719 | F23: 34764877 | G23: 33634899 | H23: 34529467 | I23: 68602755 | J23: 81820805 | K23: 81626203 | L23: 81434968 | M23: 81275547 | N23: 81127540 | O23: 80947852 | P23: 66139055 | Q23: 66005431 | R23: 65942098 | S23: 66502906 | T23: 65853324 | U23: 65688133 | V23: 67183766 | W23: 65821598 | X23: 65674810 | Y23: 66551962 | Z23: 66368220 | AA23: 66332668 | AB23: 66868520 | AC23: 66752159 | AD23: 66589310 | AE23: 67135670 | AF23: 66744795 | AG23: 68815078 | AH23: 65420012 | AI23: =66635551-AI25 -> 65997591 | AJ23: 65691619 | AK23: 65661070 | AL23: 65488205 | AM23: 65599196 | AN23: 65405868 | AO23: 65230122 | AP23: 65600456 | AQ23: 65190740 | AR23: 65017736 | AS23: 64662690 | AT23: 64724750 | AU23: 4434899.9 | AV23: =66635364-637961 -> 65997403 | AW23: 4358754.8 | AX23: 4301478 | AY23: 4228706.2 | AZ23: 4590950 | BA23: 4549799.1 | BB23: 4490022.2 | BC23: 4767228.3 | BD23: 4969646.8 | BE23: 4901768.6 | BF23: 5280579 | BG23: 5279015.2 | BH23: 4626937.9 | BI23: 7592189 | BJ23: 4906334.4 | BK23: 4936595.2 | BL23: 4857251.3 | BM23: 4809192.5 | BN23: 5067602 | BO23: 4771818 | BP23: 4671285.5 | BQ23: 4695247.6 | BR23: 8044766.8 | BS23: 8019247.5 | BT23: 7914948.3 | BU23: 7020122.9 | BV23: 9153451 | BW23: 6920479 | BX23: 6778829.9 | BY23: 6691681.3 | BZ23: 6556567.4 | CA23: 6617545.6 | CB23: 6758640.2 | CC23: 6525401.9 | CD23: 6487237.4 | CE23: 6329159 | CF23: 6171225.2 | CG23: 6051200.5 | CH23: =7544530-1493330 -> 6051200 | CI23: 5935931.1 | CJ23: 5822302.7 | CK23: 5705401.6 | CL23: 5588330.6 | CM23: 5609924.4 | CN23: 5544603.7 | CO23: 5432321.2 | CP23: 5485539.4 | CQ23: 5362391.7 | CR23: 5246380.7 | CS23: 5286203.9 | CT23: 5158193 | CU23: 6203525 | CV23: 8299778 | CW23: 8159712.3 | CX23: 8023159.5 | CY23: 7884534.9 | CZ23: 7748104.5 | DA23: 7622913.2 | DB23: 7631502.6 | DC23: 7571749.7 | DD23: 7256570.6 | DE23: 7196848.3
A24: Prepaid Lease Rentals | J24: 34170 | K24: 62170 | L24: 83170 | M24: 79170 | N24: 77170 | O24: 111170 | P24: 93170 | Q24: 73170 | R24: 74170 | S24: 72170 | T24: 77170 | U24: 0 | W24: 0 | X24: 0 | Y24: 0 | Z24: 0 | AA24: 0 | AB24: 0 | AC24: 0 | AD24: 0 | AE24: 0 | AF24: 0 | AG24: 0 | AH24: 0 | AI24: 0 | AJ24: 0 | AK24: 0 | AL24: 0 | AM24: 0 | AN24: 0 | AO24: 0 | AP24: 0 | AR24: 0 | AS24: 0 | AT24: 0 | AU24: 0 | AW24: 0 | AX24: 0 | AY24: 0 | AZ24: 0 | BA24: 0 | BB24: 0 | BC24: 0 | BD24: 0 | BE24: 0 | BG24: 0 | BH24: 0 | BJ24: 0 | BK24: 0 | BL24: 0 | BM24: 0 | BN24: 0 | BO24: 0 | BP24: 0 | BQ24: 0 | BR24: 0 | BS24: 0 | BT24: 0 | BU24: 0 | BW24: 0 | BX24: 0 | BY24: 0 | BZ24: 0 | CA24: 0 | CB24: 0 | CC24: 0 | CD24: 0 | CE24: 0 | CF24: 0 | CG24: 0 | CI24: 0 | CJ24: 0 | CK24: 0 | CL24: 0 | CM24: 0 | CN24: 0 | CO24: 0 | CP24: 0 | CQ24: 0 | CR24: 0 | CS24: 0 | CT24: 0 | CV24: 10122308 | CW24: 0 | CX24: 0 | CY24: 0 | CZ24: 0 | DA24: 0 | DB24: 0 | DC24: 0 | DD24: 0 | DE24: 0
A25: Intangible Assets | J25: 7989641.1 | K25: 7876453.5 | L25: 7841728.8 | M25: 7652727.2 | N25: 7542144.6 | O25: 7464572.1 | P25: 1689266.9 | Q25: 1658671.1 | R25: 1628840.2 | S25: 1128495.3 | T25: 1100282.9 | U25: 1077359.9 | W25: 1045956.8 | X25: 1019807.9 | Y25: 0 | Z25: 0 | AA25: 0 | AB25: 0 | AC25: 0 | AD25: 0 | AE25: 0 | AF25: 0 | AG25: 0 | AH25: 637960.4 | AI25: 637960.4 | AJ25: 622010.99 | AK25: 606460.69 | AL25: 591299 | AM25: 576515.69 | AN25: 560713.99 | AO25: 545805.79 | AP25: 3989511.2 | AQ25: 4853570.9 | AR25: 4732231.6 | AS25: 4579191.3 | AT25: 4499446 | AU25: 4310881.7 | AV25: 637961 | AW25: 4203969.8 | AX25: 4096657.4 | AY25: 3989376.6 | AZ25: 3882126.4 | BA25: 3774905.8 | BB25: 3667723.2 | BC25: 4086455.6 | BD25: 3965788.1 | BE25: 3858605.5 | BF25: 3751422.9 | BG25: 3680378.7 | BH25: 2965251.3 | BJ25: 2900782.8 | BK25: 2818143 | BL25: 2748316.5 | BM25: 2675938.7 | BN25: 2645833.9 | BO25: 2578464.7 | BP25: 2512734 | BQ25: 2449589.3 | BR25: 2429493.3 | BS25: 2365696.3 | BT25: 2306133.3 | BU25: 2133327.9 | BW25: 2079578.4 | BX25: 2027260.3 | BY25: 1976252.5 | BZ25: 1926896.2 | CA25: 1878406.9 | CB25: 1831129.8 | CC25: 1706655 | CD25: 1653329.1 | CE25: 1599995.9 | CF25: 1546662.7 | CG25: 1493329.5 | CH25: 1493330 | CI25: 1455996.3 | CJ25: 1419596.4 | CK25: 1381339.8 | CL25: 1343073.2 | CM25: 1306663.4 | CN25: 1269330.1 | CO25: 1231996.9 | CP25: 1194663.6 | CQ25: 1157330.4 | CR25: 1119997.2 | CS25: 1082663.9 | CT25: 1045330.7 | CV25: 807332 | CW25: 10726972 | CX25: 10662353 | CY25: 10597638 | CZ25: 10537608 | DA25: 10504967 | DB25: 10440530 | DC25: 10349137 | DD25: 10319993 | DE25: 10262257
A26: Other Assets | B26: 282462 | C26: 242485 | D26: 235589 | E26: 281992 | F26: 422311 | G26: 484464.8 | H26: 471942 | I26: 140017 | J26: 11386542 | K26: 11150285 | L26: 5809887.1 | M26: 5679460.9 | N26: 5624742.5 | O26: 23508249 | P26: 5439213.4 | Q26: 20420890 | R26: 5254148.3 | S26: 9603160.1 | T26: 26183386 | U26: 0 | V26: 185954 | W26: 0 | X26: 0 | Y26: 0 | Z26: 3782806.4 | AA26: 206422 | AB26: 192866 | AC26: 216700 | AD26: 0 | AE26: 0 | AF26: 0 | AG26: 0 | AH26: 188499.7 | AI26: 188500 | AJ26: 168864.7 | AK26: 0 | AL26: 0 | AM26: 0 | AN26: 0 | AO26: 0 | AP26: 0 | AQ26: 0 | AR26: 0 | AS26: 0 | AT26: 0 | AU26: 0 | AV26: 146861 | AW26: 0 | AX26: 0 | AY26: 0 | AZ26: 0 | BA26: 0 | BB26: 0 | BC26: 0 | BD26: 0 | BE26: 0 | BG26: 0 | BH26: 0 | BI26: 184749 | BJ26: 0 | BK26: 0 | BL26: 0 | BM26: 0 | BN26: 0 | BO26: 0 | BP26: 0 | BQ26: 0 | BR26: 0 | BS26: 0 | BT26: 0 | BU26: 0 | BV26: 561318 | BW26: 0 | BX26: 0 | BY26: 0 | BZ26: 0 | CA26: 0 | CB26: 0 | CC26: 0 | CD26: 0 | CE26: 0 | CF26: 0 | CG26: 0 | CH26: 361862 | CI26: 0 | CJ26: 0 | CK26: 0 | CL26: 0 | CM26: 0 | CN26: 0 | CO26: 0 | CP26: 0 | CQ26: 0 | CR26: 0 | CS26: 0 | CT26: 0 | CU26: 308836 | CV26: 277687 | CW26: 0 | CX26: 0 | CY26: 0 | CZ26: 0 | DA26: 0 | DB26: 0 | DC26: 0 | DD26: 0 | DE26: 0
A27: Total Assets | B27: =(B21+B17+B14+B8+B7+B4) -> 101042159 | C27: =(C21+C17+C14+C8+C7+C4) -> 106951763 | D27: =(D21+D17+D14+D8+D7+D4) -> 130959400 | E27: =(E21+E17+E14+E8+E7+E4) -> 132850579 | F27: =(F21+F17+F14+F8+F7+F4) -> 1.2630166e+08 | G27: =(G21+G17+G14+G8+G7+G4) -> 2.5342774e+08 | H27: =(H21+H17+H14+H8+H7+H4) -> 242665216 | I27: =(I21+I17+I14+I8+I7+I4) -> 284500118 | ... DE27: =(DE21+DE17+DE14+DE8+DE7+DE4) -> 6.8298175e+08
A28: Savings and Deposits | B28: 47903083 | C28: 49187636 | D28: 48437747 | E28: 48437747 | F28: 85304630 | G28: =42085730.1+145020+28086.53+23367955.35+12503253 -> 78130045 | H28: =18227509+9386042+144353 -> 27757904 | I28: =101506537-72218472 -> 29288065 | J28: 25114982 | K28: 25462821 | L28: 24471914 | M28: 24597731 | N28: 26079998 | O28: 94663575 | P28: 61871615 | Q28: 43266174 | R28: 38620458 | S28: 36730143 | T28: 38339741 | U28: 34694880 | V28: 34968731 | W28: 31005437 | X28: 31294881 | Y28: 28693138 | Z28: 28077067 | AA28: 28152801 | AB28: 81865550 | AC28: 74456950 | AD28: 60562986 | AE28: 46909980 | AF28: 45343284 | AG28: 39478956 | AH28: 37978118 | AI28: 37978118 | AJ28: 35707716 | AK28: 39805563 | AL28: 46251171 | AM28: 45643638 | AN28: 1.1295355e+08 | AO28: 81835798 | AP28: 74451398 | AQ28: 61751109 | AR28: 55872667 | AS28: 52880183 | AT28: 47979528 | AU28: 45097081 | AV28: 46990567 | AW28: 42575519 | AX28: 38973246 | AY28: 37876191 | AZ28: 42110381 | BA28: 1.1550149e+08 | BB28: 88892029 | BC28: 81711392 | BD28: 77180553 | BE28: 73292762 | BF28: 73617816 | BG28: 65216431 | BH28: 58834888 | BI28: 60006858 | BJ28: 55246692 | BK28: 56487575 | BL28: 53595962 | BM28: 49652052 | BN28: 48949135 | BO28: 53756186 | BP28: 1.6663096e+08 | BQ28: 1.5224484e+08 | BR28: 1.1683412e+08 | BS28: 1.0564632e+08 | BT28: 85169406 | BU28: 75021439 | BV28: 77305996 | BW28: 67371608 | BX28: 68738339 | BY28: 66715778 | BZ28: 1.1318954e+08 | CA28: 1.129156e+08 | CB28: 1.7331063e+08 | CC28: 1.2512086e+08 | CD28: 2.5823128e+08 | CE28: 1.8720633e+08 | CF28: 1.3778075e+08 | CG28: 1.1258053e+08 | CH28: 116282188 | CI28: 99048951 | CJ28: 91994700 | CK28: 91318467 | CL28: 97616332 | CM28: 94226503 | CN28: 92864639 | CO28: 89521526 | CP28: 86599721 | CQ28: 1.7038283e+08 | CR28: 2.1733685e+08 | CS28: 1.6526133e+08 | CT28: 1.4481464e+08 | CU28: 151885246 | CV28: 144662107 | CW28: 1.2764875e+08 | CX28: 1.2620993e+08 | CY28: 1.2861542e+08 | CZ28: 1.3246865e+08 | DA28: 1.2752404e+08 | DB28: 1.3530791e+08 | DC28: 1.960286e+08 | DD28: 1.6349904e+08 | DE28: 1.5177236e+08
A29: Short Terrm Deposits | B29: 594854 | C29: 594854 | D29: 594854 | E29: 594854 | F29: 39525985 | J29: 0 | K29: 0 | L29: 0 | M29: 0 | N29: 0 | O29: 0 | P29: 0 | Q29: 0 | R29: 0 | S29: 0 | T29: 260000 | U29: 260000 | W29: 275000 | X29: 275000 | Y29: 275000 | Z29: 265000 | AA29: 265000 | AB29: 0 | AC29: 0 | AD29: 0 | AE29: 0 | AF29: 0 | AG29: 0 | AH29: 0 | AI29: 0 | AJ29: 0 | AK29: 0 | AL29: 0 | AM29: 0 | AN29: 0 | AO29: 0 | AP29: 180000 | AQ29: 790000 | AR29: 760000 | AS29: 410000 | AT29: 710000 | AU29: 710000 | AW29: 814998 | AX29: 914996 | AY29: 854996 | AZ29: 504996 | BA29: 1022182.9 | BB29: 1062182.9 | BC29: 1062182.9 | BD29: 1111980.9 | BE29: 1111970.9 | BF29: 1456970.9 | BG29: 1271970 | BH29: 1171970 | BJ29: 1066980 | BK29: 1066980 | BL29: 1237182 | BM29: 1261749 | BN29: 1304567 | BO29: 1304567 | BP29: 2281754 | BQ29: 2441754 | BR29: 2546754 | BS29: 2619754 | BT29: 2364567 | BU29: 2284557 | BV29: 109252459 | BW29: 2286157 | BX29: 3281157 | BY29: 3370167 | BZ29: 4056000 | CA29: 4554400 | CB29: 4309400 | CC29: 4116200 | CD29: 3631200 | CE29: 3782460 | CF29: 3932460 | CG29: 3701660 | CI29: 3500400 | CJ29: 4850400 | CK29: 6085000 | CL29: 6085000 | CM29: 6150000 | CN29: 5672050 | CO29: 5626800 | CP29: 5601400 | CQ29: 4255050 | CR29: 6294154 | CS29: 6220904 | CT29: 7070604 | CW29: 6503285 | CX29: 6631385 | CY29: 7004485 | CZ29: 6746193 | DA29: 7038293 | DB29: 4990693 | DC29: 5538797 | DD29: 5390497 | DE29: 5590497
A30: Non Withdrawable Deposits | B30: 39804485 | C30: 39804485 | D30: 39525985 | E30: 39525985 | F30: 5978896 | G30: =39525985 -> 39525985 | H30: 65012036 | I30: 72218472 | J30: 72437415 | K30: 72746392 | L30: 73080937 | M30: 73444770 | N30: 73979692 | O30: 75456788 | P30: 77480018 | Q30: 79938926 | R30: 80414495 | S30: 81425798 | T30: 84524458 | U30: 84274209 | V30: 79759358 | W30: 79808845 | X30: 80665221 | Y30: 82086292 | Z30: 83087102 | AA30: 83685610 | AB30: 88045834 | AC30: 90935673 | AD30: 92736142 | AE30: 93486726 | AF30: 91958826 | AG30: 94543744 | AH30: 89586054 | AI30: 89650681 | AJ30: 90251415 | AK30: 90940015 | AL30: 91229290 | AM30: 91520602 | AN30: 93030414 | AO30: 95071534 | AP30: 97197282 | AQ30: 97792761 | AR30: 98354890 | AS30: 98961025 | AT30: 99553496 | AU30: 99641667 | AV30: 94380497 | AW30: 94864059 | AX30: 95534037 | AY30: 96189608 | AZ30: 96483421 | BA30: 1.0007996e+08 | BB30: 1.0189561e+08 | BC30: 1.0606116e+08 | BD30: 1.0702818e+08 | BE30: 1.0686529e+08 | BF30: 1.0321255e+08 | BG30: 1.0338553e+08 | BH30: 99022261 | BI30: 99022261 | BJ30: 99345353 | BK30: 99471042 | BL30: 1.007383e+08 | BM30: 1.0122515e+08 | BN30: 101827212 | BO30: 1.0278297e+08 | BP30: 1.0854551e+08 | BQ30: 1.1299435e+08 | BR30: 1.1584463e+08 | BS30: 1.1721558e+08 | BT30: 1.1843542e+08 | BU30: 1.0925246e+08 | BW30: 1.0883129e+08 | BX30: 1.0917769e+08 | BY30: 1.0834248e+08 | BZ30: 1.0909378e+08 | CA30: 91930311 | CB30: 1.1649716e+08 | CC30: 1.2017729e+08 | CD30: 1.2260357e+08 | CE30: 1.2799435e+08 | CF30: 1.2994695e+08 | CG30: 1.3090945e+08 | CH30: 130909445 | CI30: 1.3131777e+08 | CJ30: 1.3238356e+08 | CK30: 1.327135e+08 | CL30: 1.3314603e+08 | CM30: 1.3376227e+08 | CN30: 1.3424132e+08 | CO30: 1.3570885e+08 | CP30: 1.3600388e+08 | CQ30: 1.3664754e+08 | CR30: 1.4313259e+08 | CS30: 1.4058583e+08 | CT30: 1.3840726e+08 | CU30: 138407264 | CV30: 160511165 | CW30: 1.6296771e+08 | CX30: 1.6392101e+08 | CY30: 1.6588523e+08 | CZ30: 1.6786545e+08 | DA30: 1.7059832e+08 | DB30: 1.7223813e+08 | DC30: 1.7786135e+08 | DD30: 1.8153271e+08 | DE30: 1.8415523e+08
A31: Total Deposit Liabilities | B31: =SUM(B28:B30) -> 88302422 | C31: =SUM(C28:C30) -> 89586975 | D31: =SUM(D28:D30) -> 88558586 | E31: =SUM(E28:E30) -> 88558586 | F31: =SUM(F28:F30) -> 130809511 | G31: =SUM(G28:G30) -> 1.1765603e+08 | H31: =SUM(H28:H30) -> 92769940 | I31: =SUM(I28:I30) -> 101506537 | ... DE31: =SUM(DE28:DE30) -> 3.4151808e+08
A32: Tax Payable | B32: 44330 | C32: 44330 | D32: 224330 | E32: 224330 | F32: 393743 | J32: 0 | K32: 0 | L32: 0 | M32: 0 | N32: 162492 | O32: 0 | P32: 0 | Q32: 0 | R32: 0 | S32: 0 | T32: 651967 | U32: 651967 | W32: 651967 | X32: 651967 | Y32: 651967 | Z32: 651967 | AA32: 651967 | AB32: 651967 | AC32: 651967 | AD32: 651967 | AE32: 353160 | AF32: 179126 | AG32: 179126 | AH32: 1716001 | AI32: 1311634 | AJ32: 1716001 | AK32: 1418808 | AL32: 0 | AM32: 0 | AN32: 0 | AO32: 0 | AP32: 0 | AQ32: 0 | AR32: 0 | AS32: 0 | AT32: 0 | AU32: 0 | AV32: 0 | AW32: 0 | AX32: 0 | AY32: 0 | AZ32: 0 | BA32: 0 | BB32: 0 | BC32: 0 | BD32: 0 | BE32: 0 | BF32: 0 | BG32: 0 | BH32: 0 | BJ32: 0 | BK32: 0 | BL32: 0 | BM32: 0 | BN32: 0 | BO32: 0 | BP32: 0 | BQ32: 0 | BR32: 0 | BS32: 0 | BT32: 0 | BU32: 0 | BW32: 0 | BX32: 0 | BY32: 0 | BZ32: 0 | CA32: 0 | CB32: 0 | CC32: 0 | CD32: 539534.95 | CE32: 361223.95 | CF32: 182912.95 | CG32: 0 | CH32: 0 | CI32: 0 | CJ32: 0 | CK32: 0 | CL32: 0 | CM32: 0 | CN32: 0 | CO32: 0 | CP32: 0 | CQ32: 0 | CR32: 0 | CS32: 0 | CT32: 0 | CU32: 6543446 | CV32: 4113004 | CW32: 0 | CX32: 0 | CY32: 0 | CZ32: 0 | DA32: 0 | DB32: 0 | DC32: 0 | DD32: 0 | DE32: 0
A33: Dividends Payable | J33: 0 | K33: 0 | L33: 0 | M33: 0 | N33: 0 | O33: 0 | P33: 0 | Q33: 0 | R33: 0 | S33: 0 | T33: 0 | U33: 0 | W33: 0 | X33: 0 | Y33: 0 | Z33: 0 | AA33: 0 | AB33: 0 | AC33: 0 | AD33: 0 | AE33: 0 | AF33: 0 | AG33: 0 | AH33: 0 | AI33: 0 | AJ33: 0 | AK33: 0 | AL33: 0 | AM33: 0 | AN33: 0 | AO33: 0 | AP33: 0 | AQ33: 0 | AR33: 0 | AS33: 0 | AT33: 0 | AU33: 0 | AV33: 4275560 | AW33: 0 | AX33: 0 | AY33: 0 | AZ33: 0 | BA33: 0 | BB33: 0 | BC33: 0 | BD33: 0 | BE33: 0 | BF33: 0 | BG33: 0 | BH33: 0 | BI33: 5000000 | BJ33: 0 | BK33: 0 | BL33: 0 | BM33: 0 | BN33: 0 | BO33: 0 | BP33: 0 | BQ33: 0 | BR33: 0 | BS33: 0 | BT33: 0 | BU33: 0 | BW33: 0 | BX33: 0 | BY33: 0 | BZ33: 0 | CA33: 0 | CB33: 0 | CC33: 0 | CD33: 0 | CE33: 0 | CF33: 0 | CG33: 0 | CH33: 0 | CI33: 7000000 | CJ33: 7000000 | CK33: 7000000 | CL33: 45029.55 | CM33: 45029.55 | CN33: 45029.55 | CO33: 45029.55 | CP33: 0 | CQ33: 0 | CR33: 0 | CS33: 0 | CT33: 0 | CW33: 0 | CX33: 0 | CY33: 0 | CZ33: 0 | DA33: 0 | DB33: 0 | DC33: 0 | DD33: 0 | DE33: 0
A34: Deferred Tax Liability | C34: 9039797 | D34: 31164651 | E34: 32763062 | F34: 30784235 | M34: 0 | N34: 0 | O34: 0 | P34: 0 | Q34: 0 | R34: 0 | S34: 0 | T34: 0 | U34: 0 | W34: 0 | X34: 0 | Y34: 0 | Z34: 0 | AA34: 0 | AB34: 1042028 | AC34: 1159690 | AD34: 1059710 | AE34: 0 | AF34: 0 | AG34: 0 | AH34: 0 | AI34: 0 | AJ34: 0 | AK34: 0 | AL34: 0 | AM34: 0 | AN34: 0 | AO34: 0 | AP34: 0 | AQ34: 0 | AR34: 0 | AS34: 0 | AT34: 0 | AU34: 0 | AV34: 0 | AW34: 0 | AX34: 0 | AY34: 0 | AZ34: 0 | BA34: 0 | BB34: 0 | BC34: 0 | BD34: 0 | BE34: 0 | BF34: 0 | BG34: 0 | BH34: 0 | BJ34: 0 | BK34: 0 | BL34: 0 | BM34: 0 | BN34: 0 | BO34: 0 | BP34: 0 | BQ34: 0 | BR34: 0 | BS34: 0 | BT34: 0 | BU34: 0 | BW34: 0 | BX34: 0 | BY34: 0 | BZ34: 0 | CA34: 0 | CB34: 0 | CC34: 0 | CD34: 0 | CE34: 0 | CF34: 0 | CG34: 0 | CH34: 0 | CI34: 0 | CJ34: 0 | CK34: 0 | CL34: 0 | CM34: 0 | CN34: 0 | CO34: 0 | CP34: 0 | CQ34: 0 | CR34: 0 | CS34: 0 | CT34: 0 | CW34: 0 | CX34: 0 | CY34: 0 | CZ34: 0 | DA34: 0 | DB34: 0 | DC34: 0 | DD34: 0 | DE34: 0
A35: Retirement Benefits Liabilty | B35: 5005464 | C35: 5220296 | D35: 5418645 | E35: 5418645 | J35: 1223471.3 | K35: 1326475.9 | L35: 993408.4 | M35: 1081892.9 | N35: 1172922.8 | O35: 1266320.3 | P35: 1001671.6 | Q35: 1105083.4 | R35: 1212035.1 | S35: 1318986.6 | T35: 1011412 | U35: 1123693 | V35: 11725823 | W35: 1023241.1 | X35: 1152847 | Y35: 1024493 | Z35: 1283450 | AA35: 1408487 | AB35: 10083404 | AC35: 7085661 | AD35: 6052202 | AE35: 1059710 | AF35: 1161902 | AG35: 1264509.6 | AH35: 1051361.3 | AJ35: 1168066.3 | AK35: 493414.95 | AL35: 376705.95 | AM35: 0 | AN35: 0 | AO35: 0 | AP35: 0 | AQ35: 0 | AR35: 0 | AS35: 0 | AT35: 0 | AU35: 0 | AV35: 0 | AW35: 0 | AX35: 0 | AY35: 0 | AZ35: 0 | BA35: 0 | BB35: 0 | BC35: 0 | BD35: 0 | BE35: 0 | BF35: 0 | BJ35: 7714596.7 | BK35: 7302673.1 | BL35: 7461822.2 | BM35: 7741287.6 | BN35: 7201286.4 | BS35: 0 | BW35: 0 | BX35: 0 | BY35: 0 | BZ35: 0 | CA35: 0 | CB35: 0 | CC35: 0 | CD35: 591083.59 | CE35: 569475.89 | CF35: 601107.79 | CG35: 412846 | CI35: 0 | CJ35: 0 | CK35: 0 | CL35: 0 | CM35: 713139.85 | CN35: 731282.85 | CO35: 764363.02 | CP35: 796846.02 | CQ35: 803839.02 | CR35: 834132.02 | CS35: 838754.52 | CT35: 872447.52 | CW35: 1048167.5 | CX35: 1080029.5 | CY35: 1112527.9 | CZ35: 1144744.2 | DA35: 1110826 | DB35: 1141857.9 | DC35: 1161726.4 | DD35: 1406399.3 | DE35: 1195236
A36: Other Liabilities | B36: =33883+64158+167379+8428187+13200000 -> 21893607 | G36: =19443773.41+393743.4+178213656 -> 1.9805117e+08 | H36: =4362880+10817111+178213656 -> 193393647 | I36: 10157592 | J36: 6727894.1 | K36: 6742858.3 | L36: 6277336 | M36: 6806684.2 | N36: 6331607.8 | O36: -6106433.7 | P36: 24113829 | Q36: 7369849.1 | R36: 10046738 | S36: 11050821 | T36: 9347244.4 | U36: 8486407.2 | W36: 8394823.5 | X36: 6604477 | Y36: 7740138.6 | Z36: 6533790.7 | AA36: 7718599 | AB36: 0 | AC36: 0 | AD36: 0 | AE36: 7842750 | AF36: 7002474 | AG36: 6693157.7 | AH36: 2893506.8 | AI36: =4034281+3999868 -> 8034149 | AJ36: 2893505.8 | AK36: 6681300.3 | AL36: 8567645.2 | AM36: 7669947.6 | AN36: 6964469.5 | AO36: 3065908.1 | AP36: 2668084.2 | AQ36: 4010665.1 | AR36: 4183358.2 | AS36: 4111078.7 | AT36: 4242112 | AU36: 2198262.9 | AV36: 2233621 | AW36: 2749440 | AX36: 2640228.3 | AY36: 2759673.2 | AZ36: 1818411.3 | BA36: 1177797.1 | BB36: 195312.3 | BC36: 1420285.1 | BD36: 1827256.9 | BE36: 1293035.6 | BF36: 2046605.5 | BG36: 4539384.6 | BH36: 8004071.8 | BI36: 3004072 | BJ36: 0 | BK36: 0 | BL36: 0 | BM36: 0 | BN36: 0 | BO36: 6916192 | BP36: 3366208 | BQ36: 3629076 | BR36: 6431941.9 | BS36: 6291352.8 | BT36: 4763249.6 | BU36: 11600951 | BV36: =9600951+3878837.5 -> 13479788 | BW36: 11464601 | BX36: 12411077 | BY36: 12015102 | BZ36: 10514832 | CA36: 5183510.2 | CB36: 4364729.5 | CC36: 3439965.8 | CD36: 34676669 | CE36: 4991838.4 | CF36: 2731401.4 | CG36: 10685643 | CH36: =11098489+2554227 -> 13652716 | CI36: 4161802.1 | CJ36: 4914619.5 | CK36: 5376745.1 | CL36: 5387752.9 | CM36: 3206020.4 | CN36: 3541266.4 | CO36: 2715412.8 | CP36: 2921561.9 | CQ36: 88544509 | CR36: 7541690.3 | CS36: 3808915.7 | CT36: 11945442 | CU36: 12817890 | CV36: 17166685 | CW36: 15435563 | CX36: 15424156 | CY36: 15602246 | CZ36: 7820357.4 | DA36: 3862057.1 | DB36: 4830228.9 | DC36: 5835191.4 | DD36: 8544929.3 | DE36: 8570291.2
A37: External Borrowings | B37: 23369140 | C37: 22592216 | D37: 21733302 | E37: 20582216 | F37: 19635543 | G37: 28914 | H37: 28914 | J37: 0 | K37: 0 | L37: 0 | M37: 0 | N37: 0 | O37: 0 | P37: 0 | W37: 0 | X37: 0 | Y37: 0 | Z37: 0 | AA37: 0 | AE37: 0 | AF37: 0 | AG37: 0 | AH37: 0 | AI37: 0 | AJ37: 0 | AK37: 0 | AL37: 0 | AM37: 0 | AN37: 0 | AO37: 0 | AP37: 0 | AQ37: 0 | AR37: 0 | AS37: 0 | AT37: 0 | AU37: 0 | AV37: 0 | AW37: 0 | AX37: 0 | AY37: 0 | AZ37: 0 | BA37: 0 | BB37: 0 | BC37: 0 | BD37: 0 | BE37: 0 | BF37: 0 | BG37: 0 | BH37: 0 | BS37: 0 | BT37: 0 | BU37: 0 | BW37: 0 | BX37: 0 | BY37: 0 | BZ37: 0 | CA37: 0 | CB37: 0 | CC37: 0 | CD37: 0 | CE37: 0 | CF37: 0 | CG37: 0 | CH37: 0 | CI37: 0 | CJ37: 0 | CK37: 0 | CL37: 0 | CM37: 0 | CN37: 0 | CO37: 0 | CP37: 0 | CQ37: 0 | CR37: 0 | CS37: 0 | CT37: 0 | CW37: 0 | CX37: 0 | CY37: 0 | CZ37: 0 | DA37: 0 | DB37: 0 | DC37: 0 | DD37: 0 | DE37: 0
A38: Total Liabilities | B38: =SUM(B31:B37) -> 138614963 | C38: =SUM(C31:C37) -> 126483614 | D38: =SUM(D31:D37) -> 147099514 | E38: =SUM(E31:E37) -> 147546839 | F38: =SUM(F31:F37) -> 1.8162303e+08 | G38: =SUM(G31:G37) -> 3.1573612e+08 | H38: =SUM(H31:H37) -> 286192501 | I38: =SUM(I31:I37) -> 111664129 | ... DE38: =SUM(DE31:DE37) -> 3.5128361e+08
A39: Share Capital | B39: 39654157 | C39: 42633397 | D39: 45827379 | E39: 46758589 | F39: 7234210 | G39: 6384515 | H39: 29031754 | I39: 30295797 | J39: 30374854 | K39: 30458377 | L39: 30496327 | M39: 30601194 | N39: 30741444 | O39: 30982542 | P39: 31205332 | Q39: 31359394 | R39: 31478786 | S39: 31560786 | T39: 31690048 | U39: 31816457 | V39: 37302914 | W39: 37326707 | X39: 37355231 | Y39: 37499688 | Z39: 37614688 | AA39: 37739780 | AB39: 38173480 | AC39: 38695298 | AD39: 38894098 | AE39: 38977898 | AF39: 39026898 | AG39: 39061898 | AH39: 44659170 | AI39: 44659171 | AJ39: 44743259 | AK39: 44817259 | AL39: 44880859 | AM39: 44950459 | AN39: 45097359 | AO39: 45354840 | AP39: 45459140 | AQ39: 45598940 | AR39: 45677790 | AS39: 45771505 | AT39: 45885591 | AU39: 45958981 | AV39: 51220150 | AW39: 51274918 | AX39: 51389970 | AY39: 51449946 | AZ39: 51557960 | BA39: 52114502 | BB39: 52450928 | BC39: 52710774 | BD39: 52889882 | BE39: 52997068 | BF39: 53128365 | BG39: 53410692 | BH39: 58962034 | BI39: 58962034 | BJ39: 59174647 | BK39: 59307947 | BL39: 59510137 | BM39: 59661537 | BN39: 59793337 | BO39: 59900537 | BP39: 60573193 | BQ39: 60859093 | BR39: 61012093 | BS39: 61139610 | BT39: 61290690 | BU39: 66711730 | BV39: 66711729 | BW39: 66839130 | BX39: 66942030 | BY39: 67024730 | BZ39: 67228416 | CA39: 67195060 | CB39: 67539981 | CC39: 67783453 | CD39: 67986283 | CE39: 68176578 | CF39: 68306878 | CG39: 68433278 | CH39: 68433278 | CI39: 68636428 | CJ39: 68700328 | CK39: 68784228 | CL39: 68852728 | CM39: 68933138 | CN39: 69003738 | CO39: 69120988 | CP39: 69151988 | CQ39: 69504626 | CR39: 70390202 | CS39: 70538002 | CT39: 70707252 | CU39: 70707252 | CV39: 77017592 | CW39: 77287991 | CX39: 77557841 | CY39: 77824566 | CZ39: 78015216 | DA39: 78347332 | DB39: 78671212 | DC39: 79543392 | DD39: 80174491 | DE39: 80618050
A40: Capital Grants | J40: 0 | K40: 0 | L40: 0 | M40: 0 | N40: 0 | O40: 0 | P40: 0 | Q40: 0 | R40: 0 | S40: 0 | T40: 0 | U40: 0 | W40: 0 | X40: 0 | Y40: 0 | Z40: 0 | AA40: 0 | AB40: 163561391 | AC40: 163561391 | AD40: 163561391 | AE40: 163561391 | AF40: 163561391 | AG40: 163561391 | AH40: 163561391 | AI40: 79163018 | AJ40: 163561391 | AK40: 163561391 | AL40: 163561391 | AM40: 163561391 | AN40: 163561391 | AO40: 163561391 | AP40: 163561391 | AQ40: 163561391 | AR40: 163561391 | AS40: 163561391 | AT40: 163561391 | AU40: 163561391 | AV40: 163561391 | AW40: 163561391 | AX40: 163561391 | AY40: 163561391 | AZ40: 163561391 | BA40: 163561391 | BB40: 163561391 | BC40: 163561391 | BD40: 163561391 | BE40: 163561391 | BF40: 163561391 | BG40: 163561391 | BH40: 163561391 | BI40: 163561391 | BJ40: 163561391 | BK40: 163561391 | BL40: 163561391 | BM40: 163561391 | BN40: 163561391 | BO40: 163561391 | BP40: 163561391 | BQ40: 163561391 | BR40: 163561391 | BS40: 163561391 | BT40: 163561391 | BU40: 163561391 | BV40: 163561391 | BW40: 163561391 | BX40: 163561391 | BY40: 163561391 | BZ40: 163561391 | CA40: 163561391 | CB40: 163561391 | CC40: 163561391 | CD40: 163561391 | CE40: 163561391 | CF40: 163561391 | CG40: 163561391 | CH40: 163561391 | CI40: 163561391 | CJ40: 163561391 | CK40: 163561391 | CL40: 163561391 | CM40: 163561391 | CN40: 163561391 | CO40: 163561391 | CP40: 163561391 | CQ40: 163561391 | CR40: 163561391 | CS40: 163561391 | CT40: 163561391 | CU40: 163561391 | CV40: 163561391 | CW40: 163561391 | CX40: 163561391 | CY40: 163561391 | CZ40: 163561391 | DA40: 163561391 | DB40: 163561391 | DC40: 163561391 | DD40: 163561391 | DE40: 163561391
A41: Prior Year Retained Earnigs | F41: -115950062 | G41: -116905773 | H41: -123040086 | I41: 49993382 | J41: 57092304 | K41: 57835132 | L41: 57835132 | M41: 57835132 | N41: 54585301 | O41: 54585301 | P41: 54585301 | Q41: 54585301 | R41: 54585301 | S41: -81477078 | T41: -82127078 | U41: -82127078 | V41: =-82339117-27338672 -> -109677789 | W41: -82127078 | X41: -82163214 | Y41: -82224151 | Z41: -82225841 | AA41: -82546764 | AB41: -106964013 | AC41: -1.0696338e+08 | AD41: -1.0696338e+08 | AE41: -106984383 | AF41: -106987284 | AG41: -106987284 | AH41: -116058311 | AI41: -107127007 | AJ41: -112205112 | AK41: -115411797 | AL41: -115411797 | AM41: -1.1462557e+08 | AN41: -1.1462557e+08 | AO41: -1.139161e+08 | AP41: -1.1406151e+08 | AQ41: -1.1405802e+08 | AR41: -1.1405802e+08 | AS41: -1.1427865e+08 | AT41: -1.1428205e+08 | AU41: -1.1427865e+08 | AV41: -114885111 | AW41: -1.0744527e+08 | AX41: -1.0742332e+08 | AY41: -1.0745267e+08 | AZ41: -1.0744017e+08 | BA41: -1.1166081e+08 | BB41: -1.1166081e+08 | BC41: -1.1310365e+08 | BD41: -1.1318899e+08 | BE41: -1.1317677e+08 | BF41: -1.1316032e+08 | BG41: -1.1316032e+08 | BH41: -1.1330413e+08 | BJ41: -1.1131316e+08 | BK41: -1.1131316e+08 | BL41: -1.1128443e+08 | BM41: -1.1128443e+08 | BN41: -1.1128938e+08 | BO41: -1.1128938e+08 | BP41: -1.1126688e+08 | BQ41: -1.1126688e+08 | BR41: -1.1126688e+08 | BS41: -1.1318168e+08 | BT41: -1.1317673e+08 | BU41: -1.134572e+08 | BW41: -1.0252601e+08 | BX41: -1.0252601e+08 | BY41: -1.0252601e+08 | BZ41: -1.0252601e+08 | CA41: -1.0252601e+08 | CB41: -1.037163e+08 | CC41: -1.054817e+08 | CD41: -1.0548041e+08 | CE41: -1.0548041e+08 | CF41: -1.0548041e+08 | CG41: -1.0561029e+08 | CH41: =-100842397-8514089 -> -109356486 | CI41: -97094425 | CJ41: -97094425 | CK41: -97094425 | CL41: -97094425 | CM41: -97317647 | CN41: -97316647 | CO41: -97316647 | CP41: -99263019 | CQ41: -99263019 | CR41: -99263019 | CS41: -99449782 | CT41: -99533275 | CU41: -87318842 | CV41: =-87318842 -> -87318842 | CW41: -67562652 | CX41: -67658261 | CY41: -67759932 | CZ41: -67859932 | DA41: -69979229 | DB41: -70179229 | DC41: -70999128 | DD41: -70366496 | DE41: -70366496
A42: Current Year Surplus | B42: -130940764 | C42: -116486412 | D42: -116181177 | E42: -115950062 | F42: -955711.15 | G42: =-1402826.62-4731486.71 -> -6134313.3 | H42: =6650208-1311042-95000-4200000-6224355 -> -5180189 | I42: =-4913141-651967+9577031-1785013 -> 2226910 | J42: 47850246 | K42: 45789586 | L42: 48191825 | M42: 45716944 | N42: 45642436 | O42: 1.0959294e+08 | P42: 1.0655574e+08 | Q42: 94673557 | R42: 95635875 | S42: -177104.95 | T42: 291803.16 | U42: 352055.5 | V42: =3533017-637695-344540 -> 2550782 | W42: -1751482 | X42: -2020632 | Y42: -1667106 | Z42: -4580025.6 | AA42: -6974110 | AB42: 3984840 | AC42: 10245189 | AD42: 9397571 | AE42: 6864348 | AF42: 4675375 | AG42: 3537371.7 | AH42: 3275621.6 | AI42: -8272686 | AJ42: -1273664.9 | AK42: -2418322.6 | AL42: -4026833 | AM42: -6271929.5 | AN42: 4970410.1 | AO42: 4232213.1 | AP42: 9325556.5 | AQ42: 9476242.6 | AR42: 5457402.7 | AS42: 4304103.2 | AT42: 7770391.7 | AU42: 6088530.1 | AV42: =268110+893699-178740 -> 983069 | AW42: 256615.05 | AX42: 1772847.8 | AY42: 1644693.8 | AZ42: 753600.8 | BA42: 13088010 | BB42: 11716333 | BC42: 16625033 | BD42: 15559286 | BE42: 11035639 | BF42: 11261568 | BG42: 9536226.5 | BH42: 1989229.5 | BJ42: -202442.76 | BK42: -2757121.5 | BL42: -1572399.7 | BM42: -3013962.1 | BN42: -5392383.8 | BO42: -2776123.2 | BP42: 20653432 | BQ42: 19887512 | BR42: 17337132 | BS42: 15958595 | BT42: 12817639 | BU42: 10929458 | BW42: -1625892.4 | BX42: -7871405.1 | BY42: -9667210.7 | BZ42: -2310492.3 | CA42: -3658232.4 | CB42: 13277539 | CC42: 14305206 | CD42: 18238936 | CE42: 20559541 | CF42: 17036661 | CG42: 8514088.8 | CH42: 8514089 | CI42: -2723103.5 | CJ42: -6723743.5 | CK42: -8277081.9 | CL42: -1525729.3 | CM42: -5879876.9 | CN42: -10736905 | CO42: -13482934 | CP42: -21124000 | CQ42: -27727835 | CR42: 9850147.1 | CS42: 14713687 | CT42: 21811485 | CV42: =13710012-1919402-4113004+4921767+494802 -> 13094175 | CW42: -1363497.8 | CX42: -4306039.1 | CY42: -4890257.2 | CZ42: -7368355 | DA42: -12707884 | DB42: -2501231.4 | DC42: 34683084 | DD42: 32866118 | DE42: 25752856
A43: Statutory Reserves | B43: 10535391 | C43: 10848979 | D43: 11035272 | E43: 11316801 | F43: 11316801 | G43: 11316801 | H43: 12627843 | I43: 14412856 | J43: 12627843 | K43: 12627843 | L43: 12627843 | M43: 12627843 | N43: 12627843 | O43: 12627843 | P43: 14412856 | Q43: 14412856 | R43: 14412856 | S43: 14412856 | T43: 14412856 | U43: 14412856 | V43: 15050551 | W43: 14412856 | X43: 14412856 | Y43: 14412856 | Z43: 14412856 | AA43: 14412856 | AB43: 15050551 | AC43: 15050551 | AD43: 15050551 | AE43: 15050551 | AF43: 15050551 | AG43: 15050551 | AH43: 15705675 | AI43: 15215344 | AJ43: 15705675 | AK43: 15215344 | AL43: 15215344 | AM43: 15179196 | AN43: 15179196 | AO43: 15179196 | AP43: 15179196 | AQ43: 15179196 | AR43: 15179196 | AS43: 15179196 | AT43: 15179196 | AU43: 15179196 | AV43: 15357936 | AW43: 15179196 | AX43: 15179196 | AY43: 15179196 | AZ43: 15179196 | BA43: 15179196 | BB43: 15179196 | BC43: 15291911 | BD43: 15291911 | BE43: 15291911 | BF43: 15291911 | BG43: 15291911 | BH43: 15291911 | BI43: 15699380 | BJ43: 15291911 | BK43: 15291911 | BL43: 15291911 | BM43: 15291911 | BN43: 15291911 | BP43: 15291911 | BQ43: 15291911 | BR43: 15291911 | BS43: 15699379 | BT43: 15699379 | BU43: 15699379 | BV43: 17509504 | BW43: 15699379 | BX43: 15699379 | BY43: 15699379 | BZ43: 15699379 | CA43: 15699379 | CB43: 15699379 | CC43: 17509504 | CD43: 17509504 | CE43: 17509504 | CF43: 17509504 | CG43: 17509504 | CH43: 18701476 | CI43: 17509504 | CJ43: 17509504 | CK43: 17509504 | CL43: 17509504 | CM43: 17509504 | CN43: 17509504 | CO43: 17509504 | CP43: 18701476 | CQ43: 18701476 | CR43: 18701476 | CS43: 18701476 | CT43: 18701476 | CU43: 21755084 | CV43: 23674486 | CW43: 21755084 | CX43: 21755084 | CY43: 21755084 | CZ43: 21755084 | DA43: 23674486 | DB43: 23674486 | DC43: 23674486 | DD43: 23674486 | DE43: 23674486
A44: Other Reserves | B44: =43033392+145020 -> 43178412 | C44: =43178412+145020 -> 43323432 | D44: 43178412 | E44: 43178412 | F44: 43033392 | G44: 43033392 | H44: 43033392 | I44: 75907044 | J44: 75907044 | K44: 75907044 | L44: 75907044 | M44: 75907044 | N44: 75907044 | O44: 75907044 | P44: 75907044 | Q44: 75907044 | R44: 75907044 | S44: 32873652 | T44: 179256111 | U44: 179256111 | V44: =163561391+75907044 -> 239468435 | W44: 179256111 | X44: 179256111 | Y44: 179256111 | Z44: 179256111 | AA44: 179256111 | AB44: 75907044 | AC44: 75907044 | AD44: 75907044 | AE44: 75907044 | AF44: 75907044 | AG44: 75907044 | AH44: 75907044 | AI44: 75907044 | AJ44: 75907044 | AK44: 75907044 | AL44: 75907044 | AM44: 75907044 | AN44: 75907044 | AO44: 75907044 | AP44: 75907044 | AQ44: 75907044 | AR44: 75907044 | AS44: 75907044 | AT44: 75907044 | AU44: 75907044 | AV44: 75907044 | AW44: 75907044 | AX44: 75907044 | AY44: 75907044 | AZ44: 75907044 | BA44: 75907044 | BB44: 75907044 | BC44: 75907044 | BD44: 75907044 | BE44: 75907044 | BF44: 75907044 | BG44: 75907044 | BH44: 75907044 | BI44: 75907044 | BJ44: 75907044 | BK44: 75907044 | BL44: 75907044 | BM44: 75907044 | BN44: 75907044 | BO44: 75907044 | BP44: 75907044 | BQ44: 75907044 | BR44: 75907044 | BS44: 75907044 | BT44: 75907044 | BU44: 75907044 | BV44: 75907044 | BW44: 75907044 | BX44: 75907044 | BY44: 75907044 | BZ44: 75907044 | CA44: 75907044 | CB44: 75907044 | CC44: 75907044 | CD44: 75907044 | CE44: 75907044 | CF44: 75907044 | CG44: 75907044 | CH44: 75907044 | CI44: 75907044 | CJ44: 75907044 | CK44: 75907044 | CL44: 75907044 | CM44: 75907044 | CN44: 75907044 | CO44: 75907044 | CP44: 75907044 | CQ44: 75907044 | CR44: 75907044 | CS44: 75907044 | CT44: 75907044 | CU44: 75907044 | CV44: =75907044 -> 75907044 | CW44: 75907044 | CX44: 75907044 | CY44: 75907044 | CZ44: 75907044 | DA44: 75907044 | DB44: 75907044 | DC44: 75907044 | DD44: 75907044 | DE44: 75907044
A45: Revaluation Reserves | S45: 179256111 | T45: 32873652 | U45: 32873652 | W45: 32873652 | X45: 32873652 | Y45: 32873652 | Z45: 32873652 | AA45: 32873652 | AB45: 0 | AC45: 0 | AD45: 0 | AE45: 0 | AF45: 0 | AG45: 0 | AH45: 0 | AW45: 0 | AX45: 0 | AY45: 0 | AZ45: 0 | BB45: 0 | BJ45: 0 | BK45: 0 | BL45: 0 | BM45: 0 | BN45: 0 | BO45: 0 | BP45: 0 | BQ45: 0 | BS45: 0 | BT45: 0 | BU45: 0 | BV45: -106216703 | BW45: 0 | BX45: 0 | BY45: 0 | BZ45: 0 | CA45: 0 | CB45: 0 | CC45: 0 | CD45: 0 | CE45: 0 | CF45: 0 | CG45: 0 | CI45: 0 | CJ45: 0 | CK45: 0 | CL45: 0 | CM45: 0 | CN45: 0 | CO45: 0 | CP45: 0 | CQ45: 0 | CR45: 0 | CS45: 0 | CT45: 0 | CV45: 32550815 | CW45: 32550815 | CX45: 32550815 | CY45: 32550815 | CZ45: 32550815 | DA45: 32550815 | DB45: 32550815 | DC45: 32550815 | DD45: 32550815 | DE45: 32550815
A46: Proposed Dividends | W46: 0 | X46: 0 | Y46: 0 | Z46: 0 | AA46: 0 | AB46: 0 | AC46: 0 | AD46: 0 | AE46: 0 | AF46: 0 | AG46: 0 | AH46: 0 | AI46: 1 | AW46: 0 | AX46: 0 | AY46: 0 | AZ46: 0 | BB46: 0 | BJ46: 0 | BK46: 0 | BL46: 0 | BM46: 0 | BN46: 0 | BO46: 0 | BP46: 0 | BQ46: 0 | BS46: 0 | BW46: 0 | BX46: 0 | BY46: 0 | BZ46: 0 | CA46: 0 | CB46: 0 | CC46: 0 | CD46: 0 | CE46: 0 | CF46: 0 | CG46: 0 | CI46: 0 | CJ46: 0 | CK46: 0 | CL46: 0 | CM46: 0 | CN46: 0 | CO46: 0 | CP46: 0 | CQ46: 0 | CR46: 0 | CS46: 0 | CT46: 0 | CW46: 0 | CX46: 0 | CY46: 0 | CZ46: 0 | DA46: 0 | DB46: 0 | DC46: 0 | DD46: 0 | DE46: 0
A47: Adjustment To Equity | BW47: 0 | BX47: 0 | BY47: 0 | BZ47: 0 | CA47: 0 | CB47: 0 | CC47: 0 | CD47: 0 | CE47: 0 | CF47: 0 | CG47: 0 | CI47: 0 | CJ47: 0 | CK47: 0 | CL47: 0 | CM47: 0 | CN47: 0 | CO47: 0 | CP47: 0 | CQ47: 0 | CR47: 0 | CS47: 0 | CT47: 0 | CW47: 0 | CX47: 0 | CY47: 0 | CZ47: 0 | DA47: 0 | DB47: 0 | DC47: 0 | DD47: 0 | DE47: 0
A48: Total Equity | B48: =SUM(B39:B47) -> -37572804 | C48: =SUM(C39:C47) -> -19680604 | D48: =SUM(D39:D47) -> -16140114 | E48: =SUM(E39:E47) -> -14696260 | F48: =SUM(F39:F47) -> -55321370 | G48: =SUM(G39:G47) -> -62305378 | H48: =SUM(H39:H47) -> -43527286 | I48: =SUM(I39:I47) -> 172835989 | ... DE48: =SUM(DE39:DE47) -> 3.3169815e+08
A49: Total Liabilities and Equity | B49: =SUM(B48+B38) -> 101042159 | C49: =SUM(C48+C38) -> 106803010 | D49: =SUM(D48+D38) -> 130959400 | E49: =SUM(E48+E38) -> 132850579 | F49: =SUM(F48+F38) -> 1.2630166e+08 | G49: =SUM(G48+G38) -> 2.5343074e+08 | H49: =SUM(H48+H38) -> 242665215 | I49: =SUM(I48+I38) -> 284500118 | ... DE49: =SUM(DE48+DE38) -> 6.8298175e+08
B51: =B49-B27 -> 0 | C51: =C49-C27 -> -148753 | D51: =D49-D27 -> 0 | E51: =E49-E27 -> 0 | F51: =F49-F27 -> 0.2 | G51: =G49-G27 -> 2998.79 | H51: =H49-H27 -> -1 | I51: =I49-I27 -> 0 | ... DE51: =DE49-DE27 -> 0

Sheet Evolutitve SCI
BV1: "000"
B2: Audited 2007 | C2: Audited 2008 | D2: Audited 2009 | E2: Audited 2010 | F2: Audited 2011 | G2: Audited 2012 | H2: Audited 2013 | I2: Audited 2014 | J2: 42005 | K2: 42036 | L2: 42064 | M2: 42095 | N2: 42125 | O2: 42156 | P2: 42186 | Q2: 42217 | R2: 42248 | S2: 42278 | T2: 42309 | U2: 42339 | V2: Audited 2015 | W2: 42370 | X2: 42401 | Y2: 42430 | Z2: 42461 | AA2: 42491 | AB2: 42522 | AC2: 42552 | AD2: 42583 | AE2: 42614 | AF2: 42644 | AG2: 42675 | AH2: 42705 | AI2: Audited 2016 | AJ2: 42736 | AK2: 42767 | AL2: 42795 | AM2: 42826 | AN2: 42856 | AO2: 42887 | AP2: 42917 | AQ2: 42948 | AR2: 42979 | AS2: 43009 | AT2: 43040 | AU2: 43070 | AV2: AUDITED 2017 | AW2: 43101 | AX2: 43132 | AY2: 43160 | AZ2: 43191 | BA2: 43221 | BB2: 43252 | BC2: 43282 | BD2: 43313 | BE2: 43344 | BF2: 43374 | BG2: 43405 | BH2: 43435 | BI2: Audited 2018 | BJ2: 43466 | BK2: 43497 | BL2: 43525 | BM2: 43556 | BN2: 43586 | BO2: 43617 | BP2: 43647 | BQ2: 43678 | BR2: 43709 | BS2: 43739 | BT2: 43770 | BU2: 43800 | BV2: Audited 2019 | BW2: 43831 | BX2: 43862 | BY2: 43891 | BZ2: 43922 | CA2: 43952 | CB2: 43983 | CC2: 44044 | CD2: 44075 | CE2: 44105 | CF2: 44136 | CG2: 44166 | CH2: Audited 2020 | CI2: 44197 | CJ2: 44228 | CK2: 44256 | CL2: 44287 | CM2: 44317 | CN2: 44348 | CO2: 44378 | CP2: 44409 | CQ2: 44440 | CR2: 44470 | CS2: 44501 | CT2: 44531 | CU2: AUDITED 2021 | CV2: AUDITED 2022 | CW2: 44927 | CX2: 44958 | CY2: 44986 | CZ2: 45017 | DA2: 45047 | DB2: 45078 | DC2: 45108 | DD2: 45139 | DE2: 45170
A3: Financial Income | B3: =B4+B7 -> 13158687 | C3: =C4+C7 -> 11857416 | D3: =D4+D7 -> 15384310 | E3: =E4+E7 -> 15961562 | F3: =F4+F7 -> 11480294 | G3: =G4+G7 -> 8973589.6 | H3: =H4+H7 -> 22684355 | I3: =I4+I7 -> 20513783 | ... DE3: =DE4+DE7 -> 73275129
A4: Financial Income From Loans Portfolio | B4: =SUM(B5:B6) -> 11379426 | C4: =SUM(C5:C6) -> 11438776 | D4: =SUM(D5:D6) -> 13726979 | E4: =SUM(E5:E6) -> 9328665 | F4: =SUM(F5:F6) -> 6088928 | G4: =SUM(G5:G6) -> 2789845.9 | H4: =SUM(H5:H6) -> 12329678 | I4: =SUM(I5:I6) -> 18685473 | ... DE4: =SUM(DE5:DE6) -> 50915900
A5: Interest from Loans Portfolio | B5: 10152482 | C5: 10211832 | D5: 12399467 | E5: 9281285 | F5: 6040159 | G5: 2789845.9 | H5: 7897863 | I5: =17456381+2277287 -> 19733668 | J5: 1162807.6 | K5: 1216044.4 | L5: 1586685.7 | M5: 1711984.9 | N5: 1921596.9 | O5: 9601630.1 | P5: 9767452.4 | Q5: 9953574 | R5: 10138157 | S5: 10316477 | T5: 11347332 | U5: 12517818 | V5: 19575641 | W5: 649462.04 | X5: 2663614 | Y5: 1947234 | Z5: 2636333.9 | AA5: 3491603 | AB5: 14227993 | AC5: 16738052 | AD5: 18333463 | AE5: 19694355 | AF5: 20684019 | AG5: 22023584 | AH5: 26354999 | AI5: 26354999 | AJ5: 1210333.4 | AK5: 1998296.3 | AL5: 2653801.4 | AM5: 3930006.4 | AN5: 14840284 | AO5: 16274655 | AP5: 19234639 | AQ5: 21208747 | AR5: 18337606 | AS5: 18668439 | AT5: 19907077 | AU5: 20641122 | AV5: 20641122 | AW5: 1521953.9 | AX5: 2792545.5 | AY5: 4105261.5 | AZ5: 5683462.5 | BA5: 16508988 | BB5: 18350279 | BC5: 19604598 | BD5: 20262501 | BE5: 21089272 | BF5: 22786412 | BG5: 23785976 | BH5: 25234232 | BI5: 25234232 | BJ5: 2147516.7 | BK5: 2796959.3 | BL5: 4053433.1 | BM5: 5168948 | BN5: 6568291.8 | BO5: 7360664.3 | BP5: 24339366 | BQ5: 26791529 | BR5: 27459301 | BS5: 28478076 | BT5: 29740382 | BU5: 32292356 | BV5: 32292356 | BW5: 885005.09 | BX5: 2669645.9 | BY5: 4156606.2 | BZ5: 8922644.2 | CA5: 10198918 | CB5: 20458900 | CC5: 23151979 | CD5: 28027805 | CE5: 29207338 | CF5: 30722944 | CG5: 32014808 | CH5: 32014808 | CI5: 1290259.8 | CJ5: 3189198.6 | CK5: 4721226.8 | CL5: 6563958.4 | CM5: 7907017.2 | CN5: 8963019.7 | CO5: 9991014.4 | CP5: 11381188 | CQ5: 12440411 | CR5: 36404952 | CS5: 38936870 | CT5: 43172690 | CU5: 43172690 | CV5: =526780+3135093+1595106+25864+15413073+770044+5505486+190780+30383+739704+733782+10417+768033+161850+1238588+489138 -> 31334121 | CW5: 2100203.5 | CX5: 3624906.6 | CY5: 6165554.7 | CZ5: 9360454.8 | DA5: 12293423 | DB5: 15773278 | DC5: 37460627 | DD5: 39790891 | DE5: 41082932
A6: Fees&Commision on Loan Portfolio | B6: =1166114+60830 -> 1226944 | C6: 1226944 | D6: 1327512 | E6: 47380 | F6: 48769 | H6: 4431815 | I6: =28901-3205-147756-926135 -> -1048195 | J6: 144309.5 | K6: 294814.8 | L6: 527926.8 | M6: 712380.8 | N6: 828785.6 | O6: 3416219.1 | P6: 4346846.1 | Q6: 4898474.7 | R6: 5433783.7 | S6: 5814868.7 | T6: 8078754.3 | U6: 5492273.2 | W6: 333197 | X6: 0 | Y6: 551892 | Z6: 691823 | AA6: 844113 | AB6: 1325244 | AC6: 2607385.9 | AD6: 3291983 | AE6: 3632122 | AF6: 3843085 | AG6: 4045534.8 | AH6: 4251404.8 | AI6: =4251404 -> 4251404 | AJ6: 189534 | AK6: 302675 | AL6: 424125.2 | AM6: 550085.2 | AN6: 695375 | AO6: 1433389 | AP6: 2630467.3 | AQ6: 3014789.7 | AR6: 3252005.8 | AS6: 3416575.4 | AT6: 3745274.4 | AU6: 3827118.4 | AV6: 3133581 | AW6: 282321 | AX6: 223477 | AY6: 346383 | AZ6: 631819.3 | BA6: 806702.3 | BB6: 3128075.9 | BC6: 2733255.1 | BD6: 3607007.1 | BE6: 3918449.1 | BF6: 4158088.6 | BG6: 4563784.6 | BH6: 4822610.6 | BI6: 4795166 | BJ6: 349162 | BK6: 561314 | BL6: 952901 | BM6: 1103350.3 | BN6: 1268652.2 | BO6: 1419501 | BP6: 2768146.6 | BQ6: 4180596.4 | BR6: 4821724.5 | BS6: 5363610.4 | BT6: 5873725 | BU6: 6189275.8 | BW6: 299084.7 | BX6: 550611.6 | BY6: 759043.6 | BZ6: 869645.6 | CA6: 1331582.4 | CB6: 2015553 | CC6: 4418391.5 | CD6: 5203757.2 | CE6: 6046948.3 | CF6: 6666721 | CG6: 7074173.5 | CI6: 388419.8 | CJ6: 752916.9 | CK6: 1163475.4 | CL6: 1519211.8 | CM6: 1821745.2 | CN6: 2106217.7 | CO6: 3079633.2 | CP6: 3712954.6 | CQ6: 3943552.1 | CR6: 5078648 | CS6: 6671438.2 | CT6: 7315271.1 | CU6: 4810957 | CV6: 14946316 | CW6: 709445.5 | CX6: 1139994.8 | CY6: 1516157.1 | CZ6: 1998602 | DA6: 2913913.2 | DB6: 3321826.4 | DC6: 6130097.6 | DD6: 8808486.7 | DE6: 9832968.4
A7: Financial Income from Investments | B7: =SUM(B8:B11) -> 1779261 | C7: =SUM(C8:C11) -> 418640 | D7: =SUM(D8:D11) -> 1657331 | E7: =SUM(E8:E11) -> 6632897 | F7: =SUM(F8:F11) -> 5391365.8 | G7: =SUM(G8:G11) -> 6183743.7 | H7: =SUM(H8:H11) -> 10354677 | I7: =SUM(I8:I11) -> 1828310 | ... DE7: =SUM(DE8:DE11) -> 22359229
A8: Government Securities | J8: 0 | K8: 0 | L8: 0 | M8: 0 | N8: 0 | O8: 0 | P8: 0 | Q8: 0 | R8: 0 | S8: 0 | T8: 0 | U8: 0 | V8: 0 | W8: 0 | X8: 0 | Y8: 0 | Z8: 0 | AA8: 0 | AB8: 0 | AC8: 0 | AD8: 0 | AE8: 0 | AF8: 0 | AG8: 0 | AH8: 0 | AI8: 0 | AJ8: 0 | AK8: 0 | AL8: 0 | AM8: 0 | AN8: 0 | AO8: 0 | AP8: 0 | AQ8: 0 | AR8: 0 | AS8: 0 | AT8: 0 | AU8: 0 | AV8: 0 | AW8: 0 | AX8: 0 | AY8: 0 | AZ8: 0 | BA8: 0 | BB8: 0 | BC8: 0 | BD8: 0 | BE8: 0 | BF8: 0 | BG8: 0 | BH8: 0 | BJ8: 0 | BK8: 0 | BL8: 0 | BM8: 0 | BN8: 0 | BO8: 0 | BP8: 0 | BQ8: 0 | BR8: 0 | BS8: 0 | BT8: 0 | BU8: 0 | BW8: 0 | BX8: 0 | BY8: 0 | BZ8: 0 | CA8: 0 | CB8: 0 | CC8: 0 | CD8: 0 | CE8: 0 | CF8: 0 | CG8: 0 | CI8: 0 | CJ8: 0 | CK8: 0 | CL8: 0 | CM8: 0 | CN8: 0 | CO8: 0 | CP8: 0 | CW8: 0 | CX8: 0 | CY8: 0 | CZ8: 0 | DA8: 0 | DB8: 0 | DC8: 0 | DD8: 0 | DE8: 0
A9: Deposits with Banks & other Financial Institutions | E9: 145384 | F9: 841581 | I9: 1824740 | T9: 0 | U9: 0 | V9: 0 | W9: 0 | X9: 0 | Y9: 0 | Z9: 0 | AA9: 0 | AB9: 0 | AC9: 0 | AD9: 0 | AE9: 0 | AF9: 0 | AG9: 0 | AH9: 0 | AI9: 0 | AJ9: 0 | AK9: 0 | AL9: 0 | AM9: 0 | AN9: 0 | AO9: 0 | AP9: 0 | AQ9: 0 | AR9: 0 | AS9: 0 | AT9: 0 | AU9: 0 | AV9: 4604960 | AW9: 0 | AX9: 0 | AY9: 0 | AZ9: 0 | BA9: 0 | BB9: 0 | BC9: 0 | BD9: 0 | BE9: 0 | BF9: 0 | BG9: 0 | BH9: 0 | BI9: 4597538 | BJ9: 0 | BK9: 0 | BL9: 0 | BM9: 0 | BN9: 0 | BO9: 0 | BP9: 0 | BQ9: 0 | BR9: 0 | BS9: 0 | BT9: 0 | BU9: 0 | BV9: 5415233 | BW9: 0 | BX9: 0 | BY9: 0 | BZ9: 0 | CA9: 0 | CB9: 0 | CC9: 0 | CD9: 0 | CE9: 0 | CF9: 0 | CG9: 0 | CH9: 7298266 | CI9: 0 | CJ9: 0 | CK9: 0 | CL9: 0 | CM9: 0 | CN9: 0 | CO9: 0 | CP9: 0 | CW9: 0 | CX9: 0 | CY9: 0 | CZ9: 0 | DA9: 0 | DB9: 0 | DC9: 0 | DD9: 0 | DE9: 0
A10: Other Investments | C10: 242821 | D10: 263308 | E10: 540680 | F10: 1030283 | H10: =734825+52145+706662-391551-113296+52497+1752874+8820 -> 2802976 | J10: 0 | K10: 0 | L10: 0 | M10: 0 | N10: 0 | O10: 0 | P10: 2296935 | Q10: 2296935 | R10: 2296935 | S10: 2296935 | T10: 2296935 | U10: 2296935 | V10: 0 | AB10: 0 | AC10: 0 | AD10: 0 | AE10: 0 | AF10: 0 | AG10: 0 | AH10: 0 | AJ10: 0 | AK10: 0 | AL10: 0 | AM10: 0 | AN10: 0 | AO10: 0 | AP10: 0 | AQ10: 0 | AR10: 0 | AS10: 0 | AT10: 0 | AU10: 0 | AV10: 0 | AW10: 0 | AX10: 0 | AY10: 0 | AZ10: 0 | BA10: 0 | BB10: 0 | BC10: 0 | BD10: 0 | BE10: 0 | BF10: 0 | BG10: 0 | BH10: 0 | BJ10: 0 | BK10: 0 | BL10: 0 | BM10: 0 | BN10: 0 | BO10: 0 | BP10: 0 | BQ10: 0 | BR10: 0 | BS10: 0 | BT10: 0 | BU10: 0 | BW10: 0 | BX10: 0 | BY10: 0 | BZ10: 0 | CA10: 0 | CB10: 0 | CC10: 0 | CD10: 8497655.1 | CE10: 10938597 | CF10: 10944520 | CG10: 13091735 | CI10: 0 | CJ10: 0 | CK10: 0 | CL10: 0 | CM10: 0 | CN10: 0 | CO10: 0 | CP10: 0 | CW10: 0 | CX10: 0 | CY10: 0 | CZ10: 0 | DA10: 0 | DB10: 0 | DC10: 0 | DD10: 0 | DE10: 0
A11: Other Operating Income | B11: =1360424+240267+89013+89557 -> 1779261 | C11: 175819 | D11: 1394023 | E11: 5946833 | F11: 3519501.8 | G11: 6183743.7 | H11: 7551701 | I11: 3570 | J11: 636426.28 | K11: 1866682.3 | L11: 2417816.3 | M11: 2931194.7 | N11: 3767064.7 | O11: 5876296.2 | P11: 6618126 | Q11: 7402078.7 | R11: 8140911.7 | S11: 8754105.7 | T11: 8642899.2 | U11: 14024529 | V11: 16542501 | W11: 696667.33 | X11: 5067417.1 | Y11: 2291785 | Z11: 3496432 | AA11: 4204775 | AB11: 5266767 | AC11: 10790937 | AD11: 11751613 | AE11: 12921704 | AF11: 13597629 | AG11: 14281394 | AH11: 15601172 | AI11: 14167079 | AJ11: 663030.5 | AK11: 1162049.6 | AL11: 2361933.4 | AM11: 3283229.7 | AN11: 3982334 | AO11: 5380917 | AP11: 9678689.6 | AQ11: 10632487 | AR11: 13280927 | AS11: 14137816 | AT11: 14787617 | AU11: 16349709 | AV11: =17043245-4604960 -> 12438285 | AW11: 659756.5 | AX11: 1515788 | AY11: 3145587.4 | AZ11: 3635402 | BA11: 5877249.5 | BB11: 5173214.5 | BC11: 12075238 | BD11: 12422700 | BE11: 13278449 | BF11: 15008838 | BG11: 15516495 | BH11: 17455039 | BI11: 12884946 | BJ11: 1083747.6 | BK11: 1686529.9 | BL11: 2315517.2 | BM11: 3023394 | BN11: 3898925.1 | BO11: 10207932 | BP11: 12396686 | BQ11: 13699014 | BR11: 14726115 | BS11: 16562070 | BT11: 17604775 | BU11: 20158805 | BV11: 20932347 | BW11: 470005.76 | BX11: 1148238.8 | BY11: 1771807.6 | BZ11: 9794754.3 | CA11: 10708443 | CB11: 11726948 | CC11: 14621940 | CD11: 7135248.1 | CE11: 8012806.9 | CF11: 8689497.7 | CG11: 8075428.8 | CH11: 20943071 | CI11: 602795.83 | CJ11: 1241902.9 | CK11: 2076950 | CL11: 10180808 | CM11: 10821550 | CN11: 11409091 | CO11: 12995544 | CP11: 13724697 | CQ11: 14371927 | CR11: 16339188 | CS11: 17305609 | CT11: 19598246 | CU11: 22102560 | CV11: =770746+1625219+136480+129230+820+7413+5809104+17490+35575+2500+605376+548325+88729+30009+9610+4083509+9894439 -> 23794574 | CW11: 957020.62 | CX11: 2492490.9 | CY11: 3813210.4 | CZ11: 5365694.9 | DA11: 6971332.5 | DB11: 17442148 | DC11: 19195464 | DD11: 21291726 | DE11: 22359229
A12: Financial Expenses | B12: =SUM(B13:B18) -> 2779329 | C12: =SUM(C13:C18) -> 622913 | D12: =SUM(D13:D18) -> 168581 | E12: =SUM(E13:E18) -> 3153250 | F12: =SUM(F13:F18) -> 1625181 | G12: =SUM(G13:G18) -> 0 | H12: =SUM(H13:H18) -> 51517 | I12: =SUM(I13:I18) -> 6737881 | ... DE12: =SUM(DE13:DE18) -> 0
A13: Interest Expense on Deposits | E13: 2968189 | F13: 1625181 | I13: =1824740 -> 1824740 | J13: 0 | K13: 0 | L13: 0 | M13: 0 | N13: 0 | O13: 0 | P13: 0 | Q13: 0 | R13: 0 | S13: 0 | T13: 0 | U13: 0 | V13: 3589171 | W13: 0 | X13: 0 | Y13: 0 | Z13: 7800 | AA13: 7800 | AB13: 7800 | AC13: 8175 | AD13: 8175 | AE13: 8175 | AF13: 14425 | AG13: 14425 | AH13: 14425 | AI13: 4048705 | AJ13: 0 | AK13: 0 | AL13: 0 | AM13: 0 | AN13: 0 | AO13: 0 | AP13: 0 | AQ13: 0 | AR13: 0 | AS13: 0 | AT13: 0 | AU13: 0 | AV13: 4275560 | AW13: 0 | AX13: 0 | AY13: 0 | AZ13: 0 | BA13: 0 | BB13: 0 | BC13: 0 | BD13: 0 | BE13: 0 | BF13: 0 | BG13: 0 | BH13: 0 | BI13: 5041448 | BJ13: 0 | BK13: 0 | BL13: 0 | BM13: 0 | BN13: 0 | BO13: 0 | BP13: 0 | BQ13: 0 | BR13: 0 | BS13: 0 | BT13: 0 | BU13: 0 | BV13: 6105198 | BW13: 0 | BX13: 0 | BY13: 0 | BZ13: 0 | CA13: 0 | CB13: 75860 | CC13: 78380 | CD13: 78380 | CE13: 114544 | CF13: 144049 | CG13: 7000000 | CH13: 7169807 | CI13: 0 | CJ13: 0 | CK13: 0 | CL13: 0 | CM13: 0 | CN13: 0 | CO13: 0 | CP13: 0 | CQ13: 0 | CR13: 0 | CS13: 0 | CT13: 0 | CU13: 7785466 | CV13: =9300000+500792 -> 9800792 | CW13: 0 | CX13: 0 | CY13: 0 | CZ13: 0 | DA13: 0 | DB13: 0 | DC13: 0 | DD13: 0 | DE13: 0
A14: Cost of External Borrowings | B14: 2586917 | C14: 404095 | J14: 0 | K14: 0 | L14: 0 | M14: 0 | N14: 0 | O14: 0 | P14: 0 | Q14: 0 | R14: 0 | S14: 0 | T14: 0 | U14: 0 | W14: 0 | X14: 0 | Y14: 0 | Z14: 0 | AA14: 0 | AB14: 0 | AC14: 0 | AD14: 0 | AE14: 0 | AF14: 0 | AG14: 0 | AH14: 0 | AI14: 0 | AJ14: 0 | AK14: 0 | AL14: 0 | AM14: 0 | AN14: 0 | AO14: 0 | AP14: 0 | AQ14: 0 | AR14: 0 | AS14: 0 | AT14: 0 | AU14: 0 | AV14: 0 | AW14: 0 | AX14: 0 | AY14: 0 | AZ14: 0 | BA14: 0 | BB14: 0 | BC14: 0 | BD14: 0 | BE14: 0 | BF14: 0 | BG14: 0 | BH14: 0 | BI14: 0 | BJ14: 0 | BK14: 0 | BL14: 0 | BM14: 0 | BN14: 0 | BO14: 0 | BP14: 0 | BQ14: 0 | BR14: 0 | BS14: 0 | BT14: 0 | BU14: 0 | BW14: 0 | BX14: 0 | BY14: 0 | BZ14: 0 | CA14: 0 | CB14: 0 | CC14: 0 | CD14: 0 | CE14: 0 | CF14: 0 | CG14: 0 | CI14: 0 | CJ14: 0 | CK14: 0 | CL14: 0 | CM14: 0 | CN14: 0 | CO14: 0 | CP14: 0 | CQ14: 0 | CR14: 0 | CS14: 0 | CT14: 0 | CU14: 0 | CV14: 0 | CW14: 0 | CX14: 0 | CY14: 0 | CZ14: 0 | DA14: 0 | DB14: 0 | DC14: 0 | DD14: 0 | DE14: 0
A15: Dividend Expenses | I15: 4913141 | J15: 0 | K15: 0 | L15: 0 | M15: 0 | N15: 0 | O15: 0 | P15: 0 | Q15: 0 | R15: 0 | S15: 0 | T15: 0 | U15: 0 | W15: 0 | X15: 0 | Y15: 0 | Z15: 0 | AA15: 0 | AB15: 0 | AC15: 0 | AD15: 0 | AE15: 0 | AF15: 0 | AG15: 0 | AH15: 0 | AI15: 0 | AJ15: 0 | AK15: 0 | AL15: 0 | AM15: 0 | AN15: 0 | AO15: 0 | AP15: 0 | AQ15: 0 | AR15: 0 | AS15: 0 | AT15: 0 | AU15: 0 | AV15: 0 | AW15: 0 | AX15: 0 | AY15: 0 | AZ15: 0 | BA15: 0 | BB15: 0 | BC15: 0 | BD15: 0 | BE15: 0 | BF15: 0 | BG15: 0 | BH15: 0 | BI15: 0 | BJ15: 0 | BK15: 0 | BL15: 0 | BM15: 0 | BN15: 0 | BO15: 0 | BP15: 0 | BQ15: 0 | BR15: 0 | BS15: 0 | BT15: 0 | BU15: 0 | BW15: 0 | BX15: 0 | BY15: 0 | BZ15: 0 | CA15: 0 | CB15: 0 | CC15: 0 | CD15: 0 | CE15: 0 | CF15: 0 | CG15: 0 | CI15: 0 | CJ15: 0 | CK15: 0 | CL15: 0 | CM15: 0 | CN15: 0 | CO15: 0 | CP15: 0 | CQ15: 0 | CR15: 0 | CS15: 0 | CT15: 0 | CU15: 0 | CV15: 0 | CW15: 0 | CX15: 0 | CY15: 0 | CZ15: 0 | DA15: 0 | DB15: 0 | DC15: 0 | DD15: 0 | DE15: 0
A16: Other Financial Expense | B16: =71521+120891 -> 192412 | C16: 218818 | D16: 168581 | E16: 185061 | H16: 51517 | J16: 0 | K16: 0 | L16: 0 | M16: 0 | N16: 0 | O16: 2195 | P16: 0 | Q16: 2195 | R16: 2855 | S16: 71214 | T16: 71214 | U16: 76631.5 | W16: 0 | X16: 0 | Y16: 0 | Z16: 0 | AA16: 0 | AB16: 0 | AC16: 0 | AD16: 0 | AE16: 0 | AF16: 0 | AG16: 0 | AH16: 0 | AI16: 0 | AJ16: 0 | AK16: 0 | AL16: 0 | AM16: 0 | AN16: 0 | AO16: 0 | AP16: 0 | AQ16: 0 | AR16: 0 | AS16: 0 | AT16: 0 | AU16: 0 | AV16: 0 | AW16: 0 | AX16: 0 | AY16: 0 | AZ16: 0 | BA16: 0 | BB16: 0 | BC16: 0 | BD16: 0 | BE16: 0 | BF16: 0 | BG16: 0 | BH16: 0 | BI16: 0 | BJ16: 0 | BK16: 0 | BL16: 0 | BM16: 0 | BN16: 0 | BO16: 0 | BP16: 0 | BQ16: 0 | BR16: 0 | BS16: 0 | BT16: 0 | BU16: 0 | BW16: 0 | BX16: 0 | BY16: 0 | BZ16: 0 | CA16: 0 | CB16: 0 | CC16: 0 | CD16: 0 | CE16: 0 | CF16: 0 | CG16: 0 | CI16: 0 | CJ16: 0 | CK16: 0 | CL16: 0 | CM16: 0 | CN16: 0 | CO16: 0 | CP16: 0 | CQ16: 0 | CR16: 0 | CS16: 0 | CT16: 0 | CU16: 0 | CV16: 0 | CW16: 0 | CX16: 0 | CY16: 0 | CZ16: 0 | DA16: 0 | DB16: 0 | DC16: 0 | DD16: 0 | DE16: 0
A17: Fees & Commision Expense | J17: 8390 | K17: 648930 | L17: 674820 | M17: 683210 | N17: 699660 | O17: 716110 | P17: 795490 | Q17: 884130 | R17: 901610 | S17: 911640 | T17: 983080 | U17: 981840 | W17: 0 | X17: 0 | Y17: 0 | Z17: 0 | AA17: 0 | AB17: 0 | AC17: 0 | AD17: 0 | AE17: 0 | AF17: 0 | AG17: 0 | AH17: 0 | AI17: 0 | AJ17: 0 | AK17: 0 | AL17: 0 | AM17: 0 | AN17: 0 | AO17: 0 | AP17: 0 | AQ17: 0 | AR17: 0 | AS17: 0 | AT17: 0 | AU17: 0 | AV17: 0 | AW17: 0 | AX17: 0 | AY17: 0 | AZ17: 0 | BA17: 0 | BB17: 0 | BC17: 0 | BD17: 0 | BE17: 0 | BF17: 0 | BG17: 0 | BH17: 0 | BI17: 0 | BJ17: 0 | BK17: 0 | BL17: 0 | BM17: 0 | BN17: 0 | BO17: 0 | BP17: 0 | BQ17: 0 | BR17: 0 | BS17: 0 | BT17: 0 | BU17: 0 | BW17: 0 | BX17: 0 | BY17: 0 | BZ17: 0 | CA17: 0 | CB17: 0 | CC17: 0 | CD17: 0 | CE17: 0 | CF17: 0 | CG17: 0 | CI17: 0 | CJ17: 0 | CK17: 0 | CL17: 0 | CM17: 0 | CN17: 0 | CO17: 0 | CP17: 0 | CQ17: 0 | CR17: 0 | CS17: 0 | CT17: 0 | CU17: 0 | CV17: 0 | CW17: 0 | CX17: 0 | CY17: 0 | CZ17: 0 | DA17: 0 | DB17: 0 | DC17: 0 | DD17: 0 | DE17: 0
A18: Other Expenses | J18: 447090.9 | K18: 695456.8 | L18: 1271283.9 | M18: 1851185.6 | N18: 2306094.6 | O18: 2912244.1 | P18: 3867353.4 | Q18: 4518159.9 | R18: 5104346.8 | S18: 5833305.9 | T18: 0 | U18: 7654462.9 | V18: =76277+25000 -> 101277 | W18: 0 | X18: 0 | Y18: 0 | Z18: 0 | AA18: 0 | AB18: 0 | AC18: 0 | AD18: 0 | AE18: 0 | AF18: 0 | AG18: 0 | AH18: 0 | AI18: 0 | AJ18: 0 | AK18: 0 | AL18: 0 | AM18: 0 | AN18: 0 | AO18: 0 | AP18: 0 | AQ18: 0 | AR18: 0 | AS18: 0 | AT18: 0 | AU18: 0 | AV18: 0 | AW18: 0 | AX18: 0 | AY18: 0 | AZ18: 0 | BA18: 0 | BB18: 0 | BC18: 0 | BD18: 0 | BE18: 0 | BF18: 0 | BG18: 0 | BH18: 0 | BI18: 0 | BJ18: 0 | BK18: 0 | BL18: 0 | BM18: 0 | BN18: 0 | BO18: 0 | BP18: 0 | BQ18: 0 | BR18: 0 | BS18: 0 | BT18: 0 | BU18: 0 | BW18: 0 | BX18: 0 | BY18: 0 | BZ18: 0 | CA18: 0 | CB18: 0 | CC18: 0 | CD18: 0 | CE18: 0 | CF18: 0 | CG18: 0 | CI18: 0 | CJ18: 0 | CK18: 0 | CL18: 0 | CM18: 0 | CN18: 0 | CO18: 0 | CP18: 0 | CQ18: 0 | CR18: 0 | CS18: 0 | CT18: 0 | CU18: 0 | CV18: 0 | CW18: 0 | CX18: 0 | CY18: 0 | CZ18: 0 | DA18: 0 | DB18: 0 | DC18: 0 | DD18: 0 | DE18: 0
A19: Net Financial Income | B19: =B3-B12 -> 10379358 | C19: =C3-C12 -> 11234503 | D19: =D3-D12 -> 15215729 | E19: =E3-E12 -> 12808312 | F19: =F3-F12 -> 9855112.8 | G19: =G3-G12 -> 8973589.6 | H19: =H3-H12 -> 22632838 | I19: =I3-I12 -> 13775902 | ... DE19: =DE3-DE12 -> 73275129
A20: Allowance for Loan Loss | B20: =B21-B22 -> 3721845 | C20: =C21-C22 -> 4860905 | D20: =D21-D22 -> 8476830 | E20: =E21-E22 -> 0 | F20: =F21-F22 -> 458650 | G20: =G21-G22 -> 0 | H20: =H21-H22 -> 1330352 | I20: =I21-I22 -> 2277287 | ... DE20: =DE21-DE22 -> 5594318.1
A21: Provision for Loan Losses | B21: 3721845 | C21: 4860905 | D21: 8476830 | F21: 458650 | H21: 1330352 | I21: 2277287 | J21: 1525420.1 | K21: 1715254.6 | L21: 1581353.3 | M21: 1560645.6 | N21: 1329634.7 | O21: 1819986 | P21: 2355463.6 | Q21: 2667629.1 | R21: 3049289.1 | S21: 3193905.9 | T21: 3338256.9 | U21: 3736596.3 | V21: 3736596 | W21: 1574976.6 | X21: 3638617 | Y21: 1291892.1 | Z21: 2353528.7 | AA21: 3965084 | AB21: 3491281 | AC21: 4248542.9 | AD21: 4964208 | AE21: 6151133 | AF21: 7568882 | AG21: 8476568 | AH21: 9769186 | AI21: 9769186 | AJ21: 1222704 | AK21: 1956331 | AL21: 3165035.1 | AM21: 4733849.1 | AN21: 3001056.8 | AO21: 5101425.1 | AP21: 6404478 | AQ21: 7031208.7 | AR21: 7649164.6 | AS21: 8035598.7 | AT21: 5131415.8 | AU21: 5944652.3 | AV21: 6944652 | AW21: 330013.9 | AX21: -1308634.3 | AY21: -472091.3 | AZ21: -380369.7 | BA21: -2066990.2 | BB21: -783540.59 | BC21: 451920.9 | BD21: 1170213.4 | BE21: 2326386.1 | BF21: 15008838 | BG21: 4533804.1 | BH21: 7013807.5 | BI21: 7013807.5 | BJ21: 1516261.5 | BK21: 2740343.4 | BL21: 1140921.4 | BM21: 1682208.5 | BN21: 3089796 | BO21: 4967836.3 | BP21: -1214926 | BQ21: 1886381.3 | BR21: 2286873.7 | BS21: 3561686.6 | BT21: 6521791.6 | BU21: 1036249.2 | BV21: 1036246.2 | BW21: 515553.9 | BX21: 6174547.8 | BY21: 7665939.9 | BZ21: 10485616 | CA21: 11756524 | CB21: 3862638 | CC21: 5078697.1 | CD21: 4537302.3 | CE21: 3901374.6 | CF21: 5902563.1 | CG21: 6967222.8 | CH21: 6967223 | CI21: 2348372.2 | CJ21: 6215566.8 | CK21: 7666654.1 | CL21: 7898780.6 | CM21: 11908447 | CN21: 15871825 | CO21: 19595948 | CP21: 27158287 | CQ21: 32485313 | CR21: 17224953 | CS21: 12640764 | CT21: 1010744.4 | CU21: 1010744 | CV21: 0 | CW21: 1661066.4 | CX21: 4234523 | CY21: 5300052.6 | CZ21: 8299091 | DA21: 14862529 | DB21: 14850068 | DC21: -1394423.3 | DD21: 2793005.2 | DE21: 5594318.1
A22: Value of Loans Recovered | J22: 2648320.3 | K22: 4172868.6 | L22: 6291684.4 | M22: 7785567.9 | N22: 9600551.5 | O22: 73072513 | P22: 76975921 | Q22: 78695849 | R22: 80614087 | S22: 82042130 | T22: 0 | U22: 0 | W22: 0 | X22: 0 | Y22: 0 | Z22: 0 | AA22: 0 | AB22: 0 | AC22: 0 | AD22: 0 | AE22: 0 | AF22: 0 | AG22: 0 | AH22: 0 | AI22: 0 | AJ22: 0 | AK22: 0 | AL22: 0 | AM22: 0 | AN22: 0 | AO22: 0 | AP22: 0 | AQ22: 0 | AR22: 0 | AS22: 0 | AT22: 0 | AU22: 0 | AV22: 0 | AW22: 0 | AX22: 0 | AY22: 0 | AZ22: 0 | BA22: 0 | BB22: 0 | BC22: 0 | BD22: 0 | BE22: 0 | BF22: 0 | BG22: 0 | BH22: 0 | BJ22: 0 | BK22: 0 | BL22: 0 | BM22: 0 | BN22: 0 | BO22: 0 | BP22: 0 | BQ22: 0 | BR22: 0 | BS22: 0 | BT22: 0 | BU22: 0 | BW22: 0 | BX22: 0 | BY22: 0 | BZ22: 0 | CA22: 0 | CB22: 0 | CC22: 0 | CD22: 0 | CE22: 0 | CF22: 0 | CG22: 0 | CI22: 0 | CJ22: 0 | CK22: 0 | CL22: 0 | CM22: 0 | CN22: 0 | CO22: 0 | CP22: 0 | CQ22: 0 | CR22: 0 | CS22: 0 | CT22: 0 | CW22: 0 | CX22: 0 | CY22: 0 | CZ22: 0 | DA22: 0 | DB22: 0 | DC22: 0 | DD22: 0 | DE22: 0
A23: Operating Expeses | B23: =SUM(B24:B28) -> 2142646 | C23: =SUM(C24:C28) -> 4805658 | D23: =SUM(D24:D28) -> 5807436 | E23: =SUM(E24:E28) -> 11147282 | F23: =SUM(F24:F28) -> 10803260 | G23: =SUM(G24:G28) -> 13705076 | H23: =SUM(H24:H28) -> 14652953 | I23: =SUM(I24:I28) -> 8659465 | ... DE23: =SUM(DE24:DE28) -> 41927955
A24: Personel Expenses | B24: =351364+320110+105532+11600+41880+37234 -> 867720 | C24: 1660110 | D24: 1969819 | E24: 2577933 | F24: 3233358 | G24: =505056+14400+151152+4800+113800+279644+44000+1273925.73+184964+390651+26000+76900+93305+645165 -> 3803762.7 | H24: =1357152+1917462+440906+558884+30400+138890+163548+844910 -> 5452152 | I24: 1488847 | J24: 292210 | K24: 1209634.4 | L24: 1830507.1 | M24: 2209498.2 | N24: 2969589.4 | O24: 3594698.2 | P24: 4299333.8 | Q24: 5019258.2 | R24: 5715644.1 | S24: 6578008 | T24: 7202740.4 | U24: 8048948.9 | V24: 9764166 | W24: 923355.7 | X24: 3659091.8 | Y24: 1873735.9 | Z24: 3871782.1 | AA24: 5000461 | AB24: 6081812 | AC24: 7074015.7 | AD24: 6749759 | AE24: 8792458 | AF24: 9952909 | AG24: 10699402 | AH24: 11673199 | AI24: 11673199 | AJ24: 876695 | AK24: 1898445.9 | AL24: 2812347.9 | AM24: 3871896.9 | AN24: 4763377.9 | AO24: 5587562.4 | AP24: 6736788.9 | AQ24: 7825088.9 | AR24: 8735354.7 | AS24: 9799230.4 | AT24: 10825402 | AU24: 11868293 | AV24: 11868293 | AW24: 968581.3 | AX24: 2043442.5 | AY24: 3155683.8 | AZ24: 4351472.4 | BA24: 5645517.1 | BB24: 7553147 | BC24: 8956997.5 | BD24: 10126089 | BE24: 11368043 | BF24: 12652554 | BG24: 13804863 | BH24: 15041825 | BI24: 15041825 | BJ24: 1281570.6 | BK24: 2656253.8 | BL24: 4023744.4 | BM24: 5489840.6 | BN24: 6882798.3 | BO24: 8279955.5 | BP24: 9964709.7 | BQ24: 11507100 | BR24: 12800386 | BS24: 14559783 | BT24: 15930439 | BU24: 17536646 | BV24: 17536646 | BW24: 1410258 | BX24: 2942785.6 | BY24: 4454751.8 | BZ24: 5966166.5 | CA24: 7471253.2 | CB24: 8933622.9 | CC24: 11990948 | CD24: 13377234 | CE24: 14872020 | CF24: 16369413 | CG24: 18207692 | CH24: 18207692 | CI24: 1562958.6 | CJ24: 3087263.2 | CK24: 4662153 | CL24: 6169586.6 | CM24: 7686677.7 | CN24: 9273684.9 | CO24: 10838665 | CP24: 12414813 | CQ24: 14125216 | CR24: 15921025 | CS24: 17693476 | CT24: 20218638 | CU24: 20218637 | CV24: =17807684+155950+1614900+467039+383730+1618526 -> 22047829 | CW24: 1935573.5 | CX24: 3866452.8 | CY24: 5906308 | CZ24: 7905959.3 | DA24: 10194016 | DB24: 12326212 | DC24: 14426260 | DD24: 16523687 | DE24: 19102589
A25: Governance Expenses | C25: 816499 | D25: 785969 | E25: 919202 | F25: 1260108 | G25: =812271+369464+802961 -> 1984696 | H25: 1713793 | I25: 1567604 | J25: 131669 | K25: 663533 | L25: 1029191 | M25: 1516174 | N25: 1723337 | O25: 1943375 | P25: 2705939 | Q25: 2731493 | R25: 3316442 | S25: 3663294 | T25: 4301094.3 | U25: 4222795 | V25: 6193300 | W25: 133347 | X25: 534750 | Y25: 402423 | Z25: 1169945 | AA25: 1405285 | AB25: 1519670 | AC25: 1774723 | AD25: 2179204 | AE25: 5475782 | AF25: 5586992 | AG25: 5883435 | AH25: 6333379 | AI25: 6333379 | AJ25: 168353 | AK25: 311595 | AL25: 821708 | AM25: 1816521 | AN25: 2170860 | AO25: 2601131 | AP25: 3182919 | AQ25: 3303069.3 | AR25: 4768605.2 | AS25: 5006012.7 | AT25: 5227704.2 | AU25: 5515965.4 | AV25: 5515965 | AW25: 159433 | AX25: 349938.3 | AY25: 521994.45 | AZ25: 1418650.4 | BA25: 1780295.7 | BB25: 2228254.2 | BC25: 2554111.4 | BD25: 3008650.4 | BE25: 5766849.5 | BF25: 6299803 | BG25: 6448644.6 | BH25: 6853374.6 | BI25: 6853374.6 | BJ25: 271461.05 | BK25: 747080.75 | BL25: 913152.75 | BM25: 1444682.8 | BN25: 1700049 | BO25: 2251123.5 | BP25: 2610083.5 | BQ25: 3083631.5 | BR25: 5543509.2 | BS25: 5839539.2 | BT25: 6522340.2 | BU25: 7070378.3 | BV25: 7070378.3 | BW25: 232605.1 | BX25: 569972.3 | BY25: 775920.9 | BZ25: 992104.4 | CA25: 1205420.1 | CB25: 1436379.6 | CC25: 1931383.7 | CD25: 2183601.8 | CE25: 3472336.5 | CF25: 5135865.2 | CG25: 5905635.8 | CH25: 5905636 | CI25: 331662.7 | CJ25: 619739.4 | CK25: 1224382.7 | CL25: 2031772.7 | CM25: 2283887.7 | CN25: 2567069 | CO25: 2845213.4 | CP25: 3346624 | CQ25: 3911538.6 | CR25: 5964564.5 | CS25: 6628927.6 | CT25: 7399778.5 | CU25: 7399779 | CV25: =1107820+4175880+1006417+1063950+276175+743473 -> 8373715 | CW25: 333600 | CX25: 533151.05 | CY25: 891351.05 | CZ25: 2062191.1 | DA25: 2696858 | DB25: 3040608 | DC25: 3577474.4 | DD25: 4292718 | DE25: 7874479.1
A26: Marketing Expenses | F26: 60350 | H26: 135400 | I26: 891573 | J26: 100832 | K26: 129972 | L26: 458532 | M26: 774767 | N26: 889622 | O26: 1037417 | P26: 1021052 | Q26: 1826457 | R26: 1791222 | S26: 1920587 | T26: 5891170 | U26: 4989209 | V26: 2446302 | W26: 91815.02 | X26: 338040 | Y26: 146655 | Z26: 251970 | AA26: 447822 | AB26: 572450 | AC26: 671138 | AD26: 696263 | AE26: 758628 | AF26: 1367073 | AG26: 1408798 | AH26: 2003348 | AI26: 2003348 | AJ26: 206498 | AK26: 282430 | AL26: 318452 | AM26: 403284 | AN26: 486902 | AO26: 510874 | AP26: 883146 | AQ26: 906438 | AR26: 1000613 | AS26: 1098222 | AT26: 1132094 | AU26: 1528826 | AV26: 1528826 | AW26: 117323 | AX26: 246205 | AY26: 321353 | AZ26: 414215 | BA26: 622042 | BB26: 976838 | BC26: 945955 | BD26: 1061815 | BE26: 1108215 | BF26: 1236032 | BG26: 1415326 | BH26: 1775042 | BI26: 1775042 | BJ26: 113114 | BK26: 140869 | BL26: 275763 | BM26: 305338 | BN26: 686307 | BO26: 752121 | BP26: 1729865 | BQ26: 1771294 | BR26: 1764456 | BS26: 1903556 | BT26: 1977256 | BU26: 2476068 | BV26: 2476068 | BW26: 250741 | BX26: 287041 | BY26: 333046 | BZ26: 466083 | CA26: 729181 | CB26: 799712 | CC26: 1040767 | CD26: 1222148 | CE26: 1242838 | CF26: 1340867 | CG26: 1687546 | CH26: 1687546 | CI26: 6950 | CJ26: 69269 | CK26: 161975 | CL26: 214502 | CM26: 303696 | CN26: 338566 | CO26: 415820 | CP26: 525343 | CQ26: 505325 | CR26: 622834 | CS26: 1084433 | CT26: 1516164 | CU26: 1516164 | CV26: 2109891 | CW26: 34000 | CX26: 68783 | CY26: 135753 | CZ26: 213168 | DA26: 567633 | DB26: 635729 | DC26: 734992 | DD26: 1033492 | DE26: 1194580
A27: Depreciation and Amortization | B27: 585711 | C27: 501634 | D27: 500963 | E27: 418766 | F27: 1502177 | G27: 375444 | H27: 548504 | J27: 306657.42 | K27: 614447.28 | L27: 840407.2 | M27: 1219431.6 | N27: 1521051.9 | O27: 1788348.6 | P27: 1588173.8 | Q27: 1779604.5 | R27: 1983380.8 | S27: 2190398.4 | T27: 2387941.8 | U27: 2576055.8 | V27: 990241 | W27: 200446 | X27: 798020 | Y27: 588168.59 | Z27: 790681.72 | AA27: 983148 | AB27: 1156511 | AC27: 1351602.7 | AD27: 1542546 | AE27: 1542546 | AF27: 1933421.2 | AG27: 2125259.7 | AH27: 3167243.9 | AI27: 2593160 | AJ27: 185908.81 | AK27: 374508.21 | AL27: 562825.21 | AM27: 756327.21 | AN27: 968241.75 | AO27: 1158896.4 | AP27: 974596.75 | AQ27: 1792112.4 | AR27: 2056655.5 | AS27: 2344111.8 | AT27: 2407272.4 | AU27: 3117011.2 | AV27: 3899892 | AW27: 284360.05 | AX27: 569267.82 | AY27: 853647.07 | AZ27: 1069122 | BA27: 1311576.6 | BB27: 1504321 | BC27: 1474329.9 | BD27: 1585520.2 | BE27: 1788081 | BF27: 2018041.2 | BG27: 2237714.1 | BH27: 3575053.9 | BI27: 2653796 | BJ27: 148272 | BK27: 354251.1 | BL27: 528416.42 | BM27: 704033.96 | BN27: 872449.3 | BO27: 1042742.5 | BP27: 1245740.7 | BQ27: 1410203.2 | BR27: 1582020.1 | BS27: 1750426.4 | BT27: 1914288.5 | BU27: 3138119.4 | BV27: 3138119 | BW27: 198633.49 | BX27: 392600.59 | BY27: 582727.01 | BZ27: 767197.17 | CA27: 944108.38 | CB27: 1204180.8 | CC27: 1675447.9 | CD27: 1930123.3 | CE27: 2141534.9 | CF27: 2403061.8 | CG27: 2499320.8 | CH27: 2499321 | CI27: 152602.64 | CJ27: 306631 | CK27: 461788.65 | CL27: 619626.15 | CM27: 776942.29 | CN27: 939571.18 | CO27: 1089636.9 | CP27: 1291032 | CQ27: 1451512.9 | CR27: 1612857.2 | CS27: 1836567.2 | CT27: 1994961.4 | CU27: 1994960 | CV27: 3080929 | CW27: 342731.84 | CX27: 543903.3 | CY27: 750543.47 | CZ27: 968003.59 | DA27: 1128535.9 | DB27: 1328590.7 | DC27: 1524237.4 | DD27: 1760852.1 | DE27: 1938630.9
A28: Administrative Expenses | B28: =100+194402+38950+104691+40067+60986+228000+22019 -> 689215 | C28: 1827415 | D28: 2550685 | E28: 7231381 | F28: 4747267 | G28: =8420624.05+5284452.28-G24-G25-G27 -> 7541173.6 | H28: =3829793+640980+8405+233528+79625+37100+103400+398810+186751+265577+307189+421500+290446 -> 6803104 | I28: =5603014-891573 -> 4711441 | J28: 124049 | K28: 246497.7 | L28: 371946.4 | M28: 485071.4 | N28: 604820.1 | O28: 722268.8 | P28: 837617.5 | Q28: 952166.2 | R28: 1340814.9 | S28: 1459263.6 | T28: 6042971.4 | U28: 1692961 | V28: 5764072 | W28: 506868.25 | X28: 2803775.7 | Y28: 2155143 | Z28: 2958907 | AA28: 3705001 | AB28: 4005640 | AC28: 4762988.5 | AD28: 7839334 | AE28: 6655111 | AF28: 7025656 | AG28: 8205253.6 | AH28: 9971173 | AI28: 8207596 | AJ28: 676403.94 | AK28: 1058033.4 | AL28: 1786324.3 | AM28: 2453372.6 | AN28: 3157144.6 | AO28: 3896858.6 | AP28: 4036310.5 | AQ28: 4521864.1 | AR28: 5202742.8 | AS28: 5635552.2 | AT28: 5945687.9 | AU28: 6754671.2 | AV28: 5891059 | AW28: 347705.17 | AX28: 858743.42 | AY28: 1571951.2 | AZ28: 2323992.9 | BA28: 2812489 | BB28: 3456216.7 | BC28: 3404743.6 | BD28: 3780634.1 | BE28: 4892956.5 | BF28: 5364167 | BG28: 5889677.7 | BH28: 11263548 | BI28: 6222100.5 | BJ28: 452189.91 | BK28: 1163126.6 | BL28: 2012252.9 | BM28: 2683550.6 | BN28: 3896853.3 | BO28: 4470441.4 | BP28: 4515294.3 | BQ28: 5125016.6 | BR28: 5692762.9 | BS28: 6830169.5 | BT28: 7535127.6 | BU28: 16453517 | BV28: 8348319.1 | BW28: 672196.38 | BX28: 1872954 | BY28: 2542282.5 | BZ28: 3220369.1 | CA28: 3790688.7 | CB28: 4611468.2 | CC28: 6091480.7 | CD28: 7296740.3 | CE28: 7901501.4 | CF28: 8691202.1 | CG28: 9474638.7 | CH28: 9304832 | CI28: 602032.78 | CJ28: 1609292.6 | CK28: 2061780.7 | CL28: 2855439.4 | CM28: 3470538.8 | CN28: 4224518 | CO28: 4763842.3 | CP28: 5206739.7 | CQ28: 6004820.2 | CR28: 6626407.8 | CS28: 8316062.6 | CT28: 16134437 | CU28: 8348971 | CV28: =186593+653035+132469+683413+139119+442871+325905+784367+8000+921663+1144965+332244+46800+300400+684957+402500+1000987+346784+1199000+173650+202798+61265+12615+520000+245445 -> 10951845 | CW28: 823195.63 | CX28: 2316618.2 | CY28: 3401171.3 | CZ28: 4644693.8 | DA28: 5436980.1 | DB28: 6857277.2 | DC28: 9234564.8 | DD28: 10621231 | DE28: 11817676
A29: Net Operating Income | B29: =B19-B20-B23 -> 4514867 | C29: =C19-C20-C23 -> 1567940 | D29: =D19-D20-D23 -> 931463 | E29: =E19-E20-E23 -> 1661030 | F29: =F19-F20-F23 -> -1406797.2 | G29: =G19-G20-G23 -> -4731486.7 | H29: =H19-H20-H23 -> 6649533 | I29: =I19-I20-I23 -> 2839150 | ... DE29: =DE19-DE20-DE23 -> 25752856
A30: Net Non operating Income/Expense | B30: =B31-B32 -> 0 | C30: =C31-C32 -> 0 | D30: =D31-D32 -> 0 | E30: =E31-E32 -> 0 | F30: =F31-F32 -> 0 | G30: =G31-G32 -> 0 | H30: =H31-H32 -> 0 | I30: =I31-I32 -> 0 | ... DE30: =DE31-DE32 -> 0
A31: Non Operating Income | J31: 0 | K31: 0 | L31: 0 | M31: 0 | N31: 0 | O31: 0 | P31: 0 | Q31: 0 | R31: 0 | S31: 0 | T31: 0 | U31: 0 | V31: 0 | W31: 0 | X31: 0 | Y31: 0 | Z31: 0 | AA31: 0 | AB31: 0 | AC31: 0 | AD31: 0 | AE31: 0 | AF31: 0 | AG31: 0 | AH31: 0 | AI31: 0 | AJ31: 0 | AK31: 0 | AL31: 0 | AM31: 0 | AN31: 0 | AO31: 0 | AP31: 0 | AQ31: 0 | AR31: 0 | AS31: 0 | AT31: 0 | AU31: 0 | AV31: 0 | AW31: 0 | AX31: 0 | AY31: 0 | AZ31: 0 | BA31: 0 | BB31: 0 | BC31: 0 | BD31: 0 | BE31: 0 | BF31: 0 | BG31: 0 | BH31: 0 | BJ31: 0 | BK31: 0 | BL31: 0 | BM31: 0 | BN31: 0 | BO31: 0 | BP31: 0 | BQ31: 0 | BR31: 0 | BS31: 0 | BT31: 0 | BU31: 0 | BW31: 0 | BX31: 0 | BY31: 0 | BZ31: 0 | CA31: 0 | CB31: 0 | CC31: 0 | CD31: 0 | CE31: 0 | CF31: 0 | CG31: 0 | CI31: 0 | CJ31: 0 | CK31: 0 | CL31: 0 | CM31: 0 | CN31: 0 | CO31: 0 | CP31: 0 | CQ31: 0 | CR31: 0 | CS31: 0 | CT31: 0 | CU31: 0 | CV31: 0 | CW31: 0 | CX31: 0 | CY31: 0 | CZ31: 0 | DA31: 0 | DB31: 0 | DC31: 0 | DD31: 0 | DE31: 0
A32: Non Operating Expense | J32: 0 | K32: 0 | L32: 0 | M32: 0 | N32: 0 | O32: 0 | P32: 0 | Q32: 0 | R32: 0 | S32: 0 | T32: 0 | U32: 0 | V32: 0 | W32: 0 | X32: 0 | Y32: 0 | Z32: 0 | AA32: 0 | AB32: 0 | AC32: 0 | AD32: 0 | AE32: 0 | AF32: 0 | AG32: 0 | AH32: 0 | AI32: 0 | AJ32: 0 | AK32: 0 | AL32: 0 | AM32: 0 | AN32: 0 | AO32: 0 | AP32: 0 | AQ32: 0 | AR32: 0 | AS32: 0 | AT32: 0 | AU32: 0 | AV32: 0 | AW32: 0 | AX32: 0 | AY32: 0 | AZ32: 0 | BA32: 0 | BB32: 0 | BC32: 0 | BD32: 0 | BE32: 0 | BF32: 0 | BG32: 0 | BH32: 0 | BJ32: 0 | BK32: 0 | BL32: 0 | BM32: 0 | BN32: 0 | BO32: 0 | BP32: 0 | BQ32: 0 | BR32: 0 | BS32: 0 | BT32: 0 | BU32: 0 | BW32: 0 | BX32: 0 | BY32: 0 | BZ32: 0 | CA32: 0 | CB32: 0 | CC32: 0 | CD32: 0 | CE32: 0 | CF32: 0 | CG32: 0 | CI32: 0 | CJ32: 0 | CK32: 0 | CL32: 0 | CM32: 0 | CN32: 0 | CO32: 0 | CP32: 0 | CQ32: 0 | CR32: 0 | CS32: 0 | CT32: 0 | CU32: 0 | CV32: 0 | CW32: 0 | CX32: 0 | CY32: 0 | CZ32: 0 | DA32: 0 | DB32: 0 | DC32: 0 | DD32: 0 | DE32: 0
A33: Net Income(Before Tax & Donations) | B33: =B29+B30 -> 4514867 | C33: =C29+C30 -> 1567940 | D33: =D29+D30 -> 931463 | E33: =E29+E30 -> 1661030 | F33: =F29+F30 -> -1406797.2 | G33: =G29+G30 -> -4731486.7 | H33: =H29+H30 -> 6649533 | I33: =I29+I30 -> 2839150 | ... DE33: =DE29+DE30 -> 25752856
A34: Taxes | H34: 95000 | I34: 651967 | J34: 0 | K34: 0 | L34: 0 | M34: 0 | N34: 0 | O34: 0 | P34: 0 | Q34: 0 | R34: 0 | S34: 0 | T34: 0 | U34: 0 | V34: 344540 | W34: 0 | X34: 0 | Y34: 0 | Z34: 0 | AA34: 0 | AB34: 0 | AC34: 0 | AD34: 0 | AE34: 0 | AF34: 0 | AG34: 0 | AH34: 0 | AI34: 1414209 | AJ34: 0 | AK34: 0 | AL34: 0 | AM34: 0 | AN34: 0 | AO34: 0 | AP34: 0 | AQ34: 0 | AR34: 0 | AS34: 0 | AT34: 0 | AU34: 0 | AV34: 268110 | AW34: 0 | AX34: 0 | AY34: 0 | AZ34: 0 | BD34: 0 | BE34: 0 | BF34: 0 | BG34: 0 | BH34: 0 | BI34: 873146.35 | BJ34: 0 | BK34: 0 | BL34: 0 | BM34: 0 | BN34: 0 | BO34: 0 | BP34: 0 | BQ34: 0 | BR34: 0 | BS34: 0 | BT34: 0 | BU34: 0 | BW34: 0 | BX34: 0 | BY34: 0 | BZ34: 0 | CA34: 0 | CB34: 0 | CC34: 0 | CD34: 0 | CE34: 0 | CF34: 0 | CG34: 0 | CH34: -2554226.6 | CI34: 0 | CJ34: 0 | CK34: 0 | CL34: 0 | CM34: 0 | CN34: 0 | CO34: 0 | CP34: 0 | CU34: 6543446 | CV34: 4113004 | CW34: 0 | CX34: 0 | CY34: 0 | CZ34: 0 | DA34: 0 | DB34: 0 | DC34: 0 | DD34: 0 | DE34: 0
A35: Net Income(After Tax Before Donations) | B35: =B33-B34 -> 4514867 | C35: =C33-C34 -> 1567940 | D35: =D33-D34 -> 931463 | E35: =E33-E34 -> 1661030 | F35: =F33-F34 -> -1406797.2 | G35: =G33-G34 -> -4731486.7 | H35: =H33-H34 -> 6554533 | I35: =I33-I34 -> 2187183 | ... DE35: =DE33-DE34 -> 25752856
A36: Donations | J36: 0 | K36: 0 | L36: 0 | M36: 0 | N36: 0 | O36: 0 | P36: 0 | Q36: 0 | R36: 0 | S36: 0 | T36: 0 | U36: 0 | W36: 0 | X36: 0 | Y36: 0 | Z36: 0 | AA36: 0 | AB36: 0 | AC36: 0 | AD36: 0 | AE36: 0 | AF36: 0 | AG36: 0 | AH36: 0 | AI36: 0 | AJ36: 0 | AK36: 0 | AL36: 0 | AM36: 0 | AN36: 0 | AO36: 0 | AP36: 0 | AQ36: 0 | AR36: 0 | AS36: 0 | AT36: 0 | AU36: 0 | AW36: 0 | AX36: 0 | AY36: 0 | AZ36: 0 | BA36: 0 | BB36: 0 | BC36: 0 | BD36: 0 | BE36: 0 | BF36: 0 | BG36: 0 | BH36: 0 | BJ36: 0 | BK36: 0 | BL36: 0 | BM36: 0 | BN36: 0 | BO36: 0 | BP36: 0 | BQ36: 0 | BR36: 0 | BS36: 0 | BT36: 0 | BU36: 0 | BW36: 0 | BX36: 0 | BY36: 0 | BZ36: 0 | CA36: 0 | CB36: 0 | CC36: 0 | CD36: 0 | CE36: 0 | CF36: 0 | CG36: 0 | CI36: 0 | CJ36: 0 | CK36: 0 | CL36: 0 | CM36: 0 | CN36: 0 | CO36: 0 | CP36: 0 | CW36: 0 | CX36: 0 | CY36: 0 | CZ36: 0 | DA36: 0 | DB36: 0 | DC36: 0 | DD36: 0 | DE36: 0
A37: Net Income/(After Tax & Donations) | B37: =B35-B36 -> 4514867 | C37: =C35-C36 -> 1567940 | D37: =D35-D36 -> 931463 | E37: =E35-E36 -> 1661030 | F37: =F35-F36 -> -1406797.2 | G37: =G35-G36 -> -4731486.7 | H37: =H35-H36 -> 6554533 | I37: =I35-I36 -> 2187183 | ... DE37: =DE35-DE36 -> 25752856
A39: Total Expenses | B39: =B12+B23 -> 4921975 | C39: =C12+C23 -> 5428571 | D39: =D12+D23 -> 5976017 | E39: =E12+E23 -> 14300532 | F39: =F12+F23 -> 12428441 | G39: =G12+G23 -> 13705076 | H39: =H12+H23 -> 14704470 | I39: =I12+I23 -> 15397346 | ... DE39: =DE12+DE23 -> 41927955
CI44: =CI37-164292468.04 -> -1.6701557e+08

Sheet Feedback report
A1: STIMA SACCO SOCIETY LIMITED CS/NO: 2207
A2: PERFORMANCE AND COMPLIANCE REPORT AS AT : 30TH JUNE , 2018
B3: Prudential Standard | C3: Audited | D3: Returns | F3: Validated | G3: Average for all Licensed Saccos
C4: 2017 | D4: 43160 | E4: 43252
A5: A. CAPITAL ADEQUACY
A6: Core Capital | B6: ≥10M | C6: =C33 -> 3575294000 | D6: =D33 -> 3.6383881e+09 | E6: =E33 -> 3.8508836e+09 | F6: =F33 -> 0 | G6: =G33 -> 6.9326568e+10
A7: Core Capital/Total Assets | B7: ≥10% | C7: =C33/C29 -> 0.12516247 | D7: =D33/D29 -> 0.12404378 | E7: =E33/E29 -> 0.12810105 | F7: =F33/F29 -> #DIV/0! | G7: =G33/G29 -> 0.15142619
A8: Institutional Capital/Total Assets | B8: ≥8% | C8: =C34/C29 -> 0.084655346 | D8: =D34/D29 -> 0.080427602 | E8: =E34/E29 -> 0.082116799 | F8: =F34/F29 -> #DIV/0! | G8: =G34/G29 -> 0.086793277
A9: B. ASSET QUALITY
A10: NPL (Substandard+Doubtful+Loss) | B10: <5% | C10: =C35/C32 -> 0.083758752 | D10: =D35/D32 -> 0.069905965 | E10: =E35/E32 -> 0.064128919 | F10: =F35/F32 -> #DIV/0! | G10: =G35/G32 -> 0.064216556
A11: Non-Earning Assets | B11: <10% | C11: =C36/C29 -> 0.078233551 | D11: =D36/D29 -> 0.07077156 | E11: =E36/E29 -> 0.073871285 | F11: =F36/F29 -> #DIV/0! | G11: =G36/G29 -> 0.21105592
A12: Equity investments/Deposits | B12: <5% | C12: =C38/C31 -> 0.039319754 | D12: =D38/D31 -> 0.035325792 | E12: =E38/E31 -> 0.037197617 | F12: =F38/F31 -> #DIV/0! | G12: =G38/G31 -> 0.041240427
A13: Equity investments/Core capital | B13: <40% | C13: =C38/C33 -> 0.24098997 | D13: =D38/D33 -> 0.22956689 | E13: =E38/E33 -> 0.22930111 | F13: =F38/F33 -> #DIV/0! | G13: =G38/G33 -> 0.19351903
A14: C. EARNINGS RATING
A15: Yield on Gross Loans | C15: =C41/C32 -> 0.076755322 | D15: =D41/D32 -> 0.019738298 | E15: =E41/E32 -> 0.038638319 | F15: =F41/F32 -> #DIV/0! | G15: =G41/G32 -> 0.060128916
A16: Total Expense/Total Income | C16: =C44/C40 -> 0.8602912 | D16: =D44/D40 -> 0.91284222 | E16: =E44/E40 -> 0.88209003 | F16: =F44/F40 -> #DIV/0! | G16: =G44/G40 -> 0.79898157
A17: Net Income/Average Assets | C17: =C42/C30 -> 0.021114194 | D17: =D42/D30 -> 0.0032004404 | E17: =E42/E30 -> 0.0085246189 | F17: =F42/F30 -> #DIV/0! | G17: =G42/G30 -> 0.014471496
A18: Operating Expenses/Net Income (OPEX) | C18: =C45/C42 -> 1.8241433 | D18: =D45/D42 -> 2.5388457 | E18: =E45/E42 -> 2.0792721 | F18: =F45/F42 -> #DIV/0! | G18: =G45/G42 -> 1.6778105
A19: D. LIQUIDITY
A20: Liquid Assets/Short-term Liabilities | B20: >15% | C20: =C46/C47 -> 0.33588266 | D20: =D46/D47 -> 0.44544133 | E20: =E46/E47 -> 0.45759283 | F20: =F46/F47 -> #DIV/0! | G20: =G46/G47 -> 0.53762833
A21: External Borrowing/Total Assets | B21: <25% | C21: =C48/C29 -> 0.015941271 | D21: =D48/D29 -> 0.014155771 | E21: =E48/E29 -> 0.012698777 | F21: =F48/F29 -> #DIV/0! | G21: =G48/G29 -> 0.048858222
A22: Liquid Assets/Total Assets | C22: =C46/C29 -> 0.089409238 | D22: =D46/D29 -> 0.11709895 | E22: =E46/E29 -> 0.11553873 | F22: =F46/F29 -> #DIV/0! | G22: =G46/G29 -> 0.10366677
A23: E. STRUCTURE/SENSITIVITY TO RISK
A24: Gross loans /Total Assets | B24: 70-80 | C24: =C32/C29 -> 0.81615737 | D24: =D32/D29 -> 0.80219752 | E24: =E32/E29 -> 0.80146237 | F24: =F32/F29 -> #DIV/0! | G24: =G32/G29 -> 0.75746736
A25: Gross loans/Deposits | B25: >100% | C25: =C32/C31 -> 1.0639265 | D25: =D32/D31 -> 0.99515095 | E25: =E32/E31 -> 1.0149377 | F25: =F32/F31 -> #DIV/0! | G25: =G32/G31 -> 1.0660128
A26: Financial Investments/Total Assets | C26: =C39/C29 -> 0.038223399 | D26: =D39/D29 -> 0.02937488 | E26: =E39/E29 -> 0.030250433 | F26: =F39/F29 -> #DIV/0! | G26: =G39/G29 -> 0.043658487
A27: Dividends+Interest on Deposits/Total Income | C27: =C43/C40 -> 0.95525793 | D27: =D43/D40 -> 0.54694558 | E27: =E43/E40 -> 0.54728259 | F27: =F43/F40 -> #DIV/0! | G27: =G43/G40 -> 0.27724023
A28: F. KEY FINANCIAL STATISTICS | C28: 2015 | D28: 2016 | E28: 2017 | G28: AGGREGATE
A29: Total Assets | C29: 28565225000 | D29: 2.9331483e+10 | E29: 3.0061295e+10 | G29: 4.5782417e+11
A30: Average Assets | C30: 26523579000 | D30: 2.8948354e+10 | E30: 2.931326e+10 | G30: 4.5005065e+11
A31: Total Deposits | C31: 21912904000 | D31: 2.3644295e+10 | E31: 2.3738399e+10 | G31: 3.253121e+11
A32: Gross Loans | C32: 23313719000 | D32: 2.3529643e+10 | E32: 2.4092997e+10 | G32: 3.4678687e+11
A33: Core Capital | C33: 3575294000 | D33: 3.6383881e+09 | E33: 3.8508836e+09 | G33: 6.9326568e+10
A34: Institutional Capital | C34: 2418199000 | D34: 2.3590608e+09 | E34: 2.4685373e+09 | G34: 3.973606e+10
A35: Non-performing Loans | C35: 1952728000 | D35: 1.6448624e+09 | E35: 1.5450578e+09 | G35: 2.2269458e+10
A36: Non-Earning Assets | C36: 2234759000 | D36: 2.0758348e+09 | E36: 2.2206665e+09 | G36: 9.66265e+10
A37: Property and Equipment | C37: 235465000 | D37: 2.3485688e+08 | E37: 2.2615095e+08 | G37: 1.5408701e+10
A38: Equity Investments | C38: 861610000 | D38: 8.3525346e+08 | E38: 8.8301186e+08 | G38: 1.341601e+10
A39: Financial Investments | C39: 1091860000 | D39: 8.616088e+08 | E39: 9.0936721e+08 | G39: 1.9987911e+10
A40: Total Income | C40: 4008509000 | D40: 1.0629858e+09 | E40: 2.119281e+09 | G40: 3.2399548e+10
... A48: External Borrowing | C48: 455366000 | D48: 4.1520974e+08 | E48: 3.8174169e+08 | G48: 2.2368475e+10
A49: G. AREAS OF IMPROVEMENT/REGULARTORY CONCERNS
A50: 1. The ratio of NPL is above the prescribed limit
A51: 2
A52: 3
A53: 4
A54: Prepared by: Daniel Mwatu
A56: Checked by:
A58: Approved by: Peter Njuguna
A60: DISCLAIMER: This report is prepared based on information submitted by the Sacco as at the stated date and may change upon verification by the Authority.

Sheet FORM 4
D1: 42795
B2: CLASSIFICATION | C2: NO. OF A/Cs | D2: OUTSTANDING LOAN PORTFOLIO(Kshs) | E2: REQUIRED PROVISION | F2: REQUIRED PROVISION AMOUNT(Kshs)
B3: Performing | C3: 56175 | D3: 1.993701e+10 | E3: 0 | F3: =D3*E3 -> 0
B4: Watch | C4: 342 | D4: 6.0964609e+08 | E4: 0.05 | F4: =D4*E4 -> 30482304
B5: Substandard | C5: 721 | D5: 5.3176756e+08 | E5: 0.25 | F5: =D5*E5 -> 1.3294189e+08
B6: Doubtful | C6: 182 | D6: 1.3302199e+08 | E6: 0.5 | F6: =D6*E6 -> 66510994
B7: Loss | C7: 285 | D7: 53640300 | E7: 1 | F7: =D7*E7 -> 53640300
B8: subtotal | C8: =SUM(C3:C7) -> 57705 | D8: =SUM(D3:D7) -> 2.1265086e+10 | F8: =SUM(F3:F7) -> 2.8357549e+08
D10: 42887
B11: CLASSIFICATION | C11: NO. OF A/Cs | D11: OUTSTANDING LOAN PORTFOLIO(Kshs) | E11: REQUIRED PROVISION | F11: REQUIRED PROVISION AMOUNT(Kshs)
B12: Performing | C12: 52931 | D12: 2.0932769e+10 | E12: 0.01 | F12: =D12*E12 -> 2.0932769e+08
B13: Watch | C13: 1072 | D13: 6.9302846e+08 | E13: 0.05 | F13: =D13*E13 -> 34651423
B14: Substandard | C14: 237 | D14: 2.1101418e+08 | E14: 0.25 | F14: =D14*E14 -> 52753546
B15: Doubtful | C15: 75 | D15: 31560414 | E15: 0.5 | F15: =D15*E15 -> 15780207
B16: Loss | C16: 16 | D16: 4449341.3 | E16: 1 | F16: =D16*E16 -> 4449341.3
B17: subtotal | C17: =SUM(C12:C16) -> 54331 | D17: =SUM(D12:D16) -> 2.1872821e+10 | E17: 1.81 | F17: =SUM(F12:F16) -> 3.169622e+08
C18: NPL | D18: =SUM(D14:D16) -> 2.4702394e+08
C19: PAR | D19: =D18/D17 -> 0.011293648
D21: 42979
B22: CLASSIFICATION | C22: NO. OF A/Cs | D22: OUTSTANDING LOAN PORTFOLIO(Kshs) | E22: REQUIRED PROVISION | F22: REQUIRED PROVISION AMOUNT(Kshs)
B23: Performing | C23: 48840 | D23: 19551006671 | E23: 0.01
B24: Watch | C24: 2088 | D24: 1.0437061e+09 | E24: 0.05 | F24: =D24*E24 -> 52185307
B25: Substandard | C25: 4389 | D25: 1.5125185e+09 | E25: 0.25 | F25: =D25*E25 -> 3.7812962e+08
B26: Doubtful | C26: 927 | D26: 4.2115024e+08 | E26: 0.5 | F26: =D26*E26 -> 2.1057512e+08
B27: Loss | C27: 1102 | D27: 229316298 | E27: 1 | F27: =D27*E27 -> 229316298
B28: subtotal | C28: =SUM(C23:C27) -> 57346 | D28: =SUM(D23:D27) -> 2.2757698e+10 | F28: =SUM(F23:F27) -> 8.7020635e+08
C29: NPL | D29: =SUM(D25:D27) -> 2.162985e+09
C30: PAR | D30: =D29/D28 -> 0.095044105
D32: 43070
B33: CLASSIFICATION | C33: NO. OF A/Cs | D33: OUTSTANDING LOAN PORTFOLIO(Kshs) | E33: REQUIRED PROVISION | F33: REQUIRED PROVISION AMOUNT(Kshs)
B34: Performing | C34: 50625 | D34: 2.0056569e+10 | E34: 0 | F34: =D34*E34 -> 0
B35: Watch | C35: 1985 | D35: 817339191 | E35: 0.05 | F35: =D35*E35 -> 40866960
B36: Substandard | C36: 4389 | D36: 1.2107046e+09 | E36: 0.25 | F36: =D36*E36 -> 3.0267616e+08
B37: Doubtful | C37: 1012 | D37: 6.4041824e+08 | E37: 0.5 | F37: =D37*E37 -> 3.2020912e+08
B38: Loss | C38: 1121 | D38: 4.8124864e+08 | E38: 1 | F38: =D38*E38 -> 4.8124864e+08
B39: subtotal | C39: =SUM(C34:C38) -> 59132 | D39: =SUM(D34:D38) -> 2.320628e+10 | E39: 1.81 | F39: =SUM(F34:F38) -> 1.1450009e+09
C40: NPL | D40: =SUM(D36:D38) -> 2.3323715e+09
C41: PAR | D41: =D40/D39 -> 0.10050605
D43: Audited 2017
B44: CLASSIFICATION | C44: NO. OF A/Cs | D44: OUTSTANDING LOAN PORTFOLIO(Kshs) | E44: REQUIRED PROVISION | F44: REQUIRED PROVISION AMOUNT(Kshs)
B45: Performing | E45: 0 | F45: =D45*E45 -> 0
B46: Watch | E46: 0.05 | F46: 6739000
B47: Substandard | E47: 0.25 | F47: 54183000 | H47: =SUM(D47:D49)/D50 -> #DIV/0!
B48: Doubtful | E48: 0.5 | F48: 33315000
B49: Loss | E49: 1 | F49: 11377000
B50: subtotal | C50: =SUM(C45:C49) -> 0 | D50: =SUM(D45:D49) -> 0 | E50: 1.81 | F50: =SUM(F45:F49) -> 105614000
D53: 43160
B54: CLASSIFICATION | C54: NO. OF A/Cs | D54: OUTSTANDING LOAN PORTFOLIO(Kshs) | E54: REQUIRED PROVISION | F54: REQUIRED PROVISION AMOUNT(Kshs)
B55: Performing | C55: 47697 | D55: 2.1205447e+10 | E55: 0 | F55: =D55*E55 -> 0
B56: Watch | C56: 26917 | D56: 6.7933412e+08 | E56: 0.05 | F56: =D56*E56 -> 33966706
B57: Substandard | C57: 3726 | D57: 1.003759e+09 | E57: 0.25 | F57: =D57*E57 -> 2.5093975e+08
B58: Doubtful | C58: 2799 | D58: 3.4918089e+08 | E58: 0.5 | F58: =D58*E58 -> 1.7459044e+08
B59: Loss | C59: 1768 | D59: 2.9192251e+08 | E59: 1 | F59: =D59*E59 -> 2.9192251e+08
B60: subtotal | C60: 82907 | D60: 2.3529643e+10 | F60: =SUM(F55:F59) -> 7.5141941e+08 | H60: NPL | I60: =(D57+D58+D59)/D60 -> 0.069905965
D62: 43252
B63: CLASSIFICATION | C63: NO. OF A/Cs | D63: OUTSTANDING LOAN PORTFOLIO(Kshs) | E63: REQUIRED PROVISION | F63: REQUIRED PROVISION AMOUNT(Kshs)
B64: Performing | C64: 49406 | D64: 2.1905084e+10 | E64: 0.01
B65: Watch | C65: 3346 | D65: 6.4285512e+08 | E65: 0.05 | F65: =D65*E65 -> 32142756
B66: Substandard | C66: 4337 | D66: 9.8318969e+08 | E66: 0.25 | F66: =D66*E66 -> 2.4579742e+08
B67: Doubtful | C67: 1945 | D67: 2.0661378e+08 | E67: 0.5 | F67: =D67*E67 -> 1.0330689e+08
B68: Loss | C68: 2419 | D68: 3.5525437e+08 | E68: 1 | F68: =D68*E68 -> 3.5525437e+08
B69: subtotal | C69: =SUM(C64:C68) -> 61453 | D69: =SUM(D64:D68) -> 2.4092997e+10 | F69: =SUM(F64:F68) -> 7.3650143e+08 | H69: NPL | I69: =(D66+D67+D68)/D69 -> 0.064128919
C70: NPL | D70: =SUM(D66:D68) -> 1.5450578e+09
C71: PAR | D71: =D70/D69 -> 0.064128919
D73: 43344
B74: CLASSIFICATION | C74: NO. OF A/Cs | D74: OUTSTANDING LOAN PORTFOLIO(Kshs) | E74: REQUIRED PROVISION | F74: REQUIRED PROVISION AMOUNT(Kshs)
B75: Performing | C75: 52325 | D75: 2.3771723e+10 | E75: 0.01
B76: Watch | C76: 3425 | D76: 5.7053399e+08 | E76: 0.05 | F76: =D76*E76 -> 28526700
B77: Substandard | C77: 3825 | D77: 2.9021825e+08 | E77: 0.25 | F77: =D77*E77 -> 72554563
B78: Doubtful | C78: 1852 | D78: 27072771 | E78: 0.5 | F78: =D78*E78 -> 13536386
B79: Loss | C79: 2325 | D79: 1.5075147e+08 | E79: 1 | F79: =D79*E79 -> 1.5075147e+08
B80: subtotal | C80: 63752 | D80: 2.4810299e+10 | F80: =SUM(F75:F79) -> 2.6536911e+08 | H80: NPL | I80: =(D77+D78+D79)/D80 -> 0.018864847
C81: NPL | D81: =SUM(D77:D79) -> 4.6804249e+08
C82: PAR | D82: =D81/D80 -> 0.018864847
D84: 43435
B85: CLASSIFICATION | C85: NO. OF A/Cs | D85: OUTSTANDING LOAN PORTFOLIO(Kshs) | E85: REQUIRED PROVISION | F85: REQUIRED PROVISION AMOUNT(Kshs)
B86: Performing | E86: 0 | F86: =D86*E86 -> 0
B87: Watch | E87: 0.05 | F87: =D87*E87 -> 0
B88: Substandard | E88: 0.25 | F88: =D88*E88 -> 0
B89: Doubtful | E89: 0.5 | F89: =D89*E89 -> 0
B90: Loss | E90: 1 | F90: =D90*E90 -> 0
B91: subtotal | E91: 1.81 | F91: =SUM(F86:F90) -> 0 | H91: NPL | I91: =(D88+D89+D90)/D91 -> #DIV/0!
C92: NPL | D92: =SUM(D88:D90) -> 0
C93: PAR | D93: =D92/D91 -> #DIV/0!
D95: Audited 2018
B96: CLASSIFICATION | C96: NO. OF A/Cs | D96: OUTSTANDING LOAN PORTFOLIO(Kshs) | E96: REQUIRED PROVISION | F96: REQUIRED PROVISION AMOUNT(Kshs)
B97: Performing | C97: 61808 | D97: 23864790000 | E97: 0 | F97: =D97*E97 -> 0
B98: Watch | C98: 2558 | D98: 543816000 | E98: 0.05 | F98: 6739000
B99: Substandard | C99: 3972 | D99: 838253000 | E99: 0.25 | F99: 54183000
B100: Doubtful | C100: 2510 | D100: 373254000 | E100: 0.5 | F100: 33315000
B101: Loss | C101: 2139 | D101: 210209000 | E101: 1 | F101: 11377000
B102: subtotal | C102: =SUM(C97:C101) -> 72987 | D102: =SUM(D97:D101) -> 25830322000 | E102: 1.81 | F102: =SUM(F97:F101) -> 105614000 | H102: NPL | I102: =(D99+D100+D101)/D102 -> 0.055040584
C103: NPL | D103: =SUM(D99:D101) -> 1421716000
C104: PAR | D104: =D103/D102 -> 0.055040584
D107: 44075
B108: CLASSIFICATION | C108: NO. OF A/Cs | D108: OUTSTANDING LOAN PORTFOLIO(Kshs) | E108: REQUIRED PROVISION | F108: REQUIRED PROVISION AMOUNT(Kshs)
B109: Performing | C109: 56618 | D109: 3.1475041e+10 | E109: 0.01 | F109: =D109*E109 -> 3.1475041e+08
B110: Watch | C110: 2064 | D110: 4.7265764e+08 | E110: 0.05 | F110: =D110*E110 -> 23632882
B111: Substandard | C111: 4931 | D111: 8.0013981e+08 | E111: 0.25 | F111: =D111*E111 -> 2.0003495e+08
B112: Doubtful | C112: 2310 | D112: 1.3164484e+08 | E112: 0.5 | F112: =D112*E112 -> 65822422
...

Sheet CAELS
A1: LAINISHA SACCO 2022 CAELS
D2: 2013 Audited | E2: 2014 Audited | F2: 2015 Audited | G2: 2016 Audited | H2: 42736 | I2: 42767 | J2: 42795 | K2: 42826 | L2: 42856 | M2: 42887 | N2: 42917 | O2: 42948 | P2: 42979 | Q2: 43009 | R2: 43040 | S2: 43070 | T2: Audited 2017 | U2: 43101 | V2: 43132 | W2: 43160 | X2: 43191 | Y2: 43221 | Z2: 43252 | AA2: 43282 | AB2: 43313 | AC2: 43344 | AD2: 43374 | AE2: 43405 | AF2: 43435 | AG2: Audited 2018 | AH2: 43466 | AI2: 43497 | AJ2: 43525 | AK2: 43556 | AL2: 43586 | AM2: 43617 | AN2: 43647 | AO2: 43678 | AP2: 43709 | AQ2: 43739 | AR2: 43770 | AS2: 43800 | AT2: Audited 2019 | AU2: 43831 | AV2: 43862 | AW2: 43891 | AX2: 43922 | AY2: 43952 | AZ2: 43983 | BA2: 44013 | BB2: 44044 | BC2: 44075 | BD2: 44105 | BE2: 44136 | BF2: 44166 | BG2: Audited 2020 | BH2: 44197 | BI2: 44228 | BJ2: 44256 | BK2: 44287 | BL2: 44317 | BM2: 44348 | BN2: 44378 | BO2: 44409 | BP2: 44440 | BQ2: 44470 | BR2: 44501 | BS2: 44531 | BT2: Audited 2021 | BU2: Audited 2022 | BV2: 44927 | BW2: 44958 | BX2: 44986 | BY2: 45017 | BZ2: 45047 | CA2: 45078 | CB2: 45108 | CC2: 45139 | CD2: 45170
A3: CAPITAL ADEQUACY | B3: Core Capital | C3: 10 M | D3: =(('Evolutive SFP'!#REF!+'Evolutive SFP'!#REF!+'Evolutive SFP'!#REF!+'Evolutive SFP'!#REF!+'Evolutive SFP'!#REF!+'Evolutive SFP'!#REF!)-'Evolutive SFP'!#REF!)/1000000 -> #REF! | E3: =(('Evolutive SFP'!#REF!+'Evolutive SFP'!#REF!+'Evolutive SFP'!#REF!+'Evolutive SFP'!#REF!+'Evolutive SFP'!#REF!+'Evolutive SFP'!#REF!)-'Evolutive SFP'!#REF!)/1000000 -> #REF! | F3: =(('Evolutive SFP'!#REF!+'Evolutive SFP'!#REF!+'Evolutive SFP'!#REF!+'Evolutive SFP'!#REF!+'Evolutive SFP'!#REF!+'Evolutive SFP'!#REF!)-'Evolutive SFP'!#REF!)/1000000 -> #REF! | G3: =(('Evolutive SFP'!#REF!+'Evolutive SFP'!#REF!+'Evolutive SFP'!#REF!+'Evolutive SFP'!#REF!+'Evolutive SFP'!#REF!+'Evolutive SFP'!#REF!)-'Evolutive SFP'!#REF!)/1000000 -> #REF! | H3: =(('Evolutive SFP'!#REF!+'Evolutive SFP'!#REF!+'Evolutive SFP'!#REF!+'Evolutive SFP'!#REF!+'Evolutive SFP'!#REF!+'Evolutive SFP'!#REF!)-'Evolutive SFP'!#REF!)/1000000 -> #REF! | I3: =(('Evolutive SFP'!#REF!+'Evolutive SFP'!#REF!+'Evolutive SFP'!#REF!+'Evolutive SFP'!#REF!+'Evolutive SFP'!#REF!+'Evolutive SFP'!#REF!)-'Evolutive SFP'!#REF!)/1000000 -> #REF! | J3: =(('Evolutive SFP'!#REF!+'Evolutive SFP'!#REF!+'Evolutive SFP'!#REF!+'Evolutive SFP'!#REF!+'Evolutive SFP'!#REF!+'Evolutive SFP'!#REF!)-'Evolutive SFP'!#REF!)/1000000 -> #REF! | K3: =(('Evolutive SFP'!#REF!+'Evolutive SFP'!#REF!+'Evolutive SFP'!#REF!+'Evolutive SFP'!#REF!+'Evolutive SFP'!#REF!+'Evolutive SFP'!#REF!)-'Evolutive SFP'!#REF!)/1000000 -> #REF! | ... AS3: =(('Evolutive SFP'!#REF!+'Evolutive SFP'!#REF!+'Evolutive SFP'!#REF!+'Evolutive SFP'!#REF!+'Evolutive SFP'!#REF!+'Evolutive SFP'!#REF!)-'Evolutive SFP'!#REF!)/1000000 -> #REF! | AT3: =(('Evolutive SFP'!BV39+'Evolutive SFP'!BV40+'Evolutive SFP'!BV41+'Evolutive SFP'!BV42+'Evolutive SFP'!BV43+'Evolutive SFP'!BV44)-'Evolutive SFP'!BV10)/1000000 -> 323.68967 | AU3: =(('Evolutive SFP'!BW39+'Evolutive SFP'!BW40+'Evolutive SFP'!BW41+'Evolutive SFP'!BW42+'Evolutive SFP'!BW43+'Evolutive SFP'!BW44)-'Evolutive SFP'!BW10)/1000000 -> 217.85504 | AV3: =(('Evolutive SFP'!BX39+'Evolutive SFP'!BX40+'Evolutive SFP'!BX41+'Evolutive SFP'!BX42+'Evolutive SFP'!BX43+'Evolutive SFP'!BX44)-'Evolutive SFP'!BX10)/1000000 -> 211.71243 | AW3: =(('Evolutive SFP'!BY39+'Evolutive SFP'!BY40+'Evolutive SFP'!BY41+'Evolutive SFP'!BY42+'Evolutive SFP'!BY43+'Evolutive SFP'!BY44)-'Evolutive SFP'!BY10)/1000000 -> 209.99932 | AX3: =(('Evolutive SFP'!BZ39+'Evolutive SFP'!BZ40+'Evolutive SFP'!BZ41+'Evolutive SFP'!BZ42+'Evolutive SFP'!BZ43+'Evolutive SFP'!BZ44)-'Evolutive SFP'!BZ10)/1000000 -> 217.55973 | AY3: =(('Evolutive SFP'!CA39+'Evolutive SFP'!CA40+'Evolutive SFP'!CA41+'Evolutive SFP'!CA42+'Evolutive SFP'!CA43+'Evolutive SFP'!CA44)-'Evolutive SFP'!CA10)/1000000 -> 216.17863 | AZ3: =(('Evolutive SFP'!CB39+'Evolutive SFP'!CB40+'Evolutive SFP'!CB41+'Evolutive SFP'!CB42+'Evolutive SFP'!CB43+'Evolutive SFP'!CB44)-'Evolutive SFP'!CB10)/1000000 -> 232.26903 | BA3: =(('Evolutive SFP'!#REF!+'Evolutive SFP'!#REF!+'Evolutive SFP'!#REF!+'Evolutive SFP'!#REF!+'Evolutive SFP'!#REF!+'Evolutive SFP'!#REF!)-'Evolutive SFP'!#REF!)/1000000 -> #REF! | BB3: =(('Evolutive SFP'!CC39+'Evolutive SFP'!CC40+'Evolutive SFP'!CC41+'Evolutive SFP'!CC42+'Evolutive SFP'!CC43+'Evolutive SFP'!CC44)-'Evolutive SFP'!CC10)/1000000 -> 233.5849 | BC3: =(('Evolutive SFP'!CD39+'Evolutive SFP'!CD40+'Evolutive SFP'!CD41+'Evolutive SFP'!CD42+'Evolutive SFP'!CD43+'Evolutive SFP'!CD44)-'Evolutive SFP'!CD10)/1000000 -> 237.72275 | BD3: =(('Evolutive SFP'!CE39+'Evolutive SFP'!CE40+'Evolutive SFP'!CE41+'Evolutive SFP'!CE42+'Evolutive SFP'!CE43+'Evolutive SFP'!CE44)-'Evolutive SFP'!CE10)/1000000 -> 240.23365 | BE3: =(('Evolutive SFP'!CF39+'Evolutive SFP'!CF40+'Evolutive SFP'!CF41+'Evolutive SFP'!CF42+'Evolutive SFP'!CF43+'Evolutive SFP'!CF44)-'Evolutive SFP'!CF10)/1000000 -> 236.84107 | BF3: =(('Evolutive SFP'!CG39+'Evolutive SFP'!CG40+'Evolutive SFP'!CG41+'Evolutive SFP'!CG42+'Evolutive SFP'!CG43+'Evolutive SFP'!CG44)-'Evolutive SFP'!CG10)/1000000 -> 228.31502 | BG3: =(('Evolutive SFP'!CH39+'Evolutive SFP'!CH40+'Evolutive SFP'!CH41+'Evolutive SFP'!CH42+'Evolutive SFP'!CH43+'Evolutive SFP'!CH44)-'Evolutive SFP'!CH10)/1000000 -> 225.76079 | BH3: =(('Evolutive SFP'!CI39+'Evolutive SFP'!CI40+'Evolutive SFP'!CI41+'Evolutive SFP'!CI42+'Evolutive SFP'!CI43+'Evolutive SFP'!CI44)-'Evolutive SFP'!CI10)/1000000 -> 225.79684 | BI3: =(('Evolutive SFP'!CJ39+'Evolutive SFP'!CJ40+'Evolutive SFP'!CJ41+'Evolutive SFP'!CJ42+'Evolutive SFP'!CJ43+'Evolutive SFP'!CJ44)-'Evolutive SFP'!CJ10)/1000000 -> 221.8601 | ... CD3: =(('Evolutive SFP'!DE39+'Evolutive SFP'!DE40+'Evolutive SFP'!DE41+'Evolutive SFP'!DE42+'Evolutive SFP'!DE43+'Evolutive SFP'!DE44)-'Evolutive SFP'!DE10)/1000000 -> 299.14733
B4: CCA | C4: Min 10% | D4: =D3/(('Evolutive SFP'!#REF!)/1000000) -> #REF! | E4: =E3/(('Evolutive SFP'!#REF!)/1000000) -> #REF! | F4: =F3/(('Evolutive SFP'!#REF!)/1000000) -> #REF! | G4: =G3/(('Evolutive SFP'!#REF!)/1000000) -> #REF! | H4: =H3/(('Evolutive SFP'!#REF!)/1000000) -> #REF! | I4: =I3/(('Evolutive SFP'!#REF!)/1000000) -> #REF! | J4: =J3/(('Evolutive SFP'!#REF!)/1000000) -> #REF! | K4: =K3/(('Evolutive SFP'!#REF!)/1000000) -> #REF! | ... AS4: =AS3/(('Evolutive SFP'!#REF!)/1000000) -> #REF! | AT4: =AT3/(('Evolutive SFP'!BV27)/1000000) -> 0.77528378 | AU4: =AU3/(('Evolutive SFP'!BW27)/1000000) -> 0.53420891 | AV4: =AV3/(('Evolutive SFP'!BX27)/1000000) -> 0.52233314 | AW4: =AW3/(('Evolutive SFP'!BY27)/1000000) -> 0.52441772 | AX4: =AX3/(('Evolutive SFP'!BZ27)/1000000) -> 0.47876999 | AY4: =AY3/(('Evolutive SFP'!CA27)/1000000) -> 0.50185115 | AZ4: =AZ3/(('Evolutive SFP'!CB27)/1000000) -> 0.43762339 | BA4: =BA3/(('Evolutive SFP'!#REF!)/1000000) -> #REF! | BB4: =BB3/(('Evolutive SFP'!CC27)/1000000) -> 0.48019339 | BC4: =BC3/(('Evolutive SFP'!CD27)/1000000) -> 0.36128292 | BD4: =BD3/(('Evolutive SFP'!CE27)/1000000) -> 0.42508747 | BE4: =BE3/(('Evolutive SFP'!CF27)/1000000) -> 0.46256518 | BF4: =BF3/(('Evolutive SFP'!CG27)/1000000) -> 0.46919977 | BG4: =BG3/(('Evolutive SFP'!CH27)/1000000) -> 0.46395069 | BH4: =BH3/(('Evolutive SFP'!CI27)/1000000) -> 0.47957621 | BI4: =BI3/(('Evolutive SFP'!CJ27)/1000000) -> 0.47917598 | ... CD4: =CD3/(('Evolutive SFP'!DE27)/1000000) -> 0.43800194
B5: CCD | C5: Min 8% | D5: =D3/('Evolutive SFP'!#REF!/1000000) -> #REF! | E5: =E3/('Evolutive SFP'!#REF!/1000000) -> #REF! | F5: =F3/('Evolutive SFP'!#REF!/1000000) -> #REF! | G5: =G3/('Evolutive SFP'!#REF!/1000000) -> #REF! | H5: =H3/('Evolutive SFP'!#REF!/1000000) -> #REF! | I5: =I3/('Evolutive SFP'!#REF!/1000000) -> #REF! | J5: =J3/('Evolutive SFP'!#REF!/1000000) -> #REF! | K5: =K3/('Evolutive SFP'!#REF!/1000000) -> #REF! | ... AS5: =AS3/('Evolutive SFP'!#REF!/1000000) -> #REF! | AT5: =AT3/('Evolutive SFP'!BV31/1000000) -> 1.7350576 | AU5: =AU3/('Evolutive SFP'!BW31/1000000) -> 1.2205512 | AV5: =AV3/('Evolutive SFP'!BX31/1000000) -> 1.1684091 | AW5: =AW3/('Evolutive SFP'!BY31/1000000) -> 1.1769387 | AX5: =AX3/('Evolutive SFP'!BZ31/1000000) -> 0.96121048 | AY5: =AY3/('Evolutive SFP'!CA31/1000000) -> 1.0323702 | AZ5: =AZ3/('Evolutive SFP'!CB31/1000000) -> 0.78971594 | BA5: =BA3/('Evolutive SFP'!#REF!/1000000) -> #REF! | BB5: =BB3/('Evolutive SFP'!CC31/1000000) -> 0.93653348 | BC5: =BC3/('Evolutive SFP'!CD31/1000000) -> 0.61831922 | BD5: =BD3/('Evolutive SFP'!CE31/1000000) -> 0.75312334 | BE5: =BE3/('Evolutive SFP'!CF31/1000000) -> 0.87182852 | BF5: =BF3/('Evolutive SFP'!CG31/1000000) -> 0.92363571 | BG5: =BG3/('Evolutive SFP'!CH31/1000000) -> 0.91330272 | BH5: =BH3/('Evolutive SFP'!CI31/1000000) -> 0.965492 | BI5: =BI3/('Evolutive SFP'!CJ31/1000000) -> 0.96785497 | ... CD5: =CD3/('Evolutive SFP'!DE31/1000000) -> 0.87593409
B6: ICA | C6: Min 8% | D6: =((D3*1000000)-'Evolutive SFP'!#REF!)/'Evolutive SFP'!#REF! -> #REF! | E6: =((E3*1000000)-'Evolutive SFP'!#REF!)/'Evolutive SFP'!#REF! -> #REF! | F6: =((F3*1000000)-'Evolutive SFP'!#REF!)/'Evolutive SFP'!#REF! -> #REF! | G6: =((G3*1000000)-'Evolutive SFP'!#REF!)/'Evolutive SFP'!#REF! -> #REF! | H6: =((H3*1000000)-'Evolutive SFP'!#REF!)/'Evolutive SFP'!#REF! -> #REF! | I6: =((I3*1000000)-'Evolutive SFP'!#REF!)/'Evolutive SFP'!#REF! -> #REF! | J6: =((J3*1000000)-'Evolutive SFP'!#REF!)/'Evolutive SFP'!#REF! -> #REF! | K6: =((K3*1000000)-'Evolutive SFP'!#REF!)/'Evolutive SFP'!#REF! -> #REF! | ... AS6: =((AS3*1000000)-'Evolutive SFP'!#REF!)/'Evolutive SFP'!#REF! -> #REF! | AT6: =((AT3*1000000)-'Evolutive SFP'!BV39)/'Evolutive SFP'!BV27 -> 0.6154995 | AU6: =((AU3*1000000)-'Evolutive SFP'!BW39)/'Evolutive SFP'!BW27 -> 0.37031067 | AV6: =((AV3*1000000)-'Evolutive SFP'!BX39)/'Evolutive SFP'!BX27 -> 0.35717496 | AW6: =((AW3*1000000)-'Evolutive SFP'!BY39)/'Evolutive SFP'!BY27 -> 0.3570412 | AX6: =((AX3*1000000)-'Evolutive SFP'!BZ39)/'Evolutive SFP'!BZ27 -> 0.33082465 | AY6: =((AY3*1000000)-'Evolutive SFP'!CA39)/'Evolutive SFP'!CA27 -> 0.34586016 | AZ6: =((AZ3*1000000)-'Evolutive SFP'!CB39)/'Evolutive SFP'!CB27 -> 0.31036977 | BA6: =((BA3*1000000)-'Evolutive SFP'!#REF!)/'Evolutive SFP'!#REF! -> #REF! | BB6: =((BB3*1000000)-'Evolutive SFP'!CC39)/'Evolutive SFP'!CC27 -> 0.34084719 | BC6: =((BC3*1000000)-'Evolutive SFP'!CD39)/'Evolutive SFP'!CD27 -> 0.25795969 | BD6: =((BD3*1000000)-'Evolutive SFP'!CE39)/'Evolutive SFP'!CE27 -> 0.30445071 | BE6: =((BE3*1000000)-'Evolutive SFP'!CF39)/'Evolutive SFP'!CF27 -> 0.32915764 | BF6: =((BF3*1000000)-'Evolutive SFP'!CG39)/'Evolutive SFP'!CG27 -> 0.32856566 | BG6: =((BG3*1000000)-'Evolutive SFP'!CH39)/'Evolutive SFP'!CH27 -> 0.32331659 | BH6: =((BH3*1000000)-'Evolutive SFP'!CI39)/'Evolutive SFP'!CI27 -> 0.33379739 | BI6: =((BI3*1000000)-'Evolutive SFP'!CJ39)/'Evolutive SFP'!CJ27 -> 0.33079623 | ... CD6: =((CD3*1000000)-'Evolutive SFP'!DE39)/'Evolutive SFP'!DE27 -> 0.31996357
A7: ASSET QUALITY | B7: A/LNPL30 | F7: 0.36 | G7: 0.52149977 | J7: ='Evolutive SFP'!#REF!/('FORM 4'!D5+'FORM 4'!D6+'FORM 4'!D7) -> #REF! | M7: ='Evolutive SFP'!#REF!/('FORM 4'!D14+'FORM 4'!D15+'FORM 4'!D16) -> #REF! | P7: ='Evolutive SFP'!#REF!/('FORM 4'!D25+'FORM 4'!D26+'FORM 4'!D27) -> #REF! | S7: ='Evolutive SFP'!#REF!/('FORM 4'!D36+'FORM 4'!D37+'FORM 4'!D38) -> #REF! | T7: ='Evolutive SFP'!#REF!/('FORM 4'!E36+'FORM 4'!E37+'FORM 4'!E38) -> #REF! | U7: ='Evolutive SFP'!#REF!/('FORM 4'!F36+'FORM 4'!F37+'FORM 4'!F38) -> #REF! | V7: ='Evolutive SFP'!#REF!/('FORM 4'!G36+'FORM 4'!G37+'FORM 4'!G38) -> #REF! | W7: ='Evolutive SFP'!#REF!/('FORM 4'!H36+'FORM 4'!H37+'FORM 4'!H38) -> #REF! | X7: ='Evolutive SFP'!#REF!/('FORM 4'!I36+'FORM 4'!I37+'FORM 4'!I38) -> #REF! | Y7: ='Evolutive SFP'!#REF!/('FORM 4'!J36+'FORM 4'!J37+'FORM 4'!J38) -> #REF! | Z7: ='Evolutive SFP'!#REF!/('FORM 4'!#REF!+'FORM 4'!#REF!+'FORM 4'!#REF!) -> #REF! | AA7: ='Evolutive SFP'!#REF!/('FORM 4'!K36+'FORM 4'!K37+'FORM 4'!K38) -> #REF! | AB7: ='Evolutive SFP'!#REF!/('FORM 4'!L36+'FORM 4'!L37+'FORM 4'!L38) -> #REF! | AC7: ='Evolutive SFP'!#REF!/('FORM 4'!M36+'FORM 4'!M37+'FORM 4'!M38) -> #REF! | AD7: ='Evolutive SFP'!#REF!/('FORM 4'!N36+'FORM 4'!N37+'FORM 4'!N38) -> #REF! | AE7: ='Evolutive SFP'!#REF!/('FORM 4'!O36+'FORM 4'!O37+'FORM 4'!O38) -> #REF! | AF7: ='Evolutive SFP'!#REF!/('FORM 4'!P36+'FORM 4'!P37+'FORM 4'!P38) -> #REF! | AG7: ='Evolutive SFP'!#REF!/('FORM 4'!Q36+'FORM 4'!Q37+'FORM 4'!Q38) -> #REF! | AH7: ='Evolutive SFP'!#REF!/('FORM 4'!R36+'FORM 4'!R37+'FORM 4'!R38) -> #REF! | ... AP7: ='Evolutive SFP'!#REF!/('FORM 4'!Z36+'FORM 4'!Z37+'FORM 4'!Z38) -> #REF!
B8: NPL30 | F8: 0.02 | G8: 0.051294614 | J8: =('FORM 4'!D5+'FORM 4'!D6+'FORM 4'!D7)/'Evolutive SFP'!#REF! -> #REF! | M8: =('FORM 4'!D14+'FORM 4'!D15+'FORM 4'!D16)/'Evolutive SFP'!#REF! -> #REF! | P8: =('FORM 4'!D25+'FORM 4'!D26+'FORM 4'!D27)/'Evolutive SFP'!#REF! -> #REF! | S8: =('FORM 4'!D36+'FORM 4'!D37+'FORM 4'!D38)/'Evolutive SFP'!#REF! -> #REF! | T8: =('FORM 4'!E36+'FORM 4'!E37+'FORM 4'!E38)/'Evolutive SFP'!#REF! -> #REF! | U8: =('FORM 4'!F36+'FORM 4'!F37+'FORM 4'!F38)/'Evolutive SFP'!#REF! -> #REF! | V8: =('FORM 4'!G36+'FORM 4'!G37+'FORM 4'!G38)/'Evolutive SFP'!#REF! -> #REF! | W8: =('FORM 4'!H36+'FORM 4'!H37+'FORM 4'!H38)/'Evolutive SFP'!#REF! -> #REF! | X8: =('FORM 4'!I36+'FORM 4'!I37+'FORM 4'!I38)/'Evolutive SFP'!#REF! -> #REF! | Y8: =('FORM 4'!J36+'FORM 4'!J37+'FORM 4'!J38)/'Evolutive SFP'!#REF! -> #REF! | Z8: =('FORM 4'!#REF!+'FORM 4'!#REF!+'FORM 4'!#REF!)/'Evolutive SFP'!#REF! -> #REF! | AA8: =('FORM 4'!K36+'FORM 4'!K37+'FORM 4'!K38)/'Evolutive SFP'!#REF! -> #REF! | AB8: =('FORM 4'!L36+'FORM 4'!L37+'FORM 4'!L38)/'Evolutive SFP'!#REF! -> #REF! | AC8: =('FORM 4'!M36+'FORM 4'!M37+'FORM 4'!M38)/'Evolutive SFP'!#REF! -> #REF! | AD8: =('FORM 4'!N36+'FORM 4'!N37+'FORM 4'!N38)/'Evolutive SFP'!#REF! -> #REF! | AE8: =('FORM 4'!O36+'FORM 4'!O37+'FORM 4'!O38)/'Evolutive SFP'!#REF! -> #REF! | AF8: =('FORM 4'!P36+'FORM 4'!P37+'FORM 4'!P38)/'Evolutive SFP'!#REF! -> #REF! | AG8: =('FORM 4'!Q36+'FORM 4'!Q37+'FORM 4'!Q38)/'Evolutive SFP'!#REF! -> #REF! | AH8: =('FORM 4'!R36+'FORM 4'!R37+'FORM 4'!R38)/'Evolutive SFP'!#REF! -> #REF! | ... AS8: =('FORM 4'!AC36+'FORM 4'!AC37+'FORM 4'!AC38)/'Evolutive SFP'!#REF! -> #REF! | AT8: =('FORM 4'!AD36+'FORM 4'!AD37+'FORM 4'!AD38)/'Evolutive SFP'!BV15 -> 0 | AU8: =('FORM 4'!AE36+'FORM 4'!AE37+'FORM 4'!AE38)/'Evolutive SFP'!BW15 -> 0 | AV8: =('FORM 4'!AF36+'FORM 4'!AF37+'FORM 4'!AF38)/'Evolutive SFP'!BX15 -> 0 | AW8: =('FORM 4'!AG36+'FORM 4'!AG37+'FORM 4'!AG38)/'Evolutive SFP'!BY15 -> 0 | AX8: =('FORM 4'!AH36+'FORM 4'!AH37+'FORM 4'!AH38)/'Evolutive SFP'!BZ15 -> 0 | AY8: =('FORM 4'!AI36+'FORM 4'!AI37+'FORM 4'!AI38)/'Evolutive SFP'!CA15 -> 0 | AZ8: =('FORM 4'!AJ36+'FORM 4'!AJ37+'FORM 4'!AJ38)/'Evolutive SFP'!CB15 -> 0 | BA8: =('FORM 4'!AK36+'FORM 4'!AK37+'FORM 4'!AK38)/'Evolutive SFP'!#REF! -> #REF! | BB8: =('FORM 4'!AL36+'FORM 4'!AL37+'FORM 4'!AL38)/'Evolutive SFP'!CC15 -> 0 | BC8: =('FORM 4'!AM36+'FORM 4'!AM37+'FORM 4'!AM38)/'Evolutive SFP'!CD15 -> 0 | BD8: =('FORM 4'!AN36+'FORM 4'!AN37+'FORM 4'!AN38)/'Evolutive SFP'!CE15 -> 0 | BE8: =('FORM 4'!AO36+'FORM 4'!AO37+'FORM 4'!AO38)/'Evolutive SFP'!CF15 -> 0 | BF8: =('FORM 4'!AP36+'FORM 4'!AP37+'FORM 4'!AP38)/'Evolutive SFP'!CG15 -> 0 | BG8: =('FORM 4'!AQ36+'FORM 4'!AQ37+'FORM 4'!AQ38)/'Evolutive SFP'!CH15 -> 0 | BH8: =('FORM 4'!AR36+'FORM 4'!AR37+'FORM 4'!AR38)/'Evolutive SFP'!CI15 -> 0 | BI8: =('FORM 4'!AS36+'FORM 4'!AS37+'FORM 4'!AS38)/'Evolutive SFP'!CJ15 -> 0 | ... CD8: =('FORM 4'!BN36+'FORM 4'!BN37+'FORM 4'!BN38)/'Evolutive SFP'!DE15 -> 0
A9: EARNINGS | B9: ROA | E9: ='Evolutitve SCI'!#REF!/(('Evolutive SFP'!#REF!+'Evolutive SFP'!#REF!)/2) -> #REF! | H9: ='Evolutitve SCI'!#REF!/(('Evolutive SFP'!#REF!+'Evolutive SFP'!#REF!)/2) -> #REF! | I9: ='Evolutitve SCI'!#REF!/(('Evolutive SFP'!#REF!+'Evolutive SFP'!#REF!)/2) -> #REF! | J9: ='Evolutitve SCI'!#REF!/(('Evolutive SFP'!#REF!+'Evolutive SFP'!#REF!)/2) -> #REF! | K9: ='Evolutitve SCI'!#REF!/(('Evolutive SFP'!#REF!+'Evolutive SFP'!#REF!)/2) -> #REF! | L9: ='Evolutitve SCI'!#REF!/(('Evolutive SFP'!#REF!+'Evolutive SFP'!#REF!)/2) -> #REF! | M9: ='Evolutitve SCI'!#REF!/(('Evolutive SFP'!#REF!+'Evolutive SFP'!#REF!)/2) -> #REF! | N9: ='Evolutitve SCI'!#REF!/(('Evolutive SFP'!#REF!+'Evolutive SFP'!#REF!)/2) -> #REF! | O9: ='Evolutitve SCI'!#REF!/(('Evolutive SFP'!#REF!+'Evolutive SFP'!#REF!)/2) -> #REF! | ... AS9: ='Evolutitve SCI'!#REF!/(('Evolutive SFP'!#REF!+'Evolutive SFP'!#REF!)/2) -> #REF! | AT9: ='Evolutitve SCI'!BV33/(('Evolutive SFP'!#REF!+'Evolutive SFP'!BV27)/2) -> #REF! | AU9: ='Evolutitve SCI'!BW33/(('Evolutive SFP'!BV27+'Evolutive SFP'!BW27)/2) -> -0.0039400293 | AV9: ='Evolutitve SCI'!BX33/(('Evolutive SFP'!BW27+'Evolutive SFP'!BX27)/2) -> -0.019360769 | AW9: ='Evolutitve SCI'!BY33/(('Evolutive SFP'!BX27+'Evolutive SFP'!BY27)/2) -> -0.023995155 | AX9: ='Evolutitve SCI'!BZ33/(('Evolutive SFP'!BY27+'Evolutive SFP'!BZ27)/2) -> -0.0054055663 | AY9: ='Evolutitve SCI'!CA33/(('Evolutive SFP'!BZ27+'Evolutive SFP'!CA27)/2) -> -0.0082655447 | AZ9: ='Evolutitve SCI'!CB33/(('Evolutive SFP'!CA27+'Evolutive SFP'!CB27)/2) -> 0.027618001 | BA9: ='Evolutitve SCI'!#REF!/(('Evolutive SFP'!CB27+'Evolutive SFP'!#REF!)/2) -> #REF! | BB9: ='Evolutitve SCI'!CC33/(('Evolutive SFP'!#REF!+'Evolutive SFP'!CC27)/2) -> #REF! | BC9: ='Evolutitve SCI'!CD33/(('Evolutive SFP'!CC27+'Evolutive SFP'!CD27)/2) -> 0.031874123 | BD9: ='Evolutitve SCI'!CE33/(('Evolutive SFP'!CD27+'Evolutive SFP'!CE27)/2) -> 0.033617767 | BE9: ='Evolutitve SCI'!CF33/(('Evolutive SFP'!CE27+'Evolutive SFP'!CF27)/2) -> 0.031632673 | BF9: ='Evolutitve SCI'!CG33/(('Evolutive SFP'!CF27+'Evolutive SFP'!CG27)/2) -> 0.017051678 | BG9: ='Evolutitve SCI'!CH33/(('Evolutive SFP'!CG27+'Evolutive SFP'!CH27)/2) -> 0.017496913 | BH9: ='Evolutitve SCI'!CI33/(('Evolutive SFP'!CH27+'Evolutive SFP'!CI27)/2) -> -0.0056883551 | BI9: ='Evolutitve SCI'!CJ33/(('Evolutive SFP'!CI27+'Evolutive SFP'!CJ27)/2) -> -0.014400372 | BJ9: ='Evolutitve SCI'!CK33/(('Evolutive SFP'!CJ27+'Evolutive SFP'!CK27)/2) -> -0.017879234 | ... CD9: ='Evolutitve SCI'!DE33/(('Evolutive SFP'!DD27+'Evolutive SFP'!DE27)/2) -> 0.037276433
B10: Cost Income ratio | D10: ='Evolutitve SCI'!#REF!/'Evolutitve SCI'!#REF! -> #REF! | E10: ='Evolutitve SCI'!#REF!/'Evolutitve SCI'!#REF! -> #REF! | F10: ='Evolutitve SCI'!#REF!/'Evolutitve SCI'!#REF! -> #REF! | G10: ='Evolutitve SCI'!#REF!/'Evolutitve SCI'!#REF! -> #REF! | H10: ='Evolutitve SCI'!#REF!/'Evolutitve SCI'!#REF! -> #REF! | I10: ='Evolutitve SCI'!#REF!/'Evolutitve SCI'!#REF! -> #REF! | J10: ='Evolutitve SCI'!#REF!/'Evolutitve SCI'!#REF! -> #REF! | K10: ='Evolutitve SCI'!#REF!/'Evolutitve SCI'!#REF! -> #REF! | ... AS10: ='Evolutitve SCI'!#REF!/'Evolutitve SCI'!#REF! -> #REF! | AT10: ='Evolutitve SCI'!BV23/'Evolutitve SCI'!BV19 -> 0.73417195 | AU10: ='Evolutitve SCI'!BW23/'Evolutitve SCI'!BW19 -> 1.6712662 | AV10: ='Evolutitve SCI'!BX23/'Evolutitve SCI'!BX19 -> 1.3884305 | AW10: ='Evolutitve SCI'!BY23/'Evolutitve SCI'!BY19 -> 1.2992573 | AX10: ='Evolutitve SCI'!BZ23/'Evolutitve SCI'!BZ19 -> 0.58262595 | AY10: ='Evolutitve SCI'!CA23/'Evolutitve SCI'!CA19 -> 0.63585087 | AZ10: ='Evolutitve SCI'!CB23/'Evolutitve SCI'!CB19 -> 0.49773171 | BA10: ='Evolutitve SCI'!#REF!/'Evolutitve SCI'!#REF! -> #REF! | BB10: ='Evolutitve SCI'!CC23/'Evolutitve SCI'!CC19 -> 0.53972706 | BC10: ='Evolutitve SCI'!CD23/'Evolutitve SCI'!CD19 -> 0.5331407 | BD10: ='Evolutitve SCI'!CE23/'Evolutitve SCI'!CE19 -> 0.54778338 | BE10: ='Evolutitve SCI'!CF23/'Evolutitve SCI'!CF19 -> 0.59670583 | BF10: ='Evolutitve SCI'!CG23/'Evolutitve SCI'!CG19 -> 0.70930469 | BG10: ='Evolutitve SCI'!CH23/'Evolutitve SCI'!CH19 -> 0.70837486 | BH10: ='Evolutitve SCI'!CI23/'Evolutitve SCI'!CI19 -> 1.1642495 | BI10: ='Evolutitve SCI'!CJ23/'Evolutitve SCI'!CJ19 -> 1.0980276 | ... CD10: ='Evolutitve SCI'!DE23/'Evolutitve SCI'!DE19 -> 0.57219899
B11: Operating Expense ratio | D11: =('Evolutitve SCI'!#REF!+'Evolutitve SCI'!#REF!)/(('Evolutive SFP'!#REF!+'Evolutive SFP'!#REF!)/2) -> #REF! | E11: =('Evolutitve SCI'!#REF!+'Evolutitve SCI'!#REF!)/(('Evolutive SFP'!#REF!+'Evolutive SFP'!#REF!)/2) -> #REF! | F11: =('Evolutitve SCI'!#REF!+'Evolutitve SCI'!#REF!)/(('Evolutive SFP'!#REF!+'Evolutive SFP'!#REF!)/2) -> #REF! | G11: =('Evolutitve SCI'!#REF!+'Evolutitve SCI'!#REF!)/(('Evolutive SFP'!#REF!+'Evolutive SFP'!#REF!)/2) -> #REF! | H11: =('Evolutitve SCI'!#REF!+'Evolutitve SCI'!#REF!)/(('Evolutive SFP'!#REF!+'Evolutive SFP'!#REF!)/2) -> #REF! | I11: =('Evolutitve SCI'!#REF!+'Evolutitve SCI'!#REF!)/(('Evolutive SFP'!#REF!+'Evolutive SFP'!#REF!)/2) -> #REF! | J11: =('Evolutitve SCI'!#REF!+'Evolutitve SCI'!#REF!)/(('Evolutive SFP'!#REF!+'Evolutive SFP'!#REF!)/2) -> #REF! | K11: =('Evolutitve SCI'!#REF!+'Evolutitve SCI'!#REF!)/(('Evolutive SFP'!#REF!+'Evolutive SFP'!#REF!)/2) -> #REF! | ... AQ11: =('Evolutitve SCI'!#REF!+'Evolutitve SCI'!#REF!)/(('Evolutive SFP'!#REF!+'Evolutive SFP'!#REF!)/2) -> #REF! | AR11: =('Evolutitve SCI'!#REF!+'Evolutitve SCI'!#REF!)/(('Evolutive SFP'!#REF!+'Evolutive SFP'!BV27)/2) -> #REF! | AS11: =('Evolutitve SCI'!#REF!+'Evolutitve SCI'!#REF!)/(('Evolutive SFP'!#REF!+'Evolutive SFP'!BW27)/2) -> #REF! | AT11: =('Evolutitve SCI'!BV23+'Evolutitve SCI'!BV12)/(('Evolutive SFP'!BV27+'Evolutive SFP'!BX27)/2) -> 0.10858774 | AU11: =('Evolutitve SCI'!BW23+'Evolutitve SCI'!BW12)/(('Evolutive SFP'!BW27+'Evolutive SFP'!BY27)/2) -> 0.0068405287 | AV11: =('Evolutitve SCI'!BX23+'Evolutitve SCI'!BX12)/(('Evolutive SFP'!BX27+'Evolutive SFP'!BZ27)/2) -> 0.014109828 | AW11: =('Evolutitve SCI'!BY23+'Evolutitve SCI'!BY12)/(('Evolutive SFP'!BY27+'Evolutive SFP'!CA27)/2) -> 0.020906335 | AX11: =('Evolutitve SCI'!BZ23+'Evolutitve SCI'!BZ12)/(('Evolutive SFP'!BZ27+'Evolutive SFP'!CB27)/2) -> 0.023167535 | AY11: =('Evolutitve SCI'!CA23+'Evolutitve SCI'!CA12)/(('Evolutive SFP'!CA27+'Evolutive SFP'!#REF!)/2) -> #REF! | AZ11: =('Evolutitve SCI'!CB23+'Evolutitve SCI'!CB12)/(('Evolutive SFP'!CB27+'Evolutive SFP'!CC27)/2) -> 0.033545789 | BA11: =('Evolutitve SCI'!#REF!+'Evolutitve SCI'!#REF!)/(('Evolutive SFP'!#REF!+'Evolutive SFP'!CD27)/2) -> #REF! | BB11: =('Evolutitve SCI'!CC23+'Evolutitve SCI'!CC12)/(('Evolutive SFP'!CC27+'Evolutive SFP'!CE27)/2) -> 0.043379371 | BC11: =('Evolutitve SCI'!CD23+'Evolutitve SCI'!CD12)/(('Evolutive SFP'!CD27+'Evolutive SFP'!#REF!)/2) -> #REF! | BD11: =('Evolutitve SCI'!CE23+'Evolutitve SCI'!CE12)/(('Evolutive SFP'!CE27+'Evolutive SFP'!#REF!)/2) -> #REF! | BE11: =('Evolutitve SCI'!CF23+'Evolutitve SCI'!CF12)/(('Evolutive SFP'!CF27+'Evolutive SFP'!#REF!)/2) -> #REF! | BF11: =('Evolutitve SCI'!CG23+'Evolutitve SCI'!CG12)/(('Evolutive SFP'!CG27+'Evolutive SFP'!#REF!)/2) -> #REF! | BG11: =('Evolutitve SCI'!CH23+'Evolutitve SCI'!CH12)/(('Evolutive SFP'!CH27+'Evolutive SFP'!#REF!)/2) -> #REF! | BH11: =('Evolutitve SCI'!CI23+'Evolutitve SCI'!CI12)/(('Evolutive SFP'!CI27+'Evolutive SFP'!#REF!)/2) -> #REF! | BI11: =('Evolutitve SCI'!CJ23+'Evolutitve SCI'!CJ12)/(('Evolutive SFP'!CJ27+'Evolutive SFP'!#REF!)/2) -> #REF! | BJ11: =('Evolutitve SCI'!CK23+'Evolutitve SCI'!CK12)/(('Evolutive SFP'!CK27+'Evolutive SFP'!#REF!)/2) -> #REF! | ... CD11: =('Evolutitve SCI'!DE23+'Evolutitve SCI'!DE12)/(('Evolutive SFP'!DE27+'Evolutive SFP'!#REF!)/2) -> #REF!
A12: LIQUIDITY | B12: MIN LIQ ratio | C12: Min 15% | D12: =('Evolutive SFP'!#REF!)/('Evolutive SFP'!#REF!+'Evolutive SFP'!#REF!+'Evolutive SFP'!#REF!+'Evolutive SFP'!#REF!+'Evolutive SFP'!#REF!+'Evolutive SFP'!#REF!+'Evolutive SFP'!#REF!) -> #REF! | E12: =('Evolutive SFP'!#REF!)/('Evolutive SFP'!#REF!+'Evolutive SFP'!#REF!+'Evolutive SFP'!#REF!+'Evolutive SFP'!#REF!+'Evolutive SFP'!#REF!+'Evolutive SFP'!#REF!+'Evolutive SFP'!#REF!) -> #REF! | F12: =('Evolutive SFP'!#REF!)/('Evolutive SFP'!#REF!+'Evolutive SFP'!#REF!+'Evolutive SFP'!#REF!+'Evolutive SFP'!#REF!+'Evolutive SFP'!#REF!+'Evolutive SFP'!#REF!+'Evolutive SFP'!#REF!) -> #REF! | G12: =('Evolutive SFP'!#REF!)/('Evolutive SFP'!#REF!+'Evolutive SFP'!#REF!+'Evolutive SFP'!#REF!+'Evolutive SFP'!#REF!+'Evolutive SFP'!#REF!+'Evolutive SFP'!#REF!+'Evolutive SFP'!#REF!) -> #REF! | H12: =('Evolutive SFP'!#REF!)/('Evolutive SFP'!#REF!+'Evolutive SFP'!#REF!+'Evolutive SFP'!#REF!+'Evolutive SFP'!#REF!+'Evolutive SFP'!#REF!+'Evolutive SFP'!#REF!+'Evolutive SFP'!#REF!) -> #REF! | I12: =('Evolutive SFP'!#REF!)/('Evolutive SFP'!#REF!+'Evolutive SFP'!#REF!+'Evolutive SFP'!#REF!+'Evolutive SFP'!#REF!+'Evolutive SFP'!#REF!+'Evolutive SFP'!#REF!+'Evolutive SFP'!#REF!) -> #REF! | J12: =('Evolutive SFP'!#REF!)/('Evolutive SFP'!#REF!+'Evolutive SFP'!#REF!+'Evolutive SFP'!#REF!+'Evolutive SFP'!#REF!+'Evolutive SFP'!#REF!+'Evolutive SFP'!#REF!+'Evolutive SFP'!#REF!) -> #REF! | K12: =('Evolutive SFP'!#REF!)/('Evolutive SFP'!#REF!+'Evolutive SFP'!#REF!+'Evolutive SFP'!#REF!+'Evolutive SFP'!#REF!+'Evolutive SFP'!#REF!+'Evolutive SFP'!#REF!+'Evolutive SFP'!#REF!) -> #REF! | ... AS12: =('Evolutive SFP'!#REF!)/('Evolutive SFP'!#REF!+'Evolutive SFP'!#REF!+'Evolutive SFP'!#REF!+'Evolutive SFP'!#REF!+'Evolutive SFP'!#REF!+'Evolutive SFP'!#REF!+'Evolutive SFP'!#REF!) -> #REF! | AT12: =('Evolutive SFP'!BV4)/('Evolutive SFP'!BV28+'Evolutive SFP'!BV29+'Evolutive SFP'!BV32+'Evolutive SFP'!BV33+'Evolutive SFP'!BV34+'Evolutive SFP'!BV35+'Evolutive SFP'!BV36) -> 0.11889364 | AU12: =('Evolutive SFP'!BW4)/('Evolutive SFP'!BW28+'Evolutive SFP'!BW29+'Evolutive SFP'!BW32+'Evolutive SFP'!BW33+'Evolutive SFP'!BW34+'Evolutive SFP'!BW35+'Evolutive SFP'!BW36) -> 0.36750772 | AV12: =('Evolutive SFP'!BX4)/('Evolutive SFP'!BX28+'Evolutive SFP'!BX29+'Evolutive SFP'!BX32+'Evolutive SFP'!BX33+'Evolutive SFP'!BX34+'Evolutive SFP'!BX35+'Evolutive SFP'!BX36) -> 0.36711337 | AW12: =('Evolutive SFP'!BY4)/('Evolutive SFP'!BY28+'Evolutive SFP'!BY29+'Evolutive SFP'!BY32+'Evolutive SFP'!BY33+'Evolutive SFP'!BY34+'Evolutive SFP'!BY35+'Evolutive SFP'!BY36) -> 0.39381743 | AX12: =('Evolutive SFP'!BZ4)/('Evolutive SFP'!BZ28+'Evolutive SFP'!BZ29+'Evolutive SFP'!BZ32+'Evolutive SFP'!BZ33+'Evolutive SFP'!BZ34+'Evolutive SFP'!BZ35+'Evolutive SFP'!BZ36) -> 1.0277814 | AY12: =('Evolutive SFP'!CA4)/('Evolutive SFP'!CA28+'Evolutive SFP'!CA29+'Evolutive SFP'!CA32+'Evolutive SFP'!CA33+'Evolutive SFP'!CA34+'Evolutive SFP'!CA35+'Evolutive SFP'!CA36) -> 0.75490155 | AZ12: =('Evolutive SFP'!CB4)/('Evolutive SFP'!CB28+'Evolutive SFP'!CB29+'Evolutive SFP'!CB32+'Evolutive SFP'!CB33+'Evolutive SFP'!CB34+'Evolutive SFP'!CB35+'Evolutive SFP'!CB36) -> 1.0162315 | BA12: =('Evolutive SFP'!#REF!)/('Evolutive SFP'!#REF!+'Evolutive SFP'!#REF!+'Evolutive SFP'!#REF!+'Evolutive SFP'!#REF!+'Evolutive SFP'!#REF!+'Evolutive SFP'!#REF!+'Evolutive SFP'!#REF!) -> #REF! | BB12: =('Evolutive SFP'!CC4)/('Evolutive SFP'!CC28+'Evolutive SFP'!CC29+'Evolutive SFP'!CC32+'Evolutive SFP'!CC33+'Evolutive SFP'!CC34+'Evolutive SFP'!CC35+'Evolutive SFP'!CC36) -> 0.62353393 | BC12: =('Evolutive SFP'!CD4)/('Evolutive SFP'!CD28+'Evolutive SFP'!CD29+'Evolutive SFP'!CD32+'Evolutive SFP'!CD33+'Evolutive SFP'!CD34+'Evolutive SFP'!CD35+'Evolutive SFP'!CD36) -> 0.75818838 | BD12: =('Evolutive SFP'!CE4)/('Evolutive SFP'!CE28+'Evolutive SFP'!CE29+'Evolutive SFP'!CE32+'Evolutive SFP'!CE33+'Evolutive SFP'!CE34+'Evolutive SFP'!CE35+'Evolutive SFP'!CE36) -> 0.50284351 | BE12: =('Evolutive SFP'!CF4)/('Evolutive SFP'!CF28+'Evolutive SFP'!CF29+'Evolutive SFP'!CF32+'Evolutive SFP'!CF33+'Evolutive SFP'!CF34+'Evolutive SFP'!CF35+'Evolutive SFP'!CF36) -> 0.21041418 | BF12: =('Evolutive SFP'!CG4)/('Evolutive SFP'!CG28+'Evolutive SFP'!CG29+'Evolutive SFP'!CG32+'Evolutive SFP'!CG33+'Evolutive SFP'!CG34+'Evolutive SFP'!CG35+'Evolutive SFP'!CG36) -> 0.34403043 | BG12: =('Evolutive SFP'!CH4)/('Evolutive SFP'!CH28+'Evolutive SFP'!CH29+'Evolutive SFP'!CH32+'Evolutive SFP'!CH33+'Evolutive SFP'!CH34+'Evolutive SFP'!CH35+'Evolutive SFP'!CH36) -> 0.33726758 | BH12: =('Evolutive SFP'!CI4)/('Evolutive SFP'!CI28+'Evolutive SFP'!CI29+'Evolutive SFP'!CI32+'Evolutive SFP'!CI33+'Evolutive SFP'!CI34+'Evolutive SFP'!CI35+'Evolutive SFP'!CI36) -> 0.16557582 | BI12: =('Evolutive SFP'!CJ4)/('Evolutive SFP'!CJ28+'Evolutive SFP'!CJ29+'Evolutive SFP'!CJ32+'Evolutive SFP'!CJ33+'Evolutive SFP'!CJ34+'Evolutive SFP'!CJ35+'Evolutive SFP'!CJ36) -> 0.36412944 | ... CD12: =('Evolutive SFP'!DE4)/('Evolutive SFP'!DE28+'Evolutive SFP'!DE29+'Evolutive SFP'!DE32+'Evolutive SFP'!DE33+'Evolutive SFP'!DE34+'Evolutive SFP'!DE35+'Evolutive SFP'!DE36) -> 1.2281716
B13: T/LIQ ratio | D13: =('Evolutive SFP'!#REF!+'Evolutive SFP'!#REF!)/('Evolutive SFP'!#REF!+'Evolutive SFP'!#REF!+'Evolutive SFP'!#REF!+'Evolutive SFP'!#REF!+'Evolutive SFP'!#REF!+'Evolutive SFP'!#REF!) -> #REF! | E13: =('Evolutive SFP'!#REF!+'Evolutive SFP'!#REF!)/('Evolutive SFP'!#REF!+'Evolutive SFP'!#REF!+'Evolutive SFP'!#REF!+'Evolutive SFP'!#REF!+'Evolutive SFP'!#REF!+'Evolutive SFP'!#REF!) -> #REF! | F13: =('Evolutive SFP'!#REF!+'Evolutive SFP'!#REF!)/('Evolutive SFP'!#REF!+'Evolutive SFP'!#REF!+'Evolutive SFP'!#REF!+'Evolutive SFP'!#REF!+'Evolutive SFP'!#REF!+'Evolutive SFP'!#REF!) -> #REF! | G13: =('Evolutive SFP'!#REF!+'Evolutive SFP'!#REF!)/('Evolutive SFP'!#REF!+'Evolutive SFP'!#REF!+'Evolutive SFP'!#REF!+'Evolutive SFP'!#REF!+'Evolutive SFP'!#REF!+'Evolutive SFP'!#REF!) -> #REF! | H13: =('Evolutive SFP'!#REF!+'Evolutive SFP'!#REF!)/('Evolutive SFP'!#REF!+'Evolutive SFP'!#REF!+'Evolutive SFP'!#REF!+'Evolutive SFP'!#REF!+'Evolutive SFP'!#REF!+'Evolutive SFP'!#REF!) -> #REF! | I13: =('Evolutive SFP'!#REF!+'Evolutive SFP'!#REF!)/('Evolutive SFP'!#REF!+'Evolutive SFP'!#REF!+'Evolutive SFP'!#REF!+'Evolutive SFP'!#REF!+'Evolutive SFP'!#REF!+'Evolutive SFP'!#REF!) -> #REF! | J13: =('Evolutive SFP'!#REF!+'Evolutive SFP'!#REF!)/('Evolutive SFP'!#REF!+'Evolutive SFP'!#REF!+'Evolutive SFP'!#REF!+'Evolutive SFP'!#REF!+'Evolutive SFP'!#REF!+'Evolutive SFP'!#REF!) -> #REF! | K13: =('Evolutive SFP'!#REF!+'Evolutive SFP'!#REF!)/('Evolutive SFP'!#REF!+'Evolutive SFP'!#REF!+'Evolutive SFP'!#REF!+'Evolutive SFP'!#REF!+'Evolutive SFP'!#REF!+'Evolutive SFP'!#REF!) -> #REF! | ... O13: =('Evolutive SFP'!#REF!+'Evolutive SFP'!#REF!)/('Evolutive SFP'!#REF!+'Evolutive SFP'!#REF!+'Evolutive SFP'!#REF!+'Evolutive SFP'!#REF!+'Evolutive SFP'!#REF!+'Evolutive SFP'!#REF!) -> #REF! | P13: ='Evolutive SFP'!#REF!/('Evolutive SFP'!#REF!+'Evolutive SFP'!#REF!) -> #REF! | Q13: ='Evolutive SFP'!#REF!/('Evolutive SFP'!#REF!+'Evolutive SFP'!#REF!) -> #REF! | R13: ='Evolutive SFP'!#REF!/('Evolutive SFP'!#REF!+'Evolutive SFP'!#REF!) -> #REF! | S13: ='Evolutive SFP'!#REF!/('Evolutive SFP'!#REF!+'Evolutive SFP'!#REF!) -> #REF! | T13: ='Evolutive SFP'!#REF!/('Evolutive SFP'!#REF!+'Evolutive SFP'!#REF!) -> #REF! | U13: ='Evolutive SFP'!#REF!/('Evolutive SFP'!#REF!+'Evolutive SFP'!#REF!) -> #REF! | V13: ='Evolutive SFP'!#REF!/('Evolutive SFP'!#REF!+'Evolutive SFP'!#REF!) -> #REF! | W13: ='Evolutive SFP'!#REF!/('Evolutive SFP'!#REF!+'Evolutive SFP'!#REF!) -> #REF! | ... AS13: ='Evolutive SFP'!#REF!/('Evolutive SFP'!#REF!+'Evolutive SFP'!#REF!) -> #REF! | AT13: ='Evolutive SFP'!BV4/('Evolutive SFP'!BV31+'Evolutive SFP'!BV36) -> 0.11889364 | AU13: ='Evolutive SFP'!BW4/('Evolutive SFP'!BW31+'Evolutive SFP'!BW36) -> 0.15694931 | AV13: ='Evolutive SFP'!BX4/('Evolutive SFP'!BX31+'Evolutive SFP'!BX36) -> 0.16009437 | AW13: ='Evolutive SFP'!BY4/('Evolutive SFP'!BY31+'Evolutive SFP'!BY36) -> 0.16977644 | AX13: ='Evolutive SFP'!BZ4/('Evolutive SFP'!BZ31+'Evolutive SFP'!BZ36) -> 0.55439065 | AY13: ='Evolutive SFP'!CA4/('Evolutive SFP'!CA31+'Evolutive SFP'!CA36) -> 0.43149257 | AZ13: ='Evolutive SFP'!CB4/('Evolutive SFP'!CB31+'Evolutive SFP'!CB36) -> 0.61959748 | BA13: ='Evolutive SFP'!#REF!/('Evolutive SFP'!#REF!+'Evolutive SFP'!#REF!) -> #REF! | BB13: ='Evolutive SFP'!CC4/('Evolutive SFP'!CC31+'Evolutive SFP'!CC36) -> 0.32717902 | BC13: ='Evolutive SFP'!CD4/('Evolutive SFP'!CD31+'Evolutive SFP'!CD36) -> 0.53845563 | BD13: ='Evolutive SFP'!CE4/('Evolutive SFP'!CE31+'Evolutive SFP'!CE36) -> 0.30562725 | BE13: ='Evolutive SFP'!CF4/('Evolutive SFP'!CF31+'Evolutive SFP'!CF36) -> 0.111367 | BF13: ='Evolutive SFP'!CG4/('Evolutive SFP'!CG31+'Evolutive SFP'!CG36) -> 0.16993676 | BG13: ='Evolutive SFP'!CH4/('Evolutive SFP'!CH31+'Evolutive SFP'!CH36) -> 0.16800375 | BH13: ='Evolutive SFP'!CI4/('Evolutive SFP'!CI31+'Evolutive SFP'!CI36) -> 0.079098864 | BI13: ='Evolutive SFP'!CJ4/('Evolutive SFP'!CJ31+'Evolutive SFP'!CJ36) -> 0.16913838 | ... CD13: ='Evolutive SFP'!DE4/('Evolutive SFP'!DE31+'Evolutive SFP'!DE36) -> 0.58631575
B14: EB ratio | C14: Max 25% | D14: ='Evolutive SFP'!#REF!/'Evolutive SFP'!#REF! -> #REF! | E14: ='Evolutive SFP'!#REF!/'Evolutive SFP'!#REF! -> #REF! | F14: ='Evolutive SFP'!#REF!/'Evolutive SFP'!#REF! -> #REF! | G14: ='Evolutive SFP'!#REF!/'Evolutive SFP'!#REF! -> #REF! | H14: ='Evolutive SFP'!#REF!/'Evolutive SFP'!#REF! -> #REF! | I14: ='Evolutive SFP'!#REF!/'Evolutive SFP'!#REF! -> #REF! | J14: ='Evolutive SFP'!#REF!/'Evolutive SFP'!#REF! -> #REF! | K14: ='Evolutive SFP'!#REF!/'Evolutive SFP'!#REF! -> #REF! | ... AS14: ='Evolutive SFP'!#REF!/'Evolutive SFP'!#REF! -> #REF! | AT14: ='Evolutive SFP'!BV37/'Evolutive SFP'!BV27 -> 0 | AU14: ='Evolutive SFP'!BW37/'Evolutive SFP'!BW27 -> 0 | AV14: ='Evolutive SFP'!BX37/'Evolutive SFP'!BX27 -> 0 | AW14: ='Evolutive SFP'!BY37/'Evolutive SFP'!BY27 -> 0 | AX14: ='Evolutive SFP'!BZ37/'Evolutive SFP'!BZ27 -> 0 | AY14: ='Evolutive SFP'!CA37/'Evolutive SFP'!CA27 -> 0 | AZ14: ='Evolutive SFP'!CB37/'Evolutive SFP'!CB27 -> 0 | BA14: ='Evolutive SFP'!#REF!/'Evolutive SFP'!#REF! -> #REF! | BB14: ='Evolutive SFP'!CC37/'Evolutive SFP'!CC27 -> 0 | BC14: ='Evolutive SFP'!CD37/'Evolutive SFP'!CD27 -> 0 | BD14: ='Evolutive SFP'!CE37/'Evolutive SFP'!CE27 -> 0 | BE14: ='Evolutive SFP'!CF37/'Evolutive SFP'!CF27 -> 0 | BF14: ='Evolutive SFP'!CG37/'Evolutive SFP'!CG27 -> 0 | BG14: ='Evolutive SFP'!CH37/'Evolutive SFP'!CH27 -> 0 | BH14: ='Evolutive SFP'!CI37/'Evolutive SFP'!CI27 -> 0 | BI14: ='Evolutive SFP'!CJ37/'Evolutive SFP'!CJ27 -> 0 | ... CD14: ='Evolutive SFP'!DE37/'Evolutive SFP'!DE27 -> 0
B15: LA to TA ratio | D15: ='Evolutive SFP'!#REF!/'Evolutive SFP'!#REF! -> #REF! | E15: ='Evolutive SFP'!#REF!/'Evolutive SFP'!#REF! -> #REF! | F15: ='Evolutive SFP'!#REF!/'Evolutive SFP'!#REF! -> #REF! | G15: ='Evolutive SFP'!#REF!/'Evolutive SFP'!#REF! -> #REF! | H15: ='Evolutive SFP'!#REF!/'Evolutive SFP'!#REF! -> #REF! | I15: ='Evolutive SFP'!#REF!/'Evolutive SFP'!#REF! -> #REF! | J15: ='Evolutive SFP'!#REF!/'Evolutive SFP'!#REF! -> #REF! | K15: ='Evolutive SFP'!#REF!/'Evolutive SFP'!#REF! -> #REF! | ... AS15: ='Evolutive SFP'!#REF!/'Evolutive SFP'!#REF! -> #REF! | AT15: ='Evolutive SFP'!BV4/'Evolutive SFP'!BV27 -> 0.056964397 | AU15: ='Evolutive SFP'!BW4/'Evolutive SFP'!BW27 -> 0.07310559 | AV15: ='Evolutive SFP'!BX4/'Evolutive SFP'!BX27 -> 0.076471775 | AW15: ='Evolutive SFP'!BY4/'Evolutive SFP'!BY27 -> 0.080742665 | AX15: ='Evolutive SFP'!BZ4/'Evolutive SFP'!BZ27 -> 0.28896505 | AY15: ='Evolutive SFP'!CA4/'Evolutive SFP'!CA27 -> 0.21494753 | AZ15: ='Evolutive SFP'!CB4/'Evolutive SFP'!CB27 -> 0.34844713 | BA15: ='Evolutive SFP'!#REF!/'Evolutive SFP'!#REF! -> #REF! | BB15: ='Evolutive SFP'!CC4/'Evolutive SFP'!CC27 -> 0.17006982 | BC15: ='Evolutive SFP'!CD4/'Evolutive SFP'!CD27 -> 0.34299559 | BD15: ='Evolutive SFP'!CE4/'Evolutive SFP'!CE27 -> 0.17520561 | BE15: ='Evolutive SFP'!CF4/'Evolutive SFP'!CF27 -> 0.059681972 | BF15: ='Evolutive SFP'!CG4/'Evolutive SFP'!CG27 -> 0.090058295 | BG15: ='Evolutive SFP'!CH4/'Evolutive SFP'!CH27 -> 0.090058296 | BH15: ='Evolutive SFP'!CI4/'Evolutive SFP'!CI27 -> 0.039988928 | BI15: ='Evolutive SFP'!CJ4/'Evolutive SFP'!CJ27 -> 0.085534182 | ... CD15: ='Evolutive SFP'!DE4/'Evolutive SFP'!DE27 -> 0.30053852
A16: STRUCTURE | B16: NEA ratio | C16: Max 10% | D16: =('Evolutive SFP'!#REF!+'Evolutive SFP'!#REF!)/'Evolutive SFP'!#REF! -> #REF! | E16: =('Evolutive SFP'!#REF!+'Evolutive SFP'!#REF!)/'Evolutive SFP'!#REF! -> #REF! | F16: =('Evolutive SFP'!#REF!+'Evolutive SFP'!#REF!)/'Evolutive SFP'!#REF! -> #REF! | G16: =('Evolutive SFP'!#REF!+'Evolutive SFP'!#REF!)/'Evolutive SFP'!#REF! -> #REF! | H16: =('Evolutive SFP'!#REF!+'Evolutive SFP'!#REF!)/'Evolutive SFP'!#REF! -> #REF! | I16: =('Evolutive SFP'!#REF!+'Evolutive SFP'!#REF!)/'Evolutive SFP'!#REF! -> #REF! | J16: =('Evolutive SFP'!#REF!+'Evolutive SFP'!#REF!)/'Evolutive SFP'!#REF! -> #REF! | K16: =('Evolutive SFP'!#REF!+'Evolutive SFP'!#REF!)/'Evolutive SFP'!#REF! -> #REF! | ... AS16: =('Evolutive SFP'!#REF!+'Evolutive SFP'!#REF!)/'Evolutive SFP'!#REF! -> #REF! | AT16: =('Evolutive SFP'!BV7+'Evolutive SFP'!BV21)/'Evolutive SFP'!BV27 -> 0.36746879 | AU16: =('Evolutive SFP'!BW7+'Evolutive SFP'!BW21)/'Evolutive SFP'!BW27 -> 0.19814854 | AV16: =('Evolutive SFP'!BX7+'Evolutive SFP'!BX21)/'Evolutive SFP'!BX27 -> 0.19624893 | AW16: =('Evolutive SFP'!BY7+'Evolutive SFP'!BY21)/'Evolutive SFP'!BY27 -> 0.19776978 | AX16: =('Evolutive SFP'!BZ7+'Evolutive SFP'!BZ21)/'Evolutive SFP'!BZ27 -> 0.17666891 | AY16: =('Evolutive SFP'!CA7+'Evolutive SFP'!CA21)/'Evolutive SFP'!CA27 -> 0.18676669 | AZ16: =('Evolutive SFP'!CB7+'Evolutive SFP'!CB21)/'Evolutive SFP'!CB27 -> 0.15137981 | BA16: =('Evolutive SFP'!#REF!+'Evolutive SFP'!#REF!)/'Evolutive SFP'!#REF! -> #REF! | BB16: =('Evolutive SFP'!CC7+'Evolutive SFP'!CC21)/'Evolutive SFP'!CC27 -> 0.1659787 | BC16: =('Evolutive SFP'!CD7+'Evolutive SFP'!CD21)/'Evolutive SFP'!CD27 -> 0.12270392 | BD16: =('Evolutive SFP'!CE7+'Evolutive SFP'!CE21)/'Evolutive SFP'!CE27 -> 0.14730118 | BE16: =('Evolutive SFP'!CF7+'Evolutive SFP'!CF21)/'Evolutive SFP'!CF27 -> 0.16012459 | BF16: =('Evolutive SFP'!CG7+'Evolutive SFP'!CG21)/'Evolutive SFP'!CG27 -> 0.17069966 | BG16: =('Evolutive SFP'!CH7+'Evolutive SFP'!CH21)/'Evolutive SFP'!CH27 -> 0.17069966 | BH16: =('Evolutive SFP'!CI7+'Evolutive SFP'!CI21)/'Evolutive SFP'!CI27 -> 0.17644881 | BI16: =('Evolutive SFP'!CJ7+'Evolutive SFP'!CJ21)/'Evolutive SFP'!CJ27 -> 0.17779676 | ... CD16: =('Evolutive SFP'!DE7+'Evolutive SFP'!DE21)/'Evolutive SFP'!DE27 -> 0.11439211
B17: LB ratio | C17: Max 5% | D17: ='Evolutive SFP'!#REF!/'Evolutive SFP'!#REF! -> #REF! | E17: ='Evolutive SFP'!#REF!/'Evolutive SFP'!#REF! -> #REF! | F17: ='Evolutive SFP'!#REF!/'Evolutive SFP'!#REF! -> #REF! | G17: ='Evolutive SFP'!#REF!/'Evolutive SFP'!#REF! -> #REF! | H17: ='Evolutive SFP'!#REF!/'Evolutive SFP'!#REF! -> #REF! | I17: ='Evolutive SFP'!#REF!/'Evolutive SFP'!#REF! -> #REF! | J17: ='Evolutive SFP'!#REF!/'Evolutive SFP'!#REF! -> #REF! | K17: ='Evolutive SFP'!#REF!/'Evolutive SFP'!#REF! -> #REF! | ... AS17: ='Evolutive SFP'!#REF!/'Evolutive SFP'!#REF! -> #REF! | AT17: ='Evolutive SFP'!BV21/'Evolutive SFP'!BV27 -> 0.36746879 | AU17: ='Evolutive SFP'!BW21/'Evolutive SFP'!BW27 -> 0.16828542 | AV17: ='Evolutive SFP'!BX21/'Evolutive SFP'!BX27 -> 0.1701819 | AW17: ='Evolutive SFP'!BY21/'Evolutive SFP'!BY27 -> 0.17167981 | AX17: ='Evolutive SFP'!BZ21/'Evolutive SFP'!BZ27 -> 0.15068106 | AY17: ='Evolutive SFP'!CA21/'Evolutive SFP'!CA27 -> 0.15877034 | AZ17: ='Evolutive SFP'!CB21/'Evolutive SFP'!CB27 -> 0.12886102 | BA17: ='Evolutive SFP'!#REF!/'Evolutive SFP'!#REF! -> #REF! | BB17: ='Evolutive SFP'!CC21/'Evolutive SFP'!CC27 -> 0.1394814 | BC17: ='Evolutive SFP'!CD21/'Evolutive SFP'!CD27 -> 0.10283391 | BD17: ='Evolutive SFP'!CE21/'Evolutive SFP'!CE27 -> 0.11919271 | BE17: ='Evolutive SFP'!CF21/'Evolutive SFP'!CF27 -> 0.13096603 | BF17: ='Evolutive SFP'!CG21/'Evolutive SFP'!CG27 -> 0.13491086 | BG17: ='Evolutive SFP'!CH21/'Evolutive SFP'!CH27 -> 0.13565451 | BH17: ='Evolutive SFP'!CI21/'Evolutive SFP'!CI27 -> 0.13892188 | BI17: ='Evolutive SFP'!CJ21/'Evolutive SFP'!CJ27 -> 0.14075586 | ... CD17: ='Evolutive SFP'!DE21/'Evolutive SFP'!DE27 -> 0.10649411
B18: PI to Deposit ratio | C18: Max 5% | D18: ='Evolutive SFP'!#REF!/'Evolutive SFP'!#REF! -> #REF! | E18: ='Evolutive SFP'!#REF!/'Evolutive SFP'!#REF! -> #REF! | F18: ='Evolutive SFP'!#REF!/'Evolutive SFP'!#REF! -> #REF! | G18: ='Evolutive SFP'!#REF!/'Evolutive SFP'!#REF! -> #REF! | H18: ='Evolutive SFP'!#REF!/'Evolutive SFP'!#REF! -> #REF! | I18: ='Evolutive SFP'!#REF!/'Evolutive SFP'!#REF! -> #REF! | J18: ='Evolutive SFP'!#REF!/'Evolutive SFP'!#REF! -> #REF! | K18: ='Evolutive SFP'!#REF!/'Evolutive SFP'!#REF! -> #REF! | ... AS18: ='Evolutive SFP'!#REF!/'Evolutive SFP'!#REF! -> #REF! | AT18: ='Evolutive SFP'!BV13/'Evolutive SFP'!BV31 -> 0.062837742 | AU18: ='Evolutive SFP'!BW13/'Evolutive SFP'!BW31 -> 0 | AV18: ='Evolutive SFP'!BX13/'Evolutive SFP'!BX31 -> 0 | AW18: ='Evolutive SFP'!BY13/'Evolutive SFP'!BY31 -> 0 | AX18: ='Evolutive SFP'!BZ13/'Evolutive SFP'!BZ31 -> 0 | AY18: ='Evolutive SFP'!CA13/'Evolutive SFP'!CA31 -> 0 | AZ18: ='Evolutive SFP'!CB13/'Evolutive SFP'!CB31 -> 0 | BA18: ='Evolutive SFP'!#REF!/'Evolutive SFP'!#REF! -> #REF! | BB18: ='Evolutive SFP'!CC13/'Evolutive SFP'!CC31 -> 0 | BC18: ='Evolutive SFP'!CD13/'Evolutive SFP'!CD31 -> 0 | BD18: ='Evolutive SFP'!CE13/'Evolutive SFP'!CE31 -> 0 | BE18: ='Evolutive SFP'!CF13/'Evolutive SFP'!CF31 -> 0 | BF18: ='Evolutive SFP'!CG13/'Evolutive SFP'!CG31 -> 0 | BG18: ='Evolutive SFP'!CH13/'Evolutive SFP'!CH31 -> 0.068533295 | BH18: ='Evolutive SFP'!CI13/'Evolutive SFP'!CI31 -> 0 | BI18: ='Evolutive SFP'!CJ13/'Evolutive SFP'!CJ31 -> 0 | ... CD18: ='Evolutive SFP'!DE13/'Evolutive SFP'!DE31 -> 0.14501226
B19: PI to CC ratio | C19: Max 40% | D19: ='Evolutive SFP'!#REF!/(CAELS!D3*1000000) -> #REF! | E19: ='Evolutive SFP'!#REF!/(CAELS!E3*1000000) -> #REF! | F19: ='Evolutive SFP'!#REF!/(CAELS!F3*1000000) -> #REF! | G19: ='Evolutive SFP'!#REF!/(CAELS!G3*1000000) -> #REF! | H19: ='Evolutive SFP'!#REF!/(CAELS!H3*1000000) -> #REF! | I19: ='Evolutive SFP'!#REF!/(CAELS!I3*1000000) -> #REF! | J19: ='Evolutive SFP'!#REF!/(CAELS!J3*1000000) -> #REF! | K19: ='Evolutive SFP'!#REF!/(CAELS!K3*1000000) -> #REF! | ... AS19: ='Evolutive SFP'!#REF!/(CAELS!AS3*1000000) -> #REF! | AT19: ='Evolutive SFP'!BV13/(CAELS!AT3*1000000) -> 0.036216516 | AU19: ='Evolutive SFP'!BW13/(CAELS!AU3*1000000) -> 0 | AV19: ='Evolutive SFP'!BX13/(CAELS!AV3*1000000) -> 0 | AW19: ='Evolutive SFP'!BY13/(CAELS!AW3*1000000) -> 0 | AX19: ='Evolutive SFP'!BZ13/(CAELS!AX3*1000000) -> 0 | AY19: ='Evolutive SFP'!CA13/(CAELS!AY3*1000000) -> 0 | AZ19: ='Evolutive SFP'!CB13/(CAELS!AZ3*1000000) -> 0 | BA19: ='Evolutive SFP'!#REF!/(CAELS!BA3*1000000) -> #REF! | BB19: ='Evolutive SFP'!CC13/(CAELS!BB3*1000000) -> 0 | BC19: ='Evolutive SFP'!CD13/(CAELS!BC3*1000000) -> 0 | BD19: ='Evolutive SFP'!CE13/(CAELS!BD3*1000000) -> 0 | BE19: ='Evolutive SFP'!CF13/(CAELS!BE3*1000000) -> 0 | BF19: ='Evolutive SFP'!CG13/(CAELS!BF3*1000000) -> 0 | BG19: ='Evolutive SFP'!CH13/(CAELS!BG3*1000000) -> 0.075038969 | BH19: ='Evolutive SFP'!CI13/(CAELS!BH3*1000000) -> 0 | BI19: ='Evolutive SFP'!CJ13/(CAELS!BI3*1000000) -> 0 | ... CD19: ='Evolutive SFP'!DE13/(CAELS!CD3*1000000) -> 0.16555156
B20: Gross loans/TA | D20: ='Evolutive SFP'!#REF!/'Evolutive SFP'!#REF! -> #REF! | E20: ='Evolutive SFP'!#REF!/'Evolutive SFP'!#REF! -> #REF! | F20: ='Evolutive SFP'!#REF!/'Evolutive SFP'!#REF! -> #REF! | G20: ='Evolutive SFP'!#REF!/'Evolutive SFP'!#REF! -> #REF! | H20: ='Evolutive SFP'!#REF!/'Evolutive SFP'!#REF! -> #REF! | I20: ='Evolutive SFP'!#REF!/'Evolutive SFP'!#REF! -> #REF! | J20: ='Evolutive SFP'!#REF!/'Evolutive SFP'!#REF! -> #REF! | K20: ='Evolutive SFP'!#REF!/'Evolutive SFP'!#REF! -> #REF! | ... AS20: ='Evolutive SFP'!#REF!/'Evolutive SFP'!#REF! -> #REF! | AT20: ='Evolutive SFP'!BV15/'Evolutive SFP'!BV27 -> 0.61566296 | AU20: ='Evolutive SFP'!BW15/'Evolutive SFP'!BW27 -> 0.64216083 | AV20: ='Evolutive SFP'!BX15/'Evolutive SFP'!BX27 -> 0.65412453 | AW20: ='Evolutive SFP'!BY15/'Evolutive SFP'!BY27 -> 0.65116604 | AX20: ='Evolutive SFP'!BZ15/'Evolutive SFP'!BZ27 -> 0.47860175 | AY20: ='Evolutive SFP'!CA15/'Evolutive SFP'!CA27 -> 0.53776843 | AZ20: ='Evolutive SFP'!CB15/'Evolutive SFP'!CB27 -> 0.34197742 | BA20: ='Evolutive SFP'!#REF!/'Evolutive SFP'!#REF! -> #REF! | BB20: ='Evolutive SFP'!CC15/'Evolutive SFP'!CC27 -> 0.49384508 | BC20: ='Evolutive SFP'!CD15/'Evolutive SFP'!CD27 -> 0.40669387 | BD20: ='Evolutive SFP'!CE15/'Evolutive SFP'!CE27 -> 0.52779458 | BE20: ='Evolutive SFP'!CF15/'Evolutive SFP'!CF27 -> 0.61887174 | BF20: ='Evolutive SFP'!CG15/'Evolutive SFP'!CG27 -> 0.67443645 | BG20: ='Evolutive SFP'!CH15/'Evolutive SFP'!CH27 -> 0.67443645 | BH20: ='Evolutive SFP'!CI15/'Evolutive SFP'!CI27 -> 0.72157253 | BI20: ='Evolutive SFP'!CJ15/'Evolutive SFP'!CJ27 -> 0.72518066 | ... CD20: ='Evolutive SFP'!DE15/'Evolutive SFP'!DE27 -> 0.57297078
A21: FUNDING MIX | B21: Total Deposits/Total Assets | D21: ='Evolutive SFP'!#REF!/'Evolutive SFP'!#REF! -> #REF! | E21: ='Evolutive SFP'!#REF!/'Evolutive SFP'!#REF! -> #REF! | F21: ='Evolutive SFP'!#REF!/'Evolutive SFP'!#REF! -> #REF! | G21: ='Evolutive SFP'!#REF!/'Evolutive SFP'!#REF! -> #REF! | H21: ='Evolutive SFP'!#REF!/'Evolutive SFP'!#REF! -> #REF! | I21: ='Evolutive SFP'!#REF!/'Evolutive SFP'!#REF! -> #REF! | J21: ='Evolutive SFP'!#REF!/'Evolutive SFP'!#REF! -> #REF! | K21: ='Evolutive SFP'!#REF!/'Evolutive SFP'!#REF! -> #REF! | ... AS21: ='Evolutive SFP'!#REF!/'Evolutive SFP'!#REF! -> #REF! | AT21: ='Evolutive SFP'!BV31/'Evolutive SFP'!BV27 -> 0.4468346 | AU21: ='Evolutive SFP'!BW31/'Evolutive SFP'!BW27 -> 0.43767839 | AV21: ='Evolutive SFP'!BX31/'Evolutive SFP'!BX27 -> 0.44704647 | AW21: ='Evolutive SFP'!BY31/'Evolutive SFP'!BY27 -> 0.44557775 | AX21: ='Evolutive SFP'!BZ31/'Evolutive SFP'!BZ27 -> 0.49809068 | AY21: ='Evolutive SFP'!CA31/'Evolutive SFP'!CA27 -> 0.48611551 | AZ21: ='Evolutive SFP'!CB31/'Evolutive SFP'!CB27 -> 0.55415292 | BA21: ='Evolutive SFP'!#REF!/'Evolutive SFP'!#REF! -> #REF! | BB21: ='Evolutive SFP'!CC31/'Evolutive SFP'!CC27 -> 0.51273488 | BC21: ='Evolutive SFP'!CD31/'Evolutive SFP'!CD27 -> 0.58429838 | BD21: ='Evolutive SFP'!CE31/'Evolutive SFP'!CE27 -> 0.56443274 | BE21: ='Evolutive SFP'!CF31/'Evolutive SFP'!CF27 -> 0.53056899 | BF21: ='Evolutive SFP'!CG31/'Evolutive SFP'!CG27 -> 0.50799223 | BG21: ='Evolutive SFP'!CH31/'Evolutive SFP'!CH27 -> 0.50799223 | BH21: ='Evolutive SFP'!CI31/'Evolutive SFP'!CI27 -> 0.49671692 | BI21: ='Evolutive SFP'!CJ31/'Evolutive SFP'!CJ27 -> 0.49509069 | ... CD21: ='Evolutive SFP'!DE31/'Evolutive SFP'!DE27 -> 0.50003983
B22: BOSA Deposits/Total Assets | D22: ='Evolutive SFP'!#REF!/'Evolutive SFP'!#REF! -> #REF! | E22: ='Evolutive SFP'!#REF!/'Evolutive SFP'!#REF! -> #REF! | F22: ='Evolutive SFP'!#REF!/'Evolutive SFP'!#REF! -> #REF! | G22: ='Evolutive SFP'!#REF!/'Evolutive SFP'!#REF! -> #REF! | H22: ='Evolutive SFP'!#REF!/'Evolutive SFP'!#REF! -> #REF! | I22: ='Evolutive SFP'!#REF!/'Evolutive SFP'!#REF! -> #REF! | J22: ='Evolutive SFP'!#REF!/'Evolutive SFP'!#REF! -> #REF! | K22: ='Evolutive SFP'!#REF!/'Evolutive SFP'!#REF! -> #REF! | ... AS22: ='Evolutive SFP'!#REF!/'Evolutive SFP'!#REF! -> #REF! | AT22: ='Evolutive SFP'!BV30/'Evolutive SFP'!BV27 -> 0 | AU22: ='Evolutive SFP'!BW30/'Evolutive SFP'!BW27 -> 0.26686849 | AV22: ='Evolutive SFP'!BX30/'Evolutive SFP'!BX27 -> 0.26936125 | AW22: ='Evolutive SFP'!BY30/'Evolutive SFP'!BY27 -> 0.27055666 | AX22: ='Evolutive SFP'!BZ30/'Evolutive SFP'!BZ27 -> 0.24007582 | AY22: ='Evolutive SFP'!CA30/'Evolutive SFP'!CA27 -> 0.21341301 | AZ22: ='Evolutive SFP'!CB30/'Evolutive SFP'!CB27 -> 0.21949496 | BA22: ='Evolutive SFP'!#REF!/'Evolutive SFP'!#REF! -> #REF! | BB22: ='Evolutive SFP'!CC30/'Evolutive SFP'!CC27 -> 0.24705511 | BC22: ='Evolutive SFP'!CD30/'Evolutive SFP'!CD27 -> 0.18632872 | BD22: ='Evolutive SFP'!CE30/'Evolutive SFP'!CE27 -> 0.22648282 | BE22: ='Evolutive SFP'!CF30/'Evolutive SFP'!CF27 -> 0.25379438 | BF22: ='Evolutive SFP'!CG30/'Evolutive SFP'!CG27 -> 0.26902602 | BG22: ='Evolutive SFP'!CH30/'Evolutive SFP'!CH27 -> 0.26902602 | BH22: ='Evolutive SFP'!CI30/'Evolutive SFP'!CI27 -> 0.27890949 | BI22: ='Evolutive SFP'!CJ30/'Evolutive SFP'!CJ27 -> 0.28592353 | ... CD22: ='Evolutive SFP'!DE30/'Evolutive SFP'!DE27 -> 0.26963418
B23: FOSA Deposits/Total Assets | D23: =('Evolutive SFP'!#REF!+'Evolutive SFP'!#REF!)/'Evolutive SFP'!#REF! -> #REF! | E23: =('Evolutive SFP'!#REF!+'Evolutive SFP'!#REF!)/'Evolutive SFP'!#REF! -> #REF! | F23: =('Evolutive SFP'!#REF!+'Evolutive SFP'!#REF!)/'Evolutive SFP'!#REF! -> #REF! | G23: =('Evolutive SFP'!#REF!+'Evolutive SFP'!#REF!)/'Evolutive SFP'!#REF! -> #REF! | H23: =('Evolutive SFP'!#REF!+'Evolutive SFP'!#REF!)/'Evolutive SFP'!#REF! -> #REF! | I23: =('Evolutive SFP'!#REF!+'Evolutive SFP'!#REF!)/'Evolutive SFP'!#REF! -> #REF! | J23: =('Evolutive SFP'!#REF!+'Evolutive SFP'!#REF!)/'Evolutive SFP'!#REF! -> #REF! | K23: =('Evolutive SFP'!#REF!+'Evolutive SFP'!#REF!)/'Evolutive SFP'!#REF! -> #REF! | ... AS23: =('Evolutive SFP'!#REF!+'Evolutive SFP'!#REF!)/'Evolutive SFP'!#REF! -> #REF! | AT23: =('Evolutive SFP'!BV28+'Evolutive SFP'!BV29)/'Evolutive SFP'!BV27 -> 0.4468346 | AU23: =('Evolutive SFP'!BW28+'Evolutive SFP'!BW29)/'Evolutive SFP'!BW27 -> 0.1708099 | AV23: =('Evolutive SFP'!BX28+'Evolutive SFP'!BX29)/'Evolutive SFP'!BX27 -> 0.17768522 | AW23: =('Evolutive SFP'!BY28+'Evolutive SFP'!BY29)/'Evolutive SFP'!BY27 -> 0.17502109 | AX23: =('Evolutive SFP'!BZ28+'Evolutive SFP'!BZ29)/'Evolutive SFP'!BZ27 -> 0.25801487 | AY23: =('Evolutive SFP'!CA28+'Evolutive SFP'!CA29)/'Evolutive SFP'!CA27 -> 0.2727025 | AZ23: =('Evolutive SFP'!CB28+'Evolutive SFP'!CB29)/'Evolutive SFP'!CB27 -> 0.33465796 | BA23: =('Evolutive SFP'!#REF!+'Evolutive SFP'!#REF!)/'Evolutive SFP'!#REF! -> #REF! | BB23: =('Evolutive SFP'!CC28+'Evolutive SFP'!CC29)/'Evolutive SFP'!CC27 -> 0.26567978 | BC23: =('Evolutive SFP'!CD28+'Evolutive SFP'!CD29)/'Evolutive SFP'!CD27 -> 0.39796966 | BD23: =('Evolutive SFP'!CE28+'Evolutive SFP'!CE29)/'Evolutive SFP'!CE27 -> 0.33794992 | BE23: =('Evolutive SFP'!CF28+'Evolutive SFP'!CF29)/'Evolutive SFP'!CF27 -> 0.27677461 | BF23: =('Evolutive SFP'!CG28+'Evolutive SFP'!CG29)/'Evolutive SFP'!CG27 -> 0.23896621 | BG23: =('Evolutive SFP'!CH28+'Evolutive SFP'!CH29)/'Evolutive SFP'!CH27 -> 0.23896621 | BH23: =('Evolutive SFP'!CI28+'Evolutive SFP'!CI29)/'Evolutive SFP'!CI27 -> 0.21780743 | BI23: =('Evolutive SFP'!CJ28+'Evolutive SFP'!CJ29)/'Evolutive SFP'!CJ27 -> 0.20916716 | ... CD23: =('Evolutive SFP'!DE28+'Evolutive SFP'!DE29)/'Evolutive SFP'!DE27 -> 0.23040565
A24: GROWTH RATIOS | B24: Total Assets | E24: =(Financials!D4-Financials!C4)/Financials!C4 -> #REF! | H24: =(Financials!G4-Financials!D4)/Financials!D4 -> #REF! | I24: =(Financials!H4-Financials!G4)/Financials!G4 -> #REF! | J24: =(Financials!I4-Financials!H4)/Financials!H4 -> #REF! | K24: =(Financials!J4-Financials!I4)/Financials!I4 -> #REF! | L24: =(Financials!K4-Financials!J4)/Financials!J4 -> #REF! | M24: =(Financials!L4-Financials!K4)/Financials!K4 -> #REF! | N24: =(Financials!M4-Financials!L4)/Financials!L4 -> #REF! | O24: =(Financials!N4-Financials!M4)/Financials!M4 -> #REF! | P24: =(Financials!O4-Financials!N4)/Financials!N4 -> #REF! | ... CD24: =(Financials!CC4-Financials!CB4)/Financials!CB4 -> -0.022554364
B25: Total Deposits | D25: =Financials!D5/Financials!C5-1 -> #REF! | E25: =Financials!G5/Financials!D5-1 -> #REF! | F25: =Financials!H5/Financials!G5-1 -> #REF! | G25: =Financials!H5/Financials!G5-1 -> #REF! | H25: =Financials!H5/Financials!G5-1 -> #REF! | I25: =Financials!I5/Financials!H5-1 -> #REF! | J25: =Financials!J5/Financials!I5-1 -> #REF! | K25: =Financials!K5/Financials!J5-1 -> #REF! | L25: =Financials!L5/Financials!K5-1 -> #REF! | M25: =Financials!M5/Financials!L5-1 -> #REF! | N25: =Financials!N5/Financials!M5-1 -> #REF! | O25: =Financials!O5/Financials!N5-1 -> #REF! | ... R25: =Financials!R5/Financials!Q5-1 -> #REF! | S25: =Financials!#REF!/Financials!R5-1 -> #REF! | T25: =Financials!#REF!/Financials!S5-1 -> #REF! | U25: =Financials!#REF!/Financials!T5-1 -> #REF! | V25: =Financials!#REF!/Financials!U5-1 -> #REF! | W25: =Financials!#REF!/Financials!V5-1 -> #REF! | X25: =Financials!#REF!/Financials!W5-1 -> #REF! | Y25: =Financials!#REF!/Financials!X5-1 -> #REF! | Z25: =Financials!#REF!/Financials!Y5-1 -> #REF! | ... CD25: =Financials!#REF!/Financials!CC5-1 -> #REF!
B26: BOSA Deposits | D26: =Financials!D6/Financials!C6-1 -> #REF! | E26: =Financials!G6/Financials!D6-1 -> #REF! | F26: =Financials!H6/Financials!G6-1 -> #REF! | G26: =Financials!H6/Financials!G6-1 -> #REF! | H26: =Financials!H6/Financials!G6-1 -> #REF! | I26: =Financials!I6/Financials!H6-1 -> #REF! | J26: =Financials!J6/Financials!I6-1 -> #REF! | K26: =Financials!K6/Financials!J6-1 -> #REF! | L26: =Financials!L6/Financials!K6-1 -> #REF! | M26: =Financials!M6/Financials!L6-1 -> #REF! | N26: =Financials!N6/Financials!M6-1 -> #REF! | O26: =Financials!O6/Financials!N6-1 -> #REF! | ... R26: =Financials!R6/Financials!Q6-1 -> #REF! | S26: =Financials!#REF!/Financials!R6-1 -> #REF! | T26: =Financials!#REF!/Financials!S6-1 -> #REF! | U26: =Financials!#REF!/Financials!T6-1 -> #REF! | V26: =Financials!#REF!/Financials!U6-1 -> #REF! | W26: =Financials!#REF!/Financials!V6-1 -> #REF! | X26: =Financials!#REF!/Financials!W6-1 -> #REF! | Y26: =Financials!#REF!/Financials!X6-1 -> #REF! | Z26: =Financials!#REF!/Financials!Y6-1 -> #REF! | ... CD26: =Financials!#REF!/Financials!CC6-1 -> #REF!
B27: FOSA Deposits | D27: =Financials!D7/Financials!C7-1 -> #REF! | E27: =Financials!G7/Financials!D7-1 -> #REF! | F27: =Financials!H7/Financials!G7-1 -> #REF! | G27: =Financials!H7/Financials!G7-1 -> #REF! | H27: =Financials!H7/Financials!G7-1 -> #REF! | I27: =Financials!I7/Financials!H7-1 -> #REF! | J27: =Financials!J7/Financials!I7-1 -> #REF! | K27: =Financials!K7/Financials!J7-1 -> #REF! | L27: =Financials!L7/Financials!K7-1 -> #REF! | M27: =Financials!M7/Financials!L7-1 -> #REF! | N27: =Financials!N7/Financials!M7-1 -> #REF! | O27: =Financials!O7/Financials!N7-1 -> #REF! | ... R27: =Financials!R7/Financials!Q7-1 -> #REF! | S27: =Financials!#REF!/Financials!R7-1 -> #REF! | T27: =Financials!#REF!/Financials!S7-1 -> #REF! | U27: =Financials!#REF!/Financials!T7-1 -> #REF! | V27: =Financials!#REF!/Financials!U7-1 -> #REF! | W27: =Financials!#REF!/Financials!V7-1 -> #REF! | X27: =Financials!#REF!/Financials!W7-1 -> #REF! | Y27: =Financials!#REF!/Financials!X7-1 -> #REF! | Z27: =Financials!#REF!/Financials!Y7-1 -> #REF! | ... CD27: =Financials!#REF!/Financials!CC7-1 -> #REF!
B28: Total Loans & advances | D28: =Financials!D31/Financials!C31-1 -> #REF! | E28: =Financials!G31/Financials!D31-1 -> #REF! | F28: =Financials!H31/Financials!G31-1 -> #REF! | G28: =Financials!H31/Financials!G31-1 -> #REF! | H28: =Financials!H31/Financials!G31-1 -> #REF! | I28: =Financials!I31/Financials!H31-1 -> #REF! | J28: =Financials!J31/Financials!I31-1 -> #REF! | K28: =Financials!K31/Financials!J31-1 -> #REF! | L28: =Financials!L31/Financials!K31-1 -> #REF! | M28: =Financials!M31/Financials!L31-1 -> #REF! | N28: =Financials!N31/Financials!M31-1 -> #REF! | O28: =Financials!O31/Financials!N31-1 -> #REF! | ... R28: =Financials!R31/Financials!Q31-1 -> #REF! | S28: =Financials!#REF!/Financials!R31-1 -> #REF! | T28: =Financials!#REF!/Financials!S31-1 -> #REF! | U28: =Financials!#REF!/Financials!T31-1 -> #REF! | V28: =Financials!#REF!/Financials!U31-1 -> #REF! | W28: =Financials!#REF!/Financials!V31-1 -> #REF! | X28: =Financials!#REF!/Financials!W31-1 -> #REF! | Y28: =Financials!#REF!/Financials!X31-1 -> #REF! | Z28: =Financials!#REF!/Financials!Y31-1 -> #REF! | ... CD28: =Financials!#REF!/Financials!CC31-1 -> #REF!
B29: Core capital | D29: =Financials!D11/Financials!C11-1 -> #REF! | E29: =Financials!G11/Financials!D11-1 -> #REF! | F29: =Financials!H11/Financials!G11-1 -> #REF! | G29: =Financials!H11/Financials!G11-1 -> #REF! | H29: =Financials!H11/Financials!G11-1 -> #REF! | I29: =Financials!I11/Financials!H11-1 -> #REF! | J29: =Financials!J11/Financials!I11-1 -> #REF! | K29: =Financials!K11/Financials!J11-1 -> #REF! | L29: =Financials!L11/Financials!K11-1 -> #REF! | M29: =Financials!M11/Financials!L11-1 -> #REF! | N29: =Financials!N11/Financials!M11-1 -> #REF! | O29: =Financials!O11/Financials!N11-1 -> #REF! | ... R29: =Financials!R11/Financials!Q11-1 -> #REF! | S29: =Financials!#REF!/Financials!R11-1 -> #REF! | T29: =Financials!#REF!/Financials!S11-1 -> #REF! | U29: =Financials!#REF!/Financials!T11-1 -> #REF! | V29: =Financials!#REF!/Financials!U11-1 -> #REF! | W29: =Financials!#REF!/Financials!V11-1 -> #REF! | X29: =Financials!#REF!/Financials!W11-1 -> #REF! | Y29: =Financials!#REF!/Financials!X11-1 -> #REF! | Z29: =Financials!#REF!/Financials!Y11-1 -> #REF! | ... CD29: =Financials!#REF!/Financials!CC11-1 -> #REF!
B30: Turnover | D30: =Financials!D37/Financials!C37-1 -> #REF! | E30: =Financials!G37/Financials!D37-1 -> #REF! | F30: =Financials!H37/Financials!G37-1 -> #REF! | G30: =Financials!H37/Financials!G37-1 -> #REF! | H30: =Financials!H37/Financials!G37-1 -> #REF! | I30: =Financials!I37/Financials!H37-1 -> #REF! | J30: =Financials!J37/Financials!I37-1 -> #REF! | K30: =Financials!K37/Financials!J37-1 -> #REF! | L30: =Financials!L37/Financials!K37-1 -> #REF! | M30: =Financials!M37/Financials!L37-1 -> #REF! | N30: =Financials!N37/Financials!M37-1 -> #REF! | O30: =Financials!O37/Financials!N37-1 -> #REF! | ... R30: =Financials!R37/Financials!Q37-1 -> #REF! | S30: =Financials!#REF!/Financials!R37-1 -> #REF! | T30: =Financials!#REF!/Financials!S37-1 -> #REF! | U30: =Financials!#REF!/Financials!T37-1 -> #REF! | V30: =Financials!#REF!/Financials!U37-1 -> #REF! | W30: =Financials!#REF!/Financials!V37-1 -> #REF! | X30: =Financials!#REF!/Financials!W37-1 -> #REF! | Y30: =Financials!#REF!/Financials!X37-1 -> #REF! | Z30: =Financials!#REF!/Financials!Y37-1 -> #REF! | ... CD30: =Financials!#REF!/Financials!CC37-1 -> #REF!
B31: Membership
B32: Expenses | D32: ='Evolutitve SCI'!#REF!/'Evolutitve SCI'!#REF!-1 -> #REF! | E32: ='Evolutitve SCI'!#REF!/'Evolutitve SCI'!#REF!-1 -> #REF! | F32: ='Evolutitve SCI'!#REF!/'Evolutitve SCI'!#REF!-1 -> #REF! | G32: ='Evolutitve SCI'!#REF!/'Evolutitve SCI'!#REF!-1 -> #REF! | H32: ='Evolutitve SCI'!#REF!/'Evolutitve SCI'!#REF!-1 -> #REF! | I32: ='Evolutitve SCI'!#REF!/'Evolutitve SCI'!#REF!-1 -> #REF! | J32: ='Evolutitve SCI'!#REF!/'Evolutitve SCI'!#REF!-1 -> #REF! | K32: ='Evolutitve SCI'!#REF!/'Evolutitve SCI'!#REF!-1 -> #REF! | ... AS32: ='Evolutitve SCI'!#REF!/'Evolutitve SCI'!#REF!-1 -> #REF! | AT32: ='Evolutitve SCI'!#REF!/'Evolutitve SCI'!BV39-1 -> #REF! | AU32: ='Evolutitve SCI'!#REF!/'Evolutitve SCI'!BW39-1 -> #REF! | AV32: ='Evolutitve SCI'!#REF!/'Evolutitve SCI'!BX39-1 -> #REF! | AW32: ='Evolutitve SCI'!#REF!/'Evolutitve SCI'!BY39-1 -> #REF! | AX32: ='Evolutitve SCI'!#REF!/'Evolutitve SCI'!BZ39-1 -> #REF! | AY32: ='Evolutitve SCI'!#REF!/'Evolutitve SCI'!CA39-1 -> #REF! | AZ32: ='Evolutitve SCI'!#REF!/'Evolutitve SCI'!CB39-1 -> #REF! | BA32: ='Evolutitve SCI'!#REF!/'Evolutitve SCI'!#REF!-1 -> #REF! | BB32: ='Evolutitve SCI'!#REF!/'Evolutitve SCI'!CC39-1 -> #REF! | BC32: ='Evolutitve SCI'!#REF!/'Evolutitve SCI'!CD39-1 -> #REF! | BD32: ='Evolutitve SCI'!#REF!/'Evolutitve SCI'!CE39-1 -> #REF! | BE32: ='Evolutitve SCI'!#REF!/'Evolutitve SCI'!CF39-1 -> #REF! | BF32: ='Evolutitve SCI'!#REF!/'Evolutitve SCI'!CG39-1 -> #REF! | BG32: ='Evolutitve SCI'!#REF!/'Evolutitve SCI'!CH39-1 -> #REF! | BH32: ='Evolutitve SCI'!#REF!/'Evolutitve SCI'!CI39-1 -> #REF! | BI32: ='Evolutitve SCI'!#REF!/'Evolutitve SCI'!CJ39-1 -> #REF! | ... CD32: ='Evolutitve SCI'!#REF!/'Evolutitve SCI'!DE39-1 -> #REF!
A33: Efficiency Ratios | B33: FinCost-Deposits/Avg Deposits | E33: =Financials!D44/('Evolutive SFP'!#REF!+'Evolutive SFP'!#REF!)/2 -> #REF! | H33: =Financials!G44/('Evolutive SFP'!#REF!+'Evolutive SFP'!#REF!)/2 -> #REF! | I33: =Financials!H44/('Evolutive SFP'!#REF!+'Evolutive SFP'!#REF!)/2 -> #REF! | J33: =Financials!I44/('Evolutive SFP'!#REF!+'Evolutive SFP'!#REF!)/2 -> #REF! | K33: =Financials!J44/('Evolutive SFP'!#REF!+'Evolutive SFP'!#REF!)/2 -> #REF! | L33: =Financials!K44/('Evolutive SFP'!#REF!+'Evolutive SFP'!#REF!)/2 -> #REF! | M33: =Financials!L44/('Evolutive SFP'!#REF!+'Evolutive SFP'!#REF!)/2 -> #REF! | N33: =Financials!M44/('Evolutive SFP'!#REF!+'Evolutive SFP'!#REF!)/2 -> #REF! | O33: =Financials!N44/('Evolutive SFP'!#REF!+'Evolutive SFP'!#REF!)/2 -> #REF! | ... AS33: =Financials!AR44/('Evolutive SFP'!#REF!+'Evolutive SFP'!#REF!)/2 -> #REF! | AT33: =Financials!AS44/('Evolutive SFP'!#REF!+'Evolutive SFP'!BV30)/2 -> #REF! | AU33: =Financials!AT44/('Evolutive SFP'!BV30+'Evolutive SFP'!BW30)/2 -> 0 | AV33: =Financials!AU44/('Evolutive SFP'!BW30+'Evolutive SFP'!BX30)/2 -> 0 | AW33: =Financials!AV44/('Evolutive SFP'!BX30+'Evolutive SFP'!BY30)/2 -> 0 | AX33: =Financials!AW44/('Evolutive SFP'!BY30+'Evolutive SFP'!BZ30)/2 -> 0 | AY33: =Financials!AX44/('Evolutive SFP'!BZ30+'Evolutive SFP'!CA30)/2 -> 0 | AZ33: =Financials!AY44/('Evolutive SFP'!CA30+'Evolutive SFP'!CB30)/2 -> 0.00018198177 | BA33: =Financials!AZ44/('Evolutive SFP'!CB30+'Evolutive SFP'!#REF!)/2 -> #REF! | BB33: =Financials!BA44/('Evolutive SFP'!#REF!+'Evolutive SFP'!CC30)/2 -> #REF! | BC33: =Financials!BB44/('Evolutive SFP'!CC30+'Evolutive SFP'!CD30)/2 -> 0.00016142129 | BD33: =Financials!BC44/('Evolutive SFP'!CD30+'Evolutive SFP'!CE30)/2 -> 0.0002285414 | BE33: =Financials!BD44/('Evolutive SFP'!CE30+'Evolutive SFP'!CF30)/2 -> 0.00027922826 | BF33: =Financials!BE44/('Evolutive SFP'!CF30+'Evolutive SFP'!CG30)/2 -> 0.013417344 | BG33: =Financials!BF44/('Evolutive SFP'!CG30+'Evolutive SFP'!CH30)/2 -> 0.013692303 | BH33: =Financials!BG44/('Evolutive SFP'!CH30+'Evolutive SFP'!CI30)/2 -> 0 | BI33: =Financials!BH44/('Evolutive SFP'!CI30+'Evolutive SFP'!CJ30)/2 -> 0 | BJ33: =Financials!BI44/('Evolutive SFP'!CJ30+'Evolutive SFP'!CK30)/2 -> 0 | ... CD33: =Financials!CC44/('Evolutive SFP'!DD30+'Evolutive SFP'!DE30)/2 -> 0
B34: FinCost-Shares/Avg Share capital | E34: =Financials!D45/('Evolutive SFP'!#REF!+'Evolutive SFP'!#REF!)/2 -> #REF! | H34: =Financials!G45/('Evolutive SFP'!#REF!+'Evolutive SFP'!#REF!)/2 -> #REF! | I34: =Financials!H45/('Evolutive SFP'!#REF!+'Evolutive SFP'!#REF!)/2 -> #REF! | J34: =Financials!I45/('Evolutive SFP'!#REF!+'Evolutive SFP'!#REF!)/2 -> #REF! | K34: =Financials!J45/('Evolutive SFP'!#REF!+'Evolutive SFP'!#REF!)/2 -> #REF! | L34: =Financials!K45/('Evolutive SFP'!#REF!+'Evolutive SFP'!#REF!)/2 -> #REF! | M34: =Financials!L45/('Evolutive SFP'!#REF!+'Evolutive SFP'!#REF!)/2 -> #REF! | N34: =Financials!M45/('Evolutive SFP'!#REF!+'Evolutive SFP'!#REF!)/2 -> #REF! | O34: =Financials!N45/('Evolutive SFP'!#REF!+'Evolutive SFP'!#REF!)/2 -> #REF! | ... AS34: =Financials!AR45/('Evolutive SFP'!#REF!+'Evolutive SFP'!#REF!)/2 -> #REF! | AT34: =Financials!AS45/('Evolutive SFP'!#REF!+'Evolutive SFP'!BV39)/2 -> #REF! | AU34: =Financials!AT45/('Evolutive SFP'!BV39+'Evolutive SFP'!BW39)/2 -> 0 | AV34: =Financials!AU45/('Evolutive SFP'!BW39+'Evolutive SFP'!BX39)/2 -> 0 | AW34: =Financials!AV45/('Evolutive SFP'!BX39+'Evolutive SFP'!BY39)/2 -> 0 | AX34: =Financials!AW45/('Evolutive SFP'!BY39+'Evolutive SFP'!BZ39)/2 -> 0 | AY34: =Financials!AX45/('Evolutive SFP'!BZ39+'Evolutive SFP'!CA39)/2 -> 0 | AZ34: =Financials!AY45/('Evolutive SFP'!CA39+'Evolutive SFP'!CB39)/2 -> 0 | BA34: =Financials!AZ45/('Evolutive SFP'!CB39+'Evolutive SFP'!#REF!)/2 -> #REF! | BB34: =Financials!BA45/('Evolutive SFP'!#REF!+'Evolutive SFP'!CC39)/2 -> #REF! | BC34: =Financials!BB45/('Evolutive SFP'!CC39+'Evolutive SFP'!CD39)/2 -> 0 | BD34: =Financials!BC45/('Evolutive SFP'!CD39+'Evolutive SFP'!CE39)/2 -> 0 | BE34: =Financials!BD45/('Evolutive SFP'!CE39+'Evolutive SFP'!CF39)/2 -> 0 | BF34: =Financials!BE45/('Evolutive SFP'!CF39+'Evolutive SFP'!CG39)/2 -> 0 | BG34: =Financials!BF45/('Evolutive SFP'!CG39+'Evolutive SFP'!CH39)/2 -> 0 | BH34: =Financials!BG45/('Evolutive SFP'!CH39+'Evolutive SFP'!CI39)/2 -> 0 | BI34: =Financials!BH45/('Evolutive SFP'!CI39+'Evolutive SFP'!CJ39)/2 -> 0 | BJ34: =Financials!BI45/('Evolutive SFP'!CJ39+'Evolutive SFP'!CK39)/2 -> 0 | ... CD34: =Financials!CC45/('Evolutive SFP'!DD39+'Evolutive SFP'!DE39)/2 -> 0
B35: FinCost-Ext Loans/Avg Ext Loans | E35: =Financials!D46/(Financials!C31+Financials!D31)/2 -> #REF! | H35: =Financials!G46/(Financials!D31+Financials!G31)/2 -> #REF! | I35: =Financials!H46/(Financials!G31+Financials!H31)/2 -> #REF! | J35: =Financials!I46/(Financials!H31+Financials!I31)/2 -> #REF! | K35: =Financials!J46/(Financials!I31+Financials!J31)/2 -> #REF! | L35: =Financials!K46/(Financials!J31+Financials!K31)/2 -> #REF! | M35: =Financials!L46/(Financials!K31+Financials!L31)/2 -> #REF! | N35: =Financials!M46/(Financials!L31+Financials!M31)/2 -> #REF! | O35: =Financials!N46/(Financials!M31+Financials!N31)/2 -> #REF! | P35: =Financials!O46/(Financials!N31+Financials!O31)/2 -> #REF! | ... CD35: =Financials!CC46/(Financials!CB31+Financials!CC31)/2 -> 0
B36: OpEx/Average Total Assets | E36: =Financials!D47/(Financials!C4+Financials!D4)/2 -> #REF! | H36: =Financials!G47/(Financials!D4+Financials!G4)/2 -> #REF! | I36: =Financials!H47/(Financials!G4+Financials!H4)/2 -> #REF! | J36: =Financials!I47/(Financials!H4+Financials!I4)/2 -> #REF! | K36: =Financials!J47/(Financials!I4+Financials!J4)/2 -> #REF! | L36: =Financials!K47/(Financials!J4+Financials!K4)/2 -> #REF! | M36: =Financials!L47/(Financials!K4+Financials!L4)/2 -> #REF! | N36: =Financials!M47/(Financials!L4+Financials!M4)/2 -> #REF! | O36: =Financials!N47/(Financials!M4+Financials!N4)/2 -> #REF! | P36: =Financials!O47/(Financials!N4+Financials!O4)/2 -> #REF! | ... CD36: =Financials!CC47/(Financials!CB4+Financials!CC4)/2 -> 0.015172343
B37: Opex/Turnover | E37: =Financials!D47/Financials!D37 -> #REF! | H37: =Financials!G47/Financials!G37 -> #REF! | I37: =Financials!H47/Financials!H37 -> #REF! | J37: =Financials!I47/Financials!I37 -> #REF! | K37: =Financials!J47/Financials!J37 -> #REF! | L37: =Financials!K47/Financials!K37 -> #REF! | M37: =Financials!L47/Financials!L37 -> #REF! | N37: =Financials!M47/Financials!M37 -> #REF! | O37: =Financials!N47/Financials!N37 -> #REF! | ... CD37: =Financials!CC47/Financials!CC37 -> 0.57219899
B38: Avge yield on Net loans | E38: =Financials!D38/('Evolutive SFP'!#REF!+'Evolutive SFP'!#REF!)/2 -> #REF! | H38: =Financials!G38/('Evolutive SFP'!#REF!+'Evolutive SFP'!#REF!)/2 -> #REF! | I38: =Financials!H38/('Evolutive SFP'!#REF!+'Evolutive SFP'!#REF!)/2 -> #REF! | J38: =Financials!I38/('Evolutive SFP'!#REF!+'Evolutive SFP'!#REF!)/2 -> #REF! | K38: =Financials!J38/('Evolutive SFP'!#REF!+'Evolutive SFP'!#REF!)/2 -> #REF! | L38: =Financials!K38/('Evolutive SFP'!#REF!+'Evolutive SFP'!#REF!)/2 -> #REF! | M38: =Financials!L38/('Evolutive SFP'!#REF!+'Evolutive SFP'!#REF!)/2 -> #REF! | N38: =Financials!M38/('Evolutive SFP'!#REF!+'Evolutive SFP'!#REF!)/2 -> #REF! | O38: =Financials!N38/('Evolutive SFP'!#REF!+'Evolutive SFP'!#REF!)/2 -> #REF! | ... AS38: =Financials!AR38/('Evolutive SFP'!#REF!+'Evolutive SFP'!#REF!)/2 -> #REF! | AT38: =Financials!AS38/('Evolutive SFP'!BV14+'Evolutive SFP'!#REF!)/2 -> #REF! | AU38: =Financials!AT38/('Evolutive SFP'!BW14+'Evolutive SFP'!BV14)/2 -> 0.00095882087 | AV38: =Financials!AU38/('Evolutive SFP'!BX14+'Evolutive SFP'!BW14)/2 -> 0.002880243 | AW38: =Financials!AV38/('Evolutive SFP'!BY14+'Evolutive SFP'!BX14)/2 -> 0.0045660263 | AX38: =Financials!AW38/('Evolutive SFP'!BZ14+'Evolutive SFP'!BY14)/2 -> 0.011064548 | AY38: =Financials!AX38/('Evolutive SFP'!CA14+'Evolutive SFP'!BZ14)/2 -> 0.013781808 | AZ38: =Financials!AY38/('Evolutive SFP'!CB14+'Evolutive SFP'!CA14)/2 -> 0.030028475 | BA38: =Financials!AZ38/('Evolutive SFP'!#REF!+'Evolutive SFP'!CB14)/2 -> #REF! | BB38: =Financials!BA38/('Evolutive SFP'!CC14+'Evolutive SFP'!#REF!)/2 -> #REF! | BC38: =Financials!BB38/('Evolutive SFP'!CD14+'Evolutive SFP'!CC14)/2 -> 0.031753451 | BD38: =Financials!BC38/('Evolutive SFP'!CE14+'Evolutive SFP'!CD14)/2 -> 0.029174431 | BE38: =Financials!BD38/('Evolutive SFP'!CF14+'Evolutive SFP'!CE14)/2 -> 0.028007945 | BF38: =Financials!BE38/('Evolutive SFP'!CG14+'Evolutive SFP'!CF14)/2 -> 0.027823997 | BG38: =Financials!BF38/('Evolutive SFP'!CH14+'Evolutive SFP'!CG14)/2 -> 0.02733709 | BH38: =Financials!BG38/('Evolutive SFP'!CI14+'Evolutive SFP'!CH14)/2 -> 0.0010846921 | BI38: =Financials!BH38/('Evolutive SFP'!CJ14+'Evolutive SFP'!CI14)/2 -> 0.0026749643 | BJ38: =Financials!BI38/('Evolutive SFP'!CK14+'Evolutive SFP'!CJ14)/2 -> 0.0040864857 | ... CD38: =Financials!CC38/('Evolutive SFP'!DE14+'Evolutive SFP'!DD14)/2 -> 0.030009836
B39: Avge yield on Gross loans | E39: =Financials!D37/('Evolutive SFP'!#REF!+'Evolutive SFP'!#REF!)/2 -> #REF! | H39: =Financials!G37/('Evolutive SFP'!#REF!+'Evolutive SFP'!#REF!)/2 -> #REF! | I39: =Financials!H37/('Evolutive SFP'!#REF!+'Evolutive SFP'!#REF!)/2 -> #REF! | J39: =Financials!I37/('Evolutive SFP'!#REF!+'Evolutive SFP'!#REF!)/2 -> #REF! | K39: =Financials!J37/('Evolutive SFP'!#REF!+'Evolutive SFP'!#REF!)/2 -> #REF! | L39: =Financials!K37/('Evolutive SFP'!#REF!+'Evolutive SFP'!#REF!)/2 -> #REF! | M39: =Financials!L37/('Evolutive SFP'!#REF!+'Evolutive SFP'!#REF!)/2 -> #REF! | N39: =Financials!M37/('Evolutive SFP'!#REF!+'Evolutive SFP'!#REF!)/2 -> #REF! | O39: =Financials!N37/('Evolutive SFP'!#REF!+'Evolutive SFP'!#REF!)/2 -> #REF! | ... AS39: =Financials!AR37/('Evolutive SFP'!#REF!+'Evolutive SFP'!#REF!)/2 -> #REF! | AT39: =Financials!AS37/('Evolutive SFP'!BV15+'Evolutive SFP'!#REF!)/2 -> #REF! | AU39: =Financials!AT37/('Evolutive SFP'!BW15+'Evolutive SFP'!BV15)/2 -> 0.0015937714 | AV39: =Financials!AU37/('Evolutive SFP'!BX15+'Evolutive SFP'!BW15)/2 -> 0.0041446127 | AW39: =Financials!AV37/('Evolutive SFP'!BY15+'Evolutive SFP'!BX15)/2 -> 0.006358289 | AX39: =Financials!AW37/('Evolutive SFP'!BZ15+'Evolutive SFP'!BY15)/2 -> 0.020478341 | AY39: =Financials!AX37/('Evolutive SFP'!CA15+'Evolutive SFP'!BZ15)/2 -> 0.024757597 | AZ39: =Financials!AY37/('Evolutive SFP'!CB15+'Evolutive SFP'!CA15)/2 -> 0.041390491 | BA39: =Financials!AZ37/('Evolutive SFP'!#REF!+'Evolutive SFP'!CB15)/2 -> #REF! | BB39: =Financials!BA37/('Evolutive SFP'!CC15+'Evolutive SFP'!#REF!)/2 -> #REF! | BC39: =Financials!BB37/('Evolutive SFP'!CD15+'Evolutive SFP'!CC15)/2 -> 0.04811118 | BD39: =Financials!BC37/('Evolutive SFP'!CE15+'Evolutive SFP'!CD15)/2 -> 0.047895001 | BE39: =Financials!BD37/('Evolutive SFP'!CF15+'Evolutive SFP'!CE15)/2 -> 0.046349405 | BF39: =Financials!BE37/('Evolutive SFP'!CG15+'Evolutive SFP'!CF15)/2 -> 0.046706071 | BG39: =Financials!BF37/('Evolutive SFP'!CH15+'Evolutive SFP'!CG15)/2 -> 0.045901156 | BH39: =Financials!BG37/('Evolutive SFP'!CI15+'Evolutive SFP'!CH15)/2 -> 0.0017078978 | BI39: =Financials!BH37/('Evolutive SFP'!CJ15+'Evolutive SFP'!CI15)/2 -> 0.0038371938 | BJ39: =Financials!BI37/('Evolutive SFP'!CK15+'Evolutive SFP'!CJ15)/2 -> 0.0060100832 | ... CD39: =Financials!CC37/('Evolutive SFP'!DE15+'Evolutive SFP'!DD15)/2 -> 0.047941613
A41: ALL/Average Gross Loan portfolio

Sheet Financials
B1: Lainisha Sacco Financial Performance
B2: Year | C2: 2013 Audited | D2: 2014 Audited | E2: 2015 Audited | F2: 2016 Audited | G2: 42736 | H2: 42767 | I2: 42795 | J2: 42826 | K2: 42856 | L2: 42887 | M2: 42917 | N2: 42948 | O2: 42979 | P2: 43009 | Q2: 43040 | R2: 43070 | S2: Audited 2017 | T2: 43101 | U2: 43132 | V2: 43160 | W2: 43191 | X2: 43221 | Y2: 43252 | Z2: 43282 | AA2: 43313 | AB2: 43344 | AC2: 43374 | AD2: 43405 | AE2: 43435 | AF2: Audited 2018 | AG2: 43466 | AH2: 43497 | AI2: 43525 | AJ2: 43556 | AK2: 43586 | AL2: 43617 | AM2: 43647 | AN2: 43678 | AO2: 43709 | AP2: 43739 | AQ2: 43770 | AR2: 43800 | AS2: Audited 2019 | AT2: 43831 | AU2: 43862 | AV2: 43891 | AW2: 43922 | AX2: 43952 | AY2: 43983 | AZ2: 44013 | BA2: 44044 | BB2: 44075 | BC2: 44105 | BD2: 44136 | BE2: 44166 | BF2: Audited 2020 | BG2: 44197 | BH2: 44228 | BI2: 44256 | BJ2: 44287 | BK2: 44317 | BL2: 44348 | BM2: 44378 | BN2: 44409 | BO2: 44440 | BP2: 44470 | BQ2: 44501 | BR2: 44531 | BS2: AUDITED 2021 | BT2: AUDITED 2022 | BU2: 44927 | BV2: 44958 | BW2: 44986 | BX2: 45017 | BY2: 45047 | BZ2: 45078 | CA2: 45108 | CB2: 45139 | CC2: 45170
A3: 1 | B3: Membership | D3: 39898 | E3: 55854
A4: 2 | B4: Total Assets | C4: ='Evolutive SFP'!#REF! -> #REF! | D4: ='Evolutive SFP'!#REF! -> #REF! | E4: ='Evolutive SFP'!#REF! -> #REF! | F4: ='Evolutive SFP'!#REF! -> #REF! | G4: ='Evolutive SFP'!#REF! -> #REF! | H4: ='Evolutive SFP'!#REF! -> #REF! | I4: ='Evolutive SFP'!#REF! -> #REF! | J4: ='Evolutive SFP'!#REF! -> #REF! | ... R4: ='Evolutive SFP'!#REF! -> #REF! | S4: ='Evolutive SFP'!AV27 -> 338132752 | T4: ='Evolutive SFP'!AW27 -> 3.3973792e+08 | U4: ='Evolutive SFP'!AX27 -> 3.3844964e+08 | V4: ='Evolutive SFP'!AY27 -> 3.3797007e+08 | W4: ='Evolutive SFP'!AZ27 -> 3.4043624e+08 | X4: ='Evolutive SFP'!BA27 -> 4.2597076e+08 | Y4: ='Evolutive SFP'!BB27 -> 3.9919921e+08 | Z4: ='Evolutive SFP'!BC27 -> 4.0124752e+08 | ... AY4: ='Evolutive SFP'!CB27 -> 5.3075095e+08 | AZ4: ='Evolutive SFP'!#REF! -> #REF! | BA4: ='Evolutive SFP'!CC27 -> 4.8643922e+08 | BB4: ='Evolutive SFP'!CD27 -> 6.5799608e+08 | BC4: ='Evolutive SFP'!CE27 -> 5.6513933e+08 | BD4: ='Evolutive SFP'!CF27 -> 5.1201665e+08 | BE4: ='Evolutive SFP'!CG27 -> 4.8660514e+08 | BF4: ='Evolutive SFP'!CH27 -> 486605145 | BG4: ='Evolutive SFP'!CI27 -> 4.7082577e+08 | BH4: ='Evolutive SFP'!CJ27 -> 4.6300338e+08 | ... CC4: ='Evolutive SFP'!DE27 -> 6.8298175e+08
A5: 3 | B5: Total Deposits | C5: ='Evolutive SFP'!#REF! -> #REF! | D5: ='Evolutive SFP'!#REF! -> #REF! | E5: ='Evolutive SFP'!#REF! -> #REF! | F5: ='Evolutive SFP'!#REF! -> #REF! | G5: ='Evolutive SFP'!#REF! -> #REF! | H5: ='Evolutive SFP'!#REF! -> #REF! | I5: ='Evolutive SFP'!#REF! -> #REF! | J5: ='Evolutive SFP'!#REF! -> #REF! | ... R5: ='Evolutive SFP'!#REF! -> #REF! | S5: ='Evolutive SFP'!AV31 -> 141371064 | T5: ='Evolutive SFP'!AW31 -> 1.3825458e+08 | U5: ='Evolutive SFP'!AX31 -> 1.3542228e+08 | V5: ='Evolutive SFP'!AY31 -> 1.3492079e+08 | W5: ='Evolutive SFP'!AZ31 -> 1.390988e+08 | X5: ='Evolutive SFP'!BA31 -> 2.1660363e+08 | Y5: ='Evolutive SFP'!BB31 -> 1.9184982e+08 | Z5: ='Evolutive SFP'!BC31 -> 1.8883473e+08 | ... AY5: ='Evolutive SFP'!CB31 -> 2.9411719e+08 | AZ5: ='Evolutive SFP'!#REF! -> #REF! | BA5: ='Evolutive SFP'!CC31 -> 2.4941436e+08 | BB5: ='Evolutive SFP'!CD31 -> 3.8446605e+08 | BC5: ='Evolutive SFP'!CE31 -> 3.1898314e+08 | BD5: ='Evolutive SFP'!CF31 -> 2.7166015e+08 | BE5: ='Evolutive SFP'!CG31 -> 2.4719163e+08 | BF5: ='Evolutive SFP'!CH31 -> 247191633 | BG5: ='Evolutive SFP'!CI31 -> 2.3386713e+08 | BH5: ='Evolutive SFP'!CJ31 -> 2.2922866e+08 | ... CC5: ='Evolutive SFP'!DE31 -> 3.4151808e+08
A6: 3.1 | B6: Deposits-Members(BOSA) | C6: ='Evolutive SFP'!#REF! -> #REF! | D6: ='Evolutive SFP'!#REF! -> #REF! | E6: ='Evolutive SFP'!#REF! -> #REF! | F6: ='Evolutive SFP'!#REF! -> #REF! | G6: ='Evolutive SFP'!#REF! -> #REF! | H6: ='Evolutive SFP'!#REF! -> #REF! | I6: ='Evolutive SFP'!#REF! -> #REF! | J6: ='Evolutive SFP'!#REF! -> #REF! | ... R6: ='Evolutive SFP'!#REF! -> #REF! | S6: ='Evolutive SFP'!AV30 -> 94380497 | T6: ='Evolutive SFP'!AW30 -> 94864059 | U6: ='Evolutive SFP'!AX30 -> 95534037 | V6: ='Evolutive SFP'!AY30 -> 96189608 | W6: ='Evolutive SFP'!AZ30 -> 96483421 | X6: ='Evolutive SFP'!BA30 -> 1.0007996e+08 | Y6: ='Evolutive SFP'!BB30 -> 1.0189561e+08 | Z6: ='Evolutive SFP'!BC30 -> 1.0606116e+08 | ... AY6: ='Evolutive SFP'!CB30 -> 1.1649716e+08 | AZ6: ='Evolutive SFP'!#REF! -> #REF! | BA6: ='Evolutive SFP'!CC30 -> 1.2017729e+08 | BB6: ='Evolutive SFP'!CD30 -> 1.2260357e+08 | BC6: ='Evolutive SFP'!CE30 -> 1.2799435e+08 | BD6: ='Evolutive SFP'!CF30 -> 1.2994695e+08 | BE6: ='Evolutive SFP'!CG30 -> 1.3090945e+08 | BF6: ='Evolutive SFP'!CH30 -> 130909445 | BG6: ='Evolutive SFP'!CI30 -> 1.3131777e+08 | BH6: ='Evolutive SFP'!CJ30 -> 1.3238356e+08 | ... CC6: ='Evolutive SFP'!DE30 -> 1.8415523e+08
A7: 3.2 | B7: Deposits-Customers(FOSA) | C7: =('Evolutive SFP'!#REF!+'Evolutive SFP'!#REF!) -> #REF! | D7: =('Evolutive SFP'!#REF!+'Evolutive SFP'!#REF!) -> #REF! | E7: =('Evolutive SFP'!#REF!+'Evolutive SFP'!#REF!) -> #REF! | F7: =('Evolutive SFP'!#REF!+'Evolutive SFP'!#REF!) -> #REF! | G7: =('Evolutive SFP'!#REF!+'Evolutive SFP'!#REF!) -> #REF! | H7: =('Evolutive SFP'!#REF!+'Evolutive SFP'!#REF!) -> #REF! | I7: =('Evolutive SFP'!#REF!+'Evolutive SFP'!#REF!) -> #REF! | J7: =('Evolutive SFP'!#REF!+'Evolutive SFP'!#REF!) -> #REF! | ... R7: =('Evolutive SFP'!#REF!+'Evolutive SFP'!#REF!) -> #REF! | S7: =('Evolutive SFP'!AV28+'Evolutive SFP'!AV29) -> 46990567 | T7: =('Evolutive SFP'!AW28+'Evolutive SFP'!AW29) -> 43390517 | U7: =('Evolutive SFP'!AX28+'Evolutive SFP'!AX29) -> 39888242 | V7: =('Evolutive SFP'!AY28+'Evolutive SFP'!AY29) -> 38731187 | W7: =('Evolutive SFP'!AZ28+'Evolutive SFP'!AZ29) -> 42615377 | X7: =('Evolutive SFP'!BA28+'Evolutive SFP'!BA29) -> 1.1652367e+08 | Y7: =('Evolutive SFP'!BB28+'Evolutive SFP'!BB29) -> 89954212 | Z7: =('Evolutive SFP'!BC28+'Evolutive SFP'!BC29) -> 82773575 | ... AY7: =('Evolutive SFP'!CB28+'Evolutive SFP'!CB29) -> 1.7762003e+08 | AZ7: =('Evolutive SFP'!#REF!+'Evolutive SFP'!#REF!) -> #REF! | BA7: =('Evolutive SFP'!CC28+'Evolutive SFP'!CC29) -> 1.2923706e+08 | BB7: =('Evolutive SFP'!CD28+'Evolutive SFP'!CD29) -> 2.6186248e+08 | BC7: =('Evolutive SFP'!CE28+'Evolutive SFP'!CE29) -> 1.9098879e+08 | BD7: =('Evolutive SFP'!CF28+'Evolutive SFP'!CF29) -> 1.4171321e+08 | BE7: =('Evolutive SFP'!CG28+'Evolutive SFP'!CG29) -> 1.1628219e+08 | BF7: =('Evolutive SFP'!CH28+'Evolutive SFP'!CH29) -> 116282188 | BG7: =('Evolutive SFP'!CI28+'Evolutive SFP'!CI29) -> 1.0254935e+08 | BH7: =('Evolutive SFP'!CJ28+'Evolutive SFP'!CJ29) -> 96845100 | ... CC7: =('Evolutive SFP'!DE28+'Evolutive SFP'!DE29) -> 1.5736285e+08
A8: 4 | B8: External Borrowing | C8: ='Evolutive SFP'!#REF! -> #REF! | D8: ='Evolutive SFP'!#REF! -> #REF! | E8: ='Evolutive SFP'!#REF! -> #REF! | F8: ='Evolutive SFP'!#REF! -> #REF! | G8: ='Evolutive SFP'!#REF! -> #REF! | H8: ='Evolutive SFP'!#REF! -> #REF! | I8: ='Evolutive SFP'!#REF! -> #REF! | J8: ='Evolutive SFP'!#REF! -> #REF! | ... R8: ='Evolutive SFP'!#REF! -> #REF! | S8: ='Evolutive SFP'!AV37 -> 0 | T8: ='Evolutive SFP'!AW37 -> 0 | U8: ='Evolutive SFP'!AX37 -> 0 | V8: ='Evolutive SFP'!AY37 -> 0 | W8: ='Evolutive SFP'!AZ37 -> 0 | X8: ='Evolutive SFP'!BA37 -> 0 | Y8: ='Evolutive SFP'!BB37 -> 0 | Z8: ='Evolutive SFP'!BC37 -> 0 | ... AY8: ='Evolutive SFP'!CB37 -> 0 | AZ8: ='Evolutive SFP'!#REF! -> #REF! | BA8: ='Evolutive SFP'!CC37 -> 0 | BB8: ='Evolutive SFP'!CD37 -> 0 | BC8: ='Evolutive SFP'!CE37 -> 0 | BD8: ='Evolutive SFP'!CF37 -> 0 | BE8: ='Evolutive SFP'!CG37 -> 0 | BF8: ='Evolutive SFP'!CH37 -> 0 | BG8: ='Evolutive SFP'!CI37 -> 0 | BH8: ='Evolutive SFP'!CJ37 -> 0 | ... CC8: ='Evolutive SFP'!DE37 -> 0
B9: Short term Liabilities | D9: =SUM('Evolutive SFP'!#REF!) -> #REF! | E9: =SUM('Evolutive SFP'!#REF!) -> #REF! | F9: =SUM('Evolutive SFP'!#REF!) -> #REF! | G9: =SUM('Evolutive SFP'!#REF!) -> #REF! | H9: =SUM('Evolutive SFP'!#REF!) -> #REF! | I9: =SUM('Evolutive SFP'!#REF!) -> #REF! | J9: =SUM('Evolutive SFP'!#REF!) -> #REF! | K9: =SUM('Evolutive SFP'!#REF!) -> #REF! | ... R9: =SUM('Evolutive SFP'!#REF!) -> #REF! | S9: =SUM('Evolutive SFP'!AV32:AV36) -> 6509181 | T9: =SUM('Evolutive SFP'!AW32:AW36) -> 2749440 | U9: =SUM('Evolutive SFP'!AX32:AX36) -> 2640228.3 | V9: =SUM('Evolutive SFP'!AY32:AY36) -> 2759673.2 | W9: =SUM('Evolutive SFP'!AZ32:AZ36) -> 1818411.3 | X9: =SUM('Evolutive SFP'!BA32:BA36) -> 1177797.1 | Y9: =SUM('Evolutive SFP'!BB32:BB36) -> 195312.3 | Z9: =SUM('Evolutive SFP'!BC32:BC36) -> 1420285.1 | ... AY9: =SUM('Evolutive SFP'!CB32:CB36) -> 4364729.5 | AZ9: =SUM('Evolutive SFP'!#REF!) -> #REF! | BA9: =SUM('Evolutive SFP'!CC32:CC36) -> 3439965.8 | BB9: =SUM('Evolutive SFP'!CD32:CD36) -> 35807287 | BC9: =SUM('Evolutive SFP'!CE32:CE36) -> 5922538.3 | BD9: =SUM('Evolutive SFP'!CF32:CF36) -> 3515422.2 | BE9: =SUM('Evolutive SFP'!CG32:CG36) -> 11098489 | BF9: =SUM('Evolutive SFP'!CH32:CH36) -> 13652716 | BG9: =SUM('Evolutive SFP'!CI32:CI36) -> 11161802 | BH9: =SUM('Evolutive SFP'!CJ32:CJ36) -> 11914619 | ... CC9: =SUM('Evolutive SFP'!DE32:DE36) -> 9765527.2
A10: 5 | B10: Share capital and Reserves
A11: 5.1 | B11: Core Capital | C11: =C14-C22-C26-C27 -> #REF! | D11: =D14-D22-D26-D27 -> #REF! | E11: =E14-E22-E26-E27 -> #REF! | F11: =F14-F22-F26-F27 -> #REF! | G11: =G14-G22-G26-G27 -> #REF! | H11: =H14-H22-H26-H27 -> #REF! | I11: =I14-I22-I26-I27 -> #REF! | J11: =J14-J22-J26-J27 -> #REF! | ... R11: =R14-R22-R26-R27 -> #REF! | S11: =S14-S22 -> 28583088 | T11: =T14-T22 -> 35172508 | U11: =U14-U22 -> 36825743 | V11: =V14-V22 -> 36728215 | W11: =W14-W22 -> 35957636 | X11: =X14-X22 -> 44627940 | Y11: =Y14-Y22 -> 43592689 | Z11: =Z14-Z22 -> 47431110 | ... CC11: =CC14-CC22 -> 1.3558594e+08
A12: 5.2 | B12: Institutional Capital | C12: =C11-C15 -> #REF! | D12: =D11-D15 -> #REF! | E12: =E11-E15 -> #REF! | F12: =F11-F15 -> #REF! | G12: =G11-G15 -> #REF! | H12: =H11-H15 -> #REF! | I12: =I11-I15 -> #REF! | J12: =J11-J15 -> #REF! | ... CC12: =CC11-CC15 -> 54967890
A14: 5.3 | B14: Total Capital | C14: =C15+C16+C17+C18+C19+C20+C21 -> #REF! | D14: =D15+D16+D17+D18+D19+D20+D21 -> #REF! | E14: =E15+E16+E17+E18+E19+E20+E21 -> #REF! | F14: =F15+F16+F17+F18+F19+F20+F21 -> #REF! | G14: =G15+G16+G17+G18+G19+G20+G21 -> #REF! | H14: =H15+H16+H17+H18+H19+H20+H21 -> #REF! | I14: =I15+I16+I17+I18+I19+I20+I21 -> #REF! | J14: =J15+J16+J17+J18+J19+J20+J21 -> #REF! | ... CC14: =CC15+CC16+CC17+CC18+CC19+CC20+CC21 -> 1.3558594e+08
A15: 5.3.1 | B15: Members Share Capital | C15: ='Evolutive SFP'!#REF! -> #REF! | D15: ='Evolutive SFP'!#REF! -> #REF! | E15: ='Evolutive SFP'!#REF! -> #REF! | F15: ='Evolutive SFP'!#REF! -> #REF! | G15: ='Evolutive SFP'!#REF! -> #REF! | H15: ='Evolutive SFP'!#REF! -> #REF! | I15: ='Evolutive SFP'!#REF! -> #REF! | J15: ='Evolutive SFP'!#REF! -> #REF! | ... R15: ='Evolutive SFP'!#REF! -> #REF! | S15: ='Evolutive SFP'!AV39 -> 51220150 | T15: ='Evolutive SFP'!AW39 -> 51274918 | U15: ='Evolutive SFP'!AX39 -> 51389970 | V15: ='Evolutive SFP'!AY39 -> 51449946 | W15: ='Evolutive SFP'!AZ39 -> 51557960 | X15: ='Evolutive SFP'!BA39 -> 52114502 | Y15: ='Evolutive SFP'!BB39 -> 52450928 | Z15: ='Evolutive SFP'!BC39 -> 52710774 | ... AY15: ='Evolutive SFP'!CB39 -> 67539981 | AZ15: ='Evolutive SFP'!#REF! -> #REF! | BA15: ='Evolutive SFP'!CC39 -> 67783453 | BB15: ='Evolutive SFP'!CD39 -> 67986283 | BC15: ='Evolutive SFP'!CE39 -> 68176578 | BD15: ='Evolutive SFP'!CF39 -> 68306878 | BE15: ='Evolutive SFP'!CG39 -> 68433278 | BF15: ='Evolutive SFP'!CH39 -> 68433278 | BG15: ='Evolutive SFP'!CI39 -> 68636428 | BH15: ='Evolutive SFP'!CJ39 -> 68700328 | ... CC15: ='Evolutive SFP'!DE39 -> 80618050
A16: 5.3.2 | B16: Entrance Fees
A17: 5.3.3 | B17: Retained Earnings | C17: ='Evolutive SFP'!#REF! -> #REF! | D17: ='Evolutive SFP'!#REF! -> #REF! | E17: ='Evolutive SFP'!#REF! -> #REF! | F17: ='Evolutive SFP'!#REF! -> #REF! | G17: ='Evolutive SFP'!#REF! -> #REF! | H17: ='Evolutive SFP'!#REF! -> #REF! | I17: ='Evolutive SFP'!#REF! -> #REF! | J17: ='Evolutive SFP'!#REF! -> #REF! | ... R17: ='Evolutive SFP'!#REF! -> #REF! | S17: ='Evolutive SFP'!AV41 -> -114885111 | T17: ='Evolutive SFP'!AW41 -> -1.0744527e+08 | U17: ='Evolutive SFP'!AX41 -> -1.0742332e+08 | V17: ='Evolutive SFP'!AY41 -> -1.0745267e+08 | W17: ='Evolutive SFP'!AZ41 -> -1.0744017e+08 | X17: ='Evolutive SFP'!BA41 -> -1.1166081e+08 | Y17: ='Evolutive SFP'!BB41 -> -1.1166081e+08 | Z17: ='Evolutive SFP'!BC41 -> -1.1310365e+08 | ... AY17: ='Evolutive SFP'!CB41 -> -1.037163e+08 | AZ17: ='Evolutive SFP'!#REF! -> #REF! | BA17: ='Evolutive SFP'!CC41 -> -1.054817e+08 | BB17: ='Evolutive SFP'!CD41 -> -1.0548041e+08 | BC17: ='Evolutive SFP'!CE41 -> -1.0548041e+08 | BD17: ='Evolutive SFP'!CF41 -> -1.0548041e+08 | BE17: ='Evolutive SFP'!CG41 -> -1.0561029e+08 | BF17: ='Evolutive SFP'!CH41 -> -109356486 | BG17: ='Evolutive SFP'!CI41 -> -97094425 | BH17: ='Evolutive SFP'!CJ41 -> -97094425 | ... CC17: ='Evolutive SFP'!DE41 -> -70366496
A18: 5.3.4 | B18: Appropriation Account | C18: ='Evolutive SFP'!#REF! -> #REF! | D18: ='Evolutive SFP'!#REF! -> #REF! | E18: ='Evolutive SFP'!#REF! -> #REF! | F18: ='Evolutive SFP'!#REF! -> #REF! | G18: ='Evolutive SFP'!#REF! -> #REF! | H18: ='Evolutive SFP'!#REF! -> #REF! | I18: ='Evolutive SFP'!#REF! -> #REF! | J18: ='Evolutive SFP'!#REF! -> #REF! | ... R18: ='Evolutive SFP'!#REF! -> #REF! | S18: ='Evolutive SFP'!AV42 -> 983069 | T18: ='Evolutive SFP'!AW42 -> 256615.05 | U18: ='Evolutive SFP'!AX42 -> 1772847.8 | V18: ='Evolutive SFP'!AY42 -> 1644693.8 | W18: ='Evolutive SFP'!AZ42 -> 753600.8 | X18: ='Evolutive SFP'!BA42 -> 13088010 | Y18: ='Evolutive SFP'!BB42 -> 11716333 | Z18: ='Evolutive SFP'!BC42 -> 16625033 | ... AY18: ='Evolutive SFP'!CB42 -> 13277539 | AZ18: ='Evolutive SFP'!#REF! -> #REF! | BA18: ='Evolutive SFP'!CC42 -> 14305206 | BB18: ='Evolutive SFP'!CD42 -> 18238936 | BC18: ='Evolutive SFP'!CE42 -> 20559541 | BD18: ='Evolutive SFP'!CF42 -> 17036661 | BE18: ='Evolutive SFP'!CG42 -> 8514088.8 | BF18: ='Evolutive SFP'!CH42 -> 8514089 | BG18: ='Evolutive SFP'!CI42 -> -2723103.5 | BH18: ='Evolutive SFP'!CJ42 -> -6723743.5 | ... CC18: ='Evolutive SFP'!DE42 -> 25752856
A19: 5.3.5 | B19: Statutory Reserves | C19: ='Evolutive SFP'!#REF! -> #REF! | D19: ='Evolutive SFP'!#REF! -> #REF! | E19: ='Evolutive SFP'!#REF! -> #REF! | F19: ='Evolutive SFP'!#REF! -> #REF! | G19: ='Evolutive SFP'!#REF! -> #REF! | H19: ='Evolutive SFP'!#REF! -> #REF! | I19: ='Evolutive SFP'!#REF! -> #REF! | J19: ='Evolutive SFP'!#REF! -> #REF! | ... R19: ='Evolutive SFP'!#REF! -> #REF! | S19: ='Evolutive SFP'!AV43 -> 15357936 | T19: ='Evolutive SFP'!AW43 -> 15179196 | U19: ='Evolutive SFP'!AX43 -> 15179196 | V19: ='Evolutive SFP'!AY43 -> 15179196 | W19: ='Evolutive SFP'!AZ43 -> 15179196 | X19: ='Evolutive SFP'!BA43 -> 15179196 | Y19: ='Evolutive SFP'!BB43 -> 15179196 | Z19: ='Evolutive SFP'!BC43 -> 15291911 | ... AY19: ='Evolutive SFP'!CB43 -> 15699379 | AZ19: ='Evolutive SFP'!#REF! -> #REF! | BA19: ='Evolutive SFP'!CC43 -> 17509504 | BB19: ='Evolutive SFP'!CD43 -> 17509504 | BC19: ='Evolutive SFP'!CE43 -> 17509504 | BD19: ='Evolutive SFP'!CF43 -> 17509504 | BE19: ='Evolutive SFP'!CG43 -> 17509504 | BF19: ='Evolutive SFP'!CH43 -> 18701476 | BG19: ='Evolutive SFP'!CI43 -> 17509504 | BH19: ='Evolutive SFP'!CJ43 -> 17509504 | ... CC19: ='Evolutive SFP'!DE43 -> 23674486
A20: 5.3.6 | B20: Capital Reserves | C20: =('Evolutive SFP'!#REF!) -> #REF! | D20: =('Evolutive SFP'!#REF!) -> #REF! | E20: =('Evolutive SFP'!#REF!) -> #REF! | F20: =('Evolutive SFP'!#REF!) -> #REF! | G20: =('Evolutive SFP'!#REF!) -> #REF! | H20: =('Evolutive SFP'!#REF!) -> #REF! | I20: =('Evolutive SFP'!#REF!) -> #REF! | J20: =('Evolutive SFP'!#REF!) -> #REF! | ... R20: =('Evolutive SFP'!#REF!) -> #REF! | S20: =('Evolutive SFP'!AV44) -> 75907044 | T20: =('Evolutive SFP'!AW44) -> 75907044 | U20: =('Evolutive SFP'!AX44) -> 75907044 | V20: =('Evolutive SFP'!AY44) -> 75907044 | W20: =('Evolutive SFP'!AZ44) -> 75907044 | X20: =('Evolutive SFP'!BA44) -> 75907044 | Y20: =('Evolutive SFP'!BB44) -> 75907044 | Z20: =('Evolutive SFP'!BC44) -> 75907044 | ... AY20: =('Evolutive SFP'!CB44) -> 75907044 | AZ20: =('Evolutive SFP'!#REF!) -> #REF! | BA20: =('Evolutive SFP'!CC44) -> 75907044 | BB20: =('Evolutive SFP'!CD44) -> 75907044 | BC20: =('Evolutive SFP'!CE44) -> 75907044 | BD20: =('Evolutive SFP'!CF44) -> 75907044 | BE20: =('Evolutive SFP'!CG44) -> 75907044 | BF20: =('Evolutive SFP'!CH44) -> 75907044 | BG20: =('Evolutive SFP'!CI44) -> 75907044 | BH20: =('Evolutive SFP'!CJ44) -> 75907044 | ... CC20: =('Evolutive SFP'!DE44) -> 75907044
A21: 5.3.7 | B21: Supplementary Capital & reserves | C21: =C22+C23 -> #REF! | D21: =D22+D23 -> #REF! | E21: =E22+E23 -> #REF! | F21: =F22+F23 -> #REF! | G21: =G22+G23 -> #REF! | H21: =H22+H23 -> #REF! | I21: =I22+I23 -> #REF! | J21: =J22+J23 -> #REF! | ... CC21: =CC22+CC23 -> 0
A22: a | B22: Proposed Dividends | C22: ='Evolutive SFP'!#REF! -> #REF! | D22: ='Evolutive SFP'!#REF! -> #REF! | E22: ='Evolutive SFP'!#REF! -> #REF! | F22: ='Evolutive SFP'!#REF! -> #REF! | G22: ='Evolutive SFP'!#REF! -> #REF! | H22: ='Evolutive SFP'!#REF! -> #REF! | I22: ='Evolutive SFP'!#REF! -> #REF! | J22: ='Evolutive SFP'!#REF! -> #REF! | ... R22: ='Evolutive SFP'!#REF! -> #REF! | S22: ='Evolutive SFP'!AV46 -> 0 | T22: ='Evolutive SFP'!AW46 -> 0 | U22: ='Evolutive SFP'!AX46 -> 0 | V22: ='Evolutive SFP'!AY46 -> 0 | W22: ='Evolutive SFP'!AZ46 -> 0 | X22: ='Evolutive SFP'!BA46 -> 0 | Y22: ='Evolutive SFP'!BB46 -> 0 | Z22: ='Evolutive SFP'!BC46 -> 0 | ... AY22: ='Evolutive SFP'!CB46 -> 0 | AZ22: ='Evolutive SFP'!#REF! -> #REF! | BA22: ='Evolutive SFP'!CC46 -> 0 | BB22: ='Evolutive SFP'!CD46 -> 0 | BC22: ='Evolutive SFP'!CE46 -> 0 | BD22: ='Evolutive SFP'!CF46 -> 0 | BE22: ='Evolutive SFP'!CG46 -> 0 | BF22: ='Evolutive SFP'!CH46 -> 0 | BG22: ='Evolutive SFP'!CI46 -> 0 | BH22: ='Evolutive SFP'!CJ46 -> 0 | ... CC22: ='Evolutive SFP'!DE46 -> 0
A23: b | B23: Risk Mgt Fund
A25: 6 | B25: Investments | C25: =C26+C27+C28 -> #REF! | D25: =D26+D27+D28 -> #REF! | E25: =E26+E27+E28 -> #REF! | F25: =F26+F27+F28 -> #REF! | G25: =G26+G27+G28 -> #REF! | H25: =H26+H27+H28 -> #REF! | I25: =I26+I27+I28 -> #REF! | J25: =J26+J27+J28 -> #REF! | ... CC25: =CC26+CC27+CC28 -> #REF!
A26: 6.1 | B26: Shares in Kusco,CIC,Coop Bank | C26: ='Evolutive SFP'!#REF! -> #REF! | D26: ='Evolutive SFP'!#REF! -> #REF! | E26: ='Evolutive SFP'!#REF! -> #REF! | F26: ='Evolutive SFP'!#REF! -> #REF! | G26: ='Evolutive SFP'!#REF! -> #REF! | H26: ='Evolutive SFP'!#REF! -> #REF! | I26: ='Evolutive SFP'!#REF! -> #REF! | J26: ='Evolutive SFP'!#REF! -> #REF! | ... R26: ='Evolutive SFP'!#REF! -> #REF! | S26: ='Evolutive SFP'!AV13 -> 0 | T26: ='Evolutive SFP'!AW13 -> 0 | U26: ='Evolutive SFP'!AX13 -> 0 | V26: ='Evolutive SFP'!AY13 -> 0 | W26: ='Evolutive SFP'!AZ13 -> 0 | X26: ='Evolutive SFP'!BA13 -> 0 | Y26: ='Evolutive SFP'!BB13 -> 0 | Z26: ='Evolutive SFP'!BC13 -> 0 | ... BW26: ='Evolutive SFP'!CZ13 -> 49524309 | BX26: ='Evolutive SFP'!#REF! -> #REF! | BY26: ='Evolutive SFP'!#REF! -> #REF! | BZ26: ='Evolutive SFP'!#REF! -> #REF! | CA26: ='Evolutive SFP'!#REF! -> #REF! | CB26: ='Evolutive SFP'!#REF! -> #REF! | CC26: ='Evolutive SFP'!#REF! -> #REF!
