Workbook
Name BALANCE1_LDA01: '[1]Financial Statements'!$E$112
Name BALANCE1_LDA12: '[1]Financial Statements'!$E$123
Name BALANCE2_LDA01: '[1]Financial Statements'!$F$112
Name BALANCE2_LDA12: '[1]Financial Statements'!$F$123
Name BALANCE3_LDA01: '[1]Financial Statements'!$G$112
Name BALANCE3_LDA12: '[1]Financial Statements'!$G$123
Name BALANCE4_LDA01: '[1]Financial Statements'!$H$112
Name BALANCE4_LDA12: '[1]Financial Statements'!$H$123
Name BALANCE5_LDA01: '[1]Financial Statements'!$I$112
Name BALANCE5_LDA12: '[1]Financial Statements'!$I$123
Name BALANCE6_LDA01: '[1]Financial Statements'!$J$112
Name BALANCE6_LDA12: '[1]Financial Statements'!$J$123
Name NotApplicable: 'Prudential Ratios'!#REF!
Name PEARLS1_LA002: '[1]Financial Statements'!$E$280
Name PEARLS1_LE008: '[1]Financial Statements'!$E$275
Name PEARLS1_LE009: '[1]Financial Statements'!$E$276
Name PEARLS1_LR001: '[1]Financial Statements'!$E$282
Name PEARLS1_LR005: '[1]Financial Statements'!$E$286
Name PEARLS1_LR006: '[1]Financial Statements'!$E$287
Name PEARLS1_LR007: '[1]Financial Statements'!$E$288
Name PEARLS1_LR009: '[1]Financial Statements'!$E$290
Name PEARLS1_LS001: '[1]Financial Statements'!$E$298
Name PEARLS1_LS005: '[1]Financial Statements'!$E$302
Name PEARLS1_LS011: '[1]Financial Statements'!$E$308
Name PEARLS2_LA002: '[1]Financial Statements'!$F$280
Name PEARLS2_LE008: '[1]Financial Statements'!$F$275
Name PEARLS2_LE009: '[1]Financial Statements'!$F$276
Name PEARLS2_LR001: '[1]Financial Statements'!$F$282
Name PEARLS2_LR005: '[1]Financial Statements'!$F$286
Name PEARLS2_LR006: '[1]Financial Statements'!$F$287
Name PEARLS2_LR007: '[1]Financial Statements'!$F$288
Name PEARLS2_LR009: '[1]Financial Statements'!$F$290
Name PEARLS2_LS001: '[1]Financial Statements'!$F$298
Name PEARLS2_LS005: '[1]Financial Statements'!$F$302
Name PEARLS2_LS010: '[1]Financial Statements'!$F$307
Name PEARLS2_LS011: '[1]Financial Statements'!$F$308
Name PEARLS3_LA002: '[1]Financial Statements'!$G$280
Name PEARLS3_LE008: '[1]Financial Statements'!$G$275
Name PEARLS3_LE009: '[1]Financial Statements'!$G$276
Name PEARLS3_LR001: '[1]Financial Statements'!$G$282
Name PEARLS3_LR005: '[1]Financial Statements'!$G$286
Name PEARLS3_LR006: '[1]Financial Statements'!$G$287
Name PEARLS3_LR007: '[1]Financial Statements'!$G$288
Name PEARLS3_LR009: '[1]Financial Statements'!$G$290
Name PEARLS3_LS001: '[1]Financial Statements'!$G$298
Name PEARLS3_LS005: '[1]Financial Statements'!$G$302
Name PEARLS3_LS010: '[1]Financial Statements'!$G$307
Name PEARLS3_LS011: '[1]Financial Statements'!$G$308
Name PEARLS4_LA002: '[1]Financial Statements'!$H$280
Name PEARLS4_LE008: '[1]Financial Statements'!$H$275
Name PEARLS4_LE009: '[1]Financial Statements'!$H$276
Name PEARLS4_LR001: '[1]Financial Statements'!$H$282
Name PEARLS4_LR005: '[1]Financial Statements'!$H$286
Name PEARLS4_LR006: '[1]Financial Statements'!$H$287
Name PEARLS4_LR007: '[1]Financial Statements'!$H$288
Name PEARLS4_LR009: '[1]Financial Statements'!$H$290
Name PEARLS4_LS001: '[1]Financial Statements'!$H$298
Name PEARLS4_LS005: '[1]Financial Statements'!$H$302
Name PEARLS4_LS010: '[1]Financial Statements'!$H$307
Name PEARLS4_LS011: '[1]Financial Statements'!$H$308

Sheet SFP
A1: MENTOR SACCO LTD | AA1: =W29+W36+W37 -> 3.2550511e+08
A2: STATEMENT OF FINANCIAL POSITION | T2: =G29+G37 -> 599293835
B3: 2011 AUDITED | C3: 2012 AUDITED | D3: 2013 AUDITED | E3: 2014 AUDITED | F3: Audited 2015 | G3: Audited 2016 | H3: 42736 | I3: 42767 | J3: 42795 | K3: 42826 | L3: 42856 | M3: 42887 | N3: 42917 | O3: 42948 | P3: 42979 | Q3: 43009 | R3: 43040 | S3: 43070 | T3: Audited 2017 | U3: 43101 | V3: 43132 | W3: 43160 | X3: 43191 | Y3: 43221 | Z3: 43252 | AA3: 43282 | AB3: 43313 | AC3: 43344 | AD3: 43374 | AE3: 43405 | AF3: 43435 | AG3: Audited 2018 | AH3: 43466 | AI3: 43497 | AJ3: 43525 | AK3: 43556 | AL3: 43586 | AM3: 43617 | AN3: 43647 | AO3: 43678 | AP3: 43709 | AQ3: 43739 | AR3: 43770 | AS3: 43800 | AT3: Audited-19 | AU3: 43831 | AV3: 43862 | AW3: 43891 | AX3: 43922 | AY3: 43952 | AZ3: 43983 | BA3: 44013 | BB3: 44044 | BC3: 44075 | BD3: 44105 | BE3: 44136 | BF3: 44166 | BG3: Audited-20 | BH3: 44197 | BI3: 44228 | BJ3: 44256 | BK3: 44287 | BL3: 44317 | BM3: 44348 | BN3: 44378 | BO3: 44409 | BP3: 44440 | BQ3: 44470 | BR3: 44501 | BS3: 44531 | BT3: Audited 2021 | BU3: 44562 | BV3: 44593 | BW3: 44621 | BX3: 44652 | BY3: 44682 | BZ3: 44713 | CA3: 44743 | CB3: 44774 | CC3: 44805 | CD3: 44835 | CE3: 44866 | CF3: 44896 | CG3: Audited 2022 | CH3: 44927 | CI3: 44958 | CJ3: 44986 | CK3: 45017 | CL3: 45047 | CM3: 45078 | CN3: 45108 | CO3: 45139 | CP3: 45170 | CQ3: 45200 | CR3: 45231 | CS3: 45261 | CT3: 45292
A4: Cash & Cash Equivalent | B4: =B5+B6 -> 283849000 | C4: =SUM(C5:C6) -> 110263000 | D4: =SUM(D5:D6) -> 201351000 | E4: =SUM(E5:E6) -> 182728629 | F4: =SUM(F5:F6) -> 214035021 | G4: =G5+G6 -> 258656183 | H4: =H5+H6 -> 2.6039096e+08 | I4: =I5+I6 -> 2.060013e+08 | J4: =J5+J6 -> 1.0801628e+08 | K4: =K5+K6 -> 14196015 | L4: =L5+L6 -> 1.0980475e+08 | M4: =M5+M6 -> 3.0429329e+08 | N4: =N5+N6 -> 1.7228961e+08 | ... CT4: =CT5+CT6 -> 0
A5: Cash in hand | B5: 11890000 | C5: 11448000 | D5: 9314000 | E5: 13696359 | F5: 14717887 | G5: 13984867 | H5: 35143309 | I5: 26264561 | J5: 44358499 | K5: 43330869 | L5: 49061791 | M5: 36316107 | N5: 22025163 | O5: 37004143 | P5: 70548604 | Q5: 58248806 | R5: 43484491 | S5: 48699124 | T5: 38502052 | U5: 94212113 | V5: 30945812 | W5: 46177858 | X5: 46531909 | Y5: 50359866 | Z5: 45193443 | AA5: 57753553 | AB5: 48345214 | AC5: 29655766 | AD5: 47543125 | AE5: 49112474 | AF5: 40714606 | AG5: 40714606 | AH5: 35588028 | AI5: 52941129 | AJ5: 51049723 | AK5: 40476884 | AL5: 44279602 | AM5: 48540718 | AN5: 70466476 | AO5: 37316349 | AP5: 41215416 | AQ5: 43392514 | AR5: 31611042 | AS5: 36928070 | AT5: 37108170 | AU5: 70501994 | AV5: 68837451 | AW5: 56149989 | AX5: 90734149 | AY5: 54762587 | AZ5: 50711831 | BA5: 75916162 | BB5: 77209066 | BC5: 64098527 | BD5: 89383375 | BE5: 69358932 | BF5: 95087912 | BG5: 95087912 | BH5: 93608224 | BI5: 96070443 | BJ5: 65165218 | BK5: 85967749 | BL5: 1.0035976e+08 | BM5: 69289471 | BN5: 59743888 | BO5: 54801305 | BP5: 72432908 | BQ5: 76585214 | BR5: 61423807 | BS5: 71614010 | BT5: 71614010 | BU5: 55238333 | BV5: 90694612 | BW5: 61292454 | BX5: 87027470 | BY5: 59032999 | BZ5: 44678209 | CA5: 88328946 | CB5: 97253998 | CC5: 1.0376684e+08 | CD5: 88603868 | CE5: 76011280 | CF5: 1.113003e+08 | CG5: 112430117 | CH5: 54774550 | CI5: 88163721 | CJ5: 1.2730836e+08 | CK5: 77437439 | CL5: 90238416 | CM5: 96989477 | CN5: 88377095 | CO5: 1.2804257e+08 | CP5: 68546524
A6: Cash at bank | B6: 271959000 | C6: =81972000+16843000 -> 98815000 | D6: 192037000 | E6: =50323695+118708575 -> 169032270 | F6: =118899613+80417521 -> 199317134 | G6: =181414760+63256556 -> 244671316 | H6: 2.2524765e+08 | I6: 1.7973674e+08 | J6: 63657780 | K6: -29134854 | L6: 60742963 | M6: 2.6797718e+08 | N6: 1.5026445e+08 | O6: 33321793 | P6: 18074529 | Q6: 2.3037456e+08 | R6: 65179884 | S6: 1.1396201e+08 | T6: 113944466 | U6: 2.3320839e+08 | V6: -12960349 | W6: 84919556 | X6: 11688599 | Y6: 84426721 | Z6: 1.6266697e+08 | AA6: 1.0140057e+08 | AB6: 1.3019334e+08 | AC6: 2.0525131e+08 | AD6: 1.8390621e+08 | AE6: 1.8911156e+08 | AF6: 1.8714287e+08 | AG6: =123605753+63313356 -> 186919109 | AH6: 3.0978772e+08 | AI6: 3.3048856e+08 | AJ6: 3.571304e+08 | AK6: 2.8681085e+08 | AL6: 5.1439929e+08 | AM6: 4.661812e+08 | AN6: 4.8131121e+08 | AO6: 6.400575e+08 | AP6: 5.4370434e+08 | AQ6: 6.4545303e+08 | AR6: 7.477479e+08 | AS6: 7.617262e+08 | AT6: 761724576 | AU6: 6.6865175e+08 | AV6: 6.5355856e+08 | AW6: 6.6563703e+08 | AX6: 8.6558653e+08 | AY6: 1.0239525e+09 | AZ6: 1.2556211e+09 | BA6: 1.1563399e+09 | BB6: 1.0488559e+09 | BC6: 1.1679097e+09 | BD6: 1.0894321e+09 | BE6: 1.3235119e+09 | BF6: 1.1854314e+09 | BG6: 1185431357 | BH6: 1.2367631e+09 | BI6: 1.2306368e+09 | BJ6: 1.2815229e+09 | BK6: 1.469488e+09 | BL6: 1.3336836e+09 | BM6: 1.5895219e+09 | BN6: 1.7176034e+09 | BO6: 1.7815225e+09 | BP6: 2.1146008e+09 | BQ6: 1.9174287e+09 | BR6: 1.9671777e+09 | BS6: 2.1530978e+09 | BT6: =2224711816-BT5 -> 2153097806 | BU6: 1.8403474e+09 | BV6: 1.7386821e+09 | BW6: 1.601886e+09 | BX6: 1.5075133e+09 | BY6: 1.6229175e+09 | BZ6: 1.941945e+09 | CA6: 1.8145568e+09 | CB6: 1.8295875e+09 | CC6: 1.7623086e+09 | CD6: 1.8287338e+09 | CE6: 1.9705585e+09 | CF6: 1.9200011e+09 | CG6: =2033555086-CG5 -> 1921124969 | CH6: 1.6143013e+09 | CI6: 1.5189528e+09 | CJ6: 1.386027e+09 | CK6: 1.4970817e+09 | CL6: 1.6593924e+09 | CM6: 2.055872e+09 | CN6: 2.132503e+09 | CO6: 2.0724994e+09 | CP6: 2.1520789e+09
A7: Prepayments & Sundry Receivables | B7: 80742000 | C7: 157802000 | D7: 3.5042493e+08 | E7: 270176551 | F7: 229086382 | G7: 214520369 | H7: 1.3999113e+08 | I7: 1.2352411e+08 | J7: 2.0780945e+08 | K7: 2.2550666e+08 | L7: 1.0702057e+08 | M7: 1.2099601e+08 | N7: 2.1594307e+08 | O7: 2.0080532e+08 | P7: 2.3879896e+08 | Q7: 1.2496983e+08 | R7: 2.4157564e+08 | S7: 1.4594799e+08 | T7: 145940535 | U7: 3.1776137e+08 | V7: 2.4301911e+08 | W7: 1.2430703e+08 | X7: 1.2035957e+08 | Y7: 1.100997e+08 | Z7: 1.1677677e+08 | AA7: 2.6216769e+08 | AB7: 1.3144614e+08 | AC7: 1.2748276e+08 | AD7: 2.4566809e+08 | AE7: 2.7592658e+08 | AF7: 3.2413739e+08 | AG7: 326646200 | AH7: 3.3360807e+08 | AI7: 3.0189081e+08 | AJ7: 3.2094147e+08 | AK7: 3.1127279e+08 | AL7: 1.6231158e+08 | AM7: 3.2488625e+08 | AN7: 4.5861151e+08 | AO7: 1.8689115e+08 | AP7: 3.1194967e+08 | AQ7: 3.3452979e+08 | AR7: 2.3369236e+08 | AS7: 1.5679987e+08 | AT7: 221973821 | AU7: 3.4666681e+08 | AV7: 3.5994937e+08 | AW7: 3.6822632e+08 | AX7: 3.7530246e+08 | AY7: 3.9533228e+08 | AZ7: 2.2811918e+08 | BA7: 4.1405969e+08 | BB7: 4.2390266e+08 | BC7: 3.0089762e+08 | BD7: 4.0214201e+08 | BE7: 2.2784826e+08 | BF7: 4.2399877e+08 | BG7: 487149053 | BH7: 4.6123653e+08 | BI7: 4.4312419e+08 | BJ7: 4.5791043e+08 | BK7: 2.4266969e+08 | BL7: 4.6482451e+08 | BM7: 2.5875842e+08 | BN7: 4.2831425e+08 | BO7: 4.1459534e+08 | BP7: 2.0747715e+08 | BQ7: 4.0680765e+08 | BR7: 4.0746645e+08 | BS7: 1.8478803e+08 | BT7: 187408031 | BU7: 3.7861221e+08 | BV7: 4.3621138e+08 | BW7: 4.1575786e+08 | BX7: 4.2732627e+08 | BY7: 4.693709e+08 | BZ7: 2.3024234e+08 | CA7: 4.6829452e+08 | CB7: 466614669 | CC7: 4.8606502e+08 | CD7: 5.1795276e+08 | CE7: 5.0409518e+08 | CF7: 4.8257375e+08 | CG7: 400156900 | CH7: 5.1287388e+08 | CI7: 5.5253662e+08 | CJ7: 6.2877602e+08 | CK7: 5.9459769e+08 | CL7: 5.3517112e+08 | CM7: 3.8535251e+08 | CN7: 5.6484034e+08 | CO7: 6.4019452e+08 | CP7: 5.859976e+08
A8: Financial Investments | B8: =SUM(B9:B12) -> 140316000 | C8: =SUM(C9:C12) -> 136004000 | D8: =SUM(D9:D12) -> 269992000 | E8: =SUM(E9:E12) -> 267823506 | F8: =SUM(F9:F12) -> 249273506 | G8: 232172149 | H8: =SUM(H9:H12) -> 2.2073579e+08 | I8: =SUM(I9:I12) -> 193214051 | J8: =SUM(J9:J12) -> 193214051 | K8: =SUM(K9:K12) -> 193214051 | L8: =SUM(L9:L12) -> 194114051 | M8: =SUM(M9:M12) -> 194114051 | N8: =SUM(N9:N12) -> 194114051 | O8: =SUM(O9:O12) -> 194514051 | ... CT8: =SUM(CT9:CT12) -> 0
A9: Government Securities - Treasury Bills/bonds, | B9: 0 | H9: 0 | I9: 0 | J9: 0 | L9: 0 | M9: 0 | N9: 0 | O9: 0 | P9: 0 | Q9: 0 | R9: 0 | S9: 0 | T9: 0 | U9: 0 | V9: 0 | W9: 0 | X9: 0 | Y9: 0 | Z9: 0 | AA9: 0 | AB9: 0 | AC9: 0 | AD9: 0 | AE9: 0 | AF9: 0 | AG9: 0 | AH9: 0 | AI9: 0 | AJ9: 0 | AK9: 0 | AL9: 0 | AM9: 0 | AN9: 0 | AO9: 0 | AP9: 0 | AQ9: 0 | AR9: 0 | AS9: 0 | AT9: 0 | AU9: 0 | AV9: 0 | AW9: 0 | AX9: 0 | AY9: 0 | AZ9: 0 | BA9: 0 | BB9: 0 | BC9: 0 | BD9: 0 | BE9: 0 | BF9: 0 | BG9: 0 | BH9: 0 | BI9: 0 | BJ9: 0 | BK9: 0 | BL9: 0 | BM9: 0 | BN9: 0 | BO9: 0 | BP9: 0 | BQ9: 0 | BR9: 0 | BS9: 0 | BU9: 0 | BV9: 0 | BW9: 0 | BX9: 0 | BY9: 0 | BZ9: 0 | CA9: 0 | CB9: 0 | CC9: 0 | CD9: 0 | CE9: 0 | CF9: 0 | CH9: 0 | CI9: 0 | CJ9: 0 | CK9: 0 | CL9: 0 | CM9: 0 | CN9: 0 | CO9: 0 | CP9: 0
A10: Other Securities - Commercial papers/Bonds | B10: 140316000 | H10: 0 | I10: 0 | J10: 0 | L10: 0 | M10: 0 | N10: 0 | O10: 0 | P10: 0 | Q10: 0 | R10: 0 | S10: 0 | T10: 0 | U10: 0 | V10: 0 | W10: 0 | X10: 0 | Y10: 0 | Z10: 0 | AA10: 0 | AB10: 0 | AC10: 0 | AD10: 0 | AE10: 0 | AF10: 0 | AG10: 0 | AH10: 0 | AI10: 0 | AJ10: 0 | AK10: 0 | AL10: 0 | AM10: 0 | AN10: 0 | AO10: 0 | AP10: 0 | AQ10: 0 | AR10: 0 | AS10: 0 | AT10: 0 | AU10: 0 | AV10: 0 | AW10: 0 | AX10: 0 | AY10: 0 | AZ10: 0 | BA10: 0 | BB10: 0 | BC10: 0 | BD10: 0 | BE10: 0 | BF10: 0 | BG10: 0 | BH10: 0 | BI10: 0 | BJ10: 0 | BK10: 0 | BL10: 0 | BM10: 0 | BN10: 0 | BO10: 0 | BP10: 0 | BQ10: 0 | BR10: 0 | BS10: 0 | BU10: 0 | BV10: 0 | BW10: 0 | BX10: 0 | BY10: 0 | BZ10: 0 | CA10: 0 | CB10: 0 | CC10: 0 | CD10: 0 | CE10: 0 | CF10: 0 | CH10: 0 | CI10: 0 | CJ10: 0 | CK10: 0 | CL10: 0 | CM10: 0 | CN10: 0 | CO10: 0 | CP10: 0
A11: Balances with other SACCO Societies | B11: 0 | H11: 0 | I11: 0 | J11: 0 | L11: 0 | M11: 0 | N11: 0 | O11: 0 | P11: 0 | Q11: 0 | R11: 0 | S11: 0 | T11: 0 | U11: 0 | V11: 0 | W11: 0 | X11: 0 | Y11: 0 | Z11: 0 | AA11: 0 | AB11: 0 | AC11: 0 | AD11: 0 | AE11: 0 | AF11: 0 | AG11: 5050000 | AH11: 0 | AI11: 0 | AJ11: 0 | AK11: 0 | AL11: 0 | AM11: 0 | AN11: 0 | AO11: 0 | AP11: 0 | AQ11: 0 | AR11: 0 | AS11: 0 | AT11: =15748623 -> 15748623 | AU11: 0 | AV11: 0 | AW11: 0 | AX11: 0 | AY11: 0 | AZ11: 0 | BA11: 0 | BB11: 0 | BC11: 0 | BD11: 0 | BE11: 0 | BF11: 0 | BG11: =149997404+10000000+2101780 -> 162099184 | BH11: 0 | BI11: 0 | BJ11: 0 | BK11: 0 | BL11: 0 | BM11: 0 | BN11: 0 | BO11: 0 | BP11: 0 | BQ11: 0 | BR11: 0 | BS11: 0 | BT11: =255575965+12805000+2101780 -> 270482745 | BU11: 17883954 | BV11: 17883954 | BW11: 17883954 | BX11: 17883954 | BY11: 17883954 | BZ11: 17883954 | CA11: 17883954 | CB11: 17883954 | CC11: 17883954 | CD11: 17883954 | CE11: 17883954 | CF11: 17883954 | CG11: =197057330-CG12 -> 178120686 | CH11: 178425686 | CI11: 178725686 | CJ11: 179035686 | CK11: 179335686 | CL11: 179645686 | CM11: 179950686 | CN11: 180255686 | CO11: 180560686 | CP11: 180965686
A12: Investments in companies - shares/stocks | B12: 0 | C12: =132292000+143968000-140256000 -> 136004000 | D12: =184621000+18684000+5881000+2491000+21000+50000+300000+57944000 -> 269992000 | E12: 267823506 | F12: 249273506 | H12: 2.2073579e+08 | I12: 193214051 | J12: 193214051 | K12: 193214051 | L12: 194114051 | M12: 194114051 | N12: 194114051 | O12: 194514051 | P12: 194514051 | Q12: 194614051 | R12: 195114051 | S12: 195614051 | T12: 212113083 | U12: 391228102 | V12: 236613083 | W12: 236713083 | X12: 238990740 | Y12: 239090740 | Z12: 239190740 | AA12: 239290740 | AB12: 239290740 | AC12: 215690740 | AD12: 215790740 | AE12: 215890740 | AF12: 215990740 | AG12: 189994836 | AH12: 216688611 | AI12: 195942707 | AJ12: 196142707 | AK12: 196842707 | AL12: 197042707 | AM12: 197242707 | AN12: 197442707 | AO12: 197642707 | AP12: 197842707 | AQ12: 1.9814346e+08 | AR12: 1.9834346e+08 | AS12: 1.9854346e+08 | AT12: 201602738 | AU12: 1.9874346e+08 | AV12: 217667338 | AW12: 218267309 | AX12: 218467309 | AY12: 218667309 | AZ12: 218867309 | BA12: 219067309 | BB12: 219267309 | BC12: 219467309 | BD12: 219667309 | BE12: 220767309 | BF12: 221917309 | BG12: =206000+10651836 -> 10857836 | BH12: 172414104 | BI12: 172614104 | BJ12: 174383138 | BK12: 1.7458314e+08 | BL12: 1.7578314e+08 | BM12: 1.7598314e+08 | BN12: 1.7648314e+08 | BO12: 1.7698314e+08 | BP12: 1.7748314e+08 | BQ12: 1.7798314e+08 | BR12: 1.7848314e+08 | BS12: 1.7898814e+08 | BT12: 14083954 | BU12: 173149342 | BV12: 173454342 | BW12: 1.7376434e+08 | BX12: 174069342 | BY12: 174374342 | BZ12: 174679342 | CA12: 174984342 | CB12: 175289342 | CC12: 180950462 | CD12: 181255462 | CE12: 181560462 | CF12: 181865462 | CG12: 18936644 | CH12: 17883954 | CI12: 18936644 | CJ12: 18936644 | CK12: 24148066 | CL12: 24148066 | CM12: 24148066 | CN12: 24148066 | CO12: 24148066 | CP12: 24148066
A13: Net Loan Portfolio | B13: =B14-B15 -> 1447463000 | C13: =C14-C15 -> 1669487000 | D13: =D14-D15 -> 1976393000 | E13: =E14-E15 -> 2511315580 | F13: =F14-F15 -> 3150143542 | G13: =G14-G15 -> 4068599457 | H13: =H14-H15 -> 4.0453554e+09 | I13: =I14-I15 -> 4.060404e+09 | ... CT13: =CT14-CT15 -> 0
A14: Gross Loan Portfolio | B14: 1458954000 | C14: =1379419000+307755000 -> 1687174000 | D14: 1994080000 | E14: =2018922702+520080194 -> 2539002896 | F14: =2549758075+633072783 -> 3182830858 | G14: =3211069464+905029993 -> 4116099457 | H14: 4.0900427e+09 | I14: 4.115904e+09 | J14: 4.1189591e+09 | K14: 4187669091 | L14: 4.2389847e+09 | M14: 4.3553488e+09 | N14: 4.4689274e+09 | O14: 4.777266e+09 | P14: 4.8561686e+09 | Q14: 4.9767383e+09 | R14: 5.1654906e+09 | S14: 5.2846032e+09 | T14: 5284603210 | U14: 1.0616962e+10 | V14: 5.2867716e+09 | W14: 5.2813699e+09 | X14: 5.3863046e+09 | Y14: 5.3928834e+09 | Z14: 5.434176e+09 | AA14: 5.4835737e+09 | AB14: 5.7088185e+09 | AC14: 5.691086e+09 | AD14: 5.6936377e+09 | AE14: 5.7803049e+09 | AF14: 5.842582e+09 | AG14: 5.842582e+09 | AH14: 5.8312835e+09 | AI14: 5.7329808e+09 | AJ14: 5.7233535e+09 | AK14: 5.7738519e+09 | AL14: 5.7585449e+09 | AM14: 5.7748863e+09 | AN14: 5.7717548e+09 | AO14: 5.9352799e+09 | AP14: 5961879039 | AQ14: 5.9394012e+09 | AR14: 6.0948893e+09 | AS14: 6.3019321e+09 | AT14: 6239183746 | AU14: 6.2786665e+09 | AV14: 6.137941e+09 | AW14: 6.0968277e+09 | AX14: 6.0144043e+09 | AY14: 5.9504236e+09 | AZ14: 5.9946589e+09 | BA14: 6.0457836e+09 | BB14: 6.2984433e+09 | BC14: 6.4145722e+09 | BD14: 6.4977427e+09 | BE14: 6.5444039e+09 | BF14: 6.6411301e+09 | BG14: 6580599847 | BH14: 6.5020714e+09 | BI14: 6.4381125e+09 | BJ14: 6.4655145e+09 | BK14: 6.5669295e+09 | BL14: 6.6021417e+09 | BM14: 6.6720977e+09 | BN14: 6.7332468e+09 | BO14: 6.7508116e+09 | BP14: 6.8050678e+09 | BQ14: 7.0037444e+09 | BR14: 7.1347103e+09 | BS14: 7.3453139e+09 | BT14: 7345313859 | BU14: 7.2706676e+09 | BV14: 7.3079378e+09 | BW14: 7.5720804e+09 | BX14: 7.6981923e+09 | BY14: 7.7928833e+09 | BZ14: 7.8931031e+09 | CA14: 8.0072904e+09 | CB14: 8.1210119e+09 | CC14: 8.2589067e+09 | CD14: 8.3630602e+09 | CE14: 8.4539099e+09 | CF14: 8.6716295e+09 | CG14: 8683011938 | CH14: 8.6818253e+09 | CI14: 8.6896773e+09 | CJ14: 8.7666961e+09 | CK14: 8.8853504e+09 | CL14: 8.9216015e+09 | CM14: 9.0415623e+09 | CN14: 9.1130199e+09 | CO14: 9.2999382e+09 | CP14: 9.4379687e+09
A15: Allowance for Loan Loss | B15: 11491000 | C15: 17687000 | D15: 17687000 | E15: 27687316 | F15: 32687316 | G15: 47500000 | H15: 44687316 | I15: 55500000 | J15: 59500000 | K15: 63500000 | L15: 67500000 | M15: 71500000 | N15: 75500000 | O15: 79500000 | P15: 83500000 | Q15: 87500000 | R15: 91500000 | S15: 95500000 | T15: 95500000 | U15: 191000000 | V15: 105500000 | W15: 110500000 | X15: 115500000 | Y15: 120500000 | Z15: 125500000 | AA15: 130500000 | AB15: 135500000 | AC15: 140500000 | AD15: 145500000 | AE15: 150500000 | AF15: 155500000 | AG15: 155500000 | AH15: 164500000 | AI15: 173500000 | AJ15: 182500000 | AK15: 191500000 | AL15: 200500000 | AM15: 209500000 | AN15: 218500000 | AO15: 227500000 | AP15: 236500000 | AQ15: 245500000 | AR15: 254500000 | AS15: 263500000 | AT15: 267784035 | AU15: 272500000 | AV15: 281500000 | AW15: 292894330 | AX15: 302692440 | AY15: 312490550 | AZ15: 322288660 | BA15: 332086770 | BB15: 341884880 | BC15: 351682990 | BD15: 361481100 | BE15: 371279210 | BF15: 385361355 | BG15: 339861355 | BH15: 349861355 | BI15: 353261355 | BJ15: 359961355 | BK15: 366661355 | BL15: 373361355 | BM15: 380061355 | BN15: 386761355 | BO15: 393461355 | BP15: 400161355 | BQ15: 406861355 | BR15: 413561355 | BS15: 420261355 | BT15: 370261355 | BU15: 377765355 | BV15: 385269355 | BW15: 392773355 | BX15: 400277355 | BY15: 407781355 | BZ15: 415285355 | CA15: 422789355 | CB15: 430293355 | CC15: 437797355 | CD15: 437797355 | CE15: 437797355 | CF15: 437797355 | CG15: 407797355 | CH15: 411797355 | CI15: 413797355 | CJ15: 416797355 | CK15: 419797355 | CL15: 422797355 | CM15: 425797355 | CN15: 428797355 | CO15: 431797355 | CP15: 434797355
A16: Accounts Receivables | B16: =SUM(B17:B19) -> 0 | C16: =SUM(C17:C19) -> 0 | D16: =SUM(D17:D19) -> 0 | E16: =SUM(E17:E19) -> 0 | F16: =SUM(F17:F19) -> 0 | G16: =SUM(G17:G19) -> 0 | H16: =SUM(H17:H19) -> 0 | I16: =SUM(I17:I19) -> 0 | K16: 0 | L16: 0 | M16: 0 | N16: 0 | O16: 0 | P16: 0 | Q16: 0 | R16: 0 | S16: 0 | T16: 0 | U16: 0 | V16: 0 | W16: 0 | X16: 0 | Y16: 0 | Z16: 0 | AA16: 0 | AB16: 0 | AC16: 0 | AD16: 0 | AE16: 0 | AF16: 0 | AG16: 0 | AH16: 0 | AI16: 0 | AJ16: 0 | AK16: 0 | AL16: 0 | AM16: 0 | AN16: 0 | AO16: 0 | AP16: 0 | AQ16: 0 | AR16: 0 | AS16: 0 | AT16: 0 | AU16: 0 | AV16: 0 | AW16: 0 | AX16: 0 | AY16: 0 | AZ16: 0 | BA16: 0 | BB16: 0 | BC16: 0 | BD16: 0 | BE16: 0 | BF16: 0 | BG16: 0 | BH16: 0 | BI16: 0 | BJ16: 0 | BK16: 0 | BL16: 0 | BM16: 0 | BN16: 0 | BO16: 0 | BP16: 0 | BQ16: 0 | BR16: 0 | BS16: 0 | BT16: 0 | BU16: 0 | BV16: 0 | BW16: 0 | BX16: 0 | BY16: 0 | BZ16: 0 | CA16: 0 | CB16: 0 | CC16: 0 | CD16: 0 | CE16: 0 | CF16: 0 | CG16: 0 | CH16: 0 | CI16: 0 | CJ16: 0 | CK16: 0 | CL16: 0 | CM16: 0 | CN16: 0 | CO16: 0 | CP16: 0 | CQ16: 0 | CR16: 0 | CS16: 0 | CT16: 0 | CU16: 0
A17: Tax Recoverable | B17: 0 | H17: 0 | I17: 0 | J17: 0 | K17: 0 | L17: 0 | M17: 0 | N17: 0 | O17: 0 | P17: 0 | Q17: 0 | R17: 0 | S17: 0 | T17: 0 | U17: 0 | V17: 0 | W17: 0 | X17: 0 | Y17: 0 | Z17: 0 | AA17: 0 | AB17: 0 | AC17: 0 | AD17: 0 | AE17: 0 | AF17: 0 | AG17: 0 | AH17: 0 | AI17: 0 | AJ17: 0 | AK17: 0 | AL17: 0 | AM17: 0 | AN17: 0 | AO17: 0 | AP17: 0 | AQ17: 0 | AR17: 0 | AS17: 0 | AT17: 0 | AU17: 0 | AV17: 0 | AW17: 0 | AX17: 0 | AY17: 0 | AZ17: 0 | BA17: 0 | BB17: 0 | BC17: 0 | BD17: 0 | BE17: 0 | BF17: 0 | BG17: 0 | BH17: 0 | BI17: 0 | BJ17: 0 | BK17: 0 | BL17: 0 | BM17: 0 | BN17: 0 | BO17: 0 | BP17: 0 | BQ17: 0 | BR17: 0 | BS17: 0 | BU17: 0 | BV17: 0 | BW17: 0 | BX17: 0 | BY17: 0 | BZ17: 0 | CA17: 0 | CB17: 0 | CC17: 0 | CD17: 0 | CE17: 0 | CF17: 0 | CH17: 0 | CI17: 0 | CJ17: 0 | CK17: 0 | CL17: 0 | CM17: 0 | CN17: 0 | CO17: 0 | CP17: 0
A18: Deferred Tax Assets | B18: 0 | H18: 0 | I18: 0 | J18: 0 | K18: 0 | L18: 0 | M18: 0 | N18: 0 | O18: 0 | P18: 0 | Q18: 0 | R18: 0 | S18: 0 | T18: 0 | U18: 0 | V18: 0 | W18: 0 | X18: 0 | Y18: 0 | Z18: 0 | AA18: 0 | AB18: 0 | AC18: 0 | AD18: 0 | AE18: 0 | AF18: 0 | AG18: 0 | AH18: 0 | AI18: 0 | AJ18: 0 | AK18: 0 | AL18: 0 | AM18: 0 | AN18: 0 | AO18: 0 | AP18: 0 | AQ18: 0 | AR18: 0 | AS18: 0 | AT18: 0 | AU18: 0 | AV18: 0 | AW18: 0 | AX18: 0 | AY18: 0 | AZ18: 0 | BA18: 0 | BB18: 0 | BC18: 0 | BD18: 0 | BE18: 0 | BF18: 0 | BG18: 0 | BH18: 0 | BI18: 0 | BJ18: 0 | BK18: 0 | BL18: 0 | BM18: 0 | BN18: 0 | BO18: 0 | BP18: 0 | BQ18: 0 | BR18: 0 | BS18: 0 | BU18: 0 | BV18: 0 | BW18: 0 | BX18: 0 | BY18: 0 | BZ18: 0 | CA18: 0 | CB18: 0 | CC18: 0 | CD18: 0 | CE18: 0 | CF18: 0 | CH18: 0 | CI18: 0 | CJ18: 0 | CK18: 0 | CL18: 0 | CM18: 0 | CN18: 0 | CO18: 0 | CP18: 0
A19: Retirement Benefit Assets | B19: 0 | H19: 0 | I19: 0 | J19: 0 | K19: 0 | L19: 0 | M19: 0 | N19: 0 | O19: 0 | P19: 0 | Q19: 0 | R19: 0 | S19: 0 | T19: 0 | U19: 0 | V19: 0 | W19: 0 | X19: 0 | Y19: 0 | Z19: 0 | AA19: 0 | AB19: 0 | AC19: 0 | AD19: 0 | AE19: 0 | AF19: 0 | AG19: 0 | AH19: 0 | AI19: 0 | AJ19: 0 | AK19: 0 | AL19: 0 | AM19: 0 | AN19: 0 | AO19: 0 | AP19: 0 | AQ19: 0 | AR19: 0 | AS19: 0 | AT19: 0 | AU19: 0 | AV19: 0 | AW19: 0 | AX19: 0 | AY19: 0 | AZ19: 0 | BA19: 0 | BB19: 0 | BC19: 0 | BD19: 0 | BE19: 0 | BF19: 0 | BG19: 0 | BH19: 0 | BI19: 0 | BJ19: 0 | BK19: 0 | BL19: 0 | BM19: 0 | BN19: 0 | BO19: 0 | BP19: 0 | BQ19: 0 | BR19: 0 | BS19: 0 | BU19: 0 | BV19: 0 | BW19: 0 | BX19: 0 | BY19: 0 | BZ19: 0 | CA19: 0 | CB19: 0 | CC19: 0 | CD19: 0 | CE19: 0 | CF19: 0 | CH19: 0 | CI19: 0 | CJ19: 0 | CK19: 0 | CL19: 0 | CM19: 0 | CN19: 0 | CO19: 0 | CP19: 0
A20: Property & Equipment & Other assets | B20: =SUM(B21:B25) -> 30561000 | C20: =SUM(C21:C25) -> 172627000 | D20: =SUM(D21:D25) -> 36204000 | E20: =SUM(E21:E25) -> 51908954 | F20: =SUM(F21:F25) -> 83695847 | G20: =SUM(G21:G25) -> 103160569 | H20: =SUM(H21:H25) -> 2.8750153e+08 | I20: =SUM(I21:I25) -> 2.83721e+08 | ... CU20: =SUM(CU21:CU25) -> 0
A21: Investment Properties | B21: 0 | C21: 140256000 | H21: 0 | I21: 0 | J21: 0 | L21: 0 | M21: 0 | N21: 0 | O21: 0 | P21: 0 | Q21: 0 | R21: 0 | S21: 0 | T21: 0 | U21: 0 | V21: 0 | W21: 4.9494235e+08 | X21: 4.9494235e+08 | Y21: 5.2679428e+08 | Z21: 5.3538136e+08 | AA21: 5.3539136e+08 | AB21: 5.3731034e+08 | AC21: 5.7373003e+08 | AD21: 5.7720249e+08 | AE21: 5.8117958e+08 | AF21: 6.3502798e+08 | AG21: 6.3502798e+08 | AH21: 6.3765069e+08 | AI21: 6.4408747e+08 | AJ21: 6.4463607e+08 | AK21: 6.4463607e+08 | AL21: 6.4463607e+08 | AM21: 6.4740434e+08 | AN21: 6.4748996e+08 | AO21: 6.4748996e+08 | AP21: 6.4748996e+08 | AQ21: 6.4748996e+08 | AR21: 6.4748996e+08 | AS21: 6.4748996e+08 | AT21: 635027979 | AU21: 6.4748996e+08 | AV21: 6.4805496e+08 | AW21: 6.4805496e+08 | AX21: 6.4805496e+08 | AY21: 6.4805496e+08 | AZ21: 6.4805496e+08 | BA21: 6.3559298e+08 | BB21: 6.3559298e+08 | BC21: 6.3559298e+08 | BD21: 6.3609298e+08 | BE21: 6.4141385e+08 | BF21: 6.4353054e+08 | BG21: 641578411 | BH21: 6.4157841e+08 | BI21: 6.4157841e+08 | BJ21: 6.4157841e+08 | BK21: 6.4157841e+08 | BL21: 6.4157841e+08 | BM21: 6.4903683e+08 | BN21: 6.4955616e+08 | BO21: 6.4955616e+08 | BP21: 6.4955616e+08 | BQ21: 6.4955616e+08 | BR21: 6.4955616e+08 | BS21: 6.4955616e+08 | BT21: 649556155 | BU21: 6.4955616e+08 | BV21: 6.4955616e+08 | BW21: 6.4955616e+08 | BX21: 6.4955616e+08 | BY21: 6.4955616e+08 | BZ21: 6.4955616e+08 | CA21: 6.4955616e+08 | CB21: 6.5491228e+08 | CC21: 6.4955616e+08 | CD21: 6.4955616e+08 | CE21: 6.4955616e+08 | CF21: 6.4955616e+08 | CG21: 734528001 | CH21: 6.4955616e+08 | CI21: 6.4955616e+08 | CJ21: 6.4955616e+08 | CK21: 6.4955616e+08 | CL21: 6.4955616e+08 | CM21: 6.4955616e+08 | CN21: 6.4955616e+08 | CO21: 6.4955616e+08 | CP21: 6.4955616e+08
A22: Property & Equipment | B22: 30561000 | C22: 32371000 | D22: 36204000 | E22: 51908954 | F22: 69245464 | G22: 103160569 | H22: 2.8750153e+08 | I22: 2.5621178e+08 | J22: 2.836322e+08 | K22: 3.0235245e+08 | L22: 3.2550446e+08 | M22: 3.6390347e+08 | N22: 3.9684084e+08 | O22: 4.3942418e+08 | P22: 4.6937879e+08 | Q22: 5.2098278e+08 | R22: 5.2715923e+08 | S22: 5.524183e+08 | T22: 551045563 | U22: 1.177155e+09 | V22: 5.9187039e+08 | W22: 97838612 | X22: 97823012 | Y22: 97823012 | Z22: 98614052 | AA22: 1.0142069e+08 | AB22: 99101594 | AC22: 1.0062143e+08 | AD22: 1.0083453e+08 | AE22: 1.0078453e+08 | AF22: 1.0048976e+08 | AG22: 74914831 | AH22: 1.0677359e+08 | AI22: 75120154 | AJ22: 75626219 | AK22: 75642294 | AL22: 84050272 | AM22: 84850772 | AN22: 90161580 | AO22: 91622440 | AP22: 92450582 | AQ22: 92533610 | AR22: 93359518 | AS22: 97960048 | AT22: 77497991 | AU22: 99659474 | AV22: 67373440 | AW22: 68643250 | AX22: 71617514 | AY22: 79765990 | AZ22: 81086010 | BA22: 95933663 | BB22: 97750558 | BC22: 98303343 | BD22: 1.0099088e+08 | BE22: 1.0221091e+08 | BF22: 1.0418958e+08 | BG22: 71351099 | BH22: 1.0617915e+08 | BI22: 74272961 | BJ22: 79418054 | BK22: 80346109 | BL22: 83165372 | BM22: 83407051 | BN22: 83790881 | BO22: 85758421 | BP22: 89870120 | BQ22: 90303137 | BR22: 90467230 | BS22: 91361770 | BT22: 70645484 | BU22: 72251980 | BV22: 72342272 | BW22: 73596129 | BX22: 74630897 | BY22: 87816701 | BZ22: 90110696 | CA22: 94096976 | CB22: 96503426 | CC22: 1.0162697e+08 | CD22: 1.0649072e+08 | CE22: 1.1061685e+08 | CF22: 1.1089234e+08 | CG22: 90247140 | CH22: 92616666 | CI22: 99499734 | CJ22: 1.0069273e+08 | CK22: 1.0282611e+08 | CL22: 1.0329998e+08 | CM22: 1.0802566e+08 | CN22: 1.0889217e+08 | CO22: 1.0968867e+08 | CP22: 1.1162517e+08
A23: Prepaid Lease rentals | B23: 0 | H23: 0 | I23: 0 | J23: 0 | L23: 0 | M23: 0 | N23: 0 | O23: 0 | P23: 0 | Q23: 0 | R23: 0 | S23: 0 | U23: 0 | V23: 0 | W23: 0 | X23: 0 | Y23: 0 | Z23: 0 | AA23: 0 | AB23: 0 | AC23: 2415000 | AD23: 2415000 | AE23: 2415000 | AF23: 2415000 | AH23: 2415000 | AI23: 2415000 | AJ23: 2415000 | AK23: 2415000 | AL23: 2415000 | AM23: 2415000 | AN23: 2415000 | AO23: 2415000 | AP23: 2415000 | AQ23: 2415000 | AR23: 2415000 | AS23: 2415000 | AT23: 0 | AU23: 2595000 | AV23: 2595000 | AW23: 2595000 | AX23: 2608200 | AY23: 2608200 | AZ23: 2608200 | BA23: 2608200 | BB23: 2608200 | BC23: 2620000 | BD23: 2620000 | BE23: 2620000 | BF23: 2620000 | BG23: 0 | BH23: 2620000 | BI23: 2620000 | BJ23: 2620000 | BK23: 2620000 | BL23: 2620000 | BM23: 2620000 | BN23: 2620000 | BO23: 2620000 | BP23: 2620000 | BQ23: 2620000 | BR23: 2620000 | BS23: 2620000 | BU23: 2620000 | BV23: 2620000 | BW23: 2620000 | BX23: 2620000 | BY23: 2620000 | BZ23: 2620000 | CA23: 2620000 | CB23: 2620000 | CC23: 2620000 | CD23: 2620000 | CE23: 2620000 | CF23: 2620000 | CH23: 2620000 | CI23: 2620000 | CJ23: 2620000 | CK23: 2620000 | CL23: 3370000 | CM23: 3370000 | CN23: 3370000 | CO23: 2920000 | CP23: 2920000
A24: Intangible Assets | B24: 0 | F24: 14450383 | H24: 0 | I24: 27509216 | J24: 27509216 | K24: 27509216 | L24: 27509216 | M24: 27509216 | N24: 28147216 | O24: 28147216 | P24: 28147216 | Q24: 28147216 | R24: 28161716 | S24: 28161716 | T24: 22007373 | U24: 56323432 | V24: 22659874 | W24: 22659874 | X24: 0 | Y24: 0 | Z24: 0 | AA24: 0 | AB24: 22659874 | AC24: 22659874 | AD24: 22659874 | AE24: 22659874 | AF24: 22659874 | AG24: 17605898 | AH24: 22659874 | AI24: 18258399 | AJ24: 18258399 | AK24: 18258399 | AL24: 18258399 | AM24: 18258399 | AN24: 18258399 | AO24: 18258399 | AP24: 18258399 | AQ24: 18258399 | AR24: 18258399 | AS24: 18258399 | AT24: 18498997 | AU24: 18258399 | AV24: 30161999 | AW24: 30161999 | AX24: 30161999 | AY24: 22076799 | AZ24: 22076799 | BA24: 22076799 | BB24: 22076799 | BC24: 23246399 | BD24: 28196415 | BE24: 28130295 | BF24: 28370893 | BG24: 23460394 | BH24: 28370893 | BI24: 23460694 | BJ24: 23460694 | BK24: 23460694 | BL24: 23460694 | BM24: 23460694 | BN24: 23460694 | BO24: 23662344 | BP24: 23662344 | BQ24: 23675294 | BR24: 23675294 | BS24: 25484764 | BT24: 20387812 | BU24: 20387812 | BV24: 20387812 | BW24: 20847232 | BX24: 20861612 | BY24: 23241492 | BZ24: 25148854 | CA24: 34138749 | CB24: 41760456 | CC24: 42016628 | CD24: 42016628 | CE24: 44372100 | CF24: 45073695 | CG24: 36058956 | CH24: 37258306 | CI24: 38463276 | CJ24: 39399096 | CK24: 40895475 | CL24: 41690372 | CM24: 42947602 | CN24: 42969422 | CO24: 44127014 | CP24: 44127014
A25: Other Assets | B25: 0 | H25: 0 | I25: 0 | J25: 0 | L25: 0 | M25: 0 | N25: 0 | O25: 0 | P25: 0 | Q25: 0 | R25: 0 | S25: 0 | U25: 0 | V25: 0 | W25: 0 | X25: 22659874 | Y25: 22659874 | Z25: 22659874 | AA25: 22659874 | AB25: 0 | AC25: 0 | AD25: 0 | AE25: 0 | AF25: 0 | AG25: 0 | AH25: 0 | AI25: 0 | AJ25: 0 | AK25: 0 | AL25: 0 | AM25: 0 | AN25: 0 | AO25: 0 | AP25: 0 | AQ25: 0 | AR25: 0 | AS25: 0 | AT25: 0 | AU25: 0 | AV25: 0 | AW25: 0 | AX25: 0 | AY25: 0 | AZ25: 0 | BA25: 0 | BB25: 0 | BC25: 0 | BD25: 0 | BE25: 0 | BF25: 0 | BG25: 0 | BH25: 0 | BI25: 0 | BJ25: 0 | BK25: 0 | BL25: 0 | BM25: 0 | BN25: 0 | BO25: 0 | BP25: 0 | BQ25: 0 | BR25: 0 | BS25: 0 | BU25: 0 | BV25: 0 | BW25: 0 | BX25: 0 | BY25: 0 | BZ25: 0 | CA25: 0 | CB25: 0 | CC25: 0 | CD25: 0 | CE25: 0 | CF25: 0 | CH25: 0 | CI25: 0 | CJ25: 0 | CK25: 0 | CL25: 0 | CM25: 0 | CN25: 0 | CO25: 0 | CP25: 0
A26: Total Assets | B26: =B4+B7+B8+B13+B16+B20 -> 1982931000 | C26: =C4+C7+C8+C13+C16+C20 -> 2246183000 | D26: =D4+D7+D8+D13+D16+D20 -> 2.8343649e+09 | E26: =E4+E7+E8+E13+E16+E20 -> 3283953220 | F26: =F4+F7+F8+F13+F16+F20 -> 3926234298 | G26: =G4+G7+G8+G13+G16+G20 -> 4877108727 | H26: =H4+H7+H8+H13+H16+H20 -> 4.9539748e+09 | I26: =I4+I7+I8+I13+I16+I20 -> 4.8668645e+09 | ... CT26: =CT4+CT7+CT8+CT13+CT16+CT20 -> 0
A27: LIABILITIES
A28: Savings Deposits - Withdrawable deposits - FOSA) | B28: 231784000 | C28: 295250000 | D28: =255216000+25824000 -> 281040000 | E28: =340104982+130154418 -> 470259400 | F28: =802585086-93508240 -> 709076846 | G28: =1039952796-169467928 -> 870484868 | H28: 6.6357237e+08 | I28: 8.575616e+08 | J28: 7.7867401e+08 | K28: 7.060101e+08 | L28: 6.7478755e+08 | M28: 7.552045e+08 | N28: 7.7449626e+08 | O28: 7.9182659e+08 | P28: 7.5439305e+08 | Q28: 8.0076958e+08 | R28: 8.3889495e+08 | S28: 8.4638712e+08 | T28: =845689214+166870517 -> 1012559731 | U28: 1.6496088e+09 | V28: 1.0727991e+09 | W28: 9.4118713e+08 | X28: 8.6361089e+08 | Y28: 9.002975e+08 | Z28: 9.0060125e+08 | AA28: 9.3175511e+08 | AB28: 8.4087444e+08 | AC28: 8.3669399e+08 | AD28: 8.3986133e+08 | AE28: 8.4478993e+08 | AF28: 8.668944e+08 | AG28: 1113131850 | AH28: 8.6981707e+08 | AI28: 1.102212e+09 | AJ28: 1.0171218e+09 | AK28: 9.6083387e+08 | AL28: 9.380954e+08 | AM28: 9.4614015e+08 | AN28: 1.0240645e+09 | AO28: 9.8244957e+08 | AP28: 9.9483811e+08 | AQ28: 1.0567557e+09 | AR28: 1.0210911e+09 | AS28: 1068718094 | AT28: 1044401969 | AU28: 1.0521322e+09 | AV28: 1.3766238e+09 | AW28: 1.2156317e+09 | AX28: 1.2599495e+09 | AY28: 1.1935774e+09 | AZ28: 1.2446125e+09 | BA28: 1.2592962e+09 | BB28: 1.264537e+09 | BC28: 1.2404931e+09 | BD28: 1.2234482e+09 | BE28: 1.169445e+09 | BF28: 1.2613943e+09 | BG28: 1316646547 | BH28: 1.7206967e+09 | BI28: 1.4714235e+09 | BJ28: 1.4081926e+09 | BK28: 1.3907992e+09 | BL28: 1.341004e+09 | BM28: 1.2897406e+09 | BN28: 1.4478553e+09 | BO28: 1.3999098e+09 | BP28: 1.4313115e+09 | BQ28: 1.4525743e+09 | BR28: 1.4483924e+09 | BS28: 1.4712819e+09 | BT28: 1523215887 | BU28: 1.8941279e+09 | BV28: 1.7348896e+09 | BW28: 1.6771324e+09 | BX28: 1.5595995e+09 | BY28: 1.5778586e+09 | BZ28: 1.561895e+09 | CA28: 1.6404028e+09 | CB28: 1.5805744e+09 | CC28: 1489211113 | CD28: 1.4624322e+09 | CE28: 1.4635855e+09 | CF28: 1.4940718e+09 | CG28: 1551178695 | CH28: 1.9093209e+09 | CI28: 1.7405702e+09 | CJ28: 1.6352992e+09 | CK28: 1.5956036e+09 | CL28: 1.5321929e+09 | CM28: 1.5704042e+09 | CN28: 1.6421796e+09 | CO28: 1.6497224e+09 | CP28: 1.5199615e+09
A29: Short Term Deposits (e.g Fixed deposits, special savings) | B29: 0 | D29: 108217000 | E29: =38697335+57549083 -> 96246418 | F29: 93508240 | G29: 169467928 | H29: 0 | I29: 0 | J29: 0 | L29: 0 | M29: 0 | N29: 0 | O29: 0 | P29: 0 | Q29: 0 | R29: 0 | S29: 0 | T29: =270087385+89041333 -> 359128718 | U29: 0 | V29: 0 | W29: 0 | X29: 0 | Y29: 0 | Z29: 0 | AA29: 0 | AB29: 86459308 | AC29: 82037207 | AD29: 79915724 | AE29: 80054724 | AF29: 75425724 | AG29: 533621828 | AH29: 77358930 | AI29: 68838930 | AJ29: 74228892 | AK29: 71089475 | AL29: 64596429 | AM29: 64591175 | AN29: 56203245 | AO29: 61315274 | AP29: 60074267 | AQ29: 64427021 | AR29: 63457017 | AS29: 63217017 | AT29: =530439545+263432355 -> 793871900 | AU29: 62933136 | AV29: 61358589 | AW29: 56554589 | AX29: 60378565 | AY29: 63495458 | AZ29: 63845458 | BA29: 62675444 | BB29: 61279222 | BC29: 60430222 | BD29: 61920222 | BE29: 59820222 | BF29: 55252222 | BG29: 0 | BH29: 56232222 | BI29: 57752222 | BJ29: 57564000 | BK29: 59752000 | BL29: 58365000 | BM29: 58911000 | BN29: 61095000 | BO29: 61196000 | BP29: 61551000 | BQ29: 61607000 | BR29: 56474000 | BS29: 51934000 | BU29: 48428403 | BV29: 45108403 | BW29: 45572403 | BX29: 43641000 | BY29: 48173000 | BZ29: 50473000 | CA29: 47043000 | CB29: 46588000 | CC29: 42338000 | CD29: 44077000 | CE29: 48630000 | CF29: 45725500 | CG29: 45725500 | CH29: 44396500 | CI29: 45396500 | CJ29: 45875200 | CK29: 40937200 | CL29: 39337200 | CM29: 90553000 | CN29: 91688000 | CO29: 86488000 | CP29: 85740000
A30: Non withdrawable deposits (BOSA member deposits) | B30: 1309041000 | C30: 1412967000 | D30: 1638628000 | E30: 1909635651 | F30: 2204621249 | G30: 2548520382 | H30: 2.9156687e+09 | I30: 2.9495685e+09 | J30: 3.0007471e+09 | K30: 3.0380822e+09 | L30: 3.0861625e+09 | M30: 3.1380294e+09 | N30: 3.174952e+09 | O30: 3.2314918e+09 | P30: 3.2763935e+09 | Q30: 3.3255117e+09 | R30: 3.3845389e+09 | S30: 3.416673e+09 | T30: 2979715072 | U30: 6.9472519e+09 | V30: 3.5310138e+09 | W30: 3.60518e+09 | X30: 3.6557248e+09 | Y30: 3.691673e+09 | Z30: 3.7470154e+09 | AA30: 3792366999 | AB30: 3.8408767e+09 | AC30: 3.8878325e+09 | AD30: 3.9460004e+09 | AE30: 3.9983527e+09 | AF30: 4.0332867e+09 | AG30: 3488295940 | AH30: 4.0911833e+09 | AI30: 4.3025887e+09 | AJ30: 4.3850462e+09 | AK30: 4.4128937e+09 | AL30: 4.4659512e+09 | AM30: 4.5123082e+09 | AN30: 4.5719484e+09 | AO30: 4.6394924e+09 | AP30: 4.6684274e+09 | AQ30: 4.7263117e+09 | AR30: 4.8187225e+09 | AS30: 4.8409901e+09 | AT30: 4134637410 | AU30: 4.8964286e+09 | AV30: 4.9461011e+09 | AW30: 5.0269878e+09 | AX30: 5.0858533e+09 | AY30: 5.1520075e+09 | AZ30: 5.1376724e+09 | BA30: 5.2235408e+09 | BB30: 5.2921537e+09 | BC30: 5.3367628e+09 | BD30: 5.3972264e+09 | BE30: 5.4607011e+09 | BF30: 5.4588113e+09 | BG30: 5458811312 | BH30: 5.528779e+09 | BI30: 5.6168593e+09 | BJ30: 5.6963139e+09 | BK30: 5.7586531e+09 | BL30: 5.8313061e+09 | BM30: 5.9038546e+09 | BN30: 6.0007245e+09 | BO30: 6.033339e+09 | BP30: 6.1115931e+09 | BQ30: 6.1962111e+09 | BR30: 6.2735678e+09 | BS30: 6.3162116e+09 | BT30: 6316211595 | BU30: 6.3922039e+09 | BV30: 6.4861692e+09 | BW30: 6.565832e+09 | BX30: 6.6712638e+09 | BY30: 6.7841946e+09 | BZ30: 6.8547903e+09 | CA30: 6.9696178e+09 | CB30: 7.0611481e+09 | CC30: 7.1453804e+09 | CD30: 7.2443676e+09 | CE30: 7.3269811e+09 | CF30: 7.3573529e+09 | CG30: =7357287925-CG29 -> 7311562425 | CH30: 7.4246863e+09 | CI30: 7.5066947e+09 | CJ30: 7.5890967e+09 | CK30: 7.6886922e+09 | CL30: 7.7922286e+09 | CM30: 7.9237572e+09 | CN30: 8.0790294e+09 | CO30: 8.2095667e+09 | CP30: 8.3161393e+09
A31: Total Deposit liabilities | B31: =SUM(B28:B30) -> 1540825000 | C31: =SUM(C28:C30) -> 1708217000 | D31: =SUM(D28:D30) -> 2027885000 | E31: =SUM(E28:E30) -> 2476141469 | F31: =SUM(F28:F30) -> 3007206335 | G31: =SUM(G28:G30) -> 3588473178 | H31: =SUM(H28:H30) -> 3.5792411e+09 | I31: =SUM(I28:I30) -> 3.8071301e+09 | ... CT31: =SUM(CT28:CT30) -> 0
A32: Accounts Payable & Other Liabilities | B32: =SUM(B33:B38) -> 56399000 | C32: =SUM(C33:C38) -> 273714000 | D32: =SUM(D33:D38) -> 11930000 | E32: =SUM(E33:E38) -> 278665461 | F32: =SUM(F33:F38) -> 3.5486019e+08 | G32: =SUM(G33:G38) -> 612597954 | H32: =SUM(H33:H38) -> 6.6680284e+08 | I32: =SUM(I33:I38) -> 4.0464208e+08 | ... CT32: =SUM(CT33:CT38) -> 0
A33: Tax Payable | B33: 296000 | C33: 627000 | D33: 542000 | E33: 4130450 | F33: 2596929.8 | G33: -561286 | H33: 0 | I33: 0 | J33: 0 | L33: 0 | M33: 0 | N33: 0 | O33: 0 | P33: 0 | Q33: 0 | R33: 0 | S33: 0 | T33: 1103303 | U33: 0 | V33: 0 | W33: 0 | X33: 0 | Y33: 0 | Z33: 0 | AA33: 0 | AB33: 0 | AC33: 0 | AD33: 0 | AE33: 0 | AF33: 0 | AG33: 2484330 | AH33: 0 | AI33: 95000000 | AJ33: 0 | AK33: 190000000 | AL33: 0 | AM33: 0 | AN33: 0 | AO33: 0 | AP33: 0 | AQ33: 0 | AR33: 0 | AS33: 0 | AT33: 3125556 | AU33: 0 | AV33: 0 | AW33: 0 | AX33: 0 | AY33: 0 | AZ33: 0 | BA33: 0 | BB33: 0 | BC33: 0 | BD33: 0 | BE33: 0 | BF33: 0 | BG33: 10285340 | BH33: 0 | BI33: 0 | BJ33: 0 | BK33: 0 | BL33: 0 | BM33: 0 | BN33: 0 | BO33: 0 | BP33: 0 | BQ33: 0 | BR33: 0 | BS33: 0 | BT33: 5625813 | BU33: 0 | BV33: 0 | BW33: 0 | BX33: 0 | BY33: 0 | BZ33: 0 | CA33: 0 | CB33: 0 | CC33: 0 | CD33: 0 | CE33: 0 | CF33: 0 | CG33: 14525411 | CH33: 0 | CI33: 0 | CJ33: 0 | CK33: 0 | CL33: 0 | CM33: 0 | CN33: 0 | CO33: 0 | CP33: 0
A34: Dividends Payable | B34: 0 | C34: 175761000 | H34: 0 | I34: 0 | J34: 0 | L34: 0 | M34: 0 | N34: 0 | O34: 0 | P34: 0 | Q34: 0 | R34: 0 | S34: 0 | U34: 0 | V34: 0 | W34: 0 | X34: 0 | Y34: 0 | Z34: 0 | AA34: 0 | AB34: 321600000 | AC34: 321600000 | AD34: 402000000 | AE34: 442200000 | AF34: 482400000 | AH34: 527400000 | AI34: 0 | AJ34: 142500000 | AK34: 0 | AL34: 237500000 | AM34: 285000000 | AN34: 332500000 | AO34: 380000000 | AP34: 427500000 | AQ34: 475000000 | AR34: 522500000 | AS34: 570000000 | AT34: 564645701 | AU34: 617500000 | AV34: 62051444 | AW34: 150000000 | AX34: 200000000 | AY34: 250000000 | AZ34: 300000000 | BA34: 350000000 | BB34: 400000000 | BC34: 450000000 | BD34: 500000000 | BE34: 550000000 | BF34: 600000000 | BG34: 645500000 | BH34: 55000000 | BI34: 120000000 | BJ34: 180000000 | BK34: 240000000 | BL34: 300000000 | BM34: 360000000 | BN34: 420000000 | BO34: 480000000 | BP34: 540000000 | BQ34: 600000000 | BR34: 660000000 | BS34: 720000000 | BT34: 764541806 | BU34: 76666667 | BV34: 153333334 | BW34: 230000001 | BX34: 306666668 | BY34: 383333335 | BZ34: 460000002 | CA34: 536666669 | CB34: 613333336 | CC34: 690000000 | CD34: 7.6666667e+08 | CE34: 843333334 | CF34: 920000000 | CG34: 904946415 | CH34: 92000000 | CI34: 184000000 | CJ34: 271912217 | CK34: 351648868 | CL34: 439561085 | CM34: 527473302 | CN34: 615385519 | CO34: 703297736 | CP34: 791209953
A35: Deferred Tax Liability | B35: 0 | H35: 0 | I35: 0 | J35: 0 | L35: 0 | M35: 0 | N35: 0 | O35: 0 | P35: 0 | Q35: 0 | R35: 0 | S35: 0 | T35: 0 | U35: 0 | V35: 0 | W35: 0 | X35: 0 | Y35: 0 | Z35: 0 | AA35: 0 | AB35: 0 | AC35: 0 | AD35: 0 | AE35: 0 | AF35: 0 | AH35: 0 | AI35: 0 | AJ35: 0 | AK35: 0 | AL35: 0 | AM35: 0 | AN35: 0 | AO35: 0 | AP35: 0 | AQ35: 0 | AR35: 0 | AS35: 0 | AT35: 0 | AU35: 0 | AV35: 0 | AW35: 0 | AX35: 0 | AY35: 0 | AZ35: 0 | BA35: 0 | BB35: 0 | BC35: 0 | BD35: 0 | BE35: 0 | BF35: 0 | BG35: 0 | BH35: 0 | BI35: 0 | BJ35: 0 | BK35: 0 | BL35: 0 | BM35: 0 | BN35: 0 | BO35: 0 | BP35: 0 | BQ35: 0 | BR35: 0 | BS35: 0 | BU35: 0 | BV35: 0 | BW35: 0 | BX35: 0 | BY35: 0 | BZ35: 0 | CA35: 0 | CB35: 0 | CC35: 0 | CD35: 0 | CE35: 0 | CF35: 0 | CH35: 0 | CI35: 0 | CJ35: 0 | CK35: 0 | CL35: 0 | CM35: 0 | CN35: 0 | CO35: 0 | CP35: 0
A36: Retirement Benefits Liability | B36: 0 | H36: 17393917 | I36: 19393917 | J36: 20393917 | K36: 21393917 | L36: 22393917 | M36: 6737962.1 | N36: 7737962.1 | O36: 3334753 | P36: 4334753 | Q36: 4334753 | R36: 4334753 | S36: 3334753 | U36: 4669506 | V36: 2643761 | W36: 2643761 | X36: 2643761 | Y36: 2643761 | Z36: 2643761 | AA36: 3643761 | AB36: 1643761 | AC36: 643761.02 | AD36: 1643761 | AE36: 1643761 | AF36: 643761.02 | AH36: 643761.02 | AI36: 643761.02 | AJ36: 643761.02 | AK36: 1643761 | AL36: 643761.02 | AM36: 862924.22 | AN36: 0 | AO36: 0 | AP36: 0 | AQ36: 0 | AR36: 0 | AS36: 0 | AT36: 0 | AU36: 0 | AV36: 0 | AW36: 0 | AX36: 0 | AY36: 0 | AZ36: 0 | BA36: 0 | BB36: 0 | BC36: 0 | BD36: 0 | BE36: 0 | BF36: 0 | BG36: 0 | BH36: 0 | BI36: 0 | BJ36: 0 | BK36: 0 | BL36: 0 | BM36: 0 | BN36: 0 | BO36: 0 | BP36: 0 | BQ36: 0 | BR36: 0 | BS36: 0 | BU36: 0 | BV36: 0 | BW36: 0 | BX36: 0 | BY36: 0 | BZ36: 0 | CA36: 0 | CB36: 0 | CC36: 0 | CD36: 0 | CE36: 0 | CF36: 0 | CH36: 0 | CI36: 0 | CJ36: 0 | CK36: 0 | CL36: 0 | CM36: 0 | CN36: 0 | CO36: 0 | CP36: 0
A37: Other Liabilities | B37: 6936000 | C37: =88420000+8906000 -> 97326000 | D37: =155000+12000+17000+27000+806000+8552000+36000+477000+121000+1185000 -> 11388000 | E37: =251475140+23059871 -> 274535011 | F37: =306347796+45915461 -> 352263257 | G37: =87213374+342612533 -> 429825907 | H37: 4.6607559e+08 | I37: 2.185815e+08 | J37: 2.5232542e+08 | K37: 2.9773305e+08 | L37: 3.2547814e+08 | M37: 3.7017674e+08 | N37: 4.1080733e+08 | O37: 4.5603781e+08 | P37: 5.0020308e+08 | Q37: 5.452702e+08 | R37: 590240855 | S37: 6.3141081e+08 | T37: =67893441+374569299 -> 442462740 | U37: 1.2667611e+09 | V37: 2.6878764e+08 | W37: 3.2286135e+08 | X37: 3.7643395e+08 | Y37: 4.0061704e+08 | Z37: 4.2638194e+08 | AA37: 4.8341306e+08 | AB37: 2.0696278e+08 | AC37: 2.37707e+08 | AD37: 2.0831584e+08 | AE37: 2.2407055e+08 | AF37: 2.3147792e+08 | AG37: =83043250+468684234 -> 551727484 | AH37: 2.4417613e+08 | AI37: 89946581 | AJ37: 1.0978236e+08 | AK37: 84100921 | AL37: 93554185 | AM37: 1.1078147e+08 | AN37: 1.0719783e+08 | AO37: 1.2529733e+08 | AP37: 1.4247191e+08 | AQ37: 1.5856674e+08 | AR37: 1.7603689e+08 | AS37: 1.3846716e+08 | AT37: 88124106 | AU37: 1.537726e+08 | AV37: 1.4891903e+08 | AW37: 1.0519672e+08 | AX37: 75459348 | AY37: 82006126 | AZ37: 93418760 | BA37: 86477155 | BB37: 94568826 | BC37: 97172933 | BD37: 1.0372597e+08 | BE37: 1.1072696e+08 | BF37: 1.1231847e+08 | BG37: =18872704+82534142+1500000 -> 102906846 | BH37: 1.2212012e+08 | BI37: 92602416 | BJ37: 92016796 | BK37: 68006373 | BL37: 73655597 | BM37: 79738053 | BN37: 76219978 | BO37: 86913229 | BP37: 1.0410044e+08 | BQ37: 1.2150464e+08 | BR37: 1.4287154e+08 | BS37: 1.5560798e+08 | BT37: =7010120+93875670+1800000 -> 102685790 | BU37: 91291615 | BV37: 95571669 | BW37: 70599495 | BX37: 85385286 | BY37: 1.0529991e+08 | BZ37: 1.12859e+08 | CA37: 1.1411713e+08 | CB37: 1.2570592e+08 | CC37: 1.3677807e+08 | CD37: 1.5040582e+08 | CE37: 1.6536768e+08 | CF37: 89295345 | CG37: =1017976559-CG34+19404423 -> 132434567 | CH37: 1.1732018e+08 | CI37: 1.2204532e+08 | CJ37: 88444346 | CK37: 1.0082471e+08 | CL37: 1.0613773e+08 | CM37: 1.224506e+08 | CN37: 1.0843725e+08 | CO37: 1.2167381e+08 | CP37: 1.2742136e+08
A38: External Borrowings | B38: 49167000 | G38: 183333333 | H38: 183333333 | I38: 166666666 | J38: 166666666 | K38: 166666666 | L38: 166666666 | M38: 349999999 | N38: 349999999 | O38: 433333332 | P38: 5.2291667e+08 | Q38: 6.1875e+08 | R38: 5.875e+08 | S38: 5.7708333e+08 | T38: 577083332 | U38: 1.1333333e+09 | V38: 5.3958333e+08 | W38: 5.2916666e+08 | X38: 5.1875e+08 | Y38: 4.9166666e+08 | Z38: 4.812583e+08 | AA38: 4.7084164e+08 | AB38: 4.6042497e+08 | AC38: 4.3334164e+08 | AD38: 4.2292497e+08 | AE38: 4.125083e+08 | AF38: 3.8542497e+08 | AG38: 3.8542497e+08 | AH38: 3.750083e+08 | AI38: 3.6459164e+08 | AJ38: 3.375083e+08 | AK38: 2.9375831e+08 | AL38: 2.8334169e+08 | AM38: 2.7675867e+08 | AN38: 2.625514e+08 | AO38: 1.4913473e+08 | AP38: 89293633 | AQ38: -1221150.5 | AR38: 0 | AS38: 0 | AT38: 0 | AU38: 0 | AV38: 0 | AW38: 0 | AX38: 0 | AY38: 0 | AZ38: 0 | BA38: 0 | BB38: 0 | BC38: 0 | BD38: 0 | BE38: 0 | BF38: 0 | BG38: 0 | BH38: 0 | BI38: 0 | BJ38: 0 | BK38: 0 | BL38: 0 | BM38: 0 | BN38: 0 | BO38: 0 | BP38: 0 | BQ38: 0 | BR38: 0 | BS38: 0 | BU38: 0 | BV38: 0 | BW38: 0 | BX38: 0 | BY38: 0 | BZ38: 0 | CA38: 0 | CB38: 0 | CC38: 0 | CD38: 0 | CE38: 0 | CF38: 0 | CH38: 0 | CI38: 0 | CJ38: 0 | CK38: 0 | CL38: 0 | CM38: 0 | CN38: 0 | CO38: 0 | CP38: 0
A39: Total Liabilities | B39: =B31+B32 -> 1597224000 | C39: =C31+C32 -> 1981931000 | D39: =D31+D32 -> 2039815000 | E39: =E31+E32 -> 2754806930 | F39: =F31+F32 -> 3.3620665e+09 | G39: =G31+G32 -> 4201071132 | H39: =H31+H32 -> 4.2460439e+09 | I39: =I31+I32 -> 4.2117722e+09 | ... CT39: =CT31+CT32 -> 0
A40: EQUITY
A41: Share Capital (Members share capital per Bylaws) | B41: 17007000 | C41: 17738000 | D41: 46593000 | E41: 51183315 | F41: 57957132 | G41: 163048132 | H41: 1.6468447e+08 | I41: 1.7584819e+08 | J41: 1.7977609e+08 | K41: 1.8202445e+08 | L41: 1.8528474e+08 | M41: 1.9201765e+08 | N41: 1.9573865e+08 | O41: 2.0721896e+08 | P41: 2.1140688e+08 | Q41: 2.2216042e+08 | R41: 2.3230715e+08 | S41: 2.4489806e+08 | T41: 244898056 | U41: 4.9689413e+08 | V41: 2.6485082e+08 | W41: 2.6928915e+08 | X41: 2.8070594e+08 | Y41: 2.932949e+08 | Z41: 3.0956524e+08 | AA41: 3.2324509e+08 | AB41: 3.3617104e+08 | AC41: 3.4388072e+08 | AD41: 3.4879522e+08 | AE41: 3.5421089e+08 | AF41: 3.6294537e+08 | AG41: 362945371 | AH41: 3.6696953e+08 | AI41: 4.436122e+08 | AJ41: 4.4698105e+08 | AK41: 452858470 | AL41: 4.5643556e+08 | AM41: 4.59781e+08 | AN41: 4.6291837e+08 | AO41: 4.6760893e+08 | AP41: 4.7357881e+08 | AQ41: 4.7624294e+08 | AR41: 4.8024872e+08 | AS41: 4.8921659e+08 | AT41: 489216589 | AU41: 4.9099105e+08 | AV41: 5.0642283e+08 | AW41: 5.1247197e+08 | AX41: 5.144786e+08 | AY41: 5.186576e+08 | AZ41: 5.226867e+08 | BA41: 5.2432358e+08 | BB41: 5.2745507e+08 | BC41: 5.2914864e+08 | BD41: 5.320807e+08 | BE41: 5.3538514e+08 | BF41: 5.5022761e+08 | BG41: 550227614 | BH41: 5.6735237e+08 | BI41: 5.7268555e+08 | BJ41: 5.7566957e+08 | BK41: 5.8003706e+08 | BL41: 5.8726178e+08 | BM41: 5.911998e+08 | BN41: 5.9401567e+08 | BO41: 5.9815758e+08 | BP41: 6.0174669e+08 | BQ41: 605170489 | BR41: 6.0920811e+08 | BS41: 6.258378e+08 | BT41: 625837800 | BU41: 6.4762254e+08 | BV41: 6.5259047e+08 | BW41: 6.5548999e+08 | BX41: 6.613253e+08 | BY41: 6.7461271e+08 | BZ41: 6.8207954e+08 | CA41: 6.9181659e+08 | CB41: 7.0049993e+08 | CC41: 7.0498989e+08 | CD41: 7.1294675e+08 | CE41: 7.3191527e+08 | CF41: 7.3953429e+08 | CG41: 739534288 | CH41: 7.6703995e+08 | CI41: 7.7930595e+08 | CJ41: 7.9007263e+08 | CK41: 8.0046457e+08 | CL41: 8.1333504e+08 | CM41: 8.3941614e+08 | CN41: 8.4397271e+08 | CO41: 8.491473e+08 | CP41: 8.5341459e+08
A42: Capital Grants | H42: 0 | I42: 0 | J42: 0 | S42: 0 | T42: 0 | U42: 0 | V42: 0 | W42: 0 | X42: 0 | Y42: 0 | Z42: 0 | AA42: 0 | AB42: 0 | AC42: 0 | AD42: 0 | AE42: 0 | AF42: 0 | AG42: 0 | AH42: 0 | AI42: 0 | AJ42: 0 | AK42: 0 | AL42: 0 | AM42: 0 | AN42: 0 | AO42: 0 | AP42: 0 | AQ42: 0 | AR42: 0 | AS42: 0 | AT42: 0 | AU42: 0 | AV42: 0 | AW42: 0 | AX42: 0 | AY42: 0 | AZ42: 0 | BA42: 0 | BB42: 0 | BC42: 0 | BD42: 0 | BE42: 0 | BF42: 0 | BG42: 0 | BH42: 0 | BI42: 0 | BJ42: 0 | BK42: 0 | BL42: 0 | BM42: 0 | BN42: 0 | BO42: 0 | BP42: 0 | BQ42: 0 | BR42: 0 | BS42: 0 | BU42: 0 | BV42: 0 | BW42: 0 | BX42: 0 | BY42: 0 | BZ42: 0 | CA42: 0 | CB42: 0 | CC42: 0 | CD42: 0 | CE42: 0 | CF42: 0 | CH42: 0 | CI42: 0 | CJ42: 0 | CK42: 0 | CL42: 0 | CM42: 0 | CN42: 0 | CO42: 0 | CP42: 0
A43: Prior Years' Retained Earnings | B43: 46757000 | C43: 63640000 | D43: 90987000 | E43: 149785000 | F43: 186014434 | G43: 192417306 | H43: 2.1519289e+08 | I43: 215610102 | J43: 215610102 | K43: 215610102 | L43: 215610102 | M43: 215610102 | N43: 215610102 | O43: 215610102 | P43: 215610102 | Q43: 215610102 | R43: 215610102 | S43: 215610102 | T43: 215610102 | U43: 5.13477e+08 | V43: 224571429 | W43: 224571429 | X43: 224571429 | Y43: 224571429 | Z43: 224571429 | AA43: 224571429 | AB43: 224571429 | AC43: 224571429 | AD43: 224571429 | AE43: 224571429 | AF43: 224571429 | AG43: 224571429 | AH43: 3.3180507e+08 | AI43: 271061486 | AJ43: 271061486 | AK43: 271061486 | AL43: 271061486 | AM43: 271061486 | AN43: 271061486 | AO43: 271061486 | AP43: 271061486 | AQ43: 271061486 | AR43: 271061486 | AS43: 331061486 | AT43: 271061485 | AU43: 3.3268186e+08 | AV43: 3.3268186e+08 | AW43: 319647574 | AX43: 3.1964757e+08 | AY43: 3.1964757e+08 | AZ43: 3.1964757e+08 | BA43: 3.1964757e+08 | BB43: 3.1964757e+08 | BC43: 3.1964757e+08 | BD43: 3.1964757e+08 | BE43: 3.1964767e+08 | BF43: 3.1964767e+08 | BG43: 318027199 | BH43: 369783005 | BI43: 366063134 | BJ43: 366063134 | BK43: 366063134 | BL43: 366063134 | BM43: 366063134 | BN43: 366063134 | BO43: 366063134 | BP43: 366063134 | BQ43: 366063134 | BR43: 366063134 | BS43: 366063134 | BT43: 366063134 | BU43: 474856634 | BV43: 474856634 | BW43: 474856634 | BX43: 474856634 | BY43: 474856634 | BZ43: 474856634 | CA43: 474856634 | CB43: 474856634 | CC43: 474856634 | CD43: 474856634 | CE43: 474856634 | CF43: 474856634 | CG43: 474856634 | CH43: 5.5144706e+08 | CI43: 5.5144706e+08 | CJ43: 5.5144706e+08 | CK43: 5.5144706e+08 | CL43: 5.5144706e+08 | CM43: 5.5144706e+08 | CN43: 5.5144706e+08 | CO43: 5.5144706e+08 | CP43: 5.5144706e+08
A44: Current Year's Surplus | B44: 16883000 | C44: 27347000 | D44: 58798000 | E44: =190000000-E43 -> 40215000 | F44: =57040879-11408176-8660233-8113998-1320000 -> 27538472 | G44: 23192796 | H44: 35394973 | I44: -33745366 | J44: -31933391 | K44: -37953401 | L44: -38326789 | M44: -30492385 | N44: -25960956 | O44: -5251501.4 | P44: 9491888.8 | Q44: 16787848 | R44: 23857971 | S44: 41128398 | T44: 8961328 | U44: 89093079 | V44: -41964153 | W44: -47605080 | X44: -49774018 | Y44: -32260669 | Z44: -22234452 | AA44: -16035294 | AB44: 2724994.2 | AC44: 14428366 | AD44: 24772725 | AE44: 39126611 | AF44: 1.0723364e+08 | AG44: 46490056 | AH44: 2236620 | AI44: -13132450 | AJ44: -33082546 | AK44: -34795274 | AL44: -41004109 | AM44: -27381568 | AN44: -24295818 | AO44: -2148444.4 | AP44: -1802739.8 | AQ44: -6289782.9 | AR44: 4927046.6 | AS44: 1620375 | AT44: 46965714 | AU44: -2968252.9 | AV44: -3704573.9 | AW44: -29353266 | AX44: -6054075.8 | AY44: -770222.22 | AZ44: -6899919.1 | BA44: 4798673.1 | BB44: 19648316 | BC44: 36837692 | BD44: 62205427 | BE44: 78727857 | BF44: 98731350 | BG44: 48035935 | BH44: 7704065.8 | BI44: 4529656 | BJ44: -11520951 | BK44: -9641922.5 | BL44: 29287267 | BM44: 27293692 | BN44: 54771317 | BO44: 53957688 | BP44: 58930300 | BQ44: 71398660 | BR44: 78128878 | BS44: 1.0831383e+08 | BT44: =98722491+132208349-26461670-93875670-1800000 -> 108793500 | BU44: -23968096 | BV44: -19738048 | BW44: -24691580 | BX44: -45054036 | BY44: -58132580 | BZ44: -43991037 | CA44: -47278859 | CB44: -31281922 | CC44: -17369847 | CD44: 2903723.2 | CE44: 16997797 | CF44: 1.330427e+08 | CG44: =536949277-CG43 -> 62092643 | CH44: -5612620 | CI44: -35865286 | CJ44: -19637175 | CK44: -25307018 | CL44: -18663618 | CM44: 6735390.9 | CN44: 17254705 | CO44: 18794754 | CP44: 48062613
A45: Statutory Reserve | B45: 33539000 | C45: 39631000 | D45: 54556000 | E45: 72274432 | F45: 91411000 | G45: 103653504 | H45: 91411000 | I45: 103653504 | J45: 103653504 | K45: 103653504 | L45: 103653504 | M45: 103653504 | N45: 103653504 | O45: 103653504 | P45: 103653504 | Q45: 103653504 | R45: 103653504 | S45: 103653504 | T45: 126907513 | U45: 207307008 | V45: 126907513 | W45: 126907513 | X45: 126907513 | Y45: 126907513 | Z45: 126907513 | AA45: 126907513 | AB45: 126907513 | AC45: 126907513 | AD45: 126907513 | AE45: 126907513 | AF45: 126907513 | AG45: 155984729 | AH45: 126907513 | AI45: 155984729 | AJ45: 155984729 | AK45: 155984729 | AL45: 155984729 | AM45: 155984729 | AN45: 155984729 | AO45: 155984729 | AP45: 155984729 | AQ45: 155984729 | AR45: 155984729 | AS45: 155984729 | AT45: 186446779 | AU45: 155984729 | AV45: 155984729 | AW45: 186446780 | AX45: 186446780 | AY45: 186446780 | AZ45: 186446780 | BA45: 186446780 | BB45: 186446780 | BC45: 186446780 | BD45: 186446780 | BE45: 186446780 | BF45: 186446780 | BG45: 200882891 | BH45: 200882891 | BI45: 200882891 | BJ45: 200882891 | BK45: 200882891 | BL45: 200882891 | BM45: 200882891 | BN45: 200882891 | BO45: 200882891 | BP45: 200882891 | BQ45: 200882891 | BR45: 200882891 | BS45: 200882891 | BT45: 227344561 | BU45: 227344561 | BV45: 227344561 | BW45: 227344561 | BX45: 227344561 | BY45: 227344561 | BZ45: 227344561 | CA45: 227344561 | CB45: 227344561 | CC45: 227344561 | CD45: 227344561 | CE45: 227344561 | CF45: 227344561 | CG45: 259109764 | CH45: 259109764 | CI45: 259109764 | CJ45: 259109764 | CK45: 259109764 | CL45: 259109764 | CM45: 259109764 | CN45: 259109764 | CO45: 259109764 | CP45: 259109764
A46: Other Reserves (provide notes on these reserves) | B46: 1147000 | C46: =4225000 -> 4225000 | D46: 6146000 | E46: 28383729 | F46: 30000000 | G46: 50001500 | H46: 30001500 | I46: 50001500 | J46: 50002500 | K46: 50002500 | L46: 50003000 | M46: 50003000 | N46: 50003000 | O46: 50003000 | P46: 50003000 | Q46: 50003000 | R46: 50003000 | S46: 50003000 | T46: 120003000 | U46: 100006000 | V46: 120003000 | W46: 120003000 | X46: 120003000 | Y46: 120003000 | Z46: 148225440 | AA46: 148225440 | AB46: 148225440 | AC46: 148225440 | AD46: 148225440 | AE46: 148225440 | AF46: 148225440 | AG46: 150000000 | AH46: 148225440 | AI46: 150000000 | AJ46: 150000000 | AK46: 150000000 | AL46: 150000000 | AM46: 150000000 | AN46: 150000000 | AO46: 150000000 | AP46: 150000000 | AQ46: 150000000 | AR46: 150000000 | AS46: 150000000 | AT46: 150000000 | AU46: 150000000 | AV46: 150000000 | AW46: 150000000 | AX46: 150000000 | AY46: 150000000 | AZ46: 150000000 | BA46: 150000000 | BB46: 150000000 | BC46: 150000000 | BD46: 150000000 | BE46: 150000000 | BF46: 150000000 | BG46: 150000000 | BH46: 150000000 | BI46: 150000000 | BJ46: 150000000 | BK46: 150000000 | BL46: 150000000 | BM46: 150000000 | BN46: 150000000 | BO46: 150000000 | BP46: 150000000 | BQ46: 150000000 | BR46: 150000000 | BS46: 150000000 | BT46: 150000000 | BU46: 150000000 | BV46: 150000000 | BW46: 150000000 | BX46: 150000000 | BY46: 150000000 | BZ46: 150000000 | CA46: 150000000 | CB46: 150000000 | CC46: 150000000 | CD46: 150000000 | CE46: 150000000 | CF46: 150000000 | CG46: 150221218 | CH46: 150000000 | CI46: 150000000 | CJ46: 150000000 | CK46: 150000000 | CL46: 150000000 | CM46: 150000000 | CN46: 150000000 | CO46: 150000000 | CP46: 150000000
A47: Revaluation Reserves (Not part of core capital) | B47: 119688000 | C47: 111671000 | D47: 187305000 | E47: 187304813 | F47: 171246737 | G47: 143724358 | H47: 1.712461e+08 | I47: 143724358 | J47: 143724358 | K47: 143724358 | L47: 143724358 | M47: 143724358 | N47: 143724358 | O47: 143724358 | P47: 143724358 | Q47: 0 | R47: 0 | S47: 0 | T47: 184223390 | U47: 287448716 | V47: 184223390 | W47: 184223390 | X47: 184223390 | Y47: 184223390 | Z47: 184223390 | AA47: 184223390 | AB47: 184223390 | AC47: 170223390 | AD47: 170223390 | AE47: 170223390 | AF47: 170223390 | AG47: 149277486 | AH47: 170223390 | AI47: 149277486 | AJ47: 149277486 | AK47: 149277486 | AL47: 149277486 | AM47: 149277486 | AN47: 149277486 | AO47: 149277486 | AP47: 149277486 | AQ47: 149277486 | AR47: 149277486 | AS47: 149277486 | AT47: 168085388 | AU47: 149277486 | AV47: 168200337 | AW47: 168085388 | AX47: 168085388 | AY47: 168085388 | AZ47: 168085388 | BA47: 168085388 | BB47: 168085388 | BC47: 168085388 | BD47: 168085388 | BE47: 168085388 | BF47: 168085388 | BG47: 116430054 | BH47: 116430054 | BI47: 116430054 | BJ47: 116430054 | BK47: 116430054 | BL47: 116430054 | BM47: 116430054 | BN47: 116430054 | BO47: 116430054 | BP47: 116430054 | BQ47: 116430054 | BR47: 116430054 | BS47: 116430054 | BT47: 222008615 | BU47: 124375212 | BV47: 124375212 | BW47: 124375212 | BX47: 124375212 | BY47: 124375212 | BZ47: 124375212 | CA47: 124375212 | CB47: 124375212 | CC47: 124375212 | CD47: 124375212 | CE47: 124375212 | CF47: 124375212 | CG47: 120630436 | CH47: 120630436 | CI47: 120630436 | CJ47: 120630436 | CK47: 120630436 | CL47: 120630436 | CM47: 120630436 | CN47: 120630436 | CO47: 120630436 | CP47: 120630436
A48: Proposed Dividends | B48: 150686000 | D48: 201743000 | H48: 0 | I48: 0 | J48: 0 | L48: 0 | M48: 0 | N48: 0 | O48: 0 | P48: 0 | Q48: 143724358 | R48: 143724358 | S48: 143724358 | U48: 0 | V48: 0 | W48: 0 | X48: 0 | Y48: 0 | Z48: 0 | AA48: 0 | AB48: 0 | AC48: 0 | AD48: 0 | AE48: 0 | AF48: 0 | AG48: 0 | AH48: 0 | AI48: 0 | AJ48: 0 | AK48: 0 | AL48: 0 | AM48: 0 | AN48: 0 | AO48: 0 | AP48: 0 | AQ48: 0 | AR48: 0 | AS48: 0 | AT48: 0 | AU48: 0 | AV48: 0 | AW48: 0 | AX48: 0 | AY48: 0 | AZ48: 0 | BA48: 0 | BB48: 0 | BC48: 0 | BD48: 0 | BE48: 0 | BF48: 0 | BG48: 0 | BH48: 0 | BI48: 0 | BJ48: 0 | BK48: 0 | BL48: 0 | BM48: 0 | BN48: 0 | BO48: 0 | BP48: 0 | BQ48: 0 | BR48: 0 | BS48: 0 | BU48: 0 | BV48: 0 | BW48: 0 | BX48: 0 | BY48: 0 | BZ48: 0 | CA48: 0 | CB48: 0 | CC48: 0 | CD48: 0 | CE48: 0 | CF48: 0 | CH48: 0 | CI48: 0 | CJ48: 0 | CK48: 0 | CL48: 0 | CM48: 0 | CN48: 0 | CO48: 0 | CP48: 0
A49: Adjustment to Equity | B49: 0 | H49: 0 | I49: 0 | J49: 0 | Q49: 0 | R49: 0 | S49: 0 | U49: 0 | V49: 0 | W49: 0 | X49: 0 | Y49: 0 | Z49: 0 | AA49: 0 | AB49: 0 | AC49: 0 | AD49: 0 | AE49: 0 | AF49: 0 | AG49: 0 | AH49: 0 | AI49: 0 | AJ49: 0 | AK49: 0 | AL49: 0 | AM49: 0 | AN49: 0 | AO49: 0 | AP49: 0 | AQ49: 0 | AR49: 0 | AS49: 0 | AT49: 0 | AU49: 0 | AV49: 0 | AW49: 0 | AX49: 0 | AY49: 0 | AZ49: 0 | BA49: 0 | BB49: 0 | BC49: 0 | BD49: 0 | BE49: 0 | BF49: 0 | BG49: 0 | BU49: 0 | BV49: 0 | BW49: 0 | BX49: 0 | BY49: 0 | BZ49: 0 | CA49: 0 | CB49: 0 | CC49: 0 | CD49: 0 | CE49: 0 | CF49: 0 | CH49: 0 | CI49: 0 | CJ49: 0 | CK49: 0 | CL49: 0 | CM49: 0 | CN49: 0 | CO49: 0 | CP49: 0
A50: Total Equity | B50: =B41+B42+B43+B44+B45+B46+B47+B48 -> 385707000 | C50: =C41+C42+C43+C44+C45+C46+C47+C48 -> 264252000 | D50: =D41+D42+D43+D44+D45+D46+D47+D48 -> 646128000 | E50: =E41+E42+E43+E44+E45+E46+E47+E48 -> 529146289 | F50: =F41+F42+F43+F44+F45+F46+F47+F48 -> 564167775 | G50: =G41+G42+G43+G44+G45+G46+G47+G48 -> 676037596 | H50: =H41+H42+H43+H44+H45+H46+H47+H48 -> 7.0793092e+08 | I50: =I41+I42+I43+I44+I45+I46+I47+I48 -> 6.5509229e+08 | ... BT50: =BT41+BT42+BT43+BT44+BT45+BT46+BT47+BT48 -> 1700047610 | BU50: =BY41+BY42+BY43+BY44+BY45+BY46+BY47+BY48 -> 1.5930565e+09 | BV50: =BZ41+BZ42+BZ43+BZ44+BZ45+BZ46+BZ47+BZ48 -> 1.6146649e+09 | BW50: =CA41+CA42+CA43+CA44+CA45+CA46+CA47+CA48 -> 1.6211141e+09 | BX50: =CB41+CB42+CB43+CB44+CB45+CB46+CB47+CB48 -> 1.6457944e+09 | BY50: =#REF!+#REF!+#REF!+#REF!+#REF!+#REF!+#REF!+#REF! -> #REF! | BZ50: =CD41+CD42+CD43+CD44+CD45+CD46+CD47+CD48 -> 1.6924269e+09 | CA50: =CE41+CE42+CE43+CE44+CE45+CE46+CE47+CE48 -> 1.7254895e+09 | CB50: =CF41+CF42+CF43+CF44+CF45+CF46+CF47+CF48 -> 1.8491534e+09 | CC50: =SUM(CC41:CC49) -> 1.6641965e+09 | CD50: =SUM(CD41:CD49) -> 1.6924269e+09 | CE50: =SUM(CE41:CE49) -> 1.7254895e+09 | CF50: =SUM(CF41:CF49) -> 1.8491534e+09 | CG50: =SUM(CG41:CG49) -> 1806444983 | CH50: =SUM(CH41:CH49) -> 1.8426146e+09 | CI50: =SUM(CI41:CI49) -> 1.8246279e+09 | CJ50: =SUM(CJ41:CJ49) -> 1.8516227e+09 | ... CT50: =SUM(CT41:CT49) -> 0
A51: Total Liabilities and Equity | B51: =B50+B39 -> 1982931000 | C51: =C50+C39 -> 2246183000 | D51: =D50+D39 -> 2685943000 | E51: =E50+E39 -> 3283953219 | F51: =F50+F39 -> 3.9262343e+09 | G51: =G50+G39 -> 4877108728 | H51: =H50+H39 -> 4.9539748e+09 | I51: =I50+I39 -> 4.8668645e+09 | ... BT51: =BT50+BT39 -> 10412328501 | BV51: =BV42+BV43+BV44+BV45+BV46+BV47+BV48+BV49 -> 9.5683836e+08 | BW51: =BW42+BW43+BW44+BW45+BW46+BW47+BW48+BW49 -> 9.5188483e+08 | BX51: =BX42+BX43+BX44+BX45+BX46+BX47+BX48+BX49 -> 9.3152237e+08 | BY51: =BU50+BY39 -> 1.0491916e+10 | BZ51: =BV50+BZ39 -> 1.0654682e+10 | CA51: =BW50+CA39 -> 1.0928962e+10 | CB51: =BX50+CB39 -> 1.1073144e+10 | CC51: =SUM(BV51:CB51) -> 4.5988949e+10 | CD51: =BZ50+CD39 -> 1.1360376e+10 | CE51: =CA50+CE39 -> 1.1573387e+10 | CF51: =CB50+CF39 -> 1.1755599e+10 | CG51: =CC50+CG39 -> 1.1624569e+10 | CH51: =CD50+CH39 -> 1.1280151e+10 | CI51: =CE50+CI39 -> 1.1324196e+10 | CJ51: =CF50+CJ39 -> 1.1479781e+10 | CK51: =CG50+CK39 -> 1.1584152e+10 | ... CN51: =CJ50+CN39 -> 1.2388343e+10 | CO51: =CO50+CO39 -> 1.2719878e+10 | CP51: =CP50+CP39 -> 1.2823137e+10 | CQ51: =CM50+CQ39 -> 1.9273388e+09 | CR51: =CN50+CR39 -> 1.9424147e+09 | CS51: =CO50+CS39 -> 1949129311 | CT51: =CP50+CT39 -> 1.9826645e+09
B52: =B26-B51 -> 0 | C52: =C26-C51 -> 0 | D52: =D26-D51 -> 1.4842193e+08 | E52: =E26-E51 -> 1 | F52: =F26-F51 -> 1.21 | G52: =G26-G51 -> -1 | H52: =H26-H51 -> 0 | I52: =I26-I51 -> 0 | ... AQ52: =AQ26-AQ51 -> 0 | AS52: =AS26-AS51 -> 0.60000038 | AT52: =AT26-AT51 -> 9 | AU52: =AU26-AU51 -> 0 | AV52: =AV26-AV51 -> 0 | AW52: =AW26-AW51 -> 0.60000134 | AX52: =AX26-AX51 -> 0 | AY52: =AY26-AY51 -> -0.060001373 | AZ52: =AZ26-AZ51 -> 0 | ... BT52: =BT26-BT51 -> 0 | BV52: =BV51+BV40 -> 9.5683836e+08 | BW52: =BW51+BW40 -> 9.5188483e+08 | BX52: =BX51+BX40 -> 9.3152237e+08 | BY52: =BY26-BY51 -> 0 | BZ52: =BZ26-BZ51 -> 0 | CA52: =CA26-CA51 -> 0 | CD52: =SUM(CD41:CD50) -> 3.3848538e+09 | CO52: =CO51-CO26 -> 0 | CP52: =CP51-CP26 -> 0

Sheet SCI
B2: 2011 AUDITED | C2: 2012 AUDITED | D2: 2013 AUDITED | E2: 2014 AUDITED | F2: audited 2015 | G2: Audited 2016 | H2: 42736 | I2: 42767 | J2: 42795 | K2: 42826 | L2: 42856 | M2: 42887 | N2: 42917 | O2: 42948 | P2: 42979 | Q2: 43009 | R2: 43040 | S2: 43070 | T2: Audited 2017 | U2: 43101 | V2: 43132 | W2: 43160 | X2: 43191 | Y2: 43221 | Z2: 43252 | AA2: 43282 | AB2: 43313 | AC2: 43344 | AD2: 43374 | AE2: 43405 | AF2: 43435 | AG2: Audited 2018 | AH2: 43466 | AI2: 43497 | AJ2: 43525 | AK2: 43556 | AL2: 43586 | AM2: 43617 | AN2: 43647 | AO2: 43678 | AP2: 43709 | AQ2: 43739 | AR2: 43770 | AS2: 43800 | AT2: Audited-19 | AU2: 43831 | AV2: 43862 | AW2: 43891 | AX2: 43922 | AY2: 43952 | AZ2: 43983 | BA2: 44013 | BB2: 44044 | BC2: 44075 | BD2: 44105 | BE2: 44136 | BF2: 44166 | BG2: Audited-20 | BH2: 44197 | BI2: 44228 | BJ2: 44256 | BK2: 44287 | BL2: 44317 | BM2: 44348 | BN2: 44378 | BO2: 44409 | BP2: 44440 | BQ2: 44470 | BR2: 44501 | BS2: 44531 | BT2: Audited 2021 | BU2: 44562 | BV2: 44593 | BW2: 44621 | BX2: 44652 | BY2: 44682 | BZ2: 44713 | CA2: 44743 | CB2: 44774 | CC2: 44805 | CD2: 44835 | CE2: 44866 | CF2: 44896 | CG2: Audited 2022 | CH2: 44927 | CI2: 44958 | CJ2: 44986 | CK2: 45017 | CL2: 45047 | CM2: 45078 | CN2: 45108 | CO2: 45139 | CP2: 45170 | CQ2: 45200 | CR2: 45231 | CS2: 45261
A3: Financial Income | B3: 272737000 | C3: =C4+C7 -> 315395000 | D3: =D4+D7 -> 391908000 | E3: =E4+E7 -> 486302029 | F3: =F4+F7 -> 557411649 | G3: =G4+G7 -> 691077004 | H3: =H4+H7 -> 60018212 | I3: =I4+I7 -> 1.1929711e+08 | J3: =J4+J7 -> 1.82223e+08 | ... CS3: =CS4+CS7 -> 0
A4: Financial Income from Loans Portfolio | B4: 254043000 | C4: =C5+C6 -> 310677000 | D4: =D5+D6 -> 363369000 | E4: =E5+E6 -> 442597728 | F4: =F5+F6 -> 519200042 | G4: =G5+G6 -> 645382510 | H4: =H5+H6 -> 56614856 | I4: =I5+I6 -> 1.1177208e+08 | J4: =J5+J6 -> 1.7018352e+08 | ... CS4: =CS5+CS6 -> 0
A5: Interest on Loan Portfolio | B5: 253602000 | C5: 289168000 | D5: 356158000 | E5: 442597728 | F5: 503688132 | G5: 635979383 | H5: 56614856 | I5: 1.1177208e+08 | J5: 1.7018352e+08 | K5: 2.3215714e+08 | L5: 2.9495932e+08 | M5: 3.5979667e+08 | N5: 4.2774414e+08 | O5: 5.1038563e+08 | P5: 5.9673823e+08 | Q5: 6.7240514e+08 | R5: 7.509777e+08 | S5: 8.3783551e+08 | T5: 837835511 | U5: 1.5081321e+08 | V5: 1.4386766e+08 | W5: 2.2065185e+08 | X5: 3.019857e+08 | Y5: 3.8159725e+08 | Z5: 4.5724309e+08 | AA5: 5.3582301e+08 | AB5: 6.2999948e+08 | AC5: 7.0534261e+08 | AD5: 7.8567222e+08 | AE5: 8.7534744e+08 | AF5: 9.6967851e+08 | AG5: 969678514 | AH5: 83871107 | AI5: 1.6288703e+08 | AJ5: 2.463056e+08 | AK5: 3.3564803e+08 | AL5: 4.1758611e+08 | AM5: 5.017181e+08 | AN5: 5.8952797e+08 | AO5: 6.8930236e+08 | AP5: 7.7556576e+08 | AQ5: 8.5928326e+08 | AR5: 9.5559684e+08 | AS5: 1.0437813e+09 | AT5: 1043781324 | AU5: 86861126 | AV5: 1.7023577e+08 | AW5: 2.5688825e+08 | AX5: 3.3671949e+08 | AY5: 4.1746785e+08 | AZ5: 4.9561048e+08 | BA5: 577932569 | BB5: 6.7336089e+08 | BC5: 7.6311549e+08 | BD5: 854738566 | BE5: 9.4519752e+08 | BF5: 1.0345234e+09 | BG5: 1034523352 | BH5: 85521103 | BI5: 1.6809339e+08 | BJ5: 2.5701691e+08 | BK5: 3.4923213e+08 | BL5: 4.3970593e+08 | BM5: 5.3117806e+08 | BN5: 6.3141356e+08 | BO5: 7.1429947e+08 | BP5: 7.9976236e+08 | BQ5: 8.9512929e+08 | BR5: 9.853325e+08 | BS5: 1.0781276e+09 | BT5: 1078127618 | BU5: 90384420 | BV5: 1.8425522e+08 | BW5: 2.8183036e+08 | BX5: 3.7975309e+08 | BY5: 4.7743814e+08 | BZ5: 5.7622051e+08 | CA5: 6.7970578e+08 | CB5: 7.8326126e+08 | CC5: 8.9306085e+08 | CD5: 1.001066e+09 | CE5: 1.1107351e+09 | CF5: 1.3220519e+09 | CG5: 1222051910 | CH5: 1.1040754e+08 | CI5: 2.2047827e+08 | CJ5: 3.317881e+08 | CK5: 4.4475594e+08 | CL5: 5.6023906e+08 | CM5: 6.7440579e+08 | CN5: 7.903733e+08 | CO5: 9.1359402e+08 | CP5: 1.0340612e+09
A6: Fees & Commission on Loan Portfolio | B6: 441000 | C6: 21509000 | D6: =2131000+5080000 -> 7211000 | F6: 15511910 | G6: 9403127 | H6: 0 | I6: 0 | J6: 0 | L6: 0 | M6: 0 | N6: 0 | O6: 0 | P6: 0 | Q6: 0 | R6: 0 | S6: 0 | T6: 51453557 | U6: 0 | V6: 0 | W6: 0 | X6: 0 | Y6: 0 | Z6: 0 | AA6: 0 | AB6: 0 | AC6: 21966026 | AD6: 24277059 | AE6: 26624007 | AF6: 0 | AG6: 0 | AH6: 2417191.9 | AI6: 5295197.1 | AJ6: 0 | AK6: 0 | AL6: 0 | AM6: 17167750 | AN6: 0 | AO6: 22344149 | AP6: 25051257 | AQ6: 27785828 | AR6: 31200650 | AS6: 33178858 | AU6: 2856228.7 | AV6: 6522594.5 | AW6: 10211472 | AX6: 12544931 | AY6: 15275572 | AZ6: 17610374 | BA6: 20793774 | BB6: 24211550 | BC6: 26440217 | BD6: 29618294 | BE6: 32754598 | BF6: 35899447 | BH6: 11025132 | BI6: 17737654 | BJ6: 26730070 | BK6: 43529160 | BL6: 52147675 | BM6: 0 | BN6: 26631296 | BO6: 30183022 | BP6: 33989228 | BQ6: 38151114 | BR6: 41795194 | BS6: 51361864 | BT6: 41456567 | BU6: 4353745 | BV6: 8459541.6 | BW6: 13379120 | BX6: 17554676 | BY6: 21683209 | BZ6: 27831422 | CA6: 32636720 | CB6: 37279164 | CC6: 41997668 | CD6: 46615707 | CE6: 34548487 | CF6: 39288543 | CG6: =5816395+2424080+3384554+22285852 -> 33910881 | CH6: 6658215.2 | CI6: 11737248 | CJ6: 17010359 | CK6: 21738356 | CL6: 30032580 | CM6: 36627813 | CN6: 42846817 | CO6: 49513792 | CP6: 55936221
A7: Financial Income from Investments in: | B7: 18694000 | C7: =SUM(C9:C11) -> 4718000 | D7: =SUM(D9:D11) -> 28539000 | E7: =SUM(E9:E11) -> 43704301 | F7: =SUM(F9:F11) -> 38211607 | G7: =SUM(G9:G11) -> 45694494 | H7: =SUM(H9:H11) -> 3403356.2 | I7: =SUM(I9:I11) -> 7525036.9 | J7: =SUM(J9:J11) -> 12039484 | ... CS7: =SUM(CS9:CS11) -> 0
A8: Government Securities | B8: 0 | H8: 0 | I8: 0 | J8: 0 | L8: 0 | M8: 0 | N8: 0 | O8: 0 | P8: 0 | Q8: 0 | R8: 0 | S8: 0 | U8: 0 | V8: 0 | W8: 0 | X8: 0 | Y8: 0 | Z8: 0 | AA8: 0 | AB8: 0 | AC8: 0 | AD8: 0 | AE8: 0 | AF8: 0 | AG8: 0 | AH8: 0 | AI8: 0 | AJ8: 0 | AK8: 0 | AL8: 0 | AM8: 0 | AN8: 0 | AO8: 0 | AP8: 0 | AQ8: 0 | AR8: 0 | AS8: 0 | AT8: 0 | AU8: 0 | AV8: 0 | AW8: 0 | AX8: 0 | AY8: 0 | AZ8: 0 | BA8: 0 | BB8: 0 | BC8: 0 | BD8: 0 | BE8: 0 | BF8: 0 | BH8: 0 | BI8: 0 | BJ8: 0 | BK8: 0 | BL8: 0 | BM8: 0 | BN8: 0 | BO8: 0 | BP8: 0 | BQ8: 0 | BR8: 0 | BS8: 0 | BU8: 0 | BV8: 0 | BW8: 0 | BX8: 0 | BY8: 0 | BZ8: 0 | CA8: 0 | CB8: 0 | CC8: 0 | CD8: 0 | CE8: 0 | CF8: 0 | CH8: 0 | CI8: 0 | CJ8: 0 | CK8: 0 | CL8: 0 | CM8: 0 | CN8: 0 | CO8: 0 | CP8: 0
A9: Deposit with Banks and Other Financial Inst. | B9: 2376000 | C9: 4180000 | E9: 9995324 | H9: 0 | I9: 0 | J9: 0 | L9: 0 | M9: 0 | N9: 0 | O9: 0 | P9: 0 | Q9: 0 | R9: 0 | S9: 0 | T9: 7030991 | U9: 0 | V9: 0 | W9: 0 | X9: 0 | Y9: 0 | Z9: 0 | AA9: 0 | AB9: 0 | AC9: 0 | AD9: 0 | AE9: 0 | AF9: 15317368 | AH9: 0 | AI9: 0 | AJ9: 1164687.8 | AK9: 1608670.2 | AL9: 1731344 | AM9: 0 | AN9: 19168067 | AO9: 0 | AP9: 0 | AQ9: 0 | AR9: 0 | AS9: 0 | AT9: 0 | AU9: 0 | AV9: 0 | AW9: 0 | AX9: 0 | AY9: 0 | AZ9: 0 | BA9: 0 | BB9: 0 | BC9: 0 | BD9: 0 | BE9: 0 | BF9: 0 | BG9: 72113370 | BH9: 0 | BI9: 0 | BJ9: 0 | BK9: 0 | BL9: 0 | BM9: 0 | BN9: 0 | BO9: 0 | BP9: 0 | BQ9: 0 | BR9: 0 | BS9: 0 | BT9: 136913280 | BU9: 0 | BV9: 0 | BW9: 0 | BX9: 0 | BY9: 0 | BZ9: 0 | CA9: 0 | CB9: 0 | CC9: 0 | CD9: 0 | CE9: 0 | CF9: 0 | CG9: 145851486 | CH9: 0 | CI9: 0 | CJ9: 0 | CK9: 0 | CL9: 0 | CM9: 0 | CN9: 0 | CO9: 0 | CP9: 0
A10: Other Investments - dividend & Interest incomes from investments | B10: 0 | H10: 0 | I10: 0 | J10: 0 | L10: 0 | M10: 10382382 | N10: 11620662 | O10: 11620662 | P10: 11054511 | Q10: 11054511 | R10: 11054511 | S10: 11054511 | U10: 2096398 | V10: 3605517 | W10: 489936.92 | X10: 636913.82 | Y10: 717436.82 | Z10: 14379340 | AA10: 14194008 | AB10: 14317493 | AC10: 14439313 | AD10: 14787490 | AE10: 15195967 | AF10: 20886748 | AG10: 4227975 | AH10: 651686.77 | AI10: 786042.34 | AJ10: 9341817.3 | AK10: 11080490 | AL10: 13689207 | AM10: 18860633 | AN10: 20826675 | AO10: 21954320 | AP10: 22049873 | AQ10: 22362171 | AR10: 22766472 | AS10: 23032866 | AT10: =27723128+20660701 -> 48383829 | AU10: 99445.95 | AV10: 172840.5 | AW10: 714496.9 | AX10: 19167419 | AY10: 19228743 | AZ10: 19683827 | BA10: 19782874 | BB10: 19860389 | BC10: 20156777 | BD10: 20262246 | BE10: 20379323 | BF10: 20794064 | BG10: =18538297 -> 18538297 | BH10: 0 | BI10: 523459.24 | BJ10: 1257465.6 | BK10: 19647403 | BL10: 20351648 | BM10: 43733255 | BN10: 21740727 | BO10: 22051260 | BP10: 22305370 | BQ10: 22602407 | BR10: 22914358 | BS10: 23714209 | BT10: 18250100 | BU10: 318872.3 | BV10: 665924.3 | BW10: 1408023.7 | BX10: 1324001.8 | BY10: 1652414.5 | BZ10: 19530288 | CA10: 22832326 | CB10: 23175653 | CC10: 23555838 | CD10: 23829994 | CE10: 24729877 | CF10: 25243947 | CG10: 18058312 | CH10: 359204.68 | CI10: 769068.42 | CJ10: 1178932.2 | CK10: 2407665.2 | CL10: 3258127.2 | CM10: 30038971 | CN10: 30859407 | CO10: 31478855 | CP10: 32256213
A11: Other Operating Income- Salary processing fees, transaction fees, membership fees | B11: 16318000 | C11: 538000 | D11: =7060000+946000+27744000-D6 -> 28539000 | E11: 33708977 | F11: 38211607 | G11: 45694494 | H11: 3403356.2 | I11: 7525036.9 | J11: 12039484 | K11: 14673097 | L11: 19243738 | M11: 22718288 | N11: 26208338 | O11: 32138665 | P11: 35842328 | Q11: 39011027 | R11: 34080445 | S11: 47430036 | U11: 4603522.7 | V11: 5420515.5 | W11: 13173824 | X11: 16700631 | Y11: 20120938 | Z11: 23518415 | AA11: 27915923 | AB11: 32504410 | AC11: 14673582 | AD11: 16801616 | AE11: 18626911 | AF11: 30812315 | AG11: 64579420 | AH11: 2188601.4 | AI11: 7108139.4 | AJ11: 8883035.5 | AK11: 11841612 | AL11: 14598352 | AM11: 16947658 | AN11: 18718204 | AO11: 26087340 | AP11: 30782264 | AQ11: 34481217 | AR11: 38453892 | AS11: 45331479 | AT11: 93728335 | AU11: 2906373.6 | AV11: 12834070 | AW11: 17580449 | AX11: 21536782 | AY11: 25696481 | AZ11: 32634424 | BA11: 41175578 | BB11: 46872883 | BC11: 55368582 | BD11: 63670277 | BE11: 68578667 | BF11: 83442391 | BG11: =54428983+5391390 -> 59820373 | BH11: 3360824.2 | BI11: 7251179 | BJ11: 11003044 | BK11: 14514916 | BL11: 17769288 | BM11: 59220393 | BN11: 72792458 | BO11: 81641574 | BP11: 1.0471878e+08 | BQ11: 1.1351785e+08 | BR11: 1.2422801e+08 | BS11: 1.5629705e+08 | BT11: 34753173 | BU11: 7723379.4 | BV11: 30016586 | BW11: 44628919 | BX11: 46950258 | BY11: 66038514 | BZ11: 76752948 | CA11: 80057878 | CB11: 1.0252716e+08 | CC11: 1.2515824e+08 | CD11: 1.3828256e+08 | CE11: 1.5087529e+08 | CF11: 1.6513517e+08 | CG11: =164047337-CG6-CG10 -> 112078144 | CH11: 17573806 | CI11: 20199308 | CJ11: 46959355 | CK11: 56408714 | CL11: 63005460 | CM11: 76831060 | CN11: 85801021 | CO11: 89903450 | CP11: 1.2961477e+08
A12: Financial Expense | B12: 161587000 | C12: =SUM(C13:C16)+C17+C18 -> 179955000 | D12: =SUM(D13:D16)+D17+D18 -> 202204000 | E12: =SUM(E13:E16)+E17+E18 -> 253507699 | F12: =F13+F14+F15+F16+F17+F18 -> 3.0907542e+08 | G12: =G13+G14+G15+G16+G17+G18 -> 377000555 | H12: =H13+H14+H15+H16+H17+H18 -> 3576601.2 | I12: =I13+I14+I15+I16+I17+I18 -> 93484527 | J12: =J13+J14+J15+J16+J17+J18 -> 1.3603003e+08 | K12: =K13+K14+K15+K16+K17+K18 -> 1.7881736e+08 | L12: =L13+L14+L15+L16+L17+L18 -> 2.2153768e+08 | M12: =M13+M14+M15+M16+M17+M18 -> 2.7071822e+08 | ... CS12: =CS13+CS14+CS15+CS16+CS17+CS18 -> 0
A13: Interest Expense on Deposits | B13: 148036000 | C13: 172768000 | D13: =192153000+8690000 -> 200843000 | E13: 252903029 | F13: 307717763 | G13: 374176451 | H13: 432589.6 | I13: 77703090 | J13: 1.1645913e+08 | K13: 1.5516839e+08 | L13: 1.9373689e+08 | M13: 2.3266265e+08 | N13: 2.7156256e+08 | O13: 3.1015966e+08 | P13: 3.4915531e+08 | Q13: 3.8896937e+08 | R13: 4.2752865e+08 | S13: 4.6656716e+08 | T13: 374569299 | U13: 935398 | V13: 90901486 | W13: 136689278 | X13: 182294326 | Y13: 2.0258499e+08 | Z13: 2.4308037e+08 | AA13: 2.8381469e+08 | AB13: 0 | AC13: 3.6544453e+08 | AD13: 4.0680262e+08 | AE13: 447239436 | AF13: 500193931 | AG13: 468684234 | AH13: 45513264 | AI13: 95671409 | AJ13: 145543167 | AK13: 193917757 | AL13: 2.4176373e+08 | AM13: 2.8931245e+08 | AN13: 3.3721477e+08 | AO13: 3.8505402e+08 | AP13: 4.3260626e+08 | AQ13: 4.8063212e+08 | AR13: 5.2849379e+08 | AS13: 5.7611797e+08 | AT13: 564645701 | AU13: 47864450 | AV13: 95599250 | AW13: 1.5073424e+08 | AX13: 2.010419e+08 | AY13: 2.5138476e+08 | AZ13: 3.014158e+08 | BA13: 3.5185781e+08 | BB13: 4.019834e+08 | BC13: 4.5113647e+08 | BD13: 5.0136708e+08 | BE13: 5.5260185e+08 | BF13: 6.0310091e+08 | BG13: 648599707 | BH13: 55532892 | BI13: 1.2065285e+08 | BJ13: 1.8085273e+08 | BK13: 2.4108133e+08 | BL13: 3.0138393e+08 | BM13: 3.6154889e+08 | BN13: 4.2201158e+08 | BO13: 4.821146e+08 | BP13: 5.4233551e+08 | BQ13: 6.0259242e+08 | BR13: 6.6278942e+08 | BS13: 7.2298217e+08 | BT13: 767523975 | BU13: 77350542 | BV13: 1.5427091e+08 | BW13: 2.3100224e+08 | BX13: 3.0802188e+08 | BY13: 3.8513893e+08 | BZ13: 4.6169185e+08 | CA13: 5.3873317e+08 | CB13: 6.1576181e+08 | CC13: 6.9261547e+08 | CD13: 7.6948905e+08 | CE13: 8.4617972e+08 | CF13: 9.230281e+08 | CG13: 904946415 | CH13: 92549279 | CI13: 184952029 | CJ13: 272895787 | CK13: 3.5305016e+08 | CL13: 4.4110104e+08 | CM13: 5.2905276e+08 | CN13: 6.1719248e+08 | CO13: 7.055632e+08 | CP13: 7.9849479e+08
A14: Cost of External Borrowings | B14: 9065000 | C14: 5096000 | D14: 0 | H14: 2761000 | I14: 9804164.1 | J14: 10011613 | K14: 10781408 | L14: 11682753 | M14: 18579360 | N14: 22592659 | O14: 30228768 | P14: 37774430 | Q14: 41672836 | R14: 54178898 | S14: 60308343 | T14: =4567162+60308343 -> 64875505 | U14: 12944687 | V14: 20157629 | W14: 25491057 | X14: 31844224 | Y14: 40971042 | Z14: 46739542 | AA14: 52039725 | AB14: 56482704 | AC14: 63933922 | AD14: 68191191 | AE14: 72204165 | AF14: 78131445 | AG14: 83702936 | AH14: 3750443.3 | AI14: 7374003.9 | AJ14: 12180265 | AK14: 16338525 | AL14: 19491189 | AM14: 22622334 | AN14: 25584196 | AO14: 28482484 | AP14: 29417892 | AQ14: 30447267 | AR14: 31668417 | AS14: 31668417 | AT14: =31668417+6117967 -> 37786384 | AU14: 0 | AV14: 0 | AW14: 0 | AX14: 0 | AY14: 0 | AZ14: 0 | BA14: 0 | BB14: 0 | BC14: 0 | BD14: 0 | BE14: 0 | BF14: 0 | BG14: 0 | BH14: 0 | BI14: 0 | BJ14: 0 | BK14: 0 | BL14: 0 | BM14: 0 | BN14: 0 | BO14: 0 | BP14: 0 | BQ14: 0 | BR14: 0 | BS14: 0 | BU14: 0 | BV14: 0 | BW14: 0 | BX14: 0 | BY14: 0 | BZ14: 0 | CA14: 0 | CB14: 0 | CC14: 0 | CD14: 0 | CE14: 0 | CF14: 0 | CH14: 0 | CI14: 0 | CJ14: 0 | CK14: 0 | CL14: 0 | CM14: 0 | CN14: 0 | CO14: 0 | CP14: 0
A15: Dividend Expenses (on member shares) | B15: 2762000 | C15: 2091000 | D15: 0 | H15: 0 | I15: 0 | J15: 0 | L15: 0 | M15: 0 | N15: 0 | O15: 0 | P15: 0 | Q15: 0 | R15: 0 | S15: 0 | U15: 0 | V15: 0 | W15: 0 | X15: 0 | Y15: 0 | Z15: 0 | AA15: 0 | AB15: 3.2446461e+08 | AC15: 0 | AD15: 0 | AE15: 0 | AF15: 0 | AG15: 0 | AH15: 0 | AI15: 0 | AJ15: 0 | AK15: 0 | AL15: 0 | AM15: 0 | AN15: 0 | AO15: 0 | AP15: 0 | AQ15: 0 | AR15: 0 | AS15: 0 | AT15: 0 | AU15: 0 | AV15: 0 | AW15: 0 | AX15: 0 | AY15: 0 | AZ15: 0 | BA15: 0 | BB15: 0 | BC15: 0 | BD15: 0 | BE15: 0 | BF15: 0 | BG15: 0 | BH15: 0 | BI15: 0 | BJ15: 0 | BK15: 0 | BL15: 0 | BM15: 0 | BN15: 0 | BO15: 0 | BP15: 0 | BQ15: 0 | BR15: 0 | BS15: 0 | BU15: 0 | BV15: 0 | BW15: 0 | BX15: 0 | BY15: 0 | BZ15: 0 | CA15: 0 | CB15: 0 | CC15: 0 | CD15: 0 | CE15: 0 | CF15: 0 | CH15: 0 | CI15: 0 | CJ15: 0 | CK15: 0 | CL15: 0 | CM15: 0 | CN15: 0 | CO15: 0 | CP15: 0
A16: Other Financial Expense | B16: 0 | D16: 1361000 | E16: 604670 | F16: 1357661.9 | G16: 2824104 | H16: 280261.6 | I16: 359811.62 | J16: 536061.42 | K16: 595050.91 | L16: 693912.68 | M16: 964862.46 | N16: 1014019.9 | O16: 1757512.5 | P16: 394190.05 | Q16: 1033960.3 | R16: 1277918 | S16: 1479172.6 | U16: 590586.56 | V16: 545826.66 | W16: 738807.42 | X16: 911501.96 | Y16: 991162.9 | Z16: 1408546.1 | AA16: 1510912 | AB16: 1624767.6 | AC16: 1766468.6 | AD16: 1866018 | AE16: 2020430.6 | AF16: 2131691 | AH16: 146257.03 | AI16: 246806.78 | AJ16: 351310.19 | AK16: 456819.85 | AL16: 624652.99 | AM16: 729752.32 | AN16: 823103.74 | AO16: 1054522.4 | AP16: 1152495.8 | AQ16: 1256840.7 | AR16: 1404038.8 | AS16: 1583461.7 | AT16: 0 | AU16: 89436.4 | AV16: 166141.34 | AW16: 438516.16 | AX16: 515773.33 | AY16: 582436.64 | AZ16: 780534.76 | BA16: 854395.69 | BB16: 951487.39 | BC16: 1348763.2 | BD16: 1466488.6 | BE16: 1591493.3 | BF16: 1725466.6 | BG16: 1738335 | BH16: 70392.12 | BI16: 176397.6 | BJ16: 266831.21 | BK16: 358387.65 | BL16: 449445.75 | BM16: 543344.85 | BN16: 643994.07 | BO16: 748064.97 | BP16: 852744.16 | BQ16: 961596.16 | BR16: 1045190.2 | BS16: 1192244.1 | BT16: 1192244 | BU16: 91385.72 | BV16: 181515.12 | BW16: 314377.93 | BX16: 443188.11 | BY16: 500702.98 | BZ16: 623262.98 | CA16: 747456.84 | CB16: 850753.14 | CC16: 980760.89 | CD16: 1105060.9 | CE16: 1265348.2 | CF16: 1413596.6 | CG16: 1413597 | CH16: 113794.05 | CI16: 233736 | CJ16: 423732.56 | CK16: 534781.1 | CL16: 653981.5 | CM16: 749200.7 | CN16: 910701.3 | CO16: 1048207.4 | CP16: 1187146.2
A17: Fees & Commission Expense | B17: 1724000 | D17: 0 | H17: 25000 | I17: 25000 | J17: 254175 | K17: 554175 | L17: 695935 | M17: 695935 | N17: 845575 | O17: 845575 | P17: 845575 | Q17: 876987.5 | R17: 876987.5 | S17: 876987.5 | U17: 138000 | V17: 828175 | W17: 828175 | X17: 828175 | Y17: 828175 | Z17: 828175 | AA17: 828175 | AB17: 862105 | AC17: 862105 | AD17: 862105 | AE17: 862105 | AF17: 862105 | AH17: 599750 | AI17: 599750 | AJ17: 599750 | AK17: 599750 | AL17: 599750 | AM17: 599750 | AN17: 599750 | AO17: 599750 | AP17: 599750 | AQ17: 599750 | AR17: 599750 | AS17: 599750 | AT17: 0 | AU17: 307350 | AV17: 307350 | AW17: 543350 | AX17: 543350 | AY17: 543350 | AZ17: 543350 | BA17: 543350 | BB17: 543350 | BC17: 543350 | BD17: 543350 | BE17: 543350 | BF17: 543350 | BG17: 0 | BH17: 307350 | BI17: 307350 | BJ17: 807350 | BK17: 807350 | BL17: 807350 | BM17: 807350 | BN17: 807350 | BO17: 807350 | BP17: 807350 | BQ17: 807350 | BR17: 813350 | BS17: 813350 | BU17: 535000 | BV17: 535000 | BW17: 815000 | BX17: 815000 | BY17: 854850 | BZ17: 854850 | CA17: 854850 | CB17: 854850 | CC17: 854850 | CD17: 854850 | CE17: 854850 | CF17: 854850 | CH17: 231850 | CI17: 231850 | CJ17: 556850 | CK17: 556850 | CL17: 556850 | CM17: 556850 | CN17: 556850 | CO17: 556850 | CP17: 556850
A18: Other Expense | B18: 0 | D18: 0 | H18: 77750 | I18: 5592462 | J18: 8769044 | K18: 11718333 | L18: 14728188 | M18: 17815416 | N18: 20839746 | O18: 23543702 | P18: 26473531 | Q18: 29248390 | R18: 32098791 | S18: 35036878 | U18: 408675.6 | V18: 6372245.8 | W18: 9276897.8 | X18: 10476579 | Y18: 13249158 | Z18: 16157903 | AA18: 18855200 | AB18: 20728671 | AC18: 2985148.1 | AD18: 455202 | AE18: 3353720 | AF18: 474616.9 | AH18: 435140 | AI18: 1338105 | AJ18: 2209570 | AK18: 3353070 | AL18: 270694 | AM18: 585496.6 | AN18: 477826.6 | AO18: 628140.6 | AP18: 887749.8 | AQ18: 1010449.8 | AR18: 1207669.8 | AS18: 687779 | AT18: 0 | AU18: 179425 | AV18: 47060 | AW18: 9051445 | AX18: 897394 | AY18: 1143709 | AZ18: 1546630.4 | BA18: 1225459.4 | BB18: 4748624.4 | BC18: 1809557.1 | BD18: 2134752.1 | BE18: 1435613.8 | BF18: 1570025.8 | BG18: 0 | BH18: 50009.7 | BI18: 210386.7 | BJ18: 259251.7 | BK18: 30346330 | BL18: 406424.9 | BM18: 581875.4 | BN18: 616071.4 | BO18: 644805.4 | BP18: 4901161.4 | BQ18: 916921.4 | BR18: 990279.4 | BS18: 1097121 | BU18: 37800 | BV18: 70255 | BW18: 157926 | BX18: 268795.2 | BY18: 5387253.2 | BZ18: 408359.2 | CA18: 445334 | CB18: 576726.8 | CC18: 681517.6 | CD18: 730379.6 | CE18: 760704.6 | CF18: 867757.6 | CG18: 3028096 | CH18: 54188.8 | CI18: 186132.8 | CJ18: 498975.8 | CK18: 514004.4 | CL18: 592420 | CM18: 769236 | CN18: 857665 | CO18: 1253765.9 | CP18: 1030828.9
A19: Net Financial Income/(Loss) | B19: 9920000 | C19: =C3-C12 -> 135440000 | D19: =D3-D12 -> 189704000 | E19: =E3-E12 -> 232794330 | F19: =F3-F12 -> 2.4833622e+08 | G19: =G3-G12 -> 314076449 | H19: =H3-H12 -> 56441611 | I19: =I3-I12 -> 25812585 | J19: =J3-J12 -> 46192975 | ... CS19: =CS3-CS12 -> 0
A20: Allowance for Loan Loss | B20: 0 | C20: =C21-C22 -> 6196000 | D20: =D21-D22 -> 17687000 | E20: =E21-E22 -> 0 | F20: =F21-F22 -> 0 | G20: =G21-G22 -> 0 | H20: =H21-H22 -> 0 | I20: =I21-I22 -> 8000000 | J20: =J21-J22 -> 12000000 | ... CS20: =CS21-CS22 -> 0
A21: Provision for Loan Losses | B21: 0 | C21: 6196000 | D21: 17687000 | H21: 0 | I21: 8000000 | J21: 12000000 | K21: 16000000 | L21: 20000000 | M21: 24000000 | N21: 28000000 | O21: 32000000 | P21: 36000000 | Q21: 40000000 | R21: 44000000 | S21: 48000000 | T21: 48000000 | U21: 0 | V21: 10000000 | W21: 15000000 | X21: 20000000 | Y21: 25000000 | Z21: 30000000 | AA21: 35000000 | AB21: 40000000 | AC21: 45000000 | AD21: 50000000 | AE21: 55000000 | AF21: 60000000 | AG21: 60000000 | AH21: 9000000 | AI21: 18000000 | AJ21: 27000000 | AK21: 36000000 | AL21: 45000000 | AM21: 54000000 | AN21: 63000000 | AO21: 72000000 | AP21: 81000000 | AQ21: 90000000 | AR21: 99000000 | AS21: 108000000 | AT21: 112284035 | AU21: 9000000 | AV21: 18000000 | AW21: 29394330 | AX21: 39192440 | AY21: 48990550 | AZ21: 58788660 | BA21: 68586770 | BB21: 78384880 | BC21: 88182990 | BD21: 97981100 | BE21: 107779210 | BF21: 117577320 | BG21: 72077320 | BH21: 10000000 | BI21: 13400000 | BJ21: 20100000 | BK21: 26800000 | BL21: 33500000 | BM21: 40200000 | BN21: 46900000 | BO21: 53600000 | BP21: 60300000 | BQ21: 67000000 | BR21: 73700000 | BS21: 80400000 | BT21: 30400000 | BU21: 7504000 | BV21: 15008000 | BW21: 22512000 | BX21: 30016000 | BY21: 37520000 | BZ21: 45024000 | CA21: 52528000 | CB21: 60032000 | CC21: 67536000 | CD21: 67536000 | CE21: 67536000 | CF21: 67536000 | CG21: 37536000 | CH21: 4000000 | CI21: 6000000 | CJ21: 9000000 | CK21: 12000000 | CL21: 15000000 | CM21: 18000000 | CN21: 21000000 | CO21: 24000000 | CP21: 27000000
A22: Value of Loans Recovered | B22: 79770000 | D22: 0 | H22: 0 | I22: 0 | J22: 0 | L22: 0 | M22: 0 | N22: 0 | O22: 0 | P22: 0 | Q22: 0 | R22: 0 | S22: 0 | T22: 0 | U22: 0 | V22: 0 | W22: 0 | X22: 0 | Y22: 0 | Z22: 0 | AA22: 0 | AB22: 0 | AC22: 0 | AD22: 0 | AE22: 0 | AF22: 0 | AG22: 0 | AH22: 0 | AI22: 0 | AJ22: 0 | AK22: 0 | AL22: 0 | AM22: 0 | AN22: 0 | AO22: 0 | AP22: 0 | AQ22: 0 | AR22: 0 | AS22: 0 | AT22: 0 | AU22: 0 | AV22: 0 | AW22: 0 | AX22: 0 | AY22: 0 | AZ22: 0 | BA22: 0 | BB22: 0 | BC22: 0 | BD22: 0 | BE22: 0 | BF22: 0 | BG22: 0 | BH22: 0 | BI22: 0 | BJ22: 0 | BK22: 0 | BL22: 0 | BM22: 0 | BN22: 0 | BO22: 0 | BP22: 0 | BQ22: 0 | BR22: 0 | BS22: 0 | BU22: 0 | BV22: 0 | BW22: 0 | BX22: 0 | BY22: 0 | BZ22: 0 | CA22: 0 | CB22: 0 | CC22: 0 | CD22: 0 | CE22: 0 | CF22: 0 | CH22: 0 | CI22: 0 | CJ22: 0 | CK22: 0 | CL22: 0 | CM22: 0 | CN22: 0 | CO22: 0 | CP22: 0
A23: Operating Expenses | B23: =B24+B25+B26+B27+B28 -> 48209000 | C23: =C24+C25+C26+C27+C28 -> 97557000 | D23: =D24+D25+D26+D27+D28 -> 114022000 | E23: =E24+E25+E26+E27+E28 -> 140092462 | F23: =F24+F25+F26+F27+F28 -> 184357219 | G23: =G24+G25+G26+G27+G28 -> 245246790 | H23: =H24+H25+H26+H27+H28 -> 21046638 | I23: =I24+I25+I26+I27+I28 -> 51557951 | ... CS23: =CS24+CS25+CS26+CS27+CS28 -> 0
A24: Personnel Expenses | B24: 2007000 | C24: 34295000 | D24: 37013000 | E24: 43883272 | F24: 68695800 | G24: 66805300 | H24: 4156221 | I24: 12848701 | J24: 18582383 | K24: 25488260 | L24: 32477367 | M24: 38404144 | N24: 46497031 | O24: 53044556 | P24: 59852634 | Q24: 67779081 | R24: 73273372 | S24: 80729868 | T24: 80370625 | U24: 5550119.2 | V24: 13373508 | W24: 22016243 | X24: 28471315 | Y24: 34829171 | Z24: 42739472 | AA24: 46198469 | AB24: 53579009 | AC24: 63672226 | AD24: 69060565 | AE24: 76712668 | AF24: 87160980 | AG24: 84677464 | AH24: 8984236 | AI24: 17780262 | AJ24: 24889808 | AK24: 31886324 | AL24: 42157556 | AM24: 50930058 | AN24: 57906695 | AO24: 65914043 | AP24: 74015272 | AQ24: 81679013 | AR24: 83156785 | AS24: 99260335 | AT24: 110575042 | AU24: 6800138 | AV24: 17312001 | AW24: 25964514 | AX24: 33390494 | AY24: 43212334 | AZ24: 52068527 | BA24: 60880571 | BB24: 69775044 | BC24: 78586279 | BD24: 87388858 | BE24: 96296560 | BF24: 104963917 | BG24: 111337305 | BH24: 9989325 | BI24: 20544098 | BJ24: 30363174 | BK24: 40104585 | BL24: 50125192 | BM24: 60046078 | BN24: 69947695 | BO24: 79643361 | BP24: 89543759 | BQ24: 99198428 | BR24: 1.0939547e+08 | BS24: 1.1918259e+08 | BT24: 136938046 | BU24: 9493732 | BV24: 19077668 | BW24: 33858466 | BX24: 43788000 | BY24: 57607088 | BZ24: 68389895 | CA24: 79412039 | CB24: 90417369 | CC24: 1.0136584e+08 | CD24: 1.1229183e+08 | CE24: 1.2355403e+08 | CF24: 1.3511296e+08 | CG24: 155087214 | CH24: 9641865 | CI24: 23949854 | CJ24: 35622736 | CK24: 47437953 | CL24: 59285574 | CM24: 71078076 | CN24: 83003895 | CO24: 97976032 | CP24: 1.0744148e+08
A25: Governance Expenses | B25: 5511000 | C25: 33577000 | D25: 41103000 | E25: 48527275 | F25: 52825047 | G25: 66047004 | H25: 1853071 | I25: 3215333.4 | J25: 4496952.4 | K25: 6136329.1 | L25: 8406420.1 | M25: 9714676 | N25: 12043269 | O25: 13333768 | P25: 14774809 | Q25: 17520015 | R25: 20167436 | S25: 21879034 | T25: 78642230 | U25: 3798126 | V25: 14895777 | W25: 22051377 | X25: 29135863 | Y25: 36063278 | Z25: 43020785 | AA25: 50169622 | AB25: 57796858 | AC25: 64640948 | AD25: 71708891 | AE25: 78813099 | AF25: 17730530 | AG25: 41172198 | AH25: 9491612 | AI25: 18968653 | AJ25: 28202767 | AK25: 37470701 | AL25: 47120922 | AM25: 56752942 | AN25: 66528790 | AO25: 76032902 | AP25: 85439950 | AQ25: 95144856 | AR25: 1.0633068e+08 | AS25: 1.1561087e+08 | AT25: 46028189 | AU25: 9320205 | AV25: 18638246 | AW25: 28031186 | AX25: 36319507 | AY25: 37184772 | AZ25: 38872472 | BA25: 40271799 | BB25: 41800018 | BC25: 42873919 | BD25: 44907279 | BE25: 46045646 | BF25: 48353098 | BG25: 36698374 | BH25: 1728412 | BI25: 4003862.3 | BJ25: 6338661.6 | BK25: 7333268.6 | BL25: 10243370 | BM25: 12373000 | BN25: 14620488 | BO25: 17068721 | BP25: 19125901 | BQ25: 22454579 | BR25: 24615320 | BS25: 27390532 | BT25: 45140733 | BU25: 2248338 | BV25: 4484532 | BW25: 6516432 | BX25: 8217673 | BY25: 10566851 | BZ25: 12644484 | CA25: 16986942 | CB25: 18204421 | CC25: 19931561 | CD25: 22931351 | CE25: 24500681 | CF25: 27009183 | CG25: 60887043 | CH25: 2658014 | CI25: 4730551 | CJ25: 6443123 | CK25: 7822090 | CL25: 10868596 | CM25: 14193426 | CN25: 15674247 | CO25: 17685281 | CP25: 19328892
A26: Marketing Expenses | B26: 19231000 | C26: 1467000 | D26: 3438000 | E26: 2888770 | F26: 8673784 | G26: 10130261 | H26: 3898108.7 | I26: 10347282 | J26: 10941047 | K26: 15794659 | L26: 16854466 | M26: 18919701 | N26: 19711606 | O26: 20089446 | P26: 21347764 | Q26: 22040197 | R26: 24403630 | S26: 27367445 | T26: 14906136 | U26: 6667806 | V26: 10206569 | W26: 10723594 | X26: 11335654 | Y26: 12047737 | Z26: 12535068 | AA26: 15395783 | AB26: 15919794 | AC26: 16452233 | AD26: 17213960 | AE26: 17639794 | AF26: 20336639 | AG26: 4935654.2 | AH26: 4378730 | AI26: 12486158 | AJ26: 13883361 | AK26: 14371374 | AL26: 16490109 | AM26: 16880439 | AN26: 20257254 | AO26: 21399328 | AP26: 22202543 | AQ26: 22821321 | AR26: 24296294 | AS26: 28358679 | AT26: 5787019 | AU26: 9648756 | AV26: 16566037 | AW26: 18390572 | AX26: 19008912 | AY26: 19415999 | AZ26: 20687059 | BA26: 21122681 | BB26: 21988931 | BC26: 23026851 | BD26: 23960901 | BE26: 24765214 | BF26: 25899027 | BG26: 6010057 | BH26: 5124010 | BI26: 7621968.1 | BJ26: 8880972.1 | BK26: 10052036 | BL26: 11496239 | BM26: 12302608 | BN26: 13013601 | BO26: 14819112 | BP26: 15199414 | BQ26: 17307134 | BR26: 19007364 | BS26: 21844710 | BT26: 7812155 | BU26: 7910638 | BV26: 10454516 | BW26: 12289246 | BX26: 13384990 | BY26: 22545542 | BZ26: 26532092 | CA26: 30533056 | CB26: 33822802 | CC26: 34841140 | CD26: 36441544 | CE26: 38640388 | CF26: 39700800 | CG26: 9493765 | CH26: 10071663 | CI26: 16440443 | CJ26: 21295244 | CK26: 22559347 | CL26: 31050343 | CM26: 38815167 | CN26: 42925610 | CO26: 44950142 | CP26: 48297867
A27: Depreciation and Amortization Charges | B27: 0 | C27: 6571000 | D27: 8112000 | E27: 7672051 | F27: 12634731 | G27: 20255096 | H27: 0 | I27: 5025000 | J27: 7537500 | K27: 10050000 | L27: 12562500 | M27: 15075000 | N27: 17587500 | O27: 20178358 | P27: 22690858 | Q27: 25203358 | R27: 27715858 | S27: 31497047 | T27: 31605440 | U27: 0 | V27: 7697552 | W27: 11546328 | X27: 15395104 | Y27: 19243880 | Z27: 23092656 | AA27: 26941432 | AB27: 30790208 | AC27: 34638984 | AD27: 38487760 | AE27: 42336536 | AF27: 46185312 | AG27: 30598469 | AH27: 0 | AI27: 4388323 | AJ27: 13164969 | AK27: 17553292 | AL27: 21941615 | AM27: 26329938 | AN27: 30718261 | AO27: 35106584 | AP27: 39494907 | AQ27: 43883230 | AR27: 48271553 | AS27: 52659876 | AT27: 33390493 | AU27: 4388323 | AV27: 8776646 | AW27: 9878889 | AX27: 13171852 | AY27: 16464815 | AZ27: 19757778 | BA27: 23050741 | BB27: 26343704 | BC27: 29636667 | BD27: 32929630 | BE27: 36222593 | BF27: 39515556 | BG27: 37748984 | BH27: 3400000 | BI27: 6920650 | BJ27: 10380975 | BK27: 13841300 | BL27: 17301625 | BM27: 20761950 | BN27: 24222275 | BO27: 27682600 | BP27: 31142925 | BQ27: 34603250 | BR27: 38063575 | BS27: 41523900 | BT27: 25813238 | BU27: 2137322.8 | BV27: 5470655.8 | BW27: 8803988.8 | BX27: 12137322 | BY27: 15470655 | BZ27: 18803988 | CA27: 22137321 | CB27: 25470654 | CC27: 28803987 | CD27: 32137320 | CE27: 35470653 | CF27: 38803990 | CG27: 29659943 | CH27: 2500000 | CI27: 5276658 | CJ27: 7914987 | CK27: 10553316 | CL27: 13191645 | CM27: 15829974 | CN27: 18468303 | CO27: 21106632 | CP27: 23744961
A28: Administrative Expenses | B28: 21460000 | C28: 21647000 | D28: 24356000 | E28: 37121094 | F28: 41527857 | G28: 82009129 | H28: 11139237 | I28: 20121634 | J28: 24568483 | K28: 32497035 | L28: 40691355 | M28: 46557983 | N28: 50840135 | O28: 54215107 | P28: 64834078 | Q28: 71338630 | R28: 76007592 | S28: 81449724 | T28: 77729181 | U28: 37386657 | V28: 21879075 | W28: 27558933 | X28: 38404518 | Y28: 48887696 | Z28: 57772780 | AA28: 63214223 | AB28: 71847665 | AC28: 81921871 | AD28: 91220864 | AE28: 1.012916e+08 | AF28: 1.1634456e+08 | AG28: =105433131+2132691 -> 107565822 | AH28: 5139656.6 | AI28: 12133892 | AJ28: 30460006 | AK28: 42736021 | AL28: 50359569 | AM28: 62318988 | AN28: 68061247 | AO28: 73908198 | AP28: 86504089 | AQ28: 1.0040905e+08 | AR28: 1.1546925e+08 | AS28: 1.2736735e+08 | AT28: =102418819+1583462 -> 104002281 | AU28: 7368867.5 | AV28: 18637776 | AW28: 42108134 | AX28: 51263218 | AY28: 58423248 | AZ28: 77000817 | BA28: 84392203 | BB28: 95814213 | BC28: 1.0861305e+08 | BD28: 110961186 | BE28: 119541260 | BF28: 1.3599697e+08 | BG28: 117071421 | BH28: 6054852.1 | BI28: 14338711 | BJ28: 47260434 | BK28: 65005213 | BL28: 73769180 | BM28: 95555721 | BN28: 1.0375406e+08 | BO28: 1.1530802e+08 | BP28: 1.3573213e+08 | BQ28: 1.5015632e+08 | BR28: 1.6329545e+08 | BS28: 1.8172223e+08 | BT28: 132143434 | BU28: 20467178 | BV28: 33921760 | BW28: 50714850 | BX28: 75351441 | BY28: 90482254 | BZ28: 109969095 | CA28: 1.2034127e+08 | CB28: 1.3248881e+08 | CC28: 1.5444123e+08 | CD28: 1.640697e+08 | CE28: 1.6490875e+08 | CF28: 1.8567658e+08 | CG28: 138738900 | CH28: 19632823 | CI28: 47196835 | CJ28: 62077237 | CK28: 93924276 | CL28: 103588689 | CM28: 121900783 | CN28: 1.3126881e+08 | CO28: 1.4996608e+08 | CP28: 174572665
A29: Net Operating Income | B29: 0 | C29: =C19-C20-C23 -> 31687000 | D29: =D19-D20-D23 -> 57995000 | E29: =E19-E20-E23 -> 92701868 | F29: =F19-F20-F23 -> 63979005 | G29: =G19-G20-G23 -> 68829659 | H29: =H19-H20-H23 -> 35394973 | I29: =I19-I20-I23 -> -33745366 | J29: =J19-J20-J23 -> -31933391 | ... CS29: =CS19-CS20-CS23 -> 0
A30: Net Non- Operating Income/ (Expense) | B30: 0 | C30: =C31-C32 -> 0 | D30: =D31-D32 -> 0 | E30: =E31-E32 -> 0 | F30: =F31-F32 -> 0 | G30: =G31-G32 -> 0 | H30: =H31-H32 -> 0 | I30: =I31-I32 -> 0 | J30: =J31-J32 -> 0 | ... CS30: =CS31-CS32 -> 0
A31: Non- Operating Income | B31: 0 | C31: 0 | D31: 0 | H31: 0 | I31: 0 | J31: 0 | L31: 0 | M31: 0 | N31: 0 | O31: 0 | P31: 0 | Q31: 0 | R31: 0 | S31: 0 | T31: 0 | U31: 0 | V31: 0 | W31: 0 | X31: 0 | Y31: 0 | Z31: 0 | AA31: 0 | AB31: 0 | AC31: 207000 | AD31: 416700 | AE31: 2294764.6 | AF31: 2333764.6 | AG31: 0 | AH31: 955382.3 | AI31: 553532.3 | AJ31: 1093532.3 | AK31: 1319382.3 | AL31: 1434862.3 | AM31: 1599862.3 | AN31: 1623277.3 | AO31: 1785937.3 | AP31: 1858437.3 | AQ31: 1953287.3 | AR31: 2089287.3 | AS31: 3989327.9 | AU31: 9210 | AV31: 1158072.4 | AW31: 1388842.4 | AX31: 1467502.4 | AY31: 1522502.4 | AZ31: 2784932.8 | BA31: 2851432.8 | BB31: 3016782.8 | BC31: 3066782.8 | BD31: 3099782.8 | BE31: 4848534 | BF31: 5391390 | BG31: 0 | BH31: 316985 | BI31: 524935 | BJ31: 600535 | BK31: 2517802.1 | BL31: 2848103.1 | BM31: 2929187.1 | BN31: 4145949.6 | BO31: 4266362.7 | BP31: 4733800.7 | BQ31: 5396537.2 | BR31: 5650873.2 | BS31: 6106640.2 | BT31: 6106640 | BU31: 990073 | BV31: 1008922 | BW31: 2109823.5 | BX31: 3760123.1 | BY31: 3950359.1 | BZ31: 4433391.1 | CA31: 4854631.1 | CB31: 6273256.2 | CC31: 6610220.2 | CD31: 7004476.2 | CE31: 7265703.2 | CF31: 9281265.3 | CG31: 9281265 | CH31: 2139663.1 | CI31: 2557285.1 | CJ31: 2862562.1 | CK31: 3745376.2 | CL31: 6787060.5 | CM31: 6990362.5 | CN31: 7449955.5 | CO31: 7689940.4 | CP31: 7862691.4
A32: Non- Operating Expense | B32: 21460000 | C32: 0 | D32: 0 | H32: 0 | I32: 0 | J32: 0 | L32: 0 | M32: 0 | N32: 0 | O32: 0 | P32: 0 | Q32: 0 | R32: 0 | S32: 0 | T32: 0 | U32: 0 | V32: 0 | W32: 0 | X32: 0 | Y32: 0 | Z32: 0 | AA32: 0 | AB32: 0 | AC32: 881731 | AD32: 1313186 | AE32: 1488926 | AF32: 2243256 | AG32: 0 | AH32: 408260.7 | AI32: 775032.7 | AJ32: 1386240.7 | AK32: 1609820.7 | AL32: 2228657.7 | AM32: 2613423.7 | AN32: 2988123.7 | AO32: 3442570.7 | AP32: 3789422.7 | AQ32: 4271649.7 | AR32: 5281869.7 | AS32: 5779009.7 | AU32: 733686 | AV32: 577414 | AW32: 1601602 | AX32: 2145360 | AY32: 2615393 | AZ32: 3762334 | BA32: 4951777 | BB32: 5340531 | BC32: 5552259 | BD32: 5543110 | BE32: 6207989.7 | BF32: 7006737.7 | BG32: 0 | BH32: 262736 | BI32: 1424683.2 | BJ32: 2618595.2 | BK32: 3353533.8 | BL32: 4052622.8 | BM32: 5046381.8 | BN32: 5415556.8 | BO32: 6047372.8 | BP32: 6638349.8 | BQ32: 7400538.8 | BR32: 8076643.8 | BS32: 9144701.8 | BU32: -37351 | BV32: 669431 | BW32: 1063302 | BX32: 1961900 | BY32: 2821082 | BZ32: 3817714 | CA32: 4646753 | CB32: 5318225 | CC32: 5700298 | CD32: 6307938 | CE32: 7485563 | CF32: 7954326 | CH32: 1297573 | CI32: 2408377 | CJ32: 3293920 | CK32: 5410296 | CL32: 6096767.1 | CM32: 7213127.1 | CN32: 8217230.1 | CO32: 9279112.1 | CP32: 10012959
A33: Net Income (Before Taxes and Donations) | B33: 356000 | C33: =C29+C30 -> 31687000 | D33: =D29+D30 -> 57995000 | E33: =E29+E30 -> 92701868 | F33: =F29+F30 -> 63979005 | G33: =G29+G30 -> 68829659 | H33: =H29+H30 -> 35394973 | I33: =I29+I30 -> -33745366 | J33: =J29+J30 -> -31933391 | ... CS33: =CS29+CS30 -> 0
A34: Taxes (Incomes taxes & Other payable to KRA) | C34: =627000+608000 -> 1235000 | D34: 1144000 | E34: 4104450 | F34: 6938128 | G34: 7617138 | H34: 0 | I34: 0 | J34: 0 | L34: 0 | M34: 0 | N34: 0 | O34: 0 | P34: 0 | Q34: 0 | R34: 0 | S34: 0 | T34: 9351589 | U34: 0 | V34: 0 | W34: 0 | X34: 0 | Y34: 0 | Z34: 0 | AA34: 0 | AB34: 0 | AC34: 0 | AD34: 0 | AE34: 0 | AF34: 0 | AG34: 11764054 | AH34: 0 | AI34: 0 | AJ34: 0 | AK34: 0 | AL34: 0 | AM34: 0 | AN34: 0 | AO34: 0 | AP34: 0 | AQ34: 0 | AR34: 0 | AS34: 0 | AT34: 19084108 | AZ34: 0 | BA34: 0 | BB34: 0 | BC34: 0 | BD34: 0 | BE34: 0 | BF34: 0 | BG34: 29878000 | BT34: 36435204 | BU34: 0 | BV34: 0 | BW34: 0 | BX34: 0 | BY34: 0 | BZ34: 0 | CA34: 0 | CB34: 0 | CC34: 0 | CD34: 0 | CE34: 0 | CF34: 0 | CG34: 41615007 | CH34: 0 | CI34: 0 | CJ34: 0 | CK34: 0 | CL34: 0 | CM34: 0 | CN34: 0 | CO34: 0 | CP34: 0
A35: Net Income (After Taxes before Donations) | B35: =B33-B34 -> 356000 | C35: =C33-C34 -> 30452000 | D35: =D33-D34 -> 56851000 | E35: =E33-E34 -> 88597418 | F35: =F33-F34 -> 57040877 | G35: =G33-G34 -> 61212521 | H35: =H33-H34 -> 35394973 | I35: =I33-I34 -> -33745366 | ... CS35: =CS33-CS34 -> 0
A36: Donations | D36: 0 | I36: 0 | J36: 0 | L36: 0 | M36: 0 | N36: 0 | O36: 0 | P36: 0 | Q36: 0 | R36: 0 | S36: 0 | U36: 0 | V36: 0 | W36: 0 | X36: 0 | Y36: 0 | Z36: 0 | AA36: 0 | AB36: 0 | AC36: 0 | AD36: 0 | AE36: 0 | AF36: 0 | AH36: 0 | AI36: 0 | AJ36: 0 | AK36: 0 | AL36: 0 | AM36: 0 | AN36: 0 | AO36: 0 | AP36: 0 | AQ36: 0 | AR36: 0 | AS36: 0 | AZ36: 0 | BA36: 0 | BB36: 0 | BC36: 0 | BD36: 0 | BE36: 0 | BF36: 0 | BG36: 0 | BU36: 0 | BV36: 0 | BW36: 0 | BX36: 0 | BY36: 0 | BZ36: 0 | CA36: 0 | CB36: 0 | CC36: 0 | CD36: 0 | CE36: 0 | CF36: 0 | CH36: 0 | CI36: 0 | CJ36: 0 | CK36: 0 | CL36: 0 | CM36: 0 | CN36: 0 | CO36: 0 | CP36: 0
A37: Net Income/(After Taxes and Donations) | B37: =B35-B36 -> 356000 | C37: =C35-C36 -> 30452000 | D37: =D35+D36 -> 56851000 | E37: =E35+E36 -> 88597418 | F37: =F35+F36 -> 57040877 | G37: =G35+G36 -> 61212521 | H37: =H35+H36 -> 35394973 | I37: =I35+I36 -> -33745366 | J37: =J35+J36 -> -31933391 | K37: =K35+K36 -> -37953401 | ... CS37: =CS35+CS36 -> 0

Sheet Financials
B2: MENTOR SACCO
B3: Year | C3: 2011 AUDITED | D3: 2012 audited | E3: 2013 audited | F3: 2014 audited | G3: audited2015 | H3: Audited 2016 | I3: 42736 | J3: 42767 | K3: 42795 | L3: 42826 | M3: 42856 | N3: 42887 | O3: 42917 | P3: 42948 | Q3: 42979 | R3: 43009 | S3: 43040 | T3: 43070 | U3: Audited 2017 | V3: 43101 | W3: 43132 | X3: 43160 | Y3: 43191 | Z3: 43221 | AA3: 43252 | AB3: 43282 | AC3: 43313 | AD3: 43344 | AE3: 43374 | AF3: 43405 | AG3: 43435 | AH3: Audited 2018 | AI3: 43466 | AJ3: 43497 | AK3: 43525 | AL3: 43556 | AM3: 43586 | AN3: 43617 | AO3: 43647 | AP3: 43678 | AQ3: 43709 | AR3: 43739 | AS3: 43770 | AT3: 43800 | AU3: Audited-2019 | AV3: 43831 | AW3: 43862 | AX3: 43891 | AY3: 43922 | AZ3: 43952 | BA3: 43983 | BB3: 44013 | BC3: 44044 | BD3: 44075 | BE3: 44105 | BF3: 44136 | BG3: 44166 | BH3: Audited-20 | BI3: 44197 | BJ3: 44228 | BK3: 44256 | BL3: 44287 | BM3: 44317 | BN3: 44348 | BO3: 44378 | BP3: 44409 | BQ3: 44440 | BR3: 44470 | BS3: 44501 | BT3: 44531 | BU3: Audited 2021 | BV3: 44562 | BW3: 44593 | BX3: 44621 | BY3: 44652 | BZ3: 44682 | CA3: 44713 | CB3: 44743 | CC3: 44774 | CD3: 44805 | CE3: 44835 | CF3: 44866 | CG3: 44896 | CH3: Audited 2022 | CI3: 44927 | CJ3: 44958 | CK3: 44986 | CL3: 45017 | CM3: 45047 | CN3: 45078 | CO3: 45108 | CP3: 45139 | CQ3: 45170 | CR3: 45200 | CS3: 45231 | CT3: 45261
A4: 1 | B4: Membership | D4: 9048 | E4: 7907 | F4: 9167 | G4: 12386 | H4: 13471 | U4: 16376 | AH4: 19056 | AU4: 22069 | BH4: 24356
A5: 2 | B5: Total Assets | C5: =SFP!B26 -> 1982931000 | D5: =SFP!C26 -> 2246183000 | E5: =SFP!D26 -> 2.8343649e+09 | F5: =SFP!E26 -> 3283953220 | G5: =SFP!F26 -> 3926234298 | H5: =SFP!G26 -> 4877108727 | I5: =SFP!H26 -> 4.9539748e+09 | J5: =SFP!I26 -> 4.8668645e+09 | ... CT5: =SFP!CS26 -> 0
A6: 3 | B6: Total Deposits | C6: =SFP!B31 -> 1540825000 | D6: =SFP!C31 -> 1708217000 | E6: =SFP!D31 -> 2027885000 | F6: =SFP!E31 -> 2476141469 | G6: =SFP!F31 -> 3007206335 | H6: =SFP!G31 -> 3588473178 | I6: =SFP!H31 -> 3.5792411e+09 | J6: =SFP!I31 -> 3.8071301e+09 | ... CT6: =SFP!CS31 -> 0
A7: 3.1 | B7: Deposits-Members(BOSA) | C7: =SFP!B30 -> 1309041000 | D7: =SFP!C30 -> 1412967000 | E7: =SFP!D30 -> 1638628000 | F7: =SFP!E30 -> 1909635651 | G7: =SFP!F30 -> 2204621249 | H7: =SFP!G30 -> 2548520382 | I7: =SFP!H30 -> 2.9156687e+09 | J7: =SFP!I30 -> 2.9495685e+09 | ... AB7: =SFP!AA30 -> 3792366999 | AC7: =SFP!AB31 -> 4.7682104e+09 | AD7: =SFP!AC31 -> 4.8065636e+09 | AE7: =SFP!AD31 -> 4.8657774e+09 | AF7: =SFP!AE31 -> 4.9231973e+09 | AG7: =SFP!AF31 -> 4.9756068e+09 | AH7: =SFP!AG31 -> 5135049618 | AI7: =SFP!AH31 -> 5.0383593e+09 | AJ7: =SFP!AI31 -> 5.4736396e+09 | ... CT7: =SFP!CS31 -> 0
A8: 3.2 | B8: Deposits-Customers(FOSA) | C8: =SFP!B28+SFP!B29 -> 231784000 | D8: =SFP!C28+SFP!C29 -> 295250000 | E8: =SFP!D28+SFP!D29 -> 389257000 | F8: =SFP!E28+SFP!E29 -> 566505818 | G8: =SFP!F28+SFP!F29 -> 802585086 | H8: =SFP!G28+SFP!G29 -> 1039952796 | I8: =SFP!H28+SFP!H29 -> 6.6357237e+08 | J8: =SFP!I28+SFP!I29 -> 8.575616e+08 | ... L8: =SFP!K28+SFP!K29 -> 7.060101e+08 | M8: =SFP!M27+SFP!L29 -> 0 | N8: =SFP!M28+SFP!M29 -> 7.552045e+08 | O8: =SFP!N28+SFP!N29 -> 7.7449626e+08 | P8: =SFP!O28+SFP!O29 -> 7.9182659e+08 | Q8: =SFP!P28+SFP!P29 -> 7.5439305e+08 | R8: =SFP!Q28+SFP!Q29 -> 8.0076958e+08 | S8: =SFP!R28+SFP!R29 -> 8.3889495e+08 | T8: =SFP!S28+SFP!S29 -> 8.4638712e+08 | U8: =SFP!T28+SFP!T29 -> 1371688449 | ... AB8: =SFP!AA28+SFP!AA29 -> 9.3175511e+08 | AC8: =SFP!AB29+SFP!AB30 -> 3.927336e+09 | AD8: =SFP!AC29+SFP!AC30 -> 3.9698697e+09 | AE8: =SFP!AD29+SFP!AD30 -> 4.0259161e+09 | AF8: =SFP!AE29+SFP!AE30 -> 4.0784074e+09 | AG8: =SFP!AF29+SFP!AF30 -> 4.1087124e+09 | AH8: =SFP!AG29+SFP!AG30 -> 4021917768 | AI8: =SFP!AH29+SFP!AH30 -> 4.1685423e+09 | AJ8: =SFP!AI29+SFP!AI30 -> 4.3714276e+09 | ... CT8: =SFP!CS29+SFP!CS30 -> 0
A9: 4 | B9: External Borrowing | C9: =SFP!B38 -> 49167000 | D9: =SFP!C38 -> 0 | E9: =SFP!D38 -> 0 | F9: =SFP!E38 -> 0 | G9: =SFP!F38 -> 0 | H9: =SFP!G38 -> 183333333 | I9: =SFP!H38 -> 183333333 | J9: =SFP!I38 -> 166666666 | ... AB9: =SFP!AA38 -> 4.7084164e+08 | AC9: =SFP!AB41 -> 3.3617104e+08 | AD9: =SFP!AC41 -> 3.4388072e+08 | AE9: =SFP!AD41 -> 3.4879522e+08 | AF9: =SFP!AE41 -> 3.5421089e+08 | AG9: =SFP!AF41 -> 3.6294537e+08 | AH9: =SFP!AG41 -> 362945371 | AI9: =SFP!AH41 -> 3.6696953e+08 | AJ9: =SFP!AI41 -> 4.436122e+08 | ... BR9: =SFP!BQ41 -> 605170489 | BS9: =SFP!BR30+SFP!BR31 -> 1.4052002e+10 | BT9: =SFP!BS41 -> 6.258378e+08 | BU9: =SFP!BT41 -> 625837800 | BV9: =SFP!BU41 -> 6.4762254e+08 | BW9: =SFP!BV41 -> 6.5259047e+08 | BX9: =SFP!BW41 -> 6.5548999e+08 | BY9: =SFP!BX41 -> 6.613253e+08 | BZ9: =SFP!BY41 -> 6.7461271e+08 | CA9: =SFP!BZ41 -> 6.8207954e+08 | ... CT9: =SFP!CS41 -> 0
A10: 4.1 | B10: Short term Liabilities | C10: =SFP!B33+SFP!B34+SFP!B35+SFP!B36+SFP!B37 -> 7232000 | D10: =SFP!C33+SFP!C34+SFP!C35+SFP!C36+SFP!C37 -> 273714000 | E10: =SFP!D33+SFP!D34+SFP!D35+SFP!D36+SFP!D37 -> 11930000 | F10: =SFP!E33+SFP!E34+SFP!E35+SFP!E36+SFP!E37 -> 278665461 | G10: =SFP!F33+SFP!F34+SFP!F35+SFP!F36+SFP!F37 -> 3.5486019e+08 | H10: =SFP!G33+SFP!G34+SFP!G35+SFP!G36+SFP!G37 -> 429264621 | I10: =SFP!H33+SFP!H34+SFP!H35+SFP!H36+SFP!H37 -> 4.834695e+08 | J10: =SFP!I33+SFP!I34+SFP!I35+SFP!I36+SFP!I37 -> 2.3797541e+08 | ... AB10: =SFP!AA33+SFP!AA34+SFP!AA35+SFP!AA36+SFP!AA37 -> 4.8705682e+08 | AC10: =SFP!AB35+SFP!AB36+SFP!AB37+SFP!AB38+SFP!AB39 -> 6.4278735e+09 | AD10: =SFP!AC35+SFP!AC36+SFP!AC37+SFP!AC38+SFP!AC39 -> 6.4715484e+09 | AE10: =SFP!AD35+SFP!AD36+SFP!AD37+SFP!AD38+SFP!AD39 -> 6.5335466e+09 | AF10: =SFP!AE35+SFP!AE36+SFP!AE37+SFP!AE38+SFP!AE39 -> 6.6418426e+09 | AG10: =SFP!AF35+SFP!AF36+SFP!AF37+SFP!AF38+SFP!AF39 -> 6.6931001e+09 | AH10: =SFP!AG35+SFP!AG36+SFP!AG37+SFP!AG38+SFP!AG39 -> 7.0118389e+09 | AI10: =SFP!AH35+SFP!AH36+SFP!AH37+SFP!AH38+SFP!AH39 -> 6.8054157e+09 | AJ10: =SFP!AI35+SFP!AI36+SFP!AI37+SFP!AI38+SFP!AI39 -> 6.4790036e+09 | ... BR10: =SFP!BQ35+SFP!BQ36+SFP!BQ37+SFP!BQ38+SFP!BQ39 -> 8.5534017e+09 | BS10: =SFP!BR31+SFP!BR32 -> 8.5813057e+09 | BT10: =SFP!BS35+SFP!BS36+SFP!BS37+SFP!BS38+SFP!BS39 -> 8.8706435e+09 | BU10: =SFP!BT35+SFP!BT36+SFP!BT37+SFP!BT38+SFP!BT39 -> 8814966681 | BV10: =SFP!BU35+SFP!BU36+SFP!BU37+SFP!BU38+SFP!BU39 -> 8.5940102e+09 | BW10: =SFP!BV35+SFP!BV36+SFP!BV37+SFP!BV38+SFP!BV39 -> 8.6106438e+09 | BX10: =SFP!BW35+SFP!BW36+SFP!BW37+SFP!BW38+SFP!BW39 -> 8.6597358e+09 | BY10: =SFP!BX35+SFP!BX36+SFP!BX37+SFP!BX38+SFP!BX39 -> 8.7519415e+09 | BZ10: =SFP!BY35+SFP!BY36+SFP!BY37+SFP!BY38+SFP!BY39 -> 9.0041594e+09 | CA10: =SFP!BZ35+SFP!BZ36+SFP!BZ37+SFP!BZ38+SFP!BZ39 -> 9.1528764e+09 | ... CT10: =SFP!CS35+SFP!CS36+SFP!CS37+SFP!CS38+SFP!CS39 -> 0
A13: 5 | B13: Share capital and Reserves
A14: 5.1 | B14: Core Capital | C14: =C17-(C27+C28) -> -24983000 | D14: =D17-(D27+D28) -> 16577000 | E14: =E17-(E27+E28) -> -12912000 | F14: =F17 -> 341841476 | G14: =G17 -> 392921038 | H14: =H17 -> 532313238 | I14: =I17 -> 5.3668483e+08 | J14: =J17 -> 5.1136793e+08 | K14: =K17 -> 5.171088e+08 | L14: =L17 -> 5.1333716e+08 | M14: =M17 -> 5.1622456e+08 | ... BT14: =BT17 -> 1.3969407e+09 | BU14: =BU17-BU27 -> 1463955041 | BV14: =BV17-BV27 -> 1.3027063e+09 | BW14: =BW17-BW27 -> 1.3115993e+09 | BX14: =BX17-BX27 -> 1.3092353e+09 | BY14: =BY17-BY27 -> 1.2944031e+09 | BZ14: =BZ17-BZ27 -> 1.294307e+09 | CA14: =CA17-CA27 -> 1.3156104e+09 | CB14: =CB17-CB27 -> 1.3217546e+09 | ... CN14: =CN17-CN27 -> 1.7825603e+09 | CO14: =CO17-CO28 -> 1.8217842e+09 | CP14: =CP17-CP28 -> 1828498875 | CQ14: =CQ17-CQ28 -> 1.862034e+09 | CR14: =CR17-CR28 -> 0 | CS14: =CS17-CS28 -> 0 | CT14: =CT17-CT28 -> 0
A15: 5.2 | B15: Institutional Capital | C15: =C14-C18 -> -41990000 | D15: =D14-D18 -> -1161000 | E15: =E14-E18 -> -59505000 | F15: =F14-F18 -> 290658161 | G15: =G14-G18 -> 334963906 | H15: =H14-H18 -> 369265106 | I15: =I14-I18 -> 3.7200036e+08 | J15: =J14-J18 -> 3.3551974e+08 | ... CT15: =CT14-CT18 -> 0
A17: 5.3 | B17: Total Capital | C17: =SUM(C18:C21) -> 115333000 | D17: =SUM(D18:D21) -> 152581000 | E17: =SUM(E18:E21) -> 257080000 | F17: =SUM(F18:F21) -> 341841476 | G17: =SUM(G18:G21) -> 392921038 | H17: =SUM(H18:H21) -> 532313238 | I17: =SUM(I18:I21) -> 5.3668483e+08 | J17: =SUM(J18:J21) -> 5.1136793e+08 | ... CT17: =SUM(CT18:CT21) -> 0
A18: 5.3.1 | B18: Members Share Capital | C18: =SFP!B41 -> 17007000 | D18: =SFP!C41 -> 17738000 | E18: =SFP!D41 -> 46593000 | F18: =SFP!E41 -> 51183315 | G18: =SFP!F41 -> 57957132 | H18: =SFP!G41 -> 163048132 | I18: =SFP!H41 -> 1.6468447e+08 | J18: =SFP!I41 -> 1.7584819e+08 | ... CT18: =SFP!CS41 -> 0
A19: 5.3.3 | B19: Retained Earnings | C19: =SFP!B43+SFP!B44 -> 63640000 | D19: =SFP!C43+SFP!C44 -> 90987000 | E19: =SFP!D43+SFP!D44 -> 149785000 | F19: =SFP!E43+SFP!E44 -> 190000000 | G19: =SFP!F43+SFP!F44 -> 213552906 | H19: =SFP!G43+SFP!G44 -> 215610102 | I19: =SFP!H43+SFP!H44 -> 2.5058786e+08 | J19: =SFP!I43+SFP!I44 -> 1.8186474e+08 | ... BH19: =SFP!BG43+SFP!BG44 -> 366063134 | BI19: =SFP!BH43+0.5*SFP!BH44 -> 3.7363504e+08 | BJ19: =SFP!BI43+0.5*SFP!BI44 -> 368327962 | BK19: =SFP!BJ43+0.5*SFP!BJ44 -> 3.6030266e+08 | BL19: =SFP!BK43+0.5*SFP!BK44 -> 3.6124217e+08 | BM19: =SFP!BL43+0.5*SFP!BL44 -> 3.8070677e+08 | BN19: =SFP!BM43+0.5*SFP!BM44 -> 3.7970998e+08 | BO19: =SFP!BN43+0.5*SFP!BN44 -> 3.9344879e+08 | BP19: =SFP!BO43+0.5*SFP!BO44 -> 3.9304198e+08 | BQ19: =SFP!BP43+0.5*SFP!BP44 -> 3.9552828e+08 | BR19: =SFP!BQ43+SFP!BQ44 -> 4.3746179e+08 | BS19: =SFP!BR43+SFP!BR44 -> 4.4419201e+08 | BT19: =SFP!BS43+0.5*SFP!BS44 -> 4.2022005e+08 | BU19: =SFP!BT43+SFP!BT44 -> 474856634 | BV19: =SFP!BU43+SFP!BU44 -> 4.5088854e+08 | BW19: =SFP!BV43+SFP!BV44 -> 4.5511859e+08 | BX19: =SFP!BW43+SFP!BW44 -> 4.5016505e+08 | BY19: =SFP!BX43+SFP!BX44 -> 4.298026e+08 | BZ19: =SFP!BY43+SFP!BY44 -> 4.1672405e+08 | CA19: =SFP!BZ43+SFP!BZ44 -> 4.308656e+08 | CB19: =SFP!CA43+SFP!CA44 -> 4.2757777e+08 | ... CT19: =SFP!CS43+SFP!CS44 -> 0
A20: 5.3.5 | B20: Statutory Reserves | C20: =SFP!B45 -> 33539000 | D20: =SFP!C45 -> 39631000 | E20: =SFP!D45 -> 54556000 | F20: =SFP!E45 -> 72274432 | G20: =SFP!F45 -> 91411000 | H20: =SFP!G45 -> 103653504 | I20: =SFP!H45 -> 91411000 | J20: =SFP!I45 -> 103653504 | ... CT20: =SFP!CS45 -> 0
A21: 5.3.6 | B21: Capital Reserve | C21: =SFP!B46 -> 1147000 | D21: =SFP!C46 -> 4225000 | E21: =SFP!D46 -> 6146000 | F21: =SFP!E46 -> 28383729 | G21: =SFP!F46 -> 30000000 | H21: =SFP!G46 -> 50001500 | I21: =SFP!H46 -> 30001500 | J21: =SFP!I46 -> 50001500 | ... CT21: =SFP!CS46 -> 0
A22: 5.3.7 | B22: Supplementary Capital & reserves
A23: a | B23: Proposed Dividends | C23: =SFP!B48 -> 150686000 | D23: =SFP!C48 -> 0 | E23: =SFP!D48 -> 201743000 | F23: =SFP!E48 -> 0 | G23: =SFP!F48 -> 0 | H23: =SFP!G48 -> 0 | I23: =SFP!H48 -> 0 | J23: =SFP!I48 -> 0 | ... O23: =SFP!N48 -> 0 | P23: =SFP!O47 -> 143724358 | Q23: =SFP!P47 -> 143724358 | R23: =SFP!Q47 -> 0 | S23: =SFP!R47 -> 0 | T23: =SFP!S47 -> 0 | U23: =SFP!T47 -> 184223390 | V23: =SFP!U47 -> 287448716 | W23: =SFP!V47 -> 184223390 | ... AB23: =SFP!AA47 -> 184223390 | AC23: =SFP!AB50 -> 1.0228238e+09 | AD23: =SFP!AC50 -> 1.0282369e+09 | AE23: =SFP!AD50 -> 1.0434957e+09 | AF23: =SFP!AE50 -> 1.0632653e+09 | AG23: =SFP!AF50 -> 1.1401068e+09 | AH23: =SFP!AG50 -> 1089269071 | AI23: =SFP!AH50 -> 1.1463676e+09 | AJ23: =SFP!AI50 -> 1.1568034e+09 | ... CT23: =SFP!CS50 -> 0
A24: b
A26: 6 | B26: Investments | C26: =C27+C28+C29 -> 140316000 | D26: =D27+D28+D29 -> 136004000 | E26: =E27+E28+E29 -> 269992000 | F26: =F27+F28+F29 -> 267823506 | G26: =G27+G28+G29 -> 249273506 | H26: =H27+H28+H29 -> 0 | I26: =I27+I28+I29 -> 2.2073579e+08 | J26: =J27+J28+J29 -> 193214051 | ... CT26: =CT27+CT28+CT29 -> 0
A27: 6.1 | B27: Investments in Coop bank, CIC, Kuscco, Kerussu & Codic | C27: =SFP!B12 -> 0 | D27: =SFP!C12 -> 136004000 | E27: =SFP!D12 -> 269992000 | F27: =SFP!E12 -> 267823506 | G27: =SFP!F12 -> 249273506 | H27: =SFP!G12 -> 0 | I27: =SFP!H12 -> 2.2073579e+08 | J27: =SFP!I12 -> 193214051 | ... CT27: =SFP!CS12 -> 0
A28: 6.2 | B28: Equity Investments (at cost) | C28: =SFP!B10 -> 140316000 | D28: =SFP!C10 -> 0 | E28: =SFP!D10 -> 0 | F28: =SFP!E10 -> 0 | G28: =SFP!F10 -> 0 | H28: =SFP!G10 -> 0 | I28: =SFP!H10 -> 0 | J28: =SFP!I10 -> 0 | ... CT28: =SFP!CS10 -> 0
A29: 6.3 | B29: Deposits in KUSCCO CFP | C29: =SFP!B11 -> 0 | D29: =SFP!C11 -> 0 | E29: =SFP!D11 -> 0 | F29: =SFP!E11 -> 0 | G29: =SFP!F11 -> 0 | H29: =SFP!G11 -> 0 | I29: =SFP!H11 -> 0 | J29: =SFP!I11 -> 0 | ... CT29: =SFP!CS11 -> 0
A31: 7 | B31: Net Loans & advances | C31: =C32-C33 -> 1447463000 | D31: =D32-D33 -> 1669487000 | E31: =E32-E33 -> 1976393000 | F31: =F32-F33 -> 2511315580 | G31: =G32-G33 -> 3150143542 | H31: =H32-H33 -> 4068599457 | I31: =I32-I33 -> 4.0453554e+09 | J31: =J32-J33 -> 4.060404e+09 | ... CT31: =CT32-CT33 -> 0
A32: 7.1 | B32: Gross Loans & advances | C32: =SFP!B14 -> 1458954000 | D32: =SFP!C14 -> 1687174000 | E32: =SFP!D14 -> 1994080000 | F32: =SFP!E14 -> 2539002896 | G32: =SFP!F14 -> 3182830858 | H32: =SFP!G14 -> 4116099457 | I32: =SFP!H14 -> 4.0900427e+09 | J32: =SFP!I14 -> 4.115904e+09 | ... CT32: =SFP!CS14 -> 0
A33: 7.3 | B33: Allowance for loan losses | C33: =SFP!B15 -> 11491000 | D33: =SFP!C15 -> 17687000 | E33: =SFP!D15 -> 17687000 | F33: =SFP!E15 -> 27687316 | G33: =SFP!F15 -> 32687316 | H33: =SFP!G15 -> 47500000 | I33: =SFP!H15 -> 44687316 | J33: =SFP!I15 -> 55500000 | ... CT33: =SFP!CS15 -> 0
A34: 7.4 | B34: Non Performing Loans | C34: 0 | D34: 0 | E34: 0 | F34: 0 | G34: 0 | H34: 0 | I34: 0 | J34: 0 | K34: 0 | L34: 0 | M34: 0 | N34: 0 | O34: 0 | P34: 0 | Q34: 1 | R34: 2 | S34: 3 | T34: 3 | U34: 3 | V34: 3 | W34: 3 | X34: 3 | Y34: 3 | Z34: 3 | AA34: 3 | AB34: 3 | AC34: 3 | AD34: 3 | AE34: 3 | AF34: 3 | AG34: 3 | AH34: 3 | AI34: 3 | AJ34: 3 | AK34: 3 | AL34: 3 | AM34: 3 | AN34: 3 | AO34: 3 | AP34: 3 | AQ34: 3 | AR34: 3 | AS34: 3 | AT34: 3 | AU34: 3 | AV34: 3 | AW34: 3 | AX34: 3 | AY34: 3 | AZ34: 3 | BA34: 3 | BB34: 3 | BC34: 3 | BD34: 3 | BE34: 3 | BF34: 3 | BG34: 3 | BH34: 3 | BI34: 3 | BJ34: 3 | BK34: 3 | BL34: 3 | BM34: 3 | BN34: 3 | BO34: 3 | BP34: 3 | BQ34: 3 | BR34: 3 | BS34: 3 | BT34: 3 | BU34: 3 | BV34: 3 | BW34: 3 | BX34: 3 | BY34: 3 | BZ34: 3 | CA34: 3 | CB34: 3 | CC34: 3 | CD34: 3 | CE34: 3 | CF34: 3 | CG34: 3 | CH34: 3 | CI34: 3 | CJ34: 3 | CK34: 3 | CL34: 3 | CM34: 3 | CN34: 3 | CO34: 3 | CP34: 3 | CQ34: 3 | CR34: 3 | CS34: 3 | CT34: 3
A35: 7.5 | B35: Required loan loss provision | C35: 0 | D35: 0 | E35: 0 | F35: 0 | G35: 0 | H35: 0 | I35: 0 | J35: 0 | K35: 0 | L35: 0 | M35: 0 | N35: 0 | O35: 0 | P35: 0 | Q35: 1 | R35: 2 | S35: 3 | T35: 3 | U35: 3 | V35: 3 | W35: 3 | X35: 3 | Y35: 3 | Z35: 3 | AA35: 3 | AB35: 3 | AC35: 3 | AD35: 3 | AE35: 3 | AF35: 3 | AG35: 3 | AH35: 3 | AI35: 3 | AJ35: 3 | AK35: 3 | AL35: 3 | AM35: 3 | AN35: 3 | AO35: 3 | AP35: 3 | AQ35: 3 | AR35: 3 | AS35: 3 | AT35: 3 | AU35: 3 | AV35: 3 | AW35: 3 | AX35: 3 | AY35: 3 | AZ35: 3 | BA35: 3 | BB35: 3 | BC35: 3 | BD35: 3 | BE35: 3 | BF35: 3 | BG35: 3 | BH35: 3 | BI35: 3 | BJ35: 3 | BK35: 3 | BL35: 3 | BM35: 3 | BN35: 3 | BO35: 3 | BP35: 3 | BQ35: 3 | BR35: 3 | BS35: 3 | BT35: 3 | BU35: 3 | BV35: 3 | BW35: 3 | BX35: 3 | BY35: 3 | BZ35: 3 | CA35: 3 | CB35: 3 | CC35: 3 | CD35: 3 | CE35: 3 | CF35: 3 | CG35: 3 | CH35: 3 | CI35: 3 | CJ35: 3 | CK35: 3 | CL35: 3 | CM35: 3 | CN35: 3 | CO35: 3 | CP35: 3 | CQ35: 3 | CR35: 3 | CS35: 3 | CT35: 3
A36: 7.6 | B36: Cash and Cash equipments | C36: =SFP!B4 -> 283849000 | D36: =SFP!C4 -> 110263000 | E36: =SFP!D4 -> 201351000 | F36: =SFP!E4 -> 182728629 | G36: =SFP!F4 -> 214035021 | H36: =SFP!G4 -> 258656183 | I36: =SFP!H4 -> 2.6039096e+08 | J36: =SFP!I4 -> 2.060013e+08 | ... CT36: =SFP!CS4 -> 0
A38: 8 | B38: Non-Earning Assets | C38: =SFP!B7+SFP!B16+SFP!B22+SFP!B23+SFP!B24+SFP!B25 -> 111303000 | D38: =SFP!C7+SFP!C16+SFP!C22+SFP!C23+SFP!C24+SFP!C25 -> 190173000 | E38: =SFP!D7+SFP!D16+SFP!D22+SFP!D23+SFP!D24+SFP!D25 -> 3.8662893e+08 | F38: =SFP!E7+SFP!E16+SFP!E22+SFP!E23+SFP!E24+SFP!E25 -> 322085505 | G38: =SFP!F7+SFP!F16+SFP!F22+SFP!F23+SFP!F24+SFP!F25 -> 312782229 | H38: =SFP!G7+SFP!G16+SFP!G22+SFP!G23+SFP!G24+SFP!G25 -> 317680938 | I38: =SFP!H7+SFP!H16+SFP!H22+SFP!H23+SFP!H24+SFP!H25 -> 4.2749267e+08 | J38: =SFP!I7+SFP!I16+SFP!I22+SFP!I23+SFP!I24+SFP!I25 -> 4.0724511e+08 | ... CT38: =SFP!CS7+SFP!CS16+SFP!CS22+SFP!CS23+SFP!CS24+SFP!CS25 -> 0
A39: 8.1 | B39: Property and Equipment | C39: =SFP!B22 -> 30561000 | D39: =SFP!C22 -> 32371000 | E39: =SFP!D22 -> 36204000 | F39: =SFP!E22 -> 51908954 | G39: =SFP!F22 -> 69245464 | H39: =SFP!G22 -> 103160569 | I39: =SFP!H22 -> 2.8750153e+08 | J39: =SFP!I22 -> 2.5621178e+08 | ... CT39: =SFP!CS22 -> 0
A41: 9 | B41: Turnover | C41: =C42+C43+C44 -> 272737000 | D41: =D42+D43+D44 -> 315395000 | E41: =E42+E43+E44 -> 391908000 | F41: =F42+F43+F44 -> 486302029 | G41: =G42+G43+G44 -> 557411649 | H41: =H42+H43+H44 -> 691077004 | I41: =I42+I43+I44 -> 60018212 | J41: =J42+J43+J44 -> 1.1929711e+08 | ... CT41: =CT42+CT43+CT44 -> 0
A42: 9.1 | B42: Loan Interest | C42: =SCI!B5 -> 253602000 | D42: =SCI!C5 -> 289168000 | E42: =SCI!D5 -> 356158000 | F42: =SCI!E5 -> 442597728 | G42: =SCI!F5 -> 503688132 | H42: =SCI!G5 -> 635979383 | I42: =SCI!H5 -> 56614856 | J42: =SCI!I5 -> 1.1177208e+08 | ... CT42: =SCI!CS5 -> 0
B43: Income from investments | C43: =SCI!B7 -> 18694000 | D43: =SCI!C7 -> 4718000 | E43: =SCI!D7 -> 28539000 | F43: =SCI!E7 -> 43704301 | G43: =SCI!F7 -> 38211607 | H43: =SCI!G7 -> 45694494 | I43: =SCI!H7 -> 3403356.2 | J43: =SCI!I7 -> 7525036.9 | ... CT43: =SCI!CS7 -> 0
A44: 9.2 | B44: Fees & Commissions | C44: =SCI!B6 -> 441000 | D44: =SCI!C6 -> 21509000 | E44: =SCI!D6 -> 7211000 | F44: =SCI!E6 -> 0 | G44: =SCI!F6 -> 15511910 | H44: =SCI!G6 -> 9403127 | I44: =SCI!H6 -> 0 | J44: =SCI!I6 -> 0 | ... CT44: =SCI!CS6 -> 0
B45: Average yield on loans | C45: =C42/C32 -> 0.17382453 | D45: =D42/D32 -> 0.17139193 | E45: =E42/E32 -> 0.17860768 | F45: =F42/F32 -> 0.1743195 | G45: =G42/G32 -> 0.15825162 | H45: =H42/H32 -> 0.15451021 | I45: =I42/I32 -> 0.013842118 | J45: =J42/J32 -> 0.027156142 | ... CT45: =CT42/CT32 -> #DIV/0!
A47: 10 | B47: Total Expenses (FinCosts + OpEx) | C47: =SUM(C48:C53) -> 188558000 | D47: =SUM(D48:D53) -> 235179000 | E47: =SUM(E48:E53) -> 267663000 | F47: =SUM(F48:F53) -> 339156068 | G47: =SUM(G48:G53) -> 4.0342833e+08 | H47: =SUM(H48:H53) -> 525056688 | I47: =SUM(I48:I53) -> 16568910 | J47: =SUM(J48:J53) -> 1.168215e+08 | ... CT47: =SUM(CT48:CT53) -> 0
A48: 10.1 | B48: Financial Exp. (Interest on deposits) | C48: =SCI!B13 -> 148036000 | D48: =SCI!C13 -> 172768000 | E48: =SCI!D13 -> 200843000 | F48: =SCI!E13 -> 252903029 | G48: =SCI!F13 -> 307717763 | H48: =SCI!G13 -> 374176451 | I48: =SCI!H13 -> 432589.6 | J48: =SCI!I13 -> 77703090 | ... CT48: =SCI!CS13 -> 0
A49: 10.2 | B49: Financial Exp. (Dividends) | C49: =SCI!B15 -> 2762000 | D49: =SCI!C15 -> 2091000 | E49: =SCI!D15 -> 0 | F49: =SCI!E15 -> 0 | G49: =SCI!F15 -> 0 | H49: =SCI!G15 -> 0 | I49: =SCI!H15 -> 0 | J49: =SCI!I15 -> 0 | ... CT49: =SCI!CS15 -> 0
A50: 10.3 | B50: Financial Exp. (Interest on bank loans) | C50: =SCI!B14 -> 9065000 | D50: =SCI!C14 -> 5096000 | E50: =SCI!D14 -> 0 | F50: =SCI!E14 -> 0 | G50: =SCI!F14 -> 0 | H50: =SCI!G14 -> 0 | I50: =SCI!H14 -> 2761000 | J50: =SCI!I14 -> 9804164.1 | ... CT50: =SCI!CS14 -> 0
A51: 10.4 | B51: Other Financial Expenses | C51: =SCI!B16+SCI!B17+SCI!B18 -> 1724000 | D51: =SCI!C16+SCI!C17+SCI!C18 -> 0 | E51: =SCI!D16+SCI!D17+SCI!D18 -> 1361000 | F51: =SCI!E16+SCI!E17+SCI!E18 -> 604670 | G51: =SCI!F16+SCI!F17+SCI!F18 -> 1357661.9 | H51: =SCI!G16+SCI!G17+SCI!G18 -> 2824104 | I51: =SCI!H16+SCI!H17+SCI!H18 -> 383011.6 | J51: =SCI!I16+SCI!I17+SCI!I18 -> 5977273.6 | ... CT51: =SCI!CS16+SCI!CS17+SCI!CS18 -> 0
A52: 10.5 | B52: Administrative Expenses | C52: =SCI!B28 -> 21460000 | D52: =SCI!C28 -> 21647000 | E52: =SCI!D28 -> 24356000 | F52: =SCI!E28 -> 37121094 | G52: =SCI!F28 -> 41527857 | H52: =SCI!G28 -> 82009129 | I52: =SCI!H28 -> 11139237 | J52: =SCI!I28 -> 20121634 | ... CT52: =SCI!CS28 -> 0
A53: 10.6 | B53: Governance Expenses | C53: =SCI!B25 -> 5511000 | D53: =SCI!C25 -> 33577000 | E53: =SCI!D25 -> 41103000 | F53: =SCI!E25 -> 48527275 | G53: =SCI!F25 -> 52825047 | H53: =SCI!G25 -> 66047004 | I53: =SCI!H25 -> 1853071 | J53: =SCI!I25 -> 3215333.4 | ... CT53: =SCI!CS25 -> 0
B54: LLP
B56: Net Surplus | C56: =SCI!B37 -> 356000 | D56: =SCI!C37 -> 30452000 | E56: =SCI!D37 -> 56851000 | F56: =SCI!E37 -> 88597418 | G56: =SCI!F37 -> 57040877 | H56: =SCI!G37 -> 61212521 | I56: =SCI!H37 -> 35394973 | J56: =SCI!I37 -> -33745366 | ... CT56: =SCI!CS37 -> 0
B57: Core Capital

Sheet Prudential Ratios
A1: MENTOR SACCO SOCIETY LTD
A2: Sacco Financial Performance
A4: FINANCIAL SOUNDNESS INDICATORS | B4: Prude. Std | C4: 2011 AUDITED | D4: 2012 audited | E4: 2013 audited | F4: 2014 audited | G4: Audited 2015 | H4: Audited 2016 | I4: 42736 | J4: 42767 | K4: 42795 | L4: 42826 | M4: 42856 | N4: 42887 | O4: 42917 | P4: 42948 | Q4: 42979 | R4: 43009 | S4: 43040 | T4: 43070 | U4: Audited 2017 | V4: 43101 | W4: 43132 | X4: 43160 | Y4: 43191 | Z4: 43221 | AA4: 43252 | AB4: 43282 | AC4: 43313 | AD4: 43344 | AE4: 43374 | AF4: 43405 | AG4: 43435 | AH4: Audited 2018 | AI4: 43466 | AJ4: 43497 | AK4: 43525 | AL4: 43556 | AM4: 43586 | AN4: 43617 | AO4: 43647 | AP4: 43678 | AQ4: 43709 | AR4: 43739 | AS4: 43770 | AT4: 43800 | AU4: Audited-2019 | AV4: 43831 | AW4: 43862 | AX4: 43891 | AY4: 43922 | AZ4: 43952 | BA4: 43983 | BB4: 44013 | BC4: 44044 | BD4: 44075 | BE4: 44105 | BF4: 44136 | BG4: 44166 | BH4: Audited-20 | BI4: 44197 | BJ4: 44228 | BK4: 44256 | BL4: 44287 | BM4: 44317 | BN4: 44348 | BO4: 44378 | BP4: 44409 | BQ4: 44440 | BR4: 44470 | BS4: 44501 | BT4: 44531 | BU4: Audited 2021 | BV4: 44562 | BW4: 44593 | BX4: 44621 | BY4: 44652 | BZ4: 44682 | CA4: 44713 | CB4: 44743 | CC4: 44774 | CD4: 44805 | CE4: 44835 | CF4: 44866 | CG4: 44896 | CH4: Audited 2022 | CI4: 44927 | CJ4: 44958 | CK4: 44986 | CL4: 45017 | CM4: 45047 | CN4: 45078 | CO4: 45108 | CP4: 45139 | CQ4: 45170 | CR4: 45200 | CS4: 45231 | CT4: 45261 | CU4: 45292 | CV4: 45323 | CW4: 45352 | CX4: 45383 | CY4: 45413 | CZ4: 45444 | DA4: 45474 | DB4: 45505 | DC4: 45536 | DD4: 45566 | DE4: 45597
A5: CAPITAL ADEQUACY REQUIREMENTS
A6: Core capital | B6: ≥ Ksh.10M | C6: =Financials!C14/1000000 -> -24.983 | D6: =Financials!D14/1000000 -> 16.577 | E6: =Financials!E14/1000000 -> -12.912 | F6: =Financials!F14/1000000 -> 341.84148 | G6: =Financials!G14/1000000 -> 392.92104 | H6: =Financials!H14/1000000 -> 532.31324 | I6: =Financials!I14/1000000 -> 536.68483 | J6: =Financials!J14/1000000 -> 511.36793 | ... DV6: =Financials!DV14/1000000 -> 0
A7: Core capital /Total Assets | B7: ≥ 10% | C7: =Financials!C14/Financials!C5 -> -0.012599026 | D7: =Financials!D14/Financials!D5 -> 0.0073800754 | E7: =Financials!E14/Financials!E5 -> -0.0045555178 | F7: =Financials!F14/Financials!F5 -> 0.1040945 | G7: =Financials!G14/Financials!G5 -> 0.1000758 | H7: =Financials!H14/Financials!H5 -> 0.10914525 | I7: =Financials!I14/Financials!I5 -> 0.10833419 | J7: =Financials!J14/Financials!J5 -> 0.10507133 | ... DV7: =Financials!DV14/Financials!DV5 -> #DIV/0!
A8: Core capital /Total Deposits | B8: ≥ 8% | C8: =Financials!C14/Financials!C6 -> -0.016214041 | D8: =Financials!D14/Financials!D6 -> 0.0097042706 | E8: =Financials!E14/Financials!E6 -> -0.006367225 | F8: =Financials!F14/Financials!F6 -> 0.1380541 | G8: =Financials!G14/Financials!G6 -> 0.13065982 | H8: =Financials!H14/Financials!H6 -> 0.14833976 | I8: =Financials!I14/Financials!I6 -> 0.14994375 | J8: =Financials!J14/Financials!J6 -> 0.13431848 | ... DV8: =Financials!DV14/Financials!DV6 -> #DIV/0!
A9: Share Capital/Total Assets | B9: ≤2% | C9: =Financials!C18/Financials!C5 -> 0.0085766978 | D9: =Financials!D18/Financials!D5 -> 0.0078969523 | E9: =Financials!E18/Financials!E5 -> 0.016438603 | F9: =Financials!F18/Financials!F5 -> 0.015585884 | G9: =Financials!G18/Financials!G5 -> 0.014761506 | H9: =Financials!H18/Financials!H5 -> 0.03343131 | I9: =Financials!I18/Financials!I5 -> 0.033242896 | J9: =Financials!J18/Financials!J5 -> 0.036131722 | ... DV9: =Financials!DV18/Financials!DV5 -> #DIV/0!
A10: Institutional Capital/Total Assets | B10: ≥ 8% | C10: =Financials!C15/Financials!C5 -> -0.021175724 | D10: =Financials!D15/Financials!D5 -> -0.00051687685 | E10: =Financials!E15/Financials!E5 -> -0.020994121 | F10: =Financials!F15/Financials!F5 -> 0.088508618 | G10: =Financials!G15/Financials!G5 -> 0.085314294 | H10: =Financials!H15/Financials!H5 -> 0.075713938 | I10: =Financials!I15/Financials!I5 -> 0.07509129 | J10: =Financials!J15/Financials!J5 -> 0.06893961 | ... DV10: =Financials!DV15/Financials!DV5 -> #DIV/0!
A12: ASSET MIX AND QUALITY
A13: Non Earning Assets
A14: Non earning Assets/Total assets | B14: ≤ 10% | C14: =Financials!C38/Financials!C5 -> 0.056130546 | D14: =Financials!D38/Financials!D5 -> 0.084664963 | E14: =Financials!E38/Financials!E5 -> 0.13640761 | F14: =Financials!F38/Financials!F5 -> 0.098078591 | G14: =Financials!G38/Financials!G5 -> 0.079664688 | H14: =Financials!H38/Financials!H5 -> 0.065137145 | I14: =Financials!I38/Financials!I5 -> 0.086292862 | J14: =Financials!J38/Financials!J5 -> 0.0836771 | ... DV14: =Financials!DV38/Financials!DV5 -> #DIV/0!
A15: Property and Equipment/Total Assets | B15: ≤ 5% | C15: =Financials!C39/Financials!C5 -> 0.015412034 | D15: =Financials!D39/Financials!D5 -> 0.01441156 | E15: =Financials!E39/Financials!E5 -> 0.012773232 | F15: =Financials!F39/Financials!F5 -> 0.015806849 | G15: =Financials!G39/Financials!G5 -> 0.01763661 | H15: =Financials!H39/Financials!H5 -> 0.021151993 | I15: =Financials!I39/Financials!I5 -> 0.058034517 | J15: =Financials!J39/Financials!J5 -> 0.052644116 | ... DV15: =Financials!DV39/Financials!DV5 -> #DIV/0!
A16: Non Performing loans/Gross Loans | B16: ≤ 6% | C16: =Financials!C34/Financials!C32 -> 0 | D16: =Financials!D34/Financials!D32 -> 0 | E16: =Financials!E34/Financials!E32 -> 0 | F16: =Financials!F34/Financials!F32 -> 0 | G16: =Financials!G34/Financials!G32 -> 0 | H16: =Financials!H34/Financials!H32 -> 0 | I16: =Financials!I34/Financials!I32 -> 0 | J16: =Financials!J34/Financials!J32 -> 0 | ... DV16: =Financials!DV34/Financials!DV32 -> #DIV/0!
A18: Earning Assets
A19: Equities & Investments/Deposits | B19: ≤ 5% | C19: =Financials!C26/Financials!C6 -> 0.091065501 | D19: =Financials!D26/Financials!D6 -> 0.079617519 | E19: =Financials!E26/Financials!E6 -> 0.1331397 | F19: =Financials!F26/Financials!F6 -> 0.10816163 | G19: =Financials!G26/Financials!G6 -> 0.082892053 | H19: =Financials!H26/Financials!H6 -> 0 | I19: =Financials!I26/Financials!I6 -> 0.061671115 | J19: =Financials!J26/Financials!J6 -> 0.050750577 | ... DV19: =Financials!DV26/Financials!DV6 -> #DIV/0!
A20: Equities & Investments/Core Capital | B20: ≤ 40% | C20: =Financials!C26/Financials!C14 -> -5.6164592 | D20: =Financials!D26/Financials!D14 -> 8.2043796 | E20: =Financials!E26/Financials!E14 -> -20.910161 | F20: =Financials!F26/Financials!F14 -> 0.78347282 | G20: =Financials!G26/Financials!G14 -> 0.6344112 | H20: =Financials!H26/Financials!H14 -> 0 | I20: =Financials!I26/Financials!I14 -> 0.411295 | J20: =Financials!J26/Financials!J14 -> 0.37783764 | ... DV20: =Financials!DV26/Financials!DV14 -> #DIV/0!
A21: Net Loans & advances /Total assets | B21: NPR | C21: =Financials!C31/Financials!C5 -> 0.72996136 | D21: =Financials!D31/Financials!D5 -> 0.74325511 | E21: =Financials!E31/Financials!E5 -> 0.69729659 | F21: =Financials!F31/Financials!F5 -> 0.76472331 | G21: =Financials!G31/Financials!G5 -> 0.80233203 | H21: =Financials!H31/Financials!H5 -> 0.83422365 | I21: =Financials!I31/Financials!I5 -> 0.8165878 | J21: =Financials!J31/Financials!J5 -> 0.83429568 | ... DV21: =Financials!DV31/Financials!DV5 -> #DIV/0!
A23: FUNDING MIX
A24: Total Deposits/Total Assets | B24: NPR | C24: =Financials!C6/Financials!C5 -> 0.77704418 | D24: =Financials!D6/Financials!D5 -> 0.7604977 | E24: =Financials!E6/Financials!E5 -> 0.71546362 | F24: =Financials!F6/Financials!F5 -> 0.75401241 | G24: =Financials!G6/Financials!G5 -> 0.76592636 | H24: =Financials!H6/Financials!H5 -> 0.73577879 | I24: =Financials!I6/Financials!I5 -> 0.72249884 | J24: =Financials!J6/Financials!J5 -> 0.78225521 | ... DV24: =Financials!DV6/Financials!DV5 -> #DIV/0!
A25: BOSA Deposits/Total Assets | B25: NPR | C25: =Financials!C7/Financials!C5 -> 0.66015459 | D25: =Financials!D7/Financials!D5 -> 0.62905249 | E25: =Financials!E7/Financials!E5 -> 0.5781288 | F25: =Financials!F7/Financials!F5 -> 0.58150513 | G25: =Financials!G7/Financials!G5 -> 0.56151036 | H25: =Financials!H7/Financials!H5 -> 0.52254738 | I25: =Financials!I7/Financials!I5 -> 0.58855138 | J25: =Financials!J7/Financials!J5 -> 0.60605109 | ... DV25: =Financials!DV7/Financials!DV5 -> #DIV/0!
A26: FOSA Deposits/Total Assets | B26: NPR | C26: =Financials!C8/Financials!C5 -> 0.11688959 | D26: =Financials!D8/Financials!D5 -> 0.13144521 | E26: =Financials!E8/Financials!E5 -> 0.13733482 | F26: =Financials!F8/Financials!F5 -> 0.17250727 | G26: =Financials!G8/Financials!G5 -> 0.20441599 | H26: =Financials!H8/Financials!H5 -> 0.21323142 | I26: =Financials!I8/Financials!I5 -> 0.13394746 | J26: =Financials!J8/Financials!J5 -> 0.17620412 | ... DV26: =Financials!DV8/Financials!DV5 -> #DIV/0!
A27: External Borrowing/Total assets | B27: ≤ 25% | C27: =Financials!C9/Financials!C5 -> 0.024795114 | D27: =Financials!D9/Financials!D5 -> 0 | E27: =Financials!E9/Financials!E5 -> 0 | F27: =Financials!F9/Financials!F5 -> 0 | G27: =Financials!G9/Financials!G5 -> 0 | H27: =Financials!H9/Financials!H5 -> 0.037590577 | I27: =Financials!I9/Financials!I5 -> 0.03700732 | J27: =Financials!J9/Financials!J5 -> 0.034245183 | ... DV27: =Financials!DV9/Financials!DV5 -> #DIV/0!
A29: GROWTH RATIOS
A30: Total Assets | B30: NPR | C30: =Financials!C5/Financials!B5-1 -> #VALUE! | D30: =Financials!D5/Financials!C5-1 -> 0.13275903 | E30: =Financials!E5/Financials!D5-1 -> 0.26185842 | F30: =Financials!F5/Financials!E5-1 -> 0.15862047 | G30: =Financials!G5/Financials!F5-1 -> 0.19558168 | H30: =Financials!H5/Financials!G5-1 -> 0.24218484 | I30: =Financials!I5/Financials!H5-1 -> 0.015760588 | J30: =Financials!J5/Financials!I5-1 -> -0.017583926 | ... DV30: =Financials!DV5/Financials!DU5-1 -> #DIV/0!
A31: Total Deposits | B31: NPR | C31: =Financials!C6/Financials!B6-1 -> #VALUE! | D31: =Financials!D6/Financials!C6-1 -> 0.10863791 | E31: =Financials!E6/Financials!D6-1 -> 0.18713548 | F31: =Financials!F6/Financials!E6-1 -> 0.2210463 | G31: =Financials!G6/Financials!F6-1 -> 0.21447275 | H31: =Financials!H6/Financials!G6-1 -> 0.19329131 | I31: =Financials!I6/Financials!H6-1 -> -0.0025727124 | J31: =Financials!J6/Financials!I6-1 -> 0.06366966 | ... DV31: =Financials!DV6/Financials!DU6-1 -> #DIV/0!
A32: FOSA Deposits | B32: NPR | C32: =Financials!C8/Financials!B8-1 -> #VALUE! | D32: =Financials!D8/Financials!C8-1 -> 0.27381528 | E32: =Financials!E8/Financials!D8-1 -> 0.31839797 | F32: =Financials!F8/Financials!E8-1 -> 0.45535165 | G32: =Financials!G8/Financials!F8-1 -> 0.41672876 | H32: =Financials!H8/Financials!G8-1 -> 0.29575395 | I32: =Financials!I8/Financials!H8-1 -> -0.36192069 | J32: =Financials!J8/Financials!I8-1 -> 0.29234073 | ... DV32: =Financials!DV8/Financials!DU8-1 -> #DIV/0!
A33: BOSA Deposits | B33: NPR | C33: =Financials!C7/Financials!B7-1 -> #VALUE! | D33: =Financials!D7/Financials!C7-1 -> 0.079390943 | E33: =Financials!E7/Financials!D7-1 -> 0.1597072 | F33: =Financials!F7/Financials!E7-1 -> 0.16538693 | G33: =Financials!G7/Financials!F7-1 -> 0.15447219 | H33: =Financials!H7/Financials!G7-1 -> 0.15599012 | I33: =Financials!I7/Financials!H7-1 -> 0.14406333 | J33: =Financials!J7/Financials!I7-1 -> 0.011626778 | ... DV33: =Financials!DV7/Financials!DU7-1 -> #DIV/0!
A34: Net Loans & advances | B34: NPR | C34: =Financials!C31/Financials!B31-1 -> #VALUE! | D34: =Financials!D31/Financials!C31-1 -> 0.15338838 | E34: =Financials!E31/Financials!D31-1 -> 0.18383252 | F34: =Financials!F31/Financials!E31-1 -> 0.27065598 | G34: =Financials!G31/Financials!F31-1 -> 0.2543798 | H34: =Financials!H31/Financials!G31-1 -> 0.29156002 | I34: =Financials!I31/Financials!H31-1 -> -0.0057130326 | J34: =Financials!J31/Financials!I31-1 -> 0.0037199774 | ... DV34: =Financials!DV31/Financials!DU31-1 -> #DIV/0!
A35: Core capital | B35: NPR | C35: =Financials!C14/Financials!B14-1 -> #VALUE! | D35: =Financials!D14/Financials!C14-1 -> -1.6635312 | E35: =Financials!E14/Financials!D14-1 -> -1.7789105 | F35: =Financials!F14/Financials!E14-1 -> -27.474712 | G35: =Financials!G14/Financials!F14-1 -> 0.14942471 | H35: =Financials!H14/Financials!G14-1 -> 0.35475881 | I35: =Financials!I14/Financials!H14-1 -> 0.0082124398 | J35: =Financials!J14/Financials!I14-1 -> -0.04717274 | ... DV35: =Financials!DV14/Financials!DU14-1 -> #DIV/0!
A36: Total Gross Income | B36: NPR | C36: =Financials!C41/Financials!B41-1 -> #VALUE! | D36: =Financials!D41/Financials!C41-1 -> 0.15640709 | E36: =Financials!E41/Financials!D41-1 -> 0.24259421 | F36: =Financials!F41/Financials!E41-1 -> 0.24085762 | G36: =Financials!G41/Financials!F41-1 -> 0.14622522 | H36: =Financials!H41/Financials!G41-1 -> 0.23979649 | I36: =Financials!I41/Financials!H41-1 -> -0.91315264 | J36: =Financials!J41/Financials!I41-1 -> 0.98768188 | ... DV36: =Financials!DV41/Financials!DU41-1 -> #DIV/0!
A37: Membership | B37: NPR | C37: 8795 | D37: 8796 | E37: 8797 | F37: 8798 | G37: 8799 | H37: 8800 | I37: 8801 | J37: 8802 | K37: 8803 | L37: 8804 | M37: 8805 | N37: 8806 | O37: 8807 | P37: 8808 | Q37: 8809 | R37: 8810 | S37: 8811 | T37: 8812 | U37: 8813 | V37: 8814 | W37: 8815 | X37: 8816 | Y37: 8817 | Z37: 8818 | AA37: 8819 | AB37: 8820 | AC37: 8821 | AD37: 8822 | AE37: 8823 | AF37: 8824 | AG37: 8825 | AH37: 8826 | AI37: 8827 | AJ37: 8828 | AK37: 8829 | AL37: 8830 | AM37: 8831 | AN37: 8832 | AO37: 8833 | AP37: 8834 | AQ37: 8835 | AR37: 8836 | AS37: 8837 | AT37: 8838 | AU37: 8839 | AV37: 8840 | AW37: 8841 | AX37: 8842 | AY37: 8843 | AZ37: 8844 | BA37: 8845 | BB37: 8846 | BC37: 8847 | BD37: 8848 | BE37: 8849 | BF37: 8850 | BG37: 8851 | BH37: 8852 | BI37: 8853 | BJ37: 8854 | BK37: 8855 | BL37: 8856 | BM37: 8857 | BN37: 8858 | BO37: 8859 | BP37: 8860 | BQ37: 8861 | BR37: 8862 | BS37: 8863 | BT37: 8864 | BU37: 8865 | BV37: 8866 | BW37: 8867 | BX37: 8868 | BY37: 8869 | BZ37: 8870 | CA37: 8871 | CB37: 8872 | CC37: 8873 | CD37: 8874 | CE37: 8875 | CF37: 8876 | CG37: 8877 | CH37: 8878 | CI37: 8879 | CJ37: 8880 | CK37: 8881 | CL37: 8882 | CM37: 8883 | CN37: 8884 | CO37: 8885 | CP37: 8886 | CQ37: 8887 | CR37: 8888 | CS37: 8889 | CT37: 8890 | CU37: 8891 | CV37: 8892 | CW37: 8893 | CX37: 8894 | CY37: 8895 | CZ37: 8896 | DA37: 8897 | DB37: 8898 | DC37: 8899 | DD37: 8900 | DE37: 8901 | DF37: 8902 | DG37: 8903 | DH37: 8904 | DI37: 8905 | DJ37: 8906 | DK37: 8907 | DL37: 8908 | DM37: 8909 | DN37: 8910 | DO37: 8911 | DP37: 8912 | DQ37: 8913 | DR37: 8914 | DS37: 8915 | DT37: 8916 | DU37: 8917 | DV37: 8918
A39: Efficiency Ratios
A40: FinCost-Deposits/Average Deposits | B40: NPR | C40: =Financials!C48/((Financials!C6+Financials!B6)/2) -> #VALUE! | D40: =Financials!D48/((Financials!D6+Financials!C6)/2) -> 0.10635012 | E40: =Financials!E48/((Financials!E6+Financials!D6)/2) -> 0.10751473 | F40: =Financials!F48/((Financials!F6+Financials!E6)/2) -> 0.11230086 | G40: =Financials!G48/((Financials!G6+Financials!F6)/2) -> 0.11223719 | H40: =Financials!H48/((Financials!H6+Financials!G6)/2) -> 0.11346108 | I40: =Financials!I48/((Financials!I6+Financials!H6)/2) -> 0.00012070504 | J40: =Financials!J48/((Financials!J6+Financials!I6)/2) -> 0.021039584 | ... DV40: =Financials!DV48/((Financials!DV6+Financials!DU6)/2) -> #DIV/0!
A41: FinCost-Shares/Average Share capital | B41: NPR | C41: =Financials!C49/((Financials!C18+Financials!B18)/2) -> #VALUE! | D41: =Financials!D49/((Financials!D18+Financials!C18)/2) -> 0.12036264 | E41: =Financials!E49/((Financials!E18+Financials!D18)/2) -> 0 | F41: =Financials!F49/((Financials!F18+Financials!E18)/2) -> 0 | G41: =Financials!G49/((Financials!G18+Financials!F18)/2) -> 0 | H41: =Financials!H49/((Financials!H18+Financials!G18)/2) -> 0 | I41: =Financials!I49/((Financials!I18+Financials!H18)/2) -> 0 | J41: =Financials!J49/((Financials!J18+Financials!I18)/2) -> 0 | ... DV41: =Financials!DV49/((Financials!DV18+Financials!DU18)/2) -> #DIV/0!
A42: FinCost-Ext Loans/Average Ext Loans | B42: NPR | C42: =Financials!C50/((Financials!C9+Financials!B9)/2) -> #VALUE! | D42: =Financials!D50/((Financials!D9+Financials!C9)/2) -> 0.20729351 | E42: =Financials!E50/((Financials!E9+Financials!D9)/2) -> #DIV/0! | F42: =Financials!F50/((Financials!F9+Financials!E9)/2) -> #DIV/0! | G42: =Financials!G50/((Financials!G9+Financials!F9)/2) -> #DIV/0! | H42: =Financials!H50/((Financials!H9+Financials!G9)/2) -> 0 | I42: =Financials!I50/((Financials!I9+Financials!H9)/2) -> 0.01506 | J42: =Financials!J50/((Financials!J9+Financials!I9)/2) -> 0.056023795 | ... DV42: =Financials!DV50/((Financials!DV9+Financials!DU9)/2) -> #DIV/0!
A43: OpEx/Average Total Assets | B43: NPR | C43: =(Financials!C52+Financials!C53)/((Financials!C5+Financials!B5)/2) -> #VALUE! | D43: =(Financials!D52+Financials!D53)/((Financials!D5+Financials!C5)/2) -> 0.026116108 | E43: =(Financials!E52+Financials!E53)/((Financials!E5+Financials!D5)/2) -> 0.02576848 | F43: =(Financials!F52+Financials!F53)/((Financials!F5+Financials!E5)/2) -> 0.027997357 | G43: =(Financials!G52+Financials!G53)/((Financials!G5+Financials!F5)/2) -> 0.026172108 | H43: =(Financials!H52+Financials!H53)/((Financials!H5+Financials!G5)/2) -> 0.033636343 | I43: =(Financials!I52+Financials!I53)/((Financials!I5+Financials!H5)/2) -> 0.0026431081 | J43: =(Financials!J52+Financials!J53)/((Financials!J5+Financials!I5)/2) -> 0.0047525404 | ... DV43: =(Financials!DV52+Financials!DV53)/((Financials!DV5+Financials!DU5)/2) -> #DIV/0!
A44: Avge yield on Net loans | B44: NPR | C44: =Financials!C42/((Financials!C31+Financials!B31)/2) -> #VALUE! | D44: =Financials!D42/((Financials!D31+Financials!C31)/2) -> 0.18554549 | E44: =Financials!E42/((Financials!E31+Financials!D31)/2) -> 0.1953756 | F44: =Financials!F42/((Financials!F31+Financials!E31)/2) -> 0.19724887 | G44: =Financials!G42/((Financials!G31+Financials!F31)/2) -> 0.1779358 | H44: =Financials!H42/((Financials!H31+Financials!G31)/2) -> 0.17620225 | I44: =Financials!I42/((Financials!I31+Financials!H31)/2) -> 0.013954935 | J44: =Financials!J42/((Financials!J31+Financials!I31)/2) -> 0.027578434 | ... DV44: =Financials!DV42/((Financials!DV31+Financials!DU31)/2) -> #DIV/0!
A45: OpEx/Gross Loans | B45: NPR
A46: Liquidity Ratio
A47: minimum Liquidity | B47: 0.15 | C47: =SFP!B4/(SFP!B28+SFP!B29) -> 1.2246272 | D47: =SFP!C4/(SFP!C28+SFP!C29) -> 0.37345639 | E47: =SFP!D4/(SFP!D28+SFP!D29) -> 0.51727008 | F47: =SFP!E4/(SFP!E28+SFP!E29) -> 0.32255384 | G47: =SFP!F4/(SFP!F28+SFP!F29+SFP!F33+SFP!F37) -> 0.18492021 | H47: =SFP!G4/(SFP!G28+SFP!G29+SFP!G33+SFP!G37) -> 0.17605031 | I47: =SFP!H4/(SFP!H28+SFP!H29+SFP!H33+SFP!H37) -> 0.23050629 | J47: =SFP!I4/(SFP!I28+SFP!I29+SFP!I33+SFP!I37) -> 0.19142556 | K47: =SFP!J4/(SFP!J28+SFP!J29+SFP!J33+SFP!J37) -> 0.10476851 | L47: =SFP!K4/(SFP!K28+SFP!K29+SFP!K33+SFP!K37) -> 0.014143075 | M47: =SFP!L4/(SFP!L28+SFP!L29+SFP!L33+SFP!L37) -> 0.10977559 | N47: =SFP!M4/(SFP!M28+SFP!M29+SFP!M33+SFP!M37) -> 0.27039129 | ... AT47: =SFP!AS4/(SFP!AS28+SFP!AS29+SFP!AS33+SFP!AS37) -> 0.6286625 | AU47: =SFP!AT4/(SFP!AT28+SFP!AT29+SFP!AT34+SFP!AT37) -> 0.32068195 | AV47: =SFP!AU4/(SFP!AU28+SFP!AU29+SFP!AU34+SFP!AU37) -> 0.39184588 | AW47: =SFP!AV4/(SFP!AV28+SFP!AV29+SFP!AV34+SFP!AV37) -> 0.43809378 | AX47: =SFP!AW4/(SFP!AW28+SFP!AW29+SFP!AW34+SFP!AW37) -> 0.47256452 | AY47: =SFP!AX4/(SFP!AX28+SFP!AX29+SFP!AX34+SFP!AX37) -> 0.59927824 | AZ47: =SFP!AY4/(SFP!AY28+SFP!AY29+SFP!AY34+SFP!AY37) -> 0.67883035 | BA47: =SFP!AZ4/(SFP!AZ28+SFP!AZ29+SFP!AZ34+SFP!AZ37) -> 0.76758377 | BB47: =SFP!BA4/(SFP!BA28+SFP!BA29+SFP!BA34+SFP!BA37) -> 0.70076313 | ... CM47: =SFP!CL4/(SFP!CL28+SFP!CL29+SFP!CL34+SFP!CL37) -> 0.8263777 | CN47: =SFP!CN4/(SFP!CN28+SFP!CN29+SFP!CN34+SFP!CN37) -> 0.9036452 | CO47: =SFP!CO4/(SFP!CO28+SFP!CO29+SFP!CO34+SFP!CO37) -> 0.85919003 | CP47: =SFP!CP4/(SFP!CP28+SFP!CP29+SFP!CP34+SFP!CP37) -> 0.87968807 | CQ47: =SFP!CQ4/(SFP!CQ28+SFP!CQ29+SFP!CQ34+SFP!CQ37) -> #DIV/0! | CR47: =SFP!CR4/(SFP!CR28+SFP!CR29+SFP!CR34+SFP!CR37) -> #DIV/0! | CS47: =SFP!CS4/(SFP!CS28+SFP!CS29+SFP!CS34+SFP!CS37) -> #DIV/0! | CT47: =SFP!CT4/(SFP!CT28+SFP!CT29+SFP!CT34+SFP!CT37) -> #DIV/0! | CU47: =SFP!CU4/(SFP!CU28+SFP!CU29+SFP!CU34+SFP!CU37) -> #DIV/0! | ... DV47: =SFP!DV4/(SFP!DV28+SFP!DV29+SFP!DV34+SFP!DV37) -> #DIV/0!
A48: technical Liquidity | C48: =SFP!B4/(SFP!B31+SFP!B32-SFP!B38) -> 0.18335824 | D48: =SFP!C4/(SFP!C31+SFP!C32-SFP!C38) -> 0.055634127 | E48: =SFP!D4/(SFP!D31+SFP!D32-SFP!D38) -> 0.098710422 | F48: =SFP!E4/(SFP!E31+SFP!E32-SFP!E38) -> 0.06633083 | G48: =SFP!F4/(SFP!F28+SFP!F29+SFP!F33+SFP!F37+SFP!F38) -> 0.18492021 | H48: =SFP!G4/(SFP!G28+SFP!G29+SFP!G33+SFP!G37+SFP!G38) -> 0.15651936 | I48: =SFP!H4/(SFP!H28+SFP!H29+SFP!H33+SFP!H37+SFP!H38) -> 0.19832039 | J48: =SFP!I4/(SFP!I28+SFP!I29+SFP!I33+SFP!I37+SFP!I38) -> 0.16575449 | K48: =SFP!J4/(SFP!J28+SFP!J29+SFP!J33+SFP!J37+SFP!J38) -> 0.090188976 | L48: =SFP!K4/(SFP!K28+SFP!K29+SFP!K33+SFP!K37+SFP!K38) -> 0.012129097 | M48: =SFP!L4/(SFP!L28+SFP!L29+SFP!L33+SFP!L37+SFP!L38) -> 0.094096932 | N48: =SFP!M4/(SFP!M28+SFP!M29+SFP!M33+SFP!M37+SFP!M38) -> 0.20624723 | ... AT48: =SFP!AS4/(SFP!AS28+SFP!AS29+SFP!AS33+SFP!AS37+SFP!AS38) -> 0.6286625 | AU48: =SFP!AT4/(SFP!AT28+SFP!AT29+SFP!AT34+SFP!AT37+SFP!AT38) -> 0.32068195 | AV48: =SFP!AU4/(SFP!AU28+SFP!AU29+SFP!AU34+SFP!AU37+SFP!AU38) -> 0.39184588 | AW48: =SFP!AV4/(SFP!AV28+SFP!AV29+SFP!AV34+SFP!AV37+SFP!AV38) -> 0.43809378 | AX48: =SFP!AW4/(SFP!AW28+SFP!AW29+SFP!AW34+SFP!AW37+SFP!AW38) -> 0.47256452 | AY48: =SFP!AX4/(SFP!AX28+SFP!AX29+SFP!AX34+SFP!AX37+SFP!AX38) -> 0.59927824 | AZ48: =SFP!AY4/(SFP!AY28+SFP!AY29+SFP!AY34+SFP!AY37+SFP!AY38) -> 0.67883035 | BA48: =SFP!AZ4/(SFP!AZ28+SFP!AZ29+SFP!AZ34+SFP!AZ37+SFP!AZ38) -> 0.76758377 | BB48: =SFP!BA4/(SFP!BA28+SFP!BA29+SFP!BA34+SFP!BA37+SFP!BA38) -> 0.70076313 | ... CM48: =SFP!CL4/(SFP!CL28+SFP!CL29+SFP!CL34+SFP!CL37+SFP!CL38) -> 0.8263777 | CN48: =SFP!CN4/(SFP!CN28+SFP!CN29+SFP!CN34+SFP!CN37+SFP!CN38) -> 0.9036452 | CO48: =SFP!CO4/(SFP!CO28+SFP!CO29+SFP!CO34+SFP!CO37+SFP!CO38) -> 0.85919003 | CP48: =SFP!CP4/(SFP!CP28+SFP!CP29+SFP!CP34+SFP!CP37+SFP!CP38) -> 0.87968807 | CQ48: =SFP!CQ4/(SFP!CQ28+SFP!CQ29+SFP!CQ34+SFP!CQ37+SFP!CQ38) -> #DIV/0! | CR48: =SFP!CR4/(SFP!CR28+SFP!CR29+SFP!CR34+SFP!CR37+SFP!CR38) -> #DIV/0! | CS48: =SFP!CS4/(SFP!CS28+SFP!CS29+SFP!CS34+SFP!CS37+SFP!CS38) -> #DIV/0! | CT48: =SFP!CT4/(SFP!CT28+SFP!CT29+SFP!CT34+SFP!CT37+SFP!CT38) -> #DIV/0! | CU48: =SFP!CU4/(SFP!CU28+SFP!CU29+SFP!CU34+SFP!CU37+SFP!CU38) -> #DIV/0! | ... DV48: =SFP!DV4/(SFP!DV28+SFP!DV29+SFP!DV34+SFP!DV37+SFP!DV38) -> #DIV/0!
A49: Loan Loss Provisions Ratios
A50: Actual LLP / Required LLP | B50: 1
A52: Loan interest/Net Loans | C52: =SCI!B5/SFP!B13 -> 0.17520448 | D52: =SCI!C5/SFP!C13 -> 0.1732077 | E52: =SCI!D5/SFP!D13 -> 0.18020606 | F52: =SCI!E5/SFP!E13 -> 0.17624138 | G52: =SCI!F5/SFP!F13 -> 0.15989371 | H52: =SCI!G5/SFP!G13 -> 0.15631408 | I52: =SCI!H5/SFP!H13 -> 0.013995026 | J52: =SCI!I5/SFP!I13 -> 0.027527328 | ... CM52: =SCI!CL5/SFP!CL13 -> 0.065919752 | CN52: =SCI!CM5/SFP!CN13 -> 0.077658741 | CO52: =SCI!CN5/SFP!CO13 -> 0.089125028 | CP52: =SCI!CO5/SFP!CP13 -> 0.10147469 | CQ52: =SCI!CP5/SFP!CQ13 -> #DIV/0! | CR52: =SCI!CQ5/SFP!CR13 -> #DIV/0! | CS52: =SCI!CR5/SFP!CS13 -> #DIV/0! | CT52: =SCI!CS5/SFP!CT13 -> #DIV/0! | CU52: =SCI!CT5/SFP!CU13 -> #DIV/0! | ... DV52: =SCI!DU5/SFP!DV13 -> #DIV/0!
A53: Earnings
A54: Return on Assets | C54: =SCI!B33/(SFP!B26+SFP!A26/2) -> #VALUE! | D54: =SCI!C33/(SFP!C26+SFP!B26/2) -> 0.0097870414 | E54: =SCI!D33/(SFP!D26+SFP!C26/2) -> 0.014654615 | F54: =SCI!E33/(SFP!E26+SFP!D26/2) -> 0.019719037 | G54: =SCI!F33/(SFP!F26+SFP!E26/2) -> 0.011490047 | H54: =SCI!G33/(SFP!G26+SFP!F26/2) -> 0.010062483 | I54: =SCI!H33/(SFP!H26+SFP!G26/2) -> 0.0047879382 | J54: =SCI!I33/(SFP!I26+SFP!H26/2) -> -0.0045950499 | ... CM54: =SCI!CL33/(SFP!CL26+SFP!CK26/2) -> -0.0010602918 | CN54: =SCI!CM33/(SFP!CN26+SFP!CM26/2) -> 0.00036289581 | CO54: =SCI!CN33/(SFP!CO26+SFP!CN26/2) -> 0.0009100849 | CP54: =SCI!CO33/(SFP!CP26+SFP!CO26/2) -> 0.00097975706 | CQ54: =SCI!CP33/(SFP!CQ26+SFP!CP26/2) -> 0.0074962335 | CR54: =SCI!CQ33/(SFP!CR26+SFP!CQ26/2) -> #DIV/0! | CS54: =SCI!CR33/(SFP!CS26+SFP!CR26/2) -> #DIV/0! | CT54: =SCI!CS33/(SFP!CT26+SFP!CS26/2) -> #DIV/0! | CU54: =SCI!CT33/(SFP!CU26+SFP!CT26/2) -> #DIV/0! | ... DV54: =SCI!DU33/(SFP!DV26+SFP!DU26/2) -> #DIV/0!
A55: Cost income ration | C55: =SCI!B23/SCI!B19 -> 4.8597782 | D55: =SCI!C23/SCI!C19 -> 0.72029681 | E55: =SCI!D23/SCI!D19 -> 0.60105217 | F55: =SCI!E23/SCI!E19 -> 0.6017864 | G55: =SCI!F23/SCI!F19 -> 0.74236942 | H55: =SCI!G23/SCI!G19 -> 0.78085062 | I55: =SCI!H23/SCI!H19 -> 0.37289223 | J55: =SCI!I23/SCI!I19 -> 1.9973959 | ... DV55: =SCI!DU23/SCI!DU19 -> #DIV/0!
A56: Operating expense ratio | C56: =SCI!#REF!/SFP!B26 -> #REF! | D56: =SCI!#REF!/SFP!C26 -> #REF! | E56: =SCI!#REF!/SFP!D26 -> #REF! | F56: =SCI!#REF!/SFP!E26 -> #REF! | G56: =SCI!#REF!/SFP!F26 -> #REF! | H56: =SCI!#REF!/SFP!G26 -> #REF! | I56: =SCI!#REF!/SFP!H26 -> #REF! | J56: =SCI!#REF!/SFP!I26 -> #REF! | ... CM56: =SCI!#REF!/SFP!CL26 -> #REF! | CN56: =SCI!#REF!/SFP!CN26 -> #REF! | CO56: =SCI!#REF!/SFP!CO26 -> #REF! | CP56: =SCI!#REF!/SFP!CP26 -> #REF! | CQ56: =SCI!#REF!/SFP!CQ26 -> #REF! | CR56: =SCI!#REF!/SFP!CR26 -> #REF! | CS56: =SCI!#REF!/SFP!CS26 -> #REF! | CT56: =SCI!#REF!/SFP!CT26 -> #REF! | CU56: =SCI!#REF!/SFP!CU26 -> #REF! | ... DV56: =SCI!#REF!/SFP!DV26 -> #REF!
A57: liquid assets/ta | C57: =SFP!B4/SFP!B26 -> 0.14314618 | D57: =SFP!C4/SFP!C26 -> 0.049089055 | E57: =SFP!D4/SFP!D26 -> 0.071039194 | F57: =SFP!E4/SFP!E26 -> 0.055642884 | G57: =SFP!F4/SFP!F26 -> 0.054514072 | H57: =SFP!G4/SFP!G26 -> 0.053034738 | I57: =SFP!H4/SFP!H26 -> 0.052562027 | J57: =SFP!I4/SFP!I26 -> 0.042327313 | ... CM57: =SFP!CL4/SFP!CL26 -> 0.14845853 | CN57: =SFP!CN4/SFP!CN26 -> 0.17796748 | CO57: =SFP!CO4/SFP!CO26 -> 0.17300024 | CP57: =SFP!CP4/SFP!CP26 -> 0.17317334 | CQ57: =SFP!CQ4/SFP!CQ26 -> #DIV/0! | CR57: =SFP!CR4/SFP!CR26 -> #DIV/0! | CS57: =SFP!CS4/SFP!CS26 -> #DIV/0! | CT57: =SFP!CT4/SFP!CT26 -> #DIV/0! | CU57: =SFP!CU4/SFP!CU26 -> #DIV/0! | ... DV57: =SFP!DV4/SFP!DV26 -> #DIV/0!

Sheet caels
A2: FINANCIAL SOUNDNESS INDICATORS | B2: Prude. Std | C2: 2011 Audited | D2: 2012 Audited | E2: 2013 Audited | F2: 2014 Audited | G2: Audited 2015 | H2: Audited 2016 | I2: 42736 | J2: 42767 | K2: 42795 | L2: 42826 | M2: 42856 | N2: 42887 | O2: 42917 | P2: 42948 | Q2: 42979 | R2: 43009 | S2: 43040 | T2: 43070 | U2: Audited 2017 | V2: 43101 | W2: 43132 | X2: 43160 | Y2: 43191 | Z2: 43221 | AA2: 43252 | AB2: 43282 | AC2: 43313 | AD2: 43344 | AE2: 43374 | AF2: 43405 | AG2: 43435 | AH2: Audited-2018 | AI2: 43466 | AJ2: 43497 | AK2: 43525 | AL2: 43556 | AM2: 43586 | AN2: 43617 | AO2: 43647 | AP2: 43678 | AQ2: 43709 | AR2: 43739 | AS2: 43770 | AT2: 43800 | AU2: Audited 2019 | AV2: 43831 | AW2: 43862 | AX2: 43891 | AY2: 43922 | AZ2: 43952 | BA2: 43983 | BB2: 44013 | BC2: 44044 | BD2: 44075 | BE2: 44105 | BF2: 44136 | BG2: 44166 | BH2: Audited 2020 | BI2: 44197 | BJ2: 44228 | BK2: 44256 | BL2: 44287 | BM2: 44317 | BN2: 44348 | BO2: 44378 | BP2: 44409 | BQ2: 44440 | BR2: 44470 | BS2: 44501 | BT2: 44531 | BU2: audited 2021 | BV2: 44562 | BW2: 44593 | BX2: 44621 | BY2: 44652 | BZ2: 44682 | CA2: 44713 | CB2: 44743 | CC2: 44774 | CD2: 44805 | CE2: 44835 | CF2: 44866 | CG2: 44896 | CH2: Audited 2022 | CI2: 44927 | CJ2: 44958 | CK2: 44986 | CL2: 45017 | CM2: 45047
A3: CAPITAL
A4: CORE CAPITAL | B4: ≥ Ksh.10M | C4: ='Prudential Ratios'!C6 -> -24.983 | D4: ='Prudential Ratios'!D6 -> 16.577 | E4: ='Prudential Ratios'!E6 -> -12.912 | F4: ='Prudential Ratios'!F6 -> 341.84148 | G4: ='Prudential Ratios'!#REF! -> #REF! | H4: ='Prudential Ratios'!H6 -> 532.31324 | I4: ='Prudential Ratios'!I6 -> 536.68483 | J4: ='Prudential Ratios'!J6 -> 511.36793 | K4: ='Prudential Ratios'!K6 -> 517.1088 | L4: ='Prudential Ratios'!L6 -> 513.33716 | M4: ='Prudential Ratios'!M6 -> 516.22456 | N4: ='Prudential Ratios'!N6 -> 530.79187 | O4: ='Prudential Ratios'!O6 -> 539.0443 | ... CO4: ='Prudential Ratios'!CO6 -> 1821.7842
A5: CCA | B5: ≥ 10% | C5: ='Prudential Ratios'!C7 -> -0.012599026 | D5: ='Prudential Ratios'!D7 -> 0.0073800754 | E5: ='Prudential Ratios'!E7 -> -0.0045555178 | F5: ='Prudential Ratios'!F7 -> 0.1040945 | G5: ='Prudential Ratios'!#REF! -> #REF! | H5: ='Prudential Ratios'!H7 -> 0.10914525 | I5: ='Prudential Ratios'!I7 -> 0.10833419 | J5: ='Prudential Ratios'!J7 -> 0.10507133 | K5: ='Prudential Ratios'!K7 -> 0.10597273 | L5: ='Prudential Ratios'!L7 -> 0.10504249 | M5: ='Prudential Ratios'!M7 -> 0.1045955 | N5: ='Prudential Ratios'!N7 -> 0.10025032 | O5: ='Prudential Ratios'!O7 -> 0.099808931 | ... CO5: ='Prudential Ratios'!CO7 -> 0.14598643
A6: ICA | B6: ≥ 8% | C6: ='Prudential Ratios'!C10 -> -0.021175724 | D6: ='Prudential Ratios'!D10 -> -0.00051687685 | E6: ='Prudential Ratios'!E10 -> -0.020994121 | F6: ='Prudential Ratios'!F10 -> 0.088508618 | G6: ='Prudential Ratios'!#REF! -> #REF! | H6: ='Prudential Ratios'!H10 -> 0.075713938 | I6: ='Prudential Ratios'!I10 -> 0.07509129 | J6: ='Prudential Ratios'!J10 -> 0.06893961 | K6: ='Prudential Ratios'!K10 -> 0.069130652 | L6: ='Prudential Ratios'!L10 -> 0.06779543 | M6: ='Prudential Ratios'!M10 -> 0.067053793 | N6: ='Prudential Ratios'!N10 -> 0.063984073 | O6: ='Prudential Ratios'!O10 -> 0.063566148 | ... CO6: ='Prudential Ratios'!CO10 -> 0.078355717
A7: CCD | B7: ≥ 8% | C7: ='Prudential Ratios'!C8 -> -0.016214041 | D7: ='Prudential Ratios'!D8 -> 0.0097042706 | E7: ='Prudential Ratios'!E8 -> -0.006367225 | F7: ='Prudential Ratios'!F8 -> 0.1380541 | G7: ='Prudential Ratios'!#REF! -> #REF! | H7: ='Prudential Ratios'!H8 -> 0.14833976 | I7: ='Prudential Ratios'!I8 -> 0.14994375 | J7: ='Prudential Ratios'!J8 -> 0.13431848 | K7: ='Prudential Ratios'!K8 -> 0.13682222 | L7: ='Prudential Ratios'!L8 -> 0.1371059 | M7: ='Prudential Ratios'!M8 -> 0.13725908 | N7: ='Prudential Ratios'!N8 -> 0.13633701 | O7: ='Prudential Ratios'!O8 -> 0.13648598 | ... CO7: ='Prudential Ratios'!CO8 -> 0.18565203
A8: Asset Quality
A9: NPL | B9: ≤ 6% | C9: ='Prudential Ratios'!C16 -> 0 | D9: ='Prudential Ratios'!D16 -> 0 | E9: ='Prudential Ratios'!E16 -> 0 | F9: ='Prudential Ratios'!F16 -> 0 | G9: ='Prudential Ratios'!#REF! -> #REF! | H9: ='Prudential Ratios'!H16 -> 0 | K9: ='Prudential Ratios'!K16 -> 0 | L9: ='Prudential Ratios'!L16 -> 0 | M9: ='Prudential Ratios'!M16 -> 0 | N9: ='Prudential Ratios'!N16 -> 0 | O9: ='Prudential Ratios'!O16 -> 0 | P9: ='Prudential Ratios'!P16 -> 0 | Q9: ='Prudential Ratios'!Q16 -> 2.0592366e-10 | R9: ='Prudential Ratios'!R16 -> 4.0186964e-10 | ... CO9: ='Prudential Ratios'!CO16 -> 3.2919933e-10
A10: Earnings
A11: ROA | C11: ='Prudential Ratios'!C54 -> #VALUE! | D11: ='Prudential Ratios'!D54 -> 0.0097870414 | E11: ='Prudential Ratios'!E54 -> 0.014654615 | F11: ='Prudential Ratios'!F54 -> 0.019719037 | G11: ='Prudential Ratios'!G54 -> 0.011490047 | H11: ='Prudential Ratios'!H54 -> 0.010062483 | I11: ='Prudential Ratios'!I54 -> 0.0047879382 | J11: ='Prudential Ratios'!J54 -> -0.0045950499 | ... CO11: ='Prudential Ratios'!CO54 -> 0.0009100849
A12: CIR | C12: ='Prudential Ratios'!C55 -> 4.8597782 | D12: ='Prudential Ratios'!D55 -> 0.72029681 | E12: ='Prudential Ratios'!E55 -> 0.60105217 | F12: ='Prudential Ratios'!F55 -> 0.6017864 | G12: ='Prudential Ratios'!G55 -> 0.74236942 | H12: ='Prudential Ratios'!H55 -> 0.78085062 | I12: ='Prudential Ratios'!I55 -> 0.37289223 | J12: ='Prudential Ratios'!J55 -> 1.9973959 | ... CO12: ='Prudential Ratios'!CO55 -> 0.88188145
A13: OER | C13: ='Prudential Ratios'!C56 -> #REF! | D13: ='Prudential Ratios'!D56 -> #REF! | E13: ='Prudential Ratios'!E56 -> #REF! | F13: ='Prudential Ratios'!F56 -> #REF! | G13: ='Prudential Ratios'!G56 -> #REF! | H13: ='Prudential Ratios'!H56 -> #REF! | I13: ='Prudential Ratios'!I56 -> #REF! | J13: ='Prudential Ratios'!J56 -> #REF! | ... CO13: ='Prudential Ratios'!CO56 -> #REF!
A14: LIQUIDITY
A15: MIN LIQ | B15: 0.15 | C15: ='Prudential Ratios'!C47 -> 1.2246272 | D15: ='Prudential Ratios'!D47 -> 0.37345639 | E15: ='Prudential Ratios'!E47 -> 0.51727008 | F15: ='Prudential Ratios'!F47 -> 0.32255384 | G15: ='Prudential Ratios'!G47 -> 0.18492021 | H15: ='Prudential Ratios'!H47 -> 0.17605031 | I15: ='Prudential Ratios'!I47 -> 0.23050629 | J15: ='Prudential Ratios'!J47 -> 0.19142556 | ... CO15: ='Prudential Ratios'!CO47 -> 0.85919003
A16: TEC LIQ | C16: ='Prudential Ratios'!C48 -> 0.18335824 | D16: ='Prudential Ratios'!D48 -> 0.055634127 | E16: ='Prudential Ratios'!E48 -> 0.098710422 | F16: ='Prudential Ratios'!F48 -> 0.06633083 | G16: ='Prudential Ratios'!G48 -> 0.18492021 | H16: ='Prudential Ratios'!H48 -> 0.15651936 | I16: ='Prudential Ratios'!I48 -> 0.19832039 | J16: ='Prudential Ratios'!J48 -> 0.16575449 | ... CO16: ='Prudential Ratios'!CO48 -> 0.85919003
A17: EB | B17: ≤ 25% | C17: ='Prudential Ratios'!C27 -> 0.024795114 | D17: ='Prudential Ratios'!D27 -> 0 | E17: ='Prudential Ratios'!E27 -> 0 | F17: ='Prudential Ratios'!F27 -> 0 | G17: ='Prudential Ratios'!#REF! -> #REF! | H17: ='Prudential Ratios'!#REF! -> #REF! | I17: ='Prudential Ratios'!#REF! -> #REF! | J17: ='Prudential Ratios'!#REF! -> #REF! | K17: ='Prudential Ratios'!#REF! -> #REF! | L17: ='Prudential Ratios'!#REF! -> #REF! | M17: ='Prudential Ratios'!#REF! -> #REF! | N17: ='Prudential Ratios'!#REF! -> #REF! | ... CO17: ='Prudential Ratios'!#REF! -> #REF!
A18: LIQ/TA | C18: ='Prudential Ratios'!C57 -> 0.14314618 | D18: ='Prudential Ratios'!D57 -> 0.049089055 | E18: ='Prudential Ratios'!E57 -> 0.071039194 | F18: ='Prudential Ratios'!F57 -> 0.055642884 | G18: ='Prudential Ratios'!G57 -> 0.054514072 | H18: ='Prudential Ratios'!H57 -> 0.053034738 | I18: ='Prudential Ratios'!I57 -> 0.052562027 | J18: ='Prudential Ratios'!J57 -> 0.042327313 | ... CO18: ='Prudential Ratios'!CO57 -> 0.17300024
A19: STRUCTURE
A20: NEA | B20: ≤ 10% | C20: ='Prudential Ratios'!C14 -> 0.056130546 | D20: ='Prudential Ratios'!D14 -> 0.084664963 | E20: ='Prudential Ratios'!E14 -> 0.13640761 | F20: ='Prudential Ratios'!F14 -> 0.098078591 | G20: ='Prudential Ratios'!#REF! -> #REF! | H20: ='Prudential Ratios'!#REF! -> #REF! | I20: ='Prudential Ratios'!#REF! -> #REF! | J20: ='Prudential Ratios'!#REF! -> #REF! | K20: ='Prudential Ratios'!#REF! -> #REF! | L20: ='Prudential Ratios'!#REF! -> #REF! | M20: ='Prudential Ratios'!#REF! -> #REF! | N20: ='Prudential Ratios'!#REF! -> #REF! | ... CO20: ='Prudential Ratios'!#REF! -> #REF!
A21: LB | B21: ≤ 5% | C21: ='Prudential Ratios'!C15 -> 0.015412034 | D21: ='Prudential Ratios'!D15 -> 0.01441156 | E21: ='Prudential Ratios'!E15 -> 0.012773232 | F21: ='Prudential Ratios'!F15 -> 0.015806849 | G21: ='Prudential Ratios'!#REF! -> #REF! | H21: ='Prudential Ratios'!#REF! -> #REF! | I21: ='Prudential Ratios'!#REF! -> #REF! | J21: ='Prudential Ratios'!#REF! -> #REF! | K21: ='Prudential Ratios'!#REF! -> #REF! | L21: ='Prudential Ratios'!#REF! -> #REF! | M21: ='Prudential Ratios'!#REF! -> #REF! | N21: ='Prudential Ratios'!#REF! -> #REF! | ... CO21: ='Prudential Ratios'!#REF! -> #REF!
A22: FITD | B22: ≤ 5% | C22: ='Prudential Ratios'!C19 -> 0.091065501 | D22: ='Prudential Ratios'!D19 -> 0.079617519 | E22: ='Prudential Ratios'!E19 -> 0.1331397 | F22: ='Prudential Ratios'!F19 -> 0.10816163 | G22: ='Prudential Ratios'!#REF! -> #REF! | H22: ='Prudential Ratios'!#REF! -> #REF! | I22: ='Prudential Ratios'!#REF! -> #REF! | J22: ='Prudential Ratios'!#REF! -> #REF! | K22: ='Prudential Ratios'!#REF! -> #REF! | L22: ='Prudential Ratios'!#REF! -> #REF! | M22: ='Prudential Ratios'!#REF! -> #REF! | N22: ='Prudential Ratios'!#REF! -> #REF! | ... CO22: ='Prudential Ratios'!#REF! -> #REF!
A23: FICC | B23: ≤ 40% | C23: ='Prudential Ratios'!C20 -> -5.6164592 | D23: ='Prudential Ratios'!D20 -> 8.2043796 | E23: ='Prudential Ratios'!E20 -> -20.910161 | F23: ='Prudential Ratios'!F20 -> 0.78347282 | G23: ='Prudential Ratios'!#REF! -> #REF! | H23: ='Prudential Ratios'!#REF! -> #REF! | I23: ='Prudential Ratios'!#REF! -> #REF! | J23: ='Prudential Ratios'!#REF! -> #REF! | K23: ='Prudential Ratios'!#REF! -> #REF! | L23: ='Prudential Ratios'!#REF! -> #REF! | M23: ='Prudential Ratios'!#REF! -> #REF! | N23: ='Prudential Ratios'!#REF! -> #REF! | ... CO23: ='Prudential Ratios'!#REF! -> #REF!
A26: CAELS RATINGS
A27: FINANCIAL SOUNDNESS INDICATORS | B27: Prude. Std | C27: 2011 Audited | D27: 2012 Audited | E27: 2013 Audited | F27: 2014 Audited
A28: CAPITAL
A29: CORE CAPITAL | B29: ≥ Ksh.10M | C29: =IF(C4>10,"1","5") -> 5 | D29: =IF(D4>10,"1","5") -> 1 | E29: =IF(E4>10,"1","5") -> 5 | F29: =IF(F4>10,"1","5") -> 1
A30: CCA | B30: ≥ 10% | C30: =IF(C5>20%,"1",IF(C5>15%,"2",IF(C5>12%,"3",IF(C5>10%,"4","5")))) -> 5 | D30: =IF(D5>20%,"1",IF(D5>15%,"2",IF(D5>12%,"3",IF(D5>10%,"4","5")))) -> 5 | E30: =IF(E5>20%,"1",IF(E5>15%,"2",IF(E5>12%,"3",IF(E5>10%,"4","5")))) -> 5 | F30: =IF(F5>20%,"1",IF(F5>15%,"2",IF(F5>12%,"3",IF(F5>10%,"4","5")))) -> 4
A31: ICA | B31: ≥ 8% | C31: =IF(C6>15%,"1",IF(C6>12%,"2",IF(C6>10%,"3",IF(C6>8%,"4","5")))) -> 5 | D31: =IF(D6>15%,"1",IF(D6>12%,"2",IF(D6>10%,"3",IF(D6>8%,"4","5")))) -> 5 | E31: =IF(E6>15%,"1",IF(E6>12%,"2",IF(E6>10%,"3",IF(E6>8%,"4","5")))) -> 5 | F31: =IF(F6>15%,"1",IF(F6>12%,"2",IF(F6>10%,"3",IF(F6>8%,"4","5")))) -> 4
A32: CCD | B32: ≥ 8% | C32: =IF(C7>15%,"1",IF(C7>12%,"2",IF(C7>10%,"3",IF(C7>8%,"4","5")))) -> 5 | D32: =IF(D7>15%,"1",IF(D7>12%,"2",IF(D7>10%,"3",IF(D7>8%,"4","5")))) -> 5 | E32: =IF(E7>15%,"1",IF(E7>12%,"2",IF(E7>10%,"3",IF(E7>8%,"4","5")))) -> 5 | F32: =IF(F7>15%,"1",IF(F7>12%,"2",IF(F7>10%,"3",IF(F7>8%,"4","5")))) -> 2
C33: =(C29+C30+C31+C32)/4 -> 5 | D33: =(D29+D30+D31+D32)/4 -> 4 | E33: =(E29+E30+E31+E32)/4 -> 5 | F33: =(F29+F30+F31+F32)/4 -> 2.75
A34: Asset Quality
A35: NPL | B35: ≤ 6% | C35: =IF(C9<4%,"1",IF(C9<8%,"2",IF(C9<12%,"3",IF(C9<15%,"4","5")))) -> 1 | D35: =IF(D9<4%,"1",IF(D9<8%,"2",IF(D9<12%,"3",IF(D9<15%,"4","5")))) -> 1 | E35: =IF(E9<4%,"1",IF(E9<8%,"2",IF(E9<12%,"3",IF(E9<15%,"4","5")))) -> 1 | F35: =IF(F9<4%,"1",IF(F9<8%,"2",IF(F9<12%,"3",IF(F9<15%,"4","5")))) -> 1
C36: =C35 -> 1 | D36: =D35 -> 1 | E36: =E35 -> 1 | F36: =F35 -> 1
A37: Earnings
A38: ROA | C38: =IF(C11>6%,"1",IF(C11>4%,"2",IF(C11>2%,"3",IF(C11>0%,"4","5")))) -> #VALUE! | D38: =IF(D11>6%,"1",IF(D11>4%,"2",IF(D11>2%,"3",IF(D11>0%,"4","5")))) -> 4 | E38: =IF(E11>6%,"1",IF(E11>4%,"2",IF(E11>2%,"3",IF(E11>0%,"4","5")))) -> 4 | F38: =IF(F11>6%,"1",IF(F11>4%,"2",IF(F11>2%,"3",IF(F11>0%,"4","5")))) -> 4
A39: CIR | C39: =IF(C12<60%,"1",IF(C12<70%,"2",IF(C12<80%,"3",IF(C12<90%,"4","5")))) -> 5 | D39: =IF(D12<60%,"1",IF(D12<70%,"2",IF(D12<80%,"3",IF(D12<90%,"4","5")))) -> 3 | E39: =IF(E12<60%,"1",IF(E12<70%,"2",IF(E12<80%,"3",IF(E12<90%,"4","5")))) -> 2 | F39: =IF(F12<60%,"1",IF(F12<70%,"2",IF(F12<80%,"3",IF(F12<90%,"4","5")))) -> 2
A40: OER | C40: =IF(C13>4%,"1",IF(C13>6%,"2",IF(C13>8%,"3",IF(C13>10%,"4","5")))) -> #REF! | D40: =IF(D13>4%,"1",IF(D13>6%,"2",IF(D13>8%,"3",IF(D13>10%,"4","5")))) -> #REF! | E40: =IF(E13>4%,"1",IF(E13>6%,"2",IF(E13>8%,"3",IF(E13>10%,"4","5")))) -> #REF! | F40: =IF(F13>4%,"1",IF(F13>6%,"2",IF(F13>8%,"3",IF(F13>10%,"4","5")))) -> #REF!
C41: =(C38+C39+C40)/3 -> #VALUE! | D41: =(D38+D39+D40)/3 -> #REF! | E41: =(E38+E39+E40)/3 -> #REF! | F41: =(F38+F39+F40)/3 -> #REF!
A42: LIQUIDITY
A43: MIN LIQ | B43: 0.15 | C43: =IF(C15>30%,"1",IF(C15>25%,"2",IF(C15>20%,"3",IF(C15>15%,"4","5")))) -> 1 | D43: =IF(D15>30%,"1",IF(D15>25%,"2",IF(D15>20%,"3",IF(D15>15%,"4","5")))) -> 1 | E43: =IF(E15>30%,"1",IF(E15>25%,"2",IF(E15>20%,"3",IF(E15>15%,"4","5")))) -> 1 | F43: =IF(F15>30%,"1",IF(F15>25%,"2",IF(F15>20%,"3",IF(F15>15%,"4","5")))) -> 1
A44: TECH LIQ | C44: =IF(C16>30%,"1",IF(C16>25%,"2",IF(C16>20%,"3",IF(C16>15%,"4","5")))) -> 4 | D44: =IF(D16>30%,"1",IF(D16>25%,"2",IF(D16>20%,"3",IF(D16>15%,"4","5")))) -> 5 | E44: =IF(E16>30%,"1",IF(E16>25%,"2",IF(E16>20%,"3",IF(E16>15%,"4","5")))) -> 5 | F44: =IF(F16>30%,"1",IF(F16>25%,"2",IF(F16>20%,"3",IF(F16>15%,"4","5")))) -> 5
A45: EB | B45: ≤ 25% | C45: =IF(C17<15%,"1",IF(C17<18%,"2",IF(C17<22%,"3",IF(C17<25%,"4","5")))) -> 1 | D45: =IF(D17<15%,"1",IF(D17<18%,"2",IF(D17<22%,"3",IF(D17<25%,"4","5")))) -> 1 | E45: =IF(E17<15%,"1",IF(E17<18%,"2",IF(E17<22%,"3",IF(E17<25%,"4","5")))) -> 1 | F45: =IF(F17<15%,"1",IF(F17<18%,"2",IF(F17<22%,"3",IF(F17<25%,"4","5")))) -> 1
A46: LIQ/TA | C46: =IF(C18>15%,"1",IF(C18>12%,"2",IF(C18>9%,"3",IF(C18>6%,"4","5")))) -> 2 | D46: =IF(D18>15%,"1",IF(D18>12%,"2",IF(D18>9%,"3",IF(D18>6%,"4","5")))) -> 5 | E46: =IF(E18>15%,"1",IF(E18>12%,"2",IF(E18>9%,"3",IF(E18>6%,"4","5")))) -> 4 | F46: =IF(F18>15%,"1",IF(F18>12%,"2",IF(F18>9%,"3",IF(F18>6%,"4","5")))) -> 5
C47: =(C43+C44+C45+C46)/4 -> 2 | D47: =(D43+D44+D45+D46)/4 -> 3 | E47: =(E43+E44+E45+E46)/4 -> 2.75 | F47: =(F43+F44+F45+F46)/4 -> 3
A48: STRUCTURE
A49: NEA | B49: ≤ 10% | C49: =IF(C20<6%,"1",IF(C20<7%,"2",IF(C20<8%,"3",IF(C20<10%,"4","5")))) -> 1 | D49: =IF(D20<6%,"1",IF(D20<7%,"2",IF(D20<8%,"3",IF(D20<10%,"4","5")))) -> 4 | E49: =IF(E20<6%,"1",IF(E20<7%,"2",IF(E20<8%,"3",IF(E20<10%,"4","5")))) -> 5 | F49: =IF(F20<6%,"1",IF(F20<7%,"2",IF(F20<8%,"3",IF(F20<10%,"4","5")))) -> 4
A50: LB | B50: ≤ 5% | C50: =IF(C21<2%,"1",IF(C21<3%,"2",IF(C21<4%,"3",IF(C21<5%,"4","5")))) -> 1 | D50: =IF(D21<2%,"1",IF(D21<3%,"2",IF(D21<4%,"3",IF(D21<5%,"4","5")))) -> 1 | E50: =IF(E21<2%,"1",IF(E21<3%,"2",IF(E21<4%,"3",IF(E21<5%,"4","5")))) -> 1 | F50: =IF(F21<2%,"1",IF(F21<3%,"2",IF(F21<4%,"3",IF(F21<5%,"4","5")))) -> 1
A51: FITD | B51: ≤ 5% | C51: =IF(C22<2%,"1",IF(C22<3%,"2",IF(C22<4%,"3",IF(C22<5%,"4","5")))) -> 5 | D51: =IF(D22<2%,"1",IF(D22<3%,"2",IF(D22<4%,"3",IF(D22<5%,"4","5")))) -> 5 | E51: =IF(E22<2%,"1",IF(E22<3%,"2",IF(E22<4%,"3",IF(E22<5%,"4","5")))) -> 5 | F51: =IF(F22<2%,"1",IF(F22<3%,"2",IF(F22<4%,"3",IF(F22<5%,"4","5")))) -> 5
A52: FICC | B52: ≤ 40% | C52: =IF(C23<20%,"1",IF(C23<25%,"2",IF(C23<30%,"3",IF(C23<40%,"4","5")))) -> 1 | D52: =IF(D23<20%,"1",IF(D23<25%,"2",IF(D23<30%,"3",IF(D23<40%,"4","5")))) -> 5 | E52: =IF(E23<20%,"1",IF(E23<25%,"2",IF(E23<30%,"3",IF(E23<40%,"4","5")))) -> 1 | F52: =IF(F23<20%,"1",IF(F23<25%,"2",IF(F23<30%,"3",IF(F23<40%,"4","5")))) -> 5
C53: =(C49+C50+C51+C52)/4 -> 2 | D53: =(D49+D50+D51+D52)/4 -> 3.75 | E53: =(E49+E50+E51+E52)/4 -> 3 | F53: =(F49+F50+F51+F52)/4 -> 3.75
A54: FINAL RATING

Sheet F4
B1: 31/12/2021
C2: A | D2: B | E2: C | F2: D
A3: NO. | B3: CLASSIFICATION | C3: NO. OF A/Cs | D3: OUTSTANDING LOAN PORTFOLIO(Kshs) | E3: REQUIRED PROVISION | F3: REQUIRED PROVISION AMOUNT(Kshs)
A4: 1 | B4: Performing | C4: 23916 | D4: 7087070080 | E4: 0.01 | F4: =D4*E4 -> 70870701
A5: 2 | B5: Watch | C5: 684 | D5: 33563540 | E5: 0.05 | F5: =D5*E5 -> 1678177
A6: 3 | B6: Substandard | C6: 428 | D6: 49523088 | E6: 0.25 | F6: =D6*E6 -> 12380772
A7: 4 | B7: Doubtful | C7: 518 | D7: 46822836 | E7: 0.5 | F7: =D7*E7 -> 23411418
A8: 5 | B8: Loss | C8: 989 | D8: 128358910 | E8: 1 | F8: =D8*E8 -> 128358910
B9: subtotal | C9: =SUM(C4:C8) -> 26535 | D9: =SUM(D4:D8) -> 7345338454 | F9: =SUM(F4:F8) -> 2.3669998e+08
B10: Reschedule/Renegotiated loans
A11: 1 | B11: Performing | C11: 0 | E11: 0.01 | F11: =D11*E11 -> 0
A12: 2 | B12: Watch | C12: 0 | E12: 0.05 | F12: =D12*E12 -> 0
A13: 3 | B13: Substandard | C13: 0 | E13: 0.25 | F13: =D13*E13 -> 0
A14: 4 | B14: Doubtful | C14: 0 | E14: 0.5 | F14: =D14*E14 -> 0
A15: 5 | B15: Loss | C15: 0 | E15: 1 | F15: =D15*E15 -> 0
B16: subtotal | C16: =SUM(C10:C15) -> 0 | D16: =SUM(D10:D15) -> 0 | F16: =SUM(F10:F15) -> 0
B17: GRAND TOTAL | C17: =C9+C16 -> 26535 | D17: =D9+D16 -> 7345338454 | F17: =F9+F16 -> 2.3669998e+08
B20: =(D6+D7+D8)/D9 -> 0.030591488
B22: 31/3/2022
C23: A | D23: B | E23: C | F23: D
A24: NO. | B24: CLASSIFICATION | C24: NO. OF A/Cs | D24: OUTSTANDING LOAN PORTFOLIO(Kshs) | E24: REQUIRED PROVISION | F24: REQUIRED PROVISION AMOUNT(Kshs)
A25: 1 | B25: Performing | E25: 0.01 | F25: =D25*E25 -> 0
A26: 2 | B26: Watch | E26: 0.05 | F26: =D26*E26 -> 0
A27: 3 | B27: Substandard | E27: 0.25 | F27: =D27*E27 -> 0
A28: 4 | B28: Doubtful | E28: 0.5 | F28: =D28*E28 -> 0
A29: 5 | B29: Loss | E29: 1 | F29: =D29*E29 -> 0
B30: subtotal | F30: =SUM(F25:F29) -> 0
B31: Reschedule/Renegotiated loans
A32: 1 | B32: Performing | C32: 0 | E32: 0.01 | F32: =D32*E32 -> 0
A33: 2 | B33: Watch | C33: 0 | E33: 0.05 | F33: =D33*E33 -> 0
A34: 3 | B34: Substandard | C34: 0 | E34: 0.25 | F34: =D34*E34 -> 0
A35: 4 | B35: Doubtful | C35: 0 | E35: 0.5 | F35: =D35*E35 -> 0
A36: 5 | B36: Loss | C36: 0 | E36: 1 | F36: =D36*E36 -> 0
B37: subtotal | C37: =SUM(C31:C36) -> 0 | D37: =SUM(D31:D36) -> 0 | F37: =SUM(F31:F36) -> 0
B38: GRAND TOTAL | F38: =F30+F37 -> 0
B41: =(D27+D28+D29)/D30 -> #DIV/0!
B44: 31/06/2022
C45: A | D45: B | E45: C | F45: D
A46: NO. | B46: CLASSIFICATION | C46: NO. OF A/Cs | D46: OUTSTANDING LOAN PORTFOLIO(Kshs) | E46: REQUIRED PROVISION | F46: REQUIRED PROVISION AMOUNT(Kshs)
A47: 1 | B47: Performing | E47: 0.01 | F47: =D47*E47 -> 0
A48: 2 | B48: Watch | E48: 0.05 | F48: =D48*E48 -> 0
A49: 3 | B49: Substandard | E49: 0.25 | F49: =D49*E49 -> 0
A50: 4 | B50: Doubtful | E50: 0.5 | F50: =D50*E50 -> 0
A51: 5 | B51: Loss | E51: 1 | F51: =D51*E51 -> 0
B52: subtotal | C52: =SUM(C47:C51) -> 0 | D52: =SUM(D47:D51) -> 0 | F52: =SUM(F47:F51) -> 0
B53: Reschedule/Renegotiated loans
A54: 1 | B54: Performing | C54: 0 | E54: 0.01 | F54: =D54*E54 -> 0
A55: 2 | B55: Watch | C55: 0 | E55: 0.05 | F55: =D55*E55 -> 0
A56: 3 | B56: Substandard | C56: 0 | E56: 0.25 | F56: =D56*E56 -> 0
A57: 4 | B57: Doubtful | C57: 0 | E57: 0.5 | F57: =D57*E57 -> 0
A58: 5 | B58: Loss | C58: 0 | E58: 1 | F58: =D58*E58 -> 0
B59: subtotal | C59: =SUM(C53:C58) -> 0 | D59: =SUM(D53:D58) -> 0 | F59: =SUM(F53:F58) -> 0
B60: GRAND TOTAL | C60: =C52+C59 -> 0 | D60: =D52+D59 -> 0 | F60: =F52+F59 -> 0
B63: =(D49+D50+D51)/D52 -> #DIV/0!
B66: 31/09/2022
C67: A | D67: B | E67: C | F67: D
A68: NO. | B68: CLASSIFICATION | C68: NO. OF A/Cs | D68: OUTSTANDING LOAN PORTFOLIO(Kshs) | E68: REQUIRED PROVISION | F68: REQUIRED PROVISION AMOUNT(Kshs)
A69: 1 | B69: Performing | E69: 0.01 | F69: =D69*E69 -> 0
A70: 2 | B70: Watch | E70: 0.05 | F70: =D70*E70 -> 0
A71: 3 | B71: Substandard | E71: 0.25 | F71: =D71*E71 -> 0
A72: 4 | B72: Doubtful | E72: 0.5 | F72: =D72*E72 -> 0
A73: 5 | B73: Loss | E73: 1 | F73: =D73*E73 -> 0
B74: subtotal | C74: =SUM(C69:C73) -> 0 | D74: =SUM(D69:D73) -> 0 | F74: =SUM(F69:F73) -> 0
B75: Reschedule/Renegotiated loans
A76: 1 | B76: Performing | C76: 0 | E76: 0.01 | F76: =D76*E76 -> 0
A77: 2 | B77: Watch | C77: 0 | E77: 0.05 | F77: =D77*E77 -> 0
A78: 3 | B78: Substandard | C78: 0 | E78: 0.25 | F78: =D78*E78 -> 0
A79: 4 | B79: Doubtful | C79: 0 | E79: 0.5 | F79: =D79*E79 -> 0
A80: 5 | B80: Loss | C80: 0 | E80: 1 | F80: =D80*E80 -> 0
B81: subtotal | C81: =SUM(C75:C80) -> 0 | D81: =SUM(D75:D80) -> 0 | F81: =SUM(F75:F80) -> 0
B82: GRAND TOTAL | C82: =C74+C81 -> 0 | D82: =D74+D81 -> 0 | F82: =F74+F81 -> 0
B85: =(D71+D72+D73)/D74 -> #DIV/0!
B87: 31/12/2022
C88: A | D88: B | E88: C | F88: D
A89: NO. | B89: CLASSIFICATION | C89: NO. OF A/Cs | D89: OUTSTANDING LOAN PORTFOLIO(Kshs) | E89: REQUIRED PROVISION | F89: REQUIRED PROVISION AMOUNT(Kshs)
A90: 1 | B90: Performing | E90: 0.01 | F90: =D90*E90 -> 0
A91: 2 | B91: Watch | E91: 0.05 | F91: =D91*E91 -> 0
A92: 3 | B92: Substandard | E92: 0.25 | F92: =D92*E92 -> 0
A93: 4 | B93: Doubtful | E93: 0.5 | F93: =D93*E93 -> 0
A94: 5 | B94: Loss | E94: 1 | F94: =D94*E94 -> 0
B95: subtotal | C95: =SUM(C90:C94) -> 0 | D95: =SUM(D90:D94) -> 0 | F95: =SUM(F90:F94) -> 0
B96: Reschedule/Renegotiated loans
A97: 1 | B97: Performing | C97: 0 | E97: 0.01 | F97: =D97*E97 -> 0
A98: 2 | B98: Watch | C98: 0 | E98: 0.05 | F98: =D98*E98 -> 0
A99: 3 | B99: Substandard | C99: 0 | E99: 0.25 | F99: =D99*E99 -> 0
A100: 4 | B100: Doubtful | C100: 0 | E100: 0.5 | F100: =D100*E100 -> 0
A101: 5 | B101: Loss | C101: 0 | E101: 1 | F101: =D101*E101 -> 0
B102: subtotal | C102: =SUM(C96:C101) -> 0 | D102: =SUM(D96:D101) -> 0 | F102: =SUM(F96:F101) -> 0
B103: GRAND TOTAL | C103: =C95+C102 -> 0 | D103: =D95+D102 -> 0 | F103: =F95+F102 -> 0
B106: =(D92+D93+D94)/D95 -> #DIV/0!
B108: 31/12/2022
C109: A | D109: B | E109: C | F109: D
A110: NO. | B110: CLASSIFICATION | C110: NO. OF A/Cs | D110: OUTSTANDING LOAN PORTFOLIO(Kshs) | E110: REQUIRED PROVISION | F110: REQUIRED PROVISION AMOUNT(Kshs)
A111: 1 | B111: Performing | E111: 0.01 | F111: =D111*E111 -> 0
A112: 2 | B112: Watch | E112: 0.05 | F112: =D112*E112 -> 0
A113: 3 | B113: Substandard | E113: 0.25 | F113: =D113*E113 -> 0
A114: 4 | B114: Doubtful | E114: 0.5 | F114: =D114*E114 -> 0
A115: 5 | B115: Loss | E115: 1 | F115: =D115*E115 -> 0
B116: subtotal | C116: =SUM(C111:C115) -> 0 | D116: =SUM(D111:D115) -> 0 | F116: =SUM(F111:F115) -> 0
B117: Reschedule/Renegotiated loans
...

Sheet F4 Mar 17
B1: FORM 4 SASRA2/004
B2: RISK CLASSIFICATION OF ASSETS AND PROVISIONING
B3: NAME OF SACCO SOCIETY | F3: 2648
B4: FINANCIAL YEAR | F4: 2017
B5: START DATE: | F5: 1/1/2017
B6: END DATE: | F6: 31/3/2017
B7: PORTFOLIO AGEING REPORT
C8: A | D8: B | E8: C | F8: D
A9: NO. | B9: CLASSIFICATION | C9: NO. OF A/Cs | D9: OUTSTANDING LOAN PORTFOLIO(Kshs) | E9: REQUIRED PROVISION | F9: REQUIRED PROVISION AMOUNT(Kshs)
A10: 1 | B10: Performing | C10: 18844 | D10: 4.0922231e+09 | E10: 99.46 | F10: 0
A11: 2 | B11: Watch | C11: 298 | D11: 1866685.8 | E11: 0.05 | F11: 93334.29
A12: 3 | B12: Substandard | C12: 122 | D12: 901898 | E12: 0.02 | F12: 225474.5
A13: 4 | B13: Doubtful | C13: 119 | D13: 1199458.2 | E13: 0.03 | F13: 599729.09 | G13: =D12+D13+D14 -> 20345747
A14: 5 | B14: Loss | C14: 259 | D14: 18244390 | E14: 0.44 | F14: 18244390 | G14: =G13/D15 -> 0.0049449666
B15: subtotal | C15: =SUM(C10:C14) -> 19642 | D15: =SUM(D10:D14) -> 4.1144356e+09 | E15: 100 | F15: =SUM(F11:F14) -> 19162928
B16: Reschedule/Renegotiated loans
A17: 1 | B17: Performing
A18: 2 | B18: Watch
A19: 3 | B19: Substandard
A20: 4 | B20: Doubtful
A21: 5 | B21: Loss
B22: subtotal
B23: GRAND TOTAL
A25: Note: This return should be received on or before the 15th day of the month following end of every quarter
B27: AUTHORIZATION:
B28: We declare that this return, to the best of our knowledge and belief is correct.
B29: …………………………………………………..sign……………………………..date……………………..
B30: Name of Authorizing Officer
B31: …………………………………………………..sign……………………………..date……………………..
B32: Name of Countersigning Officer

Sheet F4 June 17
B1: FORM 4 SASRA2/004
B2: RISK CLASSIFICATION OF ASSETS AND PROVISIONING
B3: NAME OF SACCO SOCIETY | F3: 2648
B4: FINANCIAL YEAR | F4: 2017
B5: START DATE: | F5: 1/1/2017
B6: END DATE: | F6: 30/6/2017
B7: PORTFOLIO AGEING REPORT
C8: A | D8: B | E8: C | F8: D
A9: NO. | B9: CLASSIFICATION | C9: NO. OF A/Cs | D9: OUTSTANDING LOAN PORTFOLIO(Kshs) | E9: REQUIRED PROVISION | F9: REQUIRED PROVISION AMOUNT(Kshs)
A10: 1 | B10: Performing | C10: 19227 | D10: 4.2698047e+09 | E10: 0.01 | F10: 0
A11: 2 | B11: Watch | C11: 458 | D11: 46848841 | E11: 0.25 | F11: 2342442
A12: 3 | B12: Substandard | C12: 176 | D12: 2832236.3 | E12: 0.5 | F12: 708059
A13: 4 | B13: Doubtful | C13: 126 | D13: 1584372.7 | E13: 0.75 | F13: 792186.35
A14: 5 | B14: Loss | C14: 260 | D14: 33735785 | E14: 1 | F14: 33735785
B15: subtotal | C15: =SUM(C10:C14) -> 20247 | D15: =SUM(D10:D14) -> 4.3548059e+09 | E15: 100 | F15: =SUM(F11:F14) -> 37578473
B16: Reschedule/Renegotiated loans
A17: 1 | B17: Performing
A18: 2 | B18: Watch
A19: 3 | B19: Substandard
A20: 4 | B20: Doubtful
A21: 5 | B21: Loss
B22: subtotal
B23: GRAND TOTAL
A25: Note: This return should be received on or before the 15th day of the month following end of every quarter
B27: AUTHORIZATION:
B28: We declare that this return, to the best of our knowledge and belief is correct.
B29: …………………………………………………..sign……………………………..date……………………..
B30: Name of Authorizing Officer
B31: …………………………………………………..sign……………………………..date……………………..
B32: Name of Countersigning Officer

Sheet F4 Sept 17
B1: FORM 4 SASRA2/004
B2: RISK CLASSIFICATION OF ASSETS AND PROVISIONING
B3: NAME OF SACCO SOCIETY | F3: 2648
B4: FINANCIAL YEAR | F4: 2017
B5: START DATE: | F5: 1/1/2017
B6: END DATE: | F6: 30/9/2017
B7: PORTFOLIO AGEING REPORT
C8: A | D8: B | E8: C | F8: D
A9: NO. | B9: CLASSIFICATION | C9: NO. OF A/Cs | D9: OUTSTANDING LOAN PORTFOLIO(Kshs) | E9: REQUIRED PROVISION | F9: REQUIRED PROVISION AMOUNT(Kshs)
A10: 1 | B10: Performing | C10: 20073 | D10: 4.7622123e+09 | E10: 0.01 | F10: 47622123
A11: 2 | B11: Watch | C11: 458 | D11: 25499215 | E11: 0.25 | F11: 1272460.7 | G11: =D12+D13+D14 -> 69670283
A12: 3 | B12: Substandard | C12: 234 | D12: 3869101.3 | E12: 0.5 | F12: 967275.33 | G12: =G11/D15 -> 0.014343176
A13: 4 | B13: Doubtful | C13: 198 | D13: 20994438 | E13: 0.75 | F13: 10497219
A14: 5 | B14: Loss | C14: 355 | D14: 44806743 | E14: 1 | F14: 33735785
B15: subtotal | C15: =SUM(C10:C14) -> 21318 | D15: =SUM(D10:D14) -> 4.8573818e+09 | F15: =SUM(F10:F14) -> 94094863
B16: Reschedule/Renegotiated loans
A17: 1 | B17: Performing
A18: 2 | B18: Watch
A19: 3 | B19: Substandard
A20: 4 | B20: Doubtful
A21: 5 | B21: Loss
B22: subtotal
B23: GRAND TOTAL
A25: Note: This return should be received on or before the 15th day of the month following end of every quarter
B27: AUTHORIZATION:
B28: We declare that this return, to the best of our knowledge and belief is correct.
B29: …………………………………………………..sign……………………………..date……………………..
B30: Name of Authorizing Officer
B31: …………………………………………………..sign……………………………..date……………………..
B32: Name of Countersigning Officer

Sheet F4 Dec 17
B1: FORM 4 SASRA2/004
B2: RISK CLASSIFICATION OF ASSETS AND PROVISIONING
B3: SACCO SOCIETY CS NUMBER | F3: 2648
B4: FINANCIAL YEAR | F4: 2017
B5: START DATE: | F5: 1/1/2017
B6: END DATE: | F6: 31/12/2017
B7: PORTFOLIO AGEING REPORT
C8: A | D8: B | E8: C | F8: D
A9: NO. | B9: CLASSIFICATION | C9: NO. OF A/Cs | D9: OUTSTANDING LOAN PORTFOLIO(Kshs) | E9: REQUIRED PROVISION | F9: REQUIRED PROVISION AMOUNT(Kshs)
A10: 1 | B10: Performing | C10: 20997 | D10: 5.2464741e+09 | E10: 0.01 | F10: =D10*E10 -> 52464741
A11: 2 | B11: Watch | C11: 459 | D11: 2917192.1 | E11: 0.05 | F11: =D11*E11 -> 145859.61
A12: 3 | B12: Substandard | C12: 226 | D12: 1864231.4 | E12: 0.25 | F12: =D12*E12 -> 466057.84
A13: 4 | B13: Doubtful | C13: 189 | D13: 1452176.3 | E13: 0.5 | F13: =D13*E13 -> 726088.16 | G13: =(D12+D13+D14)/D15 -> 0.0067674516
A14: 5 | B14: Loss | C14: 419 | D14: 32450646 | E14: 1 | F14: =D14*E14 -> 32450646
B15: subtotal | C15: =SUM(C10:C14) -> 22290 | D15: =SUM(D10:D14) -> 5.2851584e+09 | F15: =SUM(F10:F14) -> 86253393
B16: Reschedule/Renegotiated loans
A17: 1 | B17: Performing | C17: 0 | E17: 0.01 | F17: =D17*E17 -> 0
A18: 2 | B18: Watch | C18: 0 | E18: 0.05 | F18: =D18*E18 -> 0
A19: 3 | B19: Substandard | C19: 0 | E19: 0.25 | F19: =D19*E19 -> 0
A20: 4 | B20: Doubtful | C20: 0 | E20: 0.5 | F20: =D20*E20 -> 0
A21: 5 | B21: Loss | C21: 0 | E21: 1 | F21: =D21*E21 -> 0
B22: subtotal | C22: =SUM(C16:C21) -> 0 | D22: =SUM(D16:D21) -> 0 | F22: =SUM(F16:F21) -> 0
B23: GRAND TOTAL | C23: =C15+C22 -> 22290 | D23: =D15+D22 -> 5.2851584e+09 | F23: =F15+F22 -> 86253393
A25: Note: This return should be received on or before the 15th day of the month following end of every quarter
B27: AUTHORIZATION:
B28: We declare that this return, to the best of our knowledge and belief is correct.
B29: sign ………………….……………. date……………………………
B30: Name of Authorizing Officer
B31: …………………………………………………..sign……………………………..date……………………..
B32: Name of Countersigning Officer

Sheet Sheet1
A2: MENTOR SACCO | E2: 2017 Returns
A3: Year | B3: Audited 2016 | C3: 42809 | D3: 42901 | E3: 42979 | F3: 43070 | G3: Audited 2017
A4: Membership
A5: Total Assets | B5: 4877108727 | C5: 4.8796403e+09 | D5: 5.2946649e+09
A6: Total Deposits | B6: 3588473178 | C6: 3.7794211e+09 | D6: 3.8932339e+09
A7: External Borrowing | B7: 183333333 | C7: 166666666 | D7: 349999999
A8: Short term Liabilities | B8: 429264621 | C8: 2.7271934e+08 | D8: 3.7691471e+08
A9: Core Capital | B9: 532313238 | C9: 5.171088e+08 | D9: 5.3079187e+08
A10: Members Share Capital | B10: 163048132 | C10: 1.7977609e+08 | D10: 1.9201765e+08
A11: Retained Earnings | B11: 215610102 | C11: 1.8367671e+08 | D11: 1.8511772e+08
A12: Statutory Reserves | B12: 103653504 | C12: 103653504 | D12: 103653504
A13: Capital Reserve | B13: 50001500 | C13: 50002500 | D13: 50003000
A14: Investments | B14: 0 | C14: 193214051 | D14: 194114051
A15: Gross Loans & advances | B15: 4.0900427e+09 | C15: 4.1189591e+09 | D15: 4.3553488e+09
A16: Allowance for loan losses | B16: 47500000 | C16: 59500000 | D16: 71500000
... A20: Total Expenses (FinCosts + OpEx) | B20: 525056688 | C20: 1.6509546e+08 | D20: 3.2699088e+08
A21: Growth Ratios
A22: Total Assets | B22: 0.24218484 | C22: 0.0026250525 | D22: 0.072785266
A23: Total Deposits | B23: 0.19329131 | C23: 0.17744677 | D23: 0.030113822
A24: External Borrowing | B24: 0 | C24: 0 | D24: 1.1
A25: Net Loans & advances | B25: 0.29156002 | C25: -0.00023272662 | D25: 0.026936253
A26: Tunover | B26: 0.23979649 | C26: 0.52747201 | D26: 0.25045677

Sheet Sheet2
A1: Sacco Financial Performance
A3: FINANCIAL SOUNDNESS INDICATORS | B3: Prude. Std | C3: 2016 | D3: 42809 | E3: 42901 | F3: 42231
A4: CAPITAL ADEQUACY REQUIREMENTS
A5: Core capital | B5: ≥ Ksh.10M | C5: 532.31324 | D5: 517.1088 | E5: 530.79187 | F5: 571.23407
A6: Core capital /Total Assets | B6: ≥ 10% | C6: 0.10914525 | D6: 0.10597273 | E6: 0.10025032 | F6: 0.10144483
A7: Core capital /Total Deposits | B7: ≥ 8% | C7: 0.14833976 | D7: 0.13682222 | E7: 0.13633701 | F7: 0.14198083
A8: Share Capital/Total Assets | B8: ≤2% | C8: 0.03343131 | D8: 0.036842078 | E8: 0.036266252 | F8: 0.036799787
A9: Institutional Capital/Total Assets | B9: ≥ 8% | C9: 0.075713938 | D9: 0.069130652 | E9: 0.063984073 | F9: 0.064645041
A10: ASSET MIX AND QUALITY
A11: Non Earning Assets
A12: Non earning Assets/Total assets | B12: ≤ 10% | C12: 0.065137145 | D12: 0.10635023 | E12: 0.096778306 | F12: 0.11869629
A13: Property and Equipment/Total Assets | B13: ≤ 5% | C13: 0.021151993 | D13: 0.058125638 | E13: 0.068730218 | F13: 0.078036856
A14: Non Performing loans/Gross Loans | B14: ≤ 5% | D14: 0.0049449666 | E14: 0.0087609862
A15: Earning Assets
A16: Equities & Investments/Deposits | B16: ≤ 5% | C16: 0 | D16: 0.051122657 | E16: 0.049859334 | F16: 0.048346672
A17: Equities & Investments/Core Capital | B17: ≤ 40% | C17: 0 | D17: 0.37364293 | E17: 0.36570653 | F17: 0.3405155
A18: Net Loans & advances /Total assets | B18: NPR | C18: 0.83422365 | D18: 0.83191769 | E18: 0.80908781 | F18: 0.83427107
A19: FUNDING MIX
A20: Total Deposits/Total Assets | B20: NPR | C20: 0.73577879 | D20: 0.77452863 | E20: 0.73531263 | F20: 0.71449667
A21: BOSA Deposits/Total Assets | B21: NPR | C21: 0.52254738 | D21: 0.61495252 | E21: 0.59267763 | F21: 0.57387706
A22: FOSA Deposits/Total Assets | B22: NPR | C22: 0.21323142 | D22: 0.15957611 | E22: 0.142635 | F22: 0.14061961
A23: External Borrowing/Total assets | B23: ≤ 25% | C23: 0.037590577 | D23: 0.034155523 | E23: 0.066104278 | F23: 0.076955188
A24: Liquidity Ratio
A25: minimum Liquidity | B25: ≥ 15% | C25: 0.24871916 | D25: 0.13871823 | E25: 0.40292833 | F25: 0.08881482

Sheet Dec 2013
B1: FORM 4 SASRA2/004
B2: RISK CLASSIFICATION OF ASSETS AND PROVISIONING
B3: NAME OF SACCO SOCIETY | F3: 2648
B4: FINANCIAL YEAR | F4: 2013
B5: START DATE: | F5: 1/1/2013
B6: END DATE: | F6: 31/12/2013
B7: PORTFOLIO AGEING REPORT
C8: A | D8: B | E8: C | F8: D
A9: NO. | B9: CLASSIFICATION | C9: NO. OF A/Cs | D9: OUTSTANDING LOAN PORTFOLIO(Kshs) | E9: REQUIRED PROVISION | F9: REQUIRED PROVISION AMOUNT(Kshs)
A10: 1 | B10: Performing | C10: 14815 | D10: 1.9839781e+09 | E10: 99.39 | F10: 0
A11: 2 | B11: Watch | C11: 141 | D11: 707842.11 | E11: 0.12 | F11: 35392.11
A12: 3 | B12: Substandard | C12: 81 | D12: 587546.81 | E12: 0.03 | F12: 146886.7
A13: 4 | B13: Doubtful | C13: 84 | D13: 539766.81 | E13: 0.03 | F13: 269883.41
A14: 5 | B14: Loss | C14: 201 | D14: 8707018.9 | E14: 0.43 | F14: 8707018.9
B15: subtotal | C15: =SUM(C10:C14) -> 15322 | D15: =SUM(D10:D14) -> 1.9945203e+09 | E15: 100 | F15: =SUM(F11:F14) -> 9159181.1
B16: Reschedule/Renegotiated loans
A17: 1 | B17: Performing
A18: 2 | B18: Watch
A19: 3 | B19: Substandard
A20: 4 | B20: Doubtful
A21: 5 | B21: Loss
B22: subtotal
B23: GRAND TOTAL
A25: Note: This return should be received on or before the 15th day of the month following end of every quarter
B27: AUTHORIZATION:
B28: We declare that this return, to the best of our knowledge and belief is correct.
B29: …………………………………………………..sign……………………………..date……………………..
B30: Name of Authorizing Officer
B31: …………………………………………………..sign……………………………..date……………………..
B32: Name of Countersigning Officer
