Workbook

Sheet Evolutive SFP
B3: 2019 Audited | C3: 43831 | D3: 43891 | E3: 43922 | F3: 43952 | G3: 43983 | H3: 44075 | I3: 44105 | J3: 44136 | K3: 44166 | L3: 2020 Audited | M3: 44197 | N3: 44228 | O3: 44256 | P3: 44287 | Q3: 44317 | R3: 44348 | S3: 44378 | T3: 44409 | U3: 44440 | V3: 44470 | W3: 44501 | X3: 44531 | Y3: Audited 2021 | Z3: 44562 | AA3: 44593 | AB3: 44621 | AC3: 44652 | AD3: 44682 | AE3: 44713 | AF3: 44743 | AG3: 44774 | AH3: 44805 | AI3: 44835 | AJ3: 44866 | AK3: 44896 | AL3: Audit 2022 | AM3: 44927 | AN3: 44958 | AO3: 44986 | AP3: 45017 | AQ3: 45047 | AR3: 45078 | AS3: 45108 | AT3: 45139 | AU3: 45170
A4: Cash & cash Equivalent | B4: =SUM(B5:B6) -> 175549981 | C4: =SUM(C5:C6) -> 1.157514e+08 | D4: =SUM(D5:D6) -> 125385395 | E4: =SUM(E5:E6) -> 1.179096e+08 | F4: =SUM(F5:F6) -> 126001573 | G4: =SUM(G5:G6) -> 148703736 | H4: =SUM(H5:H6) -> 1.2921568e+08 | I4: =SUM(I5:I6) -> 1.2338319e+08 | ... AU4: =SUM(AU5:AU6) -> 79311802
A5: Cash In Hand | B5: 8591212 | C5: 17832612 | D5: 15586292 | E5: 15056377 | F5: 12355166 | G5: 10652458 | H5: 14669693 | I5: 16702119 | J5: 13350145 | K5: 9681170.4 | L5: 6227987 | M5: 13331270 | N5: 15844732 | O5: 11710705 | P5: 12317590 | Q5: 17336531 | R5: 16573995 | S5: 13036614 | T5: 19169044 | U5: 18630358 | V5: 21827599 | W5: 13262105 | X5: 16753691 | Y5: 9062258 | Z5: 14111195 | AA5: 19339799 | AB5: 15725381 | AC5: 9274176.4 | AD5: 12990645 | AE5: 12403405 | AF5: 12499839 | AG5: 15903644 | AH5: 15952756 | AI5: 22610230 | AJ5: 19019582 | AK5: 17040235 | AL5: 10576584 | AM5: 16438713 | AN5: 16148057 | AO5: 10043356 | AP5: 13390029 | AQ5: 17560632 | AR5: 15457613 | AS5: 12803728 | AT5: 16200090 | AU5: 13812725
A6: Cash at Bank | B6: 166958769 | C6: 97918785 | D6: 109799103 | E6: 1.0285322e+08 | F6: 113646407 | G6: 138051278 | H6: 1.1454598e+08 | I6: 1.0668107e+08 | J6: 1.1022427e+08 | K6: 1.1526995e+08 | L6: 1.7397932e+08 | M6: 1.0004873e+08 | N6: 101855561 | O6: 95857220 | P6: 89764090 | Q6: 76661529 | R6: 81225205 | S6: 91622066 | T6: 95270418 | U6: 1.0585771e+08 | V6: 99382522 | W6: 1.1464897e+08 | X6: 114945395 | Y6: 180854127 | Z6: 1.3112243e+08 | AA6: 1.2869697e+08 | AB6: 1.1310081e+08 | AC6: 93222784 | AD6: 92773814 | AE6: 1.226478e+08 | AF6: 98856232 | AG6: 96443830 | AH6: 96634886 | AI6: 1.0079811e+08 | AJ6: 1.1300765e+08 | AK6: 1.2256137e+08 | AL6: =186297973+5634445 -> 191932418 | AM6: 1.0964733e+08 | AN6: 1.1106953e+08 | AO6: 1.039034e+08 | AP6: 78067028 | AQ6: 69516244 | AR6: 90275916 | AS6: 81405867 | AT6: 74693236 | AU6: 65499077
A7: Prepayment and Sundry | B7: 30658423 | C7: 49059837 | D7: 53633771 | E7: 55448583 | F7: 56053750 | G7: 37613575 | H7: 50010771 | I7: 50209894 | J7: 51738791 | K7: 46830377 | L7: 50040207 | M7: 53438434 | N7: 54872394 | O7: 56410640 | P7: 49352949 | Q7: 58299742 | R7: 56254662 | S7: 66279487 | T7: 70186680 | U7: 67762721 | V7: 73793352 | W7: 75645352 | X7: 78688571 | Y7: 67454301 | Z7: 73311975 | AA7: 77422792 | AB7: 76487391 | AC7: 76030076 | AD7: 69064605 | AE7: 55974276 | AF7: 71472081 | AG7: 78914063 | AH7: 74315450 | AI7: 76980173 | AJ7: 71098043 | AK7: 75085842 | AL7: =875745+75586335.24 -> 76462080 | AM7: 79871425 | AN7: 78773193 | AO7: 78872340 | AP7: 67739111 | AQ7: 81463015 | AR7: 62101770 | AS7: 80672122 | AT7: 84631843 | AU7: 85004676
A8: Financial Investment | B8: =SUM(B9:B12) -> 9221631 | C8: =SUM(C9:C12) -> 57779478 | D8: =SUM(D9:D12) -> 58489478 | E8: =SUM(E9:E12) -> 59744505 | F8: =SUM(F9:F12) -> 60099478 | G8: =SUM(G9:G12) -> 60454478 | H8: =SUM(H9:H12) -> 61519478 | I8: =SUM(I9:I12) -> 62774478 | ... AU8: =SUM(AU9:AU12) -> 75323929
A9: Government Security | C9: 0 | D9: 0 | E9: 0 | F9: 0 | G9: 0 | H9: 0 | I9: 0 | J9: 0 | K9: 0 | M9: 0 | N9: 0 | O9: 0 | P9: 0 | Q9: 0 | R9: 0 | S9: 0 | T9: 0 | U9: 0 | V9: 0 | W9: 0 | X9: 0 | Z9: 0 | AA9: 0 | AB9: 0 | AC9: 0 | AD9: 0 | AE9: 0 | AF9: 0 | AG9: 0 | AH9: 0 | AI9: 0 | AJ9: 0 | AK9: 0 | AM9: 0 | AN9: 0 | AO9: 0 | AP9: 0 | AQ9: 0 | AR9: 0 | AS9: 0 | AT9: 0 | AU9: 0
A10: Other Securities | C10: 0 | D10: 0 | E10: 0 | F10: 0 | G10: 0 | H10: 0 | I10: 0 | J10: 0 | K10: 0 | M10: 0 | N10: 0 | O10: 0 | P10: 0 | Q10: 0 | R10: 0 | S10: 0 | T10: 0 | U10: 0 | V10: 0 | W10: 0 | X10: 0 | Z10: 0 | AA10: 0 | AB10: 0 | AC10: 0 | AD10: 0 | AE10: 0 | AF10: 0 | AG10: 0 | AH10: 0 | AI10: 0 | AJ10: 0 | AK10: 0 | AM10: 0 | AN10: 0 | AO10: 0 | AP10: 0 | AQ10: 0 | AR10: 0 | AS10: 0 | AT10: 0 | AU10: 0
A11: Balances with Other Saccos | B11: 9221631 | C11: 48557847 | D11: 49267847 | E11: 50522874 | F11: 50877847 | G11: 51232847 | H11: 52297847 | I11: 53552847 | J11: 54507847 | K11: 56592358 | L11: 9317364 | M11: 56947358 | N11: 57302358 | O11: 57657358 | P11: 58012358 | Q11: 58367358 | R11: 58722358 | S11: 56442298 | T11: 56797298 | U11: 57152298 | V11: 57507298 | W11: 57862298 | X11: 58217298 | Y11: 9150631 | Z11: 58572298 | AA11: 58927298 | AB11: 59712298 | AC11: 60067298 | AD11: 60422298 | AE11: 60777298 | AF11: 61132298 | AG11: 61487298 | AH11: 61842298 | AI11: 62197298 | AJ11: 62552298 | AK11: 62907298 | AL11: =203767+307580+8639284+41000 -> 9191631 | AM11: 63262298 | AN11: 63617298 | AO11: 63972298 | AP11: 64327298 | AQ11: 64682298 | AR11: 65037298 | AS11: 65392298 | AT11: 65747298 | AU11: 66102298
A12: Investment In Companies | C12: 9221631 | D12: 9221631 | E12: 9221631 | F12: 9221631 | G12: 9221631 | H12: 9221631.3 | I12: 9221631.3 | J12: 9221631.3 | K12: 9221631 | M12: 9221631 | N12: 9221631 | O12: 9221631 | P12: 9221631 | Q12: 9221631 | R12: 9221631 | S12: 9221631 | T12: 9221631 | U12: 9221631 | V12: 9221631 | W12: 9221631 | X12: 9221631 | Y12: 71000 | Z12: 9221631 | AA12: 9221631 | AB12: 9221631 | AC12: 9221631 | AD12: 9221631 | AE12: 9221631 | AF12: 9221631 | AG12: 9221631 | AH12: 9221631 | AI12: 9221631 | AJ12: 9221631 | AK12: 9221631 | AL12: 30000 | AM12: 9221631 | AN12: 9221631 | AO12: 9221631 | AP12: 9221631 | AQ12: 9221631 | AR12: 9221631 | AS12: 9221631 | AT12: 9221631 | AU12: 9221631
A13: Net Loan Portfolio | B13: =B14-B15 -> 360423402 | C13: =C14-C15 -> 3.5757131e+08 | D13: =D14-D15 -> 3.4700111e+08 | E13: =E14-E15 -> 340745739 | F13: =F14-F15 -> 331981703 | G13: =G14-G15 -> 324174103 | H13: =H14-H15 -> 3.2941099e+08 | I13: =I14-I15 -> 3.361167e+08 | ... AU13: =AU14-AU15 -> 4.9239623e+08
A14: Gross Loan Portfolio | B14: 369086787 | C14: 366682836 | D14: 3.5626197e+08 | E14: 350006594 | F14: 341242558 | G14: 333434958 | H14: 3.496496e+08 | I14: 3.5635532e+08 | J14: 3.5601312e+08 | K14: 3.7668332e+08 | L14: 393314726 | M14: 3.7693815e+08 | N14: 3.758275e+08 | O14: 3.8291083e+08 | P14: 3.8593014e+08 | Q14: 3.9492702e+08 | R14: 3.9388915e+08 | S14: 4.0752463e+08 | T14: 4.0862996e+08 | U14: 4.0635407e+08 | V14: 4.0928779e+08 | W14: 4.1003297e+08 | X14: 4.0937931e+08 | Y14: 409379310 | Z14: 4.160264e+08 | AA14: 4.1652954e+08 | AB14: 422681669 | AC14: 4.3395563e+08 | AD14: 4.4003127e+08 | AE14: 4.3666859e+08 | AF14: 4.4320895e+08 | AG14: 4.4322052e+08 | AH14: 4.442866e+08 | AI14: 4.4600293e+08 | AJ14: 4.4944439e+08 | AK14: 4.5117654e+08 | AL14: 4.5117654e+08 | AM14: 4.6686895e+08 | AN14: 4.6781576e+08 | AO14: 4.7477445e+08 | AP14: 4.8917091e+08 | AQ14: 4.8977436e+08 | AR14: 4.9759461e+08 | AS14: 4.9921479e+08 | AT14: 5.107986e+08 | AU14: 5.1685656e+08
A15: Allowance For Loan Loss | B15: 8663385 | C15: 9111524.9 | D15: 9260855 | E15: 9260855 | F15: 9260855 | G15: 9260855 | H15: 20238613 | I15: 20238613 | J15: 20238613 | K15: 27703571 | L15: 27690971 | M15: 27703571 | N15: 27703571 | O15: 27690971 | P15: 27690971 | Q15: 27690971 | R15: 27690971 | S15: 27690971 | T15: 27690971 | U15: 27690971 | V15: 27690971 | W15: 27690971 | X15: 24223709 | Y15: 24223709 | Z15: 24223709 | AA15: 24223709 | AB15: 24223709 | AC15: 24223709 | AD15: 24223709 | AE15: 24223709 | AF15: 24223709 | AG15: 24223709 | AH15: 24223709 | AI15: 24223709 | AJ15: 24223709 | AK15: 24460329 | AL15: 24460329 | AM15: 24460329 | AN15: 24460329 | AO15: 24460329 | AP15: 24460329 | AQ15: 24460329 | AR15: 24460329 | AS15: 24460329 | AT15: 24460329 | AU15: 24460329
A16: Accounts Recievables | B16: =SUM(B17:B18) -> 0 | C16: =SUM(C17:C18) -> 0 | D16: =SUM(D17:D18) -> 0 | E16: =SUM(E17:E18) -> 0 | F16: =SUM(F17:F18) -> 0 | G16: =SUM(G17:G18) -> 0 | H16: =SUM(H17:H18) -> 0 | I16: =SUM(I17:I18) -> 0 | ... AU16: =SUM(AU17:AU18) -> 0
A17: Tax Recoverable | C17: 0 | D17: 0 | E17: 0 | F17: 0 | G17: 0 | H17: 0 | I17: 0 | J17: 0 | K17: 0 | M17: 0 | N17: 0 | O17: 0 | P17: 0 | Q17: 0 | R17: 0 | S17: 0 | T17: 0 | Z17: 0 | AA17: 0 | AB17: 0 | AC17: 0 | AD17: 0 | AE17: 0 | AF17: 0 | AG17: 0 | AH17: 0 | AI17: 0 | AJ17: 0 | AK17: 0 | AM17: 0 | AN17: 0 | AO17: 0 | AP17: 0 | AQ17: 0 | AR17: 0 | AS17: 0 | AT17: 0 | AU17: 0
A18: Deffered Tax Assets | C18: 0 | D18: 0 | E18: 0 | F18: 0 | G18: 0 | H18: 0 | I18: 0 | J18: 0 | K18: 0 | M18: 0 | N18: 0 | O18: 0 | P18: 0 | Q18: 0 | R18: 0 | S18: 0 | T18: 0 | Z18: 0 | AA18: 0 | AB18: 0 | AC18: 0 | AD18: 0 | AE18: 0 | AF18: 0 | AG18: 0 | AH18: 0 | AI18: 0 | AJ18: 0 | AK18: 0 | AM18: 0 | AN18: 0 | AO18: 0 | AP18: 0 | AQ18: 0 | AR18: 0 | AS18: 0 | AT18: 0 | AU18: 0
A19: Retirement Benefit Assets | C19: 0 | D19: 0 | E19: 0 | F19: 0 | G19: 0 | H19: 0 | I19: 0 | J19: 0 | K19: 0 | M19: 0 | N19: 0 | O19: 0 | P19: 0 | Q19: 0 | R19: 0 | S19: 0 | T19: 0 | Z19: 0 | AA19: 0 | AB19: 0 | AC19: 0 | AD19: 0 | AE19: 0 | AF19: 0 | AG19: 0 | AH19: 0 | AI19: 0 | AJ19: 0 | AK19: 0 | AM19: 0 | AN19: 0 | AO19: 0 | AP19: 0 | AQ19: 0 | AR19: 0 | AS19: 0 | AT19: 0 | AU19: 0
A20: Property&Equipments&Other Assets | B20: =SUM(B21:B25) -> 40896479 | C20: =SUM(C21:C25) -> 181645018 | D20: =SUM(D21:D25) -> 181645018 | E20: =SUM(E21:E25) -> 181645038 | F20: =SUM(F21:F25) -> 181645038 | G20: =SUM(G21:G25) -> 181645038 | H20: =SUM(H21:H25) -> 1.8350993e+08 | I20: =SUM(I21:I25) -> 1.842383e+08 | ... AU20: =SUM(AU21:AU25) -> 1.6703031e+08
A21: Investment Properties | C21: 0 | D21: 0 | E21: 0 | F21: 0 | G21: 0 | H21: 0 | I21: 0 | J21: 0 | K21: 0 | M21: 0 | N21: 0 | O21: 0 | P21: 0 | Q21: 0 | R21: 0 | S21: 0 | T21: 0 | U21: 0 | V21: 0 | W21: 0 | X21: 0 | Z21: 0 | AA21: 0 | AB21: 0 | AC21: 0 | AD21: 0 | AE21: 0 | AF21: 0 | AG21: 0 | AH21: 0 | AI21: 0 | AJ21: 0 | AK21: 0 | AM21: 0 | AN21: 0 | AO21: 0 | AP21: 0 | AQ21: 0 | AR21: 0 | AS21: 0 | AT21: 0 | AU21: 0
A22: Property and Equipment | B22: 23963774 | C22: 22863775 | D22: 22863775 | E22: 22863775 | F22: 22863775 | G22: 22863775 | H22: 23946128 | I22: 24674503 | J22: 24674503 | K22: 25397132 | L22: 23660693 | M22: 26062032 | N22: 24547049 | O22: 24594849 | P22: 24594849 | Q22: 24820149 | R22: 25138439 | S22: 25146039 | T22: 25193739 | U22: 25555779 | V22: 25555779 | W22: 25555779 | X22: 25577679 | Y22: 22963419 | Z22: 25639209 | AA22: 25639209 | AB22: 23024950 | AC22: 23024950 | AD22: 23525650 | AE22: 23525650 | AF22: 23525650 | AG22: 23525650 | AH22: 23525650 | AI22: 23525650 | AJ22: 23686650 | AK22: 23686650 | AL22: 21262616 | AM22: 23686650 | AN22: 23850350 | AO22: 21478316 | AP22: 21478316 | AQ22: 21478316 | AR22: 21478316 | AS22: 24678316 | AT22: 24969746 | AU22: 24969746
A23: Prepaid Lease Rentals | C23: 0 | D23: 0 | E23: 0 | F23: 0 | G23: 0 | H23: 0 | I23: 0 | J23: 0 | K23: 0 | M23: 0 | N23: 0 | O23: 0 | P23: 0 | Q23: 0 | R23: 0 | S23: 0 | T23: 0 | U23: 0 | V23: 0 | W23: 0 | X23: 0 | Z23: 0 | AA23: 0 | AB23: 0 | AC23: 0 | AD23: 0 | AE23: 0 | AF23: 0 | AG23: 0 | AH23: 0 | AI23: 0 | AJ23: 0 | AK23: 0 | AM23: 0 | AN23: 0 | AO23: 0 | AP23: 0 | AQ23: 0 | AR23: 0 | AS23: 0 | AT23: 0 | AU23: 0
A24: Intangible Assets | B24: 1105020 | C24: 655020 | D24: 655020 | E24: 655020 | F24: 655020 | G24: 655020 | H24: 1437557.5 | I24: 1437557.5 | J24: 1437557.5 | K24: 1437557.5 | L24: 771182 | M24: 1437557.5 | N24: 1244762 | O24: 771181.68 | P24: 771181.68 | Q24: 771181.68 | R24: 771181.68 | S24: 771181.68 | T24: 771181.68 | U24: 771181.68 | V24: 771181.68 | W24: 771181.68 | X24: 771181.68 | Y24: 616945 | Z24: 771181.68 | AA24: 771181.68 | AB24: 616945.28 | AC24: 616945.28 | AD24: 616945.28 | AE24: 616945.28 | AF24: 616945.28 | AG24: 616945.28 | AH24: 616945.28 | AI24: 616945.28 | AJ24: 616945.28 | AK24: 616945.28 | AL24: 462709.1 | AM24: 616945.28 | AN24: 616945.28 | AO24: 462708.78 | AP24: 462708.78 | AQ24: 462708.78 | AR24: 462708.78 | AS24: 462708.78 | AT24: 462708.78 | AU24: 462708.78
A25: Other Assets | B25: 15827685 | C25: 158126223 | D25: 158126223 | E25: 158126243 | F25: 158126243 | G25: 158126243 | H25: 1.5812624e+08 | I25: 1.5812624e+08 | J25: 1.5812624e+08 | K25: 1.5462624e+08 | L25: 15827685 | M25: 1.5462017e+08 | N25: 1.5462017e+08 | O25: 1.5462017e+08 | P25: 1.5462017e+08 | Q25: 1.5462017e+08 | R25: 1.5462017e+08 | S25: 1.5462019e+08 | T25: 1.5462019e+08 | U25: 1.5462019e+08 | V25: 1.5462019e+08 | W25: 1.5462019e+08 | X25: 1.5112019e+08 | Y25: =148126223+13621436.3 -> 1.6174766e+08 | Z25: 1.5112019e+08 | AA25: 1.5110806e+08 | AB25: 1.4810806e+08 | AC25: 1.4810806e+08 | AD25: 1.4810806e+08 | AE25: 1.4810806e+08 | AF25: 1.4810806e+08 | AG25: 1.4810806e+08 | AH25: 1.4810806e+08 | AI25: 1.4810806e+08 | AJ25: 1.4810606e+08 | AK25: 1.4160406e+08 | AL25: =6300000+7321436.3+141626223 -> 1.5524766e+08 | AM25: 1.4160202e+08 | AN25: 1.4159786e+08 | AO25: 1.4159786e+08 | AP25: 1.4159786e+08 | AQ25: 1.4159786e+08 | AR25: 1.4159786e+08 | AS25: 1.4159786e+08 | AT25: 1.4159786e+08 | AU25: 1.4159786e+08
A26: Total Assets | B26: =B20+B16+B13+B8+B7+B4 -> 616749916 | C26: =C20+C16+C13+C8+C7+C4 -> 7.6180704e+08 | D26: =D20+D16+D13+D8+D7+D4 -> 7.6615477e+08 | E26: =E20+E16+E13+E8+E7+E4 -> 7.5549346e+08 | F26: =F20+F16+F13+F8+F7+F4 -> 7.5578154e+08 | G26: =G20+G16+G13+G8+G7+G4 -> 7.5259093e+08 | H26: =H20+H16+H13+H8+H7+H4 -> 7.5366684e+08 | I26: =I20+I16+I13+I8+I7+I4 -> 7.5672257e+08 | ... AU26: =AU20+AU16+AU13+AU8+AU7+AU4 -> 8.9906695e+08
A27: Savings and Deposits | B27: 127986727 | C27: 97743215 | D27: 103735571 | E27: 1.130541e+08 | F27: 1.0809158e+08 | G27: 1.0286644e+08 | H27: 1.1367251e+08 | I27: 1.1411871e+08 | J27: 1.11392e+08 | K27: 1.2545408e+08 | L27: 145871163 | M27: 1.1410223e+08 | N27: 1.1415724e+08 | O27: 1.356129e+08 | P27: 1.1310659e+08 | Q27: 1.1752093e+08 | R27: 1.1608396e+08 | S27: 1.2354028e+08 | T27: 1.2996222e+08 | U27: 1.2266211e+08 | V27: 1.2318017e+08 | W27: 1.2506294e+08 | X27: 1.2457183e+08 | Y27: 143820589 | Z27: 1.2691902e+08 | AA27: 1.3250748e+08 | AB27: 1.5232834e+08 | AC27: 1.3149993e+08 | AD27: 1.2332032e+08 | AE27: 1.3099475e+08 | AF27: 1.2790434e+08 | AG27: 1.2502628e+08 | AH27: 1.1855901e+08 | AI27: 1.2786296e+08 | AJ27: 1.3187994e+08 | AK27: 1.3860573e+08 | AL27: =138605725+12616719+4706998+411650+1604200+622144 -> 158567436 | AM27: 1.3420874e+08 | AN27: 1.2738977e+08 | AO27: 1.5178706e+08 | AP27: 1.2787914e+08 | AQ27: 1.2992657e+08 | AR27: 1.3069846e+08 | AS27: 1.379955e+08 | AT27: 1.397159e+08 | AU27: 1.3180921e+08
A28: Short Terrm Deposits | B28: 27362889 | C28: 48022408 | D28: 51077224 | E28: 52285954 | F28: 53544527 | G28: 54705990 | H28: 56248600 | I28: 56010701 | J28: 56202227 | K28: 58128748 | L28: 37711665 | M28: 60067995 | N28: 58383273 | O28: 54593574 | P28: 57936327 | Q28: 56706975 | R28: 55940179 | S28: 57885735 | T28: 59894932 | U28: 66021396 | V28: 64409910 | W28: 65271957 | X28: 65200524 | Y28: 45951567 | Z28: 69289523 | AA28: 67210468 | AB28: 68322544 | AC28: 67443281 | AD28: 70614372 | AE28: 73247487 | AF28: 75113729 | AG28: 75689517 | AH28: 75676983 | AI28: 76451572 | AJ28: 77134666 | AK28: 73888005 | AL28: 53926294 | AM28: 78937745 | AN28: 81864015 | AO28: 80719162 | AP28: 81874989 | AQ28: 79310674 | AR28: 80573118 | AS28: 77454987 | AT28: 83604355 | AU28: 78021902
A29: Non Withdrawable Deposits | B29: 418806431 | C29: 4.2198244e+08 | D29: 427325266 | E29: 4.2916071e+08 | F29: 4.3220893e+08 | G29: 4.3426279e+08 | H29: 4.4005123e+08 | I29: 4.4155717e+08 | J29: 4.4332697e+08 | K29: 4.4463522e+08 | L29: 444635223 | M29: 4.4719704e+08 | N29: 4.4989727e+08 | O29: 4.5203289e+08 | P29: 4.5356745e+08 | Q29: 4.5647932e+08 | R29: 4.4982749e+08 | S29: 4.5087945e+08 | T29: 4.5354175e+08 | U29: 4.5538079e+08 | V29: 4.5762464e+08 | W29: 4.5927695e+08 | X29: 4.6201706e+08 | Y29: 462017056 | Z29: 4.6480839e+08 | AA29: 4.6707999e+08 | AB29: 4.7070883e+08 | AC29: 4.7292531e+08 | AD29: 4.7617714e+08 | AE29: 4.7941537e+08 | AF29: 4.7750452e+08 | AG29: 4.8137474e+08 | AH29: 4.8284536e+08 | AI29: 4.8333572e+08 | AJ29: 4.8233205e+08 | AK29: 4.7901831e+08 | AL29: 479018315 | AM29: 4.8162851e+08 | AN29: 4.847309e+08 | AO29: 4.8966111e+08 | AP29: 4.9289653e+08 | AQ29: 4.949934e+08 | AR29: 4.9724728e+08 | AS29: 4.9908491e+08 | AT29: 4.9826451e+08 | AU29: 5.0059285e+08
A30: Total Deposit Liabilities | B30: =SUM(B27:B29) -> 574156047 | C30: =SUM(C27:C29) -> 5.6774807e+08 | D30: =SUM(D27:D29) -> 582138061 | E30: =SUM(E27:E29) -> 5.9450076e+08 | F30: =SUM(F27:F29) -> 5.9384504e+08 | G30: =SUM(G27:G29) -> 5.9183523e+08 | H30: =SUM(H27:H29) -> 6.0997234e+08 | I30: =SUM(I27:I29) -> 6.1168659e+08 | ... AU30: =SUM(AU27:AU29) -> 7.1042396e+08
A31: Tax Payable | B31: 1800000 | C31: 0 | D31: 0 | E31: 0 | F31: 0 | G31: 0 | H31: 0 | I31: 0 | J31: 0 | K31: 0 | L31: 1500000 | M31: 0 | N31: 0 | O31: 0 | P31: 0 | Q31: 0 | R31: 0 | S31: 0 | T31: 0 | U31: 0 | V31: 0 | W31: 0 | X31: 0 | Y31: 2500000 | Z31: 0 | AA31: 0 | AB31: 0 | AC31: 0 | AD31: 0 | AE31: 0 | AF31: 0 | AG31: 0 | AH31: 0 | AI31: 0 | AJ31: 0 | AK31: 0 | AL31: 706224 | AM31: 0 | AN31: 0 | AO31: 0 | AQ31: 0 | AR31: 0 | AS31: 0 | AT31: 0 | AU31: 0
A32: Dividends Payable | B32: 31410482 | C32: 49781424 | D32: 45072728 | E32: 12898801 | F32: 17441784 | G32: 21445740 | H32: 0 | I32: 0 | J32: 0 | K32: 0 | L32: 35570818 | M32: 0 | N32: 0 | O32: 0 | P32: 0 | Q32: 0 | R32: 0 | S32: 0 | T32: 0 | U32: 0 | V32: 0 | W32: 0 | X32: 0 | Y32: 39271450 | Z32: 50000000 | AA32: 50000000 | AB32: 0 | AC32: 0 | AD32: 0 | AE32: 0 | AF32: 0 | AG32: 0 | AH32: 0 | AI32: 0 | AJ32: 0 | AK32: 0 | AL32: 38321465 | AM32: 0 | AN32: 0 | AO32: 0 | AP32: 0 | AQ32: 0 | AR32: 0 | AS32: 0 | AT32: 0 | AU32: 0
A33: Deferred Tax Liability | C33: 0 | D33: 0 | E33: 0 | F33: 0 | G33: 0 | H33: 0 | I33: 0 | J33: 0 | K33: 0 | M33: 0 | N33: 0 | O33: 0 | P33: 0 | Q33: 0 | R33: 0 | S33: 0 | T33: 0 | U33: 0 | V33: 0 | W33: 0 | X33: 0 | Z33: 0 | AA33: 0 | AB33: 0 | AC33: 0 | AD33: 0 | AE33: 0 | AF33: 0 | AG33: 0 | AH33: 0 | AI33: 0 | AJ33: 0 | AK33: 0 | AM33: 0 | AN33: 0 | AO33: 0 | AP33: 0 | AQ33: 0 | AR33: 0 | AS33: 0 | AT33: 0 | AU33: 0
A34: Retirement Benefits Liabilty | C34: 0 | D34: 0 | E34: 0 | F34: 0 | G34: 0 | H34: 0 | I34: 0 | J34: 0 | K34: 0 | M34: 0 | N34: 0 | O34: 0 | P34: 0 | Q34: 0 | R34: 0 | S34: 0 | T34: 0 | U34: 0 | V34: 0 | W34: 0 | X34: 0 | Z34: 0 | AA34: 0 | AB34: 0 | AC34: 0 | AD34: 0 | AE34: 0 | AF34: 0 | AG34: 0 | AH34: 0 | AI34: 0 | AJ34: 0 | AK34: 0 | AM34: 0 | AN34: 0 | AO34: 0 | AP34: 0 | AQ34: 0 | AR34: 0 | AS34: 0 | AT34: 0 | AU34: 0
A35: Other Liabilities | B35: 11233128 | C35: 9394483 | D35: 9449472 | E35: 9206836 | F35: 8770448 | G35: 6857934 | H35: 5404385 | I35: 4988367.3 | J35: 5498614.6 | K35: -5923672.9 | L35: 7359120 | M35: -5970032 | N35: 32416732 | O35: -2657389.3 | P35: 382751.23 | Q35: 568958.8 | R35: 45111.87 | S35: 10862855 | T35: 9655862.9 | U35: 9635729.4 | V35: 10891535 | W35: 11843905 | X35: 6402788.6 | Y35: 7224159 | Z35: 5888900.5 | AA35: 8522411.1 | AB35: 9762219 | AC35: 8376563.8 | AD35: 8791570.2 | AE35: 5699462.8 | AF35: 7217666.5 | AG35: 7886425.2 | AH35: 8180742.2 | AI35: 9237083.6 | AJ35: 10013380 | AK35: 32473318 | AL35: 5863487 | AM35: 41251590 | AN35: 42099275 | AO35: 5078318.4 | AP35: 5878765.8 | AQ35: 7241519.8 | AR35: 6947017.2 | AS35: 8320309.8 | AT35: 9285533.9 | AU35: 9693076.4
A36: External Borrowings | B36: 30000000 | C36: 26040073 | D36: 20587500 | E36: 19480080 | F36: 16342580 | G36: 13205080 | H36: 3792579.8 | I36: 2197660.8 | J36: -79939.3 | K36: -1830436.2 | L36: 0 | M36: -4967936.2 | N36: -4967936.2 | O36: 3039457.8 | P36: 3039457.8 | Q36: 3039457.8 | R36: 0 | S36: 0 | T36: 0 | U36: 0 | V36: 0 | W36: 0 | X36: 0 | Z36: 0 | AA36: 0 | AB36: 0 | AC36: 0 | AD36: 0 | AE36: 0 | AF36: 0 | AG36: 0 | AH36: 0 | AI36: 0 | AJ36: 0 | AK36: 0 | AL36: 0 | AM36: 0 | AN36: 0 | AO36: 0 | AP36: 0 | AQ36: 0 | AR36: 0 | AS36: 0 | AT36: 0 | AU36: 0
A37: Total Liabilities | B37: =SUM(B30:B36) -> 6.4859966e+08 | C37: =SUM(C30:C36) -> 6.5296405e+08 | D37: =SUM(D30:D36) -> 6.5724776e+08 | E37: =SUM(E30:E36) -> 6.3608647e+08 | F37: =SUM(F30:F36) -> 6.3639985e+08 | G37: =SUM(G30:G36) -> 6.3334398e+08 | H37: =SUM(H30:H36) -> 6.1916931e+08 | I37: =SUM(I30:I36) -> 6.1887261e+08 | ... AU37: =SUM(AU30:AU36) -> 7.2011704e+08
A38: Share Capital | B38: 48764688 | C38: 48777188 | D38: 48771288 | E38: 48771288 | F38: 48771288 | G38: 48771288 | H38: 49431500 | I38: 49432000 | J38: 49434000 | K38: 49435000 | L38: 49435000 | M38: 49435000 | N38: 49435200 | O38: 49438421 | P38: 49438421 | Q38: 49442421 | R38: 58592805 | S38: 58594805 | T38: 58594805 | U38: 58595805 | V38: 58595805 | W38: 58606805 | X38: 58607805 | Y38: 58607805 | Z38: 58607805 | AA38: 58609305 | AB38: 58498533 | AC38: 58498533 | AD38: 58498533 | AE38: 58498533 | AF38: 58498533 | AG38: 58498533 | AH38: 58520308 | AI38: 59285431 | AJ38: 59285431 | AK38: 68817747 | AL38: 68817747 | AM38: 68817747 | AN38: 68817747 | AO38: 68802747 | AP38: 68815247 | AQ38: 69000962 | AR38: 68985962 | AS38: 68987162 | AT38: 68989362 | AU38: 68990362
A39: Capital Grants | C39: 0 | D39: 0 | E39: 0 | F39: 0 | G39: 0 | H39: 0 | I39: 0 | J39: 0 | K39: 0 | M39: 0 | N39: 0 | O39: 0 | P39: 0 | Q39: 0 | R39: 0 | S39: 0 | T39: 0 | U39: 0 | V39: 0 | W39: 0 | X39: 0 | Z39: 0 | AA39: 0 | AB39: 0 | AC39: 0 | AD39: 0 | AE39: 0 | AF39: 0 | AG39: 0 | AH39: 0 | AI39: 0 | AJ39: 0 | AK39: 0 | AL39: 0 | AM39: 0 | AN39: 0 | AO39: 0 | AP39: 0 | AQ39: 0 | AR39: 0 | AS39: 0 | AT39: 0 | AU39: 0
A40: Prior Year Retained Earnigs | B40: 30492146 | C40: 30942146 | D40: 30942146 | E40: 38134753 | F40: 38134753 | G40: 38134753 | H40: 21503348 | I40: 21503348 | J40: 21503348 | K40: 21503295 | L40: 38134753 | M40: 47693974 | N40: 0 | O40: 0 | P40: 0 | Q40: 0 | R40: 27089696 | S40: 29196279 | T40: 29196279 | U40: 29196279 | V40: 29196279 | W40: 29196279 | X40: 29196232 | Y40: 45827684 | Z40: 39951182 | AA40: 38251182 | AB40: 36283733 | AC40: 36283693 | AD40: 36283733 | AE40: 36283733 | AF40: 36283833 | AG40: 36283833 | AH40: 36283833 | AI40: 36283833 | AJ40: 36283833 | AK40: 36283833 | AL40: 36283733 | AM40: 42219097 | AN40: 42219097 | AO40: 35587821 | AP40: 31755354 | AQ40: 31713783 | AR40: 31713725 | AS40: 32547970 | AT40: 32547970 | AU40: 32547970
A41: Current Year Surplus | B41: =-4643649+12286256.35 -> 7642607.3 | C41: 855316.06 | D41: 925234.67 | E41: 1161015.3 | F41: 1135746.2 | G41: 1001002.5 | H41: 0 | I41: 0 | J41: 0 | K41: 0 | L41: 7692930 | M41: 21503348 | N41: 27992993 | O41: 29196279 | P41: 29196279 | Q41: 29196279 | R41: 27820931 | S41: 32688113 | T41: 37997672 | U41: 43417208 | V41: 47052383 | W41: 51345032 | X41: 61129358 | Y41: =7087454.1-16631405 -> -9543950.9 | Z41: 4193655.6 | AA41: 5237610.3 | AB41: 12133302 | AC41: 17852612 | AD41: 22427625 | AE41: 25162694 | AF41: 25477436 | AG41: 32040693 | AH41: 33796411 | AI41: 36962810 | AJ41: 39182322 | AK41: 13935382 | AL41: =14259291.55-2851858.31-300000 -> 11107433 | AM41: 3274284.2 | AN41: 4711561.6 | AO41: 8960035.9 | AP41: 12624759 | AQ41: 19840040 | AR41: 23332044 | AS41: 27328372 | AT41: 32185270 | AU41: 38141805
A42: Statutory Reserves | B42: 13603823 | C42: 10532259 | D42: 10532259 | E42: 13603823 | F42: 13603823 | G42: 13603823 | H42: 0 | I42: 0 | J42: 0 | K42: 0 | L42: 15589556 | M42: 0 | N42: 0 | O42: 0 | P42: 0 | Q42: 0 | R42: 15589556 | S42: 15589556 | T42: 15589556 | U42: 15589556 | V42: 15589556 | W42: 15589556 | X42: 15589556 | Y42: 18681835 | Z42: 18278235 | AA42: 18278235 | AB42: 18681835 | AC42: 18681835 | AD42: 18681835 | AE42: 18681835 | AF42: 18681835 | AG42: 18681835 | AH42: 18681835 | AI42: 18681835 | AJ42: 18681835 | AK42: 18681835 | AL42: 21533693 | AM42: 18681835 | AN42: 18681835 | AO42: 21533694 | AP42: 21533694 | AQ42: 21533694 | AR42: 21533694 | AS42: 21533694 | AT42: 21533694 | AU42: 21533694
A43: Other Reserves | B43: =17608559+127525 -> 17736084 | C43: 17736084 | D43: 17736084 | E43: 17736084 | F43: 17736084 | G43: 17736084 | H43: 13603823 | I43: 13603823 | J43: 13603823 | K43: 13603823 | L43: =17608559+127525 -> 17736084 | M43: 0 | N43: 0 | O43: 0 | P43: 0 | Q43: 0 | R43: 17736084 | S43: 17736084 | T43: 17736084 | U43: 17736084 | V43: 17736084 | W43: 17736084 | X43: 17736084 | Y43: =127525+17608559 -> 17736084 | Z43: 17736084 | AA43: 17736084 | AB43: 17736084 | AC43: 17736084 | AD43: 17736084 | AE43: 17736084 | AF43: 17736084 | AG43: 17736084 | AH43: 17736084 | AI43: 127525 | AJ43: 127525 | AK43: =17608559+127525 -> 17736084 | AL43: =17608559+127525 -> 17736084 | AM43: =17608559+127525 -> 17736084 | AN43: =17608559+127525 -> 17736084 | AO43: =17608559+127525 -> 17736084 | AP43: 127525 | AQ43: 127525 | AR43: 127525 | AS43: 127525 | AT43: 127525 | AU43: 127525
A44: Revaluation Reserves | C44: 0 | D44: 0 | E44: 0 | F44: 0 | G44: 0 | H44: 17736084 | I44: 17736084 | J44: 17736084 | K44: 17736084 | M44: 13603823 | N44: 15589556 | O44: 15589556 | P44: 15589556 | Q44: 15589556 | R44: 0 | S44: 0 | T44: 0 | U44: 0 | V44: 0 | W44: 0 | X44: 0 | Z44: 0 | AA44: 0 | AB44: 0 | AC44: 0 | AD44: 0 | AE44: 0 | AF44: 0 | AG44: 0 | AH44: 0 | AI44: 17608559 | AJ44: 17608559 | AP44: 17608559 | AQ44: 17608559 | AR44: 17608559 | AS44: 17608559 | AT44: 17608559 | AU44: 17608559
A45: Proposed Dividends | C45: 0 | D45: 0 | E45: 0 | F45: 0 | G45: 0 | H45: 0 | I45: 0 | J45: 0 | K45: 0 | M45: 17736084 | N45: 17736084 | O45: 17736084 | P45: 17736084 | Q45: 17736084 | R45: 0 | S45: 0 | T45: 0 | Y45: 4981663.4 | Z45: 0 | AA45: 0 | AB45: 0 | AC45: 0 | AD45: 0 | AE45: 0 | AF45: 0 | AG45: 0 | AH45: 0 | AI45: 0 | AJ45: 0 | AK45: 0 | AM45: 0 | AN45: 0 | AO45: 0 | AP45: 0 | AQ45: 0 | AR45: 0 | AS45: 0 | AT45: 0 | AU45: 0
A46: Adjustment To Equity | C46: 0 | D46: 0 | E46: 0 | F46: 0 | G46: 0 | H46: 0 | I46: 0 | J46: 0 | K46: 0 | M46: 0 | N46: 0 | O46: 0 | P46: 0 | Q46: 0 | R46: 0 | S46: 0 | T46: 0 | AF46: 0 | AG46: 0 | AH46: 0 | AI46: 0 | AJ46: 0 | AK46: 0 | AM46: 0 | AN46: 0 | AO46: 0 | AP46: 0 | AQ46: 0 | AR46: 0 | AS46: 0 | AT46: 0 | AU46: 0
A47: Total Equity | B47: =SUM(B38:B46) -> 1.1823935e+08 | C47: =SUM(C38:C46) -> 1.0884299e+08 | D47: =SUM(D38:D46) -> 1.0890701e+08 | E47: =SUM(E38:E46) -> 1.1940696e+08 | F47: =SUM(F38:F46) -> 1.1938169e+08 | G47: =SUM(G38:G46) -> 1.1924695e+08 | H47: =SUM(H38:H46) -> 1.0227476e+08 | I47: =SUM(I38:I46) -> 1.0227526e+08 | ... AU47: =SUM(AU38:AU46) -> 1.7894991e+08
A48: Total Liabilities and Equity | B48: =B47+B37 -> 7.6683901e+08 | C48: =C47+C37 -> 7.6180704e+08 | D48: =D47+D37 -> 7.6615477e+08 | E48: =E47+E37 -> 7.5549344e+08 | F48: =F47+F37 -> 7.5578154e+08 | G48: =G47+G37 -> 7.5259093e+08 | H48: =H47+H37 -> 7.2144406e+08 | I48: =I47+I37 -> 7.2114787e+08 | ... AU48: =AU47+AU37 -> 8.9906695e+08
AT49: =AT48-AT26 -> 0 | AU49: =AU48-AU26 -> 0
B50: =B48-B26 -> 1.5008909e+08 | C50: =C48-C26 -> 0 | D50: =D48-D26 -> 0 | E50: =E48-E26 -> -27 | F50: =F48-F26 -> 0 | G50: =G48-G26 -> 0 | H50: =H48-H26 -> -32222782 | I50: =I48-I26 -> -35574698 | ... AP50: =AP48-AP26 -> 0

Sheet Evolutitve SCI
B2: 2019 Audited | C2: 43831 | D2: 43891 | E2: 43922 | F2: 43952 | G2: 43983 | H2: 44075 | I2: 44105 | J2: 44136 | K2: 44166 | L2: 2020 Audited | M2: 44197 | N2: 44228 | O2: 44256 | P2: 44287 | Q2: 44317 | R2: 44348 | S2: 44378 | T2: 44409 | U2: 44440 | V2: 44470 | W2: 44501 | X2: 44531 | Y2: Audited 2021 | Z2: 44562 | AA2: 44593 | AB2: 44621 | AC2: 44652 | AD2: 44682 | AE2: 44713 | AF2: 44743 | AG2: 44774 | AH2: 44805 | AI2: 44835 | AJ2: 44866 | AK2: 44896 | AL2: Audit 2022 | AM2: 44927 | AN2: 44958 | AO2: 44986 | AP2: 45017 | AQ2: 45047 | AR2: 45078 | AS2: 45108 | AT2: 45139 | AU2: 45170
A3: Financial Income | B3: =B4+B7 -> 96487681 | C3: =C4+C7 -> 12861103 | D3: =D4+D7 -> 26935221 | E3: =E4+E7 -> 34915525 | F3: =F4+F7 -> 42684260 | G3: =G4+G7 -> 50417367 | H3: =H4+H7 -> 75135052 | I3: =I4+I7 -> 84769011 | ... AU3: =AU4+AU7 -> 77624275
A4: Financial Income From Loans Portfolio | B4: =SUM(B5:B6) -> 77566990 | C4: =SUM(C5:C6) -> 7835719.5 | D4: =SUM(D5:D6) -> 21312529 | E4: =SUM(E5:E6) -> 27052029 | F4: =SUM(F5:F6) -> 32952055 | G4: =SUM(G5:G6) -> 39366821 | H4: =SUM(H5:H6) -> 59356592 | I4: =SUM(I5:I6) -> 67027324 | ... AU4: =SUM(AU5:AU6) -> 67516324
A5: Interest from Loans Portfolio | B5: 77566990 | C5: 6732613.4 | D5: 19015406 | E5: 24439884 | F5: 30141958 | G5: 35979618 | H5: 53936455 | I5: 60560876 | J5: 66932004 | K5: 72832194 | L5: 75449048 | M5: 6276569.2 | N5: 13209014 | O5: 20411142 | P5: 27727065 | Q5: 35762505 | R5: 43141143 | S5: 51508820 | T5: 59246778 | U5: 66917748 | V5: 74752209 | W5: 82125927 | X5: 90279888 | Y5: 90924708 | Z5: 7101003 | AA5: 14133425 | AB5: 22523119 | AC5: 31123896 | AD5: 39848385 | AE5: 46604783 | AF5: 50134503 | AG5: 61629315 | AH5: 66891279 | AI5: 73429223 | AJ5: 76893658 | AK5: 86721719 | AL5: 86721720 | AM5: 6924024.7 | AN5: 13986055 | AO5: 21833612 | AP5: 27929546 | AQ5: 36881736 | AR5: 44059876 | AS5: 51189565 | AT5: 58666439 | AU5: 66918164
A6: Fees&Commision on Loan Portfolio | C6: 1103106.1 | D6: 2297122.6 | E6: 2612145.2 | F6: 2810097.7 | G6: 3387203.7 | H6: 5420137.4 | I6: 6466447.1 | J6: 7466629.3 | K6: 8325578.6 | M6: 28300 | N6: 61500 | O6: 105700 | P6: 146800 | Q6: 201000 | R6: 233300 | S6: 297200 | T6: 341300 | U6: 375400 | V6: 421400 | W6: 460900 | X6: 503700 | Z6: 42200 | AA6: 76200 | AB6: 124100 | AC6: 185200 | AD6: 238900 | AE6: 274400 | AF6: 325700 | AG6: 368200 | AH6: 411600 | AI6: 456400 | AJ6: 500800 | AK6: 540900 | AL6: =534800+6100 -> 540900 | AM6: 64800 | AN6: 110000 | AO6: 168100 | AP6: 233800 | AQ6: 330600 | AR6: 402520 | AS6: 460420 | AT6: 543350 | AU6: 598160
A7: Financial Income from Investments | B7: =SUM(B8:B11) -> 18920691 | C7: =SUM(C8:C11) -> 5025383.4 | D7: =SUM(D8:D11) -> 5622692.2 | E7: =SUM(E8:E11) -> 7863496.3 | F7: =SUM(F8:F11) -> 9732204.7 | G7: =SUM(G8:G11) -> 11050546 | H7: =SUM(H8:H11) -> 15778460 | I7: =SUM(I8:I11) -> 17741687 | ... AU7: =SUM(AU8:AU11) -> 10107951
A8: Government Securities | C8: 0 | D8: 0 | E8: 0 | F8: 0 | G8: 0 | H8: 0 | I8: 0 | J8: 0 | K8: 0 | M8: 0 | N8: 0 | O8: 0 | P8: 0 | Q8: 0 | R8: 0 | S8: 0 | T8: 0 | U8: 0 | V8: 0 | W8: 0 | X8: 0 | Z8: 0 | AA8: 0 | AB8: 0 | AC8: 0 | AD8: 0 | AE8: 0 | AF8: 0 | AG8: 0 | AH8: 0 | AI8: 0 | AJ8: 0 | AK8: 0 | AM8: 0 | AN8: 0 | AO8: 0 | AP8: 0 | AQ8: 0 | AR8: 0 | AS8: 0 | AT8: 0 | AU8: 0
A9: Deposits with Banks & other Financial Institutions | B9: 516362 | C9: 0 | D9: 0 | E9: 0 | F9: 0 | G9: 0 | H9: 0 | I9: 0 | J9: 0 | K9: 0 | L9: 1050595 | M9: 0 | N9: 0 | O9: 0 | P9: 0 | Q9: 0 | R9: 0 | S9: 0 | T9: 0 | U9: 0 | V9: 0 | W9: 0 | X9: 0 | Y9: 437375 | Z9: 0 | AA9: 0 | AB9: 0 | AC9: 0 | AD9: 0 | AE9: 0 | AF9: 0 | AG9: 0 | AH9: 0 | AI9: 0 | AJ9: 0 | AK9: 0 | AL9: 1371524 | AM9: 0 | AN9: 0 | AO9: 0 | AP9: 0 | AQ9: 0 | AR9: 0 | AS9: 0 | AT9: 0 | AU9: 0
A10: Other Investments | C10: 3252227 | D10: 433399.55 | E10: 1921172.1 | F10: 1921172.1 | G10: 1921172.1 | H10: 2220703.7 | I10: 2329211.7 | J10: 2534831.6 | K10: 3101631.6 | M10: 4000 | N10: 68000 | O10: 1854300 | P10: 2045032 | Q10: 2049032 | R10: 2137032 | S10: 2619429.1 | T10: 2635685.6 | U10: 2658035.6 | V10: 2719855.6 | W10: 2748901.6 | X10: 3015901.6 | Y10: 1966684.4 | Z10: 476188 | AA10: 484243.39 | AB10: 2816325.4 | AC10: 2883125.4 | AD10: 2955625.4 | AE10: 3157351.2 | AF10: 3254299.2 | AG10: 3262299.2 | AH10: 3330299.2 | AI10: 3212618 | AJ10: 4592142 | AK10: 4609642 | AL10: 2770405 | AM10: 4000 | AN10: 249576.45 | AO10: 1086047.4 | AP10: 1094047.4 | AQ10: 3401205.5 | AR10: 3413461.9 | AS10: 3693657.3 | AT10: 3754157.3 | AU10: 3814657.3
A11: Other Operating Income | B11: 18404329 | C11: 1773156.4 | D11: 5189292.7 | E11: 5942324.3 | F11: 7811032.6 | G11: 9129374 | H11: 13557756 | I11: 15412475 | J11: 17387354 | K11: 19567528 | L11: 19530533 | M11: 491632 | N11: 1017832.5 | O11: 1955343.1 | P11: 2617278.6 | Q11: 3204313.1 | R11: 3812354.1 | S11: 4515596.1 | T11: 5211628.1 | U11: 5821971.1 | V11: 6500385.1 | W11: 7132707.6 | X11: 22199463 | Y11: =24637069-Y10 -> 22670385 | Z11: 600397.5 | AA11: 1115901.5 | AB11: 2176355 | AC11: 2906483 | AD11: 3548642.5 | AE11: 4132019.5 | AF11: 4672350.5 | AG11: 5275788 | AH11: 5913288.5 | AI11: 6503356 | AJ11: 7071293 | AK11: 20354111 | AL11: =24967374-AL10-AL31-AL6 -> 20354111 | AM11: 592917 | AN11: 1185396 | AO11: 2277281 | AP11: 2859771.5 | AQ11: 3620316.5 | AR11: 4315317 | AS11: 4928429.5 | AT11: 5579654 | AU11: 6293293.6
A12: Financial Expenses | B12: =SUM(B13:B18) -> 35880704 | C12: =SUM(C13:C18) -> 302470.65 | D12: =SUM(D13:D18) -> 741170 | E12: =SUM(E13:E18) -> 1001490.8 | F12: =SUM(F13:F18) -> 1073810.1 | G12: =SUM(G13:G18) -> 1353220.2 | H12: =SUM(H13:H18) -> 1761001.9 | I12: =SUM(I13:I18) -> 1763521.9 | ... AU12: =SUM(AU13:AU18) -> 5583916.2
A13: Interest Expense on Deposits | B13: 31410482 | C13: 302470.65 | D13: 741170 | E13: 1001490.8 | F13: 1073810.1 | G13: 1353220.2 | H13: 1761001.9 | I13: 1763521.9 | J13: 1893062.8 | K13: 13600868 | L13: 35570818 | M13: 442387.58 | N13: 587817.37 | O13: 1232932.1 | P13: 1507700.3 | Q13: 1647941 | R13: 1917672.1 | S13: 2432275.1 | T13: 2498725.1 | U13: 2812688.2 | V13: 3270822.4 | W13: 3427981.1 | X13: 3927469.2 | Y13: =3927469+39271449.75 -> 43198919 | Z13: 593702.9 | AA13: 681355.19 | AB13: 1270476.1 | AC13: 1700851.1 | AD13: 1827557.5 | AE13: 2267319.1 | AF13: 2925786.8 | AG13: 3082880.5 | AH13: 3623548.2 | AI13: 4152968.5 | AJ13: 4225431 | AK13: 5005476.4 | AL13: =38321465+5005476 -> 43326941 | AM13: 690599.48 | AN13: 892365.88 | AO13: 1448869.6 | AP13: 2115299.1 | AQ13: 2683594.8 | AR13: 3273132.2 | AS13: 3740885.9 | AT13: 4106241.5 | AU13: 4546380.4
A14: Cost of External Borrowings | B14: 4470222 | C14: 0 | D14: 0 | E14: 0 | F14: 0 | G14: 0 | H14: 0 | I14: 0 | J14: 0 | K14: 0 | L14: 6009362 | M14: 0 | N14: 0 | O14: 0 | P14: 0 | Q14: 0 | R14: 0 | S14: 0 | T14: 0 | U14: 0 | V14: 0 | W14: 0 | X14: 0 | Z14: 0 | AA14: 0 | AB14: 0 | AC14: 0 | AD14: 0 | AE14: 0 | AF14: 0 | AG14: 0 | AH14: 0 | AI14: 0 | AJ14: 0 | AK14: 0 | AL14: 0 | AM14: 0 | AN14: 0 | AO14: 0 | AP14: 0 | AQ14: 0 | AR14: 0 | AS14: 0 | AT14: 0 | AU14: 0
A15: Dividend Expenses | C15: 0 | D15: 0 | E15: 0 | F15: 0 | G15: 0 | H15: 0 | I15: 0 | J15: 0 | K15: 0 | M15: 0 | N15: 0 | O15: 0 | P15: 0 | Q15: 0 | R15: 0 | S15: 0 | T15: 0 | U15: 0 | V15: 0 | W15: 0 | X15: 0 | Z15: 0 | AA15: 0 | AB15: 0 | AC15: 0 | AD15: 0 | AE15: 0 | AF15: 0 | AG15: 0 | AH15: 0 | AI15: 0 | AJ15: 0 | AK15: 41700000 | AM15: 0 | AN15: 0 | AO15: 0 | AP15: 0 | AQ15: 0 | AR15: 0 | AS15: 0 | AT15: 0 | AU15: 0
A16: Other Financial Expense | C16: 0 | D16: 0 | E16: 0 | F16: 0 | G16: 0 | H16: 0 | I16: 0 | J16: 0 | K16: 0 | M16: 131880 | N16: 355097 | O16: 483052 | P16: 966071 | Q16: 2870704 | R16: 1210280 | S16: 1329291 | T16: 1395628 | U16: 1463518 | V16: 1520148 | W16: 1552760 | X16: 8271534 | Z16: 91980 | AA16: 261800 | AB16: 565737 | AC16: 648754 | AD16: 755094 | AE16: 810190 | AF16: 854372 | AG16: 917266 | AH16: 986906 | AI16: 1078317 | AJ16: 1230924 | AK16: 8306584 | AM16: 86958 | AN16: 130395 | AO16: 236870.5 | AP16: 301710.5 | AQ16: 383898.5 | AR16: 555561.35 | AS16: 591927.45 | AT16: 694663.95 | AU16: 751474.1
A17: Fees & Commision Expense | C17: 0 | D17: 0 | E17: 0 | F17: 0 | G17: 0 | H17: 0 | I17: 0 | J17: 0 | K17: 0 | M17: 26466.2 | N17: 68453.19 | O17: 111250.19 | P17: 151273.24 | Q17: 186207.2 | R17: 210440.17 | S17: 262942.98 | T17: 303011.98 | U17: 335003.98 | V17: 365373.98 | W17: 386287.98 | X17: 415075.99 | Z17: 27099.56 | AA17: 53942.56 | AB17: 95512.56 | AC17: 132076.56 | AD17: 166215.06 | AE17: 201955.06 | AF17: 228689.06 | AG17: 256573.06 | AH17: 283353.06 | AI17: 304714.06 | AJ17: 330109.06 | AK17: 356935.06 | AM17: 26972 | AN17: 63671 | AO17: 97616 | AP17: 133744 | AQ17: 166081.35 | AR17: 192861.35 | AS17: 192861.35 | AT17: 192861.35 | AU17: 286061.75
A18: Other Expenses | C18: 0 | D18: 0 | E18: 0 | F18: 0 | G18: 0 | H18: 0 | I18: 0 | J18: 0 | K18: 0 | M18: 0 | N18: 0 | O18: 0 | P18: 0 | Q18: 0 | R18: 0 | S18: 0 | T18: 0 | U18: 0 | V18: 0 | W18: 0 | X18: 0 | Z18: 0 | AA18: 0 | AB18: 0 | AC18: 0 | AD18: 0 | AE18: 0 | AF18: 0 | AG18: 0 | AH18: 0 | AI18: 0 | AJ18: 0 | AK18: 0 | AM18: 0 | AN18: 0 | AO18: 0 | AP18: 0 | AQ18: 0 | AR18: 0 | AS18: 0 | AT18: 0 | AU18: 0
A19: Net Financial Income | B19: =B3-B12 -> 60606977 | C19: =C3-C12 -> 12558632 | D19: =D3-D12 -> 26194051 | E19: =E3-E12 -> 33914034 | F19: =F3-F12 -> 41610450 | G19: =G3-G12 -> 49064147 | H19: =H3-H12 -> 73374050 | I19: =I3-I12 -> 83005489 | ... AU19: =AU3-AU12 -> 72040359
A20: Allowance for Loan Loss | B20: =B21-B22 -> 8663385.1 | C20: =C21-C22 -> 0 | D20: =D21-D22 -> 0 | E20: =E21-E22 -> 0 | F20: =F21-F22 -> 0 | G20: =G21-G22 -> 0 | H20: =H21-H22 -> 0 | I20: =I21-I22 -> 0 | ... AU20: =AU21-AU22 -> 0
A21: Provision for Loan Losses | B21: 8663385.1 | C21: 0 | D21: 0 | E21: 0 | F21: 0 | G21: 0 | H21: 0 | I21: 0 | J21: 0 | K21: 0 | L21: 7452358.1 | M21: 0 | N21: 0 | O21: 0 | P21: 0 | Q21: 0 | R21: 0 | S21: 0 | T21: 0 | U21: 0 | V21: 0 | W21: 0 | X21: 0 | Y21: 0 | Z21: 0 | AA21: 0 | AB21: 0 | AC21: 0 | AD21: 0 | AE21: 0 | AF21: 0 | AG21: 0 | AH21: 0 | AI21: 0 | AJ21: 0 | AK21: 0 | AL21: 236620 | AM21: 0 | AN21: 0 | AO21: 0 | AP21: 0 | AQ21: 0 | AR21: 0 | AS21: 0 | AT21: 0 | AU21: 0
A22: Value of Loans Recovered | C22: 0 | D22: 0 | E22: 0 | F22: 0 | G22: 0 | H22: 0 | I22: 0 | J22: 0 | K22: 0 | M22: 0 | N22: 0 | O22: 0 | P22: 0 | Q22: 0 | R22: 0 | S22: 0 | T22: 0 | U22: 0 | V22: 0 | W22: 0 | X22: 0 | Z22: 0 | AA22: 0 | AB22: 0 | AC22: 0 | AD22: 0 | AE22: 0 | AF22: 0 | AG22: 0 | AH22: 0 | AI22: 0 | AJ22: 0 | AK22: 0 | AM22: 0 | AN22: 0 | AO22: 0 | AP22: 0 | AQ22: 0 | AR22: 0 | AS22: 0 | AT22: 0 | AU22: 0
A23: Operating Expeses | B23: =SUM(B24:B28) -> 35085771 | C23: =SUM(C24:C28) -> 4984381.4 | D23: =SUM(D24:D28) -> 11914000 | E23: =SUM(E24:E28) -> 16787404 | F23: =SUM(F24:F28) -> 19791445 | G23: =SUM(G24:G28) -> 23674921 | H23: =SUM(H24:H28) -> 35116361 | I23: =SUM(I24:I28) -> 38375896 | ... AU23: =SUM(AU24:AU28) -> 33651434
A24: Personel Expenses | B24: 16521475 | C24: 1737585.4 | D24: 3466463 | E24: 6954219.8 | F24: 8727232 | G24: 10475187 | H24: 15979365 | I24: 17699475 | J24: 19422668 | K24: 21504192 | L24: 15472331 | M24: 1419138 | N24: 2786172 | O24: 4409173 | P24: 5741483 | Q24: 7076239 | R24: 8469272 | S24: 11691139 | T24: 13135137 | U24: 14524182 | V24: 16086302 | W24: 17655804 | X24: 21811979 | Y24: 21818016 | Z24: 1554504 | AA24: 3123651 | AB24: 4960538 | AC24: 6496777 | AD24: 8072862 | AE24: 9663433 | AF24: 11303892 | AG24: 12808755 | AH24: 14577505 | AI24: 16206438 | AJ24: 17551359 | AK24: 21136116 | AL24: 21138710 | AM24: 1553728 | AN24: 3142478 | AO24: 5044761 | AP24: 6510558 | AQ24: 8307629 | AR24: 9796180 | AS24: 11363378 | AT24: 12911179 | AU24: 14485459
A25: Governance Expenses | B25: 2991144 | C25: 330605 | D25: 1101032 | E25: 1175042 | F25: 1252637 | G25: 1477567 | H25: 1960502 | I25: 2075932 | J25: 2203217 | K25: 2498907 | L25: 2827400 | M25: 181780 | N25: 666540 | O25: 1644680 | P25: 2090790 | Q25: 2339840 | R25: 2721060 | S25: 3090290 | T25: 3524490 | U25: 3732580 | V25: 4237410 | W25: 4760370 | X25: 5147480 | Y25: 5147480 | Z25: 525510 | AA25: 1799300 | AB25: 3143690 | AC25: 3643820 | AD25: 4155980 | AE25: 4821640 | AF25: 5580700 | AG25: 6079360 | AH25: 6394820 | AI25: 6607090 | AJ25: 6715840 | AK25: 7323260 | AL25: 6623260 | AM25: 562050 | AN25: 1247750 | AO25: 2637500 | AP25: 3022180 | AQ25: 3249470 | AR25: 3904460 | AS25: 4265770 | AT25: 5237820 | AU25: 5533830
A26: Marketing Expenses | C26: 129565 | D26: 642394 | E26: 843169 | F26: 1007639 | G26: 1027519 | H26: 1518323 | I26: 1670863 | J26: 1854278 | K26: 2062618 | M26: 61950 | N26: 112500 | O26: 193160 | P26: 286580 | Q26: 410400 | R26: 493600 | S26: 524700 | T26: 615900 | U26: 668670 | V26: 707170 | W26: 793350 | X26: 842800 | Y26: 662710 | Z26: 36000 | AA26: 92020 | AB26: 114020 | AC26: 131640 | AD26: 280004 | AE26: 344724 | AF26: 399444 | AG26: 522604 | AH26: 682404 | AI26: 735604 | AJ26: 764004 | AK26: 823004 | AL26: 601564 | AM26: 53100 | AN26: 104200 | AO26: 168900 | AP26: 214820 | AQ26: 587560 | AR26: 730880 | AS26: 756680 | AT26: 773680 | AU26: 819980
A27: Depreciation and Amortization | B27: 1519419.1 | C27: 138128 | D27: 414384 | E27: 528924 | F27: 661155 | G27: 793386 | H27: 1190079 | I27: 1322310 | J27: 1454541 | K27: 1586772 | L27: 1707778.4 | M27: 0 | N27: 0 | O27: 0 | P27: 0 | Q27: 0 | R27: 0 | S27: 0 | T27: 0 | U27: 0 | V27: 0 | W27: 0 | X27: 0 | Y27: =2614259.25+154236.4 -> 2768495.6 | Z27: 0 | AA27: 0 | AB27: 0 | AC27: 0 | AD27: 0 | AE27: 0 | AF27: 0 | AG27: 0 | AH27: 0 | AI27: 0 | AJ27: 0 | AK27: 0 | AL27: =2424033.05+154236.5 -> 2578269.5 | AM27: 0 | AN27: 0 | AO27: 0 | AP27: 0 | AQ27: 0 | AR27: 0 | AS27: 0 | AT27: 0 | AU27: 0
A28: Administrative Expenses | B28: 14053733 | C28: 2648498 | D28: 6289727 | E28: 7286049 | F28: 8142781.6 | G28: 9901262.6 | H28: 14468092 | I28: 15607316 | J28: 17023013 | K28: 20159602 | L28: 15261465 | M28: 583667 | N28: 2765111.9 | O28: 4736903.1 | P28: 4853713.6 | Q28: 5593663 | R28: 6417073.5 | S28: 6831794.5 | T28: 7844327.4 | U28: 8678803.9 | V28: 11000740 | W28: 12375351 | X28: 14266757 | Y28: =25104844.7-Y26 -> 24442135 | Z28: 1165336.5 | AA28: 4506090.9 | AB28: 5302623 | AC28: 6430173.8 | AD28: 8816714.8 | AE28: 10774098 | AF28: 11463912 | AG28: 14665850 | AH28: 16020899 | AI28: 17351035 | AJ28: 18845284 | AK28: 13423994 | AL28: =24191301.9-AL26 -> 23589738 | AM28: 1324050 | AN28: 5212606 | AO28: 6716487 | AP28: 7111095 | AQ28: 8888584 | AR28: 10233056 | AS28: 11841198 | AT28: 12221764 | AU28: 12812165
A29: Net Operating Income | B29: =B19-B20-B23 -> 16857820 | C29: =C19-C20-C23 -> 7574250.8 | D29: =D19-D20-D23 -> 14280051 | E29: =E19-E20-E23 -> 17126631 | F29: =F19-F20-F23 -> 21819006 | G29: =G19-G20-G23 -> 25389226 | H29: =H19-H20-H23 -> 38257689 | I29: =I19-I20-I23 -> 44629593 | ... AU29: =AU19-AU20-AU23 -> 38388925
A30: Net Non operating Income/Expense | B30: =B31-B32 -> 0 | C30: =C31-C32 -> 0 | D30: =D31-D32 -> 0 | E30: =E31-E32 -> 0 | F30: =F31-F32 -> 0 | G30: =G31-G32 -> 0 | H30: =H31-H32 -> 0 | I30: =I31-I32 -> 0 | ... AR30: =AR31-AR32 -> 0
A31: Non Operating Income | C31: 0 | D31: 0 | E31: 0 | F31: 0 | G31: 0 | H31: 0 | I31: 0 | J31: 0 | K31: 0 | M31: 0 | N31: 0 | O31: 0 | P31: 0 | Q31: 0 | R31: 0 | S31: 0 | T31: 0 | U31: 0 | V31: 0 | W31: 0 | X31: 0 | Z31: 0 | AA31: 0 | AB31: 0 | AC31: 0 | AD31: 0 | AE31: 0 | AF31: 0 | AG31: 0 | AH31: 0 | AL31: 1301958 | AM31: 0 | AN31: 0 | AO31: 0 | AP31: 0 | AQ31: 0 | AR31: 0 | AS31: 0 | AT31: 0 | AU31: 0
A32: Non Operating Expense | C32: 0 | D32: 0 | E32: 0 | F32: 0 | G32: 0 | H32: 0 | I32: 0 | J32: 0 | K32: 0 | M32: 0 | N32: 0 | O32: 0 | P32: 0 | Q32: 0 | R32: 0 | S32: 0 | T32: 0 | U32: 0 | V32: 0 | W32: 0 | X32: 0 | Z32: 0 | AA32: 0 | AB32: 0 | AC32: 0 | AD32: 0 | AE32: 0 | AF32: 0 | AG32: 0 | AH32: 0 | AM32: 0 | AN32: 0 | AO32: 0 | AP32: 0 | AQ32: 0 | AR32: 0 | AS32: 0 | AT32: 0 | AU32: 0
A33: Net Income(Before Tax & Donations) | B33: =B29+B30 -> 16857820 | C33: =C29+C30 -> 7574250.8 | D33: =D29+D30 -> 14280051 | E33: =E29+E30 -> 17126631 | F33: =F29+F30 -> 21819006 | G33: =G29+G30 -> 25389226 | H33: =H29+H30 -> 38257689 | I33: =I29+I30 -> 44629593 | ... AU33: =AU29+AU30 -> 38388925
A34: Taxes | C34: 0 | D34: 0 | E34: 271967 | F34: 150000 | G34: 300000 | H34: 450000 | I34: 450000 | J34: 450000 | K34: 600000 | P34: 0 | Q34: 0 | R34: 0 | S34: 0 | T34: 0 | U34: 140500 | V34: 153500 | W34: 171500 | X34: 186500 | Y34: 2500000 | AF34: 0 | AG34: 0 | AH34: 0 | AL34: 706224 | AM34: 0 | AN34: 0 | AO34: 0 | AP34: 0 | AQ34: 0 | AR34: 0 | AS34: 0 | AT34: 0 | AU34: 0
A35: Net Income(After Tax Before Donations) | B35: =B33-B34 -> 16857820 | C35: =C33-C34 -> 7574250.8 | D35: =D33-D34 -> 14280051 | E35: =E33-E34 -> 16854664 | F35: =F33-F34 -> 21669006 | G35: =G33-G34 -> 25089226 | H35: =H33-H34 -> 37807689 | I35: =I33-I34 -> 44179593 | ... AU35: =AU33-AU34 -> 38388925
A36: Donations | C36: 0 | D36: 0 | E36: 0 | F36: 0 | G36: 0 | H36: 0 | I36: 0 | J36: 0 | K36: 0 | M36: 13000 | N36: 22500 | O36: 33500 | P36: 37500 | Q36: 37500 | R36: 63500 | S36: 90500 | T36: 120500 | Z36: 32000 | AA36: 54000 | AB36: 54000 | AC36: 62000 | AD36: 89500 | AE36: 122500 | AF36: 152620 | AG36: 161620 | AH36: 180620 | AI36: 202620 | AJ36: 212620 | AK36: 215620 | AM36: 14000 | AN36: 26000 | AO36: 54000 | AP36: 83000 | AQ36: 127000 | AR36: 173000 | AS36: 191000 | AT36: 220120 | AU36: 247120
A37: Net Income/(After Tax & Donations) | B37: =B35-B36 -> 16857820 | C37: =C35-C36 -> 7574250.8 | D37: =D35-D36 -> 14280051 | E37: =E35-E36 -> 16854664 | F37: =F35-F36 -> 21669006 | G37: =G35-G36 -> 25089226 | H37: =H35-H36 -> 37807689 | I37: =I35-I36 -> 44179593 | ... AU37: =AU35-AU36 -> 38141805
A39: Total Expenses | B39: =B12+B23 -> 70966475 | C39: =C12+C23 -> 5286852.1 | D39: =D12+D23 -> 12655170 | E39: =E12+E23 -> 17788895 | F39: =F12+F23 -> 20865255 | G39: =G12+G23 -> 25028141 | H39: =H12+H23 -> 36877363 | I39: =I12+I23 -> 40139418 | ... AP39: =AP12+AP23 -> 19409407

Sheet Financials
A1: PTIMETIME
A2: Year | B2: 2012 Audited | C2: 2019 Audited | D2: 43831 | E2: 43891 | F2: 43922 | G2: 43952 | H2: 43983 | I2: 44075 | J2: 44105 | K2: 44136 | L2: 44166 | M2: Audited 2020 | N2: 44197 | O2: 44228 | P2: 44256 | Q2: 44287 | R2: 44317 | S2: 44348 | T2: 44378 | U2: 44409 | V2: 44440 | W2: 44470 | X2: 44501 | Y2: 44531 | Z2: Audited 2021 | AA2: 44562 | AB2: 44593 | AC2: 44621 | AD2: 44652 | AE2: 44682 | AF2: 44713 | AG2: 44743 | AH2: 44774 | AI2: 44805 | AJ2: 44835 | AK2: 44866 | AL2: 44896 | AM2: Audit 2022 | AN2: 44927 | AO2: 44958 | AP2: 44986 | AQ2: 45017 | AR2: 45047 | AS2: 45078 | AT2: 45108 | AU2: 45139 | AV2: 45170 | AW2: 45200 | AX2: 45231 | AY2: 45261
A3: Membership | M3: 3462 | Z3: 4013 | AM3: 4324
A4: Total Assets | B4: ='Evolutive SFP'!B26 -> 616749916 | C4: ='Evolutive SFP'!B26 -> 616749916 | D4: ='Evolutive SFP'!C26 -> 7.6180704e+08 | E4: ='Evolutive SFP'!D26 -> 7.6615477e+08 | F4: ='Evolutive SFP'!E26 -> 7.5549346e+08 | G4: ='Evolutive SFP'!F26 -> 7.5578154e+08 | H4: ='Evolutive SFP'!G26 -> 7.5259093e+08 | I4: ='Evolutive SFP'!H26 -> 7.5366684e+08 | J4: ='Evolutive SFP'!I26 -> 7.5672257e+08 | ... AY4: ='Evolutive SFP'!AX26 -> 0
A5: Total Deposits | B5: ='Evolutive SFP'!B30 -> 574156047 | C5: ='Evolutive SFP'!B30 -> 574156047 | D5: ='Evolutive SFP'!C30 -> 5.6774807e+08 | E5: ='Evolutive SFP'!D30 -> 582138061 | F5: ='Evolutive SFP'!E30 -> 5.9450076e+08 | G5: ='Evolutive SFP'!F30 -> 5.9384504e+08 | H5: ='Evolutive SFP'!G30 -> 5.9183523e+08 | I5: ='Evolutive SFP'!H30 -> 6.0997234e+08 | J5: ='Evolutive SFP'!I30 -> 6.1168659e+08 | ... AY5: ='Evolutive SFP'!AX30 -> 0
A6: Deposits-Members(BOSA) | B6: ='Evolutive SFP'!B29 -> 418806431 | C6: ='Evolutive SFP'!B29 -> 418806431 | D6: ='Evolutive SFP'!C29 -> 4.2198244e+08 | E6: ='Evolutive SFP'!D29 -> 427325266 | F6: ='Evolutive SFP'!E29 -> 4.2916071e+08 | G6: ='Evolutive SFP'!F29 -> 4.3220893e+08 | H6: ='Evolutive SFP'!G29 -> 4.3426279e+08 | I6: ='Evolutive SFP'!H29 -> 4.4005123e+08 | J6: ='Evolutive SFP'!I29 -> 4.4155717e+08 | ... AY6: ='Evolutive SFP'!AX29 -> 0
A7: Deposits-Customers(FOSA) | B7: =('Evolutive SFP'!B27+'Evolutive SFP'!B28) -> 155349616 | C7: ='Evolutive SFP'!B27 -> 127986727 | D7: ='Evolutive SFP'!C27 -> 97743215 | E7: ='Evolutive SFP'!D27 -> 103735571 | F7: ='Evolutive SFP'!E27 -> 1.130541e+08 | G7: ='Evolutive SFP'!F27 -> 1.0809158e+08 | H7: ='Evolutive SFP'!G27 -> 1.0286644e+08 | I7: ='Evolutive SFP'!H27 -> 1.1367251e+08 | J7: ='Evolutive SFP'!I27 -> 1.1411871e+08 | ... AY7: ='Evolutive SFP'!AX27 -> 0
A8: External Borrowing | B8: ='Evolutive SFP'!B36 -> 30000000 | C8: ='Evolutive SFP'!B36 -> 30000000 | D8: ='Evolutive SFP'!C36 -> 26040073 | E8: ='Evolutive SFP'!D36 -> 20587500 | F8: ='Evolutive SFP'!E36 -> 19480080 | G8: ='Evolutive SFP'!F36 -> 16342580 | H8: ='Evolutive SFP'!G36 -> 13205080 | I8: ='Evolutive SFP'!H36 -> 3792579.8 | J8: ='Evolutive SFP'!I36 -> 2197660.8 | ... AY8: ='Evolutive SFP'!AX36 -> 0
A10: Share capital and Reserves
A11: Core Capital | B11: =B14-B22-B25 -> 1.0901772e+08 | C11: =C14-C22 -> 1.1823935e+08 | D11: =D14-D22 -> 1.0884299e+08 | E11: =E14-E22 -> 1.0890701e+08 | F11: =F14-F22 -> 1.1940696e+08 | G11: =G14-G22 -> 1.1938169e+08 | H11: =H14-H22 -> 1.1924695e+08 | I11: =I14-I22 -> 84538672 | J11: =J14-J22 -> 84539172 | ... Y11: =Y14-Y22 -> 1.8225903e+08 | Z11: =Z14-Z27 -> 1.3123846e+08 | AA11: =AA14-AA27 -> 1.2954533e+08 | AB11: =AB14-AB27 -> 1.2889079e+08 | AC11: =AC14-AC27 -> 1.3411186e+08 | AD11: =AD14-AD27 -> 1.3983113e+08 | AE11: =AE14-AE27 -> 1.4440618e+08 | AF11: =AF14-AF27 -> 1.4714125e+08 | AG11: =AG14-AG27 -> 1.474561e+08 | ... AY11: =AY14-AY27 -> 25
A12: Institutional Capital | B12: =B11-B15 -> 60253029 | C12: =C11-C15 -> 69474660 | D12: =D11-D15 -> 60065805 | E12: =E11-E15 -> 60135724 | F12: =F11-F15 -> 70635675 | G12: =G11-G15 -> 70610406 | H12: =H11-H15 -> 70475662 | I12: =I11-I15 -> 35107171 | ... AY12: =AY11-AY15 -> 25
A14: Total Capital | B14: =B15+B16+B17+B18+B19+B20+B21 -> 1.1823935e+08 | C14: =C15+C16+C17+C18+C19+C20+C21 -> 1.1823935e+08 | D14: =D15+D16+D17+D18+D19+D20+D21 -> 1.0884299e+08 | E14: =E15+E16+E17+E18+E19+E20+E21 -> 1.0890701e+08 | F14: =F15+F16+F17+F18+F19+F20+F21 -> 1.1940696e+08 | G14: =G15+G16+G17+G18+G19+G20+G21 -> 1.1938169e+08 | H14: =H15+H16+H17+H18+H19+H20+H21 -> 1.1924695e+08 | I14: =I15+I16+I17+I18+I19+I20+I21 -> 84538672 | ... AY14: =AY15+AY16+AY17+AY18+AY19+AY20+AY21 -> 25
A15: Members Share Capital | B15: ='Evolutive SFP'!B38 -> 48764688 | C15: ='Evolutive SFP'!B38 -> 48764688 | D15: ='Evolutive SFP'!C38 -> 48777188 | E15: ='Evolutive SFP'!D38 -> 48771288 | F15: ='Evolutive SFP'!E38 -> 48771288 | G15: ='Evolutive SFP'!F38 -> 48771288 | H15: ='Evolutive SFP'!G38 -> 48771288 | I15: ='Evolutive SFP'!H38 -> 49431500 | J15: ='Evolutive SFP'!I38 -> 49432000 | ... AY15: ='Evolutive SFP'!AX38 -> 0
A16: Entrance Fees
A17: Retained Earnings | B17: ='Evolutive SFP'!B40 -> 30492146 | C17: ='Evolutive SFP'!B40 -> 30492146 | D17: ='Evolutive SFP'!C40 -> 30942146 | E17: ='Evolutive SFP'!D40 -> 30942146 | F17: ='Evolutive SFP'!E40 -> 38134753 | G17: ='Evolutive SFP'!F40 -> 38134753 | H17: ='Evolutive SFP'!G40 -> 38134753 | I17: ='Evolutive SFP'!H40 -> 21503348 | J17: ='Evolutive SFP'!I40 -> 21503348 | ... AY17: ='Evolutive SFP'!AX40 -> 0
A18: Appropriation Account | B18: ='Evolutive SFP'!B41 -> 7642607.3 | C18: ='Evolutive SFP'!B41 -> 7642607.3 | D18: ='Evolutive SFP'!C41 -> 855316.06 | E18: ='Evolutive SFP'!D41 -> 925234.67 | F18: ='Evolutive SFP'!E41 -> 1161015.3 | G18: ='Evolutive SFP'!F41 -> 1135746.2 | H18: ='Evolutive SFP'!G41 -> 1001002.5 | I18: ='Evolutive SFP'!H41 -> 0 | J18: ='Evolutive SFP'!I41 -> 0 | ... AY18: ='Evolutive SFP'!AX41 -> 0
A19: Statutory Reserves | B19: ='Evolutive SFP'!B42 -> 13603823 | C19: ='Evolutive SFP'!B42 -> 13603823 | D19: ='Evolutive SFP'!C42 -> 10532259 | E19: ='Evolutive SFP'!D42 -> 10532259 | F19: ='Evolutive SFP'!E42 -> 13603823 | G19: ='Evolutive SFP'!F42 -> 13603823 | H19: ='Evolutive SFP'!G42 -> 13603823 | I19: ='Evolutive SFP'!H42 -> 0 | J19: ='Evolutive SFP'!I42 -> 0 | ... AY19: ='Evolutive SFP'!AX42 -> 0
A20: Capital Reserves | B20: =('Evolutive SFP'!B43) -> 17736084 | C20: ='Evolutive SFP'!B43 -> 17736084 | D20: ='Evolutive SFP'!C43 -> 17736084 | E20: ='Evolutive SFP'!D43 -> 17736084 | F20: ='Evolutive SFP'!E43 -> 17736084 | G20: ='Evolutive SFP'!F43 -> 17736084 | H20: ='Evolutive SFP'!G43 -> 17736084 | I20: ='Evolutive SFP'!H43 -> 13603823 | J20: ='Evolutive SFP'!I43 -> 13603823 | ... AY20: ='Evolutive SFP'!AX43 -> 0
A21: Supplementary Capital & reserves | B21: =B22+B23 -> 0 | C21: =C22+C23 -> 0 | D21: =D22+D23 -> 0 | E21: =E22+E23 -> 0 | F21: =F22+F23 -> 0 | G21: =G22+G23 -> 0 | H21: =H22+H23 -> 0 | I21: =I22+I23 -> 0 | ... Y21: =Y22+Y23 -> 0 | Z21: 0 | AA21: 1 | AB21: 2 | AC21: 3 | AD21: 4 | AE21: 5 | AF21: 6 | AG21: 7 | AH21: 8 | AI21: 9 | AJ21: 10 | AK21: 11 | AL21: 12 | AM21: 13 | AN21: 14 | AO21: 15 | AP21: 16 | AQ21: 17 | AR21: 18 | AS21: 19 | AT21: 20 | AU21: 21 | AV21: 22 | AW21: 23 | AX21: 24 | AY21: 25
A22: Proposed Dividends | B22: ='Evolutive SFP'!B45 -> 0 | C22: ='Evolutive SFP'!B45 -> 0 | D22: ='Evolutive SFP'!C45 -> 0 | E22: ='Evolutive SFP'!D45 -> 0 | F22: ='Evolutive SFP'!E45 -> 0 | G22: ='Evolutive SFP'!F45 -> 0 | H22: ='Evolutive SFP'!G45 -> 0 | I22: ='Evolutive SFP'!H45 -> 0 | J22: ='Evolutive SFP'!I45 -> 0 | ... AY22: ='Evolutive SFP'!AX45 -> 0
A23: Risk Mgt Fund
A25: Investments | B25: =B26+B27+B28 -> 9221631 | C25: =C26+C27+C28 -> 9221631 | D25: =D26+D27+D28 -> 57779478 | E25: =E26+E27+E28 -> 58489478 | F25: =F26+F27+F28 -> 59744505 | G25: =G26+G27+G28 -> 60099478 | H25: =H26+H27+H28 -> 60454478 | I25: =I26+I27+I28 -> 61519478 | ... AY25: =AY26+AY27+AY28 -> 0
A26: Shares in Kusco,CIC,Coop Bank | B26: ='Evolutive SFP'!B12 -> 0 | C26: ='Evolutive SFP'!B11 -> 9221631 | D26: ='Evolutive SFP'!C11 -> 48557847 | E26: ='Evolutive SFP'!D11 -> 49267847 | F26: ='Evolutive SFP'!E11 -> 50522874 | G26: ='Evolutive SFP'!F11 -> 50877847 | H26: ='Evolutive SFP'!G11 -> 51232847 | I26: ='Evolutive SFP'!H11 -> 52297847 | J26: ='Evolutive SFP'!I11 -> 53552847 | ... AY26: ='Evolutive SFP'!AX11 -> 0
A27: Equity Investments (at cost) | B27: ='Evolutive SFP'!B10 -> 0 | C27: ='Evolutive SFP'!B12 -> 0 | D27: ='Evolutive SFP'!C12 -> 9221631 | E27: ='Evolutive SFP'!D12 -> 9221631 | F27: ='Evolutive SFP'!E12 -> 9221631 | G27: ='Evolutive SFP'!F12 -> 9221631 | H27: ='Evolutive SFP'!G12 -> 9221631 | I27: ='Evolutive SFP'!H12 -> 9221631.3 | J27: ='Evolutive SFP'!I12 -> 9221631.3 | ... AY27: ='Evolutive SFP'!AX12 -> 0
A28: Deposits in KUSCCO CFP | B28: ='Evolutive SFP'!B11 -> 9221631
A30: Net Loans & Advances | B30: ='Evolutive SFP'!B13 -> 360423402 | C30: ='Evolutive SFP'!B13 -> 360423402 | D30: ='Evolutive SFP'!C13 -> 3.5757131e+08 | E30: ='Evolutive SFP'!D13 -> 3.4700111e+08 | F30: ='Evolutive SFP'!E13 -> 340745739 | G30: ='Evolutive SFP'!F13 -> 331981703 | H30: ='Evolutive SFP'!G13 -> 324174103 | I30: ='Evolutive SFP'!H13 -> 3.2941099e+08 | J30: ='Evolutive SFP'!I13 -> 3.361167e+08 | ... AY30: ='Evolutive SFP'!AX13 -> 0
A31: Gross Loans & advances | B31: ='Evolutive SFP'!B14 -> 369086787 | C31: ='Evolutive SFP'!B14 -> 369086787 | D31: ='Evolutive SFP'!C14 -> 366682836 | E31: ='Evolutive SFP'!D14 -> 3.5626197e+08 | F31: ='Evolutive SFP'!E14 -> 350006594 | G31: ='Evolutive SFP'!F14 -> 341242558 | H31: ='Evolutive SFP'!G14 -> 333434958 | I31: ='Evolutive SFP'!H14 -> 3.496496e+08 | J31: ='Evolutive SFP'!I14 -> 3.5635532e+08 | ... AY31: ='Evolutive SFP'!AX14 -> 0
A32: Allowance for loan losses | B32: ='Evolutive SFP'!B15 -> 8663385 | C32: ='Evolutive SFP'!B15 -> 8663385 | D32: ='Evolutive SFP'!C15 -> 9111524.9 | E32: ='Evolutive SFP'!D15 -> 9260855 | F32: ='Evolutive SFP'!E15 -> 9260855 | G32: ='Evolutive SFP'!F15 -> 9260855 | H32: ='Evolutive SFP'!G15 -> 9260855 | I32: ='Evolutive SFP'!H15 -> 20238613 | J32: ='Evolutive SFP'!I15 -> 20238613 | ... AY32: ='Evolutive SFP'!AX15 -> 0
A34: Non-Earning Assets | B34: ='Evolutive SFP'!B20+'Evolutive SFP'!B7 -> 71554902 | C34: ='Evolutive SFP'!B7+'Evolutive SFP'!B16+'Evolutive SFP'!B20 -> 71554902 | D34: ='Evolutive SFP'!C7+'Evolutive SFP'!C16+'Evolutive SFP'!C20 -> 2.3070485e+08 | E34: ='Evolutive SFP'!D7+'Evolutive SFP'!D16+'Evolutive SFP'!D20 -> 2.3527879e+08 | F34: ='Evolutive SFP'!E7+'Evolutive SFP'!E16+'Evolutive SFP'!E20 -> 2.3709362e+08 | G34: ='Evolutive SFP'!F7+'Evolutive SFP'!F16+'Evolutive SFP'!F20 -> 2.3769879e+08 | H34: ='Evolutive SFP'!G7+'Evolutive SFP'!G16+'Evolutive SFP'!G20 -> 2.1925861e+08 | I34: ='Evolutive SFP'!H7+'Evolutive SFP'!H16+'Evolutive SFP'!H20 -> 2.335207e+08 | J34: ='Evolutive SFP'!I7+'Evolutive SFP'!I16+'Evolutive SFP'!I20 -> 2.344482e+08 | ... AY34: ='Evolutive SFP'!AX7+'Evolutive SFP'!AX16+'Evolutive SFP'!AX20 -> 0
A35: Property and Equipment | B35: ='Evolutive SFP'!B22 -> 23963774 | C35: ='Evolutive SFP'!B22 -> 23963774 | D35: ='Evolutive SFP'!C22 -> 22863775 | E35: ='Evolutive SFP'!D22 -> 22863775 | F35: ='Evolutive SFP'!E22 -> 22863775 | G35: ='Evolutive SFP'!F22 -> 22863775 | H35: ='Evolutive SFP'!G22 -> 22863775 | I35: ='Evolutive SFP'!H22 -> 23946128 | J35: ='Evolutive SFP'!I22 -> 24674503 | ... AY35: ='Evolutive SFP'!AX22 -> 0
A37: Turnover | B37: =B38+B39+B40+B41 -> #REF! | C37: =C38+C39+C40+C41 -> 96487681 | D37: =D38+D39+D40+D41 -> 12861103 | E37: =E38+E39+E40+E41 -> 26935221 | F37: =F38+F39+F40+F41 -> 34915525 | G37: =G38+G39+G40+G41 -> 42684260 | H37: =H38+H39+H40+H41 -> 50417367 | I37: =I38+I39+I40+I41 -> 75135052 | ... AY37: =AY38+AY39+AY40+AY41 -> 0
A38: Loan Interest | B38: ='Evolutitve SCI'!#REF! -> #REF! | C38: ='Evolutitve SCI'!B5 -> 77566990 | D38: ='Evolutitve SCI'!C5 -> 6732613.4 | E38: ='Evolutitve SCI'!D5 -> 19015406 | F38: ='Evolutitve SCI'!E5 -> 24439884 | G38: ='Evolutitve SCI'!F5 -> 30141958 | H38: ='Evolutitve SCI'!G5 -> 35979618 | I38: ='Evolutitve SCI'!H5 -> 53936455 | J38: ='Evolutitve SCI'!I5 -> 60560876 | ... AY38: ='Evolutitve SCI'!AX5 -> 0
A39: Income from investments | B39: ='Evolutitve SCI'!#REF! -> #REF! | C39: ='Evolutitve SCI'!B7 -> 18920691 | D39: ='Evolutitve SCI'!C7 -> 5025383.4 | E39: ='Evolutitve SCI'!D7 -> 5622692.2 | F39: ='Evolutitve SCI'!E7 -> 7863496.3 | G39: ='Evolutitve SCI'!F7 -> 9732204.7 | H39: ='Evolutitve SCI'!G7 -> 11050546 | I39: ='Evolutitve SCI'!H7 -> 15778460 | J39: ='Evolutitve SCI'!I7 -> 17741687 | ... AY39: ='Evolutitve SCI'!AX7 -> 0
A40: Fees & Commissions | B40: ='Evolutitve SCI'!#REF! -> #REF! | C40: ='Evolutitve SCI'!B6 -> 0 | D40: ='Evolutitve SCI'!C6 -> 1103106.1 | E40: ='Evolutitve SCI'!D6 -> 2297122.6 | F40: ='Evolutitve SCI'!E6 -> 2612145.2 | G40: ='Evolutitve SCI'!F6 -> 2810097.7 | H40: ='Evolutitve SCI'!G6 -> 3387203.7 | I40: ='Evolutitve SCI'!H6 -> 5420137.4 | J40: ='Evolutitve SCI'!I6 -> 6466447.1 | ... AY40: ='Evolutitve SCI'!AX6 -> 0
A41: Average yield on loans
A43: Financial and Operating costs | B43: =SUM(B44:B47) -> #REF! | C43: =SUM(C44:C47) -> 70966475 | D43: =SUM(D44:D47) -> 5286852.1 | E43: =SUM(E44:E47) -> 12655170 | F43: =SUM(F44:F47) -> 17788895 | G43: =SUM(G44:G47) -> 20865255 | H43: =SUM(H44:H47) -> 25028141 | I43: =SUM(I44:I47) -> 36877363 | ... AY43: =SUM(AY44:AY47) -> 0
A44: Interest expense on deposits | B44: ='Evolutitve SCI'!#REF!+'Evolutitve SCI'!#REF! -> #REF! | C44: ='Evolutitve SCI'!B13+'Evolutitve SCI'!B16 -> 31410482 | D44: ='Evolutitve SCI'!C13+'Evolutitve SCI'!C16 -> 302470.65 | E44: ='Evolutitve SCI'!D13+'Evolutitve SCI'!D16 -> 741170 | F44: ='Evolutitve SCI'!E13+'Evolutitve SCI'!E16 -> 1001490.8 | G44: ='Evolutitve SCI'!F13+'Evolutitve SCI'!F16 -> 1073810.1 | H44: ='Evolutitve SCI'!G13+'Evolutitve SCI'!G16 -> 1353220.2 | I44: ='Evolutitve SCI'!H13+'Evolutitve SCI'!H16 -> 1761001.9 | J44: ='Evolutitve SCI'!I13+'Evolutitve SCI'!I16 -> 1763521.9 | ... AY44: ='Evolutitve SCI'!AX13+'Evolutitve SCI'!AX16 -> 0
A45: Dividend expense on share capital | B45: ='Evolutitve SCI'!#REF! -> #REF! | C45: ='Evolutitve SCI'!B15 -> 0 | D45: ='Evolutitve SCI'!C15 -> 0 | E45: ='Evolutitve SCI'!D15 -> 0 | F45: ='Evolutitve SCI'!E15 -> 0 | G45: ='Evolutitve SCI'!F15 -> 0 | H45: ='Evolutitve SCI'!G15 -> 0 | I45: ='Evolutitve SCI'!H15 -> 0 | J45: ='Evolutitve SCI'!I15 -> 0 | ... AY45: ='Evolutitve SCI'!AX15 -> 0
A46: Interest expense on borrowed funds | B46: ='Evolutitve SCI'!#REF! -> #REF! | C46: ='Evolutitve SCI'!B14 -> 4470222 | D46: ='Evolutitve SCI'!C14 -> 0 | E46: ='Evolutitve SCI'!D14 -> 0 | F46: ='Evolutitve SCI'!E14 -> 0 | G46: ='Evolutitve SCI'!F14 -> 0 | H46: ='Evolutitve SCI'!G14 -> 0 | I46: ='Evolutitve SCI'!H14 -> 0 | J46: ='Evolutitve SCI'!I14 -> 0 | ... AY46: ='Evolutitve SCI'!AX14 -> 0
A47: Opperating expenses | B47: ='Evolutitve SCI'!#REF! -> #REF! | C47: ='Evolutitve SCI'!B23 -> 35085771 | D47: ='Evolutitve SCI'!C23 -> 4984381.4 | E47: ='Evolutitve SCI'!D23 -> 11914000 | F47: ='Evolutitve SCI'!E23 -> 16787404 | G47: ='Evolutitve SCI'!F23 -> 19791445 | H47: ='Evolutitve SCI'!G23 -> 23674921 | I47: ='Evolutitve SCI'!H23 -> 35116361 | J47: ='Evolutitve SCI'!I23 -> 38375896 | ... AY47: ='Evolutitve SCI'!AX23 -> 0

Sheet CAELS
A1: PRIMETIME
D2: 2019 Audited | E2: 43831 | F2: 43891 | G2: 43922 | H2: 43952 | I2: 43983 | J2: 44075 | K2: 44105 | L2: 44136 | M2: 44166 | N2: Audited 2020 | O2: 44197 | P2: 44228 | Q2: 44256 | R2: 44287 | S2: 44317 | T2: 44348 | U2: 44378 | V2: 44409 | W2: 44440 | X2: 44470 | Y2: 44501 | Z2: 44531 | AA2: Audited 2021 | AB2: 44562 | AC2: 44593 | AD2: 44621 | AE2: 44652 | AF2: 44682 | AG2: 44713 | AH2: 44743 | AI2: 44774 | AJ2: 44805 | AK2: 44835 | AL2: 44866 | AM2: 44896 | AN2: Audit 2022 | AO2: 44927 | AP2: 44958 | AQ2: 44986 | AR2: 45017 | AS2: 45047 | AT2: 45078 | AU2: 45108 | AV2: 45139 | AW2: 45170 | AX2: 45200 | AY2: 45231 | AZ2: 45261
A3: CAPITAL ADEQUACY | B3: Core Capital | C3: 10 M | D3: =(('Evolutive SFP'!B38+'Evolutive SFP'!B39+'Evolutive SFP'!B40+'Evolutive SFP'!B41+'Evolutive SFP'!B42+'Evolutive SFP'!B43)-'Evolutive SFP'!B12)/1000000 -> 118.23935 | E3: =(('Evolutive SFP'!C38+'Evolutive SFP'!C39+'Evolutive SFP'!C40+'Evolutive SFP'!C41+'Evolutive SFP'!C42+'Evolutive SFP'!C43)-'Evolutive SFP'!C12)/1000000 -> 99.621362 | F3: =(('Evolutive SFP'!D38+'Evolutive SFP'!D39+'Evolutive SFP'!D40+'Evolutive SFP'!D41+'Evolutive SFP'!D42+'Evolutive SFP'!D43)-'Evolutive SFP'!D12)/1000000 -> 99.685381 | G3: =(('Evolutive SFP'!E38+'Evolutive SFP'!E39+'Evolutive SFP'!E40+'Evolutive SFP'!E41+'Evolutive SFP'!E42+'Evolutive SFP'!E43)-'Evolutive SFP'!E12)/1000000 -> 110.18533 | H3: =(('Evolutive SFP'!F38+'Evolutive SFP'!F39+'Evolutive SFP'!F40+'Evolutive SFP'!F41+'Evolutive SFP'!F42+'Evolutive SFP'!F43)-'Evolutive SFP'!F12)/1000000 -> 110.16006 | I3: =(('Evolutive SFP'!G38+'Evolutive SFP'!G39+'Evolutive SFP'!G40+'Evolutive SFP'!G41+'Evolutive SFP'!G42+'Evolutive SFP'!G43)-'Evolutive SFP'!G12)/1000000 -> 110.02532 | J3: =(('Evolutive SFP'!H38+'Evolutive SFP'!H39+'Evolutive SFP'!H40+'Evolutive SFP'!H41+'Evolutive SFP'!H42+'Evolutive SFP'!H43)-'Evolutive SFP'!H12)/1000000 -> 75.31704 | K3: =(('Evolutive SFP'!I38+'Evolutive SFP'!I39+'Evolutive SFP'!I40+'Evolutive SFP'!I41+'Evolutive SFP'!I42+'Evolutive SFP'!I43)-'Evolutive SFP'!I12)/1000000 -> 75.31754 | ... AZ3: =(('Evolutive SFP'!AX38+'Evolutive SFP'!AX39+'Evolutive SFP'!AX40+'Evolutive SFP'!AX41+'Evolutive SFP'!AX42+'Evolutive SFP'!AX43)-'Evolutive SFP'!AX12)/1000000 -> 0
B4: CCA | C4: Min 10% | D4: =D3/(('Evolutive SFP'!B26)/1000000) -> 0.1917136 | E4: =E3/(('Evolutive SFP'!C26)/1000000) -> 0.13076981 | F4: =F3/(('Evolutive SFP'!D26)/1000000) -> 0.13011128 | G4: =G3/(('Evolutive SFP'!E26)/1000000) -> 0.14584551 | H4: =H3/(('Evolutive SFP'!F26)/1000000) -> 0.14575649 | I4: =I3/(('Evolutive SFP'!G26)/1000000) -> 0.14619538 | J4: =J3/(('Evolutive SFP'!H26)/1000000) -> 0.09993413 | K4: =K3/(('Evolutive SFP'!I26)/1000000) -> 0.099531246 | ... AZ4: =AZ3/(('Evolutive SFP'!AX26)/1000000) -> #DIV/0!
B5: CCD | C5: Min 8% | D5: =D3/('Evolutive SFP'!B30/1000000) -> 0.20593591 | E5: =E3/('Evolutive SFP'!C30/1000000) -> 0.17546755 | F5: =F3/('Evolutive SFP'!D30/1000000) -> 0.1712401 | G5: =G3/('Evolutive SFP'!E30/1000000) -> 0.18534095 | H5: =H3/('Evolutive SFP'!F30/1000000) -> 0.18550305 | I5: =I3/('Evolutive SFP'!G30/1000000) -> 0.18590532 | J5: =J3/('Evolutive SFP'!H30/1000000) -> 0.12347616 | K5: =K3/('Evolutive SFP'!I30/1000000) -> 0.12313093 | ... AZ5: =AZ3/('Evolutive SFP'!AX30/1000000) -> #DIV/0!
B6: ICA | C6: Min 8% | D6: =((D3*1000000)-'Evolutive SFP'!B38)/'Evolutive SFP'!B26 -> 0.1126464 | E6: =((E3*1000000)-'Evolutive SFP'!C38)/'Evolutive SFP'!C26 -> 0.066741539 | F6: =((F3*1000000)-'Evolutive SFP'!D38)/'Evolutive SFP'!D26 -> 0.066454057 | G6: =((G3*1000000)-'Evolutive SFP'!E38)/'Evolutive SFP'!E26 -> 0.081289974 | H6: =((H3*1000000)-'Evolutive SFP'!F38)/'Evolutive SFP'!F26 -> 0.081225555 | I6: =((I3*1000000)-'Evolutive SFP'!G38)/'Evolutive SFP'!G26 -> 0.081390871 | J6: =((J3*1000000)-'Evolutive SFP'!H38)/'Evolutive SFP'!H26 -> 0.034346131 | K6: =((K3*1000000)-'Evolutive SFP'!I38)/'Evolutive SFP'!I26 -> 0.034207438 | ... AZ6: =((AZ3*1000000)-'Evolutive SFP'!AX38)/'Evolutive SFP'!AX26 -> #DIV/0!
A7: ASSET QUALITY | B7: A/LNPL30
B8: NPL30
A9: EARNINGS | B9: ROA | D9: ='Evolutitve SCI'!B37/'Evolutive SFP'!B26 -> 0.027333316 | E9: ='Evolutitve SCI'!C37/'Evolutive SFP'!C26 -> 0.0099424795 | F9: ='Evolutitve SCI'!D37/'Evolutive SFP'!D26 -> 0.018638599 | G9: ='Evolutitve SCI'!E37/'Evolutive SFP'!E26 -> 0.022309477 | H9: ='Evolutitve SCI'!F37/'Evolutive SFP'!F26 -> 0.028670991 | I9: ='Evolutitve SCI'!G37/'Evolutive SFP'!G26 -> 0.033337136 | J9: ='Evolutitve SCI'!H37/'Evolutive SFP'!H26 -> 0.050164989 | K9: ='Evolutitve SCI'!I37/'Evolutive SFP'!I26 -> 0.058382814 | ... AZ9: ='Evolutitve SCI'!AX37/'Evolutive SFP'!AX26 -> #DIV/0!
B10: Cost Income ratio | D10: ='Evolutitve SCI'!B23/'Evolutitve SCI'!B19 -> 0.57890647 | E10: ='Evolutitve SCI'!C23/'Evolutitve SCI'!C19 -> 0.39688887 | F10: ='Evolutitve SCI'!D23/'Evolutitve SCI'!D19 -> 0.45483609 | G10: ='Evolutitve SCI'!E23/'Evolutitve SCI'!E19 -> 0.49499872 | H10: ='Evolutitve SCI'!F23/'Evolutitve SCI'!F19 -> 0.4756364 | I10: ='Evolutitve SCI'!G23/'Evolutitve SCI'!G19 -> 0.48252997 | J10: ='Evolutitve SCI'!H23/'Evolutitve SCI'!H19 -> 0.47859374 | K10: ='Evolutitve SCI'!I23/'Evolutitve SCI'!I19 -> 0.46232962 | ... AZ10: ='Evolutitve SCI'!AX23/'Evolutitve SCI'!AX19 -> #DIV/0!
B11: Operating Expense ratio | D11: =('Evolutitve SCI'!#REF!+'Evolutitve SCI'!#REF!)/(('Evolutive SFP'!B26+'Evolutive SFP'!#REF!)/2) -> #REF! | E11: =('Evolutitve SCI'!#REF!+'Evolutitve SCI'!#REF!)/(('Evolutive SFP'!C26+'Evolutive SFP'!#REF!)/2) -> #REF! | F11: =('Evolutitve SCI'!#REF!+'Evolutitve SCI'!#REF!)/(('Evolutive SFP'!D26+'Evolutive SFP'!#REF!)/2) -> #REF! | G11: =('Evolutitve SCI'!#REF!+'Evolutitve SCI'!#REF!)/(('Evolutive SFP'!E26+'Evolutive SFP'!#REF!)/2) -> #REF! | H11: =('Evolutitve SCI'!#REF!+'Evolutitve SCI'!#REF!)/(('Evolutive SFP'!F26+'Evolutive SFP'!#REF!)/2) -> #REF! | I11: =('Evolutitve SCI'!#REF!+'Evolutitve SCI'!#REF!)/(('Evolutive SFP'!G26+'Evolutive SFP'!#REF!)/2) -> #REF! | J11: =('Evolutitve SCI'!#REF!+'Evolutitve SCI'!#REF!)/(('Evolutive SFP'!H26+'Evolutive SFP'!#REF!)/2) -> #REF! | K11: =('Evolutitve SCI'!#REF!+'Evolutitve SCI'!#REF!)/(('Evolutive SFP'!I26+'Evolutive SFP'!#REF!)/2) -> #REF! | ... AZ11: =('Evolutitve SCI'!#REF!+'Evolutitve SCI'!#REF!)/(('Evolutive SFP'!AX26+'Evolutive SFP'!#REF!)/2) -> #REF!
A12: LIQUIDITY | B12: MIN LIQ ratio | C12: Min 15% | D12: =('Evolutive SFP'!B4)/('Evolutive SFP'!B27+'Evolutive SFP'!B28+'Evolutive SFP'!B31+'Evolutive SFP'!B32+'Evolutive SFP'!B33+'Evolutive SFP'!B34+'Evolutive SFP'!B35) -> 0.87865832 | E12: =('Evolutive SFP'!C4)/('Evolutive SFP'!C27+'Evolutive SFP'!C28+'Evolutive SFP'!C31+'Evolutive SFP'!C32+'Evolutive SFP'!C33+'Evolutive SFP'!C34+'Evolutive SFP'!C35) -> 0.56480205 | F12: =('Evolutive SFP'!D4)/('Evolutive SFP'!D27+'Evolutive SFP'!D28+'Evolutive SFP'!D31+'Evolutive SFP'!D32+'Evolutive SFP'!D33+'Evolutive SFP'!D34+'Evolutive SFP'!D35) -> 0.59897006 | G12: =('Evolutive SFP'!E4)/('Evolutive SFP'!E27+'Evolutive SFP'!E28+'Evolutive SFP'!E31+'Evolutive SFP'!E32+'Evolutive SFP'!E33+'Evolutive SFP'!E34+'Evolutive SFP'!E35) -> 0.6290334 | H12: =('Evolutive SFP'!F4)/('Evolutive SFP'!F27+'Evolutive SFP'!F28+'Evolutive SFP'!F31+'Evolutive SFP'!F32+'Evolutive SFP'!F33+'Evolutive SFP'!F34+'Evolutive SFP'!F35) -> 0.67076224 | I12: =('Evolutive SFP'!G4)/('Evolutive SFP'!G27+'Evolutive SFP'!G28+'Evolutive SFP'!G31+'Evolutive SFP'!G32+'Evolutive SFP'!G33+'Evolutive SFP'!G34+'Evolutive SFP'!G35) -> 0.80001534 | J12: =('Evolutive SFP'!H4)/('Evolutive SFP'!H27+'Evolutive SFP'!H28+'Evolutive SFP'!H31+'Evolutive SFP'!H32+'Evolutive SFP'!H33+'Evolutive SFP'!H34+'Evolutive SFP'!H35) -> 0.73700448 | K12: =('Evolutive SFP'!I4)/('Evolutive SFP'!I27+'Evolutive SFP'!I28+'Evolutive SFP'!I31+'Evolutive SFP'!I32+'Evolutive SFP'!I33+'Evolutive SFP'!I34+'Evolutive SFP'!I35) -> 0.7045726 | ... AZ12: =('Evolutive SFP'!AX4)/('Evolutive SFP'!AX27+'Evolutive SFP'!AX28+'Evolutive SFP'!AX31+'Evolutive SFP'!AX32+'Evolutive SFP'!AX33+'Evolutive SFP'!AX34+'Evolutive SFP'!AX35) -> #DIV/0!
B13: T/LIQ ratio | D13: =('Evolutive SFP'!B4+'Evolutive SFP'!B8)/('Evolutive SFP'!B30+'Evolutive SFP'!B31+'Evolutive SFP'!B32+'Evolutive SFP'!B33+'Evolutive SFP'!B34+'Evolutive SFP'!B35) -> 0.29869336 | E13: =('Evolutive SFP'!C4+'Evolutive SFP'!C8)/('Evolutive SFP'!C30+'Evolutive SFP'!C31+'Evolutive SFP'!C32+'Evolutive SFP'!C33+'Evolutive SFP'!C34+'Evolutive SFP'!C35) -> 0.27679732 | F13: =('Evolutive SFP'!D4+'Evolutive SFP'!D8)/('Evolutive SFP'!D30+'Evolutive SFP'!D31+'Evolutive SFP'!D32+'Evolutive SFP'!D33+'Evolutive SFP'!D34+'Evolutive SFP'!D35) -> 0.28881161 | G13: =('Evolutive SFP'!E4+'Evolutive SFP'!E8)/('Evolutive SFP'!E30+'Evolutive SFP'!E31+'Evolutive SFP'!E32+'Evolutive SFP'!E33+'Evolutive SFP'!E34+'Evolutive SFP'!E35) -> 0.2881159 | H13: =('Evolutive SFP'!F4+'Evolutive SFP'!F8)/('Evolutive SFP'!F30+'Evolutive SFP'!F31+'Evolutive SFP'!F32+'Evolutive SFP'!F33+'Evolutive SFP'!F34+'Evolutive SFP'!F35) -> 0.30013526 | I13: =('Evolutive SFP'!G4+'Evolutive SFP'!G8)/('Evolutive SFP'!G30+'Evolutive SFP'!G31+'Evolutive SFP'!G32+'Evolutive SFP'!G33+'Evolutive SFP'!G34+'Evolutive SFP'!G35) -> 0.3372764 | J13: =('Evolutive SFP'!H4+'Evolutive SFP'!H8)/('Evolutive SFP'!H30+'Evolutive SFP'!H31+'Evolutive SFP'!H32+'Evolutive SFP'!H33+'Evolutive SFP'!H34+'Evolutive SFP'!H35) -> 0.3099486 | K13: =('Evolutive SFP'!I4+'Evolutive SFP'!I8)/('Evolutive SFP'!I30+'Evolutive SFP'!I31+'Evolutive SFP'!I32+'Evolutive SFP'!I33+'Evolutive SFP'!I34+'Evolutive SFP'!I35) -> 0.30187324 | ... AZ13: =('Evolutive SFP'!AX4+'Evolutive SFP'!AX8)/('Evolutive SFP'!AX30+'Evolutive SFP'!AX31+'Evolutive SFP'!AX32+'Evolutive SFP'!AX33+'Evolutive SFP'!AX34+'Evolutive SFP'!AX35) -> #DIV/0!
B14: EB ratio | C14: Max 25% | D14: ='Evolutive SFP'!B36/'Evolutive SFP'!B26 -> 0.048642082 | E14: ='Evolutive SFP'!C36/'Evolutive SFP'!C26 -> 0.03418198 | F14: ='Evolutive SFP'!D36/'Evolutive SFP'!D26 -> 0.026871202 | G14: ='Evolutive SFP'!E36/'Evolutive SFP'!E26 -> 0.025784578 | H14: ='Evolutive SFP'!F36/'Evolutive SFP'!F26 -> 0.021623418 | I14: ='Evolutive SFP'!G36/'Evolutive SFP'!G26 -> 0.017546159 | J14: ='Evolutive SFP'!H36/'Evolutive SFP'!H26 -> 0.0050321702 | K14: ='Evolutive SFP'!I36/'Evolutive SFP'!I26 -> 0.002904183 | ... AZ14: ='Evolutive SFP'!AX36/'Evolutive SFP'!AX26 -> #DIV/0!
B15: LA to TA ratio | D15: ='Evolutive SFP'!B4/'Evolutive SFP'!B26 -> 0.28463722 | E15: ='Evolutive SFP'!C4/'Evolutive SFP'!C26 -> 0.1519432 | F15: ='Evolutive SFP'!D4/'Evolutive SFP'!D26 -> 0.16365544 | G15: ='Evolutive SFP'!E4/'Evolutive SFP'!E26 -> 0.15606965 | H15: ='Evolutive SFP'!F4/'Evolutive SFP'!F26 -> 0.16671692 | I15: ='Evolutive SFP'!G4/'Evolutive SFP'!G26 -> 0.19758906 | J15: ='Evolutive SFP'!H4/'Evolutive SFP'!H26 -> 0.17144933 | K15: ='Evolutive SFP'!I4/'Evolutive SFP'!I26 -> 0.16304944 | ... AZ15: ='Evolutive SFP'!AX4/'Evolutive SFP'!AX26 -> #DIV/0!
A16: STRUCTURE | B16: NEA ratio | C16: Max 10% | D16: =('Evolutive SFP'!B7+'Evolutive SFP'!B20)/'Evolutive SFP'!B26 -> 0.11601931 | E16: =('Evolutive SFP'!C7+'Evolutive SFP'!C20)/'Evolutive SFP'!C26 -> 0.30283896 | F16: =('Evolutive SFP'!D7+'Evolutive SFP'!D20)/'Evolutive SFP'!D26 -> 0.30709042 | G16: =('Evolutive SFP'!E7+'Evolutive SFP'!E20)/'Evolutive SFP'!E26 -> 0.31382617 | H16: =('Evolutive SFP'!F7+'Evolutive SFP'!F20)/'Evolutive SFP'!F26 -> 0.31450727 | I16: =('Evolutive SFP'!G7+'Evolutive SFP'!G20)/'Evolutive SFP'!G26 -> 0.29133837 | J16: =('Evolutive SFP'!H7+'Evolutive SFP'!H20)/'Evolutive SFP'!H26 -> 0.30984606 | K16: =('Evolutive SFP'!I7+'Evolutive SFP'!I20)/'Evolutive SFP'!I26 -> 0.30982054 | ... AZ16: =('Evolutive SFP'!AX7+'Evolutive SFP'!AX20)/'Evolutive SFP'!AX26 -> #DIV/0!
B17: LB ratio | C17: Max 5% | D17: ='Evolutive SFP'!B20/'Evolutive SFP'!B26 -> 0.066309663 | E17: ='Evolutive SFP'!C20/'Evolutive SFP'!C26 -> 0.23843967 | F17: ='Evolutive SFP'!D20/'Evolutive SFP'!D26 -> 0.23708658 | G17: ='Evolutive SFP'!E20/'Evolutive SFP'!E26 -> 0.24043231 | H17: ='Evolutive SFP'!F20/'Evolutive SFP'!F26 -> 0.24034066 | I17: ='Evolutive SFP'!G20/'Evolutive SFP'!G26 -> 0.24135959 | J17: ='Evolutive SFP'!H20/'Evolutive SFP'!H26 -> 0.24348946 | K17: ='Evolutive SFP'!I20/'Evolutive SFP'!I26 -> 0.24346876 | ... AZ17: ='Evolutive SFP'!AX20/'Evolutive SFP'!AX26 -> #DIV/0!
B18: PI to Deposit ratio | C18: Max 5% | D18: ='Evolutive SFP'!B12/'Evolutive SFP'!B30 -> 0 | E18: ='Evolutive SFP'!C12/'Evolutive SFP'!C30 -> 0.01624247 | F18: ='Evolutive SFP'!D12/'Evolutive SFP'!D30 -> 0.015840969 | G18: ='Evolutive SFP'!E12/'Evolutive SFP'!E30 -> 0.015511555 | H18: ='Evolutive SFP'!F12/'Evolutive SFP'!F30 -> 0.015528682 | I18: ='Evolutive SFP'!G12/'Evolutive SFP'!G30 -> 0.015581416 | J18: ='Evolutive SFP'!H12/'Evolutive SFP'!H30 -> 0.015118114 | K18: ='Evolutive SFP'!I12/'Evolutive SFP'!I30 -> 0.015075745 | ... AZ18: ='Evolutive SFP'!AX12/'Evolutive SFP'!AX30 -> #DIV/0!
B19: PI to CC ratio | C19: Max 40% | D19: ='Evolutive SFP'!B12/(CAELS!D3*1000000) -> 0 | E19: ='Evolutive SFP'!C12/(CAELS!E3*1000000) -> 0.092566803 | F19: ='Evolutive SFP'!D12/(CAELS!F3*1000000) -> 0.092507356 | G19: ='Evolutive SFP'!E12/(CAELS!G3*1000000) -> 0.083692002 | H19: ='Evolutive SFP'!F12/(CAELS!H3*1000000) -> 0.083711199 | I19: ='Evolutive SFP'!G12/(CAELS!I3*1000000) -> 0.083813717 | J19: ='Evolutive SFP'!H12/(CAELS!J3*1000000) -> 0.12243752 | K19: ='Evolutive SFP'!I12/(CAELS!K3*1000000) -> 0.1224367 | ... AZ19: ='Evolutive SFP'!AX12/(CAELS!AZ3*1000000) -> #DIV/0!
B20: Gross loans/TA | D20: ='Evolutive SFP'!B14/'Evolutive SFP'!B26 -> 0.59843833 | E20: ='Evolutive SFP'!C14/'Evolutive SFP'!C26 -> 0.48133296 | F20: ='Evolutive SFP'!D14/'Evolutive SFP'!D26 -> 0.465 | G20: ='Evolutive SFP'!E14/'Evolutive SFP'!E26 -> 0.46328209 | H20: ='Evolutive SFP'!F14/'Evolutive SFP'!F26 -> 0.45150952 | I20: ='Evolutive SFP'!G14/'Evolutive SFP'!G26 -> 0.4430494 | J20: ='Evolutive SFP'!H14/'Evolutive SFP'!H26 -> 0.46393125 | K20: ='Evolutive SFP'!I14/'Evolutive SFP'!I26 -> 0.47091937 | ... AZ20: ='Evolutive SFP'!AX14/'Evolutive SFP'!AX26 -> #DIV/0!
A21: FUNDING MIX | B21: Total Deposits/Total Assets | D21: ='Evolutive SFP'!B30/'Evolutive SFP'!B26 -> 0.93093818 | E21: ='Evolutive SFP'!C30/'Evolutive SFP'!C26 -> 0.74526493 | F21: ='Evolutive SFP'!D30/'Evolutive SFP'!D26 -> 0.75981784 | G21: ='Evolutive SFP'!E30/'Evolutive SFP'!E26 -> 0.7869039 | H21: ='Evolutive SFP'!F30/'Evolutive SFP'!F26 -> 0.78573636 | I21: ='Evolutive SFP'!G30/'Evolutive SFP'!G26 -> 0.78639697 | J21: ='Evolutive SFP'!H30/'Evolutive SFP'!H26 -> 0.80933949 | K21: ='Evolutive SFP'!I30/'Evolutive SFP'!I26 -> 0.80833665 | ... AZ21: ='Evolutive SFP'!AX30/'Evolutive SFP'!AX26 -> #DIV/0!
B22: BOSA Deposits/Total Assets | D22: ='Evolutive SFP'!B29/'Evolutive SFP'!B26 -> 0.67905389 | E22: ='Evolutive SFP'!C29/'Evolutive SFP'!C26 -> 0.553923 | F22: ='Evolutive SFP'!D29/'Evolutive SFP'!D26 -> 0.55775319 | G22: ='Evolutive SFP'!E29/'Evolutive SFP'!E26 -> 0.5680535 | H22: ='Evolutive SFP'!F29/'Evolutive SFP'!F26 -> 0.57187018 | I22: ='Evolutive SFP'!G29/'Evolutive SFP'!G26 -> 0.57702369 | J22: ='Evolutive SFP'!H29/'Evolutive SFP'!H26 -> 0.58388031 | K22: ='Evolutive SFP'!I29/'Evolutive SFP'!I26 -> 0.58351263 | ... AZ22: ='Evolutive SFP'!AX29/'Evolutive SFP'!AX26 -> #DIV/0!
B23: FOSA Deposits/Total Assets | D23: =('Evolutive SFP'!B27+'Evolutive SFP'!B28)/'Evolutive SFP'!B26 -> 0.25188429 | E23: =('Evolutive SFP'!C27+'Evolutive SFP'!C28)/'Evolutive SFP'!C26 -> 0.19134192 | F23: =('Evolutive SFP'!D27+'Evolutive SFP'!D28)/'Evolutive SFP'!D26 -> 0.20206465 | G23: =('Evolutive SFP'!E27+'Evolutive SFP'!E28)/'Evolutive SFP'!E26 -> 0.21885041 | H23: =('Evolutive SFP'!F27+'Evolutive SFP'!F28)/'Evolutive SFP'!F26 -> 0.21386618 | I23: =('Evolutive SFP'!G27+'Evolutive SFP'!G28)/'Evolutive SFP'!G26 -> 0.20937328 | J23: =('Evolutive SFP'!H27+'Evolutive SFP'!H28)/'Evolutive SFP'!H26 -> 0.22545918 | K23: =('Evolutive SFP'!I27+'Evolutive SFP'!I28)/'Evolutive SFP'!I26 -> 0.22482402 | ... AZ23: =('Evolutive SFP'!AX27+'Evolutive SFP'!AX28)/'Evolutive SFP'!AX26 -> #DIV/0!
A24: GROWTH RATIOS | B24: Total Assets
B25: Total Deposits | E25: =Financials!C5/Financials!B5-1 -> 0 | F25: =Financials!D5/Financials!C5-1 -> -0.011160694 | G25: =Financials!E5/Financials!D5-1 -> 0.025345738 | H25: =Financials!F5/Financials!E5-1 -> 0.021236707 | I25: =Financials!G5/Financials!F5-1 -> -0.0011029756 | J25: =Financials!H5/Financials!G5-1 -> -0.003384403 | K25: =Financials!I5/Financials!H5-1 -> 0.030645548 | L25: =Financials!J5/Financials!I5-1 -> 0.0028103675 | ... AZ25: =Financials!AX5/Financials!AW5-1 -> #DIV/0!
B26: BOSA Deposits | E26: =Financials!C6/Financials!B6-1 -> 0 | F26: =Financials!D6/Financials!C6-1 -> 0.0075834871 | G26: =Financials!E6/Financials!D6-1 -> 0.012661242 | H26: =Financials!F6/Financials!E6-1 -> 0.0042951803 | I26: =Financials!G6/Financials!F6-1 -> 0.0071027527 | J26: =Financials!H6/Financials!G6-1 -> 0.0047520219 | K26: =Financials!I6/Financials!H6-1 -> 0.013329336 | L26: =Financials!J6/Financials!I6-1 -> 0.0034222062 | ... AZ26: =Financials!AX6/Financials!AW6-1 -> #DIV/0!
B27: FOSA Deposits | E27: =Financials!C7/Financials!B7-1 -> -0.17613747 | F27: =Financials!D7/Financials!C7-1 -> -0.23630194 | G27: =Financials!E7/Financials!D7-1 -> 0.06130713 | H27: =Financials!F7/Financials!E7-1 -> 0.089829614 | I27: =Financials!G7/Financials!F7-1 -> -0.043895049 | J27: =Financials!H7/Financials!G7-1 -> -0.048339943 | K27: =Financials!I7/Financials!H7-1 -> 0.10504953 | L27: =Financials!J7/Financials!I7-1 -> 0.0039253091 | ... AZ27: =Financials!AX7/Financials!AW7-1 -> #DIV/0!
B28: Total Loans & advances | E28: =Financials!C31/Financials!B31-1 -> 0 | F28: =Financials!D31/Financials!C31-1 -> -0.0065132405 | G28: =Financials!E31/Financials!D31-1 -> -0.028419301 | H28: =Financials!F31/Financials!E31-1 -> -0.01755835 | I28: =Financials!G31/Financials!F31-1 -> -0.025039631 | J28: =Financials!H31/Financials!G31-1 -> -0.022879913 | K28: =Financials!I31/Financials!H31-1 -> 0.048629101 | L28: =Financials!J31/Financials!I31-1 -> 0.019178392 | ... AZ28: =Financials!AX31/Financials!AW31-1 -> #DIV/0!
B29: Core capital | E29: =Financials!C11/Financials!B11-1 -> 0.08458837 | F29: =Financials!D11/Financials!C11-1 -> -0.079468937 | G29: =Financials!E11/Financials!D11-1 -> 0.00058817392 | H29: =Financials!F11/Financials!E11-1 -> 0.096412081 | I29: =Financials!G11/Financials!F11-1 -> -0.00021162141 | J29: =Financials!H11/Financials!G11-1 -> -0.0011286802 | K29: =Financials!I11/Financials!H11-1 -> -0.29106219 | L29: =Financials!J11/Financials!I11-1 -> 5.914453e-06 | ... AZ29: =Financials!AX11/Financials!AW11-1 -> 0.043478261
B30: Turnover | E30: =Financials!C37/Financials!B37-1 -> #REF! | F30: =Financials!D37/Financials!C37-1 -> -0.86670731 | G30: =Financials!E37/Financials!D37-1 -> 1.0943166 | H30: =Financials!F37/Financials!E37-1 -> 0.29627765 | I30: =Financials!G37/Financials!F37-1 -> 0.22250087 | J30: =Financials!H37/Financials!G37-1 -> 0.18117 | K30: =Financials!I37/Financials!H37-1 -> 0.49026131 | L30: =Financials!J37/Financials!I37-1 -> 0.1282219 | ... N30: =Financials!L37/Financials!K37-1 -> 0.10078489
B31: Membership
B32: Expenses | D32: ='Evolutitve SCI'!B39/'Evolutitve SCI'!#REF!-1 -> #REF! | E32: ='Evolutitve SCI'!C39/'Evolutitve SCI'!#REF!-1 -> #REF! | F32: ='Evolutitve SCI'!D39/'Evolutitve SCI'!#REF!-1 -> #REF! | G32: ='Evolutitve SCI'!E39/'Evolutitve SCI'!#REF!-1 -> #REF! | H32: ='Evolutitve SCI'!F39/'Evolutitve SCI'!#REF!-1 -> #REF! | I32: ='Evolutitve SCI'!G39/'Evolutitve SCI'!#REF!-1 -> #REF! | J32: ='Evolutitve SCI'!H39/'Evolutitve SCI'!#REF!-1 -> #REF! | K32: ='Evolutitve SCI'!I39/'Evolutitve SCI'!#REF!-1 -> #REF! | ... N32: ='Evolutitve SCI'!L39/'Evolutitve SCI'!#REF!-1 -> #REF!
A33: Efficiency Ratios | B33: FinCost-Deposits/Avg Deposits
B34: FinCost-Shares/Avg Share capital
B35: FinCost-Ext Loans/Avg Ext Loans
B36: OpEx/Average Total Assets
B37: Opex/Turnover
B38: Avge yield on Net loans
B39: Avge yield on Gross loans
A41: ALL/Average Gross Loan portfolio

Sheet FORM 4
K1: 3325 | L1: 23 | M1: 24 | N1: 0 | O1: 303
A2: FORM 4 SASRA2/004
A3: RISK CLASSIFICATION OF ASSETS AND PROVISIONING
A4: SACCO SOCIETY CS NUMBER | E4: 6403
A5: FINANCIAL YEAR
A8: PORTFOLIO AGEING REPORT
B9: Audited 2020 | G9: Audited 2021 | K9: 44621 | O9: 44713 | S9: 44805 | W9: 44896 | AA9: Audited 2022
A10: CLASSIFICATION | B10: NO. OF A/Cs | C10: OUTSTANDING LOAN PORTFOLIO(Kshs) | D10: REQUIRED PROVISION | E10: REQUIRED PROVISION AMOUNT(Kshs) | F10: CLASSIFICATION | G10: NO. OF A/Cs | H10: OUTSTANDING LOAN PORTFOLIO(Kshs) | I10: REQUIRED PROVISION | J10: REQUIRED PROVISION AMOUNT(Kshs) | K10: NO. OF A/Cs | L10: OUTSTANDING LOAN PORTFOLIO(Kshs) | M10: REQUIRED PROVISION | N10: REQUIRED PROVISION AMOUNT(Kshs) | O10: NO. OF A/Cs | P10: OUTSTANDING LOAN PORTFOLIO(Kshs) | Q10: REQUIRED PROVISION | R10: REQUIRED PROVISION AMOUNT(Kshs) | S10: NO. OF A/Cs | T10: OUTSTANDING LOAN PORTFOLIO(Kshs) | U10: REQUIRED PROVISION | V10: REQUIRED PROVISION AMOUNT(Kshs) | W10: NO. OF A/Cs | X10: OUTSTANDING LOAN PORTFOLIO(Kshs) | Y10: REQUIRED PROVISION | Z10: REQUIRED PROVISION AMOUNT(Kshs) | AA10: NO. OF A/Cs | AB10: OUTSTANDING LOAN PORTFOLIO(Kshs) | AC10: REQUIRED PROVISION | AD10: REQUIRED PROVISION AMOUNT(Kshs)
A11: Performing | B11: 2644 | C11: 3.5602685e+08 | D11: 0.01 | E11: =C11*D11 -> 3560268.5 | F11: Performing | G11: 2644 | H11: 3.8328374e+08 | I11: 0.01 | J11: =I11*H11 -> 3832837.4 | K11: 3043 | L11: 3.9724912e+08 | M11: 0.01 | N11: =M11*L11 -> 3972491.2 | O11: 3158 | P11: 4.113493e+08 | Q11: 0.01 | R11: =Q11*P11 -> 4113493 | S11: 3325 | T11: 4.1246907e+08 | U11: 0.01 | V11: =U11*T11 -> 4124690.7 | W11: 3264 | X11: 4.2288383e+08 | Y11: 0.01 | Z11: =Y11*X11 -> 4228838.3 | AA11: 3264 | AB11: 4.2658751e+08 | AC11: 0.01 | AD11: =AC11*AB11 -> 4265875.1
A12: Watch | B12: 54 | C12: 5574440.4 | D12: 0.05 | E12: =C12*D12 -> 278722.02 | F12: Watch | G12: 54 | H12: 1251329.8 | I12: 0.05 | J12: =I12*H12 -> 62566.49 | K12: 10 | L12: 1076852.7 | M12: 0.05 | N12: =M12*L12 -> 53842.633 | O12: 13 | P12: 1926243.8 | Q12: 0.05 | R12: =Q12*P12 -> 96312.188 | S12: 23 | T12: 2746800.6 | U12: 0.05 | V12: =U12*T12 -> 137340.03 | W12: 21 | X12: 1538144.9 | Y12: 0.05 | Z12: =Y12*X12 -> 76907.243 | AA12: 21 | AB12: 1574042.1 | AC12: 0.05 | AD12: =AC12*AB12 -> 78702.103
A13: Substandard | B13: 95 | C13: 4342205 | D13: 0.25 | E13: =C13*D13 -> 1085551.3 | F13: Substandard | G13: 95 | H13: 4311503.2 | I13: 0.25 | J13: =I13*H13 -> 1077875.8 | K13: 21 | L13: 3037550.5 | M13: 0.25 | N13: =M13*L13 -> 759387.64 | O13: 8 | P13: 1699501.2 | Q13: 0.25 | R13: =Q13*P13 -> 424875.3 | S13: 24 | T13: 3979142.6 | U13: 0.25 | V13: =U13*T13 -> 994785.64 | W13: 23 | X13: 2929111 | Y13: 0.25 | Z13: =Y13*X13 -> 732277.76 | AA13: 23 | AB13: 2929111 | AC13: 0.25 | AD13: =AC13*AB13 -> 732277.76
A14: Doubtful | B14: 113 | C14: 8876974.4 | D14: 0.5 | E14: =C14*D14 -> 4438487.2 | F14: Doubtful | G14: 113 | H14: 2564624 | I14: 0.5 | J14: =I14*H14 -> 1282312 | K14: 18 | L14: 3805791.2 | M14: 0.5 | N14: =M14*L14 -> 1902895.6 | O14: 13 | P14: 2922176.3 | Q14: 0.5 | R14: =Q14*P14 -> 1461088.1 | S14: 7 | T14: 1052571 | U14: 0.5 | V14: =U14*T14 -> 526285.48 | W14: 5 | X14: 1371786.9 | Y14: 0.5 | Z14: =Y14*X14 -> 685893.45 | AA14: 5 | AB14: 1371786.9 | AC14: 0.5 | AD14: =AC14*AB14 -> 685893.45
A15: Loss | B15: 254 | C15: 18494256 | D15: 1 | E15: =C15*D15 -> 18494256 | F15: Loss | G15: 254 | H15: 17968117 | I15: 1 | J15: =I15*H15 -> 17968117 | K15: 275 | L15: 17512359 | M15: 1 | N15: =M15*L15 -> 17512359 | O15: 298 | P15: 18771370 | Q15: 1 | R15: =Q15*P15 -> 18771370 | S15: 303 | T15: 19439647 | U15: 1 | V15: =U15*T15 -> 19439647 | W15: 286 | X15: 18509725 | Y15: 1 | Z15: =Y15*X15 -> 18509725 | AA15: 286 | AB15: 18714095 | AC15: 1 | AD15: =AC15*AB15 -> 18714095
A16: subtotal | B16: =SUM(B11:B15) -> 3160 | C16: =SUM(C11:C15) -> 3.9331473e+08 | E16: =SUM(E11:E15) -> 27857285 | F16: subtotal | G16: =SUM(G11:G15) -> 3160 | H16: =SUM(H11:H15) -> 4.0937931e+08 | J16: =SUM(J11:J15) -> 24223709 | K16: =SUM(K11:K15) -> 3367 | L16: =SUM(L11:L15) -> 4.2268167e+08 | N16: =SUM(N11:N15) -> 24200976 | O16: =SUM(O11:O15) -> 3490 | P16: =SUM(P11:P15) -> 4.3666859e+08 | R16: =SUM(R11:R15) -> 24867139 | S16: =SUM(S11:S15) -> 3682 | T16: =SUM(T11:T15) -> 4.3968723e+08 | V16: =SUM(V11:V15) -> 25222749 | W16: =SUM(W11:W15) -> 3599 | X16: =SUM(X11:X15) -> 4.472326e+08 | Z16: =SUM(Z11:Z15) -> 24233642 | AA16: =SUM(AA11:AA15) -> 3599 | AB16: =SUM(AB11:AB15) -> 4.5117654e+08 | AD16: =SUM(AD11:AD15) -> 24476843
A17: Reschedule/Renegotiated loans | F17: Reschedule/Renegotiated loans
A18: Performing | B18: 0 | D18: 0.01 | E18: 0 | F18: Performing | G18: 0 | I18: 0.01 | J18: 0 | K18: 0 | M18: 0.01 | N18: 0 | O18: 16 | P18: 4319647.3 | Q18: 0.01 | R18: =P18*Q18 -> 43196.473 | S18: 0 | U18: 0.01 | V18: 0 | W18: 0 | Y18: 0.01 | Z18: 0 | AA18: 0 | AC18: 0.01 | AD18: 0
A19: Watch | B19: 0 | D19: 0.05 | E19: 0 | F19: Watch | G19: 0 | I19: 0.05 | J19: 0 | K19: 0 | M19: 0.05 | N19: 0 | O19: 1 | P19: 35897.21 | Q19: 0.05 | R19: =P19*Q19 -> 1794.8605 | S19: 0 | U19: 0.05 | V19: 0 | W19: 0 | Y19: 0.05 | Z19: 0 | AA19: 0 | AC19: 0.05 | AD19: 0
A20: Substandard | B20: 0 | D20: 0.25 | E20: 0 | F20: Substandard | G20: 0 | I20: 0.25 | J20: 0 | K20: 0 | M20: 0.25 | N20: 0 | O20: 2 | P20: 243819.95 | Q20: 0.25 | R20: =P20*Q20 -> 60954.988 | S20: 0 | U20: 0.25 | V20: 0 | W20: 0 | Y20: 0.25 | Z20: 0 | AA20: 0 | AC20: 0.25 | AD20: 0
A21: Doubtful | B21: 0 | D21: 0.5 | E21: 0 | F21: Doubtful | G21: 0 | I21: 0.5 | J21: 0 | K21: 0 | M21: 0.5 | N21: 0 | O21: 0 | P21: 4599364.5 | Q21: 0.5 | R21: =P21*Q21 -> 2299682.2 | S21: 0 | U21: 0.5 | V21: 0 | W21: 0 | Y21: 0.5 | Z21: 0 | AA21: 0 | AC21: 0.5 | AD21: 0
A22: Loss | B22: 0 | D22: 1 | E22: 0 | F22: Loss | G22: 0 | I22: 1 | J22: 0 | K22: 0 | M22: 1 | N22: 0 | O22: 0 | Q22: 1 | R22: =P22*Q22 -> 0 | S22: 0 | U22: 1 | V22: 0 | W22: 0 | Y22: 1 | Z22: 0 | AA22: 0 | AC22: 1 | AD22: 0
A23: subtotal | B23: 0 | C23: 0 | E23: 0 | F23: subtotal | G23: 0 | H23: 0 | J23: 0 | K23: 0 | L23: 0 | N23: 0 | O23: =SUM(O18:O22) -> 19 | P23: =SUM(P18:P22) -> 9198728.9 | R23: =SUM(R18:R22) -> 2405628.5 | S23: 0 | T23: 0 | V23: 0 | W23: 0 | X23: 0 | Z23: 0 | AA23: 0 | AB23: 0 | AD23: 0
A24: GRAND TOTAL | B24: 0 | C24: 9.0128218e+08 | E24: 68570306 | F24: GRAND TOTAL | G24: 0 | H24: 9.0128218e+08 | J24: 68570306 | K24: 0 | L24: =L23+L16 -> 4.2268167e+08 | N24: =N23+N16 -> 24200976 | O24: =O16+O23 -> 3509 | P24: =P23+P16 -> 4.4586732e+08 | R24: =R23+R16 -> 27272767 | S24: 0 | T24: =T23+T16 -> 4.3968723e+08 | V24: =V23+V16 -> 25222749 | W24: 0 | X24: =X23+X16 -> 4.472326e+08 | Z24: =Z23+Z16 -> 24233642 | AA24: 0 | AB24: =AB23+AB16 -> 4.5117654e+08 | AD24: =AD23+AD16 -> 24476843
G25: NPL | H25: =SUM(H13:H15) -> 24844244 | K25: NPL | L25: =SUM(L13:L15) -> 24355701 | O25: NPL | P25: =SUM(P13:P15)+P20+P21 -> 28236232 | S25: NPL | T25: =SUM(T13:T15) -> 24471361 | W25: NPL | X25: =SUM(X13:X15) -> 22810623 | AA25: NPL | AB25: =SUM(AB13:AB15) -> 23014993
B26: npl | C26: =SUM(C13:C15) -> 31713436 | H26: =H25/H16 -> 0.060687592 | L26: =L25/L16 -> 0.057621853 | P26: =P25/P16 -> 0.064662843 | T26: =T25/T16 -> 0.055656291 | X26: =X25/X16 -> 0.051003936 | AB26: =AB25/AB16 -> 0.051011058
C27: =C26/C24 -> 0.035187022

Sheet Performance Tool
A1: PRIME-TIME SACCO SOCIETY LIMITED
A2: PERFORMANCE AND COMPLIANCE REPORT AS AT : 31st December , 2022
B3: Prudential Standard | C3: Audited | D3: Audited 2021
C4: 2020 | E4: 44562 | F4: 44593 | G4: 44621 | H4: 44652 | I4: 44682 | J4: 44713 | K4: 44743 | L4: 44774 | M4: 44805 | N4: 44835 | O4: 44866 | P4: 44896 | Q4: Audited 2022 | R4: 44927 | S4: 44958 | T4: 44986 | U4: 45017 | V4: 45047 | W4: 45078 | X4: 45108 | Y4: 45139 | Z4: 45170 | AA4: 45200 | AB4: 45231 | AC4: 45261
A5: A. CAPITAL ADEQUACY
A6: Core Capital | B6: ≥10M | C6: =C33 -> 1.2858832e+08 | D6: =D33 -> 1.3123846e+08 | E6: =E33 -> 1.2954533e+08 | F6: =F33 -> 1.2889079e+08 | G6: =G33 -> 1.3411186e+08 | H6: =H33 -> 1.3983113e+08 | I6: =I33 -> 1.4440618e+08 | J6: =J33 -> 1.4714125e+08 | ... V6: =V33 -> 1.3299439e+08
A7: Core Capital/Total Assets | B7: ≥10% | C7: =C33/C29 -> 0.16042732 | D7: =D33/D29 -> 0.15678202 | E7: =E33/E29 -> 0.15139588 | F7: =F33/F29 -> 0.14927716 | G7: =G33/G29 -> 0.15881461 | H7: =H33/H29 -> 0.16861388 | I7: =I33/I29 -> 0.17345438 | J7: =J33/J29 -> 0.17398343 | ... V7: =V33/V29 -> 0.15263961
A8: Institutional Capital/Total Assets | B8: ≥8% | C8: =C34/C29 -> 0.098752011 | D8: =D34/D29 -> 0.086767101 | E8: =E34/E29 -> 0.082902632 | F8: =F34/F29 -> 0.081397748 | G8: =G34/G29 -> 0.089540933 | H8: =H34/H29 -> 0.09807405 | I8: =I34/I29 -> 0.10318851 | J8: =J34/J29 -> 0.10481333 | ... V8: =V34/V29 -> 0.073446194
A9: B. ASSET QUALITY
A10: NPL (Substandard+Doubtful+Loss) | B10: <5% | C10: =C35/C32 -> 0.080631194 | D10: =D35/D32 -> 0.060687592 | E10: =E35/E32 -> 0 | F10: =F35/F32 -> 0 | G10: =G35/G32 -> 0.057621853 | H10: =H35/H32 -> 0 | I10: =I35/I32 -> 0 | J10: =J35/J32 -> 0.053571629 | ... V10: =V35/V32 -> 0
A11: Non-Earning Assets | B11: <10% | C11: =C36/C29 -> 0.30584696 | D11: =D36/D29 -> 0.30198255 | E11: =E36/E29 -> 0.29315242 | F11: =F36/F29 -> 0.29526473 | G11: =G36/G29 -> 0.29396146 | H11: =H36/H29 -> 0.29878292 | I11: =I36/I29 -> 0.28985731 | J11: =J36/J29 -> 0.26985875 | ... V11: =V36/V29 -> 0.28119226
A12: Equity investments/Deposits | B12: <5% | C12: =C38/C31 -> 0 | D12: =D38/D31 -> 0.00010893092 | E12: =E38/E31 -> 0.013950673 | F12: =F38/F31 -> 0.013829723 | G12: =G38/G31 -> 0.013338398 | H12: =H38/H31 -> 0.013725351 | I12: =I38/I31 -> 0.013761331 | J12: =J38/J31 -> 0.013488669 | ... V12: =V38/V31 -> 0.013094618
A13: Equity investments/Core capital | B13: <40% | C13: =C38/C33 -> 0 | D13: =D38/D33 -> 0.00054099996 | E13: =E38/E33 -> 0.071184588 | F13: =F38/F33 -> 0.071546083 | G13: =G38/G33 -> 0.068760743 | H13: =H38/H33 -> 0.06594834 | I13: =I38/I33 -> 0.063858976 | J13: =J38/J33 -> 0.062671961 | ... V13: =V38/V33 -> 0.069338496
A14: C. EARNINGS RATING
A15: Yield on Gross Loans | C15: =C48/C32 -> 0.19182869 | D15: =D48/D32 -> 0.22210382 | E15: =E48/E32 -> 0.017170072 | F15: =F48/F32 -> 0.034114328 | G15: =G48/G32 -> 0.053579846 | H15: =H48/H32 -> 0.072148151 | I15: =I48/I32 -> 0.09110099 | J15: =J48/J32 -> 0.10735644 | ... V15: =V48/V32 -> 0.075978531
A16: Total Expense/Total Income | C16: =C49/C44 -> 0.80026048 | D16: =D49/D44 -> 0.86671112 | E16: =E49/E44 -> 0.48591675 | F16: =F49/F44 -> 0.66529492 | G16: =G49/G44 -> 0.55906849 | H16: =H49/H44 -> 0.5171095 | I16: =I49/I44 -> 0.51671228 | J16: =J49/J44 -> 0.53321267 | ... V16: =V49/V44 -> 0.54860278
A17: Net Income/Average Assets (ROA) | C17: =C50/C30 -> 0.01263952 | D17: =D50/D30 -> 0.018871331 | E17: =E50/E30 -> 0.0049548471 | F17: =F50/F30 -> 0.0060934133 | G17: =G50/G30 -> 0.014208544 | H17: =H50/H30 -> 0.02133243 | I17: =I50/I30 -> 0.026991495 | J17: =J50/J30 -> 0.029986804 | ... V17: =V50/V30 -> 0.022906125
A18: Operating Expenses/Financial Income (OPEX) | C18: =C47/C44 -> 0.36726971 | D18: =D47/D44 -> 0.47275205 | E18: =E47/E44 -> 0.39920132 | F18: =F47/F44 -> 0.60222647 | G18: =G47/G44 -> 0.48917946 | H18: =H47/H44 -> 0.45021547 | I18: =I47/I44 -> 0.45771303 | J18: =J47/J44 -> 0.47267083 | ... V18: =V47/V44 -> 0.47550098
A19: D. LIQUIDITY
A20: Liquid Assets/Short-term Liabilities | B20: >15% | C20: =C40/C41 -> 0.56414276 | D20: =D40/D41 -> 0.79540211 | E20: =E40/E41 -> 0.57610113 | F20: =F40/F41 -> 0.57325185 | G20: =G40/G41 -> 0.55910964 | H20: =H40/H41 -> 0.49439065 | I20: =I40/I41 -> 0.5217107 | J20: =J40/J41 -> 0.64327958 | ... V20: =V40/V41 -> 0.40224211
A21: External Borrowing/Total Assets | B21: <25% | C21: =C42/C29 -> 0 | D21: =D42/D29 -> 0 | E21: =E42/E29 -> 0 | F21: =F42/F29 -> 0 | G21: =G42/G29 -> 0 | H21: =H42/H29 -> 0 | I21: =I42/I29 -> 0 | J21: =J42/J29 -> 0 | ... V21: =V42/V29 -> 0
A22: Liquid Assets/Total Assets | C22: =C40/C29 -> 0.13565695 | D22: =D40/D29 -> 0.22688071 | E22: =E40/E29 -> 0.16973033 | F22: =F40/F29 -> 0.17145141 | G22: =G40/G29 -> 0.15255534 | H22: =H40/H29 -> 0.12359487 | I22: =I40/I29 -> 0.12703963 | J22: =J40/J29 -> 0.15968786 | ... V22: =V40/V29 -> 0.099939404
A23: E. STRUCTURE/SENSITIVITY TO RISK
A24: Gross loans /Total Assets | B24: 70-80 | C24: =C32/C29 -> 0.49070107 | D24: =D32/D29 -> 0.48905875 | E24: =E32/E29 -> 0.486198 | F24: =F32/F29 -> 0.48241108 | G24: =G32/G29 -> 0.50053757 | H24: =H32/H29 -> 0.52328079 | I24: =I32/I29 -> 0.52854628 | J24: =J32/J29 -> 0.51632764 | ... V24: =V32/V29 -> 0.5621212
A25: Gross loans/Deposits | B25: >100% | C25: =C32/C31 -> 0.62607995 | D25: =D32/D31 -> 0.62808543 | E25: =E32/E31 -> 0.62937329 | F25: =F32/F31 -> 0.6246713 | G25: =G32/G31 -> 0.61137735 | H25: =H32/H31 -> 0.64589368 | I25: =I32/I31 -> 0.65665349 | J25: =J32/J31 -> 0.6387241 | ... V25: =V32/V31 -> 0.69547436
A26: Financial Investments/Total Assets | C26: =C39/C31 -> 0.13057749 | D26: =D39/D31 -> 0.01414818 | E26: =E39/E31 -> 0.10256005 | F26: =F39/F31 -> 0.10220327 | G26: =G39/G31 -> 0.09970776 | H26: =H39/H31 -> 0.1031287 | I26: =I39/I31 -> 0.10392881 | J26: =J39/J31 -> 0.10238887 | ... V26: =V39/V31 -> 0.10494279
A27: Dividends+Interest on Deposits/Total Income | C27: =C46/C44 -> 0.37041292 | D27: =D46/D44 -> 0.37240719 | E27: =E46/E44 -> 0.072228489 | F27: =F46/F44 -> 0.043097097 | G27: =G46/G44 -> 0.045965293 | H27: =H46/H44 -> 0.045846643 | I27: =I46/I44 -> 0.039225083 | J27: =J46/J44 -> 0.04185674 | ... V27: =V46/V44 -> 0.060668342
A28: F. KEY FINANCIAL STATISTICS
A29: Total Assets | C29: 8.0153631e+08 | D29: ='Evolutive SFP'!Y26 -> 8.3707594e+08 | E29: =Financials!AA4 -> 8.5567279e+08 | F29: =Financials!AB4 -> 8.6343277e+08 | G29: =Financials!AC4 -> 8.4445542e+08 | H29: =Financials!AD4 -> 8.2929784e+08 | I29: =Financials!AE4 -> 8.3253121e+08 | J29: =Financials!AF4 -> 8.4571995e+08 | K29: =Financials!AG4 -> 8.4441798e+08 | L29: =Financials!AH4 -> 8.5321793e+08 | ... W29: =Financials!AS4 -> 8.7876739e+08
A30: Average Assets | C30: 7.8552534e+08 | D30: =(C29+D29)/2 -> 8.1930613e+08 | E30: =(D29+E29)/2 -> 8.4637436e+08 | F30: =(E29+F29)/2 -> 8.5955278e+08 | G30: =(F29+G29)/2 -> 8.5394409e+08 | H30: =(G29+H29)/2 -> 8.3687663e+08 | I30: =(H29+I29)/2 -> 8.3091453e+08 | J30: =(I29+J29)/2 -> 8.3912558e+08 | K30: =(J29+K29)/2 -> 8.4506896e+08 | ... W30: =(V29+W29)/2 -> 8.7503206e+08
A31: Total Deposits | C31: 628218051 | D31: =Financials!Z5 -> 651789212 | E31: =Financials!AA5 -> 6.6101693e+08 | F31: =Financials!AB5 -> 6.6679794e+08 | G31: =Financials!AC5 -> 6.9135972e+08 | H31: =Financials!AD5 -> 6.7186852e+08 | I31: =Financials!AE5 -> 6.7011183e+08 | J31: =Financials!AF5 -> 6.8365761e+08 | K31: =Financials!AG5 -> 6.8052259e+08 | ... W31: =Financials!AS5 -> 7.0851886e+08
A32: Gross Loans | C32: 393314725 | D32: ='Evolutive SFP'!Y14 -> 409379310 | E32: ='Evolutive SFP'!Z14 -> 4.160264e+08 | F32: ='Evolutive SFP'!AA14 -> 4.1652954e+08 | G32: ='Evolutive SFP'!AB14 -> 422681669 | H32: ='Evolutive SFP'!AC14 -> 4.3395563e+08 | I32: ='Evolutive SFP'!AD14 -> 4.4003127e+08 | J32: ='Evolutive SFP'!AE14 -> 4.3666859e+08 | K32: ='Evolutive SFP'!AF14 -> 4.4320895e+08 | ... W32: ='Evolutive SFP'!AR14 -> 4.9759461e+08
A33: Core Capital | C33: 1.2858832e+08 | D33: =Financials!Z11 -> 1.3123846e+08 | E33: =Financials!AA11 -> 1.2954533e+08 | F33: =Financials!AB11 -> 1.2889079e+08 | G33: =Financials!AC11 -> 1.3411186e+08 | H33: =Financials!AD11 -> 1.3983113e+08 | I33: =Financials!AE11 -> 1.4440618e+08 | J33: =Financials!AF11 -> 1.4714125e+08 | K33: =Financials!AG11 -> 1.474561e+08 | ... W33: =Financials!AS11 -> 1.3647134e+08
A34: Institutional Capital | C34: 79153323 | D34: =Financials!Z12 -> 72630653 | E34: =Financials!AA12 -> 70937527 | F34: =Financials!AB12 -> 70281482 | G34: =Financials!AC12 -> 75613326 | H34: =Financials!AD12 -> 81332598 | I34: =Financials!AE12 -> 85907652 | J34: =Financials!AF12 -> 88642722 | K34: =Financials!AG12 -> 88957565 | ... W34: =Financials!AS12 -> 67485375
A35: Non-performing Loans | C35: ='FORM 4'!C13+'FORM 4'!C14+'FORM 4'!C15 -> 31713436 | D35: ='FORM 4'!H13+'FORM 4'!H14+'FORM 4'!H15 -> 24844244 | G35: ='FORM 4'!L13+'FORM 4'!L14+'FORM 4'!L15 -> 24355701 | J35: ='FORM 4'!P13+'FORM 4'!P14+'FORM 4'!P15 -> 23393048 | M35: ='FORM 4'!T13+'FORM 4'!T14+'FORM 4'!T15 -> 24471361 | P35: ='FORM 4'!X13+'FORM 4'!X14+'FORM 4'!X15 -> 22810623 | Q35: ='FORM 4'!AB13+'FORM 4'!AB14+'FORM 4'!AB15 -> 23014993 | W35: 30233363
A36: Non-Earning Assets | C36: 245147446 | D36: =Financials!Z34 -> 2.5278232e+08 | E36: =Financials!AA34 -> 2.5084255e+08 | F36: =Financials!AB34 -> 2.5494124e+08 | G36: =Financials!AC34 -> 2.4823735e+08 | H36: =Financials!AD34 -> 2.4778003e+08 | I36: =Financials!AE34 -> 2.4131526e+08 | J36: =Financials!AF34 -> 2.2822493e+08 | K36: =Financials!AG34 -> 2.4372274e+08 | ... W36: =Financials!AS34 -> 2.2564065e+08
A37: Property and Equipment | C37: 24653331 | D37: =Financials!Z35 -> 22963419 | E37: =Financials!AA35 -> 25639209 | F37: =Financials!AB35 -> 25639209 | G37: =Financials!AC35 -> 23024950 | H37: =Financials!AD35 -> 23024950 | I37: =Financials!AE35 -> 23525650 | J37: =Financials!AF35 -> 23525650 | K37: =Financials!AG35 -> 23525650 | ... W37: =Financials!AS35 -> 21478316
A38: Equity Investments | C38: 0 | D38: =Financials!Z27 -> 71000 | E38: =Financials!AA27 -> 9221631 | F38: =Financials!AB27 -> 9221631 | G38: =Financials!AC27 -> 9221631 | H38: =Financials!AD27 -> 9221631 | I38: =Financials!AE27 -> 9221631 | J38: =Financials!AF27 -> 9221631 | K38: =Financials!AG27 -> 9221631 | ... W38: =Financials!AS27 -> 9221631
A39: Financial Investments | C39: 82031137 | D39: =Financials!Z25 -> 9221631 | E39: =Financials!AA25 -> 67793929 | F39: =Financials!AB25 -> 68148929 | G39: =Financials!AC25 -> 68933929 | H39: =Financials!AD25 -> 69288929 | I39: =Financials!AE25 -> 69643929 | J39: =Financials!AF25 -> 69998929 | K39: =Financials!AG25 -> 70353929 | ... W39: =Financials!AS25 -> 74258929
A40: Liquid Assets | C40: 108733975 | D40: ='Evolutive SFP'!Y4 -> 189916385 | E40: ='Evolutive SFP'!Z4 -> 1.4523362e+08 | F40: ='Evolutive SFP'!AA4 -> 1.4803677e+08 | G40: ='Evolutive SFP'!AB4 -> 1.2882619e+08 | H40: ='Evolutive SFP'!AC4 -> 1.0249696e+08 | I40: ='Evolutive SFP'!AD4 -> 1.0576446e+08 | J40: ='Evolutive SFP'!AE4 -> 1.3505121e+08 | K40: ='Evolutive SFP'!AF4 -> 1.1135607e+08 | ... W40: ='Evolutive SFP'!AR4 -> 1.0573353e+08
A41: Short-term Liabilities) | C41: 192741948 | D41: ='Evolutive SFP'!Y27+'Evolutive SFP'!Y28+'Evolutive SFP'!Y31+'Evolutive SFP'!Y32+'Evolutive SFP'!Y33+'Evolutive SFP'!Y34+'Evolutive SFP'!Y35 -> 2.3876776e+08 | E41: ='Evolutive SFP'!Z27+'Evolutive SFP'!Z28+'Evolutive SFP'!Z31+'Evolutive SFP'!Z32+'Evolutive SFP'!Z33+'Evolutive SFP'!Z34+'Evolutive SFP'!Z35 -> 2.5209744e+08 | F41: ='Evolutive SFP'!AA27+'Evolutive SFP'!AA28+'Evolutive SFP'!AA31+'Evolutive SFP'!AA32+'Evolutive SFP'!AA33+'Evolutive SFP'!AA34+'Evolutive SFP'!AA35 -> 2.5824036e+08 | G41: ='Evolutive SFP'!AB27+'Evolutive SFP'!AB28+'Evolutive SFP'!AB31+'Evolutive SFP'!AB32+'Evolutive SFP'!AB33+'Evolutive SFP'!AB34+'Evolutive SFP'!AB35 -> 2.304131e+08 | H41: ='Evolutive SFP'!AC27+'Evolutive SFP'!AC28+'Evolutive SFP'!AC31+'Evolutive SFP'!AC32+'Evolutive SFP'!AC33+'Evolutive SFP'!AC34+'Evolutive SFP'!AC35 -> 2.0731978e+08 | I41: ='Evolutive SFP'!AD27+'Evolutive SFP'!AD28+'Evolutive SFP'!AD31+'Evolutive SFP'!AD32+'Evolutive SFP'!AD33+'Evolutive SFP'!AD34+'Evolutive SFP'!AD35 -> 2.0272626e+08 | J41: ='Evolutive SFP'!AE27+'Evolutive SFP'!AE28+'Evolutive SFP'!AE31+'Evolutive SFP'!AE32+'Evolutive SFP'!AE33+'Evolutive SFP'!AE34+'Evolutive SFP'!AE35 -> 2.099417e+08 | K41: ='Evolutive SFP'!AF27+'Evolutive SFP'!AF28+'Evolutive SFP'!AF31+'Evolutive SFP'!AF32+'Evolutive SFP'!AF33+'Evolutive SFP'!AF34+'Evolutive SFP'!AF35 -> 2.1023573e+08 | ... W41: ='Evolutive SFP'!AR27+'Evolutive SFP'!AR28+'Evolutive SFP'!AR31+'Evolutive SFP'!AR32+'Evolutive SFP'!AR33+'Evolutive SFP'!AR34+'Evolutive SFP'!AR35 -> 2.182186e+08
A42: External Borrowing | C42: 0 | D42: ='Evolutive SFP'!Y36 -> 0 | E42: ='Evolutive SFP'!Z36 -> 0 | F42: ='Evolutive SFP'!AA36 -> 0 | G42: ='Evolutive SFP'!AB36 -> 0 | H42: ='Evolutive SFP'!AC36 -> 0 | I42: ='Evolutive SFP'!AD36 -> 0 | J42: ='Evolutive SFP'!AE36 -> 0 | K42: ='Evolutive SFP'!AF36 -> 0 | ... W42: ='Evolutive SFP'!AR36 -> 0
A43: Average Gross Loans | C43: 3.812033e+08 | D43: =(D32+C32)/2 -> 4.0134702e+08 | E43: =(E32+D32)/2 -> 4.1270285e+08 | F43: =(F32+E32)/2 -> 4.1627797e+08 | G43: =(G32+F32)/2 -> 4.196056e+08 | H43: =(H32+G32)/2 -> 4.2831865e+08 | I43: =(I32+H32)/2 -> 4.3699345e+08 | J43: =(J32+I32)/2 -> 4.3834993e+08 | K43: =(K32+J32)/2 -> 4.3993877e+08 | ... W43: =(W32+V32)/2 -> 4.9368448e+08
A44: Total Income | C44: 96030176 | D44: ='Evolutitve SCI'!Y3+'Evolutitve SCI'!Y30 -> 115999152 | E44: ='Evolutitve SCI'!Z3+'Evolutitve SCI'!Z30 -> 8219788.5 | F44: ='Evolutitve SCI'!AA3+'Evolutitve SCI'!AA30 -> 15809770 | G44: ='Evolutitve SCI'!AB3+'Evolutitve SCI'!AB30 -> 27639899 | H44: ='Evolutitve SCI'!AC3+'Evolutitve SCI'!AC30 -> 37098705 | I44: ='Evolutitve SCI'!AD3+'Evolutitve SCI'!AD30 -> 46591552 | J44: ='Evolutitve SCI'!AE3+'Evolutitve SCI'!AE30 -> 54168554 | K44: ='Evolutitve SCI'!AF3+'Evolutitve SCI'!AF30 -> 58386853 | ... W44: ='Evolutitve SCI'!AR3+'Evolutitve SCI'!AR30 -> 52191175
A45: Net Financial Income/Loss | C45: 54449996 | D45: ='Evolutitve SCI'!Y19 -> 72800233 | E45: ='Evolutitve SCI'!Z19 -> 7507006 | F45: ='Evolutitve SCI'!AA19 -> 14812672 | G45: ='Evolutitve SCI'!AB19 -> 25708174 | H45: ='Evolutitve SCI'!AC19 -> 34617023 | I45: ='Evolutitve SCI'!AD19 -> 43842686 | J45: ='Evolutitve SCI'!AE19 -> 50889090 | K45: ='Evolutitve SCI'!AF19 -> 54378005 | ... W45: ='Evolutitve SCI'!AR19 -> 48169620
A46: Dividends+Interest on Deposits | C46: 35570818 | D46: ='Evolutitve SCI'!Y13 -> 43198919 | E46: ='Evolutitve SCI'!Z13 -> 593702.9 | F46: ='Evolutitve SCI'!AA13 -> 681355.19 | G46: ='Evolutitve SCI'!AB13 -> 1270476.1 | H46: ='Evolutitve SCI'!AC13 -> 1700851.1 | I46: ='Evolutitve SCI'!AD13 -> 1827557.5 | J46: ='Evolutitve SCI'!AE13 -> 2267319.1 | K46: ='Evolutitve SCI'!AF13 -> 2925786.8 | ... W46: ='Evolutitve SCI'!AR13 -> 3273132.2
A47: Operating Expenses | C47: 35268974 | D47: ='Evolutitve SCI'!Y23 -> 54838836 | E47: ='Evolutitve SCI'!Z23 -> 3281350.5 | F47: ='Evolutitve SCI'!AA23 -> 9521061.9 | G47: ='Evolutitve SCI'!AB23 -> 13520871 | H47: ='Evolutitve SCI'!AC23 -> 16702411 | I47: ='Evolutitve SCI'!AD23 -> 21325561 | J47: ='Evolutitve SCI'!AE23 -> 25603895 | K47: ='Evolutitve SCI'!AF23 -> 28747948 | ... W47: ='Evolutitve SCI'!AR23 -> 24664576
A48: Interest on Loan portfolio+Fees&Commission on Loan | C48: 75449048 | D48: ='Evolutitve SCI'!Y4 -> 90924708 | E48: ='Evolutitve SCI'!Z4 -> 7143203 | F48: ='Evolutitve SCI'!AA4 -> 14209625 | G48: ='Evolutitve SCI'!AB4 -> 22647219 | H48: ='Evolutitve SCI'!AC4 -> 31309096 | I48: ='Evolutitve SCI'!AD4 -> 40087285 | J48: ='Evolutitve SCI'!AE4 -> 46879183 | K48: ='Evolutitve SCI'!AF4 -> 50460203 | ... W48: ='Evolutitve SCI'!AR4 -> 44462396
A49: Total Expenses | C49: 76849154 | D49: ='Evolutitve SCI'!Y12+'Evolutitve SCI'!Y23+'Evolutitve SCI'!Y34 -> 1.0053776e+08 | E49: ='Evolutitve SCI'!Z12+'Evolutitve SCI'!Z23+'Evolutitve SCI'!Z34 -> 3994132.9 | F49: ='Evolutitve SCI'!AA12+'Evolutitve SCI'!AA23+'Evolutitve SCI'!AA34 -> 10518160 | G49: ='Evolutitve SCI'!AB12+'Evolutitve SCI'!AB23+'Evolutitve SCI'!AB34 -> 15452597 | H49: ='Evolutitve SCI'!AC12+'Evolutitve SCI'!AC23+'Evolutitve SCI'!AC34 -> 19184092 | I49: ='Evolutitve SCI'!AD12+'Evolutitve SCI'!AD23+'Evolutitve SCI'!AD34 -> 24074427 | J49: ='Evolutitve SCI'!AE12+'Evolutitve SCI'!AE23+'Evolutitve SCI'!AE34 -> 28883359 | K49: ='Evolutitve SCI'!AF12+'Evolutitve SCI'!AF23+'Evolutitve SCI'!AF34 -> 32756796 | ... W49: ='Evolutitve SCI'!AR12+'Evolutitve SCI'!AR23+'Evolutitve SCI'!AR34 -> 28686131
A50: Net Income | C50: 9928663.6 | D50: ='Evolutitve SCI'!Y37 -> 15461397 | E50: ='Evolutitve SCI'!Z37 -> 4193655.6 | F50: ='Evolutitve SCI'!AA37 -> 5237610.3 | G50: ='Evolutitve SCI'!AB37 -> 12133303 | H50: ='Evolutitve SCI'!AC37 -> 17852612 | I50: ='Evolutitve SCI'!AD37 -> 22427625 | J50: ='Evolutitve SCI'!AE37 -> 25162694 | K50: ='Evolutitve SCI'!AF37 -> 25477436 | ... W50: ='Evolutitve SCI'!AR37 -> 23332044
A51: G. AREAS OF IMPROVEMENT/REGULATORY CONCERNS
A52: 1
A53: 2
A54: 3
A55: 4
A56: DISCLAIMER: This report is prepared based on information submitted by the Sacco as at the stated date and may change upon verification by the Authority.

Sheet Sectoral Lending
B1: FORM 4B: | C1: PRIME-TIME SACCO
C2: SECTORAL LENDING RETURN
B3: Sacco Society CS Number: | F3: 7591
B4: Financial Year: | F4: 2020
B6: SASRA/GG/2/2019 : SECTORAL CLASSIFICATION OF CREDIT FINANCING BY DT-SACCOS | D6: 44562 | E6: 44593 | F6: 44621 | G6: 44652 | H6: 44682 | I6: 44713 | J6: 44743
F7: LOANS &
B8: Code | C8: ECONOMIC SECTORS | F8: ADVANCES
B9: 0 | C9: Refinancing | D9: 0 | E9: 0 | F9: 294100
B10: 1000 | C10: AGRICULTURE | D10: 0 | E10: 0 | F10: 0
C11: 1100 Crop Farming | D11: 0 | E11: 0 | F11: 0
C12: 1110 Tea | D12: 287100 | E12: 293100 | F12: 1743700
C13: 1120 Coffee | D13: 243500 | E13: 672500 | F13: 1171500
C14: 1130 Sugarcane | D14: 371000 | E14: 729500 | F14: 2245700
C15: 1140 Others, cotton, sisal etc | D15: 547700 | E15: 901700 | F15: 8885390
C16: 1150 Cereals such as maize, wheat, sorghum. Millet etc | D16: 1908520 | E16: 4336420 | F16: 914850
C17: 1160 Legumes such as beans, peas, snow peas, cow peas, french beans etc | D17: 534350 | E17: 557350 | F17: 1966300
C18: 1170 Horticulture crops such as vegetables, fruits, flowers | D18: 539400 | E18: 1015500 | F18: 967200
C19: 1180 Roots & tubers such as Irish potatoes, sweet potatoes and cassava | D19: 479500 | E19: 542000 | F19: 2880100
C20: 1200 Animal Production | D20: 0 | E20: 0 | F20: 0
C21: 1210 Dairy farming | D21: 225200 | E21: 976100 | F21: 647050
C22: 1220 Beef Production | D22: 376750 | E22: 524050 | F22: 1518000
... C38: 1510 Agro-forestry | D38: 1611900 | E38: 2033400 | F38: 774850
B39: 2000 | C39: TRADE | D39: 0 | E39: 0 | F39: 0
C40: 2100 Wholesale and Retail | D40: 0 | E40: 0 | F40: 0
C41: 2110 Wholesale | D41: 247350 | E41: 399350 | F41: 653400
C42: 2120 Retail | D42: 39600 | E42: 202250 | F42: 1028450
C43: 2200 Transport | D43: 0 | E43: 0 | F43: 0
C44: 2210 Public service transport | D44: 277250 | E44: 505250 | F44: 0
C45: 2220 Purchase of motorvehicle accessories | D45: 0 | E45: 0 | F45: 0
C46: 2230 Transportation of goods | D46: 0 | E46: 0 | F46: 1234000
C47: 2300 Hospitality | D47: 0 | E47: 0 | F47: 0
C48: 2310 Accomodation, restaurants, conference facilities, event planning & outside catering, theme parks (wedding and others) | D48: 1234000 | E48: 1234000 | F48: 987200
C49: 2320 Schools and kindergartens | D49: 262700 | E49: 637200 | F49: 12000
C50: 2330 Medical clinics and equipment | D50: 12000 | E50: 12000 | F50: 110000
C51: 2400 Foreign Trade | D51: 0 | E51: 0 | F51: 0
... C53: 2420 Export | D53: 300000 | E53: 300000 | F53: 234100
B54: 3000 | C54: MANUFACTURING AND SERVICING INDUSTRIES | D54: 0 | E54: 0 | F54: 0
C55: 3100 Cottage Industry | D55: 0 | E55: 0 | F55: 0
C56: 3110 Jua kali Industry | D56: 102100 | E56: 234100 | F56: 274000
C57: 3120 Small scale Agricultural Produce processing | D57: 230000 | E57: 230000 | F57: 61500
C58: 3130 Dressmaking Industry | D58: 26500 | E58: 26500 | F58: 520000
C59: 3140 Leather tanning | D59: 420000 | E59: 420000 | F59: 912500
C60: 3150 Carving and handcrafts | D60: 212500 | E60: 362500 | F60: 1512200
C61: 3200 Servicing Industry | D61: 0 | E61: 0 | F61: 0
C62: 3210 Motorvehicle repairs | D62: 1350000 | E62: 1350000 | F62: 300000
C63: 3220 Professional services such as Barber shops | D63: 282000 | E63: 300000 | F63: 2295000
C64: 3230 Working capital for learning institutions, churches & business enterprises | D64: 1230000 | E64: 1230000 | F64: 396000
C65: 3240 Promotion of local tourism | D65: 46000 | E65: 146000 | F65: 105000
C66: 3300 Information, Communication and Technology | D66: 0 | E66: 0 | F66: 0
... C69: 3330 Telecommunication Equipment | D69: 55000 | E69: 55000 | F69: 41799550
B70: 4000 | C70: EDUCATION | D70: 0 | E70: 0 | F70: 0
C71: 4100 Education and related services | D71: 0 | E71: 0 | F71: 0
C72: 4110 School fees for primary and secondary schools including shopping and accomodation | D72: 14832450 | E72: 28942000 | F72: 6650000
C73: 4120 College fees, University fees, training fees, seminar fees | D73: 3190000 | E73: 4956000 | F73: 1453000
C74: 4130 Research and scientific activities etc | D74: 625000 | E74: 625000 | F74: 1137500
B75: 5000 | C75: HUMAN HEALTH | D75: 0 | E75: 0 | F75: 0
C76: 5100 Human health and related services | D76: 0 | E76: 0 | F76: 0
C77: 5110 Medical Bills, purchase of medicine | D77: 800000 | E77: 972500 | F77: 0
C78: 5120 Maternity Bills and expenses | D78: 0 | E78: 0 | F78: 12081000
B79: 6000 | C79: LAND AND HOUSING | D79: 0 | E79: 0 | F79: 0
C80: 6100 Land | D80: 0 | E80: 0 | F80: 0
C81: 6110 Purchase of plots | D81: 200000 | E81: 10296000 | F81: 5027000
C82: 6120 Land purchase services such as surveying and valuation | D82: 2310000 | E82: 3510000 | F82: 600000
C83: 6200 Housing | D83: 0 | E83: 0 | F83: 0
C84: 6210 Construction of multiple residential buildings | D84: 600000 | E84: 600000 | F84: 300000
C85: 6220 Construction of commercial buildings | D85: 40000 | E85: 40000 | F85: 2285000
C86: 6230 Construction of single residential dwelling units | D86: 2165000 | E86: 2165000 | F86: 1153000
C87: 6240 Renoivations of the buildings | D87: 617000 | E87: 647000 | F87: 2275000
B88: 7000 | C88: FINANCE, INVESTMENTS AND INSURANCE | D88: 0 | E88: 0 | F88: 0
C89: 7100 Microfinance | D89: 0 | E89: 0 | F89: 0
C90: 7110 Payment to microfinance loans | D90: 2275000 | E90: 2275000 | F90: 2190000
C91: 7200 Commercial Banks | D91: 0 | E91: 0 | F91: 0
C92: 7210 Payment to Commercial bank loans | D92: 680000 | E92: 1280000 | F92: 400000
C93: 7300 Mortgage Finance | D93: 0 | E93: 0 | F93: 0
C94: 7310 Purchase of residential property/payments to mortgage loans in other financial institutions | D94: 400000 | E94: 400000 | F94: 0
C95: 7400 Insurance | D95: 0 | E95: 0 | F95: 0
C96: 7410 Payment to insurance policies | D96: 0 | E96: 0 | F96: 422100
C97: 7500 Investments | D97: 0 | E97: 0 | F97: 0
C98: 7510 Buying of Sacco shares | D98: 420000 | E98: 420000 | F98: 600000
C99: 7520 purchase of quote shares, unquoted shares, treasury bills & bonds, commercial papers, unit trusts and other quoted public funds | D99: 600000 | E99: 600000 | F99: 2042250
C100: 7530 Paying personal debtsto non-registered institutions | D100: 154100 | E100: 826600 | F100: 450800
B101: 8000 | C101: CONSUMPTION AND SOCIAL SERVICES | D101: 0 | E101: 0 | F101: 0
C102: 8100 Utilities | D102: 0 | E102: 0 | F102: 0
C103: 8110 Expenses incurred relating to car and electronic repairs, bills like electricity, sewer, water, telephone, decoder, personal debts to family members and friends etc. | D103: 300000 | E103: 346800 | F103: 1297930
C104: 8200 Utilities | D104: 0 | E104: 0 | F104: 0
C105: 8210 Household necessities like food, beverages and basic household products. | D105: 212500 | E105: 791800 | F105: 105000
C106: 8300 Consumer Durables | D106: 0 | E106: 0 | F106: 0
C107: 8310 Goods that do not wear out quickly like automobiles(cars), books, household(home appliances, consumer electronics, furniture, tools etc) sports equipment, jewellery, toys etc | D107: 25000 | E107: 25000 | F107: 33500
C108: 8400 Social and communal expenses | D108: 0 | E108: 0 | F108: 0
C109: 8410 Burial expenses, wedding expenses, rites of passage expenses. | D109: 773691.96 | E109: 1315592 | F109: 0
C110: TOTAL | D110: =SUM(D9:D109) -> 52035387 | E110: =SUM(E9:E109) -> 90214487 | F110: =SUM(F9:F109) -> 131318595
