Workbook

Sheet Evolutitve SCI
B2: 2010 Audited | C2: 2020 Audited | D2: 44197 | E2: 44229 | F2: 44258 | G2: 44290 | H2: 44321 | I2: 44353 | J2: 44384 | K2: 44416 | L2: 44448 | M2: 44479 | N2: 44511 | O2: 44542 | P2: Audited 2021 | Q2: 44562 | R2: 44593 | S2: 44621 | T2: 44652 | U2: 44682 | V2: 44713 | W2: 44743 | X2: 44774 | Y2: 44805 | Z2: 44835 | AA2: 44866 | AB2: 44896 | AC2: Audited 2022 | AD2: 44949 | AE2: 44980 | AF2: 45008 | AG2: 45039 | AH2: 45069 | AI2: 45100 | AJ2: 45130 | AK2: 45161 | AL2: 45192 | AM2: 45222 | AN2: 45253 | AO2: 45283
A3: Financial Income | B3: =B4+B7 -> 14599.248 | C3: =C4+C7 -> 118584595 | D3: =D4+D7 -> 10079332 | E3: =E4+E7 -> 20545692 | F3: =F4+F7 -> 33311767 | G3: =G4+G7 -> 47098671 | H3: =H4+H7 -> 59410884 | I3: =I4+I7 -> 73036293 | ... AO3: =AO4+AO7 -> 0
A4: Financial Income From Loans Portfolio | B4: =SUM(B5:B6) -> 12855.806 | C4: =SUM(C5:C6) -> 88458375 | D4: =SUM(D5:D6) -> 8099005 | E4: =SUM(E5:E6) -> 15832497 | F4: =SUM(F5:F6) -> 24875910 | G4: =SUM(G5:G6) -> 34583604 | H4: =SUM(H5:H6) -> 44665750 | I4: =SUM(I5:I6) -> 55806894 | ... AO4: =SUM(AO5:AO6) -> 0
A5: Interest from Loans Portfolio | B5: 11945.435 | C5: 88458375 | D5: 8099005 | E5: 15832497 | F5: 24875910 | G5: 34583604 | H5: 44665750 | I5: 55806894 | J5: 69071138 | K5: 80411931 | L5: 92232153 | M5: 103945112 | N5: 114740008 | O5: 126726553 | P5: 126726553 | Q5: 10562905 | R5: 22627633 | S5: 36086795 | T5: 51827462 | U5: 64176506 | V5: 76832128 | W5: 88985276 | X5: 103062264 | Y5: 115658570 | Z5: 129443405 | AA5: 142266251 | AB5: 155095951 | AC5: 155095951 | AD5: 13625273 | AE5: 25931024 | AF5: 39351953 | AG5: 52289788 | AH5: 66108386 | AI5: 78795356 | AJ5: 91844866 | AK5: 105795895
A6: Fees&Commision on Loan Portfolio | B6: 910.371 | D6: 0 | E6: 0 | F6: 0 | G6: 0 | H6: 0 | I6: 0 | J6: 0 | K6: 0 | L6: 0 | M6: 0 | N6: 0 | O6: 0 | Q6: 0 | R6: 0 | S6: 0 | T6: 0 | U6: 0 | V6: 0 | W6: 0 | X6: 0 | Y6: 0 | Z6: 0 | AA6: 0 | AB6: 0 | AD6: 0 | AE6: 0 | AF6: 0 | AG6: 0 | AH6: 0 | AI6: 0 | AJ6: 0 | AK6: 0
A7: Financial Income from Investments | B7: =SUM(B8:B11) -> 1743.4416 | C7: =SUM(C8:C11) -> 30126220 | D7: =SUM(D8:D11) -> 1980327 | E7: =SUM(E8:E11) -> 4713195 | F7: =SUM(F8:F11) -> 8435857 | G7: =SUM(G8:G11) -> 12515067 | H7: =SUM(H8:H11) -> 14745134 | I7: =SUM(I8:I11) -> 17229399 | ... AO7: =SUM(AO8:AO11) -> 0
A8: Government Securities | C8: - | D8: 0 | E8: 0 | F8: 0 | G8: 0 | H8: 0 | I8: 0 | J8: 0 | K8: 0 | L8: 0 | M8: 0 | N8: 0 | O8: 0 | Q8: 0 | R8: 0 | S8: 0 | T8: 0 | U8: 0 | V8: 0 | W8: 0 | X8: 0 | Y8: 0 | Z8: 0 | AA8: 0 | AB8: 0 | AD8: 0 | AE8: 0 | AF8: 0 | AG8: 0 | AH8: 0 | AI8: 0 | AJ8: 0 | AK8: 0
A9: Deposits with Banks & other Financial Institutions | C9: 1966450 | D9: 0 | E9: 0 | F9: 0 | G9: 0 | H9: 0 | I9: 0 | J9: 0 | K9: 0 | L9: 0 | M9: 0 | N9: 0 | O9: 0 | P9: 1950937 | Q9: 0 | R9: 0 | S9: 0 | T9: 0 | U9: 0 | V9: 0 | W9: 0 | X9: 0 | Y9: 0 | Z9: 0 | AA9: 0 | AB9: 0 | AC9: 1870115 | AD9: 0 | AE9: 0 | AF9: 0 | AG9: 0 | AH9: 0 | AI9: 0 | AJ9: 0 | AK9: 0
A10: Other Investments | C10: - | D10: 0 | E10: 0 | F10: 0 | G10: 0 | H10: 0 | I10: 0 | J10: 0 | K10: 0 | L10: 0 | M10: 0 | N10: 0 | O10: 0 | Q10: 0 | R10: 0 | S10: 0 | T10: 0 | U10: 0 | V10: 0 | W10: 0 | X10: 0 | Y10: 0 | Z10: 0 | AA10: 0 | AB10: 0 | AD10: 0 | AE10: 0 | AF10: 0 | AG10: 0 | AH10: 0 | AI10: 0 | AJ10: 0 | AK10: 0
A11: Other Operating Income | B11: 1743.4416 | C11: 28159770 | D11: 1980327 | E11: 4713195 | F11: 8435857 | G11: 12515067 | H11: 14745134 | I11: 17229399 | J11: 20466689 | K11: 23188437 | L11: 25668575 | M11: 28312182 | N11: 30508945 | O11: 33788242 | P11: =31380556+15049+441700 -> 31837305 | Q11: 2310707 | R11: 4056977 | S11: 9430516 | T11: 12896000 | U11: 15634480 | V11: 19342262 | W11: 21377006 | X11: 24834371 | Y11: 27512745 | Z11: 29988393 | AA11: 32180733 | AB11: 35234684 | AC11: =32951820+403400+9350 -> 33364570 | AD11: 2695055 | AE11: 5183034 | AF11: 12381014 | AG11: 12956592 | AH11: 15790270 | AI11: 19381815 | AJ11: 26178140 | AK11: 29951489
A12: Financial Expenses | B12: =SUM(B13:B18) -> 549.0847 | C12: =SUM(C13:C18) -> 58726389 | D12: =SUM(D13:D18) -> 2061192 | E12: =SUM(E13:E18) -> 5180036 | F12: =SUM(F13:F18) -> 9173589 | G12: =SUM(G13:G18) -> 12244352 | H12: =SUM(H13:H18) -> 18286396 | I12: =SUM(I13:I18) -> 27280369 | ... AO12: =SUM(AO13:AO18) -> 0
A13: Interest Expense on Deposits | B13: 185.36 | C13: 41798147 | D13: 1000000 | E13: 2000000 | F13: 5000000 | G13: 7000000 | H13: 12000000 | I13: 20000000 | J13: 30000000 | K13: 37000000 | L13: 44000000 | M13: 50000000 | N13: 55000000 | O13: 60000000 | P13: 58000000 | Q13: 2000000 | R13: 4000000 | S13: 6000000 | T13: 8000000 | U13: 16000000 | V13: 26000000 | W13: 40600000 | X13: 46400000 | Y13: 52200000 | Z13: 58000000 | AA13: 63800000 | AB13: 66000000 | AC13: 61000000 | AD13: 5000000 | AE13: 6000000 | AF13: 15000000 | AG13: 20000000 | AH13: 25000000 | AI13: 30000000 | AJ13: 35000000 | AK13: 40000000
A14: Cost of External Borrowings | B14: 363.7247 | C14: 14829925 | D14: 895320 | E14: 1757401 | F14: 2495757 | G14: 3274296 | H14: 3993847 | I14: 4694532 | J14: 5340633 | K14: 5965364 | L14: 6549268 | M14: 7661777 | N14: 8715033 | O14: 11710144 | P14: =10035652+1674492 -> 11710144 | Q14: 1104110 | R14: 2666590 | S14: 4099890 | T14: 5611953 | U14: 7022687 | V14: 8416847 | W14: 9733978 | X14: 11032713 | Y14: 12283175 | Z14: 13466263 | AA14: 13822260 | AB14: 17641219 | AC14: =12430511+5210708 -> 17641219 | AD14: 1679272 | AE14: 3161201 | AF14: 4587268 | AG14: 6135786 | AH14: 7584957 | AI14: 9032944 | AJ14: 10163081 | AK14: 11477801
A15: Dividend Expenses | C15: 0 | D15: 0 | E15: 0 | F15: 0 | G15: 0 | H15: 0 | I15: 0 | J15: 0 | K15: 0 | L15: 0 | M15: 0 | N15: 0 | O15: 0 | Q15: 0 | R15: 0 | S15: 0 | T15: 0 | U15: 0 | V15: 0 | W15: 0 | X15: 0 | Y15: 0 | Z15: 0 | AA15: 0 | AB15: 0 | AD15: 0 | AE15: 0 | AF15: 0 | AG15: 0 | AH15: 0 | AI15: 0 | AJ15: 0 | AK15: 0
A16: Other Financial Expense | C16: - | D16: 43217 | E16: 43217 | F16: 125058 | G16: 174164 | H16: 251698 | I16: 286873 | J16: 758844 | K16: 991550 | L16: 1032378 | M16: 1032378 | N16: 1032378 | O16: 1032378 | P16: =42294824-P17-P14-P21 -> 16272909 | Q16: 1000000 | R16: 2000000 | S16: 3000000 | T16: 4000000 | U16: 720344 | V16: 0 | W16: 0 | X16: 0 | Y16: 0 | Z16: 0 | AA16: 0 | AB16: 0 | AC16: =43131530-AC14-AC17-AC21 -> 23468517 | AD16: 0 | AE16: 4000000 | AF16: 6000000 | AG16: 8000000 | AH16: 10000000 | AI16: 12000000 | AJ16: 14000000 | AK16: 16000000
A17: Fees & Commision Expense | C17: 2098317 | D17: 26285 | E17: 66379 | F17: 104485 | G17: 115559 | H17: 137611 | I17: 156048 | J17: 953938 | K17: 962655 | L17: 1023182 | M17: 1061810 | N17: 1655487 | O17: 1700843 | P17: 1710767 | Q17: 558528 | R17: 583352 | S17: 616466 | T17: 650818 | U17: 650818 | V17: 747403 | W17: 2776014 | X17: 1910739 | Y17: 1943893 | Z17: 1960993 | AA17: 2008300 | AB17: 1565202 | AC17: 1548311 | AD17: 43611 | AE17: 1911232 | AF17: 1773395 | AG17: 1469538 | AH17: 1715339 | AI17: 285063 | AJ17: 302066 | AK17: 302066
A18: Other Expenses | C18: - | D18: 96370 | E18: 1313039 | F18: 1448289 | G18: 1680333 | H18: 1903240 | I18: 2142916 | J18: 2391215 | K18: 2662308 | L18: 2844347 | M18: 3126306 | N18: 3623895 | O18: 13250455 | Q18: 117874 | R18: 1829234 | S18: 2209659 | T18: 2341788 | U18: 2682888 | V18: 3112451 | W18: 3224444 | X18: 3616521 | Y18: 3803109 | Z18: 4155506 | AA18: 5663747 | AB18: 5489512 | AD18: 2433451 | AE18: 439616 | AF18: 649607 | AG18: 979290 | AH18: 1176901 | AI18: 3227984 | AJ18: 3907443 | AK18: 4146547
A19: Net Financial Income | B19: =B3-B12 -> 14050.163 | C19: =C3-C12 -> 59858206 | D19: =D3-D12 -> 8018140 | E19: =E3-E12 -> 15365656 | F19: =F3-F12 -> 24138178 | G19: =G3-G12 -> 34854319 | H19: =H3-H12 -> 41124488 | I19: =I3-I12 -> 45755924 | ... AO19: =AO3-AO12 -> 0
A20: Allowance for Loan Loss | B20: =B21-B22 -> 0 | C20: =C21-C22 -> 13181219 | D20: =D21-D22 -> 1000000 | E20: =E21-E22 -> 2000000 | F20: =F21-F22 -> 3000000 | G20: =G21-G22 -> 4000000 | H20: =H21-H22 -> 5000000 | I20: =I21-I22 -> 6000000 | ... AO20: =AO21-AO22 -> 0
A21: Provision for Loan Losses | C21: 13181219 | D21: 1000000 | E21: 2000000 | F21: 3000000 | G21: 4000000 | H21: 5000000 | I21: 6000000 | J21: 7000000 | K21: 8000000 | L21: 9000000 | M21: 10000000 | N21: 12000000 | O21: 12401004 | P21: 12601004 | Q21: 1000000 | R21: 2000000 | S21: 3000000 | T21: 3000000 | U21: 8000000 | V21: 9000000 | W21: 10000000 | X21: 11000000 | Y21: 10269557 | Z21: 10574633 | AA21: 11574633 | AB21: 15473483 | AC21: 473483 | AD21: 0 | AE21: 2125830 | AF21: 0 | AG21: 0 | AH21: 0 | AI21: 0 | AJ21: 1079623 | AK21: 1390912
A22: Value of Loans Recovered | D22: 0 | E22: 0 | F22: 0 | G22: 0 | H22: 0 | I22: 0 | J22: 0 | K22: 0 | L22: 0 | M22: 0 | N22: 0 | O22: 0 | Q22: 0 | R22: 0 | S22: 0 | T22: 0 | U22: 0 | V22: 0 | W22: 0 | X22: 0 | Y22: 0 | Z22: 0 | AA22: 0 | AB22: 0 | AD22: 0 | AE22: 0 | AF22: 0 | AG22: 0 | AH22: 0 | AI22: 0 | AJ22: 0 | AK22: 0
A23: Operating Expeses | B23: =SUM(B24:B28) -> 11019.38 | C23: =SUM(C24:C28) -> 41765573 | D23: =SUM(D24:D28) -> 2725789 | E23: =SUM(E24:E28) -> 8588399 | F23: =SUM(F24:F28) -> 11513740 | G23: =SUM(G24:G28) -> 14779697 | H23: =SUM(H24:H28) -> 17742988 | I23: =SUM(I24:I28) -> 22111423 | ... AO23: =SUM(AO24:AO28) -> 0
A24: Personel Expenses | B24: 3512.444 | C24: 21003549 | D24: 1347309 | E24: 3092017 | F24: 4755430 | G24: 6116773 | H24: 7695779 | I24: 9487565 | J24: 12335468 | K24: 13847231 | L24: 15270288 | M24: 17324377 | N24: 19319770 | O24: 17429683 | P24: 19109783 | Q24: 1420310 | R24: 2785854 | S24: 4584477 | T24: 6075761 | U24: 8358265 | V24: 9746132 | W24: 11128619 | X24: 12528250 | Y24: 14091316 | Z24: 15477583 | AA24: 16911038 | AB24: 18758205 | AC24: 18298205 | AD24: 2748133 | AE24: 5977144 | AF24: 7367535 | AG24: 9243562 | AH24: 11677886 | AI24: 13113768 | AJ24: 14710022 | AK24: 16269502
A25: Governance Expenses | B25: 401.873 | C25: 4104017 | D25: 118460 | E25: 275660 | F25: 1258260 | G25: 1547760 | H25: 1838060 | I25: 2249360 | J25: 2543160 | K25: 2703060 | L25: 2871160 | M25: 2990060 | N25: 3205560 | O25: 3591060 | P25: =4459275-P26 -> 3591060 | Q25: 224500 | R25: 1640080 | S25: 3501090 | T25: 3636490 | U25: 3847660 | V25: 3979700 | W25: 4173590 | X25: 4355299 | Y25: 4749779 | Z25: 4912739 | AA25: 5063039 | AB25: 5638729 | AC25: =6850019-AC26 -> 5278729 | AD25: 542670 | AE25: 939920 | AF25: 3046150 | AG25: 3269670 | AH25: 3563240 | AI25: 4199160 | AJ25: 4646610 | AK25: 4820110
A26: Marketing Expenses | B26: 919.3528 | D26: 28900 | E26: 57600 | F26: 227200 | G26: 250100 | H26: 277650 | I26: 320700 | J26: 386500 | K26: 524840 | L26: 560020 | M26: 805800 | N26: 858320 | O26: 868215 | P26: 868215 | Q26: 68500 | R26: 280700 | S26: 505000 | T26: 581500 | U26: 688400 | V26: 849310 | W26: 977510 | X26: 1110510 | Y26: 1175280 | Z26: 1319330 | AA26: 1425440 | AB26: 1571290 | AC26: 1571290 | AD26: 53050 | AE26: 389735 | AF26: 662855 | AG26: 1099705 | AH26: 1297005 | AI26: 1411055 | AJ26: 1559305 | AK26: 1698205
A27: Depreciation and Amortization | B27: 1276.981 | C27: 2525292 | D27: 214525 | E27: 412197 | F27: 614510 | G27: 980289 | H27: 1294557 | I27: 1561172 | J27: 1940083 | K27: 2217038 | L27: 2493508 | M27: 2770565 | N27: 3273377 | O27: 3594135 | P27: 3594135 | Q27: 221703 | R27: 387117 | S27: 609426 | T27: 969136 | U27: 1210670 | V27: 1487826 | W27: 1738915 | X27: 1987332 | Y27: 2235748 | Z27: 2484165 | AA27: 2558622 | AB27: 3465247 | AC27: 3465248 | AD27: 229554 | AE27: 459108 | AF27: 730564 | AG27: 975503 | AH27: 1258742 | AI27: 1477036 | AJ27: 1723209 | AK27: 2215555
A28: Administrative Expenses | B28: 4908.7291 | C28: 14132715 | D28: 1016595 | E28: 4750925 | F28: 4658340 | G28: 5884775 | H28: 6636942 | I28: 8492626 | J28: 9461535 | K28: 10946397 | L28: 12515358 | M28: 13380691 | N28: 15975190 | O28: 19400679 | P28: =17863179-142600 -> 17720579 | Q28: 1721829 | R28: 5674610 | S28: 7081516 | T28: 9279700 | U28: 7714250 | V28: 10491694 | W28: 11547184 | X28: 13045695 | Y28: 16414496 | Z28: 18451612 | AA28: 21757070 | AB28: 20557818 | AC28: =20682918-AC36 -> 20557818 | AD28: 1967935 | AE28: 4709928 | AF28: 7314289 | AG28: 10708493 | AH28: 11988478 | AI28: 15385750 | AJ28: 16932276 | AK28: 17809547
A29: Net Operating Income | B29: =B19-B20-B23 -> 3030.7829 | C29: =C19-C20-C23 -> 4911414 | D29: =D19-D20-D23 -> 4292351 | E29: =E19-E20-E23 -> 4777257 | F29: =F19-F20-F23 -> 9624438 | G29: =G19-G20-G23 -> 16074622 | H29: =H19-H20-H23 -> 18381500 | I29: =I19-I20-I23 -> 17644501 | ... AO29: =AO19-AO20-AO23 -> 0
A30: Net Non operating Income/Expense | B30: =B31-B32 -> 0 | C30: 0 | D30: =D31-D32 -> 0 | E30: =E31-E32 -> 0 | F30: =F31-F32 -> 0 | G30: =G31-G32 -> 0 | H30: =H31-H32 -> 0 | I30: =I31-I32 -> 0 | J30: =J31-J32 -> 0 | K30: =K31-K32 -> 0 | ... AO30: =AO31-AO32 -> 0
A31: Non Operating Income | C31: - | D31: 0 | E31: 0 | F31: 0 | G31: 0 | H31: 0 | I31: 0 | J31: 0 | K31: 0 | L31: 0 | M31: 0 | N31: 0 | O31: 0 | P31: 441700 | Q31: 0 | R31: 0 | S31: 0 | T31: 0 | U31: 0 | V31: 0 | W31: 0 | X31: 0 | Y31: 0 | Z31: 0 | AA31: 0 | AB31: 0 | AD31: 0 | AE31: 0 | AF31: 0 | AG31: 0 | AH31: 0 | AI31: 0 | AJ31: 0 | AK31: 0
A32: Non Operating Expense | C32: - | D32: 0 | E32: 0 | F32: 0 | G32: 0 | H32: 0 | I32: 0 | J32: 0 | K32: 0 | L32: 0 | M32: 0 | N32: 0 | O32: 2529357 | Q32: 0 | R32: 0 | S32: 0 | T32: 0 | U32: 0 | V32: 0 | W32: 0 | X32: 0 | Y32: 0 | Z32: 0 | AA32: 0 | AB32: 0 | AD32: 0 | AE32: 0 | AF32: 0 | AG32: 0 | AH32: 0 | AI32: 0 | AJ32: 0 | AK32: 0
A33: Net Income(Before Tax & Donations) | B33: =B29+B30 -> 3030.7829 | C33: =C29+C30 -> 4911414 | D33: =D29+D30 -> 4292351 | E33: =E29+E30 -> 4777257 | F33: =F29+F30 -> 9624438 | G33: =G29+G30 -> 16074622 | H33: =H29+H30 -> 18381500 | I33: =I29+I30 -> 17644501 | ... AO33: =AO29+AO30 -> 0
A34: Taxes | B34: 20 | C34: 2147442 | D34: 237867 | E34: 248779 | F34: 396897 | G34: 301068 | H34: 312518 | I34: 343574 | J34: 0 | K34: 0 | L34: 0 | M34: 0 | N34: 0 | O34: 4546814 | P34: 4546814 | Q34: 300000 | R34: 0 | S34: 0 | T34: 0 | U34: 0 | V34: 0 | W34: 0 | X34: 0 | Y34: 0 | Z34: 0 | AA34: 0 | AB34: 369209 | AC34: 167995 | AD34: 0 | AE34: 0 | AF34: 0 | AG34: 0 | AH34: 0 | AI34: 0 | AJ34: 0 | AK34: 0
A35: Net Income(After Tax Before Donations) | B35: =B33-B34 -> 3010.7829 | C35: =C33-C34 -> 2763972 | D35: =D33-D34 -> 4054484 | E35: =E33-E34 -> 4528478 | F35: =F33-F34 -> 9227541 | G35: =G33-G34 -> 15773554 | H35: =H33-H34 -> 18068982 | I35: =I33-I34 -> 17300927 | ... AO35: =AO33-AO34 -> 0
A36: Donations | D36: 0 | E36: 30000 | F36: 40000 | G36: 40000 | H36: 55000 | I36: 55000 | J36: 60000 | K36: 75600 | L36: 80600 | M36: 100600 | N36: 125600 | O36: 142600 | P36: 142600 | Q36: 5000 | R36: 17000 | S36: 17000 | T36: 22000 | U36: 32000 | V36: 99100 | W36: 104100 | X36: 114100 | Y36: 114100 | Z36: 114100 | AA36: 125100 | AB36: 125100 | AC36: 125100 | AD36: 5000 | AE36: 10000 | AF36: 20000 | AG36: 25000 | AH36: 30000 | AI36: 35000 | AJ36: 40000 | AK36: 40000
A37: Net Income/(After Tax & Donations) | B37: =B35-B36 -> 3010.7829 | C37: =C35-C36 -> 2763972 | D37: =D35-D36 -> 4054484 | E37: =E35-E36 -> 4498478 | F37: =F35-F36 -> 9187541 | G37: =G35-G36 -> 15733554 | H37: =H35-H36 -> 18013982 | I37: =I35-I36 -> 17245927 | ... AO37: =AO35-AO36 -> 0
A39: Total Expenses | B39: =B12+B23 -> 11568.465 | C39: =C12+C23 -> 100491962 | D39: =D12+D23 -> 4786981 | E39: =E12+E23 -> 13768435 | F39: =F12+F23 -> 20687329 | G39: =G12+G23 -> 27024049 | H39: =H12+H23 -> 36029384 | I39: =I12+I23 -> 49391792 | ... AC39: =AC12+AC23 -> 152829337
J41: =J39-I39 -> 16719584 | K41: =K39-J39 -> 11709067 | L41: =L39-K39 -> 11339066 | M41: =M39-L39 -> 10994255 | N41: =N39-M39 -> 12505246 | O41: =O39-N39 -> 19918582 | P41: =P39-O39 -> 0 | Q41: =Q39-#REF! -> #REF! | R41: =R39-Q39 -> 13410183 | S41: =S39-R39 -> 10359987 | T41: =T39-S39 -> 8939622 | U41: =U39-T39 -> 7748836 | V41: =V39-U39 -> 15935381 | W41: =W39-V39 -> 21068891 | X41: =X39-W39 -> 10086805 | Y41: =Y39-X39 -> 12909737 | ... AC41: =AC39-AB39 -> 12142115

Sheet Evolutive SFP
B3: 2010 Audited | C3: 2020 Audited | D3: 44197 | E3: 44228 | F3: 44256 | G3: 44287 | H3: 44317 | I3: 44348 | J3: 44378 | K3: 44409 | L3: 44440 | M3: 44470 | N3: 44501 | O3: 44531 | P3: Audited 2021 | Q3: 44562 | R3: 44593 | S3: 44621 | T3: 44652 | U3: 44682 | V3: 44713 | W3: 44743 | X3: 44774 | Y3: 44805 | Z3: 44835 | AA3: 44866 | AB3: 44896 | AC3: Audited 2022 | AD3: 44949 | AE3: 44980 | AF3: 45008 | AG3: 45039 | AH3: 45069 | AI3: 45100 | AJ3: 45130 | AK3: 45161 | AL3: 45192 | AM3: 45222 | AN3: 45253 | AO3: 45283
A4: Cash & cash Equivalent | B4: =SUM(B5:B6) -> 19363224 | C4: =SUM(C5:C6) -> 128614953 | D4: =SUM(D5:D6) -> 127864143 | E4: =SUM(E5:E6) -> 118444272 | F4: =SUM(F5:F6) -> 66778450 | G4: =SUM(G5:G6) -> 84467545 | H4: =SUM(H5:H6) -> 57536247 | I4: =SUM(I5:I6) -> 91149655 | ... AO4: =SUM(AO5:AO6) -> 0
A5: Cash In Hand | B5: 19363224 | C5: 2686350 | D5: 7676670 | E5: 3831445 | F5: 9591338 | G5: 7447272 | H5: 11787193 | I5: 8116471 | J5: 3739371 | K5: 8236628 | L5: 5833562 | M5: 7284269 | N5: 12026502 | O5: 6042390 | P5: 6042390 | Q5: 8077430 | R5: 15642655 | S5: 7579113 | T5: 9088953 | U5: 4470470 | V5: 18933536 | W5: 16029828 | X5: 8626488 | Y5: 12619194 | Z5: 10905309 | AA5: 10106374 | AB5: 6106691 | AC5: =6106691+503949 -> 6610640 | AD5: 6715372 | AE5: 14362099 | AF5: 16564967 | AG5: 6130094 | AH5: 18514179 | AI5: 5358200 | AJ5: 16214537 | AK5: 6860818
A6: Cash at Bank | C6: 125928603 | D6: 120187473 | E6: 114612827 | F6: 57187112 | G6: 77020273 | H6: 45749054 | I6: 83033184 | J6: 64077460 | K6: 65415309 | L6: 84409762 | M6: 105270649 | N6: 113060898 | O6: 166559775 | P6: =111228428+55000000+331347 -> 166559775 | Q6: 141208488 | R6: 180766446 | S6: 147393822 | T6: 79584873 | U6: 86966429 | V6: 121609782 | W6: 88231678 | X6: 103747342 | Y6: 97181948 | Z6: 106049805 | AA6: 114367673 | AB6: 173572282 | AC6: =111502512+60000000 -> 171502512 | AD6: 159820476 | AE6: 154861826 | AF6: 131734240 | AG6: 124930044 | AH6: 114940252 | AI6: 136949595 | AJ6: 156953733 | AK6: 161520014
A7: Prepayment and Sundry | B7: 13400392 | C7: 89293794 | D7: 22972619 | E7: 20716662 | F7: 103616312 | G7: 88797119 | H7: 114427077 | I7: 68135442 | J7: 101961296 | K7: 103920108 | L7: 111267825 | M7: 95122533 | N7: 84007973 | O7: 66515095 | P7: =66515095-12000000 -> 54515095 | Q7: 123539280 | R7: 87030760 | S7: 90586804 | T7: 40411890 | U7: 32184925 | V7: 534685 | W7: 32591960 | X7: 31389019 | Y7: 30167754 | Z7: 32383451 | AA7: 33371063 | AB7: 30366824 | AC7: =30571824 -> 30571824 | AD7: 32978963 | AE7: 35216654 | AF7: 33200037 | AG7: 42908470 | AH7: 34808055 | AI7: 28932530 | AJ7: 40713806 | AK7: 41145922
A8: Financial Investment | B8: =SUM(B9:B13) -> 472260 | C8: =SUM(C9:C13) -> 48158789 | D8: =SUM(D9:D13) -> 51742253 | E8: =SUM(E9:E13) -> 80400025 | F8: =SUM(F9:F13) -> 80400025 | G8: =SUM(G9:G13) -> 80400025 | H8: =SUM(H9:H13) -> 80556471 | I8: =SUM(I9:I13) -> 80556471 | ... AO8: =SUM(AO9:AO13) -> 0
A9: Government Securities - Treasury Bills/bonds, | C9: 0 | D9: 0 | E9: 0 | F9: 0 | G9: 0 | H9: 0 | I9: 0 | J9: 0 | K9: 0 | L9: 0 | M9: 0 | N9: 0 | O9: 0 | Q9: 0 | R9: 0 | S9: 0 | T9: 0 | U9: 0 | V9: 0 | W9: 0 | X9: 0 | Y9: 0 | Z9: 0 | AA9: 0 | AB9: 0 | AD9: 0 | AE9: 0 | AF9: 0 | AG9: 0 | AH9: 0 | AI9: 0 | AJ9: 0 | AK9: 0
A10: Other Securities - Commercial papers/Bonds | C10: 0 | D10: 0 | E10: 0 | F10: 0 | G10: 0 | H10: 0 | I10: 0 | J10: 0 | K10: 0 | L10: 0 | M10: 0 | N10: 0 | O10: 0 | Q10: 0 | R10: 0 | S10: 0 | T10: 0 | U10: 0 | V10: 0 | W10: 0 | X10: 0 | Y10: 0 | Z10: 0 | AA10: 0 | AB10: 0 | AD10: 0 | AE10: 0 | AF10: 0 | AG10: 0 | AH10: 0 | AI10: 0 | AJ10: 0 | AK10: 0
A11: Balances in NACCOS (E.g Jungu Kuu, ESS, Savings,Money Market, CFP) | C11: 45647269 | D11: 31991236 | E11: 31991236 | F11: 31991236 | G11: 31991236 | H11: 32147682 | I11: 32147682 | J11: 32147682 | K11: 32147682 | L11: 32147682 | M11: 32373682 | N11: 32599681 | O11: 34119292 | P11: 34119292 | Q11: 34359442 | R11: 34585442 | S11: 34811442 | T11: 35483697 | U11: 35709697 | V11: 35935697 | W11: 36161697 | X11: 36489030 | Y11: 36715030 | Z11: 36941030 | AA11: 37167030 | AB11: 37835432 | AC11: 39401254 | AD11: 38061432 | AE11: 38287432 | AF11: 38513432 | AG11: 38739432 | AH11: 38965432 | AI11: 39381283 | AJ11: 39813015 | AK11: 40039015
A12: Equity Investments in NACCOs(Shares in- CIC, KUSCCO, COOP BANK,CAK, KERUSSU) | P12: =12139125+5757349+25913328+2087467 -> 45897269 | AC12: =12139126+6007349+25913328+2087467 -> 46147270 | AD12: 48658789 | AE12: 48658789 | AF12: 48658789 | AG12: 48658789 | AH12: 48658789 | AI12: 48658789 | AJ12: 48658789 | AK12: 48658789
A13: Equity Investments in companies - shares/stocks | B13: 472260 | C13: 2511520 | D13: 19751017 | E13: 48408789 | F13: 48408789 | G13: 48408789 | H13: 48408789 | I13: 48408789 | J13: 48408789 | K13: 48408789 | L13: 48408789 | M13: 48408789 | N13: 48408789 | O13: 48408789 | P13: =2511520 -> 2511520 | Q13: 48408789 | R13: 48408789 | S13: 48658789 | T13: 48658789 | U13: 48658789 | V13: 48658789 | W13: 48658789 | X13: 48658789 | Y13: 48658789 | Z13: 48658789 | AA13: 48658789 | AB13: 48658789 | AC13: 2511520
A14: Net Loan Portfolio | B14: =B15-B16 -> 112905266 | C14: =C15-C16 -> 945191720 | D14: =D15-D16 -> 949574103 | E14: =E15-E16 -> 945974458 | F14: =F15-F16 -> 945527615 | G14: =G15-G16 -> 945103539 | H14: =H15-H16 -> 944515624 | I14: =I15-I16 -> 964550729 | ... AO14: =AO15-AO16 -> 0
A15: Gross Loan Portfolio | B15: 112905266 | C15: 994788305 | D15: 1000170688 | E15: 997571043 | F15: 998124200 | G15: 998700124 | H15: 999112209 | I15: 1020147314 | J15: 1023417329 | K15: 1024214400 | L15: 1058417904 | M15: 1058417904 | N15: 1065218794 | O15: 1089345186 | P15: 1099345186 | Q15: 1065218794 | R15: 1068748915 | S15: 1081740012 | T15: 752122230 | U15: 762735725 | V15: 753318303 | W15: 758057271 | X15: 770490393 | Y15: 771992553 | Z15: 771916311 | AA15: 769859428 | AB15: 778820671 | AC15: 778820671 | AD15: 797611909 | AE15: 799587538 | AF15: 791436543 | AG15: 795572569 | AH15: 800003088 | AI15: 804016813 | AJ15: 800870142 | AK15: 825108150
A16: Allowance For Loan Loss | C16: 49596585 | D16: 50596585 | E16: 51596585 | F16: 52596585 | G16: 53596585 | H16: 54596585 | I16: 55596585 | J16: 56596585 | K16: 57596585 | L16: 58596585 | M16: 59596585 | N16: 61596585 | O16: 61997589 | P16: 62197589 | Q16: 63197589 | R16: 64197589 | S16: 65197589 | T16: 53066286 | U16: 40162289 | V16: 37793271 | W16: 38478743 | X16: 37720603 | Y16: 38431846 | Z16: 37736923 | AA16: 36725966 | AB16: 37635773 | AC16: 37635771 | AD16: 38884135 | AE16: 39761885 | AF16: 35760457 | AG16: 37294472 | AH16: 37461770 | AI16: 37285746 | AJ16: 38715396 | AK16: 39093914
A17: Accounts Recievables | B17: =SUM(B18:B20) -> 0 | C17: =SUM(C18:C20) -> 0 | D17: =SUM(D18:D20) -> 0 | E17: =SUM(E18:E20) -> 0 | F17: =SUM(F18:F20) -> 0 | G17: =SUM(G18:G20) -> 0 | H17: =SUM(H18:H20) -> 0 | I17: =SUM(I18:I20) -> 0 | ... AO17: =SUM(AO18:AO20) -> 0
A18: Tax Recoverable | C18: 0 | D18: 0 | E18: 0 | F18: 0 | G18: 0 | H18: 0 | I18: 0 | J18: 0 | K18: 0 | L18: 0 | M18: 0 | N18: 0 | O18: 0 | Q18: 0 | R18: 0 | S18: 0 | T18: 0 | U18: 0 | V18: 0 | W18: 0 | X18: 0 | Y18: 0 | Z18: 0 | AA18: 0 | AB18: 0 | AD18: 0 | AE18: 0 | AF18: 0 | AG18: 0 | AH18: 0 | AI18: 0 | AJ18: 0 | AK18: 0
A19: Deffered Tax Assets | C19: 0 | D19: 0 | E19: 0 | F19: 0 | G19: 0 | H19: 0 | I19: 0 | J19: 0 | K19: 0 | L19: 0 | M19: 0 | N19: 0 | O19: 0 | Q19: 0 | R19: 0 | S19: 0 | T19: 0 | U19: 0 | V19: 0 | W19: 0 | X19: 0 | Y19: 0 | Z19: 0 | AA19: 0 | AB19: 0 | AD19: 0 | AE19: 0 | AF19: 0 | AG19: 0 | AH19: 0 | AI19: 0 | AJ19: 0 | AK19: 0
A20: Retirement Benefit Assets | C20: 0 | D20: 0 | E20: 0 | F20: 0 | G20: 0 | H20: 0 | I20: 0 | J20: 0 | K20: 0 | L20: 0 | M20: 0 | N20: 0 | O20: 0 | Q20: 0 | R20: 0 | S20: 0 | T20: 0 | U20: 0 | V20: 0 | W20: 0 | X20: 0 | Y20: 0 | Z20: 0 | AA20: 0 | AB20: 0 | AD20: 0 | AE20: 0 | AF20: 0 | AG20: 0 | AH20: 0 | AI20: 0 | AJ20: 0 | AK20: 0
A21: Property&Equipments&Other Assets | B21: =SUM(B22:B26) -> 4874587 | C21: =SUM(C22:C26) -> 25718556 | D21: =SUM(D22:D26) -> 23155004 | E21: =SUM(E22:E26) -> 23515693 | F21: =SUM(F22:F26) -> 23581880 | G21: =SUM(G22:G26) -> 24303315 | H21: =SUM(H22:H26) -> 24819659 | I21: =SUM(I22:I26) -> 28489669 | ... AO21: =SUM(AO22:AO26) -> 0
A22: Investment Properties | D22: 3851000 | E22: 3851000 | F22: 3851000 | G22: 3851000 | H22: 3851000 | I22: 3851000 | J22: 3851000 | K22: 3851000 | L22: 3851000 | M22: 3851000 | N22: 3851000 | O22: 3851000 | Q22: 3851000 | R22: 3851000 | S22: 3851000 | T22: 4851000 | U22: 4851000 | V22: 4851000 | W22: 4851000 | X22: 4851000 | Y22: 4851000 | Z22: 4851000 | AA22: 4851000 | AB22: 4851000 | AD22: 4851000 | AE22: 4851000 | AF22: 4851000 | AG22: 4851000 | AH22: 4851000 | AI22: 4851000 | AJ22: 4851000 | AK22: 4851000
A23: Property and Equipment | B23: 4123114 | C23: 22098514 | D23: 18083810 | E23: 17937047 | F23: 18054199 | G23: 18826000 | H23: 18824438 | I23: 22477624 | J23: 18901572 | K23: 18696523 | L23: 18940393 | M23: 18733901 | N23: 18711770 | O23: 18484754 | P23: 22335754 | Q23: 17256614 | R23: 18600463 | S23: 22994217 | T23: 22983810 | U23: 22784839 | V23: 22585868 | W23: 22386897 | X23: 22187926 | Y23: 22013955 | Z23: 21814984 | AA23: 21905973 | AB23: 21048793 | AC23: 25899792 | AD23: 20853838 | AE23: 20658883 | AF23: 21216919 | AG23: 21038961 | AH23: 21302932 | AI23: 21338119 | AJ23: 21124927 | AK23: 21124927
A24: Prepaid Lease Rentals | B24: 0 | C24: 0 | D24: 0 | E24: 0 | F24: 0 | G24: 0 | H24: 0 | I24: 0 | J24: 0 | K24: 0 | L24: 0 | M24: 0 | N24: 0 | O24: 0 | Q24: 0 | R24: 0 | S24: 0 | T24: 205000 | U24: 205000 | V24: 205000 | W24: 0 | X24: 0 | Y24: 0 | Z24: 0 | AA24: 0 | AB24: 205000 | AD24: 205000 | AE24: 205000 | AF24: 205000 | AG24: 205000 | AH24: 0 | AI24: 0 | AJ24: 0 | AK24: 0
A25: Intangible Assets | B25: 751473 | C25: 1829376 | D25: 1220194 | E25: 1727646 | F25: 1676681 | G25: 1626315 | H25: 2144221 | I25: 2161045 | J25: 2039540 | K25: 1967634 | L25: 1907794 | M25: 1837229 | N25: 1766664 | O25: 1742522 | P25: 1742522 | Q25: 1698959 | R25: 1655396 | S25: 1611833 | T25: 1569270 | U25: 1566007 | V25: 1487822 | W25: 1435704 | X25: 1386258 | Y25: 1336813 | Z25: 1287367 | AA25: 1237921 | AB25: 1188476 | AC25: 1188475 | AD25: 1153877 | AE25: 1119278 | AF25: 1089536 | AG25: 1056555 | AH25: 1023576 | AI25: 990595 | AJ25: 957614 | AK25: 957614
A26: Other Assets | C26: 1790666 | D26: 0 | E26: 0 | F26: 0 | G26: 0 | H26: 0 | I26: 0 | J26: 0 | K26: 0 | L26: 0 | M26: 0 | N26: 0 | O26: 1790666 | P26: 1790666 | Q26: 0 | R26: 0 | S26: 0 | T26: 418788148 | U26: 404232984 | V26: 402878958 | W26: 411407226 | X26: 398891285 | Y26: 404408813 | Z26: 405398731 | AA26: 403374085 | AB26: 400771712 | AC26: 395771710 | AD26: 393588686 | AE26: 396896059 | AF26: 388525810 | AG26: 384754056 | AH26: 385078134 | AI26: 380859359 | AJ26: 377652365 | AK26: 375652365
A27: Total Assets | B27: =B21+B17+B14+B8+B7+B4 -> 151015729 | C27: =C21+C17+C14+C8+C7+C4 -> 1236977812 | D27: =D21+D17+D14+D8+D7+D4 -> 1175308122 | E27: =E21+E17+E14+E8+E7+E4 -> 1189051110 | F27: =F21+F17+F14+F8+F7+F4 -> 1219904282 | G27: =G21+G17+G14+G8+G7+G4 -> 1223071543 | H27: =H21+H17+H14+H8+H7+H4 -> 1221855078 | I27: =I21+I17+I14+I8+I7+I4 -> 1232881966 | ... AO27: =AO21+AO17+AO14+AO8+AO7+AO4 -> 0
A28: Savings and Deposits | B28: 8112861 | C28: 196597486 | D28: 160094607 | E28: 144474108 | F28: 165646387 | G28: 155276718 | H28: 144478780 | I28: 146250517 | J28: 152918909 | K28: 149269584 | L28: 145882062 | M28: 147305327 | N28: 155412239 | O28: 148467369 | P28: 184968757 | Q28: 149428757 | R28: 159822084 | S28: 189938230 | T28: 155584657 | U28: 148675981 | V28: 152995040 | W28: 151349612 | X28: 154851879 | Y28: 151477016 | Z28: 152988067 | AA28: 152119545 | AB28: 159702332 | AC28: 202098796 | AD28: 158213177 | AE28: 157480121 | AF28: 169957870 | AG28: 154024015 | AH28: 146668825 | AI28: 142176533 | AJ28: 172023155 | AK28: 182424131
A29: Short Terrm Deposits | B29: 8350444 | C29: 22744581 | D29: 27240666 | E29: 28980670 | F29: 31005770 | G29: 34844770 | H29: 36440611 | I29: 38825897 | J29: 36476526 | K29: 39644265 | L29: 40738819 | M29: 37281819 | N29: 34110327 | O29: 38432727 | P29: 38432727 | Q29: 36705237 | R29: 40412232 | S29: 39467005 | T29: 41096817 | U29: 44584817 | V29: 47714517 | W29: 49804418 | X29: 49666417 | Y29: 48013888 | Z29: 47171661 | AA29: 46054150 | AB29: 43583125 | AC29: 43583126 | AD29: 46097781 | AE29: 47319049 | AF29: 51294232 | AG29: 54835511 | AH29: 54422221 | AI29: 54570722 | AJ29: 55469442 | AK29: 55176774
A30: Non Withdrawable Deposits | B30: 112140909 | C30: 648119220 | D30: 653027408 | E30: 657560984 | F30: 658237631 | G30: 663672071 | H30: 667297041 | I30: 672478023 | J30: 671289225 | K30: 674145345 | L30: 677288785 | M30: 677014567 | N30: 681062853 | O30: 688606121 | P30: 688580171 | Q30: 693913233 | R30: 699331954 | S30: 703419370 | T30: 707120558 | U30: 711700029 | V30: 711246774 | W30: 711177383 | X30: 710435343 | Y30: 713581190 | Z30: 716857531 | AA30: 720983998 | AB30: 726994123 | AC30: 727001223 | AD30: 729441854 | AE30: 735032641 | AF30: 738093934 | AG30: 742920489 | AH30: 747616909 | AI30: 751271783 | AJ30: 746110350 | AK30: 747558830
A31: Total Deposit Liabilities | B31: =SUM(B28:B30) -> 128604214 | C31: =SUM(C28:C30) -> 867461287 | D31: =SUM(D28:D30) -> 840362681 | E31: =SUM(E28:E30) -> 831015762 | F31: =SUM(F28:F30) -> 854889788 | G31: =SUM(G28:G30) -> 853793559 | H31: =SUM(H28:H30) -> 848216432 | I31: =SUM(I28:I30) -> 857554437 | ... AO31: =SUM(AO28:AO30) -> 0
A32: Tax Payable | B32: 27231 | C32: 2147442 | D32: 237867 | E32: 248779 | F32: 396897 | G32: 301068 | H32: 312518 | I32: 343574 | J32: 0 | K32: 0 | L32: 0 | M32: 0 | N32: 0 | O32: 2947779 | P32: 2947779 | Q32: 300000 | R32: 0 | S32: 0 | T32: 0 | U32: 0 | V32: 0 | W32: 0 | X32: 0 | Y32: 0 | Z32: 0 | AA32: 0 | AB32: 1731947 | AC32: 2057169 | AD32: 0 | AE32: 0 | AF32: 0 | AG32: 0 | AH32: 0 | AI32: 0 | AJ32: 0 | AK32: 0
A33: Dividends Payable | B33: 3618123 | C33: 40280000 | D33: 1000000 | E33: 2000000 | F33: 5000000 | G33: 7000000 | H33: 12000000 | I33: 20000000 | J33: 30000000 | K33: 37000000 | L33: 44000000 | M33: 50000000 | N33: 55000000 | O33: 60000000 | P33: 58000000 | Q33: 2000000 | R33: 4000000 | S33: 6000000 | T33: 8000000 | U33: 16000000 | V33: 26000000 | W33: 40600000 | X33: 46400000 | Y33: 52200000 | Z33: 58000000 | AA33: 63800000 | AB33: 66000000 | AC33: 61000000 | AD33: 66000000 | AE33: 67000000 | AF33: 20361698 | AG33: 22460124 | AH33: 25000000 | AI33: 30000000 | AJ33: 35000000 | AK33: 40000000
A34: Deferred Tax Liability | C34: 0 | D34: 0 | E34: 0 | F34: 0 | G34: 0 | H34: 0 | I34: 0 | J34: 0 | K34: 0 | L34: 0 | M34: 0 | N34: 0 | O34: 0 | Q34: 0 | R34: 0 | S34: 0 | T34: 0 | U34: 0 | V34: 0 | W34: 0 | X34: 0 | Y34: 0 | Z34: 0 | AA34: 0 | AB34: 0 | AD34: 0 | AE34: 0 | AF34: 0 | AG34: 0 | AH34: 0 | AI34: 0 | AJ34: 0 | AK34: 0
A35: Retirement Benefits Liabilty | D35: 0 | E35: 0 | F35: 0 | G35: 0 | H35: 0 | I35: 0 | J35: 0 | K35: 0 | L35: 0 | M35: 0 | N35: 0 | O35: 0 | Q35: 0 | R35: 0 | S35: 0 | T35: 0 | U35: 0 | V35: 0 | W35: 0 | X35: 0 | Y35: 0 | Z35: 0 | AA35: 0 | AB35: 0 | AD35: 0 | AE35: 0 | AF35: 0 | AG35: 0 | AH35: 0 | AI35: 0 | AJ35: 0 | AK35: 0
A36: Other Liabilities | B36: 1214920 | C36: 1662567 | D36: 35647251 | E36: 33391294 | F36: 36018635 | G36: 35078954 | H36: 36224122 | I36: 33981112 | J36: 34508937 | K36: 35115761 | L36: 35455529 | M36: 39521305 | N36: 38355000 | O36: 39589774 | P36: =2754336+360000 -> 3114336 | Q36: 101366275 | R36: 98856737 | S36: 40685202 | T36: 46232258 | U36: 42153455 | V36: 38704100 | W36: 46433542 | X36: 43221390 | Y36: 42630921 | Z36: 43103540 | AA36: 43861370 | AB36: 45021948 | AC36: =820000+1731947 -> 2551947 | AD36: 46175731 | AE36: 48627384 | AF36: 46610040 | AG36: 48964308 | AH36: 47417317 | AI36: 49458537 | AJ36: 52426619 | AK36: 52438404
A37: External Borrowings | B37: 2291669 | C37: 86676534 | D37: 82942020 | E37: 78518799 | F37: 74852133 | G37: 71185467 | H37: 66760355 | I37: 63093688 | J37: 59427022 | K37: 55000013 | L37: 101333347 | M37: 96277793 | N37: 91184333 | O37: 145741122 | P37: 145741122 | Q37: 142364405 | R37: 138101668 | S37: 133841034 | T37: 129863219 | U37: 125572404 | V37: 121264026 | W37: 114161192 | X37: 109818728 | Y37: 105458661 | Z37: 101088594 | AA37: 96692814 | AB37: 138434460 | AC37: 138434460 | AD37: 133712944 | AE37: 128984534 | AF37: 124293770 | AG37: 119528144 | AH37: 114743280 | AI37: 109953977 | AJ37: 105130154 | AK37: 100316438
A38: Total Liabilities | B38: =SUM(B31:B37) -> 135756157 | C38: =SUM(C31:C37) -> 998227830 | D38: =SUM(D31:D37) -> 960189819 | E38: =SUM(E31:E37) -> 945174634 | F38: =SUM(F31:F37) -> 971157453 | G38: =SUM(G31:G37) -> 967359048 | H38: =SUM(H31:H37) -> 963513427 | I38: =SUM(I31:I37) -> 974972811 | ... AO38: =SUM(AO31:AO37) -> 0
A39: Share Capital | B39: 10494697 | C39: 89412126 | D39: 89754772 | E39: 90040142 | F39: 90221432 | G39: 90641085 | H39: 90989813 | I39: 91325372 | J39: 91622528 | K39: 92044339 | L39: 92591109 | M39: 92961774 | N39: 93128535 | O39: 93531639 | P39: 93531639 | Q39: 93586416 | R39: 94151903 | S39: 94273046 | T39: 94633923 | U39: 95038260 | V39: 95442159 | W39: 95853606 | X39: 96212068 | Y39: 96665839 | Z39: 97149961 | AA39: 97328132 | AB39: 97671003 | AC39: 97671003 | AD39: 98127674 | AE39: 98548744 | AF39: 98813674 | AG39: 99188780 | AH39: 99563636 | AI39: 99964203 | AJ39: 100330070 | AK39: 100687987
A40: Capital Grants | B40: 340425 | C40: 0 | D40: 0 | E40: 0 | F40: 0 | G40: 0 | H40: 0 | I40: 0 | J40: 0 | K40: 0 | L40: 0 | M40: 0 | N40: 0 | O40: 0 | P40: 0 | Q40: 0 | R40: 0 | S40: 0 | T40: 0 | U40: 0 | V40: 0 | W40: 0 | X40: 0 | Y40: 0 | Z40: 0 | AA40: 0 | AB40: 0 | AD40: 0 | AE40: 0 | AF40: 0 | AG40: 0 | AH40: 0 | AI40: 0 | AJ40: 0 | AK40: 0
A41: Prior Year Retained Earnigs | B41: 351220 | C41: 60964231 | D41: 64270660 | E41: 63291409 | F41: 63291409 | G41: 63291409 | H41: 63291409 | I41: 63291409 | J41: 63291409 | K41: 63291409 | L41: 63291409 | M41: 63291409 | N41: 63291409 | O41: 69329545 | P41: =63291409-2279292-2129357-360000 -> 58522760 | Q41: 69369767 | R41: 69369767 | S41: 69369767 | T41: 69369767 | U41: 69369767 | V41: 69369767 | W41: 69369767 | X41: 69369767 | Y41: 69369767 | Z41: 69369767 | AA41: 69369767 | AB41: 91210399 | AC41: =68909767-5838174-820000 -> 62251593 | AD41: 90655591 | AE41: 90655591 | AF41: 90655591 | AG41: 90655591 | AH41: 90655591 | AI41: 90655591 | AJ41: 90655591 | AK41: 90655591
A42: Current Year Surplus | B42: 3541956 | C42: 2327178 | D42: 4054484 | E42: 4498478 | F42: 9187541 | G42: 15733554 | H42: 18013982 | I42: 17245927 | J42: 16366451 | K42: 17704325 | L42: 19960619 | M42: 22002930 | N42: 20464343 | O42: 0 | P42: =10646785 -> 10646785 | Q42: 3161258 | R42: 2820073 | S42: 8809930 | T42: 20554316 | U42: 22883004 | V42: 22243927 | W42: 14357928 | X42: 20795476 | Y42: 23890862 | Z42: 28514874 | AA42: 29737735 | AB42: 0 | AC42: 28567777 | AD42: 1617652 | AE42: 5720906 | AF42: 4581304 | AG42: 3399833 | AH42: 6606108 | AI42: 8009411 | AJ42: 13959371 | AK42: 19577139
A43: Statutory Reserves | B43: 531274 | C43: 17513072 | D43: 17162784 | E43: 17513072 | F43: 17513072 | G43: 17513072 | H43: 17513072 | I43: 17513072 | J43: 17513072 | K43: 17513072 | L43: 17513072 | M43: 17513072 | N43: 17513072 | O43: 19682429 | P43: 19642429 | Q43: 19692484 | R43: 19692484 | S43: 19692484 | T43: 19692484 | U43: 19692484 | V43: 19692484 | W43: 19692484 | X43: 19692484 | Y43: 19692484 | Z43: 19692484 | AA43: 19692484 | AB43: 26907185 | AC43: 27039428 | AD43: 27039428 | AE43: 27039428 | AF43: 27039428 | AG43: 27039428 | AH43: 27039428 | AI43: 27039428 | AJ43: 27039428 | AK43: 27039428
A44: Other Reserves | C44: 39875603 | D44: 39875603 | E44: 39875603 | F44: 39875603 | G44: 39875603 | H44: 39875603 | I44: 39875603 | J44: 39875603 | K44: 39875603 | L44: 39875603 | M44: 39875603 | N44: 39875603 | O44: 39875603 | P44: =680000+39195603 -> 39875603 | Q44: 39875603 | R44: 39875603 | S44: 39875603 | T44: 39875603 | U44: 39875603 | V44: 39875603 | W44: 39875603 | X44: 39875603 | Y44: 39875603 | Z44: 39875603 | AA44: 39875603 | AB44: 39875603 | AC44: =680000+39195603 -> 39875603 | AD44: 39875603 | AE44: 39876503 | AF44: 39876503 | AG44: 39876503 | AH44: 42292580 | AI44: 42292580 | AJ44: 42292580 | AK44: 42292206
A45: Revaluation Reserves | C45: 28657772 | D45: 0 | E45: 28657772 | F45: 28657772 | G45: 28657772 | H45: 28657772 | I45: 28657772 | J45: 28657772 | K45: 28657772 | L45: 28657772 | M45: 28657772 | N45: 28657772 | O45: 28657772 | P45: 28657772 | Q45: 28657772 | R45: 28657772 | S45: 28657772 | T45: 28657772 | U45: 28657772 | V45: 28657772 | W45: 28657772 | X45: 28657772 | Y45: 28657772 | Z45: 28657772 | AA45: 28657772 | AB45: 28657772 | AC45: 28657772 | AD45: 28657772 | AE45: 28657772 | AF45: 28657772 | AG45: 28657772 | AH45: 28657772 | AI45: 28657772 | AJ45: 28657772 | AK45: 28657772
A46: Proposed Dividends | C46: 0 | D46: 0 | E46: 0 | F46: 0 | G46: 0 | H46: 0 | I46: 0 | J46: 0 | K46: 0 | L46: 0 | M46: 0 | N46: 0 | O46: 0 | Q46: 0 | R46: 0 | S46: 0 | T46: 0 | U46: 0 | V46: 0 | W46: 0 | X46: 0 | Y46: 0 | Z46: 0 | AA46: 0 | AB46: 0 | AD46: 0 | AE46: 0 | AF46: 0 | AG46: 0 | AH46: 0 | AI46: 0 | AJ46: 0 | AK46: 0
A47: Adjustment To Equity | C47: 0 | D47: 0 | E47: 0 | F47: 0 | G47: 0 | H47: 0 | I47: 0 | J47: 0 | K47: 0 | L47: 0 | M47: 0 | N47: 0 | O47: 0 | Q47: 0 | R47: 0 | S47: 0 | T47: 0 | U47: 0 | V47: 0 | W47: 0 | X47: 0 | Y47: 0 | Z47: 0 | AA47: 0 | AB47: 0 | AD47: 0 | AE47: 0 | AF47: 0 | AG47: 0 | AH47: 0 | AI47: 0 | AJ47: 0 | AK47: 0
A48: Total Equity | B48: =SUM(B39:B47) -> 15259572 | C48: =SUM(C39:C47) -> 238749982 | D48: =SUM(D39:D47) -> 215118303 | E48: =SUM(E39:E47) -> 243876476 | F48: =SUM(F39:F47) -> 248746829 | G48: =SUM(G39:G47) -> 255712495 | H48: =SUM(H39:H47) -> 258341651 | I48: =SUM(I39:I47) -> 257909155 | ... AO48: =SUM(AO39:AO47) -> 0
A49: Total Liabilities and Equity | B49: =B48+B38 -> 151015729 | C49: =C48+C38 -> 1236977812 | D49: =D48+D38 -> 1175308122 | E49: =E48+E38 -> 1189051110 | F49: =F48+F38 -> 1219904282 | G49: =G48+G38 -> 1223071543 | H49: =H48+H38 -> 1221855078 | I49: =I48+I38 -> 1232881966 | ... AO49: =AO48+AO38 -> 0
B51: =B49-B27 -> 0 | C51: =C49-C27 -> 0 | D51: =D49-D27 -> 0 | E51: =E49-E27 -> 0 | F51: =F49-F27 -> 0 | G51: =G49-G27 -> 0 | H51: =H49-H27 -> 0 | I51: =I49-I27 -> 0 | ... AK51: =AK49-AK27 -> 0

Sheet Compliancereport Audited2021
A1: SMARTLIFE SACCO SOCIETY LIMITED
A2: PERFORMANCE AND COMPLIANCE REPORT AS AT : 31st December , 2021
B3: Prudential Standard | C3: Audited | D3: Returns | F3: Audited 2021 | G3: Aggregate for all Licensed Saccos
C4: 2020 | D4: 30th September , 2021 | E4: 31st December , 2021
A5: A. CAPITAL ADEQUACY
A6: Core Capital | B6: ≥10M | C6: =C33 -> 2.0758069e+08 | D6: =D33 -> 1.7484271e+08 | E6: =E33 -> 174010427 | F6: =F33 -> 222237053 | G6: =G33 -> 1.1717834e+11
A7: Core Capital/Total Assets | B7: ≥10% | C7: =C33/C29 -> 0.16781278 | D7: =D33/D29 -> 0.13381624 | E7: =E33/E29 -> 0.12656575 | F7: =F33/F29 -> 0.16190225 | G7: =G33/G29 -> 0.17065191
A8: Institutional Capital/Total Assets | B8: ≥8% | C8: =C34/C29 -> 0.09553006 | D8: =D34/D29 -> 0.06295144 | E8: =E34/E29 -> 0.058535908 | F8: =F34/F29 -> 0.093763377 | G8: =G34/G29 -> 0.10490582
A9: B. ASSET QUALITY
A10: NPL (Substandard+Doubtful+Loss) | B10: <5% | C10: =C35/C32 -> 0 | D10: =D35/D32 -> 0.020000001 | E10: =E35/E32 -> 0.017517802 | F10: =F35/F32 -> 0.046495215 | G10: =G35/G32 -> 0.08178734
A11: Non-Earning Assets | B11: <10% | C11: =C36/C29 -> 0.092978507 | D11: =D36/D29 -> 0.10111527 | E11: =E36/E29 -> 0.064394132 | F11: =F36/F29 -> 0.058560697 | G11: =G36/G29 -> 0.10019208
A12: Equity investments/Deposits | B12: <5% | C12: =C38/C31 -> 0.0028952531 | D12: =D38/D31 -> 0.05603455 | E12: =E38/E31 -> 0.055292342 | F12: =F38/F31 -> 0.002753915 | G12: =G38/G31 -> 0.02863476
A13: Equity investments/Core capital | B13: <40% | C13: =C38/C33 -> 0.012099006 | D13: =D38/D33 -> 0.2768705 | E13: =E38/E33 -> 0.27819476 | F13: =F38/F33 -> 0.011301086 | G13: =G38/G33 -> 0.11343868
A14: C. EARNINGS RATING
A15: Yield on Gross Loans | C15: =C48/C32 -> 0.088921808 | D15: =D48/D32 -> 0.087141528 | E15: =E48/E32 -> 0.11633278 | F15: =F48/F32 -> 0.11527458 | G15: =G48/G32 -> 0.158556
A16: Total Expense/Total Income | C16: =C49/C44 -> 0.35220066 | D16: =D49/D44 -> 0.75622526 | E16: =E49/E44 -> 0.84171025 | F16: =F49/F44 -> 0.82368588 | G16: =G49/G44 -> 0.71531043
A17: Net Income/Average Assets (ROA) | C17: =C50/C30 -> 0.051126501 | D17: =D50/D30 -> 0.015886054 | E17: =E50/E30 -> 0.006437902 | F17: =F50/F30 -> 0.0084980965 | G17: =G50/G30 -> 0.036318533
A18: Operating Expenses/Financial Income (OPEX) | C18: =C47/C44 -> 0.35220066 | D18: =D47/D44 -> 0.28592134 | E18: =E47/E44 -> 0.27962389 | F18: =F47/F44 -> 0.27885654 | G18: =G47/G44 -> 0.32493127
A19: D. LIQUIDITY
A20: Liquid Assets/Short-term Liabilities | B20: >15% | C20: =C40/C41 -> 0.31777559 | D20: =D40/D41 -> 0.33916319 | E20: =E40/E41 -> 0.59633626 | F20: =F40/F41 -> 0.75219846 | G20: =G40/G41 -> 0.70602321
A21: External Borrowing/Total Assets | B21: <25% | C21: =C42/C29 -> 0 | D21: =D42/D29 -> 0.077555693 | E21: =E42/E29 -> 0.10600419 | F21: =F42/F29 -> 0.10617409 | G21: =G42/G29 -> 0.034506714
A22: Liquid Assets/Total Assets | C22: =C40/C29 -> 0.079593966 | D22: =D40/D29 -> 0.06906792 | E22: =E40/E29 -> 0.12554146 | F22: =F40/F29 -> 0.12574267 | G22: =G40/G29 -> 0.13781953
A23: E. STRUCTURE/SENSITIVITY TO RISK
A24: Gross loans /Total Assets | B24: 70-80 | C24: =C32/C29 -> 0.80420869 | D24: =D32/D29 -> 0.81006239 | E24: =E32/E29 -> 0.79233063 | F24: =F32/F29 -> 0.80088564 | G24: =G32/G29 -> 0.74612895
A25: Gross loans/Deposits | B25: >100% | C25: =C32/C31 -> 1.1467812 | D25: =D32/D31 -> 1.2251488 | E25: =E32/E31 -> 1.2442461 | F25: =F32/F31 -> 1.2054466 | G25: =G32/G31 -> 1.1036595
A26: Financial Investments/Total Assets | C26: =C39/C31 -> 0.090283881 | D26: =D39/D31 -> 0.093246405 | E26: =E39/E31 -> 0.094263272 | F26: =F39/F31 -> 0.090493137 | G26: =G39/G31 -> 0.063826668
A27: Dividends+Interest on Deposits/Total Income | C27: =C46/C44 -> 0 | D27: =D46/D44 -> 0.37319532 | E27: =E46/E44 -> 0.37379732 | F27: =F46/F44 -> 0.36034582 | G27: =G46/G44 -> 0.32674991
A28: F. KEY FINANCIAL STATISTICS
A29: Total Assets | C29: 1236977812 | D29: 1306588126 | E29: 1374861880 | F29: ='[1]Evolutive SFP'!P27 -> 1372661880 | G29: 6.8665121e+11
A30: Average Assets | C30: 1202710145 | D30: 1237602419 | E30: 1.291947e+09 | F30: =('[1]Evolutive SFP'!C27+'[1]Evolutive SFP'!P27)/2 -> 1304819846 | G30: 6.5195014e+11
A31: Total Deposits | C31: 867461287 | D31: 863909666 | E31: 875506217 | F31: ='[1]Evolutive SFP'!P31 -> 911981655 | G31: 4.6421053e+11
A32: Gross Loans | C32: 994788305 | D32: 1058417904 | E32: 1089345186 | F32: ='[1]Evolutive SFP'!P15 -> 1099345186 | G32: 5.1233035e+11
A33: Core Capital | C33: 2.0758069e+08 | D33: 1.7484271e+08 | E33: 174010427 | F33: ='[1]Evolutive SFP'!P39+'[1]Evolutive SFP'!P41+'[1]Evolutive SFP'!P42+'[1]Evolutive SFP'!P43+'[1]Evolutive SFP'!P44-'[1]Evolutive SFP'!P13 -> 222237053 | G33: 1.1717834e+11
A34: Institutional Capital | C34: 1.1816856e+08 | D34: 82251604 | E34: 80478788 | F34: =[1]Financials!Q12 -> 128705414 | G34: 7.2033707e+10
A35: Non-performing Loans | C35: 0 | D35: 21168359 | E35: 19082933 | F35: ='[1]FORM 4'!D42+'[1]FORM 4'!D43+'[1]FORM 4'!D44 -> 51114291 | G35: 4.1902136e+10
A36: Non-Earning Assets | C36: 115012350 | D36: 132116012 | E36: 88533037 | F36: ='[1]Evolutive SFP'!P7+'[1]Evolutive SFP'!P17+'[1]Evolutive SFP'!P23+'[1]Evolutive SFP'!P24+'[1]Evolutive SFP'!P25+'[1]Evolutive SFP'!P26 -> 80384037 | G36: 6.8797012e+10
A37: Property and Equipment | C37: 23927890 | D37: 20848187 | E37: 20227276 | F37: ='[1]Evolutive SFP'!P23+'[1]Evolutive SFP'!P25 -> 24078276 | G37: 1.934763e+10
A38: Equity Investments | C38: 2511520 | D38: 48408789 | E38: 48408789 | F38: ='[1]Evolutive SFP'!P13 -> 2511520 | G38: 1.3292557e+10
A39: Financial Investments | C39: 78317772 | D39: 80556471 | E39: 82528081 | F39: ='[1]Evolutive SFP'!P8 -> 82528081 | G39: 2.9629011e+10
A40: Liquid Assets | C40: 98455970 | D40: 90243324 | E40: 172602165 | F40: ='[1]Evolutive SFP'!P4+'[1]Evolutive SFP'!P9+'[1]Evolutive SFP'!P10 -> 172602165 | G40: 9.463395e+10
A41: Short-term Liabilities) | C41: 309828610 | D41: 266076410 | E41: 289437649 | F41: ='[1]Evolutive SFP'!P28+'[1]Evolutive SFP'!P29+'[1]Evolutive SFP'!P32+'[1]Evolutive SFP'!P34+'[1]Evolutive SFP'!P35+'[1]Evolutive SFP'!P36 -> 229463599 | G41: 1.3403802e+11
A42: External Borrowing | C42: 0 | D42: 101333347 | E42: 145741122 | F42: ='[1]Evolutive SFP'!P37 -> 145741122 | G42: 2.3694077e+10
A43: Average Gross Loans | C43: 972889404 | D43: 1.0077634e+09 | E43: 1.0440694e+09 | F43: =('[1]Evolutive SFP'!P15+'[1]Evolutive SFP'!C15)/2 -> 1.0470667e+09 | G43: 4.8882665e+11
A44: Total Income | C44: 118584595 | D44: 117900728 | E44: 160514795 | F44: ='[1]Evolutitve SCI'!P3+'[1]Evolutitve SCI'!P31 -> 160956495 | G44: 9.4683788e+10
A45: Net Financial Income/Loss | C45: 118584595 | D45: 62451553 | E45: 72820975 | F45: ='[1]Evolutitve SCI'!P19 -> 72820975 | G45: 5.7608722e+10
A46: Dividends+Interest on Deposits | C46: 0 | D46: 44000000 | E46: 60000000 | F46: ='[1]Evolutitve SCI'!P15+'[1]Evolutitve SCI'!P13 -> 58000000 | G46: 3.0937919e+10
A47: Operating Expenses | C47: 41765573 | D47: 33710334 | E47: 44883772 | F47: ='[1]Evolutitve SCI'!P23 -> 44883772 | G47: 3.0765724e+10
A48: Interest on Loan portfolio+Fees&Commission on Loan | C48: 88458375 | D48: 92232153 | E48: 126726553 | F48: ='[1]Evolutitve SCI'!P5+'[1]Evolutitve SCI'!P6 -> 126726553 | G48: 8.1233051e+10
A49: Total Expenses | C49: 41765573 | D49: 89159509 | E49: 135106949 | F49: ='[1]Evolutitve SCI'!P39 -> 132577592 | G49: 6.7728301e+10
A50: Net Income | C50: 61490361 | D50: 19660619 | E50: 8317428 | F50: ='[1]Evolutitve SCI'!P37 -> 11088485 | G50: 2.3677872e+10
A51: Checked by:Masphine Abongo
A53: Approved by:
A55: DISCLAIMER: This report is prepared based on information submitted by the Sacco as at the stated date and may change upon verification by the Authority.

Sheet Sheet1

Sheet FORM 4
D1: 44256
B2: CLASSIFICATION | C2: NO. OF A/Cs | D2: OUTSTANDING LOAN PORTFOLIO(Kshs) | E2: REQUIRED PROVISION | F2: REQUIRED PROVISION AMOUNT(Kshs)
B3: Performing | C3: 95 | D3: 896051883 | E3: 0.01 | F3: =D3*E3 -> 8960518.8
B4: Watch | C4: 3 | D4: 28296375 | E4: 0.05 | F4: =D4*E4 -> 1414818.8 | H4: NPL | I4: =D5+D6+D7 -> 18864250
B5: Substandard | C5: 1 | D5: 9432125 | E5: 0.25 | F5: =D5*E5 -> 2358031.2 | H5: PAR | I5: =I4/D8 -> 0.02
B6: Doubtful | C6: 0 | D6: 5659275 | E6: 0.5 | F6: =D6*E6 -> 2829637.5
B7: Loss | C7: 0 | D7: 3772850 | E7: 1 | F7: =D7*E7 -> 3772850
B8: subtotal | C8: =SUM(C3:C7) -> 99 | D8: =SUM(D3:D7) -> 943212508 | E8: =SUM(E3:E7) -> 1.81 | F8: =SUM(F3:F7) -> 19335856
D10: 44348
B11: CLASSIFICATION | C11: NO. OF A/Cs | D11: OUTSTANDING LOAN PORTFOLIO(Kshs) | E11: REQUIRED PROVISION | F11: REQUIRED PROVISION AMOUNT(Kshs)
B12: Performing | D12: 969139948 | E12: 0.01 | F12: =D12*E12 -> 9691399.5
B13: Watch | D13: 30604419 | E13: 0.05 | F13: =D13*E13 -> 1530221 | H13: NPL | I13: =D14+D15+D16 -> 20402945
B14: Substandard | D14: 10201473 | E14: 0.25 | F14: =D14*E14 -> 2550368.2 | H14: PAR | I14: =I13/D17 -> 0.019999999
B15: Doubtful | D15: 6120883 | E15: 0.5 | F15: =D15*E15 -> 3060441.5
B16: Loss | D16: 4080589 | E16: 1 | F16: =D16*E16 -> 4080589
B17: subtotal | C17: =SUM(C12:C16) -> 0 | D17: =SUM(D12:D16) -> 1020147312 | E17: 1.81 | F17: =SUM(F12:F16) -> 20913019
D19: 44440
B20: CLASSIFICATION | C20: NO. OF A/Cs | D20: OUTSTANDING LOAN PORTFOLIO(Kshs) | E20: REQUIRED PROVISION | F20: REQUIRED PROVISION AMOUNT(Kshs)
B21: Performing | C21: 95 | D21: 1005497008 | E21: 0.01 | F21: =D21*E21 -> 10054970
B22: Watch | C22: 3 | D22: 31752537 | E22: 0.05 | F22: =D22*E22 -> 1587626.9 | H22: NPL | I22: =D23+D24+D25 -> 21168359
B23: Substandard | C23: 1 | D23: 10584179 | E23: 0.25 | F23: =D23*E23 -> 2646044.8 | H23: PAR | I23: =I22/D26 -> 0.020000001
B24: Doubtful | C24: 0 | D24: 6350509 | E24: 0.5 | F24: =D24*E24 -> 3175254.5
B25: Loss | C25: 0 | D25: 4233671 | E25: 1 | F25: =D25*E25 -> 4233671
B26: subtotal | C26: =SUM(C21:C25) -> 99 | D26: =SUM(D21:D25) -> 1058417904 | E26: 1.81 | F26: =SUM(F21:F25) -> 21697567
D28: 44531
B29: CLASSIFICATION | C29: NO. OF A/Cs | D29: OUTSTANDING LOAN PORTFOLIO(Kshs) | E29: REQUIRED PROVISION | F29: REQUIRED PROVISION AMOUNT(Kshs)
B30: Performing | C30: 4961 | D30: 1043560612 | E30: 0.01 | F30: =D30*E30 -> 10435606
B31: Watch | C31: 157 | D31: 26701641 | E31: 0.05 | F31: =D31*E31 -> 1335082.1 | H31: NPL | I31: =D32+D33+D34 -> 19082933
B32: Substandard | C32: 25 | D32: 2486540 | E32: 0.25 | F32: =D32*E32 -> 621635 | H32: PAR | I32: =I31/D35 -> 0.017517802
B33: Doubtful | C33: 33 | D33: 5183552 | E33: 0.5 | F33: =D33*E33 -> 2591776
B34: Loss | C34: 321 | D34: 11412841 | E34: 1 | F34: =D34*E34 -> 11412841
B35: subtotal | C35: =SUM(C30:C34) -> 5497 | D35: =SUM(D30:D34) -> 1089345186 | E35: 1.81 | F35: =SUM(F30:F34) -> 26396940
D38: Audited 2021
B39: CLASSIFICATION | C39: NO. OF A/Cs | D39: OUTSTANDING LOAN PORTFOLIO(Kshs) | E39: REQUIRED PROVISION | F39: REQUIRED PROVISION AMOUNT(Kshs)
B40: Performing | C40: 4961 | D40: 10312387 | E40: 0.01 | F40: =D40*E40 -> 103123.87
B41: Watch | C41: 157 | D41: 770911 | E41: 0.05 | F41: =D41*E41 -> 38545.55
B42: Substandard | C42: 25 | D42: 2716646 | E42: 0.25 | F42: =D42*E42 -> 679161.5
B43: Doubtful | C43: 33 | D43: 4710165 | E43: 0.5 | F43: =D43*E43 -> 2355082.5
B44: Loss | C44: 321 | D44: 43687480 | E44: 1 | F44: =D44*E44 -> 43687480
B45: subtotal | C45: =SUM(C40:C44) -> 5497 | D45: =SUM(D40:D44) -> 62197589 | E45: 1.81 | F45: =SUM(F40:F44) -> 46863393
D47: 44621
B48: CLASSIFICATION | C48: NO. OF A/Cs | D48: OUTSTANDING LOAN PORTFOLIO(Kshs) | E48: REQUIRED PROVISION | F48: REQUIRED PROVISION AMOUNT(Kshs)
B49: Performing | C49: 95 | D49: 896051883 | E49: 0.01 | F49: =D49*E49 -> 8960518.8
B50: Watch | C50: 3 | D50: 28296375 | E50: 0.05 | F50: =D50*E50 -> 1414818.8
B51: Substandard | C51: 1 | D51: 9432125 | E51: 0.25 | F51: =D51*E51 -> 2358031.2
B52: Doubtful | C52: 0 | D52: 5659275 | E52: 0.5 | F52: =D52*E52 -> 2829637.5
B53: Loss | C53: 0 | D53: 3772850 | E53: 1 | F53: =D53*E53 -> 3772850
B54: subtotal | C54: =SUM(C49:C53) -> 99 | D54: =SUM(D49:D53) -> 943212508 | E54: =SUM(E49:E53) -> 1.81 | F54: =SUM(F49:F53) -> 19335856
D56: 44713
B57: CLASSIFICATION | C57: NO. OF A/Cs | D57: OUTSTANDING LOAN PORTFOLIO(Kshs) | E57: REQUIRED PROVISION | F57: REQUIRED PROVISION AMOUNT(Kshs)
B58: Performing | D58: 969139948 | E58: 0.01 | F58: =D58*E58 -> 9691399.5
B59: Watch | D59: 30604419 | E59: 0.05 | F59: =D59*E59 -> 1530221
B60: Substandard | D60: 10201473 | E60: 0.25 | F60: =D60*E60 -> 2550368.2
B61: Doubtful | D61: 6120883 | E61: 0.5 | F61: =D61*E61 -> 3060441.5
B62: Loss | D62: 4080589 | E62: 1 | F62: =D62*E62 -> 4080589
B63: subtotal | C63: =SUM(C58:C62) -> 0 | D63: =SUM(D58:D62) -> 1020147312 | E63: 1.81 | F63: =SUM(F58:F62) -> 20913019
D65: 44805
B66: CLASSIFICATION | C66: NO. OF A/Cs | D66: OUTSTANDING LOAN PORTFOLIO(Kshs) | E66: REQUIRED PROVISION | F66: REQUIRED PROVISION AMOUNT(Kshs)
B67: Performing | C67: 95 | D67: 1005497008 | E67: 0.01 | F67: =D67*E67 -> 10054970
B68: Watch | C68: 3 | D68: 31752537 | E68: 0.05 | F68: =D68*E68 -> 1587626.9
B69: Substandard | C69: 1 | D69: 10584179 | E69: 0.25 | F69: =D69*E69 -> 2646044.8
B70: Doubtful | C70: 0 | D70: 6350509 | E70: 0.5 | F70: =D70*E70 -> 3175254.5
B71: Loss | C71: 0 | D71: 4233671 | E71: 1 | F71: =D71*E71 -> 4233671
B72: subtotal | C72: =SUM(C67:C71) -> 99 | D72: =SUM(D67:D71) -> 1058417904 | E72: 1.81 | F72: =SUM(F67:F71) -> 21697567
D74: 44896
B75: CLASSIFICATION | C75: NO. OF A/Cs | D75: OUTSTANDING LOAN PORTFOLIO(Kshs) | E75: REQUIRED PROVISION | F75: REQUIRED PROVISION AMOUNT(Kshs)
B76: Performing | C76: =7682+23 -> 7705 | D76: =706850894+3236633 -> 710087527 | E76: 0.01 | F76: =D76*E76 -> 7100875.3
B77: Watch | C77: 6742 | D77: 13762599 | E77: 0.05 | F77: =D77*E77 -> 688129.95 | J77: =I76*J76 -> 0
B78: Substandard | C78: 4802 | D78: =28622469+896584 -> 29519053 | E78: 0.25 | F78: =D78*E78 -> 7379763.2
B79: Doubtful | C79: 4862 | D79: =5301136+340277 -> 5641413 | E79: 0.5 | F79: =D79*E79 -> 2820706.5
B80: Loss | C80: 3927 | D80: =19629836+180239 -> 19810075 | E80: 1 | F80: =D80*E80 -> 19810075
B81: subtotal | C81: =SUM(C76:C80) -> 28038 | D81: =SUM(D76:D80) -> 778820667 | E81: 1.81 | F81: =SUM(F76:F80) -> 37799550
D84: Audited 2022
B85: CLASSIFICATION | C85: NO. OF A/Cs | D85: OUTSTANDING LOAN PORTFOLIO(Kshs) | E85: REQUIRED PROVISION | F85: REQUIRED PROVISION AMOUNT(Kshs)
B86: Performing | C86: =7682+23 -> 7705 | D86: =706850894+3236633 -> 710087527 | E86: 0.01 | F86: =D86*E86 -> 7100875.3
B87: Watch | C87: 6742 | D87: 13762599 | E87: 0.05 | F87: =D87*E87 -> 688129.95
B88: Substandard | C88: 4802 | D88: =28622469+896584 -> 29519053 | E88: 0.25 | F88: =D88*E88 -> 7379763.2
B89: Doubtful | C89: 4862 | D89: =5301136+340277 -> 5641413 | E89: 0.5 | F89: =D89*E89 -> 2820706.5
B90: Loss | C90: 3927 | D90: =19629836+180239 -> 19810075 | E90: 1 | F90: =D90*E90 -> 19810075
B91: subtotal | C91: =SUM(C86:C90) -> 28038 | D91: =SUM(D86:D90) -> 778820667 | E91: 1.81 | F91: =SUM(F86:F90) -> 37799550

Sheet CAELS
A1: SMARTLIFE SACCO 2017 CAELS
D2: 2010 Audited | E2: 2020Audited | F2: 44198 | G2: 44230 | H2: 44259 | I2: 44291 | J2: 44322 | K2: 44354 | L2: 44385 | M2: 44417 | N2: 44449 | O2: 44480 | P2: 44512 | Q2: 44543 | R2: 2021 AUDITED | S2: 44576 | T2: 44608 | U2: 44637 | V2: 44669 | W2: 44700 | X2: 44732 | Y2: 44763 | Z2: 44795 | AA2: 44827 | AB2: 44858 | AC2: 44890 | AD2: 44921 | AE2: AUDITED2022 | AF2: 44952 | AG2: 44983 | AH2: 45011 | AI2: 45042 | AJ2: 45072 | AK2: 45103 | AL2: 45133 | AM2: 45164
A3: CAPITAL ADEQUACY | B3: Core Capital | C3: 10 M | D3: =(('Evolutive SFP'!B39+'Evolutive SFP'!B40+'Evolutive SFP'!B41+'Evolutive SFP'!B42+'Evolutive SFP'!B43+'Evolutive SFP'!B44)-'Evolutive SFP'!B10)/1000000 -> 15.259572 | E3: =(('Evolutive SFP'!C39+'Evolutive SFP'!C40+'Evolutive SFP'!C41+'Evolutive SFP'!C42+'Evolutive SFP'!C43+'Evolutive SFP'!C44)-'Evolutive SFP'!C10)/1000000 -> 210.09221 | F3: =(('Evolutive SFP'!D39+'Evolutive SFP'!D40+'Evolutive SFP'!D41+'Evolutive SFP'!D42+'Evolutive SFP'!D43+'Evolutive SFP'!D44)-'Evolutive SFP'!D10)/1000000 -> 215.1183 | G3: =(('Evolutive SFP'!E39+'Evolutive SFP'!E40+'Evolutive SFP'!E41+'Evolutive SFP'!E42+'Evolutive SFP'!E43+'Evolutive SFP'!E44)-'Evolutive SFP'!E10)/1000000 -> 215.2187 | H3: =(('Evolutive SFP'!F39+'Evolutive SFP'!F40+'Evolutive SFP'!F41+'Evolutive SFP'!F42+'Evolutive SFP'!F43+'Evolutive SFP'!F44)-'Evolutive SFP'!F10)/1000000 -> 220.08906 | I3: =(('Evolutive SFP'!G39+'Evolutive SFP'!G40+'Evolutive SFP'!G41+'Evolutive SFP'!G42+'Evolutive SFP'!G43+'Evolutive SFP'!G44)-'Evolutive SFP'!G10)/1000000 -> 227.05472 | J3: =(('Evolutive SFP'!H39+'Evolutive SFP'!H40+'Evolutive SFP'!H41+'Evolutive SFP'!H42+'Evolutive SFP'!H43+'Evolutive SFP'!H44)-'Evolutive SFP'!H10)/1000000 -> 229.68388 | K3: =(('Evolutive SFP'!I39+'Evolutive SFP'!I40+'Evolutive SFP'!I41+'Evolutive SFP'!I42+'Evolutive SFP'!I43+'Evolutive SFP'!I44)-'Evolutive SFP'!I10)/1000000 -> 229.25138 | ... AJ3: =(('Evolutive SFP'!AH39+'Evolutive SFP'!AH40+'Evolutive SFP'!AH41+'Evolutive SFP'!AH42+'Evolutive SFP'!AH43+'Evolutive SFP'!AH44)-'Evolutive SFP'!AH10)/1000000 -> 266.15734
B4: CCA | C4: Min 10% | D4: =D3/(('Evolutive SFP'!B27)/1000000) -> 0.10104624 | E4: =E3/(('Evolutive SFP'!C27)/1000000) -> 0.16984315 | F4: =F3/(('Evolutive SFP'!D27)/1000000) -> 0.18303141 | G4: =G3/(('Evolutive SFP'!E27)/1000000) -> 0.18100038 | H4: =H3/(('Evolutive SFP'!F27)/1000000) -> 0.18041502 | I4: =I3/(('Evolutive SFP'!G27)/1000000) -> 0.18564304 | J4: =J3/(('Evolutive SFP'!H27)/1000000) -> 0.18797964 | K4: =K3/(('Evolutive SFP'!I27)/1000000) -> 0.18594755 | ... AJ4: =AJ3/(('Evolutive SFP'!AH27)/1000000) -> 0.18603507
B5: CCD | C5: Min 8% | D5: =D3/('Evolutive SFP'!B31/1000000) -> 0.1186553 | E5: =E3/('Evolutive SFP'!C31/1000000) -> 0.24219203 | F5: =F3/('Evolutive SFP'!D31/1000000) -> 0.25598269 | G5: =G3/('Evolutive SFP'!E31/1000000) -> 0.2589827 | H5: =H3/('Evolutive SFP'!F31/1000000) -> 0.25744729 | I5: =I3/('Evolutive SFP'!G31/1000000) -> 0.26593633 | J5: =J3/('Evolutive SFP'!H31/1000000) -> 0.27078452 | K5: =K3/('Evolutive SFP'!I31/1000000) -> 0.26733158 | ... AJ5: =AJ3/('Evolutive SFP'!AH31/1000000) -> 0.28054718
B6: ICA | C6: Min 8% | D6: =((D3*1000000)-'Evolutive SFP'!B39)/'Evolutive SFP'!B27 -> 0.031552177 | E6: =((E3*1000000)-'Evolutive SFP'!C39)/'Evolutive SFP'!C27 -> 0.097560427 | F6: =((F3*1000000)-'Evolutive SFP'!D39)/'Evolutive SFP'!D27 -> 0.1066644 | G6: =((G3*1000000)-'Evolutive SFP'!E39)/'Evolutive SFP'!E27 -> 0.10527601 | H6: =((H3*1000000)-'Evolutive SFP'!F39)/'Evolutive SFP'!F27 -> 0.10645723 | I6: =((I3*1000000)-'Evolutive SFP'!G39)/'Evolutive SFP'!G27 -> 0.11153365 | J6: =((J3*1000000)-'Evolutive SFP'!H39)/'Evolutive SFP'!H27 -> 0.11351106 | K6: =((K3*1000000)-'Evolutive SFP'!I39)/'Evolutive SFP'!I27 -> 0.11187284 | ... AJ6: =((AJ3*1000000)-'Evolutive SFP'!AH39)/'Evolutive SFP'!AH27 -> 0.11644343
A7: ASSET QUALITY | B7: A/LNPL30 | H7: ='Evolutive SFP'!P312 -> 0 | N7: ='Evolutive SFP'!G16/('FORM 4'!E5+'FORM 4'!E6+'FORM 4'!E7) -> 30626620 | P7: ='Evolutive SFP'!N16/('FORM 4'!D14+'FORM 4'!D15+'FORM 4'!D16) -> 3.0190046 | Q7: ='Evolutive SFP'!O16/('FORM 4'!E14+'FORM 4'!E15+'FORM 4'!E16) -> 35427194 | R7: ='Evolutive SFP'!P16/('FORM 4'!F14+'FORM 4'!F15+'FORM 4'!F16) -> 6.4178134 | S7: ='Evolutive SFP'!Q16/('FORM 4'!G14+'FORM 4'!G15+'FORM 4'!G16) -> #DIV/0! | T7: ='Evolutive SFP'!R16/('FORM 4'!H14+'FORM 4'!H15+'FORM 4'!H16) -> #VALUE! | U7: ='Evolutive SFP'!S16/('FORM 4'!I14+'FORM 4'!I15+'FORM 4'!I16) -> 3.2598796e+09 | V7: ='Evolutive SFP'!T16/('FORM 4'!J14+'FORM 4'!J15+'FORM 4'!J16) -> #DIV/0! | W7: ='Evolutive SFP'!U16/('FORM 4'!K14+'FORM 4'!K15+'FORM 4'!K16) -> #DIV/0! | ... AJ7: ='Evolutive SFP'!AH16/('FORM 4'!X14+'FORM 4'!X15+'FORM 4'!X16) -> #DIV/0!
B8: NPL30 | H8: =('FORM 4'!D5+'FORM 4'!D6+'FORM 4'!D7) -> 18864250 | K8: =('FORM 4'!D14+'FORM 4'!D15+'FORM 4'!D16)/'Evolutive SFP'!I15 -> 0.019999999 | M8: =('FORM 4'!D5+'FORM 4'!D6+'FORM 4'!D7)/'Evolutive SFP'!K15 -> 0.018418263 | N8: =('FORM 4'!D23+'FORM 4'!D24+'FORM 4'!D25)/'Evolutive SFP'!L15 -> 0.020000001 | O8: =('FORM 4'!F5+'FORM 4'!F6+'FORM 4'!F7)/'Evolutive SFP'!M15 -> 0.0084659554 | P8: =('FORM 4'!G5+'FORM 4'!G6+'FORM 4'!G7)/'Evolutive SFP'!N15 -> 0 | Q8: =('FORM 4'!H5+'FORM 4'!H6+'FORM 4'!H7)/'Evolutive SFP'!O15 -> #VALUE! | R8: =('FORM 4'!I5+'FORM 4'!I6+'FORM 4'!I7)/'Evolutive SFP'!P15 -> 1.8192648e-11 | S8: =('FORM 4'!J5+'FORM 4'!J6+'FORM 4'!J7)/'Evolutive SFP'!Q15 -> 0 | T8: =('FORM 4'!K5+'FORM 4'!K6+'FORM 4'!K7)/'Evolutive SFP'!R15 -> 0 | U8: =('FORM 4'!L5+'FORM 4'!L6+'FORM 4'!L7)/'Evolutive SFP'!S15 -> 0 | V8: =('FORM 4'!M5+'FORM 4'!M6+'FORM 4'!M7)/'Evolutive SFP'!T15 -> 0 | ... AJ8: =('FORM 4'!AA5+'FORM 4'!AA6+'FORM 4'!AA7)/'Evolutive SFP'!AH15 -> 0
A9: EARNINGS | B9: ROA | E9: ='Evolutitve SCI'!C33/(('Evolutive SFP'!B27+'Evolutive SFP'!C27)/2) -> 0.0070769984 | F9: ='Evolutitve SCI'!D33/(('Evolutive SFP'!C27+'Evolutive SFP'!D27)/2) -> 0.0035587415 | G9: ='Evolutitve SCI'!E33/(('Evolutive SFP'!D27+'Evolutive SFP'!E27)/2) -> 0.0040410585 | H9: ='Evolutitve SCI'!F33/(('Evolutive SFP'!E27+'Evolutive SFP'!F27)/2) -> 0.007990549 | I9: ='Evolutitve SCI'!G33/(('Evolutive SFP'!F27+'Evolutive SFP'!G27)/2) -> 0.01315987 | J9: ='Evolutitve SCI'!H33/(('Evolutive SFP'!G27+'Evolutive SFP'!H27)/2) -> 0.015036443 | K9: ='Evolutitve SCI'!I33/(('Evolutive SFP'!H27+'Evolutive SFP'!I27)/2) -> 0.014375879 | L9: ='Evolutitve SCI'!J33/(('Evolutive SFP'!I27+'Evolutive SFP'!J27)/2) -> 0.013274815 | ... AJ9: ='Evolutitve SCI'!AH33/(('Evolutive SFP'!AG27+'Evolutive SFP'!AH27)/2) -> 0.0046370126
B10: Cost Income ratio | D10: ='Evolutitve SCI'!B23/'Evolutitve SCI'!B19 -> 0.78428841 | E10: ='Evolutitve SCI'!C23/'Evolutitve SCI'!C19 -> 0.69774181 | F10: ='Evolutitve SCI'!D23/'Evolutitve SCI'!D19 -> 0.33995278 | G10: ='Evolutitve SCI'!E23/'Evolutitve SCI'!E19 -> 0.55893474 | H10: ='Evolutitve SCI'!F23/'Evolutitve SCI'!F19 -> 0.47699292 | I10: ='Evolutitve SCI'!G23/'Evolutitve SCI'!G19 -> 0.42404205 | J10: ='Evolutitve SCI'!H23/'Evolutitve SCI'!H19 -> 0.43144581 | K10: ='Evolutitve SCI'!I23/'Evolutitve SCI'!I19 -> 0.48324722 | ... AJ10: ='Evolutitve SCI'!AH23/'Evolutitve SCI'!AH19 -> 0.81779676
B11: Operating Expense ratio | D11: =('Evolutitve SCI'!B23+'Evolutitve SCI'!B12)/(('Evolutive SFP'!B27+'Evolutive SFP'!C27)/2) -> 1.6669335e-05 | E11: =('Evolutitve SCI'!C23+'Evolutitve SCI'!C12)/(('Evolutive SFP'!C27+'Evolutive SFP'!D27)/2) -> 0.083316791 | F11: =('Evolutitve SCI'!D23+'Evolutitve SCI'!D12)/(('Evolutive SFP'!D27+'Evolutive SFP'!E27)/2) -> 0.004049284 | G11: =('Evolutitve SCI'!E23+'Evolutitve SCI'!E12)/(('Evolutive SFP'!E27+'Evolutive SFP'!F27)/2) -> 0.011431042 | H11: =('Evolutitve SCI'!F23+'Evolutitve SCI'!F12)/(('Evolutive SFP'!F27+'Evolutive SFP'!G27)/2) -> 0.016936172 | I11: =('Evolutitve SCI'!G23+'Evolutitve SCI'!G12)/(('Evolutive SFP'!G27+'Evolutive SFP'!H27)/2) -> 0.022106225 | J11: =('Evolutitve SCI'!H23+'Evolutitve SCI'!H12)/(('Evolutive SFP'!H27+'Evolutive SFP'!I27)/2) -> 0.029354985 | K11: =('Evolutitve SCI'!I23+'Evolutitve SCI'!I12)/(('Evolutive SFP'!I27+'Evolutive SFP'!J27)/2) -> 0.03991531 | ... AJ11: =('Evolutitve SCI'!AH23+'Evolutitve SCI'!AH12)/(('Evolutive SFP'!AH27+'Evolutive SFP'!AI27)/2) -> 0.052544175
A12: LIQUIDITY | B12: MIN LIQ ratio | C12: Min 15% | D12: =('Evolutive SFP'!B4)/('Evolutive SFP'!B28+'Evolutive SFP'!B29+'Evolutive SFP'!B32+'Evolutive SFP'!B33+'Evolutive SFP'!B34+'Evolutive SFP'!B35+'Evolutive SFP'!B36) -> 0.90806632 | E12: =('Evolutive SFP'!C4)/('Evolutive SFP'!C28+'Evolutive SFP'!C29+'Evolutive SFP'!C32+'Evolutive SFP'!C33+'Evolutive SFP'!C34+'Evolutive SFP'!C35+'Evolutive SFP'!C36) -> 0.48822814 | F12: =('Evolutive SFP'!D4)/('Evolutive SFP'!D28+'Evolutive SFP'!D29+'Evolutive SFP'!D32+'Evolutive SFP'!D33+'Evolutive SFP'!D34+'Evolutive SFP'!D35+'Evolutive SFP'!D36) -> 0.57026099 | G12: =('Evolutive SFP'!E4)/('Evolutive SFP'!E28+'Evolutive SFP'!E29+'Evolutive SFP'!E32+'Evolutive SFP'!E33+'Evolutive SFP'!E34+'Evolutive SFP'!E35+'Evolutive SFP'!E36) -> 0.56646193 | H12: =('Evolutive SFP'!F4)/('Evolutive SFP'!F28+'Evolutive SFP'!F29+'Evolutive SFP'!F32+'Evolutive SFP'!F33+'Evolutive SFP'!F34+'Evolutive SFP'!F35+'Evolutive SFP'!F36) -> 0.28050195 | I12: =('Evolutive SFP'!G4)/('Evolutive SFP'!G28+'Evolutive SFP'!G29+'Evolutive SFP'!G32+'Evolutive SFP'!G33+'Evolutive SFP'!G34+'Evolutive SFP'!G35+'Evolutive SFP'!G36) -> 0.36329891 | J12: =('Evolutive SFP'!H4)/('Evolutive SFP'!H28+'Evolutive SFP'!H29+'Evolutive SFP'!H32+'Evolutive SFP'!H33+'Evolutive SFP'!H34+'Evolutive SFP'!H35+'Evolutive SFP'!H36) -> 0.25075064 | K12: =('Evolutive SFP'!I4)/('Evolutive SFP'!I28+'Evolutive SFP'!I29+'Evolutive SFP'!I32+'Evolutive SFP'!I33+'Evolutive SFP'!I34+'Evolutive SFP'!I35+'Evolutive SFP'!I36) -> 0.38074033 | ... AJ12: =('Evolutive SFP'!AH4)/('Evolutive SFP'!AH28+'Evolutive SFP'!AH29+'Evolutive SFP'!AH32+'Evolutive SFP'!AH33+'Evolutive SFP'!AH34+'Evolutive SFP'!AH35+'Evolutive SFP'!AH36) -> 0.48793547
B13: T/LIQ ratio | D13: ='Evolutive SFP'!B4/('Evolutive SFP'!B31+'Evolutive SFP'!B36) -> 0.14915539 | E13: ='Evolutive SFP'!C4/('Evolutive SFP'!C31+'Evolutive SFP'!C36) -> 0.14798231 | F13: ='Evolutive SFP'!D4/('Evolutive SFP'!D31+'Evolutive SFP'!D36) -> 0.14596198 | G13: ='Evolutive SFP'!E4/('Evolutive SFP'!E31+'Evolutive SFP'!E36) -> 0.13702372 | H13: ='Evolutive SFP'!F4/('Evolutive SFP'!F31+'Evolutive SFP'!F36) -> 0.074955459 | I13: ='Evolutive SFP'!G4/('Evolutive SFP'!G31+'Evolutive SFP'!G36) -> 0.095027739 | J13: ='Evolutive SFP'!H4/('Evolutive SFP'!H31+'Evolutive SFP'!H36) -> 0.065053832 | K13: ='Evolutive SFP'!I4/('Evolutive SFP'!I31+'Evolutive SFP'!I36) -> 0.10223895 | ... AJ13: ='Evolutive SFP'!AH4/('Evolutive SFP'!AH31+'Evolutive SFP'!AH36) -> 0.13397354
B14: EB ratio | C14: Max 25% | D14: ='Evolutive SFP'!B37/'Evolutive SFP'!B27 -> 0.015175035 | E14: ='Evolutive SFP'!C37/'Evolutive SFP'!C27 -> 0.070071212 | F14: ='Evolutive SFP'!D37/'Evolutive SFP'!D27 -> 0.070570447 | G14: ='Evolutive SFP'!E37/'Evolutive SFP'!E27 -> 0.066034839 | H14: ='Evolutive SFP'!F37/'Evolutive SFP'!F27 -> 0.061359021 | I14: ='Evolutive SFP'!G37/'Evolutive SFP'!G27 -> 0.05820221 | J14: ='Evolutive SFP'!H37/'Evolutive SFP'!H27 -> 0.054638522 | K14: ='Evolutive SFP'!I37/'Evolutive SFP'!I27 -> 0.051175773 | ... AJ14: ='Evolutive SFP'!AH37/'Evolutive SFP'!AH27 -> 0.080201712
B15: LA to TA ratio | D15: ='Evolutive SFP'!B4/'Evolutive SFP'!B27 -> 0.12821992 | E15: ='Evolutive SFP'!C4/'Evolutive SFP'!C27 -> 0.10397515 | F15: ='Evolutive SFP'!D4/'Evolutive SFP'!D27 -> 0.10879202 | G15: ='Evolutive SFP'!E4/'Evolutive SFP'!E27 -> 0.099612431 | H15: ='Evolutive SFP'!F4/'Evolutive SFP'!F27 -> 0.054740729 | I15: ='Evolutive SFP'!G4/'Evolutive SFP'!G27 -> 0.069061819 | J15: ='Evolutive SFP'!H4/'Evolutive SFP'!H27 -> 0.047089256 | K15: ='Evolutive SFP'!I4/'Evolutive SFP'!I27 -> 0.073932183 | ... AJ15: ='Evolutive SFP'!AH4/'Evolutive SFP'!AH27 -> 0.093280181
A16: STRUCTURE | B16: NEA ratio | C16: Max 10% | D16: =('Evolutive SFP'!B7+'Evolutive SFP'!B21)/'Evolutive SFP'!B27 -> 0.12101375 | E16: =('Evolutive SFP'!C7+'Evolutive SFP'!C21)/'Evolutive SFP'!C27 -> 0.092978507 | F16: =('Evolutive SFP'!D7+'Evolutive SFP'!D21)/'Evolutive SFP'!D27 -> 0.03924726 | G16: =('Evolutive SFP'!E7+'Evolutive SFP'!E21)/'Evolutive SFP'!E27 -> 0.037199709 | H16: =('Evolutive SFP'!F7+'Evolutive SFP'!F21)/'Evolutive SFP'!F27 -> 0.10426899 | I16: =('Evolutive SFP'!G7+'Evolutive SFP'!G21)/'Evolutive SFP'!G27 -> 0.09247246 | J16: =('Evolutive SFP'!H7+'Evolutive SFP'!H21)/'Evolutive SFP'!H27 -> 0.11396338 | K16: =('Evolutive SFP'!I7+'Evolutive SFP'!I21)/'Evolutive SFP'!I27 -> 0.078373367 | ... AJ16: =('Evolutive SFP'!AH7+'Evolutive SFP'!AH21)/'Evolutive SFP'!AH27 -> 0.31248256
B17: LB ratio | C17: Max 5% | D17: ='Evolutive SFP'!B21/'Evolutive SFP'!B27 -> 0.032278671 | E17: ='Evolutive SFP'!C21/'Evolutive SFP'!C27 -> 0.020791445 | F17: ='Evolutive SFP'!D21/'Evolutive SFP'!D27 -> 0.01970122 | G17: ='Evolutive SFP'!E21/'Evolutive SFP'!E27 -> 0.019776856 | H17: ='Evolutive SFP'!F21/'Evolutive SFP'!F27 -> 0.019330926 | I17: ='Evolutive SFP'!G21/'Evolutive SFP'!G27 -> 0.019870722 | J17: ='Evolutive SFP'!H21/'Evolutive SFP'!H27 -> 0.020313096 | K17: ='Evolutive SFP'!I21/'Evolutive SFP'!I27 -> 0.023108189 | ... AJ17: ='Evolutive SFP'!AH21/'Evolutive SFP'!AH27 -> 0.2881529
B18: PI to Deposit ratio | C18: Max 5% | D18: ='Evolutive SFP'!B13/'Evolutive SFP'!B31 -> 0.0036721969 | E18: ='Evolutive SFP'!C13/'Evolutive SFP'!C31 -> 0.0028952531 | F18: ='Evolutive SFP'!D13/'Evolutive SFP'!D31 -> 0.023502968 | G18: ='Evolutive SFP'!E13/'Evolutive SFP'!E31 -> 0.058252552 | H18: ='Evolutive SFP'!F13/'Evolutive SFP'!F31 -> 0.056625766 | I18: ='Evolutive SFP'!G13/'Evolutive SFP'!G31 -> 0.056698471 | J18: ='Evolutive SFP'!H13/'Evolutive SFP'!H31 -> 0.05707127 | K18: ='Evolutive SFP'!I13/'Evolutive SFP'!I31 -> 0.056449815 | ... AJ18: ='Evolutive SFP'!AH13/'Evolutive SFP'!AH31 -> 0
B19: PI to CC ratio | C19: Max 40% | D19: ='Evolutive SFP'!B13/(CAELS!D3*1000000) -> 0.030948443 | E19: ='Evolutive SFP'!C13/(CAELS!E3*1000000) -> 0.01195437 | F19: ='Evolutive SFP'!D13/(CAELS!F3*1000000) -> 0.091814675 | G19: ='Evolutive SFP'!E13/(CAELS!G3*1000000) -> 0.22492835 | H19: ='Evolutive SFP'!F13/(CAELS!H3*1000000) -> 0.21995091 | I19: ='Evolutive SFP'!G13/(CAELS!I3*1000000) -> 0.21320318 | J19: ='Evolutive SFP'!H13/(CAELS!J3*1000000) -> 0.21076268 | K19: ='Evolutive SFP'!I13/(CAELS!K3*1000000) -> 0.21116029 | ... AJ19: ='Evolutive SFP'!AH13/(CAELS!AJ3*1000000) -> 0
B20: Gross loans/TA | D20: ='Evolutive SFP'!B15/'Evolutive SFP'!B27 -> 0.74763912 | E20: ='Evolutive SFP'!C15/'Evolutive SFP'!C27 -> 0.80420869 | F20: ='Evolutive SFP'!D15/'Evolutive SFP'!D27 -> 0.85098594 | G20: ='Evolutive SFP'!E15/'Evolutive SFP'!E27 -> 0.83896397 | H20: ='Evolutive SFP'!F15/'Evolutive SFP'!F27 -> 0.81819878 | I20: ='Evolutive SFP'!G15/'Evolutive SFP'!G27 -> 0.81655086 | J20: ='Evolutive SFP'!H15/'Evolutive SFP'!H27 -> 0.81770107 | K20: ='Evolutive SFP'!I15/'Evolutive SFP'!I27 -> 0.8274493 | ... AJ20: ='Evolutive SFP'!AH15/'Evolutive SFP'!AH27 -> 0.55917538
A21: FUNDING MIX | B21: Total Deposits/Total Assets | D21: ='Evolutive SFP'!B31/'Evolutive SFP'!B27 -> 0.85159483 | E21: ='Evolutive SFP'!C31/'Evolutive SFP'!C27 -> 0.70127473 | F21: ='Evolutive SFP'!D31/'Evolutive SFP'!D27 -> 0.71501478 | G21: ='Evolutive SFP'!E31/'Evolutive SFP'!E27 -> 0.69888986 | H21: ='Evolutive SFP'!F31/'Evolutive SFP'!F27 -> 0.70078432 | I21: ='Evolutive SFP'!G31/'Evolutive SFP'!G27 -> 0.69807328 | J21: ='Evolutive SFP'!H31/'Evolutive SFP'!H27 -> 0.69420379 | K21: ='Evolutive SFP'!I31/'Evolutive SFP'!I27 -> 0.69556897 | ... AJ21: ='Evolutive SFP'!AH31/'Evolutive SFP'!AH27 -> 0.66311511
B22: BOSA Deposits/Total Assets | D22: ='Evolutive SFP'!B30/'Evolutive SFP'!B27 -> 0.74257768 | E22: ='Evolutive SFP'!C30/'Evolutive SFP'!C27 -> 0.5239538 | F22: ='Evolutive SFP'!D30/'Evolutive SFP'!D27 -> 0.55562231 | G22: ='Evolutive SFP'!E30/'Evolutive SFP'!E27 -> 0.55301322 | H22: ='Evolutive SFP'!F30/'Evolutive SFP'!F27 -> 0.53958138 | I22: ='Evolutive SFP'!G30/'Evolutive SFP'!G27 -> 0.54262735 | J22: ='Evolutive SFP'!H30/'Evolutive SFP'!H27 -> 0.54613436 | K22: ='Evolutive SFP'!I30/'Evolutive SFP'!I27 -> 0.54545207 | ... AJ22: ='Evolutive SFP'!AH30/'Evolutive SFP'!AH27 -> 0.5225592
B23: FOSA Deposits/Total Assets | D23: =('Evolutive SFP'!B28+'Evolutive SFP'!B29)/'Evolutive SFP'!B27 -> 0.10901715 | E23: =('Evolutive SFP'!C28+'Evolutive SFP'!C29)/'Evolutive SFP'!C27 -> 0.17732094 | F23: =('Evolutive SFP'!D28+'Evolutive SFP'!D29)/'Evolutive SFP'!D27 -> 0.15939248 | G23: =('Evolutive SFP'!E28+'Evolutive SFP'!E29)/'Evolutive SFP'!E27 -> 0.14587664 | H23: =('Evolutive SFP'!F28+'Evolutive SFP'!F29)/'Evolutive SFP'!F27 -> 0.16120294 | I23: =('Evolutive SFP'!G28+'Evolutive SFP'!G29)/'Evolutive SFP'!G27 -> 0.15544593 | J23: =('Evolutive SFP'!H28+'Evolutive SFP'!H29)/'Evolutive SFP'!H27 -> 0.14806943 | K23: =('Evolutive SFP'!I28+'Evolutive SFP'!I29)/'Evolutive SFP'!I27 -> 0.1501169 | ... AJ23: =('Evolutive SFP'!AH28+'Evolutive SFP'!AH29)/'Evolutive SFP'!AH27 -> 0.14055591
A24: GROWTH RATIOS | B24: Total Assets | D24: =(Financials!C4-Financials!B4)/Financials!B4 -> #VALUE! | E24: =(Financials!D4-Financials!C4)/Financials!C4 -> 7.1910528 | F24: =(Financials!E4-Financials!D4)/Financials!D4 -> -0.04985513 | G24: =(Financials!F4-Financials!E4)/Financials!E4 -> 0.011693094 | H24: =(Financials!G4-Financials!F4)/Financials!F4 -> 0.025947726 | I24: =(Financials!H4-Financials!G4)/Financials!G4 -> 0.0025963193 | J24: =(Financials!I4-Financials!H4)/Financials!H4 -> -0.0009945984 | K24: =(Financials!J4-Financials!I4)/Financials!I4 -> 0.0090247102 | ... AJ24: =(Financials!AI4-Financials!AH4)/Financials!AH4 -> -0.00060551898
B25: Total Deposits | C25: =IF(CAELS!D16<6%,"1",_xludf.IF) -> #NAME? | D25: =Financials!D5/Financials!C5-1 -> 5.7452011 | E25: =Financials!E5/Financials!D5-1 -> -0.03123898 | F25: =Financials!F5/Financials!E5-1 -> -0.011122482 | G25: =Financials!G5/Financials!F5-1 -> 0.028728728 | H25: =Financials!H5/Financials!G5-1 -> -0.0012823045 | I25: =Financials!I5/Financials!H5-1 -> -0.0065321727 | J25: =Financials!J5/Financials!I5-1 -> 0.011008989 | K25: =Financials!K5/Financials!J5-1 -> 0.0036501741 | ... AJ25: =Financials!AJ5/Financials!AI5-1 -> -0.00072616341
B26: BOSA Deposits | D26: =Financials!D6/Financials!C6-1 -> 4.7795075 | E26: =Financials!E6/Financials!D6-1 -> 0.0075729709 | F26: =Financials!F6/Financials!E6-1 -> 0.0069423977 | G26: =Financials!G6/Financials!F6-1 -> 0.0010290255 | H26: =Financials!H6/Financials!G6-1 -> 0.0082560458 | I26: =Financials!I6/Financials!H6-1 -> 0.0054619897 | J26: =Financials!J6/Financials!I6-1 -> 0.0077641315 | K26: =Financials!K6/Financials!J6-1 -> -0.0017677871 | ... AJ26: =Financials!AJ6/Financials!AI6-1 -> 0.004888699
B27: FOSA Deposits | D27: =Financials!D7/Financials!C7-1 -> 12.323088 | E27: =Financials!E7/Financials!D7-1 -> -0.14592182 | F27: =Financials!F7/Financials!E7-1 -> -0.074094402 | G27: =Financials!G7/Financials!F7-1 -> 0.13373733 | H27: =Financials!H7/Financials!G7-1 -> -0.033209242 | I27: =Financials!I7/Financials!H7-1 -> -0.048401141 | J27: =Financials!J7/Financials!I7-1 -> 0.022977211 | K27: =Financials!K7/Financials!J7-1 -> 0.02333642 | ... AJ27: =Financials!AJ7/Financials!AI7-1 -> -0.021601116
B28: Total Loans & advances | D28: =Financials!D31/Financials!C31-1 -> 7.8108229 | E28: =Financials!E31/Financials!D31-1 -> 0.0054105813 | F28: =Financials!F31/Financials!E31-1 -> -0.0025992013 | G28: =Financials!G31/Financials!F31-1 -> 0.00055450387 | H28: =Financials!H31/Financials!G31-1 -> 0.00057700635 | I28: =Financials!I31/Financials!H31-1 -> 0.00041262136 | J28: =Financials!J31/Financials!I31-1 -> 0.021053796 | K28: =Financials!K31/Financials!J31-1 -> 0.0032054341 | ... AJ28: =Financials!AJ31/Financials!AI31-1 -> 0.0050171369
B29: Core capital | D29: =Financials!D11/Financials!C11-1 -> 13.368541 | E29: =Financials!E11/Financials!D11-1 -> -0.058836899 | F29: =Financials!F11/Financials!E11-1 -> -0.14617274 | G29: =Financials!G11/Financials!F11-1 -> 0.029197023 | H29: =Financials!H11/Financials!G11-1 -> 0.04057348 | I29: =Financials!I11/Financials!H11-1 -> 0.014717133 | J29: =Financials!J11/Financials!I11-1 -> -0.0023858546 | K29: =Financials!K11/Financials!J11-1 -> -0.0032200379 | ... AJ29: =Financials!AJ11/Financials!AI11-1 -> 0.0067774572
B30: Turnover | D30: =Financials!D37/Financials!C37-1 -> 8121.6512 | E30: =Financials!E37/Financials!D37-1 -> -0.91500302 | F30: =Financials!F37/Financials!E37-1 -> 1.0383982 | G30: =Financials!G37/Financials!F37-1 -> 0.62135045 | H30: =Financials!H37/Financials!G37-1 -> 0.41387489 | I30: =Financials!I37/Financials!H37-1 -> 0.26141317 | J30: =Financials!J37/Financials!I37-1 -> 0.22934197 | K30: =Financials!K37/Financials!J37-1 -> 0.22593608 | ... AJ30: =Financials!AJ37/Financials!AI37-1 -> 0.19876413
B31: Membership
B32: Expenses | D32: ='Evolutitve SCI'!E39/'Evolutitve SCI'!B39-1 -> 1189.1696 | E32: ='Evolutitve SCI'!F39/'Evolutitve SCI'!C39-1 -> -0.79413947 | F32: ='Evolutitve SCI'!G39/'Evolutitve SCI'!D39-1 -> 4.645322 | G32: ='Evolutitve SCI'!H39/'Evolutitve SCI'!E39-1 -> 1.6168104 | H32: ='Evolutitve SCI'!I39/'Evolutitve SCI'!F39-1 -> 1.3875384 | I32: ='Evolutitve SCI'!I39/'Evolutitve SCI'!G39-1 -> 0.82769769 | J32: ='Evolutitve SCI'!I39/'Evolutitve SCI'!H39-1 -> 0.37087528 | K32: ='Evolutitve SCI'!J39/'Evolutitve SCI'!I39-1 -> 0.33850936 | L32: ='Evolutitve SCI'!K39/'Evolutitve SCI'!J39-1 -> 0.17711123 | M32: ='Evolutitve SCI'!L39/'Evolutitve SCI'!K39-1 -> 0.14570806 | N32: ='Evolutitve SCI'!M39/'Evolutitve SCI'!L39-1 -> 0.12330995 | O32: ='Evolutitve SCI'!N39/'Evolutitve SCI'!M39-1 -> 0.12486047 | P32: ='Evolutitve SCI'!O39/'Evolutitve SCI'!N39-1 -> 0.17680416 | Q32: ='Evolutitve SCI'!P39/'Evolutitve SCI'!O39-1 -> 0 | ... AJ32: ='Evolutitve SCI'!AI39/'Evolutitve SCI'!AH39-1 -> #DIV/0!
A33: Efficiency Ratios | B33: FinCost-Deposits/Avg Deposits | H33: =Financials!G44/('Evolutive SFP'!B30+'Evolutive SFP'!F30)/2 -> 0.0033263245 | K33: =Financials!J44/('Evolutive SFP'!F30+'Evolutive SFP'!I30)/2 -> 0.0076225424 | L33: =Financials!K44/('Evolutive SFP'!I30+'Evolutive SFP'!J30)/2 -> 0.011445004 | M33: =Financials!L44/('Evolutive SFP'!J30+'Evolutive SFP'!K30)/2 -> 0.014118691 | N33: =Financials!M44/('Evolutive SFP'!K30+'Evolutive SFP'!L30)/2 -> 0.016660959 | O33: =Financials!N44/('Evolutive SFP'!L30+'Evolutive SFP'!M30)/2 -> 0.018840822 | P33: =Financials!O44/('Evolutive SFP'!M30+'Evolutive SFP'!N30)/2 -> 0.020629302 | Q33: =Financials!P44/('Evolutive SFP'!N30+'Evolutive SFP'!O30)/2 -> 0.022279974 | R33: =Financials!Q44/('Evolutive SFP'!O30+'Evolutive SFP'!P30)/2 -> 0.026965455 | S33: =Financials!R44/('Evolutive SFP'!P30+'Evolutive SFP'!Q30)/2 -> 0.0010849961 | ... AJ33: =Financials!AI44/('Evolutive SFP'!AG30+'Evolutive SFP'!AH30)/2 -> 0.011740732
B34: FinCost-Shares/Avg Share capital | H34: =Financials!G45/('Evolutive SFP'!B39+'Evolutive SFP'!F39)/2 -> 0 | K34: =Financials!J45/('Evolutive SFP'!F39+'Evolutive SFP'!I39)/2 -> 0 | L34: =Financials!K45/('Evolutive SFP'!I39+'Evolutive SFP'!J39)/2 -> 0 | M34: =Financials!L45/('Evolutive SFP'!J39+'Evolutive SFP'!K39)/2 -> 0 | N34: =Financials!M45/('Evolutive SFP'!K39+'Evolutive SFP'!L39)/2 -> 0 | O34: =Financials!N45/('Evolutive SFP'!L39+'Evolutive SFP'!M39)/2 -> 0 | P34: =Financials!O45/('Evolutive SFP'!M39+'Evolutive SFP'!N39)/2 -> 0 | Q34: =Financials!P45/('Evolutive SFP'!N39+'Evolutive SFP'!O39)/2 -> 0 | R34: =Financials!Q45/('Evolutive SFP'!O39+'Evolutive SFP'!P39)/2 -> 0 | S34: =Financials!R45/('Evolutive SFP'!P39+'Evolutive SFP'!Q39)/2 -> 0 | ... AJ34: =Financials!AI45/('Evolutive SFP'!AG39+'Evolutive SFP'!AH39)/2 -> 0
B35: FinCost-Ext Loans/Avg Ext Loans | H35: =Financials!G46/(Financials!F31+Financials!G31)/2 -> 0.0006252851 | K35: =Financials!J46/(Financials!G31+Financials!J31)/2 -> 0.001163008 | L35: =Financials!K46/(Financials!J31+Financials!K31)/2 -> 0.0013066954 | M35: =Financials!L46/(Financials!K31+Financials!L31)/2 -> 0.0014566496 | N35: =Financials!M46/(Financials!L31+Financials!M31)/2 -> 0.0015723534 | O35: =Financials!N46/(Financials!M31+Financials!N31)/2 -> 0.001809724 | P35: =Financials!O46/(Financials!N31+Financials!O31)/2 -> 0.0020519124 | Q35: =Financials!P46/(Financials!O31+Financials!P31)/2 -> 0.0027175206 | R35: =Financials!Q46/(Financials!P31+Financials!Q31)/2 -> 0.0026751486 | S35: =Financials!R46/(Financials!Q31+Financials!R31)/2 -> 0.00025504213 | ... AJ35: =Financials!AI46/(Financials!AH31+Financials!AI31)/2 -> 0.0023768716
B36: OpEx/Average Total Assets | H36: =Financials!G47/(Financials!F4+Financials!G4)/2 -> 0.0023897786 | K36: =Financials!J47/(Financials!G4+Financials!J4)/2 -> 0.0045074093 | L36: =Financials!K47/(Financials!J4+Financials!K4)/2 -> 0.0053875927 | M36: =Financials!L47/(Financials!K4+Financials!L4)/2 -> 0.0060690546 | N36: =Financials!M47/(Financials!L4+Financials!M4)/2 -> 0.0065947413 | O36: =Financials!N47/(Financials!M4+Financials!N4)/2 -> 0.0071175217 | P36: =Financials!O47/(Financials!N4+Financials!O4)/2 -> 0.0081057274 | Q36: =Financials!P47/(Financials!O4+Financials!P4)/2 -> 0.0083336705 | R36: =Financials!Q47/(Financials!P4+Financials!Q4)/2 -> 0.0081680407 | S36: =Financials!R47/(Financials!Q4+Financials!R4)/2 -> 0.00066413579 | ... AJ36: =Financials!AI47/(Financials!AH4+Financials!AI4)/2 -> 0.0052031646
B37: Opex/Turnover | H37: =Financials!G47/Financials!G37 -> 0.34563582 | K37: =Financials!J47/Financials!J37 -> 0.30274569 | L37: =Financials!K47/Financials!K37 -> 0.29782659 | M37: =Financials!L47/Financials!L37 -> 0.29187701 | N37: =Financials!M47/Financials!M37 -> 0.28592134 | O37: =Financials!N47/Financials!N37 -> 0.28181049 | P37: =Financials!O47/Financials!O37 -> 0.29351135 | Q37: =Financials!P47/Financials!P37 -> 0.27962389 | R37: =Financials!Q47/Financials!Q37 -> 0.27962389 | ... AJ37: =Financials!AI47/Financials!AI37 -> 0.36368547
B38: Avge yield on Net loans | H38: =Financials!G38/('Evolutive SFP'!F14+'Evolutive SFP'!B14)/2 -> 0.011751293 | K38: =Financials!J38/('Evolutive SFP'!I14+'Evolutive SFP'!F14)/2 -> 0.014608535 | L38: =Financials!K38/('Evolutive SFP'!J14+'Evolutive SFP'!I14)/2 -> 0.017881371 | M38: =Financials!L38/('Evolutive SFP'!K14+'Evolutive SFP'!J14)/2 -> 0.020795057 | N38: =Financials!M38/('Evolutive SFP'!L14+'Evolutive SFP'!K14)/2 -> 0.023451566 | O38: =Financials!N38/('Evolutive SFP'!M14+'Evolutive SFP'!L14)/2 -> 0.026003926 | P38: =Financials!O38/('Evolutive SFP'!N14+'Evolutive SFP'!M14)/2 -> 0.028649998 | Q38: =Financials!P38/('Evolutive SFP'!O14+'Evolutive SFP'!N14)/2 -> 0.031198532 | R38: =Financials!Q38/('Evolutive SFP'!P14+'Evolutive SFP'!O14)/2 -> 0.030691898 | S38: =Financials!R38/('Evolutive SFP'!Q14+'Evolutive SFP'!P14)/2 -> 0.0025900026 | ... AJ38: =Financials!AI38/('Evolutive SFP'!AH14+'Evolutive SFP'!AG14)/2 -> 0.021734463
B39: Avge yield on Gross loans | H39: =Financials!G37/('Evolutive SFP'!F15+'Evolutive SFP'!B15)/2 -> 0.014991397 | K39: =Financials!J37/('Evolutive SFP'!I15+'Evolutive SFP'!F15)/2 -> 0.018093773 | L39: =Financials!K37/('Evolutive SFP'!J15+'Evolutive SFP'!I15)/2 -> 0.021907266 | M39: =Financials!L37/('Evolutive SFP'!K15+'Evolutive SFP'!J15)/2 -> 0.025297608 | N39: =Financials!M37/('Evolutive SFP'!L15+'Evolutive SFP'!K15)/2 -> 0.028305699 | O39: =Financials!N37/('Evolutive SFP'!M15+'Evolutive SFP'!L15)/2 -> 0.031239384 | P39: =Financials!O37/('Evolutive SFP'!N15+'Evolutive SFP'!M15)/2 -> 0.034198164 | Q39: =Financials!P37/('Evolutive SFP'!O15+'Evolutive SFP'!N15)/2 -> 0.037249949 | R39: =Financials!Q37/('Evolutive SFP'!P15+'Evolutive SFP'!O15)/2 -> 0.036669142 | S39: =Financials!R37/('Evolutive SFP'!Q15+'Evolutive SFP'!P15)/2 -> 0.0029737194 | ... AJ39: =Financials!AI37/('Evolutive SFP'!AH15+'Evolutive SFP'!AG15)/2 -> 0.025664297
A41: ALL/Average Gross Loan portfolio

Sheet Financials
B1: SOLUTION Sacco Financial Performance
B2: Year | C2: 2010 Audited | D2: 2020 Audited | E2: 44197 | F2: 44229 | G2: 44258 | H2: 44290 | I2: 44321 | J2: 44353 | K2: 44384 | L2: 44416 | M2: 44448 | N2: 44479 | O2: 44511 | P2: 44542 | Q2: audited 2021 | R2: 44575 | S2: 44607 | T2: 44636 | U2: 44668 | V2: 44699 | W2: 44731 | X2: 44762 | Y2: 44794 | Z2: 44826 | AA2: 44857 | AB2: 44889 | AC2: 44920 | AD2: Audited 2022 | AE2: 44953 | AF2: 44984 | AG2: 45012 | AH2: 45043 | AI2: 45073 | AJ2: 45104 | AK2: 45134 | AL2: 45165 | AM2: 45196 | AN2: 45226 | AO2: 45257
A3: 1 | B3: Membership
A4: 2 | B4: Total Assets | C4: ='Evolutive SFP'!B27 -> 151015729 | D4: ='Evolutive SFP'!C27 -> 1236977812 | E4: ='Evolutive SFP'!D27 -> 1175308122 | F4: ='Evolutive SFP'!E27 -> 1189051110 | G4: ='Evolutive SFP'!F27 -> 1219904282 | H4: ='Evolutive SFP'!G27 -> 1223071543 | I4: ='Evolutive SFP'!H27 -> 1221855078 | J4: ='Evolutive SFP'!I27 -> 1232881966 | ... AX4: ='Evolutive SFP'!AW27 -> 0
A5: 3 | B5: Total Deposits | C5: ='Evolutive SFP'!B31 -> 128604214 | D5: ='Evolutive SFP'!C31 -> 867461287 | E5: ='Evolutive SFP'!D31 -> 840362681 | F5: ='Evolutive SFP'!E31 -> 831015762 | G5: ='Evolutive SFP'!F31 -> 854889788 | H5: ='Evolutive SFP'!G31 -> 853793559 | I5: ='Evolutive SFP'!H31 -> 848216432 | J5: ='Evolutive SFP'!I31 -> 857554437 | ... AX5: ='Evolutive SFP'!AW31 -> 0
A6: 3.1 | B6: Deposits-Members(BOSA) | C6: ='Evolutive SFP'!B30 -> 112140909 | D6: ='Evolutive SFP'!C30 -> 648119220 | E6: ='Evolutive SFP'!D30 -> 653027408 | F6: ='Evolutive SFP'!E30 -> 657560984 | G6: ='Evolutive SFP'!F30 -> 658237631 | H6: ='Evolutive SFP'!G30 -> 663672071 | I6: ='Evolutive SFP'!H30 -> 667297041 | J6: ='Evolutive SFP'!I30 -> 672478023 | ... AX6: ='Evolutive SFP'!AW30 -> 0
A7: 3.2 | B7: Deposits-Customers(FOSA) | C7: =('Evolutive SFP'!B28+'Evolutive SFP'!B29) -> 16463305 | D7: =('Evolutive SFP'!C28+'Evolutive SFP'!C29) -> 219342067 | E7: =('Evolutive SFP'!D28+'Evolutive SFP'!D29) -> 187335273 | F7: =('Evolutive SFP'!E28+'Evolutive SFP'!E29) -> 173454778 | G7: =('Evolutive SFP'!F28+'Evolutive SFP'!F29) -> 196652157 | H7: =('Evolutive SFP'!G28+'Evolutive SFP'!G29) -> 190121488 | I7: =('Evolutive SFP'!H28+'Evolutive SFP'!H29) -> 180919391 | J7: =('Evolutive SFP'!I28+'Evolutive SFP'!I29) -> 185076414 | ... AX7: =('Evolutive SFP'!AW28+'Evolutive SFP'!AW29) -> 0
A8: 4 | B8: External Borrowing | C8: ='Evolutive SFP'!B37 -> 2291669 | D8: ='Evolutive SFP'!C37 -> 86676534 | E8: ='Evolutive SFP'!D37 -> 82942020 | F8: ='Evolutive SFP'!E37 -> 78518799 | G8: ='Evolutive SFP'!F37 -> 74852133 | H8: ='Evolutive SFP'!G37 -> 71185467 | I8: ='Evolutive SFP'!H37 -> 66760355 | J8: ='Evolutive SFP'!I37 -> 63093688 | ... AX8: ='Evolutive SFP'!AW37 -> 0
A10: 5 | B10: Share capital and Reserves
A11: 5.1 | B11: Core Capital | C11: =C14-C22-C25 -> 14446887 | D11: =D14-D22-D26 -> 207580690 | E11: =E14-E22-E26 -> 195367286 | F11: =F14-F22-F26 -> 166809915 | G11: =G14-G22-G26 -> 171680268 | H11: =H14-H22-H26 -> 178645934 | I11: =I14-I22-I26 -> 181275090 | J11: =J14-J22-J26 -> 180842594 | K11: =K14-K22-K26 -> 180260274 | ... AX11: =AX14-AX22-AX26 -> 0
A12: 5.2 | B12: Institutional Capital | C12: =C11-C15 -> 3952190 | D12: =D11-D15 -> 118168564 | E12: =E11-E15 -> 105612514 | F12: =F11-F15 -> 76769773 | G12: =G11-G15 -> 81458836 | H12: =H11-H15 -> 88004849 | I12: =I11-I15 -> 90285277 | J12: =J11-J15 -> 89517222 | ... AX12: =AX11-AX15 -> 0
A14: 5.3 | B14: Total Capital | C14: =C15+C16+C17+C18+C19+C20+C21 -> 14919147 | D14: =D15+D16+D17+D18+D19+D20+D21 -> 210092210 | E14: =E15+E16+E17+E18+E19+E20+E21 -> 215118303 | F14: =F15+F16+F17+F18+F19+F20+F21 -> 215218704 | G14: =G15+G16+G17+G18+G19+G20+G21 -> 220089057 | H14: =H15+H16+H17+H18+H19+H20+H21 -> 227054723 | I14: =I15+I16+I17+I18+I19+I20+I21 -> 229683879 | J14: =J15+J16+J17+J18+J19+J20+J21 -> 229251383 | ... AX14: =AX15+AX16+AX17+AX18+AX19+AX20+AX21 -> 0
A15: 5.3.1 | B15: Members Share Capital | C15: ='Evolutive SFP'!B39 -> 10494697 | D15: ='Evolutive SFP'!C39 -> 89412126 | E15: ='Evolutive SFP'!D39 -> 89754772 | F15: ='Evolutive SFP'!E39 -> 90040142 | G15: ='Evolutive SFP'!F39 -> 90221432 | H15: ='Evolutive SFP'!G39 -> 90641085 | I15: ='Evolutive SFP'!H39 -> 90989813 | J15: ='Evolutive SFP'!I39 -> 91325372 | ... AX15: ='Evolutive SFP'!AW39 -> 0
A16: 5.3.2 | B16: Entrance Fees
A17: 5.3.3 | B17: Retained Earnings | C17: ='Evolutive SFP'!B41 -> 351220 | D17: ='Evolutive SFP'!C41 -> 60964231 | E17: ='Evolutive SFP'!D41 -> 64270660 | F17: ='Evolutive SFP'!E41 -> 63291409 | G17: ='Evolutive SFP'!F41 -> 63291409 | H17: ='Evolutive SFP'!G41 -> 63291409 | I17: ='Evolutive SFP'!H41 -> 63291409 | J17: ='Evolutive SFP'!I41 -> 63291409 | ... AX17: ='Evolutive SFP'!AW41 -> 0
A18: 5.3.4 | B18: Appropriation Account | C18: ='Evolutive SFP'!B42 -> 3541956 | D18: ='Evolutive SFP'!C42 -> 2327178 | E18: ='Evolutive SFP'!D42 -> 4054484 | F18: ='Evolutive SFP'!E42 -> 4498478 | G18: ='Evolutive SFP'!F42 -> 9187541 | H18: ='Evolutive SFP'!G42 -> 15733554 | I18: ='Evolutive SFP'!H42 -> 18013982 | J18: ='Evolutive SFP'!I42 -> 17245927 | ... AX18: ='Evolutive SFP'!AW42 -> 0
A19: 5.3.5 | B19: Statutory Reserves | C19: ='Evolutive SFP'!B43 -> 531274 | D19: ='Evolutive SFP'!C43 -> 17513072 | E19: ='Evolutive SFP'!D43 -> 17162784 | F19: ='Evolutive SFP'!E43 -> 17513072 | G19: ='Evolutive SFP'!F43 -> 17513072 | H19: ='Evolutive SFP'!G43 -> 17513072 | I19: ='Evolutive SFP'!H43 -> 17513072 | J19: ='Evolutive SFP'!I43 -> 17513072 | ... AX19: ='Evolutive SFP'!AW43 -> 0
A20: 5.3.6 | B20: Capital Reserves | C20: =('Evolutive SFP'!B44) -> 0 | D20: =('Evolutive SFP'!C44) -> 39875603 | E20: =('Evolutive SFP'!D44) -> 39875603 | F20: =('Evolutive SFP'!E44) -> 39875603 | G20: =('Evolutive SFP'!F44) -> 39875603 | H20: =('Evolutive SFP'!G44) -> 39875603 | I20: =('Evolutive SFP'!H44) -> 39875603 | J20: =('Evolutive SFP'!I44) -> 39875603 | ... AX20: =('Evolutive SFP'!AW44) -> 0
A21: 5.3.7 | B21: Supplementary Capital & reserves | C21: =C22+C23 -> 0 | D21: =D22+D23 -> 0 | E21: =E22+E23 -> 0 | F21: =F22+F23 -> 0 | G21: =G22+G23 -> 0 | H21: =H22+H23 -> 0 | I21: =I22+I23 -> 0 | J21: =J22+J23 -> 0 | ... AX21: =AX22+AX23 -> 0
A22: a | B22: Proposed Dividends | C22: ='Evolutive SFP'!B46 -> 0 | D22: ='Evolutive SFP'!C46 -> 0 | E22: ='Evolutive SFP'!D46 -> 0 | F22: ='Evolutive SFP'!E46 -> 0 | G22: ='Evolutive SFP'!F46 -> 0 | H22: ='Evolutive SFP'!G46 -> 0 | I22: ='Evolutive SFP'!H46 -> 0 | J22: ='Evolutive SFP'!I46 -> 0 | ... AX22: ='Evolutive SFP'!AW46 -> 0
A23: b | B23: Risk Mgt Fund
A25: 6 | B25: Investments | C25: =C26+C27+C28 -> 472260 | D25: =D26+D27+D28 -> 48158789 | E25: =E26+E27+E28 -> 51742253 | F25: =F26+F27+F28 -> 80400025 | G25: =G26+G27+G28 -> 80400025 | H25: =H26+H27+H28 -> 80400025 | I25: =I26+I27+I28 -> 80556471 | J25: =J26+J27+J28 -> 80556471 | ... AX25: =AX26+AX27+AX28 -> 0
A26: 6.1 | B26: Shares in Kusco,CIC,Coop Bank | C26: ='Evolutive SFP'!B13 -> 472260 | D26: ='Evolutive SFP'!C13 -> 2511520 | E26: ='Evolutive SFP'!D13 -> 19751017 | F26: ='Evolutive SFP'!E13 -> 48408789 | G26: ='Evolutive SFP'!F13 -> 48408789 | H26: ='Evolutive SFP'!G13 -> 48408789 | I26: ='Evolutive SFP'!H13 -> 48408789 | J26: ='Evolutive SFP'!I13 -> 48408789 | ... AX26: ='Evolutive SFP'!AW13 -> 0
A27: 6.2 | B27: Equity Investments (at cost) | C27: ='Evolutive SFP'!B10 -> 0 | D27: ='Evolutive SFP'!C10 -> 0 | E27: ='Evolutive SFP'!D10 -> 0 | F27: ='Evolutive SFP'!E10 -> 0 | G27: ='Evolutive SFP'!F10 -> 0 | H27: ='Evolutive SFP'!G10 -> 0 | I27: ='Evolutive SFP'!H10 -> 0 | J27: ='Evolutive SFP'!I10 -> 0 | ... AX27: ='Evolutive SFP'!AW10 -> 0
A28: 6.3 | B28: Deposits in KUSCCO CFP | C28: ='Evolutive SFP'!B11 -> 0 | D28: ='Evolutive SFP'!C11 -> 45647269 | E28: ='Evolutive SFP'!D11 -> 31991236 | F28: ='Evolutive SFP'!E11 -> 31991236 | G28: ='Evolutive SFP'!F11 -> 31991236 | H28: ='Evolutive SFP'!G11 -> 31991236 | I28: ='Evolutive SFP'!H11 -> 32147682 | J28: ='Evolutive SFP'!I11 -> 32147682 | ... AX28: ='Evolutive SFP'!AW11 -> 0
A30: 7 | B30: Net Loans & Advances | C30: ='Evolutive SFP'!B14 -> 112905266 | D30: ='Evolutive SFP'!C14 -> 945191720 | E30: ='Evolutive SFP'!D14 -> 949574103 | F30: ='Evolutive SFP'!E14 -> 945974458 | G30: ='Evolutive SFP'!F14 -> 945527615 | H30: ='Evolutive SFP'!G14 -> 945103539 | I30: ='Evolutive SFP'!H14 -> 944515624 | J30: ='Evolutive SFP'!I14 -> 964550729 | ... AX30: ='Evolutive SFP'!AW14 -> 0
A31: 7.1 | B31: Gross Loans & advances | C31: ='Evolutive SFP'!B15 -> 112905266 | D31: ='Evolutive SFP'!C15 -> 994788305 | E31: ='Evolutive SFP'!D15 -> 1000170688 | F31: ='Evolutive SFP'!E15 -> 997571043 | G31: ='Evolutive SFP'!F15 -> 998124200 | H31: ='Evolutive SFP'!G15 -> 998700124 | I31: ='Evolutive SFP'!H15 -> 999112209 | J31: ='Evolutive SFP'!I15 -> 1020147314 | ... AX31: ='Evolutive SFP'!AW15 -> 0
A32: 7.2 | B32: Allowance for loan losses | C32: ='Evolutive SFP'!B16 -> 0 | D32: ='Evolutive SFP'!C16 -> 49596585 | E32: ='Evolutive SFP'!D16 -> 50596585 | F32: ='Evolutive SFP'!E16 -> 51596585 | G32: ='Evolutive SFP'!F16 -> 52596585 | H32: ='Evolutive SFP'!G16 -> 53596585 | I32: ='Evolutive SFP'!H16 -> 54596585 | J32: ='Evolutive SFP'!I16 -> 55596585 | ... AX32: ='Evolutive SFP'!AW16 -> 0
A34: 8 | B34: Non-Earning Assets | C34: ='Evolutive SFP'!B21+'Evolutive SFP'!B7 -> 18274979 | D34: ='Evolutive SFP'!C21+'Evolutive SFP'!C7 -> 115012350 | E34: ='Evolutive SFP'!D21+'Evolutive SFP'!D7 -> 46127623 | F34: ='Evolutive SFP'!E21+'Evolutive SFP'!E7 -> 44232355 | G34: ='Evolutive SFP'!F21+'Evolutive SFP'!F7 -> 127198192 | H34: ='Evolutive SFP'!G21+'Evolutive SFP'!G7 -> 113100434 | I34: ='Evolutive SFP'!H21+'Evolutive SFP'!H7 -> 139246736 | J34: ='Evolutive SFP'!I21+'Evolutive SFP'!I7 -> 96625111 | ... AX34: ='Evolutive SFP'!AW21+'Evolutive SFP'!AW7 -> 0
A35: 8.1 | B35: Property and Equipment | C35: ='Evolutive SFP'!B23 -> 4123114 | D35: ='Evolutive SFP'!C23 -> 22098514 | E35: ='Evolutive SFP'!D23 -> 18083810 | F35: ='Evolutive SFP'!E23 -> 17937047 | G35: ='Evolutive SFP'!F23 -> 18054199 | H35: ='Evolutive SFP'!G23 -> 18826000 | I35: ='Evolutive SFP'!H23 -> 18824438 | J35: ='Evolutive SFP'!I23 -> 22477624 | ... AX35: ='Evolutive SFP'!AW23 -> 0
A37: 9 | B37: Turnover | C37: =C38+C39+C40+C41 -> 14599.248 | D37: =D38+D39+D40+D41 -> 118584595 | E37: =E38+E39+E40+E41 -> 10079332 | F37: =F38+F39+F40+F41 -> 20545692 | G37: =G38+G39+G40+G41 -> 33311767 | H37: =H38+H39+H40+H41 -> 47098671 | I37: =I38+I39+I40+I41 -> 59410884 | J37: =J38+J39+J40+J41 -> 73036293 | ... AX37: =AX38+AX39+AX40+AX41 -> 0
A38: 9.1 | B38: Loan Interest | C38: ='Evolutitve SCI'!B5 -> 11945.435 | D38: ='Evolutitve SCI'!C5 -> 88458375 | E38: ='Evolutitve SCI'!D5 -> 8099005 | F38: ='Evolutitve SCI'!E5 -> 15832497 | G38: ='Evolutitve SCI'!F5 -> 24875910 | H38: ='Evolutitve SCI'!G5 -> 34583604 | I38: ='Evolutitve SCI'!H5 -> 44665750 | J38: ='Evolutitve SCI'!I5 -> 55806894 | ... AX38: ='Evolutitve SCI'!AW5 -> 0
A39: 9.2 | B39: Income from investments | C39: ='Evolutitve SCI'!B7 -> 1743.4416 | D39: ='Evolutitve SCI'!C7 -> 30126220 | E39: ='Evolutitve SCI'!D7 -> 1980327 | F39: ='Evolutitve SCI'!E7 -> 4713195 | G39: ='Evolutitve SCI'!F7 -> 8435857 | H39: ='Evolutitve SCI'!G7 -> 12515067 | I39: ='Evolutitve SCI'!H7 -> 14745134 | J39: ='Evolutitve SCI'!I7 -> 17229399 | ... AX39: ='Evolutitve SCI'!AW7 -> 0
A40: 9.3 | B40: Fees & Commissions | C40: ='Evolutitve SCI'!B6 -> 910.371 | D40: ='Evolutitve SCI'!C6 -> 0 | E40: ='Evolutitve SCI'!D6 -> 0 | F40: ='Evolutitve SCI'!E6 -> 0 | G40: ='Evolutitve SCI'!F6 -> 0 | H40: ='Evolutitve SCI'!G6 -> 0 | I40: ='Evolutitve SCI'!H6 -> 0 | J40: ='Evolutitve SCI'!I6 -> 0 | ... AX40: ='Evolutitve SCI'!AW6 -> 0
A41: 9.4 | B41: Average yield on loans
A43: 10 | B43: Financial and Operating costs | C43: =SUM(C44:C47) -> 11568.465 | D43: =SUM(D44:D47) -> #VALUE! | E43: =SUM(E44:E47) -> 4664326 | F43: =SUM(F44:F47) -> 12389017 | G43: =SUM(G44:G47) -> 19134555 | H43: =SUM(H44:H47) -> 25228157 | I43: =SUM(I44:I47) -> 33988533 | J43: =SUM(J44:J47) -> 47092828 | ... AX43: =SUM(AX44:AX47) -> 0
A44: 10.1 | B44: Interest expense on deposits | C44: ='Evolutitve SCI'!B13+'Evolutitve SCI'!B16 -> 185.36 | D44: ='Evolutitve SCI'!C13+'Evolutitve SCI'!C16 -> #VALUE! | E44: ='Evolutitve SCI'!D13+'Evolutitve SCI'!D16 -> 1043217 | F44: ='Evolutitve SCI'!E13+'Evolutitve SCI'!E16 -> 2043217 | G44: ='Evolutitve SCI'!F13+'Evolutitve SCI'!F16 -> 5125058 | H44: ='Evolutitve SCI'!G13+'Evolutitve SCI'!G16 -> 7174164 | I44: ='Evolutitve SCI'!H13+'Evolutitve SCI'!H16 -> 12251698 | J44: ='Evolutitve SCI'!I13+'Evolutitve SCI'!I16 -> 20286873 | ... AX44: ='Evolutitve SCI'!AW13+'Evolutitve SCI'!AW16 -> 0
A45: 10.2 | B45: Dividend expense on share capital | C45: ='Evolutitve SCI'!B15 -> 0 | D45: ='Evolutitve SCI'!C15 -> 0 | E45: ='Evolutitve SCI'!D15 -> 0 | F45: ='Evolutitve SCI'!E15 -> 0 | G45: ='Evolutitve SCI'!F15 -> 0 | H45: ='Evolutitve SCI'!G15 -> 0 | I45: ='Evolutitve SCI'!H15 -> 0 | J45: ='Evolutitve SCI'!I15 -> 0 | ... AX45: ='Evolutitve SCI'!AW15 -> 0
A46: 10.3 | B46: Interest expense on borrowed funds | C46: ='Evolutitve SCI'!B14 -> 363.7247 | D46: ='Evolutitve SCI'!C14 -> 14829925 | E46: ='Evolutitve SCI'!D14 -> 895320 | F46: ='Evolutitve SCI'!E14 -> 1757401 | G46: ='Evolutitve SCI'!F14 -> 2495757 | H46: ='Evolutitve SCI'!G14 -> 3274296 | I46: ='Evolutitve SCI'!H14 -> 3993847 | J46: ='Evolutitve SCI'!I14 -> 4694532 | ... AX46: ='Evolutitve SCI'!AW14 -> 0
A47: 10.4 | B47: Opperating expenses | C47: ='Evolutitve SCI'!B23 -> 11019.38 | D47: ='Evolutitve SCI'!C23 -> 41765573 | E47: ='Evolutitve SCI'!D23 -> 2725789 | F47: ='Evolutitve SCI'!E23 -> 8588399 | G47: ='Evolutitve SCI'!F23 -> 11513740 | H47: ='Evolutitve SCI'!G23 -> 14779697 | I47: ='Evolutitve SCI'!H23 -> 17742988 | J47: ='Evolutitve SCI'!I23 -> 22111423 | ... AX47: ='Evolutitve SCI'!AW23 -> 0

Sheet CAELS Rating
A2: CAELS RATINGS KINGDOM SACCO
A3: FINANCIAL SOUNDNESS INDICATORS | B3: Prude. Std | C3: 2010 Audited | D3: 2021 Audited | E3: 44197.12 | F3: 44229 | G3: 44258 | H3: 44290 | I3: 44321 | J3: 44353 | K3: 44384 | L3: 44416 | M3: 44448 | N3: 44479 | O3: 44511 | P3: 44542 | Q3: Audited 2021 | R3: 44562 | S3: 44593 | T3: 44621 | U3: 44652
A4: CAPITAL
A5: CORE CAPITAL | B5: ≥ Ksh.10M | C5: =IF(CAELS!D3>10,"1","5") -> 1 | D5: =IF(CAELS!E3>10,"1","5") -> 1 | E5: =IF(CAELS!F3>10,"1","5") -> 1 | F5: =IF(CAELS!G3>10,"1","5") -> 1 | G5: =IF(CAELS!H3>10,"1","5") -> 1 | H5: =IF(CAELS!I3>10,"1","5") -> 1 | I5: =IF(CAELS!J3>10,"1","5") -> 1 | J5: =IF(CAELS!K3>10,"1","5") -> 1 | ... U5: =IF(CAELS!V3>10,"1","5") -> 1
A6: CCA | B6: ≥ 10% | C6: =IF(CAELS!D4>20%,"1",IF(CAELS!D4>15%,"2",IF(CAELS!D4>12%,"3",IF(CAELS!D4>10%,"4","5")))) -> 4 | D6: =IF(CAELS!E4>20%,"1",IF(CAELS!E4>15%,"2",IF(CAELS!E4>12%,"3",IF(CAELS!E4>10%,"4","5")))) -> 2 | E6: =IF(CAELS!F4>20%,"1",IF(CAELS!F4>15%,"2",IF(CAELS!F4>12%,"3",IF(CAELS!F4>10%,"4","5")))) -> 2 | F6: =IF(CAELS!G4>20%,"1",IF(CAELS!G4>15%,"2",IF(CAELS!G4>12%,"3",IF(CAELS!G4>10%,"4","5")))) -> 2 | G6: =IF(CAELS!H4>20%,"1",IF(CAELS!H4>15%,"2",IF(CAELS!H4>12%,"3",IF(CAELS!H4>10%,"4","5")))) -> 2 | H6: =IF(CAELS!I4>20%,"1",IF(CAELS!I4>15%,"2",IF(CAELS!I4>12%,"3",IF(CAELS!I4>10%,"4","5")))) -> 2 | I6: =IF(CAELS!J4>20%,"1",IF(CAELS!J4>15%,"2",IF(CAELS!J4>12%,"3",IF(CAELS!J4>10%,"4","5")))) -> 2 | J6: =IF(CAELS!K4>20%,"1",IF(CAELS!K4>15%,"2",IF(CAELS!K4>12%,"3",IF(CAELS!K4>10%,"4","5")))) -> 2 | ... U6: =IF(CAELS!V4>20%,"1",IF(CAELS!V4>15%,"2",IF(CAELS!V4>12%,"3",IF(CAELS!V4>10%,"4","5")))) -> 2
A7: ICA | B7: ≥ 8% | C7: =IF(CAELS!D6>15%,"1",IF(CAELS!D6>12%,"2",IF(CAELS!D6>10%,"3",IF(CAELS!D6>8,"4","5")))) -> 5 | D7: =IF(CAELS!E6>15%,"1",IF(CAELS!E6>12%,"2",IF(CAELS!E6>10%,"3",IF(CAELS!E6>8,"4","5")))) -> 5 | E7: =IF(CAELS!F6>15%,"1",IF(CAELS!F6>12%,"2",IF(CAELS!F6>10%,"3",IF(CAELS!F6>8,"4","5")))) -> 3 | F7: =IF(CAELS!G6>15%,"1",IF(CAELS!G6>12%,"2",IF(CAELS!G6>10%,"3",IF(CAELS!G6>8,"4","5")))) -> 3 | G7: =IF(CAELS!H6>15%,"1",IF(CAELS!H6>12%,"2",IF(CAELS!H6>10%,"3",IF(CAELS!H6>8,"4","5")))) -> 3 | H7: =IF(CAELS!I6>15%,"1",IF(CAELS!I6>12%,"2",IF(CAELS!I6>10%,"3",IF(CAELS!I6>8,"4","5")))) -> 3 | I7: =IF(CAELS!J6>15%,"1",IF(CAELS!J6>12%,"2",IF(CAELS!J6>10%,"3",IF(CAELS!J6>8,"4","5")))) -> 3 | J7: =IF(CAELS!K6>15%,"1",IF(CAELS!K6>12%,"2",IF(CAELS!K6>10%,"3",IF(CAELS!K6>8,"4","5")))) -> 3 | ... U7: =IF(CAELS!V6>15%,"1",IF(CAELS!V6>12%,"2",IF(CAELS!V6>10%,"3",IF(CAELS!V6>8,"4","5")))) -> 3
A8: CCD | B8: ≥ 8% | C8: =IF(CAELS!D5>20%,"1",IF(CAELS!D5>15%,"2",IF(CAELS!D5>12%,"3",IF(CAELS!D5>10%,"4","5")))) -> 4 | D8: =IF(CAELS!E5>20%,"1",IF(CAELS!E5>15%,"2",IF(CAELS!E5>12%,"3",IF(CAELS!E5>10%,"4","5")))) -> 1 | E8: =IF(CAELS!F5>20%,"1",IF(CAELS!F5>15%,"2",IF(CAELS!F5>12%,"3",IF(CAELS!F5>10%,"4","5")))) -> 1 | F8: =IF(CAELS!G5>20%,"1",IF(CAELS!G5>15%,"2",IF(CAELS!G5>12%,"3",IF(CAELS!G5>10%,"4","5")))) -> 1 | G8: =IF(CAELS!H5>20%,"1",IF(CAELS!H5>15%,"2",IF(CAELS!H5>12%,"3",IF(CAELS!H5>10%,"4","5")))) -> 1 | H8: =IF(CAELS!I5>20%,"1",IF(CAELS!I5>15%,"2",IF(CAELS!I5>12%,"3",IF(CAELS!I5>10%,"4","5")))) -> 1 | I8: =IF(CAELS!J5>20%,"1",IF(CAELS!J5>15%,"2",IF(CAELS!J5>12%,"3",IF(CAELS!J5>10%,"4","5")))) -> 1 | J8: =IF(CAELS!K5>20%,"1",IF(CAELS!K5>15%,"2",IF(CAELS!K5>12%,"3",IF(CAELS!K5>10%,"4","5")))) -> 1 | ... U8: =IF(CAELS!V5>20%,"1",IF(CAELS!V5>15%,"2",IF(CAELS!V5>12%,"3",IF(CAELS!V5>10%,"4","5")))) -> 1
C9: =(C5+C6+C7+C8)/4 -> 3.5 | D9: =(D5+D6+D7+D8)/4 -> 2.25 | E9: =(E5+E6+E7+E8)/4 -> 1.75 | F9: =(F5+F6+F7+F8)/4 -> 1.75 | G9: =(G5+G6+G7+G8)/4 -> 1.75 | H9: =(H5+H6+H7+H8)/4 -> 1.75 | I9: =(I5+I6+I7+I8)/4 -> 1.75 | J9: =(J5+J6+J7+J8)/4 -> 1.75 | ... U9: =(U5+U6+U7+U8)/4 -> 1.75
A10: Asset Quality
A11: NPL | B11: ≤ 6% | L11: =IF(CAELS!M8<4%,"1",IF(CAELS!M8<8%,"2",IF(CAELS!M8<12%,"3",IF(CAELS!M8<15%,"4","5")))) -> 1 | O11: =IF(CAELS!P8<4%,"1",IF(CAELS!P8<8%,"2",IF(CAELS!P8<12%,"3",IF(CAELS!P8<15%,"4","5")))) -> 1 | R11: =IF(CAELS!S8<4%,"1",IF(CAELS!S8<8%,"2",IF(CAELS!S8<12%,"3",IF(CAELS!S8<15%,"4","5")))) -> 1 | U11: =IF(CAELS!V8<4%,"1",IF(CAELS!V8<8%,"2",IF(CAELS!V8<12%,"3",IF(CAELS!V8<15%,"4","5")))) -> 1
C12: =C11 -> 0 | D12: =D11 -> 0 | E12: =E11 -> 0 | F12: =F11 -> 0 | G12: =G11 -> 0 | H12: =H11 -> 0 | I12: =I11 -> 0 | J12: =J11 -> 0 | ... U12: =U11 -> 1
A13: Earnings
A14: ROA | D14: =IF(CAELS!E9>6%,"1",IF(CAELS!E9>4%,"2",IF(CAELS!E9>2%,"3",IF(CAELS!E9>0%,"4","5")))) -> 4 | E14: =IF(CAELS!F9>6%,"1",IF(CAELS!F9>4%,"2",IF(CAELS!F9>2%,"3",IF(CAELS!F9>0%,"4","5")))) -> 4 | F14: =IF(CAELS!G9>6%,"1",IF(CAELS!G9>4%,"2",IF(CAELS!G9>2%,"3",IF(CAELS!G9>0%,"4","5")))) -> 4 | G14: =IF(CAELS!H9>6%,"1",IF(CAELS!H9>4%,"2",IF(CAELS!H9>2%,"3",IF(CAELS!H9>0%,"4","5")))) -> 4 | H14: =IF(CAELS!I9>6%,"1",IF(CAELS!I9>4%,"2",IF(CAELS!I9>2%,"3",IF(CAELS!I9>0%,"4","5")))) -> 4 | I14: =IF(CAELS!J9>6%,"1",IF(CAELS!J9>4%,"2",IF(CAELS!J9>2%,"3",IF(CAELS!J9>0%,"4","5")))) -> 4 | J14: =IF(CAELS!K9>6%,"1",IF(CAELS!K9>4%,"2",IF(CAELS!K9>2%,"3",IF(CAELS!K9>0%,"4","5")))) -> 4 | K14: =IF(CAELS!L9>6%,"1",IF(CAELS!L9>4%,"2",IF(CAELS!L9>2%,"3",IF(CAELS!L9>0%,"4","5")))) -> 4 | ... U14: =IF(CAELS!V9>6%,"1",IF(CAELS!V9>4%,"2",IF(CAELS!V9>2%,"3",IF(CAELS!V9>0%,"4","5")))) -> 4
A15: CIR | C15: =IF(CAELS!D10<60%,"1",IF(CAELS!D10<70%,"2",IF(CAELS!D10<80%,"3",IF(CAELS!D10<90%,"4","5")))) -> 3 | D15: =IF(CAELS!E10<60%,"1",IF(CAELS!E10<70%,"2",IF(CAELS!E10<80%,"3",IF(CAELS!E10<90%,"4","5")))) -> 2 | E15: =IF(CAELS!F10<60%,"1",IF(CAELS!F10<70%,"2",IF(CAELS!F10<80%,"3",IF(CAELS!F10<90%,"4","5")))) -> 1 | F15: =IF(CAELS!G10<60%,"1",IF(CAELS!G10<70%,"2",IF(CAELS!G10<80%,"3",IF(CAELS!G10<90%,"4","5")))) -> 1 | G15: =IF(CAELS!H10<60%,"1",IF(CAELS!H10<70%,"2",IF(CAELS!H10<80%,"3",IF(CAELS!H10<90%,"4","5")))) -> 1 | H15: =IF(CAELS!I10<60%,"1",IF(CAELS!I10<70%,"2",IF(CAELS!I10<80%,"3",IF(CAELS!I10<90%,"4","5")))) -> 1 | I15: =IF(CAELS!J10<60%,"1",IF(CAELS!J10<70%,"2",IF(CAELS!J10<80%,"3",IF(CAELS!J10<90%,"4","5")))) -> 1 | J15: =IF(CAELS!K10<60%,"1",IF(CAELS!K10<70%,"2",IF(CAELS!K10<80%,"3",IF(CAELS!K10<90%,"4","5")))) -> 1 | ... U15: =IF(CAELS!V10<60%,"1",IF(CAELS!V10<70%,"2",IF(CAELS!V10<80%,"3",IF(CAELS!V10<90%,"4","5")))) -> 1
A16: OER | C16: =IF(CAELS!D11<4%,"1",IF(CAELS!D11<6%,"2",IF(CAELS!D11<8%,"3",IF(CAELS!D11<10%,"4","5")))) -> 1 | D16: =IF(CAELS!E11<4%,"1",IF(CAELS!E11<6%,"2",IF(CAELS!E11<8%,"3",IF(CAELS!E11<10%,"4","5")))) -> 4 | E16: =IF(CAELS!F11<4%,"1",IF(CAELS!F11<6%,"2",IF(CAELS!F11<8%,"3",IF(CAELS!F11<10%,"4","5")))) -> 1 | F16: =IF(CAELS!G11<4%,"1",IF(CAELS!G11<6%,"2",IF(CAELS!G11<8%,"3",IF(CAELS!G11<10%,"4","5")))) -> 1 | G16: =IF(CAELS!H11<4%,"1",IF(CAELS!H11<6%,"2",IF(CAELS!H11<8%,"3",IF(CAELS!H11<10%,"4","5")))) -> 1 | H16: =IF(CAELS!I11<4%,"1",IF(CAELS!I11<6%,"2",IF(CAELS!I11<8%,"3",IF(CAELS!I11<10%,"4","5")))) -> 1 | I16: =IF(CAELS!J11<4%,"1",IF(CAELS!J11<6%,"2",IF(CAELS!J11<8%,"3",IF(CAELS!J11<10%,"4","5")))) -> 1 | J16: =IF(CAELS!K11<4%,"1",IF(CAELS!K11<6%,"2",IF(CAELS!K11<8%,"3",IF(CAELS!K11<10%,"4","5")))) -> 1 | ... U16: =IF(CAELS!V11<4%,"1",IF(CAELS!V11<6%,"2",IF(CAELS!V11<8%,"3",IF(CAELS!V11<10%,"4","5")))) -> 1
C17: =(C14+C15+C16)/3 -> 1.3333333 | D17: =(D14+D15+D16)/3 -> 3.3333333 | E17: =(E14+E15+E16)/3 -> 2 | F17: =(F14+F15+F16)/3 -> 2 | G17: =(G14+G15+G16)/3 -> 2 | H17: =(H14+H15+H16)/3 -> 2 | I17: =(I14+I15+I16)/3 -> 2 | J17: =(J14+J15+J16)/3 -> 2 | ... U17: =(U14+U15+U16)/3 -> 2
A18: LIQUIDITY
A19: MIN LIQ | B19: 0.15 | C19: =IF(CAELS!D12>30%,"1",IF(CAELS!D12>25%,"2",IF(CAELS!D12>20%,"3",IF(CAELS!D12>15%,"4","5")))) -> 1 | D19: =IF(CAELS!E12>30%,"1",IF(CAELS!E12>25%,"2",IF(CAELS!E12>20%,"3",IF(CAELS!E12>15%,"4","5")))) -> 1 | E19: =IF(CAELS!F12>30%,"1",IF(CAELS!F12>25%,"2",IF(CAELS!F12>20%,"3",IF(CAELS!F12>15%,"4","5")))) -> 1 | F19: =IF(CAELS!G12>30%,"1",IF(CAELS!G12>25%,"2",IF(CAELS!G12>20%,"3",IF(CAELS!G12>15%,"4","5")))) -> 1 | G19: =IF(CAELS!H12>30%,"1",IF(CAELS!H12>25%,"2",IF(CAELS!H12>20%,"3",IF(CAELS!H12>15%,"4","5")))) -> 2 | H19: =IF(CAELS!I12>30%,"1",IF(CAELS!I12>25%,"2",IF(CAELS!I12>20%,"3",IF(CAELS!I12>15%,"4","5")))) -> 1 | I19: =IF(CAELS!J12>30%,"1",IF(CAELS!J12>25%,"2",IF(CAELS!J12>20%,"3",IF(CAELS!J12>15%,"4","5")))) -> 2 | J19: =IF(CAELS!K12>30%,"1",IF(CAELS!K12>25%,"2",IF(CAELS!K12>20%,"3",IF(CAELS!K12>15%,"4","5")))) -> 1 | ... U19: =IF(CAELS!V12>30%,"1",IF(CAELS!V12>25%,"2",IF(CAELS!V12>20%,"3",IF(CAELS!V12>15%,"4","5")))) -> 1
A20: TECH LIQ | C20: =IF(CAELS!D13>30%,"1",IF(CAELS!D13>25%,"2",IF(CAELS!D13>20%,"3",IF(CAELS!D13>15%,"4","5")))) -> 5 | D20: =IF(CAELS!E13>30%,"1",IF(CAELS!E13>25%,"2",IF(CAELS!E13>20%,"3",IF(CAELS!E13>15%,"4","5")))) -> 5 | E20: =IF(CAELS!F13>30%,"1",IF(CAELS!F13>25%,"2",IF(CAELS!F13>20%,"3",IF(CAELS!F13>15%,"4","5")))) -> 5 | F20: =IF(CAELS!G13>30%,"1",IF(CAELS!G13>25%,"2",IF(CAELS!G13>20%,"3",IF(CAELS!G13>15%,"4","5")))) -> 5 | G20: =IF(CAELS!H13>30%,"1",IF(CAELS!H13>25%,"2",IF(CAELS!H13>20%,"3",IF(CAELS!H13>15%,"4","5")))) -> 5 | H20: =IF(CAELS!I13>30%,"1",IF(CAELS!I13>25%,"2",IF(CAELS!I13>20%,"3",IF(CAELS!I13>15%,"4","5")))) -> 5 | I20: =IF(CAELS!J13>30%,"1",IF(CAELS!J13>25%,"2",IF(CAELS!J13>20%,"3",IF(CAELS!J13>15%,"4","5")))) -> 5 | J20: =IF(CAELS!K13>30%,"1",IF(CAELS!K13>25%,"2",IF(CAELS!K13>20%,"3",IF(CAELS!K13>15%,"4","5")))) -> 5 | ... U20: =IF(CAELS!V13>30%,"1",IF(CAELS!V13>25%,"2",IF(CAELS!V13>20%,"3",IF(CAELS!V13>15%,"4","5")))) -> 5
A21: EB | B21: ≤ 25% | C21: =IF(CAELS!D14<15%,"1",IF(CAELS!D14<18%,"2",IF(CAELS!D14<22%,"3",IF(CAELS!D14<25%,"4","5")))) -> 1 | D21: =IF(CAELS!E14<15%,"1",IF(CAELS!E14<18%,"2",IF(CAELS!E14<22%,"3",IF(CAELS!E14<25%,"4","5")))) -> 1 | E21: =IF(CAELS!F14<15%,"1",IF(CAELS!F14<18%,"2",IF(CAELS!F14<22%,"3",IF(CAELS!F14<25%,"4","5")))) -> 1 | F21: =IF(CAELS!G14<15%,"1",IF(CAELS!G14<18%,"2",IF(CAELS!G14<22%,"3",IF(CAELS!G14<25%,"4","5")))) -> 1 | G21: =IF(CAELS!H14<15%,"1",IF(CAELS!H14<18%,"2",IF(CAELS!H14<22%,"3",IF(CAELS!H14<25%,"4","5")))) -> 1 | H21: =IF(CAELS!I14<15%,"1",IF(CAELS!I14<18%,"2",IF(CAELS!I14<22%,"3",IF(CAELS!I14<25%,"4","5")))) -> 1 | I21: =IF(CAELS!J14<15%,"1",IF(CAELS!J14<18%,"2",IF(CAELS!J14<22%,"3",IF(CAELS!J14<25%,"4","5")))) -> 1 | J21: =IF(CAELS!K14<15%,"1",IF(CAELS!K14<18%,"2",IF(CAELS!K14<22%,"3",IF(CAELS!K14<25%,"4","5")))) -> 1 | ... U21: =IF(CAELS!V14<15%,"1",IF(CAELS!V14<18%,"2",IF(CAELS!V14<22%,"3",IF(CAELS!V14<25%,"4","5")))) -> 1
A22: LIQ/TA | C22: =IF(CAELS!D15>15%,"1",IF(CAELS!D15>12%,"2",IF(CAELS!D15>9%,"3",IF(CAELS!D15>6%,"4","5")))) -> 2 | D22: =IF(CAELS!E15>15%,"1",IF(CAELS!E15>12%,"2",IF(CAELS!E15>9%,"3",IF(CAELS!E15>6%,"4","5")))) -> 3 | E22: =IF(CAELS!F15>15%,"1",IF(CAELS!F15>12%,"2",IF(CAELS!F15>9%,"3",IF(CAELS!F15>6%,"4","5")))) -> 3 | F22: =IF(CAELS!G15>15%,"1",IF(CAELS!G15>12%,"2",IF(CAELS!G15>9%,"3",IF(CAELS!G15>6%,"4","5")))) -> 3 | G22: =IF(CAELS!H15>15%,"1",IF(CAELS!H15>12%,"2",IF(CAELS!H15>9%,"3",IF(CAELS!H15>6%,"4","5")))) -> 5 | H22: =IF(CAELS!I15>15%,"1",IF(CAELS!I15>12%,"2",IF(CAELS!I15>9%,"3",IF(CAELS!I15>6%,"4","5")))) -> 4 | I22: =IF(CAELS!J15>15%,"1",IF(CAELS!J15>12%,"2",IF(CAELS!J15>9%,"3",IF(CAELS!J15>6%,"4","5")))) -> 5 | J22: =IF(CAELS!K15>15%,"1",IF(CAELS!K15>12%,"2",IF(CAELS!K15>9%,"3",IF(CAELS!K15>6%,"4","5")))) -> 4 | ... U22: =IF(CAELS!V15>15%,"1",IF(CAELS!V15>12%,"2",IF(CAELS!V15>9%,"3",IF(CAELS!V15>6%,"4","5")))) -> 4
C23: =(C19+C20+C21+C22)/4 -> 2.25 | D23: =(D19+D20+D21+D22)/4 -> 2.5 | E23: =(E19+E20+E21+E22)/4 -> 2.5 | F23: =(F19+F20+F21+F22)/4 -> 2.5 | G23: =(G19+G20+G21+G22)/4 -> 3.25 | H23: =(H19+H20+H21+H22)/4 -> 2.75 | I23: =(I19+I20+I21+I22)/4 -> 3.25 | J23: =(J19+J20+J21+J22)/4 -> 2.75 | ... U23: =(U19+U20+U21+U22)/4 -> 2.75
A24: STRUCTURE
A25: NEA | B25: ≤ 10% | C25: =IF(CAELS!D16<6%,"1",IF(CAELS!D16<7%,"2",IF(CAELS!D16<8%,"3",IF(CAELS!D16<10%,"4","5")))) -> 5 | D25: =IF(CAELS!E16<6%,"1",IF(CAELS!E16<7%,"2",IF(CAELS!E16<8%,"3",IF(CAELS!E16<10%,"4","5")))) -> 4 | E25: =IF(CAELS!F16<6%,"1",IF(CAELS!F16<7%,"2",IF(CAELS!F16<8%,"3",IF(CAELS!F16<10%,"4","5")))) -> 1 | F25: =IF(CAELS!G16<6%,"1",IF(CAELS!G16<7%,"2",IF(CAELS!G16<8%,"3",IF(CAELS!G16<10%,"4","5")))) -> 1 | G25: =IF(CAELS!H16<6%,"1",IF(CAELS!H16<7%,"2",IF(CAELS!H16<8%,"3",IF(CAELS!H16<10%,"4","5")))) -> 5 | H25: =IF(CAELS!I16<6%,"1",IF(CAELS!I16<7%,"2",IF(CAELS!I16<8%,"3",IF(CAELS!I16<10%,"4","5")))) -> 4 | I25: =IF(CAELS!J16<6%,"1",IF(CAELS!J16<7%,"2",IF(CAELS!J16<8%,"3",IF(CAELS!J16<10%,"4","5")))) -> 5 | J25: =IF(CAELS!K16<6%,"1",IF(CAELS!K16<7%,"2",IF(CAELS!K16<8%,"3",IF(CAELS!K16<10%,"4","5")))) -> 3 | ... U25: =IF(CAELS!V16<6%,"1",IF(CAELS!V16<7%,"2",IF(CAELS!V16<8%,"3",IF(CAELS!V16<10%,"4","5")))) -> 5
A26: LB | B26: ≤ 5% | C26: =IF(CAELS!D17<2%,"1",IF(CAELS!D17<3%,"2",IF(CAELS!D17<4%,"3",IF(CAELS!D17<5%,"4","5")))) -> 3 | D26: =IF(CAELS!E17<2%,"1",IF(CAELS!E17<3%,"2",IF(CAELS!E17<4%,"3",IF(CAELS!E17<5%,"4","5")))) -> 2 | E26: =IF(CAELS!F17<2%,"1",IF(CAELS!F17<3%,"2",IF(CAELS!F17<4%,"3",IF(CAELS!F17<5%,"4","5")))) -> 1 | F26: =IF(CAELS!G17<2%,"1",IF(CAELS!G17<3%,"2",IF(CAELS!G17<4%,"3",IF(CAELS!G17<5%,"4","5")))) -> 1 | G26: =IF(CAELS!H17<2%,"1",IF(CAELS!H17<3%,"2",IF(CAELS!H17<4%,"3",IF(CAELS!H17<5%,"4","5")))) -> 1 | H26: =IF(CAELS!I17<2%,"1",IF(CAELS!I17<3%,"2",IF(CAELS!I17<4%,"3",IF(CAELS!I17<5%,"4","5")))) -> 1 | I26: =IF(CAELS!J17<2%,"1",IF(CAELS!J17<3%,"2",IF(CAELS!J17<4%,"3",IF(CAELS!J17<5%,"4","5")))) -> 2 | J26: =IF(CAELS!K17<2%,"1",IF(CAELS!K17<3%,"2",IF(CAELS!K17<4%,"3",IF(CAELS!K17<5%,"4","5")))) -> 2 | ... U26: =IF(CAELS!V17<2%,"1",IF(CAELS!V17<3%,"2",IF(CAELS!V17<4%,"3",IF(CAELS!V17<5%,"4","5")))) -> 5
A27: FITD | B27: ≤ 5% | C27: =IF(CAELS!D18<2%,"1",IF(CAELS!D18<3%,"2",IF(CAELS!D18<4%,"3",IF(CAELS!D18<5%,"4","5")))) -> 1 | D27: =IF(CAELS!E18<2%,"1",IF(CAELS!E18<3%,"2",IF(CAELS!E18<4%,"3",IF(CAELS!E18<5%,"4","5")))) -> 1 | E27: =IF(CAELS!F18<2%,"1",IF(CAELS!F18<3%,"2",IF(CAELS!F18<4%,"3",IF(CAELS!F18<5%,"4","5")))) -> 2 | F27: =IF(CAELS!G18<2%,"1",IF(CAELS!G18<3%,"2",IF(CAELS!G18<4%,"3",IF(CAELS!G18<5%,"4","5")))) -> 5 | G27: =IF(CAELS!H18<2%,"1",IF(CAELS!H18<3%,"2",IF(CAELS!H18<4%,"3",IF(CAELS!H18<5%,"4","5")))) -> 5 | H27: =IF(CAELS!I18<2%,"1",IF(CAELS!I18<3%,"2",IF(CAELS!I18<4%,"3",IF(CAELS!I18<5%,"4","5")))) -> 5 | I27: =IF(CAELS!J18<2%,"1",IF(CAELS!J18<3%,"2",IF(CAELS!J18<4%,"3",IF(CAELS!J18<5%,"4","5")))) -> 5 | J27: =IF(CAELS!K18<2%,"1",IF(CAELS!K18<3%,"2",IF(CAELS!K18<4%,"3",IF(CAELS!K18<5%,"4","5")))) -> 5 | ... U27: =IF(CAELS!V18<2%,"1",IF(CAELS!V18<3%,"2",IF(CAELS!V18<4%,"3",IF(CAELS!V18<5%,"4","5")))) -> 5
A28: FICC | B28: ≤ 40% | C28: =IF(CAELS!D19<20%,"1",IF(CAELS!D19<25%,"2",IF(CAELS!D19<30%,"3",IF(CAELS!D19<40%,"4","5")))) -> 1 | D28: =IF(CAELS!E19<20%,"1",IF(CAELS!E19<25%,"2",IF(CAELS!E19<30%,"3",IF(CAELS!E19<40%,"4","5")))) -> 1 | E28: =IF(CAELS!F19<20%,"1",IF(CAELS!F19<25%,"2",IF(CAELS!F19<30%,"3",IF(CAELS!F19<40%,"4","5")))) -> 1 | F28: =IF(CAELS!G19<20%,"1",IF(CAELS!G19<25%,"2",IF(CAELS!G19<30%,"3",IF(CAELS!G19<40%,"4","5")))) -> 2 | G28: =IF(CAELS!H19<20%,"1",IF(CAELS!H19<25%,"2",IF(CAELS!H19<30%,"3",IF(CAELS!H19<40%,"4","5")))) -> 2 | H28: =IF(CAELS!I19<20%,"1",IF(CAELS!I19<25%,"2",IF(CAELS!I19<30%,"3",IF(CAELS!I19<40%,"4","5")))) -> 2 | I28: =IF(CAELS!J19<20%,"1",IF(CAELS!J19<25%,"2",IF(CAELS!J19<30%,"3",IF(CAELS!J19<40%,"4","5")))) -> 2 | J28: =IF(CAELS!K19<20%,"1",IF(CAELS!K19<25%,"2",IF(CAELS!K19<30%,"3",IF(CAELS!K19<40%,"4","5")))) -> 2 | ... U28: =IF(CAELS!V19<20%,"1",IF(CAELS!V19<25%,"2",IF(CAELS!V19<30%,"3",IF(CAELS!V19<40%,"4","5")))) -> 1
C29: =(C25+C26+C27+C28)/4 -> 2.5 | D29: =(D25+D26+D27+D28)/4 -> 2 | E29: =(E25+E26+E27+E28)/4 -> 1.25 | F29: =(F25+F26+F27+F28)/4 -> 2.25 | G29: =(G25+G26+G27+G28)/4 -> 3.25 | H29: =(H25+H26+H27+H28)/4 -> 3 | I29: =(I25+I26+I27+I28)/4 -> 3.5 | J29: =(J25+J26+J27+J28)/4 -> 3 | ... U29: =(U25+U26+U27+U28)/4 -> 4
A30: FINAL RATING | C30: =(C9+C12+C17+C23)/4 -> 1.7708333 | D30: =(D9+D12+D17+D23)/4 -> 2.0208333 | E30: =(E9+E12+E17+E23)/4 -> 1.5625 | F30: =(F9+F12+F17+F23)/4 -> 1.5625 | G30: =(G9+G12+G17+G23)/4 -> 1.75 | H30: =(H9+H12+H17+H23)/4 -> 1.625 | I30: =(I9+I12+I17+I23)/4 -> 1.75 | J30: =(J9+J12+J17+J23)/4 -> 1.625 | ... U30: =(U9+U12+U17+U23)/4 -> 1.875

Sheet compliance report audited 2022
A1: SMARTLIFE DT SACCO SOCIETY LIMITED
A2: PERFORMANCE AND COMPLIANCE REPORT AS AT : 31st December , 2022
B3: Prudential Standard | C3: Audited | D3: Returns | F3: Aggregate for all Licensed Saccos
C4: 2021 | D4: 30th September , 2022 | E4: 31st December , 2022
A5: A. CAPITAL ADEQUACY
A6: Core Capital | B6: ≥10M | C6: 173810427 | D6: 188890335 | E6: 207005401 | F6: 133542865117
A7: Core Capital/Total Assets | B7: ≥10% | C7: 0.127 | D7: 0.136 | E7: 0.141 | F7: 0.177
A8: Institutional Capital/Total Assets | B8: ≥8% | C8: 0.058 | D8: 0.066 | E8: 0.075 | F8: 0.11
A9: B. ASSET QUALITY
A10: NPL (Substandard+Doubtful+Loss) | B10: <5% | C10: 0.058 | D10: 0.072 | E10: 0.075 | F10: 0.074
A11: Non-Earning Assets | B11: <10% | C11: 0.059 | D11: 0.329 | E11: 0.309 | F11: 0.103
A12: Equity investments/Deposits | B12: <5% | C12: 0.053 | D12: 0.053 | E12: 0.052 | F12: 0.027
A13: Equity investments/Core capital | B13: <40% | C13: 0.279 | D13: 0.258 | E13: 0.235 | F13: 0.105
A14: C. EARNINGS RATING
A15: Yield on Gross Loans | C15: 0.115 | D15: 0.15 | E15: 0.199 | F15: 0.16
A16: Total Expense/Total Income | C16: 0.824 | D16: 0.761 | E16: 0.739 | F16: 0.712
A17: Net Income/Average Assets (ROA) | C17: 0.008 | D17: 0.018 | E17: 0.024 | F17: 0.037
A18: Operating Expenses/Financial Income (OPEX) | C18: 0.279 | D18: 0.27 | E18: 0.263 | F18: 0.341
A19: D. LIQUIDITY
A20: Liquid Assets/Short-term Liabilities | B20: >15% | C20: 0.752 | D20: 0.373 | E20: 0.569 | F20: 0.651
A21: External Borrowing/Total Assets | B21: <25% | C21: 0.106 | D21: 0.076 | E21: 0.094 | F21: 0.025
A22: Liquid Assets/Total Assets | C22: 0.126 | D22: 0.079 | E22: 0.123 | F22: 0.128
A23: E. STRUCTURE/SENSITIVITY TO RISK
A24: Gross loans /Total Assets | B24: 70-80 | C24: 0.801 | D24: 0.555 | E24: 0.531 | F24: 0.753
A25: Gross loans/Deposits | B25: >100% | C25: 1.205 | D25: 0.845 | E25: 0.837 | F25: 1.103
A26: Financial Investments/Total Assets | C26: 0.09 | D26: 0.094 | E26: 0.093 | F26: 0.076
A27: Dividends+Interest on Deposits/Total Income | C27: 0.36 | D27: 0.365 | E27: 0.347 | F27: 0.313
A28: F. KEY FINANCIAL STATISTICS
A29: Total Assets | C29: 1372661880 | D29: 1391514003 | E29: 1465789897 | F29: 7.5329685e+11
A30: Average Assets | C30: 1304819846 | D30: 1.3490511e+09 | E30: 1.4203259e+09 | F30: 7.2382483e+11
A31: Total Deposits | C31: 911981655 | D31: 913072094 | E31: 930279580 | F31: 5.1446129e+11
A32: Gross Loans | C32: 1099345186 | D32: 771992553 | E32: 778820671 | F32: 5.672322e+11
A33: Core Capital | C33: 173810427 | D33: 188890335 | E33: 207005401 | F33: 1.3354287e+11
A34: Institutional Capital | C34: 80278788 | D34: 92224496 | E34: 109334398 | F34: 8.2971467e+10
A35: Non-performing Loans | C35: 63974397 | D35: 55446903 | E35: 58207177 | F35: 4.184069e+10
A36: Non-Earning Assets | C36: 80384037 | D36: 457927335 | E36: 453580805 | F36: 7.7758148e+10
A37: Property and Equipment | C37: 24078276 | D37: 23350768 | E37: 22237269 | F37: 2.1946422e+10
A38: Equity Investments | C38: 48408789 | D38: 48658789 | E38: 48658789 | F38: 1.4010325e+10
A39: Financial Investments | C39: 82528081 | D39: 85373819 | E39: 86494221 | F39: 3.8922699e+10
A40: Liquid Assets | C40: 172602165 | D40: 109801142 | E40: 179678973 | F40: 9.6165936e+10
... A50: Net Income | C50: 11088485 | D50: 23890862 | E50: 33675621 | F50: 2.6549395e+10

Sheet Sheet2
G4: =16*2 -> 32 | H4: =32/4 -> 8

Sheet Compliance Status
B2: 2010 Audited | C2: 2020 audited | D2: 44197 | E2: 44229 | F2: 44258 | G2: 44290 | H2: 44321 | I2: 44353 | J2: 44384 | K2: 44416 | L2: 44448 | M2: 44479 | N2: 44511 | O2: 44542 | P2: AUDITED 2021 | Q2: 44563 | R2: 44595 | S2: 44624 | T2: 44656
A3: CORE CAPITAL | B3: =IF(CAELS!D3>10,"Compliant","Non-Compliant") -> Compliant | C3: =IF(CAELS!E3>10,"Compliant","Non-Compliant") -> Compliant | D3: =IF(CAELS!F3>10,"Compliant","Non-Compliant") -> Compliant | E3: =IF(CAELS!G3>10,"Compliant","Non-Compliant") -> Compliant | F3: =IF(CAELS!H3>10,"Compliant","Non-Compliant") -> Compliant | G3: =IF(CAELS!I3>10,"Compliant","Non-Compliant") -> Compliant | H3: =IF(CAELS!J3>10,"Compliant","Non-Compliant") -> Compliant | I3: =IF(CAELS!K3>10,"Compliant","Non-Compliant") -> Compliant | ... T3: =IF(CAELS!V3>10,"Compliant","Non-Compliant") -> Compliant
A4: CCA (Min 10%) | B4: =IF(CAELS!D4>10%,"Compliant","Non-Compliant") -> Compliant | C4: =IF(CAELS!E4>10%,"Compliant","Non-Compliant") -> Compliant | D4: =IF(CAELS!F4>10%,"Compliant","Non-Compliant") -> Compliant | E4: =IF(CAELS!G4>10%,"Compliant","Non-Compliant") -> Compliant | F4: =IF(CAELS!H4>10%,"Compliant","Non-Compliant") -> Compliant | G4: =IF(CAELS!I4>10%,"Compliant","Non-Compliant") -> Compliant | H4: =IF(CAELS!J4>10%,"Compliant","Non-Compliant") -> Compliant | I4: =IF(CAELS!K4>10%,"Compliant","Non-Compliant") -> Compliant | ... T4: =IF(CAELS!V4>10%,"Compliant","Non-Compliant") -> Compliant
A5: ICA (Min 8%) | B5: =IF(CAELS!D6>8%,"Compliant","Non-Compliant") -> Non-Compliant | C5: =IF(CAELS!E6>8%,"Compliant","Non-Compliant") -> Compliant | D5: =IF(CAELS!F6>8%,"Compliant","Non-Compliant") -> Compliant | E5: =IF(CAELS!G6>8%,"Compliant","Non-Compliant") -> Compliant | F5: =IF(CAELS!H6>8%,"Compliant","Non-Compliant") -> Compliant | G5: =IF(CAELS!I6>8%,"Compliant","Non-Compliant") -> Compliant | H5: =IF(CAELS!J6>8%,"Compliant","Non-Compliant") -> Compliant | I5: =IF(CAELS!K6>8%,"Compliant","Non-Compliant") -> Compliant | ... T5: =IF(CAELS!V6>8%,"Compliant","Non-Compliant") -> Compliant
A6: CCD (Min 8%) | B6: =IF(CAELS!D5>8%,"Compliant","Non-Compiant") -> Compliant | C6: =IF(CAELS!E5>8%,"Compliant","Non-Compiant") -> Compliant | D6: =IF(CAELS!F5>8%,"Compliant","Non-Compiant") -> Compliant | E6: =IF(CAELS!G5>8%,"Compliant","Non-Compiant") -> Compliant | F6: =IF(CAELS!H5>8%,"Compliant","Non-Compiant") -> Compliant | G6: =IF(CAELS!I5>8%,"Compliant","Non-Compiant") -> Compliant | H6: =IF(CAELS!J5>8%,"Compliant","Non-Compiant") -> Compliant | I6: =IF(CAELS!K5>8%,"Compliant","Non-Compiant") -> Compliant | ... T6: =IF(CAELS!V5>8%,"Compliant","Non-Compiant") -> Compliant
A7: NPL(5%)
A8: Liquidity(15%) | B8: =IF(CAELS!D12>15%,"Compliant","Non-Compliant") -> Compliant | C8: =IF(CAELS!E12>15%,"Compliant","Non-Compliant") -> Compliant | D8: =IF(CAELS!F12>15%,"Compliant","Non-Compliant") -> Compliant | E8: =IF(CAELS!G12>15%,"Compliant","Non-Compliant") -> Compliant | F8: =IF(CAELS!H12>15%,"Compliant","Non-Compliant") -> Compliant | G8: =IF(CAELS!I12>15%,"Compliant","Non-Compliant") -> Compliant | H8: =IF(CAELS!J12>15%,"Compliant","Non-Compliant") -> Compliant | I8: =IF(CAELS!K12>15%,"Compliant","Non-Compliant") -> Compliant | ... T8: =IF(CAELS!V12>15%,"Compliant","Non-Compliant") -> Compliant
A9: NEA (Max 10%) | B9: =IF(CAELS!D16<10%,"Compliant","Non-Compliant") -> Non-Compliant | C9: =IF(CAELS!E16<10%,"Compliant","Non-Compliant") -> Compliant | D9: =IF(CAELS!F16<10%,"Compliant","Non-Compliant") -> Compliant | E9: =IF(CAELS!G16<10%,"Compliant","Non-Compliant") -> Compliant | F9: =IF(CAELS!H16<10%,"Compliant","Non-Compliant") -> Non-Compliant | G9: =IF(CAELS!I16<10%,"Compliant","Non-Compliant") -> Compliant | H9: =IF(CAELS!J16<10%,"Compliant","Non-Compliant") -> Non-Compliant | I9: =IF(CAELS!K16<10%,"Compliant","Non-Compliant") -> Compliant | ... T9: =IF(CAELS!V16<10%,"Compliant","Non-Compliant") -> Non-Compliant
A10: LB ratio (Max 5%) | B10: =IF(CAELS!D17<5%,"Compliant","Non-Compliant") -> Compliant | C10: =IF(CAELS!E17<5%,"Compliant","Non-Compliant") -> Compliant | D10: =IF(CAELS!F17<5%,"Compliant","Non-Compliant") -> Compliant | E10: =IF(CAELS!G17<5%,"Compliant","Non-Compliant") -> Compliant | F10: =IF(CAELS!H17<5%,"Compliant","Non-Compliant") -> Compliant | G10: =IF(CAELS!I17<5%,"Compliant","Non-Compliant") -> Compliant | H10: =IF(CAELS!J17<5%,"Compliant","Non-Compliant") -> Compliant | I10: =IF(CAELS!K17<5%,"Compliant","Non-Compliant") -> Compliant | ... T10: =IF(CAELS!V17<5%,"Compliant","Non-Compliant") -> Non-Compliant
A11: FITD (Max 5%) | B11: =IF(CAELS!D18<5%,"Compliant","Non-Compliant") -> Compliant | C11: =IF(CAELS!E18<5%,"Compliant","Non-Compliant") -> Compliant | D11: =IF(CAELS!F18<5%,"Compliant","Non-Compliant") -> Compliant | E11: =IF(CAELS!G18<5%,"Compliant","Non-Compliant") -> Non-Compliant | F11: =IF(CAELS!H18<5%,"Compliant","Non-Compliant") -> Non-Compliant | G11: =IF(CAELS!I18<5%,"Compliant","Non-Compliant") -> Non-Compliant | H11: =IF(CAELS!J18<5%,"Compliant","Non-Compliant") -> Non-Compliant | I11: =IF(CAELS!K18<5%,"Compliant","Non-Compliant") -> Non-Compliant | ... T11: =IF(CAELS!V18<5%,"Compliant","Non-Compliant") -> Non-Compliant
A12: FICC (Max 40%) | B12: =IF(CAELS!D19<40%,"Compliant","Non-Compliant") -> Compliant | C12: =IF(CAELS!E19<40%,"Compliant","Non-Compliant") -> Compliant | D12: =IF(CAELS!F19<40%,"Compliant","Non-Compliant") -> Compliant | E12: =IF(CAELS!G19<40%,"Compliant","Non-Compliant") -> Compliant | F12: =IF(CAELS!H19<40%,"Compliant","Non-Compliant") -> Compliant | G12: =IF(CAELS!I19<40%,"Compliant","Non-Compliant") -> Compliant | H12: =IF(CAELS!J19<40%,"Compliant","Non-Compliant") -> Compliant | I12: =IF(CAELS!K19<40%,"Compliant","Non-Compliant") -> Compliant | ... T12: =IF(CAELS!V19<40%,"Compliant","Non-Compliant") -> Compliant
A13: EB ratio (Max 25%) | B13: =IF(CAELS!D14<25%,"Compliant","Non-Compliant") -> Compliant | C13: =IF(CAELS!E14<25%,"Compliant","Non-Compliant") -> Compliant | D13: =IF(CAELS!F14<25%,"Compliant","Non-Compliant") -> Compliant | E13: =IF(CAELS!G14<25%,"Compliant","Non-Compliant") -> Compliant | F13: =IF(CAELS!H14<25%,"Compliant","Non-Compliant") -> Compliant | G13: =IF(CAELS!I14<25%,"Compliant","Non-Compliant") -> Compliant | H13: =IF(CAELS!J14<25%,"Compliant","Non-Compliant") -> Compliant | I13: =IF(CAELS!K14<25%,"Compliant","Non-Compliant") -> Compliant | ... T13: =IF(CAELS!V14<25%,"Compliant","Non-Compliant") -> Compliant
A14: A=S+L | B14: =IF('Evolutive SFP'!B27='Evolutive SFP'!B49,"BALANCING","NOT BALANCING") -> BALANCING | C14: =IF('Evolutive SFP'!C27='Evolutive SFP'!C49,"BALANCING","NOT BALANCING") -> BALANCING | D14: =IF('Evolutive SFP'!D27='Evolutive SFP'!D49,"BALANCING","NOT BALANCING") -> BALANCING | E14: =IF('Evolutive SFP'!E27='Evolutive SFP'!E49,"BALANCING","NOT BALANCING") -> BALANCING | F14: =IF('Evolutive SFP'!F27='Evolutive SFP'!F49,"BALANCING","NOT BALANCING") -> BALANCING | G14: =IF('Evolutive SFP'!G27='Evolutive SFP'!G49,"BALANCING","NOT BALANCING") -> BALANCING | H14: =IF('Evolutive SFP'!H27='Evolutive SFP'!H49,"BALANCING","NOT BALANCING") -> BALANCING | I14: =IF('Evolutive SFP'!I27='Evolutive SFP'!I49,"BALANCING","NOT BALANCING") -> BALANCING | ... P14: =IF('Evolutive SFP'!P27='Evolutive SFP'!P49,"BALANCING","NOT BALANCING") -> BALANCING | Q14: =IF('Evolutive SFP'!#REF!='Evolutive SFP'!#REF!,"BALANCING","NOT BALANCING") -> #REF! | R14: =IF('Evolutive SFP'!#REF!='Evolutive SFP'!#REF!,"BALANCING","NOT BALANCING") -> #REF! | S14: =IF('Evolutive SFP'!Q27='Evolutive SFP'!Q49,"BALANCING","NOT BALANCING") -> BALANCING | T14: =IF('Evolutive SFP'!R27='Evolutive SFP'!R49,"BALANCING","NOT BALANCING") -> BALANCING

Sheet CashFlow Stmnt
A1: STATEMENT OF CASHFLOWS FOR THE YEAR ENDED 31ST DECEMBER 2020
B2: 2020 | C2: 2021 | D2: Audited -2021 | E2: Variance
A3: Cash flows from operating activities
A4: Interest receipts
A5: Interest Payments | J5: .
A6: Payment to employees and suppliers | J6: .
A7: Other operating income
A8: (Increase)/Decrease in Operating assets | B8: =B4+B5+B6+B7 -> 0 | C8: =SUM(C4:C7) -> 0 | D8: =SUM(D4:D7) -> 0
A9: Net loans to members
A10: Recievables and prepayments
A11: Trade and Other Receivables
A12: Inventories
A13: Short term investments
A14: Increase/(Decrease) in Operating liabilities | B14: =SUM(B9:B13) -> 0 | C14: =SUM(C9:C13) -> 0 | D14: =SUM(D9:D13) -> 0
A15: Deposits from members
A16: Trade and Accrued Expenses
A17: Sundry creditors
A18: Net cashflow from operating activities before income taxes | B18: =B8+B14+B15+B16+B17 -> 0 | C18: =C8+C14+C15+C16+C17 -> 0 | D18: =D8+D14+D15+D16+D17 -> 0
A19: Income tax paid
A20: Net Cash from Operating activities
A22: Cashflow from investing activities
A23: Purchase of Property and equipment
A24: Purchase of intangible assets
A25: Increase in Other Assets
A26: Purchase of Investment Securities
A27: Dividends Received
A28: Net Cash from investing activities | B28: =SUM(B23:B27) -> 0 | C28: =SUM(C23:C27) -> 0 | D28: =SUM(D23:D27) -> 0
A30: Cashflow from financing activities
A31: Share capital contributions
A32: Proceeds from long-term borrowings
A33: Prior Year Adjustments
A34: Housing Contributions Plaza
A35: Repayments of long term borrowings
A36: Dividend paid
A37: Net cash from financing activities | B37: =SUM(B31:B36) -> 0 | C37: =SUM(C31:C36) -> 0 | D37: =SUM(D31:D36) -> 0
A38: Net (Decrease)/Increase in cash and cash equivalent | B38: =B20+B28+B37 -> 0 | C38: =C20+C28+C37 -> 0 | D38: =D20+D28+D37 -> 0
A39: Cash and cash equivalent at the beginning of the year
A40: Cash and cash equivalent at the end of the year | B40: =SUM(B38:B39) -> 0 | C40: =SUM(C38:C39) -> 0 | D40: =SUM(D38:D39) -> 0
