Workbook
Name BALANCE1_LDA01: '[1]Financial Statements'!$E$112
Name BALANCE1_LDA12: '[1]Financial Statements'!$E$123
Name BALANCE2_LDA01: '[1]Financial Statements'!$F$112
Name BALANCE2_LDA12: '[1]Financial Statements'!$F$123
Name BALANCE3_LDA01: '[1]Financial Statements'!$G$112
Name BALANCE3_LDA12: '[1]Financial Statements'!$G$123
Name BALANCE4_LDA01: '[1]Financial Statements'!$H$112
Name BALANCE4_LDA12: '[1]Financial Statements'!$H$123
Name BALANCE5_LDA01: '[1]Financial Statements'!$I$112
Name BALANCE5_LDA12: '[1]Financial Statements'!$I$123
Name BALANCE6_LDA01: '[1]Financial Statements'!$J$112
Name BALANCE6_LDA12: '[1]Financial Statements'!$J$123
Name NotApplicable: #REF!
Name PEARLS1_LA002: '[1]Financial Statements'!$E$280
Name PEARLS1_LE008: '[1]Financial Statements'!$E$275
Name PEARLS1_LE009: '[1]Financial Statements'!$E$276
Name PEARLS1_LR001: '[1]Financial Statements'!$E$282
Name PEARLS1_LR005: '[1]Financial Statements'!$E$286
Name PEARLS1_LR006: '[1]Financial Statements'!$E$287
Name PEARLS1_LR007: '[1]Financial Statements'!$E$288
Name PEARLS1_LR009: '[1]Financial Statements'!$E$290
Name PEARLS1_LS001: '[1]Financial Statements'!$E$298
Name PEARLS1_LS005: '[1]Financial Statements'!$E$302
Name PEARLS1_LS011: '[1]Financial Statements'!$E$308
Name PEARLS2_LA002: '[1]Financial Statements'!$F$280
Name PEARLS2_LE008: '[1]Financial Statements'!$F$275
Name PEARLS2_LE009: '[1]Financial Statements'!$F$276
Name PEARLS2_LR001: '[1]Financial Statements'!$F$282
Name PEARLS2_LR005: '[1]Financial Statements'!$F$286
Name PEARLS2_LR006: '[1]Financial Statements'!$F$287
Name PEARLS2_LR007: '[1]Financial Statements'!$F$288
Name PEARLS2_LR009: '[1]Financial Statements'!$F$290
Name PEARLS2_LS001: '[1]Financial Statements'!$F$298
Name PEARLS2_LS005: '[1]Financial Statements'!$F$302
Name PEARLS2_LS010: '[1]Financial Statements'!$F$307
Name PEARLS2_LS011: '[1]Financial Statements'!$F$308
Name PEARLS3_LA002: '[1]Financial Statements'!$G$280
Name PEARLS3_LE008: '[1]Financial Statements'!$G$275
Name PEARLS3_LE009: '[1]Financial Statements'!$G$276
Name PEARLS3_LR001: '[1]Financial Statements'!$G$282
Name PEARLS3_LR005: '[1]Financial Statements'!$G$286
Name PEARLS3_LR006: '[1]Financial Statements'!$G$287
Name PEARLS3_LR007: '[1]Financial Statements'!$G$288
Name PEARLS3_LR009: '[1]Financial Statements'!$G$290
Name PEARLS3_LS001: '[1]Financial Statements'!$G$298
Name PEARLS3_LS005: '[1]Financial Statements'!$G$302
Name PEARLS3_LS010: '[1]Financial Statements'!$G$307
Name PEARLS3_LS011: '[1]Financial Statements'!$G$308
Name PEARLS4_LA002: '[1]Financial Statements'!$H$280
Name PEARLS4_LE008: '[1]Financial Statements'!$H$275
Name PEARLS4_LE009: '[1]Financial Statements'!$H$276
Name PEARLS4_LR001: '[1]Financial Statements'!$H$282
Name PEARLS4_LR005: '[1]Financial Statements'!$H$286
Name PEARLS4_LR006: '[1]Financial Statements'!$H$287
Name PEARLS4_LR007: '[1]Financial Statements'!$H$288
Name PEARLS4_LR009: '[1]Financial Statements'!$H$290
Name PEARLS4_LS001: '[1]Financial Statements'!$H$298
Name PEARLS4_LS005: '[1]Financial Statements'!$H$302
Name PEARLS4_LS010: '[1]Financial Statements'!$H$307
Name PEARLS4_LS011: '[1]Financial Statements'!$H$308

Sheet Trend
B1: SOTICO SACCO
B2: ASSETS | C2: Audit 2016 | D2: Audit 2017 | E2: Audit 2018 | F2: Audit 2019 | G2: 43831 | H2: 43862 | I2: 43891 | J2: 43922 | K2: 43952 | L2: 43983 | M2: 44013 | N2: 44044 | O2: 44075 | P2: 44105 | Q2: 44136 | R2: 44166 | S2: Audited 2020 | T2: 44217 | U2: 44248 | V2: 44276 | W2: 44307 | X2: 44337 | Y2: 44368 | Z2: 44398 | AA2: 44429 | AB2: 44460 | AC2: 44490 | AD2: 44521 | AE2: 44551 | AF2: audited 21 | AG2: 44582 | AH2: 44613 | AI2: 44641 | AJ2: 44672 | AK2: 44702 | AL2: 44733 | AM2: 44763 | AN2: 44794 | AO2: 44825 | AP2: 44855 | AQ2: 44886 | AR2: 44916 | AS2: Audited 2022 | AT2: 44927 | AU2: 44958 | AV2: 44986 | AW2: 45017 | AX2: 45047 | AY2: 45078 | AZ2: 45108 | BA2: 45139 | BB2: 45170 | BC2: 45200
B3: Cash and Cash Equivalent | C3: =C4+C5 -> 27227584 | D3: =D4+D5 -> 20473615 | E3: =E4+E5 -> 29501244 | F3: =F4+F5 -> 52141499 | G3: =G4+G5 -> 28844168 | H3: =H4+H5 -> 28253972 | I3: =I4+I5 -> 41920668 | J3: =J4+J5 -> 37566335 | ... BC3: =BC4+BC5 -> 0
B4: Cash in hand(both local and foreign notes and coins) | C4: 169124 | D4: 895020 | E4: 1271319 | F4: 3664875 | G4: 1795796 | H4: 2840851 | I4: 11998592 | J4: 2633772 | K4: 2443459 | L4: 1180714 | M4: 1859636 | N4: 1697909 | O4: 3188901 | P4: 1602048 | Q4: 279037 | R4: 648514 | S4: 631414 | T4: 1512742 | U4: 1735893 | V4: 4383087 | W4: 744029 | X4: 1864038 | Y4: 1410962 | Z4: 695173 | AA4: 577366 | AB4: 528792 | AC4: 733129 | AD4: 737157 | AE4: 1327867 | AF4: 1200917 | AG4: 1463496 | AH4: 397781 | AI4: 1935733 | AJ4: 1225532 | AK4: 292550 | AL4: 758099 | AM4: 1875881 | AN4: 2344131 | AO4: 2474530 | AP4: 2879290 | AQ4: 1345227 | AR4: 4462609 | AS4: 4328509 | AT4: 2535627 | AU4: 937581 | AV4: 1291167 | AW4: 656334 | AX4: 630848 | AY4: 1296450 | AZ4: 3799733
B5: Cash at bank:(placement with financial institutions) | C5: 27058460 | D5: 19578595 | E5: 28229925 | F5: =52141499-3664875 -> 48476624 | G5: 27048372 | H5: 25413121 | I5: 29922076 | J5: 34932563 | K5: 33397671 | L5: 33252214 | M5: 30648873 | N5: 28143498 | O5: 28705517 | P5: 25104929 | Q5: 30725664 | R5: 27038645 | S5: =27606849-S4 -> 26975435 | T5: 35633245 | U5: 32524837 | V5: 33033300 | W5: 34540914 | X5: 30026103 | Y5: 29131596 | Z5: 21076734 | AA5: 19527515 | AB5: 21883073 | AC5: 25014973 | AD5: 48735601 | AE5: 25612090 | AF5: 25645434 | AG5: 31826537 | AH5: 21620058 | AI5: 29450093 | AJ5: 16931651 | AK5: 16881830 | AL5: 24688130 | AM5: 25726686 | AN5: 21493412 | AO5: 23906817 | AP5: 25671312 | AQ5: 29994725 | AR5: 24165791 | AS5: =5505784+537250+17519568+15000+134100+588189 -> 24299891 | AT5: 25365880 | AU5: 24212389 | AV5: 15699303 | AW5: 20973910 | AX5: 21016722 | AY5: 25853378 | AZ5: 48236559
B7: Prepayments and Sundry Receivables | C7: 625108 | D7: 109588 | E7: 292674 | F7: 83945 | G7: 1374105.4 | H7: 1264313.4 | I7: 1198812.4 | J7: 1198812.4 | K7: 990479.02 | L7: 948812.35 | M7: 982916.35 | N7: 982916.35 | O7: 863394.35 | P7: 854931.35 | Q7: 112307.18 | R7: 661012.35 | S7: 81853 | T7: 752023.35 | U7: 690999.35 | V7: 682023.35 | W7: 682023.35 | X7: 397847.52 | Y7: 341012.35 | Z7: 284177.18 | AA7: 227342.02 | AB7: 170506.85 | AC7: 113671.68 | AD7: 56836.52 | AE7: 769726.5 | AF7: 912262 | AG7: 906229.18 | AH7: 500716.86 | AI7: 928158.75 | AJ7: 121349.35 | AK7: 106180.85 | AL7: 91012.35 | AM7: 75843.85 | AN7: 1.35 | AO7: 1.35 | AP7: 1.35 | AQ7: 1.35 | AR7: 667030.22 | AS7: 674602 | AT7: 731249.5 | AU7: 763289.5 | AV7: 0 | AW7: 640688.98 | AX7: 820328.67 | AY7: 657174.8 | AZ7: 951507.05
B9: Financial Investments | C9: =SUM(C10:C14) -> 40449810 | D9: =SUM(D10:D14) -> 49120055 | E9: =SUM(E10:E14) -> 49120055 | F9: =SUM(F10:F14) -> 49120055 | G9: =SUM(G10:G14) -> 49120055 | H9: =SUM(H10:H14) -> 49120055 | I9: =SUM(I10:I14) -> 49120055 | J9: =SUM(J10:J14) -> 49120055 | ... BC9: =SUM(BC10:BC14) -> 0
B10: Government Securities - Treasury Bills/bonds, | G10: 0 | H10: 0 | I10: 0 | J10: 0 | K10: 0 | L10: 0 | M10: 0 | N10: 0 | O10: 0 | P10: 0 | Q10: 0 | R10: 0 | S10: 0 | T10: 0 | U10: 0 | V10: 0 | W10: 0 | X10: 0 | Y10: 0 | Z10: 0 | AA10: 0 | AB10: 0 | AC10: 0 | AD10: 0 | AE10: 0 | AG10: 0 | AH10: 0 | AI10: 0 | AJ10: 0 | AK10: 0 | AL10: 0 | AM10: 0 | AN10: 0 | AO10: 0 | AP10: 0 | AQ10: 0 | AR10: 0 | AS10: 0 | AT10: 0 | AU10: 0 | AV10: 0 | AW10: 0 | AX10: 0 | AY10: 0 | AZ10: 0
B11: Other Securities - Commercial papers/Bonds | G11: 0 | H11: 0 | I11: 0 | J11: 0 | K11: 0 | L11: 0 | M11: 0 | N11: 0 | O11: 0 | P11: 0 | Q11: 0 | R11: 0 | S11: 0 | T11: 0 | U11: 0 | V11: 0 | W11: 0 | X11: 0 | Y11: 0 | Z11: 0 | AA11: 0 | AB11: 0 | AC11: 0 | AD11: 0 | AE11: 0 | AG11: 0 | AH11: 0 | AI11: 0 | AJ11: 0 | AK11: 0 | AL11: 0 | AM11: 0 | AN11: 0 | AO11: 0 | AP11: 0 | AQ11: 0 | AR11: 0 | AT11: 0 | AU11: 0 | AV11: 0 | AW11: 0 | AX11: 0 | AY11: 0 | AZ11: 0
B12: Balances with other SACCO Societies | G12: 0 | H12: 0 | I12: 0 | J12: 0 | K12: 0 | L12: 0 | M12: 0 | N12: 0 | AB12: 0 | AC12: 0 | AD12: 0 | AE12: 0 | AG12: 5151497.8 | AH12: 5151497.8 | AI12: 5151497.8 | AJ12: 5151497.8 | AK12: 5151497.8 | AL12: 5151497.8 | AM12: 5151497.8 | AN12: 5151497.8 | AO12: 5151497.8 | AP12: 5151497.8 | AQ12: 5151497.8 | AR12: 5151497.8 | AS12: =5051088+35280+65130 -> 5151498 | AT12: 5151497.8 | AU12: 5151497.8 | AV12: 5151497.8 | AW12: 5151497.8 | AX12: 5151497.8 | AY12: 5151497.8 | AZ12: 0
B13: Equity Investments in NACCOs(Shares in- CIC, KUSCCO, COOP BANK,CAK, KERUSSU) | C13: 40449810 | D13: 49120055 | E13: 49120055 | F13: 49120055 | G13: 49120055 | H13: 49120055 | I13: 49120055 | J13: 49120055 | K13: 49120055 | L13: 49120055 | M13: 49120055 | N13: 49120055 | O13: 49120055 | P13: 49120055 | Q13: 49120055 | R13: 49120055 | S13: 5151498 | T13: 49120055 | U13: 5151497.8 | V13: 5151497.8 | W13: 5151497.8 | X13: 5151497.8 | Y13: 5151497.8 | Z13: 5151497.8 | AA13: 5151497.8 | AB13: 5151497.8 | AC13: 5151497.8 | AD13: 5151497.8 | AE13: 5151497.8 | AF13: 5151498 | AG13: 0 | AH13: 0 | AI13: 0 | AJ13: 0 | AK13: 0 | AL13: 0 | AM13: 0 | AN13: 0 | AO13: 0 | AP13: 0 | AQ13: 0 | AR13: 0
B14: Investments in companies - shares/stocks | AQ14: 0 | AR14: 0 | AS14: 0 | AT14: 0 | AU14: 0 | AV14: 0 | AW14: 5151497.8
B16: Net Loan Portfolio | C16: =C17-C18 -> 108864930 | D16: =D17-D18 -> 112673981 | E16: =E17-E18 -> 118004126 | F16: =F17-F18 -> 126643002 | G16: =G17-G18 -> 144740267 | H16: =H17-H18 -> 139423704 | I16: =I17-I18 -> 138129985 | J16: =J17-J18 -> 133289652 | ... BC16: =BC17-BC18 -> 0
B17: Gross Loan Portfolio | C17: 112489704 | D17: 116513632 | E17: 121965745 | F17: 131804621 | G17: 149901886 | H17: 144585323 | I17: 143291604 | J17: 138451271 | K17: 139995318 | L17: 140220540 | M17: 1.4525861e+08 | N17: 150498478 | O17: 160536761 | P17: 166635163 | Q17: 170750046 | R17: 170698863 | S17: 1.7059549e+08 | T17: 178942254 | U17: 178656087 | V17: 174685518 | W17: 174679684 | X17: 173688465 | Y17: 171002891 | Z17: 189899417 | AA17: 187254428 | AB17: 183109082 | AC17: 183367220 | AD17: 178461929 | AE17: 181539412 | AF17: 181532478 | AG17: 178604455 | AH17: 174805092 | AI17: 171770087 | AJ17: 188776405 | AK17: 187498957 | AL17: 184227194 | AM17: 182534610 | AN17: 188451436 | AO17: 189307357 | AP17: 192071109 | AQ17: 187514511 | AR17: 191230019 | AS17: =188945414+2285196 -> 191230610 | AT17: 210078476 | AU17: 212498557 | AV17: 203656338 | AW17: 197965618 | AX17: 197327218 | AY17: 195353913 | AZ17: 187471588
B18: Allowance for Loan Loss | C18: 3624774 | D18: 3839651 | E18: 3961619 | F18: 5161619 | G18: 5161619 | H18: 5161619 | I18: 5161619 | J18: 5161619 | K18: 5494952.3 | L18: 5561619 | M18: 5661619 | N18: 5661619 | O18: 5661619 | P18: 5661619 | Q18: 5661619 | R18: 5661619 | S18: 5661619 | T18: 5661619 | U18: 5661619 | V18: 5661619 | W18: 5661619 | X18: 5661619 | Y18: 5661619 | Z18: 5661619 | AA18: 5661619 | AB18: 5661619 | AC18: 5661619 | AD18: 5661619 | AE18: 5961619 | AF18: 5961619 | AG18: 5961619 | AH18: 5961619 | AI18: 5961619 | AJ18: 5961619 | AK18: 5961619 | AL18: 5961619 | AM18: 5961619 | AN18: 5961619 | AO18: 5961619 | AP18: 5961619 | AQ18: 5961619 | AR18: 6261619 | AS18: 6261619 | AT18: 6261619 | AU18: 6261619 | AV18: 6261619 | AW18: 6261619 | AX18: 6261619 | AY18: 6411619 | AZ18: 6411619
AS19: 0
B20: Account Receivables | C20: =SUM(C21:C23) -> 0 | D20: =SUM(D21:D23) -> 0 | E20: =SUM(E21:E23) -> 0 | F20: =SUM(F21:F23) -> 24654 | G20: =SUM(G21:G23) -> 24654.37 | H20: =SUM(H21:H23) -> 24654.37 | I20: =SUM(I21:I23) -> 24654.37 | J20: =SUM(J21:J23) -> 24654.37 | ... AE20: =SUM(AE21:AE23) -> 0 | AF20: 0 | AG20: =SUM(AG21:AG23) -> 0 | AH20: =SUM(AH21:AH23) -> 0 | AI20: =SUM(AI21:AI23) -> 0 | AJ20: =SUM(AJ21:AJ23) -> 0 | AK20: =SUM(AK21:AK23) -> 0 | AL20: =SUM(AL21:AL23) -> 0 | AM20: =SUM(AM21:AM23) -> 0 | AN20: =SUM(AN21:AN23) -> 0 | ... BC20: =SUM(BC21:BC23) -> 0
B21: Tax Recoverable | G21: 0 | H21: 0 | I21: 0 | J21: 0 | K21: 0 | L21: 0 | N21: 0 | O21: 0 | P21: 0 | Q21: 0 | R21: 0 | S21: 0 | T21: 0 | U21: 0 | V21: 0 | W21: 0 | X21: 0 | Y21: 0 | Z21: 0 | AA21: 0 | AS21: 87423 | AT21: 0 | AU21: 0 | AV21: 0 | AW21: 0 | AX21: 0 | AY21: 0 | AZ21: 0
B22: Deferred Tax Assets | F22: 24654 | G22: 24654.37 | H22: 24654.37 | I22: 24654.37 | J22: 24654.37 | K22: 24654.37 | L22: 24654.37 | M22: 24654.365 | N22: 24654.37 | O22: 24654.37 | P22: 24654.37 | Q22: 24654.37 | R22: 24654.37 | S22: 24654.37 | T22: 24654.37 | U22: 0 | V22: 0 | W22: 0 | X22: 0 | Y22: 0 | Z22: 0 | AA22: 0 | AS22: 0 | AT22: 0 | AU22: 0 | AV22: 0 | AW22: 0 | AX22: 0 | AY22: 0 | AZ22: 0
B23: Retirement Benefit Assets | G23: 0 | H23: 0 | I23: 0 | J23: 0 | K23: 0 | L23: 0 | N23: 0 | O23: 0 | P23: 0 | Q23: 0 | R23: 0 | S23: 0 | T23: 0 | U23: 0 | V23: 0 | W23: 0 | X23: 0 | Y23: 0 | Z23: 0 | AA23: 0 | AS23: 0 | AT23: 0 | AU23: 0 | AV23: 0 | AW23: 0 | AX23: 0 | AY23: 0 | AZ23: 0
B25: Property and Equipment and Other Assets | C25: =SUM(C26:C30) -> 12988708 | D25: =SUM(D26:D30) -> 16405838 | E25: =SUM(E26:E30) -> 18915297 | F25: =SUM(F26:F30) -> 18369726 | G25: =SUM(G26:G30) -> 17066422 | H25: =SUM(H26:H30) -> 17019582 | I25: =SUM(I26:I30) -> 17004895 | J25: =SUM(J26:J30) -> 16944609 | ... BC25: =SUM(BC26:BC30) -> 0
B26: Investment Properties | F26: 4728302 | G26: 4038480 | H26: 4728302 | I26: 4728302 | J26: 4728302 | K26: 4728302 | L26: 4728302 | M26: 4728302 | N26: 4728302 | O26: 4728302 | P26: 4728302 | Q26: 4728302 | R26: 4728302 | T26: 4728302 | U26: 4728302 | V26: 4774302 | W26: 4781552 | X26: 4781552 | Y26: 4781552 | Z26: 4821552 | AA26: 4938552 | AB26: 6310511.4 | AC26: 5990211.4 | AD26: 5990211.4 | AE26: 5990211.4 | AG26: 5990211.4 | AH26: 5990211.4 | AI26: 5990211.4 | AJ26: 5990211.4 | AK26: 5990211.4 | AL26: 5990211.4 | AM26: 5990211.4 | AN26: 5990211.4 | AO26: 5990211.4 | AP26: 5990211.4 | AQ26: 5990211.4 | AR26: 5990211.4 | AT26: 5990211.4 | AU26: 5990211.4 | AV26: 5990211.4 | AW26: 5990211.4 | AX26: 5990211.4 | AY26: 5990211.4 | AZ26: 5990211
B27: Property and Equipment | C27: 10052178 | D27: 14045660 | E27: 16051260 | F27: =10646547+399391+117946+468108 -> 11631992 | G27: 12221216 | H27: 11505240 | I27: 11511238 | J27: 11445987 | K27: 11380736 | L27: 11357710 | M27: 11357710 | N27: 11225284 | O27: 11159071 | P27: 11092858 | Q27: 11038721 | R27: 10972366 | S27: 15634519 | T27: 10849265 | U27: 10865392 | V27: 10807179 | W27: 10748967 | X27: 10711265 | Y27: 10652826 | Z27: 10594388 | AA27: 10535950 | AB27: 10477512 | AC27: 10587505 | AD27: 10524818 | AE27: 10465663 | AF27: 16491564 | AG27: 10450124 | AH27: 10398896 | AI27: 10347668 | AJ27: 10296440 | AK27: 10245212 | AL27: 10193984 | AM27: 10157352 | AN27: 10105995 | AO27: 10054638 | AP27: 10003280 | AQ27: 11455428 | AR27: 9900566 | AS27: 15890778 | AT27: 9853417 | AU27: 9806268 | AV27: 9759119 | AW27: 9711970 | AX27: 9664821 | AY27: 9617672 | AZ27: 9570523
B28: Prepaid lease rentals | G28: 0 | H28: 0 | I28: 0 | J28: 0 | K28: 0 | L28: 0 | M28: 0 | N28: 0 | O28: 0 | P28: 0 | Q28: 0 | R28: 0 | T28: 0 | U28: 0 | V28: 0 | W28: 0 | X28: 0 | Y28: 0 | Z28: 0 | AA28: 0 | AB28: 0 | AC28: 0 | AD28: 0 | AE28: 0 | AG28: 0 | AH28: 0 | AI28: 0 | AJ28: 0 | AK28: 0 | AL28: 0 | AM28: 0 | AN28: 0 | AO28: 0 | AP28: 0 | AQ28: 0 | AR28: 0 | AT28: 0 | AU28: 0 | AV28: 0 | AW28: 0 | AX28: 0 | AY28: 0 | AZ28: 0
B29: intangible assets | C29: 254508 | D29: 178156.03 | E29: 1182015 | F29: 827410 | G29: 806725.58 | H29: 786040.31 | I29: 765355.04 | J29: 770319.77 | K29: 748922 | L29: 703299.23 | M29: 703299.23 | N29: 661928.68 | O29: 641243.41 | P29: 620558.14 | Q29: 599872.87 | R29: 579187.6 | S29: 645336 | T29: 579187.6 | U29: 613069.67 | V29: 596936.26 | W29: 580802.85 | X29: 564669.44 | Y29: 548536.02 | Z29: 532402.61 | AA29: 516269.2 | AB29: 500135.79 | AC29: 484002.37 | AD29: 467868.96 | AE29: 451735.55 | AF29: 484002 | AG29: 473919.2 | AH29: 463835.81 | AI29: 453752.42 | AJ29: 443669.04 | AK29: 433585.65 | AL29: 423502.26 | AM29: 413418.88 | AN29: 403335.49 | AO29: 393252.1 | AP29: 383168.71 | AQ29: 373085.33 | AR29: 363001.94 | AS29: 363001 | AT29: 355439.64 | AU29: 347877.1 | AV29: 340314.55 | AW29: 332752.01 | AX29: 325189.46 | AY29: 317626.92 | AZ29: 310064
B30: Other Assets | C30: 2682022 | D30: 2182022 | E30: 1682022 | F30: 1182022 | G30: 0 | H30: 0 | I30: 0 | J30: 0 | K30: 0 | L30: 0 | N30: 0 | O30: 0 | P30: 0 | Q30: 0 | R30: 0 | S30: 682022 | T30: 0 | U30: 0 | V30: 0 | W30: 0 | X30: 0 | Y30: 0 | Z30: 0 | AA30: 0 | AB30: 0 | AC30: 0 | AD30: 0 | AE30: 0 | AG30: 0 | AH30: 0 | AI30: 0 | AJ30: 0 | AK30: 0 | AL30: 0 | AM30: 0 | AN30: 0 | AO30: 0 | AP30: 0 | AQ30: 0 | AR30: 0 | AT30: 0 | AU30: 0 | AV30: 0 | AW30: 0 | AX30: 0 | AY30: 0 | AZ30: 0
B32: Total Assets | C32: =C3+C7+C9+C16+C20+C25 -> 190156140 | D32: =D3+D7+D9+D16+D20+D25 -> 1.9878308e+08 | E32: =E3+E7+E9+E16+E20+E25 -> 215833396 | F32: =F3+F7+F9+F16+F20+F25 -> 246382881 | G32: =G3+G7+G9+G16+G20+G25 -> 2.4116967e+08 | H32: =H3+H7+H9+H16+H20+H25 -> 2.3510628e+08 | I32: =I3+I7+I9+I16+I20+I25 -> 2.4739907e+08 | J32: =J3+J7+J9+J16+J20+J25 -> 2.3814412e+08 | ... AS32: =AS3+AS7+AS9+AS16+AS20+AS25 -> 235764693 | AT32: =AT3+#REF!+AT9+AT16+AT20+AT25 -> #REF! | AU32: =AU3+#REF!+AU9+AU16+AU20+AU25 -> #REF! | AV32: =AV3+#REF!+AV9+AV16+AV20+AV25 -> #REF! | AW32: =AW3+#REF!+AW9+AW16+AW20+AW25 -> #REF! | AX32: =AX3+#REF!+AX9+AX16+AX20+AX25 -> #REF! | AY32: =AY3+#REF!+AY9+AY16+AY20+AY25 -> #REF! | AZ32: =AZ3+#REF!+AZ9+AZ16+AZ20+AZ25 -> #REF! | BA32: =BA3+BA7+BA9+BA16+BA20+BA25 -> 0 | BB32: =BB3+BB7+BB9+BB16+BB20+BB25 -> 0 | BC32: =BC3+BC7+BC9+BC16+BC20+BC25 -> 0
B34: LIABILITIES
B35: Savings Deposits - Withdrawable deposits - FOSA) | C35: 8225206 | D35: 7582824 | E35: 12295782 | F35: =2750359+13768541 -> 16518900 | G35: 10725594 | H35: 9323076 | I35: 9323076 | J35: 9323076 | K35: 12848608 | L35: 12332975 | M35: 12332975 | N35: 11041856 | O35: 12509093 | P35: 11318113 | Q35: 16644640 | R35: 14908062 | S35: 14908062 | T35: 14174609 | U35: 14174609 | V35: 24128229 | W35: 12983252 | X35: 13708126 | Y35: 12824131 | Z35: 16101738 | AA35: 16384201 | AB35: 12302073 | AC35: 11240594 | AD35: 11011255 | AE35: 11261843 | AF35: 10866395 | AG35: 11477157 | AH35: 13578330 | AI35: 15269225 | AJ35: 16288304 | AK35: 14249401 | AL35: 14249401 | AM35: 11203778 | AN35: 12634700 | AO35: 12403805 | AP35: 13252408 | AQ35: 12393395 | AR35: 11231947 | AS35: 11188730
B36: Short Term Deposits (e.g Fixed deposits, special savings) | C36: 1506728 | D36: 972987 | G36: 2210643 | H36: 2214951 | I36: 1961671 | J36: 2086980 | K36: 2963541 | L36: 3022835 | M36: 3143066.1 | N36: 3724149 | O36: 3597590 | P36: 3604241 | Q36: 3744423 | R36: 3455423 | S36: 3455423 | T36: 3329227 | U36: 3219756 | V36: 3058071 | W36: 3498168 | X36: 2686474 | Y36: 2616111 | Z36: 2045376 | AA36: 2359674 | AB36: 2037786 | AC36: 2560064 | AD36: 2649900 | AE36: 3329981 | AF36: 3732181 | AG36: 3629057 | AH36: 3297345 | AI36: 4706910 | AJ36: 3317899 | AK36: 3491565 | AL36: 3197394 | AM36: 3544007 | AN36: 3602829 | AO36: 3768963 | AP36: 3565751 | AQ36: 3984635 | AR36: 3956965 | AS36: =981250+2975715 -> 3956965
B37: Non withdrawable deposits (BOSA member deposits) | C37: 93532161 | D37: 98991963 | E37: 109828204 | F37: 116729770 | G37: 117465834 | H37: 118247917 | I37: 119559661 | J37: 120700906 | K37: 122212542 | L37: 124213870 | M37: 1.2626295e+08 | N37: 128279307 | O37: 130016226 | P37: 131724520 | Q37: 133734795 | R37: 135994936 | S37: 135994936 | T37: 136653263 | U37: 137537284 | V37: 139195096 | W37: 140475752 | X37: 141528870 | Y37: 141453588 | Z37: 142098601 | AA37: 142486180 | AB37: 143168702 | AC37: 143994254 | AD37: 143554875 | AE37: 146927870 | AF37: 146924536 | AG37: 147221478 | AH37: 148468081 | AI37: 150105966 | AJ37: 151905118 | AK37: 152648620 | AL37: 152865832 | AM37: 153860576 | AN37: 154727604 | AO37: 155462672 | AP37: 158029895 | AQ37: 156535062 | AR37: 157906218 | AS37: 157906218
B38: Total Deposit Liabilities | C38: =SUM(C35:C37) -> 103264095 | D38: =SUM(D35:D37) -> 107547774 | E38: =SUM(E35:E37) -> 122123986 | F38: =SUM(F35:F37) -> 133248670 | G38: =SUM(G35:G37) -> 130402071 | H38: =SUM(H35:H37) -> 129785944 | I38: =SUM(I35:I37) -> 130844408 | J38: =SUM(J35:J37) -> 132110962 | ... AE38: =SUM(AE35:AE37) -> 161519694 | AF38: 161523112 | AG38: =SUM(AG35:AG37) -> 162327692 | AH38: =SUM(AH35:AH37) -> 165343756 | AI38: =SUM(AI35:AI37) -> 170082101 | AJ38: =SUM(AJ35:AJ37) -> 171511321 | AK38: =SUM(AK35:AK37) -> 170389586 | AL38: =SUM(AL35:AL37) -> 170312627 | AM38: =SUM(AM35:AM37) -> 168608361 | AN38: =SUM(AN35:AN37) -> 170965133 | ... BC38: =SUM(BC35:BC37) -> 0
B40: Accounts Payable Other Liabilities | C40: =SUM(C41:C46) -> 25491076 | D40: =SUM(D41:D46) -> 19847333 | E40: =SUM(E41:E46) -> 21277512 | F40: =SUM(F41:F46) -> 39923867 | G40: =SUM(G41:G46) -> 36157376 | H40: =SUM(H42:H46) -> 31404626 | I40: =SUM(I42:I46) -> 42591870 | J40: =SUM(J42:J46) -> 32154417 | K40: =SUM(K42:K46) -> 24771760 | L40: =SUM(L42:L46) -> 21188898 | M40: =SUM(M42:M46) -> 21177452 | N40: =SUM(N42:N46) -> 21688671 | O40: =SUM(O42:O46) -> 29589025 | ... S40: =SUM(S42:S46) -> 26166271 | T40: =T41+T42+T43+T44+T45+T46 -> 44792538 | U40: =U41+U42+U43+U44+U45+U46 -> 40229835 | V40: =V41+V42+V43+V44+V45+V46 -> 27648444 | W40: =W41+W42+W43+W44+W45+W46 -> 31182796 | X40: =X41+X42+X43+X44+X45+X46 -> 25544616 | Y40: =Y41+Y42+Y43+Y44+Y45+Y46 -> 22264807 | Z40: =Z41+Z42+Z43+Z44+Z45+Z46 -> 29286390 | AA40: =AA41+AA42+AA43+AA44+AA45+AA46 -> 23802904 | ... AE40: =AE41+AE42+AE43+AE44+AE45+AE46 -> 26401893 | AF40: 28558245 | AG40: =AG41+AG42+AG43+AG44+AG45+AG46 -> 30937410 | AH40: =AH41+AH42+AH43+AH44+AH45+AH46 -> 12178724 | AI40: =AI41+AI42+AI43+AI44+AI45+AI46 -> 13403851 | AJ40: =AJ41+AJ42+AJ43+AJ44+AJ45+AJ46 -> 15127650 | AK40: =AK41+AK42+AK43+AK44+AK45+AK46 -> 13514942 | AL40: =AL41+AL42+AL43+AL44+AL45+AL46 -> 18119376 | AM40: =AM41+AM42+AM43+AM44+AM45+AM46 -> 19692739 | AN40: =AN41+AN42+AN43+AN44+AN45+AN46 -> 18673318 | ... BC40: =BC41+BC42+BC43+BC44+BC45+BC46 -> 0
B41: Tax Payable | C41: 46171 | D41: 45756 | E41: 66991 | F41: 0 | G41: 0 | H41: 0 | I41: 0 | J41: 0 | K41: 0 | L41: 0 | N41: 0 | O41: 0 | P41: 0 | Q41: 0 | R41: 0 | S41: 0 | T41: 0 | U41: 3057048 | V41: 3117312 | W41: 789464 | X41: 536064 | Y41: 84408 | Z41: 145703 | AA41: 207313 | AB41: 264868 | AC41: 309927 | AD41: 380294 | AE41: 351837 | AF41: 33481 | AG41: 315592 | AH41: 537672 | AI41: 430774 | AJ41: 318125 | AK41: 395314 | AL41: 315771 | AM41: 376319 | AN41: 423512 | AO41: 247907 | AP41: 297130 | AQ41: 407657 | AR41: 204879 | AS41: 0
B42: Dividends Payable | C42: 10618031 | D42: 11160836 | E42: 12285140 | F42: 13018317 | G42: 12813817 | H42: 14813817 | I42: 14940262 | J42: 3800755 | K42: 8514761 | L42: 9214331 | M42: 10014331 | N42: 11013741 | O42: 12013281 | P42: 13013281 | Q42: 13763281 | R42: 13598769 | S42: 13598769 | T42: 16178541 | U42: 1445817 | V42: 743561 | W42: 9068 | X42: 9068 | Y42: 9068 | Z42: 8468 | AA42: 4388 | AB42: 3528 | AC42: 3528 | AD42: 2248 | AE42: 2248 | AF42: 16669637 | AG42: 1639429 | AH42: 2681850 | AI42: 2510683 | AJ42: 3806545 | AK42: 5097204 | AL42: 10199543 | AM42: 10906945 | AN42: 11613057 | AO42: 12963710 | AP42: 14494561 | AQ42: 15661993 | AR42: 15799109 | AS42: 15284564
B43: Deferred Tax Liability | G43: 0 | H43: 0 | I43: 0 | J43: 0 | K43: 0 | L43: 0 | M43: 0 | N43: 0 | O43: 0 | P43: 0 | Q43: 0 | R43: 0 | S43: 0 | T43: 0 | U43: 0 | V43: 0 | W43: 0 | X43: 0 | Y43: 0 | Z43: 0 | AA43: 0 | AB43: 0 | AC43: 0 | AD43: 0 | AE43: 0 | AG43: 0 | AH43: 0 | AI43: 0 | AJ43: 0 | AK43: 0 | AL43: 0 | AM43: 0 | AN43: 0 | AO43: 0 | AP43: 0 | AQ43: 0 | AR43: 0
B44: Retirement Benefits Liability | E44: 1578142 | F44: 1841591 | G44: 0 | H44: 0 | I44: 0 | J44: 0 | K44: 0 | L44: 0 | M44: 0 | N44: 0 | O44: 0 | P44: 0 | Q44: 0 | R44: 0 | S44: 0 | T44: 0 | U44: 0 | V44: 0 | W44: 0 | X44: 0 | Y44: 0 | Z44: 0 | AA44: 0 | AB44: 0 | AC44: 0 | AD44: 0 | AE44: 0 | AG44: 2452000 | AH44: 2452000 | AI44: 2505789 | AJ44: 2532684 | AK44: 2559579 | AL44: 2586474 | AM44: 2613368 | AN44: 2640263 | AO44: 2667158 | AP44: 2694052 | AQ44: 2747842 | AR44: 2747842
B45: Other Liabilities | C45: 7826874 | D45: 8640741 | E45: 7347239 | F45: 13063959 | G45: 15424764 | H45: 12760343 | I45: 15651608 | J45: 20474711 | K45: 12539722 | L45: 11974567 | M45: 11163121 | N45: 10674930 | O45: 9575744 | P45: 10618644 | Q45: 11947976 | R45: 12567502 | S45: 12567502 | T45: 16613997 | U45: 27868011 | V45: 11787571 | W45: 18384264 | X45: 17170443 | Y45: 18128591 | Z45: 17132219 | AA45: 15676682 | AB45: 19189083 | AC45: 23016791 | AD45: 44481633 | AE45: 23543552 | AF45: 9350871 | AG45: 26530389 | AH45: 6507202 | AI45: 7956605 | AJ45: 8470296 | AK45: 5462845 | AL45: 5017588 | AM45: 5796107 | AN45: 3996486 | AO45: 5265131 | AP45: 5367323 | AQ45: 5090725 | AR45: 4600070 | AS45: =4893878+2747842 -> 7641720
B46: External Borrowings | C46: 7000000 | F46: 12000000 | G46: 7918795 | H46: 3830466 | I46: 12000000 | J46: 7878951 | K46: 3717277 | L46: 0 | M46: 0 | N46: 0 | O46: 8000000 | P46: 5270648 | Q46: 2544373 | R46: 0 | S46: 0 | T46: 12000000 | U46: 7858959 | V46: 12000000 | W46: 12000000 | X46: 7829041 | Y46: 4042740 | Z46: 12000000 | AA46: 7914521 | AB46: 8000000 | AC46: 8000000 | AD46: 5227909 | AE46: 2504256 | AF46: 2504256 | AG46: 0 | AH46: 0 | AI46: 0 | AJ46: 0 | AK46: 0 | AL46: 0 | AM46: 0 | AN46: 0 | AO46: 0 | AP46: 0 | AQ46: 0 | AR46: 0 | AS46: 0
B47: Total Liabilities | C47: =C38+C40 -> 128755171 | D47: =D38+D40 -> 127395107 | E47: =E38+E40 -> 143401498 | F47: =F38+F40 -> 173172537 | G47: =G38+G40 -> 166559447 | H47: =H38+H40 -> 161190570 | I47: =I38+I40 -> 173436278 | J47: =J38+J40 -> 164265379 | ... AE47: =AE38+AE40 -> 187921587 | AF47: 190081357 | AG47: =AG38+AG40 -> 193265102 | AH47: =AH38+AH40 -> 177522480 | AI47: =AI38+AI40 -> 183485952 | AJ47: =AJ38+AJ40 -> 186638971 | AK47: =AK38+AK40 -> 183904528 | AL47: =AL38+AL40 -> 188432003 | AM47: =AM38+AM40 -> 188301100 | AN47: =AN38+AN40 -> 189638451 | ... BC47: =BC38+BC40 -> 0
B49: EQUITY
B50: Share Capital (Members share capital per Bylaws) | C50: 10092600 | D50: 10571400 | E50: 10978200 | F50: 11404800 | G50: 11404800 | H50: 11404800 | I50: 11548800 | J50: 11548800 | K50: 11667600 | L50: 11945719 | M50: 12340353 | N50: 12779540 | O50: 13211239 | P50: 13589570 | Q50: 13980210 | R50: 14458167 | S50: 14458167 | T50: 14808084 | U50: 15166381 | V50: 15288654 | W50: 15698722 | X50: 15872188 | Y50: 15939395 | Z50: 16042617 | AA50: 16118036 | AB50: 16150196 | AC50: 16181908 | AD50: 16293098 | AE50: 16370661 | AF50: 16371815 | AG50: 16392886 | AH50: 16483845 | AI50: 16569936 | AJ50: 16603732 | AK50: 16680213 | AL50: 16712323 | AM50: 16791479 | AN50: 16848441 | AO50: 16904201 | AP50: 16929441 | AQ50: 16966895 | AR50: 17043686 | AS50: 17043686
B51: Capital Grants | G51: 0 | H51: 0 | I51: 0 | J51: 0 | K51: 0 | L51: 0 | N51: 0 | O51: 0 | P51: 0 | Q51: 0 | R51: 0 | S51: 0 | T51: 0 | U51: 0 | V51: 0 | W51: 0 | X51: 0 | Y51: 0 | Z51: 0 | AA51: 0 | AB51: 0 | AC51: 0 | AD51: 0 | AE51: 0 | AG51: 0 | AH51: 0 | AI51: 0 | AJ51: 0 | AK51: 0 | AL51: 0 | AM51: 0 | AN51: 0 | AO51: 0 | AP51: 0 | AQ51: 0 | AR51: 0 | AS51: 0
B53: Retained Earnings | C53: =C54+C55 -> 1279011 | D53: =D54+D55 -> 1697046.7 | E53: =E54+E55 -> 1946285 | F53: =F54+F55 -> 1958695 | G53: =G54+G55 -> 3353455 | H53: =H54+H55 -> 2464062 | I53: =I54+I55 -> 2267142 | J53: =J54+J55 -> 2083089 | ... AE53: =AE54+AE55 -> 2571365 | AF53: 2166296 | AG53: =AG54+AG55 -> 2263767 | AH53: =AH54+AH55 -> 2211604 | AI53: =AI54+AI55 -> 2648150 | AJ53: =AJ54+AJ55 -> 2194937 | AK53: =AK54+AK55 -> 2337875 | AL53: =AL54+AL55 -> 2524547 | AM53: =AM54+AM55 -> 2657603 | AN53: =AN54+AN55 -> 3096865 | ... BC53: =BC54+BC55 -> 0
B54: Prior Years' Retained Earnings | C54: 1238165 | D54: 1279010.7 | E54: 1697047 | F54: 1946285 | G54: 1979175 | H54: 1958694 | I54: 1958694 | J54: 1958694 | K54: 1958694 | L54: 1958694 | M54: 1958694.4 | N54: 1958694 | O54: 1958694 | P54: 1958694 | Q54: 1958694 | R54: 1958694 | S54: 1958694 | T54: 1958694 | U54: 2019454 | V54: 2019454 | W54: 2019454 | X54: 2019454 | Y54: 2019454 | Z54: 2019454 | AA54: 2019454 | AB54: 2019454 | AC54: 2019454 | AD54: 2019454 | AE54: 2019454 | AF54: 2019454 | AG54: 2166297 | AH54: 2166297 | AI54: 2166297 | AJ54: 2166297 | AK54: 2166297 | AL54: 2166297 | AM54: 2166297 | AN54: 2166297 | AO54: 2166297 | AP54: 2166297 | AQ54: 2166297 | AR54: 2166297 | AS54: 2166297
B55: Current Year's Surplus | C55: 40846 | D55: 418036 | E55: 249238 | F55: =1697187-339437-1140840-204500 -> 12410 | G55: 1374280 | H55: 505368 | I55: 308448 | J55: 124395 | K55: 390084 | L55: 654883 | M55: 1050130 | N55: 1064735 | O55: 1410257 | P55: 1880312 | Q55: 1827070 | R55: 187873 | S55: 187873 | T55: 375660 | U55: 98063 | V55: 128694 | W55: 3277614 | X55: 2895364 | Y55: 2838739 | Z55: 2257665 | AA55: 2216256 | AB55: 1516477 | AC55: 364669 | AD55: 608264 | AE55: 551911 | AF55: 146842 | AG55: 97470 | AH55: 45307 | AI55: 481853 | AJ55: 28640 | AK55: 171578 | AL55: 358250 | AM55: 491306 | AN55: 930568 | AO55: 853663 | AP55: 561546 | AQ55: 933895 | AR55: 985652 | AS55: =3062352-AS54 -> 896055
B57: Other Equity Accounts | C57: =SUM(C58:C62) -> 50029358 | D57: =SUM(D58:D62) -> 59119522 | E57: =SUM(E58:E62) -> 59507412 | F57: =SUM(F58:F62) -> 59846849 | G57: =SUM(G58:G62) -> 59851969 | H57: =SUM(H58:H62) -> 60046849 | I57: =SUM(I58:I62) -> 60146849 | J57: =SUM(J58:J62) -> 60246849 | ... AE57: =SUM(AE58:AE62) -> 18482971 | AF57: 16837068 | AG57: =SUM(AG58:AG62) -> 16983096 | AH57: =SUM(AH58:AH62) -> 17148541 | AI57: =SUM(AI58:AI62) -> 17361544 | AJ57: =SUM(AJ58:AJ62) -> 17537497 | AK57: =SUM(AK58:AK62) -> 17715791 | AL57: =SUM(AL58:AL62) -> 17893141 | AM57: =SUM(AM58:AM62) -> 18213700 | AN57: =SUM(AN58:AN62) -> 18394644 | ... BC57: =SUM(BC58:BC62) -> 0
B58: Statutory Reserve | C58: 4468256 | D58: 4888175 | E58: 5276065 | F58: 5615502 | G58: 5620622 | H58: 5615502 | I58: 5615502 | J58: 5615502 | K58: 5790468 | L58: 5825461 | M58: 5825461.4 | N58: 5853108 | O58: 5882809 | P58: 5912509 | Q58: 5942210 | R58: 6003391 | S58: 6003391 | T58: 6036201 | U58: 6343271 | V58: 6343271 | W58: 6343271 | X58: 6343271 | Y58: 6343271 | Z58: 6343271 | AA58: 6343271 | AB58: 6343271 | AC58: 6343271 | AD58: 6343271 | AE58: 6583115 | AF58: 6574278 | AG58: 6611020 | AH58: 6611020 | AI58: 6684506 | AJ58: 6721249 | AK58: 6757992 | AL58: 6794735 | AM58: 6831478 | AN58: 6868221 | AO58: 6941707 | AP58: 7015193 | AQ58: 7015193 | AR58: 7059284 | AS58: 7322167
B59: Other Reserves (provide notes on these reserves) | C59: 8982342 | D59: 17158163 | E59: 17158163 | F59: 17158163 | G59: 17158163 | H59: 17158163 | I59: 17158163 | J59: 17158163 | K59: 17158163 | L59: 17158163 | M59: 17158163 | N59: 17158163 | O59: 17158163 | P59: 17158163 | Q59: 17158163 | R59: 17158163 | S59: 17158163 | T59: 17158163 | U59: 10262790 | V59: 10262790 | W59: 10262790 | X59: 10262790 | Y59: 10262790 | Z59: 10262790 | AA59: 10262790 | AB59: 10262790 | AC59: 10262790 | AD59: 10262790 | AE59: 10262790 | AF59: 10262790 | AG59: 10262790 | AH59: 10262790 | AI59: 10262790 | AJ59: 10262790 | AK59: 10262790 | AL59: 10262790 | AM59: 10262790 | AN59: 10262790 | AO59: 10262790 | AP59: 10262790 | AQ59: 10262790 | AR59: 10262790 | AS59: 10262790
B60: Revaluation Reserves (Not part of core capital) | C60: 36578760 | D60: 37073184 | E60: 37073184 | F60: 37073184 | G60: 37073184 | H60: 37073184 | I60: 37073184 | J60: 37073184 | K60: 37073184 | L60: 37073184 | M60: 37073184 | N60: 37073184 | O60: 37073184 | P60: 37073184 | Q60: 37073184 | R60: 37073184 | S60: 37073184 | T60: 37073184 | U60: 0 | V60: 0 | W60: 0 | X60: 0 | Y60: 0 | Z60: 0 | AA60: 0 | AB60: 0 | AC60: 0 | AD60: 0 | AE60: 0 | AG60: 0 | AH60: 0 | AI60: 0 | AJ60: 0 | AK60: 0 | AL60: 0 | AM60: 0 | AN60: 0 | AO60: 0 | AP60: 0 | AQ60: 0 | AR60: 0 | AS60: 0
B61: Proposed Dividends | G61: 0 | H61: 200000 | I61: 300000 | J61: 400000 | K61: 500000 | L61: 600000 | M61: 700000 | N61: 800000 | O61: 900000 | P61: 1000000 | Q61: 1398021 | R61: 1445817 | S61: 1445817 | T61: 120485 | U61: 253016 | V61: 379524 | W61: 506032 | X61: 662666 | Y61: 796970 | Z61: 935819 | AA61: 1074536 | AB61: 1211265 | AC61: 1483342 | AD61: 1629310 | AE61: 1637066 | AG61: 109286 | AH61: 274731 | AI61: 414248 | AJ61: 553458 | AK61: 695009 | AL61: 835616 | AM61: 1119432 | AN61: 1263633 | AO61: 1408683 | AP61: 1551865 | AQ61: 1696689 | AR61: 1704369 | AS61: =1755500+340002 -> 2095502
B62: Adjustment to Equity | T62: 0 | U62: 0 | V62: 0 | W62: 0 | X62: 0 | Y62: 0 | Z62: 0 | AA62: 0 | AB62: 0 | AC62: 0 | AD62: 0 | AE62: 0 | AG62: 0 | AH62: 0 | AI62: 0 | AJ62: 0 | AK62: 0 | AL62: 0 | AM62: 0 | AN62: 0 | AO62: 0 | AP62: 0 | AQ62: 0 | AR62: 0
B63: Total Equity | C63: =C50+C53+C57 -> 61400969 | D63: =D50+D53+D57 -> 71387969 | E63: =E50+E53+E57 -> 72431897 | F63: =F50+F53+F57 -> 73210344 | G63: =G50+G53+G57 -> 74610224 | H63: =H50+H53+H57 -> 73915711 | I63: =I50+I53+I57 -> 73962791 | J63: =J50+J53+J57 -> 73878738 | ... AE63: =AE50+AE53+AE57 -> 37424997 | AF63: 35375179 | AG63: =AG50+AG53+AG57 -> 35639749 | AH63: =AH50+AH53+AH57 -> 35843990 | AI63: =AI50+AI53+AI57 -> 36579630 | AJ63: =AJ50+AJ53+AJ57 -> 36336166 | AK63: =AK50+AK53+AK57 -> 36733879 | AL63: =AL50+AL53+AL57 -> 37130011 | AM63: =AM50+AM53+AM57 -> 37662782 | AN63: =AN50+AN53+AN57 -> 38339950 | ... BC63: =BC50+BC53+BC57 -> 0
B65: Total Liabilities and Equity | C65: =C63+C47 -> 190156140 | D65: =D63+D47 -> 1.9878308e+08 | E65: =E63+E47 -> 215833395 | F65: =F63+F47 -> 246382881 | G65: =G63+G47 -> 241169671 | H65: =H63+H47 -> 235106281 | I65: =I63+I47 -> 247399069 | J65: =J63+J47 -> 238144117 | ... AE65: =AE63+AE47 -> 225346584 | AF65: 225456536 | AG65: =AG63+AG47 -> 228904851 | AH65: =AH63+AH47 -> 213366470 | AI65: =AI63+AI47 -> 220065582 | AJ65: =AJ63+AJ47 -> 222975137 | AK65: =AK63+AK47 -> 220638407 | AL65: =AL63+AL47 -> 225562014 | AM65: =AM63+AM47 -> 225963882 | AN65: =AN63+AN47 -> 227978401 | ... BC65: =BC63+BC47 -> 0
B67: Suspense (Difference in Books) | C67: =C65-C32 -> 0 | D67: =D65-D32 -> -1.279 | E67: =E65-E32 -> -1 | F67: =F65-F32 -> 0 | G67: =G65-G32 -> 0.24000001 | H67: =H65-H32 -> 0.49000001 | I67: =I65-I32 -> -0.65000001 | J67: =J65-J32 -> -0.21000001 | ... AE67: =AE65-AE32 -> 0.24000001 | AS67: =AS65-AS32 -> 1 | AT67: =AT65-AT32 -> #REF! | AU67: =AU65-AU32 -> #REF! | AV67: =AV65-AV32 -> #REF! | AW67: =AW65-AW32 -> #REF! | AX67: =AX65-AX32 -> #REF! | AY67: =AY65-AY32 -> #REF! | AZ67: =AZ65-AZ32 -> #REF! | ... BC67: =BC65-BC32 -> 0
B70: Sacco Name: SOTICO SACCO
B71: AUDITED YEAR TO | C71: Audit 2016 | D71: Audit 2017 | E71: Audit 2018 | F71: Audit 2019 | G71: 43831 | H71: 43862 | I71: 43891 | J71: 43922 | K71: 43952 | L71: 43983 | M71: 44013 | N71: 44044 | O71: 44075 | P71: 44105 | Q71: 44136 | R71: 44166 | S71: Audited 2020 | T71: 44197 | U71: 44228 | V71: 44256 | W71: 44287 | X71: 44317 | Y71: 44348 | Z71: 44378 | AA71: 44409 | AB71: 44440 | AC71: 44470 | AD71: 44501 | AE71: 44531 | AS71: Audited 2022
B72: Financial Income | C72: =C73+C76 -> 27127521 | D72: =D73+D76 -> 27376695 | E72: =E73+E76 -> 28491876 | F72: =F73+F76 -> 30436001 | G72: =G73+G76 -> 2318955.6 | H72: =H73+H76 -> 4953370.5 | I72: =I73+I76 -> 7211467.8 | J72: =J73+J76 -> 9740396.4 | ... AE72: =AE73+AE76 -> 36726268 | AG72: =AG73+AG76 -> 2527419.3 | AH72: =AH73+AH76 -> 5006252.4 | AI72: =AI73+AI76 -> 7571888.9 | AJ72: =AJ73+AJ76 -> 10236489 | AK72: =AK73+AK76 -> 13030833 | AL72: =AL73+AL76 -> 20262518 | AM72: =AM73+AM76 -> 22848276 | AN72: =AN73+AN76 -> 25517577 | ... AQ72: =AQ73+AQ76 -> 33959721 | AS72: =AS73+AS76 -> 36979854 | AT72: =AT73+AT76 -> 0 | AU72: =AU73+AU76 -> 0 | AV72: =AV73+AV76 -> 0 | AW72: =AW73+AW76 -> 0 | AX72: =AX73+AX76 -> 0 | AY72: =AY73+AY76 -> 0 | AZ72: =AZ73+AZ76 -> 0 | ... BC72: =BC73+BC76 -> 0
B73: Financial Income from Loans Portfolio | C73: =C74+C75 -> 20991266 | D73: =D74+D75 -> 20574476 | E73: =E74+E75 -> 21879593 | F73: =F74+F75 -> 18377030 | G73: =G74+G75 -> 2030007.6 | H73: =H74+H75 -> 4314076.2 | I73: =I74+I75 -> 6151500.4 | J73: =J74+J75 -> 8127739.7 | ... AE73: =AE74+AE75 -> 27867865 | AG73: =AG74+AG75 -> 2259229 | AH73: =AH74+AH75 -> 4328981.9 | AI73: =AI74+AI75 -> 6503053.2 | AJ73: =AJ74+AJ75 -> 8817570.7 | AK73: =AK74+AK75 -> 11288063 | AL73: =AL74+AL75 -> 13612263 | AM73: =AM74+AM75 -> 15860996 | AN73: =AN74+AN75 -> 18169042 | ... AQ73: =AQ74+AQ75 -> 25627913 | AS73: =AS74+AS75 -> 27587210 | AT73: =AT74+AT75 -> 0 | AU73: =AU74+AU75 -> 0 | AV73: =AV74+AV75 -> 0 | AW73: =AW74+AW75 -> 0 | AX73: =AX74+AX75 -> 0 | AY73: =AY74+AY75 -> 0 | AZ73: =AZ74+AZ75 -> 0 | ... BC73: =BC74+BC75 -> 0
B74: Interest on Loan Portfolio | C74: 18352026 | D74: 18322301 | E74: 18131997 | F74: 18377030 | G74: 1756233.8 | H74: 3494619.5 | I74: 5151232.2 | J74: 6814814 | K74: 8648603.5 | L74: 10428847 | M74: 12286089 | N74: 13737399 | O74: 16213730 | P74: 18093425 | Q74: 20227999 | R74: 67300739 | S74: 67300739 | T74: 1968749.5 | U74: 4034586.6 | V74: 5968272.4 | W74: 7962660.2 | X74: 9930248 | Y74: 11941394 | Z74: 14067206 | AA74: 16107786 | AB74: 17984424 | AC74: 20025321 | AD74: 22276679 | AE74: 24477670 | AG74: 2008244.1 | AH74: 3861609.6 | AI74: 5885049.7 | AJ74: 7992142.7 | AK74: 9922023.4 | AL74: 11975440 | AM74: 14016816 | AN74: 16095631 | AO74: 18176266 | AP74: 20254309 | AQ74: 22649593 | AS74: =22783165+2136371 -> 24919536
B75: Fees & Commission on Loan Portfolio | C75: 2639240 | D75: 2252175 | E75: 3747596 | G75: 273773.8 | H75: 819456.7 | I75: 1000268.2 | J75: 1312925.7 | K75: 1498060.2 | L75: 1828055.2 | M75: 2108560 | N75: 2529445 | O75: 2912399 | P75: 3379361.3 | Q75: 3822954.4 | R75: 12595465 | S75: 12595465 | T75: 207969.6 | U75: 594237.4 | V75: 861522.1 | W75: 1102882.8 | X75: 1322796.9 | Y75: 1526352.5 | Z75: 1826754.9 | AA75: 2393251.2 | AB75: 2613178.4 | AC75: 2830457 | AD75: 3065382.7 | AE75: 3390195 | AG75: 250984.9 | AH75: 467372.3 | AI75: 618003.5 | AJ75: 825428 | AK75: 1366039.2 | AL75: 1636822.7 | AM75: 1844179.8 | AN75: 2073410.8 | AO75: 2402929.6 | AP75: 2661947.7 | AQ75: 2978319.5 | AS75: 2667674
B76: Financial Income From Investments | C76: =SUM(C77:C80) -> 6136255 | D76: =SUM(D77:D80) -> 6802219 | E76: =SUM(E77:E80) -> 6612283 | F76: =SUM(F77:F80) -> 12058971 | G76: =SUM(G77:G80) -> 288948.04 | H76: =SUM(H77:H80) -> 639294.26 | I76: =SUM(I77:I80) -> 1059967.4 | J76: =SUM(J77:J80) -> 1612656.6 | ... AE76: =SUM(AE77:AE80) -> 8858403.1 | AG76: =SUM(AG77:AG80) -> 268190.3 | AH76: =SUM(AH77:AH80) -> 677270.55 | AI76: =SUM(AI77:AI80) -> 1068835.8 | AJ76: =SUM(AJ77:AJ80) -> 1418918.3 | AK76: =SUM(AK77:AK80) -> 1742770 | AL76: =SUM(AL77:AL80) -> 6650254.5 | AM76: =SUM(AM77:AM80) -> 6987280.4 | AN76: =SUM(AN77:AN80) -> 7348535.2 | ... AQ76: =SUM(AQ77:AQ80) -> 8331808.1 | AS76: =SUM(AS77:AS80) -> 9392644 | AT76: =SUM(AT77:AT80) -> 0 | AU76: =SUM(AU77:AU80) -> 0 | AV76: =SUM(AV77:AV80) -> 0 | AW76: =SUM(AW77:AW80) -> 0 | AX76: =SUM(AX77:AX80) -> 0 | AY76: =SUM(AY77:AY80) -> 0 | AZ76: =SUM(AZ77:AZ80) -> 0 | ... BC76: =SUM(BC77:BC80) -> 0
B77: Government Securities | G77: 0 | H77: 0 | I77: 0 | J77: 0 | K77: 0 | L77: 0 | N77: 0 | O77: 0 | P77: 0 | Q77: 0 | R77: 0 | S77: 0 | T77: 0 | U77: 0 | V77: 0 | W77: 0 | X77: 0 | Y77: 0 | Z77: 0 | AA77: 0 | AB77: 0 | AC77: 0 | AD77: 0 | AE77: 0 | AG77: 0 | AH77: 0 | AI77: 0 | AJ77: 0 | AK77: 0 | AL77: 0 | AM77: 0 | AN77: 0 | AO77: 0 | AP77: 0 | AQ77: 0 | AS77: 0
B78: Deposit with Banks and Other Financial Inst. | G78: 0 | H78: 0 | I78: 0 | J78: 0 | K78: 0 | L78: 0 | N78: 0 | O78: 0 | P78: 0 | Q78: 0 | R78: 0 | S78: 0 | T78: 0 | U78: 0 | V78: 0 | W78: 0 | X78: 0 | Y78: 0 | Z78: 0 | AA78: 0 | AB78: 0 | AC78: 0 | AD78: 0 | AE78: 0 | AG78: 0 | AH78: 0 | AI78: 0 | AJ78: 0 | AK78: 0 | AL78: 0 | AM78: 0 | AN78: 0 | AO78: 0 | AP78: 0 | AQ78: 0 | AS78: 0
B79: Other Investments - dividend & Interest incomes from investments | C79: 2899215 | D79: 3896606 | F79: 4717217 | G79: 0 | H79: 0 | I79: 0 | J79: 33516 | K79: 4714005.6 | L79: 4714005.6 | M79: 4714005.6 | N79: 4714005.6 | O79: 4714005.6 | P79: 4714005.6 | Q79: 4714005.6 | R79: 14142017 | S79: 14142017 | T79: 0 | U79: 0 | V79: 0 | W79: 4640108.3 | X79: 4640108.3 | Y79: 4640108.3 | Z79: 4640108.3 | AA79: 4640108.3 | AB79: 4640108.3 | AC79: 4640108.3 | AD79: 4640108.3 | AE79: 4640108.3 | AG79: 0 | AH79: 0 | AI79: 0 | AJ79: 0 | AK79: 0 | AL79: 4474558.8 | AM79: 4474558.8 | AN79: 4474558.8 | AO79: 4474558.8 | AP79: 4474558.8 | AQ79: 4474558.8 | AS79: 4522926
B80: Other Operating Income- Salary processing fees, transaction fees, membership fees | C80: 3237040 | D80: 2905613 | E80: 6612283 | F80: 7341754 | G80: 288948.04 | H80: 639294.26 | I80: 1059967.4 | J80: 1579140.6 | K80: 1924526 | L80: 2266385.6 | M80: 2609322.1 | N80: 2962004.9 | O80: 3314421.6 | P80: 3674071.3 | Q80: 4030674.4 | R80: 13329508 | S80: 13329508 | T80: 313921.25 | U80: 668351.36 | V80: 1060922.7 | W80: 1395492.6 | X80: 1770479.4 | Y80: 2105430.7 | Z80: 2452696.5 | AA80: 2796424.7 | AB80: 3108046.2 | AC80: 3413146.1 | AD80: 3761314.5 | AE80: 4218294.8 | AG80: 268190.3 | AH80: 677270.55 | AI80: 1068835.8 | AJ80: 1418918.3 | AK80: 1742770 | AL80: 2175695.7 | AM80: 2512721.6 | AN80: 2873976.4 | AO80: 3222302 | AP80: 3575676.3 | AQ80: 3857249.3 | AS80: =55881+2997450+1050477+12433+168341+48490+800+177146+137301+221399 -> 4869718
B81: Financial Expense | C81: =SUM(C82:C87) -> 10222087 | D81: =SUM(D82:D87) -> 10502116 | E81: =SUM(E82:E87) -> 12059614 | F81: =SUM(F82:F87) -> 13430945 | G81: =SUM(G82:G87) -> 54840 | H81: =SUM(H82:H87) -> 2290222 | I81: =SUM(I82:I87) -> 3305698 | J81: =SUM(J82:J87) -> 4937066 | ... AE81: =SUM(AE82:AE87) -> 19244617 | AG81: =SUM(AG82:AG87) -> 1319426.3 | AH81: =SUM(AH82:AH87) -> 2436917.7 | AI81: =SUM(AI82:AI87) -> 3280885.4 | AJ81: =SUM(AJ82:AJ87) -> 4769182.6 | AK81: =SUM(AK82:AK87) -> 6295269.5 | AL81: =SUM(AL82:AL87) -> 11614871 | AM81: =SUM(AM82:AM87) -> 12645587 | AN81: =SUM(AN82:AN87) -> 13534157 | ... AQ81: =SUM(AQ82:AQ87) -> 18125175 | AS81: =SUM(AS82:AS87) -> 15883112 | AT81: =SUM(AT82:AT87) -> 0 | AU81: =SUM(AU82:AU87) -> 0 | AV81: =SUM(AV82:AV87) -> 0 | AW81: =SUM(AW82:AW87) -> 0 | AX81: =SUM(AX82:AX87) -> 0 | AY81: =SUM(AY82:AY87) -> 0 | AZ81: =SUM(AZ82:AZ87) -> 0 | ... BC81: =SUM(BC82:BC87) -> 0
B82: Interest Expense on Deposits | C82: 9449807 | D82: 9899196 | E82: 11083861 | F82: =11672977+67437 -> 11740414 | G82: 0 | H82: 2000000 | I82: 2300000 | J82: 3800000 | K82: 8514005.6 | L82: 9214005.6 | M82: 10014006 | N82: 11014006 | O82: 12014006 | P82: 13014006 | Q82: 13764006 | R82: 40798481 | S82: 40798481 | T82: 1133291.1 | U82: 1784925.7 | V82: 2379900.9 | W82: 4759801.8 | X82: 6233073.8 | Y82: 7072679.4 | Z82: 8289085.1 | AA82: 9499078.7 | AB82: 10737653 | AC82: 12599497 | AD82: 13757342 | AE82: 14691330 | AG82: 981476.52 | AH82: 1855851 | AI82: 2501766.1 | AJ82: 3797628 | AK82: 5088287.3 | AL82: 10191055 | AM82: 10898458 | AN82: 11604570 | AO82: 12955223 | AP82: 14486074 | AQ82: 15653506 | AS82: =15284564+173318+51354 -> 15509236
B83: Cost of External Borrowings | C83: 772280 | D83: 505621 | E83: 975753 | F83: 1298320 | G83: 0 | H83: 0 | I83: 583973.01 | J83: 583973.01 | K83: 583973.01 | L83: 835860.23 | M83: 835860.23 | N83: 835860.23 | O83: 1082450.2 | P83: 1082450.2 | Q83: 1082450.2 | R83: 3701590.9 | S83: 3701590.9 | T83: 0 | U83: 370590 | V83: 611357.14 | W83: 981947.14 | X83: 981947.14 | Y83: 1283974.6 | Z83: 1728614.6 | AA83: 1818614.6 | AB83: 2369524.5 | AC83: 2369524.5 | AD83: 2369524.5 | AE83: 2369524.5 | AG83: 191853.9 | AH83: 191853.9 | AI83: 191853.9 | AJ83: 191853.9 | AK83: 191853.9 | AL83: 191853.9 | AM83: 191853.9 | AN83: 191853.9 | AO83: 191853.9 | AP83: 191853.9 | AQ83: 191853.9 | AS83: 191854
B84: Dividend Expenses (on member shares) | G84: 0 | H84: 200000 | I84: 300000 | J84: 400000 | K84: 500000 | L84: 600000 | M84: 700000 | N84: 800000 | O84: 900000 | P84: 1000000 | Q84: 1398021 | R84: 4337450 | S84: 4337450 | T84: 120484.72 | U84: 253016 | V84: 379524 | W84: 506032 | X84: 662665.98 | Y84: 796969.77 | Z84: 935819.31 | AA84: 1074535.7 | AB84: 1211264.7 | AC84: 1483341.6 | AD84: 1629309.8 | AE84: 1637066.1 | AG84: 109285.91 | AH84: 274730.75 | AI84: 414248.4 | AJ84: 553457.74 | AK84: 695008.87 | AL84: 835616.16 | AM84: 1119431.9 | AN84: 1263633.1 | AO84: 1408683.4 | AP84: 1551865.4 | AQ84: 1696689.5 | AS84: 0
B85: Other Financial Expense | D85: 97299 | F85: 392211 | G85: 54840 | H85: 90222 | I85: 121725 | J85: 153093 | K85: 169362 | L85: 185182 | M85: 185794 | N85: 233640 | O85: 262536 | P85: 296287 | Q85: 333345.61 | R85: 1118956.8 | S85: 1118956.8 | T85: 0 | U85: 130864 | V85: 174424 | W85: 153994 | X85: 153994 | Y85: 240952 | Z85: 291706 | AA85: 368282.29 | AB85: 411356.29 | AC85: 452934.29 | AD85: 489708.29 | AE85: 546696.49 | AG85: 36810 | AH85: 114482 | AI85: 173017 | AJ85: 226243 | AK85: 320119.43 | AL85: 396345.89 | AM85: 435843.89 | AN85: 474099.89 | AO85: 511629.89 | AP85: 563205.89 | AQ85: 583125.89 | AS85: 182022
B86: Fees & Commission Expense | G86: 0 | H86: 0 | I86: 0 | J86: 0 | K86: 0 | L86: 0 | N86: 0 | O86: 0 | P86: 0 | Q86: 0 | R86: 0 | S86: 0 | T86: 0 | U86: 0 | V86: 0 | W86: 0 | X86: 0 | Y86: 0 | Z86: 0 | AA86: 0 | AB86: 0 | AC86: 0 | AD86: 0 | AE86: 0 | AG86: 0 | AH86: 0 | AI86: 0 | AJ86: 0 | AK86: 0 | AL86: 0 | AM86: 0 | AN86: 0 | AO86: 0 | AP86: 0 | AQ86: 0 | AS86: 0
B87: Other Expense | G87: 0 | H87: 0 | I87: 0 | J87: 0 | K87: 0 | L87: 0 | N87: 0 | O87: 0 | P87: 0 | Q87: 0 | R87: 0 | S87: 0 | T87: 0 | U87: 0 | V87: 0 | W87: 0 | X87: 0 | Y87: 0 | Z87: 0 | AA87: 0 | AB87: 0 | AC87: 0 | AD87: 0 | AE87: 0 | AG87: 0 | AH87: 0 | AI87: 0 | AJ87: 0 | AK87: 0 | AL87: 0 | AM87: 0 | AN87: 0 | AO87: 0 | AP87: 0 | AQ87: 0 | AS87: 0
B88: Net Financial Income | C88: =C72-C81 -> 16905434 | D88: =D72-D81 -> 16874579 | E88: =E72-E81 -> 16432262 | F88: =F72-F81 -> 17005056 | G88: =G72-G81 -> 2264115.6 | H88: =H72-H81 -> 2663148.5 | I88: =I72-I81 -> 3905769.8 | J88: =J72-J81 -> 4803330.3 | ... AE88: =AE72-AE81 -> 17481651 | AG88: =AG72-AG81 -> 1207993 | AH88: =AH72-AH81 -> 2569334.8 | AI88: =AI72-AI81 -> 4291003.5 | AJ88: =AJ72-AJ81 -> 5467306.4 | AK88: =AK72-AK81 -> 6735563 | AL88: =AL72-AL81 -> 8647646.2 | AM88: =AM72-AM81 -> 10202689 | AN88: =AN72-AN81 -> 11983420 | ... AQ88: =AQ72-AQ81 -> 15834545 | AS88: =AS72-AS81 -> 21096742 | AT88: =AT72-AT81 -> 0 | AU88: =AU72-AU81 -> 0 | AV88: =AV72-AV81 -> 0 | AW88: =AW72-AW81 -> 0 | AX88: =AX72-AX81 -> 0 | AY88: =AY72-AY81 -> 0 | AZ88: =AZ72-AZ81 -> 0 | ... BC88: =BC72-BC81 -> 0
B89: Allowance For Loan Loss | C89: =C90-C91 -> 1145539 | D89: =D90-D91 -> 214877 | E89: =E90-E91 -> 121968 | F89: =F90-F91 -> 1700000 | G89: =G90-G91 -> 0 | H89: =H90-H91 -> 0 | I89: =I90-I91 -> 0 | J89: 0 | K89: =K90-K91 -> 333333.33 | L89: =L90-L91 -> 400000 | M89: =M90-M91 -> 500000 | N89: =N90-N91 -> 500000 | O89: =O90-O91 -> 500000 | P89: =P90-P91 -> 500000 | Q89: =Q90-Q91 -> 500000 | R89: =R90-R91 -> 1500000 | ... AE89: =AE90-AE91 -> 300000 | AG89: =AG90-AG91 -> 0 | AH89: =AH90-AH91 -> 0 | AI89: =AI90-AI91 -> 0 | AJ89: =AJ90-AJ91 -> 0 | AK89: =AK90-AK91 -> 0 | AL89: =AL90-AL91 -> 0 | AM89: =AM90-AM91 -> 0 | AN89: =AN90-AN91 -> 0 | ... AQ89: =AQ90-AQ91 -> 0 | AS89: =AS90-AS91 -> 300000 | AT89: =AT90-AT91 -> 0 | AU89: =AU90-AU91 -> 0 | AV89: =AV90-AV91 -> 0 | AW89: =AW90-AW91 -> 0 | AX89: =AX90-AX91 -> 0 | AY89: =AY90-AY91 -> 0 | AZ89: =AZ90-AZ91 -> 0 | ... BC89: =BC90-BC91 -> 0
B90: Provision for Loan Losses | C90: 1145539 | D90: 214877 | E90: 121968 | F90: 1700000 | G90: 0 | H90: 0 | I90: 0 | J90: 0 | K90: 333333.33 | L90: 400000 | M90: 500000 | N90: 500000 | O90: 500000 | P90: 500000 | Q90: 500000 | R90: 1500000 | S90: 1500000 | T90: 0 | U90: 0 | V90: 0 | W90: 0 | X90: 0 | Y90: 0 | Z90: 0 | AA90: 0 | AE90: 300000 | AG90: 0 | AH90: 0 | AI90: 0 | AJ90: 0 | AK90: 0 | AL90: 0 | AM90: 0 | AN90: 0 | AO90: 0 | AP90: 0 | AQ90: 0 | AS90: 300000
B91: Value of Loans Recovered | G91: 0 | H91: 0 | I91: 0 | J91: 0 | K91: 0 | L91: 0 | N91: 0 | O91: 0 | P91: 0 | Q91: 0 | R91: 0 | S91: 0 | T91: 0 | U91: 0 | V91: 0 | W91: 0 | X91: 0 | Y91: 0 | Z91: 0 | AA91: 0 | AG91: 0 | AH91: 0 | AI91: 0 | AJ91: 0 | AK91: 0 | AL91: 0 | AM91: 0 | AN91: 0 | AO91: 0 | AP91: 0 | AQ91: 0 | AS91: 0
B92: Operating Expenses | C92: =SUM(C93:C97) -> 14145467 | D92: =SUM(D93:D97) -> 14462350 | E92: =SUM(E93:E97) -> 14206098 | F92: =SUM(F93:F97) -> 13467776 | G92: =SUM(G93:G97) -> 889835.41 | H92: =SUM(H93:H97) -> 2157780.4 | I92: =SUM(I93:I97) -> 3597321.7 | J92: =SUM(J93:J97) -> 4678935.4 | ... AE92: =SUM(AE93:AE97) -> 15781139 | AG92: =SUM(AG93:AG97) -> 1056887.2 | AH92: =SUM(AH93:AH97) -> 2403193.4 | AI92: =SUM(AI93:AI97) -> 3619587 | AJ92: =SUM(AJ93:AJ97) -> 5199918.2 | AK92: =SUM(AK93:AK97) -> 6254462.3 | AL92: =SUM(AL93:AL97) -> 7836217.1 | AM92: =SUM(AM93:AM97) -> 9200386.8 | AN92: =SUM(AN93:AN97) -> 10476372 | ... AQ92: =SUM(AQ93:AQ97) -> 14133064 | AS92: =SUM(AS93:AS97) -> 16262395 | AT92: =SUM(AT93:AT97) -> 0 | AU92: =SUM(AU93:AU97) -> 0 | AV92: =SUM(AV93:AV97) -> 0 | AW92: =SUM(AW93:AW97) -> 0 | AX92: =SUM(AX93:AX97) -> 0 | AY92: =SUM(AY93:AY97) -> 0 | AZ92: =SUM(AZ93:AZ97) -> 0 | ... BC92: =SUM(BC93:BC97) -> 0
B93: Personnel Expenses | C93: 4472114 | D93: 5710996 | E93: 5971894 | F93: 6436772 | G93: 588360.4 | H93: 1165382.8 | I93: 1771537.7 | J93: 2345206.1 | K93: 3013000 | L93: 3590790.3 | M93: 4200083.7 | N93: 4757233.1 | O93: 5403492.2 | P93: 5996477.6 | Q93: 6595132.8 | R93: 21601342 | S93: 21601342 | T93: 580725.4 | U93: 1156964.8 | V93: 1753879.7 | W93: 2340114.1 | X93: 2907993.5 | Y93: 3633286.5 | Z93: 4228171.1 | AA93: 4870009.8 | AB93: 5466529.4 | AC93: 6083015.1 | AD93: 6708415.8 | AE93: 7337830.4 | AG93: 650516.83 | AH93: 1264244.9 | AI93: 1955841.5 | AJ93: 2607010.8 | AK93: 3237218.6 | AL93: 3870476.5 | AM93: 4492764.3 | AN93: 5184524.6 | AO93: 5823522.9 | AP93: 6486978.8 | AQ93: 7166179.3 | AS93: =6733911+16500+13250+322737+281635 -> 7368033
B94: Governance Expenses | C94: 1296449 | D94: 1871226 | E94: 1650234 | F94: 1966056 | G94: 185483.4 | H94: 473562.6 | I94: 728291.4 | J94: 790050.15 | K94: 942162.69 | L94: 1058861.4 | M94: 1099749.1 | N94: 1192858.6 | O94: 1337194.9 | P94: 1561892.9 | Q94: 1660168.1 | R94: 5552392.7 | S94: 5552392.7 | T94: 84516 | U94: 240274.6 | V94: 475593 | W94: 612106.4 | X94: 806953.13 | Y94: 980883.8 | Z94: 1190888.9 | AA94: 1501700.7 | AB94: 1700225.2 | AC94: 1860042 | AD94: 2177986.4 | AE94: 2367682 | AG94: 132987.5 | AH94: 418352.9 | AI94: 598824.5 | AJ94: 1135610.2 | AK94: 1335172.9 | AL94: 1787981.6 | AM94: 2217146.9 | AN94: 2511916.6 | AO94: 2689398.2 | AP94: 2904093.2 | AQ94: 3194527.8 | AS94: =701420+74700+893635+129480+504449+777636 -> 3081320
B95: Marketing Expenses | E95: 59700 | F95: 189420 | G95: 0 | H95: 0 | I95: 0 | J95: 0 | K95: 0 | L95: 0 | M95: 0 | N95: 0 | O95: 0 | P95: 0 | Q95: 0 | R95: 0 | S95: 0 | T95: 0 | U95: 0 | V95: 0 | W95: 0 | X95: 0 | Y95: 0 | Z95: 0 | AA95: 0 | AB95: 0 | AC95: 0 | AD95: 0 | AE95: 0 | AG95: 0 | AH95: 0 | AI95: 0 | AJ95: 0 | AK95: 0 | AL95: 0 | AM95: 0 | AN95: 0 | AO95: 0 | AP95: 0 | AQ95: 0 | AS95: 0
B96: Depreciation and Amortization Charges | C96: 2497819 | D96: 1079211 | E96: 1452835 | F96: 1219993 | G96: 86791.61 | H96: 168122.12 | I96: 257808.03 | J96: 346594.04 | K96: 433242.55 | L96: 521391.06 | M96: 521391.06 | N96: 695188.08 | O96: 782086.59 | P96: 868985.1 | Q96: 957446.53 | R96: 3133461.4 | S96: 3133461.4 | T96: 56952.71 | U96: 148692.25 | V96: 223038.38 | W96: 292344.51 | X96: 372857.6 | Y96: 447429.11 | Z96: 522000.63 | AA96: 596572.15 | AB96: 671143.67 | AC96: 753038.26 | AD96: 828173.17 | AE96: 903461.64 | AG96: 61311.41 | AH96: 122622.82 | AI96: 183934.23 | AJ96: 245245.64 | AK96: 306557.05 | AL96: 367868.46 | AM96: 430084.04 | AN96: 491524.61 | AO96: 552965.19 | AP96: 614405.77 | AQ96: 748067.12 | AS96: 737787
B97: Administrative Expenses | C97: 5879085 | D97: 5800917 | E97: 5071435 | F97: =4237166-F95-F85 -> 3655535 | G97: 29200 | H97: 350712.85 | I97: 839684.54 | J97: 1197085.1 | K97: 1906032.6 | L97: 2176320.1 | M97: 2610963.5 | N97: 2849334 | O97: 3462533.6 | P97: 3660452.5 | Q97: 4677993.9 | R97: 25060434 | S97: 25060434 | T97: 139010 | U97: 994265 | V97: 1584521.5 | W97: 1837061.9 | X97: 2241455.2 | Y97: 2446332.4 | Z97: 3009480 | AA97: 3397575.6 | AB97: 3609083.4 | AC97: 4245411.5 | AD97: 4406834.5 | AE97: 5172164.7 | AG97: 212071.42 | AH97: 597972.79 | AI97: 880986.74 | AJ97: 1212051.6 | AK97: 1375513.8 | AL97: 1809890.6 | AM97: 2060391.6 | AN97: 2288406.3 | AO97: 2647545.7 | AP97: 2897935.2 | AQ97: 3024290.2 | AS97: =609428+238760+519470+29510+444140+42330+116000+582190+141081+78488+574529+89400+52100+132000+16000+109000+57050+142435+282665+818679 -> 5075255
B98: Net Operating Income | C98: =C88-C89-C92 -> 1614428 | D98: =D88-D89-D92 -> 2197352 | E98: =E88-E89-E92 -> 2104196 | F98: =F88-F89-F92 -> 1837280 | G98: =G88-G89-G92 -> 1374280.2 | H98: =H88-H89-H92 -> 505368.12 | I98: =I88-I89-I92 -> 308448.16 | J98: =J88-J89-J92 -> 124394.97 | ... AE98: =AE88-AE89-AE92 -> 1400512 | AG98: =AG88-AG89-AG92 -> 151105.84 | AH98: =AH88-AH89-AH92 -> 166141.31 | AI98: =AI88-AI89-AI92 -> 671416.59 | AJ98: =AJ88-AJ89-AJ92 -> 267388.19 | AK98: =AK88-AK89-AK92 -> 481100.7 | AL98: =AL88-AL89-AL92 -> 811429.04 | AM98: =AM88-AM89-AM92 -> 1002302.4 | AN98: =AN88-AN89-AN92 -> 1507047.9 | ... AQ98: =AQ88-AQ89-AQ92 -> 1701480.9 | AS98: =AS88-AS89-AS92 -> 4534347 | AT98: =AT88-AT89-AT92 -> 0 | AU98: =AU88-AU89-AU92 -> 0 | AV98: =AV88-AV89-AV92 -> 0 | AW98: =AW88-AW89-AW92 -> 0 | AX98: =AX88-AX89-AX92 -> 0 | AY98: =AY88-AY89-AY92 -> 0 | AZ98: =AZ88-AZ89-AZ92 -> 0 | ... BC98: =BC88-BC89-BC92 -> 0
B99: Net Non Operating Income | C99: =C100-C101 -> 0 | D99: =D100-D101 -> 0 | E99: =E100-E101 -> 0 | F99: =F100-F101 -> 0 | G99: =G100-G101 -> 0 | H99: =H100-H101 -> 0 | I99: =I100-I101 -> 0 | J99: =J100-J101 -> 0 | ... AE99: =AE100-AE101 -> 0 | AG99: =AG100-AG101 -> 0 | AH99: =AH100-AH101 -> 0 | AI99: =AI100-AI101 -> 0 | AJ99: =AJ100-AJ101 -> 0 | AK99: =AK100-AK101 -> 0 | AL99: =AL100-AL101 -> 0 | AM99: =AM100-AM101 -> 0 | AN99: =AN100-AN101 -> 0 | ... AQ99: =AQ100-AQ101 -> 0 | AS99: =AS100-AS101 -> 0 | AT99: =AT100-AT101 -> 0 | AU99: =AU100-AU101 -> 0 | AV99: =AV100-AV101 -> 0 | AW99: =AW100-AW101 -> 0 | AX99: =AX100-AX101 -> 0 | AY99: =AY100-AY101 -> 0 | AZ99: =AZ100-AZ101 -> 0 | ... BC99: =BC100-BC101 -> 0
B100: Non- Operating Income | G100: 0 | H100: 0 | I100: 0 | J100: 0 | K100: 0 | L100: 0 | N100: 0 | O100: 0 | P100: 0 | Q100: 0 | R100: 0 | S100: 0 | T100: 0 | U100: 0 | V100: 0 | W100: 0 | X100: 0 | Y100: 0 | Z100: 0 | AA100: 0 | AS100: 0
B101: Non- Operating Expense | G101: 0 | H101: 0 | I101: 0 | J101: 0 | K101: 0 | L101: 0 | N101: 0 | O101: 0 | P101: 0 | Q101: 0 | R101: 0 | S101: 0 | T101: 0 | U101: 0 | V101: 0 | W101: 0 | X101: 0 | Y101: 0 | Z101: 0 | AA101: 0 | AS101: 0
B102: Net Income (Before Taxes and Donations) | C102: =C98+C99 -> 1614428 | D102: =D98+D99 -> 2197352 | E102: =E98+E99 -> 2104196 | F102: =F98+F99 -> 1837280 | G102: =G98+G99 -> 1374280.2 | H102: =H98+H99 -> 505368.12 | I102: =I98+I99 -> 308448.16 | J102: =J98+J99 -> 124394.97 | ... AE102: =AE98+AE99 -> 1400512 | AG102: =AG98+AG99 -> 151105.84 | AH102: =AH98+AH99 -> 166141.31 | AI102: =AI98+AI99 -> 671416.59 | AJ102: =AJ98+AJ99 -> 267388.19 | AK102: =AK98+AK99 -> 481100.7 | AL102: =AL98+AL99 -> 811429.04 | AM102: =AM98+AM99 -> 1002302.4 | AN102: =AN98+AN99 -> 1507047.9 | ... AQ102: =AQ98+AQ99 -> 1701480.9 | AS102: =AS98+AS99 -> 4534347 | AT102: =AT98+AT99 -> 0 | AU102: =AU98+AU99 -> 0 | AV102: =AV98+AV99 -> 0 | AW102: =AW98+AW99 -> 0 | AX102: =AX98+AX99 -> 0 | AY102: =AY98+AY99 -> 0 | AZ102: =AZ98+AZ99 -> 0 | ... BC102: =BC98+BC99 -> 0
B103: Taxes (Incomes taxes & Other payable to KRA) | C103: 46171 | E103: 164747 | F103: 140093 | G103: 0 | H103: 0 | I103: 0 | J103: 0 | K103: 0 | L103: 0 | N103: 0 | O103: 0 | P103: 0 | Q103: 0 | R103: 0 | S103: 1 | T103: 0 | U103: 119520.5 | V103: 179785 | W103: 335257.1 | X103: 407328.5 | Y103: 472039.6 | Z103: 533335.2 | AA103: 594945.1 | AG103: 53635.5 | AH103: 120834.7 | AI103: 189563.2 | AJ103: 238747.8 | AK103: 309522.7 | AL103: 453178.7 | AM103: 510996.3 | AN103: 576479.6 | AO103: 641572.2 | AP103: 708534.2 | AQ103: 767585.9 | AS103: 795401
B104: Net Income After Tax Before Donations | C104: =C102-C103 -> 1568257 | D104: =D102-D103 -> 2197352 | E104: =E102-E103 -> 1939449 | F104: =F102-F103 -> 1697187 | G104: =G102-G103 -> 1374280.2 | H104: =H102-H103 -> 505368.12 | I104: =I102-I103 -> 308448.16 | J104: =J102-J103 -> 124394.97 | ... AE104: =AE102-AE103 -> 1400512 | AG104: =AG102-AG103 -> 97470.34 | AH104: =AH102-AH103 -> 45306.61 | AI104: =AI102-AI103 -> 481853.39 | AJ104: =AJ102-AJ103 -> 28640.39 | AK104: =AK102-AK103 -> 171578 | AL104: =AL102-AL103 -> 358250.34 | AM104: =AM102-AM103 -> 491306.11 | AN104: =AN102-AN103 -> 930568.3 | ... AQ104: =AQ102-AQ103 -> 933895.04 | AS104: =AS102-AS103 -> 3738946 | AT104: =AT102-AT103 -> 0 | AU104: =AU102-AU103 -> 0 | AV104: =AV102-AV103 -> 0 | AW104: =AW102-AW103 -> 0 | AX104: =AX102-AX103 -> 0 | AY104: =AY102-AY103 -> 0 | AZ104: =AZ102-AZ103 -> 0 | ... BC104: =BC102-BC103 -> 0
B105: Donations | J105: 0 | K105: 0 | L105: 0 | N105: 0 | O105: 0 | P105: 0 | Q105: 0 | R105: 0 | S105: 1 | T105: 0 | U105: 0 | V105: 0 | X105: 0 | Y105: 0 | Z105: 0 | AA105: 0 | AB105: 652500.1 | AC105: 697558.6 | AD105: 767925.7 | AE105: 848600.8 | AS105: 0
B106: Net Income | C106: =C104-C105 -> 1568257 | D106: =D104-D105 -> 2197352 | E106: =E104-E105 -> 1939449 | F106: =F104-F105 -> 1697187 | G106: =G104-G105 -> 1374280.2 | H106: =H104-H105 -> 505368.12 | I106: =I104-I105 -> 308448.16 | J106: =J104-J105 -> 124394.97 | ... AE106: =AE104-AE105 -> 551911.15 | AS106: =AS104-AS105 -> 3738946 | AT106: =AT104-AT105 -> 0 | AU106: =AU104-AU105 -> 0 | AV106: =AV104-AV105 -> 0 | AW106: =AW104-AW105 -> 0 | AX106: =AX104-AX105 -> 0 | AY106: =AY104-AY105 -> 0 | AZ106: =AZ104-AZ105 -> 0 | ... BC106: =BC104-BC105 -> 0
B107: Total income | F107: =F100+F76+F73 -> 30436001 | G107: =G100+G76+G73 -> 2318955.6 | H107: =H100+H76+H73 -> 4953370.5 | I107: =I100+I76+I73 -> 7211467.8 | J107: =J100+J76+J73 -> 9740396.4 | K107: =K100+K76+K73 -> 16785195 | L107: =L100+L76+L73 -> 19237294 | M107: =M100+M76+M73 -> 21717977 | ... AA107: =AA100+AA76+AA73 -> 25937570
B108: Total expenses | F108: =F101+F92+F81 -> 26898721 | G108: =G101+G92+G81 -> 944675.41 | H108: =H101+H92+H81 -> 4448002.4 | I108: =I101+I92+I81 -> 6903019.7 | J108: =J101+J92+J81 -> 9616001.4 | K108: =K101+K92+K81 -> 16061778 | L108: =L101+L92+L81 -> 18182411 | M108: =M101+M92+M81 -> 20167847 | ... AA108: =AA101+AA92+AA81 -> 23126370

Sheet Financials
B2: Sotico Sacco
A3: 1 | B3: Year | C3: Audit 2016 | D3: Audit 2017 | E3: Audit 2018 | F3: Audit 2019 | G3: 43831 | H3: 43862 | I3: 43891 | J3: 43922 | K3: 43952 | L3: 43983 | M3: 44013 | N3: 44044 | O3: 44075 | P3: 44105 | Q3: 44136 | R3: 44166 | S3: Audit 20 | T3: 44217 | U3: 44228 | V3: 44256 | W3: 44287 | X3: 44317 | Y3: 44348 | Z3: 44378 | AA3: 44409 | AB3: 44440 | AC3: 44470 | AD3: 44501 | AE3: 44531 | AF3: Audited 2021 | AG3: 44562 | AH3: 44593 | AI3: 44621 | AJ3: 44652 | AK3: 44682 | AL3: 44713 | AM3: 44743 | AN3: 44774 | AO3: 44805 | AP3: 44835 | AQ3: 44866 | AR3: 44896 | AS3: audited 22 | AT3: 44958 | AU3: 44986 | AV3: 45017 | AW3: 45047 | AX3: 45078 | AY3: 45108 | AZ3: 45139 | BA3: 45170 | BB3: 45200
B4: Membership | D4: 5832 | E4: 6054 | F4: 6290 | R4: 6599 | S4: 6600 | T4: 6601 | U4: 6602 | V4: 6603 | W4: 6604 | X4: 6605 | Y4: 6606 | Z4: 6607 | AA4: 6608 | AB4: 6609 | AC4: 6610 | AD4: 6611 | AE4: 6612 | AF4: 6613 | AG4: 6614 | AH4: 6615 | AI4: 6616 | AJ4: 6617 | AK4: 6618 | AL4: 6619 | AM4: 6620 | AN4: 6621 | AO4: 6622 | AP4: 6623 | AQ4: 6624 | AR4: 6625 | AS4: 6626 | AT4: 6627 | AU4: 6628 | AV4: 6629 | AW4: 6630 | AX4: 6631 | AY4: 6632 | AZ4: 6633
A5: 2 | B5: Total Assets | C5: =Trend!C32 -> 190156140 | D5: =Trend!D32 -> 1.9878308e+08 | E5: =Trend!E32 -> 215833396 | F5: =Trend!F32 -> 246382881 | G5: =Trend!G32 -> 2.4116967e+08 | H5: =Trend!H32 -> 2.3510628e+08 | I5: =Trend!I32 -> 2.4739907e+08 | J5: =Trend!J32 -> 2.3814412e+08 | ... AZ5: =Trend!AZ32 -> #REF!
A6: 3 | B6: Total Deposits | C6: =Trend!C38 -> 103264095 | D6: =Trend!D38 -> 107547774 | E6: =Trend!E38 -> 122123986 | F6: =Trend!F38 -> 133248670 | G6: =Trend!G38 -> 130402071 | H6: =Trend!H38 -> 129785944 | I6: =Trend!I38 -> 130844408 | J6: =Trend!J38 -> 132110962 | ... AZ6: =Trend!AZ38 -> 0
A7: 3.1 | B7: Deposits-Members(BOSA) | C7: =Trend!C37 -> 93532161 | D7: =Trend!D37 -> 98991963 | E7: =Trend!E37 -> 109828204 | F7: =Trend!F37 -> 116729770 | G7: =Trend!G37 -> 117465834 | H7: =Trend!H37 -> 118247917 | I7: =Trend!I37 -> 119559661 | J7: =Trend!J37 -> 120700906 | ... AZ7: =Trend!AZ37 -> 0
A8: 3.2 | B8: Deposits-Customers(FOSA) | C8: =Trend!C35+Trend!C36 -> 9731934 | D8: =Trend!D35+Trend!D36 -> 8555811 | E8: =Trend!E35+Trend!E36 -> 12295782 | F8: =Trend!F35+Trend!F36 -> 16518900 | G8: =Trend!G35+Trend!G36 -> 12936237 | H8: =Trend!H35+Trend!H36 -> 11538027 | I8: =Trend!I35+Trend!I36 -> 11284747 | J8: =Trend!J35+Trend!J36 -> 11410056 | ... AZ8: =Trend!AZ35+Trend!AZ36 -> 0
A9: 4 | B9: External Borrowing | C9: =Trend!C46 -> 7000000 | D9: =Trend!D46 -> 0 | E9: =Trend!E46 -> 0 | F9: =Trend!F46 -> 12000000 | G9: =Trend!G46 -> 7918795 | H9: =Trend!H46 -> 3830466 | I9: =Trend!I46 -> 12000000 | J9: =Trend!J46 -> 7878951 | ... AZ9: =Trend!AZ46 -> 0
A10: 4.1 | B10: Short term Liabilities | C10: =Trend!C41+Trend!C42+Trend!C43+Trend!C45 -> 18491076 | D10: =Trend!D41+Trend!D42+Trend!D43+Trend!D45 -> 19847333 | E10: =Trend!E41+Trend!E42+Trend!E43+Trend!E45 -> 19699370 | F10: =Trend!F41+Trend!F42+Trend!F43+Trend!F45 -> 26082276 | G10: =Trend!G41+Trend!G42+Trend!G43+Trend!G45 -> 28238581 | H10: =Trend!H41+Trend!H42+Trend!H43+Trend!H45 -> 27574160 | I10: =Trend!I41+Trend!I42+Trend!I43+Trend!I45 -> 30591870 | J10: =Trend!J41+Trend!J42+Trend!J43+Trend!J45 -> 24275466 | ... AZ10: =Trend!AZ41+Trend!AZ42+Trend!AZ43+Trend!AZ45 -> 0
A11: 5 | B11: Share capital and Reserves
A12: 5.1 | B12: Core Capital | C12: =C14 -> 24822209 | D12: =D14 -> 34314785 | E12: =E14 -> 35358713 | F12: =F14 -> 36137160 | G12: =G14 -> 37537040 | H12: =H14 -> 36642527 | I12: =I14 -> 36589607 | J12: =J14 -> 36405554 | ... AZ12: =AZ14 -> 0
A13: 5.2 | B13: Institutional Capital | C13: =C12-C15 -> 14729609 | D13: =D12-D15 -> 23743385 | E13: =E12-E15 -> 24380513 | F13: =F12-F15 -> 24732360 | G13: =G12-G15 -> 26132240 | H13: =H12-H15 -> 25237727 | I13: =I12-I15 -> 25040807 | J13: =J12-J15 -> 24856754 | ... AZ13: =AZ12-AZ15 -> 0
A14: 5.3 | B14: Total Capital | C14: =SUM(C15:C19) -> 24822209 | D14: =SUM(D15:D19) -> 34314785 | E14: =SUM(E15:E19) -> 35358713 | F14: =SUM(F15:F19) -> 36137160 | G14: =SUM(G15:G19) -> 37537040 | H14: =SUM(H15:H19) -> 36642527 | I14: =SUM(I15:I19) -> 36589607 | J14: =SUM(J15:J19) -> 36405554 | ... AZ14: =SUM(AZ15:AZ19) -> 0
A15: 5.3.1 | B15: Members Share Capital | C15: =Trend!C50 -> 10092600 | D15: =Trend!D50 -> 10571400 | E15: =Trend!E50 -> 10978200 | F15: =Trend!F50 -> 11404800 | G15: =Trend!G50 -> 11404800 | H15: =Trend!H50 -> 11404800 | I15: =Trend!I50 -> 11548800 | J15: =Trend!J50 -> 11548800 | ... AZ15: =Trend!AZ50 -> 0
A16: 5.3.3 | B16: Retained Earnings | C16: =Trend!C53 -> 1279011 | D16: =Trend!D53 -> 1697046.7 | E16: =Trend!E53 -> 1946285 | F16: =Trend!F53 -> 1958695 | G16: =Trend!G53 -> 3353455 | H16: =Trend!H53 -> 2464062 | I16: =Trend!I53 -> 2267142 | J16: =Trend!J53 -> 2083089 | ... AZ16: =Trend!AZ53 -> 0
A17: 5.3.5 | B17: Statutory Reserves | C17: =Trend!C58 -> 4468256 | D17: =Trend!D58 -> 4888175 | E17: =Trend!E58 -> 5276065 | F17: =Trend!F58 -> 5615502 | G17: =Trend!G58 -> 5620622 | H17: =Trend!H58 -> 5615502 | I17: =Trend!I58 -> 5615502 | J17: =Trend!J58 -> 5615502 | ... AZ17: =Trend!AZ58 -> 0
A18: 5.3.6 | B18: Capital Reserve | C18: =Trend!C59 -> 8982342 | D18: =Trend!D59 -> 17158163 | E18: =Trend!E59 -> 17158163 | F18: =Trend!F59 -> 17158163 | G18: =Trend!G59 -> 17158163 | H18: =Trend!H59 -> 17158163 | I18: =Trend!I59 -> 17158163 | J18: =Trend!J59 -> 17158163 | ... AZ18: =Trend!AZ59 -> 0
A19: `nbnmn | B19: Supplementary Capital & reserves
A20: a | B20: Proposed Dividends | C20: =Trend!C82+Trend!C84 -> 9449807 | D20: =Trend!D82+Trend!D84 -> 9899196 | E20: =Trend!E82+Trend!E84 -> 11083861 | F20: =Trend!F82+Trend!F84 -> 11740414 | G20: =Trend!G82+Trend!G84 -> 0 | H20: =Trend!H82+Trend!H84 -> 2200000 | I20: =Trend!I82+Trend!I84 -> 2600000 | J20: =Trend!J82+Trend!J84 -> 4200000 | ... AZ20: =Trend!AZ82+Trend!AZ84 -> 0
A21: 6 | B21: Investments | C21: =C23 -> 40449810 | D21: =D23 -> 49120055 | E21: =E23 -> 49120055 | F21: =F23 -> 49120055 | G21: =G23 -> 49120055 | H21: =H23 -> 49120055 | I21: =I23 -> 49120055 | J21: =J23 -> 49120055 | K21: =K23+K22 -> 49120055 | L21: =L23+L22 -> 49120055 | M21: =M23+M22 -> 49120055 | N21: =N23+N22 -> 49120055 | O21: =O23+O22 -> 49120055 | P21: =P23+P22 -> 49120055 | Q21: =Q23+Q22 -> 49120055 | R21: =R23+R22 -> 49120055 | ... AZ21: =AZ23+AZ22 -> 0
A22: 6.1 | B22: Investments in Coop bank, CIC, Kuscco, Kerussu & Codic | C22: =Trend!C12 -> 0 | D22: =Trend!D12 -> 0 | E22: =Trend!E12 -> 0 | F22: =Trend!F12 -> 0 | G22: =Trend!G12 -> 0 | H22: =Trend!H12 -> 0 | I22: =Trend!I12 -> 0 | J22: =Trend!J12 -> 0 | ... AR22: =Trend!AR12 -> 5151497.8 | AS22: =Trend!#REF! -> #REF! | AT22: =Trend!AT12 -> 5151497.8 | AU22: =Trend!AU12 -> 5151497.8 | AV22: =Trend!AV12 -> 5151497.8 | AW22: =Trend!AW12 -> 5151497.8 | AX22: =Trend!AX12 -> 5151497.8 | AY22: =Trend!AY12 -> 5151497.8 | AZ22: =Trend!AZ12 -> 0
A23: 6.2 | B23: Equity Investments (at cost) | C23: =Trend!C13 -> 40449810 | D23: =Trend!D13 -> 49120055 | E23: =Trend!E13 -> 49120055 | F23: =Trend!F13 -> 49120055 | G23: =Trend!G13 -> 49120055 | H23: =Trend!H13 -> 49120055 | I23: =Trend!I13 -> 49120055 | J23: =Trend!J13 -> 49120055 | ... AR23: =Trend!AR13 -> 0 | AS23: =Trend!AS12 -> 5151498 | AT23: =Trend!AT13 -> 0 | AU23: =Trend!AU13 -> 0 | AV23: =Trend!AV13 -> 0 | AW23: =Trend!AW13 -> 0 | AX23: =Trend!AX13 -> 0 | AY23: =Trend!AY13 -> 0 | AZ23: =Trend!AZ13 -> 0
A24: 6.3 | B24: Deposits in KUSCCO CFP
A25: 7 | B25: Net Loans & advances | C25: =C26-C27 -> 108864930 | D25: =D26-D27 -> 112673981 | E25: =E26-E27 -> 118004126 | F25: =F26-F27 -> 126643002 | G25: =G26-G27 -> 144740267 | H25: =H26-H27 -> 139423704 | I25: =I26-I27 -> 138129985 | J25: =J26-J27 -> 133289652 | ... AZ25: =AZ26-AZ27 -> 181059969
A26: 7.1 | B26: Gross Loans & advances | C26: =Trend!C17 -> 112489704 | D26: =Trend!D17 -> 116513632 | E26: =Trend!E17 -> 121965745 | F26: =Trend!F17 -> 131804621 | G26: =Trend!G17 -> 149901886 | H26: =Trend!H17 -> 144585323 | I26: =Trend!I17 -> 143291604 | J26: =Trend!J17 -> 138451271 | ... AZ26: =Trend!AZ17 -> 187471588
A27: 7.3 | B27: Allowance for loan losses | C27: =Trend!C18 -> 3624774 | D27: =Trend!D18 -> 3839651 | E27: =Trend!E18 -> 3961619 | F27: =Trend!F18 -> 5161619 | G27: =Trend!G18 -> 5161619 | H27: =Trend!H18 -> 5161619 | I27: =Trend!I18 -> 5161619 | J27: =Trend!J18 -> 5161619 | ... AZ27: =Trend!AZ18 -> 6411619
A28: 7.4 | B28: Non Performing Loans (A/L NPL30 | C28: -4 | D28: -3 | E28: -2 | F28: -1 | G28: 0 | H28: 0 | I28: 0 | J28: 0 | K28: 10 | M28: 24 | N28: 25 | O28: 26 | P28: 27 | Q28: 28 | R28: 29 | S28: 30 | T28: 31 | U28: 32 | V28: 33 | W28: 34 | X28: 35 | Y28: 36 | Z28: 37 | AA28: 38 | AB28: 39 | AC28: 40 | AD28: 41 | AE28: 42 | AF28: 43 | AG28: 44 | AH28: 45 | AI28: 46 | AJ28: 47 | AK28: 48 | AL28: 49 | AM28: 50 | AN28: 51 | AO28: 52 | AP28: 53 | AQ28: 54 | AR28: 55 | AS28: 56 | AT28: 57 | AU28: 58 | AV28: 59 | AW28: 60 | AX28: 61 | AY28: 62 | AZ28: 63
A29: 7.5666667 | B29: Non Performing Loans NPL30 | L29: 19839389
A30: 7.7166667 | B30: Required loan loss provision
A31: 7.8666667 | B31: Cash and Cash equipments | C31: =Trend!C3 -> 27227584 | D31: =Trend!D3 -> 20473615 | E31: =Trend!E3 -> 29501244 | F31: =Trend!F3 -> 52141499 | G31: =Trend!G3 -> 28844168 | H31: =Trend!H3 -> 28253972 | I31: =Trend!I3 -> 41920668 | J31: =Trend!J3 -> 37566335 | ... AZ31: =Trend!AZ3 -> 52036292
A32: 8 | B32: Non-Earning Assets | C32: =Trend!C7+Trend!C25 -> 13613816 | D32: =Trend!D7+Trend!D25 -> 16515426 | E32: =Trend!E7+Trend!E25 -> 19207971 | F32: =Trend!F7+Trend!F25 -> 18453671 | G32: =Trend!G7+Trend!G25 -> 18440527 | H32: =Trend!H7+Trend!H25 -> 18283896 | I32: =Trend!I7+Trend!I25 -> 18203707 | J32: =Trend!J7+Trend!J25 -> 18143421 | ... AS32: =Trend!AS7+Trend!AS25 -> 16928381 | AT32: =Trend!#REF!+Trend!AT25 -> #REF! | AU32: =Trend!#REF!+Trend!AU25 -> #REF! | AV32: =Trend!#REF!+Trend!AV25 -> #REF! | AW32: =Trend!#REF!+Trend!AW25 -> #REF! | AX32: =Trend!#REF!+Trend!AX25 -> #REF! | AY32: =Trend!#REF!+Trend!AY25 -> #REF! | AZ32: =Trend!#REF!+Trend!AZ25 -> #REF!
A33: 8.1 | B33: Property and Equipment | C33: =Trend!C27 -> 10052178 | D33: =Trend!D27 -> 14045660 | E33: =Trend!E27 -> 16051260 | F33: =Trend!F27 -> 11631992 | G33: =Trend!G27 -> 12221216 | H33: =Trend!H27 -> 11505240 | I33: =Trend!I27 -> 11511238 | J33: =Trend!J27 -> 11445987 | ... AZ33: =Trend!AZ27 -> 9570523
A34: 8.2 | B34: Land and Building | C34: 12999996 | D34: 12999997 | E34: 12999998 | F34: 12999999 | G34: 13000000 | H34: 13000002 | I34: 13000015 | J34: 13000021 | K34: 13000041 | L34: 13000054 | M34: 13000055 | N34: 13000056 | O34: 13000057 | P34: 13000058 | Q34: 13000059 | R34: 13000060 | S34: 13000060 | T34: 13000061 | U34: 13000062 | V34: 13000063 | W34: 13000064 | X34: 13000065 | Y34: 13000066 | Z34: 13000067 | AA34: 13000068 | AB34: 13000069 | AC34: 13000070 | AD34: 13000071 | AE34: 13000072 | AF34: 13000073 | AG34: 13000074 | AH34: 13000075 | AI34: 13000076 | AJ34: 13000077 | AK34: 13000078 | AL34: 13000079 | AM34: 13000080 | AN34: 13000081 | AO34: 13000082 | AP34: 13000083 | AQ34: 13000084 | AR34: 13000085 | AS34: 13000086 | AT34: 13000087 | AU34: 13000088 | AV34: 13000089 | AW34: 13000090 | AX34: 13000091 | AY34: 13000092 | AZ34: 13000093
A35: 9 | B35: Turnover | C35: =C36+C37+C38 -> 27127521 | D35: =D36+D37+D38 -> 27376695 | E35: =E36+E37+E38 -> 28491876 | F35: =F36+F37+F38 -> 30436001 | G35: =G36+G37+G38 -> 2318955.6 | H35: =H36+H37+H38 -> 4953370.5 | I35: =I36+I37+I38 -> 7211467.8 | J35: =J36+J37+J38 -> 9740396.4 | ... AZ35: =AZ36+AZ37+AZ38 -> 0
A36: 9.1 | B36: Loan Interest | C36: =Trend!C74 -> 18352026 | D36: =Trend!D74 -> 18322301 | E36: =Trend!E74 -> 18131997 | F36: =Trend!F74 -> 18377030 | G36: =Trend!G74 -> 1756233.8 | H36: =Trend!H74 -> 3494619.5 | I36: =Trend!I74 -> 5151232.2 | J36: =Trend!J74 -> 6814814 | ... AZ36: =Trend!AZ74 -> 0
B37: Income from investments | C37: =Trend!C76 -> 6136255 | D37: =Trend!D76 -> 6802219 | E37: =Trend!E76 -> 6612283 | F37: =Trend!F76 -> 12058971 | G37: =Trend!G76 -> 288948.04 | H37: =Trend!H76 -> 639294.26 | I37: =Trend!I76 -> 1059967.4 | J37: =Trend!J76 -> 1612656.6 | ... AZ37: =Trend!AZ76 -> 0
A38: 9.2 | B38: Fees & Commissions | C38: =Trend!C75 -> 2639240 | D38: =Trend!D75 -> 2252175 | E38: =Trend!E75 -> 3747596 | F38: =Trend!F75 -> 0 | G38: =Trend!G75 -> 273773.8 | H38: =Trend!H75 -> 819456.7 | I38: =Trend!I75 -> 1000268.2 | J38: =Trend!J75 -> 1312925.7 | ... AZ38: =Trend!AZ75 -> 0
B39: Average yield on loans | C39: =C36/C26 -> 0.16314405 | D39: =D36/D26 -> 0.15725457 | E39: =E36/E26 -> 0.14866467 | F39: =F36/F26 -> 0.1394263 | G39: =G36/G26 -> 0.011715889 | H39: =H36/H26 -> 0.024169947 | I39: =I36/I26 -> 0.035949295 | J39: =J36/J26 -> 0.049221751 | ... AZ39: =AZ36/AZ26 -> 0
A40: 10 | B40: Total Expenses (FinCosts + OpEx) | C40: =SUM(C41:C47) -> 29985207 | D40: =SUM(D41:D47) -> 30890339 | E40: =SUM(E41:E47) -> 32359574 | F40: =SUM(F41:F47) -> 35035493 | G40: =SUM(G41:G47) -> 1533035.8 | H40: =SUM(H41:H47) -> 3613385.2 | I40: =SUM(I41:I47) -> 6374557.4 | J40: =SUM(J41:J47) -> 8161207.5 | ... AZ40: =SUM(AZ41:AZ47) -> 0
A41: 10.1 | B41: Financial Exp. (Interest on deposits) | C41: =Trend!C93 -> 4472114 | D41: =Trend!D93 -> 5710996 | E41: =Trend!E93 -> 5971894 | F41: =Trend!F93 -> 6436772 | G41: =Trend!G93 -> 588360.4 | H41: =Trend!H93 -> 1165382.8 | I41: =Trend!I93 -> 1771537.7 | J41: =Trend!J93 -> 2345206.1 | ... AZ41: =Trend!AZ93 -> 0
A42: 10.2 | B42: Financial Exp. (Dividends) | C42: =Trend!C82 -> 9449807 | D42: =Trend!D82 -> 9899196 | E42: =Trend!E82 -> 11083861 | F42: =Trend!F82 -> 11740414 | G42: =Trend!G84 -> 0 | H42: =Trend!H84 -> 200000 | I42: =Trend!I84 -> 300000 | J42: =Trend!J84 -> 400000 | K42: =Trend!K84 -> 500000 | L42: =Trend!L84 -> 600000 | M42: =Trend!M84 -> 700000 | N42: =Trend!N84 -> 800000 | ... AZ42: =Trend!AZ84 -> 0
A43: 10.3 | B43: Financial Exp. (Interest on bank loans) | C43: =Trend!C83 -> 772280 | D43: =Trend!D83 -> 505621 | E43: =Trend!E83 -> 975753 | F43: =Trend!F83 -> 1298320 | G43: =Trend!G83 -> 0 | H43: =Trend!H83 -> 0 | I43: =Trend!I83 -> 583973.01 | J43: =Trend!J83 -> 583973.01 | ... AZ43: =Trend!AZ83 -> 0
A44: 10.4 | B44: Other Financial Expenses | C44: =Trend!C85+Trend!C86+Trend!C87 -> 0 | D44: =Trend!D85+Trend!D86+Trend!D87 -> 97299 | E44: =Trend!E85+Trend!E86+Trend!E87 -> 0 | F44: =Trend!F85+Trend!F86+Trend!F87 -> 392211 | G44: =Trend!G85+Trend!G86+Trend!G87 -> 54840 | H44: =Trend!H85+Trend!H86+Trend!H87 -> 90222 | I44: =Trend!I85+Trend!I86+Trend!I87 -> 121725 | J44: =Trend!J85+Trend!J86+Trend!J87 -> 153093 | ... AZ44: =Trend!AZ85+Trend!AZ86+Trend!AZ87 -> 0
A45: 10.5 | B45: Operating Expenses | C45: =Trend!C92 -> 14145467 | D45: =Trend!D92 -> 14462350 | E45: =Trend!E92 -> 14206098 | F45: =Trend!F92 -> 13467776 | G45: =Trend!G92 -> 889835.41 | H45: =Trend!H92 -> 2157780.4 | I45: =Trend!I92 -> 3597321.7 | J45: =Trend!J92 -> 4678935.4 | ... AZ45: =Trend!AZ92 -> 0
B47: LLP | C47: =Trend!C89 -> 1145539 | D47: =Trend!D89 -> 214877 | E47: =Trend!E89 -> 121968 | F47: =Trend!F89 -> 1700000 | G47: =Trend!G89 -> 0 | H47: =Trend!H89 -> 0 | I47: =Trend!I89 -> 0 | J47: =Trend!J89 -> 0 | ... AZ47: =Trend!AZ89 -> 0
B48: Liquid Assets | C48: =Trend!C3+Trend!C10+Trend!C11+Trend!C12 -> 27227584 | D48: =Trend!D3+Trend!D10+Trend!D11+Trend!D12 -> 20473615 | E48: =Trend!E3+Trend!E10+Trend!E11+Trend!E12 -> 29501244 | F48: =Trend!F3+Trend!F10+Trend!F11+Trend!F12 -> 52141499 | G48: =Trend!G3+Trend!G10+Trend!G11+Trend!G12 -> 28844168 | H48: =Trend!H3+Trend!H10+Trend!H11+Trend!H12 -> 28253972 | I48: =Trend!I3+Trend!I10+Trend!I11+Trend!I12 -> 41920668 | J48: =Trend!J3+Trend!J10+Trend!J11+Trend!J12 -> 37566335 | ... AR48: =Trend!AR3+Trend!AR10+Trend!AR11+Trend!AR12 -> 33779898 | AS48: =Trend!AS3+Trend!AS10+Trend!AS11+Trend!#REF! -> #REF! | AT48: =Trend!AT3+Trend!AT10+Trend!AT11+Trend!AT12 -> 33053005 | AU48: =Trend!AU3+Trend!AU10+Trend!AU11+Trend!AU12 -> 30301467 | AV48: =Trend!AV3+Trend!AV10+Trend!AV11+Trend!AV12 -> 22141968 | AW48: =Trend!AW3+Trend!AW10+Trend!AW11+Trend!AW12 -> 26781742 | AX48: =Trend!AX3+Trend!AX10+Trend!AX11+Trend!AX12 -> 26799067 | AY48: =Trend!AY3+Trend!AY10+Trend!AY11+Trend!AY12 -> 32301326 | AZ48: =Trend!AZ3+Trend!AZ10+Trend!AZ11+Trend!AZ12 -> 52036292
B49: Total Income | C49: =Trend!C72+Trend!C91+Trend!C100 -> 27127521 | D49: =Trend!D72+Trend!D91+Trend!D100 -> 27376695 | E49: =Trend!E72+Trend!E91+Trend!E100 -> 28491876 | F49: =Trend!F72+Trend!F91+Trend!F100 -> 30436001 | G49: =Trend!G72+Trend!G91+Trend!G100 -> 2318955.6 | H49: =Trend!H72+Trend!H91+Trend!H100 -> 4953370.5 | I49: =Trend!I72+Trend!I91+Trend!I100 -> 7211467.8 | J49: =Trend!J72+Trend!J91+Trend!J100 -> 9740396.4 | ... AZ49: =Trend!AZ72+Trend!AZ91+Trend!AZ100 -> 0
B50: Total Expenses | C50: =Trend!C81+Trend!C90+Trend!C92+Trend!C101+Trend!C103 -> 25559264 | D50: =Trend!D81+Trend!D90+Trend!D92+Trend!D101+Trend!D103 -> 25179343 | E50: =Trend!E81+Trend!E90+Trend!E92+Trend!E101+Trend!E103 -> 26552427 | F50: =Trend!F81+Trend!F90+Trend!F92+Trend!F101+Trend!F103 -> 28738814 | G50: =Trend!G81+Trend!G90+Trend!G92+Trend!G101+Trend!G103 -> 944675.41 | H50: =Trend!H81+Trend!H90+Trend!H92+Trend!H101+Trend!H103 -> 4448002.4 | I50: =Trend!I81+Trend!I90+Trend!I92+Trend!I101+Trend!I103 -> 6903019.7 | J50: =Trend!J81+Trend!J90+Trend!J92+Trend!J101+Trend!J103 -> 9616001.4 | ... AZ50: =Trend!AZ81+Trend!AZ90+Trend!AZ92+Trend!AZ101+Trend!AZ103 -> 0
B51: Short Term Liabilities | C51: =C10+C8 -> 28223010 | D51: =D10+D8 -> 28403144 | E51: =E10+E8 -> 31995152 | F51: =F10+F8 -> 42601176 | G51: =G10+G8 -> 41174818 | H51: =H10+H8 -> 39112187 | I51: =I10+I8 -> 41876617 | J51: =J10+J8 -> 35685522 | ... AZ51: =AZ10+AZ8 -> 0
B52: Average Assets | S52: =(S5+F5)/2 -> 2.3057174e+08 | T52: =(T5+G5)/2 -> 2.5882489e+08 | U52: =(U5+H5)/2 -> 2.3220537e+08 | V52: =(V5+I5)/2 -> 2.3792565e+08 | W52: =(W5+J5)/2 -> 2.3219598e+08 | X52: =(X5+K5)/2 -> 2.2942923e+08 | Y52: =(Y5+L5)/2 -> 2.2666697e+08 | Z52: =(Z5+M5)/2 -> 2.3320808e+08 | ... AZ52: =(AZ5+AM5)/2 -> #REF!
B53: Core Capital
B54: Institutional Capital
B55: Average gross loans | S55: =(S26+F26)/2 -> 1.5120006e+08 | T55: =(T26+G26)/2 -> 164422070 | U55: =(U26+H26)/2 -> 161620705 | V55: =(V26+I26)/2 -> 158988561 | W55: =(W26+J26)/2 -> 1.5656548e+08 | X55: =(X26+K26)/2 -> 1.5684189e+08 | Y55: =(Y26+L26)/2 -> 1.5561172e+08 | Z55: =(Z26+M26)/2 -> 1.6757901e+08 | ... AZ55: =(AZ26+AM26)/2 -> 185003099
B61: Description | C61: Audited 2016 | D61: Audited 2017 | E61: Audited 2018 | F61: Audited 2019 | G61: 43891 | H61: 43983 | I61: 44075 | J61: 44166
B62: Total Assets | C62: 190156140 | D62: 1.9878308e+08 | E62: 215833396 | F62: 246382881 | G62: 2.4739907e+08 | H62: 2.3597468e+08 | I62: 2.5330628e+08 | J62: 2.5880998e+08
B63: Core Capital | C63: 24822209 | D63: 34314785 | E63: 35358713 | F63: 36137160 | G63: 36589607 | H63: 37542920 | I63: 39621162 | J63: 39766288
B64: Share Capital | C64: 10092600 | D64: 10571400 | E64: 10978200 | F64: 11404800 | G64: 11548800 | H64: 11945719 | I64: 13211239 | J64: 14458167
B65: Gross Loans Portfolio | C65: 112489704 | D65: 116513632 | E65: 121965745 | F65: 131804621 | G65: 143291604 | H65: 140220540 | I65: 160536761 | J65: 170698863
B66: FOSA Deposits | C66: 8225206 | D66: 7582824 | E66: 12295782 | F66: 16518900 | G66: 9323076 | H66: 12332975 | I66: 12509093 | J66: 14908062
B67: BOSA Deposits | C67: 93532161 | D67: 98991963 | E67: 109828204 | F67: 116729770 | G67: 119559661 | H67: 124213870 | I67: 130016226 | J67: 135994936

Sheet Prudential Ratios
C1: Sotico Sacco Society
C2: Financial Performance
C3: FINANCIAL SOUNDNESS INDICATORS | D3: Prude. Std | E3: Ref. # | F3: Audit 16 | G3: Audit 17 | H3: Audit 18 | I3: Audit 19 | J3: 43831 | K3: 43862 | L3: 43891 | M3: 43922 | N3: 43952 | O3: 43983 | P3: 44013 | Q3: 44044 | R3: 44075 | S3: 44105 | T3: 44136 | U3: 44166 | V3: Audit 20 | W3: 44217 | X3: 44248 | Y3: 44276 | Z3: 44307 | AA3: 44337 | AB3: 44368 | AC3: 44398 | AD3: 44429 | AE3: 44460 | AF3: 44490 | AG3: 44521 | AH3: 44551 | AI3: Audited 2021 | AJ3: 44562 | AK3: 44593 | AL3: 44621 | AM3: 44652 | AN3: 44682 | AO3: 44713 | AP3: 44743 | AQ3: 44774 | AR3: 44805 | AS3: 44835 | AT3: 44866 | AU3: 44896 | AV3: audited 22
B4: 1 | C4: CAPITAL ADEQUACY REQUIREMENTS
B5: 1.1 | C5: Core capital | D5: ≥ Ksh.10M | E5: 9.a | F5: =Financials!C12/1000000 -> 24.822209 | G5: =Financials!D12/1000000 -> 34.314785 | H5: =Financials!E12/1000000 -> 35.358713 | I5: =Financials!F12/1000000 -> 36.13716 | J5: =Financials!G12/1000000 -> 37.53704 | K5: =Financials!H12/1000000 -> 36.642527 | L5: =Financials!I12/1000000 -> 36.589607 | M5: =Financials!J12/1000000 -> 36.405554 | ... AV5: =Financials!AS12/1000000 -> 37.690995
B6: 1.2 | C6: Core capital /Total Assets | D6: ≥ 10% | E6: 9.b | F6: =Financials!C12/Financials!C5 -> 0.13053593 | G6: =Financials!D12/Financials!D5 -> 0.17262428 | H6: =Financials!E12/Financials!E5 -> 0.16382411 | I6: =Financials!F12/Financials!F5 -> 0.14667074 | J6: =Financials!G12/Financials!G5 -> 0.15564577 | K6: =Financials!H12/Financials!H5 -> 0.15585516 | L6: =Financials!I12/Financials!I5 -> 0.14789711 | M6: =Financials!J12/Financials!J5 -> 0.15287194 | ... AV6: =Financials!AS12/Financials!AS5 -> 0.159867
B7: 1.3 | C7: Core capital /Total Deposits | D7: ≥ 8% | E7: 9.d | F7: =Financials!C12/Financials!C6 -> 0.24037599 | G7: =Financials!D12/Financials!D6 -> 0.3190655 | H7: =Financials!E12/Financials!E6 -> 0.28953127 | I7: =Financials!F12/Financials!F6 -> 0.27120091 | J7: =Financials!G12/Financials!G6 -> 0.28785616 | K7: =Financials!H12/Financials!H6 -> 0.28233047 | L7: =Financials!I12/Financials!I6 -> 0.27964212 | M7: =Financials!J12/Financials!J6 -> 0.275568 | ... AV7: =Financials!AS12/Financials!AS6 -> 0.21780167
B8: 1.4 | C8: Share Capital/Total Assets | D8: ≤2% | E8: 9.c | F8: =Financials!C15/Financials!C5 -> 0.053075331 | G8: =Financials!D15/Financials!D5 -> 0.053180583 | H8: =Financials!E15/Financials!E5 -> 0.050864232 | I8: =Financials!F15/Financials!F5 -> 0.04628893 | J8: =Financials!G15/Financials!G5 -> 0.047289528 | K8: =Financials!H15/Financials!H5 -> 0.048509125 | L8: =Financials!I15/Financials!I5 -> 0.046680855 | M8: =Financials!J15/Financials!J5 -> 0.048495004 | ... AV8: =Financials!AS15/Financials!AS5 -> 0.072291087
B9: 1.5 | C9: Institutional Capital/Total Assets | D9: ≥ 8% | E9: 9.c | F9: =Financials!C13/Financials!C5 -> 0.077460602 | G9: =Financials!D13/Financials!D5 -> 0.11944369 | H9: =Financials!E13/Financials!E5 -> 0.11295987 | I9: =Financials!F13/Financials!F5 -> 0.10038181 | J9: =Financials!G13/Financials!G5 -> 0.10835625 | K9: =Financials!H13/Financials!H5 -> 0.10734603 | L9: =Financials!I13/Financials!I5 -> 0.10121625 | M9: =Financials!J13/Financials!J5 -> 0.10437694 | ... AV9: =Financials!AS13/Financials!AS5 -> 0.087575916
B10: 2 | C10: ASSET MIX AND QUALITY
B11: 2.1 | C11: Non Earning Assets
B12: 2.1.1 | C12: Non earning Assets/Total assets | D12: ≤ 10% | E12: 48.1 | F12: =Financials!C32/Financials!C5 -> 0.071592829 | G12: =Financials!D32/Financials!D5 -> 0.083082656 | H12: =Financials!E32/Financials!E5 -> 0.088994434 | I12: =Financials!F32/Financials!F5 -> 0.074898349 | J12: =Financials!G32/Financials!G5 -> 0.076462877 | K12: =Financials!H32/Financials!H5 -> 0.07776864 | L12: =Financials!I32/Financials!I5 -> 0.073580339 | M12: =Financials!J32/Financials!J5 -> 0.076186728 | ... AV12: =Financials!AS32/Financials!AS5 -> 0.071802019
B13: 2.1.2 | C13: Property and Equipment/Total Assets | D13: ≤ 5% | E13: 48.1 | F13: =Financials!C33/Financials!C5 -> 0.052862758 | G13: =Financials!D33/Financials!D5 -> 0.070658228 | H13: =Financials!E33/Financials!E5 -> 0.074368751 | I13: =Financials!F33/Financials!F5 -> 0.04721104 | J13: =Financials!G33/Financials!G5 -> 0.050674763 | K13: =Financials!H33/Financials!H5 -> 0.048936336 | L13: =Financials!I33/Financials!I5 -> 0.046529027 | M13: =Financials!J33/Financials!J5 -> 0.048063278 | ... AV13: =Financials!AS33/Financials!AS5 -> 0.067401008
B14: 2.1.3 | C14: Non Performing loans/Gross Loans | D14: ≤ 6% | E14: 41 | F14: =Financials!C28/Financials!C26 -> -3.555881e-08 | G14: =Financials!D28/Financials!D26 -> -2.574806e-08 | H14: =Financials!E28/Financials!E26 -> -1.6398047e-08 | I14: =Financials!F28/Financials!F26 -> -7.5869874e-09 | J14: =Financials!G28/Financials!G26 -> 0 | K14: =Financials!H28/Financials!H26 -> 0 | L14: =Financials!I28/Financials!I26 -> 0 | M14: =Financials!J28/Financials!J26 -> 0 | N14: =Financials!K28/Financials!K26 -> 7.143096e-08 | O14: =Financials!L29/Financials!L26 -> 0.14148704 | P14: =Financials!M29/Financials!M26 -> 0 | Q14: =Financials!N29/Financials!N26 -> 0 | R14: =Financials!O29/Financials!O26 -> 0 | S14: =Financials!P29/Financials!P26 -> 0 | T14: =Financials!Q29/Financials!Q26 -> 0 | U14: =Financials!R29/Financials!R26 -> 0 | V14: =Financials!S29/Financials!S26 -> 0 | ... AV14: =Financials!AS29/Financials!AS26 -> 0
B15: 2.2 | C15: Earning Assets
B16: 2.2.1 | C16: Equities & Investments/Deposits | D16: ≤ 5% | E16: 48.4 | F16: =Financials!C21/Financials!C6 -> 0.39171224 | G16: =Financials!D21/Financials!D6 -> 0.45672777 | H16: =Financials!E21/Financials!E6 -> 0.40221464 | I16: =Financials!F21/Financials!F6 -> 0.36863449 | J16: =Financials!G21/Financials!G6 -> 0.37668155 | K16: =Financials!H21/Financials!H6 -> 0.37846976 | L16: =Financials!I21/Financials!I6 -> 0.37540813 | M16: =Financials!J21/Financials!J6 -> 0.37180908 | ... AV16: =Financials!AS21/Financials!AS6 -> #REF!
B17: 2.2.2 | C17: Equities & Investments/Core Capital | D17: ≤ 40% | E17: 48.4 | F17: =Financials!C21/Financials!C12 -> 1.6295814 | G17: =Financials!D21/Financials!D12 -> 1.4314546 | H17: =Financials!E21/Financials!E12 -> 1.3891924 | I17: =Financials!F21/Financials!F12 -> 1.3592672 | J17: =Financials!G21/Financials!G12 -> 1.3085756 | K17: =Financials!H21/Financials!H12 -> 1.3405204 | L17: =Financials!I21/Financials!I12 -> 1.3424592 | M17: =Financials!J21/Financials!J12 -> 1.3492462 | ... AV17: =Financials!AS21/Financials!AS12 -> #REF!
B18: 2.2.3 | C18: Net Loans & advances /Total assets | D18: NPR | F18: =Financials!C25/Financials!C5 -> 0.57250284 | G18: =Financials!D25/Financials!D5 -> 0.56681878 | H18: =Financials!E25/Financials!E5 -> 0.5467371 | I18: =Financials!F25/Financials!F5 -> 0.51400893 | J18: =Financials!G25/Financials!G5 -> 0.60015949 | K18: =Financials!H25/Financials!H5 -> 0.59302416 | L18: =Financials!I25/Financials!I5 -> 0.55832864 | M18: =Financials!J25/Financials!J5 -> 0.55970164 | ... AV18: =Financials!AS25/Financials!AS5 -> 0.78454916
B19: 3 | C19: FUNDING MIX
B20: 3.1 | C20: Total Deposits/Total Assets | D20: NPR | F20: =Financials!C6/Financials!C5 -> 0.54304896 | G20: =Financials!D6/Financials!D5 -> 0.54103083 | H20: =Financials!E6/Financials!E5 -> 0.56582525 | I20: =Financials!F6/Financials!F5 -> 0.54081951 | J20: =Financials!G6/Financials!G5 -> 0.54070676 | K20: =Financials!H6/Financials!H5 -> 0.55203095 | L20: =Financials!I6/Financials!I5 -> 0.52887995 | M20: =Financials!J6/Financials!J5 -> 0.55475215 | ... AV20: =Financials!AS6/Financials!AS5 -> 0.73400267
B21: 3.1.1 | C21: BOSA Deposits/Total Assets | D21: NPR | F21: =Financials!C7/Financials!C5 -> 0.49187032 | G21: =Financials!D7/Financials!D5 -> 0.49798989 | H21: =Financials!E7/Financials!E5 -> 0.5088564 | I21: =Financials!F7/Financials!F5 -> 0.47377387 | J21: =Financials!G7/Financials!G5 -> 0.48706719 | K21: =Financials!H7/Financials!H5 -> 0.50295516 | L21: =Financials!I7/Financials!I5 -> 0.48326641 | M21: =Financials!J7/Financials!J5 -> 0.50683975 | ... AV21: =Financials!AS7/Financials!AS5 -> 0.66976194
B22: 3.1.2 | C22: FOSA Deposits/Total Assets | D22: NPR | F22: =Financials!C8/Financials!C5 -> 0.051178647 | G22: =Financials!D8/Financials!D5 -> 0.043040943 | H22: =Financials!E8/Financials!E5 -> 0.056968858 | I22: =Financials!F8/Financials!F5 -> 0.067045648 | J22: =Financials!G8/Financials!G5 -> 0.053639568 | K22: =Financials!H8/Financials!H5 -> 0.049075792 | L22: =Financials!I8/Financials!I5 -> 0.045613539 | M22: =Financials!J8/Financials!J5 -> 0.047912399 | ... AV22: =Financials!AS8/Financials!AS5 -> 0.064240726
B23: 3.2 | C23: External Borrowing/Total assets | D23: ≤ 25% | E23: 35.1 | F23: =Financials!C9/Financials!C5 -> 0.036811854 | G23: =Financials!D9/Financials!D5 -> 0 | H23: =Financials!E9/Financials!E5 -> 0 | I23: =Financials!F9/Financials!F5 -> 0.048704683 | J23: =Financials!G9/Financials!G5 -> 0.032834954 | K23: =Financials!H9/Financials!H5 -> 0.016292487 | L23: =Financials!I9/Financials!I5 -> 0.048504629 | M23: =Financials!J9/Financials!J5 -> 0.033084802 | ... AV23: =Financials!AS9/Financials!AS5 -> 0
B24: 4 | C24: GROWTH RATIOS
B25: 4.1 | C25: Total Assets | D25: NPR | G25: =Financials!D5/Financials!C5-1 -> 0.045367649 | H25: =Financials!E5/Financials!D5-1 -> 0.085773494 | I25: =Financials!F5/Financials!E5-1 -> 0.14154197 | J25: =Financials!G5/Financials!F5-1 -> -0.021158979 | K25: =Financials!H5/Financials!G5-1 -> -0.025141595 | L25: =Financials!I5/Financials!H5-1 -> 0.052286094 | M25: =Financials!J5/Financials!I5-1 -> -0.037409003 | N25: =Financials!K5/Financials!J5-1 -> -0.0033990913 | ... AV25: =Financials!AS5/Financials!AR5-1 -> 0.0004055919
B26: 4.2 | C26: Total Deposits | D26: NPR | G26: =Financials!D6/Financials!C6-1 -> 0.041482754 | H26: =Financials!E6/Financials!D6-1 -> 0.13553244 | I26: =Financials!F6/Financials!E6-1 -> 0.091093358 | J26: =Financials!G6/Financials!F6-1 -> -0.021363058 | K26: =Financials!H6/Financials!G6-1 -> -0.0047248253 | L26: =Financials!I6/Financials!H6-1 -> 0.0081554594 | M26: =Financials!J6/Financials!I6-1 -> 0.0096798481 | N26: =Financials!K6/Financials!J6-1 -> 0.044763348 | ... AV26: =Financials!AS6/Financials!AR6-1 -> -0.00024967196
B27: 4.2.1 | C27: FOSA Deposits | D27: NPR | G27: =Financials!D8/Financials!C8-1 -> -0.12085193 | H27: =Financials!E8/Financials!D8-1 -> 0.43712642 | I27: =Financials!F8/Financials!E8-1 -> 0.34346071 | J27: =Financials!G8/Financials!F8-1 -> -0.21688266 | K27: =Financials!H8/Financials!G8-1 -> -0.10808475 | L27: =Financials!I8/Financials!H8-1 -> -0.02195176 | M27: =Financials!J8/Financials!I8-1 -> 0.011104281 | N27: =Financials!K8/Financials!J8-1 -> 0.38580819 | ... AV27: =Financials!AS8/Financials!AR8-1 -> -0.0028452993
B28: 4.2.2 | C28: BOSA Deposits | D28: NPR | G28: =Financials!D7/Financials!C7-1 -> 0.058373526 | H28: =Financials!E7/Financials!D7-1 -> 0.10946587 | I28: =Financials!F7/Financials!E7-1 -> 0.062839651 | J28: =Financials!G7/Financials!F7-1 -> 0.0063057093 | K28: =Financials!H7/Financials!G7-1 -> 0.0066579615 | L28: =Financials!I7/Financials!H7-1 -> 0.011093168 | M28: =Financials!J7/Financials!I7-1 -> 0.0095454018 | N28: =Financials!K7/Financials!J7-1 -> 0.012523817 | ... AV28: =Financials!AS7/Financials!AR7-1 -> 0
B29: 4.3 | C29: Net Loans & advances | D29: NPR | G29: =Financials!D25/Financials!C25-1 -> 0.034988779 | H29: =Financials!E25/Financials!D25-1 -> 0.047305908 | I29: =Financials!F25/Financials!E25-1 -> 0.073208254 | J29: =Financials!G25/Financials!F25-1 -> 0.14289984 | K29: =Financials!H25/Financials!G25-1 -> -0.036731748 | L29: =Financials!I25/Financials!H25-1 -> -0.0092790463 | M29: =Financials!J25/Financials!I25-1 -> -0.03504187 | N29: =Financials!K25/Financials!J25-1 -> 0.0090833283 | ... AV29: =Financials!AS25/Financials!AR25-1 -> 3.1951404e-06
B30: 4.4 | C30: Core capital | D30: NPR | G30: =Financials!D12/Financials!C12-1 -> 0.38242268 | H30: =Financials!E12/Financials!D12-1 -> 0.030422113 | I30: =Financials!F12/Financials!E12-1 -> 0.022015705 | J30: =Financials!G12/Financials!F12-1 -> 0.038737964 | K30: =Financials!H12/Financials!G12-1 -> -0.023830142 | L30: =Financials!I12/Financials!H12-1 -> -0.0014442235 | M30: =Financials!J12/Financials!I12-1 -> -0.0050301989 | N30: =Financials!K12/Financials!J12-1 -> 0.015367298 | ... AV30: =Financials!AS12/Financials!AR12-1 -> 0.0046187788
B31: 4.5 | C31: Total Gross Income | D31: NPR | G31: =Financials!D35/Financials!C35-1 -> 0.0091852846 | H31: =Financials!E35/Financials!D35-1 -> 0.040734683 | I31: =Financials!F35/Financials!E35-1 -> 0.068234363 | J31: =Financials!G35/Financials!F35-1 -> -0.92380879 | K31: =Financials!H35/Financials!G35-1 -> 1.136035 | L31: =Financials!I35/Financials!H35-1 -> 0.45587088 | M31: =Financials!J35/Financials!I35-1 -> 0.35068152 | N31: =Financials!K35/Financials!J35-1 -> 0.72325588 | ... AV31: =Financials!AS35/Financials!AR35-1 -> #DIV/0!
B32: 4.6 | C32: Membership | D32: NPR | G32: =Financials!D3/Financials!#REF!-1 -> #VALUE! | H32: =Financials!E3/Financials!#REF!-1 -> #VALUE! | I32: =Financials!F3/Financials!#REF!-1 -> #VALUE! | J32: =Financials!G3/Financials!#REF!-1 -> #REF! | K32: =Financials!H3/Financials!#REF!-1 -> #REF! | L32: =Financials!I3/Financials!#REF!-1 -> #REF! | M32: =Financials!J3/Financials!#REF!-1 -> #REF! | N32: =Financials!K3/Financials!#REF!-1 -> #REF! | ... AV32: =Financials!AS3/Financials!#REF!-1 -> #VALUE!
B33: 5 | C33: Efficiency Ratios
B34: 5.1 | C34: FinCost-Deposits/Average Deposits | D34: NPR | G34: =Financials!D41/((Financials!D6+Financials!C6)/2) -> 0.054180972 | H34: =Financials!E41/((Financials!E6+Financials!D6)/2) -> 0.052003729 | I34: =Financials!F41/((Financials!F6+Financials!E6)/2) -> 0.050410816 | J34: =Financials!G41/((Financials!G6+Financials!F6)/2) -> 0.0044631803 | K34: =Financials!H41/((Financials!H6+Financials!G6)/2) -> 0.0089580052 | L34: =Financials!I41/((Financials!I6+Financials!H6)/2) -> 0.013594255 | M34: =Financials!J41/((Financials!J6+Financials!I6)/2) -> 0.017837294 | N34: =Financials!K41/((Financials!K6+Financials!J6)/2) -> 0.022307311 | ... AV34: =Financials!AS41/((Financials!AS6+Financials!AR6)/2) -> 0.042571694
B35: 5.2 | C35: FinCost-Shares/Average Share capital | D35: NPR | G35: =Financials!D42/((Financials!D15+Financials!C15)/2) -> 0.95811034 | H35: =Financials!E42/((Financials!E15+Financials!D15)/2) -> 1.0286837 | I35: =Financials!F42/((Financials!F15+Financials!E15)/2) -> 1.0490474 | J35: =Financials!G42/((Financials!G15+Financials!F15)/2) -> 0 | K35: =Financials!H42/((Financials!H15+Financials!G15)/2) -> 0.017536476 | L35: =Financials!I42/((Financials!I15+Financials!H15)/2) -> 0.026139691 | M35: =Financials!J42/((Financials!J15+Financials!I15)/2) -> 0.034635633 | N35: =Financials!K42/((Financials!K15+Financials!J15)/2) -> 0.043073 | ... AV35: =Financials!AS42/((Financials!AS15+Financials!AR15)/2) -> 0
B36: 5.3 | C36: FinCost-Ext Loans/Average Ext Loans | D36: NPR | G36: =Financials!D43/((Financials!D9+Financials!C9)/2) -> 0.14446314 | H36: =Financials!E43/((Financials!E9+Financials!D9)/2) -> #DIV/0! | I36: =Financials!F43/((Financials!F9+Financials!E9)/2) -> 0.21638667 | J36: =Financials!G43/((Financials!G9+Financials!F9)/2) -> 0 | K36: =Financials!H43/((Financials!H9+Financials!G9)/2) -> 0 | L36: =Financials!I43/((Financials!I9+Financials!H9)/2) -> 0.073778373 | M36: =Financials!J43/((Financials!J9+Financials!I9)/2) -> 0.0587529 | N36: =Financials!K43/((Financials!K9+Financials!J9)/2) -> 0.10071775 | ... AV36: =Financials!AS43/((Financials!AS9+Financials!AR9)/2) -> #DIV/0!
B37: 5.4 | C37: OpEx/Average Total Assets | D37: NPR | G37: =(Financials!D45+Financials!D46)/((Financials!D5+Financials!C5)/2) -> 0.074368176 | H37: =(Financials!E45+Financials!E46)/((Financials!E5+Financials!D5)/2) -> 0.068526452 | I37: =(Financials!F45+Financials!F46)/((Financials!F5+Financials!E5)/2) -> 0.05827478 | J37: =(Financials!G45+Financials!G46)/((Financials!G5+Financials!F5)/2) -> 0.0036502133 | K37: =(Financials!H45+Financials!H46)/((Financials!H5+Financials!G5)/2) -> 0.0090610511 | L37: =(Financials!I45+Financials!I46)/((Financials!I5+Financials!H5)/2) -> 0.014911013 | M37: =(Financials!J45+Financials!J46)/((Financials!J5+Financials!I5)/2) -> 0.019272994 | N37: =(Financials!K45+Financials!K46)/((Financials!K5+Financials!J5)/2) -> 0.02647621 | ... AV37: =(Financials!AS45+Financials!AS46)/((Financials!AS5+Financials!AR5)/2) -> 0.068991214
B38: 5.5 | C38: Avge yield on Net loans | D38: NPR | G38: =Financials!D36/((Financials!D25+Financials!C25)/2) -> 0.16540933 | H38: =Financials!E36/((Financials!E25+Financials!D25)/2) -> 0.15720605 | I38: =Financials!F36/((Financials!F25+Financials!E25)/2) -> 0.15023295 | J38: =Financials!G36/((Financials!G25+Financials!F25)/2) -> 0.01294283 | K38: =Financials!H36/((Financials!H25+Financials!G25)/2) -> 0.024595796 | L38: =Financials!I36/((Financials!I25+Financials!H25)/2) -> 0.037118816 | M38: =Financials!J36/((Financials!J25+Financials!I25)/2) -> 0.050216072 | N38: =Financials!K36/((Financials!K25+Financials!J25)/2) -> 0.064592427 | ... AV38: =Financials!AS36/((Financials!AS25+Financials!AR25)/2) -> 0.13472299
B39: 6 | C39: Liquidity Ratio
B40: 6.1 | C40: Liquid Assets - ST Liabilities/ Deposits | D40: ≥15% | E40: 13.2 | F40: =Financials!C10/Financials!C6 -> 0.17906588 | G40: =Financials!D10/Financials!D6 -> 0.18454434 | H40: =Financials!E10/Financials!E6 -> 0.16130631 | I40: =Financials!F10/Financials!F6 -> 0.19574136 | J40: =Financials!G10/Financials!G6 -> 0.2165501 | K40: =Financials!H10/Financials!H6 -> 0.21245875 | L40: =Financials!I10/Financials!I6 -> 0.23380342 | M40: =Financials!J10/Financials!J6 -> 0.18375058 | N40: =Financials!K10/Financials!K6 -> 0.15254142 | O40: =Financials!L48/(Financials!L10+Financials!L6) -> 0.2141903 | P40: =Financials!M48/(Financials!M10+Financials!M6) -> 0.19954099 | Q40: =Financials!N48/(Financials!N10+Financials!N6) -> 0.18114906 | R40: =Financials!O48/(Financials!O10+Financials!O6) -> 0.19017381 | S40: =Financials!P48/(Financials!P10+Financials!P6) -> 0.15684265 | T40: =Financials!Q48/(Financials!Q10+Financials!Q6) -> 0.17240627 | U40: =Financials!R48/(Financials!R10+Financials!R6) -> 0.15337048 | V40: =Financials!S48/(Financials!S10+Financials!S6) -> 0.15292561 | ... AV40: =Financials!AS48/(Financials!AS10+Financials!AS6) -> #REF!
B41: 7 | C41: Loan Loss Provisions Ratios
B42: 7.1 | C42: Actual LLP / Required LLP | D42: 1 | E42: 44.1 | F42: =Financials!C27/Financials!C30 -> #DIV/0! | G42: =Financials!D27/Financials!D30 -> #DIV/0! | H42: =Financials!E27/Financials!E30 -> #DIV/0! | I42: =Financials!F27/Financials!F30 -> #DIV/0! | J42: =Financials!G27/Financials!G30 -> #DIV/0! | K42: =Financials!H27/Financials!H30 -> #DIV/0! | L42: =Financials!I27/Financials!I30 -> #DIV/0! | M42: =Financials!J27/Financials!J30 -> #DIV/0! | ... U42: =Financials!R27/Financials!R30 -> #DIV/0!
C43: RETURN ON ASSETS
B44: 8.1 | C44: COST INCOME RATIO | F44: =Trend!C92/Trend!C88 -> 0.83674084 | G44: =Trend!D92/Trend!D88 -> 0.85704953 | H44: =Trend!E92/Trend!E88 -> 0.8645248 | I44: =Trend!F92/Trend!F88 -> 0.79198657 | J44: =Trend!G92/Trend!G88 -> 0.39301677 | K44: =Trend!H92/Trend!H88 -> 0.8102366 | L44: =Trend!I92/Trend!I88 -> 0.92102756 | M44: =Trend!J92/Trend!J88 -> 0.97410235 | ... U44: =Trend!R92/Trend!R88 -> 0.96405549
B45: 8.2 | C45: OPERATING EXPENSE RATIO | F45: =Trend!C92/Financials!C5 -> 0.074388694 | G45: =Trend!D92/Financials!D5 -> 0.072754433 | H45: =Trend!E92/Financials!E5 -> 0.06581974 | I45: =Trend!F92/Financials!F5 -> 0.05466198 | J45: =Trend!G92/Financials!G5 -> 0.0036896655 | K45: =Trend!H92/Financials!H5 -> 0.0091778934 | L45: =Trend!I92/Financials!I5 -> 0.014540563 | M45: =Trend!J92/Financials!J5 -> 0.019647495 | ... U45: =Trend!R92/Financials!R5 -> 0.21385431
B46: 8.3 | C46: TECHNICAL LIQUIDITY
B47: 8.4 | C47: LIQUID ASSETS/TOTAL ASSETS | F47: =Financials!C48/Financials!C5 -> 0.14318541 | G47: =Financials!D48/Financials!D5 -> 0.10299476 | H47: =Financials!E48/Financials!E5 -> 0.13668526 | I47: =Financials!F48/Financials!F5 -> 0.21162793 | J47: =Financials!G48/Financials!G5 -> 0.11960114 | K47: =Financials!H48/Financials!H5 -> 0.12017532 | L47: =Financials!I48/Financials!I5 -> 0.16944554 | M47: =Financials!J48/Financials!J5 -> 0.15774622 | ... U47: =Financials!R48/Financials!R5 -> 0.10697872
B48: 8.5 | C48: GROSS LOANS/TOTAL ASSETS | F48: =Financials!C26/Financials!C5 -> 0.59156493 | G48: =Financials!D26/Financials!D5 -> 0.58613456 | H48: =Financials!E26/Financials!E5 -> 0.56509209 | I48: =Financials!F26/Financials!F5 -> 0.53495852 | J48: =Financials!G26/Financials!G5 -> 0.62156193 | K48: =Financials!H26/Financials!H5 -> 0.61497856 | L48: =Financials!I26/Financials!I5 -> 0.57919217 | M48: =Financials!J26/Financials!J5 -> 0.58137599 | ... U48: =Financials!R26/Financials!R5 -> 0.65955286
AT53: =

Sheet Sheet1
B2: Description | C2: Audited 2016 | D2: Audited 2017 | E2: Audited 2018 | F2: Audited 2019 | G2: 43891 | H2: 43983 | I2: 44075 | J2: 44166 | K2: 44197 | L2: 44228 | M2: 44256 | N2: 44287 | O2: 44317 | P2: 44348 | Q2: 44378 | R2: 44409 | S2: 44440 | T2: 44470 | U2: 44501 | V2: 44531
B3: Total Assets | C3: 190156140 | D3: 1.9878308e+08 | E3: 215833396 | F3: 246382881 | G3: 2.4739907e+08 | H3: 2.3597468e+08 | I3: 2.5330628e+08 | J3: 2.5880998e+08 | K3: 2.6176359e+08 | L3: 2.6692002e+08 | M3: 2.7207645e+08 | N3: 2.7723288e+08 | O3: 2.8238932e+08 | P3: 2.8754575e+08 | Q3: 2.920728e+08
B4: FOSA Deposits | C4: 8225206 | D4: 7582824 | E4: 12295782 | F4: 16518900 | G4: 9323076 | H4: 12332975 | I4: 12509093 | J4: 14908062 | K4: 16501070 | L4: 18194178 | M4: 19887286 | N4: 21580393 | O4: 23273501 | P4: 24966608 | Q4: 26631116
B5: BOSA Deposits | C5: 93532161 | D5: 98991963 | E5: 109828204 | F5: 116729770 | G5: 119559661 | H5: 124213870 | I5: 130016226 | J5: 135994936 | K5: 1.4122322e+08 | L5: 1.4673404e+08 | M5: 1.5224485e+08 | N5: 1.5775567e+08 | O5: 1.6326649e+08 | P5: 168777309 | Q5: 1.742074e+08
B6: Gross Loans | C6: 112489704 | D6: 116513632 | E6: 121965745 | F6: 1.3180462e+08 | G6: 143291604 | H6: 140220540 | I6: 160536761 | J6: 170698863 | K6: 1.7932144e+08 | L6: 1.8957524e+08 | M6: 1.9982904e+08 | N6: 2.1008284e+08 | O6: 2.2033664e+08 | P6: 2.3059044e+08 | Q6: 2.4037818e+08
B7: Core Capital | C7: 24822209 | D7: 34314785 | E7: 35358713 | F7: 36137160 | G7: 36589607 | H7: 37542920 | I7: 39621162 | J7: 39672352 | K7: 41188129 | L7: 42320777 | M7: 43453424 | N7: 44586072 | O7: 45718719 | P7: 46851367 | Q7: 48093480
B8: Institutional Capital | C8: 14729609 | D8: 23743385 | E8: 24380513 | F8: 24732360 | G8: 25040807 | H8: 25597201 | I8: 26409923 | J8: 25214184 | K8: 25898742 | L8: 26032028 | M8: 26165313 | N8: 26298599 | O8: 26431884 | P8: 26565170 | Q8: 26855962
B9: Non-Earning Assets | C9: 13613816 | D9: 16515426 | E9: 19207971 | F9: 18478326 | G9: 18203707 | H9: 17738124 | I9: 12688363 | J9: 12237220 | K9: 9479548.2 | L9: 7184626 | M9: 4889703.9 | N9: 2594781.7 | O9: 299859.53 | P9: -1995062.6 | Q9: -4422199.1
B10: Property and Equipment | C10: 10052178 | D10: 14045660 | E10: 16051260 | F10: 17187704 | G10: 11511238 | H10: 11357710 | I10: 11800314 | J10: 11551554 | K10: 11696092 | L10: 11752447 | M10: 11808802 | N10: 11865157 | O10: 11921512 | P10: 11977867 | Q10: 12059418
B11: Financial Investments | C11: 40449810 | D11: 49120055 | E11: 49120055 | F11: 49120055 | G11: 49120055 | H11: 49120055 | I11: 49120055 | J11: 49120055 | K11: 49120055 | L11: 49120055 | M11: 49120055 | N11: 49120054 | O11: 49120054 | P11: 49120054 | Q11: 49120054
B12: Liquid Assets | C12: 27227584 | D12: 20473615 | E12: 29501244 | F12: 52141499 | G12: 41920668 | H12: 34432928 | I12: 31894418 | J12: 27687159 | K12: 22674034 | L12: 18150131 | M12: 13626227 | N12: 9102323.5 | O12: 4578419.9 | P12: 54516.31 | Q12: -4609164.8
B13: Short-term Liabilities) | C13: 33716282 | D13: 27430157 | E13: 31995152 | F13: 31424451 | G13: 41876617 | H13: 36544708 | I13: 37695708 | J13: 44529756 | K13: 42439302 | L13: 43350343 | M13: 44261385 | N13: 45172427 | O13: 46083468 | P13: 46994510 | Q13: 47047981
B14: External Borrowing | C14: 7000000 | D14: 0 | E14: 0 | F14: 12000000 | G14: 12000000 | H14: 0 | I14: 8000000 | J14: 0 | K14: -2000000 | L14: -4800000 | M14: -7600000 | N14: -10400000 | O14: -13200000 | P14: -16000000 | Q14: -18571429
... B21: Net Income | C21: 1568257 | D21: 2197352 | E21: 1939449 | F21: 1697187 | G21: 308448.16 | H21: 654882.92 | I21: 1410256.7 | J21: 187873.03 | K21: 738777.31 | L21: 778142.15 | M21: 817506.99 | N21: 856871.83 | O21: 896236.67 | P21: 935601.52 | Q21: 1121120.5

Sheet FORM 4
B2: SOTICO SACCO
B3: C/S 6128
C4: Audited 2019 | G4: Audited 2020
B5: CLASSIFICATION | C5: NO. OF A/Cs | D5: OUTSTANDING LOAN PORTFOLIO(Kshs) | E5: RQD PROVISION | F5: REQUIRED PROVISION AMOUNT(Kshs) | G5: NO. OF A/Cs | H5: OUTSTANDING LOAN PORTFOLIO(Kshs) | I5: RQD PROVISION | J5: REQUIRED PROVISION AMOUNT(Kshs)
B6: Performing | C6: 2175 | D6: 107874948 | E6: 0.01 | F6: =D6*E6 -> 1078749.5 | G6: 3311 | H6: 1.5810399e+08 | I6: 0.01 | J6: =H6*I6 -> 1581039.9
B7: Watch | C7: 206 | D7: 11902836 | E7: 0.05 | F7: =D7*E7 -> 595141.8 | G7: 180 | H7: 7578057.2 | I7: 0.05 | J7: =H7*I7 -> 378902.86
B8: Substandard | C8: 324 | D8: 10316506 | E8: 0.25 | F8: =D8*E8 -> 2579126.5 | G8: 195 | H8: 3659039.5 | I8: 0.25 | J8: =H8*I8 -> 914759.87
B9: Doubtful | C9: 56 | D9: 1603462 | E9: 0.5 | F9: =D9*E9 -> 801731 | G9: 64 | H9: 1199772.5 | I9: 0.5 | J9: =H9*I9 -> 599886.25
B10: Loss | C10: 45 | D10: 106870 | E10: 1 | F10: =D10*E10 -> 106870 | G10: 14 | H10: 54630.186 | I10: 1 | J10: =H10*I10 -> 54630.186
B11: subtotal | C11: =SUM(C6:C10) -> 2806 | D11: =SUM(D6:D10) -> 131804622 | F11: =SUM(F6:F10) -> 5161618.8 | G11: =SUM(G6:G10) -> 3764 | H11: =SUM(H6:H10) -> 1.7059549e+08 | J11: =SUM(J6:J10) -> 3529219.1
B12: Reschedule/Renegotiated loans
B13: Performing | E13: 0.01 | F13: =E13*D13 -> 0 | I13: 0.01 | J13: =I13*H13 -> 0
B14: Watch | D14: =D13/D11 -> 0 | E14: 0.05 | F14: =E14*D14 -> 0 | H14: =H13/H11 -> 0 | I14: 0.05 | J14: =I14*H14 -> 0
B15: Substandard | E15: 0.25 | F15: =E15*D15 -> 0 | I15: 0.25 | J15: =I15*H15 -> 0
B16: Doubtful | E16: 0.5 | F16: =E16*D16 -> 0 | I16: 0.5 | J16: =I16*H16 -> 0
B17: Loss | E17: 1 | F17: =E17*D17 -> 0 | I17: 1 | J17: =I17*H17 -> 0
B18: subtotal | C18: =SUM(C13:C17) -> 0 | D18: =SUM(D13:D17) -> 0 | F18: =SUM(F13:F17) -> 0 | G18: =SUM(G13:G17) -> 0 | H18: =SUM(H13:H17) -> 0 | J18: =SUM(J13:J17) -> 0
B19: GRAND TOTAL | C19: =C11+C18 -> 2806 | D19: =D11+D18 -> 131804622 | E19: =E11+E18 -> 0 | F19: =F11+F18 -> 5161618.8 | G19: =G11+G18 -> 3764 | H19: =H11+H18 -> 1.7059549e+08 | I19: =I11+I18 -> 0 | J19: =J11+J18 -> 3529219.1
B20: NPL | D20: =SUM(D8:D10) -> 12026838 | H20: =SUM(H8:H10) -> 4913442.2
B21: PAR | D21: =D20/D19 -> 0.091247468
