Workbook

Sheet Evolutive SFP
B3: 2010 Audited | C3: 2020 Audited | D3: 44197 | E3: 44228 | F3: 44256 | G3: 44287 | H3: 44317 | I3: 44348 | J3: 44378 | K3: 44409 | L3: 44440 | M3: 44470 | N3: 44501 | O3: 44531 | P3: Audited 2021 | Q3: 44562 | R3: 44593 | S3: 44621 | T3: 44652 | U3: 44682 | V3: 44713 | W3: 44743 | X3: 44774 | Y3: 44805 | Z3: 44835 | AA3: 44866 | AB3: 44896 | AC3: Audited 2022 | AD3: 44927 | AE3: 44958 | AF3: 44986 | AG3: 45017 | AH3: 45047 | AI3: 45078
A4: Cash & cash Equivalent | B4: =SUM(B5:B6) -> 19363224 | C4: =SUM(C5:C6) -> 80999768 | D4: =SUM(D5:D6) -> 77138716 | E4: =SUM(E5:E6) -> 73684628 | F4: =SUM(F5:F6) -> 74121415 | G4: =SUM(G5:G6) -> 71189444 | H4: =SUM(H5:H6) -> 70304355 | I4: =SUM(I5:I6) -> 71367924 | ... AI4: =SUM(AI5:AI6) -> 0
A5: Cash In Hand | B5: 19363224 | C5: 4035251 | D5: 3995970.5 | E5: 3766598.5 | F5: 9326300.6 | G5: 6523468.4 | H5: 6020580.6 | I5: 4661148.9 | J5: 4172915.1 | K5: 5899898 | L5: 4658033 | M5: 6059450 | N5: 8118262 | O5: 11625492 | P5: 10261482 | Q5: 10176526 | R5: 11570375 | S5: 4777669.3 | T5: 9598330.1 | U5: 9337814.5 | V5: 9646218 | W5: 6587404.5 | X5: 5381194.4 | Y5: 5547341 | Z5: 12800686 | AA5: 10878142 | AB5: 12090099 | AC5: 12090099 | AD5: 5598184.4 | AE5: 6939336.4 | AF5: 7836364.8 | AG5: 11271977 | AH5: 10975510
A6: Cash at Bank | C6: =80999768-C5 -> 76964517 | D6: 73142746 | E6: 69918030 | F6: 64795114 | G6: 64665975 | H6: 64283775 | I6: 66706775 | J6: 70796777 | K6: 68747673 | L6: 69847685 | M6: 76817871 | N6: 75811108 | O6: 72390306 | P6: =84096060-P5 -> 73834578 | Q6: 75499065 | R6: 78207876 | S6: 79393868 | T6: 69151232 | U6: 75944679 | V6: 72662792 | W6: 1.1045243e+08 | X6: 95160120 | Y6: 91045937 | Z6: 85844011 | AA6: 92890471 | AB6: 1.0171478e+08 | AC6: =114000530-AC5 -> 101910431 | AD6: 1.1005059e+08 | AE6: 1.0399697e+08 | AF6: 99499404 | AG6: 86380711 | AH6: 85059273
A7: Prepayment and Sundry | B7: 13400392 | C7: 2333374 | D7: 633118.27 | E7: 44413.73 | F7: 445154.27 | G7: 331738.27 | H7: 229721.27 | I7: 444301.27 | J7: 546243.27 | K7: 373441.27 | L7: 930490.27 | M7: 911843.27 | N7: 524693.27 | O7: 0 | P7: 1268268 | Q7: 786800.57 | R7: 462657.57 | S7: 558673.57 | T7: 399543.57 | U7: 334323.57 | V7: 1110531.6 | W7: 239495.37 | X7: 583688.37 | Y7: 0 | Z7: 1308291.4 | AA7: 307206.37 | AB7: 435016.37 | AC7: 1714134 | AD7: 986516.37 | AE7: 871836.37 | AF7: 0 | AG7: 710789.37 | AH7: 283876.51
A8: Financial Investment | B8: =SUM(B9:B13) -> 472260 | C8: =SUM(C9:C13) -> 3322320 | D8: =SUM(D9:D13) -> 4219411.4 | E8: =SUM(E9:E13) -> 3322320.4 | F8: =SUM(F9:F13) -> 3322320.4 | G8: =SUM(G9:G13) -> 3322320.4 | H8: =SUM(H9:H13) -> 3322320.4 | I8: =SUM(I9:I13) -> 3322320.4 | ... AI8: =SUM(AI9:AI13) -> 0
A9: Government Securities - Treasury Bills/bonds, | D9: 0 | E9: 0 | F9: 0 | G9: 0 | H9: 0 | I9: 0 | J9: 0 | K9: 0 | L9: 0 | M9: 0 | N9: 0 | O9: 0 | Q9: 0 | R9: 0 | S9: 0 | T9: 0 | U9: 0 | V9: 0 | W9: 0 | X9: 0 | Y9: 0 | Z9: 0 | AA9: 0 | AB9: 0 | AD9: 0 | AE9: 0 | AF9: 0 | AG9: 0 | AH9: 0
A10: Other Securities - Commercial papers/Bonds | D10: 0 | E10: 0 | F10: 0 | G10: 0 | H10: 0 | I10: 0 | J10: 0 | K10: 0 | L10: 0 | M10: 0 | N10: 0 | O10: 0 | Q10: 0 | R10: 0 | S10: 0 | T10: 0 | U10: 0 | V10: 0 | W10: 0 | X10: 0 | Y10: 0 | Z10: 0 | AA10: 0 | AB10: 0 | AD10: 0 | AE10: 0 | AF10: 0 | AG10: 0 | AH10: 0
A11: Balances in NACCOS (E.g Jungu Kuu, ESS, Savings,Money Market,Coop FD, CFP) | C11: =3322320-C13 -> 3167735 | D11: 0 | E11: 0 | F11: 0 | G11: 0 | H11: 0 | I11: 0 | J11: 0 | K11: 0 | L11: 0 | M11: 0 | N11: 0 | O11: 0 | Q11: 0 | R11: 0 | S11: 0 | T11: 0 | U11: 0 | V11: 0 | W11: 0 | X11: 0 | Y11: 0 | Z11: 0 | AA11: 0 | AB11: 0 | AD11: 0 | AE11: 0 | AF11: 0 | AG11: 0 | AH11: 0
A12: Equity Investments in NACCOs(Shares in- CIC, KUSCCO, COOP BANK,CAK, KERUSSU) | P12: =3460532-P13 -> 3297347 | AC12: =3460532-AC13 -> 3297347 | AD12: 3460532.4 | AE12: 3460532.4 | AF12: 3460532.4 | AG12: 3460532.4 | AH12: 3460532.4
A13: Equity Investments in companies - shares/stocks | B13: 472260 | C13: 154585 | D13: 4219411.4 | E13: 3322320.4 | F13: 3322320.4 | G13: 3322320.4 | H13: 3322320.4 | I13: 3322320.4 | J13: 3322320.4 | K13: 3322320.4 | L13: 3322320.4 | M13: 3322320 | N13: 3322320.4 | O13: 3322320.4 | P13: 163185 | Q13: 3322320.4 | R13: 3322320.4 | S13: 3322320.4 | T13: 3322320.4 | U13: 3322320.4 | V13: 3322320.4 | W13: 3322320.4 | X13: 3322320 | Y13: 3322320.4 | Z13: 3322320.4 | AA13: 3322320.4 | AB13: 3322320.4 | AC13: 163185
A14: Net Loan Portfolio | B14: =B15-B16 -> 112905266 | C14: =C15-C16 -> 94715902 | D14: =D15-D16 -> 99526768 | E14: =E15-E16 -> 1.0157231e+08 | F14: =F15-F16 -> 1.0014554e+08 | G14: =G15-G16 -> 1.0108718e+08 | H14: =H15-H16 -> 1.0268952e+08 | I14: =I15-I16 -> 1.0076412e+08 | ... AI14: =AI15-AI16 -> 0
A15: Gross Loan Portfolio | B15: 112905266 | C15: 117738087 | D15: 1.2341506e+08 | E15: 1.2614517e+08 | F15: 1.2572372e+08 | G15: 1.2647362e+08 | H15: 1.2571171e+08 | I15: 1.2592833e+08 | J15: 1.2270415e+08 | K15: 1.2228531e+08 | L15: 1.2298995e+08 | M15: 1.2060145e+08 | N15: 1.2367159e+08 | O15: 1.2297216e+08 | P15: 122972158 | Q15: 1.2169113e+08 | R15: 1.2135364e+08 | S15: 1.2743106e+08 | T15: 1.2994009e+08 | U15: 1.2848417e+08 | V15: 1.2840855e+08 | W15: 1.1615697e+08 | X15: 1.2939291e+08 | Y15: 1.3083972e+08 | Z15: 1.2950216e+08 | AA15: 128305935 | AB15: 1.2334043e+08 | AC15: 123584731 | AD15: 1.248453e+08 | AE15: 1.2811169e+08 | AF15: 1.3037113e+08 | AG15: 1.306111e+08 | AH15: 1.3063519e+08
A16: Allowance For Loan Loss | C16: 23022185 | D16: 23888296 | E16: 24572853 | F16: 25578182 | G16: 25386444 | H16: 23022185 | I16: 25164216 | J16: 25184107 | K16: 26026638 | L16: 25773596 | M16: 25381900 | N16: 25292796 | O16: 21966025 | P16: 21966025 | Q16: 21966025 | R16: 21966025 | S16: 24181711 | T16: 24174931 | U16: 23481600 | V16: 23472632 | W16: 22494308 | X16: 23135805 | Y16: 22759629 | Z16: 22766749 | AA16: 22547845 | AB16: 20829565 | AC16: 20874830 | AD16: 20834667 | AE16: 21275292 | AF16: 21566058 | AG16: 21739949 | AH16: 21518105
A17: Accounts Recievables | B17: =SUM(B18:B20) -> 0 | C17: =SUM(C18:C20) -> 0 | D17: =SUM(D18:D20) -> 0 | E17: =SUM(E18:E20) -> 0 | F17: =SUM(F18:F20) -> 0 | G17: =SUM(G18:G20) -> 0 | H17: =SUM(H18:H20) -> 0 | I17: =SUM(I18:I20) -> 0 | ... AI17: =SUM(AI18:AI20) -> 0
A18: Tax Recoverable | D18: 0 | E18: 0 | F18: 0 | G18: 0 | H18: 0 | I18: 0 | J18: 0 | K18: 0 | L18: 0 | M18: 0 | N18: 0 | O18: 0 | Q18: 0 | R18: 0 | S18: 0 | T18: 0 | U18: 0 | V18: 0 | W18: 0 | X18: 0 | Y18: 0 | Z18: 0 | AA18: 0 | AB18: 0 | AD18: 0 | AE18: 0 | AF18: 0 | AG18: 0 | AH18: 0
A19: Deffered Tax Assets | D19: 0 | E19: 0 | F19: 0 | G19: 0 | H19: 0 | I19: 0 | J19: 0 | K19: 0 | L19: 0 | M19: 0 | N19: 0 | O19: 0 | Q19: 0 | R19: 0 | S19: 0 | T19: 0 | U19: 0 | V19: 0 | W19: 0 | X19: 0 | Y19: 0 | Z19: 0 | AA19: 0 | AB19: 0 | AD19: 0 | AE19: 0 | AF19: 0 | AG19: 0 | AH19: 0
A20: Retirement Benefit Assets | D20: 0 | E20: 0 | F20: 0 | G20: 0 | H20: 0 | I20: 0 | J20: 0 | K20: 0 | L20: 0 | M20: 0 | N20: 0 | O20: 0 | Q20: 0 | R20: 0 | S20: 0 | T20: 0 | U20: 0 | V20: 0 | W20: 0 | X20: 0 | Y20: 0 | Z20: 0 | AA20: 0 | AB20: 0 | AD20: 0 | AE20: 0 | AF20: 0 | AG20: 0 | AH20: 0
A21: Property&Equipments&Other Assets | B21: =SUM(B22:B26) -> 4874587 | C21: =SUM(C22:C26) -> 14963299 | D21: =SUM(D22:D26) -> 15620229 | E21: =SUM(E22:E26) -> 16690034 | F21: =SUM(F22:F26) -> 16705739 | G21: =SUM(G22:G26) -> 16705180 | H21: =SUM(H22:H26) -> 16734039 | I21: =SUM(I22:I26) -> 15635767 | ... AI21: =SUM(AI22:AI26) -> 0
A22: Investment Properties | D22: 0 | E22: 0 | F22: 0 | G22: 0 | H22: 0 | I22: 0 | J22: 0 | K22: 0 | L22: 0 | M22: 0 | N22: 0 | O22: 0 | Q22: 0 | R22: 0 | S22: 0 | T22: 0 | U22: 0 | V22: 0 | W22: 0 | X22: 0 | Y22: 0 | Z22: 0 | AA22: 0 | AB22: 0 | AD22: 0 | AE22: 0 | AF22: 0 | AG22: 0 | AH22: 0
A23: Property and Equipment | B23: 4123114 | C23: 13159426 | D23: 13635196 | E23: 13635196 | F23: 13660301 | G23: 13666801 | H23: 13701801 | I23: 12851347 | J23: 12886347 | K23: 12953447 | L23: 12953447 | M23: 12963347 | N23: 12988547 | O23: 12135656 | P23: 12118019 | Q23: 12119458 | R23: 12119458 | S23: 12123882 | T23: 12124282 | U23: 12180282 | V23: 11499364 | W23: 11629864 | X23: 11474348 | Y23: 11961238 | Z23: 11961238 | AA23: 11961238 | AB23: 11482673 | AC23: 11476711 | AD23: 11478269 | AE23: 11478269 | AF23: 11477413 | AG23: 12373033 | AH23: 11859474
A24: Prepaid Lease Rentals | B24: 0 | D24: 0 | E24: 0 | F24: 0 | G24: 0 | H24: 0 | I24: 0 | J24: 0 | K24: 0 | L24: 0 | M24: 0 | N24: 0 | O24: 0 | Q24: 0 | R24: 0 | S24: 0 | T24: 0 | U24: 0 | V24: 0 | W24: 0 | X24: 0 | Y24: 0 | Z24: 0 | AA24: 0 | AB24: 0 | AD24: 0 | AE24: 0 | AF24: 0 | AG24: 0 | AH24: 0
A25: Intangible Assets | B25: 751473 | C25: 1803873 | D25: 1803872.4 | E25: 1803872.4 | F25: 1803872.4 | G25: 1803872.4 | H25: 1803872.4 | I25: 1503527.7 | J25: 1503527.7 | K25: 1503527.7 | L25: 1503527.7 | M25: 1503527.7 | N25: 1503527.7 | O25: 1203183 | P25: 1203183 | Q25: 1203183 | R25: 1203183 | S25: 1203183 | T25: 1203183 | U25: 1203183 | V25: 1002856 | W25: 1002856 | X25: 936080 | Y25: 936080.42 | Z25: 936080.42 | AA25: 936080.42 | AB25: 802523.03 | AC25: 802523 | AD25: 802523.87 | AE25: 802523.03 | AF25: 802523.03 | AG25: 802523.03 | AH25: 691172.96
A26: Other Assets | D26: 181160 | E26: 1250965 | F26: 1241565.6 | G26: 1234505.8 | H26: 1228365 | I26: 1280892.4 | J26: 1301965 | K26: 1291565 | L26: 1285625.9 | M26: 1274565 | N26: 967957.96 | O26: 1251165 | Q26: 1212565 | R26: 1200908.8 | S26: 1188765 | T26: 1175821 | U26: 1167138.6 | V26: 1255919.6 | W26: 1006868.7 | X26: 1265875.6 | Y26: 1358621.8 | Z26: 1363175.6 | AA26: 1342203.8 | AB26: 1254495.9 | AD26: 1208829.1 | AE26: 1199696 | AF26: 1182335.9 | AG26: 1183935.9 | AH26: 1165136.1
A27: Total Assets | B27: =B21+B17+B14+B8+B7+B4 -> 151015729 | C27: =C21+C17+C14+C8+C7+C4 -> 196334663 | D27: =D21+D17+D14+D8+D7+D4 -> 1.9713824e+08 | E27: =E21+E17+E14+E8+E7+E4 -> 1.9531371e+08 | F27: =F21+F17+F14+F8+F7+F4 -> 1.9474017e+08 | G27: =G21+G17+G14+G8+G7+G4 -> 1.9263586e+08 | H27: =H21+H17+H14+H8+H7+H4 -> 1.9327996e+08 | I27: =I21+I17+I14+I8+I7+I4 -> 1.9153443e+08 | ... AI27: =AI21+AI17+AI14+AI8+AI7+AI4 -> 0
A28: Savings and Deposits | B28: 8112861 | D28: 43388182 | E28: 41878809 | F28: 44019734 | G28: 42339315 | H28: 40289561 | I28: 40213381 | J28: 39423150 | K28: 37586802 | L28: 37772136 | M28: 40771718 | N28: 41579536 | O28: 40688748 | P28: 40687314 | Q28: 40668804 | R28: 42694972 | S28: 40260481 | T28: 41555416 | U28: 45199037 | V28: 42150626 | W28: 60483106 | X28: 55704378 | Y28: 52141570 | Z28: 52428644 | AA28: 53115331 | AB28: 59343782 | AC28: 59343782 | AD28: 60897812 | AE28: 55103067 | AF28: 54896465 | AG28: 49813962 | AH28: 47077439
A29: Short Terrm Deposits | B29: 8350444 | C29: 45172689 | D29: 0 | E29: 0 | F29: 0 | G29: 0 | H29: 0 | I29: 0 | J29: 0 | K29: 0 | L29: 0 | M29: 0 | N29: 0 | O29: 0 | Q29: 0 | R29: 0 | S29: 0 | T29: 0 | U29: 0 | V29: 0 | W29: 0 | X29: 0 | Y29: 0 | Z29: 0 | AA29: 0 | AB29: 0 | AD29: 0 | AE29: 0 | AF29: 0 | AG29: 0 | AH29: 0
A30: Non Withdrawable Deposits | B30: 112140909 | C30: 97747282 | D30: 98068546 | E30: 98848445 | F30: 99652558 | G30: 1.0010073e+08 | H30: 1.0079304e+08 | I30: 1.0131074e+08 | J30: 1.0204955e+08 | K30: 1.0284144e+08 | L30: 1.0298548e+08 | M30: 1.0403389e+08 | N30: 1.0598307e+08 | O30: 1.0382613e+08 | P30: 103826130 | Q30: 1.0423904e+08 | R30: 1.0530178e+08 | S30: 1.0642489e+08 | T30: 1.0641779e+08 | U30: 1.071894e+08 | V30: 107844184 | W30: 1.083984e+08 | X30: 1.0851814e+08 | Y30: 1.0894108e+08 | Z30: 1.0974554e+08 | AA30: 1.1058952e+08 | AB30: 1.1016692e+08 | AC30: 110164921 | AD30: 1.11064e+08 | AE30: 1.1176483e+08 | AF30: 1.1222131e+08 | AG30: 1.1214909e+08 | AH30: 1.1279939e+08
A31: Total Deposit Liabilities | B31: =SUM(B28:B30) -> 128604214 | C31: =SUM(C28:C30) -> 142919971 | D31: =SUM(D28:D30) -> 1.4145673e+08 | E31: =SUM(E28:E30) -> 1.4072725e+08 | F31: =SUM(F28:F30) -> 1.4367229e+08 | G31: =SUM(G28:G30) -> 1.4244005e+08 | H31: =SUM(H28:H30) -> 1.4108261e+08 | I31: =SUM(I28:I30) -> 1.4152412e+08 | ... AI31: =SUM(AI28:AI30) -> 0
A32: Tax Payable | B32: 27231 | C32: 331303 | D32: 331303 | E32: 331303 | F32: 331303 | G32: 331303 | H32: 0 | I32: 0 | J32: 0 | K32: 0 | L32: 0 | M32: 0 | N32: 200 | O32: 0 | P32: 47492 | Q32: 0 | R32: 0 | S32: 47492 | T32: 47492 | U32: 47492 | V32: 0 | W32: 0 | X32: 0 | Y32: 0 | Z32: 0 | AA32: 0 | AB32: 0 | AC32: 320845 | AD32: 0 | AE32: 320844.57 | AF32: 320844.57 | AG32: 1207.57 | AH32: 1207.57
A33: Dividends Payable | B33: 3618123 | C33: 4469416 | D33: 4469416 | E33: 4109416.8 | F33: 178005.53 | G33: 178005.53 | H33: 178005.53 | I33: 178005.53 | J33: 178005.53 | K33: 178005.53 | L33: 178005.53 | M33: 178005.53 | N33: 178005.53 | O33: 178005.53 | P33: 4982212 | Q33: 178005.53 | R33: 178005.53 | S33: 2725690.5 | T33: 239968.88 | U33: 238270.68 | V33: 238270.68 | W33: 234411.68 | X33: 195009.52 | Y33: 190317.68 | Z33: 184179.68 | AA33: 178733.68 | AB33: 178733.68 | AC33: 4492182 | AD33: 178733.68 | AE33: 4492181.4 | AF33: 529802.69 | AG33: 362474.69 | AH33: 222434.69
A34: Deferred Tax Liability | D34: 0 | E34: 0 | F34: 0 | G34: 0 | H34: 0 | I34: 0 | J34: 0 | K34: 0 | L34: 0 | M34: 0 | N34: 0 | O34: 0 | Q34: 0 | R34: 0 | S34: 0 | T34: 0 | U34: 0 | V34: 0 | W34: 0 | X34: 0 | Y34: 0 | Z34: 0 | AA34: 0 | AB34: 0 | AD34: 0 | AE34: 0 | AF34: 0 | AG34: 0 | AH34: 0
A35: Retirement Benefits Liabilty | D35: 0 | E35: 0 | F35: 0 | G35: 0 | H35: 0 | I35: 0 | J35: 0 | K35: 0 | L35: 0 | M35: 0 | N35: 0 | O35: 0 | Q35: 0 | R35: 0 | S35: 0 | T35: 0 | U35: 0 | V35: 0 | W35: 0 | X35: 0 | Y35: 0 | Z35: 0 | AA35: 0 | AB35: 0 | AD35: 0 | AE35: 0 | AF35: 0 | AG35: 0 | AH35: 0
A36: Other Liabilities | B36: 1214920 | C36: 3786965 | D36: 3553292.6 | E36: 4331685.6 | F36: 5115811.3 | G36: 2766231.6 | H36: 2183007.4 | I36: 2274820.4 | J36: 2360998.2 | K36: 2245091.8 | L36: 2262577.7 | M36: 2873146.9 | N36: 2835491.5 | O36: 3479721.9 | P36: 3897607 | Q36: 4250814 | R36: 4300142.7 | S36: 4402849.5 | T36: 3569501.6 | U36: 3392247.9 | V36: 3001895.8 | W36: 2588665.3 | X36: 2945164.6 | Y36: 2768203.4 | Z36: 2691983.5 | AA36: 3301131.6 | AB36: 4289497.7 | AC36: 4525108 | AD36: 3780541.6 | AE36: 4394962 | AF36: 5324401.7 | AG36: 2574064.7 | AH36: 2104728.3
A37: External Borrowings | B37: 2291669 | D37: 0 | E37: 0 | F37: 0 | G37: 0 | H37: 0 | I37: 0 | J37: 0 | K37: 0 | L37: 0 | M37: 0 | N37: 0 | O37: 0 | Q37: 0 | R37: 0 | S37: 0 | T37: 0 | U37: 0 | V37: 0 | W37: 0 | X37: 0 | Y37: 0 | Z37: 0 | AA37: 0 | AB37: 0 | AD37: 0 | AE37: 0 | AF37: 0 | AG37: 0 | AH37: 0
A38: Total Liabilities | B38: =SUM(B31:B37) -> 135756157 | C38: =SUM(C31:C37) -> 151507655 | D38: =SUM(D31:D37) -> 1.4981074e+08 | E38: =SUM(E31:E37) -> 1.4949966e+08 | F38: =SUM(F31:F37) -> 1.4929741e+08 | G38: =SUM(G31:G37) -> 1.4571559e+08 | H38: =SUM(H31:H37) -> 1.4344362e+08 | I38: =SUM(I31:I37) -> 1.4397694e+08 | ... AI38: =SUM(AI31:AI37) -> 0
A39: Share Capital | B39: 10494697 | C39: 20354392 | D39: 20409827 | E39: 20503312 | F39: 20818309 | G39: 21386718 | H39: 21646522 | I39: 21819583 | J39: 22004384 | K39: 22196119 | L39: 22378767 | M39: 22474919 | N39: 22686914 | O39: 22976846 | P39: 22976846 | Q39: 23140804 | R39: 23269757 | S39: 23443264 | T39: 23613532 | U39: 23856891 | V39: 24046291 | W39: 26611793 | X39: 26858915 | Y39: 27115705 | Z39: 27303776 | AA39: 27562238 | AB39: 27792649 | AC39: 27792649 | AD39: 28258881 | AE39: 28590364 | AF39: 28888314 | AG39: 29099240 | AH39: 29296147
A40: Capital Grants | B40: 340425 | D40: 0 | E40: 0 | F40: 0 | G40: 0 | H40: 0 | I40: 0 | J40: 0 | K40: 0 | L40: 0 | M40: 0 | N40: 0 | O40: 0 | Q40: 0 | R40: 0 | S40: 0 | T40: 0 | U40: 0 | V40: 0 | W40: 0 | X40: 0 | Y40: 0 | Z40: 0 | AA40: 0 | AB40: 0 | AD40: 0 | AE40: 0 | AF40: 0 | AG40: 0 | AH40: 0
A41: Prior Year Retained Earnigs | B41: 351220 | C41: 3557811 | D41: 15121447 | E41: 14903354 | F41: 14903354 | G41: 14903354 | H41: 14903354 | I41: 14903354 | J41: 14903354 | K41: 14903354 | L41: 14903354 | M41: 14903354 | N41: 14903354 | O41: 14903354 | P41: 14862025 | Q41: 21838346 | R41: 21838346 | S41: 18140371 | T41: 16019589 | U41: 16066589 | V41: 16063849 | W41: 16070380 | X41: 16063849 | Y41: 16063849 | Z41: 16016357 | AA41: 16016357 | AB41: 16016357 | AC41: 16015500 | AD41: 20349706 | AE41: 16006370 | AF41: 16006370 | AG41: 16006370 | AH41: 16006370
A42: Current Year Surplus | B42: 3541956 | C42: =14862025-C41 -> 11304214 | D42: 1999765.2 | E42: 796449.7 | F42: 110660.8 | G42: 1019263.6 | H42: 3675568.4 | I42: 1223616.2 | J42: 1519756.4 | K42: 788796.1 | L42: 1622544.4 | M42: 3226500.4 | N42: 3837707.9 | O42: 7270515.7 | P42: =4851449-970290-180000-250000-2297685 -> 1153474 | Q42: 118618.9 | R42: 280801.46 | S42: -208201.4 | T42: 695700.1 | U42: 1921498.5 | V42: 1509917.9 | W42: 2936258.1 | X42: 3514391 | Y42: 4450016 | Z42: 5319856.8 | AA42: 6051563.5 | AB42: 5243957.2 | AC42: =4001194+856-800239-180000-250000-2781799 -> -9988 | AD42: 2347310.3 | AE42: 3393614.9 | AF42: 3356802.4 | AG42: 3528907.5 | AH42: 3585005
A43: Statutory Reserves | B43: 531274 | C43: 6683483 | D43: 5972263 | E43: 6683825 | F43: 6683325 | G43: 6683825 | H43: 6683825 | I43: 6683825 | J43: 6683825 | K43: 6683825 | L43: 6683825 | M43: 6683825 | N43: 6683825 | O43: 6683825 | P43: 7653773 | Q43: 6683483 | R43: 6683483 | S43: 7653773 | T43: 7653773 | U43: 7653773 | V43: 7653773 | W43: 7653773 | X43: 7653773 | Y43: 7653773 | Z43: 7653773 | AA43: 7653773 | AB43: 7653773 | AC43: 8454012 | AD43: 7653773 | AE43: 8454012 | AF43: 8454012 | AG43: 8454012 | AH43: 8454012
A44: Other Reserves | C44: 226780 | D44: 226779.85 | E44: 226779.85 | F44: 226779.85 | G44: 226779.85 | H44: 226779.85 | I44: 226779.85 | J44: 226779.85 | K44: 226779.85 | L44: 226779.85 | M44: 226779.85 | N44: 226779.85 | O44: 226779.85 | P44: 226780 | Q44: 226779.85 | R44: 226779.85 | S44: 226779.85 | T44: 226779.76 | U44: 226779.85 | V44: 226779.85 | W44: 226779.85 | X44: 226779.85 | Y44: 226779.85 | Z44: 226779.85 | AA44: 226779.85 | AB44: 226779.85 | AC44: 226780 | AD44: 226779.85 | AE44: 226779.85 | AF44: 226779.85 | AG44: 226779.85 | AH44: 226779.85
A45: Revaluation Reserves | C45: 2700329 | D45: 3597420 | E45: 2700329.4 | F45: 2700329.4 | G45: 2700329.4 | H45: 2700329.4 | I45: 2700329.4 | J45: 2700329.4 | K45: 2700329.4 | L45: 2700329.4 | M45: 2700329.5 | N45: 2700329.4 | O45: 2700329.4 | P45: 2838541 | Q45: 2700329.4 | R45: 2700329.4 | S45: 2700329.4 | T45: 2700329.4 | U45: 2700329.4 | V45: 2700329.4 | W45: 2700329.4 | X45: 2700329.4 | Y45: 2700329.4 | Z45: 2700329.4 | AA45: 2700329.4 | AB45: 2700329.4 | AC45: 2838541 | AD45: 2838541.4 | AE45: 2838541.4 | AF45: 2838541.4 | AG45: 2838541.4 | AH45: 2838541.4
A46: Proposed Dividends | D46: 0 | E46: 0 | F46: 0 | G46: 0 | H46: 0 | I46: 0 | J46: 0 | K46: 0 | L46: 3682.6 | M46: 0 | N46: 0 | O46: 0 | Q46: 0 | R46: 0 | S46: 0 | T46: 0 | U46: 0 | V46: 0 | W46: 0 | X46: 0 | Y46: 0 | Z46: 0 | AA46: 0 | AB46: 0 | AD46: 0 | AE46: 0 | AF46: 0 | AG46: 0 | AH46: 0
A47: Adjustment To Equity | D47: 0 | E47: 0 | F47: 0 | G47: 0 | H47: 0 | I47: 0 | J47: 0 | K47: 0 | L47: 0 | M47: 0 | N47: 0 | O47: 0 | Q47: 0 | R47: 0 | S47: 0 | T47: 0 | U47: 0 | V47: 0 | W47: 0 | X47: 0 | Y47: 0 | Z47: 0 | AA47: 0 | AB47: 0 | AD47: 0 | AE47: 0 | AF47: 0 | AG47: 0 | AH47: 0
A48: Total Equity | B48: =SUM(B39:B47) -> 15259572 | C48: =SUM(C39:C47) -> 44827009 | D48: =SUM(D39:D47) -> 47327502 | E48: =SUM(E39:E47) -> 45814050 | F48: =SUM(F39:F47) -> 45442758 | G48: =SUM(G39:G47) -> 46920271 | H48: =SUM(H39:H47) -> 49836378 | I48: =SUM(I39:I47) -> 47557487 | ... AI48: =SUM(AI39:AI47) -> 0
A49: Total Liabilities and Equity | B49: =B48+B38 -> 151015729 | C49: =C48+C38 -> 196334664 | D49: =D48+D38 -> 1.9713824e+08 | E49: =E48+E38 -> 1.9531371e+08 | F49: =F48+F38 -> 1.9474017e+08 | G49: =G48+G38 -> 1.9263586e+08 | H49: =H48+H38 -> 1.9328e+08 | I49: =I48+I38 -> 1.9153443e+08 | ... AI49: =AI48+AI38 -> 0
B51: =B49-B27 -> 0 | C51: =C49-C27 -> 1 | D51: =D49-D27 -> 0 | E51: =E49-E27 -> 0 | F51: =F49-F27 -> 0 | G51: =G49-G27 -> 0 | H51: =H49-H27 -> 40 | I51: =I49-I27 -> 0 | ... P51: =P49-P27 -> -1

Sheet Evolutitve SCI
B2: 2010 Audited | C2: 2020 Audited | D2: 44197 | E2: 44229 | F2: 44258 | G2: 44290 | H2: 44321 | I2: 44348 | J2: 44378 | K2: 44409 | L2: 44440 | M2: 44472 | N2: 44501 | O2: 44531 | P2: Audited 2021 | Q2: 44564 | R2: 44596 | S2: 44625 | T2: 44657 | U2: 44688 | V2: 44720 | W2: 44751 | X2: 44783 | Y2: 44815 | Z2: 44846 | AA2: 44878 | AB2: 44909 | AC2: Audited 2022 | AD2: 44927 | AE2: 44958 | AF2: 44986 | AG2: 45017 | AH2: 45047 | AI2: 45078 | AJ2: 45108 | AK2: 45139 | AL2: 45170 | AM2: 45200
A3: Financial Income | B3: =B4+B7 -> 14599.248 | C3: =C4+C7 -> 24912213 | D3: =D4+D7 -> 3346469.6 | E3: =E4+E7 -> 4855477.2 | F3: =F4+F7 -> 6639.17 | G3: =G4+G7 -> 8837677.4 | H3: =H4+H7 -> 10209983 | I3: =I4+I7 -> 12571337 | ... AM3: =AM4+AM7 -> 0
A4: Financial Income From Loans Portfolio | B4: =SUM(B5:B6) -> 12855.806 | C4: =SUM(C5:C6) -> 14548967 | D4: =SUM(D5:D6) -> 2222474.9 | E4: =SUM(E5:E6) -> 3827277.3 | F4: =SUM(F5:F6) -> 4832.3 | G4: =SUM(G5:G6) -> 5984742 | H4: =SUM(H5:H6) -> 6784203.7 | I4: =SUM(I5:I6) -> 8447529.5 | ... AM4: =SUM(AM5:AM6) -> 0
A5: Interest from Loans Portfolio | B5: 11945.435 | C5: 14548967 | D5: 2067244.9 | E5: 3579327.3 | F5: 4523.8 | G5: 5617072 | H5: 6370913.7 | I5: 7966759.5 | J5: 9001525.2 | K5: 9823827.3 | L5: 10936923 | M5: 12398964 | N5: 13806661 | O5: 16279831 | P5: 16279831 | Q5: 1287910.1 | R5: 2464378.9 | S5: 4375359.9 | T5: 6146687.3 | U5: 7291788.5 | V5: 8210233.7 | W5: 9625651.9 | X5: 11155163 | Y5: 12513316 | Z5: 13427122 | AA5: 14627894 | AB5: 15893299 | AC5: 16139597 | AD5: 2789027.5 | AE5: 4593922.7 | AF5: 5902480.8 | AG5: 6908719.2 | AH5: 8115358.9
A6: Fees&Commision on Loan Portfolio | B6: 910.371 | D6: 155230 | E6: 247950 | F6: 308.5 | G6: 367670 | H6: 413290 | I6: 480770 | J6: 527950 | K6: 577650 | L6: 638260 | M6: 714775 | N6: 829325 | O6: 958390 | P6: =121000+837390 -> 958390 | Q6: 73760 | R6: 134660 | S6: 278470 | T6: 380630 | U6: 445520 | V6: 503320 | W6: 561020 | X6: 769410 | Y6: 852830 | Z6: 895790 | AA6: 963720 | AB6: 1010645 | AC6: =118800+891845 -> 1010645 | AD6: 118955 | AE6: 218885 | AF6: 305495 | AG6: 355095 | AH6: 417511
A7: Financial Income from Investments | B7: =SUM(B8:B11) -> 1743.4416 | C7: =SUM(C8:C11) -> 10363246 | D7: =SUM(D8:D11) -> 1123994.7 | E7: =SUM(E8:E11) -> 1028199.9 | F7: =SUM(F8:F11) -> 1806.87 | G7: =SUM(G8:G11) -> 2852935.3 | H7: =SUM(H8:H11) -> 3425779.1 | I7: =SUM(I8:I11) -> 4123807.4 | ... AM7: =SUM(AM8:AM11) -> 0
A8: Government Securities | D8: 0 | E8: 0 | F8: 0 | G8: 0 | H8: 0 | I8: 0 | J8: 0 | K8: 0 | L8: 0 | M8: 0 | N8: 0 | O8: 0 | Q8: 0 | R8: 0 | S8: 0 | T8: 0 | U8: 0 | V8: 0 | W8: 0 | X8: 0 | Y8: 0 | Z8: 0 | AA8: 0 | AB8: 0 | AD8: 0 | AE8: 0 | AF8: 0 | AG8: 0 | AH8: 0
A9: Deposits with Banks & other Financial Institutions | C9: 3397666 | D9: 0 | E9: 0 | F9: 0 | G9: 0 | H9: 0 | I9: 0 | J9: 0 | K9: 0 | L9: 0 | M9: 0 | N9: 0 | O9: 0 | P9: 3595000 | Q9: 0 | R9: 0 | S9: 0 | T9: 0 | U9: 0 | V9: 0 | W9: 5142.59 | X9: 5142.59 | Y9: 5142.59 | Z9: 0 | AA9: 0 | AB9: 0 | AC9: 3717486 | AD9: 0 | AE9: 0 | AF9: 0 | AG9: 0 | AH9: 230063
A10: Other Investments | D10: 0 | E10: 0 | F10: 0 | G10: 368484.5 | H10: 370322.75 | I10: 370857.75 | J10: 370857.75 | K10: 370857.75 | L10: 370857.75 | M10: 374615.75 | N10: 374615.75 | O10: 374615.75 | Q10: 0 | R10: 0 | S10: 0 | T10: 2614 | U10: 2614 | V10: 357856 | W10: 357856 | X10: 357856 | Y10: 360919.75 | Z10: 360919.75 | AA10: 360919.75 | AB10: 424759.75 | AD10: 0 | AE10: 0 | AF10: 483609 | AG10: 483609 | AH10: 485978.3
A11: Other Operating Income | B11: 1743.4416 | C11: 6965580 | D11: 1123994.7 | E11: 1028199.9 | F11: 1806.87 | G11: 2484450.8 | H11: 3055456.4 | I11: 3752949.6 | J11: 4463511.7 | K11: 5137703.6 | L11: 5857306.3 | M11: 6632230.7 | N11: 7065068.5 | O11: 8192540.7 | P11: =7308424-P6 -> 6350034 | Q11: 413527.76 | R11: 1100703 | S11: 1557736.3 | T11: 2517989.7 | U11: 3343123 | V11: 4103460.2 | W11: 4810620.3 | X11: 5923126.3 | Y11: 6694253.5 | Z11: 7428873.2 | AA11: 7995224.6 | AB11: 10122078 | AC11: =8027184-AC6 -> 7016539 | AD11: 471477.07 | AE11: 866372.74 | AF11: 1251944.1 | AG11: 2160196.5 | AH11: 2526495.9
A12: Financial Expenses | B12: =SUM(B13:B18) -> 549.0847 | C12: =SUM(C13:C18) -> 1954946 | D12: =SUM(D13:D18) -> 45833.4 | E12: =SUM(E13:E18) -> 53043.4 | F12: =SUM(F13:F18) -> 257.5 | G12: =SUM(G13:G18) -> 281147.6 | H12: =SUM(H13:H18) -> 282552.2 | I12: =SUM(I13:I18) -> 311174.2 | ... AM12: =SUM(AM13:AM18) -> 0
A13: Interest Expense on Deposits | B13: 185.36 | C13: 1954946 | D13: 0 | E13: 0 | F13: 0 | G13: 0 | H13: 0 | I13: 0 | J13: 0 | K13: 0 | L13: 0 | M13: 0 | N13: 0 | O13: 0 | P13: 2076522 | Q13: 0 | R13: 0 | S13: 0 | T13: 0 | U13: 0 | V13: 0 | W13: 0 | X13: 0 | Y13: 0 | Z13: 0 | AA13: 0 | AB13: 0 | AC13: 1101649 | AD13: 0 | AE13: 0 | AF13: 0 | AG13: 0 | AH13: 0
A14: Cost of External Borrowings | B14: 363.7247 | D14: 0 | E14: 0 | F14: 0 | G14: 0 | H14: 0 | I14: 0 | J14: 0 | K14: 0 | L14: 0 | M14: 0 | N14: 0 | O14: 0 | Q14: 0 | R14: 0 | S14: 0 | T14: 0 | U14: 0 | V14: 0 | W14: 0 | X14: 0 | Y14: 0 | Z14: 0 | AA14: 0 | AB14: 0 | AD14: 0 | AE14: 0 | AF14: 0 | AG14: 0 | AH14: 0
A15: Dividend Expenses | D15: 0 | E15: 0 | F15: 0 | G15: 0 | H15: 0 | I15: 0 | J15: 0 | K15: 0 | L15: 0 | M15: 0 | N15: 0 | O15: 0 | Q15: 0 | R15: 0 | S15: 0 | T15: 0 | U15: 0 | V15: 0 | W15: 0 | X15: 0 | Y15: 0 | Z15: 0 | AA15: 0 | AB15: 0 | AD15: 0 | AE15: 0 | AF15: 0 | AG15: 0 | AH15: 0
A16: Other Financial Expense | D16: 0 | E16: 0 | F16: 0 | G16: 0 | H16: 0 | I16: 0 | J16: 0 | K16: 0 | L16: 0 | M16: 0 | N16: 0 | O16: 0 | P16: 182643 | Q16: 0 | R16: 0 | S16: 0 | T16: 0 | U16: 0 | V16: 0 | W16: 0 | X16: 0 | Y16: 0 | Z16: 0 | AA16: 0 | AB16: 0 | AC16: 213780 | AD16: 0 | AE16: 0 | AF16: 0 | AG16: 0 | AH16: 0
A17: Fees & Commision Expense | D17: 45833.4 | E17: 53043.4 | F17: 257.5 | G17: 281147.6 | H17: 282552.2 | I17: 311174.2 | J17: 327199.7 | K17: 331532.1 | L17: 345948 | M17: 354114.1 | N17: 417849.2 | O17: 434016.7 | Q17: 7360 | R17: 51660 | S17: 81802.1 | T17: 99013.8 | U17: 111644.6 | V17: 111644.6 | W17: 185085.5 | X17: 208645 | Y17: 239248.5 | Z17: 259386.2 | AA17: 279645.8 | AB17: 348980.4 | AD17: 35720 | AE17: 65228.3 | AF17: 65778.3 | AG17: 121915 | AH17: 147545.2
A18: Other Expenses | D18: 0 | E18: 0 | F18: 0 | G18: 0 | H18: 0 | I18: 0 | J18: 0 | K18: 0 | L18: 0 | M18: 0 | N18: 0 | O18: 0 | Q18: 0 | R18: 0 | S18: 0 | T18: 0 | U18: 0 | V18: 0 | W18: 0 | X18: 0 | Y18: 0 | Z18: 0 | AA18: 0 | AB18: 533533.4 | AC18: 533533 | AD18: 0 | AE18: 0 | AF18: 0 | AG18: 0 | AH18: 0
A19: Net Financial Income | B19: =B3-B12 -> 14050.163 | C19: =C3-C12 -> 22957267 | D19: =D3-D12 -> 3300636.2 | E19: =E3-E12 -> 4802433.8 | F19: =F3-F12 -> 6381.67 | G19: =G3-G12 -> 8556529.8 | H19: =H3-H12 -> 9927430.6 | I19: =I3-I12 -> 12260163 | ... AM19: =AM3-AM12 -> 0
A20: Allowance for Loan Loss | B20: =B21-B22 -> 0 | C20: =C21-C22 -> 712970 | D20: =D21-D22 -> 866110.6 | E20: =E21-E22 -> 1550668.6 | F20: =F21-F22 -> 0 | G20: =G21-G22 -> 2364259.2 | H20: =H21-H22 -> 1956021.8 | I20: =I21-I22 -> 2142031.4 | ... AM20: =AM21-AM22 -> 0
A21: Provision for Loan Losses | C21: 712970 | D21: 866110.6 | E21: 1550668.6 | F21: 0 | G21: 2364259.2 | H21: 1956021.8 | I21: 2142031.4 | J21: 2161922.5 | K21: 3004453.6 | L21: 2751411.3 | M21: 2359715 | N21: 2270611.4 | O21: -1056159.9 | Q21: 0 | R21: 1489093.9 | S21: 2215685.7 | T21: 2208906.2 | U21: 1515575.1 | V21: 1506607.5 | W21: 528282.7 | X21: 1169780.4 | Y21: 793604.4 | Z21: 800724.4 | AA21: 581820 | AB21: 0 | AC21: 0 | AD21: 0 | AE21: 400463 | AF21: 691228.9 | AG21: 865119.5 | AH21: 643275
A22: Value of Loans Recovered | D22: 0 | E22: 0 | F22: 0 | G22: 0 | H22: 0 | I22: 0 | J22: 0 | K22: 0 | L22: 0 | M22: 0 | N22: 0 | O22: 0 | Q22: 0 | R22: 0 | S22: 0 | T22: 0 | U22: 0 | V22: 0 | W22: 0 | X22: 0 | Y22: 0 | Z22: 0 | AA22: 0 | AB22: 0 | AC22: 0 | AD22: 0 | AE22: 0 | AF22: 0 | AG22: 0 | AH22: 0
A23: Operating Expeses | B23: =SUM(B24:B28) -> 11019.38 | C23: =SUM(C24:C28) -> 18075183 | D23: =SUM(D24:D28) -> 434760.35 | E23: =SUM(E24:E28) -> 2455315.5 | F23: =SUM(F24:F28) -> 595087.12 | G23: =SUM(G24:G28) -> 5005006.9 | H23: =SUM(H24:H28) -> 6083862.6 | I23: =SUM(I24:I28) -> 8558515.1 | ... AM23: =SUM(AM24:AM28) -> 0
A24: Personel Expenses | B24: 3512.444 | C24: 8022789 | D24: 48173 | E24: 1332960.4 | F24: 2064.8 | G24: 2732782.8 | H24: 3476048.8 | I24: 4185253.7 | J24: 4864209.7 | K24: 5565565.6 | L24: 6249851.6 | M24: 7002132.5 | N24: 7715009.5 | O24: 9075535.8 | P24: 9075536 | Q24: 725226 | R24: 1502435.9 | S24: 1611600 | T24: 3032756.4 | U24: 3756318.5 | V24: 4502580.6 | W24: 5289042.7 | X24: 5977948.8 | Y24: 7021615.8 | Z24: 7681884.9 | AA24: 8382421.6 | AB24: 9613066 | AC24: 9613066 | AD24: 625132.1 | AE24: 864412.1 | AF24: 2120981.6 | AG24: 2834167 | AH24: 3622442.1
A25: Governance Expenses | B25: 401.873 | C25: 3550465 | D25: 69820 | E25: 615843.94 | F25: 843.95 | G25: 1172859.5 | H25: 1241669.5 | I25: 1491930.4 | J25: 1812486.3 | K25: 1996316.3 | L25: 2134266 | M25: 2277604.6 | N25: 2674672.8 | O25: 3066223.7 | P25: =3524875-P26 -> 3029675 | Q25: 200085.17 | R25: 471976.05 | S25: 885891.93 | T25: 1034007.3 | U25: 1496013.2 | V25: 1883758.6 | W25: 2049084.1 | X25: 2166244.6 | Y25: 2334455.4 | Z25: 2544921 | AA25: 2903900.7 | AB25: 3576200.5 | AC25: =4379341-AC26 -> 3576201 | AD25: 191297.2 | AE25: 620297.2 | AF25: 1210487.7 | AG25: 1709848.8 | AH25: 1889717.6
A26: Marketing Expenses | B26: 919.3528 | D26: 0 | E26: 0 | F26: 11.9 | G26: 28130 | H26: 30130 | I26: 32430 | J26: 32830 | K26: 32830 | L26: 32830 | M26: 37530 | N26: 40130 | O26: 376380 | P26: 495200 | Q26: 0 | R26: 0 | S26: 0 | T26: 3340 | U26: 3340 | V26: 55440 | W26: 92640 | X26: 94940 | Y26: 94940 | Z26: 95440 | AA26: 141040 | AB26: 803140 | AC26: 803140 | AD26: 0 | AE26: 0 | AF26: 0 | AG26: 9100 | AH26: 10700
A27: Depreciation and Amortization | B27: 1276.981 | D27: 358.75 | E27: 0 | F27: 591372.2 | G27: 0 | H27: 0 | I27: 1144298.8 | J27: 1144298.8 | K27: 1144298.8 | L27: 1144298 | M27: 1144298.8 | N27: 1144298.8 | O27: 2297535.1 | Q27: 0 | R27: 0 | S27: 0 | T27: 0 | U27: 0 | V27: 881245 | W27: 881245 | X27: 1181136.1 | Y27: 1181136.1 | Z27: 1181136.1 | AA27: 1181136.1 | AB27: 1792658.6 | AC27: =1392855+400660 -> 1793515 | AD27: 0 | AE27: 0 | AF27: 856 | AG27: 856 | AH27: 624965.43
A28: Administrative Expenses | B28: 4908.7291 | C28: 6501929 | D28: 316408.6 | E28: 506511.2 | F28: 794.27 | G28: 1071234.6 | H28: 1336014.3 | I28: 1704602.3 | J28: 2165141.3 | K28: 2710486.3 | L28: 3010517.5 | M28: 3207010.3 | N28: 3463710.3 | O28: 3759650.3 | P28: =7025461-P16 -> 6842818 | Q28: 723907.8 | R28: 1393635.8 | S28: 1577295.8 | T28: 1893705.2 | U28: 2151163.6 | V28: 2516183.6 | W28: 3191160.6 | X28: 3690120.2 | Y28: 4023953.2 | Z28: 3989355.3 | AA28: 4178310.3 | AB28: 5211325.4 | AC28: =7606719-AC36-AC27-AC16 -> 5552874 | AD28: 180000 | AE28: 335265 | AF28: 497494 | AG28: 687806 | AH28: 1101856.6
A29: Net Operating Income | B29: =B19-B20-B23 -> 3030.7829 | C29: =C19-C20-C23 -> 4169114 | D29: =D19-D20-D23 -> 1999765.2 | E29: =E19-E20-E23 -> 796449.67 | F29: =F19-F20-F23 -> -588705.45 | G29: =G19-G20-G23 -> 1187263.6 | H29: =H19-H20-H23 -> 1887546.3 | I29: =I19-I20-I23 -> 1559616.2 | ... AN29: =AN19-AN20-AN23 -> 0
A30: Net Non operating Income/Expense | B30: =B31-B32 -> 0 | C30: =C31-C32 -> 0 | D30: =D31-D32 -> 0 | E30: =E31-E32 -> 0 | F30: =F31-F32 -> 26490 | G30: =G31-G32 -> 0 | H30: =H31-H32 -> 0 | I30: =I31-I32 -> 0 | ... AN30: =AN31-AN32 -> 0
A31: Non Operating Income | D31: 0 | E31: 0 | F31: 29190 | G31: 0 | H31: 0 | I31: 0 | J31: 0 | K31: 240 | L31: 240 | M31: 240 | N31: 240 | O31: 240 | Q31: 0 | R31: 0 | S31: 0 | T31: 0 | U31: 0 | V31: 0 | W31: 0 | X31: 0 | Y31: 0 | Z31: 0 | AA31: 0 | AB31: 0 | AD31: 0 | AE31: 100 | AF31: 100 | AG31: 100 | AH31: 100
A32: Non Operating Expense | D32: 0 | E32: 0 | F32: 2700 | G32: 0 | H32: 0 | I32: 0 | J32: 0 | K32: 0 | L32: 0 | M32: 0 | N32: 0 | O32: 0 | Q32: 0 | R32: 0 | S32: 0 | T32: 0 | U32: 0 | V32: 0 | W32: 0 | X32: 0 | Y32: 0 | Z32: 0 | AA32: 0 | AB32: 0 | AD32: 0 | AE32: 0 | AF32: 0 | AG32: 0 | AH32: 0
A33: Net Income(Before Tax & Donations) | B33: =B29+B30 -> 3030.7829 | C33: =C29+C30 -> 4169114 | D33: =D29+D30 -> 1999765.2 | E33: =E29+E30 -> 796449.67 | F33: =F29+F30 -> -562215.45 | G33: =G29+G30 -> 1187263.6 | H33: =H29+H30 -> 1887546.3 | I33: =I29+I30 -> 1559616.2 | ... AM33: =AM29+AM30 -> 0
A34: Taxes | B34: 20 | C34: 611603 | D34: 0 | E34: 0 | F34: 20000 | G34: 168000 | H34: 168000 | I34: 336000 | J34: 336000 | K34: 336000 | L34: 511920.8 | M34: 511920 | N34: 511920 | O34: 581920 | P34: 629412 | Q34: 0 | R34: 0 | S34: 47492 | T34: 80492 | U34: 127492 | V34: 207492 | W34: 207492 | X34: 207492 | Y34: 287492 | Z34: 240000 | AA34: 247920 | AB34: 327920 | AC34: 648765 | AD34: 0 | AE34: 0 | AF34: 0 | AG34: 150000 | AH34: 150000
A35: Net Income(After Tax Before Donations) | B35: =B33-B34 -> 3010.7829 | C35: =C33-C34 -> 3557511 | D35: =D33-D34 -> 1999765.2 | E35: =E33-E34 -> 796449.67 | F35: =F33-F34 -> -582215.45 | G35: =G33-G34 -> 1019263.6 | H35: =H33-H34 -> 1719546.3 | I35: =I33-I34 -> 1223616.2 | ... AM35: =AM33-AM34 -> 0
A36: Donations | D36: 0 | E36: 0 | F36: 0 | G36: 0 | H36: 0 | I36: 0 | J36: 0 | K36: 0 | L36: 0 | M36: 0 | N36: 0 | O36: 0 | Q36: 0 | R36: 0 | S36: 0 | T36: 0 | U36: 0 | V36: 0 | W36: 0 | X36: 0 | Y36: 0 | Z36: 0 | AA36: 0 | AB36: 0 | AC36: 46550 | AD36: 0 | AE36: 0 | AF36: 0 | AG36: 0 | AH36: 0
A37: Net Income/(After Tax & Donations) | B37: =B35-B36 -> 3010.7829 | C37: =C35-C36 -> 3557511 | D37: =D35-D36 -> 1999765.2 | E37: =E35-E36 -> 796449.67 | F37: =F35-F36 -> -582215.45 | G37: =G35-G36 -> 1019263.6 | H37: =H35-H36 -> 1719546.3 | I37: =I35-I36 -> 1223616.2 | ... AM37: =AM35-AM36 -> 0
A39: Total Expenses | B39: =B12+B23 -> 11568.465 | C39: =C12+C23 -> 20030129 | D39: =D12+D23 -> 480593.75 | E39: =E12+E23 -> 2508358.9 | F39: =F12+F23 -> 595344.62 | G39: =G12+G23 -> 5286154.5 | H39: =H12+H23 -> 6366414.8 | I39: =I12+I23 -> 8869689.3 | ... AM39: =AM12+AM23 -> 0

Sheet FORM 4
D1: 44256
B2: CLASSIFICATION | C2: NO. OF A/Cs | D2: OUTSTANDING LOAN PORTFOLIO(Kshs) | E2: REQUIRED PROVISION | F2: REQUIRED PROVISION AMOUNT(Kshs)
B3: Performing | C3: 873 | D3: 91882522 | E3: 0.01 | F3: =D3*E3 -> 918825.22
B4: Watch | C4: 43 | D4: 1343521.2 | E4: 0.05 | F4: =D4*E4 -> 67176.061 | H4: NPL | I4: =D5+D6+D7 -> 32492431
B5: Substandard | C5: 126 | D5: 7742521 | E5: 0.25 | F5: =D5*E5 -> 1935630.3 | H5: PAR | I5: =I4/D8 -> 0.25845391
B6: Doubtful | C6: 89 | D6: 4186717.8 | E6: 0.5 | F6: =D6*E6 -> 2093358.9
B7: Loss | C7: 385 | D7: 20563192 | E7: 1 | F7: =D7*E7 -> 20563192
B8: subtotal | C8: =SUM(C3:C7) -> 1516 | D8: =SUM(D3:D7) -> 1.2571847e+08 | E8: =SUM(E3:E7) -> 1.81 | F8: =SUM(F3:F7) -> 25578182
D10: 44348
B11: CLASSIFICATION | C11: NO. OF A/Cs | D11: OUTSTANDING LOAN PORTFOLIO(Kshs) | E11: REQUIRED PROVISION | F11: REQUIRED PROVISION AMOUNT(Kshs)
B12: Performing | C12: 894 | D12: 93520897 | E12: 0.01 | F12: =D12*E12 -> 935208.97
B13: Watch | C13: 31 | D13: 500814.14 | E13: 0.05 | F13: =D13*E13 -> 25040.707 | H13: NPL | I13: =D14+D15+D16 -> 31901373
B14: Substandard | C14: 140 | D14: 6989924 | E14: 0.25 | F14: =D14*E14 -> 1747481 | H14: PAR | I14: =I13/D17 -> 0.25334015
B15: Doubtful | C15: 89 | D15: 4909926 | E15: 0.5 | F15: =D15*E15 -> 2454963
B16: Loss | C16: 395 | D16: 20001523 | E16: 1 | F16: =D16*E16 -> 20001523
B17: subtotal | C17: =SUM(C12:C16) -> 1549 | D17: =SUM(D12:D16) -> 1.2592308e+08 | E17: 1.81 | F17: =SUM(F12:F16) -> 25164216
D19: 44440
B20: CLASSIFICATION | C20: NO. OF A/Cs | D20: OUTSTANDING LOAN PORTFOLIO(Kshs) | E20: REQUIRED PROVISION | F20: REQUIRED PROVISION AMOUNT(Kshs)
B21: Performing | C21: 913 | D21: 90842702 | E21: 0.01 | F21: =D21*E21 -> 908427.02
B22: Watch | C22: 40 | D22: 1213493.9 | E22: 0.05 | F22: =D22*E22 -> 60674.694 | H22: NPL | I22: =D23+D24+D25 -> 30927101
B23: Substandard | C23: 101 | D23: 4066892.9 | E23: 0.25 | F23: =D23*E23 -> 1016723.2 | H23: PAR | I23: =I22/D26 -> 0.25147399
B24: Doubtful | C24: 88 | D24: 6144873 | E24: 0.5 | F24: =D24*E24 -> 3072436.5
B25: Loss | C25: 411 | D25: 20715335 | E25: 1 | F25: =D25*E25 -> 20715335
B26: subtotal | C26: =SUM(C21:C25) -> 1553 | D26: =SUM(D21:D25) -> 1.229833e+08 | E26: 1.81 | F26: =SUM(F21:F25) -> 25773596
D28: 44531
B29: CLASSIFICATION | C29: NO. OF A/Cs | D29: OUTSTANDING LOAN PORTFOLIO(Kshs) | E29: REQUIRED PROVISION | F29: REQUIRED PROVISION AMOUNT(Kshs)
B30: Performing | C30: 854 | D30: 95533117 | E30: 0.01 | F30: =D30*E30 -> 955331.17
B31: Watch | C31: 52 | D31: 2068944.9 | E31: 0.05 | F31: =D31*E31 -> 103447.24 | H31: NPL | I31: =D32+D33+D34 -> 25363827
B32: Substandard | C32: 95 | D32: 3139897 | E32: 0.25 | F32: =D32*E32 -> 784974.25 | H32: PAR | I32: =I31/D35 -> 0.20626718
B33: Doubtful | C33: 71 | D33: 4203314 | E33: 0.5 | F33: =D33*E33 -> 2101657
B34: Loss | C34: 354 | D34: 18020616 | E34: 1 | F34: =D34*E34 -> 18020616
B35: subtotal | C35: =SUM(C30:C34) -> 1426 | D35: =SUM(D30:D34) -> 1.2296589e+08 | E35: 1.81 | F35: =SUM(F30:F34) -> 21966025
D38: Audited 2021
B39: CLASSIFICATION | C39: NO. OF A/Cs | D39: OUTSTANDING LOAN PORTFOLIO(Kshs) | E39: REQUIRED PROVISION | F39: REQUIRED PROVISION AMOUNT(Kshs)
B40: Performing | C40: 854 | D40: 95533117 | E40: 0.01 | F40: =D40*E40 -> 955331.17
B41: Watch | C41: 52 | D41: 2068945 | E41: 0.05 | F41: =D41*E41 -> 103447.25
B42: Substandard | C42: 95 | D42: 3139897 | E42: 0.25 | F42: =D42*E42 -> 784974.25
B43: Doubtful | C43: 71 | D43: 4203314 | E43: 0.5 | F43: =D43*E43 -> 2101657
B44: Loss | C44: 354 | D44: 18020616 | E44: 1 | F44: =D44*E44 -> 18020616
B45: subtotal | C45: =SUM(C40:C44) -> 1426 | D45: =SUM(D40:D44) -> 122965889 | E45: 1.81 | F45: =SUM(F40:F44) -> 21966026
D47: 44621
B48: CLASSIFICATION | C48: NO. OF A/Cs | D48: OUTSTANDING LOAN PORTFOLIO(Kshs) | E48: REQUIRED PROVISION | F48: REQUIRED PROVISION AMOUNT(Kshs)
B49: Performing | C49: 827 | D49: 95309549 | E49: 0.01 | F49: =D49*E49 -> 953095.49
B50: Watch | C50: 63 | D50: 1185259.4 | E50: 0.05 | F50: =D50*E50 -> 59262.973
B51: Substandard | C51: 143 | D51: 8549164.2 | E51: 0.25 | F51: =D51*E51 -> 2137291
B52: Doubtful | C52: 71 | D52: 2697519.8 | E52: 0.5 | F52: =D52*E52 -> 1348759.9
B53: Loss | C53: 374 | D53: 19683301 | E53: 1 | F53: =D53*E53 -> 19683301
B54: subtotal | C54: =SUM(C49:C53) -> 1478 | D54: =SUM(D49:D53) -> 1.2742479e+08 | E54: =SUM(E49:E53) -> 1.81 | F54: =SUM(F49:F53) -> 24181711
D56: 44713
B57: CLASSIFICATION | C57: NO. OF A/Cs | D57: OUTSTANDING LOAN PORTFOLIO(Kshs) | E57: REQUIRED PROVISION | F57: REQUIRED PROVISION AMOUNT(Kshs)
B58: Performing | C58: 897 | D58: 98409707 | E58: 0.01 | F58: =D58*E58 -> 984097.07
B59: Watch | C59: 25 | D59: 565955.27 | E59: 0.05 | F59: =D59*E59 -> 28297.764
B60: Substandard | C60: 153 | D60: 7029852.6 | E60: 0.25 | F60: =D60*E60 -> 1757463.1
B61: Doubtful | C61: 84 | D61: 3387977.1 | E61: 0.5 | F61: =D61*E61 -> 1693988.6
B62: Loss | C62: 368 | D62: 19008786 | E62: 1 | F62: =D62*E62 -> 19008786
B63: subtotal | C63: =SUM(C58:C62) -> 1527 | D63: =SUM(D58:D62) -> 1.2840228e+08 | E63: 1.81 | F63: =SUM(F58:F62) -> 23472632
D65: 44805
B66: CLASSIFICATION | C66: NO. OF A/Cs | D66: OUTSTANDING LOAN PORTFOLIO(Kshs) | E66: REQUIRED PROVISION | F66: REQUIRED PROVISION AMOUNT(Kshs)
B67: Performing | C67: 895 | D67: 1.0352163e+08 | E67: 0.01 | F67: =D67*E67 -> 1035216.3
B68: Watch | C68: 34 | D68: 1155860.9 | E68: 0.05 | F68: =D68*E68 -> 57793.044
B69: Substandard | C69: 86 | D69: 2680978.6 | E69: 0.25 | F69: =D69*E69 -> 670244.64
B70: Doubtful | C70: 97 | D70: 4967751.6 | E70: 0.5 | F70: =D70*E70 -> 2483875.8
B71: Loss | C71: 379 | D71: 18512499 | E71: 1 | F71: =D71*E71 -> 18512499
B72: subtotal | C72: =SUM(C67:C71) -> 1491 | D72: =SUM(D67:D71) -> 1.3083872e+08 | E72: 1.81 | F72: =SUM(F67:F71) -> 22759629
D74: 44896
B75: CLASSIFICATION | C75: NO. OF A/Cs | D75: OUTSTANDING LOAN PORTFOLIO(Kshs) | E75: REQUIRED PROVISION | F75: REQUIRED PROVISION AMOUNT(Kshs)
B76: Performing | C76: 854 | D76: 97060405 | E76: 0.01 | F76: =D76*E76 -> 970604.05
B77: Watch | C77: 52 | D77: 1808779.1 | E77: 0.05 | F77: =D77*E77 -> 90438.953
B78: Substandard | C78: 95 | D78: 4471730.8 | E78: 0.25 | F78: =D78*E78 -> 1117932.7
B79: Doubtful | C79: 71 | D79: 3215892.5 | E79: 0.5 | F79: =D79*E79 -> 1607946.2
B80: Loss | C80: 354 | D80: 17087908 | E80: 1 | F80: =D80*E80 -> 17087908
B81: subtotal | C81: =SUM(C76:C80) -> 1426 | D81: =SUM(D76:D80) -> 1.2364472e+08 | E81: 1.81 | F81: =SUM(F76:F80) -> 20874830
D84: Audited 2022
B85: CLASSIFICATION | C85: NO. OF A/Cs | D85: OUTSTANDING LOAN PORTFOLIO(Kshs) | E85: REQUIRED PROVISION | F85: REQUIRED PROVISION AMOUNT(Kshs)
B86: Performing | C86: 854 | D86: 97060405 | E86: 0.01 | F86: =D86*E86 -> 970604.05
B87: Watch | C87: 52 | D87: 1808779.1 | E87: 0.05 | F87: =D87*E87 -> 90438.953
B88: Substandard | C88: 95 | D88: 4471730.8 | E88: 0.25 | F88: =D88*E88 -> 1117932.7
B89: Doubtful | C89: 71 | D89: 3215892.5 | E89: 0.5 | F89: =D89*E89 -> 1607946.2
B90: Loss | C90: 354 | D90: 17087908 | E90: 1 | F90: =D90*E90 -> 17087908
B91: subtotal | C91: =SUM(C86:C90) -> 1426 | D91: =SUM(D86:D90) -> 1.2364472e+08 | E91: 1.81 | F91: =SUM(F86:F90) -> 20874830

Sheet CAELS
A1: TRANSCOUNTIES SACCO 2022 CAELS
D2: 2010 Audited | E2: 2020Audited | F2: 44198 | G2: 44230 | H2: 44259 | I2: 44291 | J2: 44322 | K2: 44354 | L2: 44385 | M2: 44417 | N2: 44449 | O2: 44480 | P2: 44512 | Q2: 44543 | R2: Audited 2021 | S2: 44590 | T2: 44595 | U2: 44651 | V2: 44652 | W2: 44683 | X2: 44715 | Y2: 44746 | Z2: 44778 | AA2: 44810 | AB2: 44841 | AC2: 44873 | AD2: 44904 | AE2: Audited 2022 | AF2: 44927 | AG2: 44958 | AH2: 44986 | AI2: 45017 | AJ2: 45047 | AK2: 45078 | AL2: 45108 | AM2: 45139 | AN2: 45170 | AO2: 45200 | AP2: 45231 | AQ2: 45261 | AR2: 45292
A3: CAPITAL ADEQUACY | B3: Core Capital | C3: 10 M | D3: =(('Evolutive SFP'!B39+'Evolutive SFP'!B40+'Evolutive SFP'!B41+'Evolutive SFP'!B42+'Evolutive SFP'!B43+'Evolutive SFP'!B44)-'Evolutive SFP'!B10)/1000000 -> 15.259572 | E3: =(('Evolutive SFP'!C39+'Evolutive SFP'!C40+'Evolutive SFP'!C41+'Evolutive SFP'!C42+'Evolutive SFP'!C43+'Evolutive SFP'!C44)-'Evolutive SFP'!C10)/1000000 -> 42.12668 | F3: =(('Evolutive SFP'!D39+'Evolutive SFP'!D40+'Evolutive SFP'!D41+'Evolutive SFP'!D42+'Evolutive SFP'!D43+'Evolutive SFP'!D44)-'Evolutive SFP'!D10)/1000000 -> 43.730082 | G3: =(('Evolutive SFP'!E39+'Evolutive SFP'!E40+'Evolutive SFP'!E41+'Evolutive SFP'!E42+'Evolutive SFP'!E43+'Evolutive SFP'!E44)-'Evolutive SFP'!E10)/1000000 -> 43.113721 | H3: =(('Evolutive SFP'!F39+'Evolutive SFP'!F40+'Evolutive SFP'!F41+'Evolutive SFP'!F42+'Evolutive SFP'!F43+'Evolutive SFP'!F44)-'Evolutive SFP'!F10)/1000000 -> 42.742429 | I3: =(('Evolutive SFP'!G39+'Evolutive SFP'!G40+'Evolutive SFP'!G41+'Evolutive SFP'!G42+'Evolutive SFP'!G43+'Evolutive SFP'!G44)-'Evolutive SFP'!G10)/1000000 -> 44.219941 | J3: =(('Evolutive SFP'!H39+'Evolutive SFP'!H40+'Evolutive SFP'!H41+'Evolutive SFP'!H42+'Evolutive SFP'!H43+'Evolutive SFP'!H44)-'Evolutive SFP'!H10)/1000000 -> 47.136049 | K3: =(('Evolutive SFP'!I39+'Evolutive SFP'!I40+'Evolutive SFP'!I41+'Evolutive SFP'!I42+'Evolutive SFP'!I43+'Evolutive SFP'!I44)-'Evolutive SFP'!I10)/1000000 -> 44.857158 | ... AY3: =(('Evolutive SFP'!AW39+'Evolutive SFP'!AW40+'Evolutive SFP'!AW41+'Evolutive SFP'!AW42+'Evolutive SFP'!AW43+'Evolutive SFP'!AW44)-'Evolutive SFP'!AW10)/1000000 -> 0
B4: CCA | C4: Min 10% | D4: =D3/(('Evolutive SFP'!B27)/1000000) -> 0.10104624 | E4: =E3/(('Evolutive SFP'!C27)/1000000) -> 0.21456568 | F4: =F3/(('Evolutive SFP'!D27)/1000000) -> 0.22182445 | G4: =G3/(('Evolutive SFP'!E27)/1000000) -> 0.22074088 | H4: =H3/(('Evolutive SFP'!F27)/1000000) -> 0.2194844 | I4: =I3/(('Evolutive SFP'!G27)/1000000) -> 0.22955197 | J4: =J3/(('Evolutive SFP'!H27)/1000000) -> 0.24387448 | K4: =K3/(('Evolutive SFP'!I27)/1000000) -> 0.23419893 | ... AY4: =AY3/(('Evolutive SFP'!AW27)/1000000) -> #DIV/0!
B5: CCD | C5: Min 8% | D5: =D3/('Evolutive SFP'!B31/1000000) -> 0.1186553 | E5: =E3/('Evolutive SFP'!C31/1000000) -> 0.29475713 | F5: =F3/('Evolutive SFP'!D31/1000000) -> 0.30914105 | G5: =G3/('Evolutive SFP'!E31/1000000) -> 0.30636369 | H5: =H3/('Evolutive SFP'!F31/1000000) -> 0.29749946 | I5: =I3/('Evolutive SFP'!G31/1000000) -> 0.31044598 | J5: =J3/('Evolutive SFP'!H31/1000000) -> 0.33410248 | K5: =K3/('Evolutive SFP'!I31/1000000) -> 0.31695769 | ... AY5: =AY3/('Evolutive SFP'!AW31/1000000) -> #DIV/0!
B6: ICA | C6: Min 8% | D6: =((D3*1000000)-'Evolutive SFP'!B39)/'Evolutive SFP'!B27 -> 0.031552177 | E6: =((E3*1000000)-'Evolutive SFP'!C39)/'Evolutive SFP'!C27 -> 0.11089375 | F6: =((F3*1000000)-'Evolutive SFP'!D39)/'Evolutive SFP'!D27 -> 0.11829392 | G6: =((G3*1000000)-'Evolutive SFP'!E39)/'Evolutive SFP'!E27 -> 0.11576458 | H6: =((H3*1000000)-'Evolutive SFP'!F39)/'Evolutive SFP'!F27 -> 0.11258139 | I6: =((I3*1000000)-'Evolutive SFP'!G39)/'Evolutive SFP'!G27 -> 0.11853049 | J6: =((J3*1000000)-'Evolutive SFP'!H39)/'Evolutive SFP'!H27 -> 0.13187879 | K6: =((K3*1000000)-'Evolutive SFP'!I39)/'Evolutive SFP'!I27 -> 0.12027903 | ... AY6: =((AY3*1000000)-'Evolutive SFP'!AW39)/'Evolutive SFP'!AW27 -> #DIV/0!
A7: ASSET QUALITY | B7: A/LNPL30
B8: NPL30 | R8: =('FORM 4'!D42+'FORM 4'!D43+'FORM 4'!D44)/'Evolutive SFP'!P15 -> 0.20625666 | U8: =('FORM 4'!D51+'FORM 4'!D52+'FORM 4'!D53)/'Evolutive SFP'!S15 -> 0.24271935 | X8: =('FORM 4'!D60+'FORM 4'!D61+'FORM 4'!D62)/'Evolutive SFP'!V15 -> 0.22916399 | AA8: =('FORM 4'!D69+'FORM 4'!D70+'FORM 4'!D71)/'Evolutive SFP'!Y15 -> 0.19994869 | AD8: =('FORM 4'!D78+'FORM 4'!D79+'FORM 4'!D80)/'Evolutive SFP'!AB15 -> 0.20087112 | AE8: =('FORM 4'!D88+'FORM 4'!D89+'FORM 4'!D90)/'Evolutive SFP'!AC15 -> 0.20047405
A9: EARNINGS | B9: ROA | E9: ='Evolutitve SCI'!C33/(('Evolutive SFP'!B27+'Evolutive SFP'!C27)/2) -> 0.024005236 | F9: ='Evolutitve SCI'!D33/(('Evolutive SFP'!C27+'Evolutive SFP'!D27)/2) -> 0.010164691 | G9: ='Evolutitve SCI'!E33/(('Evolutive SFP'!D27+'Evolutive SFP'!E27)/2) -> 0.0040588391 | H9: ='Evolutitve SCI'!F33/(('Evolutive SFP'!E27+'Evolutive SFP'!F27)/2) -> -0.0028827579 | I9: ='Evolutitve SCI'!G33/(('Evolutive SFP'!F27+'Evolutive SFP'!G27)/2) -> 0.0061297734 | J9: ='Evolutitve SCI'!H33/(('Evolutive SFP'!G27+'Evolutive SFP'!H27)/2) -> 0.0097821658 | K9: ='Evolutitve SCI'!I33/(('Evolutive SFP'!H27+'Evolutive SFP'!I27)/2) -> 0.0081058103 | L9: ='Evolutitve SCI'!J33/(('Evolutive SFP'!I27+'Evolutive SFP'!J27)/2) -> 0.0096758657 | ... AY9: ='Evolutitve SCI'!AW33/(('Evolutive SFP'!AV27+'Evolutive SFP'!AW27)/2) -> #DIV/0!
B10: Cost Income ratio | D10: ='Evolutitve SCI'!B23/'Evolutitve SCI'!B19 -> 0.78428841 | E10: ='Evolutitve SCI'!C23/'Evolutitve SCI'!C19 -> 0.78734037 | F10: ='Evolutitve SCI'!D23/'Evolutitve SCI'!D19 -> 0.13172017 | G10: ='Evolutitve SCI'!E23/'Evolutitve SCI'!E19 -> 0.51126484 | H10: ='Evolutitve SCI'!F23/'Evolutitve SCI'!F19 -> 93.249435 | I10: ='Evolutitve SCI'!G23/'Evolutitve SCI'!G19 -> 0.5849342 | J10: ='Evolutitve SCI'!H23/'Evolutitve SCI'!H19 -> 0.61283355 | K10: ='Evolutitve SCI'!I23/'Evolutitve SCI'!I19 -> 0.69807516 | ... AY10: ='Evolutitve SCI'!AW23/'Evolutitve SCI'!AW19 -> #DIV/0!
B11: Operating Expense ratio | D11: =('Evolutitve SCI'!B23+'Evolutitve SCI'!B12)/(('Evolutive SFP'!B27+'Evolutive SFP'!C27)/2) -> 6.6609769e-05 | E11: =('Evolutitve SCI'!C23+'Evolutitve SCI'!C12)/(('Evolutive SFP'!C27+'Evolutive SFP'!D27)/2) -> 0.10181199 | F11: =('Evolutitve SCI'!D23+'Evolutitve SCI'!D12)/(('Evolutive SFP'!D27+'Evolutive SFP'!E27)/2) -> 0.0024491852 | G11: =('Evolutitve SCI'!E23+'Evolutitve SCI'!E12)/(('Evolutive SFP'!E27+'Evolutive SFP'!F27)/2) -> 0.012861602 | H11: =('Evolutitve SCI'!F23+'Evolutitve SCI'!F12)/(('Evolutive SFP'!F27+'Evolutive SFP'!G27)/2) -> 0.0030737298 | I11: =('Evolutitve SCI'!G23+'Evolutitve SCI'!G12)/(('Evolutive SFP'!G27+'Evolutive SFP'!H27)/2) -> 0.027395376 | J11: =('Evolutitve SCI'!H23+'Evolutitve SCI'!H12)/(('Evolutive SFP'!H27+'Evolutive SFP'!I27)/2) -> 0.033088237 | K11: =('Evolutitve SCI'!I23+'Evolutitve SCI'!I12)/(('Evolutive SFP'!I27+'Evolutive SFP'!J27)/2) -> 0.046246331 | ... AY11: =('Evolutitve SCI'!AW23+'Evolutitve SCI'!AW12)/(('Evolutive SFP'!AW27+'Evolutive SFP'!AX27)/2) -> #DIV/0!
A12: LIQUIDITY | B12: MIN LIQ ratio | C12: Min 15% | D12: =('Evolutive SFP'!B4)/('Evolutive SFP'!B28+'Evolutive SFP'!B29+'Evolutive SFP'!B32+'Evolutive SFP'!B33+'Evolutive SFP'!B34+'Evolutive SFP'!B35+'Evolutive SFP'!B36) -> 0.90806632 | E12: =('Evolutive SFP'!C4)/('Evolutive SFP'!C28+'Evolutive SFP'!C29+'Evolutive SFP'!C32+'Evolutive SFP'!C33+'Evolutive SFP'!C34+'Evolutive SFP'!C35+'Evolutive SFP'!C36) -> 1.5066817 | F12: =('Evolutive SFP'!D4)/('Evolutive SFP'!D28+'Evolutive SFP'!D29+'Evolutive SFP'!D32+'Evolutive SFP'!D33+'Evolutive SFP'!D34+'Evolutive SFP'!D35+'Evolutive SFP'!D36) -> 1.4908281 | G12: =('Evolutive SFP'!E4)/('Evolutive SFP'!E28+'Evolutive SFP'!E29+'Evolutive SFP'!E32+'Evolutive SFP'!E33+'Evolutive SFP'!E34+'Evolutive SFP'!E35+'Evolutive SFP'!E36) -> 1.4547455 | H12: =('Evolutive SFP'!F4)/('Evolutive SFP'!F28+'Evolutive SFP'!F29+'Evolutive SFP'!F32+'Evolutive SFP'!F33+'Evolutive SFP'!F34+'Evolutive SFP'!F35+'Evolutive SFP'!F36) -> 1.4930332 | I12: =('Evolutive SFP'!G4)/('Evolutive SFP'!G28+'Evolutive SFP'!G29+'Evolutive SFP'!G32+'Evolutive SFP'!G33+'Evolutive SFP'!G34+'Evolutive SFP'!G35+'Evolutive SFP'!G36) -> 1.5606636 | J12: =('Evolutive SFP'!H4)/('Evolutive SFP'!H28+'Evolutive SFP'!H29+'Evolutive SFP'!H32+'Evolutive SFP'!H33+'Evolutive SFP'!H34+'Evolutive SFP'!H35+'Evolutive SFP'!H36) -> 1.64838 | K12: =('Evolutive SFP'!I4)/('Evolutive SFP'!I28+'Evolutive SFP'!I29+'Evolutive SFP'!I32+'Evolutive SFP'!I33+'Evolutive SFP'!I34+'Evolutive SFP'!I35+'Evolutive SFP'!I36) -> 1.6727037 | ... AY12: =('Evolutive SFP'!AW4)/('Evolutive SFP'!AW28+'Evolutive SFP'!AW29+'Evolutive SFP'!AW32+'Evolutive SFP'!AW33+'Evolutive SFP'!AW34+'Evolutive SFP'!AW35+'Evolutive SFP'!AW36) -> #DIV/0!
B13: T/LIQ ratio | D13: ='Evolutive SFP'!B4/('Evolutive SFP'!B31+'Evolutive SFP'!B36) -> 0.14915539 | E13: ='Evolutive SFP'!C4/('Evolutive SFP'!C31+'Evolutive SFP'!C36) -> 0.55211955 | F13: ='Evolutive SFP'!D4/('Evolutive SFP'!D31+'Evolutive SFP'!D36) -> 0.53195438 | G13: ='Evolutive SFP'!E4/('Evolutive SFP'!E31+'Evolutive SFP'!E36) -> 0.50796337 | H13: ='Evolutive SFP'!F4/('Evolutive SFP'!F31+'Evolutive SFP'!F36) -> 0.49816762 | I13: ='Evolutive SFP'!G4/('Evolutive SFP'!G31+'Evolutive SFP'!G36) -> 0.49026422 | J13: ='Evolutive SFP'!H4/('Evolutive SFP'!H31+'Evolutive SFP'!H36) -> 0.49072735 | K13: ='Evolutive SFP'!I4/('Evolutive SFP'!I31+'Evolutive SFP'!I36) -> 0.49630355 | ... AY13: ='Evolutive SFP'!AW4/('Evolutive SFP'!AW31+'Evolutive SFP'!AW36) -> #DIV/0!
B14: EB ratio | C14: Max 25% | D14: ='Evolutive SFP'!B37/'Evolutive SFP'!B27 -> 0.015175035 | E14: ='Evolutive SFP'!C37/'Evolutive SFP'!C27 -> 0 | F14: ='Evolutive SFP'!D37/'Evolutive SFP'!D27 -> 0 | G14: ='Evolutive SFP'!E37/'Evolutive SFP'!E27 -> 0 | H14: ='Evolutive SFP'!F37/'Evolutive SFP'!F27 -> 0 | I14: ='Evolutive SFP'!G37/'Evolutive SFP'!G27 -> 0 | J14: ='Evolutive SFP'!H37/'Evolutive SFP'!H27 -> 0 | K14: ='Evolutive SFP'!I37/'Evolutive SFP'!I27 -> 0 | ... AY14: ='Evolutive SFP'!AW37/'Evolutive SFP'!AW27 -> #DIV/0!
B15: LA to TA ratio | D15: ='Evolutive SFP'!B4/'Evolutive SFP'!B27 -> 0.12821992 | E15: ='Evolutive SFP'!C4/'Evolutive SFP'!C27 -> 0.41255969 | F15: ='Evolutive SFP'!D4/'Evolutive SFP'!D27 -> 0.3912925 | G15: ='Evolutive SFP'!E4/'Evolutive SFP'!E27 -> 0.37726296 | H15: ='Evolutive SFP'!F4/'Evolutive SFP'!F27 -> 0.38061698 | I15: ='Evolutive SFP'!G4/'Evolutive SFP'!G27 -> 0.36955447 | J15: ='Evolutive SFP'!H4/'Evolutive SFP'!H27 -> 0.36374364 | K15: ='Evolutive SFP'!I4/'Evolutive SFP'!I27 -> 0.37261146 | ... AY15: ='Evolutive SFP'!AW4/'Evolutive SFP'!AW27 -> #DIV/0!
A16: STRUCTURE | B16: NEA ratio | C16: Max 10% | D16: =('Evolutive SFP'!B7+'Evolutive SFP'!B21)/'Evolutive SFP'!B27 -> 0.12101375 | E16: =('Evolutive SFP'!C7+'Evolutive SFP'!C21)/'Evolutive SFP'!C27 -> 0.088097908 | F16: =('Evolutive SFP'!D7+'Evolutive SFP'!D21)/'Evolutive SFP'!D27 -> 0.082446444 | G16: =('Evolutive SFP'!E7+'Evolutive SFP'!E21)/'Evolutive SFP'!E27 -> 0.085679841 | H16: =('Evolutive SFP'!F7+'Evolutive SFP'!F21)/'Evolutive SFP'!F27 -> 0.088070652 | I16: =('Evolutive SFP'!G7+'Evolutive SFP'!G21)/'Evolutive SFP'!G27 -> 0.08844105 | J16: =('Evolutive SFP'!H7+'Evolutive SFP'!H21)/'Evolutive SFP'!H27 -> 0.087767818 | K16: =('Evolutive SFP'!I7+'Evolutive SFP'!I21)/'Evolutive SFP'!I27 -> 0.083953933 | ... AY16: =('Evolutive SFP'!AW7+'Evolutive SFP'!AW21)/'Evolutive SFP'!AW27 -> #DIV/0!
B17: LB ratio | C17: Max 5% | D17: ='Evolutive SFP'!B21/'Evolutive SFP'!B27 -> 0.032278671 | E17: ='Evolutive SFP'!C21/'Evolutive SFP'!C27 -> 0.076213231 | F17: ='Evolutive SFP'!D21/'Evolutive SFP'!D27 -> 0.079234899 | G17: ='Evolutive SFP'!E21/'Evolutive SFP'!E27 -> 0.085452444 | H17: ='Evolutive SFP'!F21/'Evolutive SFP'!F27 -> 0.085784763 | I17: ='Evolutive SFP'!G21/'Evolutive SFP'!G27 -> 0.08671895 | J17: ='Evolutive SFP'!H21/'Evolutive SFP'!H27 -> 0.086579276 | K17: ='Evolutive SFP'!I21/'Evolutive SFP'!I27 -> 0.081634239 | ... AY17: ='Evolutive SFP'!AW21/'Evolutive SFP'!AW27 -> #DIV/0!
B18: PI to Deposit ratio | C18: Max 5% | D18: ='Evolutive SFP'!B13/'Evolutive SFP'!B31 -> 0.0036721969 | E18: ='Evolutive SFP'!C13/'Evolutive SFP'!C31 -> 0.0010816193 | F18: ='Evolutive SFP'!D13/'Evolutive SFP'!D31 -> 0.029828283 | G18: ='Evolutive SFP'!E13/'Evolutive SFP'!E31 -> 0.023608223 | H18: ='Evolutive SFP'!F13/'Evolutive SFP'!F31 -> 0.023124295 | I18: ='Evolutive SFP'!G13/'Evolutive SFP'!G31 -> 0.023324342 | J18: ='Evolutive SFP'!H13/'Evolutive SFP'!H31 -> 0.02354876 | K18: ='Evolutive SFP'!I13/'Evolutive SFP'!I31 -> 0.023475295 | ... AY18: ='Evolutive SFP'!AW13/'Evolutive SFP'!AW31 -> #DIV/0!
B19: PI to CC ratio | C19: Max 40% | D19: ='Evolutive SFP'!B13/(CAELS!D3*1000000) -> 0.030948443 | E19: ='Evolutive SFP'!C13/(CAELS!E3*1000000) -> 0.0036695272 | F19: ='Evolutive SFP'!D13/(CAELS!F3*1000000) -> 0.096487616 | G19: ='Evolutive SFP'!E13/(CAELS!G3*1000000) -> 0.077059468 | H19: ='Evolutive SFP'!F13/(CAELS!H3*1000000) -> 0.077728863 | I19: ='Evolutive SFP'!G13/(CAELS!I3*1000000) -> 0.075131724 | J19: ='Evolutive SFP'!H13/(CAELS!J3*1000000) -> 0.070483642 | K19: ='Evolutive SFP'!I13/(CAELS!K3*1000000) -> 0.074064443 | ... AY19: ='Evolutive SFP'!AW13/(CAELS!AY3*1000000) -> #DIV/0!
B20: Gross loans/TA | D20: ='Evolutive SFP'!B15/'Evolutive SFP'!B27 -> 0.74763912 | E20: ='Evolutive SFP'!C15/'Evolutive SFP'!C27 -> 0.59968059 | F20: ='Evolutive SFP'!D15/'Evolutive SFP'!D27 -> 0.62603309 | G20: ='Evolutive SFP'!E15/'Evolutive SFP'!E27 -> 0.64585926 | H20: ='Evolutive SFP'!F15/'Evolutive SFP'!F27 -> 0.64559728 | I20: ='Evolutive SFP'!G15/'Evolutive SFP'!G27 -> 0.65654246 | J20: ='Evolutive SFP'!H15/'Evolutive SFP'!H27 -> 0.65041253 | K20: ='Evolutive SFP'!I15/'Evolutive SFP'!I27 -> 0.657471 | ... AY20: ='Evolutive SFP'!AW15/'Evolutive SFP'!AW27 -> #DIV/0!
A21: FUNDING MIX | B21: Total Deposits/Total Assets | D21: ='Evolutive SFP'!B31/'Evolutive SFP'!B27 -> 0.85159483 | E21: ='Evolutive SFP'!C31/'Evolutive SFP'!C27 -> 0.72794059 | F21: ='Evolutive SFP'!D31/'Evolutive SFP'!D27 -> 0.71755093 | G21: ='Evolutive SFP'!E31/'Evolutive SFP'!E27 -> 0.72051908 | H21: ='Evolutive SFP'!F31/'Evolutive SFP'!F27 -> 0.73776403 | I21: ='Evolutive SFP'!G31/'Evolutive SFP'!G27 -> 0.73942645 | J21: ='Evolutive SFP'!H31/'Evolutive SFP'!H27 -> 0.72993914 | K21: ='Evolutive SFP'!I31/'Evolutive SFP'!I27 -> 0.73889648 | ... AY21: ='Evolutive SFP'!AW31/'Evolutive SFP'!AW27 -> #DIV/0!
B22: BOSA Deposits/Total Assets | D22: ='Evolutive SFP'!B30/'Evolutive SFP'!B27 -> 0.74257768 | E22: ='Evolutive SFP'!C30/'Evolutive SFP'!C27 -> 0.49786054 | F22: ='Evolutive SFP'!D30/'Evolutive SFP'!D27 -> 0.49746079 | G22: ='Evolutive SFP'!E30/'Evolutive SFP'!E27 -> 0.5061009 | H22: ='Evolutive SFP'!F30/'Evolutive SFP'!F27 -> 0.51172061 | I22: ='Evolutive SFP'!G30/'Evolutive SFP'!G27 -> 0.51963707 | J22: ='Evolutive SFP'!H30/'Evolutive SFP'!H27 -> 0.52148731 | K22: ='Evolutive SFP'!I30/'Evolutive SFP'!I27 -> 0.52894269 | ... AY22: ='Evolutive SFP'!AW30/'Evolutive SFP'!AW27 -> #DIV/0!
B23: FOSA Deposits/Total Assets | D23: =('Evolutive SFP'!B28+'Evolutive SFP'!B29)/'Evolutive SFP'!B27 -> 0.10901715 | E23: =('Evolutive SFP'!C28+'Evolutive SFP'!C29)/'Evolutive SFP'!C27 -> 0.23008005 | F23: =('Evolutive SFP'!D28+'Evolutive SFP'!D29)/'Evolutive SFP'!D27 -> 0.22009013 | G23: =('Evolutive SFP'!E28+'Evolutive SFP'!E29)/'Evolutive SFP'!E27 -> 0.21441817 | H23: =('Evolutive SFP'!F28+'Evolutive SFP'!F29)/'Evolutive SFP'!F27 -> 0.22604342 | I23: =('Evolutive SFP'!G28+'Evolutive SFP'!G29)/'Evolutive SFP'!G27 -> 0.21978937 | J23: =('Evolutive SFP'!H28+'Evolutive SFP'!H29)/'Evolutive SFP'!H27 -> 0.20845183 | K23: =('Evolutive SFP'!I28+'Evolutive SFP'!I29)/'Evolutive SFP'!I27 -> 0.2099538 | ... AY23: =('Evolutive SFP'!AW28+'Evolutive SFP'!AW29)/'Evolutive SFP'!AW27 -> #DIV/0!
A24: GROWTH RATIOS | B24: Total Assets | D24: =(Financials!C4-Financials!B4)/Financials!B4 -> #VALUE! | E24: =(Financials!D4-Financials!C4)/Financials!C4 -> 0.30009413 | F24: =(Financials!E4-Financials!D4)/Financials!D4 -> 0.0040929075 | G24: =(Financials!F4-Financials!E4)/Financials!E4 -> -0.0092550939 | H24: =(Financials!G4-Financials!F4)/Financials!F4 -> -0.0029365037 | I24: =(Financials!H4-Financials!G4)/Financials!G4 -> -0.010805731 | J24: =(Financials!I4-Financials!H4)/Financials!H4 -> 0.0033435976 | K24: =(Financials!J4-Financials!I4)/Financials!I4 -> -0.0090310784 | ... AY24: =(Financials!AX4-Financials!AW4)/Financials!AW4 -> #DIV/0!
B25: Total Deposits | C25: =IF(CAELS!D16<6%,"1",IF) -> #NAME? | D25: =Financials!D5/Financials!C5-1 -> 0.11131639 | E25: =Financials!E5/Financials!D5-1 -> -0.010238193 | F25: =Financials!F5/Financials!E5-1 -> -0.0051568757 | G25: =Financials!G5/Financials!F5-1 -> 0.020927275 | H25: =Financials!H5/Financials!G5-1 -> -0.0085767565 | I25: =Financials!I5/Financials!H5-1 -> -0.0095299309 | J25: =Financials!J5/Financials!I5-1 -> 0.003129455 | K25: =Financials!K5/Financials!J5-1 -> -0.0003632884 | ... AY25: =Financials!AY5/Financials!AX5-1 -> #DIV/0!
B26: BOSA Deposits | D26: =Financials!D6/Financials!C6-1 -> -0.12835304 | E26: =Financials!E6/Financials!D6-1 -> 0.0032866834 | F26: =Financials!F6/Financials!E6-1 -> 0.0079525862 | G26: =Financials!G6/Financials!F6-1 -> 0.0081348105 | H26: =Financials!H6/Financials!G6-1 -> 0.0044973894 | I26: =Financials!I6/Financials!H6-1 -> 0.0069161326 | J26: =Financials!J6/Financials!I6-1 -> 0.0051361897 | K26: =Financials!K6/Financials!J6-1 -> 0.007292579 | ... AY26: =Financials!AY6/Financials!AX6-1 -> #DIV/0!
B27: FOSA Deposits | D27: =Financials!D7/Financials!C7-1 -> 1.7438409 | E27: =Financials!E7/Financials!D7-1 -> -0.039504104 | F27: =Financials!F7/Financials!E7-1 -> -0.03478766 | G27: =Financials!G7/Financials!F7-1 -> 0.051121906 | H27: =Financials!H7/Financials!G7-1 -> -0.038174212 | I27: =Financials!I7/Financials!H7-1 -> -0.04841254 | J27: =Financials!J7/Financials!I7-1 -> -0.0018908255 | K27: =Financials!K7/Financials!J7-1 -> -0.019650937 | ... AY27: =Financials!AY7/Financials!AX7-1 -> #DIV/0!
B28: Total Loans & advances | D28: =Financials!D31/Financials!C31-1 -> 0.042804213 | E28: =Financials!E31/Financials!D31-1 -> 0.048216994 | F28: =Financials!F31/Financials!E31-1 -> 0.022121316 | G28: =Financials!G31/Financials!F31-1 -> -0.0033409378 | H28: =Financials!H31/Financials!G31-1 -> 0.0059646513 | I28: =Financials!I31/Financials!H31-1 -> -0.0060243081 | J28: =Financials!J31/Financials!I31-1 -> 0.0017232122 | K28: =Financials!K31/Financials!J31-1 -> -0.02560335 | ... AY28: =Financials!AY31/Financials!AX31-1 -> #DIV/0!
B29: Core capital | D29: =Financials!D11/Financials!C11-1 -> 1.6860015 | E29: =Financials!E11/Financials!D11-1 -> 0.018201843 | F29: =Financials!F11/Financials!E11-1 -> 0.0071051593 | G29: =Financials!G11/Financials!F11-1 -> -0.0093309558 | H29: =Financials!H11/Financials!G11-1 -> 0.037481178 | I29: =Financials!I11/Financials!H11-1 -> 0.071302629 | J29: =Financials!J11/Financials!I11-1 -> -0.052013176 | K29: =Financials!K11/Financials!J11-1 -> 0.011579224 | ... AY29: =Financials!AY11/Financials!AX11-1 -> #DIV/0!
B30: Turnover | D30: =Financials!D37/Financials!C37-1 -> 1705.4039 | E30: =Financials!E37/Financials!D37-1 -> -0.86566952 | F30: =Financials!F37/Financials!E37-1 -> 0.45092525 | G30: =Financials!G37/Financials!F37-1 -> -0.99863264 | H30: =Financials!H37/Financials!G37-1 -> 1330.1419 | I30: =Financials!I37/Financials!H37-1 -> 0.15527897 | J30: =Financials!J37/Financials!I37-1 -> 0.23127895 | K30: =Financials!K37/Financials!J37-1 -> 0.14258687 | ... AY30: =Financials!AY37/Financials!AX37-1 -> #DIV/0!
B31: Membership
B32: Expenses | D32: ='Evolutitve SCI'!E39/'Evolutitve SCI'!B39-1 -> 215.8273 | E32: ='Evolutitve SCI'!F39/'Evolutitve SCI'!C39-1 -> -0.97027754 | F32: ='Evolutitve SCI'!G39/'Evolutitve SCI'!D39-1 -> 9.9992161 | G32: ='Evolutitve SCI'!H39/'Evolutitve SCI'!E39-1 -> 1.5380797 | H32: ='Evolutitve SCI'!I39/'Evolutitve SCI'!F39-1 -> 13.898412 | I32: ='Evolutitve SCI'!J39/'Evolutitve SCI'!G39-1 -> 0.95721969 | J32: ='Evolutitve SCI'!K39/'Evolutitve SCI'!H39-1 -> 0.85049661 | K32: ='Evolutitve SCI'!L39/'Evolutitve SCI'!I39-1 -> 0.45638823 | ... AY32: ='Evolutitve SCI'!AZ39/'Evolutitve SCI'!AW39-1 -> #DIV/0!
A33: Efficiency Ratios | B33: FinCost-Deposits/Avg Deposits
B34: FinCost-Shares/Avg Share capital
B35: FinCost-Ext Loans/Avg Ext Loans
B36: OpEx/Average Total Assets
B37: Opex/Turnover
B38: Avge yield on Net loans
B39: Avge yield on Gross loans
A41: ALL/Average Gross Loan portfolio

Sheet Financials
B1: SOLUTION Sacco Financial Performance
B2: Year | C2: 2010 Audited | D2: 2020 Audited | E2: 44197 | F2: 44229 | G2: 44258 | H2: 44290 | I2: 44321 | J2: 44353 | K2: 44384 | L2: 44416 | M2: 44448 | N2: 44479 | O2: 44511 | P2: 44542 | Q2: Audited 2021 | R2: 44582 | S2: 44614 | T2: 44643 | U2: 44675 | V2: 44706 | W2: 44738 | X2: 44769 | Y2: 44801 | Z2: 44833 | AA2: 44864 | AB2: 44868 | AC2: 44896 | AD2: Audited 2022 | AE2: 44564 | AF2: 44595 | AG2: 44623 | AH2: 44654 | AI2: 44684 | AJ2: 44715 | AK2: 44745 | AL2: 44776 | AM2: 44807 | AN2: 44837
A3: 1 | B3: Membership
A4: 2 | B4: Total Assets | C4: ='Evolutive SFP'!B27 -> 151015729 | D4: ='Evolutive SFP'!C27 -> 196334663 | E4: ='Evolutive SFP'!D27 -> 1.9713824e+08 | F4: ='Evolutive SFP'!E27 -> 1.9531371e+08 | G4: ='Evolutive SFP'!F27 -> 1.9474017e+08 | H4: ='Evolutive SFP'!G27 -> 1.9263586e+08 | I4: ='Evolutive SFP'!H27 -> 1.9327996e+08 | J4: ='Evolutive SFP'!I27 -> 1.9153443e+08 | ... AY4: ='Evolutive SFP'!AX27 -> 0
A5: 3 | B5: Total Deposits | C5: ='Evolutive SFP'!B31 -> 128604214 | D5: ='Evolutive SFP'!C31 -> 142919971 | E5: ='Evolutive SFP'!D31 -> 1.4145673e+08 | F5: ='Evolutive SFP'!E31 -> 1.4072725e+08 | G5: ='Evolutive SFP'!F31 -> 1.4367229e+08 | H5: ='Evolutive SFP'!G31 -> 1.4244005e+08 | I5: ='Evolutive SFP'!H31 -> 1.4108261e+08 | J5: ='Evolutive SFP'!I31 -> 1.4152412e+08 | ... AY5: ='Evolutive SFP'!AX31 -> 0
A6: 3.1 | B6: Deposits-Members(BOSA) | C6: ='Evolutive SFP'!B30 -> 112140909 | D6: ='Evolutive SFP'!C30 -> 97747282 | E6: ='Evolutive SFP'!D30 -> 98068546 | F6: ='Evolutive SFP'!E30 -> 98848445 | G6: ='Evolutive SFP'!F30 -> 99652558 | H6: ='Evolutive SFP'!G30 -> 1.0010073e+08 | I6: ='Evolutive SFP'!H30 -> 1.0079304e+08 | J6: ='Evolutive SFP'!I30 -> 1.0131074e+08 | ... AY6: ='Evolutive SFP'!AX30 -> 0
A7: 3.2 | B7: Deposits-Customers(FOSA) | C7: =('Evolutive SFP'!B28+'Evolutive SFP'!B29) -> 16463305 | D7: =('Evolutive SFP'!C28+'Evolutive SFP'!C29) -> 45172689 | E7: =('Evolutive SFP'!D28+'Evolutive SFP'!D29) -> 43388182 | F7: =('Evolutive SFP'!E28+'Evolutive SFP'!E29) -> 41878809 | G7: =('Evolutive SFP'!F28+'Evolutive SFP'!F29) -> 44019734 | H7: =('Evolutive SFP'!G28+'Evolutive SFP'!G29) -> 42339315 | I7: =('Evolutive SFP'!H28+'Evolutive SFP'!H29) -> 40289561 | J7: =('Evolutive SFP'!I28+'Evolutive SFP'!I29) -> 40213381 | ... AY7: =('Evolutive SFP'!AX28+'Evolutive SFP'!AX29) -> 0
A8: 4 | B8: External Borrowing | C8: ='Evolutive SFP'!B37 -> 2291669 | D8: ='Evolutive SFP'!C37 -> 0 | E8: ='Evolutive SFP'!D37 -> 0 | F8: ='Evolutive SFP'!E37 -> 0 | G8: ='Evolutive SFP'!F37 -> 0 | H8: ='Evolutive SFP'!G37 -> 0 | I8: ='Evolutive SFP'!H37 -> 0 | J8: ='Evolutive SFP'!I37 -> 0 | ... AY8: ='Evolutive SFP'!AX37 -> 0
A10: 5 | B10: Share capital and Reserves
A11: 5.1 | B11: Core Capital | C11: =C14-C22-C25 -> 14446887 | D11: =D14-D22-D25 -> 38804360 | E11: =E14-E22-E25 -> 39510671 | F11: =F14-F22-F25 -> 39791400 | G11: =G14-G22-G25 -> 39420109 | H11: =H14-H22-H25 -> 40897621 | I11: =I14-I22-I25 -> 43813729 | J11: =J14-J22-J25 -> 41534837 | ... AY11: =AY14-AY22-AY25 -> 0
A12: 5.2 | B12: Institutional Capital | C12: =C11-C15 -> 3952190 | D12: =D11-D15 -> 18449968 | E12: =E11-E15 -> 19100844 | F12: =F11-F15 -> 19288088 | G12: =G11-G15 -> 18601800 | H12: =H11-H15 -> 19510902 | I12: =I11-I15 -> 22167207 | J12: =J11-J15 -> 19715255 | ... AY12: =AY11-AY15 -> 0
A14: 5.3 | B14: Total Capital | C14: =C15+C16+C17+C18+C19+C20+C21 -> 14919147 | D14: =D15+D16+D17+D18+D19+D20+D21 -> 42126680 | E14: =E15+E16+E17+E18+E19+E20+E21 -> 43730082 | F14: =F15+F16+F17+F18+F19+F20+F21 -> 43113721 | G14: =G15+G16+G17+G18+G19+G20+G21 -> 42742429 | H14: =H15+H16+H17+H18+H19+H20+H21 -> 44219941 | I14: =I15+I16+I17+I18+I19+I20+I21 -> 47136049 | J14: =J15+J16+J17+J18+J19+J20+J21 -> 44857158 | ... AY14: =AY15+AY16+AY17+AY18+AY19+AY20+AY21 -> 0
A15: 5.3.1 | B15: Members Share Capital | C15: ='Evolutive SFP'!B39 -> 10494697 | D15: ='Evolutive SFP'!C39 -> 20354392 | E15: ='Evolutive SFP'!D39 -> 20409827 | F15: ='Evolutive SFP'!E39 -> 20503312 | G15: ='Evolutive SFP'!F39 -> 20818309 | H15: ='Evolutive SFP'!G39 -> 21386718 | I15: ='Evolutive SFP'!H39 -> 21646522 | J15: ='Evolutive SFP'!I39 -> 21819583 | ... AY15: ='Evolutive SFP'!AX39 -> 0
A16: 5.3.2 | B16: Entrance Fees
A17: 5.3.3 | B17: Retained Earnings | C17: ='Evolutive SFP'!B41 -> 351220 | D17: ='Evolutive SFP'!C41 -> 3557811 | E17: ='Evolutive SFP'!D41 -> 15121447 | F17: ='Evolutive SFP'!E41 -> 14903354 | G17: ='Evolutive SFP'!F41 -> 14903354 | H17: ='Evolutive SFP'!G41 -> 14903354 | I17: ='Evolutive SFP'!H41 -> 14903354 | J17: ='Evolutive SFP'!I41 -> 14903354 | ... AY17: ='Evolutive SFP'!AX41 -> 0
A18: 5.3.4 | B18: Appropriation Account | C18: ='Evolutive SFP'!B42 -> 3541956 | D18: ='Evolutive SFP'!C42 -> 11304214 | E18: ='Evolutive SFP'!D42 -> 1999765.2 | F18: ='Evolutive SFP'!E42 -> 796449.7 | G18: ='Evolutive SFP'!F42 -> 110660.8 | H18: ='Evolutive SFP'!G42 -> 1019263.6 | I18: ='Evolutive SFP'!H42 -> 3675568.4 | J18: ='Evolutive SFP'!I42 -> 1223616.2 | ... AY18: ='Evolutive SFP'!AX42 -> 0
A19: 5.3.5 | B19: Statutory Reserves | C19: ='Evolutive SFP'!B43 -> 531274 | D19: ='Evolutive SFP'!C43 -> 6683483 | E19: ='Evolutive SFP'!D43 -> 5972263 | F19: ='Evolutive SFP'!E43 -> 6683825 | G19: ='Evolutive SFP'!F43 -> 6683325 | H19: ='Evolutive SFP'!G43 -> 6683825 | I19: ='Evolutive SFP'!H43 -> 6683825 | J19: ='Evolutive SFP'!I43 -> 6683825 | ... AY19: ='Evolutive SFP'!AX43 -> 0
A20: 5.3.6 | B20: Capital Reserves | C20: =('Evolutive SFP'!B44) -> 0 | D20: =('Evolutive SFP'!C44) -> 226780 | E20: =('Evolutive SFP'!D44) -> 226779.85 | F20: =('Evolutive SFP'!E44) -> 226779.85 | G20: =('Evolutive SFP'!F44) -> 226779.85 | H20: =('Evolutive SFP'!G44) -> 226779.85 | I20: =('Evolutive SFP'!H44) -> 226779.85 | J20: =('Evolutive SFP'!I44) -> 226779.85 | ... AY20: =('Evolutive SFP'!AX44) -> 0
A21: 5.3.7 | B21: Supplementary Capital & reserves | C21: =C22+C23 -> 0 | D21: =D22+D23 -> 0 | E21: =E22+E23 -> 0 | F21: =F22+F23 -> 0 | G21: =G22+G23 -> 0 | H21: =H22+H23 -> 0 | I21: =I22+I23 -> 0 | J21: =J22+J23 -> 0 | ... AY21: =AY22+AY23 -> 0
A22: a | B22: Proposed Dividends | C22: ='Evolutive SFP'!B46 -> 0 | D22: ='Evolutive SFP'!C46 -> 0 | E22: ='Evolutive SFP'!D46 -> 0 | F22: ='Evolutive SFP'!E46 -> 0 | G22: ='Evolutive SFP'!F46 -> 0 | H22: ='Evolutive SFP'!G46 -> 0 | I22: ='Evolutive SFP'!H46 -> 0 | J22: ='Evolutive SFP'!I46 -> 0 | ... AY22: ='Evolutive SFP'!AX46 -> 0
A23: b | B23: Risk Mgt Fund
A25: 6 | B25: Investments | C25: =C26+C27+C28 -> 472260 | D25: =D26+D27+D28 -> 3322320 | E25: =E26+E27+E28 -> 4219411.4 | F25: =F26+F27+F28 -> 3322320.4 | G25: =G26+G27+G28 -> 3322320.4 | H25: =H26+H27+H28 -> 3322320.4 | I25: =I26+I27+I28 -> 3322320.4 | J25: =J26+J27+J28 -> 3322320.4 | ... AY25: =AY26+AY27+AY28 -> 0
A26: 6.1 | B26: Shares in Kusco,CIC,Coop Bank | C26: ='Evolutive SFP'!B13 -> 472260 | D26: ='Evolutive SFP'!C13 -> 154585 | E26: ='Evolutive SFP'!D13 -> 4219411.4 | F26: ='Evolutive SFP'!E13 -> 3322320.4 | G26: ='Evolutive SFP'!F13 -> 3322320.4 | H26: ='Evolutive SFP'!G13 -> 3322320.4 | I26: ='Evolutive SFP'!H13 -> 3322320.4 | J26: ='Evolutive SFP'!I13 -> 3322320.4 | ... AY26: ='Evolutive SFP'!AX13 -> 0
A27: 6.2 | B27: Equity Investments (at cost) | C27: ='Evolutive SFP'!B10 -> 0 | D27: ='Evolutive SFP'!C10 -> 0 | E27: ='Evolutive SFP'!D10 -> 0 | F27: ='Evolutive SFP'!E10 -> 0 | G27: ='Evolutive SFP'!F10 -> 0 | H27: ='Evolutive SFP'!G10 -> 0 | I27: ='Evolutive SFP'!H10 -> 0 | J27: ='Evolutive SFP'!I10 -> 0 | ... AY27: ='Evolutive SFP'!AX10 -> 0
A28: 6.3 | B28: Deposits in KUSCCO CFP | C28: ='Evolutive SFP'!B11 -> 0 | D28: ='Evolutive SFP'!C11 -> 3167735 | E28: ='Evolutive SFP'!D11 -> 0 | F28: ='Evolutive SFP'!E11 -> 0 | G28: ='Evolutive SFP'!F11 -> 0 | H28: ='Evolutive SFP'!G11 -> 0 | I28: ='Evolutive SFP'!H11 -> 0 | J28: ='Evolutive SFP'!I11 -> 0 | ... AY28: ='Evolutive SFP'!AX11 -> 0
A30: 7 | B30: Net Loans & Advances | C30: ='Evolutive SFP'!B14 -> 112905266 | D30: ='Evolutive SFP'!C14 -> 94715902 | E30: ='Evolutive SFP'!D14 -> 99526768 | F30: ='Evolutive SFP'!E14 -> 1.0157231e+08 | G30: ='Evolutive SFP'!F14 -> 1.0014554e+08 | H30: ='Evolutive SFP'!G14 -> 1.0108718e+08 | I30: ='Evolutive SFP'!H14 -> 1.0268952e+08 | J30: ='Evolutive SFP'!I14 -> 1.0076412e+08 | ... AY30: ='Evolutive SFP'!AX14 -> 0
A31: 7.1 | B31: Gross Loans & advances | C31: ='Evolutive SFP'!B15 -> 112905266 | D31: ='Evolutive SFP'!C15 -> 117738087 | E31: ='Evolutive SFP'!D15 -> 1.2341506e+08 | F31: ='Evolutive SFP'!E15 -> 1.2614517e+08 | G31: ='Evolutive SFP'!F15 -> 1.2572372e+08 | H31: ='Evolutive SFP'!G15 -> 1.2647362e+08 | I31: ='Evolutive SFP'!H15 -> 1.2571171e+08 | J31: ='Evolutive SFP'!I15 -> 1.2592833e+08 | ... AY31: ='Evolutive SFP'!AX15 -> 0
A32: 7.2 | B32: Allowance for loan losses | C32: ='Evolutive SFP'!B16 -> 0 | D32: ='Evolutive SFP'!C16 -> 23022185 | E32: ='Evolutive SFP'!D16 -> 23888296 | F32: ='Evolutive SFP'!E16 -> 24572853 | G32: ='Evolutive SFP'!F16 -> 25578182 | H32: ='Evolutive SFP'!G16 -> 25386444 | I32: ='Evolutive SFP'!H16 -> 23022185 | J32: ='Evolutive SFP'!I16 -> 25164216 | ... AY32: ='Evolutive SFP'!AX16 -> 0
A34: 8 | B34: Non-Earning Assets | C34: ='Evolutive SFP'!B21+'Evolutive SFP'!B7 -> 18274979 | D34: ='Evolutive SFP'!C21+'Evolutive SFP'!C7 -> 17296673 | E34: ='Evolutive SFP'!D21+'Evolutive SFP'!D7 -> 16253347 | F34: ='Evolutive SFP'!E21+'Evolutive SFP'!E7 -> 16734448 | G34: ='Evolutive SFP'!F21+'Evolutive SFP'!F7 -> 17150894 | H34: ='Evolutive SFP'!G21+'Evolutive SFP'!G7 -> 17036918 | I34: ='Evolutive SFP'!H21+'Evolutive SFP'!H7 -> 16963760 | J34: ='Evolutive SFP'!I21+'Evolutive SFP'!I7 -> 16080069 | ... AY34: ='Evolutive SFP'!AX21+'Evolutive SFP'!AX7 -> 0
A35: 8.1 | B35: Property and Equipment | C35: ='Evolutive SFP'!B23 -> 4123114 | D35: ='Evolutive SFP'!C23 -> 13159426 | E35: ='Evolutive SFP'!D23 -> 13635196 | F35: ='Evolutive SFP'!E23 -> 13635196 | G35: ='Evolutive SFP'!F23 -> 13660301 | H35: ='Evolutive SFP'!G23 -> 13666801 | I35: ='Evolutive SFP'!H23 -> 13701801 | J35: ='Evolutive SFP'!I23 -> 12851347 | ... AY35: ='Evolutive SFP'!AX23 -> 0
A37: 9 | B37: Turnover | C37: =C38+C39+C40+C41 -> 14599.248 | D37: =D38+D39+D40+D41 -> 24912213 | E37: =E38+E39+E40+E41 -> 3346469.6 | F37: =F38+F39+F40+F41 -> 4855477.2 | G37: =G38+G39+G40+G41 -> 6639.17 | H37: =H38+H39+H40+H41 -> 8837677.4 | I37: =I38+I39+I40+I41 -> 10209983 | J37: =J38+J39+J40+J41 -> 12571337 | ... AY37: =AY38+AY39+AY40+AY41 -> 0
A38: 9.1 | B38: Loan Interest | C38: ='Evolutitve SCI'!B5 -> 11945.435 | D38: ='Evolutitve SCI'!C5 -> 14548967 | E38: ='Evolutitve SCI'!D5 -> 2067244.9 | F38: ='Evolutitve SCI'!E5 -> 3579327.3 | G38: ='Evolutitve SCI'!F5 -> 4523.8 | H38: ='Evolutitve SCI'!G5 -> 5617072 | I38: ='Evolutitve SCI'!H5 -> 6370913.7 | J38: ='Evolutitve SCI'!I5 -> 7966759.5 | ... AY38: ='Evolutitve SCI'!AX5 -> 0
A39: 9.2 | B39: Income from investments | C39: ='Evolutitve SCI'!B7 -> 1743.4416 | D39: ='Evolutitve SCI'!C7 -> 10363246 | E39: ='Evolutitve SCI'!D7 -> 1123994.7 | F39: ='Evolutitve SCI'!E7 -> 1028199.9 | G39: ='Evolutitve SCI'!F7 -> 1806.87 | H39: ='Evolutitve SCI'!G7 -> 2852935.3 | I39: ='Evolutitve SCI'!H7 -> 3425779.1 | J39: ='Evolutitve SCI'!I7 -> 4123807.4 | ... AY39: ='Evolutitve SCI'!AX7 -> 0
A40: 9.3 | B40: Fees & Commissions | C40: ='Evolutitve SCI'!B6 -> 910.371 | D40: ='Evolutitve SCI'!C6 -> 0 | E40: ='Evolutitve SCI'!D6 -> 155230 | F40: ='Evolutitve SCI'!E6 -> 247950 | G40: ='Evolutitve SCI'!F6 -> 308.5 | H40: ='Evolutitve SCI'!G6 -> 367670 | I40: ='Evolutitve SCI'!H6 -> 413290 | J40: ='Evolutitve SCI'!I6 -> 480770 | ... AY40: ='Evolutitve SCI'!AX6 -> 0
A41: 9.4 | B41: Average yield on loans
A43: 10 | B43: Financial and Operating costs | C43: =SUM(C44:C47) -> 11568.465 | D43: =SUM(D44:D47) -> 20030129 | E43: =SUM(E44:E47) -> 434760.35 | F43: =SUM(F44:F47) -> 2455315.5 | G43: =SUM(G44:G47) -> 595087.12 | H43: =SUM(H44:H47) -> 5005006.9 | I43: =SUM(I44:I47) -> 6083862.6 | J43: =SUM(J44:J47) -> 8558515.1 | ... AY43: =SUM(AY44:AY47) -> 0
A44: 10.1 | B44: Interest expense on deposits | C44: ='Evolutitve SCI'!B13+'Evolutitve SCI'!B16 -> 185.36 | D44: ='Evolutitve SCI'!C13+'Evolutitve SCI'!C16 -> 1954946 | E44: ='Evolutitve SCI'!D13+'Evolutitve SCI'!D16 -> 0 | F44: ='Evolutitve SCI'!E13+'Evolutitve SCI'!E16 -> 0 | G44: ='Evolutitve SCI'!F13+'Evolutitve SCI'!F16 -> 0 | H44: ='Evolutitve SCI'!G13+'Evolutitve SCI'!G16 -> 0 | I44: ='Evolutitve SCI'!H13+'Evolutitve SCI'!H16 -> 0 | J44: ='Evolutitve SCI'!I13+'Evolutitve SCI'!I16 -> 0 | ... AY44: ='Evolutitve SCI'!AX13+'Evolutitve SCI'!AX16 -> 0
A45: 10.2 | B45: Dividend expense on share capital | C45: ='Evolutitve SCI'!B15 -> 0 | D45: ='Evolutitve SCI'!C15 -> 0 | E45: ='Evolutitve SCI'!D15 -> 0 | F45: ='Evolutitve SCI'!E15 -> 0 | G45: ='Evolutitve SCI'!F15 -> 0 | H45: ='Evolutitve SCI'!G15 -> 0 | I45: ='Evolutitve SCI'!H15 -> 0 | J45: ='Evolutitve SCI'!I15 -> 0 | ... AY45: ='Evolutitve SCI'!AX15 -> 0
A46: 10.3 | B46: Interest expense on borrowed funds | C46: ='Evolutitve SCI'!B14 -> 363.7247 | D46: ='Evolutitve SCI'!C14 -> 0 | E46: ='Evolutitve SCI'!D14 -> 0 | F46: ='Evolutitve SCI'!E14 -> 0 | G46: ='Evolutitve SCI'!F14 -> 0 | H46: ='Evolutitve SCI'!G14 -> 0 | I46: ='Evolutitve SCI'!H14 -> 0 | J46: ='Evolutitve SCI'!I14 -> 0 | ... AY46: ='Evolutitve SCI'!AX14 -> 0
A47: 10.4 | B47: Opperating expenses | C47: ='Evolutitve SCI'!B23 -> 11019.38 | D47: ='Evolutitve SCI'!C23 -> 18075183 | E47: ='Evolutitve SCI'!D23 -> 434760.35 | F47: ='Evolutitve SCI'!E23 -> 2455315.5 | G47: ='Evolutitve SCI'!F23 -> 595087.12 | H47: ='Evolutitve SCI'!G23 -> 5005006.9 | I47: ='Evolutitve SCI'!H23 -> 6083862.6 | J47: ='Evolutitve SCI'!I23 -> 8558515.1 | ... AY47: ='Evolutitve SCI'!AX23 -> 0

Sheet CAELS Rating
A2: CAELS RATINGS KINGDOM SACCO
A3: FINANCIAL SOUNDNESS INDICATORS | B3: Prude. Std | C3: 2010 Audited | D3: 2021 Audited | E3: 44197.12 | F3: 44229 | G3: 44258 | H3: 44290 | I3: 44321 | J3: 44353 | K3: 44384 | L3: 44416 | M3: 44448 | N3: 44479 | O3: 44511 | P3: 44542 | Q3: Audited 2021 | R3: 44562 | S3: 44593 | T3: 44621 | U3: 44652 | V3: 44682 | W3: 44713 | X3: 44743 | Y3: 44774 | Z3: 44805 | AA3: 44835 | AB3: 44866 | AC3: 44896 | AD3: 44927 | AE3: 44958 | AF3: 44986 | AG3: 45017 | AH3: 45047 | AI3: 45078 | AJ3: 45108 | AK3: 45139 | AL3: 45170 | AM3: 45200 | AN3: 45231 | AO3: 45261 | AP3: 45292 | AQ3: 45323 | AR3: 45352 | AS3: 45383 | AT3: 45413 | AU3: 45444 | AV3: 45474 | AW3: 45505 | AX3: 45536 | AY3: 45566 | AZ3: 45597 | BA3: 45627 | BB3: 45658 | BC3: 45689 | BD3: 45717 | BE3: 45748 | BF3: 45778 | BG3: 45809 | BH3: 45839 | BI3: 45870 | BJ3: 45901 | BK3: 45931 | BL3: 45962 | BM3: 45992 | BN3: 46023 | BO3: 46054 | BP3: 46082 | BQ3: 46113 | BR3: 46143 | BS3: 46174 | BT3: 46204 | BU3: 46235 | BV3: 46266 | BW3: 46296 | BX3: 46327 | BY3: 46357
A4: CAPITAL
A5: CORE CAPITAL | B5: ≥ Ksh.10M | C5: =IF(CAELS!D3>10,"1","5") -> 1 | D5: =IF(CAELS!E3>10,"1","5") -> 1 | E5: =IF(CAELS!F3>10,"1","5") -> 1 | F5: =IF(CAELS!G3>10,"1","5") -> 1 | G5: =IF(CAELS!H3>10,"1","5") -> 1 | H5: =IF(CAELS!I3>10,"1","5") -> 1 | I5: =IF(CAELS!J3>10,"1","5") -> 1 | J5: =IF(CAELS!K3>10,"1","5") -> 1 | ... BY5: =IF(CAELS!BZ3>10,"1","5") -> 5
A6: CCA | B6: ≥ 10% | C6: =IF(CAELS!D4>20%,"1",IF(CAELS!D4>15%,"2",IF(CAELS!D4>12%,"3",IF(CAELS!D4>10%,"4","5")))) -> 4 | D6: =IF(CAELS!E4>20%,"1",IF(CAELS!E4>15%,"2",IF(CAELS!E4>12%,"3",IF(CAELS!E4>10%,"4","5")))) -> 1 | E6: =IF(CAELS!F4>20%,"1",IF(CAELS!F4>15%,"2",IF(CAELS!F4>12%,"3",IF(CAELS!F4>10%,"4","5")))) -> 1 | F6: =IF(CAELS!G4>20%,"1",IF(CAELS!G4>15%,"2",IF(CAELS!G4>12%,"3",IF(CAELS!G4>10%,"4","5")))) -> 1 | G6: =IF(CAELS!H4>20%,"1",IF(CAELS!H4>15%,"2",IF(CAELS!H4>12%,"3",IF(CAELS!H4>10%,"4","5")))) -> 1 | H6: =IF(CAELS!I4>20%,"1",IF(CAELS!I4>15%,"2",IF(CAELS!I4>12%,"3",IF(CAELS!I4>10%,"4","5")))) -> 1 | I6: =IF(CAELS!J4>20%,"1",IF(CAELS!J4>15%,"2",IF(CAELS!J4>12%,"3",IF(CAELS!J4>10%,"4","5")))) -> 1 | J6: =IF(CAELS!K4>20%,"1",IF(CAELS!K4>15%,"2",IF(CAELS!K4>12%,"3",IF(CAELS!K4>10%,"4","5")))) -> 1 | ... BY6: =IF(CAELS!BZ4>20%,"1",IF(CAELS!BZ4>15%,"2",IF(CAELS!BZ4>12%,"3",IF(CAELS!BZ4>10%,"4","5")))) -> 5
A7: ICA | B7: ≥ 8% | C7: =IF(CAELS!D6>15%,"1",IF(CAELS!D6>12%,"2",IF(CAELS!D6>10%,"3",IF(CAELS!D6>8,"4","5")))) -> 5 | D7: =IF(CAELS!E6>15%,"1",IF(CAELS!E6>12%,"2",IF(CAELS!E6>10%,"3",IF(CAELS!E6>8,"4","5")))) -> 3 | E7: =IF(CAELS!F6>15%,"1",IF(CAELS!F6>12%,"2",IF(CAELS!F6>10%,"3",IF(CAELS!F6>8,"4","5")))) -> 3 | F7: =IF(CAELS!G6>15%,"1",IF(CAELS!G6>12%,"2",IF(CAELS!G6>10%,"3",IF(CAELS!G6>8,"4","5")))) -> 3 | G7: =IF(CAELS!H6>15%,"1",IF(CAELS!H6>12%,"2",IF(CAELS!H6>10%,"3",IF(CAELS!H6>8,"4","5")))) -> 3 | H7: =IF(CAELS!I6>15%,"1",IF(CAELS!I6>12%,"2",IF(CAELS!I6>10%,"3",IF(CAELS!I6>8,"4","5")))) -> 3 | I7: =IF(CAELS!J6>15%,"1",IF(CAELS!J6>12%,"2",IF(CAELS!J6>10%,"3",IF(CAELS!J6>8,"4","5")))) -> 2 | J7: =IF(CAELS!K6>15%,"1",IF(CAELS!K6>12%,"2",IF(CAELS!K6>10%,"3",IF(CAELS!K6>8,"4","5")))) -> 2 | ... BY7: =IF(CAELS!BZ6>15%,"1",IF(CAELS!BZ6>12%,"2",IF(CAELS!BZ6>10%,"3",IF(CAELS!BZ6>8,"4","5")))) -> 5
A8: CCD | B8: ≥ 8% | C8: =IF(CAELS!D5>20%,"1",IF(CAELS!D5>15%,"2",IF(CAELS!D5>12%,"3",IF(CAELS!D5>10%,"4","5")))) -> 4 | D8: =IF(CAELS!E5>20%,"1",IF(CAELS!E5>15%,"2",IF(CAELS!E5>12%,"3",IF(CAELS!E5>10%,"4","5")))) -> 1 | E8: =IF(CAELS!F5>20%,"1",IF(CAELS!F5>15%,"2",IF(CAELS!F5>12%,"3",IF(CAELS!F5>10%,"4","5")))) -> 1 | F8: =IF(CAELS!G5>20%,"1",IF(CAELS!G5>15%,"2",IF(CAELS!G5>12%,"3",IF(CAELS!G5>10%,"4","5")))) -> 1 | G8: =IF(CAELS!H5>20%,"1",IF(CAELS!H5>15%,"2",IF(CAELS!H5>12%,"3",IF(CAELS!H5>10%,"4","5")))) -> 1 | H8: =IF(CAELS!I5>20%,"1",IF(CAELS!I5>15%,"2",IF(CAELS!I5>12%,"3",IF(CAELS!I5>10%,"4","5")))) -> 1 | I8: =IF(CAELS!J5>20%,"1",IF(CAELS!J5>15%,"2",IF(CAELS!J5>12%,"3",IF(CAELS!J5>10%,"4","5")))) -> 1 | J8: =IF(CAELS!K5>20%,"1",IF(CAELS!K5>15%,"2",IF(CAELS!K5>12%,"3",IF(CAELS!K5>10%,"4","5")))) -> 1 | ... BY8: =IF(CAELS!BZ5>20%,"1",IF(CAELS!BZ5>15%,"2",IF(CAELS!BZ5>12%,"3",IF(CAELS!BZ5>10%,"4","5")))) -> 5
C9: =(C5+C6+C7+C8)/4 -> 3.5 | D9: =(D5+D6+D7+D8)/4 -> 1.5 | E9: =(E5+E6+E7+E8)/4 -> 1.5 | F9: =(F5+F6+F7+F8)/4 -> 1.5 | G9: =(G5+G6+G7+G8)/4 -> 1.5 | H9: =(H5+H6+H7+H8)/4 -> 1.5 | I9: =(I5+I6+I7+I8)/4 -> 1.25 | J9: =(J5+J6+J7+J8)/4 -> 1.25 | ... BY9: =(BY5+BY6+BY7+BY8)/4 -> 5
A10: Asset Quality
A11: NPL | B11: ≤ 6% | L11: =IF(CAELS!M8<4%,"1",IF(CAELS!M8<8%,"2",IF(CAELS!M8<12%,"3",IF(CAELS!M8<15%,"4","5")))) -> 1 | O11: =IF(CAELS!P8<4%,"1",IF(CAELS!P8<8%,"2",IF(CAELS!P8<12%,"3",IF(CAELS!P8<15%,"4","5")))) -> 1 | R11: =IF(CAELS!S8<4%,"1",IF(CAELS!S8<8%,"2",IF(CAELS!S8<12%,"3",IF(CAELS!S8<15%,"4","5")))) -> 1 | U11: =IF(CAELS!V8<4%,"1",IF(CAELS!V8<8%,"2",IF(CAELS!V8<12%,"3",IF(CAELS!V8<15%,"4","5")))) -> 1 | V11: =IF(CAELS!W8<4%,"1",IF(CAELS!W8<8%,"2",IF(CAELS!W8<12%,"3",IF(CAELS!W8<15%,"4","5")))) -> 1 | W11: =IF(CAELS!X8<4%,"1",IF(CAELS!X8<8%,"2",IF(CAELS!X8<12%,"3",IF(CAELS!X8<15%,"4","5")))) -> 5 | X11: =IF(CAELS!Y8<4%,"1",IF(CAELS!Y8<8%,"2",IF(CAELS!Y8<12%,"3",IF(CAELS!Y8<15%,"4","5")))) -> 1 | Y11: =IF(CAELS!Z8<4%,"1",IF(CAELS!Z8<8%,"2",IF(CAELS!Z8<12%,"3",IF(CAELS!Z8<15%,"4","5")))) -> 1 | Z11: =IF(CAELS!AA8<4%,"1",IF(CAELS!AA8<8%,"2",IF(CAELS!AA8<12%,"3",IF(CAELS!AA8<15%,"4","5")))) -> 5 | AA11: =IF(CAELS!AB8<4%,"1",IF(CAELS!AB8<8%,"2",IF(CAELS!AB8<12%,"3",IF(CAELS!AB8<15%,"4","5")))) -> 1 | AB11: =IF(CAELS!AC8<4%,"1",IF(CAELS!AC8<8%,"2",IF(CAELS!AC8<12%,"3",IF(CAELS!AC8<15%,"4","5")))) -> 1 | ... BY11: =IF(CAELS!BZ8<4%,"1",IF(CAELS!BZ8<8%,"2",IF(CAELS!BZ8<12%,"3",IF(CAELS!BZ8<15%,"4","5")))) -> 1
C12: =C11 -> 0 | D12: =D11 -> 0 | E12: =E11 -> 0 | F12: =F11 -> 0 | G12: =G11 -> 0 | H12: =H11 -> 0 | I12: =I11 -> 0 | J12: =J11 -> 0 | ... BY12: =BY11 -> 1
A13: Earnings
A14: ROA | D14: =IF(CAELS!E9>6%,"1",IF(CAELS!E9>4%,"2",IF(CAELS!E9>2%,"3",IF(CAELS!E9>0%,"4","5")))) -> 3 | E14: =IF(CAELS!F9>6%,"1",IF(CAELS!F9>4%,"2",IF(CAELS!F9>2%,"3",IF(CAELS!F9>0%,"4","5")))) -> 4 | F14: =IF(CAELS!G9>6%,"1",IF(CAELS!G9>4%,"2",IF(CAELS!G9>2%,"3",IF(CAELS!G9>0%,"4","5")))) -> 4 | G14: =IF(CAELS!H9>6%,"1",IF(CAELS!H9>4%,"2",IF(CAELS!H9>2%,"3",IF(CAELS!H9>0%,"4","5")))) -> 5 | H14: =IF(CAELS!I9>6%,"1",IF(CAELS!I9>4%,"2",IF(CAELS!I9>2%,"3",IF(CAELS!I9>0%,"4","5")))) -> 4 | I14: =IF(CAELS!J9>6%,"1",IF(CAELS!J9>4%,"2",IF(CAELS!J9>2%,"3",IF(CAELS!J9>0%,"4","5")))) -> 4 | J14: =IF(CAELS!K9>6%,"1",IF(CAELS!K9>4%,"2",IF(CAELS!K9>2%,"3",IF(CAELS!K9>0%,"4","5")))) -> 4 | K14: =IF(CAELS!L9>6%,"1",IF(CAELS!L9>4%,"2",IF(CAELS!L9>2%,"3",IF(CAELS!L9>0%,"4","5")))) -> 4 | ... BY14: =IF(CAELS!BZ9>6%,"1",IF(CAELS!BZ9>4%,"2",IF(CAELS!BZ9>2%,"3",IF(CAELS!BZ9>0%,"4","5")))) -> 5
A15: CIR | C15: =IF(CAELS!D10<60%,"1",IF(CAELS!D10<70%,"2",IF(CAELS!D10<80%,"3",IF(CAELS!D10<90%,"4","5")))) -> 3 | D15: =IF(CAELS!E10<60%,"1",IF(CAELS!E10<70%,"2",IF(CAELS!E10<80%,"3",IF(CAELS!E10<90%,"4","5")))) -> 3 | E15: =IF(CAELS!F10<60%,"1",IF(CAELS!F10<70%,"2",IF(CAELS!F10<80%,"3",IF(CAELS!F10<90%,"4","5")))) -> 1 | F15: =IF(CAELS!G10<60%,"1",IF(CAELS!G10<70%,"2",IF(CAELS!G10<80%,"3",IF(CAELS!G10<90%,"4","5")))) -> 1 | G15: =IF(CAELS!H10<60%,"1",IF(CAELS!H10<70%,"2",IF(CAELS!H10<80%,"3",IF(CAELS!H10<90%,"4","5")))) -> 5 | H15: =IF(CAELS!I10<60%,"1",IF(CAELS!I10<70%,"2",IF(CAELS!I10<80%,"3",IF(CAELS!I10<90%,"4","5")))) -> 1 | I15: =IF(CAELS!J10<60%,"1",IF(CAELS!J10<70%,"2",IF(CAELS!J10<80%,"3",IF(CAELS!J10<90%,"4","5")))) -> 2 | J15: =IF(CAELS!K10<60%,"1",IF(CAELS!K10<70%,"2",IF(CAELS!K10<80%,"3",IF(CAELS!K10<90%,"4","5")))) -> 2 | ... BY15: =IF(CAELS!BZ10<60%,"1",IF(CAELS!BZ10<70%,"2",IF(CAELS!BZ10<80%,"3",IF(CAELS!BZ10<90%,"4","5")))) -> 1
A16: OER | C16: =IF(CAELS!D11<4%,"1",IF(CAELS!D11<6%,"2",IF(CAELS!D11<8%,"3",IF(CAELS!D11<10%,"4","5")))) -> 1 | D16: =IF(CAELS!E11<4%,"1",IF(CAELS!E11<6%,"2",IF(CAELS!E11<8%,"3",IF(CAELS!E11<10%,"4","5")))) -> 5 | E16: =IF(CAELS!F11<4%,"1",IF(CAELS!F11<6%,"2",IF(CAELS!F11<8%,"3",IF(CAELS!F11<10%,"4","5")))) -> 1 | F16: =IF(CAELS!G11<4%,"1",IF(CAELS!G11<6%,"2",IF(CAELS!G11<8%,"3",IF(CAELS!G11<10%,"4","5")))) -> 1 | G16: =IF(CAELS!H11<4%,"1",IF(CAELS!H11<6%,"2",IF(CAELS!H11<8%,"3",IF(CAELS!H11<10%,"4","5")))) -> 1 | H16: =IF(CAELS!I11<4%,"1",IF(CAELS!I11<6%,"2",IF(CAELS!I11<8%,"3",IF(CAELS!I11<10%,"4","5")))) -> 1 | I16: =IF(CAELS!J11<4%,"1",IF(CAELS!J11<6%,"2",IF(CAELS!J11<8%,"3",IF(CAELS!J11<10%,"4","5")))) -> 1 | J16: =IF(CAELS!K11<4%,"1",IF(CAELS!K11<6%,"2",IF(CAELS!K11<8%,"3",IF(CAELS!K11<10%,"4","5")))) -> 2 | ... BY16: =IF(CAELS!BZ11<4%,"1",IF(CAELS!BZ11<6%,"2",IF(CAELS!BZ11<8%,"3",IF(CAELS!BZ11<10%,"4","5")))) -> 1
C17: =(C14+C15+C16)/3 -> 1.3333333 | D17: =(D14+D15+D16)/3 -> 3.6666667 | E17: =(E14+E15+E16)/3 -> 2 | F17: =(F14+F15+F16)/3 -> 2 | G17: =(G14+G15+G16)/3 -> 3.6666667 | H17: =(H14+H15+H16)/3 -> 2 | I17: =(I14+I15+I16)/3 -> 2.3333333 | J17: =(J14+J15+J16)/3 -> 2.6666667 | ... BY17: =(BY14+BY15+BY16)/3 -> 2.3333333
A18: LIQUIDITY
A19: MIN LIQ | B19: 0.15 | C19: =IF(CAELS!D12>30%,"1",IF(CAELS!D12>25%,"2",IF(CAELS!D12>20%,"3",IF(CAELS!D12>15%,"4","5")))) -> 1 | D19: =IF(CAELS!E12>30%,"1",IF(CAELS!E12>25%,"2",IF(CAELS!E12>20%,"3",IF(CAELS!E12>15%,"4","5")))) -> 1 | E19: =IF(CAELS!F12>30%,"1",IF(CAELS!F12>25%,"2",IF(CAELS!F12>20%,"3",IF(CAELS!F12>15%,"4","5")))) -> 1 | F19: =IF(CAELS!G12>30%,"1",IF(CAELS!G12>25%,"2",IF(CAELS!G12>20%,"3",IF(CAELS!G12>15%,"4","5")))) -> 1 | G19: =IF(CAELS!H12>30%,"1",IF(CAELS!H12>25%,"2",IF(CAELS!H12>20%,"3",IF(CAELS!H12>15%,"4","5")))) -> 1 | H19: =IF(CAELS!I12>30%,"1",IF(CAELS!I12>25%,"2",IF(CAELS!I12>20%,"3",IF(CAELS!I12>15%,"4","5")))) -> 1 | I19: =IF(CAELS!J12>30%,"1",IF(CAELS!J12>25%,"2",IF(CAELS!J12>20%,"3",IF(CAELS!J12>15%,"4","5")))) -> 1 | J19: =IF(CAELS!K12>30%,"1",IF(CAELS!K12>25%,"2",IF(CAELS!K12>20%,"3",IF(CAELS!K12>15%,"4","5")))) -> 1 | ... BY19: =IF(CAELS!BZ12>30%,"1",IF(CAELS!BZ12>25%,"2",IF(CAELS!BZ12>20%,"3",IF(CAELS!BZ12>15%,"4","5")))) -> 5
A20: TECH LIQ | C20: =IF(CAELS!D13>30%,"1",IF(CAELS!D13>25%,"2",IF(CAELS!D13>20%,"3",IF(CAELS!D13>15%,"4","5")))) -> 5 | D20: =IF(CAELS!E13>30%,"1",IF(CAELS!E13>25%,"2",IF(CAELS!E13>20%,"3",IF(CAELS!E13>15%,"4","5")))) -> 1 | E20: =IF(CAELS!F13>30%,"1",IF(CAELS!F13>25%,"2",IF(CAELS!F13>20%,"3",IF(CAELS!F13>15%,"4","5")))) -> 1 | F20: =IF(CAELS!G13>30%,"1",IF(CAELS!G13>25%,"2",IF(CAELS!G13>20%,"3",IF(CAELS!G13>15%,"4","5")))) -> 1 | G20: =IF(CAELS!H13>30%,"1",IF(CAELS!H13>25%,"2",IF(CAELS!H13>20%,"3",IF(CAELS!H13>15%,"4","5")))) -> 1 | H20: =IF(CAELS!I13>30%,"1",IF(CAELS!I13>25%,"2",IF(CAELS!I13>20%,"3",IF(CAELS!I13>15%,"4","5")))) -> 1 | I20: =IF(CAELS!J13>30%,"1",IF(CAELS!J13>25%,"2",IF(CAELS!J13>20%,"3",IF(CAELS!J13>15%,"4","5")))) -> 1 | J20: =IF(CAELS!K13>30%,"1",IF(CAELS!K13>25%,"2",IF(CAELS!K13>20%,"3",IF(CAELS!K13>15%,"4","5")))) -> 1 | ... BY20: =IF(CAELS!BZ13>30%,"1",IF(CAELS!BZ13>25%,"2",IF(CAELS!BZ13>20%,"3",IF(CAELS!BZ13>15%,"4","5")))) -> 5
A21: EB | B21: ≤ 25% | C21: =IF(CAELS!D14<15%,"1",IF(CAELS!D14<18%,"2",IF(CAELS!D14<22%,"3",IF(CAELS!D14<25%,"4","5")))) -> 1 | D21: =IF(CAELS!E14<15%,"1",IF(CAELS!E14<18%,"2",IF(CAELS!E14<22%,"3",IF(CAELS!E14<25%,"4","5")))) -> 1 | E21: =IF(CAELS!F14<15%,"1",IF(CAELS!F14<18%,"2",IF(CAELS!F14<22%,"3",IF(CAELS!F14<25%,"4","5")))) -> 1 | F21: =IF(CAELS!G14<15%,"1",IF(CAELS!G14<18%,"2",IF(CAELS!G14<22%,"3",IF(CAELS!G14<25%,"4","5")))) -> 1 | G21: =IF(CAELS!H14<15%,"1",IF(CAELS!H14<18%,"2",IF(CAELS!H14<22%,"3",IF(CAELS!H14<25%,"4","5")))) -> 1 | H21: =IF(CAELS!I14<15%,"1",IF(CAELS!I14<18%,"2",IF(CAELS!I14<22%,"3",IF(CAELS!I14<25%,"4","5")))) -> 1 | I21: =IF(CAELS!J14<15%,"1",IF(CAELS!J14<18%,"2",IF(CAELS!J14<22%,"3",IF(CAELS!J14<25%,"4","5")))) -> 1 | J21: =IF(CAELS!K14<15%,"1",IF(CAELS!K14<18%,"2",IF(CAELS!K14<22%,"3",IF(CAELS!K14<25%,"4","5")))) -> 1 | ... BY21: =IF(CAELS!BZ14<15%,"1",IF(CAELS!BZ14<18%,"2",IF(CAELS!BZ14<22%,"3",IF(CAELS!BZ14<25%,"4","5")))) -> 1
A22: LIQ/TA | C22: =IF(CAELS!D15>15%,"1",IF(CAELS!D15>12%,"2",IF(CAELS!D15>9%,"3",IF(CAELS!D15>6%,"4","5")))) -> 2 | D22: =IF(CAELS!E15>15%,"1",IF(CAELS!E15>12%,"2",IF(CAELS!E15>9%,"3",IF(CAELS!E15>6%,"4","5")))) -> 1 | E22: =IF(CAELS!F15>15%,"1",IF(CAELS!F15>12%,"2",IF(CAELS!F15>9%,"3",IF(CAELS!F15>6%,"4","5")))) -> 1 | F22: =IF(CAELS!G15>15%,"1",IF(CAELS!G15>12%,"2",IF(CAELS!G15>9%,"3",IF(CAELS!G15>6%,"4","5")))) -> 1 | G22: =IF(CAELS!H15>15%,"1",IF(CAELS!H15>12%,"2",IF(CAELS!H15>9%,"3",IF(CAELS!H15>6%,"4","5")))) -> 1 | H22: =IF(CAELS!I15>15%,"1",IF(CAELS!I15>12%,"2",IF(CAELS!I15>9%,"3",IF(CAELS!I15>6%,"4","5")))) -> 1 | I22: =IF(CAELS!J15>15%,"1",IF(CAELS!J15>12%,"2",IF(CAELS!J15>9%,"3",IF(CAELS!J15>6%,"4","5")))) -> 1 | J22: =IF(CAELS!K15>15%,"1",IF(CAELS!K15>12%,"2",IF(CAELS!K15>9%,"3",IF(CAELS!K15>6%,"4","5")))) -> 1 | ... BY22: =IF(CAELS!BZ15>15%,"1",IF(CAELS!BZ15>12%,"2",IF(CAELS!BZ15>9%,"3",IF(CAELS!BZ15>6%,"4","5")))) -> 5
C23: =(C19+C20+C21+C22)/4 -> 2.25 | D23: =(D19+D20+D21+D22)/4 -> 1 | E23: =(E19+E20+E21+E22)/4 -> 1 | F23: =(F19+F20+F21+F22)/4 -> 1 | G23: =(G19+G20+G21+G22)/4 -> 1 | H23: =(H19+H20+H21+H22)/4 -> 1 | I23: =(I19+I20+I21+I22)/4 -> 1 | J23: =(J19+J20+J21+J22)/4 -> 1 | ... BY23: =(BY19+BY20+BY21+BY22)/4 -> 4
A24: STRUCTURE
A25: NEA | B25: ≤ 10% | C25: =IF(CAELS!D16<6%,"1",IF(CAELS!D16<7%,"2",IF(CAELS!D16<8%,"3",IF(CAELS!D16<10%,"4","5")))) -> 5 | D25: =IF(CAELS!E16<6%,"1",IF(CAELS!E16<7%,"2",IF(CAELS!E16<8%,"3",IF(CAELS!E16<10%,"4","5")))) -> 4 | E25: =IF(CAELS!F16<6%,"1",IF(CAELS!F16<7%,"2",IF(CAELS!F16<8%,"3",IF(CAELS!F16<10%,"4","5")))) -> 4 | F25: =IF(CAELS!G16<6%,"1",IF(CAELS!G16<7%,"2",IF(CAELS!G16<8%,"3",IF(CAELS!G16<10%,"4","5")))) -> 4 | G25: =IF(CAELS!H16<6%,"1",IF(CAELS!H16<7%,"2",IF(CAELS!H16<8%,"3",IF(CAELS!H16<10%,"4","5")))) -> 4 | H25: =IF(CAELS!I16<6%,"1",IF(CAELS!I16<7%,"2",IF(CAELS!I16<8%,"3",IF(CAELS!I16<10%,"4","5")))) -> 4 | I25: =IF(CAELS!J16<6%,"1",IF(CAELS!J16<7%,"2",IF(CAELS!J16<8%,"3",IF(CAELS!J16<10%,"4","5")))) -> 4 | J25: =IF(CAELS!K16<6%,"1",IF(CAELS!K16<7%,"2",IF(CAELS!K16<8%,"3",IF(CAELS!K16<10%,"4","5")))) -> 4 | ... BY25: =IF(CAELS!BZ16<6%,"1",IF(CAELS!BZ16<7%,"2",IF(CAELS!BZ16<8%,"3",IF(CAELS!BZ16<10%,"4","5")))) -> 1
A26: LB | B26: ≤ 5% | C26: =IF(CAELS!D17<2%,"1",IF(CAELS!D17<3%,"2",IF(CAELS!D17<4%,"3",IF(CAELS!D17<5%,"4","5")))) -> 3 | D26: =IF(CAELS!E17<2%,"1",IF(CAELS!E17<3%,"2",IF(CAELS!E17<4%,"3",IF(CAELS!E17<5%,"4","5")))) -> 5 | E26: =IF(CAELS!F17<2%,"1",IF(CAELS!F17<3%,"2",IF(CAELS!F17<4%,"3",IF(CAELS!F17<5%,"4","5")))) -> 5 | F26: =IF(CAELS!G17<2%,"1",IF(CAELS!G17<3%,"2",IF(CAELS!G17<4%,"3",IF(CAELS!G17<5%,"4","5")))) -> 5 | G26: =IF(CAELS!H17<2%,"1",IF(CAELS!H17<3%,"2",IF(CAELS!H17<4%,"3",IF(CAELS!H17<5%,"4","5")))) -> 5 | H26: =IF(CAELS!I17<2%,"1",IF(CAELS!I17<3%,"2",IF(CAELS!I17<4%,"3",IF(CAELS!I17<5%,"4","5")))) -> 5 | I26: =IF(CAELS!J17<2%,"1",IF(CAELS!J17<3%,"2",IF(CAELS!J17<4%,"3",IF(CAELS!J17<5%,"4","5")))) -> 5 | J26: =IF(CAELS!K17<2%,"1",IF(CAELS!K17<3%,"2",IF(CAELS!K17<4%,"3",IF(CAELS!K17<5%,"4","5")))) -> 5 | ... BY26: =IF(CAELS!BZ17<2%,"1",IF(CAELS!BZ17<3%,"2",IF(CAELS!BZ17<4%,"3",IF(CAELS!BZ17<5%,"4","5")))) -> 1
A27: FITD | B27: ≤ 5% | C27: =IF(CAELS!D18<2%,"1",IF(CAELS!D18<3%,"2",IF(CAELS!D18<4%,"3",IF(CAELS!D18<5%,"4","5")))) -> 1 | D27: =IF(CAELS!E18<2%,"1",IF(CAELS!E18<3%,"2",IF(CAELS!E18<4%,"3",IF(CAELS!E18<5%,"4","5")))) -> 1 | E27: =IF(CAELS!F18<2%,"1",IF(CAELS!F18<3%,"2",IF(CAELS!F18<4%,"3",IF(CAELS!F18<5%,"4","5")))) -> 2 | F27: =IF(CAELS!G18<2%,"1",IF(CAELS!G18<3%,"2",IF(CAELS!G18<4%,"3",IF(CAELS!G18<5%,"4","5")))) -> 2 | G27: =IF(CAELS!H18<2%,"1",IF(CAELS!H18<3%,"2",IF(CAELS!H18<4%,"3",IF(CAELS!H18<5%,"4","5")))) -> 2 | H27: =IF(CAELS!I18<2%,"1",IF(CAELS!I18<3%,"2",IF(CAELS!I18<4%,"3",IF(CAELS!I18<5%,"4","5")))) -> 2 | I27: =IF(CAELS!J18<2%,"1",IF(CAELS!J18<3%,"2",IF(CAELS!J18<4%,"3",IF(CAELS!J18<5%,"4","5")))) -> 2 | J27: =IF(CAELS!K18<2%,"1",IF(CAELS!K18<3%,"2",IF(CAELS!K18<4%,"3",IF(CAELS!K18<5%,"4","5")))) -> 2 | ... BY27: =IF(CAELS!BZ18<2%,"1",IF(CAELS!BZ18<3%,"2",IF(CAELS!BZ18<4%,"3",IF(CAELS!BZ18<5%,"4","5")))) -> 1
A28: FICC | B28: ≤ 40% | C28: =IF(CAELS!D19<20%,"1",IF(CAELS!D19<25%,"2",IF(CAELS!D19<30%,"3",IF(CAELS!D19<40%,"4","5")))) -> 1 | D28: =IF(CAELS!E19<20%,"1",IF(CAELS!E19<25%,"2",IF(CAELS!E19<30%,"3",IF(CAELS!E19<40%,"4","5")))) -> 1 | E28: =IF(CAELS!F19<20%,"1",IF(CAELS!F19<25%,"2",IF(CAELS!F19<30%,"3",IF(CAELS!F19<40%,"4","5")))) -> 1 | F28: =IF(CAELS!G19<20%,"1",IF(CAELS!G19<25%,"2",IF(CAELS!G19<30%,"3",IF(CAELS!G19<40%,"4","5")))) -> 1 | G28: =IF(CAELS!H19<20%,"1",IF(CAELS!H19<25%,"2",IF(CAELS!H19<30%,"3",IF(CAELS!H19<40%,"4","5")))) -> 1 | H28: =IF(CAELS!I19<20%,"1",IF(CAELS!I19<25%,"2",IF(CAELS!I19<30%,"3",IF(CAELS!I19<40%,"4","5")))) -> 1 | I28: =IF(CAELS!J19<20%,"1",IF(CAELS!J19<25%,"2",IF(CAELS!J19<30%,"3",IF(CAELS!J19<40%,"4","5")))) -> 1 | J28: =IF(CAELS!K19<20%,"1",IF(CAELS!K19<25%,"2",IF(CAELS!K19<30%,"3",IF(CAELS!K19<40%,"4","5")))) -> 1 | ... BY28: =IF(CAELS!BZ19<20%,"1",IF(CAELS!BZ19<25%,"2",IF(CAELS!BZ19<30%,"3",IF(CAELS!BZ19<40%,"4","5")))) -> 1
C29: =(C25+C26+C27+C28)/4 -> 2.5 | D29: =(D25+D26+D27+D28)/4 -> 2.75 | E29: =(E25+E26+E27+E28)/4 -> 3 | F29: =(F25+F26+F27+F28)/4 -> 3 | G29: =(G25+G26+G27+G28)/4 -> 3 | H29: =(H25+H26+H27+H28)/4 -> 3 | I29: =(I25+I26+I27+I28)/4 -> 3 | J29: =(J25+J26+J27+J28)/4 -> 3 | ... BY29: =(BY25+BY26+BY27+BY28)/4 -> 1
A30: FINAL RATING | C30: =(C9+C12+C17+C23)/4 -> 1.7708333 | D30: =(D9+D12+D17+D23)/4 -> 1.5416667 | E30: =(E9+E12+E17+E23)/4 -> 1.125 | F30: =(F9+F12+F17+F23)/4 -> 1.125 | G30: =(G9+G12+G17+G23)/4 -> 1.5416667 | H30: =(H9+H12+H17+H23)/4 -> 1.125 | I30: =(I9+I12+I17+I23)/4 -> 1.1458333 | J30: =(J9+J12+J17+J23)/4 -> 1.2291667 | ... BY30: =(BY9+BY12+BY17+BY23)/4 -> 3.0833333

Sheet Compliance Status
B2: 2010 Audited | C2: 2020 audited | D2: 44197 | E2: 44229 | F2: 44258 | G2: 44290 | H2: 44321 | I2: 44353 | J2: 44384 | K2: 44416 | L2: 44448 | M2: 44479 | N2: 44511 | O2: 44542 | P2: AUDITED 2021 | Q2: 44563 | R2: 44595 | S2: 44624 | T2: 44656 | U2: 44657 | V2: 44658 | W2: 44659 | X2: 44660 | Y2: 44661 | Z2: 44662 | AA2: 44663 | AB2: 44664 | AC2: 44665 | AD2: 44666 | AE2: 44667 | AF2: 44668 | AG2: 44669 | AH2: 44670 | AI2: 44671 | AJ2: 44672 | AK2: 44673 | AL2: 44674 | AM2: 44675 | AN2: 44676 | AO2: 44677 | AP2: 44678 | AQ2: 44679 | AR2: 44680 | AS2: 44681 | AT2: 44682 | AU2: 44683 | AV2: 44684 | AW2: 44685 | AX2: 44686 | AY2: 44687 | AZ2: 44688 | BA2: 44689 | BB2: 44690 | BC2: 44691 | BD2: 44692 | BE2: 44693 | BF2: 44694 | BG2: 44695 | BH2: 44696
A3: CORE CAPITAL | B3: =IF(CAELS!D3>10,"Compliant","Non-Compliant") -> Compliant | C3: =IF(CAELS!E3>10,"Compliant","Non-Compliant") -> Compliant | D3: =IF(CAELS!F3>10,"Compliant","Non-Compliant") -> Compliant | E3: =IF(CAELS!G3>10,"Compliant","Non-Compliant") -> Compliant | F3: =IF(CAELS!H3>10,"Compliant","Non-Compliant") -> Compliant | G3: =IF(CAELS!I3>10,"Compliant","Non-Compliant") -> Compliant | H3: =IF(CAELS!J3>10,"Compliant","Non-Compliant") -> Compliant | I3: =IF(CAELS!K3>10,"Compliant","Non-Compliant") -> Compliant | ... BH3: =IF(CAELS!BJ3>10,"Compliant","Non-Compliant") -> Non-Compliant
A4: CCA (Min 10%) | B4: =IF(CAELS!D4>10%,"Compliant","Non-Compliant") -> Compliant | C4: =IF(CAELS!E4>10%,"Compliant","Non-Compliant") -> Compliant | D4: =IF(CAELS!F4>10%,"Compliant","Non-Compliant") -> Compliant | E4: =IF(CAELS!G4>10%,"Compliant","Non-Compliant") -> Compliant | F4: =IF(CAELS!H4>10%,"Compliant","Non-Compliant") -> Compliant | G4: =IF(CAELS!I4>10%,"Compliant","Non-Compliant") -> Compliant | H4: =IF(CAELS!J4>10%,"Compliant","Non-Compliant") -> Compliant | I4: =IF(CAELS!K4>10%,"Compliant","Non-Compliant") -> Compliant | ... BH4: =IF(CAELS!BJ4>10%,"Compliant","Non-Compliant") -> Non-Compliant
A5: ICA (Min 8%) | B5: =IF(CAELS!D6>8%,"Compliant","Non-Compliant") -> Non-Compliant | C5: =IF(CAELS!E6>8%,"Compliant","Non-Compliant") -> Compliant | D5: =IF(CAELS!F6>8%,"Compliant","Non-Compliant") -> Compliant | E5: =IF(CAELS!G6>8%,"Compliant","Non-Compliant") -> Compliant | F5: =IF(CAELS!H6>8%,"Compliant","Non-Compliant") -> Compliant | G5: =IF(CAELS!I6>8%,"Compliant","Non-Compliant") -> Compliant | H5: =IF(CAELS!J6>8%,"Compliant","Non-Compliant") -> Compliant | I5: =IF(CAELS!K6>8%,"Compliant","Non-Compliant") -> Compliant | ... BH5: =IF(CAELS!BJ6>8%,"Compliant","Non-Compliant") -> Non-Compliant
A6: CCD (Min 8%) | B6: =IF(CAELS!D5>8%,"Compliant","Non-Compiant") -> Compliant | C6: =IF(CAELS!E5>8%,"Compliant","Non-Compiant") -> Compliant | D6: =IF(CAELS!F5>8%,"Compliant","Non-Compiant") -> Compliant | E6: =IF(CAELS!G5>8%,"Compliant","Non-Compiant") -> Compliant | F6: =IF(CAELS!H5>8%,"Compliant","Non-Compiant") -> Compliant | G6: =IF(CAELS!I5>8%,"Compliant","Non-Compiant") -> Compliant | H6: =IF(CAELS!J5>8%,"Compliant","Non-Compiant") -> Compliant | I6: =IF(CAELS!K5>8%,"Compliant","Non-Compiant") -> Compliant | ... BH6: =IF(CAELS!BJ5>8%,"Compliant","Non-Compiant") -> Non-Compiant
A7: NPL(5%)
A8: Liquidity(15%) | B8: =IF(CAELS!D12>15%,"Compliant","Non-Compliant") -> Compliant | C8: =IF(CAELS!E12>15%,"Compliant","Non-Compliant") -> Compliant | D8: =IF(CAELS!F12>15%,"Compliant","Non-Compliant") -> Compliant | E8: =IF(CAELS!G12>15%,"Compliant","Non-Compliant") -> Compliant | F8: =IF(CAELS!H12>15%,"Compliant","Non-Compliant") -> Compliant | G8: =IF(CAELS!I12>15%,"Compliant","Non-Compliant") -> Compliant | H8: =IF(CAELS!J12>15%,"Compliant","Non-Compliant") -> Compliant | I8: =IF(CAELS!K12>15%,"Compliant","Non-Compliant") -> Compliant | ... BH8: =IF(CAELS!BJ12>15%,"Compliant","Non-Compliant") -> Non-Compliant
A9: NEA (Max 10%) | B9: =IF(CAELS!D16<10%,"Compliant","Non-Compliant") -> Non-Compliant | C9: =IF(CAELS!E16<10%,"Compliant","Non-Compliant") -> Compliant | D9: =IF(CAELS!F16<10%,"Compliant","Non-Compliant") -> Compliant | E9: =IF(CAELS!G16<10%,"Compliant","Non-Compliant") -> Compliant | F9: =IF(CAELS!H16<10%,"Compliant","Non-Compliant") -> Compliant | G9: =IF(CAELS!I16<10%,"Compliant","Non-Compliant") -> Compliant | H9: =IF(CAELS!J16<10%,"Compliant","Non-Compliant") -> Compliant | I9: =IF(CAELS!K16<10%,"Compliant","Non-Compliant") -> Compliant | ... BH9: =IF(CAELS!BJ16<10%,"Compliant","Non-Compliant") -> Compliant
A10: LB ratio (Max 5%) | B10: =IF(CAELS!D17<5%,"Compliant","Non-Compliant") -> Compliant | C10: =IF(CAELS!E17<5%,"Compliant","Non-Compliant") -> Non-Compliant | D10: =IF(CAELS!F17<5%,"Compliant","Non-Compliant") -> Non-Compliant | E10: =IF(CAELS!G17<5%,"Compliant","Non-Compliant") -> Non-Compliant | F10: =IF(CAELS!H17<5%,"Compliant","Non-Compliant") -> Non-Compliant | G10: =IF(CAELS!I17<5%,"Compliant","Non-Compliant") -> Non-Compliant | H10: =IF(CAELS!J17<5%,"Compliant","Non-Compliant") -> Non-Compliant | I10: =IF(CAELS!K17<5%,"Compliant","Non-Compliant") -> Non-Compliant | ... BH10: =IF(CAELS!BJ17<5%,"Compliant","Non-Compliant") -> Compliant
A11: FITD (Max 5%) | B11: =IF(CAELS!D18<5%,"Compliant","Non-Compliant") -> Compliant | C11: =IF(CAELS!E18<5%,"Compliant","Non-Compliant") -> Compliant | D11: =IF(CAELS!F18<5%,"Compliant","Non-Compliant") -> Compliant | E11: =IF(CAELS!G18<5%,"Compliant","Non-Compliant") -> Compliant | F11: =IF(CAELS!H18<5%,"Compliant","Non-Compliant") -> Compliant | G11: =IF(CAELS!I18<5%,"Compliant","Non-Compliant") -> Compliant | H11: =IF(CAELS!J18<5%,"Compliant","Non-Compliant") -> Compliant | I11: =IF(CAELS!K18<5%,"Compliant","Non-Compliant") -> Compliant | ... BH11: =IF(CAELS!BJ18<5%,"Compliant","Non-Compliant") -> Compliant
A12: FICC (Max 40%) | B12: =IF(CAELS!D19<40%,"Compliant","Non-Compliant") -> Compliant | C12: =IF(CAELS!E19<40%,"Compliant","Non-Compliant") -> Compliant | D12: =IF(CAELS!F19<40%,"Compliant","Non-Compliant") -> Compliant | E12: =IF(CAELS!G19<40%,"Compliant","Non-Compliant") -> Compliant | F12: =IF(CAELS!H19<40%,"Compliant","Non-Compliant") -> Compliant | G12: =IF(CAELS!I19<40%,"Compliant","Non-Compliant") -> Compliant | H12: =IF(CAELS!J19<40%,"Compliant","Non-Compliant") -> Compliant | I12: =IF(CAELS!K19<40%,"Compliant","Non-Compliant") -> Compliant | ... BH12: =IF(CAELS!BJ19<40%,"Compliant","Non-Compliant") -> Compliant
A13: EB ratio (Max 25%) | B13: =IF(CAELS!D14<25%,"Compliant","Non-Compliant") -> Compliant | C13: =IF(CAELS!E14<25%,"Compliant","Non-Compliant") -> Compliant | D13: =IF(CAELS!F14<25%,"Compliant","Non-Compliant") -> Compliant | E13: =IF(CAELS!G14<25%,"Compliant","Non-Compliant") -> Compliant | F13: =IF(CAELS!H14<25%,"Compliant","Non-Compliant") -> Compliant | G13: =IF(CAELS!I14<25%,"Compliant","Non-Compliant") -> Compliant | H13: =IF(CAELS!J14<25%,"Compliant","Non-Compliant") -> Compliant | I13: =IF(CAELS!K14<25%,"Compliant","Non-Compliant") -> Compliant | ... BH13: =IF(CAELS!BJ14<25%,"Compliant","Non-Compliant") -> Compliant
A14: A=S+L | B14: =IF('Evolutive SFP'!B27='Evolutive SFP'!B49,"BALANCING","NOT BALANCING") -> BALANCING | C14: =IF('Evolutive SFP'!C27='Evolutive SFP'!C49,"BALANCING","NOT BALANCING") -> NOT BALANCING | D14: =IF('Evolutive SFP'!D27='Evolutive SFP'!D49,"BALANCING","NOT BALANCING") -> BALANCING | E14: =IF('Evolutive SFP'!E27='Evolutive SFP'!E49,"BALANCING","NOT BALANCING") -> BALANCING | F14: =IF('Evolutive SFP'!F27='Evolutive SFP'!F49,"BALANCING","NOT BALANCING") -> BALANCING | G14: =IF('Evolutive SFP'!G27='Evolutive SFP'!G49,"BALANCING","NOT BALANCING") -> BALANCING | H14: =IF('Evolutive SFP'!H27='Evolutive SFP'!H49,"BALANCING","NOT BALANCING") -> NOT BALANCING | I14: =IF('Evolutive SFP'!#REF!='Evolutive SFP'!#REF!,"BALANCING","NOT BALANCING") -> #REF! | J14: =IF('Evolutive SFP'!#REF!='Evolutive SFP'!#REF!,"BALANCING","NOT BALANCING") -> #REF! | K14: =IF('Evolutive SFP'!#REF!='Evolutive SFP'!#REF!,"BALANCING","NOT BALANCING") -> #REF! | L14: =IF('Evolutive SFP'!#REF!='Evolutive SFP'!#REF!,"BALANCING","NOT BALANCING") -> #REF! | M14: =IF('Evolutive SFP'!#REF!='Evolutive SFP'!#REF!,"BALANCING","NOT BALANCING") -> #REF! | N14: =IF('Evolutive SFP'!#REF!='Evolutive SFP'!#REF!,"BALANCING","NOT BALANCING") -> #REF! | O14: =IF('Evolutive SFP'!#REF!='Evolutive SFP'!#REF!,"BALANCING","NOT BALANCING") -> #REF! | P14: =IF('Evolutive SFP'!#REF!='Evolutive SFP'!#REF!,"BALANCING","NOT BALANCING") -> #REF! | ... BH14: =IF('Evolutive SFP'!#REF!='Evolutive SFP'!#REF!,"BALANCING","NOT BALANCING") -> #REF!

Sheet compliance report audited 2021
A1: TRANSCOUNTIES SACCO SOCIETY LIMITED
A2: PERFORMANCE AND COMPLIANCE REPORT AS AT : 31st December , 2021
B3: Prudential Standard | C3: Audited | D3: Returns | F3: Audited 2021 | G3: Aggregate for all Licensed Saccos
C4: 2020 | D4: 30th September , 2021 | E4: 31st December , 2021
A5: A. CAPITAL ADEQUACY
A6: Core Capital | B6: ≥10M | C6: =C33 -> 41972096 | D6: =D33 -> 41681678 | E6: =E33 -> 45103743 | F6: =F33 -> 46709713 | G6: =G33 -> 1.1863726e+11
A7: Core Capital/Total Assets | B7: ≥10% | C7: =C33/C29 -> 0.21377833 | D7: =D33/D29 -> 0.21741199 | E7: =E33/E29 -> 0.22225791 | F7: =F33/F29 -> 0.22992473 | G7: =G33/G29 -> 0.17098641
A8: Institutional Capital/Total Assets | B8: ≥8% | C8: =C34/C29 -> 0.1101064 | D8: =D34/D29 -> 0.10068415 | E8: =E34/E29 -> 0.1090348 | F8: =F34/F29 -> 0.11682309 | G8: =G34/G29 -> 0.10520614
A9: B. ASSET QUALITY
A10: NPL (Substandard+Doubtful+Loss) | B10: <5% | C10: =C35/C32 -> 0 | D10: =D35/D32 -> 0.2514604 | E10: =E35/E32 -> 0.20625666 | F10: =F35/F32 -> 0.20625666 | G10: =G35/G32 -> 0.081282559
A11: Non-Earning Assets | B11: <10% | C11: =C36/C29 -> 0.088097907 | D11: =D36/D29 -> 0.086966985 | E11: =E36/E29 -> 0.071895223 | F11: =F36/F29 -> 0.071815468 | G11: =G36/G29 -> 0.098107352
A12: Equity investments/Deposits | B12: <5% | C12: =C38/C31 -> 0.0010816193 | D12: =D38/D31 -> 0.023603131 | E12: =E38/E31 -> 0.02298947 | F12: =F38/F31 -> 0.02394609 | G12: =G38/G31 -> 0.028360463
A13: Equity investments/Core capital | B13: <40% | C13: =C38/C33 -> 0.0036830422 | D13: =D38/D33 -> 0.079706973 | E13: =E38/E33 -> 0.073659528 | F13: =F38/F33 -> 0.074085919 | G13: =G38/G33 -> 0.11226744
A14: C. EARNINGS RATING
A15: Yield on Gross Loans | C15: =C48/C32 -> 0.12357061 | D15: =D48/D32 -> 0.094114875 | E15: =E48/E32 -> 0.14017987 | F15: =F48/F32 -> 0.14017987 | G15: =G48/G32 -> 0.15911073
A16: Total Expense/Total Income | C16: =C49/C44 -> 0.80402849 | D16: =D49/D44 -> 0.72556787 | E16: =E49/E44 -> 0.7366358 | F16: =F49/F44 -> 0.79837363 | G16: =G49/G44 -> 0.71152696
A17: Net Income/Average Assets (ROA) | C17: =C50/C30 -> 0.019154383 | D17: =D50/D30 -> 0.0085133987 | E17: =E50/E30 -> 0.036398317 | F17: =F50/F30 -> 0.024288403 | G17: =G50/G30 -> 0.037337841
A18: Operating Expenses/Financial Income (OPEX) | C18: =C47/C44 -> 0.72555509 | D18: =D47/D44 -> 0.70613651 | E18: =E47/E44 -> 0.71981711 | F18: =F47/F44 -> 0.71526493 | G18: =G47/G44 -> 0.32598798
A19: D. LIQUIDITY
A20: Liquid Assets/Short-term Liabilities | B20: >15% | C20: =C40/C41 -> 0.85315282 | D20: =D40/D41 -> 1.8527898 | E20: =E40/E41 -> 1.8945316 | F20: =F40/F41 -> 1.6949853 | G20: =G40/G41 -> 0.70153748
A21: External Borrowing/Total Assets | B21: <25% | C21: =C42/C29 -> 0 | D21: =D42/D29 -> 0 | E21: =E42/E29 -> 0 | F21: =F42/F29 -> 0 | G21: =G42/G29 -> 0.0355491
A22: Liquid Assets/Total Assets | C22: =C40/C29 -> 0.21418897 | D22: =D40/D29 -> 0.38862246 | E22: =E40/E29 -> 0.41400501 | F22: =F40/F29 -> 0.41395595 | G22: =G40/G29 -> 0.13749251
A23: E. STRUCTURE/SENSITIVITY TO RISK
A24: Gross loans /Total Assets | B24: 70-80 | C24: =C32/C29 -> 0.59968059 | D24: =D32/D29 -> 0.6415166 | E24: =E32/E29 -> 0.60597043 | F24: =F32/F29 -> 0.60532035 | G24: =G32/G29 -> 0.74848521
A25: Gross loans/Deposits | B25: >100% | C25: =C32/C31 -> 0.8238043 | D25: =D32/D31 -> 0.87377118 | E25: =E32/E31 -> 0.85093078 | F25: =F32/F31 -> 0.85093922 | G25: =G32/G31 -> 1.1058115
A26: Financial Investments/Total Assets | C26: =C39/C31 -> 0.29575552 | D26: =D39/D31 -> 0.023603131 | E26: =E39/E31 -> 0.02298947 | F26: =F39/F31 -> 0.02394609 | G26: =G39/G31 -> 0.063523546
A27: Dividends+Interest on Deposits/Total Income | C27: =C46/C44 -> 0.078473398 | D27: =D46/D44 -> 0 | E27: =E46/E44 -> 0 | F27: =F46/F44 -> 0.076389748 | G27: =G46/G44 -> 0.32213107
A28: F. KEY FINANCIAL STATISTICS | C28: 2015 | D28: 2016 | E28: 2017 | G28: AGGREGATE
A29: Total Assets | C29: 196334664 | D29: 1.9171748e+08 | E29: 2.0293426e+08 | F29: ='Evolutive SFP'!P27 -> 203152195 | G29: 6.9384025e+11
A30: Average Assets | C30: 1.8574396e+08 | D30: 1.9058714e+08 | E30: 1.9974868e+08 | F30: =('Evolutive SFP'!C27+'Evolutive SFP'!P27)/2 -> 199743429 | G30: 6.5554466e+11
A31: Total Deposits | C31: 142919971 | D31: 1.4075761e+08 | E31: 1.4451488e+08 | F31: ='Evolutive SFP'!P31 -> 144513444 | G31: 4.6963625e+11
A32: Gross Loans | C32: 117738087 | D32: 1.2298995e+08 | E32: 1.2297216e+08 | F32: ='Evolutive SFP'!P15 -> 122972158 | G32: 5.1932916e+11
A33: Core Capital | C33: 41972096 | D33: 41681678 | E33: 45103743 | F33: ='Evolutive SFP'!P39+'Evolutive SFP'!P41+'Evolutive SFP'!P42+'Evolutive SFP'!P43+'Evolutive SFP'!P44-'Evolutive SFP'!P13 -> 46709713 | G33: 1.1863726e+11
A34: Institutional Capital | C34: 21617704 | D34: 19302911 | E34: 22126897 | F34: =F33-'Evolutive SFP'!P39 -> 23732867 | G34: 7.2996255e+10
A35: Non-performing Loans | C35: 0 | D35: 30927101 | E35: 25363827 | F35: ='FORM 4'!D42+'FORM 4'!D43+'FORM 4'!D44 -> 25363827 | G35: 4.2212404e+10
A36: Non-Earning Assets | C36: 17296673 | D36: 16673091 | E36: 14590004 | F36: ='Evolutive SFP'!P7+'Evolutive SFP'!P23+'Evolutive SFP'!P25 -> 14589470 | G36: 6.8070829e+10
A37: Property and Equipment | C37: 14963299 | D37: 14456975 | E37: 13338839 | F37: ='Evolutive SFP'!P23+'Evolutive SFP'!P25 -> 13321202 | G37: 1.9634989e+10
A38: Equity Investments | C38: 154585 | D38: 3322320.4 | E38: 3322320.4 | F38: ='Evolutive SFP'!P13+'Evolutive SFP'!P12 -> 3460532 | G38: 1.3319101e+10
A39: Financial Investments | C39: 42269370 | D39: 3322320.4 | E39: 3322320.4 | F39: ='Evolutive SFP'!P8 -> 3460532 | G39: 2.983296e+10
A40: Liquid Assets | C40: 42052719 | D40: 74505718 | E40: 84015798 | F40: ='Evolutive SFP'!P4 -> 84096060 | G40: 9.5397835e+10
A41: Short-term Liabilities) | C41: 49290957 | D41: 40212720 | E41: 44346475 | F41: ='Evolutive SFP'!P28+'Evolutive SFP'!P32+'Evolutive SFP'!P33+'Evolutive SFP'!P36 -> 49614625 | G41: 1.3598395e+11
A42: External Borrowing | C42: 0 | D42: 0 | E42: 0 | G42: 2.4665397e+10
A43: Average Gross Loans | C43: 1.1220433e+08 | D43: 1.193436e+08 | E43: 1.2044672e+08 | F43: =('Evolutive SFP'!C15+'Evolutive SFP'!P15)/2 -> 1.2035512e+08 | G43: 4.9232606e+11
A44: Total Income | C44: 24912213 | D44: 17803587 | E44: 25805617 | F44: ='Evolutitve SCI'!P3 -> 27183255 | G44: 9.6251718e+10
A45: Net Financial Income/Loss | C45: 22957267 | D45: 17457399 | E45: 25371361 | F45: ='Evolutitve SCI'!P19 -> 24924090 | G45: 5.9024776e+10
A46: Dividends+Interest on Deposits | C46: 1954946 | D46: 0 | E46: 0 | F46: ='Evolutitve SCI'!P13 -> 2076522 | G46: 3.1005669e+10
A47: Operating Expenses | C47: 18075183 | D47: 12571763 | E47: 18575325 | F47: ='Evolutitve SCI'!P23 -> 19443229 | G47: 3.1376903e+10
A48: Interest on Loan portfolio+Fees&Commission on Loan | C48: 14548967 | D48: 11575183 | E48: 17238221 | F48: ='Evolutitve SCI'!P4 -> 17238221 | G48: 8.2630841e+10
A49: Total Expenses | C49: 20030129 | D49: 12917711 | E49: 19009342 | F49: ='Evolutitve SCI'!P39 -> 21702394 | G49: 6.8485692e+10
A50: Net Income | C50: 3557811 | D50: 1622544.3 | E50: 7270515.8 | F50: ='Evolutitve SCI'!P37 -> 4851449 | G50: 2.4476622e+10
A51: G. AREAS OF IMPROVEMENT/REGULATORY CONCERNS
A52: 1.Non perfoming loan of 20.6 % against required 5% and below.
A53: 2.Gross loans to Total Assets at 60.6% against recommended industry level of 70-80%.
A54: 3.Gross loans to Deposits of 85.1% against required 100% and above.
A56: Checked by:
A58: Approved by:
A60: DISCLAIMER: This report is prepared based on information submitted by the Sacco as at the stated date and may change upon verification by the Authority.

Sheet CashFlow Stmnt
A1: STATEMENT OF CASHFLOWS FOR THE YEAR ENDED 31ST DECEMBER 2020
B2: 2020 | C2: 2021 | D2: Audited -2021 | E2: Variance
A3: Cash flows from operating activities
A4: Interest receipts
A5: Interest Payments | J5: .
A6: Payment to employees and suppliers | J6: .
A7: Other operating income
A8: (Increase)/Decrease in Operating assets | B8: =B4+B5+B6+B7 -> 0 | C8: =SUM(C4:C7) -> 0 | D8: =SUM(D4:D7) -> 0
A9: Net loans to members
A10: Recievables and prepayments
A11: Trade and Other Receivables
A12: Inventories
A13: Short term investments
A14: Increase/(Decrease) in Operating liabilities | B14: =SUM(B9:B13) -> 0 | C14: =SUM(C9:C13) -> 0 | D14: =SUM(D9:D13) -> 0
A15: Deposits from members
A16: Trade and Accrued Expenses
A17: Sundry creditors
A18: Net cashflow from operating activities before income taxes | B18: =B8+B14+B15+B16+B17 -> 0 | C18: =C8+C14+C15+C16+C17 -> 0 | D18: =D8+D14+D15+D16+D17 -> 0
A19: Income tax paid
A20: Net Cash from Operating activities
A22: Cashflow from investing activities
A23: Purchase of Property and equipment
A24: Purchase of intangible assets
A25: Increase in Other Assets
A26: Purchase of Investment Securities
A27: Dividends Received
A28: Net Cash from investing activities | B28: =SUM(B23:B27) -> 0 | C28: =SUM(C23:C27) -> 0 | D28: =SUM(D23:D27) -> 0
A30: Cashflow from financing activities
A31: Share capital contributions
A32: Proceeds from long-term borrowings
A33: Prior Year Adjustments
A34: Housing Contributions Plaza
A35: Repayments of long term borrowings
A36: Dividend paid
A37: Net cash from financing activities | B37: =SUM(B31:B36) -> 0 | C37: =SUM(C31:C36) -> 0 | D37: =SUM(D31:D36) -> 0
A38: Net (Decrease)/Increase in cash and cash equivalent | B38: =B20+B28+B37 -> 0 | C38: =C20+C28+C37 -> 0 | D38: =D20+D28+D37 -> 0
A39: Cash and cash equivalent at the beginning of the year
A40: Cash and cash equivalent at the end of the year | B40: =SUM(B38:B39) -> 0 | C40: =SUM(C38:C39) -> 0 | D40: =SUM(D38:D39) -> 0
