Workbook
Name BALANCE1_LDA01: '[1]Financial Statements'!$E$112
Name BALANCE1_LDA12: '[1]Financial Statements'!$E$123
Name BALANCE2_ILF10: '[2]Financial Statements'!$F$61
Name BALANCE2_ILI10: '[2]Financial Statements'!$F$62
Name BALANCE2_ILP10: '[2]Financial Statements'!$F$63
Name BALANCE2_INI10: '[2]Financial Statements'!$F$65
Name BALANCE2_INI40: '[2]Financial Statements'!$F$66
Name BALANCE2_IO010: '[2]Financial Statements'!$F$68
Name BALANCE2_IQ006: '[2]Financial Statements'!$F$69
Name BALANCE2_IQ009: '[2]Financial Statements'!$F$70
Name BALANCE2_LDA01: '[1]Financial Statements'!$F$112
Name BALANCE2_LDA12: '[1]Financial Statements'!$F$123
Name BALANCE2_XO010: '[2]Financial Statements'!$F$247
Name BALANCE2_XO020: '[2]Financial Statements'!$F$248
Name BALANCE2_XO030: '[2]Financial Statements'!$F$249
Name BALANCE2_XO040: '[2]Financial Statements'!$F$250
Name BALANCE2_XO050: '[2]Financial Statements'!$F$251
Name BALANCE3_ILF10: '[2]Financial Statements'!$G$61
Name BALANCE3_ILI10: '[2]Financial Statements'!$G$62
Name BALANCE3_ILP10: '[2]Financial Statements'!$G$63
Name BALANCE3_INI10: '[2]Financial Statements'!$G$65
Name BALANCE3_INI40: '[2]Financial Statements'!$G$66
Name BALANCE3_IO010: '[2]Financial Statements'!$G$68
Name BALANCE3_IQ006: '[2]Financial Statements'!$G$69
Name BALANCE3_IQ009: '[2]Financial Statements'!$G$70
Name BALANCE3_LDA01: '[1]Financial Statements'!$G$112
Name BALANCE3_LDA12: '[1]Financial Statements'!$G$123
Name BALANCE3_XO010: '[2]Financial Statements'!$G$247
Name BALANCE3_XO020: '[2]Financial Statements'!$G$248
Name BALANCE3_XO030: '[2]Financial Statements'!$G$249
Name BALANCE3_XO040: '[2]Financial Statements'!$G$250
Name BALANCE3_XO050: '[2]Financial Statements'!$G$251
Name BALANCE4_ILF10: '[2]Financial Statements'!$H$61
Name BALANCE4_ILI10: '[2]Financial Statements'!$H$62
Name BALANCE4_ILP10: '[2]Financial Statements'!$H$63
Name BALANCE4_INI10: '[2]Financial Statements'!$H$65
Name BALANCE4_INI40: '[2]Financial Statements'!$H$66
Name BALANCE4_IO010: '[2]Financial Statements'!$H$68
Name BALANCE4_IQ006: '[2]Financial Statements'!$H$69
Name BALANCE4_IQ009: '[2]Financial Statements'!$H$70
Name BALANCE4_LDA01: '[1]Financial Statements'!$H$112
Name BALANCE4_LDA12: '[1]Financial Statements'!$H$123
Name BALANCE4_XO010: '[2]Financial Statements'!$H$247
Name BALANCE4_XO020: '[2]Financial Statements'!$H$248
Name BALANCE4_XO030: '[2]Financial Statements'!$H$249
Name BALANCE4_XO040: '[2]Financial Statements'!$H$250
Name BALANCE4_XO050: '[2]Financial Statements'!$H$251
Name BALANCE5_ILI10: '[2]Financial Statements'!$I$62
Name BALANCE5_ILP10: '[2]Financial Statements'!$I$63
Name BALANCE5_INI10: '[2]Financial Statements'!$I$65
Name BALANCE5_INI40: '[2]Financial Statements'!$I$66
Name BALANCE5_IO010: '[2]Financial Statements'!$I$68
Name BALANCE5_IQ006: '[2]Financial Statements'!$I$69
Name BALANCE5_IQ009: '[2]Financial Statements'!$I$70
Name BALANCE5_LDA01: '[1]Financial Statements'!$I$112
Name BALANCE5_LDA12: '[1]Financial Statements'!$I$123
Name BALANCE5_XO010: '[2]Financial Statements'!$I$247
Name BALANCE5_XO020: '[2]Financial Statements'!$I$248
Name BALANCE5_XO030: '[2]Financial Statements'!$I$249
Name BALANCE5_XO040: '[2]Financial Statements'!$I$250

Sheet Trend
CX1: =12575870-12590309 -> -14439
B2: Nyahururu Umoja(VICTAS) | AW2: =2624555-524911-608151-200000 -> 1291493
C3: Audited Accounts
B4: AUDITED STATEMENTS | C4: 2008 | D4: 2009 | E4: 2010 | F4: 2011 | G4: 2012 | H4: 41609 | I4: 2013 | J4: 41640 | K4: 41671 | L4: 41699 | M4: 41730 | N4: 41760 | O4: 41791 | P4: 41821 | Q4: 41852 | R4: 41883 | S4: 41913 | T4: 41944 | U4: 41974 | V4: Audited 2014 | W4: Jan-15 | X4: Feb-15 | Y4: Mar-15 | Z4: Apr-15 | AA4: 42125 | AB4: 42156 | AC4: 42186 | AD4: 42217 | AE4: 42248 | AF4: 42278 | AG4: 42309 | AH4: 42339 | AI4: 2015 | AJ4: 2015 Rev. | AK4: Jan-16 | AL4: Feb-16 | AM4: Mar-16 | AN4: Apr-16 | AO4: May-16 | AP4: Jun-16 | AQ4: Jul-16 | AR4: Aug-16 | AS4: Sept-16 | AT4: Oct-16 | AU4: Nov-16 | AV4: Dec-16 | AW4: Aud-2016 | AX4: Jan-2017 | AY4: Feb-2017 | AZ4: March-2017 | BA4: Apr-2017 | BB4: May-2017 | BC4: June-2017 | BD4: July-2017 | BE4: 42948 | BF4: 42979 | BG4: 43009 | BH4: 43040 | BI4: 43070 | BJ4: Audited 2017 | BK4: 43101 | BL4: 43132 | BM4: 43160 | BN4: 43191 | BO4: 43221 | BP4: 43252 | BQ4: 43282 | BR4: 43313 | BS4: 43344 | BT4: 43374 | BU4: 43405 | BV4: 43435 | BW4: Audited-2018 | BX4: 43466 | BY4: 43497 | BZ4: 43525 | CA4: 43556 | CB4: 43586 | CC4: 43617 | CD4: 43647 | CE4: 43678 | CF4: 43709 | CG4: 43739 | CH4: 43770 | CI4: 43800 | CJ4: Audited-2019 | CK4: 43831 | CL4: 43862 | CM4: 43891 | CN4: 43922 | CO4: 43952 | CP4: 43983 | CQ4: 44013 | CR4: 44044 | CS4: 44075 | CT4: 44105 | CU4: 44136 | CV4: 44166 | CW4: Audited 2020 | CX4: 44197 | CY4: 44228 | CZ4: 44256 | DA4: 44287 | DB4: 44317 | DC4: 44348 | DD4: 44378 | DE4: 44409 | DF4: 44440 | DG4: 44470 | DH4: 44501 | DI4: 44531 | DJ4: Audited-2021 | DK4: 44562 | DL4: 44593 | DM4: 44621 | DN4: 44652 | DO4: 44682 | DP4: 44713 | DQ4: 44743 | DR4: 44774 | DS4: 44805 | DT4: 44835 | DU4: 44866 | DV4: 44896 | DW4: Audited-22
B5: Cash and Cash Equivalent | C5: =SUM(C6:C7) -> 692551 | D5: =SUM(D6:D7) -> 2050924 | E5: =SUM(E6:E7) -> 1466652 | F5: =SUM(F6:F7) -> 6631870 | G5: =SUM(G6:G7) -> 8447670 | H5: =SUM(H6:H7) -> 15934406 | I5: =SUM(I6:I7) -> 16473429 | J5: =SUM(J6:J7) -> 32498030 | ... DW5: =SUM(DW6:DW7) -> 40136992
B6: Cash in Hand | C6: 692551 | D6: 2050924 | E6: 1466652 | F6: 6631870 | G6: 8447670 | H6: 2072524.5 | I6: 2008272 | J6: 3952137 | K6: 4296961.5 | L6: 1702028.5 | M6: 3522013.5 | N6: 3800938.5 | O6: 1500354 | P6: 3681214 | Q6: 2737510 | R6: 3491663 | S6: 2336673 | T6: 1558098.2 | U6: 1597927 | V6: 1137405 | W6: 915480 | X6: 3071335 | Y6: 3011475 | Z6: 3824566 | AA6: 3938097 | AB6: 2621397 | AC6: 3484317 | AD6: 1825373 | AE6: 1811887 | AF6: 1549902 | AG6: 2789695 | AH6: 3288082 | AI6: 2528402 | AJ6: 2528402 | AL6: 1917754 | AM6: 4252295 | AN6: 4894024 | AO6: 3938097 | AP6: 5868133 | AQ6: 3957008 | AR6: 2552472 | AS6: 3339979 | AU6: 2808257 | AV6: 3022983 | AW6: 7293918 | AZ6: 3171740 | BA6: 6947564 | BB6: 4190221 | BC6: 4580682.2 | BD6: 4758799 | BE6: 3573953 | BF6: 3754606 | BH6: 4123693 | BI6: 5045728 | BJ6: 7387734 | BK6: 11253203 | BL6: 6418620 | BM6: 2929877 | BN6: 5074804 | BO6: 3187375 | BP6: 7767560 | BQ6: 7479361 | BR6: 8108751 | BS6: 7368918 | BT6: 9037659 | BU6: 6226073 | BV6: 4946234 | BW6: 4946324 | BX6: 3045083 | BY6: 2887803 | BZ6: 7680216 | CA6: 9262974 | CB6: 9250689 | CC6: 7124091 | CD6: 6858434.7 | CE6: 3742037 | CF6: 3934900 | CG6: 9111685 | CH6: 9093178 | CI6: 1806997 | CJ6: 1806997 | CK6: 5344394 | CL6: 5530420 | CM6: 4429694 | CN6: 5733045 | CO6: 5974479 | CP6: 3318368 | CQ6: 4470588 | CR6: 5627555 | CS6: 7956958 | CT6: 7956958 | CU6: 2233374 | CV6: 3485128 | CW6: 3485128 | CX6: 6041142 | CY6: 9121646 | CZ6: 8051194 | DA6: 7809168 | DB6: 5914677 | DC6: 4669718 | DD6: 5312352 | DE6: 4928248 | DF6: 7093659 | DG6: 1490080 | DH6: 5745704 | DI6: 4919895 | DJ6: 4919895 | DK6: 4234521 | DL6: 3860966 | DM6: 3933959 | DN6: 3825177 | DO6: 3858834 | DP6: 6253686 | DQ6: 7644156 | DR6: 5409180 | DS6: 4838774 | DT6: 6457883 | DU6: 8296828 | DW6: 3263540
B7: Cash at Bank | H7: 13861882 | I7: =85465+10963752+3064382+196412+155146 -> 14465157 | J7: 28545893 | K7: 12210327 | L7: 13964050 | M7: 11023350 | N7: 12099886 | O7: 15362020 | P7: 14437685 | Q7: 13605351 | R7: 9964819.7 | S7: 9155059.7 | T7: 9222167.4 | U7: 6296735.6 | V7: =16001725-V6-2000000 -> 12864320 | W7: 9240642.4 | X7: 6454678 | Y7: 8711317.3 | Z7: 13393232 | AA7: 15148205 | AB7: 16521579 | AC7: 14371492 | AD7: 8317305.4 | AE7: 8786996.5 | AF7: 7835796 | AG7: 4737561.2 | AH7: 4978470.8 | AI7: =133232+4237489+234544+1012463+230000 -> 5847728 | AJ7: =133232+1012463+4237489+234544+230000 -> 5847728 | AL7: 3484212.8 | AM7: 2922878 | AN7: 4248744.8 | AO7: 15148205 | AP7: 4231632.7 | AQ7: 5836879.8 | AR7: 1712753.4 | AS7: -1311248.1 | AU7: 2310604.2 | AV7: 2434424.3 | AW7: =2189+1916833+378525+168977+7422938+263000+18308+18000000+967548 -> 29138318 | AZ7: 4326626.9 | BA7: 2547320 | BB7: 3964486 | BC7: 5716098 | BD7: 2119693 | BE7: 7161490.3 | BF7: 5839053 | BH7: 6670240.5 | BI7: 5936081 | BJ7: =2273464+227046+245650+135664+1446742+2629031+18798925+8000000+1178716+4000000 -> 38935238 | BK7: 0 | BL7: 9139966 | BM7: 7942942 | BN7: 9414188 | BO7: 11289222 | BP7: 8559990 | BQ7: 12044444 | BR7: 9614472 | BS7: 2916863 | BT7: 3731616 | BU7: 4439296 | BV7: 14296008 | BW7: =57724521-BW6 -> 52778197 | BX7: 13206079 | BY7: 3969436 | BZ7: 9162974 | CA7: 13916816 | CB7: 9658302 | CC7: 10016359 | CD7: 10422915 | CE7: 5322970 | CF7: 10665847 | CG7: 13827291 | CH7: 2839282.7 | CI7: 40604498 | CJ7: 44438914 | CK7: 4240600 | CL7: 32501434 | CM7: 11852066 | CN7: 8944813 | CO7: 20258340 | CP7: 8213449.9 | CQ7: 5904636.1 | CR7: 14145728 | CS7: 8449131.8 | CT7: 8449131.8 | CU7: 8493932.2 | CV7: 13539967 | CW7: =31495404.03-CW6 -> 28010276 | CX7: 12857710 | CY7: 22567860 | CZ7: 12888632 | DA7: 21065300 | DB7: 9029334.8 | DC7: 17089840 | DD7: 8799668.2 | DE7: 10807547 | DF7: 13976813 | DG7: 10562216 | DH7: 9126697 | DI7: 18760462 | DJ7: 26435090 | DK7: 8513746.5 | DL7: 12080379 | DM7: 19882721 | DN7: 7407976.3 | DO7: 5525372 | DP7: 10062639 | DQ7: 11951292 | DR7: 14136732 | DS7: 6092671.7 | DT7: 6327215.8 | DU7: 10155304 | DW7: =40136992-3263540 -> 36873452
B8: Prepayments and Sundry Receivables | C8: 67039 | D8: 42292 | E8: 49508 | F8: 37292 | G8: 85800 | H8: 818633.95 | I8: 85800 | J8: 1606266.4 | K8: 986486.48 | L8: 994092.07 | M8: 937436.37 | N8: 961317.76 | O8: 1101263.8 | P8: 1126434.9 | Q8: 1925528.4 | R8: 2391641.9 | S8: 2913196.8 | T8: 3372932.3 | U8: 906298 | V8: 85800 | W8: 1074825.1 | X8: 1271350.2 | Y8: 1520532.5 | Z8: 1567860.9 | AA8: 1895761.9 | AB8: 2047687.6 | AC8: 2833915.6 | AD8: 3127239.8 | AE8: 2086448.4 | AF8: 1606975.9 | AG8: 2211469 | AH8: 704228.1 | AI8: 85800 | AJ8: 85000 | AL8: 2380719.5 | AM8: 1727893.9 | AN8: 1572852.9 | AO8: 1895761.9 | AP8: 646861.27 | AQ8: 10577806 | AR8: 13238399 | AS8: 14276306 | AU8: 18407906 | AV8: 1429677.6 | AW8: 85800 | AZ8: 0 | BA8: 0 | BB8: 0 | BC8: 0 | BD8: 0 | BE8: 0 | BH8: 0 | BI8: 0 | BJ8: 115800 | BK8: 0 | BL8: 0 | BM8: 0 | BN8: 0 | BO8: 0 | BQ8: 0 | BR8: 0 | BS8: 0 | BT8: 0 | BU8: 0 | BV8: 0 | BW8: 2747143.4 | BX8: 0 | BZ8: 0 | CA8: 0 | CB8: 0 | CC8: 0 | CD8: 0 | CE8: 6681042 | CF8: 7153115.6 | CG8: 7441332 | CH8: 8098898.2 | CI8: 7527188.6 | CJ8: 7527188.6 | CK8: 7250638.6 | CL8: 8115570.8 | CM8: 7825760 | CN8: 11397977 | CO8: 12916310 | CP8: 11613890 | CQ8: 10266776 | CR8: 11024905 | CS8: 11818197 | CT8: 12692546 | CU8: 12210435 | CV8: 9885482.6 | CW8: 9671737.5 | CX8: 9671737.5 | CY8: 9671737.5 | CZ8: 9671737.5 | DA8: 9671737.5 | DB8: 9671737.5 | DC8: 9671737.5 | DD8: 9671737.5 | DE8: 9671737.5 | DF8: 9671737.5 | DG8: 9671737.5 | DH8: 9671737.5 | DI8: 9671737.5 | DJ8: 11288794 | DK8: 15891778 | DL8: 16326724 | DM8: 16663417 | DN8: 16773933 | DO8: 17404531 | DP8: 17848677 | DQ8: 18770995 | DR8: 19474740 | DS8: 19866306 | DT8: 19575118 | DU8: 20514287 | DW8: 15809279
B9: Financial Investments | C9: =SUM(C10:C13) -> 69500 | D9: =SUM(D10:D13) -> 149500 | E9: =SUM(E10:E13) -> 209500 | F9: =SUM(F10:F13) -> 219500 | G9: =SUM(G10:G13) -> 227500 | H9: =SUM(H10:H13) -> 4870491.9 | I9: =SUM(I10:I13) -> 1727686 | J9: =SUM(J10:J13) -> 9740983.7 | ... DW9: =SUM(DW10:DW13) -> 777172
B10: Government Securities | F10: 0 | G10: 0 | H10: 1500000 | I10: 1500000 | J10: 3000000 | K10: 1500000 | L10: 1500000 | M10: 1500000 | N10: 1500000 | O10: 1500000 | P10: 1500000 | Q10: 1500000 | R10: 1500000 | S10: 1500000 | T10: 1500000 | U10: 0 | AA10: 0 | AC10: 0 | AD10: 1500000 | AE10: 1500000 | AF10: 1500000 | AG10: 1500000 | AH10: 1500000 | AI10: 1500000 | AJ10: 1500000 | AL10: 1500000 | AM10: 1500000 | AN10: 1500000 | AP10: 1500000 | AQ10: 1500000 | AR10: 3000000 | AS10: 3000000 | AU10: 3000000 | AV10: 3000000 | AW10: 3000000 | AZ10: 3000000 | BA10: 0 | BB10: 0 | BC10: 0 | BD10: 0 | BE10: 0 | BH10: 0 | BI10: 0 | BK10: 0 | BL10: 0 | BM10: 0 | BN10: 0 | BO10: 0 | BP10: 0 | BQ10: 0 | BR10: 0 | BS10: 0 | BT10: 0 | BU10: 0 | BV10: 0 | BX10: 0 | BY10: 0 | BZ10: 0 | CA10: 0 | CX10: 0 | CY10: 0 | CZ10: 0 | DA10: 0 | DB10: 0 | DC10: 0 | DD10: 0 | DE10: 0 | DF10: 0 | DG10: 0 | DH10: 0 | DI10: 0 | DK10: 0 | DL10: 0 | DM10: 0 | DN10: 0 | DO10: 0 | DP10: 0 | DQ10: 0 | DR10: 0 | DS10: 0 | DT10: 0 | DU10: 0
B11: Other Securities | F11: 0 | H11: 0 | J11: 0 | K11: 0 | L11: 0 | M11: 0 | N11: 0 | O11: 0 | P11: 0 | Q11: 0 | R11: 0 | S11: 0 | T11: 0 | U11: 0 | AA11: 0 | AC11: 0 | AD11: 0 | AE11: 0 | AF11: 0 | AG11: 0 | AH11: 0 | AL11: 0 | AM11: 0 | AN11: 0 | AO11: 0 | AP11: 0 | AQ11: 0 | AR11: 0 | AS11: 0 | AU11: 156440 | AV11: 271415 | AZ11: 3995187.5 | BA11: 952860 | BB11: 783730 | BC11: 0 | BD11: 0 | BE11: 0 | BH11: 0 | BI11: 0 | BK11: 0 | BL11: 0 | BM11: 0 | BN11: 0 | BO11: 0 | BP11: 0 | BQ11: 0 | BR11: 0 | BS11: 0 | BT11: 0 | BU11: 0 | BV11: 0 | BX11: 0 | BY11: 0 | BZ11: 0 | CA11: 0 | CB11: 0 | CC11: 0 | CD11: 0 | CE11: 0 | CF11: 0 | CG11: 0 | CH11: 0 | CI11: 0 | CL11: 0 | CM11: 0 | CN11: 0 | CO11: 0 | CP11: 0 | CR11: 0 | CS11: 0 | CT11: 0 | CU11: 0 | CX11: 0 | CY11: 0 | CZ11: 0 | DA11: 0 | DB11: 0 | DC11: 0 | DD11: 0 | DE11: 0 | DF11: 0 | DG11: 0 | DH11: 0 | DI11: 0 | DK11: 0 | DL11: 0 | DM11: 0 | DN11: 0 | DO11: 0 | DP11: 0 | DQ11: 0 | DR11: 0 | DS11: 0 | DT11: 0 | DU11: 0
B12: Balances with other SACCO Societies | F12: 0 | H12: 3370491.9 | J12: 6740983.7 | K12: 3620491.9 | L12: 3620491.9 | M12: 3620491.9 | N12: 3620491.9 | O12: 3620491.9 | P12: 3728278.5 | Q12: 3840476.5 | R12: 3840476.5 | S12: 3840476.5 | T12: 3840476.5 | U12: 4093866.5 | W12: 4093866.5 | X12: 4093866.5 | Y12: 4093866.5 | Z12: 4218188.2 | AA12: 4218188.2 | AB12: 4218188.2 | AC12: 4218188.2 | AD12: 4218188.2 | AE12: 4218188.2 | AF12: 4218188.2 | AG12: 4538109.1 | AH12: 4750876.5 | AI12: =4540018+19000+10000+100500+148186 -> 4817704 | AJ12: =148186+19000+10000+100500+4540018 -> 4817704 | AL12: 4800876.5 | AM12: 4870876.5 | AN12: 4940876.5 | AO12: 4218188.2 | AP12: 4940876.5 | AQ12: 4940876.5 | AR12: 6869187.5 | AS12: 7190687.5 | AU12: 7442187.5 | AV12: 7995187.5 | AW12: =452749+19000+10000+50500 -> 532249 | AZ12: 647965 | BA12: 9499375 | BB12: 5001187.5 | BC12: 5001187 | BD12: 5504187.5 | BE12: 5755687 | BF12: 5805687 | BH12: 2016991 | BI12: 2066991 | BJ12: 579979 | BK12: 2116991 | BL12: 2216991.9 | BM12: 2216991 | BN12: 2266991 | BO12: 2316491 | BP12: 2316991 | BQ12: 2420636 | BR12: 2470636 | BS12: 2524664 | BT12: 2574664 | BU12: 3094664 | BV12: 2579415.5 | BW12: 580249 | BX12: 2684415 | BY12: 2789415 | BZ12: 3509664 | CA12: 4694661 | CB12: 3659664 | CC12: 3659664 | CD12: 3304415.5 | CE12: 3409415.5 | CF12: 3514415.5 | CG12: 3619415.5 | CH12: 3724415.5 | CI12: 3834415.5 | CJ12: 580249 | CK12: 3939415.5 | CL12: 4044415.5 | CM12: 4149415.5 | CN12: 4254415 | CO12: 4359415.5 | CP12: 36110000 | CQ12: 4579282.8 | CR12: 4702456 | CS12: 4912456 | CT12: 4912456 | CU12: 5017456.7 | CV12: 5122456.7 | CW12: ` | CX12: 5227456.7 | CY12: 5332456.7 | CZ12: 5465456 | DA12: 5596728.9 | DB12: 5702728.3 | DC12: 5806728.3 | DD12: 5911728.3 | DE12: 6016728.3 | DF12: 6121728.3 | DG12: 6121728.3 | DH12: 6121728.3 | DI12: 7441559.3 | DK12: 7578433.8 | DL12: 7578433.8 | DM12: 7578433.8 | DN12: 7578433.8 | DO12: 7878433.8 | DP12: 7978433.8 | DQ12: 8078433.8 | DR12: 8178433.8 | DS12: 8178433.8 | DT12: 8178433.8 | DU12: 8497858.9 | DW12: 777172
B13: Investments in companies | C13: 69500 | D13: 149500 | E13: 209500 | F13: 219500 | G13: 227500 | H13: 0 | I13: =148186+19000+10000+50500+0 -> 227686 | J13: 0 | K13: 0 | L13: 0 | M13: 0 | N13: 0 | O13: 0 | P13: 0 | Q13: 0 | R13: 0 | S13: 0 | T13: 0 | U13: 2000000 | V13: 2227686 | W13: 2000000 | X13: 2000000 | Y13: 2000000 | Z13: 2000000 | AA13: 4000000 | AB13: 4000000 | AC13: 6000000 | AD13: 15000000 | AE13: 15000000 | AF13: 20000000 | AG13: 20000000 | AH13: 17735502 | AI13: 17735502 | AJ13: 17735502 | AL13: 18317067 | AM13: 18317067 | AN13: 0 | AO13: 4000000 | AP13: 0 | AV13: 18000000 | AZ13: 22000000 | BA13: 50004500 | BB13: 25419228 | BC13: 26218898 | BD13: 26318898 | BE13: 26349210 | BF13: 26259891 | BH13: 30259891 | BI13: 28798926 | BK13: 29198925 | BL13: 25198926 | BM13: 25198926 | BN13: 22597206 | BO13: 23302925 | BP13: 19302925 | BQ13: 19409525 | BR13: 27909525 | BS13: 33909525 | BT13: 34909525 | BU13: 38909525 | BV13: 35902865 | BX13: 36425114 | BY13: 41523114 | BZ13: 41780134 | CA13: 34017661 | CB13: 32106659 | CC13: 30937631 | CD13: 32871249 | CE13: 32871249 | CF13: 28652834 | CG13: 25148757 | CH13: 30348756 | CK13: 30320249 | CL13: 10000000 | CM13: 25620249 | CN13: 29620249 | CO13: 20190068 | CP13: 4464415.5 | CQ13: 33618191 | CR13: 28535519 | CS13: 34397489 | CT13: 34397489 | CU13: 36281996 | CV13: 19356085 | CW13: 10580249 | CX13: 19976334 | CY13: 10580249 | CZ13: 11541267 | DA13: 11541267 | DB13: 18541267 | DC13: 18541267 | DD13: 20921017 | DE13: 21541267 | DF13: 21541267 | DG13: 20921018 | DH13: 16541267 | DI13: 10580249 | DJ13: 10777171 | DK13: 16829639 | DL13: 16829639 | DM13: 1829638.7 | DN13: 6829638.7 | DO13: 6829638.7 | DP13: 6829638.7 | DQ13: 6829638.7 | DR13: 6829638.7 | DS13: 10829639 | DT13: 10829639 | DU13: 10905982
B14: Net Loan Portfolio | C14: =C15-C16 -> 2617776 | D14: =D15-D16 -> 6440080 | E14: =E15-E16 -> 16654373 | F14: =F15-F16 -> 26721318 | G14: =G15-G16 -> 34118230 | H14: =H15-H16 -> 48217666 | I14: =I15-I16 -> 48346848 | J14: =J15-J16 -> 98776711 | ... DW14: =DW15-DW16 -> 340435332
B15: Gross Loan Portfolio | C15: 2617776 | D15: 6440080 | E15: 16654373 | F15: 26990740 | G15: 34462859 | H15: 48487088 | I15: =34462859+14368860 -> 48831719 | J15: 99315555 | K15: 51846750 | L15: 53088544 | M15: 56012665 | N15: 56324548 | O15: 57754398 | P15: 59518852 | Q15: 61912067 | R15: 66152643 | S15: 70188955 | T15: 70768398 | U15: 71533981 | V15: 72135405 | W15: 71223638 | X15: 72077931 | Y15: 70362672 | Z15: 71532583 | AA15: 71101461 | AB15: 74317436 | AC15: 75460453 | AD15: 77333983 | AE15: 80295247 | AF15: 78495691 | AG15: 82958722 | AH15: 85166104 | AI15: 89845305 | AJ15: 89845305 | AL15: 89104254 | AM15: 89091773 | AN15: 89091823 | AO15: 71101461 | AP15: 89113099 | AQ15: 98846724 | AR15: 1.0103769e+08 | AS15: 1.0592337e+08 | AU15: 1.0864998e+08 | AV15: 1.1197105e+08 | AW15: 110900703 | AZ15: 1.0803812e+08 | BA15: 2.3738046e+08 | BB15: 1.10904e+08 | BC15: 1.147742e+08 | BD15: 1.1999948e+08 | BE15: 1.20886e+08 | BF15: 120778872 | BH15: 1.2091617e+08 | BI15: 1.2118699e+08 | BJ15: 121040684 | BK15: 1.2296005e+08 | BL15: 129701372 | BM15: 1.3299163e+08 | BN15: 133743755 | BO15: 132448001 | BP15: 136981850 | BQ15: 137779559 | BR15: 135254054 | BS15: 136462545 | BT15: 134162150 | BU15: 138637075 | BV15: 1.3949406e+08 | BW15: 1.3949406e+08 | BX15: 144178769 | BY15: 145023448 | BZ15: 143765225 | CA15: 146169076 | CB15: 158767125 | CC15: 1.6390882e+08 | CD15: 1.6687668e+08 | CE15: 175053653 | CF15: 1.8200531e+08 | CG15: 1.8822493e+08 | CH15: 1.9554765e+08 | CI15: 1.9441609e+08 | CJ15: 1.9441609e+08 | CK15: =CK16+193554184 -> 204144493 | CL15: 2.0049904e+08 | CM15: 2.0078144e+08 | CN15: 200576944 | CO15: 1.9792202e+08 | CP15: 207508084 | CQ15: 2.1203643e+08 | CR15: 2.1480735e+08 | CS15: 220509733 | CT15: 220509733 | CU15: 2.3114986e+08 | CV15: 244834214 | CW15: 2.4487058e+08 | CX15: 2.5019748e+08 | CY15: 2.5662217e+08 | CZ15: 2.5883019e+08 | DA15: 2.5470893e+08 | DB15: 2.6641078e+08 | DC15: 2.7551335e+08 | DD15: 2.8723039e+08 | DE15: 2.9256186e+08 | DF15: 2.948748e+08 | DG15: 2.9649364e+08 | DH15: 3.0807217e+08 | DI15: 3.05658e+08 | DJ15: 305657997 | DK15: 3.0997454e+08 | DL15: 3.1480338e+08 | DM15: 3.1467198e+08 | DN15: 3.2540896e+08 | DO15: 3.2880795e+08 | DP15: 3.2967017e+08 | DQ15: 3.3173253e+08 | DR15: 3.3652744e+08 | DS15: 3.4683106e+08 | DT15: 3.5043062e+08 | DU15: 3.517363e+08 | DW15: 358511202
B16: Allowance for Loan Loss | F16: 269422 | G16: 344629 | H16: 269422 | I16: 484871 | J16: 538844 | K16: 269422 | L16: 269422 | M16: 269422 | N16: 269422 | O16: 269422 | P16: 269422 | Q16: 269422 | R16: 269422 | S16: 269422 | T16: 269422 | U16: 0 | V16: 1993646 | W16: 2400000 | X16: 2400000 | Y16: 2400000 | Z16: 2400000 | AA16: 2400000 | AB16: 2400000 | AC16: 2400000 | AD16: 2400000 | AE16: 2400000 | AF16: 2400000 | AG16: 2400000 | AH16: 2400000 | AI16: 124089 | AJ16: 1869557 | AL16: 2400000 | AM16: 2400000 | AN16: 2400000 | AO16: -2400000 | AP16: 2400000 | AQ16: 2400000 | AR16: 2400000 | AS16: 2400000 | AU16: 2400000 | AV16: 3292568 | AW16: 6590309 | AZ16: 3292568 | BA16: 6585136 | BB16: 3292568 | BC16: 6599370 | BD16: 6874356.8 | BE16: 7387204.2 | BF16: 6178186 | BH16: 5771304.2 | BI16: 5838260.9 | BJ16: 8590309 | BK16: 0 | BL16: 5921870 | BM16: 7256136 | BN16: 6949166 | BO16: 7183267 | BP16: 7556873 | BQ16: 8948946 | BR16: 8619319 | BS16: 7902398 | BT16: 7949409 | BU16: 8452644 | BV16: 9590309 | BX16: 9590309 | BY16: 9590309 | BZ16: 9590309 | CA16: 9590309 | CB16: 9590309 | CC16: 9590309 | CD16: 9576686 | CE16: 9576686 | CF16: 9576686 | CG16: 9576686 | CH16: 9576686 | CI16: 10590309 | CJ16: 10590309 | CK16: ='[3]balance sheet'!$D$22 -> 10590309 | CL16: ='[4]balance sheet'!$D$22 -> 10590309 | CM16: 10590309 | CN16: 10590309 | CO16: ='[4]balance sheet'!$D$22 -> 10590309 | CP16: 10576686 | CQ16: 10576686 | CR16: 10575870 | CS16: 10575870 | CT16: 10575870 | CU16: 10575870 | CV16: 12575870 | CW16: 12575870 | CX16: 12575870 | CY16: 12575870 | CZ16: 12575870 | DA16: 12575870 | DB16: 12575870 | DC16: 12575870 | DD16: 12075870 | DE16: 12075870 | DF16: 12075870 | DG16: 12075870 | DH16: 12075870 | DI16: 14575870 | DJ16: 14575870 | DK16: 12075870 | DL16: 14075870 | DM16: 14075870 | DN16: 14075870 | DO16: 14075870 | DP16: 14075870 | DQ16: 14075870 | DR16: 14575870 | DS16: 14575870 | DT16: 14575870 | DU16: 14575870 | DW16: 18075870
B17: Account Receivables | C17: =SUM(C18:C20) -> 0 | D17: =SUM(D18:D20) -> 0 | E17: =SUM(E18:E20) -> 0 | F17: =SUM(F18:F20) -> 0 | G17: =SUM(G18:G20) -> 0 | H17: =SUM(H18:H20) -> 0 | I17: =SUM(I18:I20) -> 0 | J17: =SUM(J18:J20) -> 0 | ... S17: =SUM(S18:S20) -> 0 | AA17: 0 | AB17: 0 | AC17: 0 | AZ17: 0 | BA17: 0 | BB17: 0 | BC17: 0 | BD17: 0 | BE17: 0 | BH17: 0 | BI17: 115800 | BK17: 0 | BL17: 0 | BM17: 0 | BN17: 0 | BO17: 0 | BP17: 0 | BQ17: 0 | BR17: 0 | BS17: 0 | BT17: 0 | BU17: 0 | BV17: 0 | BX17: 0 | BY17: 0 | BZ17: 0 | CA17: 0 | CB17: 0 | CC17: 0 | CD17: 0 | CE17: 0 | CF17: 0 | CG17: 0 | CH17: 0 | CI17: 0 | DS17: 0 | DT17: 0 | DU17: 0
B18: Tax Recoverable | G18: 0 | AA18: 0 | AB18: 0 | AC18: 0 | AZ18: 0 | BA18: 0 | BB18: 0 | BC18: 0 | BD18: 0 | BE18: 0 | BH18: 0 | BI18: 0 | BK18: 0 | BL18: 0 | BM18: 0 | BN18: 0 | BO18: 0 | BP18: 0 | BQ18: 0 | BR18: 0 | BS18: 0 | BT18: 0 | BU18: 0 | BV18: 0 | BX18: 0 | BY18: 0 | BZ18: 0 | CA18: 0 | CB18: 0 | CC18: 0 | CD18: 0 | CE18: 0 | CF18: 0 | CG18: 0 | CH18: 0 | CI18: 0 | CJ18: 0 | CK18: 0 | CL18: 0 | CM18: 0 | CN18: 0 | CO18: 0 | CP18: 0 | CR18: 0 | CS18: 0 | CT18: 0 | CU18: 0 | CV18: 0 | CW18: 0 | CX18: 0 | CY18: 0 | CZ18: 0 | DA18: 0 | DB18: 0 | DC18: 0 | DD18: 0 | DE18: 0 | DF18: 0 | DG18: 0 | DH18: 0 | DI18: 0 | DK18: 0 | DL18: 0 | DM18: 0 | DN18: 0 | DO18: 0 | DP18: 0 | DQ18: 0 | DR18: 0 | DS18: 0 | DT18: 0 | DU18: 0
B19: Deferred Tax Assets | G19: 0 | AA19: 0 | AB19: 0 | AC19: 0 | AZ19: 0 | BA19: 0 | BB19: 0 | BC19: 0 | BD19: 0 | BE19: 0 | BH19: 0 | BI19: 115800 | BK19: 0 | BL19: 0 | BM19: 0 | BN19: 0 | BO19: 0 | BP19: 0 | BQ19: 0 | BR19: 0 | BS19: 0 | BT19: 0 | BU19: 0 | BV19: 0 | BX19: 0 | BY19: 0 | BZ19: 0 | CA19: 0 | CB19: 0 | CC19: 0 | CD19: 0 | CE19: 0 | CF19: 0 | CG19: 0 | CH19: 0 | CI19: 0 | CJ19: 0 | CK19: 0 | CL19: 0 | CM19: 0 | CN19: 0 | CO19: 0 | CP19: 0 | CR19: 0 | CS19: 0 | CT19: 0 | CU19: 0 | CV19: 0 | CW19: 0 | CX19: 0 | CY19: 0 | CZ19: 0 | DA19: 0 | DB19: 0 | DC19: 0 | DD19: 0 | DE19: 0 | DF19: 0 | DG19: 0 | DH19: 0 | DI19: 0 | DK19: 0 | DL19: 0 | DM19: 0 | DN19: 0 | DO19: 0 | DP19: 0 | DQ19: 0 | DR19: 0 | DS19: 0 | DT19: 0 | DU19: 0
B20: Retirement Benefit Assets | G20: 0 | AA20: 0 | AB20: 0 | AC20: 0 | AZ20: 0 | BA20: 0 | BB20: 0 | BC20: 0 | BD20: 0 | BE20: 0 | BF20: 12194820 | BH20: 12934820 | BI20: 12943020 | BK20: 0 | BL20: 0 | BM20: 0 | BN20: 0 | BO20: 0 | BP20: 0 | BQ20: 0 | BR20: 0 | BS20: 0 | BT20: 0 | BU20: 0 | BV20: 0 | BX20: 0 | BY20: 0 | BZ20: 0 | CA20: 0 | CB20: 0 | CC20: 0 | CD20: 0 | CE20: 0 | CF20: 0 | CG20: 0 | CH20: 0 | CI20: 0 | CJ20: 0 | CK20: 0 | CL20: 0 | CM20: 0 | CN20: 0 | CO20: 0 | CP20: 0 | CR20: 0 | CS20: 0 | CT20: 0 | CU20: 0 | CV20: 0 | CW20: 0 | CX20: 0 | CY20: 0 | CZ20: 0 | DA20: 0 | DB20: 0 | DC20: 0 | DD20: 0 | DE20: 0 | DF20: 0 | DG20: 0 | DH20: 0 | DI20: 0 | DK20: 0 | DL20: 0 | DM20: 0 | DN20: 0 | DO20: 0 | DP20: 0 | DQ20: 0 | DR20: 0 | DS20: 0 | DT20: 0 | DU20: 0
B21: Property and Equipment and Other Assets | C21: =SUM(C22:C26) -> 28544 | D21: =SUM(D22:D26) -> 67851 | E21: =SUM(E22:E26) -> 635468 | F21: =SUM(F22:F26) -> 2039439 | G21: =SUM(G22:G26) -> 5403162 | H21: =SUM(H22:H26) -> 5517271 | I21: =SUM(I22:I26) -> 4750838 | J21: =SUM(J22:J26) -> 11034542 | ... DW21: =SUM(DW22:DW26) -> 17961747
B22: Investment Properties | F22: 0 | G22: 0 | H22: 0 | J22: 0 | K22: 0 | L22: 0 | M22: 0 | N22: 0 | O22: 0 | P22: 0 | Q22: 0 | R22: 0 | S22: 0 | T22: 0 | U22: 0 | AA22: 0 | AB22: 0 | AC22: 0 | AZ22: 0 | BA22: 0 | BB22: 0 | BC22: 0 | BD22: 0 | BE22: 0 | BH22: 0 | BI22: 0 | BK22: 0 | BL22: 0 | BM22: 0 | BN22: 0 | BO22: 0 | BP22: 0 | BQ22: 0 | BR22: 0 | BS22: 0 | BU22: 0 | BV22: 0 | BX22: 0 | BY22: 0 | BZ22: 0 | CA22: 0 | CG22: 18105795 | CL22: 0 | CM22: 0 | CN22: 0 | CO22: 0 | CP22: 620249 | CQ22: 620249 | CR22: 620249 | CS22: 620249 | CT22: 620249 | CU22: 620249 | CV22: 580249 | CX22: 0 | CY22: 0 | CZ22: 0 | DA22: 0 | DB22: 0 | DC22: 0 | DD22: 0 | DE22: 0 | DF22: 0 | DG22: 0 | DH22: 0 | DI22: 0 | DK22: 0 | DL22: 0 | DM22: 0 | DN22: 0 | DO22: 0 | DP22: 620249 | DQ22: 620249 | DR22: 620249 | DS22: 620249 | DT22: 620249 | DU22: 620249
B23: Property and Equipment | C23: 28544 | D23: 67851 | E23: 609253 | F23: 691887 | G23: 4364687 | H23: 5375271 | I23: 4109038 | J23: 10750542 | K23: 5385636 | L23: 5385921 | M23: 5385921 | N23: 5397921 | O23: 5397921 | P23: 5397921 | Q23: 5517646 | R23: 5517646 | S23: 5623836 | T23: 5648766 | U23: 5671916 | V23: 4161589 | W23: 5709813 | X23: 5710413 | Y23: 5710688 | Z23: 5766068 | AA23: 5789568 | AB23: 5794678 | AC23: 5897898 | AD23: 5898098 | AE23: 5903168 | AF23: 6350418 | AG23: 6398798 | AH23: 6445228 | AI23: 4710275 | AJ23: 4710275 | AL23: 6517848 | AM23: 6538198 | AN23: 6547478 | AO23: 5789568 | AP23: 6707718 | AQ23: 6834418 | AR23: 6900800 | AS23: 6958800 | AU23: 7476357 | AV23: 7487007 | AW23: 5040538 | AZ23: 11040351 | BA23: 22128162 | BB23: 11080881 | BC23: 11423155 | BD23: 11287581 | BE23: 11365081 | BF23: 11792846 | BH23: 12512496 | BI23: 12513496 | BJ23: 9322504 | BK23: 12546470 | BL23: 12560046 | BM23: 12734146 | BN23: 12734146 | BO23: 13044888 | BP23: 13103178 | BQ23: 13125688 | BR23: 13195688 | BS23: 13201553 | BT23: 13201503 | BU23: 15977003 | BV23: 14409716 | BW23: 7872296.5 | BX23: 9244217 | BY23: 9244217 | BZ23: 9244217 | CA23: 23082854 | CB23: 17283839 | CC23: 19647299 | CD23: 19647299 | CE23: 17412276 | CF23: 17514216 | CG23: 0 | CH23: 18105795 | CI23: 9082567.9 | CJ23: 9656041.9 | CK23: 18272342 | CL23: 18272342 | CM23: 18272342 | CN23: 16423411 | CO23: 18650308 | CP23: 19012158 | CQ23: 19012158 | CR23: 19012158 | CS23: 19012158 | CT23: 19012158 | CU23: 16129752 | CV23: 10887952 | CW23: 10887952 | CX23: 19125047 | CY23: 19125047 | CZ23: 19125047 | DA23: 19125047 | DB23: 19466087 | DC23: 19466087 | DD23: 19721987 | DE23: 19721987 | DF23: 19721987 | DG23: 19735180 | DH23: 19735180 | DI23: 10208042 | DJ23: 10470169 | DK23: 10208042 | DL23: 10470169 | DM23: 10470169 | DN23: 10470169 | DO23: 10470169 | DP23: 12041267 | DQ23: 12041267 | DR23: 12273365 | DS23: 12273365 | DT23: 12403665 | DU23: 12403665 | DW23: 11312245
B24: Prepaid lease rentals | E24: 26215 | F24: 947552 | H24: 0 | J24: 0 | K24: 0 | L24: 0 | M24: 0 | N24: 0 | O24: 0 | P24: 0 | Q24: 0 | R24: 0 | S24: 0 | T24: 0 | U24: 0 | AA24: 0 | AB24: 0 | AC24: 0 | AD24: 0 | AE24: 0 | AF24: 0 | AG24: 0 | AH24: 0 | AL24: 0 | AM24: 0 | AN24: 0 | AO24: 0 | AP24: 0 | AQ24: 0 | AR24: 0 | AS24: 0 | AU24: 0 | AV24: 0 | AZ24: 0 | BA24: 0 | BB24: 0 | BC24: 0 | BD24: 0 | BE24: 0 | BH24: 0 | BI24: 0 | BK24: 0 | BL24: 0 | BM24: 0 | BN24: 0 | BO24: 0 | BP24: 0 | BQ24: 0 | BR24: 0 | BS24: 0 | BT24: 0 | BU24: 0 | BV24: 0 | BX24: 0 | BY24: 0 | BZ24: 0 | CA24: 0 | CK24: 0 | CL24: 0 | CM24: 0 | CN24: 0 | CO24: 0 | CP24: 0 | CQ24: 0 | CR24: 0 | CS24: 0 | CT24: 0 | CU24: 0 | CX24: 0 | CY24: 0 | CZ24: 0 | DA24: 0 | DB24: 0 | DC24: 0 | DD24: 0 | DE24: 0 | DF24: 0 | DG24: 0 | DH24: 0 | DI24: 0 | DK24: 0 | DL24: 0 | DM24: 0 | DN24: 0 | DO24: 0 | DP24: 0 | DQ24: 0 | DR24: 0 | DS24: 0 | DT24: 0 | DU24: 0
B25: Intangible Assets | F25: 0 | G25: 490000 | H25: 142000 | I25: 343000 | J25: 284000 | K25: 142000 | L25: 142000 | M25: 142000 | N25: 142000 | O25: 142000 | P25: 142000 | Q25: 142000 | R25: 142000 | S25: 142000 | T25: 142000 | U25: 142000 | V25: 273000 | W25: 142000 | X25: 142000 | Y25: 142000 | Z25: 142000 | AA25: 142000 | AB25: 142000 | AC25: 142000 | AD25: 142000 | AE25: 142000 | AF25: 142000 | AG25: 142000 | AH25: 142000 | AI25: 191100 | AJ25: 191100 | AL25: 142000 | AM25: 142000 | AN25: 142000 | AO25: 142000 | AP25: 142000 | AQ25: 142000 | AR25: 142000 | AS25: 142000 | AU25: 142000 | AV25: 142000 | AW25: 133770 | AZ25: 142000 | BA25: 284000 | BB25: 142000 | BC25: 142000 | BD25: 201000 | BE25: 201000 | BF25: 201000 | BH25: 201000 | BI25: 201000 | BJ25: 93639 | BK25: 201000 | BL25: 201000 | BM25: 201000 | BN25: 201000 | BO25: 201000 | BP25: 201000 | BQ25: 201000 | BR25: 201000 | BS25: 201000 | BT25: 201000 | BU25: 201000 | BV25: 201000 | BW25: 4323488 | BX25: 5936000 | BY25: 5936000 | BZ25: 5936000 | CA25: 5936000 | CB25: 5536000 | CC25: 5936000 | CD25: 5936000 | CE25: 5978500 | CF25: 5978500 | CG25: 5978500 | CH25: 5978500 | CI25: 4323488 | CJ25: 4650553 | CK25: 4565553 | CL25: 4565553 | CM25: 4565553 | CN25: 6021000 | CO25: 4565553 | CP25: 6021000 | CQ25: 6021000 | CR25: 6021000 | CS25: 6395076.1 | CT25: 6395076.1 | CU25: 6395076.1 | CV25: 4783235.9 | CW25: 4783235.9 | CX25: 6609738 | CY25: 6609738 | CZ25: 6609738 | DA25: 6609738 | DB25: 6609738 | DC25: 6609738 | DD25: 6703675.2 | DE25: 6703675.2 | DF25: 6703675.2 | DG25: 6703675.2 | DH25: 6703675.2 | DI25: 5304912.3 | DJ25: 5304912 | DK25: 5304912.3 | DL25: 5304912.3 | DM25: 5304912.3 | DN25: 6004912.3 | DO25: 6004912.3 | DP25: 6704412.3 | DQ25: 6609738.2 | DR25: 6609738.2 | DS25: 6609738.2 | DT25: 6609738.2 | DU25: 6609738.2 | DW25: 6383993
B26: Other Assets | F26: 400000 | G26: 548475 | H26: 0 | I26: 298800 | J26: 0 | K26: 0 | L26: 0 | M26: 0 | N26: 0 | O26: 0 | P26: 0 | Q26: 0 | R26: 0 | S26: 0 | T26: 0 | U26: 0 | V26: 398800 | AA26: 0 | AB26: 0 | AC26: 0 | AI26: =398800+309647 -> 708447 | AJ26: 398800 | AM26: 93900 | AN26: 148400 | AP26: 148400 | AQ26: 148400 | AR26: 148400 | AS26: 148400 | AU26: 173274 | AV26: 173274 | AW26: 398800 | AZ26: 173274 | BA26: 400548 | BB26: 200274 | BC26: 26745740 | BD26: 200274 | BE26: 200974 | BF26: 200974 | BH26: 221324 | BI26: 228524 | BJ26: 398800 | BK26: 228524 | BL26: 233024 | BM26: 233024 | BN26: 233024 | BO26: 233024 | BP26: 233024 | BQ26: 233024 | BR26: 233024 | BS26: 233024 | BT26: 233024 | BU26: 233024 | BV26: 233024 | BW26: 398800 | BX26: 233024 | BY26: 233024 | BZ26: 233024 | CA26: 233024 | CB26: 233024 | CC26: 233024 | CD26: 233024 | CE26: 233024 | CF26: 233024 | CG26: 233024 | CH26: 233024 | CJ26: 398800 | CK26: ='[4]balance sheet'!$D$14 -> 398800 | CL26: ='[4]balance sheet'!$D$14 -> 398800 | CM26: 398800 | CN26: 233024 | CO26: ='[4]balance sheet'!$D$14 -> 398800 | CP26: ='[4]balance sheet'!$D$14 -> 398800 | CQ26: ='[4]balance sheet'!$D$14 -> 398800 | CR26: ='[4]balance sheet'!$D$14 -> 398800 | CS26: 283308 | CT26: 283308 | CU26: 283308 | CV26: 283308 | CW26: 283308 | CX26: 283308 | CY26: 283308 | CZ26: 283308 | DA26: 283308 | DB26: 283308 | DC26: 283308 | DD26: 233024 | DE26: 233024 | DF26: 233024 | DG26: 233024 | DH26: 233024 | DI26: 283009 | DJ26: 283009 | DK26: 233024 | DL26: 233024 | DM26: 233024 | DN26: 233024 | DO26: 233024 | DP26: 233024 | DQ26: 233024 | DR26: 233024 | DS26: 233024 | DT26: 233024 | DU26: 233024 | DW26: 265509
B27: Total Assets | C27: =C5+C8+C9+C14+C17+C21 -> 3475410 | D27: =D5+D8+D9+D14+D17+D21 -> 8750647 | E27: =E5+E8+E9+E14+E17+E21 -> 19015501 | F27: =F5+F8+F9+F14+F17+F21 -> 35649419 | G27: =G5+G8+G9+G14+G17+G21 -> 48282362 | H27: =H5+H8+H9+H14+H17+H21 -> 75358469 | I27: =I5+I8+I9+I14+I17+I21 -> 71384601 | J27: =J5+J8+J9+J14+J17+J21 -> 1.5365653e+08 | ... DW27: =DW5+DW8+DW9+DW14+DW17+DW21 -> 415120522
B28: Savings Deposits | C28: 97922 | D28: 531852 | E28: 1324050 | F28: 2594007 | G28: 8012418 | H28: 1189925 | I28: 11468318 | J28: 2349166 | K28: 1377625.3 | L28: 1278331.3 | M28: 1328033.3 | N28: 1329475.3 | O28: 1518621.8 | P28: 2012881.1 | Q28: 2302081.1 | R28: 1783425.1 | S28: 2105182.1 | T28: 2012095.1 | U28: 1983098.5 | V28: 17644747 | W28: 2198601 | X28: 1844070.5 | Y28: 2343143.5 | Z28: 2214796.5 | AA28: 3183600.5 | AB28: 1848801.5 | AC28: 2550142.5 | AD28: 3045696.5 | AE28: 3176476.5 | AF28: 2945999.5 | AG28: 3315428.5 | AH28: 3139236.5 | AI28: 31883601 | AJ28: 29828486 | AL28: 4912377.5 | AM28: 4912377.5 | AN28: 4912377.5 | AO28: 3183600.5 | AP28: 4912377.5 | AQ28: 4912377.5 | AR28: 4912377.5 | AS28: 4912377.5 | AU28: 4912377.5 | AV28: 29192642 | AW28: 30360370 | AZ28: -29198403 | BA28: -64185018 | BB28: 33494205 | BC28: 25201033 | BD28: 23344433 | BE28: 25309217 | BF28: 25532401 | BH28: 26278985 | BI28: 22442805 | BJ28: 28384296 | BK28: 9580252 | BL28: 28082298 | BM28: 28008192 | BN28: 28859163 | BO28: 25848317 | BP28: 27772412 | BQ28: 27420646 | BR28: 27389852 | BS28: 26153082 | BT28: 24495777 | BU28: 27357755 | BV28: 26798754 | BW28: 26798753 | BX28: 30867006 | BY28: 25344162 | BZ28: 30618493 | CA28: 26162355 | CB28: 32755176 | CC28: 33545089 | CD28: 33829353 | CE28: 33520751 | CF28: 36163642 | CG28: 34149048 | CH28: 34248882 | CI28: 30780081 | CJ28: 36226840 | CK28: 35092536 | CL28: 35675590 | CM28: 34961927 | CN28: 36238363 | CO28: 35279535 | CP28: 40183834 | CQ28: 35234293 | CR28: 36706312 | CS28: 37542853 | CT28: 37542853 | CU28: 37406573 | CV28: 30684412 | CW28: 42490601 | CX28: 40356510 | CY28: 44126736 | CZ28: 44833373 | DA28: 44757038 | DB28: 43973474 | DC28: 45969818 | DD28: 47515134 | DE28: 48225265 | DF28: 54158548 | DG28: 44673424 | DH28: 46899778 | DI28: 43754701 | DJ28: 53205532 | DK28: 47784080 | DL28: 46326760 | DM28: 47641337 | DN28: 51852990 | DO28: 46366800 | DP28: 46819844 | DQ28: 46161312 | DR28: 46858158 | DS28: 44492963 | DT28: 46474692 | DU28: 47956549 | DW28: 42297148
B29: Short Term Deposits | F29: 0 | G29: 0 | H29: 1013916 | J29: 2030127 | K29: 1016211 | L29: 1016211 | M29: 1016211 | N29: 1016211 | O29: 1016211 | P29: 1016211 | Q29: 1016211 | R29: 1016211 | S29: 1016211 | T29: 1016211 | U29: 1016211 | W29: 1016211 | X29: 1016211 | Y29: 1016211 | Z29: 1016211 | AA29: 1016211 | AB29: 1016211 | AC29: 1016211 | AD29: 1016211 | AE29: 1016211 | AF29: 1016211 | AG29: 1016211 | AH29: 1016211 | AL29: 1016211 | AM29: 1016211 | AN29: 1016211 | AO29: 1016211 | AP29: 1016211 | AQ29: 1016211 | AR29: 1016211 | AS29: 1016211 | AU29: 1016211 | AV29: 1159711 | AZ29: -1475411 | BA29: 3605506 | BB29: 1782753 | BC29: 3148622 | BD29: 8668392.7 | BE29: 9277616.8 | BF29: 9862176.3 | BH29: 7066568.6 | BI29: 9132841.2 | BK29: 24370316 | BL29: 9395007 | BM29: 10169515 | BN29: 8778393 | BO29: 7731382 | BP29: 7631577 | BQ29: 8317507 | BR29: 10195866 | BS29: 10234420 | BT29: 9926187 | BU29: 9191558 | BV29: 0 | BX29: 8600445 | BY29: 8176402 | BZ29: 9164766 | CA29: 9164766 | CB29: 10717396 | CC29: 11124406 | CD29: 10098770 | CE29: 10279538 | CF29: 11160511 | CG29: 11377844 | CH29: 11248874 | CI29: 5037258.6 | CK29: 10582010 | CL29: 10863676 | CM29: 11904692 | CN29: 12897686 | CO29: 12194355 | CP29: 14785157 | CQ29: 14184351 | CR29: 14835886 | CS29: 15177331 | CT29: 15177331 | CU29: 14977595 | CV29: 11806189 | CX29: 14977223 | CY29: 14874509 | CZ29: 15219389 | DA29: 14921329 | DB29: 15617402 | DC29: 15532941 | DD29: 16514934 | DE29: 14574735 | DF29: 14527331 | DG29: 17544251 | DH29: 18873175 | DI29: 8790669.6 | DK29: 12549488 | DL29: 9442322.9 | DM29: 12515784 | DN29: 7610901.4 | DO29: 8428823.2 | DP29: 13122261 | DQ29: 13735453 | DR29: 10632718 | DS29: 10933569 | DT29: 11827028 | DU29: 11884327 | DW29: 16839455
B30: Non withdrawable Deposits | C30: 2181426 | D30: 5388952 | E30: 7001000 | F30: 14533589 | G30: 21381443 | H30: 43845984 | I30: 32277459 | J30: 89972427 | K30: 46620951 | L30: 49122630 | M30: 50342190 | N30: 50954933 | O30: 52579322 | P30: 54490771 | Q30: 55824059 | R30: 57102659 | S30: 59031894 | T30: 58627230 | U30: 59062799 | V30: 44483332 | W30: 60320341 | X30: 59372074 | Y30: 62934368 | Z30: 65395641 | AA30: 67369388 | AB30: 70695032 | AC30: 69971662 | AD30: 72391511 | AE30: 75061343 | AF30: 77676333 | AG30: 79274547 | AH30: 79342488 | AI30: 61929319 | AJ30: 61929319 | AL30: 82076780 | AM30: 82076780 | AN30: 82089980 | AO30: 67369388 | AP30: 82103180 | AQ30: 81999260 | AR30: 82007260 | AS30: 82020260 | AU30: 82034260 | AV30: 77417125 | AW30: 81840305 | AZ30: -83429354 | BA30: -1.845848e+08 | BB30: 91498367 | BC30: 91694235 | BD30: 93266976 | BE30: 95468682 | BF30: 93033255 | BH30: 94525854 | BI30: 92858060 | BJ30: 92858059 | BK30: 96054149 | BL30: 96140020 | BM30: 98721123 | BN30: 100460695 | BO30: 101546557 | BP30: 102510413 | BQ30: 103917025 | BR30: 106196242 | BS30: 107388717 | BT30: 109324774 | BU30: 109324774 | BV30: 111455182 | BW30: 1.1145518e+08 | BX30: 113743409 | BY30: 114087828 | BZ30: 116889196 | CA30: 119824972 | CB30: 123846171 | CC30: 126507301 | CD30: 130121236 | CE30: 1.3331167e+08 | CF30: 1.3696544e+08 | CG30: 1.3896911e+08 | CH30: 1.4111165e+08 | CI30: 35817340 | CJ30: 1.3914883e+08 | CK30: 1.433023e+08 | CL30: 1.465425e+08 | CM30: 149802524 | CN30: 152117541 | CO30: 1.5393335e+08 | CP30: 1.5629047e+08 | CQ30: 1.5882949e+08 | CR30: 161473507 | CS30: 1.6634508e+08 | CT30: 1.6634508e+08 | CU30: 1.6900733e+08 | CV30: 1.7075954e+08 | CW30: 1.7075954e+08 | CX30: 1.7421812e+08 | CY30: 1.77314e+08 | CZ30: 1.8102102e+08 | DA30: 1.8265193e+08 | DB30: 1.8597832e+08 | DC30: 1.8844333e+08 | DD30: 1.918884e+08 | DE30: 1.9481076e+08 | DF30: 1.9720545e+08 | DG30: 1.9800797e+08 | DH30: 2.014376e+08 | DI30: 1.9872373e+08 | DJ30: 198723727 | DK30: 1.9876393e+08 | DL30: 2.0261319e+08 | DM30: 2.0705445e+08 | DN30: 2.0941105e+08 | DO30: 2.12208e+08 | DP30: 2.1481892e+08 | DQ30: 217682182 | DR30: 2.1984675e+08 | DS30: 2.2445341e+08 | DT30: 2.2629534e+08 | DU30: 2.29864e+08 | DW30: 226107824
B31: Total Deposit Liabilities | C31: =SUM(C28:C30) -> 2279348 | D31: =SUM(D28:D30) -> 5920804 | E31: =SUM(E28:E30) -> 8325050 | F31: =SUM(F28:F30) -> 17127596 | G31: =SUM(G28:G30) -> 29393861 | H31: =SUM(H28:H30) -> 46049825 | I31: =SUM(I28:I30) -> 43745777 | J31: =SUM(J28:J30) -> 94351720 | ... DW31: =SUM(DW28:DW30) -> 285244427
B32: Accounts Payable Other Liabilities | C32: =SUM(C33:C38) -> 756201 | D32: =SUM(D33:D38) -> 2092982 | E32: =SUM(E33:E38) -> 1853609 | F32: =SUM(F33:F38) -> 6664957 | G32: =SUM(G33:G38) -> 2958353 | H32: =SUM(H33:H38) -> 4033865 | I32: =SUM(I33:I38) -> 7334465 | J32: =SUM(J33:J38) -> 8185123.3 | ... DW32: =SUM(DW33:DW38) -> 32358567
B33: Tax Payable | F33: 7092 | G33: 5134 | H33: 0 | J33: 0 | K33: 0 | L33: 0 | M33: 0 | N33: 0 | O33: 0 | P33: 0 | Q33: 0 | R33: 0 | S33: 0 | T33: 0 | U33: 0 | V33: 4862 | AA33: 0 | AB33: 0 | AC33: 0 | AH33: 0 | AI33: 3866 | AJ33: 3866 | AW33: 305555 | AZ33: 0 | BA33: 0 | BB33: 0 | BC33: 0 | BD33: 0 | BE33: 0 | BF33: 0 | BH33: 0 | BI33: 0 | BJ33: 302193.2 | BK33: 302193 | BL33: 302193 | BM33: 0 | BN33: 0 | BO33: 0 | BP33: 0 | BQ33: 0 | BR33: 0 | BS33: 0 | BT33: 0 | BU33: 0 | BV33: 218211 | BW33: 218211.94 | BX33: 0 | BY33: 0 | BZ33: 0 | CA33: 0 | CJ33: 381333.67 | CK33: 381333.67 | CL33: 381333.67 | CM33: 381333.67 | CN33: 381333.67 | CU33: 0 | CV33: 368496.03 | CW33: 368496.03 | CX33: 368496.03 | CY33: 368496.03 | CZ33: 0 | DA33: 0 | DB33: 0 | DC33: 0 | DD33: 44702.03 | DE33: 47336.4 | DF33: 62669.58 | DG33: 70668.44 | DH33: 52908.43 | DI33: 726933.25 | DJ33: 726933 | DK33: 726933.25 | DL33: 726933.25 | DM33: 819744.25 | DN33: 0 | DO33: 0 | DP33: 0 | DQ33: 0 | DR33: 0 | DS33: 0 | DT33: 0 | DU33: 0 | DW33: 322500
B34: Dividends Payable | C34: 255924 | D34: 457806 | E34: 1138470 | F34: 1380040 | H34: 0 | I34: =719039+2565961 -> 3285000 | J34: 377 | K34: 10103 | L34: 23996 | M34: 26089 | N34: -3201704 | O34: -3201409 | P34: -3201221 | Q34: -3201221 | R34: -3200427 | S34: -3193581.5 | T34: -3195198 | U34: 0 | V34: =160000+3113833+617260 -> 3891093 | W34: 14127.3 | X34: 13712.5 | Y34: 4380 | Z34: 4380 | AA34: 2981 | AB34: 1657 | AC34: 517 | AD34: 763 | AE34: -1284.5 | AF34: -1284.5 | AG34: -1284.5 | AH34: -2486 | AI34: =4954346+200000+1011357 -> 6165703 | AJ34: =4954346+200000+1011357 -> 6165703 | AL34: -2485 | AM34: -2485 | AN34: -2485 | AO34: 2981 | AP34: -2485 | AQ34: -894.5 | AR34: -1226 | AS34: -1226 | AU34: 55215 | AW34: 608151 | AZ34: -1539 | BA34: -2700 | BB34: 1350 | BC34: 4839 | BD34: 0 | BE34: 0 | BF34: 0 | BH34: 0 | BI34: 0 | BJ34: 2525539 | BK34: 2525539 | BL34: 0 | BM34: 0 | BN34: 0 | BO34: 0 | BP34: 0 | BQ34: 0 | BR34: 0 | BS34: 0 | BT34: 0 | BU34: 0 | BV34: 2719777 | BW34: 2719777.6 | BX34: 0 | BY34: 0 | BZ34: 0 | CA34: 0 | CB34: 0 | CC34: 0 | CD34: 0 | CE34: 0 | CF34: 0 | CG34: 0 | CH34: 0 | CI34: 0 | CJ34: 11521824 | CK34: 11521824 | CL34: 11521824 | CM34: 177375.54 | CN34: 177375.54 | CO34: 0 | CP34: 0 | CR34: 0 | CS34: 0 | CT34: 0 | CU34: 0 | CV34: 0 | CW34: 15546768 | CX34: 15546768 | CY34: 15546768 | CZ34: 1316555.6 | DA34: 0 | DB34: 0 | DC34: 0 | DD34: 0 | DE34: 0 | DF34: 0 | DG34: 0 | DH34: 0 | DI34: 20450419 | DJ34: 20052971 | DK34: 20450419 | DL34: 20450419 | DM34: 0 | DN34: 0 | DO34: 0 | DP34: 0 | DQ34: 0 | DR34: 0 | DS34: 0 | DT34: 0 | DU34: 0 | DW34: 24345394
B35: Deferred Tax Liability | C35: 6107 | D35: 7900 | E35: 9000 | F35: 555360 | G35: 33850 | H35: 0 | J35: 0 | K35: 0 | L35: 0 | M35: 0 | N35: 0 | O35: 0 | P35: 0 | Q35: 0 | R35: 0 | S35: 0 | T35: 0 | U35: 0 | AA35: 0 | AB35: 0 | AC35: 0 | AD35: 0 | AE35: 0 | AF35: 0 | AG35: 0 | AH35: 0 | AL35: 0 | AM35: 0 | AN35: 0 | AO35: 0 | AP35: 0 | AQ35: 0 | AR35: 0 | AS35: 0 | AU35: 0 | AZ35: 0 | BA35: 0 | BB35: 0 | BC35: 0 | BD35: 0 | BE35: 0 | BF35: 0 | BH35: 0 | BI35: 0 | BK35: 0 | BL35: 0 | BM35: 0 | BN35: 0 | BO35: 0 | BP35: 0 | BQ35: 0 | BR35: 0 | BS35: 0 | BT35: 0 | BU35: 0 | BV35: 0 | BX35: 0 | BY35: 0 | BZ35: 0 | CA35: 0 | CB35: 0 | CC35: 0 | CD35: 0 | CE35: 0 | CF35: 0 | CG35: 0 | CH35: 0 | CI35: 0 | CO35: 0 | CP35: 0 | CR35: 0 | CS35: 0 | CT35: 0 | CU35: 0 | CX35: 0 | CY35: 0 | CZ35: 0 | DA35: 0 | DB35: 0 | DC35: 0 | DD35: 0 | DE35: 0 | DF35: 0 | DG35: 0 | DH35: 0 | DI35: 0 | DK35: 0 | DL35: 0 | DM35: 0 | DN35: 0 | DO35: 0 | DP35: 0 | DQ35: 0 | DR35: 0
B36: Retirement Benefits Liability | F36: 0 | G36: 0 | H36: 0 | J36: 0 | K36: 0 | L36: 0 | M36: 0 | N36: 0 | O36: 0 | P36: 0 | Q36: 0 | R36: 0 | S36: 0 | T36: 0 | U36: 0 | AA36: 0 | AB36: 0 | AC36: 0 | AD36: 0 | AE36: 0 | AF36: 0 | AG36: 0 | AH36: 0 | AL36: 0 | AM36: 0 | AN36: 0 | AO36: 0 | AP36: 0 | AQ36: 0 | AR36: -133500 | AS36: -133500 | AU36: -133500 | AZ36: 0 | BA36: 0 | BB36: 0 | BC36: 0 | BD36: 0 | BE36: 0 | BF36: 0 | BH36: 0 | BI36: 0 | BK36: 0 | BL36: 0 | BM36: 0 | BN36: 0 | BO36: 0 | BP36: 0 | BQ36: 0 | BR36: 0 | BS36: 0 | BT36: 0 | BU36: 0 | BV36: 0 | BX36: 0 | BY36: 0 | BZ36: 0 | CA36: 0 | CB36: 0 | CC36: 0 | CD36: 0 | CE36: 0 | CF36: 0 | CG36: 0 | CH36: 0 | CI36: 0 | CM36: 0 | CO36: 0 | CP36: 0 | CR36: 0 | CS36: 0 | CT36: 0 | CU36: 0 | CV36: 403800 | CX36: 403800 | CY36: 403800 | CZ36: 403800 | DA36: 253800 | DB36: 253800 | DC36: 253800 | DD36: 253800 | DE36: 253800 | DF36: 253800 | DG36: 253800 | DH36: 253800 | DI36: 373800 | DK36: 373800 | DL36: 373800 | DM36: 373800 | DN36: 216800 | DO36: 216800 | DP36: 216800 | DQ36: 216800 | DR36: 216800 | DS36: 216800 | DT36: 216800 | DU36: 216800
B37: Other Liabilities | C37: 494170 | D37: 627276 | E37: 706139 | F37: 1851747 | G37: 2359159 | H37: 0 | I37: 15600 | J37: 117016.35 | K37: 224978.16 | L37: 384080.62 | M37: 513229.93 | N37: 605517.59 | O37: 718155.76 | P37: 822150.09 | Q37: 925848.2 | R37: 1064791.7 | S37: 1199169.6 | T37: 1332083.5 | U37: 25987 | V37: =325156-956+328084 -> 652284 | W37: 152926.97 | X37: 271513.04 | Y37: 564591.85 | Z37: 710727.24 | AA37: 844251.81 | AB37: 810566.63 | AC37: 1065084.7 | AD37: 1167995.9 | AE37: 1293415.7 | AF37: 227377.15 | AG37: 362579.85 | AH37: 500215.28 | AI37: =362413 -> 362413 | AJ37: =362413 -> 362413 | AL37: 274890.46 | AM37: 232621.46 | AN37: 569943.98 | AO37: 844251.81 | AP37: 896396.4 | AQ37: 1373975.2 | AR37: 1531072.4 | AS37: 1736787.2 | AU37: 1979005.9 | AV37: 63416329 | AW37: =5434834+200000+63649 -> 5698483 | AZ37: -64079015 | BA37: -1.2848413e+08 | BB37: 5729157 | BC37: 30460891 | BD37: 3501403 | BE37: 0 | BF37: 0 | BH37: 0 | BI37: 0 | BJ37: =300000+39600+6911689 -> 7251289 | BK37: 7283122 | BL37: 7283122 | BM37: 0 | BN37: 0 | BO37: 0 | BP37: 0 | BQ37: 0 | BR37: 0 | BS37: 0 | BT37: 0 | BU37: 0 | BV37: 2049850 | BW37: =500000+1549850+9040189.61+9590309 -> 20680349 | BX37: 0 | BY37: 2116369 | BZ37: 2276468 | CA37: 2076468 | CB37: 1771961 | CC37: 1771961 | CD37: 1795603 | CE37: 1796615 | CF37: 1829767.9 | CG37: 1840835.5 | CH37: 1764496.1 | CI37: 1722240 | CJ37: =300000+1813240 -> 2113240 | CK37: 2374278.6 | CL37: 1839218.2 | CM37: 1850661.2 | CN37: 1736618 | CO37: 1730259 | CP37: 1820433 | CQ37: 1884155 | CR37: 1754651 | CS37: 1849421.6 | CT37: 1809947.4 | CU37: 1747750.4 | CV37: 2222863.2 | CW37: 2441055.3 | CX37: 2037255.3 | CY37: 1660932.5 | CZ37: 2106973.5 | DA37: 2468343.5 | DB37: 2086577.4 | DC37: 1382770.4 | DD37: 1402311.6 | DE37: 1463850.4 | DF37: 1463850.4 | DG37: 1339358.2 | DH37: 1395192.5 | DI37: 2062185 | DJ37: 2469034 | DK37: 1865648.1 | DL37: 2035223.5 | DM37: 1757168.2 | DN37: 1756141.7 | DO37: 1756141.7 | DP37: 1685208.4 | DQ37: 1543337.3 | DR37: 1553728.5 | DS37: 1481577.4 | DT37: 1463267.6 | DU37: 1426262.9 | DW37: 1845338
B38: External Borrowings | D38: 1000000 | F38: 2870718 | G38: 560210 | H38: 4033865 | I38: 4033865 | J38: 8067730 | K38: 3884335 | L38: 3884335 | M38: 3724529 | N38: 3724529 | O38: 3724529 | P38: 3365209 | Q38: 3250954 | R38: 3250954 | S38: 3250954 | T38: 3250954 | U38: 2262103 | V38: 2073269 | W38: 2262103 | X38: 2262103 | Y38: 2262103 | Z38: 1896774 | AA38: 1896774 | AB38: 1896774 | AC38: 1896774 | AD38: 1896774 | AE38: 1896774 | AF38: 1896774 | AG38: 776826 | AH38: 0 | AO38: 1896774 | AZ38: 0 | BA38: 0 | BB38: 0 | BC38: 0 | BD38: 0 | BE38: 0 | BF38: 0 | BH38: 0 | BI38: 0 | BK38: 0 | BL38: 0 | BP38: 0 | BT38: 0 | BU38: 5500000 | BV38: 5347222 | BW38: 5347222 | BX38: 5347222 | BY38: 5041666 | BZ38: 4888888 | CA38: 4736110 | CB38: 4583332 | CC38: 4430500 | CD38: 4268269 | CE38: 4067710 | CF38: 3852835 | CG38: 13701781 | CH38: 13532843 | CJ38: 13317968 | CK38: 12256156 | CL38: 12084076 | CM38: 11869201 | CN38: 10935639 | CO38: 10781446 | CP38: 10626229 | CQ38: 9564417 | CR38: 9369317 | CS38: 8969554 | CT38: 9184429 | CU38: 7930131 | CV38: 7752577 | CW38: 7752577 | CX38: 6674015 | CY38: 6492640 | CZ38: 6313114.7 | DA38: 5251302.7 | DB38: 5040426.9 | DC38: 14825552 | DD38: 13487615 | DE38: 12781740 | DF38: 12075865 | DG38: 11228928 | DH38: 10543180 | DI38: 12162420 | DJ38: 12092325 | DK38: 10681516 | DL38: 10681516 | DM38: 7182065.3 | DN38: 6691065.3 | DO38: 7318252.3 | DP38: 7012352.3 | DQ38: 6661352.3 | DR38: 6607372 | DS38: 6607372 | DT38: 5627372 | DU38: 5602949 | DW38: 5845335
B39: Total Liabilities | C39: =C32+C31 -> 3035549 | D39: =D32+D31 -> 8013786 | E39: =E32+E31 -> 10178659 | F39: =F32+F31 -> 23792553 | G39: =G32+G31 -> 32352214 | H39: =H32+H31 -> 50083690 | I39: =I32+I31 -> 51080242 | J39: =J32+J31 -> 1.0253684e+08 | ... DW39: =DW32+DW31 -> 317602994
B40: Share Capital | C40: 358000 | D40: 618000 | E40: 7470000 | F40: 10188316 | G40: 13099989 | H40: 16896221 | I40: 15978641 | J40: 33927742 | K40: 17383213 | L40: 17974930 | M40: 18032037 | N40: 18444575 | O40: 18585194 | P40: 19175829 | Q40: 18691824 | R40: 18921949 | S40: 19717783 | T40: 20111540 | U40: 19718355 | V40: 18898149 | W40: 20128307 | X40: 21027549 | Y40: 21308409 | Z40: 23736308 | AA40: 24389735 | AB40: 25091160 | AC40: 26050349 | AD40: 26849736 | AE40: 27104749 | AF40: 26346064 | AG40: 27544270 | AH40: 27907588 | AI40: 21766249 | AJ40: 21766249 | AL40: 35545041 | AM40: 35304832 | AN40: 36720050 | AO40: 24389735 | AP40: 46118892 | AQ40: 49332736 | AR40: 53888952 | AS40: 57802515 | AU40: 60964425 | AV40: 31786378 | AW40: 23368005 | AZ40: -32128988 | BA40: -64836010 | BB40: 24212302 | BC40: 24338933 | BD40: 24484113 | BE40: 24627428 | BF40: 24808583 | BG40: 0 | BH40: 25137577 | BI40: 25255387 | BJ40: 25255387 | BK40: 25332452 | BL40: 25488292 | BM40: 25892885 | BN40: 26065897 | BO40: 26305008 | BP40: 26514691 | BQ40: 27608561 | BR40: 28155319 | BS40: 28590761 | BT40: 28850953 | BU40: 29309422 | BV40: 29583093 | BW40: 29583093 | BX40: 29760294 | BY40: 29914576 | BZ40: 30548189 | CA40: 30655114 | CB40: 30821674 | CC40: 30945348 | CD40: 31105148 | CE40: 31242651 | CF40: 31416532 | CG40: 31574245 | CH40: 31850792 | CI40: 31984937 | CJ40: 31984937 | CK40: 32177150 | CL40: 32428751 | CM40: 32816015 | CN40: 32990257 | CO40: 33158170 | CP40: 33451675 | CQ40: 33844749 | CR40: 34213651 | CS40: 34987929 | CT40: 34582419 | CU40: 35649779 | CV40: 35996598 | CW40: 35996598 | CX40: 36244310 | CY40: 36616409 | CZ40: 37617520 | DA40: 38070246 | DB40: 38388355 | DC40: 39005546 | DD40: 39438880 | DE40: 39852688 | DF40: 40195569 | DG40: 40528805 | DH40: 40976875 | DI40: 41367362 | DJ40: 41367361 | DK40: 41875544 | DL40: 42391440 | DM40: 46886541 | DN40: 47847277 | DO40: 48264409 | DP40: 49922679 | DQ40: 50966752 | DR40: 51420469 | DS40: 51980328 | DT40: 52440976 | DU40: 52867806 | DW40: 53313338
B41: Capital Grants | H41: 0 | J41: 0 | K41: 0 | L41: 0 | M41: 0 | N41: 0 | O41: 0 | P41: 0 | Q41: 0 | R41: 0 | S41: 0 | T41: 0 | U41: 0 | AA41: 0 | AB41: 0 | AC41: 0 | AZ41: 0 | BA41: 0 | BB41: 0 | BC41: 0 | BD41: 0 | BE41: 0 | BF41: 0 | BG41: 0 | BH41: 0 | BI41: 0 | BP41: 0 | BQ41: 0 | BR41: 0 | BS41: 0 | BT41: 0 | BU41: 0 | BV41: 0 | BX41: 0 | BY41: 0 | BZ41: 0 | CA41: 0 | CB41: 0 | CM41: 0 | CX41: 0 | CY41: 0 | CZ41: 0 | DA41: 0 | DB41: 0 | DC41: 0 | DD41: 0 | DE41: 0 | DF41: 0 | DG41: 0 | DH41: 0 | DI41: 0 | DK41: 0 | DL41: 0 | DM41: 0 | DN41: 0 | DO41: 0 | DP41: 0 | DQ41: 0 | DR41: 0 | DS41: 0 | DT41: 0 | DU41: 0
B42: Retained Earnings | C42: =SUM(C43:C44) -> 24089 | D42: =SUM(D43:D44) -> 46089 | E42: =SUM(E43:E44) -> 88005 | F42: =SUM(F43:F44) -> 211308 | G42: =SUM(G43:G44) -> 325421 | H42: =SUM(H43:H44) -> 5055549.1 | I42: =SUM(I43:I44) -> 394020 | J42: =SUM(J43:J44) -> 10499631 | ... DW42: =SUM(DW43:DW44) -> 17077729
B43: Prior Year Retained Earnings | C43: 4289 | D43: 24089 | E43: 46089 | F43: 88005 | H43: -145885.39 | I43: 325421 | J43: -291770.28 | K43: -145884.89 | L43: -145884.89 | M43: -145884.89 | N43: -145884.89 | O43: -145884.89 | P43: -145884.89 | Q43: -145884.89 | R43: -145884.89 | S43: -145884.89 | T43: -145884.89 | U43: -87726.29 | V43: 394020 | W43: -7452.29 | X43: -7452.29 | Y43: -3683680.9 | Z43: -3418305.2 | AA43: -3418305.2 | AB43: -3418305.2 | AC43: -2967366 | AD43: -2967366 | AE43: -2967366 | AF43: -2967366 | AG43: -2967366 | AH43: 875509.25 | AI43: 154751 | AJ43: 154751 | AL43: 875609.25 | AM43: 875609.25 | AN43: 986609.25 | AO43: -3418305.2 | AP43: 986609.25 | AQ43: 1006230.9 | AR43: 1006230.9 | AS43: 1006230.9 | AU43: 1006230.9 | AV43: -66657178 | AW43: 1327040 | AZ43: -1327040 | BA43: -2654080 | BB43: 1327040 | BC43: 1327040 | BD43: 2406482 | BE43: 2406482 | BF43: 2406482 | BG43: 0 | BH43: 2506482 | BI43: 3184803 | BJ43: 2618533 | BK43: 3733306 | BL43: 3733306 | BM43: 4883577 | BN43: 4883577 | BO43: 4883577 | BP43: 4883577 | BQ43: 4883577 | BR43: 4883577 | BS43: 4883577 | BT43: 4883577 | BU43: 4883577 | BV43: 4883577 | BW43: 6169776 | BX43: 6169777 | BY43: 6169777 | BZ43: 6169777 | CA43: 6169777 | CB43: 6169777 | CC43: 6169777 | CD43: 6169777 | CE43: 6169777 | CF43: 6169777 | CG43: 6169777 | CH43: 6169777 | CI43: 19824480 | CJ43: 6941524 | CK43: 6941524 | CL43: 6941523 | CM43: 6941523 | CN43: 6941523 | CO43: 6941523 | CP43: 6941523 | CQ43: 6941523 | CR43: 6941523 | CS43: 6941523 | CT43: 6941523 | CU43: 6941523 | CV43: 6941523 | CW43: =10932919.86-6941523 -> 3991396.9 | CX43: 10932920 | CY43: 10932920 | CZ43: 10932920 | DA43: 10932920 | DB43: 10932920 | DC43: 10932920 | DD43: 10932920 | DE43: 10932920 | DF43: 11989675 | DG43: 10932920 | DH43: 10932920 | DI43: 10932920 | DJ43: 14175861 | DK43: 10932920 | DL43: 13857903 | DM43: 13857903 | DN43: 13857903 | DO43: 13857903 | DP43: 13857903 | DQ43: 13857903 | DR43: 13857903 | DS43: 13857903 | DT43: 13857903 | DU43: 13857903 | DW43: 14175861
B44: Current Year Surplus | C44: 19800 | D44: 22000 | E44: 41916 | F44: 123303 | G44: 325421 | H44: 5201434.5 | I44: =1147048-229410-719039-130000 -> 68599 | J44: 10791401 | K44: 5950145.1 | L44: 3021360.4 | M44: 3434405.3 | N44: 7232371.8 | O44: 7705277.3 | P44: 8082527.1 | Q44: 8579103.4 | R44: 9363101.5 | S44: 9191917.1 | T44: 9711309.2 | U44: 5421853.1 | V44: =672489-134498-617260-160000 -> -239269 | W44: 8277430.4 | X44: 8910346.2 | Y44: 9092943.1 | Z44: 9434443.9 | AA44: 9462573 | AB44: 10224397 | AC44: 6489839.3 | AD44: 7567505.7 | AE44: 6731415.8 | AF44: 8089611.9 | AG44: 9436897.9 | AH44: 5343134.1 | AI44: =1327040-154751 -> 1172289 | AJ44: 1172289 | AL44: 821702.88 | AM44: 1779302.1 | AN44: 4459919.7 | AO44: 9462573 | AP44: 6657569.2 | AQ44: 7715985.7 | AR44: 6407735.8 | AS44: 6539615.9 | AU44: 10049264 | AV44: 9325746.7 | AW44: 1291493 | AZ44: -1023522.4 | BA44: -4910871.5 | BB44: 3571292 | BC44: 5228359.1 | BD44: 0 | BE44: 3866960.9 | BF44: 5682041.6 | BG44: 0 | BH44: 8550233 | BI44: 9480309.5 | BJ44: =5022885-1082573-2525539-300000 -> 1114773 | BK44: 743103.47 | BL44: 743103.47 | BM44: 935718 | BN44: 1686832 | BO44: 3813754 | BP44: 2920911 | BQ44: 2920911 | BR44: 2920911 | BS44: 3039073 | BT44: 4039073 | BU44: 5116539 | BV44: 1750092.5 | BX44: 706048 | BY44: 997177 | BZ44: 997177 | CA44: 1213518 | CB44: 6071315 | CC44: 7210009 | CD44: 9016989 | CE44: 10570574 | CF44: 12348784 | CG44: 14163212 | CH44: 14297305 | CI44: 6169777 | CK44: 2009032.8 | CL44: 3810740.7 | CM44: 5351730 | CN44: 6992206 | CO44: 9378315.1 | CP44: 11641356 | CQ44: 14620412 | CR44: 17776973 | CS44: 20717160 | CT44: 18936327 | CU44: 23330857 | CV44: 21114090 | CW44: 6941523 | CX44: 2526627.7 | CY44: 5383611 | CZ44: 7719895.7 | DA44: 10683946 | DB44: 13422120 | DC44: 15715597 | DD44: 18650391 | DE44: 22833874 | DF44: 25680363 | DG44: 27506846 | DH44: 30398576 | DI44: 2869780.2 | DK44: 3034364 | DL44: 6844308.3 | DM44: 10735662 | DN44: 13544295 | DO44: 16851925 | DP44: 19042419 | DQ44: 21942428 | DR44: 25804841 | DS44: 28855537 | DT44: 29968408 | DU44: 32802838 | DW44: =12260795-2452159-6256768-650000 -> 2901868
B45: Other Equity Accounts | C45: =SUM(C46:C49) -> 57772 | D45: =SUM(D46:D49) -> 72772 | E45: =SUM(E46:E49) -> 895751 | F45: =SUM(F46:F49) -> 1457242 | G45: =SUM(G46:G49) -> 2504738 | H45: =SUM(H46:H49) -> 3323008 | I45: =SUM(I46:I49) -> 3352418 | J45: =SUM(J46:J49) -> 6692316 | ... DW45: =SUM(DW46:DW49) -> 27126461
B46: Statutory Reserve | C46: 19772 | D46: 34772 | E46: 57751 | F46: 211710 | G46: 359738 | H46: 359738 | I46: 589148 | J46: 719476 | K46: 359738 | L46: 359738 | M46: 359738 | N46: 359738 | O46: 359738 | P46: 359738 | Q46: 359738 | R46: 359738 | S46: 359738 | T46: 359738 | U46: 359738 | V46: 723646 | W46: 359738 | X46: 359738 | Y46: 359738 | Z46: 359738 | AA46: 359738 | AB46: 359738 | AC46: 359738 | AD46: 359738 | AE46: 359738 | AF46: 359738 | AG46: 359738 | AH46: 359738 | AI46: 1319557 | AJ46: 1319557 | AL46: 359738 | AM46: 359738 | AN46: 359738 | AO46: 359738 | AP46: 359738 | AQ46: 359738 | AR46: 359738 | AS46: 359738 | AU46: 359738 | AV46: 1319557 | AW46: 1844468 | AZ46: -1319557 | BA46: -2639114 | BB46: 1319557 | BC46: 1319557 | BD46: 1956518 | BE46: 1956518 | BF46: 1956518 | BH46: 1956518 | BI46: 1956518 | BJ46: 2927061 | BK46: 2927061 | BL46: 2927061 | BM46: 2927718 | BN46: 2927718 | BO46: 2927718 | BP46: 2927718 | BQ46: 2927718 | BR46: 2927718 | BS46: 2927718 | BT46: 2927718 | BU46: 2927718 | BV46: 2927718 | BW46: 6113979 | BX46: 4054212 | BY46: 4054212 | BZ46: 4054212 | CA46: 4054212 | CB46: 4054212 | CC46: 4054212 | CD46: 4054212 | CE46: 4054212 | CF46: 4054212 | CG46: 4054212 | CH46: 4054212 | CI46: 4054212 | CJ46: 5115343.8 | CK46: 5115343.8 | CL46: 5115343.8 | CM46: 5115343.8 | CN46: 5115343.8 | CO46: 5115343.8 | CP46: 5115343.8 | CQ46: 5115343.8 | CR46: 5115343.8 | CS46: 5115343.8 | CT46: 5115343.8 | CU46: 5115343.8 | CV46: 5115343.8 | CW46: 6691270 | CX46: 6691270 | CY46: 6691270 | CZ46: 6691270 | DA46: 6691270 | DB46: 6691270 | DC46: 6691270 | DD46: 6691270 | DE46: 6691270 | DF46: 6691270 | DG46: 6691270 | DH46: 6691270 | DI46: 8584983.5 | DJ46: 8678273 | DK46: 8584983.5 | DL46: 8598784 | DM46: 8598784 | DN46: 8598784 | DO46: 8598784 | DP46: 8598784 | DQ46: 8598784 | DR46: 8598784 | DS46: 10319149 | DT46: 10319149 | DU46: 10319149 | DW46: 11130433
B47: Other Reserves | C47: 38000 | D47: 38000 | E47: 838000 | F47: 838000 | G47: 1667000 | H47: 2963270 | I47: 2763270 | J47: 5972840 | K47: 3037817 | L47: 3065367 | M47: 3101267 | N47: 3114117 | O47: 3130723 | P47: 3186973 | Q47: 3223973 | R47: 3262423 | S47: 3309203 | T47: 3354980 | U47: 3407670 | V47: 2764226 | W47: 3352373 | X47: 3407353 | Y47: 3453253 | Z47: 3493783 | AA47: 3526333 | AB47: 3536933 | AC47: 3575313 | AD47: 3633623 | AE47: 3672463 | AF47: 3709513 | AG47: 3758507 | AH47: 3828857 | AI47: =2764226+324200 -> 3088426 | AJ47: =2764226+324200 -> 3088426 | AL47: 3810107 | AM47: 3793107 | AN47: 3793107 | AO47: 3526333 | AP47: 3781107 | AQ47: 3998597 | AR47: 3986597 | AS47: 3960597 | AU47: 3942597 | AV47: 5684086 | AW47: =2764226+525690 -> 3289916 | AZ47: 5667086 | BA47: 10678172 | BB47: 5319086 | BC47: 5279086 | BD47: 5279086 | BE47: 5279086 | BF47: 5259086 | BH47: 5214086 | BI47: 5828746 | BJ47: 5653673 | BK47: 5653673 | BL47: 5653673 | BM47: 5653673 | BN47: 5653673 | BO47: 5783346 | BP47: 5748346 | BQ47: 5748346 | BR47: 5698346 | BS47: 5698346 | BT47: 5653673 | BU47: 5653673 | BV47: 5698346 | BW47: 4054212 | BX47: 6113979 | BY47: 6113979 | BZ47: 6113979 | CA47: 6113979 | CB47: 6113979 | CC47: 6113979 | CD47: 6113979 | CE47: 6113979 | CF47: 6113979 | CG47: 6113979 | CH47: 6113979 | CI47: 6113979 | CJ47: 6132683.7 | CK47: 6132683.7 | CL47: 6132685.7 | CM47: 6132685.7 | CN47: 6090683 | CO47: 6132685.7 | CP47: 6132685.7 | CQ47: 6132685.7 | CR47: 6132685.7 | CS47: 6132685.7 | CT47: 6132685.7 | CU47: 6132685.7 | CV47: 7016778 | CW47: 7016778 | CX47: 7016778 | CY47: 7016778 | CZ47: 7016778 | DA47: 8316778 | DB47: 8316778 | DC47: 8316778 | DD47: 8316778 | DE47: 8316777 | DF47: 8316777 | DG47: 8316777 | DH47: 8316777 | DI47: 9069149.2 | DJ47: 9069149 | DK47: 9069149.2 | DL47: 9069149.2 | DM47: 9069149.2 | DN47: 9069149.2 | DO47: 9069149.2 | DP47: 9069149.2 | DQ47: 9069149.2 | DR47: 10319149 | DS47: 0 | DT47: 0 | DU47: 0 | DW47: 15996028
B48: Revaluation Reserves | F48: 0 | G48: 0 | J48: 0 | K48: 0 | L48: 0 | M48: 0 | N48: 0 | O48: 0 | P48: 0 | Q48: 0 | R48: 0 | S48: 0 | T48: 0 | U48: 0 | AA48: 0 | AB48: 0 | AM48: 0 | AU48: 0 | AZ48: ` | BA48: 0 | BB48: 0 | BC48: 0 | BD48: 0 | BE48: 0 | BF48: 0 | BH48: 0 | BI48: 0 | BJ48: 8590309 | BP48: 0 | BR48: 0 | BS48: 0 | BT48: 0 | BU48: 0 | BV48: 0 | BX48: 0 | BY48: 0 | BZ48: 0 | CA48: 0 | CB48: 0 | CC48: 0 | CX48: 0 | CY48: 0 | CZ48: 0 | DA48: 0 | DB48: 0 | DC48: 0 | DD48: 0 | DE48: 0 | DF48: 0 | DG48: 0 | DH48: 0 | DI48: 0 | DK48: 0 | DL48: 0 | DM48: 0 | DN48: 0 | DO48: 0 | DP48: 0 | DQ48: 0 | DR48: 0 | DS48: 0 | DT48: 0 | DU48: 0
B49: Dividend Proposed | F49: 407532 | G49: 478000 | J49: 0 | K49: 0 | L49: 142610.23 | M49: 142610.23 | N49: 142610.23 | O49: 142610.23 | P49: 142610.23 | Q49: 142610.23 | R49: 142610.23 | S49: 142610.23 | T49: 142610.23 | U49: 142610.23 | W49: 142610.23 | X49: 142610.23 | AA49: 0 | AB49: 0 | AU49: 0 | AZ49: 0 | BA49: 0 | BB49: 0 | BC49: 0 | BD49: 608151 | BE49: 0 | BF49: 0 | BH49: 0 | BI49: 0 | BR49: 0 | BS49: 0 | BT49: 0 | BV49: 9040189 | BX49: 0 | BY49: 0 | BZ49: 0 | CA49: 0 | CB49: 0 | CC49: 0 | CD49: 0 | CE49: 0 | CF49: 0 | CG49: 0 | CH49: 0 | CI49: 0 | CL49: 0 | CM49: 0 | CN49: 0 | CO49: 0 | CP49: 0 | CR49: 0 | CS49: 0 | CT49: 0 | CU49: 0 | CX49: 0 | CY49: 0 | CZ49: 0 | DA49: 0 | DB49: 0 | DC49: 0 | DD49: 11535.52 | DE49: 11535.52 | DF49: 11535.52 | DG49: 0 | DH49: 0 | DI49: 0 | DK49: 0 | DL49: 0 | DM49: 0 | DN49: 0 | DO49: 0 | DP49: 0 | DQ49: 0 | DR49: 0 | DS49: 0 | DT49: 0 | DU49: 0
B50: Total Equity | C50: =C40+C41+C42+C45 -> 439861 | D50: =D40+D41+D42+D45 -> 736861 | E50: =E40+E41+E42+E45 -> 8453756 | F50: =F40+F41+F42+F45 -> 11856866 | G50: =G40+G41+G42+G45 -> 15930148 | H50: =H40+H41+H42+H45 -> 25274778 | I50: =I40+I41+I42+I45 -> 19725079 | J50: =J40+J41+J42+J45 -> 51119689 | ... DJ50: =DJ40+DJ41+DJ42+DJ45 -> 73290644 | DK50: 73496961 | DL50: 80761585 | DM50: 89148040 | DN50: 92917408 | DO50: 96642171 | DP50: 100490934 | DQ50: 1.0443502e+08 | DR50: 1.1000115e+08 | DS50: 1.136117e+08 | DT50: 1.1518522e+08 | DU50: 1.1844648e+08 | DV50: =DV40+DV41+DV42+DV45 -> 0 | DW50: =DW40+DW41+DW42+DW45 -> 97517528
B51: Total Liabilities and Equity | C51: =C39+C50 -> 3475410 | D51: =D39+D50 -> 8750647 | E51: =E39+E50 -> 18632415 | F51: =F39+F50 -> 35649419 | G51: =G39+G50 -> 48282362 | H51: =H39+H50 -> 75358468 | I51: =I39+I50 -> 70805321 | J51: =J39+J50 -> 1.5365653e+08 | ... DW51: =DW39+DW50 -> 415120522
AI52: =AI51-AI27 -> 0 | AL52: =AL27-AL51 -> -3925240.8 | AM52: =AM27-AM51 -> -3291212 | AN52: =AN27-AN51 -> -24219253 | AO52: =AO27-AO51 -> 0 | AP52: =AP27-AP51 -> -35930875 | AQ52: =AQ27-AQ51 -> -21330104 | AR52: =AR27-AR51 -> -21779750 | AS52: =AS27-AS51 -> -21951312 | ... AW52: =AW27-AW51 -> 1 | BW52: 2.1314056e+08 | CB52: =CB51-CB27 -> 0 | CI52: =CI51-CI27 -> -1.0950064e+08 | CL52: =CL51-CL27 -> -0.0040000081 | CP52: =CP51-CP27 -> 284981.17 | CS52: =CS51-CS27 -> 0 | CT52: =CT51-CT27 -> -2885292.1 | DW52: =DW51-DW27 -> 0
C53: =C27-C51 -> 0 | D53: =D27-D51 -> 0 | E53: =E27-E51 -> 383086 | F53: =F27-F51 -> 0 | G53: =G27-G51 -> 0 | H53: =H27-H51 -> 0.5 | I53: =I27-I51 -> 579280 | J53: =J27-J51 -> 0.5 | ... AC53: =AC27-AC51 -> 0 | BW53: =BW52-BW51 -> 0.30000001 | CK53: dfc loan loss
B54: Suspense (Balancing Figure capital side) | BJ54: =BJ53-BK35 -> 0 | BW54: 9590309 | BX54: =BW53-BW54 -> -9590308.7
B55: Adjustment to Equity
B56: Sacco Name
B57: AUDITED YEAR TO | C57: 2008 | D57: 2009 | E57: 2010 | F57: 2011 | G57: 2012 | H57: 41609 | I57: 2013 | J57: 41640 | K57: 41671 | L57: 41699 | M57: 41730 | N57: 41760 | O57: 41791 | P57: 41821 | Q57: 41852 | R57: 41883 | S57: 41913 | T57: 41944 | U57: 41974 | V57: 2014 | W57: 42005 | X57: 42036 | Y57: 42064 | Z57: 42095 | AA57: 42125 | AB57: 42156 | AC57: 42186 | AD57: 42217 | AE57: 42248 | AF57: 42278 | AG57: 42309 | AH57: 42339 | AI57: 2015 | AJ57: 2015 Rev. | AK57: Jan-16 | AL57: Feb-16 | AM57: Mar-16 | AN57: Apr-16 | AO57: May-16 | AP57: Jun-16 | AQ57: Jul-16 | AR57: Aug-16 | AS57: Sept-16 | AT57: Oct-16 | AU57: Nov-16 | AV57: Dec-16 | AW57: Aud-2016 | BJ57: Audited 2017 | BK57: 43101 | BL57: 43132 | BM57: 43160 | BN57: 43191 | BO57: 43221 | BP57: 43252 | BQ57: 43282 | BR57: 43313 | BS57: 43344 | BT57: 43374 | BU57: 43405 | BV57: 43435 | BW57: Audited-2018 | BX57: 43466 | BY57: 43497 | BZ57: 43525 | CA57: 43556 | CB57: 43586 | CC57: 43617 | CD57: 43647 | CE57: 43678 | CF57: 43709 | CG57: 43739 | CH57: 43770 | CI57: 43800 | CJ57: Audited-2019 | CK57: 43831 | CL57: 43862 | CM57: 43891 | CN57: 43922 | CO57: 43952 | CP57: 43983 | CQ57: 44013 | CR57: 44044 | CS57: 44075 | CT57: 44105 | CU57: 44136 | CV57: 44166 | CW57: Audited 2020 | CX57: Audited 2021 | CY57: Audited 2022 | CZ57: Audited 2023 | DA57: Audited 2024 | DB57: Audited 2025 | DC57: Audited 2026 | DD57: Audited 2027 | DE57: Audited 2028 | DF57: Audited 2029 | DG57: Audited 2030 | DH57: Audited 2031 | DI57: Audited 2032 | DJ57: Audited 2033 | DK57: 44562 | DL57: 44593 | DM57: 44621 | DN57: 44652 | DO57: 44682 | DP57: 44713 | DQ57: 44743 | DR57: 44774 | DS57: 44805 | DT57: 44835 | DU57: 44866 | DV57: 44896 | DW57: Aud-22
B58: Financial Income | C58: =C59+C62 -> 456483 | D58: =D59+D62 -> 824264 | E58: =E59+E62 -> 1989959 | F58: =F59+F62 -> 4601423 | G58: =G59+G62 -> 6686491 | H58: =H59+H62 -> 9046.74 | I58: =I59+I62 -> 8938309 | J58: =J59+J62 -> 861242.73 | ... DW58: =DW59+DW62 -> 66839759
B59: Financial Income from Loans Portfolio | C59: =C60+C61 -> 456483 | D59: =D60+D61 -> 810609 | E59: =E60+E61 -> 1952307 | F59: =F60+F61 -> 4554144 | G59: =G60+G61 -> 4723018 | H59: =H60+H61 -> 6525.85 | I59: =I60+I61 -> 6128410 | J59: =J60+J61 -> 673525.85 | ... DW59: =DW60+DW61 -> 57063371
B60: Interest on Loan Portfolio | C60: 313291 | D60: 583891 | E60: 1305578 | F60: 3611027 | G60: 4688789 | H60: 6208.39 | I60: 5914011 | J60: 640880.24 | K60: 1289.25 | L60: 1926.37 | M60: 2499.66 | N60: 3123700 | O60: 3834744 | P60: 4484048 | Q60: 5163371 | R60: 5875753 | S60: 6650077 | T60: 7416908 | U60: 8211428 | V60: 8211428 | W60: 782333 | X60: 1622777 | Y60: 2437577 | Z60: 3312456 | AA60: 4178674 | AB60: 4985182 | AC60: 6242563 | AD60: 7438738 | AE60: 7505251 | AF60: 8413548 | AG60: 9369633 | AH60: 10518378 | AI60: =9880025+638353 -> 10518378 | AJ60: =9880025+638353 -> 10518378 | AL60: 275686 | AM60: 277035 | AN60: 278735 | AO60: 292435 | AQ60: 330557 | AR60: 7960883 | AU60: 11738211 | AV60: 12250625 | AW60: =12200044+1167200 -> 13367244 | AZ60: -2651434 | BA60: 11052488 | BB60: 6967350 | BC60: 8377132 | BD60: 9771838 | BE60: 11263639 | BF60: 12810950 | BH60: 15931198 | BI60: 17603250 | BJ60: 14651350 | BK60: 1562810.8 | BL60: 2997105 | BM60: 4672848 | BN60: 6469959 | BO60: 8080915 | BP60: 9862767 | BQ60: 11433242 | BR60: 13287970 | BS60: 14897579 | BT60: 16578500 | BU60: 18173576 | BV60: 19450551 | BW60: 16299951 | BX60: 1495716 | BY60: 3145310 | BZ60: 4682305 | CA60: 6187749 | CB60: 7898797 | CC60: 9505344 | CD60: 11148023 | CE60: 12733253 | CF60: 14601482 | CG60: 16887688 | CH60: 19010897 | CI60: 21085150 | CJ60: 21085150 | CK60: 2175209.7 | CL60: 4137904.3 | CM60: 6239563 | CN60: 8770310 | CO60: 11599091 | CP60: 13945241 | CR60: 19227869 | CS60: 21696233 | CT60: 48411144 | CU60: 26986689 | CV60: 30129800 | CW60: 30129800 | CX60: 2894386 | CY60: 5796682.9 | CZ60: 8749302.6 | DA60: 11925550 | DB60: 15136677 | DC60: 18627610 | DD60: 21232272 | DE60: 24431246 | DF60: 27716425 | DG60: 31844101 | DH60: 35454366 | DI60: 39562953 | DJ60: 48530425 | DK60: 3644643.8 | DL60: 7297174.8 | DM60: 10678639 | DN60: 14224512 | DO60: 17958775 | DP60: 21713522 | DQ60: 25575497 | DR60: 29525034 | DS60: 33397080 | DT60: 37319307 | DU60: 41335716 | DW60: 57063371
B61: Fees and Commission on Loan Portfolio | C61: 143192 | D61: 226718 | E61: 646729 | F61: 943117 | G61: 34229 | H61: 317.46 | I61: 214399 | J61: 32645.61 | K61: 57.74 | L61: 99.52 | M61: 145.35 | N61: 186553.35 | O61: 212830.1 | P61: 249719.85 | Q61: 286331.85 | R61: 350422.85 | S61: 385852.35 | T61: 432037.4 | U61: 474791.65 | W61: 55080.5 | X61: 84803.5 | Y61: 123082.25 | Z61: 173023.75 | AA61: 198331.75 | AB61: 249050.75 | AC61: 294103.5 | AD61: 359747.75 | AE61: 389472.25 | AF61: 433036.35 | AG61: 506748.71 | AH61: 559945.34 | AL61: 94345.25 | AM61: 94345.25 | AN61: 94345.25 | AO61: 94220.25 | AQ61: 101220.25 | AR61: 551000.85 | AU61: 680280.9 | AV61: 881876.3 | AZ61: 0 | BA61: -622505.8 | BB61: 383342.7 | BC61: 451966.7 | BD61: 599698 | BE61: 960677.1 | BF61: 1088254.8 | BH61: 875277.2 | BI61: 1459140.7 | BJ61: 2951900 | BK61: 65251.8 | BL61: 137512.7 | BM61: 215755.7 | BN61: 313580 | BO61: 376694 | BP61: 492030 | BQ61: 556872 | BR61: 674105 | BS61: 805213.6 | BT61: 898674 | BU61: 1041449 | BV61: 674105 | BW61: 3150600 | BX61: 553013 | BY61: 913647 | BZ61: 1475959 | CA61: 2304121 | CB61: 3352845 | CC61: 4124350 | CD61: 4920434 | CE61: 5546656.3 | CF61: 6192490.4 | CG61: 6823320 | CH61: 7552686.9 | CI61: 8336029.7 | CJ61: 8336029.7 | CK61: 976137.46 | CL61: 1623293.9 | CM61: 2094012 | CN61: 2244774 | CO61: 2701998.7 | CP61: 3351124.2 | CR61: 4961961.2 | CS61: 5669770.7 | CT61: 12692945 | CU61: 6995499.8 | CV61: 8042269 | CW61: 8042269.8 | CX61: 832014.5 | CY61: 1686521.3 | CZ61: 2212109.9 | DA61: 3046263.9 | DB61: 3788133 | DC61: 4828822.3 | DD61: 6004832.2 | DE61: 6866317.5 | DF61: 7655019.5 | DG61: 8671825.1 | DH61: 9938819.4 | DI61: 11187738 | DJ61: 2514014 | DK61: 1069884.9 | DL61: 2429813 | DM61: 3567163.5 | DN61: 4749954.2 | DO61: 5692107 | DP61: 6354557.9 | DQ61: 7112951.2 | DR61: 8250543.1 | DS61: 9385453.4 | DT61: 10745304 | DU61: 11641312
B62: Financial Income From Investments | D62: =SUM(D63:D66) -> 13655 | E62: =SUM(E63:E66) -> 37652 | F62: =SUM(F63:F66) -> 47279 | G62: =SUM(G63:G66) -> 1963473 | H62: =SUM(H63:H66) -> 2520.89 | I62: =SUM(I63:I66) -> 2809899 | J62: =SUM(J63:J66) -> 187716.88 | K62: =SUM(K63:K66) -> 394.14 | ... DW62: =SUM(DW63:DW66) -> 9776388
B63: Government Securities | H63: 0 | J63: 0 | K63: 0 | L63: 0 | M63: 0 | N63: 0 | O63: 0 | P63: 0 | Q63: 0 | R63: 0 | S63: 0 | T63: 0 | U63: 0 | AA63: 0 | AB63: 0 | AC63: 0 | AD63: -120201.8 | AE63: -120201.8 | AF63: -120201.8 | AG63: -120201.8 | AH63: -120201.8 | AN63: 1500000 | AO63: 1500000 | AQ63: 1500000 | AR63: 124906.5 | AU63: 124906.5 | AV63: 124906.5 | AW63: 124908 | AZ63: 0 | BA63: 0 | BB63: 0 | BC63: 0 | BD63: 0 | BE63: 0 | BH63: 0 | BI63: 0 | BK63: 0 | BL63: 0 | BM63: 0 | BN63: 0 | BO63: 0 | BP63: 0 | BQ63: 0 | BR63: 0 | BS63: 0 | BT63: 0 | BU63: 0 | BV63: 0 | BX63: 0 | BY63: 0 | BZ63: 0 | CA63: 0 | CB63: 0 | CC63: 0 | CD63: 0 | CE63: 0 | CF63: 0 | CG63: 0 | CH63: 0 | CI63: 0 | CJ63: 0 | CL63: 0 | CM63: 0 | CN63: 0 | CO63: 0 | CP63: 0 | CR63: 0 | CS63: 0 | CT63: 0 | CU63: 0 | CV63: 0 | CX63: 0 | CY63: 0 | CZ63: 0 | DA63: 0 | DB63: 0 | DC63: 0 | DD63: 0 | DE63: 0 | DF63: 0 | DG63: 0 | DH63: 0 | DI63: 0 | DK63: 0 | DL63: 0 | DM63: 0 | DN63: 0 | DO63: 0 | DP63: 0 | DQ63: 0 | DR63: 0 | DS63: 0 | DT63: 0 | DU63: 0
B64: Deposits with Banks and other Financial Institutions | C64: 6698 | D64: 7565 | H64: 0 | I64: 31008 | J64: 0 | K64: 0 | L64: 0 | M64: 0 | N64: 0 | O64: -5075 | P64: 2711.59 | Q64: 7786.59 | R64: 7786.59 | S64: 7786.59 | T64: 17908.59 | U64: 77685.47 | V64: 32714 | AA64: 0 | AB64: 0 | AC64: 0 | AD64: 145815.44 | AE64: 147145.44 | AF64: 485567.51 | AG64: 635841.53 | AH64: 942126.78 | AI64: 46841 | AJ64: 46841 | AL64: 581565.66 | AM64: 581565.66 | AN64: 923303.57 | AO64: 1074980.6 | AQ64: 1074980.6 | AR64: 1554565.6 | AU64: 2026640.5 | AV64: 2037037.3 | AW64: =2009226+27811 -> 2037037 | AZ64: 0 | BA64: -4500.1 | BB64: 419228.47 | BC64: 1081025.7 | BD64: 1221025.7 | BE64: 1251338.5 | BF64: 1266653 | BH64: 1842636 | BI64: 2994656.4 | BJ64: =1874621+140000 -> 2014621 | BK64: 25 | BL64: 25 | BM64: 0 | BN64: 0 | BO64: 104170 | BP64: 128315 | BQ64: 214244 | BR64: 214244 | BS64: 1056416.6 | BT64: 1064358 | BU64: 1944805 | BV64: 1454746 | BW64: 1454746.3 | BX64: 0 | BY64: 0 | BZ64: 438041 | CA64: 660356 | CB64: 1010457 | CC64: 1240392 | CD64: 2217330 | CE64: 2147187.8 | CF64: 2147187.8 | CG64: 2295944.5 | CH64: 2319805.7 | CI64: 2542224.4 | CJ64: 2542224.4 | CK64: 2947968.2 | CL64: 0 | CM64: 0 | CN64: 0 | CO64: 714070 | CP64: 921415 | CR64: 2287179.4 | CS64: 2337545 | CT64: 4773122 | CU64: 2433641.3 | CV64: 2947968.2 | CW64: 2947968.2 | CX64: 0 | CY64: 0 | CZ64: 0 | DA64: 0 | DB64: 0 | DC64: 0 | DD64: 0 | DE64: 0 | DF64: 0 | DG64: 0 | DH64: 0 | DI64: 0 | DJ64: 1724284 | DK64: 0 | DL64: 0 | DM64: 0 | DN64: 0 | DO64: 0 | DP64: 0 | DQ64: 0 | DR64: 0 | DS64: 0 | DT64: 0 | DU64: 0 | DW64: 1412683
B65: Other Investments | C65: 780 | D65: 6090 | H65: 0 | J65: 0 | K65: 0 | L65: 0 | M65: 0 | N65: 0 | O65: 0 | P65: 0 | Q65: 0 | R65: 0 | S65: 0 | T65: 0 | U65: 0 | AA65: 0 | AB65: 0 | AC65: 0 | AD65: 0 | AE65: 0 | AF65: 0 | AG65: 0 | AH65: 0 | AL65: 0 | AM65: 0 | AN65: 0 | AO65: 0 | AP65: 0 | AQ65: 0 | AR65: 0 | AU65: 0 | AV65: 0 | AZ65: 0 | BA65: 0 | BB65: 0 | BC65: 0 | BD65: 0 | BE65: 0 | BH65: 0 | BI65: 0 | BK65: 0 | BL65: 0 | BM65: 0 | BN65: 0 | BO65: 0 | BP65: 0 | BQ65: 0 | BR65: 0 | BS65: 0 | BT65: 0 | BU65: 0 | BV65: 0 | BX65: 0 | BY65: 0 | BZ65: 26665 | CA65: 26665 | CB65: 26665 | CC65: 29857 | CD65: 29857 | CE65: 0 | CF65: 0 | CG65: 0 | CH65: 0 | CI65: 70023 | CJ65: 70023 | CK65: 0 | CL65: 420032.42 | CM65: 420032 | CN65: 374157 | CO65: 0 | CP65: 0 | CR65: 0 | CS65: 0 | CT65: 0 | CU65: 0 | CV65: 34654 | CW65: 34654 | CX65: 0 | CY65: 0 | CZ65: 27999.35 | DA65: 194819.57 | DB65: 194819.57 | DC65: 204699.07 | DD65: 204917.82 | DE65: 1141904.1 | DF65: 1141904.1 | DG65: 1141904.1 | DH65: 1141904.1 | DI65: 1603709.8 | DJ65: 30352 | DK65: 36874.48 | DL65: 36874.48 | DM65: 806650.56 | DN65: 806650.56 | DO65: 806650.56 | DP65: 811271.36 | DQ65: 814463.36 | DR65: 940362.79 | DS65: 940362.79 | DT65: 945777.79 | DU65: 1292743.1 | DW65: 39398
B66: Other Operating Income | E66: 37652 | F66: 47279 | G66: 1963473 | H66: 2520.89 | I66: 2778891 | J66: 187716.88 | K66: 394.14 | L66: 630.38 | M66: 933.3 | N66: 1196397 | O66: 1420510.8 | P66: 1712895.2 | Q66: 1955705.5 | R66: 2252754.6 | S66: 2462804.7 | T66: 2690567.7 | U66: 3051912.5 | V66: 4089791 | W66: 205211.5 | X66: 401021.33 | Y66: 715829.49 | Z66: 1023101.8 | AA66: 1241873.8 | AB66: 1658321 | AC66: 1979930.4 | AD66: 2230731.1 | AE66: 2494414.8 | AF66: 2841503.1 | AG66: 3665832 | AH66: 4196774.4 | AI66: 5811421 | AJ66: 5811421 | AL66: 431952.1 | AM66: 742576.1 | AN66: 752091.3 | AO66: 757152.3 | AQ66: 750657.6 | AR66: 3585003.7 | AU66: 4857541.4 | AV66: 6104690.9 | AW66: =322850+2994810+2415037+598719+68350 -> 6399766 | AZ66: -622305.09 | BA66: -3391012.7 | BB66: 2255120.8 | BC66: 2709837.6 | BD66: 3265023.5 | BE66: 3616405.1 | BF66: 4162133.5 | BH66: 5288565.9 | BI66: 5829931 | BJ66: =347000+1889083+3207477+2594506+87500 -> 8125566 | BK66: 354519.35 | BL66: 929529.29 | BM66: 1818514.8 | BN66: 2256960 | BO66: 2893743.7 | BP66: 3430335 | BQ66: 3825450 | BR66: 4438020 | BS66: 5933991.4 | BT66: 6334425 | BU66: 6936943 | BV66: 12361347 | BW66: 12361348 | BX66: 233750 | BY66: 252591 | BZ66: 844095 | CA66: 1121385 | CB66: 1370870 | CC66: 1448170 | CD66: 1845933 | CE66: 2417908.8 | CF66: 2681995 | CG66: 2577811.4 | CH66: 2847685 | CI66: 3301333.7 | CJ66: 3301333.7 | CK66: 196144.45 | CL66: 359090 | CM66: 1152263 | CN66: 1249243 | CO66: 1525404.4 | CP66: 1926416 | CR66: 2668304.5 | CS66: 2945987.7 | CT66: 6555402 | CU66: 3764884.5 | CV66: 3994041.1 | CW66: =86200+27000+388300+94800+1772416.58+110620+375944.74+1138759.75 -> 3994041.1 | CX66: 240098.74 | CY66: 677306.31 | CZ66: 1628629.8 | DA66: 2027638.1 | DB66: 2417874.6 | DC66: 2915638 | DD66: 3224891.9 | DJ66: 5607338 | DK66: 353180.06 | DL66: 698900.46 | DM66: 1785116.3 | DN66: 2216557 | DO66: 2602561 | DP66: 2990150.5 | DQ66: 3223035.3 | DR66: 4013506 | DS66: 4360705.8 | DT66: 4722165 | DU66: 5024304.6 | DW66: =5471788+2852519 -> 8324307
B67: Financial Expense | D67: =SUM(D68:D73) -> 404847 | E67: =SUM(E68:E73) -> 1148641 | F67: =SUM(F68:F73) -> 1918286 | G67: =SUM(G68:G73) -> 2325829 | H67: =SUM(H68:H73) -> 106.34 | I67: =SUM(I68:I73) -> 3194455 | J67: =SUM(J68:J73) -> 3603600 | K67: =SUM(K68:K73) -> 3600 | ... DW67: =SUM(DW68:DW73) -> 21482339
B68: Interest Expense on Deposits | E68: 1138470 | F68: 1235355 | G68: 1496701 | H68: 0 | I68: =147540+2506276 -> 2653816 | J68: 0 | K68: 0 | L68: 3225290 | M68: 3225290 | N68: 0 | O68: 0 | P68: 0 | Q68: 0 | R68: 0 | S68: 0 | V68: =93967+3113833 -> 3207800 | AA68: 0 | AB68: 0 | AC68: 0 | AF68: -2320 | AG68: -2320 | AH68: -4640 | AI68: =4954346+171717 -> 5126063 | AJ68: =4954346+171717 -> 5126063 | AR68: 5854534.1 | AU68: 5854534.1 | AV68: -27920 | AW68: =5434834+373902 -> 5808736 | AZ68: 0 | BA68: 0 | BB68: 0 | BC68: 33572 | BD68: 0 | BE68: 0 | BH68: 0 | BI68: 0 | BJ68: 6911689 | BK68: 0 | BL68: 0 | BM68: 0 | BN68: 0 | BO68: 0 | BP68: 0 | BQ68: 0 | BR68: 0 | BS68: 0 | BT68: 0 | BU68: 0 | BV68: 0 | BW68: 9040189.6 | BX68: 0 | BY68: 0 | BZ68: 0 | CA68: 0 | CB68: 0 | CC68: 0 | CD68: 0 | CE68: 0 | CF68: 0 | CG68: 217011.56 | CH68: 828440.51 | CI68: 0 | CJ68: 8349044 | CL68: 0 | CM68: 0 | CN68: 0 | CO68: 220061.21 | CP68: 266144.95 | CR68: 299899.56 | CS68: 431545.04 | CT68: 962662 | CU68: 533428.66 | CV68: 604636.78 | CW68: 13660763 | CX68: 49468 | CY68: 58230 | CZ68: 149854.66 | DA68: 206989.7 | DB68: 211116.2 | DC68: 324259.66 | DD68: 377959.39 | DE68: 395521.89 | DF68: 0 | DG68: 0 | DH68: 581163.29 | DI68: 725467.4 | DJ68: 15897898 | DK68: 122665.36 | DL68: 147220.36 | DM68: 161738.11 | DN68: 195435.89 | DO68: 234835.89 | DP68: 256265.72 | DQ68: 261813.88 | DR68: 305118.88 | DS68: 340323.3 | DT68: 344242.34 | DU68: 397523.37 | DW68: 19727218
B69: Cost of External Borrowings | F69: 152793 | G69: 257234 | H69: 0 | I69: 304823 | J69: 0 | K69: 0 | L69: 0 | M69: 95650 | N69: 95650 | O69: 95650 | P69: 145633 | Q69: 276559 | R69: 276559 | S69: 276559 | V69: 514256 | Z69: 52230 | AA69: 52230 | AB69: 61830 | AC69: 65030 | AD69: 71430 | AE69: 71430 | AF69: 71430 | AG69: 160482 | AH69: 173771 | AI69: 137397 | AJ69: 137398 | AN69: 7200 | AO69: 7200 | AQ69: 7200 | AR69: 18400 | AU69: 18400 | AV69: 18400 | AZ69: 0 | BA69: 0 | BB69: 33572 | BC69: 0 | BD69: 515523 | BE69: 0 | BH69: 0 | BI69: 0 | BJ69: 64504 | BK69: 0 | BL69: 0 | BM69: 36200 | BN69: 0 | BO69: 0 | BP69: 0 | BQ69: 0 | BR69: 0 | BS69: 0 | BT69: 0 | BU69: 0 | BV69: 0 | BW69: =78665+62097 -> 140762 | BX69: 62097 | BY69: 194036 | BZ69: 194036 | CA69: 382699 | CB69: 325485 | CC69: 382528 | CD69: 435172 | CE69: 449488 | CF69: 495132 | CG69: 513309 | CH69: 559246 | CI69: 559246 | CJ69: 828440.51 | CL69: 42795 | CM69: 85590 | CN69: 85590 | CO69: 163782 | CP69: 243440 | CR69: 311160 | CS69: 341147 | CT69: 682294 | CU69: 363599 | CV69: 400920 | CW69: 1005556.8 | CX69: 28750 | CY69: 41900 | CZ69: 52099 | DA69: 52099 | DB69: 86653.92 | DC69: 86653.92 | DD69: 86653.92 | DE69: 86653.92 | DF69: 86653.92 | DG69: 86653.92 | DH69: 106781 | DI69: 430404 | DJ69: 686269 | DK69: 0 | DL69: 0 | DM69: 109549.34 | DN69: 109549.34 | DO69: 336736.34 | DP69: 421836.34 | DQ69: 421836.34 | DR69: 798856.02 | DS69: 798856.02 | DT69: 798856.02 | DU69: 1065433 | DW69: 1197819
B70: Dividend Expenses | D70: 404847 | F70: 407532 | G70: 393000 | H70: 0 | J70: 0 | K70: 0 | L70: 0 | M70: 0 | N70: 0 | O70: 0 | P70: 0 | Q70: 0 | R70: 0 | S70: 0 | V70: 894352 | AA70: 0 | AB70: 675528 | AC70: 791435 | AD70: 796665 | AE70: 971295 | AF70: 829855 | AG70: 871260 | AH70: 926560 | AL70: 414920 | AM70: 509145 | AN70: 572540 | AO70: 566045 | AQ70: 718470 | AR70: 877570 | AU70: 984044 | AV70: 1104497 | AZ70: 2757782 | BA70: 715212 | BB70: 608151 | BC70: 503431 | BD70: 4000 | BE70: 0 | BH70: 0 | BI70: 0 | BK70: 0 | BL70: 0 | BM70: 0 | BN70: 0 | BO70: 0 | BP70: 0 | BQ70: 0 | BR70: 0 | BS70: 0 | BT70: 0 | BU70: 0 | BV70: 0 | BX70: 0 | BY70: 0 | BZ70: 0 | CA70: 0 | CB70: 0 | CC70: 0 | CD70: 0 | CE70: 0 | CF70: 0 | CG70: 0 | CH70: 0 | CI70: 0 | CJ70: 0 | CL70: 0 | CM70: 0 | CN70: 0 | CO70: 0 | CP70: 0 | CR70: 0 | CS70: 0 | CT70: 0 | CU70: 0 | CV70: 0 | CX70: 0 | CY70: 0 | CZ70: 0 | DA70: 0 | DB70: 0 | DC70: 0 | DD70: 0 | DE70: 0 | DF70: 0 | DG70: 0 | DH70: 0 | DI70: 0 | DJ70: 725467 | DK70: 0 | DL70: 0 | DM70: 0 | DN70: 0 | DO70: 0 | DP70: 0 | DQ70: 0 | DR70: 0 | DS70: 0 | DT70: 0 | DU70: 0
B71: Other Financial Expense | E71: 10171 | F71: 122606 | G71: =15415+163479 -> 178894 | H71: 12.64 | I71: =10175+207641+2400+15600 -> 235816 | J71: 3603600 | K71: 3600 | L71: 6100 | M71: 16290 | N71: 16289 | O71: 16289 | P71: 17789 | Q71: 20089 | R71: 20089 | S71: 21589 | V71: =60000+2400+746595+11127 -> 820122 | W71: 1350 | X71: 1350 | Y71: 3600 | Z71: 5100 | AA71: 6400 | AB71: 42550 | AC71: 52300 | AD71: 57800 | AE71: 119856 | AF71: 169669.5 | AG71: 180609.5 | AH71: 197414.5 | AI71: =11127+929657+2400+50000 -> 993184 | AJ71: =11127+929657+2400+50000 -> 993184 | AL71: 35207.5 | AM71: 54492.5 | AN71: 60492.5 | AO71: 49342.5 | AQ71: 52742.5 | AR71: 4122.5 | AU71: 10142.5 | AV71: 203302.5 | AW71: =75013+578000+89000+50000 -> 792013 | AZ71: 18021 | BA71: 120362 | BB71: 79272 | BC71: 87972 | BD71: 159034 | BE71: 560462.5 | BF71: 560462.5 | BH71: 0 | BI71: 0 | BJ71: =4969224-BJ69 -> 4904720 | BK71: 160281 | BL71: 160281 | BM71: 0 | BN71: 0 | BO71: 0 | BP71: 0 | BQ71: 0 | BR71: 0 | BS71: 0 | BT71: 0 | BU71: 0 | BV71: 0 | BW71: =4750915.45-BW69 -> 4610153.5 | BX71: 54210 | BY71: 54210 | BZ71: 54210 | CA71: 54210 | CB71: 6090 | CC71: 142723 | CD71: 329587 | CE71: 442678.1 | CF71: 482066.76 | CG71: 476551.18 | CH71: 491081.18 | CI71: 767275.7 | CJ71: 498081.18 | CK71: 31938.86 | CL71: 45868.86 | CM71: 127096 | CN71: 127096 | CO71: 80126.5 | CP71: 93566.5 | CR71: 313109 | CS71: 313109 | CT71: 647698 | CU71: 342051 | CV71: 869894 | CW71: 869894 | CX71: 3959.48 | CY71: 11099.48 | CZ71: 31219 | DA71: 34903.48 | DB71: 32503.48 | DC71: 38143 | DD71: 39343.48 | DE71: 285583.48 | DF71: 286843.48 | DG71: 290323.48 | DH71: 335499.48 | DI71: 837288.85 | DJ71: 838019 | DK71: 2196 | DL71: 2736 | DM71: 4923.77 | DN71: 8603.77 | DO71: 17593.77 | DP71: 20713.77 | DQ71: 21733.77 | DR71: 31920.46 | DS71: 30770.46 | DT71: 33818.21 | DU71: 41203.21
B72: Fees and Commission Expense | G72: 0 | H72: 93.7 | J72: 0 | K72: 0 | L72: 22800 | M72: 22900 | N72: 52324 | O72: 52324 | P72: 52324 | Q72: 52324 | R72: 52324 | S72: 102324 | W72: 43746 | X72: 43746 | Y72: 66246 | Z72: 66246 | AA72: 66846 | AB72: 66846 | AC72: 66846 | AD72: 66846 | AE72: 66846 | AF72: 69846 | AG72: 69846 | AH72: 119846 | AL72: 88128 | AM72: 88128 | AN72: 88128 | AO72: 88128 | AQ72: 88128 | AR72: 88128 | AU72: 153578 | AV72: 153578 | AZ72: 52500 | BA72: 288616 | BB72: 144308 | BC72: 144308 | BD72: 144308 | BE72: 178478 | BF72: 178478 | BH72: 1030176 | BI72: 2232525.3 | BK72: 0 | BL72: 0 | BM72: 188501 | BN72: 188501 | BO72: 188501 | BP72: 190751 | BQ72: 190751 | BR72: 200751 | BS72: 200751 | BT72: 200751 | BU72: 210751 | BV72: 500751 | BX72: 0 | BY72: 0 | BZ72: 0 | CA72: 0 | CB72: 0 | CC72: 0 | CD72: 0 | CE72: 0 | CF72: 3500 | CG72: 11800 | CH72: 67200 | CI72: 0 | CJ72: 0 | CK72: 10000 | CL72: 10000 | CM72: 10000 | CN72: 10000 | CO72: 10000 | CP72: 20000 | CR72: 48000 | CS72: 102000 | CT72: 214000 | CU72: 107000 | CV72: 107000 | CX72: 150 | CY72: 150 | CZ72: 32450 | DA72: 32450 | DB72: 32450 | DC72: 32450 | DD72: 136550 | DE72: 136550 | DF72: 136550 | DG72: 146605 | DH72: 146755 | DI72: 146755 | DK72: 92800 | DL72: 92800 | DM72: 99800 | DN72: 99800 | DO72: 99800 | DP72: 99800 | DQ72: 99800 | DR72: 127350 | DS72: 127350 | DT72: 127350 | DU72: 179470
B73: Other Expense | H73: 0 | J73: 0 | K73: 0 | L73: 0 | M73: 0 | N73: 0 | O73: 300 | P73: 0 | Q73: 0 | R73: 0 | S73: 0 | W73: 52798 | X73: 115238 | Y73: 115588 | Z73: 115588 | AA73: 115588 | AB73: 0 | AC73: 0 | AG73: 11200 | AH73: 11200 | AL73: 26178 | AM73: 26178 | AN73: 26178 | AO73: 26178 | AQ73: 26178 | AR73: 26178 | AU73: 60978 | AV73: 65778 | AZ73: 100 | BA73: 1100 | BB73: 800 | BC73: 800 | BD73: 2000 | BE73: 4320 | BF73: 4320 | BH73: 35720 | BI73: 35720 | BK73: 0 | BL73: 0 | BM73: 162000 | BN73: 216000 | BO73: 270000 | BP73: 324000 | BQ73: 378000 | BR73: 432000 | BS73: 486000 | BT73: 486000 | BU73: 540000 | BV73: 648000 | BX73: 0 | BY73: 0 | BZ73: 0 | CA73: 0 | CB73: 0 | CC73: 0 | CD73: 0 | CE73: 0 | CF73: 0 | CG73: 0 | CH73: 0 | CI73: 0 | CJ73: 0 | CL73: 0 | CM73: 0 | CN73: 0 | CO73: 0 | CP73: 0 | CR73: 0 | CS73: 0 | CT73: 0 | CU73: 0 | CV73: 0 | CX73: 0 | CY73: 0 | CZ73: 0 | DA73: 0 | DB73: 0 | DC73: 0 | DD73: 0 | DE73: 0 | DF73: 0 | DG73: 0 | DH73: 0 | DI73: 0 | DK73: 0 | DL73: 0 | DM73: 0 | DN73: 0 | DO73: 0 | DP73: 0 | DQ73: 0 | DR73: 0 | DS73: 0 | DT73: 0 | DU73: 0 | DW73: 557302
B74: Net Financial Income | D74: =D58-D67 -> 419417 | E74: =E58-E67 -> 841318 | F74: =F58-F67 -> 2683137 | G74: =G58-G67 -> 4360662 | H74: =H58-H67 -> 8940.4 | I74: =I58-I67 -> 5743854 | J74: =J58-J67 -> -2742357.3 | K74: =K58-K67 -> -1858.87 | ... DW74: =DW58-DW67 -> 45357420
B75: Allowance For Loan Loss | D75: =D76-D77 -> 0 | E75: =E76-E77 -> 0 | F75: =F76-F77 -> 269422 | G75: =G76-G77 -> 344629 | H75: =H76-H77 -> 0 | I75: =I76-I77 -> 484871 | J75: =J76-J77 -> 0 | K75: =K76-K77 -> 0 | ... DW75: =DW76-DW77 -> 3500000
B76: Provsion for Loan Losses | F76: 269422 | G76: 344629 | I76: 484871 | V76: 1993646 | W76: 2400000 | X76: 2400000 | Y76: -2400000 | Z76: 2400000 | AA76: -2400000 | AB76: -2400000 | AC76: 2400000 | AD76: 2400000 | AE76: 2400000 | AF76: 2400000 | AG76: 2400000 | AH76: 2400000 | AI76: -124098 | AJ76: -124097 | AW76: 4720752 | AZ76: 0 | BA76: 0 | BB76: 3292568 | BC76: 6599370 | BD76: 6874356.8 | BE76: 7387204.2 | BF76: 7387204.2 | BH76: 5771304.2 | BI76: 5838260.9 | BJ76: 2000000 | BK76: 0 | BL76: 0 | BM76: 7256136 | BN76: 6949166 | BO76: 7183267 | BP76: 7556873 | BQ76: 8948946 | BR76: 8619319 | BS76: 7902398.7 | BT76: 7949409 | BU76: 8452644 | BV76: 0 | BX76: 0 | BY76: 0 | BZ76: 0 | CA76: 0 | CB76: 0 | CC76: 0 | CD76: 0 | CE76: 0 | CF76: 0 | CG76: 0 | CH76: 0 | CI76: 1000000 | CJ76: 1000000 | CK76: 2000000 | CL76: 0 | CM76: 0 | CN76: 0 | CO76: 0 | CP76: 0 | CR76: 0 | CS76: 0 | CT76: 0 | CU76: 0 | CV76: 2000000 | CW76: 2000000 | CX76: 0 | CY76: 0 | CZ76: 0 | DA76: 0 | DB76: 0 | DC76: 0 | DD76: 0 | DE76: 0 | DF76: 0 | DG76: 0 | DH76: 0 | DI76: 2000000 | DJ76: 2000000 | DK76: 0 | DL76: 0 | DM76: 0 | DN76: 0 | DO76: 0 | DP76: 0 | DQ76: 0 | DR76: 0 | DS76: 0 | DT76: 0 | DU76: 0 | DW76: 3500000
B77: Value of Loans Recovered | AA77: 0 | AB77: 0 | AC77: 0 | AZ77: 0 | BA77: 0 | BB77: 0 | BC77: 0 | BD77: 0 | BE77: 0 | BH77: 0 | BI77: 0 | BK77: 0 | BL77: 0 | BM77: 0 | BN77: 0 | BO77: 0 | BP77: 0 | BQ77: 0 | BR77: 0 | BS77: 0 | BT77: 0 | BU77: 0 | BV77: 0 | BX77: 0 | BY77: 0 | BZ77: 0 | CA77: 0 | CB77: 0 | CC77: 0 | CD77: 0 | CE77: 0 | CF77: 0 | CG77: 0 | CH77: 0 | CI77: 0 | CJ77: 0 | CL77: 0 | CM77: 0 | CN77: 0 | CO77: 0 | CP77: 0 | CR77: 0 | CS77: 0 | CT77: 0 | CU77: 0 | CV77: 0 | CX77: 0 | CY77: 0 | CZ77: 0 | DA77: 0 | DB77: 0 | DC77: 0 | DD77: 0 | DE77: 0 | DF77: 0 | DG77: 0 | DH77: 0 | DI77: 0 | DK77: 0 | DL77: 0 | DM77: 0 | DN77: 0 | DO77: 0 | DP77: 0 | DQ77: 0 | DR77: 0 | DS77: 0 | DT77: 0 | DU77: 0
B78: Operating Expenses | D78: =SUM(D79:D83) -> 375359 | E78: =SUM(E79:E83) -> 767775 | F78: =SUM(F79:F83) -> 2044361 | G78: =SUM(G79:G83) -> 3663758 | H78: =SUM(H79:H83) -> 3739 | I78: =SUM(I79:I83) -> 4107284 | J78: =SUM(J79:J83) -> 468718300 | K78: =SUM(K79:K83) -> 988800 | ... DW78: =SUM(DW79:DW83) -> 30003663
B79: Personnel Expenses | C79: 4800 | D79: 73280 | E79: 272910 | F79: 756385 | G79: 1320054 | H79: 1471.5 | I79: 1380169 | J79: 140340200 | K79: 264900 | L79: 391100 | M79: 564400 | N79: 694200 | O79: 859170 | P79: 1055875 | Q79: 1203190 | R79: 1344320 | S79: 1491410 | V79: 1980619 | W79: 161865 | X79: 300750 | Y79: 436135 | Z79: 750650 | AA79: 977095 | AB79: 1282943 | AC79: 1520808 | AD79: 1759778 | AE79: 2015118 | AF79: 2252380 | AG79: 2490645 | AH79: 2766210 | AI79: 2751160 | AJ79: 2751160 | AL79: 488941 | AM79: 758976 | AN79: 1159166 | AO79: 1430246 | AQ79: 1667621 | AR79: 2192889 | AU79: 2924784 | AV79: 3829559 | AW79: =2385610+270601+98000+94264+109700 -> 2958175 | AZ79: 995929 | BA79: 3445110 | BB79: 1827725 | BC79: 2185210 | BD79: 2630810 | BE79: 3016170 | BF79: 3016170 | BH79: 4538670 | BI79: 4894841 | BJ79: 985445 | BK79: 322908 | BL79: 760763 | BM79: 1484053 | BN79: 1563165 | BO79: 2853600 | BP79: 2619574 | BQ79: 3664274 | BR79: 3402299 | BS79: 3402299 | BT79: 4203079 | BU79: 4623734 | BV79: 5138097 | BW79: 2890323 | BX79: 392120 | BY79: 788932 | BZ79: 1281502 | CA79: 1696986 | CB79: 2094528 | CC79: 2610628 | CD79: 2667875 | CE79: 3546317 | CF79: 4000524 | CG79: 4461661 | CH79: 5118948 | CI79: 5576360 | CJ79: 5576360 | CK79: 445347 | CL79: 940592 | CM79: 1412319 | CN79: 1909386 | CO79: 2398176 | CP79: 2932938 | CR79: 3949484 | CS79: 4522672 | CT79: 10625986 | CU79: 5975095 | CV79: 6650515 | CW79: 6650515 | CX79: 636520 | CY79: 1260133 | CZ79: 1891831.3 | DA79: 2518111.3 | DB79: 3111112.3 | DC79: 3871738 | DD79: 4327958.3 | DE79: 4975517.3 | DF79: 5735652.3 | DG79: 6794071.3 | DH79: 7651929.3 | DI79: 8698422.3 | DJ79: 8577645 | DK79: 771051 | DL79: 1687223 | DM79: 2313088 | DN79: 3079006 | DO79: 3831864 | DP79: 4751649.5 | DQ79: 5590102.5 | DR79: 6372545 | DS79: 7184906.5 | DT79: 8134057 | DU79: 9378226.5 | DW79: 10626352
B80: Governance Expenses | C80: 43100 | D80: 87359 | E80: 167980 | F80: 390700 | G80: 765660 | H80: 795.5 | I80: 1212154 | J80: 87387300 | K80: 366500 | L80: 539600 | M80: 601200 | N80: 669155 | O80: 749609 | P80: 824809 | Q80: 907509 | R80: 967809 | S80: 1036959 | V80: 1358301 | W80: 94300 | X80: 172010 | Y80: 569545 | Z80: 644645 | AA80: 709245 | AB80: 692645 | AC80: 745845 | AD80: 823693 | AE80: 888593 | AF80: 960293 | AG80: 1045493 | AH80: 1283293 | AI80: 2076338 | AJ80: 2076338 | AL80: 356314 | AM80: 588704 | AN80: 657504 | AO80: 731704 | AQ80: 794004 | AR80: 947504 | AU80: 1175599 | AV80: 1503114 | AW80: =324100+203750+262400+275600+346604+789557 -> 2202011 | AZ80: 190200 | BA80: 1225984 | BB80: 809092 | BC80: 894392 | BD80: 948292 | BE80: 1072987 | BF80: 1072987 | BH80: 1500123 | BI80: 2882154.1 | BJ80: 2675783 | BK80: 52100 | BL80: 215300 | BM80: 610322 | BN80: 770915 | BO80: 878915 | BP80: 1044725 | BQ80: 1198505 | BR80: 1553155 | BS80: 1651875 | BT80: 1745775 | BU80: 1930595 | BV80: 2095515 | BW80: 3377915 | BX80: 686050 | BY80: 831050 | BZ80: 1310410 | CA80: 1400610 | CB80: 1638010 | CC80: 1896430 | CD80: 2076980 | CE80: 2170880 | CF80: 2238180 | CG80: 2436880 | CH80: 2735705 | CI80: 3000005 | CJ80: 3000005 | CK80: 96200 | CL80: 357690 | CM80: 865360 | CN80: 897960 | CO80: 928560 | CP80: 994360 | CR80: 1290110 | CS80: 1400310 | CT80: 3017220 | CU80: 1673510 | CV80: 2467460 | CW80: 2467460 | CX80: 190500 | CY80: 442660 | CZ80: 826805 | DA80: 965105 | DB80: 1169015 | DC80: 1426265 | DD80: 1703805 | DE80: 2086360 | DF80: 2551495 | DG80: 2805995 | DH80: 3071210 | DI80: 3577410 | DJ80: 3697410 | DK80: 267300 | DL80: 385800 | DM80: 916495 | DN80: 1261145 | DO80: 1478745 | DP80: 1749475 | DQ80: 1980825 | DR80: 2147595 | DS80: 2471755 | DT80: 2616855 | DU80: 2959080 | DW80: 3820680
B81: Marketing Expenses | C81: 1960 | D81: 12800 | H81: 329.5 | J81: 12682700 | K81: 32700 | L81: 167700 | M81: 258900 | N81: 358768 | O81: 392444 | P81: 289511 | Q81: 273011 | R81: 273111 | S81: 436961 | W81: 1110 | X81: 36010 | Y81: 397590 | Z81: 486980 | AA81: 580870 | AB81: 605790 | AC81: 633390 | AD81: 688045.2 | AE81: 725195.2 | AF81: 715665.2 | AG81: 729215.2 | AH81: 742615.15 | AL81: 304600 | AM81: 382690 | AN81: 411740 | AO81: 402814 | AQ81: 563824 | AR81: 745264 | AU81: 758414 | AV81: 851597 | AZ81: 182610 | BA81: 897640 | BB81: 451730 | BC81: 457740 | BD81: 505030 | BE81: 643505 | BF81: 643505 | BH81: 740775 | BI81: 755975 | BJ81: 2010974 | BK81: 384800 | BL81: 383920 | BM81: 507330 | BN81: 633830 | BO81: 661080 | BP81: 753590 | BQ81: 977550 | BR81: 1141950 | BS81: 1143350 | BT81: 1209400 | BU81: 1289880 | BV81: 1285400 | BW81: 2218522 | BX81: 133200 | BY81: 353570 | BZ81: 506440 | CA81: 609910 | CB81: 646620 | CC81: 928040 | CD81: 1307820 | CE81: 1196260 | CF81: 1374360 | CG81: 1412573 | CH81: 1517273 | CI81: 1538773 | CJ81: 1538773 | CK81: 151500 | CL81: 278800 | CM81: 342480 | CN81: 377250 | CO81: 383000 | CP81: 393490 | CR81: 517701 | CS81: 528701 | CT81: 1204742 | CU81: 606371 | CV81: 790471 | CW81: 790471 | CX81: 26000 | CY81: 104700 | CZ81: 146600 | DA81: 372285 | DB81: 575355 | DC81: 899040 | DD81: 930290 | DE81: 950990 | DF81: 968810 | DG81: 1042610 | DH81: 1080710 | DI81: 1114260 | DJ81: 1114260 | DK81: 170660 | DL81: 179160 | DM81: 504520 | DN81: 546280 | DO81: 635440 | DP81: 669565 | DQ81: 917135 | DR81: 1066635 | DS81: 1122335 | DT81: 1300240 | DU81: 1407685 | DW81: 1606785
B82: Depreciation and Amortization Charges | C82: 4128 | D82: 20893 | E82: 134348 | F82: 491719 | G82: 521479 | H82: 0 | I82: 584058 | J82: 0 | K82: 0 | L82: 0 | M82: 0 | N82: 0 | O82: 0 | P82: 0 | Q82: 0 | R82: 0 | S82: 0 | V82: 252196 | AA82: 0 | AB82: 0 | AC82: 0 | AD82: 0 | AE82: 0 | AF82: 0 | AG82: 0 | AH82: 0 | AI82: 431538 | AJ82: 431538 | AL82: 0 | AM82: 0 | AN82: 0 | AO82: 0 | AQ82: 0 | AR82: 0 | AU82: 0 | AV82: 0 | AW82: 530508 | AZ82: 0 | BA82: 0 | BB82: 0 | BC82: 0 | BD82: 0 | BE82: 0 | BH82: 0 | BI82: 0 | BJ82: 1389959 | BK82: 0 | BL82: 0 | BM82: 0 | BN82: 0 | BO82: 0 | BP82: 0 | BQ82: 0 | BR82: 0 | BS82: 0 | BT82: 0 | BU82: 0 | BV82: 1330072 | BX82: 0 | BY82: 0 | BZ82: 0 | CA82: 0 | CB82: 0 | CC82: 0 | CD82: 0 | CE82: 0 | CF82: 0 | CG82: 0 | CH82: 0 | CI82: 1427260.6 | CJ82: 1450195.6 | CK82: 0 | CL82: 0 | CM82: 0 | CN82: 0 | CO82: 0 | CP82: 0 | CR82: 0 | CS82: 0 | CT82: 0 | CU82: 0 | CV82: 1613574.5 | CW82: 1613574.5 | CX82: 0 | CY82: 0 | CZ82: 0 | DA82: 0 | DB82: 0 | DC82: 0 | DD82: 0 | DE82: 0 | DF82: 0 | DG82: 0 | DH82: 0 | DI82: 0 | DJ82: 1905584 | DK82: 0 | DL82: 0 | DM82: 0 | DN82: 0 | DO82: 0 | DP82: 0 | DQ82: 0 | DR82: 0 | DS82: 0 | DT82: 0 | DU82: 0 | DW82: 2024860
B83: Administrative Expenses | C83: 132523 | D83: 181027 | E83: 192537 | F83: 405557 | G83: =165352+877813+13400 -> 1056565 | H83: 1142.5 | I83: =181150+749753 -> 930903 | J83: 228308100 | K83: 324700 | L83: 480700 | M83: 550600 | N83: 572187 | O83: 691263 | P83: 1033594 | Q83: 1257716 | R83: 1297864 | S83: 2019097 | V83: =464635+1065007 -> 1529642 | W83: 200339.7 | X83: 285117.7 | Y83: 359301.7 | Z83: 741178.7 | AA83: 1422380.7 | AB83: 1017110.7 | AC83: 1115799.7 | AD83: 1184878.7 | AE83: 1778326.7 | AF83: 1872880.9 | AG83: 2029481.1 | AH83: 2070644.1 | AI83: =1022802+978854 -> 2001656 | AJ83: =1022802+978854 -> 2001656 | AL83: 712420 | AM83: 995971 | AN83: 1199194 | AO83: 1242783 | AQ83: 1318408 | AR83: 1941022 | AU83: 2642670 | AV83: 4337851.5 | AW83: =1675939+310710 -> 1986649 | AZ83: 674983 | BA83: 1885812 | BB83: 1057711 | BC83: 1329102 | BD83: 1447939 | BE83: 1610181.8 | BF83: 1610181.8 | BH83: 2938851.3 | BI83: 3312288.2 | BJ83: 4471978 | BK83: 626796 | BL83: 1079579 | BM83: 1340769.7 | BN83: 1848772 | BO83: 1954853 | BP83: 2110957 | BQ83: 2955888 | BR83: 4284860 | BS83: 4867454.8 | BT83: 6029154 | BU83: 4163735 | BV83: 7578688 | BW83: 5138097 | BX83: 248755 | BY83: 1092573 | BZ83: 2251300 | CA83: 2938856 | CB83: 3177755 | CC83: 3177755 | CD83: 4327154 | CE83: 4351154 | CF83: 4644540 | CG83: 4891766 | CH83: 6693085.1 | CI83: 7429804 | CJ83: 7429804 | CK83: 603473 | CL83: 1053834 | CM83: 1711295 | CN83: 2238996 | CO83: 2978543 | CP83: 3558901 | CR83: 4638876 | CS83: 6073726 | CT83: 13643690 | CU83: 7248802 | CV83: 8212094 | CW83: 8319094 | CX83: 504524 | CY83: 858027 | CZ83: 1767287 | DA83: 2328382 | DB83: 2897178.2 | DC83: 4182623.2 | DD83: 4413962.9 | DE83: 4807891.9 | DF83: 5109986.4 | DG83: 7614850.2 | DH83: 8259908 | DI83: 13034377 | DJ83: 12301909 | DK83: 643546.75 | DL83: 1123515.1 | DM83: 1991792.4 | DN83: 2927742.5 | DO83: 3339237.5 | DP83: 4413391.5 | DQ83: 5045887 | DR83: 5621348 | DS83: 6690432.9 | DT83: 9737488.9 | DU83: 10383939 | DW83: 11924986
B84: Net Operating Income | D84: =D74-D75-D78 -> 44058 | E84: =E74-E75-E78 -> 73543 | F84: =F74-F75-F78 -> 369354 | G84: =G74-G75-G78 -> 352275 | H84: =H74-H75-H78 -> 5201.4 | I84: =I74-I75-I78 -> 1151699 | J84: =J74-J75-J78 -> -4.7146066e+08 | K84: =K74-K75-K78 -> -990658.87 | ... DW84: =DW74-DW75-DW78 -> 11853757
B85: Net Non Operating Income | D85: =D86-D87 -> 0 | E85: =E86-E87 -> 0 | F85: =F86-F87 -> 0 | G85: =G86-G87 -> 0 | H85: =H86-H87 -> 0 | I85: =I86-I87 -> 0 | J85: =J86-J87 -> 0 | K85: =K86-K87 -> 0 | ... DW85: =DW86-DW87 -> 0
B86: Non Operating Income | AA86: 0 | AB86: 0 | AC86: 0 | AZ86: 0 | BA86: 0 | BB86: 0 | BC86: 0 | BD86: 0 | BE86: 0 | BH86: 0 | BI86: 0 | BK86: 0 | BL86: 0 | BM86: 0 | BN86: 0 | BO86: 0 | BP86: 0 | BQ86: 0 | BR86: 0 | BS86: 0 | BT86: 0 | BU86: 0 | BV86: 0 | BX86: 0 | BY86: 0 | BZ86: 0 | CA86: 0 | CB86: 0 | CC86: 0 | CD86: 0 | CE86: 0 | CF86: 0 | CG86: 0 | CH86: 0 | CI86: 0 | CJ86: 0 | CK86: 0 | CL86: 0 | CM86: 0 | CN86: 0 | CO86: 0 | CP86: 0 | CR86: 0 | CS86: 0 | CT86: 0 | CU86: 0 | CV86: 550418.5 | CW86: 550418.5 | CX86: 0 | CY86: 0 | CZ86: 0 | DA86: 0 | DB86: 0 | DC86: 0 | DD86: 0 | DE86: 0 | DF86: 0 | DG86: 0 | DH86: 0 | DI86: 0 | DJ86: 0 | DK86: 0 | DL86: 0 | DM86: 0 | DN86: 0 | DO86: 0 | DP86: 0 | DQ86: 0 | DR86: 0 | DS86: 0 | DT86: 0 | DU86: 0
B87: Non Operating Expense | AA87: 0 | AB87: 0 | AC87: 0 | AZ87: 0 | BA87: 0 | BB87: 0 | BC87: 0 | BD87: 0 | BE87: 0 | BH87: 0 | BI87: 0 | BK87: 0 | BL87: 0 | BM87: 0 | BN87: 0 | BO87: 0 | BP87: 0 | BQ87: 0 | BR87: 0 | BS87: 0 | BT87: 0 | BU87: 0 | BV87: 0 | BX87: 0 | BY87: 0 | BZ87: 0 | CA87: 0 | CB87: 0 | CC87: 0 | CD87: 0 | CE87: 0 | CF87: 0 | CG87: 0 | CH87: 0 | CI87: 0 | CJ87: 0 | CK87: 0 | CL87: 0 | CM87: 0 | CN87: 0 | CO87: 0 | CP87: 0 | CR87: 0 | CS87: 0 | CT87: 0 | CU87: 0 | CV87: 500000 | CX87: 0 | CY87: 0 | CZ87: 0 | DA87: 0 | DB87: 0 | DC87: 0 | DD87: 0 | DE87: 0 | DF87: 0 | DG87: 0 | DH87: 0 | DI87: 0 | DK87: 0 | DL87: 0 | DM87: 0 | DN87: 0 | DO87: 0 | DP87: 0 | DQ87: 0 | DR87: 0 | DS87: 0 | DT87: 0 | DU87: 0
B88: Net Income before tax | D88: =D84+D85 -> 44058 | E88: =E84+E85 -> 73543 | F88: =F84+F85 -> 369354 | G88: =G84+G85 -> 352275 | H88: =H84+H85 -> 5201.4 | I88: =I84+I85 -> 1151699 | J88: =J84+J85 -> -4.7146066e+08 | K88: =K84+K85 -> -990658.87 | ... DW88: =DW84+DW85 -> 11853757
B89: Taxes | E89: 5648 | F89: 7092 | G89: 5134 | I89: 4651 | J89: 0 | K89: 0 | L89: 3000 | M89: 10100 | N89: 17140 | O89: 69118 | P89: 82747 | Q89: 96128 | R89: 110974 | S89: 125639 | V89: 4862 | W89: 16418 | X89: 29141 | Y89: 19562 | Z89: 33373 | AA89: 47505 | AB89: 44767 | AC89: 57157 | AD89: 60082 | AE89: 69929.2 | AF89: 45994.9 | AG89: 56896.9 | AH89: 66974.9 | AI89: 3866 | AJ89: 3867 | AL89: -1310.8 | AM89: -3389.4 | AN89: -4707.5 | AO89: -6266.5 | AQ89: 4647.6 | AR89: 35768.1 | AU89: 58750.1 | AV89: 33632.4 | AW89: 305555 | AZ89: 10191 | BA89: 20382 | BB89: -5763 | BC89: 0 | BD89: 49153 | BE89: 0 | BH89: 0 | BI89: 0 | BJ89: 302193 | BK89: 0 | BL89: 585583 | BM89: 0 | BN89: 0 | BO89: 0 | BP89: 0 | BQ89: 0 | BR89: 0 | BS89: 0 | BT89: 0 | BU89: 0 | BV89: 0 | BW89: 218211.94 | BX89: 0 | BZ89: 0 | CA89: 0 | CB89: 0 | CC89: 0 | CD89: 0 | CE89: 0 | CF89: 0 | CG89: 0 | CH89: 0 | CI89: 381333.7 | CJ89: 381333.7 | CL89: 0 | CM89: 0 | CN89: 0 | CO89: 0 | CP89: 0 | CR89: 0 | CS89: 0 | CT89: 0 | CU89: 0 | CV89: 368496 | CW89: 368496.03 | CX89: 0 | CY89: 0 | CZ89: 0 | DA89: 0 | DB89: 0 | DC89: 0 | DD89: 0 | DE89: 0 | DF89: 0 | DG89: 0 | DH89: 0 | DI89: 0 | DJ89: 726933 | DK89: 0 | DL89: 0 | DM89: 0 | DN89: 225816 | DO89: 233916 | DP89: 444386 | DQ89: 444386 | DR89: 453236 | DS89: 461336 | DT89: 671238 | DU89: 678678 | DW89: 722500
B90: Net Income After Tax Before Donations | D90: =D88-D89 -> 44058 | E90: =E88-E89 -> 67895 | F90: =F88-F89 -> 362262 | G90: =G88-G89 -> 347141 | H90: =H88-H89 -> 5201.4 | I90: =I88-I89 -> 1147048 | J90: =J88-J89 -> -4.7146066e+08 | K90: =K88-K89 -> -990658.87 | ... DW90: =DW88-DW89 -> 11131257
B91: Donations | AB91: 0 | AZ91: 0 | BA91: 0 | BB91: 0 | BC91: 0 | BD91: 0 | BE91: 0 | BH91: 0 | BI91: 0 | BK91: 0 | BL91: 0 | BM91: 0 | BN91: 0 | BO91: 0 | BP91: 0 | BQ91: 0 | BR91: 0 | BS91: 0 | BT91: 0 | BU91: 0 | BV91: 0 | BX91: 0 | BZ91: 0 | CA91: 0 | CB91: 0 | CC91: 0 | CD91: 0 | CE91: 0 | CF91: 0 | CG91: 0 | CH91: 0 | CI91: 0 | CJ91: 0 | CK91: 0 | CL91: 0 | CM91: 0 | CN91: 0 | CO91: 0 | CP91: 0 | CR91: 0 | CS91: 0 | CT91: 0 | CU91: 0 | CV91: 0 | CX91: 0 | CY91: 0 | CZ91: 0 | DA91: 0 | DB91: 0 | DC91: 0 | DD91: 0 | DE91: 0 | DF91: 0 | DG91: 0 | DH91: 0 | DI91: 0 | DK91: 0 | DL91: 0 | DM91: 0 | DN91: 0 | DO91: 0 | DP91: 0 | DQ91: 0 | DR91: 0 | DS91: 0 | DT91: 0 | DU91: 0
B92: Net Income | D92: =D90-D91 -> 44058 | E92: =E90-E91 -> 67895 | F92: =F90-F91 -> 362262 | G92: =G90-G91 -> 347141 | H92: =H90-H91 -> 5201.4 | I92: =I90-I91 -> 1147048 | J92: =J90-J91 -> -4.7146066e+08 | K92: =K90-K91 -> -990658.87 | ... DW92: =DW90-DW91 -> 11131257
W93: =X78/W78-1 -> 0.73483872 | X93: =Y78/X78-1 -> 1.2201776 | Y93: =Z78/Y78-1 -> 0.48842382 | Z93: =AA78/Z78-1 -> 0.40638683 | AA93: =AB78/AA78-1 -> -0.024691628 | AB93: =AC78/AB78-1 -> 0.11598035 | AC93: =AD78/AC78-1 -> 0.10970354
DW95: 11852756

Sheet Financials
B2: NYAHURURU UMOJA (VICTAS)
B3: Year | C3: 2008 | D3: 2009 | E3: 2010 | F3: 2011 | G3: 2012 | H3: 41609 | I3: 2013 | J3: 41640 | K3: 41671 | L3: 41699 | M3: 41730 | N3: 41760 | O3: 41791 | P3: 41821 | Q3: 41852 | R3: 41883 | S3: 41913 | T3: 41944 | U3: 41974 | V3: 2014 | W3: Jan-15 | X3: Feb-15 | Y3: Mar-15 | Z3: Apr-15 | AA3: 42125 | AB3: 42156 | AC3: 42186 | AD3: 42217 | AE3: 42248 | AF3: 42278 | AG3: 42309 | AH3: 42339 | AI3: 2015 | AJ3: 2015 Rev. | AK3: 42385 | AL3: 42416 | AM3: 42445 | AN3: 42476 | AO3: 42506 | AP3: 42537 | AQ3: Jul-16 | AR3: Aug-16 | AS3: Sept-16 | AT3: Oct-16 | AU3: Nov-16 | AV3: Dec-16 | AW3: Aud-16 | AX3: Jan-2017 | AY3: Feb-2017 | AZ3: Mar-2017 | BA3: Apr-2017 | BB3: 42856 | BC3: 42887 | BD3: 42917 | BE3: 42948 | BF3: 42979 | BG3: 43009 | BH3: 43040 | BI3: 43070 | BJ3: Aud-17 | BK3: 43101 | BL3: 43132 | BM3: 43160 | BN3: 43191 | BO3: 43221 | BP3: 43252 | BQ3: 43282 | BR3: 43313 | BS3: 43344 | BT3: 43374 | BU3: 43405 | BV3: 43435 | BW3: Audited 2018 | BX3: 43466 | BY3: 43497 | BZ3: 43525 | CA3: 43556 | CB3: 43586 | CC3: 43617 | CD3: 43647 | CE3: 43678 | CF3: 43709 | CG3: 43739 | CH3: 43770 | CI3: 43800 | CJ3: Audited-2019 | CK3: 43831 | CL3: 43862 | CM3: 43891 | CN3: 43922 | CO3: 43952 | CP3: 43983 | CQ3: 44013 | CR3: 44044 | CS3: 44075 | CT3: 44105 | CU3: 44136 | CV3: 44166 | CW3: Audited 2021 | CX3: 44197 | CY3: 44228 | CZ3: 44256 | DA3: 44287 | DB3: 44317 | DC3: 44348 | DD3: 44378 | DE3: 44409 | DF3: 44440 | DG3: 44470 | DH3: 44501 | DI3: 44531 | DJ3: Audited-2021 | DK3: 44562 | DL3: 44593 | DM3: 44621 | DN3: 44652 | DO3: 44682 | DP3: 44713 | DQ3: 44743 | DR3: 44774 | DS3: 44805 | DT3: 44835 | DU3: 44866 | DV3: 44896 | DW3: Audited 2022
A4: 1 | B4: Membership | C4: 179 | D4: 309 | E4: 697 | F4: 882 | G4: 1128 | I4: 1310
A5: 2 | B5: Total Assets | C5: =Trend!C27 -> 3475410 | D5: =Trend!D27 -> 8750647 | E5: =Trend!E27 -> 19015501 | F5: =Trend!F27 -> 35649419 | G5: =Trend!G27 -> 48282362 | H5: =Trend!H27 -> 75358469 | I5: =Trend!I27 -> 71384601 | J5: =Trend!J27 -> 1.5365653e+08 | ... DW5: =Trend!DW27 -> 415120522
A6: 3 | B6: Total Deposits | C6: =Trend!C31 -> 2279348 | D6: =Trend!D31 -> 5920804 | E6: =Trend!E31 -> 8325050 | F6: =Trend!F31 -> 17127596 | G6: =Trend!G31 -> 29393861 | H6: =Trend!H31 -> 46049825 | I6: =Trend!I31 -> 43745777 | J6: =Trend!J31 -> 94351720 | ... DW6: =Trend!DW31 -> 285244427
A7: 3.1 | B7: Deposits-Members(BOSA) | C7: =Trend!C30 -> 2181426 | D7: =Trend!D30 -> 5388952 | E7: =Trend!E30 -> 7001000 | F7: =Trend!F30 -> 14533589 | G7: =Trend!G30 -> 21381443 | H7: =Trend!H30 -> 43845984 | I7: =Trend!I30 -> 32277459 | J7: =Trend!J30 -> 89972427 | ... DR7: =Trend!DR30 -> 2.1984675e+08 | DS7: =Trend!DS29 -> 10933569 | DT7: =Trend!DT29 -> 11827028 | DU7: =Trend!DU29 -> 11884327 | DV7: =Trend!DV30 -> 0 | DW7: =Trend!DW30 -> 226107824
A8: 3.2 | B8: Deposits-Customers(FOSA) | C8: =Trend!C28 -> 97922 | D8: =Trend!D28 -> 531852 | E8: =Trend!E28 -> 1324050 | F8: =Trend!F28 -> 2594007 | G8: =Trend!G28 -> 8012418 | H8: =Trend!H28 -> 1189925 | I8: =Trend!I28 -> 11468318 | J8: =Trend!J28 -> 2349166 | ... DR8: =Trend!DR28 -> 46858158 | DS8: =Trend!DS27 -> 4.0179739e+08 | DT8: =Trend!DT27 -> 4.0708972e+08 | DU8: =Trend!DU27 -> 4.1539737e+08 | DV8: =Trend!DV28 -> 0 | DW8: =Trend!DW28 -> 42297148
A9: 4 | B9: External Borrowing | C9: =Trend!C38 -> 0 | D9: =Trend!D38 -> 1000000 | E9: =Trend!E38 -> 0 | F9: =Trend!F38 -> 2870718 | G9: =Trend!G38 -> 560210 | H9: =Trend!H38 -> 4033865 | I9: =Trend!I38 -> 4033865 | J9: =Trend!J38 -> 8067730 | ... DW9: =Trend!DW38 -> 5845335
A10: 4.1 | B10: Short term Liabilities | C10: =Trend!C33+Trend!C34+Trend!C35+Trend!C37 -> 756201 | D10: =Trend!D33+Trend!D34+Trend!D35+Trend!D37 -> 1092982 | E10: =Trend!E33+Trend!E34+Trend!E35+Trend!E37 -> 1853609 | F10: =Trend!F33+Trend!F34+Trend!F35+Trend!F37 -> 3794239 | G10: =Trend!G33+Trend!G34+Trend!G35+Trend!G37 -> 2398143 | H10: =Trend!H33+Trend!H34+Trend!H35+Trend!H37 -> 0 | I10: =Trend!I33+Trend!I34+Trend!I35+Trend!I37 -> 3300600 | J10: =Trend!J33+Trend!J34+Trend!J35+Trend!J37 -> 117393.35 | ... DR10: =Trend!DR33+Trend!DR34+Trend!DR35+Trend!DR37 -> 1553728.5 | DS10: =Trend!DS33+Trend!DS34+Trend!DS36+Trend!DS38 -> 6824172 | DT10: =Trend!DT33+Trend!DT34+Trend!DT36+Trend!DT38 -> 5844172 | DU10: =Trend!DU33+Trend!DU34+Trend!DU36+Trend!DU38 -> 5819749 | DV10: =Trend!DV33+Trend!DV34+Trend!DV35+Trend!DV37 -> 0 | DW10: =Trend!DW33+Trend!DW34+Trend!DW35+Trend!DW37 -> 26513232
A12: 5 | B12: Share capital and Reserves
A13: 5.1 | B13: Core Capital | C13: =C16 -> 439861 | D13: =D16 -> 736861 | E13: =E16 -> 8453756 | F13: =F16 -> 11449334 | G13: =G16 -> 15452148 | H13: =H16 -> 25274778 | I13: =I16 -> 19725079 | J13: =J16 -> 51119689 | ... DW13: =DW16 -> 97517528
A14: 5.2 | B14: Institutional Capital | C14: =C13-C17 -> 81861 | D14: =D13-D17 -> 118861 | E14: =E13-E17 -> 983756 | F14: =F13-F17 -> 1261018 | G14: =G13-G17 -> 2352159 | H14: =H13-H17 -> 8378557.1 | I14: =I13-I17 -> 3746438 | J14: =J13-J17 -> 17191947 | ... DW14: =DW13-DW17 -> 44204190
A16: 5.3 | B16: Total Capital | C16: =SUM(C17:C20) -> 439861 | D16: =SUM(D17:D20) -> 736861 | E16: =SUM(E17:E20) -> 8453756 | F16: =SUM(F17:F20) -> 11449334 | G16: =SUM(G17:G20) -> 15452148 | H16: =SUM(H17:H20) -> 25274778 | I16: =SUM(I17:I20) -> 19725079 | J16: =SUM(J17:J20) -> 51119689 | ... DW16: =SUM(DW17:DW20) -> 97517528
A17: 5.3.1 | B17: Members Share Capital | C17: =Trend!C40 -> 358000 | D17: =Trend!D40 -> 618000 | E17: =Trend!E40 -> 7470000 | F17: =Trend!F40 -> 10188316 | G17: =Trend!G40 -> 13099989 | H17: =Trend!H40 -> 16896221 | I17: =Trend!I40 -> 15978641 | J17: =Trend!J40 -> 33927742 | ... CK17: =Trend!CK40 -> 32177150 | CL17: =Trend!#REF! -> #REF! | CM17: =Trend!CM40 -> 32816015 | CN17: =Trend!CN40 -> 32990257 | CO17: =Trend!CO40 -> 33158170 | CP17: =Trend!CP40 -> 33451675 | CQ17: =Trend!CQ40 -> 33844749 | CR17: =Trend!CR40 -> 34213651 | CS17: =Trend!CS40 -> 34987929 | CT17: =Trend!CT40 -> 34582419 | ... DW17: =Trend!DW40 -> 53313338
A18: 5.3.3 | B18: Retained Earnings | C18: =Trend!C42 -> 24089 | D18: =Trend!D42 -> 46089 | E18: =Trend!E42 -> 88005 | F18: =Trend!F42 -> 211308 | G18: =Trend!G42 -> 325421 | H18: =Trend!H42 -> 5055549.1 | I18: =Trend!I42 -> 394020 | J18: =Trend!J42 -> 10499631 | ... DW18: =Trend!DW42 -> 17077729
A19: 5.3.5 | B19: Statutory Reserves | C19: =Trend!C46 -> 19772 | D19: =Trend!D46 -> 34772 | E19: =Trend!E46 -> 57751 | F19: =Trend!F46 -> 211710 | G19: =Trend!G46 -> 359738 | H19: =Trend!H46 -> 359738 | I19: =Trend!I46 -> 589148 | J19: =Trend!J46 -> 719476 | ... DW19: =Trend!DW46 -> 11130433
A20: 5.3.6 | B20: Capital Reserve | C20: =Trend!C47 -> 38000 | D20: =Trend!D47 -> 38000 | E20: =Trend!E47 -> 838000 | F20: =Trend!F47 -> 838000 | G20: =Trend!G47 -> 1667000 | H20: =Trend!H47 -> 2963270 | I20: =Trend!I47 -> 2763270 | J20: =Trend!J47 -> 5972840 | ... DW20: =Trend!DW47 -> 15996028
A21: 5.3.7 | B21: Supplementary Capital & reserves
A22: a | B22: Proposed Dividends | C22: =Trend!C68+Trend!C69 -> 0 | D22: =Trend!D68+Trend!D69 -> 0 | E22: =Trend!E68+Trend!E69 -> 1138470 | F22: =Trend!F68+Trend!F69 -> 1388148 | G22: =Trend!G68+Trend!G69 -> 1753935 | H22: =Trend!H68+Trend!H69 -> 0 | I22: =Trend!I68+Trend!I69 -> 2958639 | J22: =Trend!J68+Trend!J69 -> 0 | ... DW22: =Trend!DW68+Trend!DW69 -> 20925037
A23: b
A25: 6 | B25: Investments | C25: =SUM(C26:C27) -> 69500 | D25: =SUM(D26:D27) -> 149500 | E25: =SUM(E26:E27) -> 209500 | F25: =SUM(F26:F27) -> 219500 | G25: =SUM(G26:G27) -> 227500 | H25: =SUM(H26:H27) -> 3370491.9 | I25: =SUM(I26:I27) -> 227686 | J25: =SUM(J26:J27) -> 6740983.7 | ... DW25: =SUM(DW26:DW27) -> 17961747
A26: 6.1 | B26: Investments in Coop bank, CIC, Kuscco, Kerussu & Codic | C26: =Trend!C12 -> 0 | D26: =Trend!D12 -> 0 | E26: =Trend!E12 -> 0 | F26: =Trend!F12 -> 0 | G26: =Trend!G12 -> 0 | H26: =Trend!H12 -> 3370491.9 | I26: =Trend!I12 -> 0 | J26: =Trend!J12 -> 6740983.7 | ... CL26: =Trend!CL12 -> 4044415.5 | CM26: =Trend!#REF! -> #REF! | CN26: =Trend!CN12 -> 4254415 | CO26: =Trend!CO12 -> 4359415.5 | CP26: =Trend!CP12 -> 36110000 | CQ26: =Trend!CQ12 -> 4579282.8 | CR26: =Trend!CR12 -> 4702456 | CS26: =Trend!CS12 -> 4912456 | CT26: =Trend!CT12 -> 4912456 | CU26: =Trend!CU12 -> 5017456.7 | CV26: =Trend!CV12 -> 5122456.7 | CW26: =Trend!CW22 -> 0 | CX26: =Trend!CX22 -> 0 | CY26: =Trend!CY22 -> 0 | CZ26: =Trend!CZ22 -> 0 | DA26: =Trend!DA22 -> 0 | DB26: =Trend!DB22 -> 0 | DC26: =Trend!DC22 -> 0 | DD26: =Trend!DD22 -> 0 | ... DR26: =Trend!DR22 -> 620249 | DS26: =Trend!DS21 -> 19736376 | DT26: =Trend!DT21 -> 19866676 | DU26: =Trend!DU21 -> 19866676 | DV26: =Trend!DV21 -> 0 | DW26: =Trend!DW21 -> 17961747
A27: 6.2 | B27: Equity Investments (at cost) | C27: =Trend!C13 -> 69500 | D27: =Trend!D13 -> 149500 | E27: =Trend!E13 -> 209500 | F27: =Trend!F13 -> 219500 | G27: =Trend!G13 -> 227500 | H27: =Trend!H13 -> 0 | I27: =Trend!I13 -> 227686 | J27: =Trend!J13 -> 0 | ... CL27: =Trend!CL13 -> 10000000 | CM27: =Trend!CM12 -> 4149415.5 | CN27: =Trend!CN13 -> 29620249 | CO27: =Trend!CO13 -> 20190068 | CP27: =Trend!CP13 -> 4464415.5 | CQ27: =Trend!CQ13 -> 33618191 | CR27: =Trend!CR13 -> 28535519 | CS27: =Trend!CS13 -> 34397489 | CT27: =Trend!CT13 -> 34397489 | CU27: =Trend!CU13 -> 36281996 | ... DW27: =Trend!DW13 -> 0
A28: 6.3 | B28: Deposits in KUSCCO CFP
DQ29: =DM30-DP30 -> -14998186
A30: 7 | B30: Net Loans & advances | C30: =C31-C32 -> 2617776 | D30: =D31-D32 -> 6440080 | E30: =E31-E32 -> 16654373 | F30: =F31-F32 -> 26721318 | G30: =G31-G32 -> 34118230 | H30: =H31-H32 -> 48217666 | I30: =I31-I32 -> 48346848 | J30: =J31-J32 -> 98776711 | ... DW30: =DW31-DW32 -> 340435332
A31: 7.1 | B31: Gross Loans & advances | C31: =Trend!C15 -> 2617776 | D31: =Trend!D15 -> 6440080 | E31: =Trend!E15 -> 16654373 | F31: =Trend!F15 -> 26990740 | G31: =Trend!G15 -> 34462859 | H31: =Trend!H15 -> 48487088 | I31: =Trend!I15 -> 48831719 | J31: =Trend!J15 -> 99315555 | ... CL31: =Trend!CL15 -> 2.0049904e+08 | CM31: =Trend!#REF! -> #REF! | CN31: =Trend!CN15 -> 200576944 | CO31: =Trend!CO15 -> 1.9792202e+08 | CP31: =Trend!CP15 -> 207508084 | CQ31: =Trend!CQ15 -> 2.1203643e+08 | CR31: =Trend!CR15 -> 2.1480735e+08 | CS31: =Trend!CS15 -> 220509733 | CT31: =Trend!CT15 -> 220509733 | CU31: =Trend!CU15 -> 2.3114986e+08 | ... DW31: =Trend!DW15 -> 358511202
A32: 7.3 | B32: Allowance for loan losses | C32: =Trend!C16 -> 0 | D32: =Trend!D16 -> 0 | E32: =Trend!E16 -> 0 | F32: =Trend!F16 -> 269422 | G32: =Trend!G16 -> 344629 | H32: =Trend!H16 -> 269422 | I32: =Trend!I16 -> 484871 | J32: =Trend!J16 -> 538844 | ... CL32: =Trend!CL16 -> 10590309 | CM32: =Trend!CM15 -> 2.0078144e+08 | CN32: =Trend!CN16 -> 10590309 | CO32: =Trend!CO16 -> 10590309 | CP32: =Trend!CP16 -> 10576686 | CQ32: =Trend!CQ16 -> 10576686 | CR32: =Trend!CR16 -> 10575870 | CS32: =Trend!CS16 -> 10575870 | CT32: =Trend!CT16 -> 10575870 | CU32: =Trend!CU16 -> 10575870 | ... DW32: =Trend!DW16 -> 18075870
A33: 7.4 | B33: Non Performing Loans (A/L NPL30 | C33: 0 | D33: 0 | E33: 0 | F33: 0 | G33: 0 | H33: =+RCAP!D13+RCAP!D14+RCAP!D15+RCAP!D23 -> 3069984 | I33: =+RCAP!D13+RCAP!D14+RCAP!D15+RCAP!D23 -> 3069984 | J33: =+RCAP!E13+RCAP!E14+RCAP!E15+RCAP!E23 -> 1.75 | K33: =+RCAP!F13+RCAP!F14+RCAP!F15+RCAP!F23 -> 1470595.2 | L33: =+RCAP!G13+RCAP!G14+RCAP!G15+RCAP!G23 -> 0 | M33: =+RCAP!H13+RCAP!H14+RCAP!H15+RCAP!H23 -> 0 | N33: =+RCAP!I13+RCAP!I14+RCAP!I15+RCAP!I23 -> 1.75 | O33: =+RCAP!J13+RCAP!J14+RCAP!J15+RCAP!J23 -> 0 | P33: =+RCAP!K13+RCAP!K14+RCAP!K15+RCAP!K23 -> 992 | ... W33: =+RCAP!R13+RCAP!R14+RCAP!R15+RCAP!R23 -> 13543905 | DW33: =17997602+5748129+7800512+217017+96266+704499 -> 32564025
A34: 7.5666667 | B34: Non Performing Loans NPL30 | Y34: =SUM(RCAP!AN13:AN15) -> 2731146 | AB34: =SUM(RCAP!AR13:AR15)+RCAP!AR23 -> 4653070 | AC34: =SUM(RCAP!AS13:AS15)+RCAP!AS23 -> 1.75 | AD34: =SUM(RCAP!AT13:AT15)+RCAP!AT23 -> 2025639.2 | AE34: =SUM(RCAP!#REF!)+RCAP!#REF! -> #REF! | AF34: =SUM(RCAP!AU13:AU15)+RCAP!AU23 -> 104 | AG34: =SUM(RCAP!AV13:AV15)+RCAP!AV23 -> 4183683 | AH34: =SUM(RCAP!AW13:AW15)+RCAP!AW23 -> 1.75 | AI34: =SUM(RCAP!AX13:AX15)+RCAP!AX23 -> 1644141.7 | AJ34: =SUM(RCAP!AY13:AY15)+RCAP!AY23 -> 0 | AK34: =SUM(RCAP!AZ13:AZ15)+RCAP!AZ23 -> 0 | AL34: =SUM(RCAP!BA13:BA15)+RCAP!BA23 -> 0 | AM34: =SUM(RCAP!BB13:BB15)+RCAP!BB23 -> 0 | ... DW34: =SUM(RCAP!EL13:EL15)+RCAP!EL23 -> 0
A35: 7.7166667 | B35: Required loan loss provision | C35: =SUM(#REF!) -> #REF! | D35: =SUM(#REF!) -> #REF! | E35: =SUM(#REF!) -> #REF! | F35: =SUM(#REF!) -> #REF! | G35: =SUM(#REF!) -> #REF! | H35: =RCAP!F24 -> 1949569.6 | I35: =RCAP!F24 -> 1949569.6 | J35: =RCAP!G24 -> 0 | K35: =RCAP!H24 -> 0 | L35: =RCAP!I24 -> 0 | M35: =RCAP!J24 -> 0 | N35: =RCAP!K24 -> 5318 | O35: =RCAP!L24 -> 7.3237585e+08 | P35: =RCAP!M24 -> 0 | ... DW35: =RCAP!DT24 -> 0
A36: 7.8666667 | B36: Cash and Cash equipments | C36: =Trend!C5 -> 692551 | D36: =Trend!D5 -> 2050924 | E36: =Trend!E5 -> 1466652 | F36: =Trend!F5 -> 6631870 | G36: =Trend!G5 -> 8447670 | H36: =Trend!H5 -> 15934406 | I36: =Trend!I5 -> 16473429 | J36: =Trend!J5 -> 32498030 | ... DW36: =Trend!DW5 -> 40136992
A38: 8 | B38: Non-Earning Assets | C38: =Trend!C8+Trend!C21 -> 95583 | D38: =Trend!D8+Trend!D21 -> 110143 | E38: =Trend!E8+Trend!E21 -> 684976 | F38: =Trend!F8+Trend!F21 -> 2076731 | G38: =Trend!G8+Trend!G21 -> 5488962 | H38: =Trend!H8+Trend!H21 -> 6335905 | I38: =Trend!I8+Trend!I21 -> 4836638 | J38: =Trend!J8+Trend!J21 -> 12640808 | ... CO38: =Trend!CO8+Trend!CO21 -> 36530971 | CP38: =Trend!#REF!+Trend!CP21 -> #REF! | CQ38: =Trend!CQ8+Trend!CQ21 -> 36318983 | CR38: =Trend!CR8+Trend!CR21 -> 37077112 | CS38: =Trend!CS8+Trend!CS21 -> 38128988 | CT38: =Trend!CT8+Trend!CT21 -> 39003337 | CU38: =Trend!CU8+Trend!CU21 -> 35638820 | CV38: =Trend!CV8+Trend!CV21 -> 26420228 | CW38: =Trend!CW8+Trend!CW21 -> 25626234 | CX38: =Trend!CX8+Trend!CX21 -> 35689830 | ... DW38: =Trend!DW8+Trend!DW21 -> 33771026
A39: 8.1 | B39: Property and Equipment | C39: =Trend!C23 -> 28544 | D39: =Trend!D23 -> 67851 | E39: =Trend!E23 -> 609253 | F39: =Trend!F23 -> 691887 | G39: =Trend!G23 -> 4364687 | H39: =Trend!H23 -> 5375271 | I39: =Trend!I23 -> 4109038 | J39: =Trend!J23 -> 10750542 | ... DR39: =Trend!DR23 -> 12273365 | DS39: =Trend!DS22 -> 620249 | DT39: =Trend!DT22 -> 620249 | DU39: =Trend!DU22 -> 620249 | DV39: =Trend!DV22 -> 0 | DW39: =Trend!DW22 -> 0
A40: 8.2 | B40: Land and Building | G40: =2472280+562959 -> 3035239 | I40: =2602400+625510 -> 3227910 | J40: =2602400+625510 -> 3227910 | K40: =2602400+625510 -> 3227910 | L40: =2602400+625510 -> 3227910 | M40: =2602400+625510 -> 3227910 | N40: =2602400+625510 -> 3227910 | O40: =2602400+625510 -> 3227910 | P40: =2602400+625510 -> 3227910 | ... W40: =2602400+625510 -> 3227910
A42: 9 | B42: Turnover | C42: =C43+C44+C45 -> 456483 | D42: =D43+D44+D45 -> 824264 | E42: =E43+E44+E45 -> 1989959 | F42: =F43+F44+F45 -> 4601423 | G42: =G43+G44+G45 -> 6686491 | H42: =H43+H44+H45 -> 9046.74 | I42: =I43+I44+I45 -> 8938309 | J42: =J43+J44+J45 -> 861242.73 | ... DW42: =DW43+DW44+DW45 -> 66839759
A43: 9.1 | B43: Loan Interest | C43: =Trend!C60 -> 313291 | D43: =Trend!D60 -> 583891 | E43: =Trend!E60 -> 1305578 | F43: =Trend!F60 -> 3611027 | G43: =Trend!G60 -> 4688789 | H43: =Trend!H60 -> 6208.39 | I43: =Trend!I60 -> 5914011 | J43: =Trend!J60 -> 640880.24 | ... DW43: =Trend!DW60 -> 57063371
B44: Income from investments | C44: =Trend!C61 -> 143192 | D44: =Trend!D61 -> 226718 | E44: =Trend!E61 -> 646729 | F44: =Trend!F61 -> 943117 | G44: =Trend!G61 -> 34229 | H44: =Trend!H61 -> 317.46 | I44: =Trend!I61 -> 214399 | J44: =Trend!J61 -> 32645.61 | ... DW44: =Trend!DW61 -> 0
A45: 9.2 | B45: Fees & Commissions | C45: =Trend!C62 -> 0 | D45: =Trend!D62 -> 13655 | E45: =Trend!E62 -> 37652 | F45: =Trend!F62 -> 47279 | G45: =Trend!G62 -> 1963473 | H45: =Trend!H62 -> 2520.89 | I45: =Trend!I62 -> 2809899 | J45: =Trend!J62 -> 187716.88 | ... DW45: =Trend!DW62 -> 9776388
B46: Average yield on loans | C46: =C43/C31 -> 0.11967831 | D46: =D43/D31 -> 0.090665178 | E46: =E43/E31 -> 0.078392504 | F46: =F43/F31 -> 0.13378762 | G46: =G43/G31 -> 0.1360534 | H46: =H43/H31 -> 0.00012804213 | I46: =I43/I31 -> 0.12111003 | J46: =J43/J31 -> 0.0064529694 | ... DW46: =DW43/DW31 -> 0.15916761
A48: 10 | B48: Total Expenses (FinCosts + OpEx) | C48: =SUM(C49:C55) -> 186511 | D48: =SUM(D49:D55) -> 780206 | E48: =SUM(E49:E55) -> 1916416 | F48: =SUM(F49:F55) -> 4232069 | G48: =SUM(G49:G55) -> 6334216 | H48: =SUM(H49:H55) -> 3845.34 | I48: =SUM(I49:I55) -> 7786610 | J48: =SUM(J49:J55) -> 472321900 | ... DW48: =SUM(DW49:DW55) -> 54986002
A49: 10.1 | B49: Financial Exp. (Interest on deposits) | C49: =Trend!C68 -> 0 | D49: =Trend!D68 -> 0 | E49: =Trend!E68 -> 1138470 | F49: =Trend!F68 -> 1235355 | G49: =Trend!G68 -> 1496701 | H49: =Trend!H68 -> 0 | I49: =Trend!I68 -> 2653816 | J49: =Trend!J68 -> 0 | ... DW49: =Trend!DW68 -> 19727218
A50: 10.2 | B50: Financial Exp. (Dividends) | C50: =Trend!C70 -> 0 | D50: =Trend!D70 -> 404847 | E50: =Trend!E70 -> 0 | F50: =Trend!F70 -> 407532 | G50: =Trend!G70 -> 393000 | H50: =Trend!H70 -> 0 | I50: =Trend!I70 -> 0 | J50: =Trend!J70 -> 0 | ... DW50: =Trend!DW70 -> 0
A51: 10.3 | B51: Financial Exp. (Interest on bank loans) | C51: =Trend!C69 -> 0 | D51: =Trend!D69 -> 0 | E51: =Trend!E69 -> 0 | F51: =Trend!F69 -> 152793 | G51: =Trend!G69 -> 257234 | H51: =Trend!H69 -> 0 | I51: =Trend!I69 -> 304823 | J51: =Trend!J69 -> 0 | ... DW51: =Trend!DW69 -> 1197819
A52: 10.4 | B52: Other Financial Expenses | C52: =Trend!C71+Trend!C72+Trend!C73 -> 0 | D52: =Trend!D71+Trend!D72+Trend!D73 -> 0 | E52: =Trend!E71+Trend!E72+Trend!E73 -> 10171 | F52: =Trend!F71+Trend!F72+Trend!F73 -> 122606 | G52: =Trend!G71+Trend!G72+Trend!G73 -> 178894 | H52: =Trend!H71+Trend!H72+Trend!H73 -> 106.34 | I52: =Trend!I71+Trend!I72+Trend!I73 -> 235816 | J52: =Trend!J71+Trend!J72+Trend!J73 -> 3603600 | ... DW52: =Trend!DW71+Trend!DW72+Trend!DW73 -> 557302
A53: 10.5 | B53: Administrative Expenses | C53: =Trend!C83+Trend!C82+Trend!C81+Trend!C79 -> 143411 | D53: =Trend!D83+Trend!D82+Trend!D81+Trend!D79 -> 288000 | E53: =Trend!E83+Trend!E82+Trend!E81+Trend!E79 -> 599795 | F53: =Trend!F83+Trend!F82+Trend!F81+Trend!F79 -> 1653661 | G53: =Trend!G83+Trend!G82+Trend!G81+Trend!G79 -> 2898098 | H53: =Trend!H83+Trend!H82+Trend!H81+Trend!H79 -> 2943.5 | I53: =Trend!I83+Trend!I82+Trend!I81+Trend!I79 -> 2895130 | J53: =Trend!J83+Trend!J82+Trend!J81+Trend!J79 -> 381331000 | ... DW53: =Trend!DW83+Trend!DW82+Trend!DW81+Trend!DW79 -> 26182983
A54: 10.6 | B54: Governance Expenses | C54: =Trend!C80 -> 43100 | D54: =Trend!D80 -> 87359 | E54: =Trend!E80 -> 167980 | F54: =Trend!F80 -> 390700 | G54: =Trend!G80 -> 765660 | H54: =Trend!H80 -> 795.5 | I54: =Trend!I80 -> 1212154 | J54: =Trend!J80 -> 87387300 | ... DW54: =Trend!DW80 -> 3820680
B55: LLP | C55: =Trend!C75 -> 0 | D55: =Trend!D75 -> 0 | E55: =Trend!E75 -> 0 | F55: =Trend!F75 -> 269422 | G55: =Trend!G75 -> 344629 | H55: =Trend!H75 -> 0 | I55: =Trend!I75 -> 484871 | J55: =Trend!J75 -> 0 | ... DW55: =Trend!DW75 -> 3500000
B57: Net Surplus | C57: =Trend!C92 -> 0 | D57: =Trend!D92 -> 44058 | E57: =Trend!E92 -> 67895 | F57: =Trend!F92 -> 362262 | G57: =Trend!G92 -> 347141 | H57: =Trend!H92 -> 5201.4 | I57: =Trend!I92 -> 1147048 | J57: =Trend!J92 -> -4.7146066e+08 | ... AI57: =Trend!AI92 -> 2979536

Sheet Prudential Ratios
C1: VIKTAS SACCO SOCIETY LTD
C2: Financial Performance
C4: FINANCIAL SOUNDNESS INDICATORS | D4: Prude. Std | E4: Ref. # | F4: 2008 | G4: 2009 | H4: 2010 | I4: 2011 | J4: 2012 | K4: 41609 | L4: 2013 | M4: 41640 | N4: 41671 | O4: 41699 | P4: 41730 | Q4: 41760 | R4: 41791 | S4: 41821 | T4: 41852 | U4: 41883 | V4: 41913 | W4: 41944 | X4: 41974 | Y4: Jan-15 | Z4: Feb-15 | AA4: Mar-15 | AB4: Apr-15 | AC4: 42125 | AD4: 42156 | AE4: 42186 | AF4: 42217 | AG4: 42248 | AH4: 42278 | AI4: 42309 | AJ4: 42339 | AL4: 2015 Rev. | AN4: 42416 | AO4: 42445 | AP4: 42476 | AQ4: May-16 | AR4: Jun-16 | AS4: Jul-16 | AT4: Aug-16 | AU4: Sept-16 | AV4: Oct-16 | AW4: Nov-16 | AX4: Dec-16 | AY4: Aud-16 | AZ4: Jan -2017 | BA4: Feb-2017 | BB4: Mar-2017 | BC4: 42826 | BD4: 42856 | BE4: 42887 | BF4: 42917 | BG4: 42948 | BH4: 42979 | BI4: 43009 | BJ4: 43040 | BK4: 43070 | BL4: Aud -2017 | BM4: 43101 | BN4: 43132 | BO4: 43160 | BP4: 43191 | BQ4: 43221 | BR4: 43252 | BS4: 43282 | BT4: 43313 | BU4: 43344 | BV4: 43374 | BW4: 43405 | BX4: 43435 | BY4: Audited-2018 | BZ4: 43466 | CA4: 43497 | CB4: 43525 | CC4: 43556 | CD4: 43586 | CE4: 43617 | CF4: 43647 | CG4: 43678 | CH4: 43709 | CI4: 43739 | CJ4: 43770 | CK4: 43800 | CL4: Audited-2019 | CM4: 43862 | CN4: 43891 | CO4: 43922 | CP4: 43952 | CQ4: 43983 | CR4: 44013 | CS4: 44044 | CT4: 44075 | CU4: 44105 | CV4: 44136 | CW4: 44166 | CX4: Audited 2020 | CY4: 44197 | CZ4: 44228 | DA4: 44256 | DB4: 44287 | DC4: 44317 | DD4: 44348 | DE4: 44378 | DF4: 44378 | DG4: 44409 | DH4: 44440 | DI4: 44470 | DJ4: 44501 | DK4: 44531 | DL4: Audited-2021 | DM4: 44562 | DN4: 44593 | DO4: 44621 | DP4: 44652 | DQ4: 44682 | DR4: 44713 | DS4: 44743 | DT4: 44774 | DU4: 44805 | DV4: 44835 | DW4: 44866 | DX4: 44896 | DY4: Audited-2022
B5: 1 | C5: CAPITAL ADEQUACY REQUIREMENTS
B6: 1.1 | C6: Core capital | D6: ≥ Ksh.10M | E6: 9.a | F6: =Financials!C13/1000000 -> 0.439861 | G6: =Financials!D13/1000000 -> 0.736861 | H6: =Financials!E13/1000000 -> 8.453756 | I6: =Financials!F13/1000000 -> 11.449334 | J6: =Financials!G13/1000000 -> 15.452148 | K6: =Financials!H13/1000000 -> 25.274778 | L6: =Financials!I13/1000000 -> 19.725079 | M6: =Financials!J13/1000000 -> 51.119689 | ... X6: =Financials!U13/1000000 -> 28.81989 | Y6: =Financials!W13/1000000 -> 32.110396 | Z6: =Financials!X13/1000000 -> 33.697534 | AA6: =Financials!Y13/1000000 -> 30.530662 | AB6: =Financials!Z13/1000000 -> 33.605968 | AC6: =Financials!AA13/1000000 -> 34.320074 | AD6: =Financials!AB13/1000000 -> 35.793923 | AE6: =Financials!AC13/1000000 -> 33.507873 | AF6: =Financials!AD13/1000000 -> 35.443236 | ... DY6: =Financials!DW13/1000000 -> 97.517528
B7: 1.2 | C7: Core capital /Total Assets | D7: ≥ 10% | E7: 9.b | F7: =Financials!C13/Financials!C5 -> 0.12656377 | G7: =Financials!D13/Financials!D5 -> 0.084206459 | H7: =Financials!E13/Financials!E5 -> 0.44457183 | I7: =Financials!F13/Financials!F5 -> 0.32116467 | J7: =Financials!G13/Financials!G5 -> 0.32003712 | K7: =Financials!H13/Financials!H5 -> 0.335394 | L7: =Financials!I13/Financials!I5 -> 0.27632121 | M7: =Financials!J13/Financials!J5 -> 0.33268803 | ... X7: =Financials!U13/Financials!U5 -> 0.31243537 | Y7: =Financials!W13/Financials!W5 -> 0.34902504 | Z7: =Financials!X13/Financials!X5 -> 0.3646068 | AA7: =Financials!Y13/Financials!Y5 -> 0.32774907 | AB7: =Financials!Z13/Financials!Z5 -> 0.33591021 | AC7: =Financials!AA13/Financials!AA5 -> 0.33053058 | AD7: =Financials!AB13/Financials!AB5 -> 0.33370253 | AE7: =Financials!AC13/Financials!AC5 -> 0.30459415 | AF7: =Financials!AD13/Financials!AD5 -> 0.30830343 | ... DY7: =Financials!DW13/Financials!DW5 -> 0.23491377
B8: 1.3 | C8: Core capital /Total Deposits | D8: ≥ 8% | E8: 9.d | F8: =Financials!C13/Financials!C6 -> 0.19297668 | G8: =Financials!D13/Financials!D6 -> 0.12445286 | H8: =Financials!E13/Financials!E6 -> 1.0154601 | I8: =Financials!F13/Financials!F6 -> 0.66847291 | J8: =Financials!G13/Financials!G6 -> 0.52569304 | K8: =Financials!H13/Financials!H6 -> 0.54885721 | L8: =Financials!I13/Financials!I6 -> 0.45090247 | M8: =Financials!J13/Financials!J6 -> 0.54179922 | ... X8: =Financials!U13/Financials!U6 -> 0.46437175 | Y8: =Financials!W13/Financials!W6 -> 0.50539575 | Z8: =Financials!X13/Financials!X6 -> 0.54147933 | AA8: =Financials!Y13/Financials!Y6 -> 0.46053625 | AB8: =Financials!Z13/Financials!Z6 -> 0.48969269 | AC8: =Financials!AA13/Financials!AA6 -> 0.47953693 | AD8: =Financials!AB13/Financials!AB6 -> 0.48659464 | AE8: =Financials!AC13/Financials!AC6 -> 0.45565376 | AF8: =Financials!AD13/Financials!AD6 -> 0.46359257 | ... DY8: =Financials!DW13/Financials!DW6 -> 0.34187356
B9: 1.4 | C9: Share Capital/Total Assets | D9: ≤2% | E9: 9.c | F9: =Financials!C17/Financials!C5 -> 0.10300943 | G9: =Financials!D17/Financials!D5 -> 0.070623349 | H9: =Financials!E17/Financials!E5 -> 0.3928374 | I9: =Financials!F17/Financials!F5 -> 0.28579192 | J9: =Financials!G17/Financials!G5 -> 0.27132038 | K9: =Financials!H17/Financials!H5 -> 0.22421131 | L9: =Financials!I17/Financials!I5 -> 0.22383877 | M9: =Financials!J17/Financials!J5 -> 0.22080247 | ... X9: =Financials!U17/Financials!U5 -> 0.21376597 | Y9: =Financials!W17/Financials!W5 -> 0.21878532 | Z9: =Financials!X17/Financials!X5 -> 0.22751776 | AA9: =Financials!Y17/Financials!Y5 -> 0.22874746 | AB9: =Financials!Z17/Financials!Z5 -> 0.23725751 | AC9: =Financials!AA17/Financials!AA5 -> 0.23489324 | AD9: =Financials!AB17/Financials!AB5 -> 0.23392193 | AE9: =Financials!AC17/Financials!AC5 -> 0.23680356 | AF9: =Financials!AD17/Financials!AD5 -> 0.23355276 | ... DY9: =Financials!DW17/Financials!DW5 -> 0.12842858
B10: 1.5 | C10: Institutional Capital/Total Assets | D10: ≥ 8% | E10: 9.c | F10: =Financials!C14/Financials!C5 -> 0.023554343 | G10: =Financials!D14/Financials!D5 -> 0.01358311 | H10: =Financials!E14/Financials!E5 -> 0.051734424 | I10: =Financials!F14/Financials!F5 -> 0.03537275 | J10: =Financials!G14/Financials!G5 -> 0.048716734 | K10: =Financials!H14/Financials!H5 -> 0.11118269 | L10: =Financials!I14/Financials!I5 -> 0.052482439 | M10: =Financials!J14/Financials!J5 -> 0.11188556 | ... X10: =Financials!U14/Financials!U5 -> 0.098669406 | Y10: =Financials!W14/Financials!W5 -> 0.13023972 | Z10: =Financials!X14/Financials!X5 -> 0.13708904 | AA10: =Financials!Y14/Financials!Y5 -> 0.099001617 | AB10: =Financials!Z14/Financials!Z5 -> 0.098652699 | AC10: =Financials!AA14/Financials!AA5 -> 0.09563734 | AD10: =Financials!AB14/Financials!AB5 -> 0.099780599 | AE10: =Financials!AC14/Financials!AC5 -> 0.067790582 | AF10: =Financials!AD14/Financials!AD5 -> 0.074750672 | ... CR10: =Financials!CP14/Financials!CP5 -> 0.10404786 | CS10: =Financials!CR14/Financials!CR5 -> 0.12220217 | CT10: =Financials!CS14/Financials!CS5 -> 0.12807576 | CU10: =Financials!CT14/Financials!CT5 -> 0.12186274 | CV10: =Financials!CU14/Financials!CU5 -> 0.13470175 | CW10: =Financials!CV14/Financials!CV5 -> 0.1338778 | CX10: =Financials!CW14/Financials!CW5 -> 0.08213749 | CY10: =Financials!CX14/Financials!CX5 -> 0.085590391 | CZ10: =Financials!CY14/Financials!CY5 -> 0.091723378 | ... DX10: =Financials!DW14/Financials!DW5 -> 0.1064852 | DY10: =Financials!DW14/Financials!DW5 -> 0.1064852
B12: 2 | C12: ASSET MIX AND QUALITY
B13: 2.1 | C13: Non Earning Assets
B14: 2.1.1 | C14: Non earning Assets/Total assets | D14: ≤ 10% | E14: 48.1 | F14: =Financials!C38/Financials!C5 -> 0.027502654 | G14: =Financials!D38/Financials!D5 -> 0.012586841 | H14: =Financials!E38/Financials!E5 -> 0.03602198 | I14: =Financials!F38/Financials!F5 -> 0.058254273 | J14: =Financials!G38/Financials!G5 -> 0.11368462 | K14: =Financials!H38/Financials!H5 -> 0.08407688 | L14: =Financials!I38/Financials!I5 -> 0.067754641 | M14: =Financials!J38/Financials!J5 -> 0.082266651 | ... X14: =Financials!U38/Financials!U5 -> 0.072853594 | Y14: =Financials!W38/Financials!W5 -> 0.075289327 | Z14: =Financials!X38/Financials!X5 -> 0.077079007 | AA14: =Financials!Y38/Financials!Y5 -> 0.079152105 | AB14: =Financials!Z38/Financials!Z5 -> 0.074726037 | AC14: =Financials!AA38/Financials!AA5 -> 0.075383632 | AD14: =Financials!AB38/Financials!AB5 -> 0.0744373 | AE14: =Financials!AC38/Financials!AC5 -> 0.080664973 | AF14: =Financials!AD38/Financials!AD5 -> 0.0797422 | ... DY14: =Financials!DW38/Financials!DW5 -> 0.08135234
B15: 2.1.2 | C15: Property and Equipment/Total Assets | D15: ≤ 5% | E15: 48.1 | F15: =Financials!C39/Financials!C5 -> 0.0082131317 | G15: =Financials!D39/Financials!D5 -> 0.0077538267 | H15: =Financials!E39/Financials!E5 -> 0.032039808 | I15: =Financials!F39/Financials!F5 -> 0.019408086 | J15: =Financials!G39/Financials!G5 -> 0.090399202 | K15: =Financials!H39/Financials!H5 -> 0.071329355 | L15: =Financials!I39/Financials!I5 -> 0.057561966 | M15: =Financials!J39/Financials!J5 -> 0.069964757 | ... X15: =Financials!U39/Financials!U5 -> 0.061489034 | Y15: =Financials!W39/Financials!W5 -> 0.062063006 | Z15: =Financials!X39/Financials!X5 -> 0.06178658 | AA15: =Financials!Y39/Financials!Y5 -> 0.061304687 | AB15: =Financials!Z39/Financials!Z5 -> 0.057635033 | AC15: =Financials!AA39/Financials!AA5 -> 0.055758308 | AD15: =Financials!AB39/Financials!AB5 -> 0.054023101 | AE15: =Financials!AC39/Financials!AC5 -> 0.053613227 | AF15: =Financials!AD39/Financials!AD5 -> 0.051304678 | ... DY15: =Financials!DW39/Financials!DW5 -> 0
B16: 2.1.3 | C16: Non Performing loans/Gross Loans | D16: ≤ 6% | E16: 41 | F16: =Financials!C33/Financials!C31 -> 0 | G16: =Financials!D33/Financials!D31 -> 0 | H16: =Financials!E33/Financials!E31 -> 0 | I16: =Financials!F33/Financials!F31 -> 0 | J16: =Financials!G33/Financials!G31 -> 0 | K16: =Financials!H33/Financials!H31 -> 0.063315496 | L16: =Financials!I33/Financials!I31 -> 0.062868645 | M16: =Financials!J33/Financials!J31 -> 1.7620603e-08 | ... X16: =Financials!U33/Financials!U31 -> 0.25294023 | Y16: =Financials!W33/Financials!W31 -> 0.19016025 | Z16: =Financials!X33/Financials!X31 -> 0 | AA16: =Financials!Y33/Financials!Y31 -> 0 | AB16: =Financials!Z33/Financials!Z31 -> 0 | AC16: =Financials!AA33/Financials!AA31 -> 0 | AD16: =Financials!AB33/Financials!AB31 -> 0 | AE16: =Financials!AC33/Financials!AC31 -> 0 | AF16: =Financials!AD33/Financials!AD31 -> 0 | ... BN16: =Financials!BL33/Financials!BL31 -> 0 | BO16: =SUM('[5]Portfolio Analysis'!$D$12+'[5]Portfolio Analysis'!$D$13+'[5]Portfolio Analysis'!$D$14)/'[5]Portfolio Analysis'!$D$23 -> 0.047465454 | BP16: =Financials!BN33/Financials!BN31 -> 0 | BQ16: =Financials!BO33/Financials!BO31 -> 0 | BR16: =Financials!BP33/Financials!BP31 -> 0 | BS16: =Financials!BQ33/Financials!BQ31 -> 0 | BT16: =Financials!BR33/Financials!BR31 -> 0 | BU16: =Financials!BS33/Financials!BS31 -> 0 | BV16: =Financials!BT33/Financials!BT31 -> 0 | BW16: =Financials!BU33/Financials!BU31 -> 0 | ... DY16: =Financials!DW33/Financials!DW31 -> 0.090831262
B18: 2.2 | C18: Earning Assets
B19: 2.2.1 | C19: Equities & Investments/Deposits | D19: ≤ 5% | E19: 48.4 | F19: =Financials!C25/Financials!C6 -> 0.030491176 | G19: =Financials!D25/Financials!D6 -> 0.025249949 | H19: =Financials!E25/Financials!E6 -> 0.025165014 | I19: =Financials!F25/Financials!F6 -> 0.012815576 | J19: =Financials!G25/Financials!G6 -> 0.0077397114 | K19: =Financials!H25/Financials!H6 -> 0.073192284 | L19: =Financials!I25/Financials!I6 -> 0.0052047538 | M19: =Financials!J25/Financials!J6 -> 0.071445266 | ... X19: =Financials!U25/Financials!U6 -> 0.098189807 | Y19: =Financials!W25/Financials!W6 -> 0.095913305 | Z19: =Financials!X25/Financials!X6 -> 0.097921192 | AA19: =Financials!Y25/Financials!Y6 -> 0.091922225 | AB19: =Financials!Z25/Financials!Z6 -> 0.090608944 | AC19: =Financials!AA25/Financials!AA6 -> 0.11482856 | AD19: =Financials!AB25/Financials!AB6 -> 0.11172082 | AE19: =Financials!AC25/Financials!AC6 -> 0.1389511 | AF19: =Financials!AD25/Financials!AD6 -> 0.25137121 | ... DY19: =Financials!DW25/Financials!DW6 -> 0.062969668
B20: 2.2.2 | C20: Equities & Investments/Core Capital | D20: ≤ 40% | E20: 48.4 | F20: =Financials!C25/Financials!C13 -> 0.15800446 | G20: =Financials!D25/Financials!D13 -> 0.20288765 | H20: =Financials!E25/Financials!E13 -> 0.024781884 | I20: =Financials!F25/Financials!F13 -> 0.019171421 | J20: =Financials!G25/Financials!G13 -> 0.014722872 | K20: =Financials!H25/Financials!H13 -> 0.13335396 | L20: =Financials!I25/Financials!I13 -> 0.01154297 | M20: =Financials!J25/Financials!J13 -> 0.13186668 | ... X20: =Financials!U25/Financials!U13 -> 0.21144655 | Y20: =Financials!W25/Financials!W13 -> 0.18977861 | Z20: =Financials!X25/Financials!X13 -> 0.18084013 | AA20: =Financials!Y25/Financials!Y13 -> 0.19959824 | AB20: =Financials!Z25/Financials!Z13 -> 0.18503226 | AC20: =Financials!AA25/Financials!AA13 -> 0.23945718 | AD20: =Financials!AB25/Financials!AB13 -> 0.2295973 | AE20: =Financials!AC25/Financials!AC13 -> 0.30494887 | AF20: =Financials!AD25/Financials!AD13 -> 0.54222442 | ... DY20: =Financials!DW25/Financials!DW13 -> 0.18418993
B21: 2.2.3 | C21: Net Loans & advances /Total assets | D21: NPR | F21: =Financials!C30/Financials!C5 -> 0.75322796 | G21: =Financials!D30/Financials!D5 -> 0.73595472 | H21: =Financials!E30/Financials!E5 -> 0.87583141 | I21: =Financials!F30/Financials!F5 -> 0.7495583 | J21: =Financials!G30/Financials!G5 -> 0.70663962 | K21: =Financials!H30/Financials!H5 -> 0.63984402 | L21: =Financials!I30/Financials!I5 -> 0.67727279 | M21: =Financials!J30/Financials!J5 -> 0.64284094 | ... X21: =Financials!U30/Financials!U5 -> 0.77549727 | Y21: =Financials!W30/Financials!W5 -> 0.74808087 | Z21: =Financials!X30/Financials!X5 -> 0.75391414 | AA21: =Financials!Y30/Financials!Y5 -> 0.72958466 | AB21: =Financials!Z30/Financials!Z5 -> 0.69101834 | AC21: =Financials!AA30/Financials!AA5 -> 0.66165164 | AD21: =Financials!AB30/Financials!AB5 -> 0.67047779 | AE21: =Financials!AC30/Financials!AC5 -> 0.66413604 | AF21: =Financials!AD30/Financials!AD5 -> 0.65181417 | ... DY21: =Financials!DW30/Financials!DW5 -> 0.82008794
B23: 3 | C23: FUNDING MIX
B24: 3.1 | C24: Total Deposits/Total Assets | D24: NPR | F24: =Financials!C6/Financials!C5 -> 0.6558501 | G24: =Financials!D6/Financials!D5 -> 0.67661328 | H24: =Financials!E6/Financials!E5 -> 0.43780335 | I24: =Financials!F6/Financials!F5 -> 0.48044531 | J24: =Financials!G6/Financials!G5 -> 0.60879087 | K24: =Financials!H6/Financials!H5 -> 0.61107697 | L24: =Financials!I6/Financials!I5 -> 0.61281812 | M24: =Financials!J6/Financials!J5 -> 0.61404301 | ... X24: =Financials!U6/Financials!U5 -> 0.67281304 | Y24: =Financials!W6/Financials!W5 -> 0.69059749 | Z24: =Financials!X6/Financials!X5 -> 0.67335313 | AA24: =Financials!Y6/Financials!Y5 -> 0.71166834 | AB24: =Financials!Z6/Financials!Z5 -> 0.68596125 | AC24: =Financials!AA6/Financials!AA5 -> 0.68927033 | AD24: =Financials!AB6/Financials!AB5 -> 0.68579164 | AE24: =Financials!AC6/Financials!AC5 -> 0.66847719 | AF24: =Financials!AD6/Financials!AD5 -> 0.665031 | ... DY24: =Financials!DW6/Financials!DW5 -> 0.68713641
B25: 3.1.1 | C25: BOSA Deposits/Total Assets | D25: NPR | F25: =Financials!C7/Financials!C5 -> 0.62767443 | G25: =Financials!D7/Financials!D5 -> 0.61583469 | H25: =Financials!E7/Financials!E5 -> 0.36817331 | I25: =Financials!F7/Financials!F5 -> 0.40768095 | J25: =Financials!G7/Financials!G5 -> 0.44284169 | K25: =Financials!H7/Financials!H5 -> 0.5818322 | L25: =Financials!I7/Financials!I5 -> 0.45216277 | M25: =Financials!J7/Financials!J5 -> 0.58554248 | ... X25: =Financials!U7/Financials!U5 -> 0.64029764 | Y25: =Financials!W7/Financials!W5 -> 0.65565398 | Z25: =Financials!X7/Financials!X5 -> 0.64240492 | AA25: =Financials!Y7/Financials!Y5 -> 0.67560541 | AB25: =Financials!Z7/Financials!Z5 -> 0.65366555 | AC25: =Financials!AA7/Financials!AA5 -> 0.64882269 | AD25: =Financials!AB7/Financials!AB5 -> 0.65908146 | AE25: =Financials!AC7/Financials!AC5 -> 0.63605823 | AF25: =Financials!AD7/Financials!AD5 -> 0.62969844 | ... DY25: =Financials!DW7/Financials!DW5 -> 0.54467995
B26: 3.1.2 | C26: FOSA Deposits/Total Assets | D26: NPR | F26: =Financials!C8/Financials!C5 -> 0.028175668 | G26: =Financials!D8/Financials!D5 -> 0.060778592 | H26: =Financials!E8/Financials!E5 -> 0.069630035 | I26: =Financials!F8/Financials!F5 -> 0.072764356 | J26: =Financials!G8/Financials!G5 -> 0.16594917 | K26: =Financials!H8/Financials!H5 -> 0.015790196 | L26: =Financials!I8/Financials!I5 -> 0.16065535 | M26: =Financials!J8/Financials!J5 -> 0.015288423 | ... X26: =Financials!U8/Financials!U5 -> 0.021498698 | Y26: =Financials!W8/Financials!W5 -> 0.023897767 | Z26: =Financials!X8/Financials!X5 -> 0.019952814 | AA26: =Financials!Y8/Financials!Y5 -> 0.025153831 | AB26: =Financials!Z8/Financials!Z5 -> 0.022138114 | AC26: =Financials!AA8/Financials!AA5 -> 0.030660695 | AD26: =Financials!AB8/Financials!AB5 -> 0.017236159 | AE26: =Financials!AC8/Financials!AC5 -> 0.023181372 | AF26: =Financials!AD8/Financials!AD5 -> 0.026493028 | ... DY26: =Financials!DW8/Financials!DW5 -> 0.10189125
B27: 3.2 | C27: External Borrowing/Total assets | D27: ≤ 25% | E27: 35.1 | F27: =Financials!C9/Financials!C5 -> 0 | G27: =Financials!D9/Financials!D5 -> 0.11427726 | H27: =Financials!E9/Financials!E5 -> 0 | I27: =Financials!F9/Financials!F5 -> 0.080526361 | J27: =Financials!G9/Financials!G5 -> 0.011602788 | K27: =Financials!H9/Financials!H5 -> 0.05352902 | L27: =Financials!I9/Financials!I5 -> 0.056508896 | M27: =Financials!J9/Financials!J5 -> 0.052504959 | ... X27: =Financials!U9/Financials!U5 -> 0.024523376 | Y27: =Financials!W9/Financials!W5 -> 0.024588005 | Z27: =Financials!X9/Financials!X5 -> 0.024475919 | AA27: =Financials!Y9/Financials!Y5 -> 0.024283854 | AB27: =Financials!Z9/Financials!Z5 -> 0.018959303 | AC27: =Financials!AA9/Financials!AA5 -> 0.018267496 | AD27: =Financials!AB9/Financials!AB5 -> 0.017683401 | AE27: =Financials!AC9/Financials!AC5 -> 0.017242105 | AF27: =Financials!AD9/Financials!AD5 -> 0.016499112 | ... DY27: =Financials!DW9/Financials!DW5 -> 0.014081055
B29: 4 | C29: GROWTH RATIOS
B30: 4.1 | C30: Total Assets | D30: NPR | G30: =Financials!D5/Financials!C5-1 -> 1.5178747 | H30: =Financials!E5/Financials!D5-1 -> 1.1730394 | I30: =Financials!F5/Financials!E5-1 -> 0.87475571 | J30: =Financials!G5/Financials!F5-1 -> 0.35436603 | K30: =Financials!H5/Financials!G5-1 -> 0.56078671 | L30: =Financials!I5/Financials!G5-1 -> 0.47848196 | M30: =Financials!J5/Financials!I5-1 -> 1.1525165 | N30: =Financials!K5/Financials!J5-1 -> -0.48118554 | O30: =Financials!L5/Financials!K5-1 -> 0.0051238984 | P30: =Financials!M5/Financials!L5-1 -> 0.021799581 | Q30: =Financials!N5/Financials!M5-1 -> 0.020802901 | R30: =Financials!O5/Financials!N5-1 -> 0.030287326 | S30: =Financials!P5/Financials!O5-1 -> 0.03662726 | T30: =Financials!Q5/Financials!P5-1 -> 0.018464468 | ... X30: =Financials!U5/Financials!T5-1 -> -0.036965608 | Y30: =Financials!W5/Financials!V5-1 -> 0.0077763564 | Z30: =Financials!X5/Financials!W5-1 -> 0.0045794292 | AA30: =Financials!Y5/Financials!X5-1 -> 0.0079091676 | AB30: =Financials!Z5/Financials!Y5-1 -> 0.073985589 | AC30: =Financials!AA5/Financials!Z5-1 -> 0.037870973 | AD30: =Financials!AB5/Financials!AA5-1 -> 0.033030691 | AE30: =Financials!AC5/Financials!AB5-1 -> 0.025594092 | AF30: =Financials!AD5/Financials!AC5-1 -> 0.045032286 | ... DY30: =Financials!DW5/Financials!DV5-1 -> #DIV/0!
B31: 4.2 | C31: Total Deposits | D31: NPR | G31: =Financials!D6/Financials!C6-1 -> 1.5975867 | H31: =Financials!E6/Financials!D6-1 -> 0.40606749 | I31: =Financials!F6/Financials!E6-1 -> 1.0573565 | J31: =Financials!G6/Financials!F6-1 -> 0.71616968 | K31: =Financials!H6/Financials!G6-1 -> 0.56664771 | L31: =Financials!I6/Financials!G6-1 -> 0.48826236 | M31: =Financials!J6/Financials!I6-1 -> 1.1568189 | N31: =Financials!K6/Financials!J6-1 -> -0.48050988 | O31: =Financials!L6/Financials!K6-1 -> 0.04901348 | P31: =Financials!M6/Financials!L6-1 -> 0.024685568 | Q31: =Financials!N6/Financials!M6-1 -> 0.011657366 | R31: =Financials!O6/Financials!N6-1 -> 0.034024667 | S31: =Financials!P6/Financials!O6-1 -> 0.043649541 | T31: =Financials!Q6/Financials!P6-1 -> 0.028207451 | ... X31: =Financials!U6/Financials!T6-1 -> 0.0065942446 | Y31: =Financials!W6/Financials!V6-1 -> 0.022647949 | Z31: =Financials!X6/Financials!W6-1 -> -0.020505132 | AA31: =Financials!Y6/Financials!X6-1 -> 0.065261331 | AB31: =Financials!Z6/Financials!Y6-1 -> 0.035190765 | AC31: =Financials!AA6/Financials!Z6-1 -> 0.042877671 | AD31: =Financials!AB6/Financials!AA6-1 -> 0.027817065 | AE31: =Financials!AC6/Financials!AB6-1 -> -0.00029948119 | AF31: =Financials!AD6/Financials!AC6-1 -> 0.039644844 | ... AS31: =Financials!AQ6/Financials!AP6-1 -> -0.0011804829 | AT31: =Financials!AR6/Financials!V6-1 -> 0.41539623 | AU31: =Financials!AS6/Financials!W6-1 -> 0.38425494 | AV31: =Financials!AT6/Financials!X6-1 -> -1 | AW31: =Financials!AU6/Financials!Y6-1 -> 0.32686544 | AX31: =Financials!AV6/Financials!Z6-1 -> 0.5703736 | AY31: =Financials!AW6/Financials!AA6-1 -> 0.56772292 | AZ31: =Financials!AX6/Financials!AB6-1 -> -1 | BA31: =Financials!AY6/Financials!AC6-1 -> -1 | ... DY31: =Financials!DW6/Financials!DA6-1 -> 0.17708943
B32: 4.2.1 | C32: FOSA Deposits | D32: NPR | G32: =Financials!D8/Financials!C8-1 -> 4.4313842 | H32: =Financials!E8/Financials!D8-1 -> 1.4895084 | I32: =Financials!F8/Financials!E8-1 -> 0.9591458 | J32: =Financials!G8/Financials!F8-1 -> 2.088819 | K32: =Financials!H8/Financials!G8-1 -> -0.8514899 | L32: =Financials!I8/Financials!G8-1 -> 0.43131799 | M32: =Financials!J8/Financials!I8-1 -> -0.79516037 | N32: =Financials!K8/Financials!J8-1 -> -0.41356835 | O32: =Financials!L8/Financials!K8-1 -> -0.072076202 | P32: =Financials!M8/Financials!L8-1 -> 0.038880375 | Q32: =Financials!N8/Financials!M8-1 -> 0.0010858161 | R32: =Financials!O8/Financials!N8-1 -> 0.14227154 | S32: =Financials!P8/Financials!O8-1 -> 0.3254657 | T32: =Financials!Q8/Financials!P8-1 -> 0.14367466 | ... X32: =Financials!U8/Financials!T8-1 -> -0.014411148 | Y32: =Financials!W8/Financials!V8-1 -> -0.87539629 | Z32: =Financials!X8/Financials!W8-1 -> -0.16125275 | AA32: =Financials!Y8/Financials!X8-1 -> 0.27063662 | AB32: =Financials!Z8/Financials!Y8-1 -> -0.054775561 | AC32: =Financials!AA8/Financials!Z8-1 -> 0.43742348 | AD32: =Financials!AB8/Financials!AA8-1 -> -0.4192734 | AE32: =Financials!AC8/Financials!AB8-1 -> 0.379349 | AF32: =Financials!AD8/Financials!AC8-1 -> 0.19432404 | ... AS32: =Financials!AQ8/Financials!AP8-1 -> 0 | AT32: =Financials!AR8/Financials!V8-1 -> -0.72159547 | AU32: =Financials!AS8/Financials!W8-1 -> 1.2343197 | AV32: =Financials!AT8/Financials!X8-1 -> -1 | AW32: =Financials!AU8/Financials!Y8-1 -> 1.0964902 | AX32: =Financials!AV8/Financials!Z8-1 -> 12.180733 | AY32: =Financials!AW8/Financials!AA8-1 -> 8.5364886 | AZ32: =Financials!AX8/Financials!AB8-1 -> -1 | BA32: =Financials!AY8/Financials!AC8-1 -> -1 | ... DY32: =Financials!DW8/Financials!DA8-1 -> -0.054960965
B33: 4.2.2 | C33: BOSA Deposits | D33: NPR | G33: =Financials!D7/Financials!C7-1 -> 1.4703804 | H33: =Financials!E7/Financials!D7-1 -> 0.29913942 | I33: =Financials!F7/Financials!E7-1 -> 1.0759304 | J33: =Financials!G7/Financials!F7-1 -> 0.47117433 | K33: =Financials!H7/Financials!G7-1 -> 1.050656 | L33: =Financials!I7/Financials!G7-1 -> 0.50960153 | M33: =Financials!J7/Financials!I7-1 -> 1.7874693 | N33: =Financials!K7/Financials!J7-1 -> -0.48183069 | O33: =Financials!L7/Financials!K7-1 -> 0.053659981 | P33: =Financials!M7/Financials!L7-1 -> 0.024826848 | Q33: =Financials!N7/Financials!M7-1 -> 0.012171561 | R33: =Financials!O7/Financials!N7-1 -> 0.031878942 | S33: =Financials!P7/Financials!O7-1 -> 0.036353612 | T33: =Financials!Q7/Financials!P7-1 -> 0.024468157 | ... X33: =Financials!U7/Financials!T7-1 -> 0.0074294536 | Y33: =Financials!W7/Financials!V7-1 -> 0.35602119 | Z33: =Financials!X7/Financials!W7-1 -> -0.015720506 | AA33: =Financials!Y7/Financials!X7-1 -> 0.059999476 | AB33: =Financials!Z7/Financials!Y7-1 -> 0.03910858 | AC33: =Financials!AA7/Financials!Z7-1 -> 0.030181627 | AD33: =Financials!AB7/Financials!AA7-1 -> 0.04936432 | AE33: =Financials!AC7/Financials!AB7-1 -> -0.010232273 | AF33: =Financials!AD7/Financials!AC7-1 -> 0.034583274 | ... AS33: =Financials!AQ7/Financials!AP7-1 -> -0.0012657244 | AT33: =Financials!AR7/Financials!V7-1 -> 0.84355031 | AU33: =Financials!AS7/Financials!W7-1 -> 0.35974465 | AV33: =Financials!AT7/Financials!X7-1 -> -1 | AW33: =Financials!AU7/Financials!Y7-1 -> 0.30348907 | AX33: =Financials!AV7/Financials!Z7-1 -> 0.18382698 | AY33: =Financials!AW7/Financials!AA7-1 -> 0.21479959 | AZ33: =Financials!AX7/Financials!AB7-1 -> -1 | BA33: =Financials!AY7/Financials!AC7-1 -> -1 | ... DY33: =Financials!DW7/Financials!DA7-1 -> 0.23791645
B34: 4.3 | C34: Net Loans & advances | D34: NPR | G34: =Financials!D30/Financials!C30-1 -> 1.4601341 | H34: =Financials!E30/Financials!D30-1 -> 1.5860506 | I34: =Financials!F30/Financials!E30-1 -> 0.60446256 | J34: =Financials!G30/Financials!F30-1 -> 0.27681688 | K34: =Financials!H30/Financials!G30-1 -> 0.41325226 | L34: =Financials!I30/Financials!G30-1 -> 0.41703857 | M34: =Financials!J30/Financials!I30-1 -> 1.0430848 | N34: =Financials!K30/Financials!J30-1 -> -0.47783918 | O34: =Financials!L30/Financials!K30-1 -> 0.024076342 | P34: =Financials!M30/Financials!L30-1 -> 0.055361031 | Q34: =Financials!N30/Financials!M30-1 -> 0.0055949974 | R34: =Financials!O30/Financials!N30-1 -> 0.025507917 | S34: =Financials!P30/Financials!O30-1 -> 0.030694186 | T34: =Financials!Q30/Financials!P30-1 -> 0.040392195 | ... X34: =Financials!U30/Financials!T30-1 -> 0.014681136 | Y34: =Financials!W30/Financials!V30-1 -> -0.018792237 | Z34: =Financials!X30/Financials!W30-1 -> 0.012412785 | AA34: =Financials!Y30/Financials!X30-1 -> -0.024616962 | AB34: =Financials!Z30/Financials!Y30-1 -> 0.017214016 | AC34: =Financials!AA30/Financials!Z30-1 -> -0.0062361651 | AD34: =Financials!AB30/Financials!AA30-1 -> 0.046810874 | AE34: =Financials!AC30/Financials!AB30-1 -> 0.015893455 | AF34: =Financials!AD30/Financials!AC30-1 -> 0.025643566 | ... AS34: =Financials!AQ30/Financials!AP30-1 -> 0.11225092 | AT34: =Financials!AR30/Financials!V30-1 -> 0.40626196 | AU34: =Financials!AS30/Financials!W30-1 -> 0.50418334 | AV34: =Financials!AT30/Financials!X30-1 -> -1 | AW34: =Financials!AU30/Financials!Y30-1 -> 0.56335785 | AX34: =Financials!AV30/Financials!Z30-1 -> 0.57202976 | AY34: =Financials!AW30/Financials!AA30-1 -> 0.51831406 | AZ34: =Financials!AX30/Financials!AB30-1 -> -1 | BA34: =Financials!AY30/Financials!AC30-1 -> -1 | ... DY34: =Financials!DW30/Financials!DA30-1 -> 0.4059845
B35: 4.4 | C35: Core capital | D35: NPR | G35: =Financials!D13/Financials!C13-1 -> 0.67521331 | H35: =Financials!E13/Financials!D13-1 -> 10.47266 | I35: =Financials!F13/Financials!E13-1 -> 0.35434877 | J35: =Financials!G13/Financials!F13-1 -> 0.34961108 | K35: =Financials!H13/Financials!G13-1 -> 0.63568058 | L35: =Financials!I13/Financials!G13-1 -> 0.27652667 | M35: =Financials!J13/Financials!I13-1 -> 1.5916088 | N35: =Financials!K13/Financials!J13-1 -> -0.47994541 | O35: =Financials!L13/Financials!K13-1 -> -0.086872871 | P35: =Financials!M13/Financials!L13-1 -> 0.020846192 | Q35: =Financials!N13/Financials!M13-1 -> 0.17042325 | R35: =Financials!O13/Financials!N13-1 -> 0.021724954 | S35: =Financials!P13/Financials!O13-1 -> 0.03455823 | T35: =Financials!Q13/Financials!P13-1 -> 0.0016168494 | ... X35: =Financials!U13/Financials!T13-1 -> -0.13691411 | Y35: =Financials!W13/Financials!V13-1 -> 0.42454732 | Z35: =Financials!X13/Financials!W13-1 -> 0.049427538 | AA35: =Financials!Y13/Financials!X13-1 -> -0.093979331 | AB35: =Financials!Z13/Financials!Y13-1 -> 0.10072842 | AC35: =Financials!AA13/Financials!Z13-1 -> 0.021249382 | AD35: =Financials!AB13/Financials!AA13-1 -> 0.04294423 | AE35: =Financials!AC13/Financials!AB13-1 -> -0.063866988 | AF35: =Financials!AD13/Financials!AC13-1 -> 0.057758463 | ... AS35: =Financials!AQ13/Financials!AP13-1 -> 0.07787681 | AT35: =Financials!AR13/Financials!V13-1 -> 1.912467 | AU35: =Financials!AS13/Financials!W13-1 -> 1.1696617 | AV35: =Financials!AT13/Financials!X13-1 -> -1 | AW35: =Financials!AU13/Financials!Y13-1 -> 1.4998558 | AX35: =Financials!AV13/Financials!Z13-1 -> -1.5517297 | AY35: =Financials!AW13/Financials!AA13-1 -> -0.093215185 | AZ35: =Financials!AX13/Financials!AB13-1 -> -1 | BA35: =Financials!AY13/Financials!AC13-1 -> -1 | ... DY35: =Financials!DW13/Financials!DA13-1 -> 0.3055401
B36: 4.5 | C36: Total Gross Income | D36: NPR | G36: =Financials!D42/Financials!C42-1 -> 0.80568389 | H36: =Financials!E42/Financials!D42-1 -> 1.4142253 | I36: =Financials!F42/Financials!E42-1 -> 1.3123205 | J36: =Financials!G42/Financials!F42-1 -> 0.45313548 | K36: =Financials!H42/Financials!G42-1 -> -0.99864701 | L36: =Financials!I42/Financials!G42-1 -> 0.33677126 | M36: =Financials!J42/Financials!I42-1 -> -0.9036459 | N36: =Financials!K42/Financials!J42-1 -> -0.99797835 | O36: =Financials!L42/Financials!K42-1 -> 0.52560119 | P36: =Financials!M42/Financials!L42-1 -> 0.34711833 | Q36: =Financials!N42/Financials!M42-1 -> 1258.4354 | R36: =Financials!O42/Financials!N42-1 -> 0.21221072 | S36: =Financials!P42/Financials!O42-1 -> 0.18055336 | T36: =Financials!Q42/Financials!P42-1 -> 0.14944399 | ... X36: =Financials!U42/Financials!T42-1 -> 0.11919538 | Y36: =Financials!W42/Financials!V42-1 -> -0.91546695 | Z36: =Financials!X42/Financials!W42-1 -> 1.0223972 | AA36: =Financials!Y42/Financials!X42-1 -> 0.55386792 | AB36: =Financials!Z42/Financials!Y42-1 -> 0.3760406 | AC36: =Financials!AA42/Financials!Z42-1 -> 0.24626327 | AD36: =Financials!AB42/Financials!AA42-1 -> 0.2266776 | AE36: =Financials!AC42/Financials!AB42-1 -> 0.23562285 | AF36: =Financials!AD42/Financials!AC42-1 -> 0.180616 | ... AS36: =Financials!AQ42/Financials!AP42-1 -> #DIV/0! | AT36: =Financials!AR42/Financials!V42-1 -> 0.11694783 | AU36: =Financials!AS42/Financials!W42-1 -> -1 | AV36: =Financials!AT42/Financials!X42-1 -> -1 | AW36: =Financials!AU42/Financials!Y42-1 -> 4.9293902 | AX36: =Financials!AV42/Financials!Z42-1 -> 3.7463123 | AY36: =Financials!AW42/Financials!AA42-1 -> 2.9027273 | AZ36: =Financials!AX42/Financials!AB42-1 -> -1 | BA36: =Financials!AY42/Financials!AC42-1 -> -1 | ... DY36: =Financials!DW42/Financials!DA42-1 -> 2.8873271
B37: 4.6 | C37: Membership | D37: NPR | G37: =Financials!D4/Financials!C4-1 -> 0.72625698 | H37: =Financials!E4/Financials!D4-1 -> 1.2556634 | I37: =Financials!F4/Financials!E4-1 -> 0.26542324 | J37: =Financials!G4/Financials!F4-1 -> 0.27891156 | K37: =Financials!H4/Financials!G4-1 -> -1 | L37: =Financials!I4/Financials!H4-1 -> #DIV/0! | M37: =Financials!J4/Financials!I4-1 -> -1 | N37: =Financials!K4/Financials!J4-1 -> #DIV/0! | ... BG37: =Financials!BD4/Financials!BC4-1 -> #DIV/0!
B39: 5 | C39: Efficiency Ratios
B40: 5.1 | C40: FinCost-Deposits/Average Deposits | D40: NPR | G40: =Financials!D49/((Financials!D6+Financials!C6)/2) -> 0 | H40: =Financials!E49/((Financials!E6+Financials!D6)/2) -> 0.15983177 | I40: =Financials!F49/((Financials!F6+Financials!E6)/2) -> 0.097070851 | J40: =Financials!G49/((Financials!G6+Financials!F6)/2) -> 0.064344545 | K40: =Financials!H49/((Financials!H6+Financials!G6)/2) -> 0 | L40: =Financials!I49/((Financials!I6+Financials!G6)/2) -> 0.072568475 | M40: =Financials!J49/((Financials!J6+Financials!I6)/2) -> 0 | N40: =Financials!K49/((Financials!K6+Financials!J6)/2) -> 0 | O40: =Financials!L49/((Financials!L6+Financials!K6)/2) -> 0.06422836 | P40: =Financials!M49/((Financials!M6+Financials!L6)/2) -> 0.061963079 | Q40: =Financials!N49/((Financials!N6+Financials!M6)/2) -> 0 | R40: =Financials!O49/((Financials!O6+Financials!N6)/2) -> 0 | S40: =Financials!P49/((Financials!P6+Financials!O6)/2) -> 0 | T40: =Financials!Q49/((Financials!Q6+Financials!P6)/2) -> 0 | ... X40: =Financials!U49/((Financials!U6+Financials!T6)/2) -> 0 | Y40: =Financials!W49/((Financials!W6+Financials!V6)/2) -> 0 | Z40: =Financials!X49/((Financials!X6+Financials!W6)/2) -> 0 | AA40: =Financials!Y49/((Financials!Y6+Financials!X6)/2) -> 0 | AB40: =Financials!Z49/((Financials!Z6+Financials!Y6)/2) -> 0 | AC40: =Financials!AA49/((Financials!AA6+Financials!Z6)/2) -> 0 | AD40: =Financials!AB49/((Financials!AB6+Financials!AA6)/2) -> 0 | AE40: =Financials!AC49/((Financials!AC6+Financials!AB6)/2) -> 0 | AF40: =Financials!AD49/((Financials!AD6+Financials!AC6)/2) -> 0 | ... AS40: =Financials!AQ49/((Financials!AQ6+Financials!AP6)/2) -> 0 | AT40: =Financials!AR49/((Financials!AR6+Financials!V6)/2) -> 0.078027201 | AU40: =Financials!AS49/((Financials!AS6+Financials!W6)/2) -> 0 | AV40: =Financials!AT49/((Financials!AT6+Financials!X6)/2) -> 0 | AW40: =Financials!AU49/((Financials!AU6+Financials!Y6)/2) -> 0.075906447 | AX40: =Financials!AV49/((Financials!AV6+Financials!Z6)/2) -> -0.00031656024 | AY40: =Financials!AW49/((Financials!AW6+Financials!AA6)/2) -> 0.0632175 | AZ40: =Financials!AX49/((Financials!AX6+Financials!AB6)/2) -> 0 | BA40: =Financials!AY49/((Financials!AY6+Financials!AC6)/2) -> 0 | ... DY40: =Financials!DW49/((Financials!DW6+Financials!DA6)/2) -> 0.074784546
B41: 5.2 | C41: FinCost-Shares/Average Share capital | D41: NPR | G41: =Financials!D50/((Financials!D17+Financials!C17)/2) -> 0.82960451 | H41: =Financials!E50/((Financials!E17+Financials!D17)/2) -> 0 | I41: =Financials!F50/((Financials!F17+Financials!E17)/2) -> 0.046157516 | J41: =Financials!G50/((Financials!G17+Financials!F17)/2) -> 0.033750846 | K41: =Financials!H50/((Financials!H17+Financials!G17)/2) -> 0 | L41: =Financials!I50/((Financials!I17+Financials!G17)/2) -> 0 | M41: =Financials!J50/((Financials!J17+Financials!I17)/2) -> 0 | N41: =Financials!K50/((Financials!K17+Financials!J17)/2) -> 0 | O41: =Financials!L50/((Financials!L17+Financials!K17)/2) -> 0 | P41: =Financials!M50/((Financials!M17+Financials!L17)/2) -> 0 | Q41: =Financials!N50/((Financials!N17+Financials!M17)/2) -> 0 | R41: =Financials!O50/((Financials!O17+Financials!N17)/2) -> 0 | S41: =Financials!P50/((Financials!P17+Financials!O17)/2) -> 0 | T41: =Financials!Q50/((Financials!Q17+Financials!P17)/2) -> 0 | ... X41: =Financials!U50/((Financials!U17+Financials!T17)/2) -> 0 | Y41: =Financials!W50/((Financials!W17+Financials!V17)/2) -> 0 | Z41: =Financials!X50/((Financials!X17+Financials!W17)/2) -> 0 | AA41: =Financials!Y50/((Financials!Y17+Financials!X17)/2) -> 0 | AB41: =Financials!Z50/((Financials!Z17+Financials!Y17)/2) -> 0 | AC41: =Financials!AA50/((Financials!AA17+Financials!Z17)/2) -> 0 | AD41: =Financials!AB50/((Financials!AB17+Financials!AA17)/2) -> 0.027304599 | AE41: =Financials!AC50/((Financials!AC17+Financials!AB17)/2) -> 0.030950788 | AF41: =Financials!AD50/((Financials!AD17+Financials!AC17)/2) -> 0.030119612 | ... AS41: =Financials!AQ50/((Financials!AQ17+Financials!AP17)/2) -> 0.015054117 | AT41: =Financials!AR50/((Financials!AR17+Financials!V17)/2) -> 0.024113338 | AU41: =Financials!AS50/((Financials!AS17+Financials!W17)/2) -> 0 | AV41: =Financials!AT50/((Financials!AT17+Financials!X17)/2) -> 0 | AW41: =Financials!AU50/((Financials!AU17+Financials!Y17)/2) -> 0.02392148 | AX41: =Financials!AV50/((Financials!AV17+Financials!Z17)/2) -> 0.039785431 | AY41: =Financials!AW50/((Financials!AW17+Financials!AA17)/2) -> 0 | AZ41: =Financials!AX50/((Financials!AX17+Financials!AB17)/2) -> 0 | BA41: =Financials!AY50/((Financials!AY17+Financials!AC17)/2) -> 0 | ... DY41: =Financials!DW50/((Financials!DW17+Financials!DA17)/2) -> 0
B42: 5.3 | C42: FinCost-Ext Loans/Average Ext Loans | D42: NPR | G42: =Financials!D51/((Financials!D9+Financials!C9)/2) -> 0 | H42: =Financials!E51/((Financials!E9+Financials!D9)/2) -> 0 | I42: =Financials!F51/((Financials!F9+Financials!E9)/2) -> 0.10644933 | J42: =Financials!G51/((Financials!G9+Financials!F9)/2) -> 0.1499501 | K42: =Financials!H51/((Financials!H9+Financials!G9)/2) -> 0 | L42: =Financials!I51/((Financials!I9+Financials!G9)/2) -> 0.13270267 | M42: =Financials!J51/((Financials!J9+Financials!I9)/2) -> 0 | N42: =Financials!K51/((Financials!K9+Financials!J9)/2) -> 0 | O42: =Financials!L51/((Financials!L9+Financials!K9)/2) -> 0 | P42: =Financials!M51/((Financials!M9+Financials!L9)/2) -> 0.025141729 | Q42: =Financials!N51/((Financials!N9+Financials!M9)/2) -> 0.0256811 | R42: =Financials!O51/((Financials!O9+Financials!N9)/2) -> 0.0256811 | S42: =Financials!P51/((Financials!P9+Financials!O9)/2) -> 0.041082759 | T42: =Financials!Q51/((Financials!Q9+Financials!P9)/2) -> 0.083601024 | ... X42: =Financials!U51/((Financials!U9+Financials!T9)/2) -> 0 | Y42: =Financials!W51/((Financials!W9+Financials!V9)/2) -> 0 | Z42: =Financials!X51/((Financials!X9+Financials!W9)/2) -> 0 | AA42: =Financials!Y51/((Financials!Y9+Financials!X9)/2) -> 0 | AB42: =Financials!Z51/((Financials!Z9+Financials!Y9)/2) -> 0.025117357 | AC42: =Financials!AA51/((Financials!AA9+Financials!Z9)/2) -> 0.027536227 | AD42: =Financials!AB51/((Financials!AB9+Financials!AA9)/2) -> 0.032597452 | AE42: =Financials!AC51/((Financials!AC9+Financials!AB9)/2) -> 0.034284527 | AF42: =Financials!AD51/((Financials!AD9+Financials!AC9)/2) -> 0.037658677 | ... AS42: =Financials!AQ51/((Financials!AQ9+Financials!AP9)/2) -> #DIV/0! | AT42: =Financials!AR51/((Financials!AR9+Financials!V9)/2) -> 0.017749747 | AU42: =Financials!AS51/((Financials!AS9+Financials!W9)/2) -> 0 | AV42: =Financials!AT51/((Financials!AT9+Financials!X9)/2) -> 0 | AW42: =Financials!AU51/((Financials!AU9+Financials!Y9)/2) -> 0.016268048 | AX42: =Financials!AV51/((Financials!AV9+Financials!Z9)/2) -> 0.019401363 | AY42: =Financials!AW51/((Financials!AW9+Financials!AA9)/2) -> 0 | AZ42: =Financials!AX51/((Financials!AX9+Financials!AB9)/2) -> 0 | BA42: =Financials!AY51/((Financials!AY9+Financials!AC9)/2) -> 0 | ... BL42: =Financials!BJ51/((Financials!BJ9+Financials!AN9)/2) -> #DIV/0!
B43: 5.4 | C43: OpEx/Average Total Assets | D43: NPR | G43: =(Financials!D53+Financials!D54)/((Financials!D5+Financials!C5)/2) -> 0.061403116 | H43: =(Financials!E53+Financials!E54)/((Financials!E5+Financials!D5)/2) -> 0.055302954 | I43: =(Financials!F53+Financials!F54)/((Financials!F5+Financials!E5)/2) -> 0.074796085 | J43: =(Financials!G53+Financials!G54)/((Financials!G5+Financials!F5)/2) -> 0.087303235 | K43: =(Financials!H53+Financials!H54)/((Financials!H5+Financials!G5)/2) -> 6.0481638e-05 | L43: =(Financials!I53+Financials!I54)/((Financials!I5+Financials!G5)/2) -> 0.068645245 | M43: =(Financials!J53+Financials!J54)/((Financials!J5+Financials!I5)/2) -> 4.1656233 | N43: =(Financials!K53+Financials!K54)/((Financials!K5+Financials!J5)/2) -> 0.0084738876 | O43: =(Financials!L53+Financials!L54)/((Financials!L5+Financials!K5)/2) -> 0.019757651 | P43: =(Financials!M53+Financials!M54)/((Financials!M5+Financials!L5)/2) -> 0.024383626 | Q43: =(Financials!N53+Financials!N54)/((Financials!N5+Financials!M5)/2) -> 0.027733821 | R43: =(Financials!O53+Financials!O54)/((Financials!O5+Financials!N5)/2) -> 0.03173479 | S43: =(Financials!P53+Financials!P54)/((Financials!P5+Financials!O5)/2) -> 0.036537066 | T43: =(Financials!Q53+Financials!Q54)/((Financials!Q5+Financials!P5)/2) -> 0.040421188 | ... X43: =(Financials!U53+Financials!U54)/((Financials!U5+Financials!T5)/2) -> 0 | Y43: =(Financials!W53+Financials!W54)/((Financials!W5+Financials!V5)/2) -> 0.0049933236 | Z43: =(Financials!X53+Financials!X54)/((Financials!X5+Financials!W5)/2) -> 0.008609476 | AA43: =(Financials!Y53+Financials!Y54)/((Financials!Y5+Financials!X5)/2) -> 0.018995878 | AB43: =(Financials!Z53+Financials!Z54)/((Financials!Z5+Financials!Y5)/2) -> 0.02715832 | AC43: =(Financials!AA53+Financials!AA54)/((Financials!AA5+Financials!Z5)/2) -> 0.036194143 | AD43: =(Financials!AB53+Financials!AB54)/((Financials!AB5+Financials!AA5)/2) -> 0.034093346 | AE43: =(Financials!AC53+Financials!AC54)/((Financials!AC5+Financials!AB5)/2) -> 0.036966171 | AF43: =(Financials!AD53+Financials!AD54)/((Financials!AD5+Financials!AC5)/2) -> 0.039617602 | ... AS43: =(Financials!AQ53+Financials!AQ54)/((Financials!AQ5+Financials!AP5)/2) -> 0.036006349 | AT43: =(Financials!AR53+Financials!AR54)/((Financials!AR5+Financials!V5)/2) -> 0.05190989 | AU43: =(Financials!AS53+Financials!AS54)/((Financials!AS5+Financials!W5)/2) -> 0 | AV43: =(Financials!AT53+Financials!AT54)/((Financials!AT5+Financials!X5)/2) -> 0 | AW43: =(Financials!AU53+Financials!AU54)/((Financials!AU5+Financials!Y5)/2) -> 0.062170403 | AX43: =(Financials!AV53+Financials!AV54)/((Financials!AV5+Financials!Z5)/2) -> 0.083284514 | AY43: =(Financials!AW53+Financials!AW54)/((Financials!AW5+Financials!AA5)/2) -> 0.060507008 | AZ43: =(Financials!AX53+Financials!AX54)/((Financials!AX5+Financials!AB5)/2) -> 0 | BA43: =(Financials!AY53+Financials!AY54)/((Financials!AY5+Financials!AC5)/2) -> 0 | ... DY43: =(Financials!DW53+Financials!DW54)/((Financials!DW5+Financials!DA5)/2) -> 0.08120556
B44: 5.5 | C44: Avge yield on Net loans | D44: NPR | G44: =Financials!D43/((Financials!D30+Financials!C30)/2) -> 0.12892477 | H44: =Financials!E43/((Financials!E30+Financials!D30)/2) -> 0.11306421 | I44: =Financials!F43/((Financials!F30+Financials!E30)/2) -> 0.16650003 | J44: =Financials!G43/((Financials!G30+Financials!F30)/2) -> 0.15413622 | K44: =Financials!H43/((Financials!H30+Financials!G30)/2) -> 0.0001508064 | L44: =Financials!I43/((Financials!I30+Financials!G30)/2) -> 0.14343068 | M44: =Financials!J43/((Financials!J30+Financials!I30)/2) -> 0.0087121362 | N44: =Financials!K43/((Financials!K30+Financials!J30)/2) -> 1.7149523e-05 | O44: =Financials!L43/((Financials!L30+Financials!K30)/2) -> 3.6904895e-05 | P44: =Financials!M43/((Financials!M30+Financials!L30)/2) -> 4.6050213e-05 | Q44: =Financials!N43/((Financials!N30+Financials!M30)/2) -> 0.055880958 | R44: =Financials!O43/((Financials!O30+Financials!N30)/2) -> 0.067548715 | S44: =Financials!P43/((Financials!P30+Financials!O30)/2) -> 0.076824788 | T44: =Financials!Q43/((Financials!Q30+Financials!P30)/2) -> 0.085421166 | ... X44: =Financials!U43/((Financials!U30+Financials!T30)/2) -> 0.11562708 | Y44: =Financials!W43/((Financials!W30+Financials!V30)/2) -> 0.011259393 | Z44: =Financials!X43/((Financials!X30+Financials!W30)/2) -> 0.023433337 | AA44: =Financials!Y43/((Financials!Y30+Financials!X30)/2) -> 0.035419446 | AB44: =Financials!Z43/((Financials!Z30+Financials!Y30)/2) -> 0.048323423 | AC44: =Financials!AA43/((Financials!AA30+Financials!Z30)/2) -> 0.060633409 | AD44: =Financials!AB43/((Financials!AB30+Financials!AA30)/2) -> 0.070903443 | AE44: =Financials!AC43/((Financials!AC30+Financials!AB30)/2) -> 0.086117449 | AF44: =Financials!AD43/((Financials!AD30+Financials!AC30)/2) -> 0.10052727 | ... AS44: =Financials!AQ43/((Financials!AQ30+Financials!AP30)/2) -> 0.0036094925 | AT44: =Financials!AR43/((Financials!AR30+Financials!V30)/2) -> 0.094334745 | AU44: =Financials!AS43/((Financials!AS30+Financials!W30)/2) -> 0 | AV44: =Financials!AT43/((Financials!AT30+Financials!X30)/2) -> 0 | AW44: =Financials!AU43/((Financials!AU30+Financials!Y30)/2) -> 0.13475728 | AX44: =Financials!AV43/((Financials!AV30+Financials!Z30)/2) -> 0.13779373 | AY44: =Financials!AW43/((Financials!AW30+Financials!AA30)/2) -> 0.15452402 | AZ44: =Financials!AX43/((Financials!AX30+Financials!AB30)/2) -> 0 | BA44: =Financials!AY43/((Financials!AY30+Financials!AC30)/2) -> 0 | ... DY44: =Financials!DW43/((Financials!DW30+Financials!DA30)/2) -> 0.19590274
B46: 6 | C46: Liquidity Ratio
B47: 6.1 | C47: Liquid Assets - ST Liabilities/ Deposits | D47: 0.15 | E47: 13.2 | F47: =Financials!C10/Financials!C6 -> 0.33176198 | G47: =Financials!D10/Financials!D6 -> 0.18460027 | H47: =Financials!E10/Financials!E6 -> 0.2226544 | I47: =Financials!F10/Financials!F6 -> 0.22152782 | J47: =Financials!G10/Financials!G6 -> 0.081586526 | K47: =Financials!H10/Financials!H6 -> 0 | L47: =Financials!I10/Financials!I6 -> 0.075449569 | M47: =Financials!J10/Financials!J6 -> 0.00124421 | ... X47: =Financials!U10/Financials!U6 -> 0.0004187257 | Y47: =Financials!W10/Financials!W6 -> 0.0026293204 | Z47: =Financials!X10/Financials!X6 -> 0.0045832355 | AA47: =Financials!Y10/Financials!Y6 -> 0.0085825902 | AB47: =Financials!Z10/Financials!Z6 -> 0.010420256 | AC47: =Financials!AA10/Financials!AA6 -> 0.011837953 | AD47: =Financials!AB10/Financials!AB6 -> 0.011041641 | AE47: =Financials!AC10/Financials!AC6 -> 0.014490488 | AF47: =Financials!AD10/Financials!AD6 -> 0.015287203 | ... DX47: =Financials!DV10/Financials!DV6 -> #DIV/0! | DY47: =Financials!DW10/Financials!DW8 -> 0.62683262
B49: 7 | C49: Loan Loss Provisions Ratios
B50: 7.1 | C50: Actual LLP / Required LLP | D50: 1 | E50: 44.1 | F50: =Financials!C32/Financials!C35 -> #REF! | G50: =Financials!D32/Financials!D35 -> #REF! | H50: =Financials!E32/Financials!E35 -> #REF! | I50: =Financials!F32/Financials!F35 -> #REF! | J50: =Financials!G32/Financials!G35 -> #REF! | K50: =Financials!H32/Financials!H35 -> 0.13819563 | L50: =Financials!I32/Financials!I35 -> 0.24870669 | M50: =Financials!J32/Financials!J35 -> #DIV/0! | ... X50: =Financials!U32/Financials!U35 -> 0 | Y50: =Financials!W32/Financials!W35 -> 0.0033863324 | Z50: =Financials!X32/Financials!X35 -> #DIV/0! | AA50: =Financials!Y32/Financials!Y35 -> 0.13677916 | AB50: =Financials!Z32/Financials!Z35 -> 390.05363 | AC50: =Financials!AA32/Financials!AA35 -> 0.0030112037 | AD50: =Financials!AB32/Financials!AB35 -> #DIV/0! | AE50: =Financials!AC32/Financials!AC35 -> 0.10161793 | AF50: =Financials!AD32/Financials!AD35 -> 357.88846 | ... DY50: =Financials!DW32/Financials!DW35 -> #DIV/0!

Sheet CAELS
B3: NYAHURURU UMOJA CAELs | E3: 2008 | F3: 2009 | G3: 2010 | H3: 2011 | I3: 2012 | J3: 41609 | K3: 2013 | L3: 41640 | M3: 41671 | N3: 2011 | O3: 2012 | P3: 2014 | Q3: 42005 | R3: 42036 | S3: 42064 | T3: 42095 | U3: 42125 | V3: 42156 | W3: 42186 | X3: 42217 | Y3: 42248 | Z3: 42278 | AA3: 42309 | AB3: 42339 | AC3: 2015 | AD3: 2015 Rev. | AF3: 42416 | AG3: 42445 | AH3: 42476 | AI3: May-16 | AJ3: Jun-16 | AK3: Jul-16 | AL3: Aug-16 | AM3: Sept-16 | AN3: Oct-16 | AO3: Nov-16 | AP3: Dec-16 | AQ3: Aud-16 | AR3: 42736 | AS3: 42767 | AT3: 42795 | AU3: 42826 | AV3: 42856 | AW3: 42887 | AX3: 42917 | AY3: 42948 | AZ3: 42979 | BA3: 43390 | BB3: 43421 | BC3: 43451 | BD3: Aud-17 | BE3: 43101 | BF3: 43132 | BG3: 43160 | BH3: 43191 | BI3: 43221 | BJ3: 43252 | BK3: 43282 | BL3: 43313 | BM3: 43344 | BN3: 43374 | BO3: 43405 | BP3: 43435 | BQ3: 43466 | BR3: 43497 | BS3: 43525 | BT3: 43556 | BU3: 43586 | BV3: 43617 | BW3: 43647 | BX3: 43678 | BY3: 43709 | BZ3: 43739 | CA3: 43770 | CB3: 43800 | CC3: Audited 19 | CD3: 43831 | CE3: 43862 | CF3: 43891 | CG3: 43922 | CH3: 43952 | CI3: 43983 | CJ3: 44013 | CK3: 44044 | CL3: 44075 | CM3: 44105 | CN3: 44136 | CO3: 44166 | CP3: 44166 | CQ3: Audited-20 | CR3: 44197 | CS3: 44228 | CT3: 44256 | CU3: 44287 | CV3: 44317 | CW3: 44348 | CX3: 44378 | CY3: 44409 | CZ3: 44440 | DA3: 44470 | DB3: 44501 | DC3: 44531 | DD3: AUDITED-21 | DE3: 44562 | DF3: 44593 | DG3: 44621 | DH3: 44652 | DI3: 44682 | DJ3: 44713 | DK3: 44743 | DL3: 44774 | DM3: 44805 | DN3: 44835 | DO3: 44866 | DP3: 44896 | DQ3: audited 22
A4: INDICATORS | B4: CAPITAL ADEQUACY | C4: CORE CAPITAL | D4: 10M | E4: =Financials!C13/1000000 -> 0.439861 | F4: =Financials!D13/1000000 -> 0.736861 | G4: =Financials!E13/1000000 -> 8.453756 | H4: =Financials!F13/1000000 -> 11.449334 | I4: =Financials!G13/1000000 -> 15.452148 | J4: =Financials!H13/1000000 -> 25.274778 | K4: =Financials!I13/1000000 -> 19.725079 | L4: =Financials!J13/1000000 -> 51.119689 | M4: =Financials!K13/1000000 -> 26.585028 | N4: =Financials!F13/1000000 -> 11.449334 | O4: =Financials!G13/1000000 -> 15.452148 | P4: =Financials!V13/1000000 -> 22.540772 | Q4: =Financials!W13/1000000 -> 32.110396 | R4: =Financials!X13/1000000 -> 33.697534 | S4: =Financials!Y13/1000000 -> 30.530662 | T4: =Financials!Z13/1000000 -> 33.605968 | U4: =Financials!AA13/1000000 -> 34.320074 | V4: =Financials!AB13/1000000 -> 35.793923 | W4: =Financials!AC13/1000000 -> 33.507873 | ... BW4: =Financials!CC13/1000000 -> 54.493325
C5: CCA | D5: Min 10% | E5: =Financials!C13/Financials!C5 -> 0.12656377 | F5: =Financials!D13/Financials!D5 -> 0.084206459 | G5: =Financials!E13/Financials!E5 -> 0.44457183 | H5: =Financials!F13/Financials!F5 -> 0.32116467 | I5: =Financials!G13/Financials!G5 -> 0.32003712 | J5: =Financials!H13/Financials!H5 -> 0.335394 | K5: =Financials!I13/Financials!I5 -> 0.27632121 | L5: =Financials!J13/Financials!J5 -> 0.33268803 | M5: =Financials!K13/Financials!K5 -> 0.33348325 | N5: =Financials!F13/Financials!F5 -> 0.32116467 | O5: =Financials!G13/Financials!G5 -> 0.32003712 | P5: =Financials!V13/Financials!V5 -> 0.24691295 | Q5: =Financials!W13/Financials!W5 -> 0.34902504 | R5: =Financials!X13/Financials!X5 -> 0.3646068 | S5: =Financials!Y13/Financials!Y5 -> 0.32774907 | T5: =Financials!Z13/Financials!Z5 -> 0.33591021 | U5: =Financials!AA13/Financials!AA5 -> 0.33053058 | V5: =Financials!AB13/Financials!AB5 -> 0.33370253 | W5: =Financials!AC13/Financials!AC5 -> 0.30459415 | ... CE5: =Financials!CK13/Financials!CK5 -> 0.19551488 | CF5: =Financials!CK13/Financials!CK5 -> 0.19551488 | CG5: =Financials!CL13/Financials!CL5 -> #REF! | CH5: =Financials!CM13/Financials!CM5 -> 0.21083517 | CI5: =Financials!CN13/Financials!CN5 -> 0.2132315 | CJ5: =Financials!CO13/Financials!CO5 -> 0.2211074 | CK5: =Financials!CP13/Financials!CP5 -> 0.22072466 | CL5: =Financials!CQ13/Financials!CQ5 -> 0.23277242 | CM5: =Financials!CR13/Financials!CR5 -> 0.23844867 | ... DP5: =Financials!DU13/Financials!DU5 -> 0.26444004 | DQ5: =Financials!DW13/Financials!DW5 -> 0.23491377
C6: ICA | D6: Min 8% | E6: =Financials!C14/Financials!C5 -> 0.023554343 | F6: =Financials!D14/Financials!D5 -> 0.01358311 | G6: =Financials!E14/Financials!E5 -> 0.051734424 | H6: =Financials!F14/Financials!F5 -> 0.03537275 | I6: =Financials!G14/Financials!G5 -> 0.048716734 | J6: =Financials!H14/Financials!H5 -> 0.11118269 | K6: =Financials!I14/Financials!I5 -> 0.052482439 | L6: =Financials!J14/Financials!J5 -> 0.11188556 | ... DP6: =Financials!DN14/Financials!DN5 -> 0.12166111 | DQ6: =Financials!DP14/Financials!DP5 -> 0.13163115
C7: CCD | D7: Min 8% | E7: =Financials!C13/Financials!C6 -> 0.19297668 | F7: =Financials!D13/Financials!D6 -> 0.12445286 | G7: =Financials!E13/Financials!E6 -> 1.0154601 | H7: =Financials!F13/Financials!F6 -> 0.66847291 | I7: =Financials!G13/Financials!G6 -> 0.52569304 | J7: =Financials!H13/Financials!H6 -> 0.54885721 | K7: =Financials!I13/Financials!I6 -> 0.45090247 | L7: =Financials!J13/Financials!J6 -> 0.54179922 | M7: =Financials!K13/Financials!K6 -> 0.54238792 | N7: =Financials!F13/Financials!F6 -> 0.66847291 | O7: =Financials!G13/Financials!G6 -> 0.52569304 | P7: =Financials!V13/Financials!V6 -> 0.36281135 | Q7: =Financials!W13/Financials!W6 -> 0.50539575 | R7: =Financials!X13/Financials!X6 -> 0.54147933 | S7: =Financials!Y13/Financials!Y6 -> 0.46053625 | T7: =Financials!Z13/Financials!Z6 -> 0.48969269 | U7: =Financials!AA13/Financials!AA6 -> 0.47953693 | V7: =Financials!AB13/Financials!AB6 -> 0.48659464 | W7: =Financials!AC13/Financials!AC6 -> 0.45565376 | ... CG7: =Financials!CM13/Financials!CM6 -> 0.28655892 | CH7: =Financials!CM13/Financials!CM6 -> 0.28655892 | CI7: =Financials!CN13/Financials!CN6 -> 0.28883963 | CJ7: =Financials!CO13/Financials!CO6 -> 0.30150871 | CK7: =Financials!CP13/Financials!CP6 -> 0.2995491 | CL7: =Financials!CQ13/Financials!CQ6 -> 0.32007352 | CM7: =Financials!CR13/Financials!CR6 -> 0.3294601 | CN7: =Financials!CS13/Financials!CS6 -> 0.33731793 | CO7: =Financials!CT13/Financials!CT6 -> 0.3273376 | ... DP7: =Financials!DU13/Financials!DU6 -> 0.37917103 | DQ7: =Financials!DW13/Financials!DW6 -> 0.34187356
C8: Adjusted CCA | E8: =(Financials!C13-Financials!C33)/Financials!C5 -> 0.12656377 | F8: =(Financials!D13-Financials!D33)/Financials!D5 -> 0.084206459 | G8: =(Financials!E13-Financials!E33)/Financials!E5 -> 0.44457183 | H8: =(Financials!F13-Financials!F33)/Financials!F5 -> 0.32116467 | I8: =(Financials!G13-Financials!G33)/Financials!G5 -> 0.32003712 | J8: =(Financials!H13-Financials!H33)/Financials!H5 -> 0.29465559 | K8: =(Financials!I13-Financials!I33)/Financials!I5 -> 0.23331496 | L8: =(Financials!J13-Financials!J33)/Financials!J5 -> 0.33268801 | M8: =(Financials!K13-Financials!K33)/Financials!K5 -> 0.31503607 | N8: =(Financials!F13-Financials!F33)/Financials!F5 -> 0.32116467 | O8: =(Financials!G13-Financials!G33)/Financials!G5 -> 0.32003712 | P8: =(Financials!V13-Financials!V33)/Financials!V5 -> 0.24691293 | Q8: =(Financials!W13-Financials!W33)/Financials!W5 -> 0.20180911 | R8: =(Financials!X13-Financials!X33)/Financials!X5 -> 0.3646068 | S8: =(Financials!Y13-Financials!Y33)/Financials!Y5 -> 0.32774907 | T8: =(Financials!Z13-Financials!Z33)/Financials!Z5 -> 0.33591021 | U8: =(Financials!AA13-Financials!AA33)/Financials!AA5 -> 0.33053058 | V8: =(Financials!AB13-Financials!AB33)/Financials!AB5 -> 0.33370253 | W8: =(Financials!AC13-Financials!AC33)/Financials!AC5 -> 0.30459415 | ... CG8: =(Financials!CM13-Financials!CM33)/Financials!CM5 -> 0.21083517 | CH8: =(Financials!CM13-Financials!CM33)/Financials!CM5 -> 0.21083517 | CI8: =(Financials!CN13-Financials!CN33)/Financials!CN5 -> 0.2132315 | CJ8: =(Financials!CO13-Financials!CO33)/Financials!CO5 -> 0.2211074 | CK8: =(Financials!CP13-Financials!CP33)/Financials!CP5 -> 0.22072466 | CL8: =(Financials!CQ13-Financials!CQ33)/Financials!CQ5 -> 0.23277242 | CM8: =(Financials!CR13-Financials!CR33)/Financials!CR5 -> 0.23844867 | CN8: =(Financials!CS13-Financials!CS33)/Financials!CS5 -> 0.24325141 | CO8: =(Financials!CT13-Financials!CT33)/Financials!CT5 -> 0.23537678 | ... DP8: =(Financials!DU13-Financials!DU33)/Financials!DU5 -> 0.26444004 | DQ8: =(Financials!DW13-Financials!DW33)/Financials!DW5 -> 0.15646902
B10: ASSET QUALITY | C10: NPL30 | E10: =Financials!C34/Financials!C31 -> 0 | F10: =Financials!D34/Financials!D31 -> 0 | G10: =Financials!E34/Financials!E31 -> 0 | H10: =Financials!F34/Financials!F31 -> 0 | I10: =Financials!G34/Financials!G31 -> 0 | J10: =Financials!H34/Financials!H31 -> 0 | K10: =Financials!I34/Financials!I31 -> 0 | L10: =Financials!J34/Financials!J31 -> 0 | M10: =Financials!K34/Financials!K31 -> 0 | N10: =Financials!F34/Financials!F31 -> 0 | O10: =Financials!G34/Financials!G31 -> 0 | P10: =Financials!V34/Financials!V31 -> 0 | Q10: =Financials!W34/Financials!W31 -> 0 | R10: =Financials!X34/Financials!X31 -> 0 | S10: =Financials!Y34/Financials!Y31 -> 0.038815268 | T10: =Financials!Z34/Financials!Z31 -> 0 | U10: =Financials!AA34/Financials!AA31 -> 0 | V10: =Financials!AB34/Financials!AB31 -> 0.062610744 | W10: =Financials!AC34/Financials!AC31 -> 2.3190955e-08 | ... DP10: =Financials!DV34/Financials!DV31 -> #DIV/0! | DQ10: =Financials!DX34/Financials!DX31 -> #DIV/0!
C11: A/L NPL30 | E11: =Financials!C33/Financials!C31 -> 0 | F11: =Financials!D33/Financials!D31 -> 0 | G11: =Financials!E33/Financials!E31 -> 0 | H11: =Financials!F33/Financials!F31 -> 0 | I11: =Financials!G33/Financials!G31 -> 0 | J11: =Financials!H33/Financials!H31 -> 0.063315496 | K11: =Financials!I33/Financials!I31 -> 0.062868645 | L11: =Financials!J33/Financials!J31 -> 1.7620603e-08 | M11: =Financials!K33/Financials!K31 -> 0.02836427 | N11: =Financials!F33/Financials!F31 -> 0 | O11: =Financials!G33/Financials!G31 -> 0 | P11: =Financials!V33/Financials!V31 -> 2.4259932e-08 | Q11: =Financials!W33/Financials!W31 -> 0.19016025 | R11: =Financials!X33/Financials!X31 -> 0 | S11: =Financials!Y33/Financials!Y31 -> 0 | T11: =Financials!Z33/Financials!Z31 -> 0 | U11: =Financials!AA33/Financials!AA31 -> 0 | V11: =Financials!AB33/Financials!AB31 -> 0 | W11: =Financials!AC33/Financials!AC31 -> 0 | ... DP11: =Financials!DV33/Financials!DV31 -> #DIV/0! | DQ11: =Financials!DX33/Financials!DX31 -> #DIV/0!
B13: EARNINGS | C13: ROA | E13: =Trend!C92/((Financials!C5+Financials!B5)/2) -> #VALUE! | F13: =Trend!D92/((Financials!D5+Financials!C5)/2) -> 0.0072072296 | G13: =Trend!E92/((Financials!E5+Financials!D5)/2) -> 0.0048904875 | H13: =Trend!F92/((Financials!F5+Financials!E5)/2) -> 0.013253911 | I13: =Trend!G92/((Financials!G5+Financials!F5)/2) -> 0.0082719798 | J13: =Trend!H92/((Financials!H5+Financials!G5)/2) -> 8.4137254e-05 | K13: =Trend!I92/((Financials!I5+Financials!H5)/2) -> 0.01563342 | L13: =Trend!J92/((Financials!J5+Financials!I5)/2) -> -4.1899954 | M13: =Trend!K92/((Financials!K5+Financials!J5)/2) -> -0.0084898179 | N13: =Trend!#REF!/((Financials!F5+Financials!G5)/2) -> #REF! | O13: =Trend!#REF!/((Financials!G5+Financials!H5)/2) -> #REF! | P13: =Trend!#REF!/((Financials!V5+Financials!U5)/2) -> #REF! | Q13: =Trend!W92/((Financials!W5+Financials!W5)/2) -> -0.02097061 | R13: =Trend!X92/((Financials!X5+Financials!X5)/2) -> -0.013792893 | S13: =Trend!Y92/((Financials!Y5+Financials!Y5)/2) -> 0.03981556 | T13: =Trend!Z92/((Financials!Z5+Financials!Z5)/2) -> -0.0078705893 | U13: =Trend!AA92/((Financials!AA5+Financials!AA5)/2) -> 0.03891546 | V13: =Trend!AB92/((Financials!AB5+Financials!AB5)/2) -> 0.044773552 | W13: =Trend!AC92/((Financials!AC5+Financials!AC5)/2) -> 0.0097082356 | X13: =Trend!AD92/((Financials!AD5+Financials!AD5)/2) -> 0.018663637 | ... DP13: =Trend!DV92/((Financials!DV5+Financials!DV5)/2) -> #DIV/0! | DQ13: =Trend!#REF!/((Financials!DX5+Financials!DX5)/2) -> #REF!
C14: C/I ratio | E14: =(Trend!B78/(Trend!B74-Trend!B75)) -> #VALUE! | F14: =(Trend!C78/(Trend!C74-Trend!C75)) -> #DIV/0! | G14: =(Trend!D78/(Trend!D74-Trend!D75)) -> 0.89495419 | H14: =(Trend!E78/(Trend!E74-Trend!E75)) -> 0.91258597 | I14: =(Trend!F78/(Trend!F74-Trend!F75)) -> 0.84697696 | J14: =(Trend!G78/(Trend!G74-Trend!G75)) -> 0.91228284 | K14: =(Trend!H78/(Trend!H74-Trend!H75)) -> 0.41821395 | L14: =(Trend!I78/(Trend!I74-Trend!I75)) -> 0.78100348 | M14: =(Trend!J78/(Trend!J74-Trend!J75)) -> -170.91803 | N14: =(Trend!G78/(Trend!G74-Trend!G75)) -> 0.91228284 | O14: =(Trend!H78/(Trend!H74-Trend!H75)) -> 0.41821395 | P14: =(Trend!#REF!/(Trend!#REF!-Trend!#REF!)) -> #REF! | Q14: =(Trend!W78/(Trend!W74-Trend!W75)) -> -0.31445369 | R14: =(Trend!X78/(Trend!X74-Trend!X75)) -> -1.7574301 | S14: =(Trend!Y78/(Trend!Y74-Trend!Y75)) -> 0.32098964 | T14: =(Trend!Z78/(Trend!Z74-Trend!Z75)) -> 1.4033535 | U14: =(Trend!AA78/(Trend!AA74-Trend!AA75)) -> 0.47437364 | V14: =(Trend!AB78/(Trend!AB74-Trend!AB75)) -> 0.42606844 | W14: =(Trend!AC78/(Trend!AC74-Trend!AC75)) -> 0.78114253 | X14: =(Trend!AD78/(Trend!AD74-Trend!AD75)) -> 0.6689185 | ... DP14: =(Trend!DV78/(Trend!DV74-Trend!DV75)) -> #DIV/0! | DQ14: =(Trend!#REF!/(Trend!#REF!-Trend!#REF!)) -> #REF!
C15: OE ratio | E15: =Trend!C78/((Financials!C5+Financials!B5)/2) -> #VALUE! | F15: =Trend!D78/((Financials!D5+Financials!C5)/2) -> 0.061403116 | G15: =Trend!E78/((Financials!E5+Financials!D5)/2) -> 0.055302954 | H15: =Trend!F78/((Financials!F5+Financials!E5)/2) -> 0.074796085 | I15: =Trend!G78/((Financials!G5+Financials!F5)/2) -> 0.087303235 | J15: =Trend!H78/((Financials!H5+Financials!G5)/2) -> 6.0481638e-05 | K15: =Trend!I78/((Financials!I5+Financials!H5)/2) -> 0.055979257 | L15: =Trend!J78/((Financials!J5+Financials!I5)/2) -> 4.1656233 | M15: =Trend!K78/((Financials!K5+Financials!J5)/2) -> 0.0084738876 | N15: =Trend!#REF!/((Financials!F5+Financials!G5)/2) -> #REF! | O15: =Trend!#REF!/((Financials!G5+Financials!H5)/2) -> #REF! | P15: =Trend!#REF!/((Financials!V5+Financials!U5)/2) -> #REF! | Q15: =Trend!W78/((Financials!W5+Financials!W5)/2) -> 0.0049740585 | R15: =Trend!X78/((Financials!X5+Financials!X5)/2) -> 0.0085898526 | S15: =Trend!Y78/((Financials!Y5+Financials!Y5)/2) -> 0.018921346 | T15: =Trend!Z78/((Financials!Z5+Financials!Z5)/2) -> 0.026222868 | U15: =Trend!AA78/((Financials!AA5+Financials!AA5)/2) -> 0.035533797 | V15: =Trend!AB78/((Financials!AB5+Financials!AB5)/2) -> 0.033548287 | W15: =Trend!AC78/((Financials!AC5+Financials!AC5)/2) -> 0.036504919 | X15: =Trend!AD78/((Financials!AD5+Financials!AD5)/2) -> 0.038764006 | ... DP15: =Trend!DV78/((Financials!DV5+Financials!DV5)/2) -> #DIV/0! | DQ15: =Trend!#REF!/((Financials!DX5+Financials!DX5)/2) -> #REF!
B17: LIQUIDITY | C17: W NLIQ ratio | D17: Min 15% | E17: =Trend!C5/(Financials!C10+Trend!C28+Trend!C29) -> 0.81083287 | F17: =Trend!D5/(Financials!D10+Trend!D28+Trend!D29) -> 1.262236 | G17: =Trend!E5/(Financials!E10+Trend!E28+Trend!E29) -> 0.4615511 | H17: =Trend!F5/(Financials!F10+Trend!F28+Trend!F29) -> 1.0381363 | I17: =Trend!G5/(Financials!G10+Trend!G28+Trend!G29) -> 0.81145195 | J17: =Trend!H5/(Financials!H10+Trend!H28+Trend!H29) -> 7.2302885 | K17: =Trend!I5/(Financials!I10+Trend!I28+Trend!I29) -> 1.115412 | L17: =Trend!J5/(Financials!J10+Trend!J28+Trend!J29) -> 7.2271063 | M17: =Trend!K5/(Financials!K10+Trend!K28+Trend!K29) -> 6.2791202 | N17: =(Trend!#REF!+Trend!#REF!)/(Financials!F10+Trend!#REF!+Trend!#REF!) -> #REF! | O17: =(Trend!#REF!+Trend!#REF!)/(Financials!G10+Trend!#REF!+Trend!#REF!) -> #REF! | P17: =(Trend!#REF!+Trend!#REF!)/(Financials!V10+Trend!#REF!+Trend!#REF!) -> #REF! | Q17: =(Trend!W5+Trend!W10)/(Financials!W10+Trend!W28+Trend!W29) -> 3.0031118 | R17: =(Trend!X5+Trend!X10)/(Financials!X10+Trend!X28+Trend!X29) -> 3.0284507 | S17: =(Trend!Y5+Trend!Y10)/(Financials!Y10+Trend!Y28+Trend!Y29) -> 2.9841697 | T17: =(Trend!Z5+Trend!Z10)/(Financials!Z10+Trend!Z28+Trend!Z29) -> 4.363228 | U17: =(Trend!AA5+Trend!AA10)/(Financials!AA10+Trend!AA28+Trend!AA29) -> 3.7816791 | V17: =(Trend!AB5+Trend!AB10)/(Financials!AB10+Trend!AB28+Trend!AB29) -> 5.2058054 | W17: =(Trend!AC5+Trend!AC10)/(Financials!AC10+Trend!AC28+Trend!AC29) -> 3.8549184 | X17: =(Trend!AD5+Trend!AD10)/(Financials!AD10+Trend!AD28+Trend!AD29) -> 2.2258499 | Y17: =Trend!AE5/(Financials!AE10+Trend!AE28+Trend!AE29) -> 1.9324036 | Z17: =Trend!AF5/(Financials!AF10+Trend!AF28+Trend!AF29) -> 2.2409309 | AA17: =Trend!AG5/(Financials!AG10+Trend!AG28+Trend!AG29) -> 1.603955 | AB17: =Trend!AH5/(Financials!AH10+Trend!AH28+Trend!AH29) -> 1.7765396 | AC17: =Trend!AI5/(Financials!AI10+Trend!AI28+Trend!AI29) -> 0.2180399 | AD17: =Trend!AJ5/(Financials!AJ10+Trend!AJ28+Trend!AJ29) -> 0.23036365 | AE17: =Trend!AK5/(Financials!AK10+Trend!AK28+Trend!AK29) -> #DIV/0! | AF17: =Trend!AL5/(Financials!AL10+Trend!AL28+Trend!AL29) -> 0.8711453 | ... DP17: =Trend!DV5/(Financials!DV10+Trend!DV28+Trend!DV29) -> #DIV/0! | DQ17: =Trend!#REF!/(Financials!DX10+Trend!#REF!+Trend!#REF!) -> #REF!
C18: T NLIQ ratio | E18: =(Trend!C5+Trend!C10+Trend!C12)/Financials!C6 -> 0.30383733 | F18: =(Trend!D5+Trend!D10+Trend!D12)/Financials!D6 -> 0.34639282 | G18: =(Trend!E5+Trend!E10+Trend!E12)/Financials!E6 -> 0.17617336 | H18: =(Trend!F5+Trend!F10+Trend!F12)/Financials!F6 -> 0.38720379 | I18: =(Trend!G5+Trend!G10+Trend!G12)/Financials!G6 -> 0.28739573 | J18: =(Trend!H5+Trend!H10+Trend!H12)/Financials!H6 -> 0.45179104 | K18: =(Trend!I5+Trend!I10+Trend!I12)/Financials!I6 -> 0.41086089 | L18: =(Trend!J5+Trend!J10+Trend!J12)/Financials!J6 -> 0.44767614 | M18: =(Trend!K5+Trend!K10+Trend!K12)/Financials!K6 -> 0.44125012 | N18: =(Trend!#REF!+Trend!#REF!+Trend!#REF!)/Financials!F6 -> #REF! | O18: =(Trend!#REF!+Trend!#REF!+Trend!#REF!)/Financials!G6 -> #REF! | P18: =(Trend!#REF!+Trend!#REF!+Trend!#REF!)/Financials!V6 -> #REF! | Q18: =(Trend!W5+Trend!W10+Trend!W12)/Financials!W6 -> 0.22428511 | R18: =(Trend!X5+Trend!X10+Trend!X12)/Financials!X6 -> 0.21885528 | S18: =(Trend!Y5+Trend!Y10+Trend!Y12)/Financials!Y6 -> 0.23858456 | T18: =(Trend!Z5+Trend!Z10+Trend!Z12)/Financials!Z6 -> 0.31235659 | U18: =(Trend!AA5+Trend!AA10+Trend!AA12)/Financials!AA6 -> 0.32562178 | V18: =(Trend!AB5+Trend!AB10+Trend!AB12)/Financials!AB6 -> 0.31757952 | W18: =(Trend!AC5+Trend!AC10+Trend!AC12)/Financials!AC6 -> 0.30017125 | X18: =(Trend!AD5+Trend!AD10+Trend!AD12)/Financials!AD6 -> 0.20745791 | ... DP18: =(Trend!DV5+Trend!DV10+Trend!DV12)/Financials!DV6 -> #DIV/0! | DQ18: =(Trend!#REF!+Trend!#REF!+Trend!#REF!)/Financials!DX6 -> #REF!
C19: EB ratio | D19: Max 25% | E19: =Financials!C9/Financials!C5 -> 0 | F19: =Financials!D9/Financials!D5 -> 0.11427726 | G19: =Financials!E9/Financials!E5 -> 0 | H19: =Financials!F9/Financials!F5 -> 0.080526361 | I19: =Financials!G9/Financials!G5 -> 0.011602788 | J19: =Financials!H9/Financials!H5 -> 0.05352902 | K19: =Financials!I9/Financials!I5 -> 0.056508896 | L19: =Financials!J9/Financials!J5 -> 0.052504959 | M19: =Financials!K9/Financials!K5 -> 0.048725194 | N19: =Financials!F9/Financials!F5 -> 0.080526361 | O19: =Financials!G9/Financials!G5 -> 0.011602788 | P19: =Financials!V9/Financials!V5 -> 0.022710711 | Q19: =Financials!W9/Financials!W5 -> 0.024588005 | R19: =Financials!X9/Financials!X5 -> 0.024475919 | S19: =Financials!Y9/Financials!Y5 -> 0.024283854 | T19: =Financials!Z9/Financials!Z5 -> 0.018959303 | U19: =Financials!AA9/Financials!AA5 -> 0.018267496 | V19: =Financials!AB9/Financials!AB5 -> 0.017683401 | W19: =Financials!AC9/Financials!AC5 -> 0.017242105 | ... DP19: =Financials!DV9/Financials!DV5 -> #DIV/0! | DQ19: =Financials!DX9/Financials!DX5 -> #DIV/0!
C20: LIQ to TA ratio | E20: =(Trend!C5+Trend!C10)/Trend!C27 -> 0.19927174 | F20: =(Trend!D5+Trend!D10)/Trend!D27 -> 0.23437398 | G20: =(Trend!E5+Trend!E10)/Trend!E27 -> 0.077129285 | H20: =(Trend!F5+Trend!F10)/Trend!F27 -> 0.18603024 | I20: =(Trend!G5+Trend!G10)/Trend!G27 -> 0.17496389 | J20: =(Trend!H5+Trend!H10)/Trend!H27 -> 0.23135298 | K20: =(Trend!I5+Trend!I10)/Trend!I27 -> 0.251783 | L20: =(Trend!J5+Trend!J10)/Trend!J27 -> 0.23102194 | M20: =(Trend!K5+Trend!K10)/Trend!K27 -> 0.22588387 | N20: =(Trend!#REF!+Trend!#REF!)/Trend!#REF! -> #REF! | O20: =(Trend!#REF!+Trend!#REF!)/Trend!#REF! -> #REF! | P20: =(Trend!#REF!+Trend!#REF!)/Trend!#REF! -> #REF! | Q20: =(Trend!W5+Trend!W10)/Trend!W27 -> 0.11039232 | R20: =(Trend!X5+Trend!X10)/Trend!X27 -> 0.10307131 | S20: =(Trend!Y5+Trend!Y10)/Trend!Y27 -> 0.1258451 | T20: =(Trend!Z5+Trend!Z10)/Trend!Z27 -> 0.1721014 | U20: =(Trend!AA5+Trend!AA10)/Trend!AA27 -> 0.1838168 | V20: =(Trend!AB5+Trend!AB10)/Trend!AB27 -> 0.17846771 | W20: =(Trend!AC5+Trend!AC10)/Trend!AC27 -> 0.16231335 | X20: =(Trend!AD5+Trend!AD10)/Trend!AD27 -> 0.10127398 | ... DP20: =(Trend!DV5+Trend!DV10)/Trend!DV27 -> #DIV/0! | DQ20: =(Trend!#REF!+Trend!#REF!)/Trend!#REF! -> #REF!
B22: STRUCTURE OF ASSETS | C22: LB ratio | D22: Max 5% | E22: =Financials!#REF!/Financials!#REF! -> #REF! | F22: =Financials!C40/Financials!C5 -> 0 | G22: =Financials!D40/Financials!D5 -> 0 | H22: =Financials!E40/Financials!E5 -> 0 | I22: =Financials!F40/Financials!F5 -> 0 | J22: =Financials!G40/Financials!G5 -> 0.062864344 | K22: =Financials!H40/Financials!H5 -> 0 | L22: =Financials!I40/Financials!I5 -> 0.045218576 | M22: =Financials!J40/Financials!J5 -> 0.021007307 | N22: =Financials!F40/Financials!F5 -> 0 | O22: =Financials!G40/Financials!G5 -> 0.062864344 | P22: =Financials!U40/Financials!U5 -> 0.034993654 | Q22: =Financials!W40/Financials!W5 -> 0.035085877 | R22: =Financials!X40/Financials!X5 -> 0 | S22: =Financials!Y40/Financials!Y5 -> 0 | T22: =Financials!Z40/Financials!Z5 -> 0 | U22: =Financials!AA40/Financials!AA5 -> 0 | V22: =Financials!AB40/Financials!AB5 -> 0 | W22: =Financials!AC40/Financials!AC5 -> 0 | X22: =Financials!AD40/Financials!AD5 -> 0 | ... DP22: =Financials!DV40/Financials!DV5 -> #DIV/0! | DQ22: =Financials!DX40/Financials!DX5 -> #DIV/0!
C23: FICC | D23: Max 40% | E23: =Financials!#REF!/Financials!#REF! -> #REF! | F23: =Financials!C25/Financials!C13 -> 0.15800446 | G23: =Financials!D25/Financials!D13 -> 0.20288765 | H23: =Financials!E25/Financials!E13 -> 0.024781884 | I23: =Financials!F25/Financials!F13 -> 0.019171421 | J23: =Financials!G25/Financials!G13 -> 0.014722872 | K23: =Financials!H25/Financials!H13 -> 0.13335396 | L23: =Financials!I25/Financials!I13 -> 0.01154297 | M23: =Financials!J25/Financials!J13 -> 0.13186668 | N23: =Financials!F25/Financials!F13 -> 0.019171421 | O23: =Financials!G25/Financials!G13 -> 0.014722872 | P23: =Financials!U25/Financials!U13 -> 0.21144655 | Q23: =Financials!W25/Financials!W13 -> 0.18977861 | R23: =Financials!X25/Financials!X13 -> 0.18084013 | S23: =Financials!Y25/Financials!Y13 -> 0.19959824 | T23: =Financials!Z25/Financials!Z13 -> 0.18503226 | U23: =Financials!AA25/Financials!AA13 -> 0.23945718 | V23: =Financials!AB25/Financials!AB13 -> 0.2295973 | W23: =Financials!AC25/Financials!AC13 -> 0.30494887 | X23: =Financials!AD25/Financials!AD13 -> 0.54222442 | ... DP23: =Financials!DV25/Financials!DV13 -> #DIV/0! | DQ23: =Financials!DX25/Financials!DX13 -> #DIV/0!
C24: FITD | D24: Max 5% | E24: =Financials!#REF!/Financials!#REF! -> #REF! | F24: =Financials!C25/Financials!C6 -> 0.030491176 | G24: =Financials!D25/Financials!D6 -> 0.025249949 | H24: =Financials!E25/Financials!E6 -> 0.025165014 | I24: =Financials!F25/Financials!F6 -> 0.012815576 | J24: =Financials!G25/Financials!G6 -> 0.0077397114 | K24: =Financials!H25/Financials!H6 -> 0.073192284 | L24: =Financials!I25/Financials!I6 -> 0.0052047538 | M24: =Financials!J25/Financials!J6 -> 0.071445266 | N24: =Financials!F25/Financials!F6 -> 0.012815576 | O24: =Financials!G25/Financials!G6 -> 0.0077397114 | P24: =Financials!U25/Financials!U6 -> 0.098189807 | Q24: =Financials!W25/Financials!W6 -> 0.095913305 | R24: =Financials!X25/Financials!X6 -> 0.097921192 | S24: =Financials!Y25/Financials!Y6 -> 0.091922225 | T24: =Financials!Z25/Financials!Z6 -> 0.090608944 | U24: =Financials!AA25/Financials!AA6 -> 0.11482856 | V24: =Financials!AB25/Financials!AB6 -> 0.11172082 | W24: =Financials!AC25/Financials!AC6 -> 0.1389511 | X24: =Financials!AD25/Financials!AD6 -> 0.25137121 | ... DP24: =Financials!DV25/Financials!DV6 -> #DIV/0! | DQ24: =Financials!DX25/Financials!DX6 -> #DIV/0!
C25: NEA | D25: Max 10% | E25: =Financials!#REF!/Financials!#REF! -> #REF! | F25: =Financials!C38/Financials!C5 -> 0.027502654 | G25: =Financials!D38/Financials!D5 -> 0.012586841 | H25: =Financials!E38/Financials!E5 -> 0.03602198 | I25: =Financials!F38/Financials!F5 -> 0.058254273 | J25: =Financials!G38/Financials!G5 -> 0.11368462 | K25: =Financials!H38/Financials!H5 -> 0.08407688 | L25: =Financials!I38/Financials!I5 -> 0.067754641 | M25: =Financials!J38/Financials!J5 -> 0.082266651 | N25: =Financials!F38/Financials!F5 -> 0.058254273 | O25: =Financials!G38/Financials!G5 -> 0.11368462 | P25: =Financials!U38/Financials!U5 -> 0.072853594 | Q25: =Financials!W38/Financials!W5 -> 0.075289327 | R25: =Financials!X38/Financials!X5 -> 0.077079007 | S25: =Financials!Y38/Financials!Y5 -> 0.079152105 | T25: =Financials!Z38/Financials!Z5 -> 0.074726037 | U25: =Financials!AA38/Financials!AA5 -> 0.075383632 | V25: =Financials!AB38/Financials!AB5 -> 0.0744373 | W25: =Financials!AC38/Financials!AC5 -> 0.080664973 | X25: =Financials!AD38/Financials!AD5 -> 0.0797422 | ... DP25: =Financials!DV38/Financials!DV5 -> #DIV/0! | DQ25: =Financials!DX38/Financials!DX5 -> #DIV/0!
A28: RATING PARAMETERS | B28: CAPITAL | C28: CORE CAPITAL | D28: 10M | E28: 10M | F28: 10M | G28: 10M | H28: 10M | I28: 10M | J28: 10M | K28: 10M | L28: 10M | M28: 10M | N28: =IF(N4>10,1,5) -> 1 | O28: =IF(O4>10,1,5) -> 1 | P28: =IF(P4>10,1,5) -> 1 | Q28: =IF(Q4>10,1,5) -> 1 | R28: =IF(R4>10,1,5) -> 1 | S28: =IF(S4>10,1,5) -> 1 | T28: =IF(T4>10,1,5) -> 1 | U28: =IF(U4>10,1,5) -> 1 | ... W28: =IF(W4>10,1,5) -> 1 | AC28: =IF(AC4>10,1,5) -> 1
C29: CCA | D29: Min 10% | E29: Min 10% | F29: Min 10% | G29: Min 10% | H29: Min 10% | I29: Min 10% | J29: Min 10% | K29: Min 10% | L29: Min 10% | M29: Min 10% | N29: =IF(N5>20%,1,IF(N5>15,2,IF(N5>12,3,IF(N5>10,4,5)))) -> 1 | O29: =IF(O5>20%,1,IF(O5>15,2,IF(O5>12,3,IF(O5>10,4,5)))) -> 1 | P29: =IF(P5>20%,1,IF(P5>15,2,IF(P5>12,3,IF(P5>10,4,5)))) -> 1 | Q29: =IF(Q5>20%,1,IF(Q5>15,2,IF(Q5>12,3,IF(Q5>10,4,5)))) -> 1 | R29: =IF(R5>20%,1,IF(R5>15,2,IF(R5>12,3,IF(R5>10,4,5)))) -> 1 | S29: =IF(S5>20%,1,IF(S5>15,2,IF(S5>12,3,IF(S5>10,4,5)))) -> 1 | T29: =IF(T5>20%,1,IF(T5>15,2,IF(T5>12,3,IF(T5>10,4,5)))) -> 1 | U29: =IF(U5>20%,1,IF(U5>15,2,IF(U5>12,3,IF(U5>10,4,5)))) -> 1 | ... W29: =IF(W5>20%,1,IF(W5>15,2,IF(W5>12,3,IF(W5>10,4,5)))) -> 1 | AC29: =IF(AC5>20%,1,IF(AC5>15,2,IF(AC5>12,3,IF(AC5>10,4,5)))) -> 1 | AD29: =IF(AD5>20%,1,IF(AD5>15,2,IF(AD5>12,3,IF(AD5>10,4,5)))) -> 1
C30: ICA | D30: Min 8% | E30: Min 8% | F30: Min 8% | G30: Min 8% | H30: Min 8% | I30: Min 8% | J30: Min 8% | K30: Min 8% | L30: Min 8% | M30: Min 8% | N30: =IF(N6>15,1,IF(N6>12,2,IF(N6>10,3,IF(N6>8,4,5)))) -> 5 | O30: =IF(O6>15,1,IF(O6>12,2,IF(O6>10,3,IF(O6>8,4,5)))) -> 5 | P30: =IF(P6>15,1,IF(P6>12,2,IF(P6>10,3,IF(P6>8,4,5)))) -> 5 | Q30: =IF(Q6>15,1,IF(Q6>12,2,IF(Q6>10,3,IF(Q6>8,4,5)))) -> 5 | R30: =IF(R6>15,1,IF(R6>12,2,IF(R6>10,3,IF(R6>8,4,5)))) -> 5 | S30: =IF(S6>15,1,IF(S6>12,2,IF(S6>10,3,IF(S6>8,4,5)))) -> 5 | T30: =IF(T6>15,1,IF(T6>12,2,IF(T6>10,3,IF(T6>8,4,5)))) -> 5 | U30: =IF(U6>15,1,IF(U6>12,2,IF(U6>10,3,IF(U6>8,4,5)))) -> 5 | ... W30: =IF(W6>15,1,IF(W6>12,2,IF(W6>10,3,IF(W6>8,4,5)))) -> 5 | AC30: =IF(AC6>15,1,IF(AC6>12,2,IF(AC6>10,3,IF(AC6>8,4,5)))) -> 5 | AD30: =IF(AD6>15,1,IF(AD6>12,2,IF(AD6>10,3,IF(AD6>8,4,5)))) -> 5
C31: CCD | D31: Min 8% | E31: Min 8% | F31: Min 8% | G31: Min 8% | H31: Min 8% | I31: Min 8% | J31: Min 8% | K31: Min 8% | L31: Min 8% | M31: Min 8% | N31: =IF(N7>20%,1,IF(N7>12%,2,IF(N7>10%,3,IF(N7>8%,4,5)))) -> 1 | O31: =IF(O7>20%,1,IF(O7>12%,2,IF(O7>10%,3,IF(O7>8%,4,5)))) -> 1 | P31: =IF(P7>20%,1,IF(P7>12%,2,IF(P7>10%,3,IF(P7>8%,4,5)))) -> 1 | Q31: =IF(Q7>20%,1,IF(Q7>12%,2,IF(Q7>10%,3,IF(Q7>8%,4,5)))) -> 1 | R31: =IF(R7>20%,1,IF(R7>12%,2,IF(R7>10%,3,IF(R7>8%,4,5)))) -> 1 | S31: =IF(S7>20%,1,IF(S7>12%,2,IF(S7>10%,3,IF(S7>8%,4,5)))) -> 1 | T31: =IF(T7>20%,1,IF(T7>12%,2,IF(T7>10%,3,IF(T7>8%,4,5)))) -> 1 | U31: =IF(U7>20%,1,IF(U7>12%,2,IF(U7>10%,3,IF(U7>8%,4,5)))) -> 1 | ... W31: =IF(W7>20%,1,IF(W7>12%,2,IF(W7>10%,3,IF(W7>8%,4,5)))) -> 1 | AC31: =IF(AC7>20%,1,IF(AC7>12%,2,IF(AC7>10%,3,IF(AC7>8%,4,5)))) -> 1 | AD31: =IF(AD7>20%,1,IF(AD7>12%,2,IF(AD7>10%,3,IF(AD7>8%,4,5)))) -> 1
C32: Adjusted CCA | N32: =IF(N8>20%,1,IF(N8>15%,2,IF(N8>12%,3,IF(N8>10%,4,5)))) -> 1 | O32: =IF(O8>20%,1,IF(O8>15%,2,IF(O8>12%,3,IF(O8>10%,4,5)))) -> 1 | P32: =IF(P8>20%,1,IF(P8>15%,2,IF(P8>12%,3,IF(P8>10%,4,5)))) -> 1 | Q32: =IF(Q8>20%,1,IF(Q8>15%,2,IF(Q8>12%,3,IF(Q8>10%,4,5)))) -> 1 | R32: =IF(R8>20%,1,IF(R8>15%,2,IF(R8>12%,3,IF(R8>10%,4,5)))) -> 1 | S32: =IF(S8>20%,1,IF(S8>15%,2,IF(S8>12%,3,IF(S8>10%,4,5)))) -> 1 | T32: =IF(T8>20%,1,IF(T8>15%,2,IF(T8>12%,3,IF(T8>10%,4,5)))) -> 1 | U32: =IF(U8>20%,1,IF(U8>15%,2,IF(U8>12%,3,IF(U8>10%,4,5)))) -> 1 | ... W32: =IF(W8>20%,1,IF(W8>15%,2,IF(W8>12%,3,IF(W8>10%,4,5)))) -> 1 | AC32: =IF(AC8>20%,1,IF(AC8>15%,2,IF(AC8>12%,3,IF(AC8>10%,4,5)))) -> 1 | AD32: =IF(AD8>20%,1,IF(AD8>15%,2,IF(AD8>12%,3,IF(AD8>10%,4,5)))) -> 1
B34: ASSET QUALITY | C34: NPL30 | N34: =IF(N10<4,1,IF(N10<8,2,IF(N10<12,3,IF(N10<15,4,5)))) -> 1 | O34: =IF(O10<4,1,IF(O10<8,2,IF(O10<12,3,IF(O10<15,4,5)))) -> 1 | P34: =IF(P10<4,1,IF(P10<8,2,IF(P10<12,3,IF(P10<15,4,5)))) -> 1 | Q34: =IF(Q10<4,1,IF(Q10<8,2,IF(Q10<12,3,IF(Q10<15,4,5)))) -> 1 | R34: =IF(R10<4,1,IF(R10<8,2,IF(R10<12,3,IF(R10<15,4,5)))) -> 1 | S34: =IF(S10<4,1,IF(S10<8,2,IF(S10<12,3,IF(S10<15,4,5)))) -> 1 | T34: =IF(T10<4,1,IF(T10<8,2,IF(T10<12,3,IF(T10<15,4,5)))) -> 1 | U34: =IF(U10<4,1,IF(U10<8,2,IF(U10<12,3,IF(U10<15,4,5)))) -> 1 | ... W34: =IF(W10<4,1,IF(W10<8,2,IF(W10<12,3,IF(W10<15,4,5)))) -> 1 | AC34: =IF(AC10<4,1,IF(AC10<8,2,IF(AC10<12,3,IF(AC10<15,4,5)))) -> 1 | AD34: =IF(AD10<4,1,IF(AD10<8,2,IF(AD10<12,3,IF(AD10<15,4,5)))) -> 1
C35: A/L NPL30 | N35: =IF(N11<4,1,IF(N11<8,2,IF(N11<12,3,IF(N11<15,4,5)))) -> 1 | O35: =IF(O11<4,1,IF(O11<8,2,IF(O11<12,3,IF(O11<15,4,5)))) -> 1 | P35: =IF(P11<4,1,IF(P11<8,2,IF(P11<12,3,IF(P11<15,4,5)))) -> 1 | Q35: =IF(Q11<4,1,IF(Q11<8,2,IF(Q11<12,3,IF(Q11<15,4,5)))) -> 1 | R35: =IF(R11<4,1,IF(R11<8,2,IF(R11<12,3,IF(R11<15,4,5)))) -> 1 | S35: =IF(S11<4,1,IF(S11<8,2,IF(S11<12,3,IF(S11<15,4,5)))) -> 1 | T35: =IF(T11<4,1,IF(T11<8,2,IF(T11<12,3,IF(T11<15,4,5)))) -> 1 | U35: =IF(U11<4,1,IF(U11<8,2,IF(U11<12,3,IF(U11<15,4,5)))) -> 1 | ... W35: =IF(W11<4,1,IF(W11<8,2,IF(W11<12,3,IF(W11<15,4,5)))) -> 1 | AC35: =IF(AC11<4,1,IF(AC11<8,2,IF(AC11<12,3,IF(AC11<15,4,5)))) -> 1 | AD35: =IF(AD11<4,1,IF(AD11<8,2,IF(AD11<12,3,IF(AD11<15,4,5)))) -> 1
B37: EARNINGS | C37: ROA | N37: =IF(N17>6,1,IF(N17>4,2,IF(N17>2,3,IF(N17>0,4,5)))) -> #REF! | O37: =IF(O17>6,1,IF(O17>4,2,IF(O17>2,3,IF(O17>0,4,5)))) -> #REF! | P37: =IF(P17>6,1,IF(P17>4,2,IF(P17>2,3,IF(P17>0,4,5)))) -> #REF! | Q37: =IF(Q17>6,1,IF(Q17>4,2,IF(Q17>2,3,IF(Q17>0,4,5)))) -> 3 | R37: =IF(R17>6,1,IF(R17>4,2,IF(R17>2,3,IF(R17>0,4,5)))) -> 3 | S37: =IF(S17>6,1,IF(S17>4,2,IF(S17>2,3,IF(S17>0,4,5)))) -> 3 | T37: =IF(T17>6,1,IF(T17>4,2,IF(T17>2,3,IF(T17>0,4,5)))) -> 2 | U37: =IF(U17>6,1,IF(U17>4,2,IF(U17>2,3,IF(U17>0,4,5)))) -> 3 | ... W37: =IF(W17>6,1,IF(W17>4,2,IF(W17>2,3,IF(W17>0,4,5)))) -> 3 | AC37: =IF(AC17>6,1,IF(AC17>4,2,IF(AC17>2,3,IF(AC17>0,4,5)))) -> 4 | AD37: =IF(AD17>6,1,IF(AD17>4,2,IF(AD17>2,3,IF(AD17>0,4,5)))) -> 4
C38: C/I ratio | N38: =IF(N14<60,1,IF(N14<70,2,IF(N14<80,3,IF(N14<90,4,5)))) -> 1 | O38: =IF(O14<60,1,IF(O14<70,2,IF(O14<80,3,IF(O14<90,4,5)))) -> 1 | P38: =IF(P14<60,1,IF(P14<70,2,IF(P14<80,3,IF(P14<90,4,5)))) -> #REF! | Q38: =IF(Q14<60,1,IF(Q14<70,2,IF(Q14<80,3,IF(Q14<90,4,5)))) -> 1 | R38: =IF(R14<60,1,IF(R14<70,2,IF(R14<80,3,IF(R14<90,4,5)))) -> 1 | S38: =IF(S14<60,1,IF(S14<70,2,IF(S14<80,3,IF(S14<90,4,5)))) -> 1 | T38: =IF(T14<60,1,IF(T14<70,2,IF(T14<80,3,IF(T14<90,4,5)))) -> 1 | U38: =IF(U14<60,1,IF(U14<70,2,IF(U14<80,3,IF(U14<90,4,5)))) -> 1 | ... W38: =IF(W14<60,1,IF(W14<70,2,IF(W14<80,3,IF(W14<90,4,5)))) -> 1 | AC38: =IF(AC14<60,1,IF(AC14<70,2,IF(AC14<80,3,IF(AC14<90,4,5)))) -> 1 | AD38: =IF(AD14<60,1,IF(AD14<70,2,IF(AD14<80,3,IF(AD14<90,4,5)))) -> 1
C39: OE ratio | N39: =IF(N15<4,1,IF(N15<6,2,IF(N15<8,3,IF(N15<10,4,5)))) -> #REF! | O39: =IF(O15<4,1,IF(O15<6,2,IF(O15<8,3,IF(O15<10,4,5)))) -> #REF! | P39: =IF(P15<4,1,IF(P15<6,2,IF(P15<8,3,IF(P15<10,4,5)))) -> #REF! | Q39: =IF(Q15<4,1,IF(Q15<6,2,IF(Q15<8,3,IF(Q15<10,4,5)))) -> 1 | R39: =IF(R15<4,1,IF(R15<6,2,IF(R15<8,3,IF(R15<10,4,5)))) -> 1 | S39: =IF(S15<4,1,IF(S15<6,2,IF(S15<8,3,IF(S15<10,4,5)))) -> 1 | T39: =IF(T15<4,1,IF(T15<6,2,IF(T15<8,3,IF(T15<10,4,5)))) -> 1 | U39: =IF(U15<4,1,IF(U15<6,2,IF(U15<8,3,IF(U15<10,4,5)))) -> 1 | ... W39: =IF(W15<4,1,IF(W15<6,2,IF(W15<8,3,IF(W15<10,4,5)))) -> 1 | AC39: =IF(AC15<4,1,IF(AC15<6,2,IF(AC15<8,3,IF(AC15<10,4,5)))) -> 1 | AD39: =IF(AD15<4,1,IF(AD15<6,2,IF(AD15<8,3,IF(AD15<10,4,5)))) -> 1
B41: LIQUIDITY | C41: W NLIQ ratio | D41: Min 15% | E41: Min 15% | F41: Min 15% | G41: Min 15% | H41: Min 15% | I41: Min 15% | J41: Min 15% | K41: Min 15% | L41: Min 15% | M41: Min 15% | N41: =IF(N17>30,1,IF(N17>25,2,IF(N17>20,3,IF(N17>15,4,5)))) -> #REF! | O41: =IF(O17>30,1,IF(O17>25,2,IF(O17>20,3,IF(O17>15,4,5)))) -> #REF! | P41: =IF(P17>30,1,IF(P17>25,2,IF(P17>20,3,IF(P17>15,4,5)))) -> #REF! | Q41: =IF(Q17>30,1,IF(Q17>25,2,IF(Q17>20,3,IF(Q17>15,4,5)))) -> 5 | R41: =IF(R17>30,1,IF(R17>25,2,IF(R17>20,3,IF(R17>15,4,5)))) -> 5 | S41: =IF(S17>30,1,IF(S17>25,2,IF(S17>20,3,IF(S17>15,4,5)))) -> 5 | T41: =IF(T17>30,1,IF(T17>25,2,IF(T17>20,3,IF(T17>15,4,5)))) -> 5 | U41: =IF(U17>30,1,IF(U17>25,2,IF(U17>20,3,IF(U17>15,4,5)))) -> 5 | ... W41: =IF(W17>30,1,IF(W17>25,2,IF(W17>20,3,IF(W17>15,4,5)))) -> 5 | AC41: =IF(AC17>30,1,IF(AC17>25,2,IF(AC17>20,3,IF(AC17>15,4,5)))) -> 5 | AD41: =IF(AD17>30,1,IF(AD17>25,2,IF(AD17>20,3,IF(AD17>15,4,5)))) -> 5
C42: T NLIQ ratio | N42: =IF(N18>30,1,IF(N18>25,2,IF(N18>20,3,IF(N18>15,4,5)))) -> #REF! | O42: =IF(O18>30,1,IF(O18>25,2,IF(O18>20,3,IF(O18>15,4,5)))) -> #REF! | P42: =IF(P18>30,1,IF(P18>25,2,IF(P18>20,3,IF(P18>15,4,5)))) -> #REF! | Q42: =IF(Q18>30,1,IF(Q18>25,2,IF(Q18>20,3,IF(Q18>15,4,5)))) -> 5 | R42: =IF(R18>30,1,IF(R18>25,2,IF(R18>20,3,IF(R18>15,4,5)))) -> 5 | S42: =IF(S18>30,1,IF(S18>25,2,IF(S18>20,3,IF(S18>15,4,5)))) -> 5 | T42: =IF(T18>30,1,IF(T18>25,2,IF(T18>20,3,IF(T18>15,4,5)))) -> 5 | U42: =IF(U18>30,1,IF(U18>25,2,IF(U18>20,3,IF(U18>15,4,5)))) -> 5 | ... W42: =IF(W18>30,1,IF(W18>25,2,IF(W18>20,3,IF(W18>15,4,5)))) -> 5 | AC42: =IF(AC18>30,1,IF(AC18>25,2,IF(AC18>20,3,IF(AC18>15,4,5)))) -> 5 | AD42: =IF(AD18>30,1,IF(AD18>25,2,IF(AD18>20,3,IF(AD18>15,4,5)))) -> 5
