Workbook

Sheet CAELS
A1: WANANCHI SACCO CAELS
D2: 2010 Audited | E2: 2017Audited | F2: 43102 | G2: 43132 | H2: 43162 | I2: 43192 | J2: 43222 | K2: 43253 | L2: 43283 | M2: 43314 | N2: 43345 | O2: 43375 | P2: 43406 | Q2: 43436 | R2: Audited 2018 | S2: 43469 | T2: 43501 | U2: 43530 | V2: 43562 | W2: 43593 | X2: 43625 | Y2: 43656 | Z2: 43688 | AA2: 43720 | AB2: 43751 | AC2: 43783 | AD2: 43814 | AE2: AUDITED 2019 | AF2: 43847 | AG2: 43879 | AH2: 43909 | AI2: 43941 | AJ2: 43972 | AK2: 44004 | AL2: 44066 | AM2: 44098 | AN2: 44129 | AO2: 44161 | AP2: 44192 | AQ2: AUDITED 2020 | AR2: 44197 | AS2: 44228 | AT2: 44256 | AU2: 44287 | AV2: 44317 | AW2: 44348 | AX2: 44378 | AY2: 44409 | AZ2: 44440 | BA2: 44470 | BB2: 44501 | BC2: 44531 | BD2: Audited 2021 | BE2: 44562 | BF2: 44593 | BG2: 44621 | BH2: 44652 | BI2: 44682 | BJ2: 44713 | BK2: 44743 | BL2: 44774 | BM2: 44805 | BN2: 44835 | BO2: 44866 | BP2: 44896 | BQ2: Audited 2022
A3: CAPITAL ADEQUACY | B3: Core Capital | C3: 10 M | D3: =(('Evolutive SFP'!B39+'Evolutive SFP'!B40+'Evolutive SFP'!B41+'Evolutive SFP'!B42+'Evolutive SFP'!B43+'Evolutive SFP'!B44)-'Evolutive SFP'!B10)/1000000 -> 15.259572 | E3: =(('Evolutive SFP'!C39+'Evolutive SFP'!C40+'Evolutive SFP'!C41+'Evolutive SFP'!C42+'Evolutive SFP'!C43+'Evolutive SFP'!C44)-'Evolutive SFP'!C10)/1000000 -> 251.79176 | F3: =(('Evolutive SFP'!D39+'Evolutive SFP'!D40+'Evolutive SFP'!D41+'Evolutive SFP'!D42+'Evolutive SFP'!D43+'Evolutive SFP'!D44)-'Evolutive SFP'!D7)/1000000 -> 170.66799 | G3: =(('Evolutive SFP'!E39+'Evolutive SFP'!E40+'Evolutive SFP'!E41+'Evolutive SFP'!E42+'Evolutive SFP'!E43+'Evolutive SFP'!E44)-'Evolutive SFP'!E10)/1000000 -> 221.85869 | H3: =(('Evolutive SFP'!F39+'Evolutive SFP'!F40+'Evolutive SFP'!F41+'Evolutive SFP'!F42+'Evolutive SFP'!F43+'Evolutive SFP'!F44)-'Evolutive SFP'!F10)/1000000 -> 223.40524 | I3: =(('Evolutive SFP'!G39+'Evolutive SFP'!G40+'Evolutive SFP'!G41+'Evolutive SFP'!G42+'Evolutive SFP'!G43+'Evolutive SFP'!G44)-'Evolutive SFP'!G10)/1000000 -> 222.62504 | J3: =(('Evolutive SFP'!H39+'Evolutive SFP'!H40+'Evolutive SFP'!H41+'Evolutive SFP'!H42+'Evolutive SFP'!H43+'Evolutive SFP'!H44)-'Evolutive SFP'!H10)/1000000 -> 221.56982 | K3: =(('Evolutive SFP'!I39+'Evolutive SFP'!I40+'Evolutive SFP'!I41+'Evolutive SFP'!I42+'Evolutive SFP'!I43+'Evolutive SFP'!I44)-'Evolutive SFP'!I10)/1000000 -> 222.46421 | L3: =(('Evolutive SFP'!J39+'Evolutive SFP'!J40+'Evolutive SFP'!J41+'Evolutive SFP'!J42+'Evolutive SFP'!J43+'Evolutive SFP'!J44)-'Evolutive SFP'!J10)/1000000 -> 223.2454 | M3: =(('Evolutive SFP'!K39+'Evolutive SFP'!K40+'Evolutive SFP'!K41+'Evolutive SFP'!K42+'Evolutive SFP'!K43+'Evolutive SFP'!K44)-'Evolutive SFP'!K10)/1000000 -> 229.84013 | N3: =(('Evolutive SFP'!L39+'Evolutive SFP'!L40+'Evolutive SFP'!L41+'Evolutive SFP'!L42+'Evolutive SFP'!L43+'Evolutive SFP'!L44)-'Evolutive SFP'!L10)/1000000 -> 230.21143 | ... BJ3: =(('Evolutive SFP'!BH39+'Evolutive SFP'!BH40+'Evolutive SFP'!BH41+'Evolutive SFP'!BH42+'Evolutive SFP'!BH43+'Evolutive SFP'!BH44)-'Evolutive SFP'!BH10)/1000000 -> 340.57863 | BK3: =(('Evolutive SFP'!BI41+'Evolutive SFP'!BI42+'Evolutive SFP'!BI43+'Evolutive SFP'!BI44+'Evolutive SFP'!BI45+'Evolutive SFP'!BI46)-'Evolutive SFP'!BI10)/1000000 -> 171.55244 | BL3: =(('Evolutive SFP'!BJ39+'Evolutive SFP'!BJ40+'Evolutive SFP'!BJ41+'Evolutive SFP'!BJ42+'Evolutive SFP'!BJ43+'Evolutive SFP'!BJ44)-'Evolutive SFP'!BJ10)/1000000 -> 347.66961 | BM3: =(('Evolutive SFP'!BK41+'Evolutive SFP'!BK42+'Evolutive SFP'!BK43+'Evolutive SFP'!BK44+'Evolutive SFP'!BK45+'Evolutive SFP'!BK46)-'Evolutive SFP'!BK10)/1000000 -> 172.30637 | BN3: =(('Evolutive SFP'!BL39+'Evolutive SFP'!BL40+'Evolutive SFP'!BL41+'Evolutive SFP'!BL42+'Evolutive SFP'!BL43+'Evolutive SFP'!BL44)-'Evolutive SFP'!BL10)/1000000 -> 352.73593 | BO3: =(('Evolutive SFP'!BM41+'Evolutive SFP'!BM42+'Evolutive SFP'!BM43+'Evolutive SFP'!BM44+'Evolutive SFP'!BM45+'Evolutive SFP'!BM46)-'Evolutive SFP'!BM10)/1000000 -> 176.60764 | BP3: =(('Evolutive SFP'!BN39+'Evolutive SFP'!BN40+'Evolutive SFP'!BN41+'Evolutive SFP'!BN42+'Evolutive SFP'!BN43+'Evolutive SFP'!BN44)-'Evolutive SFP'!BN10)/1000000 -> 349.91057 | BQ3: =(('Evolutive SFP'!BO41+'Evolutive SFP'!BO42+'Evolutive SFP'!BO43+'Evolutive SFP'!BO44+'Evolutive SFP'!BO45+'Evolutive SFP'!BO46)-'Evolutive SFP'!BO10)/1000000 -> 187.43404
B4: CCA | C4: Min 10% | D4: =D3/(('Evolutive SFP'!B27)/1000000) -> 0.10104624 | E4: =E3/(('Evolutive SFP'!C27)/1000000) -> 0.21922583 | F4: =F3/(('Evolutive SFP'!D27)/1000000) -> 0.15299794 | G4: =G3/(('Evolutive SFP'!E27)/1000000) -> 0.20215401 | H4: =H3/(('Evolutive SFP'!F27)/1000000) -> 0.20775171 | I4: =I3/(('Evolutive SFP'!G27)/1000000) -> 0.19567783 | J4: =J3/(('Evolutive SFP'!H27)/1000000) -> 0.19571582 | K4: =K3/(('Evolutive SFP'!I27)/1000000) -> 0.19453998 | ... BI4: =BI3/(('Evolutive SFP'!BG27)/1000000) -> 0.25102481 | BJ4: =Financials!BI11/Financials!BI4 -> 0.25092286 | BK4: =Financials!BJ11/Financials!BJ4 -> 0.21958432 | BL4: =Financials!BK11/Financials!BK4 -> 0.22862575 | BM4: =Financials!BL11/Financials!BL4 -> 0.23757125 | BN4: =Financials!BM11/Financials!BM4 -> 0.24281241 | BO4: =Financials!BN11/Financials!BN4 -> 0.24838093 | BP4: =Financials!BO11/Financials!BO4 -> 0.24620519 | BQ4: =Financials!BP11/Financials!BP4 -> 0.26574195
B5: CCD | C5: Min 8% | D5: =D3/('Evolutive SFP'!B31/1000000) -> 0.1186553 | E5: =E3/('Evolutive SFP'!C31/1000000) -> 0.29544775 | F5: =F3/('Evolutive SFP'!D31/1000000) -> 0.21047716 | G5: =G3/('Evolutive SFP'!E31/1000000) -> 0.27916029 | H5: =H3/('Evolutive SFP'!F31/1000000) -> 0.28572414 | I5: =I3/('Evolutive SFP'!G31/1000000) -> 0.27913395 | J5: =J3/('Evolutive SFP'!H31/1000000) -> 0.2814719 | K5: =K3/('Evolutive SFP'!I31/1000000) -> 0.27975309 | ... BQ5: =BQ3/('Evolutive SFP'!BO31/1000000) -> 0.20045901
B6: ICA | C6: Min 8% | D6: =((D3*1000000)-'Evolutive SFP'!B39)/'Evolutive SFP'!B27 -> 0.031552177 | E6: =((E3*1000000)-'Evolutive SFP'!C39)/'Evolutive SFP'!C27 -> 0.096753597 | F6: =((F3*1000000)-'Evolutive SFP'!D39)/'Evolutive SFP'!D27 -> 0.026368283 | G6: =((G3*1000000)-'Evolutive SFP'!E39)/'Evolutive SFP'!E27 -> 0.072949335 | H6: =((H3*1000000)-'Evolutive SFP'!F39)/'Evolutive SFP'!F27 -> 0.075317512 | I6: =((I3*1000000)-'Evolutive SFP'!G39)/'Evolutive SFP'!G27 -> 0.069989079 | J6: =((J3*1000000)-'Evolutive SFP'!H39)/'Evolutive SFP'!H27 -> 0.068829705 | K6: =((K3*1000000)-'Evolutive SFP'!I39)/'Evolutive SFP'!I27 -> 0.068401179 | ... BI6: =((BI3*1000000)-'Evolutive SFP'!BG39)/'Evolutive SFP'!BG27 -> 0.097383349 | BJ6: =Financials!BI12/Financials!BI4 -> 0.097377175 | BK6: =Financials!BJ12/Financials!BJ4 -> 0.08488405 | BL6: =Financials!BK12/Financials!BK4 -> 0.088293115 | BM6: =Financials!BL12/Financials!BL4 -> 0.091710134 | BN6: =Financials!BM12/Financials!BM4 -> 0.094757305 | BO6: =Financials!BN12/Financials!BN4 -> 0.097240244 | BP6: =Financials!BO12/Financials!BO4 -> 0.093434303 | BQ6: =Financials!BP12/Financials!BP4 -> 0.10851981
A7: ASSET QUALITY | B7: A/LNPL30
B8: NPL30 | H8: =('FORM 4'!D5+'FORM 4'!D6+'FORM 4'!D7)/'Evolutive SFP'!F15 -> 0.1787696 | K8: =('FORM 4'!D14+'FORM 4'!D15+'FORM 4'!D16)/'Evolutive SFP'!I15 -> 0.22772293 | N8: =('FORM 4'!D23+'FORM 4'!D24+'FORM 4'!D25)/'Evolutive SFP'!L15 -> 0.2237177 | O8: =('FORM 4'!F5+'FORM 4'!F6+'FORM 4'!F7)/'Evolutive SFP'!M15 -> 0.21153621 | P8: =('FORM 4'!G5+'FORM 4'!G6+'FORM 4'!G7)/'Evolutive SFP'!N15 -> 0 | Q8: =('FORM 4'!D32+'FORM 4'!D33+'FORM 4'!D34)/'Evolutive SFP'!O15 -> 0.24478584 | R8: 0.24 | S8: =('FORM 4'!F32+'FORM 4'!F33+'FORM 4'!F34)/'Evolutive SFP'!Q15 -> 0.20539278 | T8: =('FORM 4'!G32+'FORM 4'!G33+'FORM 4'!G34)/'Evolutive SFP'!R15 -> 0 | U8: =('FORM 4'!H32+'FORM 4'!H33+'FORM 4'!H34)/'Evolutive SFP'!S15 -> 0 | V8: =('FORM 4'!I32+'FORM 4'!I33+'FORM 4'!I34)/'Evolutive SFP'!T15 -> 0 | W8: =('FORM 4'!J32+'FORM 4'!J33+'FORM 4'!J34)/'Evolutive SFP'!U15 -> 0 | X8: =('FORM 4'!K32+'FORM 4'!K33+'FORM 4'!K34)/'Evolutive SFP'!V15 -> 0 | Y8: =('FORM 4'!L32+'FORM 4'!L33+'FORM 4'!L34)/'Evolutive SFP'!W15 -> 0 | Z8: =('FORM 4'!M32+'FORM 4'!M33+'FORM 4'!M34)/'Evolutive SFP'!X15 -> 0 | ... AD8: =('FORM 4'!Q32+'FORM 4'!Q33+'FORM 4'!Q34)/'Evolutive SFP'!AB15 -> 0 | AE8: 0.22 | AF8: =('FORM 4'!S32+'FORM 4'!S33+'FORM 4'!S34)/'Evolutive SFP'!AD15 -> 0 | AH8: =('FORM 4'!D99+'FORM 4'!D100+'FORM 4'!D101)/'Evolutive SFP'!AF15 -> 0.21548708 | AK8: =('FORM 4'!D108+'FORM 4'!D109+'FORM 4'!D110)/'Evolutive SFP'!AI15 -> 0.22964994 | AQ8: 0.31 | BD8: 0.32 | BP8: 0.33 | BQ8: 0.33
A9: EARNINGS | B9: ROA | E9: ='Evolutitve SCI'!C33/(('Evolutive SFP'!B27+'Evolutive SFP'!C27)/2) -> 0.019523279 | F9: ='Evolutitve SCI'!D33/(('Evolutive SFP'!C27+'Evolutive SFP'!D24)/2) -> 0.016250527 | G9: ='Evolutitve SCI'!E33/(('Evolutive SFP'!D24+'Evolutive SFP'!E27)/2) -> 0.011846915 | H9: ='Evolutitve SCI'!F33/(('Evolutive SFP'!E27+'Evolutive SFP'!F27)/2) -> 0.0068453599 | I9: ='Evolutitve SCI'!G33/(('Evolutive SFP'!F27+'Evolutive SFP'!G27)/2) -> 0.0054872561 | J9: ='Evolutitve SCI'!H33/(('Evolutive SFP'!G14+'Evolutive SFP'!H27)/2) -> 0.0034934452 | K9: ='Evolutitve SCI'!I33/(('Evolutive SFP'!H27+'Evolutive SFP'!I27)/2) -> 0.0040989427 | L9: ='Evolutitve SCI'!J33/(('Evolutive SFP'!I27+'Evolutive SFP'!J27)/2) -> 0.0043464169 | M9: ='Evolutitve SCI'!K33/(('Evolutive SFP'!J27+'Evolutive SFP'!K27)/2) -> 0.0097450994 | N9: ='Evolutitve SCI'!L33/(('Evolutive SFP'!K27+'Evolutive SFP'!L27)/2) -> 0.0092186265 | O9: ='Evolutitve SCI'!M33/(('Evolutive SFP'!L27+'Evolutive SFP'!M27)/2) -> 0.011066532 | P9: ='Evolutitve SCI'!N33/(('Evolutive SFP'!M27+'Evolutive SFP'!N27)/2) -> 0.011602885 | Q9: ='Evolutitve SCI'!O33/(('Evolutive SFP'!N27+'Evolutive SFP'!O27)/2) -> 0.018245322 | R9: ='Evolutitve SCI'!P33/(('Evolutive SFP'!O27+'Evolutive SFP'!P27)/2) -> 0.01805693 | ... AC9: ='Evolutitve SCI'!AA33/(('Evolutive SFP'!Z27+'Evolutive SFP'!AA27)/2) -> 0.0056100663 | AD9: ='Evolutitve SCI'!#REF!/(('Evolutive SFP'!AA27+'Evolutive SFP'!AB27)/2) -> #REF! | AE9: ='Evolutitve SCI'!AC33/(('Evolutive SFP'!AB27+'Evolutive SFP'!AC27)/2) -> 0.012295926 | AF9: ='Evolutitve SCI'!AD33/(('Evolutive SFP'!AC27+'Evolutive SFP'!AD27)/2) -> 0.00330105 | AG9: ='Evolutitve SCI'!AE33/(('Evolutive SFP'!AD27+'Evolutive SFP'!AE27)/2) -> 0.0023987892 | AH9: ='Evolutitve SCI'!AF33/(('Evolutive SFP'!AE27+'Evolutive SFP'!AF27)/2) -> 0.0016206315 | AI9: ='Evolutitve SCI'!AG33/(('Evolutive SFP'!AF27+'Evolutive SFP'!AG27)/2) -> 0.0031755642 | AJ9: ='Evolutitve SCI'!AH33/(('Evolutive SFP'!AG27+'Evolutive SFP'!AH27)/2) -> 0.0033762799 | AK9: ='Evolutitve SCI'!AI33/(('Evolutive SFP'!AH27+'Evolutive SFP'!AI27)/2) -> 0.0048861222 | AL9: ='Evolutitve SCI'!AJ33/(('Evolutive SFP'!AI27+'Evolutive SFP'!AJ27)/2) -> 0.0078607831 | ... BQ9: ='Evolutitve SCI'!BO33/(('Evolutive SFP'!BN27+'Evolutive SFP'!BO27)/2) -> 0.020747704
B10: Cost Income ratio | D10: ='Evolutitve SCI'!B23/'Evolutitve SCI'!B19 -> 0.78428841 | E10: ='Evolutitve SCI'!C23/'Evolutitve SCI'!C19 -> 0.81638811 | F10: ='Evolutitve SCI'!D23/'Evolutitve SCI'!D19 -> 0.43574848 | G10: ='Evolutitve SCI'!E23/'Evolutitve SCI'!E19 -> 0.64340473 | H10: ='Evolutitve SCI'!F23/'Evolutitve SCI'!F19 -> 0.69451785 | I10: ='Evolutitve SCI'!G23/'Evolutitve SCI'!G19 -> 0.7501933 | J10: ='Evolutitve SCI'!H23/'Evolutitve SCI'!H19 -> 0.7952059 | K10: ='Evolutitve SCI'!I23/'Evolutitve SCI'!I19 -> 0.80144187 | ... AC10: ='Evolutitve SCI'!AA23/'Evolutitve SCI'!AA19 -> 0.75898885 | AD10: ='Evolutitve SCI'!#REF!/'Evolutitve SCI'!#REF! -> #REF! | AE10: ='Evolutitve SCI'!AC23/'Evolutitve SCI'!AC19 -> 0.85016836 | AF10: ='Evolutitve SCI'!AD23/'Evolutitve SCI'!AD19 -> 0.66463853 | AG10: ='Evolutitve SCI'!AE23/'Evolutitve SCI'!AE19 -> 0.79162284 | AH10: ='Evolutitve SCI'!AF23/'Evolutitve SCI'!AF19 -> 0.83079923 | AI10: ='Evolutitve SCI'!AG23/'Evolutitve SCI'!AG19 -> 0.80132628 | AJ10: ='Evolutitve SCI'!AH23/'Evolutitve SCI'!AH19 -> 0.7997106 | AK10: ='Evolutitve SCI'!AI23/'Evolutitve SCI'!AI19 -> 0.78401721 | AL10: ='Evolutitve SCI'!AJ23/'Evolutitve SCI'!AJ19 -> 0.78597285 | ... BQ10: ='Evolutitve SCI'!BO23/'Evolutitve SCI'!BO19 -> 0.7310578
B11: Operating Expense ratio | D11: =('Evolutitve SCI'!B23+'Evolutitve SCI'!B12)/(('Evolutive SFP'!B27+'Evolutive SFP'!C27)/2) -> 1.780359e-05 | E11: =('Evolutitve SCI'!C23+'Evolutitve SCI'!C12)/(('Evolutive SFP'!C27+'Evolutive SFP'!D24)/2) -> 0.29111614 | F11: =('Evolutitve SCI'!D23+'Evolutitve SCI'!D12)/(('Evolutive SFP'!D24+'Evolutive SFP'!E27)/2) -> 0.017077852 | G11: =('Evolutitve SCI'!E23+'Evolutitve SCI'!E12)/(('Evolutive SFP'!E27+'Evolutive SFP'!F27)/2) -> 0.020493816 | H11: =('Evolutitve SCI'!F23+'Evolutitve SCI'!F12)/(('Evolutive SFP'!F27+'Evolutive SFP'!G14)/2) -> 0.039794797 | I11: =('Evolutitve SCI'!G23+'Evolutitve SCI'!G12)/(('Evolutive SFP'!G27+'Evolutive SFP'!H14)/2) -> 0.053209706 | J11: =('Evolutitve SCI'!H23+'Evolutitve SCI'!H12)/(('Evolutive SFP'!H27+'Evolutive SFP'!I27)/2) -> 0.055351703 | K11: =('Evolutitve SCI'!I23+'Evolutitve SCI'!I12)/(('Evolutive SFP'!I27+'Evolutive SFP'!J27)/2) -> 0.067396876 | L11: =('Evolutitve SCI'!J23+'Evolutitve SCI'!J12)/(('Evolutive SFP'!J27+'Evolutive SFP'!K27)/2) -> 0.079615125 | M11: =('Evolutitve SCI'!K23+'Evolutitve SCI'!K12)/(('Evolutive SFP'!K27+'Evolutive SFP'!L27)/2) -> 0.092267964 | N11: =('Evolutitve SCI'!L23+'Evolutitve SCI'!L12)/(('Evolutive SFP'!L27+'Evolutive SFP'!M27)/2) -> 0.090233951 | O11: =('Evolutitve SCI'!M23+'Evolutitve SCI'!M12)/(('Evolutive SFP'!M27+'Evolutive SFP'!N27)/2) -> 0.093664394 | P11: =('Evolutitve SCI'!N23+'Evolutitve SCI'!N12)/(('Evolutive SFP'!N27+'Evolutive SFP'!O27)/2) -> 0.11349845 | Q11: =('Evolutitve SCI'!O23+'Evolutitve SCI'!O12)/(('Evolutive SFP'!O27+'Evolutive SFP'!P27)/2) -> 0.12735612 | ... AC11: =('Evolutitve SCI'!AA23+'Evolutitve SCI'!AA12)/(('Evolutive SFP'!AA27+'Evolutive SFP'!AB27)/2) -> 0.056252928 | AD11: =('Evolutitve SCI'!#REF!+'Evolutitve SCI'!#REF!)/(('Evolutive SFP'!AB27+'Evolutive SFP'!AC27)/2) -> #REF! | AE11: =('Evolutitve SCI'!AC23+'Evolutitve SCI'!AC12)/(('Evolutive SFP'!AC27+'Evolutive SFP'!AD27)/2) -> 0.15343163 | AF11: =('Evolutitve SCI'!AD23+'Evolutitve SCI'!AD12)/(('Evolutive SFP'!AD27+'Evolutive SFP'!AE27)/2) -> 0.0090367067 | AG11: =('Evolutitve SCI'!AE23+'Evolutitve SCI'!AE12)/(('Evolutive SFP'!AE27+'Evolutive SFP'!AF27)/2) -> 0.022250112 | AH11: =('Evolutitve SCI'!AF23+'Evolutitve SCI'!AF12)/(('Evolutive SFP'!AF27+'Evolutive SFP'!AG27)/2) -> 0.033644018 | AI11: =('Evolutitve SCI'!AG23+'Evolutitve SCI'!AG12)/(('Evolutive SFP'!AG27+'Evolutive SFP'!AH27)/2) -> 0.042408299 | AJ11: =('Evolutitve SCI'!AH23+'Evolutitve SCI'!AH12)/(('Evolutive SFP'!AH27+'Evolutive SFP'!AI27)/2) -> 0.050973763 | AK11: =('Evolutitve SCI'!AI23+'Evolutitve SCI'!AI12)/(('Evolutive SFP'!AI27+'Evolutive SFP'!AJ27)/2) -> 0.040122255 | AL11: =('Evolutitve SCI'!AJ23+'Evolutitve SCI'!AJ12)/(('Evolutive SFP'!AJ27+'Evolutive SFP'!AK27)/2) -> 0.10770697 | ... AZ11: =('Evolutitve SCI'!AX23+'Evolutitve SCI'!AX12)/(('Evolutive SFP'!AX27+'Evolutive SFP'!AY27)/2) -> 0.090233211 | BA11: =('Evolutitve SCI'!AY23+'Evolutitve SCI'!AY12)/(('Evolutive SFP'!AY27+'Evolutive SFP'!AZ28)/2) -> 0.1422929 | BB11: =('Evolutitve SCI'!AZ23+'Evolutitve SCI'!AZ12)/(('Evolutive SFP'!AZ27+'Evolutive SFP'!BA28)/2) -> 0.15830138 | BC11: =('Evolutitve SCI'!BA23+'Evolutitve SCI'!BA12)/(('Evolutive SFP'!BA27+'Evolutive SFP'!BB28)/2) -> 0.18900127 | BD11: =('Evolutitve SCI'!BB23+'Evolutitve SCI'!BB12)/(('Evolutive SFP'!BB27+'Evolutive SFP'!BC28)/2) -> 0.17969284 | BE11: =('Evolutitve SCI'!BC23+'Evolutitve SCI'!BC12)/(('Evolutive SFP'!BC27+'Evolutive SFP'!BD28)/2) -> 0.016625781 | BF11: =('Evolutitve SCI'!BD23+'Evolutitve SCI'!BD12)/(('Evolutive SFP'!BD27+'Evolutive SFP'!BE28)/2) -> 0.032079427 | BG11: =('Evolutitve SCI'!BE23+'Evolutitve SCI'!BE12)/(('Evolutive SFP'!BE27+'Evolutive SFP'!BF28)/2) -> 0.052587723 | BH11: =('Evolutitve SCI'!BF23+'Evolutitve SCI'!BF12)/(('Evolutive SFP'!BF27+'Evolutive SFP'!BG28)/2) -> 0.067655172 | ... BQ11: =('Evolutitve SCI'!BO23+'Evolutitve SCI'!BO12)/(('Evolutive SFP'!BO27+'Evolutive SFP'!BP28)/2) -> 0.27192475
A12: LIQUIDITY | B12: MIN LIQ ratio | C12: Min 15% | D12: =('Evolutive SFP'!B4)/('Evolutive SFP'!B28+'Evolutive SFP'!B29+'Evolutive SFP'!B32+'Evolutive SFP'!B33+'Evolutive SFP'!B34+'Evolutive SFP'!B35+'Evolutive SFP'!B36) -> 0.90806632 | E12: =('Evolutive SFP'!C4)/('Evolutive SFP'!C28+'Evolutive SFP'!C29+'Evolutive SFP'!C32+'Evolutive SFP'!C33+'Evolutive SFP'!C34+'Evolutive SFP'!C35+'Evolutive SFP'!C36) -> 0.23568422 | F12: =('Evolutive SFP'!D4)/('Evolutive SFP'!D28+'Evolutive SFP'!D29+'Evolutive SFP'!D32+'Evolutive SFP'!D33+'Evolutive SFP'!D34+'Evolutive SFP'!D35+'Evolutive SFP'!D36) -> 0.39483664 | G12: =('Evolutive SFP'!E4)/('Evolutive SFP'!E28+'Evolutive SFP'!E29+'Evolutive SFP'!E32+'Evolutive SFP'!E33+'Evolutive SFP'!E34+'Evolutive SFP'!E35+'Evolutive SFP'!E36) -> 0.37670937 | H12: =('Evolutive SFP'!F4)/('Evolutive SFP'!F28+'Evolutive SFP'!F29+'Evolutive SFP'!F32+'Evolutive SFP'!F33+'Evolutive SFP'!F34+'Evolutive SFP'!F35+'Evolutive SFP'!F36) -> 0.33875077 | I12: =('Evolutive SFP'!G4)/('Evolutive SFP'!G28+'Evolutive SFP'!G29+'Evolutive SFP'!G32+'Evolutive SFP'!G33+'Evolutive SFP'!G34+'Evolutive SFP'!G35+'Evolutive SFP'!G36) -> 0.45616628 | J12: =('Evolutive SFP'!H4)/('Evolutive SFP'!H28+'Evolutive SFP'!H29+'Evolutive SFP'!H32+'Evolutive SFP'!H33+'Evolutive SFP'!H34+'Evolutive SFP'!H35+'Evolutive SFP'!H36) -> 0.44162502 | K12: =('Evolutive SFP'!I4)/('Evolutive SFP'!I28+'Evolutive SFP'!I29+'Evolutive SFP'!I32+'Evolutive SFP'!I33+'Evolutive SFP'!I34+'Evolutive SFP'!I35+'Evolutive SFP'!I36) -> 0.47501917 | ... BQ12: =('Evolutive SFP'!BO4)/('Evolutive SFP'!BO28+'Evolutive SFP'!BO29+'Evolutive SFP'!BO32+'Evolutive SFP'!BO33+'Evolutive SFP'!BO34+'Evolutive SFP'!BO35+'Evolutive SFP'!BO36) -> 0.67297791
B13: T/LIQ ratio | D13: ='Evolutive SFP'!B4/('Evolutive SFP'!B31+'Evolutive SFP'!B36) -> 0.14915539 | E13: ='Evolutive SFP'!C4/('Evolutive SFP'!C31+'Evolutive SFP'!C36) -> 0.16596351 | F13: ='Evolutive SFP'!D4/('Evolutive SFP'!D31+'Evolutive SFP'!D36) -> 0.26874622 | G13: ='Evolutive SFP'!E4/('Evolutive SFP'!E31+'Evolutive SFP'!E36) -> 0.25383825 | H13: ='Evolutive SFP'!F4/('Evolutive SFP'!F31+'Evolutive SFP'!F36) -> 0.22433373 | I13: ='Evolutive SFP'!G4/('Evolutive SFP'!G31+'Evolutive SFP'!G36) -> 0.30410681 | J13: ='Evolutive SFP'!H4/('Evolutive SFP'!H31+'Evolutive SFP'!H36) -> 0.29288262 | K13: ='Evolutive SFP'!I4/('Evolutive SFP'!I31+'Evolutive SFP'!I36) -> 0.31624407 | ... BQ13: ='Evolutive SFP'!BO4/('Evolutive SFP'!BO31+'Evolutive SFP'!BO36) -> 0.474224
B14: EB ratio | C14: Max 25% | D14: ='Evolutive SFP'!B37/'Evolutive SFP'!B27 -> 0.015175035 | E14: ='Evolutive SFP'!C37/'Evolutive SFP'!C27 -> 0 | F14: ='Evolutive SFP'!D37/'Evolutive SFP'!D24 -> 0 | G14: ='Evolutive SFP'!E37/'Evolutive SFP'!E27 -> 0 | H14: ='Evolutive SFP'!F37/'Evolutive SFP'!F27 -> 0 | I14: ='Evolutive SFP'!G37/'Evolutive SFP'!G27 -> 0.043947848 | J14: ='Evolutive SFP'!H37/'Evolutive SFP'!H27 -> 0.044165722 | K14: ='Evolutive SFP'!I37/'Evolutive SFP'!I27 -> 0.043723882 | L14: ='Evolutive SFP'!J37/'Evolutive SFP'!J27 -> 0.044141021 | M14: ='Evolutive SFP'!K37/'Evolutive SFP'!K27 -> 0.044531396 | N14: ='Evolutive SFP'!L37/'Evolutive SFP'!L27 -> 0.045006646 | ... BQ14: ='Evolutive SFP'!BO37/'Evolutive SFP'!BO27 -> 0
B15: LA to TA ratio | D15: ='Evolutive SFP'!B4/'Evolutive SFP'!B27 -> 0.12821992 | E15: ='Evolutive SFP'!C4/'Evolutive SFP'!C27 -> 0.12741401 | F15: ='Evolutive SFP'!D4/'Evolutive SFP'!D27 -> 0.20459469 | G15: ='Evolutive SFP'!E4/'Evolutive SFP'!E27 -> 0.19277982 | H15: ='Evolutive SFP'!F4/'Evolutive SFP'!F27 -> 0.16984218 | I15: ='Evolutive SFP'!G4/'Evolutive SFP'!G27 -> 0.22115387 | J15: ='Evolutive SFP'!H4/'Evolutive SFP'!H27 -> 0.21236898 | K15: ='Evolutive SFP'!I4/'Evolutive SFP'!I27 -> 0.22993072 | ... BQ15: ='Evolutive SFP'!BO4/'Evolutive SFP'!BO27 -> 0.33505028
A16: STRUCTURE | B16: NEA ratio | C16: Max 10% | D16: =('Evolutive SFP'!B7+'Evolutive SFP'!B21)/'Evolutive SFP'!B27 -> 0.12101375 | E16: =('Evolutive SFP'!C7+'Evolutive SFP'!C21)/'Evolutive SFP'!C27 -> 0.09430328 | F16: =('Evolutive SFP'!D7+'Evolutive SFP'!D21)/'Evolutive SFP'!D27 -> 0.14869319 | G16: =('Evolutive SFP'!E7+'Evolutive SFP'!E21)/'Evolutive SFP'!E27 -> 0.14867627 | H16: =('Evolutive SFP'!F7+'Evolutive SFP'!F21)/'Evolutive SFP'!F27 -> 0.15450319 | I16: =('Evolutive SFP'!G7+'Evolutive SFP'!G21)/'Evolutive SFP'!G27 -> 0.13952584 | J16: =('Evolutive SFP'!H7+'Evolutive SFP'!H21)/'Evolutive SFP'!H27 -> 0.14166077 | K16: =('Evolutive SFP'!I7+'Evolutive SFP'!I21)/'Evolutive SFP'!I27 -> 0.13016699 | ... BF16: =('Evolutive SFP'!BD7+'Evolutive SFP'!BD21)/'Evolutive SFP'!BD27 -> 0.20574079 | BG16: =Financials!BF34/Financials!BF4 -> 0.20942097 | BH16: =Financials!BG34/Financials!BG4 -> 0.20794077 | BI16: =Financials!BH34/Financials!BH4 -> 0.20923033 | BJ16: =Financials!BI34/Financials!BI4 -> 0.20853859 | BK16: =Financials!BJ34/Financials!BJ4 -> 0.23024493 | BL16: =Financials!BK34/Financials!BK4 -> 0.19593484 | BM16: =Financials!BL34/Financials!BL4 -> 0.19157008 | BN16: =Financials!BM34/Financials!BM4 -> 0.19516672 | ... BQ16: =Financials!BP34/Financials!BP4 -> 0.19381987
B17: LB ratio | C17: Max 5% | D17: ='Evolutive SFP'!B21/'Evolutive SFP'!B27 -> 0.032278671 | E17: ='Evolutive SFP'!C21/'Evolutive SFP'!C27 -> 0.064982853 | F17: ='Evolutive SFP'!D18/'Evolutive SFP'!D24 -> 0 | G17: ='Evolutive SFP'!E21/'Evolutive SFP'!E27 -> 0.094164143 | H17: ='Evolutive SFP'!F21/'Evolutive SFP'!F27 -> 0.095631993 | I17: ='Evolutive SFP'!G21/'Evolutive SFP'!G27 -> 0.088736275 | J17: ='Evolutive SFP'!H21/'Evolutive SFP'!H27 -> 0.091507825 | K17: ='Evolutive SFP'!I21/'Evolutive SFP'!I27 -> 0.082960813 | L17: ='Evolutive SFP'!J21/'Evolutive SFP'!J27 -> 0.091122476 | M17: ='Evolutive SFP'!K21/'Evolutive SFP'!K27 -> 0.084620753 | N17: ='Evolutive SFP'!L21/'Evolutive SFP'!L27 -> 0.084094025 | ... BQ17: ='Evolutive SFP'!BO21/'Evolutive SFP'!BO27 -> 0.092802982
B18: PI to Deposit ratio | C18: Max 5% | D18: ='Evolutive SFP'!B13/'Evolutive SFP'!B31 -> 0.0036721969 | E18: ='Evolutive SFP'!C13/'Evolutive SFP'!C31 -> 0.038661194 | F18: ='Evolutive SFP'!D9/'Evolutive SFP'!D31 -> 0 | G18: ='Evolutive SFP'!E13/'Evolutive SFP'!E31 -> 0.061511492 | H18: ='Evolutive SFP'!F13/'Evolutive SFP'!F31 -> 0.062585917 | I18: ='Evolutive SFP'!G13/'Evolutive SFP'!G31 -> 0.061419348 | J18: ='Evolutive SFP'!H13/'Evolutive SFP'!H31 -> 0.062292255 | K18: ='Evolutive SFP'!I13/'Evolutive SFP'!I31 -> 0.061725836 | L18: ='Evolutive SFP'!J13/'Evolutive SFP'!J31 -> 0.06237469 | M18: ='Evolutive SFP'!K13/'Evolutive SFP'!K31 -> 0.064340137 | N18: ='Evolutive SFP'!L13/'Evolutive SFP'!L31 -> 0.065547385 | ... BQ18: ='Evolutive SFP'!BO13/'Evolutive SFP'!BO31 -> 0.044706682
B19: PI to CC ratio | C19: Max 40% | D19: ='Evolutive SFP'!B13/(CAELS!D3*1000000) -> 0.030948443 | E19: ='Evolutive SFP'!C13/(CAELS!E3*1000000) -> 0.13085628 | F19: ='Evolutive SFP'!D9/(CAELS!F3*1000000) -> 0 | G19: ='Evolutive SFP'!E13/(CAELS!G3*1000000) -> 0.2203447 | H19: ='Evolutive SFP'!F13/(CAELS!H3*1000000) -> 0.21904315 | I19: ='Evolutive SFP'!G13/(CAELS!I3*1000000) -> 0.22003539 | J19: ='Evolutive SFP'!H13/(CAELS!J3*1000000) -> 0.22130897 | K19: ='Evolutive SFP'!I13/(CAELS!K3*1000000) -> 0.22064398 | L19: ='Evolutive SFP'!J13/(CAELS!L3*1000000) -> 0.22009586 | M19: ='Evolutive SFP'!K13/(CAELS!M3*1000000) -> 0.21486843 | N19: ='Evolutive SFP'!L13/(CAELS!N3*1000000) -> 0.21473907 | ... BQ19: ='Evolutive SFP'!BO13/(CAELS!BQ3*1000000) -> 0.22302156
B20: Gross loans/TA | D20: ='Evolutive SFP'!B15/'Evolutive SFP'!B27 -> 0.74763912 | E20: ='Evolutive SFP'!C15/'Evolutive SFP'!C27 -> 0.724849 | F20: ='Evolutive SFP'!D11/'Evolutive SFP'!D24 -> 0 | G20: ='Evolutive SFP'!E15/'Evolutive SFP'!E27 -> 0.7518191 | H20: ='Evolutive SFP'!F15/'Evolutive SFP'!F27 -> 0.77258742 | I20: ='Evolutive SFP'!G15/'Evolutive SFP'!G27 -> 0.73258269 | J20: ='Evolutive SFP'!H15/'Evolutive SFP'!H27 -> 0.74134655 | K20: ='Evolutive SFP'!I15/'Evolutive SFP'!I27 -> 0.73595915 | L20: ='Evolutive SFP'!J15/'Evolutive SFP'!J27 -> 0.73729101 | M20: ='Evolutive SFP'!K15/'Evolutive SFP'!K27 -> 0.74509989 | N20: ='Evolutive SFP'!L15/'Evolutive SFP'!L27 -> 0.75894859 | ... BQ20: ='Evolutive SFP'!BO15/'Evolutive SFP'!BO27 -> 0.58810719
A21: FUNDING MIX | B21: Total Deposits/Total Assets | D21: ='Evolutive SFP'!B31/'Evolutive SFP'!B27 -> 0.85159483 | E21: ='Evolutive SFP'!C31/'Evolutive SFP'!C27 -> 0.7420122 | F21: ='Evolutive SFP'!D31/'Evolutive SFP'!D27 -> 0.72690995 | G21: ='Evolutive SFP'!E31/'Evolutive SFP'!E27 -> 0.72415032 | H21: ='Evolutive SFP'!F31/'Evolutive SFP'!F27 -> 0.7271059 | I21: ='Evolutive SFP'!G31/'Evolutive SFP'!G27 -> 0.70101766 | J21: ='Evolutive SFP'!H31/'Evolutive SFP'!H27 -> 0.69532988 | K21: ='Evolutive SFP'!I31/'Evolutive SFP'!I27 -> 0.69539884 | ... BQ21: ='Evolutive SFP'!BO31/'Evolutive SFP'!BO27 -> 0.67707456
B22: BOSA Deposits/Total Assets | D22: ='Evolutive SFP'!B30/'Evolutive SFP'!B27 -> 0.74257768 | E22: ='Evolutive SFP'!C30/'Evolutive SFP'!C27 -> 0.23640553 | F22: ='Evolutive SFP'!D30/'Evolutive SFP'!D27 -> 0.24333689 | G22: ='Evolutive SFP'!E30/'Evolutive SFP'!E27 -> 0.24793522 | H22: ='Evolutive SFP'!F30/'Evolutive SFP'!F27 -> 0.25593211 | I22: ='Evolutive SFP'!G30/'Evolutive SFP'!G27 -> 0.24254153 | J22: ='Evolutive SFP'!H30/'Evolutive SFP'!H27 -> 0.24605095 | K22: ='Evolutive SFP'!I30/'Evolutive SFP'!I27 -> 0.24483627 | ... BQ22: ='Evolutive SFP'!BO30/'Evolutive SFP'!BO27 -> 0.23772344
B23: FOSA Deposits/Total Assets | D23: =('Evolutive SFP'!B28+'Evolutive SFP'!B29)/'Evolutive SFP'!B27 -> 0.10901715 | E23: =('Evolutive SFP'!C28+'Evolutive SFP'!C29)/'Evolutive SFP'!C27 -> 0.50560666 | F23: =('Evolutive SFP'!D28+'Evolutive SFP'!D29)/'Evolutive SFP'!D27 -> 0.48357306 | G23: =('Evolutive SFP'!E28+'Evolutive SFP'!E29)/'Evolutive SFP'!E27 -> 0.47621509 | H23: =('Evolutive SFP'!F28+'Evolutive SFP'!F29)/'Evolutive SFP'!F27 -> 0.47117378 | I23: =('Evolutive SFP'!G28+'Evolutive SFP'!G29)/'Evolutive SFP'!G27 -> 0.45847614 | J23: =('Evolutive SFP'!H28+'Evolutive SFP'!H29)/'Evolutive SFP'!H27 -> 0.44927893 | K23: =('Evolutive SFP'!I28+'Evolutive SFP'!I29)/'Evolutive SFP'!I27 -> 0.45056257 | ... BQ23: =('Evolutive SFP'!BO28+'Evolutive SFP'!BO29)/'Evolutive SFP'!BO27 -> 0.43935112
A24: GROWTH RATIOS | B24: Total Assets | D24: =(Financials!C4-Financials!B4)/Financials!B4 -> #VALUE! | E24: =(Financials!D4-Financials!C4)/Financials!C4 -> 6.605497 | F24: =(Financials!E4-Financials!D4)/Financials!D4 -> -0.99948283 | G24: =(Financials!F4-Financials!E4)/Financials!E4 -> 1846.5987 | H24: =(Financials!G4-Financials!F4)/Financials!F4 -> -0.020161115 | I24: =(Financials!H4-Financials!G4)/Financials!G4 -> -0.36915538 | J24: =(Financials!I4-Financials!H4)/Financials!H4 -> 0.66883544 | K24: =(Financials!J4-Financials!I4)/Financials!I4 -> 0.010105215 | ... BQ24: =(Financials!BP4-Financials!BO4)/Financials!BO4 -> -0.028312692
B25: Total Deposits | D25: =Financials!D5/Financials!C5-1 -> 5.6268269 | E25: =Financials!E5/Financials!D5-1 -> -0.048549295 | F25: =Financials!F5/Financials!E5-1 -> -0.019888031 | G25: =Financials!G5/Financials!F5-1 -> -0.016161957 | H25: =Financials!H5/Financials!G5-1 -> -1 | I25: =Financials!I5/Financials!H5-1 -> #DIV/0! | J25: =Financials!J5/Financials!I5-1 -> 0.010205396 | K25: =Financials!K5/Financials!J5-1 -> -0.0093944797 | ... BP25: =Financials!BP5/Financials!BO5-1 -> -1.086068e-07 | BQ25: =Financials!#REF!/Financials!BP5-1 -> #REF!
B26: BOSA Deposits | D26: =Financials!D6/Financials!C6-1 -> 1.4212707 | E26: =Financials!E6/Financials!D6-1 -> 3.1082711 | F26: =Financials!F6/Financials!E6-1 -> -0.75606967 | G26: =Financials!G6/Financials!F6-1 -> 0.011442563 | H26: =Financials!H6/Financials!G6-1 -> -1 | I26: =Financials!I6/Financials!H6-1 -> #DIV/0! | J26: =Financials!J6/Financials!I6-1 -> 0.005118623 | K26: =Financials!K6/Financials!J6-1 -> 0.0047158089 | ... BP26: =Financials!BP6/Financials!BO6-1 -> -1.5237698e-06 | BQ26: =Financials!#REF!/Financials!BP6-1 -> #REF!
B27: FOSA Deposits | D27: =Financials!D7/Financials!C7-1 -> 34.273256 | E27: =Financials!E7/Financials!D7-1 -> -0.91368177 | F27: =Financials!F7/Financials!E7-1 -> 9.4263457 | G27: =Financials!G7/Financials!F7-1 -> -0.030533893 | H27: =Financials!H7/Financials!G7-1 -> -0.69390436 | I27: =Financials!I7/Financials!H7-1 -> 2.2795459 | J27: =Financials!J7/Financials!I7-1 -> 0.012991205 | K27: =Financials!K7/Financials!J7-1 -> -0.017062028 | ... BP27: =Financials!BP7/Financials!BO7-1 -> 6.5710914e-07 | BQ27: =Financials!#REF!/Financials!BP7-1 -> #REF!
B28: Total Loans & advances | D28: =Financials!D31/Financials!C31-1 -> 6.3736603 | E28: =Financials!E31/Financials!D31-1 -> -1 | F28: =Financials!F31/Financials!E31-1 -> #DIV/0! | G28: =Financials!G31/Financials!F31-1 -> 0.0069060453 | H28: =Financials!H31/Financials!G31-1 -> #REF! | I28: =Financials!I31/Financials!H31-1 -> #REF! | J28: =Financials!J31/Financials!I31-1 -> 0.0027647299 | K28: =Financials!K31/Financials!J31-1 -> -0.0076575529 | ... BP28: =Financials!BP31/Financials!BO31-1 -> 0.00011810868 | BQ28: =Financials!#REF!/Financials!BP31-1 -> #REF!
B29: Core capital | D29: =Financials!D11/Financials!C11-1 -> 13.280228 | E29: =Financials!E11/Financials!D11-1 -> -0.40945348 | F29: =Financials!F11/Financials!E11-1 -> 0.41976202 | G29: =Financials!G11/Financials!F11-1 -> 0.0086519049 | H29: =Financials!H11/Financials!G11-1 -> #REF! | I29: =Financials!I11/Financials!H11-1 -> #REF! | J29: =Financials!J11/Financials!I11-1 -> 0.28939022 | K29: =Financials!K11/Financials!J11-1 -> 0.003511538 | ... BP29: =Financials!BP11/Financials!BO11-1 -> 0.04879215 | BQ29: =Financials!#REF!/Financials!BP11-1 -> #REF!
B30: Turnover | D30: =Financials!D37/Financials!C37-1 -> 13471.472 | E30: =Financials!E37/Financials!D37-1 -> -0.895099 | F30: =Financials!F37/Financials!E37-1 -> 0.63807394 | G30: =Financials!G37/Financials!F37-1 -> 0.45806631 | H30: =Financials!H37/Financials!G37-1 -> 0.28571648 | I30: =Financials!I37/Financials!H37-1 -> 0.21417251 | J30: =Financials!J37/Financials!I37-1 -> 0.2072454 | K30: =Financials!K37/Financials!J37-1 -> 0.14389035 | ... BP30: =Financials!BP37/Financials!BO37-1 -> -0.0067396463 | BQ30: =Financials!#REF!/Financials!BP37-1 -> #REF!
B31: Membership
B32: Expenses | D32: ='Evolutitve SCI'!E39/'Evolutitve SCI'!B39-1 -> 1923.6025 | E32: ='Evolutitve SCI'!F39/'Evolutitve SCI'!C39-1 -> -0.79138429 | F32: ='Evolutitve SCI'!G39/'Evolutitve SCI'!D39-1 -> 4.1641047 | G32: ='Evolutitve SCI'!H39/'Evolutitve SCI'!E39-1 -> 1.8287052 | H32: ='Evolutitve SCI'!I39/'Evolutitve SCI'!F39-1 -> 1.198247 | I32: ='Evolutitve SCI'!J39/'Evolutitve SCI'!G39-1 -> 0.85433457 | J32: ='Evolutitve SCI'!I39/'Evolutitve SCI'!H39-1 -> 0.21795055 | K32: ='Evolutitve SCI'!J39/'Evolutitve SCI'!I39-1 -> 0.17052673 | L32: ='Evolutitve SCI'!K39/'Evolutitve SCI'!J39-1 -> 0.14773104 | M32: ='Evolutitve SCI'!L39/'Evolutitve SCI'!K39-1 -> 0.13065045 | N32: ='Evolutitve SCI'!M39/'Evolutitve SCI'!L39-1 -> 0.13009803 | O32: ='Evolutitve SCI'!N39/'Evolutitve SCI'!M39-1 -> 0.12566265 | P32: ='Evolutitve SCI'!O39/'Evolutitve SCI'!N39-1 -> 0.094009932 | Q32: ='Evolutitve SCI'!P39/'Evolutitve SCI'!O39-1 -> 0.054741701 | ... BQ32: ='Evolutitve SCI'!BP39/'Evolutitve SCI'!BO39-1 -> -1
A33: Efficiency Ratios | B33: FinCost-Deposits/Avg Deposits | H33: =Financials!G44/('Evolutive SFP'!B30+'Evolutive SFP'!F30)/2 -> 0.001918652 | I33: =Financials!H44/('Evolutive SFP'!C30+'Evolutive SFP'!G30)/2 -> 0.0018961798 | K33: =Financials!J44/('Evolutive SFP'!F30+'Evolutive SFP'!I30)/2 -> 0.0072231137 | L33: =Financials!K44/('Evolutive SFP'!I30+'Evolutive SFP'!J30)/2 -> 0.0086356146 | M33: =Financials!L44/('Evolutive SFP'!J30+'Evolutive SFP'!K30)/2 -> 0.0099848309 | N33: =Financials!M44/('Evolutive SFP'!K30+'Evolutive SFP'!L30)/2 -> 0.011312134 | O33: =Financials!N44/('Evolutive SFP'!L30+'Evolutive SFP'!M30)/2 -> 0.013096251 | P33: =Financials!O44/('Evolutive SFP'!M30+'Evolutive SFP'!N30)/2 -> 0.015179056 | Q33: =Financials!P44/('Evolutive SFP'!N30+'Evolutive SFP'!O30)/2 -> 0.016170895 | R33: =Financials!Q44/('Evolutive SFP'!O30+'Evolutive SFP'!P30)/2 -> 0.027825701 | S33: =Financials!R44/('Evolutive SFP'!P30+'Evolutive SFP'!Q30)/2 -> 0.00064628865 | ... BJ33: =Financials!BI44/('Evolutive SFP'!BG30+'Evolutive SFP'!BH30)/2 -> 0.0083614385 | BK33: =Financials!BJ44/('Evolutive SFP'!BH30+'Evolutive SFP'!BI32)/2 -> 0.023442079 | BL33: =Financials!BK44/('Evolutive SFP'!BI32+'Evolutive SFP'!BJ30)/2 -> 0.025274853 | BM33: =Financials!BL44/('Evolutive SFP'!BJ30+'Evolutive SFP'!BK32)/2 -> 0.028346955 | BN33: =Financials!BM44/('Evolutive SFP'!BK32+'Evolutive SFP'!BL30)/2 -> 0.031831381 | BO33: =Financials!BN44/('Evolutive SFP'!BL30+'Evolutive SFP'!BM32)/2 -> 0.047204935 | BP33: =Financials!BO44/('Evolutive SFP'!BM32+'Evolutive SFP'!BN30)/2 -> 0.03782544 | BQ33: =Financials!BP44/('Evolutive SFP'!BN30+'Evolutive SFP'!BO32)/2 -> 0.036826532
B34: FinCost-Shares/Avg Share capital | H34: =Financials!G45/('Evolutive SFP'!B39+'Evolutive SFP'!F39)/2 -> 0 | I34: =Financials!H45/('Evolutive SFP'!C39+'Evolutive SFP'!G39)/2 -> 0 | K34: =Financials!J45/('Evolutive SFP'!F39+'Evolutive SFP'!I39)/2 -> 0 | L34: =Financials!K45/('Evolutive SFP'!I39+'Evolutive SFP'!J39)/2 -> 0 | M34: =Financials!L45/('Evolutive SFP'!J39+'Evolutive SFP'!K39)/2 -> 0 | N34: =Financials!M45/('Evolutive SFP'!K39+'Evolutive SFP'!L39)/2 -> 0 | O34: =Financials!N45/('Evolutive SFP'!L39+'Evolutive SFP'!M39)/2 -> 0 | P34: =Financials!O45/('Evolutive SFP'!M39+'Evolutive SFP'!N39)/2 -> 0 | Q34: =Financials!P45/('Evolutive SFP'!N39+'Evolutive SFP'!O39)/2 -> 0 | R34: =Financials!Q45/('Evolutive SFP'!O39+'Evolutive SFP'!P39)/2 -> 0 | S34: =Financials!R45/('Evolutive SFP'!P39+'Evolutive SFP'!Q39)/2 -> 0 | ... BJ34: =Financials!BI45/('Evolutive SFP'!BG39+'Evolutive SFP'!BH39)/2 -> 0 | BK34: =Financials!BJ45/('Evolutive SFP'!BH39+'Evolutive SFP'!BI41)/2 -> 0 | BL34: =Financials!BK45/('Evolutive SFP'!BI41+'Evolutive SFP'!BJ39)/2 -> 0 | BM34: =Financials!BL45/('Evolutive SFP'!BJ39+'Evolutive SFP'!BK41)/2 -> 0 | BN34: =Financials!BM45/('Evolutive SFP'!BK41+'Evolutive SFP'!BL39)/2 -> 0 | BO34: =Financials!BN45/('Evolutive SFP'!BL39+'Evolutive SFP'!BM41)/2 -> 0 | BP34: =Financials!BO45/('Evolutive SFP'!BM41+'Evolutive SFP'!BN39)/2 -> 0 | BQ34: =Financials!BP45/('Evolutive SFP'!BN39+'Evolutive SFP'!BO41)/2 -> 0
B35: FinCost-Ext Loans/Avg Ext Loans | H35: =Financials!G46/(Financials!F31+Financials!G31)/2 -> 0 | I35: =Financials!H46/(Financials!G31+Financials!H31)/2 -> #REF! | K35: =Financials!J46/(Financials!G31+Financials!J31)/2 -> 0.00053773974 | L35: =Financials!K46/(Financials!J31+Financials!K31)/2 -> 0.00068336881 | M35: =Financials!L46/(Financials!K31+Financials!L31)/2 -> 0.00085137383 | N35: =Financials!M46/(Financials!L31+Financials!M31)/2 -> 0.00099900602 | O35: =Financials!N46/(Financials!M31+Financials!N31)/2 -> 0.001269647 | P35: =Financials!O46/(Financials!N31+Financials!O31)/2 -> 0.0013721221 | Q35: =Financials!P46/(Financials!O31+Financials!P31)/2 -> 0.0013135457 | R35: =Financials!Q46/(Financials!P31+Financials!Q31)/2 -> 0.0012603678 | S35: =Financials!R46/(Financials!Q31+Financials!R31)/2 -> 0 | ... BQ35: =Financials!BP46/(Financials!BO31+Financials!BP31)/2 -> 0
B36: OpEx/Average Total Assets | H36: =Financials!G47/(Financials!F4+Financials!G4)/2 -> 0.0075258994 | I36: =Financials!H47/(Financials!G4+Financials!H4)/2 -> 0.012791236 | K36: =Financials!J47/(Financials!G4+Financials!J4)/2 -> 0.014703651 | L36: =Financials!K47/(Financials!J4+Financials!K4)/2 -> 0.016495376 | M36: =Financials!L47/(Financials!K4+Financials!L4)/2 -> 0.019080754 | N36: =Financials!M47/(Financials!L4+Financials!M4)/2 -> 0.021740142 | O36: =Financials!N47/(Financials!M4+Financials!N4)/2 -> 0.021199477 | P36: =Financials!O47/(Financials!N4+Financials!O4)/2 -> 0.021899079 | Q36: =Financials!P47/(Financials!O4+Financials!P4)/2 -> 0.025959423 | R36: =Financials!Q47/(Financials!P4+Financials!Q4)/2 -> 0.026582665 | S36: =Financials!R47/(Financials!Q4+Financials!R4)/2 -> 0.0019363483 | ... BQ36: =Financials!BP47/(Financials!BO4+Financials!BP4)/2 -> 0.028981539
B37: Opex/Turnover | H37: =Financials!G47/Financials!G37 -> 0.66365772 | I37: =Financials!H47/Financials!H37 -> 0.70809323 | K37: =Financials!J47/Financials!J37 -> 0.70258851 | L37: =Financials!K47/Financials!K37 -> 0.7068753 | M37: =Financials!L47/Financials!L37 -> 0.66520745 | N37: =Financials!M47/Financials!M37 -> 0.6740788 | O37: =Financials!N47/Financials!N37 -> 0.66156979 | P37: =Financials!O47/Financials!O37 -> 0.64670572 | Q37: =Financials!P47/Financials!P37 -> 0.63952507 | R37: =Financials!Q47/Financials!Q37 -> 0.64413081 | ... BQ37: =Financials!BP47/Financials!BP37 -> 0.6562216
B38: Avge yield on Net loans | H38: =Financials!G38/('Evolutive SFP'!F14+'Evolutive SFP'!B14)/2 -> 0.015666356 | I38: =Financials!H38/('Evolutive SFP'!G14+'Evolutive SFP'!C14)/2 -> 0.012112143 | K38: =Financials!J38/('Evolutive SFP'!I14+'Evolutive SFP'!F14)/2 -> 0.018228573 | L38: =Financials!K38/('Evolutive SFP'!J14+'Evolutive SFP'!I14)/2 -> 0.021347638 | M38: =Financials!L38/('Evolutive SFP'!K14+'Evolutive SFP'!J14)/2 -> 0.024622273 | N38: =Financials!M38/('Evolutive SFP'!L14+'Evolutive SFP'!K14)/2 -> 0.02776416 | O38: =Financials!N38/('Evolutive SFP'!M14+'Evolutive SFP'!L14)/2 -> 0.035265731 | P38: =Financials!O38/('Evolutive SFP'!N14+'Evolutive SFP'!M14)/2 -> 0.04290194 | Q38: =Financials!P38/('Evolutive SFP'!O14+'Evolutive SFP'!N14)/2 -> 0.04364573 | R38: =Financials!Q38/('Evolutive SFP'!P14+'Evolutive SFP'!O14)/2 -> 0.041150538 | S38: =Financials!R38/('Evolutive SFP'!Q14+'Evolutive SFP'!P14)/2 -> 0.002978629 | ... BJ38: =Financials!BI38/('Evolutive SFP'!BH14+'Evolutive SFP'!BG14)/2 -> 0.023515405 | BK38: =Financials!BJ38/('Evolutive SFP'!BI15+'Evolutive SFP'!BH14)/2 -> 0.025544955 | BL38: =Financials!BK38/('Evolutive SFP'!BJ14+'Evolutive SFP'!BI15)/2 -> 0.028762488 | BM38: =Financials!BL38/('Evolutive SFP'!BK15+'Evolutive SFP'!BJ14)/2 -> 0.031235918 | BN38: =Financials!BM38/('Evolutive SFP'!BL14+'Evolutive SFP'!BK15)/2 -> 0.033894335 | BO38: =Financials!BN38/('Evolutive SFP'!BM15+'Evolutive SFP'!BL14)/2 -> 0.036784238 | BP38: =Financials!BO38/('Evolutive SFP'!BN14+'Evolutive SFP'!BM15)/2 -> 0.010369618 | BQ38: =Financials!BP38/('Evolutive SFP'!BO15+'Evolutive SFP'!BN14)/2 -> 0
B39: Avge yield on Gross loans | H39: =Financials!G37/('Evolutive SFP'!F15+'Evolutive SFP'!B15)/2 -> 0.026109701 | I39: =Financials!H37/('Evolutive SFP'!G15+'Evolutive SFP'!C15)/2 -> 0.019015605 | K39: =Financials!J37/('Evolutive SFP'!I15+'Evolutive SFP'!F15)/2 -> 0.027766402 | L39: =Financials!K37/('Evolutive SFP'!J15+'Evolutive SFP'!I15)/2 -> 0.031679241 | M39: =Financials!L37/('Evolutive SFP'!K15+'Evolutive SFP'!J15)/2 -> 0.038700427 | N39: =Financials!M37/('Evolutive SFP'!L15+'Evolutive SFP'!K15)/2 -> 0.042888523 | O39: =Financials!N37/('Evolutive SFP'!M15+'Evolutive SFP'!L15)/2 -> 0.054359087 | P39: =Financials!O37/('Evolutive SFP'!N15+'Evolutive SFP'!M15)/2 -> 0.067586999 | Q39: =Financials!P37/('Evolutive SFP'!O15+'Evolutive SFP'!N15)/2 -> 0.0720488 | R39: =Financials!Q37/('Evolutive SFP'!P15+'Evolutive SFP'!O15)/2 -> 0.068526296 | S39: =Financials!R37/('Evolutive SFP'!Q15+'Evolutive SFP'!P15)/2 -> 0.0046236809 | ... BJ39: =Financials!BI37/('Evolutive SFP'!BH15+'Evolutive SFP'!BG15)/2 -> 0.036839894 | BK39: =Financials!BJ37/('Evolutive SFP'!BI16+'Evolutive SFP'!BH15)/2 -> 0.072094976 | BL39: =Financials!BK37/('Evolutive SFP'!BJ15+'Evolutive SFP'!BI16)/2 -> 0.082088566 | BM39: =Financials!BL37/('Evolutive SFP'!BK16+'Evolutive SFP'!BJ15)/2 -> 0.091173462 | BN39: =Financials!BM37/('Evolutive SFP'!BL15+'Evolutive SFP'!BK16)/2 -> 0.096696873 | BO39: =Financials!BN37/('Evolutive SFP'!BM16+'Evolutive SFP'!BL15)/2 -> 0.11138136 | BP39: =Financials!BO37/('Evolutive SFP'!BN15+'Evolutive SFP'!BM16)/2 -> 0.12168168 | BQ39: =Financials!BP37/('Evolutive SFP'!BO16+'Evolutive SFP'!BN15)/2 -> 0.12065093
A41: ALL/Average Gross Loan portfolio

Sheet Sheet1
B3: =6429931/0.01 -> 642993100
B4: =1159521/0.05 -> 23190420
B5: =4472345/0.25 -> 17889380
B6: =12240162/0.5 -> 24480324
B7: =139271396 -> 139271396
B8: =SUM(B3:B7) -> 847824620

Sheet Financials
B1: WANANCHI Sacco Financial Performance
B2: Year | C2: 2010 Audited | D2: 2017 Audited | E2: 43101 | F2: 43133 | G2: 43165 | H2: 43197 | I2: 43229 | J2: 43261 | K2: 43293 | L2: 43325 | M2: 43357 | N2: 43389 | O2: 43421 | P2: 43453 | Q2: Audited 2018 | R2: 43466 | S2: 43498 | T2: 43527 | U2: 43559 | V2: 43590 | W2: 43622 | X2: 43653 | Y2: 43685 | Z2: 43717 | AA2: 43748 | AB2: 43780 | AC2: 43811 | AD2: AUDITED 2019 | AE2: 43844 | AF2: 43876 | AG2: 43906 | AH2: 43938 | AI2: 43969 | AJ2: 44001 | AK2: 44063 | AL2: 44095 | AM2: 44126 | AN2: 44158 | AO2: 44189 | AP2: AUDITED2020 | AQ2: 44197 | AR2: 44228 | AS2: 44256 | AT2: 44287 | AU2: 44317 | AV2: 44348 | AW2: 44378 | AX2: 44409 | AY2: 44440 | AZ2: 44470 | BA2: 44501 | BB2: 44531 | BC2: Audited 2021 | BD2: 44562 | BE2: 44593 | BF2: 44621 | BG2: 44652 | BH2: 44682 | BI2: 44713 | BJ2: 44743 | BK2: 44774 | BL2: 44805 | BM2: 44835 | BN2: 44866 | BO2: 44896 | BP2: Audited 2022
A3: 1 | B3: Membership
A4: 2 | B4: Total Assets | C4: ='Evolutive SFP'!B27 -> 151015729 | D4: ='Evolutive SFP'!C27 -> 1148549670 | E4: ='Evolutive SFP'!D24 -> 594000 | F4: ='Evolutive SFP'!E27 -> 1.0974736e+09 | G4: ='Evolutive SFP'!F27 -> 1.0753473e+09 | H4: ='Evolutive SFP'!G14 -> 6.7837707e+08 | I4: ='Evolutive SFP'!H27 -> 1.1320997e+09 | J4: ='Evolutive SFP'!I27 -> 1.1435398e+09 | K4: ='Evolutive SFP'!J27 -> 1.1327332e+09 | L4: ='Evolutive SFP'!K27 -> 1.1228033e+09 | M4: ='Evolutive SFP'!L27 -> 1.110947e+09 | N4: ='Evolutive SFP'!M27 -> 1.4715746e+09 | O4: ='Evolutive SFP'!N27 -> 1.3400383e+09 | P4: ='Evolutive SFP'!O27 -> 1.2718126e+09 | ... BP4: ='Evolutive SFP'!BO27 -> 1380976781 | BQ4: ='Evolutive SFP'!BQ27 -> 0 | BR4: ='Evolutive SFP'!BR27 -> 0 | BS4: ='Evolutive SFP'!BS27 -> 0 | BT4: ='Evolutive SFP'!BT27 -> 0 | BU4: ='Evolutive SFP'!BU27 -> 0 | BV4: ='Evolutive SFP'!BV27 -> 0 | BW4: ='Evolutive SFP'!BW27 -> 0
A5: 3 | B5: Total Deposits | C5: ='Evolutive SFP'!B31 -> 128604214 | D5: ='Evolutive SFP'!C31 -> 852237862 | E5: ='Evolutive SFP'!D31 -> 8.1086231e+08 | F5: ='Evolutive SFP'!E31 -> 7.9473586e+08 | G5: ='Evolutive SFP'!F31 -> 7.8189137e+08 | H5: ='Evolutive SFP'!G19 -> 0 | I5: ='Evolutive SFP'!H31 -> 7.8718275e+08 | J5: ='Evolutive SFP'!I31 -> 7.9521626e+08 | K5: ='Evolutive SFP'!J31 -> 7.8774562e+08 | L5: ='Evolutive SFP'!K31 -> 7.6756735e+08 | M5: ='Evolutive SFP'!L31 -> 7.5419314e+08 | N5: ='Evolutive SFP'!M31 -> 1.1501802e+09 | O5: ='Evolutive SFP'!N31 -> 1.013712e+09 | P5: ='Evolutive SFP'!O31 -> 9.3133619e+08 | ... BP5: ='Evolutive SFP'!BO31 -> 935024252 | BQ5: ='Evolutive SFP'!BQ31 -> 0 | BR5: ='Evolutive SFP'!BR31 -> 0 | BS5: ='Evolutive SFP'!BS31 -> 0 | BT5: ='Evolutive SFP'!BT31 -> 0 | BU5: ='Evolutive SFP'!BU31 -> 0 | BV5: ='Evolutive SFP'!BV31 -> 0 | BW5: ='Evolutive SFP'!BW31 -> 0
A6: 3.1 | B6: Deposits-Members(BOSA) | C6: ='Evolutive SFP'!B30 -> 112140909 | D6: ='Evolutive SFP'!C30 -> 271523495 | E6: ='Evolutive SFP'!D27 -> 1.1154921e+09 | F6: ='Evolutive SFP'!E30 -> 2.7210236e+08 | G6: ='Evolutive SFP'!F30 -> 2.7521591e+08 | H6: ='Evolutive SFP'!G18 -> 0 | I6: ='Evolutive SFP'!H30 -> 2.7855421e+08 | J6: ='Evolutive SFP'!I30 -> 2.7998002e+08 | K6: ='Evolutive SFP'!J30 -> 2.8130035e+08 | L6: ='Evolutive SFP'!K30 -> 2.8198335e+08 | M6: ='Evolutive SFP'!L30 -> 2.8122165e+08 | N6: ='Evolutive SFP'!M30 -> 2.8199216e+08 | O6: ='Evolutive SFP'!N30 -> 2.8522983e+08 | P6: ='Evolutive SFP'!O30 -> 2.8553958e+08 | ... BP6: ='Evolutive SFP'!BO30 -> 328290550 | BQ6: ='Evolutive SFP'!BQ30 -> 0 | BR6: ='Evolutive SFP'!BR30 -> 0 | BS6: ='Evolutive SFP'!BS30 -> 0 | BT6: ='Evolutive SFP'!BT30 -> 0 | BU6: ='Evolutive SFP'!BU30 -> 0 | BV6: ='Evolutive SFP'!BV30 -> 0 | BW6: ='Evolutive SFP'!BW30 -> 0
A7: 3.2 | B7: Deposits-Customers(FOSA) | C7: =('Evolutive SFP'!B28+'Evolutive SFP'!B29) -> 16463305 | D7: =('Evolutive SFP'!C28+'Evolutive SFP'!C29) -> 580714367 | E7: =('Evolutive SFP'!D25+'Evolutive SFP'!D26) -> 50126239 | F7: =('Evolutive SFP'!E28+'Evolutive SFP'!E29) -> 5.226335e+08 | G7: =('Evolutive SFP'!F28+'Evolutive SFP'!F29) -> 5.0667546e+08 | H7: =('Evolutive SFP'!G16+'Evolutive SFP'!G17) -> 1.5509115e+08 | I7: =('Evolutive SFP'!H28+'Evolutive SFP'!H29) -> 5.0862854e+08 | J7: =('Evolutive SFP'!I28+'Evolutive SFP'!I29) -> 5.1523624e+08 | K7: =('Evolutive SFP'!J28+'Evolutive SFP'!J29) -> 5.0644526e+08 | L7: =('Evolutive SFP'!K28+'Evolutive SFP'!K29) -> 4.85584e+08 | M7: =('Evolutive SFP'!L28+'Evolutive SFP'!L29) -> 4.729715e+08 | N7: =('Evolutive SFP'!M28+'Evolutive SFP'!M29) -> 8.6818803e+08 | O7: =('Evolutive SFP'!N28+'Evolutive SFP'!N29) -> 7.284822e+08 | P7: =('Evolutive SFP'!O28+'Evolutive SFP'!O29) -> 6.4579662e+08 | ... BP7: =('Evolutive SFP'!BO28+'Evolutive SFP'!BO29) -> 606733702 | BQ7: =('Evolutive SFP'!BQ28+'Evolutive SFP'!BQ29) -> 0 | BR7: =('Evolutive SFP'!BR28+'Evolutive SFP'!BR29) -> 0 | BS7: =('Evolutive SFP'!BS28+'Evolutive SFP'!BS29) -> 0 | BT7: =('Evolutive SFP'!BT28+'Evolutive SFP'!BT29) -> 0 | BU7: =('Evolutive SFP'!BU28+'Evolutive SFP'!BU29) -> 0 | BV7: =('Evolutive SFP'!BV28+'Evolutive SFP'!BV29) -> 0 | BW7: =('Evolutive SFP'!BW28+'Evolutive SFP'!BW29) -> 0
A8: 4 | B8: External Borrowing | C8: ='Evolutive SFP'!B37 -> 2291669 | D8: ='Evolutive SFP'!C37 -> 0 | E8: ='Evolutive SFP'!D37 -> 0 | F8: ='Evolutive SFP'!E37 -> 0 | G8: ='Evolutive SFP'!F37 -> 0 | H8: ='Evolutive SFP'!G25 -> 5489439 | I8: ='Evolutive SFP'!H37 -> 50000000 | J8: ='Evolutive SFP'!I37 -> 50000000 | K8: ='Evolutive SFP'!J37 -> 50000000 | L8: ='Evolutive SFP'!K37 -> 50000000 | M8: ='Evolutive SFP'!L37 -> 50000000 | N8: ='Evolutive SFP'!M37 -> 0 | O8: ='Evolutive SFP'!N37 -> 0 | P8: ='Evolutive SFP'!O37 -> 0 | ... BP8: ='Evolutive SFP'!BO37 -> 0 | BQ8: ='Evolutive SFP'!BQ37 -> 0 | BR8: ='Evolutive SFP'!BR37 -> 0 | BS8: ='Evolutive SFP'!BS37 -> 0 | BT8: ='Evolutive SFP'!BT37 -> 0 | BU8: ='Evolutive SFP'!BU37 -> 0 | BV8: ='Evolutive SFP'!BV37 -> 0 | BW8: ='Evolutive SFP'!BW37 -> 0
A10: 5 | B10: Share capital and Reserves
A11: 5.1 | B11: Core Capital | C11: =C14-C22-C25 -> 14446887 | D11: =D14-D22-D25 -> 206304838 | E11: =E14-E22-E25 -> 1.2183261e+08 | F11: =F14-F22-F25 -> 1.7297331e+08 | G11: =G14-G22-G25 -> 1.7446985e+08 | H11: =H14-H22-H25 -> #REF! | I11: =I14-I22-I25 -> 1.7253443e+08 | J11: =J14-J22 -> 2.2246421e+08 | K11: =K14-K22 -> 2.232454e+08 | L11: =L14-L22 -> 2.2984013e+08 | M11: =M14-M22 -> 2.3021143e+08 | N11: =N14-N22 -> 2.4210544e+08 | O11: =O14-O22 -> 2.4536548e+08 | P11: =P14-P22 -> 2.5408282e+08 | Q11: =Q14-Q22 -> 248082819 | ... BW11: =BW14-BW22 -> 0
A12: 5.2 | B12: Institutional Capital | C12: =C11-C15 -> 3952190 | D12: =D11-D15 -> 65639391 | E12: =E11-E15 -> -19421777 | F12: =F11-F15 -> 31174581 | G12: =G11-G15 -> 32057095 | H12: =H11-H15 -> #REF! | I12: =I11-I15 -> 28886699 | J12: =J11-J15 -> 78219471 | ... BW12: =BW11-BW15 -> 0
A14: 5.3 | B14: Total Capital | C14: =C15+C16+C17+C18+C19+C20+C21 -> 14919147 | D14: =D15+D16+D17+D18+D19+D20+D21 -> 256104993 | E14: =E15+E16+E17+E18+E19+E20+E21 -> 2.2846032e+08 | F14: =F15+F16+F17+F18+F19+F20+F21 -> 2.2617193e+08 | G14: =G15+G16+G17+G18+G19+G20+G21 -> 2.2340524e+08 | H14: =H15+H16+H17+H18+H19+H20+H21 -> 2.331874e+09 | I14: =I15+I16+I17+I18+I19+I20+I21 -> 2.2156982e+08 | J14: =J15+J16+J17+J18+J19+J20+J21 -> 2.2246421e+08 | ... BW14: =BW15+BW16+BW17+BW18+BW19+BW20+BW21 -> 0
A15: 5.3.1 | B15: Members Share Capital | C15: ='Evolutive SFP'!B39 -> 10494697 | D15: ='Evolutive SFP'!C39 -> 140665447 | E15: ='Evolutive SFP'!D39 -> 1.4125438e+08 | F15: ='Evolutive SFP'!E39 -> 1.4179872e+08 | G15: ='Evolutive SFP'!F39 -> 1.4241276e+08 | H15: ='Evolutive SFP'!G27 -> 1.1377121e+09 | I15: ='Evolutive SFP'!H39 -> 1.4364773e+08 | J15: ='Evolutive SFP'!I39 -> 1.4424474e+08 | K15: ='Evolutive SFP'!J39 -> 1.4474297e+08 | L15: ='Evolutive SFP'!K39 -> 1.452943e+08 | M15: ='Evolutive SFP'!L39 -> 1.4635976e+08 | N15: ='Evolutive SFP'!M39 -> 1.5426005e+08 | O15: ='Evolutive SFP'!N39 -> 1.5549845e+08 | P15: ='Evolutive SFP'!O39 -> 1.5670017e+08 | ... BP15: ='Evolutive SFP'!BO39 -> 217120114 | BQ15: ='Evolutive SFP'!BQ39 -> 0 | BR15: ='Evolutive SFP'!BR39 -> 0 | BS15: ='Evolutive SFP'!BS39 -> 0 | BT15: ='Evolutive SFP'!BT39 -> 0 | BU15: ='Evolutive SFP'!BU39 -> 0 | BV15: ='Evolutive SFP'!BV39 -> 0 | BW15: ='Evolutive SFP'!BW39 -> 0
A16: 5.3.2 | B16: Entrance Fees
A17: 5.3.3 | B17: Retained Earnings | C17: ='Evolutive SFP'!B41 -> 351220 | D17: ='Evolutive SFP'!C41 -> 14978344 | E17: ='Evolutive SFP'!D41 -> 27664229 | F17: ='Evolutive SFP'!E41 -> 20813817 | G17: ='Evolutive SFP'!F41 -> 20813817 | H17: ='Evolutive SFP'!G29 -> 99792072 | I17: ='Evolutive SFP'!H41 -> 20813817 | J17: ='Evolutive SFP'!I41 -> 20813817 | K17: ='Evolutive SFP'!J41 -> 20813817 | L17: ='Evolutive SFP'!K41 -> 20813817 | M17: ='Evolutive SFP'!L41 -> 20813817 | N17: ='Evolutive SFP'!M41 -> 20813817 | O17: ='Evolutive SFP'!N41 -> 20813817 | P17: ='Evolutive SFP'!O41 -> 20813817 | ... BP17: ='Evolutive SFP'!BO41 -> 54209976 | BQ17: ='Evolutive SFP'!BQ41 -> 0 | BR17: ='Evolutive SFP'!BR41 -> 0 | BS17: ='Evolutive SFP'!BS41 -> 0 | BT17: ='Evolutive SFP'!BT41 -> 0 | BU17: ='Evolutive SFP'!BU41 -> 0 | BV17: ='Evolutive SFP'!BV41 -> 0 | BW17: ='Evolutive SFP'!BW41 -> 0
A18: 5.3.4 | B18: Appropriation Account | C18: ='Evolutive SFP'!B42 -> 3541956 | D18: ='Evolutive SFP'!C42 -> 5835476 | E18: ='Evolutive SFP'!D42 -> 9337095 | F18: ='Evolutive SFP'!E42 -> 6504356.7 | G18: ='Evolutive SFP'!F42 -> 7436870.6 | H18: ='Evolutive SFP'!G30 -> 2.7594244e+08 | I18: ='Evolutive SFP'!H42 -> 4366474.7 | J18: ='Evolutive SFP'!I42 -> 4663858 | K18: ='Evolutive SFP'!J42 -> 4946815.8 | L18: ='Evolutive SFP'!K42 -> 10990214 | M18: ='Evolutive SFP'!L42 -> 10296055 | N18: ='Evolutive SFP'!M42 -> 14289780 | O18: ='Evolutive SFP'!N42 -> 16311411 | P18: ='Evolutive SFP'!O42 -> 23827031 | ... BP18: ='Evolutive SFP'!BO42 -> 19201722 | BQ18: ='Evolutive SFP'!BQ42 -> 0 | BR18: ='Evolutive SFP'!BR42 -> 0 | BS18: ='Evolutive SFP'!BS42 -> 0 | BT18: ='Evolutive SFP'!BT42 -> 0 | BU18: ='Evolutive SFP'!BU42 -> 0 | BV18: ='Evolutive SFP'!BV42 -> 0 | BW18: ='Evolutive SFP'!BW42 -> 0
A19: 5.3.5 | B19: Statutory Reserves | C19: ='Evolutive SFP'!B43 -> 531274 | D19: ='Evolutive SFP'!C43 -> 31870722 | E19: ='Evolutive SFP'!D43 -> 29333544 | F19: ='Evolutive SFP'!E43 -> 31870722 | G19: ='Evolutive SFP'!F43 -> 31870722 | H19: ='Evolutive SFP'!G31 -> 7.9755631e+08 | I19: ='Evolutive SFP'!H43 -> 31870722 | J19: ='Evolutive SFP'!I43 -> 31870722 | K19: ='Evolutive SFP'!J43 -> 31870722 | L19: ='Evolutive SFP'!K43 -> 31870722 | M19: ='Evolutive SFP'!L43 -> 31870722 | N19: ='Evolutive SFP'!M43 -> 31870722 | O19: ='Evolutive SFP'!N43 -> 31870722 | P19: ='Evolutive SFP'!O43 -> 31870722 | ... BP19: ='Evolutive SFP'!BO43 -> 55580570 | BQ19: ='Evolutive SFP'!BQ43 -> 0 | BR19: ='Evolutive SFP'!BR43 -> 0 | BS19: ='Evolutive SFP'!BS43 -> 0 | BT19: ='Evolutive SFP'!BT43 -> 0 | BU19: ='Evolutive SFP'!BU43 -> 0 | BV19: ='Evolutive SFP'!BV43 -> 0 | BW19: ='Evolutive SFP'!BW43 -> 0
A20: 5.3.6 | B20: Capital Reserves | C20: =('Evolutive SFP'!B44) -> 0 | D20: =('Evolutive SFP'!C44) -> 58441770 | E20: =('Evolutive SFP'!D44) -> 20871074 | F20: =('Evolutive SFP'!E44) -> 20871074 | G20: =('Evolutive SFP'!F44) -> 20871074 | H20: =('Evolutive SFP'!G44) -> 20871074 | I20: =('Evolutive SFP'!H44) -> 20871074 | J20: =('Evolutive SFP'!I44) -> 20871074 | ... BP20: =('Evolutive SFP'!BO44) -> 20871074 | BQ20: =('Evolutive SFP'!BQ44) -> 0 | BR20: =('Evolutive SFP'!BR44) -> 0 | BS20: =('Evolutive SFP'!BS44) -> 0 | BT20: =('Evolutive SFP'!BT44) -> 0 | BU20: =('Evolutive SFP'!BU44) -> 0 | BV20: =('Evolutive SFP'!BV44) -> 0 | BW20: =('Evolutive SFP'!BW44) -> 0
A21: 5.3.7 | B21: Supplementary Capital & reserves | C21: =C22+C23 -> 0 | D21: =D22+D23 -> 4313234 | E21: =E22+E23 -> 0 | F21: =F22+F23 -> 4313234 | G21: =G22+G23 -> 0 | H21: =H22+H23 -> 0 | I21: =I22+I23 -> 0 | J21: =J22+J23 -> 0 | ... BW21: =BW22+BW23 -> 0
A22: a | B22: Proposed Dividends | C22: ='Evolutive SFP'!B46 -> 0 | D22: ='Evolutive SFP'!C46 -> 4313234 | E22: ='Evolutive SFP'!D46 -> 0 | F22: ='Evolutive SFP'!E46 -> 4313234 | G22: ='Evolutive SFP'!F46 -> 0 | H22: ='Evolutive SFP'!G46 -> 0 | I22: ='Evolutive SFP'!H46 -> 0 | J22: ='Evolutive SFP'!I46 -> 0 | ... BP22: ='Evolutive SFP'!BO46 -> 0 | BQ22: ='Evolutive SFP'!BQ46 -> 0 | BR22: ='Evolutive SFP'!BR46 -> 0 | BS22: ='Evolutive SFP'!BS46 -> 0 | BT22: ='Evolutive SFP'!BT46 -> 0 | BU22: ='Evolutive SFP'!BU46 -> 0 | BV22: ='Evolutive SFP'!BV46 -> 0 | BW22: ='Evolutive SFP'!BW46 -> 0
A23: b | B23: Risk Mgt Fund
A25: 6 | B25: Investments | C25: =C26+C27+C28 -> 472260 | D25: =D26+D27+D28 -> 45486921 | E25: =E26+E27+E28 -> 1.0662772e+08 | F25: =F26+F27+F28 -> 48885388 | G25: =G26+G27+G28 -> 48935388 | H25: =H26+H27+H28 -> #REF! | I25: =I26+I27+I28 -> 49035388 | J25: =J26+J27+J28 -> 49085388 | ... BW25: =BW26+BW27+BW28 -> 0
A26: 6.1 | B26: Shares in Kusco,CIC,Coop Bank | C26: ='Evolutive SFP'!B13 -> 472260 | D26: ='Evolutive SFP'!C13 -> 32948533 | E26: ='Evolutive SFP'!D9 -> 0 | F26: ='Evolutive SFP'!E13 -> 48885388 | G26: ='Evolutive SFP'!F13 -> 48935388 | H26: ='Evolutive SFP'!#REF! -> #REF! | I26: ='Evolutive SFP'!H13 -> 49035388 | J26: ='Evolutive SFP'!I13 -> 49085388 | K26: ='Evolutive SFP'!J13 -> 49135388 | L26: ='Evolutive SFP'!K13 -> 49385388 | M26: ='Evolutive SFP'!L13 -> 49435388 | N26: ='Evolutive SFP'!M13 -> 49485388 | O26: ='Evolutive SFP'!N13 -> 3.3953539e+08 | P26: ='Evolutive SFP'!O13 -> 3.8962744e+08 | ... BP26: ='Evolutive SFP'!BO13 -> 41801832 | BQ26: ='Evolutive SFP'!BQ13 -> 0 | BR26: ='Evolutive SFP'!BR13 -> 0 | BS26: ='Evolutive SFP'!BS13 -> 0 | BT26: ='Evolutive SFP'!BT13 -> 0 | BU26: ='Evolutive SFP'!BU13 -> 0 | BV26: ='Evolutive SFP'!BV13 -> 0 | BW26: ='Evolutive SFP'!BW13 -> 0
A27: 6.2 | B27: Equity Investments (at cost) | C27: ='Evolutive SFP'!B10 -> 0 | D27: ='Evolutive SFP'!C10 -> 0 | E27: ='Evolutive SFP'!D7 -> 57792330 | F27: ='Evolutive SFP'!E10 -> 0 | G27: ='Evolutive SFP'!F10 -> 0 | H27: ='Evolutive SFP'!#REF! -> #REF! | I27: ='Evolutive SFP'!H10 -> 0 | J27: ='Evolutive SFP'!I10 -> 0 | K27: ='Evolutive SFP'!J10 -> 0 | L27: ='Evolutive SFP'!K10 -> 0 | M27: ='Evolutive SFP'!L10 -> 0 | N27: ='Evolutive SFP'!M10 -> 0 | O27: ='Evolutive SFP'!N10 -> 0 | P27: ='Evolutive SFP'!O10 -> 0 | ... BP27: ='Evolutive SFP'!BO10 -> 0 | BQ27: ='Evolutive SFP'!BQ10 -> 0 | BR27: ='Evolutive SFP'!BR10 -> 0 | BS27: ='Evolutive SFP'!BS10 -> 0 | BT27: ='Evolutive SFP'!BT10 -> 0 | BU27: ='Evolutive SFP'!BU10 -> 0 | BV27: ='Evolutive SFP'!BV10 -> 0 | BW27: ='Evolutive SFP'!BW10 -> 0
A28: 6.3 | B28: Deposits in KUSCCO CFP | C28: ='Evolutive SFP'!B11 -> 0 | D28: ='Evolutive SFP'!C11 -> 12538388 | E28: ='Evolutive SFP'!D8 -> 48835388 | F28: ='Evolutive SFP'!E11 -> 0 | G28: ='Evolutive SFP'!F11 -> 0 | H28: ='Evolutive SFP'!#REF! -> #REF! | I28: ='Evolutive SFP'!H11 -> 0 | J28: ='Evolutive SFP'!I11 -> 0 | K28: ='Evolutive SFP'!J11 -> 0 | L28: ='Evolutive SFP'!K11 -> 0 | M28: ='Evolutive SFP'!L11 -> 0 | N28: ='Evolutive SFP'!M11 -> 0 | O28: ='Evolutive SFP'!N11 -> 0 | P28: ='Evolutive SFP'!O11 -> 0 | ... BP28: ='Evolutive SFP'!BO11 -> 0 | BQ28: ='Evolutive SFP'!BQ11 -> 0 | BR28: ='Evolutive SFP'!BR11 -> 0 | BS28: ='Evolutive SFP'!BS11 -> 0 | BT28: ='Evolutive SFP'!BT11 -> 0 | BU28: ='Evolutive SFP'!BU11 -> 0 | BV28: ='Evolutive SFP'!BV11 -> 0 | BW28: ='Evolutive SFP'!BW11 -> 0
A30: 7 | B30: Net Loans & Advances | C30: ='Evolutive SFP'!B14 -> 112905266 | D30: ='Evolutive SFP'!C14 -> 685110959 | E30: ='Evolutive SFP'!D10 -> 0 | F30: ='Evolutive SFP'!E14 -> 6.7384917e+08 | G30: ='Evolutive SFP'!F14 -> 6.77628e+08 | H30: ='Evolutive SFP'!#REF! -> #REF! | I30: ='Evolutive SFP'!H14 -> 6.8226734e+08 | J30: ='Evolutive SFP'!I14 -> 6.8266836e+08 | K30: ='Evolutive SFP'!J14 -> 6.7622378e+08 | L30: ='Evolutive SFP'!K14 -> 6.7381947e+08 | M30: ='Evolutive SFP'!L14 -> 6.7845115e+08 | N30: ='Evolutive SFP'!M14 -> 5.1260223e+08 | O30: ='Evolutive SFP'!N14 -> 5.5899658e+08 | P30: ='Evolutive SFP'!O14 -> 5.7846752e+08 | ... BP30: ='Evolutive SFP'!BO14 -> 598486828 | BQ30: ='Evolutive SFP'!BQ14 -> 0 | BR30: ='Evolutive SFP'!BR14 -> 0 | BS30: ='Evolutive SFP'!BS14 -> 0 | BT30: ='Evolutive SFP'!BT14 -> 0 | BU30: ='Evolutive SFP'!BU14 -> 0 | BV30: ='Evolutive SFP'!BV14 -> 0 | BW30: ='Evolutive SFP'!BW14 -> 0
A31: 7.1 | B31: Gross Loans & advances | C31: ='Evolutive SFP'!B15 -> 112905266 | D31: ='Evolutive SFP'!C15 -> 832525078 | E31: ='Evolutive SFP'!D11 -> 0 | F31: ='Evolutive SFP'!E15 -> 8.2510161e+08 | G31: ='Evolutive SFP'!F15 -> 8.307998e+08 | H31: ='Evolutive SFP'!#REF! -> #REF! | I31: ='Evolutive SFP'!H15 -> 8.3927821e+08 | J31: ='Evolutive SFP'!I15 -> 8.4159859e+08 | K31: ='Evolutive SFP'!J15 -> 8.35154e+08 | L31: ='Evolutive SFP'!K15 -> 8.3660065e+08 | M31: ='Evolutive SFP'!L15 -> 8.4315168e+08 | N31: ='Evolutive SFP'!M15 -> 6.7922211e+08 | O31: ='Evolutive SFP'!N15 -> 7.2945516e+08 | P31: ='Evolutive SFP'!O15 -> 7.4204087e+08 | ... BP31: ='Evolutive SFP'!BO15 -> 812162376 | BQ31: ='Evolutive SFP'!BQ15 -> 0 | BR31: ='Evolutive SFP'!BR15 -> 0 | BS31: ='Evolutive SFP'!BS15 -> 0 | BT31: ='Evolutive SFP'!BT15 -> 0 | BU31: ='Evolutive SFP'!BU15 -> 0 | BV31: ='Evolutive SFP'!BV15 -> 0 | BW31: ='Evolutive SFP'!BW15 -> 0
A32: 7.2 | B32: Allowance for loan losses | C32: ='Evolutive SFP'!B16 -> 0 | D32: ='Evolutive SFP'!C16 -> 147414119 | E32: ='Evolutive SFP'!D13 -> 48835388 | F32: ='Evolutive SFP'!E16 -> 1.5125245e+08 | G32: ='Evolutive SFP'!F16 -> 1.531718e+08 | H32: ='Evolutive SFP'!#REF! -> #REF! | I32: ='Evolutive SFP'!H16 -> 1.5701087e+08 | J32: ='Evolutive SFP'!I16 -> 1.5893023e+08 | K32: ='Evolutive SFP'!J16 -> 1.5893023e+08 | L32: ='Evolutive SFP'!K16 -> 1.6278118e+08 | M32: ='Evolutive SFP'!L16 -> 1.6470053e+08 | N32: ='Evolutive SFP'!M16 -> 1.6661988e+08 | O32: ='Evolutive SFP'!N16 -> 1.7045858e+08 | P32: ='Evolutive SFP'!O16 -> 1.6357335e+08 | ... BP32: ='Evolutive SFP'!BO16 -> 213675548 | BQ32: ='Evolutive SFP'!BQ16 -> 0 | BR32: ='Evolutive SFP'!BR16 -> 0 | BS32: ='Evolutive SFP'!BS16 -> 0 | BT32: ='Evolutive SFP'!BT16 -> 0 | BU32: ='Evolutive SFP'!BU16 -> 0 | BV32: ='Evolutive SFP'!BV16 -> 0 | BW32: ='Evolutive SFP'!BW16 -> 0
A34: 8 | B34: Non-Earning Assets | C34: ='Evolutive SFP'!B21+'Evolutive SFP'!B7 -> 18274979 | D34: ='Evolutive SFP'!C21+'Evolutive SFP'!C7 -> 108312001 | E34: ='Evolutive SFP'!D18+'Evolutive SFP'!D4 -> 2.2822376e+08 | F34: ='Evolutive SFP'!E21+'Evolutive SFP'!E7 -> 1.6316829e+08 | G34: ='Evolutive SFP'!F21+'Evolutive SFP'!F7 -> 1.6614459e+08 | H34: ='Evolutive SFP'!G8+'Evolutive SFP'!#REF! -> #REF! | I34: ='Evolutive SFP'!H21+'Evolutive SFP'!H7 -> 1.6037412e+08 | J34: ='Evolutive SFP'!I21+'Evolutive SFP'!I7 -> 1.4885113e+08 | K34: ='Evolutive SFP'!J21+'Evolutive SFP'!J7 -> 1.5144491e+08 | L34: ='Evolutive SFP'!K21+'Evolutive SFP'!K7 -> 1.4181593e+08 | M34: ='Evolutive SFP'!L21+'Evolutive SFP'!L7 -> 1.3883474e+08 | N34: ='Evolutive SFP'!M21+'Evolutive SFP'!M7 -> 2.7802686e+08 | O34: ='Evolutive SFP'!N21+'Evolutive SFP'!N7 -> 2.4161782e+08 | P34: ='Evolutive SFP'!O21+'Evolutive SFP'!O7 -> 1.4569539e+08 | ... BP34: ='Evolutive SFP'!BO21+'Evolutive SFP'!BO7 -> 267660740 | BQ34: =BP34/BP4 -> 0.19381987 | BR34: ='Evolutive SFP'!BR21+'Evolutive SFP'!BR7 -> 0 | BS34: ='Evolutive SFP'!BS21+'Evolutive SFP'!BS7 -> 0 | BT34: ='Evolutive SFP'!BT21+'Evolutive SFP'!BT7 -> 0 | BU34: ='Evolutive SFP'!BU21+'Evolutive SFP'!BU7 -> 0 | BV34: ='Evolutive SFP'!BV21+'Evolutive SFP'!BV7 -> 0 | BW34: ='Evolutive SFP'!BW21+'Evolutive SFP'!BW7 -> 0
A35: 8.1 | B35: Property and Equipment | C35: ='Evolutive SFP'!B23 -> 4123114 | D35: ='Evolutive SFP'!C23 -> 67228532 | E35: ='Evolutive SFP'!D20 -> 0 | F35: ='Evolutive SFP'!E23 -> 26113023 | G35: ='Evolutive SFP'!F23 -> 25596868 | H35: ='Evolutive SFP'!G10 -> 0 | I35: ='Evolutive SFP'!H23 -> 26464472 | J35: ='Evolutive SFP'!I23 -> 26486317 | K35: ='Evolutive SFP'!J23 -> 26483317 | L35: ='Evolutive SFP'!K23 -> 25451007 | M35: ='Evolutive SFP'!L23 -> 24934852 | N35: ='Evolutive SFP'!M23 -> 24461162 | O35: ='Evolutive SFP'!N23 -> 25614712 | P35: ='Evolutive SFP'!O23 -> 25338887 | ... BP35: ='Evolutive SFP'!BO23 -> 120314235 | BQ35: ='Evolutive SFP'!BQ23 -> 0 | BR35: ='Evolutive SFP'!BR23 -> 0 | BS35: ='Evolutive SFP'!BS23 -> 0 | BT35: ='Evolutive SFP'!BT23 -> 0 | BU35: ='Evolutive SFP'!BU23 -> 0 | BV35: ='Evolutive SFP'!BV23 -> 0 | BW35: ='Evolutive SFP'!BW23 -> 0
A37: 9 | B37: Turnover | C37: =C38+C39+C40+C41 -> 14599.248 | D37: =D38+D39+D40+D41 -> 196687961 | E37: =E38+E39+E40+E41 -> 20632764 | F37: =F38+F39+F40+F41 -> 33797993 | G37: =G38+G39+G40+G41 -> 49279715 | H37: =H38+H39+H40+H41 -> 63359741 | I37: =I38+I39+I40+I41 -> 76929656 | J37: =J38+J39+J40+J41 -> 92872973 | ... BW37: =BW38+BW39+BW40+BW41 -> 0
A38: 9.1 | B38: Loan Interest | C38: ='Evolutitve SCI'!B5 -> 11945.435 | D38: ='Evolutitve SCI'!C5 -> 101379709 | E38: ='Evolutitve SCI'!D5 -> 8717884.7 | F38: ='Evolutitve SCI'!E5 -> 16536521 | G38: ='Evolutitve SCI'!F5 -> 24769552 | H38: ='Evolutitve SCI'!G5 -> 33029523 | I38: ='Evolutitve SCI'!H5 -> 41174093 | J38: ='Evolutitve SCI'!I5 -> 49592524 | ... AB38: ='Evolutitve SCI'!AA5 -> 86064271 | AC38: ='Evolutitve SCI'!#REF! -> #REF! | AD38: ='Evolutitve SCI'!AC5 -> 93202429 | AE38: ='Evolutitve SCI'!AD5 -> 8958073.4 | AF38: ='Evolutitve SCI'!AE5 -> 17474186 | AG38: ='Evolutitve SCI'!AF5 -> 25199720 | AH38: ='Evolutitve SCI'!AG5 -> 32915641 | AI38: ='Evolutitve SCI'!AH5 -> 38840640 | AJ38: ='Evolutitve SCI'!AI5 -> 46510236 | AK38: ='Evolutitve SCI'!AJ5 -> 1.2375095e+08 | ... BP38: ='Evolutitve SCI'!BO5 -> 0 | BQ38: ='Evolutitve SCI'!BQ5 -> 0 | BR38: ='Evolutitve SCI'!BR5 -> 0 | BS38: ='Evolutitve SCI'!BS5 -> 0 | BT38: ='Evolutitve SCI'!BT5 -> 0 | BU38: ='Evolutitve SCI'!BU5 -> 0 | BV38: ='Evolutitve SCI'!BV5 -> 0 | BW38: ='Evolutitve SCI'!BW5 -> 0
A39: 9.2 | B39: Income from investments | C39: ='Evolutitve SCI'!B7 -> 1743.4416 | D39: ='Evolutitve SCI'!C7 -> 95308252 | E39: ='Evolutitve SCI'!D7 -> 5930081.5 | F39: ='Evolutitve SCI'!E7 -> 8931664 | G39: ='Evolutitve SCI'!F7 -> 14342069 | H39: ='Evolutitve SCI'!G7 -> 18749494 | I39: ='Evolutitve SCI'!H7 -> 22435087 | J39: ='Evolutitve SCI'!I7 -> 28316851 | ... AB39: ='Evolutitve SCI'!AA7 -> 88857711 | AC39: ='Evolutitve SCI'!#REF! -> #REF! | AD39: ='Evolutitve SCI'!AC7 -> 127039971 | AE39: ='Evolutitve SCI'!AD7 -> 3689317.1 | AF39: ='Evolutitve SCI'!AE7 -> 10841787 | AG39: ='Evolutitve SCI'!AF7 -> 17007290 | AH39: ='Evolutitve SCI'!AG7 -> 23886870 | AI39: ='Evolutitve SCI'!AH7 -> 29807635 | AJ39: ='Evolutitve SCI'!AI7 -> 36222859 | AK39: ='Evolutitve SCI'!AJ7 -> 99213426 | ... BP39: ='Evolutitve SCI'!BO7 -> 137481530 | BQ39: ='Evolutitve SCI'!BQ7 -> 0 | BR39: ='Evolutitve SCI'!BR7 -> 0 | BS39: ='Evolutitve SCI'!BS7 -> 0 | BT39: ='Evolutitve SCI'!BT7 -> 0 | BU39: ='Evolutitve SCI'!BU7 -> 0 | BV39: ='Evolutitve SCI'!BV7 -> 0 | BW39: ='Evolutitve SCI'!BW7 -> 0
A40: 9.3 | B40: Fees & Commissions | C40: ='Evolutitve SCI'!B6 -> 910.371 | D40: ='Evolutitve SCI'!C6 -> 0 | E40: ='Evolutitve SCI'!D6 -> 5984797.8 | F40: ='Evolutitve SCI'!E6 -> 8329807.6 | G40: ='Evolutitve SCI'!F6 -> 10168094 | H40: ='Evolutitve SCI'!G6 -> 11580725 | I40: ='Evolutitve SCI'!H6 -> 13320476 | J40: ='Evolutitve SCI'!I6 -> 14963597 | ... AB40: ='Evolutitve SCI'!AA6 -> 20822827 | AC40: ='Evolutitve SCI'!#REF! -> #REF! | AD40: ='Evolutitve SCI'!AC6 -> 0 | AE40: ='Evolutitve SCI'!AD6 -> 3868442.9 | AF40: ='Evolutitve SCI'!AE6 -> 5305052.9 | AG40: ='Evolutitve SCI'!AF6 -> 6701819.5 | AH40: ='Evolutitve SCI'!AG6 -> 7576018 | AI40: ='Evolutitve SCI'!AH6 -> 9051697.2 | AJ40: ='Evolutitve SCI'!AI6 -> 10693031 | AK40: ='Evolutitve SCI'!AJ6 -> 26337947 | ... BP40: ='Evolutitve SCI'!BO6 -> 110031921 | BQ40: ='Evolutitve SCI'!BQ6 -> 0 | BR40: ='Evolutitve SCI'!BR6 -> 0 | BS40: ='Evolutitve SCI'!BS6 -> 0 | BT40: ='Evolutitve SCI'!BT6 -> 0 | BU40: ='Evolutitve SCI'!BU6 -> 0 | BV40: ='Evolutitve SCI'!BV6 -> 0 | BW40: ='Evolutitve SCI'!BW6 -> 0
A41: 9.4 | B41: Average yield on loans
A43: 10 | B43: Financial and Operating costs | C43: =SUM(C44:C47) -> 11568.465 | D43: =SUM(D44:D47) -> 167267134 | E43: =SUM(E44:E47) -> 9281060.7 | F43: =SUM(F44:F47) -> 21824284 | G43: =SUM(G44:G47) -> 34191269 | H43: =SUM(H44:H47) -> 47440792 | I43: =SUM(I44:I47) -> 61774113 | J43: =SUM(J44:J47) -> 75070600 | ... BW43: =SUM(BW44:BW47) -> 0
A44: 10.1 | B44: Interest expense on deposits | C44: ='Evolutitve SCI'!B13+'Evolutitve SCI'!B16 -> 185.36 | D44: ='Evolutitve SCI'!C13+'Evolutitve SCI'!C16 -> 18907802 | E44: ='Evolutitve SCI'!D13+'Evolutitve SCI'!D16 -> 588165.55 | F44: ='Evolutitve SCI'!E13+'Evolutitve SCI'!E16 -> 1014759.5 | G44: ='Evolutitve SCI'!F13+'Evolutitve SCI'!F16 -> 1486405.9 | H44: ='Evolutitve SCI'!G13+'Evolutitve SCI'!G16 -> 2076187.8 | I44: ='Evolutitve SCI'!H13+'Evolutitve SCI'!H16 -> 6320227.6 | J44: ='Evolutitve SCI'!I13+'Evolutitve SCI'!I16 -> 8020486.7 | ... AB44: ='Evolutitve SCI'!AA13+'Evolutitve SCI'!AA16 -> 24446528 | AC44: ='Evolutitve SCI'!#REF!+'Evolutitve SCI'!#REF! -> #REF! | AD44: ='Evolutitve SCI'!AC13+'Evolutitve SCI'!AC16 -> 54726552 | AE44: ='Evolutitve SCI'!AD13+'Evolutitve SCI'!AD16 -> 895797.3 | AF44: ='Evolutitve SCI'!AE13+'Evolutitve SCI'!AE16 -> 3045494.4 | AG44: ='Evolutitve SCI'!AF13+'Evolutitve SCI'!AF16 -> 5378648.3 | AH44: ='Evolutitve SCI'!AG13+'Evolutitve SCI'!AG16 -> 6236991.5 | AI44: ='Evolutitve SCI'!AH13+'Evolutitve SCI'!AH16 -> 8332408.7 | AJ44: ='Evolutitve SCI'!AI13+'Evolutitve SCI'!AI16 -> 10463844 | AK44: ='Evolutitve SCI'!AJ13+'Evolutitve SCI'!AJ16 -> 30343248 | ... BP44: ='Evolutitve SCI'!BO13+'Evolutitve SCI'!BO16 -> 24699335 | BQ44: ='Evolutitve SCI'!BQ13+'Evolutitve SCI'!BQ16 -> 0 | BR44: ='Evolutitve SCI'!BR13+'Evolutitve SCI'!BR16 -> 0 | BS44: ='Evolutitve SCI'!BS13+'Evolutitve SCI'!BS16 -> 0 | BT44: ='Evolutitve SCI'!BT13+'Evolutitve SCI'!BT16 -> 0 | BU44: ='Evolutitve SCI'!BU13+'Evolutitve SCI'!BU16 -> 0 | BV44: ='Evolutitve SCI'!BV13+'Evolutitve SCI'!BV16 -> 0 | BW44: ='Evolutitve SCI'!BW13+'Evolutitve SCI'!BW16 -> 0
A45: 10.2 | B45: Dividend expense on share capital | C45: ='Evolutitve SCI'!B15 -> 0 | D45: ='Evolutitve SCI'!C15 -> 0 | E45: ='Evolutitve SCI'!D15 -> 0 | F45: ='Evolutitve SCI'!E15 -> 0 | G45: ='Evolutitve SCI'!F15 -> 0 | H45: ='Evolutitve SCI'!G15 -> 0 | I45: ='Evolutitve SCI'!H15 -> 0 | J45: ='Evolutitve SCI'!I15 -> 0 | ... AB45: ='Evolutitve SCI'!AA15 -> 0 | AC45: ='Evolutitve SCI'!#REF! -> #REF! | AD45: ='Evolutitve SCI'!AC15 -> 0 | AE45: ='Evolutitve SCI'!AD15 -> 0 | AF45: ='Evolutitve SCI'!AE15 -> 0 | AG45: ='Evolutitve SCI'!AF15 -> 0 | AH45: ='Evolutitve SCI'!AG15 -> 0 | AI45: ='Evolutitve SCI'!AH15 -> 0 | AJ45: ='Evolutitve SCI'!AI15 -> 0 | AK45: ='Evolutitve SCI'!AJ15 -> 0 | ... BP45: ='Evolutitve SCI'!BO15 -> 0 | BQ45: ='Evolutitve SCI'!BQ15 -> 0 | BR45: ='Evolutitve SCI'!BR15 -> 0 | BS45: ='Evolutitve SCI'!BS15 -> 0 | BT45: ='Evolutitve SCI'!BT15 -> 0 | BU45: ='Evolutitve SCI'!BU15 -> 0 | BV45: ='Evolutitve SCI'!BV15 -> 0 | BW45: ='Evolutitve SCI'!BW15 -> 0
A46: 10.3 | B46: Interest expense on borrowed funds | C46: ='Evolutitve SCI'!B14 -> 363.7247 | D46: ='Evolutitve SCI'!C14 -> 17546381 | E46: ='Evolutitve SCI'!D14 -> 0 | F46: ='Evolutitve SCI'!E14 -> 0 | G46: ='Evolutitve SCI'!F14 -> 0 | H46: ='Evolutitve SCI'!G14 -> 500000 | I46: ='Evolutitve SCI'!H14 -> 1289041.1 | J46: ='Evolutitve SCI'!I14 -> 1798630.2 | ... AB46: ='Evolutitve SCI'!AA14 -> 0 | AC46: ='Evolutitve SCI'!#REF! -> #REF! | AD46: ='Evolutitve SCI'!AC14 -> 0 | AE46: ='Evolutitve SCI'!AD14 -> 0 | AF46: ='Evolutitve SCI'!AE14 -> 0 | AG46: ='Evolutitve SCI'!AF14 -> 0 | AH46: ='Evolutitve SCI'!AG14 -> 0 | AI46: ='Evolutitve SCI'!AH14 -> 0 | AJ46: ='Evolutitve SCI'!AI14 -> 0 | AK46: ='Evolutitve SCI'!AJ14 -> 0 | ... BP46: ='Evolutitve SCI'!BO14 -> 0 | BQ46: ='Evolutitve SCI'!BQ14 -> 0 | BR46: ='Evolutitve SCI'!BR14 -> 0 | BS46: ='Evolutitve SCI'!BS14 -> 0 | BT46: ='Evolutitve SCI'!BT14 -> 0 | BU46: ='Evolutitve SCI'!BU14 -> 0 | BV46: ='Evolutitve SCI'!BV14 -> 0 | BW46: ='Evolutitve SCI'!BW14 -> 0
A47: 10.4 | B47: Opperating expenses | C47: ='Evolutitve SCI'!B23 -> 11019.38 | D47: ='Evolutitve SCI'!C23 -> 130812951 | E47: ='Evolutitve SCI'!D23 -> 8692895.2 | F47: ='Evolutitve SCI'!E23 -> 20809524 | G47: ='Evolutitve SCI'!F23 -> 32704863 | H47: ='Evolutitve SCI'!G23 -> 44864604 | I47: ='Evolutitve SCI'!H23 -> 54164844 | J47: ='Evolutitve SCI'!I23 -> 65251484 | ... AB47: ='Evolutitve SCI'!AA23 -> 1.2836458e+08 | AC47: ='Evolutitve SCI'!#REF! -> #REF! | AD47: ='Evolutitve SCI'!AC23 -> 140716337 | AE47: ='Evolutitve SCI'!AD23 -> 10315395 | AF47: ='Evolutitve SCI'!AE23 -> 22969820 | AG47: ='Evolutitve SCI'!AF23 -> 34842817 | AH47: ='Evolutitve SCI'!AG23 -> 45276878 | AI47: ='Evolutitve SCI'!AH23 -> 54120005 | AJ47: ='Evolutitve SCI'!AI23 -> 63580525 | AK47: ='Evolutitve SCI'!AJ23 -> 1.6887081e+08 | ... BP47: ='Evolutitve SCI'!BO23 -> 162423673 | BQ47: ='Evolutitve SCI'!BQ23 -> 0 | BR47: ='Evolutitve SCI'!BR23 -> 0 | BS47: ='Evolutitve SCI'!BS23 -> 0 | BT47: ='Evolutitve SCI'!BT23 -> 0 | BU47: ='Evolutitve SCI'!BU23 -> 0 | BV47: ='Evolutitve SCI'!BV23 -> 0 | BW47: ='Evolutitve SCI'!BW23 -> 0

Sheet CAELS Rating
A2: CAELS RATINGS WANANCHI SACCO
A3: FINANCIAL SOUNDNESS INDICATORS | B3: Prude. Std | C3: 2010 Audited | D3: 2017 Audited | E3: 43101.12 | F3: 43132 | G3: 43160 | H3: 43191 | I3: 43221 | J3: 43252 | K3: 43282 | L3: 43313 | M3: 43344 | N3: 43374 | O3: 43405 | P3: 43435 | Q3: Audited 2018
A4: CAPITAL
A5: CORE CAPITAL | B5: ≥ Ksh.10M | C5: =IF(CAELS!D3>10,"1","5") -> 1 | D5: =IF(CAELS!E3>10,"1","5") -> 1 | E5: =IF(CAELS!F3>10,"1","5") -> 1 | F5: =IF(CAELS!G3>10,"1","5") -> 1 | G5: =IF(CAELS!H3>10,"1","5") -> 1 | H5: =IF(CAELS!I3>10,"1","5") -> 1 | I5: =IF(CAELS!J3>10,"1","5") -> 1 | J5: =IF(CAELS!K3>10,"1","5") -> 1 | ... Q5: =IF(CAELS!R3>10,"1","5") -> 1
A6: CCA | B6: ≥ 10% | C6: =IF(CAELS!D4>20%,"1",IF(CAELS!D4>15%,"2",IF(CAELS!D4>12%,"3",IF(CAELS!D4>10%,"4","5")))) -> 4 | D6: =IF(CAELS!E4>20%,"1",IF(CAELS!E4>15%,"2",IF(CAELS!E4>12%,"3",IF(CAELS!E4>10%,"4","5")))) -> 1 | E6: =IF(CAELS!F4>20%,"1",IF(CAELS!F4>15%,"2",IF(CAELS!F4>12%,"3",IF(CAELS!F4>10%,"4","5")))) -> 2 | F6: =IF(CAELS!G4>20%,"1",IF(CAELS!G4>15%,"2",IF(CAELS!G4>12%,"3",IF(CAELS!G4>10%,"4","5")))) -> 1 | G6: =IF(CAELS!H4>20%,"1",IF(CAELS!H4>15%,"2",IF(CAELS!H4>12%,"3",IF(CAELS!H4>10%,"4","5")))) -> 1 | H6: =IF(CAELS!I4>20%,"1",IF(CAELS!I4>15%,"2",IF(CAELS!I4>12%,"3",IF(CAELS!I4>10%,"4","5")))) -> 2 | I6: =IF(CAELS!J4>20%,"1",IF(CAELS!J4>15%,"2",IF(CAELS!J4>12%,"3",IF(CAELS!J4>10%,"4","5")))) -> 2 | J6: =IF(CAELS!K4>20%,"1",IF(CAELS!K4>15%,"2",IF(CAELS!K4>12%,"3",IF(CAELS!K4>10%,"4","5")))) -> 2 | ... Q6: =IF(CAELS!R4>20%,"1",IF(CAELS!R4>15%,"2",IF(CAELS!R4>12%,"3",IF(CAELS!R4>10%,"4","5")))) -> 2
A7: ICA | B7: ≥ 8% | C7: =IF(CAELS!D6>15%,"1",IF(CAELS!D6>12%,"2",IF(CAELS!D6>10%,"3",IF(CAELS!D6>8,"4","5")))) -> 5 | D7: =IF(CAELS!E6>15%,"1",IF(CAELS!E6>12%,"2",IF(CAELS!E6>10%,"3",IF(CAELS!E6>8,"4","5")))) -> 5 | E7: =IF(CAELS!F6>15%,"1",IF(CAELS!F6>12%,"2",IF(CAELS!F6>10%,"3",IF(CAELS!F6>8,"4","5")))) -> 5 | F7: =IF(CAELS!G6>15%,"1",IF(CAELS!G6>12%,"2",IF(CAELS!G6>10%,"3",IF(CAELS!G6>8,"4","5")))) -> 5 | G7: =IF(CAELS!H6>15%,"1",IF(CAELS!H6>12%,"2",IF(CAELS!H6>10%,"3",IF(CAELS!H6>8,"4","5")))) -> 5 | H7: =IF(CAELS!I6>15%,"1",IF(CAELS!I6>12%,"2",IF(CAELS!I6>10%,"3",IF(CAELS!I6>8,"4","5")))) -> 5 | I7: =IF(CAELS!J6>15%,"1",IF(CAELS!J6>12%,"2",IF(CAELS!J6>10%,"3",IF(CAELS!J6>8,"4","5")))) -> 5 | J7: =IF(CAELS!K6>15%,"1",IF(CAELS!K6>12%,"2",IF(CAELS!K6>10%,"3",IF(CAELS!K6>8,"4","5")))) -> 5 | ... Q7: =IF(CAELS!R6>15%,"1",IF(CAELS!R6>12%,"2",IF(CAELS!R6>10%,"3",IF(CAELS!R6>8,"4","5")))) -> 5
A8: CCD | B8: ≥ 8% | C8: =IF(CAELS!D5>20%,"1",IF(CAELS!D5>15%,"2",IF(CAELS!D5>12%,"3",IF(CAELS!D5>10%,"4","5")))) -> 4 | D8: =IF(CAELS!E5>20%,"1",IF(CAELS!E5>15%,"2",IF(CAELS!E5>12%,"3",IF(CAELS!E5>10%,"4","5")))) -> 1 | E8: =IF(CAELS!F5>20%,"1",IF(CAELS!F5>15%,"2",IF(CAELS!F5>12%,"3",IF(CAELS!F5>10%,"4","5")))) -> 1 | F8: =IF(CAELS!G5>20%,"1",IF(CAELS!G5>15%,"2",IF(CAELS!G5>12%,"3",IF(CAELS!G5>10%,"4","5")))) -> 1 | G8: =IF(CAELS!H5>20%,"1",IF(CAELS!H5>15%,"2",IF(CAELS!H5>12%,"3",IF(CAELS!H5>10%,"4","5")))) -> 1 | H8: =IF(CAELS!I5>20%,"1",IF(CAELS!I5>15%,"2",IF(CAELS!I5>12%,"3",IF(CAELS!I5>10%,"4","5")))) -> 1 | I8: =IF(CAELS!J5>20%,"1",IF(CAELS!J5>15%,"2",IF(CAELS!J5>12%,"3",IF(CAELS!J5>10%,"4","5")))) -> 1 | J8: =IF(CAELS!K5>20%,"1",IF(CAELS!K5>15%,"2",IF(CAELS!K5>12%,"3",IF(CAELS!K5>10%,"4","5")))) -> 1 | ... Q8: =IF(CAELS!R5>20%,"1",IF(CAELS!R5>15%,"2",IF(CAELS!R5>12%,"3",IF(CAELS!R5>10%,"4","5")))) -> 1
C9: =(C5+C6+C7+C8)/4 -> 3.5 | D9: =(D5+D6+D7+D8)/4 -> 2 | E9: =(E5+E6+E7+E8)/4 -> 2.25 | F9: =(F5+F6+F7+F8)/4 -> 2 | G9: =(G5+G6+G7+G8)/4 -> 2 | H9: =(H5+H6+H7+H8)/4 -> 2.25 | I9: =(I5+I6+I7+I8)/4 -> 2.25 | J9: =(J5+J6+J7+J8)/4 -> 2.25 | ... Q9: =(Q5+Q6+Q7+Q8)/4 -> 2.25
A10: Asset Quality
A11: NPL | B11: ≤ 6% | L11: =IF(CAELS!M8<4%,"1",IF(CAELS!M8<8%,"2",IF(CAELS!M8<12%,"3",IF(CAELS!M8<15%,"4","5")))) -> 1 | O11: =IF(CAELS!P8<4%,"1",IF(CAELS!P8<8%,"2",IF(CAELS!P8<12%,"3",IF(CAELS!P8<15%,"4","5")))) -> 1
C12: =C11 -> 0 | D12: =D11 -> 0 | E12: =E11 -> 0 | F12: =F11 -> 0 | G12: =G11 -> 0 | H12: =H11 -> 0 | I12: =I11 -> 0 | J12: =J11 -> 0 | ... Q12: =Q11 -> 0
A13: Earnings
A14: ROA | D14: =IF(CAELS!E9>6%,"1",IF(CAELS!E9>4%,"2",IF(CAELS!E9>2%,"3",IF(CAELS!E9>0%,"4","5")))) -> 4 | E14: =IF(CAELS!F9>6%,"1",IF(CAELS!F9>4%,"2",IF(CAELS!F9>2%,"3",IF(CAELS!F9>0%,"4","5")))) -> 4 | F14: =IF(CAELS!G9>6%,"1",IF(CAELS!G9>4%,"2",IF(CAELS!G9>2%,"3",IF(CAELS!G9>0%,"4","5")))) -> 4 | G14: =IF(CAELS!H9>6%,"1",IF(CAELS!H9>4%,"2",IF(CAELS!H9>2%,"3",IF(CAELS!H9>0%,"4","5")))) -> 4 | H14: =IF(CAELS!I9>6%,"1",IF(CAELS!I9>4%,"2",IF(CAELS!I9>2%,"3",IF(CAELS!I9>0%,"4","5")))) -> 4 | I14: =IF(CAELS!J9>6%,"1",IF(CAELS!J9>4%,"2",IF(CAELS!J9>2%,"3",IF(CAELS!J9>0%,"4","5")))) -> 4 | J14: =IF(CAELS!K9>6%,"1",IF(CAELS!K9>4%,"2",IF(CAELS!K9>2%,"3",IF(CAELS!K9>0%,"4","5")))) -> 4 | K14: =IF(CAELS!L9>6%,"1",IF(CAELS!L9>4%,"2",IF(CAELS!L9>2%,"3",IF(CAELS!L9>0%,"4","5")))) -> 4 | ... Q14: =IF(CAELS!R9>6%,"1",IF(CAELS!R9>4%,"2",IF(CAELS!R9>2%,"3",IF(CAELS!R9>0%,"4","5")))) -> 4
A15: CIR | C15: =IF(CAELS!D10<60%,"1",IF(CAELS!D10<70%,"2",IF(CAELS!D10<80%,"3",IF(CAELS!D10<90%,"4","5")))) -> 3 | D15: =IF(CAELS!E10<60%,"1",IF(CAELS!E10<70%,"2",IF(CAELS!E10<80%,"3",IF(CAELS!E10<90%,"4","5")))) -> 4 | E15: =IF(CAELS!F10<60%,"1",IF(CAELS!F10<70%,"2",IF(CAELS!F10<80%,"3",IF(CAELS!F10<90%,"4","5")))) -> 1 | F15: =IF(CAELS!G10<60%,"1",IF(CAELS!G10<70%,"2",IF(CAELS!G10<80%,"3",IF(CAELS!G10<90%,"4","5")))) -> 2 | G15: =IF(CAELS!H10<60%,"1",IF(CAELS!H10<70%,"2",IF(CAELS!H10<80%,"3",IF(CAELS!H10<90%,"4","5")))) -> 2 | H15: =IF(CAELS!I10<60%,"1",IF(CAELS!I10<70%,"2",IF(CAELS!I10<80%,"3",IF(CAELS!I10<90%,"4","5")))) -> 3 | I15: =IF(CAELS!J10<60%,"1",IF(CAELS!J10<70%,"2",IF(CAELS!J10<80%,"3",IF(CAELS!J10<90%,"4","5")))) -> 3 | J15: =IF(CAELS!K10<60%,"1",IF(CAELS!K10<70%,"2",IF(CAELS!K10<80%,"3",IF(CAELS!K10<90%,"4","5")))) -> 4 | ... Q15: =IF(CAELS!R10<60%,"1",IF(CAELS!R10<70%,"2",IF(CAELS!R10<80%,"3",IF(CAELS!R10<90%,"4","5")))) -> 3
A16: OER | C16: =IF(CAELS!D11<4%,"1",IF(CAELS!D11<6%,"2",IF(CAELS!D11<8%,"3",IF(CAELS!D11<10%,"4","5")))) -> 1 | D16: =IF(CAELS!E11<4%,"1",IF(CAELS!E11<6%,"2",IF(CAELS!E11<8%,"3",IF(CAELS!E11<10%,"4","5")))) -> 5 | E16: =IF(CAELS!F11<4%,"1",IF(CAELS!F11<6%,"2",IF(CAELS!F11<8%,"3",IF(CAELS!F11<10%,"4","5")))) -> 1 | F16: =IF(CAELS!G11<4%,"1",IF(CAELS!G11<6%,"2",IF(CAELS!G11<8%,"3",IF(CAELS!G11<10%,"4","5")))) -> 1 | G16: =IF(CAELS!H11<4%,"1",IF(CAELS!H11<6%,"2",IF(CAELS!H11<8%,"3",IF(CAELS!H11<10%,"4","5")))) -> 1 | H16: =IF(CAELS!I11<4%,"1",IF(CAELS!I11<6%,"2",IF(CAELS!I11<8%,"3",IF(CAELS!I11<10%,"4","5")))) -> 2 | I16: =IF(CAELS!J11<4%,"1",IF(CAELS!J11<6%,"2",IF(CAELS!J11<8%,"3",IF(CAELS!J11<10%,"4","5")))) -> 2 | J16: =IF(CAELS!K11<4%,"1",IF(CAELS!K11<6%,"2",IF(CAELS!K11<8%,"3",IF(CAELS!K11<10%,"4","5")))) -> 3 | ... Q16: =IF(CAELS!R11<4%,"1",IF(CAELS!R11<6%,"2",IF(CAELS!R11<8%,"3",IF(CAELS!R11<10%,"4","5")))) -> 5
C17: =(C14+C15+C16)/3 -> 1.3333333 | D17: =(D14+D15+D16)/3 -> 4.3333333 | E17: =(E14+E15+E16)/3 -> 2 | F17: =(F14+F15+F16)/3 -> 2.3333333 | G17: =(G14+G15+G16)/3 -> 2.3333333 | H17: =(H14+H15+H16)/3 -> 3 | I17: =(I14+I15+I16)/3 -> 3 | J17: =(J14+J15+J16)/3 -> 3.6666667 | ... Q17: =(Q14+Q15+Q16)/3 -> 4
A18: LIQUIDITY
A19: MIN LIQ | B19: 0.15 | C19: =IF(CAELS!D12>30%,"1",IF(CAELS!D12>25%,"2",IF(CAELS!D12>20%,"3",IF(CAELS!D12>15%,"4","5")))) -> 1 | D19: =IF(CAELS!E12>30%,"1",IF(CAELS!E12>25%,"2",IF(CAELS!E12>20%,"3",IF(CAELS!E12>15%,"4","5")))) -> 3 | E19: =IF(CAELS!F12>30%,"1",IF(CAELS!F12>25%,"2",IF(CAELS!F12>20%,"3",IF(CAELS!F12>15%,"4","5")))) -> 1 | F19: =IF(CAELS!G12>30%,"1",IF(CAELS!G12>25%,"2",IF(CAELS!G12>20%,"3",IF(CAELS!G12>15%,"4","5")))) -> 1 | G19: =IF(CAELS!H12>30%,"1",IF(CAELS!H12>25%,"2",IF(CAELS!H12>20%,"3",IF(CAELS!H12>15%,"4","5")))) -> 1 | H19: =IF(CAELS!I12>30%,"1",IF(CAELS!I12>25%,"2",IF(CAELS!I12>20%,"3",IF(CAELS!I12>15%,"4","5")))) -> 1 | I19: =IF(CAELS!J12>30%,"1",IF(CAELS!J12>25%,"2",IF(CAELS!J12>20%,"3",IF(CAELS!J12>15%,"4","5")))) -> 1 | J19: =IF(CAELS!K12>30%,"1",IF(CAELS!K12>25%,"2",IF(CAELS!K12>20%,"3",IF(CAELS!K12>15%,"4","5")))) -> 1 | ... Q19: =IF(CAELS!R12>30%,"1",IF(CAELS!R12>25%,"2",IF(CAELS!R12>20%,"3",IF(CAELS!R12>15%,"4","5")))) -> 3
A20: TECH LIQ | C20: =IF(CAELS!D13>30%,"1",IF(CAELS!D13>25%,"2",IF(CAELS!D13>20%,"3",IF(CAELS!D13>15%,"4","5")))) -> 5 | D20: =IF(CAELS!E13>30%,"1",IF(CAELS!E13>25%,"2",IF(CAELS!E13>20%,"3",IF(CAELS!E13>15%,"4","5")))) -> 4 | E20: =IF(CAELS!F13>30%,"1",IF(CAELS!F13>25%,"2",IF(CAELS!F13>20%,"3",IF(CAELS!F13>15%,"4","5")))) -> 2 | F20: =IF(CAELS!G13>30%,"1",IF(CAELS!G13>25%,"2",IF(CAELS!G13>20%,"3",IF(CAELS!G13>15%,"4","5")))) -> 2 | G20: =IF(CAELS!H13>30%,"1",IF(CAELS!H13>25%,"2",IF(CAELS!H13>20%,"3",IF(CAELS!H13>15%,"4","5")))) -> 3 | H20: =IF(CAELS!I13>30%,"1",IF(CAELS!I13>25%,"2",IF(CAELS!I13>20%,"3",IF(CAELS!I13>15%,"4","5")))) -> 1 | I20: =IF(CAELS!J13>30%,"1",IF(CAELS!J13>25%,"2",IF(CAELS!J13>20%,"3",IF(CAELS!J13>15%,"4","5")))) -> 2 | J20: =IF(CAELS!K13>30%,"1",IF(CAELS!K13>25%,"2",IF(CAELS!K13>20%,"3",IF(CAELS!K13>15%,"4","5")))) -> 1 | ... Q20: =IF(CAELS!R13>30%,"1",IF(CAELS!R13>25%,"2",IF(CAELS!R13>20%,"3",IF(CAELS!R13>15%,"4","5")))) -> 4
A21: EB | B21: ≤ 25% | C21: =IF(CAELS!D14<15%,"1",IF(CAELS!D14<18%,"2",IF(CAELS!D14<22%,"3",IF(CAELS!D14<25%,"4","5")))) -> 1 | D21: =IF(CAELS!E14<15%,"1",IF(CAELS!E14<18%,"2",IF(CAELS!E14<22%,"3",IF(CAELS!E14<25%,"4","5")))) -> 1 | E21: =IF(CAELS!F14<15%,"1",IF(CAELS!F14<18%,"2",IF(CAELS!F14<22%,"3",IF(CAELS!F14<25%,"4","5")))) -> 1 | F21: =IF(CAELS!G14<15%,"1",IF(CAELS!G14<18%,"2",IF(CAELS!G14<22%,"3",IF(CAELS!G14<25%,"4","5")))) -> 1 | G21: =IF(CAELS!H14<15%,"1",IF(CAELS!H14<18%,"2",IF(CAELS!H14<22%,"3",IF(CAELS!H14<25%,"4","5")))) -> 1 | H21: =IF(CAELS!I14<15%,"1",IF(CAELS!I14<18%,"2",IF(CAELS!I14<22%,"3",IF(CAELS!I14<25%,"4","5")))) -> 1 | I21: =IF(CAELS!J14<15%,"1",IF(CAELS!J14<18%,"2",IF(CAELS!J14<22%,"3",IF(CAELS!J14<25%,"4","5")))) -> 1 | J21: =IF(CAELS!K14<15%,"1",IF(CAELS!K14<18%,"2",IF(CAELS!K14<22%,"3",IF(CAELS!K14<25%,"4","5")))) -> 1 | ... Q21: =IF(CAELS!R14<15%,"1",IF(CAELS!R14<18%,"2",IF(CAELS!R14<22%,"3",IF(CAELS!R14<25%,"4","5")))) -> 1
A22: LIQ/TA | C22: =IF(CAELS!D15>15%,"1",IF(CAELS!D15>12%,"2",IF(CAELS!D15>9%,"3",IF(CAELS!D15>6%,"4","5")))) -> 2 | D22: =IF(CAELS!E15>15%,"1",IF(CAELS!E15>12%,"2",IF(CAELS!E15>9%,"3",IF(CAELS!E15>6%,"4","5")))) -> 2 | E22: =IF(CAELS!F15>15%,"1",IF(CAELS!F15>12%,"2",IF(CAELS!F15>9%,"3",IF(CAELS!F15>6%,"4","5")))) -> 1 | F22: =IF(CAELS!G15>15%,"1",IF(CAELS!G15>12%,"2",IF(CAELS!G15>9%,"3",IF(CAELS!G15>6%,"4","5")))) -> 1 | G22: =IF(CAELS!H15>15%,"1",IF(CAELS!H15>12%,"2",IF(CAELS!H15>9%,"3",IF(CAELS!H15>6%,"4","5")))) -> 1 | H22: =IF(CAELS!I15>15%,"1",IF(CAELS!I15>12%,"2",IF(CAELS!I15>9%,"3",IF(CAELS!I15>6%,"4","5")))) -> 1 | I22: =IF(CAELS!J15>15%,"1",IF(CAELS!J15>12%,"2",IF(CAELS!J15>9%,"3",IF(CAELS!J15>6%,"4","5")))) -> 1 | J22: =IF(CAELS!K15>15%,"1",IF(CAELS!K15>12%,"2",IF(CAELS!K15>9%,"3",IF(CAELS!K15>6%,"4","5")))) -> 1 | ... Q22: =IF(CAELS!R15>15%,"1",IF(CAELS!R15>12%,"2",IF(CAELS!R15>9%,"3",IF(CAELS!R15>6%,"4","5")))) -> 2
C23: =(C19+C20+C21+C22)/4 -> 2.25 | D23: =(D19+D20+D21+D22)/4 -> 2.5 | E23: =(E19+E20+E21+E22)/4 -> 1.25 | F23: =(F19+F20+F21+F22)/4 -> 1.25 | G23: =(G19+G20+G21+G22)/4 -> 1.5 | H23: =(H19+H20+H21+H22)/4 -> 1 | I23: =(I19+I20+I21+I22)/4 -> 1.25 | J23: =(J19+J20+J21+J22)/4 -> 1 | ... Q23: =(Q19+Q20+Q21+Q22)/4 -> 2.5
A24: STRUCTURE
A25: NEA | B25: ≤ 10% | C25: =IF(CAELS!D16<6%,"1",IF(CAELS!D16<7%,"2",IF(CAELS!D16<8%,"3",IF(CAELS!D16<10%,"4","5")))) -> 5 | D25: =IF(CAELS!E16<6%,"1",IF(CAELS!E16<7%,"2",IF(CAELS!E16<8%,"3",IF(CAELS!E16<10%,"4","5")))) -> 4 | E25: =IF(CAELS!F16<6%,"1",IF(CAELS!F16<7%,"2",IF(CAELS!F16<8%,"3",IF(CAELS!F16<10%,"4","5")))) -> 5 | F25: =IF(CAELS!G16<6%,"1",IF(CAELS!G16<7%,"2",IF(CAELS!G16<8%,"3",IF(CAELS!G16<10%,"4","5")))) -> 5 | G25: =IF(CAELS!H16<6%,"1",IF(CAELS!H16<7%,"2",IF(CAELS!H16<8%,"3",IF(CAELS!H16<10%,"4","5")))) -> 5 | H25: =IF(CAELS!I16<6%,"1",IF(CAELS!I16<7%,"2",IF(CAELS!I16<8%,"3",IF(CAELS!I16<10%,"4","5")))) -> 5 | I25: =IF(CAELS!J16<6%,"1",IF(CAELS!J16<7%,"2",IF(CAELS!J16<8%,"3",IF(CAELS!J16<10%,"4","5")))) -> 5 | J25: =IF(CAELS!K16<6%,"1",IF(CAELS!K16<7%,"2",IF(CAELS!K16<8%,"3",IF(CAELS!K16<10%,"4","5")))) -> 5 | ... Q25: =IF(CAELS!R16<6%,"1",IF(CAELS!R16<7%,"2",IF(CAELS!R16<8%,"3",IF(CAELS!R16<10%,"4","5")))) -> 3
A26: LB | B26: ≤ 5% | C26: =IF(CAELS!D17<2%,"1",IF(CAELS!D17<3%,"2",IF(CAELS!D17<4%,"3",IF(CAELS!D17<5%,"4","5")))) -> 3 | D26: =IF(CAELS!E17<2%,"1",IF(CAELS!E17<3%,"2",IF(CAELS!E17<4%,"3",IF(CAELS!E17<5%,"4","5")))) -> 5 | E26: =IF(CAELS!F17<2%,"1",IF(CAELS!F17<3%,"2",IF(CAELS!F17<4%,"3",IF(CAELS!F17<5%,"4","5")))) -> 1 | F26: =IF(CAELS!G17<2%,"1",IF(CAELS!G17<3%,"2",IF(CAELS!G17<4%,"3",IF(CAELS!G17<5%,"4","5")))) -> 5 | G26: =IF(CAELS!H17<2%,"1",IF(CAELS!H17<3%,"2",IF(CAELS!H17<4%,"3",IF(CAELS!H17<5%,"4","5")))) -> 5 | H26: =IF(CAELS!I17<2%,"1",IF(CAELS!I17<3%,"2",IF(CAELS!I17<4%,"3",IF(CAELS!I17<5%,"4","5")))) -> 5 | I26: =IF(CAELS!J17<2%,"1",IF(CAELS!J17<3%,"2",IF(CAELS!J17<4%,"3",IF(CAELS!J17<5%,"4","5")))) -> 5 | J26: =IF(CAELS!K17<2%,"1",IF(CAELS!K17<3%,"2",IF(CAELS!K17<4%,"3",IF(CAELS!K17<5%,"4","5")))) -> 5 | ... Q26: =IF(CAELS!R17<2%,"1",IF(CAELS!R17<3%,"2",IF(CAELS!R17<4%,"3",IF(CAELS!R17<5%,"4","5")))) -> 5
A27: FITD | B27: ≤ 5% | C27: =IF(CAELS!D18<2%,"1",IF(CAELS!D18<3%,"2",IF(CAELS!D18<4%,"3",IF(CAELS!D18<5%,"4","5")))) -> 1 | D27: =IF(CAELS!E18<2%,"1",IF(CAELS!E18<3%,"2",IF(CAELS!E18<4%,"3",IF(CAELS!E18<5%,"4","5")))) -> 3 | E27: =IF(CAELS!F18<2%,"1",IF(CAELS!F18<3%,"2",IF(CAELS!F18<4%,"3",IF(CAELS!F18<5%,"4","5")))) -> 1 | F27: =IF(CAELS!G18<2%,"1",IF(CAELS!G18<3%,"2",IF(CAELS!G18<4%,"3",IF(CAELS!G18<5%,"4","5")))) -> 5 | G27: =IF(CAELS!H18<2%,"1",IF(CAELS!H18<3%,"2",IF(CAELS!H18<4%,"3",IF(CAELS!H18<5%,"4","5")))) -> 5 | H27: =IF(CAELS!I18<2%,"1",IF(CAELS!I18<3%,"2",IF(CAELS!I18<4%,"3",IF(CAELS!I18<5%,"4","5")))) -> 5 | I27: =IF(CAELS!J18<2%,"1",IF(CAELS!J18<3%,"2",IF(CAELS!J18<4%,"3",IF(CAELS!J18<5%,"4","5")))) -> 5 | J27: =IF(CAELS!K18<2%,"1",IF(CAELS!K18<3%,"2",IF(CAELS!K18<4%,"3",IF(CAELS!K18<5%,"4","5")))) -> 5 | ... Q27: =IF(CAELS!R18<2%,"1",IF(CAELS!R18<3%,"2",IF(CAELS!R18<4%,"3",IF(CAELS!R18<5%,"4","5")))) -> 1
A28: FICC | B28: ≤ 40% | C28: =IF(CAELS!D19<20%,"1",IF(CAELS!D19<25%,"2",IF(CAELS!D19<30%,"3",IF(CAELS!D19<40%,"4","5")))) -> 1 | D28: =IF(CAELS!E19<20%,"1",IF(CAELS!E19<25%,"2",IF(CAELS!E19<30%,"3",IF(CAELS!E19<40%,"4","5")))) -> 1 | E28: =IF(CAELS!F19<20%,"1",IF(CAELS!F19<25%,"2",IF(CAELS!F19<30%,"3",IF(CAELS!F19<40%,"4","5")))) -> 1 | F28: =IF(CAELS!G19<20%,"1",IF(CAELS!G19<25%,"2",IF(CAELS!G19<30%,"3",IF(CAELS!G19<40%,"4","5")))) -> 2 | G28: =IF(CAELS!H19<20%,"1",IF(CAELS!H19<25%,"2",IF(CAELS!H19<30%,"3",IF(CAELS!H19<40%,"4","5")))) -> 2 | H28: =IF(CAELS!I19<20%,"1",IF(CAELS!I19<25%,"2",IF(CAELS!I19<30%,"3",IF(CAELS!I19<40%,"4","5")))) -> 2 | I28: =IF(CAELS!J19<20%,"1",IF(CAELS!J19<25%,"2",IF(CAELS!J19<30%,"3",IF(CAELS!J19<40%,"4","5")))) -> 2 | J28: =IF(CAELS!K19<20%,"1",IF(CAELS!K19<25%,"2",IF(CAELS!K19<30%,"3",IF(CAELS!K19<40%,"4","5")))) -> 2 | ... Q28: =IF(CAELS!R19<20%,"1",IF(CAELS!R19<25%,"2",IF(CAELS!R19<30%,"3",IF(CAELS!R19<40%,"4","5")))) -> 1
C29: =(C25+C26+C27+C28)/4 -> 2.5 | D29: =(D25+D26+D27+D28)/4 -> 3.25 | E29: =(E25+E26+E27+E28)/4 -> 2 | F29: =(F25+F26+F27+F28)/4 -> 4.25 | G29: =(G25+G26+G27+G28)/4 -> 4.25 | H29: =(H25+H26+H27+H28)/4 -> 4.25 | I29: =(I25+I26+I27+I28)/4 -> 4.25 | J29: =(J25+J26+J27+J28)/4 -> 4.25 | ... Q29: =(Q25+Q26+Q27+Q28)/4 -> 2.5
A30: FINAL RATING | C30: =(C9+C12+C17+C23)/4 -> 1.7708333 | D30: =(D9+D12+D17+D23)/4 -> 2.2083333 | E30: =(E9+E12+E17+E23)/4 -> 1.375 | F30: =(F9+F12+F17+F23)/4 -> 1.3958333 | G30: =(G9+G12+G17+G23)/4 -> 1.4583333 | H30: =(H9+H12+H17+H23)/4 -> 1.5625 | I30: =(I9+I12+I17+I23)/4 -> 1.625 | J30: =(J9+J12+J17+J23)/4 -> 1.7291667 | ... Q30: =(Q9+Q12+Q17+Q23)/4 -> 2.1875

Sheet Compliance Status
B2: 2010 Audited | C2: 2017 audited | D2: 43101 | E2: 43132 | F2: 43160 | G2: 43191 | H2: 43221 | I2: 43252 | J2: 43282 | K2: 43313 | L2: 43344 | M2: 43374 | N2: 43405 | O2: 43435 | P2: AUDITED 2018 | Q2: 43467 | R2: 43009 | S2: 43040 | T2: 43070
A3: CORE CAPITAL | B3: =IF(CAELS!D3>10,"Compliant","Non-Compliant") -> Compliant | C3: =IF(CAELS!E3>10,"Compliant","Non-Compliant") -> Compliant | D3: =IF(CAELS!F3>10,"Compliant","Non-Compliant") -> Compliant | E3: =IF(CAELS!G3>10,"Compliant","Non-Compliant") -> Compliant | F3: =IF(CAELS!H3>10,"Compliant","Non-Compliant") -> Compliant | G3: =IF(CAELS!I3>10,"Compliant","Non-Compliant") -> Compliant | H3: =IF(CAELS!J3>10,"Compliant","Non-Compliant") -> Compliant | I3: =IF(CAELS!K3>10,"Compliant","Non-Compliant") -> Compliant | ... P3: =IF(CAELS!R3>10,"Compliant","Non-Compliant") -> Compliant | Q3: =IF(CAELS!#REF!>10,"Compliant","Non-Compliant") -> #REF! | R3: =IF(CAELS!#REF!>10,"Compliant","Non-Compliant") -> #REF! | S3: =IF(CAELS!#REF!>10,"Compliant","Non-Compliant") -> #REF! | T3: =IF(CAELS!#REF!>10,"Compliant","Non-Compliant") -> #REF!
A4: CCA (Min 10%) | B4: =IF(CAELS!D4>10%,"Compliant","Non-Compliant") -> Compliant | C4: =IF(CAELS!E4>10%,"Compliant","Non-Compliant") -> Compliant | D4: =IF(CAELS!F4>10%,"Compliant","Non-Compliant") -> Compliant | E4: =IF(CAELS!G4>10%,"Compliant","Non-Compliant") -> Compliant | F4: =IF(CAELS!H4>10%,"Compliant","Non-Compliant") -> Compliant | G4: =IF(CAELS!I4>10%,"Compliant","Non-Compliant") -> Compliant | H4: =IF(CAELS!J4>10%,"Compliant","Non-Compliant") -> Compliant | I4: =IF(CAELS!K4>10%,"Compliant","Non-Compliant") -> Compliant | ... P4: =IF(CAELS!R4>10%,"Compliant","Non-Compliant") -> Compliant | Q4: =IF(CAELS!#REF!>10%,"Compliant","Non-Compliant") -> #REF! | R4: =IF(CAELS!#REF!>10%,"Compliant","Non-Compliant") -> #REF! | S4: =IF(CAELS!#REF!>10%,"Compliant","Non-Compliant") -> #REF! | T4: =IF(CAELS!#REF!>10%,"Compliant","Non-Compliant") -> #REF!
A5: ICA (Min 8%) | B5: =IF(CAELS!D6>8%,"Compliant","Non-Compliant") -> Non-Compliant | C5: =IF(CAELS!E6>8%,"Compliant","Non-Compliant") -> Compliant | D5: =IF(CAELS!F6>8%,"Compliant","Non-Compliant") -> Non-Compliant | E5: =IF(CAELS!G6>8%,"Compliant","Non-Compliant") -> Non-Compliant | F5: =IF(CAELS!H6>8%,"Compliant","Non-Compliant") -> Non-Compliant | G5: =IF(CAELS!I6>8%,"Compliant","Non-Compliant") -> Non-Compliant | H5: =IF(CAELS!J6>8%,"Compliant","Non-Compliant") -> Non-Compliant | I5: =IF(CAELS!K6>8%,"Compliant","Non-Compliant") -> Non-Compliant | ... P5: =IF(CAELS!R6>8%,"Compliant","Non-Compliant") -> Non-Compliant | Q5: =IF(CAELS!#REF!>8%,"Compliant","Non-Compliant") -> #REF! | R5: =IF(CAELS!#REF!>8%,"Compliant","Non-Compliant") -> #REF! | S5: =IF(CAELS!#REF!>8%,"Compliant","Non-Compliant") -> #REF! | T5: =IF(CAELS!#REF!>8%,"Compliant","Non-Compliant") -> #REF!
A6: CCD (Min 8%) | B6: =IF(CAELS!D5>8%,"Compliant","Non-Compiant") -> Compliant | C6: =IF(CAELS!E5>8%,"Compliant","Non-Compiant") -> Compliant | D6: =IF(CAELS!F5>8%,"Compliant","Non-Compiant") -> Compliant | E6: =IF(CAELS!G5>8%,"Compliant","Non-Compiant") -> Compliant | F6: =IF(CAELS!H5>8%,"Compliant","Non-Compiant") -> Compliant | G6: =IF(CAELS!I5>8%,"Compliant","Non-Compiant") -> Compliant | H6: =IF(CAELS!J5>8%,"Compliant","Non-Compiant") -> Compliant | I6: =IF(CAELS!K5>8%,"Compliant","Non-Compiant") -> Compliant | ... P6: =IF(CAELS!R5>8%,"Compliant","Non-Compiant") -> Compliant | Q6: =IF(CAELS!#REF!>8%,"Compliant","Non-Compiant") -> #REF! | R6: =IF(CAELS!#REF!>8%,"Compliant","Non-Compiant") -> #REF! | S6: =IF(CAELS!#REF!>8%,"Compliant","Non-Compiant") -> #REF! | T6: =IF(CAELS!#REF!>8%,"Compliant","Non-Compiant") -> #REF!
A7: NPL(5%)
A8: Liquidity(15%) | B8: =IF(CAELS!D12>15%,"Compliant","Non-Compliant") -> Compliant | C8: =IF(CAELS!E12>15%,"Compliant","Non-Compliant") -> Compliant | D8: =IF(CAELS!F12>15%,"Compliant","Non-Compliant") -> Compliant | E8: =IF(CAELS!G12>15%,"Compliant","Non-Compliant") -> Compliant | F8: =IF(CAELS!H12>15%,"Compliant","Non-Compliant") -> Compliant | G8: =IF(CAELS!I12>15%,"Compliant","Non-Compliant") -> Compliant | H8: =IF(CAELS!J12>15%,"Compliant","Non-Compliant") -> Compliant | I8: =IF(CAELS!K12>15%,"Compliant","Non-Compliant") -> Compliant | ... P8: =IF(CAELS!R12>15%,"Compliant","Non-Compliant") -> Compliant | Q8: =IF(CAELS!#REF!>15%,"Compliant","Non-Compliant") -> #REF! | R8: =IF(CAELS!#REF!>15%,"Compliant","Non-Compliant") -> #REF! | S8: =IF(CAELS!#REF!>15%,"Compliant","Non-Compliant") -> #REF! | T8: =IF(CAELS!#REF!>15%,"Compliant","Non-Compliant") -> #REF!
A9: NEA (Max 10%) | B9: =IF(CAELS!D16<10%,"Compliant","Non-Compliant") -> Non-Compliant | C9: =IF(CAELS!E16<10%,"Compliant","Non-Compliant") -> Compliant | D9: =IF(CAELS!F16<10%,"Compliant","Non-Compliant") -> Non-Compliant | E9: =IF(CAELS!G16<10%,"Compliant","Non-Compliant") -> Non-Compliant | F9: =IF(CAELS!H16<10%,"Compliant","Non-Compliant") -> Non-Compliant | G9: =IF(CAELS!I16<10%,"Compliant","Non-Compliant") -> Non-Compliant | H9: =IF(CAELS!J16<10%,"Compliant","Non-Compliant") -> Non-Compliant | I9: =IF(CAELS!K16<10%,"Compliant","Non-Compliant") -> Non-Compliant | ... P9: =IF(CAELS!R16<10%,"Compliant","Non-Compliant") -> Compliant | Q9: =IF(CAELS!#REF!<10%,"Compliant","Non-Compliant") -> #REF! | R9: =IF(CAELS!#REF!<10%,"Compliant","Non-Compliant") -> #REF! | S9: =IF(CAELS!#REF!<10%,"Compliant","Non-Compliant") -> #REF! | T9: =IF(CAELS!#REF!<10%,"Compliant","Non-Compliant") -> #REF!
A10: LB ratio (Max 5%) | B10: =IF(CAELS!D17<5%,"Compliant","Non-Compliant") -> Compliant | C10: =IF(CAELS!E17<5%,"Compliant","Non-Compliant") -> Non-Compliant | D10: =IF(CAELS!F17<5%,"Compliant","Non-Compliant") -> Compliant | E10: =IF(CAELS!G17<5%,"Compliant","Non-Compliant") -> Non-Compliant | F10: =IF(CAELS!H17<5%,"Compliant","Non-Compliant") -> Non-Compliant | G10: =IF(CAELS!I17<5%,"Compliant","Non-Compliant") -> Non-Compliant | H10: =IF(CAELS!J17<5%,"Compliant","Non-Compliant") -> Non-Compliant | I10: =IF(CAELS!K17<5%,"Compliant","Non-Compliant") -> Non-Compliant | ... P10: =IF(CAELS!R17<5%,"Compliant","Non-Compliant") -> Non-Compliant | Q10: =IF(CAELS!#REF!<5%,"Compliant","Non-Compliant") -> #REF! | R10: =IF(CAELS!#REF!<5%,"Compliant","Non-Compliant") -> #REF! | S10: =IF(CAELS!#REF!<5%,"Compliant","Non-Compliant") -> #REF! | T10: =IF(CAELS!#REF!<5%,"Compliant","Non-Compliant") -> #REF!
A11: FITD (Max 5%) | B11: =IF(CAELS!D18<5%,"Compliant","Non-Compliant") -> Compliant | C11: =IF(CAELS!E18<5%,"Compliant","Non-Compliant") -> Compliant | D11: =IF(CAELS!F18<5%,"Compliant","Non-Compliant") -> Compliant | E11: =IF(CAELS!G18<5%,"Compliant","Non-Compliant") -> Non-Compliant | F11: =IF(CAELS!H18<5%,"Compliant","Non-Compliant") -> Non-Compliant | G11: =IF(CAELS!I18<5%,"Compliant","Non-Compliant") -> Non-Compliant | H11: =IF(CAELS!J18<5%,"Compliant","Non-Compliant") -> Non-Compliant | I11: =IF(CAELS!K18<5%,"Compliant","Non-Compliant") -> Non-Compliant | ... P11: =IF(CAELS!R18<5%,"Compliant","Non-Compliant") -> Compliant | Q11: =IF(CAELS!#REF!<5%,"Compliant","Non-Compliant") -> #REF! | R11: =IF(CAELS!#REF!<5%,"Compliant","Non-Compliant") -> #REF! | S11: =IF(CAELS!#REF!<5%,"Compliant","Non-Compliant") -> #REF! | T11: =IF(CAELS!#REF!<5%,"Compliant","Non-Compliant") -> #REF!
A12: FICC (Max 40%) | B12: =IF(CAELS!D19<40%,"Compliant","Non-Compliant") -> Compliant | C12: =IF(CAELS!E19<40%,"Compliant","Non-Compliant") -> Compliant | D12: =IF(CAELS!F19<40%,"Compliant","Non-Compliant") -> Compliant | E12: =IF(CAELS!G19<40%,"Compliant","Non-Compliant") -> Compliant | F12: =IF(CAELS!H19<40%,"Compliant","Non-Compliant") -> Compliant | G12: =IF(CAELS!I19<40%,"Compliant","Non-Compliant") -> Compliant | H12: =IF(CAELS!J19<40%,"Compliant","Non-Compliant") -> Compliant | I12: =IF(CAELS!K19<40%,"Compliant","Non-Compliant") -> Compliant | ... P12: =IF(CAELS!R19<40%,"Compliant","Non-Compliant") -> Compliant | Q12: =IF(CAELS!#REF!<40%,"Compliant","Non-Compliant") -> #REF! | R12: =IF(CAELS!#REF!<40%,"Compliant","Non-Compliant") -> #REF! | S12: =IF(CAELS!#REF!<40%,"Compliant","Non-Compliant") -> #REF! | T12: =IF(CAELS!#REF!<40%,"Compliant","Non-Compliant") -> #REF!
A13: EB ratio (Max 25%) | B13: =IF(CAELS!D14<25%,"Compliant","Non-Compliant") -> Compliant | C13: =IF(CAELS!E14<25%,"Compliant","Non-Compliant") -> Compliant | D13: =IF(CAELS!F14<25%,"Compliant","Non-Compliant") -> Compliant | E13: =IF(CAELS!G14<25%,"Compliant","Non-Compliant") -> Compliant | F13: =IF(CAELS!H14<25%,"Compliant","Non-Compliant") -> Compliant | G13: =IF(CAELS!I14<25%,"Compliant","Non-Compliant") -> Compliant | H13: =IF(CAELS!J14<25%,"Compliant","Non-Compliant") -> Compliant | I13: =IF(CAELS!K14<25%,"Compliant","Non-Compliant") -> Compliant | ... P13: =IF(CAELS!R14<25%,"Compliant","Non-Compliant") -> Compliant | Q13: =IF(CAELS!#REF!<25%,"Compliant","Non-Compliant") -> #REF! | R13: =IF(CAELS!#REF!<25%,"Compliant","Non-Compliant") -> #REF! | S13: =IF(CAELS!#REF!<25%,"Compliant","Non-Compliant") -> #REF! | T13: =IF(CAELS!#REF!<25%,"Compliant","Non-Compliant") -> #REF!
A14: A=S+L | B14: =IF('Evolutive SFP'!B27='Evolutive SFP'!B49,"BALANCING","NOT BALANCING") -> BALANCING | C14: =IF('Evolutive SFP'!C27='Evolutive SFP'!C49,"BALANCING","NOT BALANCING") -> NOT BALANCING | D14: =IF('Evolutive SFP'!D27='Evolutive SFP'!D49,"BALANCING","NOT BALANCING") -> BALANCING | E14: =IF('Evolutive SFP'!E27='Evolutive SFP'!E49,"BALANCING","NOT BALANCING") -> NOT BALANCING | F14: =IF('Evolutive SFP'!F27='Evolutive SFP'!F49,"BALANCING","NOT BALANCING") -> BALANCING | G14: =IF('Evolutive SFP'!G27='Evolutive SFP'!G49,"BALANCING","NOT BALANCING") -> BALANCING | H14: =IF('Evolutive SFP'!H27='Evolutive SFP'!H49,"BALANCING","NOT BALANCING") -> BALANCING | I14: =IF('Evolutive SFP'!I27='Evolutive SFP'!I49,"BALANCING","NOT BALANCING") -> BALANCING | ... P14: =IF('Evolutive SFP'!P27='Evolutive SFP'!P49,"BALANCING","NOT BALANCING") -> NOT BALANCING | Q14: =IF('Evolutive SFP'!#REF!='Evolutive SFP'!#REF!,"BALANCING","NOT BALANCING") -> #REF! | R14: =IF('Evolutive SFP'!#REF!='Evolutive SFP'!#REF!,"BALANCING","NOT BALANCING") -> #REF! | S14: =IF('Evolutive SFP'!Q27='Evolutive SFP'!Q49,"BALANCING","NOT BALANCING") -> BALANCING | T14: =IF('Evolutive SFP'!R27='Evolutive SFP'!R49,"BALANCING","NOT BALANCING") -> BALANCING

Sheet CashFlow Stmnt
A1: STATEMENT OF CASHFLOWS FOR THE YEAR ENDED 31ST DECEMBER 2015
B2: 2014 | C2: 2015 | D2: Audited -2016 | E2: Variance
A3: Cash flows from operating activities
A4: Interest receipts
A5: Interest Payments | J5: 474150394
A6: Payment to employees and suppliers | J6: 65541583
A7: Other operating income | J7: -58199014
A8: (Increase)/Decrease in Operating assets | B8: =B4+B5+B6+B7 -> 0 | C8: =SUM(C4:C7) -> 0 | D8: =SUM(D4:D7) -> 0 | J8: -205444477
A9: Net loans to members | J9: -467055768
A10: Recievables and prepayments | J10: -70311815
A11: Trade and Other Receivables | J11: =SUM(J5:J10) -> -261319097
A12: Inventories
A13: Short term investments
A14: Increase/(Decrease) in Operating liabilities | B14: =SUM(B9:B13) -> 0 | C14: =SUM(C9:C13) -> 0 | D14: =SUM(D9:D13) -> 0
A15: Deposits from members
A16: Trade and Accrued Expenses
A17: Sundry creditors
A18: Net cashflow from operating activities before income taxes | B18: =B8+B14+B15+B16+B17 -> 0 | C18: =C8+C14+C15+C16+C17 -> 0 | D18: =D8+D14+D15+D16+D17 -> 0
A19: Income tax paid
A20: Net Cash from Operating activities | F20: 100000
A22: Cashflow from investing activities
A23: Purchase of Property and equipment
A24: Purchase of intangible assets
A25: Increase in Other Assets
A26: Purchase of Investment Securities
A27: Dividends Received
A28: Net Cash from investing activities | B28: =SUM(B23:B27) -> 0 | C28: =SUM(C23:C27) -> 0 | D28: =SUM(D23:D27) -> 0
A30: Cashflow from financing activities
A31: Share capital contributions
A32: Proceeds from long-term borrowings
A33: Prior Year Adjustments
A34: Housing Contributions Plaza
A35: Repayments of long term borrowings
A36: Dividend paid
A37: Net cash from financing activities | B37: =SUM(B31:B36) -> 0 | C37: =SUM(C31:C36) -> 0 | D37: =SUM(D31:D36) -> 0
A38: Net (Decrease)/Increase in cash and cash equivalent | B38: =B20+B28+B37 -> 0 | C38: =C20+C28+C37 -> 0 | D38: =D20+D28+D37 -> 0
A39: Cash and cash equivalent at the beginning of the year
A40: Cash and cash equivalent at the end of the year | B40: =SUM(B38:B39) -> 0 | C40: =SUM(C38:C39) -> 0 | D40: =SUM(D38:D39) -> 0

Sheet FORM 4
D1: 43160
B2: CLASSIFICATION | C2: NO. OF A/Cs | D2: OUTSTANDING LOAN PORTFOLIO(Kshs) | E2: REQUIRED PROVISION | F2: REQUIRED PROVISION AMOUNT(Kshs)
B3: Performing | C3: 5778 | D3: 4.344483e+08 | E3: 0.01 | F3: =D3*E3 -> 4344483
B4: Watch | C4: 537 | D4: 1.0292549e+08 | E4: 0.05 | F4: =D4*E4 -> 5146274.5
B5: Substandard | C5: 112 | D5: 5388821.3 | E5: 0.25 | F5: =D5*E5 -> 1347205.3
B6: Doubtful | C6: 17 | D6: 1600129.2 | E6: 0.5 | F6: =D6*E6 -> 800064.59
B7: Loss | C7: 5829 | D7: 1.415328e+08 | E7: 1 | F7: =D7*E7 -> 1.415328e+08
B8: subtotal | C8: 12273 | D8: 6.8589554e+08 | E8: =SUM(E3:E7) -> 1.81 | F8: =SUM(F3:F7) -> 1.5317083e+08 | H8: NPL | I8: =(D5+D6+D7)/D8 -> 0.21653698 | AQ8: ='FORM 4'!D135+'FORM 4'!D1 -> 37607460
D10: 43252
B11: CLASSIFICATION | C11: NO. OF A/Cs | D11: OUTSTANDING LOAN PORTFOLIO(Kshs) | E11: REQUIRED PROVISION | F11: REQUIRED PROVISION AMOUNT(Kshs)
B12: Performing | C12: 6832 | D12: 4.6801084e+08 | E12: 0.01 | F12: =D12*E12 -> 4680108.4
B13: Watch | C13: 808 | D13: 36252240 | E13: 0.05 | F13: =D13*E13 -> 1812612
B14: Substandard | C14: 618 | D14: 34391760 | E14: 0.25 | F14: =D14*E14 -> 8597940.1
B15: Doubtful | C15: 556 | D15: 26842797 | E15: 0.5 | F15: =D15*E15 -> 13421398
B16: Loss | C16: 3542 | D16: 1.3041674e+08 | E16: 1 | F16: =D16*E16 -> 1.3041674e+08
B17: subtotal | C17: =SUM(C12:C16) -> 12356 | D17: =SUM(D12:D16) -> 6.9591438e+08 | E17: 1.81 | F17: =SUM(F12:F16) -> 1.589288e+08 | H17: NPL | I17: =(D14+D15+D16)/D17 -> 0.27539494
D19: 43344
B20: CLASSIFICATION | C20: NO. OF A/Cs | D20: OUTSTANDING LOAN PORTFOLIO(Kshs) | E20: REQUIRED PROVISION | F20: REQUIRED PROVISION AMOUNT(Kshs)
B21: Performing | C21: 7497 | D21: 4.734315e+08 | E21: 0.01 | F21: =D21*E21 -> 4734315
B22: Watch | C22: 801 | D22: 30188934 | E22: 0.05 | F22: =D22*E22 -> 1509446.7
B23: Substandard | C23: 628 | D23: 28438963 | E23: 0.25 | F23: =D23*E23 -> 7109740.6
B24: Doubtful | C24: 362 | D24: 20850327 | E24: 0.5 | F24: =D24*E24 -> 10425163
B25: Loss | C25: 3670 | D25: 1.3933866e+08 | E25: 1 | F25: =D25*E25 -> 1.3933866e+08
B26: subtotal | C26: =SUM(C21:C25) -> 12958 | D26: =SUM(D21:D25) -> 6.9224839e+08 | E26: 1.81 | F26: =SUM(F21:F25) -> 1.6311733e+08 | H26: NPL | I26: =(D23+D24+D25)/D26 -> 0.27248594
D28: 43435
B29: CLASSIFICATION | C29: NO. OF A/Cs | D29: OUTSTANDING LOAN PORTFOLIO(Kshs) | E29: REQUIRED PROVISION | F29: REQUIRED PROVISION AMOUNT(Kshs)
B30: Performing | C30: 4512 | D30: 4.1136166e+08 | E30: 0.01 | F30: =D30*E30 -> 4113616.6
B31: Watch | C31: 650 | D31: 23190414 | E31: 0.05 | F31: =D31*E31 -> 1159520.7
B32: Substandard | C32: 735 | D32: 17889381 | E32: 0.25 | F32: =D32*E32 -> 4472345.2
B33: Doubtful | C33: 651 | D33: 24480323 | E33: 0.5 | F33: =D33*E33 -> 12240162
B34: Loss | C34: 3559 | D34: 1.392714e+08 | E34: 1 | F34: =D34*E34 -> 1.392714e+08
B35: subtotal | C35: =SUM(C30:C34) -> 10107 | D35: =SUM(D30:D34) -> 6.1619317e+08 | E35: 1.81 | F35: =SUM(F30:F34) -> 1.6125704e+08 | H35: NPL | I35: =(D32+D33+D34)/D35 -> 0.29477948
D38: Audited 2018
B39: CLASSIFICATION | C39: NO. OF A/Cs | D39: OUTSTANDING LOAN PORTFOLIO(Kshs) | E39: REQUIRED PROVISION | F39: REQUIRED PROVISION AMOUNT(Kshs)
B40: Performing | C40: 4512 | D40: 4.1136166e+08 | E40: 0.01 | F40: =D40*E40 -> 4113616.6
B41: Watch | C41: 650 | D41: 23190414 | E41: 0.05 | F41: =D41*E41 -> 1159520.7
B42: Substandard | C42: 735 | D42: 17889381 | E42: 0.25 | F42: =D42*E42 -> 4472345.2
B43: Doubtful | C43: 651 | D43: 24480323 | E43: 0.5 | F43: =D43*E43 -> 12240162
B44: Loss | C44: 3559 | D44: 1.392714e+08 | E44: 1 | F44: =D44*E44 -> 1.392714e+08
B45: subtotal | C45: =SUM(C40:C44) -> 10107 | D45: =SUM(D40:D44) -> 6.1619317e+08 | E45: 1.81 | F45: =SUM(F40:F44) -> 1.6125704e+08 | H45: NPL | I45: =(D42+D43+D44)/D45 -> 0.29477948
D49: 43525
B50: CLASSIFICATION | C50: NO. OF A/Cs | D50: OUTSTANDING LOAN PORTFOLIO(Kshs) | E50: REQUIRED PROVISION | F50: REQUIRED PROVISION AMOUNT(Kshs)
B51: Performing | E51: 0.01 | F51: =D51*E51 -> 0
B52: Watch | E52: 0.05 | F52: =D52*E52 -> 0
B53: Substandard | E53: 0.25 | F53: =D53*E53 -> 0
B54: Doubtful | E54: 0.5 | F54: =D54*E54 -> 0
B55: Loss | E55: 1 | F55: =D55*E55 -> 0
B56: subtotal | C56: 12273 | D56: 6.8589554e+08 | E56: =SUM(E51:E55) -> 1.81 | F56: =SUM(F51:F55) -> 0 | H56: NPL | I56: =(D53+D54+D55)/D56 -> 0
D58: 43617
B59: CLASSIFICATION | C59: NO. OF A/Cs | D59: OUTSTANDING LOAN PORTFOLIO(Kshs) | E59: REQUIRED PROVISION | F59: REQUIRED PROVISION AMOUNT(Kshs)
B60: Performing | E60: 0.01 | F60: =D60*E60 -> 0
B61: Watch | E61: 0.05 | F61: =D61*E61 -> 0
B62: Substandard | E62: 0.25 | F62: =D62*E62 -> 0
B63: Doubtful | E63: 0.5 | F63: =D63*E63 -> 0
B64: Loss | E64: 1 | F64: =D64*E64 -> 0
B65: subtotal | C65: =SUM(C60:C64) -> 0 | D65: =SUM(D60:D64) -> 0 | E65: 1.81 | F65: =SUM(F60:F64) -> 0 | H65: NPL | I65: =(D62+D63+D64)/D65 -> #DIV/0!
D67: 43709
B68: CLASSIFICATION | C68: NO. OF A/Cs | D68: OUTSTANDING LOAN PORTFOLIO(Kshs) | E68: REQUIRED PROVISION | F68: REQUIRED PROVISION AMOUNT(Kshs)
B69: Performing | E69: 0.01 | F69: =D69*E69 -> 0
B70: Watch | E70: 0.05 | F70: =D70*E70 -> 0
B71: Substandard | E71: 0.25 | F71: =D71*E71 -> 0
B72: Doubtful | E72: 0.5 | F72: =D72*E72 -> 0
B73: Loss | E73: 1 | F73: =D73*E73 -> 0
B74: subtotal | C74: =SUM(C69:C73) -> 0 | D74: =SUM(D69:D73) -> 0 | E74: 1.81 | F74: =SUM(F69:F73) -> 0 | H74: NPL | I74: =(D71+D72+D73)/D74 -> #DIV/0!
D76: 43800
B77: CLASSIFICATION | C77: NO. OF A/Cs | D77: OUTSTANDING LOAN PORTFOLIO(Kshs) | E77: REQUIRED PROVISION | F77: REQUIRED PROVISION AMOUNT(Kshs)
B78: Performing | E78: 0.01 | F78: =D78*E78 -> 0
B79: Watch | E79: 0.05 | F79: =D79*E79 -> 0
B80: Substandard | E80: 0.25 | F80: =D80*E80 -> 0
B81: Doubtful | E81: 0.5 | F81: =D81*E81 -> 0
B82: Loss | E82: 1 | F82: =D82*E82 -> 0
B83: subtotal | C83: =SUM(C78:C82) -> 0 | D83: =SUM(D78:D82) -> 0 | E83: 1.81 | F83: =SUM(F78:F82) -> 0 | H83: NPL | I83: =(D80+D81+D82)/D83 -> #DIV/0!
D86: Audited 2019
B87: CLASSIFICATION | C87: NO. OF A/Cs | D87: OUTSTANDING LOAN PORTFOLIO(Kshs) | E87: REQUIRED PROVISION | F87: REQUIRED PROVISION AMOUNT(Kshs)
B88: Performing | E88: 0.01 | F88: =D88*E88 -> 0
B89: Watch | E89: 0.05 | F89: =D89*E89 -> 0
B90: Substandard | E90: 0.25 | F90: =D90*E90 -> 0
B91: Doubtful | E91: 0.5 | F91: =D91*E91 -> 0
B92: Loss | E92: 1 | F92: =D92*E92 -> 0
B93: subtotal | C93: =SUM(C88:C92) -> 0 | D93: =SUM(D88:D92) -> 0 | E93: 1.81 | F93: =SUM(F88:F92) -> 0 | H93: NPL | I93: =(D90+D91+D92)/D93 -> #DIV/0!
D95: 43891
B96: CLASSIFICATION | C96: NO. OF A/Cs | D96: OUTSTANDING LOAN PORTFOLIO(Kshs) | E96: REQUIRED PROVISION | F96: REQUIRED PROVISION AMOUNT(Kshs)
B97: Performing | C97: 5333 | D97: 4.7333004e+08 | E97: 0.01 | F97: =D97*E97 -> 4733300.4
B98: Watch | C98: 276 | D98: 18748086 | E98: 0.05 | F98: =D98*E98 -> 937404.28
B99: Substandard | C99: 228 | D99: 6855993.5 | E99: 0.25 | F99: =D99*E99 -> 1713998.4
B100: Doubtful | C100: 112 | D100: 6367044.8 | E100: 0.5 | F100: =D100*E100 -> 3183522.4
B101: Loss | C101: 4561 | D101: 1.584073e+08 | E101: 1 | F101: =D101*E101 -> 1.584073e+08
B102: subtotal | C102: 12273 | D102: 6.8589554e+08 | E102: =SUM(E97:E101) -> 1.81 | F102: =SUM(F97:F101) -> 1.6897552e+08
D104: 43983
B105: CLASSIFICATION | C105: NO. OF A/Cs | D105: OUTSTANDING LOAN PORTFOLIO(Kshs) | E105: REQUIRED PROVISION | F105: REQUIRED PROVISION AMOUNT(Kshs)
B106: Performing | C106: 4523 | D106: 4.4798548e+08 | E106: 0.01 | F106: =D106*E106 -> 4479854.8
B107: Watch | C107: 551 | D107: 22735806 | E107: 0.05 | F107: =D107*E107 -> 1136790.3
B108: Substandard | C108: 476 | D108: 9634985.9 | E108: 0.25 | F108: =D108*E108 -> 2408746.5
B109: Doubtful | C109: 466 | D109: 10256741 | E109: 0.5 | F109: =D109*E109 -> 5128370.7
B110: Loss | C110: 4599 | D110: 1.5982929e+08 | E110: 1 | F110: =D110*E110 -> 1.5982929e+08
B111: subtotal | C111: =SUM(C106:C110) -> 10615 | D111: =SUM(D106:D110) -> 6.504423e+08 | E111: 1.81 | F111: =SUM(F106:F110) -> 1.7298305e+08
D113: 44075
B114: CLASSIFICATION | C114: NO. OF A/Cs | D114: OUTSTANDING LOAN PORTFOLIO(Kshs) | E114: REQUIRED PROVISION | F114: REQUIRED PROVISION AMOUNT(Kshs)
B115: Performing | C115: 4681 | D115: 4.4216027e+08 | E115: 0.01 | F115: =D115*E115 -> 4421602.7
B116: Watch | C116: 706 | D116: 31895382 | E116: 0.05 | F116: =D116*E116 -> 1594769.1
...

Sheet DEC 2020 PERFORMANCE REPORT
A1: WANANCHI SACCO SOCIETY LIMITED
A2: PERFORMANCE AND COMPLIANCE REPORT AS AT : 31st December , 2020
B3: Prudential Standard | C3: Audited | D3: Returns | F3: AUDITED 2020 | G3: Aggregate for all Licensed Saccos
C4: 2019 | D4: 30th September , 2020 | E4: 31st December , 2020
A5: A. CAPITAL ADEQUACY
A6: Core Capital | B6: ≥10M | C6: =C33 -> 227230784 | D6: =D33 -> -68790511 | E6: =E33 -> -1.7581679e+08 | F6: =F33 -> 309742324 | G6: =G33 -> 9.7147629e+10
A7: Core Capital/Total Assets | B7: ≥10% | C7: =C33/C29 -> 0.17581043 | D7: =D33/D29 -> -0.054741341 | E7: =E33/E29 -> -0.12900387 | F7: =F33/F29 -> 0.22644072 | G7: =G33/G29 -> 0.16087867
A8: Institutional Capital/Total Assets | B8: ≥8% | C8: =C34/C29 -> 0.042192271 | D8: =D34/D29 -> -0.19735048 | E8: =E34/E29 -> -0.26721783 | F8: =F34/F29 -> 0.08873135 | G8: =G34/G29 -> 0.095680972
A9: B. ASSET QUALITY
A10: NPL (Substandard+Doubtful+Loss) | B10: <5% | C10: =C35/C32 -> 0 | D10: =D35/D32 -> 0.24281002 | E10: =E35/E32 -> 0.26117856 | F10: =F35/F32 -> 0.24684659 | G10: =G35/G32 -> 0.083182068
A11: Non-Earning Assets | B11: <10% | C11: =C36/C29 -> 0.069323252 | D11: =D36/D29 -> 0.067934815 | E11: =E36/E29 -> 0.065045543 | F11: =F36/F29 -> 0.066669005 | G11: =G36/G29 -> 0.1021861
A12: Equity investments/Deposits | B12: <5% | C12: =C38/C31 -> 0.057801343 | D12: =D38/D31 -> 0.41452767 | E12: =E38/E31 -> 0.51216643 | F12: =F38/F31 -> 0.00098784024 | G12: =G38/G31 -> 0.034540372
A13: Equity investments/Core capital | B13: <40% | C13: =C38/C33 -> 0.23120794 | D13: =D38/D33 -> -5.1984453 | E13: =E38/E33 -> -2.757247 | F13: =F38/F33 -> 0.0030186382 | G13: =G38/G33 -> 0.1469197
A14: C. EARNINGS RATING
A15: Yield on Gross Loans | C15: =C48/C32 -> 0.11409705 | D15: =D48/D32 -> 0.10508457 | E15: =E48/E32 -> 0.15930188 | F15: =F48/F32 -> 0.11580077 | G15: =G48/G32 -> 0.1722909
A16: Total Expense/Total Income | C16: =C49/C44 -> 0.88739902 | D16: =D49/D44 -> 0.83705181 | E16: =E49/E44 -> 0.73405104 | F16: =F49/F44 -> 0.8169991 | G16: =G49/G44 -> 0.69909435
A17: Net Income/Average Assets (ROA) | C17: =C50/C30 -> 0.019105825 | D17: =D50/D30 -> 0.0041702561 | E17: =E50/E30 -> 0.020406586 | F17: =F50/F30 -> 0.020636484 | G17: =G50/G30 -> 0.038498141
A18: Operating Expenses/Financial Income (OPEX) | C18: =C47/C44 -> 0.63891574 | D18: =D47/D44 -> 0.69763941 | E18: =E47/E44 -> 0.62772068 | F18: =F47/F44 -> 0.6241756 | G18: =G47/G44 -> 0.30074393
A19: D. LIQUIDITY
A20: Liquid Assets/Short-term Liabilities | B20: >15% | C20: =C40/C41 -> 0.74618152 | D20: =D40/D41 -> 0.23421866 | E20: =E40/E41 -> 0.22278654 | F20: =F40/F41 -> 0.27626954 | G20: =G40/G41 -> 0.63530551
A21: External Borrowing/Total Assets | B21: <25% | C21: =C42/C29 -> 0 | D21: =D42/D29 -> 0 | E21: =E42/E29 -> 0 | F21: =F42/F29 -> 0 | G21: =G42/G29 -> 0.035514941
A22: Liquid Assets/Total Assets | C22: =C40/C29 -> 0.38478032 | D22: =D40/D29 -> 0.11554688 | E22: =E40/E29 -> 0.11498673 | F22: =F40/F29 -> 0.11456694 | G22: =G40/G29 -> 0.12047023
A23: E. STRUCTURE/SENSITIVITY TO RISK
A24: Gross loans /Total Assets | B24: 70-80 | C24: =C32/C29 -> 0.63201921 | D24: =D32/D29 -> 0.64384847 | E24: =E32/E29 -> 0.56237184 | F24: =F32/F29 -> 0.592851 | G24: =G32/G29 -> 0.75494124
A25: Gross loans/Deposits | B25: >100% | C25: =C32/C31 -> 0.89871258 | D25: =D32/D31 -> 0.93788217 | E25: =E32/E31 -> 0.80975993 | F25: =F32/F31 -> 0.85677478 | G25: =G32/G31 -> 1.1032189
A26: Financial Investments/Total Assets | C26: =C39/C31 -> 0.27739121 | D26: =D39/D31 -> 0.41452767 | E26: =E39/E31 -> 0.51216643 | F26: =F39/F31 -> 0.51216643 | G26: =G39/G31 -> 0.067171709
A27: Dividends+Interest on Deposits/Total Income | C27: =C46/C44 -> 0.11574399 | D27: =D46/D44 -> 0.12429025 | E27: =E46/E44 -> 0.093280455 | F27: =F46/F44 -> 0.09274909 | G27: =G46/G44 -> 0.33903109
A28: F. KEY FINANCIAL STATISTICS | C28: 2015 | D28: 2016 | E28: 2017 | G28: AGGREGATE
A29: Total Assets | C29: 1292476097 | D29: 1.2566464e+09 | E29: 1.36288e+09 | F29: =Financials!AP4 -> 1367873753 | G29: 6.038565e+11
A30: Average Assets | C30: 1283570201 | D30: 1.2165958e+09 | E30: 1.3247978e+09 | F30: =(Financials!AP4+Financials!AD4)/2 -> 1.3301749e+09 | G30: 5.7885393e+11
A31: Total Deposits | C31: 908933229 | D31: 8.6267753e+08 | E31: 9.4650932e+08 | F31: =Financials!AP5 -> 946509324 | G31: 4.1322369e+11
A32: Gross Loans | C32: 816869727 | D32: 8.0908988e+08 | E32: 7.6644532e+08 | F32: ='Evolutive SFP'!AO15 -> 810945319 | G32: 4.5587618e+11
A33: Core Capital | C33: 227230784 | D33: -68790511 | E33: -1.7581679e+08 | F33: =Financials!AP11 -> 309742324 | G33: 9.7147629e+10
A34: Institutional Capital | C34: 54532502 | D34: -2.4799977e+08 | E34: -3.6418583e+08 | F34: =Financials!AP12 -> 121373285 | G34: 5.7777577e+10
A35: Non-performing Loans | C35: 0 | D35: 1.9645513e+08 | E35: 2.0017909e+08 | F35: ='FORM 4'!D136+'FORM 4'!D137+'FORM 4'!D138 -> 200179089 | G35: 3.7920723e+10
A36: Non-Earning Assets | C36: 89598646 | D36: 85370043 | E36: 88649269 | F36: =Financials!AP34 -> 91194782 | G36: 6.1705742e+10
A37: Property and Equipment | C37: 70635261 | D37: 26884209 | E37: 27577948 | F37: =Financials!AP35 -> 64842765 | G37: 1.8068539e+10
A38: Equity Investments | C38: 52537561 | D38: 3.5760371e+08 | E38: 4.847703e+08 | F38: ='Evolutive SFP'!AO13 -> 935000 | G38: 1.42729e+10
A39: Financial Investments | C39: 252130091 | D39: 3.5760371e+08 | E39: 4.847703e+08 | F39: ='Evolutive SFP'!AO8 -> 484770303 | G39: 2.7756942e+10
A40: Liquid Assets | C40: 497319360 | D40: 1.4520157e+08 | E40: 1.5671311e+08 | F40: ='Evolutive SFP'!AO4+'Evolutive SFP'!AO9+'Evolutive SFP'!AO10 -> 156713110 | G40: 7.2746733e+10
A41: Short-term Liabilities) | C41: 666485763 | D41: 6.1994021e+08 | E41: 7.0342269e+08 | F41: ='Evolutive SFP'!AO28++'Evolutive SFP'!AO32+'Evolutive SFP'!AO33+'Evolutive SFP'!AO34+'Evolutive SFP'!AO35+'Evolutive SFP'!AO36 -> 567247156 | G41: 1.1450669e+11
A42: External Borrowing | C42: 0 | D42: 0 | E42: 0 | F42: ='Evolutive SFP'!AO37 -> 0 | G42: 2.1445928e+10
A43: Average Gross Loans | C43: 8.042053e+08 | D43: 8.1808344e+08 | E43: 7.6815752e+08 | F43: =('Evolutive SFP'!AC15+'Evolutive SFP'!AO15)/2 -> 813907523 | G43: 4.3816504e+11
A44: Total Income | C44: 220242400 | D44: 1.3914586e+08 | E44: 2.2204178e+08 | F44: ='Evolutitve SCI'!AO3+'Evolutitve SCI'!AO31 -> 223313868 | G44: 9.1230381e+10
A45: Net Financial Income/Loss | C45: 165515848 | D45: 1.197472e+08 | E45: 1.9838708e+08 | F45: ='Evolutitve SCI'!AO19 -> 180208783 | G45: 5.4898935e+10
A46: Dividends+Interest on Deposits | C46: 25491734 | D46: 17294473 | E46: 20712158 | F46: ='Evolutitve SCI'!AO13+'Evolutitve SCI'!AO15 -> 20712158 | G46: 3.0929935e+10
A47: Operating Expenses | C47: 140716337 | D47: 97073635 | E47: 1.3938022e+08 | F47: ='Evolutitve SCI'!AO23 -> 139387067 | G47: 2.7436983e+10
A48: Interest on Loan portfolio+Fees&Commission on Loan | C48: 93202429 | D48: 85022865 | E48: 1.2209618e+08 | F48: ='Evolutitve SCI'!AO5+'Evolutitve SCI'!AO6 -> 93908094 | G48: 7.8543316e+10
A49: Total Expenses | C49: 195442889 | D49: 1.1647229e+08 | E49: 1.6299e+08 | F49: ='Evolutitve SCI'!AO39 -> 182447229 | G49: 6.3778644e+10
A50: Net Income | C50: 24523668 | D50: 5073515.8 | E50: 27034600 | F50: ='Evolutitve SCI'!AO37 -> 27450134 | G50: 2.22848e+10
A51: G. AREAS OF IMPROVEMENT/REGULATORY CONCERNS
A52: 1.Drastic change in Equity investments to Core capital of negative-275%
A53: 2.Gross loans to Deposits of 81.0% against required 100% and above.
A54: 3.Gross loans to Total Assets at 56.2% against recommended industry level of 70-80%.
A55: 4.Non perfoming loan of 26.1% against required 5% and below.
A56: 5.Equity invetments to Deposits of 51.2 % against 5% and below
A57: 6.Core Capital to Total Assets of -12.9% below the required minimum 10%
A58: 7.Institution Capital of -26.7 % below the required minimum of 8%
A59: 8.Negative core capital against required minimum of 10 million
A60: Prepared by:
A62: Checked by:
A64: Approved by:
A66: DISCLAIMER: This report is prepared based on information submitted by the Sacco as at the stated date and may change upon verification by the Authority.

Sheet Evolutive SFP
B3: 2010 Audited | C3: 2017 Audited | D3: 43101 | E3: 43132 | F3: 43160 | G3: 43191 | H3: 43221 | I3: 43252 | J3: 43282 | K3: 43313 | L3: 43344 | M3: 43374 | N3: 43405 | O3: 43435 | P3: Audited 2018 | Q3: 43466 | R3: 43497 | S3: 43525 | T3: 43556 | U3: 43586 | V3: 43617 | W3: 43647 | X3: 43678 | Y3: 43709 | Z3: 43739 | AA3: 43770 | AB3: 43800 | AC3: Audited 2019 | AD3: 43831 | AE3: 43862 | AF3: 43891 | AG3: 43922 | AH3: 43952 | AI3: 43983 | AJ3: 44044 | AK3: 44075 | AL3: 44105 | AM3: 44136 | AN3: 44166 | AO3: AUDITED 2020 | AP3: 44197 | AQ3: 44228 | AR3: 44256 | AS3: 44287 | AT3: 44317 | AU3: 44348 | AV3: 44378 | AW3: 44409 | AX3: 44440 | AY3: 44470 | AZ3: 44501 | BA3: 44531 | BB3: Audited 2021 | BC3: 44562 | BD3: 44593 | BE3: 44621 | BF3: 44652 | BG3: 44682 | BH3: 44713 | BI3: 44743 | BJ3: 44774 | BK3: 44805 | BL3: 44835 | BM3: 44866 | BN3: 44896 | BO3: Audited 2022
A4: Cash & cash Equivalent | B4: =SUM(B5:B6) -> 19363224 | C4: 146341322 | D4: =SUM(D5:D6) -> 2.2822376e+08 | E4: =SUM(E5:E6) -> 2.1157076e+08 | F4: =SUM(F5:F6) -> 1.8263933e+08 | G4: =SUM(G5:G6) -> 2.5160945e+08 | H4: =SUM(H5:H6) -> 2.4042286e+08 | I4: =SUM(I5:I6) -> 2.6293493e+08 | J4: =SUM(J5:J6) -> 2.5592912e+08 | K4: =SUM(K5:K6) -> 2.5778256e+08 | ... BO4: =SUM(BO5:BO6) -> 462696652
A5: Cash In Hand | B5: 19363224 | C5: 55804713 | D5: 41078113 | E5: 44042528 | F5: 43846414 | G5: 58887202 | H5: 33959636 | I5: 44835718 | J5: 38501214 | K5: 45417981 | L5: 37737916 | M5: 130407996 | N5: 57806502 | O5: 48384473 | P5: 62785191 | Q5: 59424186 | R5: 43160365 | S5: 38819482 | T5: 28307829 | U5: 29580812 | V5: 73330547 | W5: 71667327 | X5: 38725456 | Y5: 62358353 | Z5: 96355827 | AA5: 74465730 | AB5: 49448037 | AC5: 49447937 | AD5: 62107086 | AE5: 57753206 | AF5: 66453904 | AG5: 79616560 | AH5: 53998041 | AI5: 48385211 | AJ5: 113714867 | AK5: 62484585 | AL5: 1.1300466e+08 | AM5: 84062755 | AN5: 51522497 | AO5: =813564+3327084 -> 4140648 | AP5: 61224937 | AQ5: 83800001 | AR5: 62222729 | AS5: 60722539 | AT5: 60779581 | AU5: 61544830 | AV5: 51925962 | AW5: 59529398 | AX5: 85693164 | AY5: 60413270 | AZ5: 51128356 | BA5: 64381169 | BB5: 64381169 | BC5: 69145796 | BD5: 68014767 | BE5: 82469099 | BF5: 59972851 | BG5: 67738783 | BH5: 66886906 | BI5: 87677416 | BJ5: 61761379 | BK5: 69582265 | BL5: 74824344 | BM5: 65700903 | BN5: 64628526 | BO5: 64628526
A6: Cash at Bank | C6: 90536609 | D6: 1.8714565e+08 | E6: 1.6752823e+08 | F6: 1.3879291e+08 | G6: 1.9272224e+08 | H6: 2.0646322e+08 | I6: 2.1809921e+08 | J6: 2.1742791e+08 | K6: 2.1236458e+08 | L6: 2.0648783e+08 | M6: 5.0105211e+08 | N6: 1.4208203e+08 | O6: 1.0963779e+08 | P6: =158022262-P5 -> 95237071 | Q6: 1.9915175e+08 | R6: 2.3533829e+08 | S6: 2.0388146e+08 | T6: 2.0888971e+08 | U6: 1.6240479e+08 | V6: 1.5815287e+08 | W6: 1.4409257e+08 | X6: 1.5628586e+08 | Y6: 1.2539742e+08 | Z6: 3.2244285e+08 | AA6: 1.785526e+08 | AB6: 2.4825917e+08 | AC6: =297726830-AC5 -> 248278893 | AD6: 1.6451697e+08 | AE6: 2.4917446e+08 | AF6: 1.7191439e+08 | AG6: 1.8568132e+08 | AH6: 1.573643e+08 | AI6: 1.2652037e+08 | AJ6: 3.1437978e+08 | AK6: 82716984 | AL6: 2.8049859e+08 | AM6: 2.4809617e+08 | AN6: 1.0519061e+08 | AO6: =51522497+65821343+10425229+24803393 -> 152572462 | AP6: 1.266383e+08 | AQ6: 91576440 | AR6: 94442527 | AS6: 1.6532071e+08 | AT6: 1.4523604e+08 | AU6: 1.2614483e+08 | AV6: 1.7912214e+08 | AW6: 85879503 | AX6: 54718858 | AY6: 2.2070149e+08 | AZ6: 1.4528545e+08 | BA6: 4.5840158e+08 | BB6: =530492225-64381169 -> 466111056 | BC6: 4.2487004e+08 | BD6: 4.008024e+08 | BE6: 3.6201237e+08 | BF6: 4.0550383e+08 | BG6: 3.9495625e+08 | BH6: 3.9080194e+08 | BI6: 5.6711627e+08 | BJ6: 5.8059232e+08 | BK6: 5.1012528e+08 | BL6: 4.7638559e+08 | BM6: 4.4094524e+08 | BN6: 3.9143621e+08 | BO6: =462696652-64628526 -> 398068126
A7: Prepayment and Sundry | B7: 13400392 | C7: 33675967 | D7: 57792330 | E7: 59825625 | F7: 63306984 | G7: 57783900 | H7: 56778137 | I7: 53982138 | J7: 48227457 | K7: 46803470 | L7: 45410736 | M7: 43995365 | N7: 43384720 | O7: 43391661 | P7: =8399391+15451011 -> 23850402 | Q7: 47921956 | R7: 51082653 | S7: 51563662 | T7: 51398380 | U7: 43978624 | V7: 42817232 | W7: 41620419 | X7: 40267974 | Y7: 40192889 | Z7: 40101571 | AA7: 49215179 | AB7: 47907969 | AC7: =11786794+5292497 -> 17079291 | AD7: 46827533 | AE7: 47512529 | AF7: 46284045 | AG7: 44952525 | AH7: 44205078 | AI7: 43487503 | AJ7: 84199624 | AK7: 45885178 | AL7: 41636903 | AM7: 42531386 | AN7: 52142130 | AO7: =16960572+4344812 -> 21305384 | AP7: 45862257 | AQ7: 47119770 | AR7: 46811426 | AS7: 47788110 | AT7: 45954032 | AU7: 45590267 | AV7: 46224426 | AW7: 46801126 | AX7: 44675575 | AY7: 42564365 | AZ7: 45732475 | BA7: 55232865 | BB7: =118292577+17352027 -> 135644604 | BC7: 58356035 | BD7: 55923612 | BE7: 55493631 | BF7: 54618964 | BG7: 53940351 | BH7: 53846481 | BI7: 52726225 | BJ7: 51602871 | BK7: 41951833 | BL7: 45755008 | BM7: 45995273 | BN7: 43944404 | BO7: =129363809+10138168 -> 139501977
A8: Financial Investment | B8: =SUM(B9:B13) -> 472260 | C8: =SUM(C9:C13) -> 208785388 | D8: =SUM(D9:D13) -> 48835388 | E8: =SUM(E9:E13) -> 48885388 | F8: =SUM(F9:F13) -> 48935388 | G8: =SUM(G9:G13) -> 48985388 | H8: =SUM(H9:H13) -> 49035388 | I8: =SUM(I9:I13) -> 49085388 | ... BO8: =SUM(BO9:BO13) -> 52132561
A9: Government Security | C9: 163298467 | D9: 0 | E9: 0 | F9: 0 | G9: 0 | H9: 0 | I9: 0 | J9: 0 | K9: 0 | L9: 0 | M9: 0 | N9: 0 | O9: 0 | P9: 343940523 | Q9: 0 | R9: 0 | S9: 0 | T9: 0 | U9: 0 | V9: 0 | W9: 0 | X9: 0 | Y9: 0 | Z9: 0 | AA9: 0 | AB9: 0 | AD9: 0 | AE9: 0 | AF9: 0 | AG9: 0 | AH9: 0 | AI9: 0 | AJ9: 0 | AK9: 0 | AL9: 0 | AM9: 0 | AN9: 0 | AO9: 0 | AP9: 0 | AQ9: 0 | AR9: 0 | AS9: 0 | AT9: 0 | AU9: 0 | AV9: 0 | AW9: 0 | AX9: 0 | AY9: 0 | AZ9: 0 | BA9: 0 | BC9: 0 | BD9: 0 | BE9: 0 | BF9: 0 | BG9: 0 | BH9: 0 | BI9: 0 | BJ9: 0 | BK9: 0 | BL9: 0 | BM9: 0 | BN9: 0 | BO9: 0
A10: Other Securities | C10: 0 | D10: 0 | E10: 0 | F10: 0 | G10: 0 | H10: 0 | I10: 0 | J10: 0 | K10: 0 | L10: 0 | M10: 0 | N10: 0 | O10: 0 | P10: 0 | Q10: 0 | R10: 0 | S10: 0 | T10: 0 | U10: 0 | V10: 0 | W10: 0 | X10: 0 | Y10: 0 | Z10: 0 | AA10: 0 | AB10: 0 | AD10: 0 | AE10: 0 | AF10: 0 | AG10: 0 | AH10: 0 | AI10: 0 | AJ10: 0 | AK10: 0 | AL10: 0 | AM10: 0 | AN10: 0 | AO10: 0 | AP10: 0 | AQ10: 0 | AR10: 0 | AS10: 0 | AT10: 0 | AU10: 0 | AV10: 0 | AW10: 0 | AX10: 0 | AY10: 0 | AZ10: 0 | BA10: 0 | BC10: 0 | BD10: 0 | BE10: 0 | BF10: 0 | BG10: 0 | BH10: 0 | BI10: 0 | BJ10: 0 | BK10: 0 | BL10: 0 | BM10: 0 | BN10: 0 | BO10: 0
A11: Balances with Other Saccos | C11: 12538388 | J11: 0 | K11: 0 | L11: 0 | M11: 0 | N11: 0 | O11: 0 | P11: =45686922-P13 -> 44751922 | Q11: 0 | R11: 0 | S11: 0 | T11: 0 | U11: 0 | V11: 0 | W11: 0 | X11: 0 | Y11: 0 | Z11: 0 | AA11: 0 | AB11: 0 | AC11: 252130090 | AD11: 2.7718009e+08 | AE11: 1.8723009e+08 | AF11: 2.3733009e+08 | AG11: 2.5733009e+08 | AH11: 3.0738009e+08 | AI11: 3.574417e+08 | AJ11: 6.1510741e+08 | AK11: 3.5760371e+08 | AL11: 3.3260371e+08 | AM11: 3.847203e+08 | AN11: 4.847703e+08 | AO11: 430232742 | AP11: 0 | AQ11: 0 | AR11: 0 | AS11: 0 | AT11: 0 | AU11: 0 | AV11: 0 | AW11: 0 | AX11: 0 | AY11: 0 | AZ11: 0 | BA11: 0 | BC11: 0 | BD11: 0 | BE11: 0 | BF11: 0 | BG11: 0 | BH11: 0 | BI11: 0 | BJ11: 0 | BK11: 0 | BL11: 0 | BM11: 0 | BN11: 0 | BO11: 0
A12: Equity Investments in NACCOs(Shares in- CIC, KUSCCO, COOP BANK,CAK, KERUSSU) | Z12: 2.2701889e+08 | AA12: 3.5706889e+08 | AB12: 2.5211889e+08 | AO12: =54537561-AO13 -> 53602561 | BK12: 0 | BO12: 10330729
A13: Investment In Companies | B13: 472260 | C13: 32948533 | D13: 48835388 | E13: 48885388 | F13: 48935388 | G13: 48985388 | H13: 49035388 | I13: 49085388 | J13: 49135388 | K13: 49385388 | L13: 49435388 | M13: 49485388 | N13: 3.3953539e+08 | O13: 3.8962744e+08 | P13: =935000 -> 935000 | Q13: 2.3962744e+08 | R13: 1.9967744e+08 | S13: 1.9972744e+08 | T13: 1.9982744e+08 | U13: 2.0657508e+08 | V13: 2.2662508e+08 | W13: 2.2657508e+08 | X13: 2.2662508e+08 | Y13: 2.2667508e+08 | Z13: 5.4903799e+08 | AA13: 5.8890139e+08 | AB13: 6.0602053e+08 | AO13: 935000 | AP13: 4.3484597e+08 | AQ13: 4.3489597e+08 | AR13: 4.3994597e+08 | AS13: 4.0999597e+08 | AT13: 4.0004597e+08 | AU13: 4.0012251e+08 | AV13: 3.5012251e+08 | AW13: 4.0027647e+08 | AX13: 3.8032647e+08 | AY13: 3.1037647e+08 | AZ13: 3.1037647e+08 | BA13: 60476474 | BB13: 54537561 | BC13: 60476474 | BD13: 60526474 | BE13: 60576474 | BF13: 60676474 | BG13: 60726474 | BH13: 60806574 | BI13: 60856574 | BJ13: 60906574 | BK13: 60956574 | BL13: 61006574 | BM13: 61119478 | BN13: 61169478 | BO13: =935000+1279992+1000+39585840 -> 41801832
A14: Net Loan Portfolio | B14: =(B15-B16) -> 112905266 | C14: =(C15-C16) -> 685110959 | D14: =(D15-D16) -> 6.7256688e+08 | E14: =(E15-E16) -> 6.7384917e+08 | F14: =(F15-F16) -> 6.77628e+08 | G14: =(G15-G16) -> 6.7837707e+08 | H14: =(H15-H16) -> 6.8226734e+08 | I14: =(I15-I16) -> 6.8266836e+08 | ... BO14: =(BO15-BO16) -> 598486828
A15: Gross Loan Portfolio | B15: 112905266 | C15: 832525078 | D15: 8.2189998e+08 | E15: 8.2510161e+08 | F15: 8.307998e+08 | G15: 8.3346822e+08 | H15: 8.3927821e+08 | I15: 8.4159859e+08 | J15: 8.35154e+08 | K15: 8.3660065e+08 | L15: 8.4315168e+08 | M15: 6.7922211e+08 | N15: 7.2945516e+08 | O15: 7.4204087e+08 | P15: 791540870 | Q15: 7.5944201e+08 | R15: 7.8391369e+08 | S15: 7.8567062e+08 | T15: 7.8951385e+08 | U15: 7.9979821e+08 | V15: 7.9799616e+08 | W15: 8.0196824e+08 | X15: 8.1606488e+08 | Y15: 8.2707701e+08 | Z15: 1.8737968e+08 | AA15: 1.8738224e+08 | AB15: 1.638492e+08 | AC15: =653020530+163849197 -> 816869727 | AD15: 7.8549151e+08 | AE15: 7.9004044e+08 | AF15: 7.9647622e+08 | AG15: 7.8890763e+08 | AH15: 7.8132751e+08 | AI15: 7.825868e+08 | AJ15: 1.5883419e+09 | AK15: 8.0908988e+08 | AL15: 7.2406128e+08 | AM15: 7.5503611e+08 | AN15: 7.6644532e+08 | AO15: =766445319+44500000 -> 810945319 | AP15: 7.7173789e+08 | AQ15: 7.8247735e+08 | AR15: 7.8828912e+08 | AS15: 7.8544494e+08 | AT15: 8.0041618e+08 | AU15: 8.1562362e+08 | AV15: 8.2724967e+08 | AW15: 8.5127402e+08 | AX15: 8.5898726e+08 | AY15: 7.8284245e+08 | AZ15: 8.2296757e+08 | BA15: 830832172 | BB15: =716041891+42000000 -> 758041891 | BC15: 8.4345026e+08 | BD15: 7.3509499e+08 | BE15: 7.3575932e+08 | BF15: 7.3897298e+08 | BG15: 7.3930339e+08 | BH15: 7.5434653e+08 | BI15: 7.0266276e+08 | BJ15: 7.2280089e+08 | BK15: 7.5243357e+08 | BL15: 7.6381764e+08 | BM15: 7.8475923e+08 | BN15: 8.1206646e+08 | BO15: 812162376
A16: Allowance For Loan Loss | C16: 147414119 | D16: 1.493331e+08 | E16: 1.5125245e+08 | F16: 1.531718e+08 | G16: 1.5509115e+08 | H16: 1.5701087e+08 | I16: 1.5893023e+08 | J16: 1.5893023e+08 | K16: 1.6278118e+08 | L16: 1.6470053e+08 | M16: 1.6661988e+08 | N16: 1.7045858e+08 | O16: 1.6357335e+08 | P16: 163573354 | Q16: 1.6357335e+08 | R16: 1.6413342e+08 | S16: 1.6469349e+08 | T16: 1.6673731e+08 | U16: 1.6752628e+08 | V16: 1.7583626e+08 | W16: 1.7788008e+08 | X16: 1.7788008e+08 | Y16: 1.7920441e+08 | Z16: 0 | AA16: 0 | AB16: 0 | AC16: 163849197 | AD16: 1.648492e+08 | AE16: 1.6690061e+08 | AF16: 1.6899235e+08 | AG16: 1.7113896e+08 | AH16: 1.7321066e+08 | AI16: 1.7526336e+08 | AJ16: 3.5883486e+08 | AK16: 1.8146575e+08 | AL16: 1.8522663e+08 | AM16: 1.7542958e+08 | AN16: 1.7454499e+08 | AO16: 175749761 | AP16: 1.7725052e+08 | AQ16: 1.7856821e+08 | AR16: 1.796109e+08 | AS16: 1.8165891e+08 | AT16: 1.838634e+08 | AU16: 1.8591928e+08 | AV16: 187962500 | AW16: 1.9090856e+08 | AX16: 1.9294429e+08 | AY16: 1.9478095e+08 | AZ16: 1.9682586e+08 | BA16: 1.8637337e+08 | BB16: 186373165 | BC16: 1.8791086e+08 | BD16: 1.891462e+08 | BE16: 1.9140109e+08 | BF16: 1.9312846e+08 | BG16: 1.9485506e+08 | BH16: 1.9858811e+08 | BI16: 2.0332475e+08 | BJ16: 2.0332475e+08 | BK16: 2.0539528e+08 | BL16: 2.0684506e+08 | BM16: 2.1188769e+08 | BN16: 2.1367555e+08 | BO16: 213675548
A17: Accounts Receivables | D17: 0 | E17: 0 | F17: 0 | G17: 0 | AD17: 0 | AE17: 0 | AF17: 0 | AG17: 0 | AH17: 0 | AI17: 0 | AJ17: 0 | AK17: 0 | AL17: 0 | AM17: 0 | AN17: 0 | AO17: 0 | AZ17: 0 | BA17: 0 | BC17: 0 | BD17: 0 | BE17: 0 | BF17: 0 | BG17: 0 | BH17: 0 | BI17: 0 | BJ17: 0 | BK17: 0 | BL17: 0 | BM17: 0 | BN17: 0 | BO17: 0
A18: Tax Recoverable | D18: 0 | E18: 0 | F18: 0 | G18: 0 | K18: 0 | L18: 0 | M18: 0 | N18: 0 | O18: 0 | Q18: 0 | R18: 0 | S18: 0 | T18: 0 | U18: 0 | V18: 0 | W18: 0 | X18: 0 | Y18: 0 | Z18: 0 | AA18: 0 | AB18: 0 | AD18: 0 | AE18: 0 | AF18: 0 | AG18: 0 | AH18: 0 | AI18: 0 | AJ18: 0 | AK18: 0 | AL18: 0 | AM18: 0 | AN18: 0 | AO18: 0 | AP18: 0 | AQ18: 0 | AR18: 0 | AS18: 0 | AT18: 0 | AU18: 0 | AV18: 0 | AW18: 0 | AX18: 0 | AY18: 0 | AZ18: 0 | BA18: 0 | BC18: 0 | BD18: 0 | BE18: 0 | BF18: 0 | BG18: 0 | BH18: 0 | BI18: 0 | BJ18: 0 | BK18: 0 | BL18: 0 | BM18: 0 | BN18: 0 | BO18: 0
A19: Deffered Tax Assets | D19: 0 | E19: 0 | F19: 0 | G19: 0 | K19: 0 | L19: 0 | M19: 0 | N19: 0 | O19: 0 | Q19: 0 | R19: 0 | S19: 0 | T19: 0 | U19: 0 | V19: 0 | W19: 0 | X19: 0 | Y19: 0 | Z19: 0 | AA19: 0 | AB19: 0 | AD19: 0 | AE19: 0 | AF19: 0 | AG19: 0 | AH19: 0 | AI19: 0 | AJ19: 0 | AK19: 0 | AL19: 0 | AM19: 0 | AN19: 0 | AO19: 0 | AP19: 0 | AQ19: 0 | AR19: 0 | AS19: 0 | AT19: 0 | AU19: 0 | AV19: 0 | AW19: 0 | AX19: 0 | AY19: 0 | AZ19: 0 | BA19: 0 | BC19: 0 | BD19: 0 | BE19: 0 | BF19: 0 | BG19: 0 | BH19: 0 | BI19: 0 | BJ19: 0 | BK19: 0 | BL19: 0 | BM19: 0 | BN19: 0 | BO19: 0
A20: Retirement Benefit Assets | D20: 0 | E20: 0 | F20: 0 | G20: 0 | K20: 0 | L20: 0 | M20: 0 | N20: 0 | O20: 0 | Q20: 0 | R20: 0 | S20: 0 | T20: 0 | U20: 0 | V20: 0 | W20: 0 | X20: 0 | Y20: 0 | Z20: 1.7884658e+08 | AA20: 85432668 | AB20: 82960990 | AD20: 0 | AE20: 0 | AF20: 0 | AG20: 0 | AH20: 0 | AI20: 0 | AJ20: 0 | AK20: 0 | AL20: 0 | AM20: 0 | AN20: 0 | AO20: 0 | AP20: 0 | AQ20: 0 | AR20: 0 | AS20: 0 | AT20: 0 | AU20: 0 | AV20: 0 | AW20: 0 | AX20: 0 | AY20: 0 | AZ20: 0 | BA20: 0 | BC20: 0 | BD20: 0 | BE20: 0 | BF20: 0 | BG20: 0 | BH20: 0 | BI20: 0 | BJ20: 0 | BK20: 0 | BL20: 0 | BM20: 0 | BN20: 0 | BO20: 0
A21: Property, Equipment & Other Assets | B21: =SUM(B22:B26) -> 4874587 | C21: =SUM(C22:C26) -> 74636034 | D21: =SUM(D22:D26) -> 1.0807375e+08 | E21: =SUM(E22:E26) -> 1.0334266e+08 | F21: =SUM(F22:F26) -> 1.0283761e+08 | G21: =SUM(G22:G26) -> 1.0095634e+08 | H21: =SUM(H22:H26) -> 1.0359598e+08 | I21: =SUM(I22:I26) -> 94868992 | ... BO21: =SUM(BO22:BO26) -> 128158763
A22: Investment Properties | D22: 40846978 | E22: 40846978 | F22: 40846978 | G22: 40846978 | H22: 40846978 | I22: 40846978 | J22: 40846978 | K22: 40846978 | L22: 40846978 | M22: 40846978 | N22: 40846978 | O22: 40846978 | Q22: 40846978 | R22: 40846978 | S22: 40846978 | T22: 40846978 | U22: 40846978 | V22: 40846978 | W22: 40846978 | X22: 40846978 | Y22: 40846978 | Z22: 21510943 | AA22: 21510943 | AB22: 22740843 | AD22: 40846978 | AE22: 40846978 | AF22: 40846978 | AG22: 40846978 | AH22: 40846978 | AI22: 40846978 | AJ22: 81693956 | AK22: 40846978 | AL22: 40846978 | AM22: 40846978 | AN22: 40846978 | AO22: 0 | AP22: 40846978 | AQ22: 41146978 | AR22: 41146978 | AS22: 41146978 | AT22: 41146978 | AU22: 41146978 | AV22: 41146978 | AW22: 41268046 | AX22: 51626667 | AY22: 51626667 | AZ22: 51626667 | BA22: 60224584 | BC22: 60224584 | BD22: 66133585 | BE22: 66133585 | BF22: 71407414 | BG22: 71407414 | BH22: 71407414 | BI22: 80284091 | BJ22: 80284091 | BK22: 80689091 | BL22: 80689091 | BM22: 82068023 | BN22: 96372278
A23: Property and Equipment | B23: 4123114 | C23: 67228532 | D23: 16506538 | E23: 26113023 | F23: 25596868 | G23: 25080713 | H23: 26464472 | I23: 26486317 | J23: 26483317 | K23: 25451007 | L23: 24934852 | M23: 24461162 | N23: 25614712 | O23: 25338887 | P23: 67832698 | Q23: 25488887 | R23: 24874196 | S23: 24874196 | T23: 25822093 | U23: 25822093 | V23: 24004439 | W23: 23670653 | X23: 23780448 | Y23: 23290977 | Z23: 0 | AA23: 0 | AB23: 0 | AC23: 66854836 | AD23: 22740843 | AE23: 25700266 | AF23: 25235439 | AG23: 23531332 | AH23: 23022091 | AI23: 24631959 | AJ23: 47226352 | AK23: 23103784 | AL23: 22245960 | AM23: 22245960 | AN23: 22751003 | AO23: 64842765 | AP23: 23992331 | AQ23: 24641986 | AR23: 23921986 | AS23: 23412595 | AT23: 24037331 | AU23: 25713555 | AV23: 25209164 | AW23: 24699772 | AX23: 24306830 | AY23: 24029439 | AZ23: 24200769 | BA23: 23349718 | BB23: 86313178 | BC23: 23050893 | BD23: 22633453 | BE23: 23492236 | BF23: 23275519 | BG23: 23163748 | BH23: 22815423 | BI23: 22428857 | BJ23: 22750344 | BK23: 22600120 | BL23: 22246493 | BM23: 21662862 | BN23: 21822980 | BO23: 120314235
A24: Prepaid Lease Rentals | D24: 594000 | E24: 540000 | F24: 486000 | G24: 432000 | H24: 378000 | I24: 324000 | J24: 270000 | K24: 216000 | L24: 162000 | M24: 108000 | N24: 0 | O24: 0 | Q24: 682000 | R24: 620000 | S24: 558000 | T24: 496000 | U24: 434000 | V24: 372000 | W24: 310000 | X24: 248000 | Y24: 186000 | Z24: 7047439 | AA24: 7047439 | AB24: 7047439 | AD24: 737000 | AE24: 670000 | AF24: 603000 | AG24: 536000 | AH24: 469000 | AI24: 402000 | AJ24: 536000 | AK24: 201000 | AL24: 0 | AM24: 0 | AN24: 0 | AO24: 0 | AP24: 0 | AQ24: 0 | AR24: 648000 | AS24: 576000 | AT24: 504000 | AU24: 432000 | AV24: 360000 | AW24: 288000 | AX24: 216000 | AY24: 144000 | AZ24: 72000 | BA24: 0 | BC24: 834680 | BD24: 745360 | BE24: 656040 | BF24: 566720 | BG24: 477400 | BH24: 388080 | BI24: 298760 | BJ24: 298760 | BK24: 209440 | BL24: 30800 | BM24: 30800 | BN24: 0
A25: Intangible Assets | B25: 751473 | C25: 5489439 | D25: 15571079 | E25: 5489439 | F25: 5489439 | G25: 5489439 | H25: 5489439 | I25: 5489439 | J25: 5489439 | K25: 7047439 | L25: 7047439 | M25: 7047439 | N25: 7047439 | O25: 7047439 | P25: 5400607 | Q25: 7047439 | R25: 7047439 | S25: 7047439 | T25: 7047439 | U25: 7047439 | V25: 7047439 | W25: 7047439 | X25: 7047439 | Y25: 7047439 | Z25: 1.0944122e+08 | AA25: 16027308 | AB25: 12325730 | AC25: 3780425 | AD25: 7047439 | AE25: 3780425 | AF25: 3780425 | AG25: 3780425 | AH25: 3780425 | AI25: 3780425 | AJ25: 7560850 | AK25: 3780425 | AL25: 3780425 | AM25: 4826945 | AN25: 4826945 | AO25: 3692818 | AP25: 4826945 | AQ25: 4826945 | AR25: 4826945 | AS25: 4826945 | AT25: 3692816.7 | AU25: 3692816.7 | AV25: 3692816.6 | AW25: 5706296.7 | AX25: 5706296.7 | AY25: 5706296.6 | AZ25: 5706297 | BA25: 5706296.6 | BB25: 4783093 | BC25: 5706296.6 | BD25: 6606296.6 | BE25: 6606296.6 | BF25: 6606296.6 | BG25: 6606296.6 | BH25: 6606296.6 | BI25: 6606296.6 | BJ25: 6606296.6 | BK25: 6606296.6 | BL25: 6606296.6 | BM25: 7034696.6 | BN25: 7034696.6 | BO25: 4915720
A26: Other Assets | C26: 1918063 | D26: 34555160 | E26: 30353222 | F26: 30418322 | G26: 29107207 | H26: 30417092 | I26: 21722258 | J26: 30127720 | K26: 21451041 | L26: 20432738 | M26: 1.6156792e+08 | N26: 1.2472397e+08 | O26: 29070427 | P26: 1963375 | Q26: 26548774 | R26: 23232811 | S26: 24667089 | T26: 28789862 | U26: 24659441 | V26: 2065116.6 | W26: 1788739 | X26: 2615548.8 | Y26: 2677337.8 | Z26: 1.4138037e+09 | AA26: 1.3336365e+09 | AB26: 1.2867156e+09 | AC26: 1884094 | AD26: 12499494 | AE26: 12374351 | AF26: 10500666 | AG26: 1120184.2 | AH26: 12378524 | AI26: 12423205 | AJ26: 24807161 | AK26: 12399655 | AL26: 1.165489e+08 | AM26: 14650223 | AN26: 8929191.4 | AO26: =1353815 -> 1353815 | AP26: 11654147 | AQ26: 12291943 | AR26: 11711268 | AS26: 11522239 | AT26: 11528471 | AU26: 11548871 | AV26: 11561931 | AW26: 8018088.3 | AX26: 7751594.8 | AY26: 1.0011914e+08 | AZ26: 1.5562498e+08 | BA26: 6019304.8 | BB26: 1476185 | BC26: 6029354.8 | BD26: 1.2649588e+08 | BE26: 1.2560403e+08 | BF26: 1.2495861e+08 | BG26: 1.2695326e+08 | BH26: 1.2798659e+08 | BI26: 2.0107641e+08 | BJ26: 1.3641441e+08 | BK26: 1.2938783e+08 | BL26: 1.2819289e+08 | BM26: 1.3240041e+08 | BN26: 1.3641572e+08 | BO26: 2928808
A27: Total Assets | B27: =SUM(B4+B7+B8+B14+B17+B21) -> 151015729 | C27: =SUM(C4+C7+C8+C14+C17+C21) -> 1148549670 | D27: =SUM(D4+D7+D8+D14+D17+D21) -> 1.1154921e+09 | E27: =SUM(E4+E7+E8+E14+E17+E21) -> 1.0974736e+09 | F27: =SUM(F4+F7+F8+F14+F17+F21) -> 1.0753473e+09 | G27: =SUM(G4+G7+G8+G14+G17+G21) -> 1.1377121e+09 | H27: =SUM(H4+H7+H8+H14+H17+H21) -> 1.1320997e+09 | I27: =SUM(I4+I7+I8+I14+I17+I21) -> 1.1435398e+09 | ... BO27: =SUM(BO4+BO7+BO8+BO14+BO17+BO21) -> 1380976781 | BP27: =1420380868-BO27 -> 39404087
A28: Savings and Deposits | B28: 8112861 | C28: 485766253 | D28: 4.4232218e+08 | E28: 4.2489766e+08 | F28: 4.031458e+08 | G28: 4.2182179e+08 | H28: 4.0854654e+08 | I28: 4.008099e+08 | J28: 3.9283844e+08 | K28: 3.7273996e+08 | L28: 3.5654796e+08 | M28: 7.5054034e+08 | N28: 6.0112332e+08 | O28: 5.3363603e+08 | P28: 533637032 | Q28: 5.0433445e+08 | R28: 4.8634986e+08 | S28: 4.7099994e+08 | T28: 4.7563184e+08 | U28: 4.3050501e+08 | V28: 4.2862419e+08 | W28: 4.315694e+08 | X28: 4.1513004e+08 | Y28: 4.1029429e+08 | Z28: 1.2069465e+08 | AA28: 1.2160996e+08 | AB28: 1.1642111e+08 | AC28: 491860828 | AD28: 4.5101154e+08 | AE28: 4.3691912e+08 | AF28: 4.3105914e+08 | AG28: 4.5396753e+08 | AH28: 4.4734807e+08 | AI28: 4.5640667e+08 | AJ28: 8.7383677e+08 | AK28: 4.2616643e+08 | AL28: 6.5181219e+08 | AM28: 5.6327581e+08 | AN28: 5.0666096e+08 | AO28: 506660959 | AP28: 4.8704027e+08 | AQ28: 4.838777e+08 | AR28: 4.8630193e+08 | AS28: 4.9724361e+08 | AT28: 4.7673702e+08 | AU28: 4.7501353e+08 | AV28: 4.6805516e+08 | AW28: 4.4443505e+08 | AX28: 4.3050502e+08 | AY28: 5.0933075e+08 | AZ28: 5.1766823e+08 | BA28: 5.0845164e+08 | BB28: 5.0845164e+08 | BC28: 4.9016749e+08 | BD28: 4.7830137e+08 | BE28: 4.6941299e+08 | BF28: 4.9208334e+08 | BG28: 4.8398245e+08 | BH28: 4.6284842e+08 | BI28: 646926258 | BJ28: 5.8990125e+08 | BK28: 5.4401475e+08 | BL28: 5.2555178e+08 | BM28: 4.9722563e+08 | BN28: 4.7138484e+08 | BO28: 471385237
A29: Short Terrm Deposits | B29: 8350444 | C29: 94948114 | D29: 97099755 | E29: 97735836 | F29: 1.0352966e+08 | G29: 99792072 | H29: 1.00082e+08 | I29: 1.1442633e+08 | J29: 1.1360682e+08 | K29: 1.1284405e+08 | L29: 1.1642354e+08 | M29: 1.176477e+08 | N29: 1.2735888e+08 | O29: 1.1216058e+08 | P29: 112160581 | Q29: 1.1181199e+08 | R29: 121759094 | S29: 119074161 | T29: 116058726 | U29: 1.1604224e+08 | V29: 115814724 | W29: 114550663 | X29: 1.1673156e+08 | Y29: 1.189874e+08 | Z29: 2.965839e+08 | AA29: 2.9911714e+08 | AB29: 3.0065129e+08 | AC29: 116421109 | AD29: 1.1717231e+08 | AE29: 1.2177834e+08 | AF29: 120705350 | AG29: 118323045 | AH29: 1.2307393e+08 | AI29: 1.2402683e+08 | AJ29: 2.5625533e+08 | AK29: 1.2872553e+08 | AL29: 1.2244618e+08 | AM29: 1.252726e+08 | AN29: 1.4043258e+08 | AO29: 140432582 | AP29: 138436700 | AQ29: 1.4093931e+08 | AR29: 1.4546242e+08 | AS29: 1.3598478e+08 | AT29: 1.4227078e+08 | AU29: 1.4284609e+08 | AV29: 1.4764673e+08 | AW29: 1.4284637e+08 | AX29: 145927250 | AY29: 1.4111838e+08 | AZ29: 137128050 | BA29: 109280050 | BB29: 109280050 | BC29: 107159100 | BD29: 1.0377424e+08 | BE29: 1.0632609e+08 | BF29: 1.0957349e+08 | BG29: 1.109277e+08 | BH29: 1.1262808e+08 | BI29: 1.3004175e+08 | BJ29: 1.3209901e+08 | BK29: 1.3276179e+08 | BL29: 1.2937683e+08 | BM29: 137825300 | BN29: 135348465 | BO29: 135348465
A30: Non Withdrawable Deposits | B30: 112140909 | C30: 271523495 | D30: 2.7144038e+08 | E30: 2.7210236e+08 | F30: 2.7521591e+08 | G30: 2.7594244e+08 | H30: 2.7855421e+08 | I30: 2.7998002e+08 | J30: 2.8130035e+08 | K30: 2.8198335e+08 | L30: 2.8122165e+08 | M30: 2.8199216e+08 | N30: 2.8522983e+08 | O30: 2.8553958e+08 | P30: 285538578 | Q30: 286341070 | R30: 2.8862874e+08 | S30: 2.9038148e+08 | T30: 2.9080629e+08 | U30: 2.9092475e+08 | V30: 2.9194191e+08 | W30: 2.9253408e+08 | X30: 2.9502058e+08 | Y30: 2.9562728e+08 | Z30: 1.0524672e+09 | AA30: 9.6744009e+08 | AB30: 9.0893323e+08 | AC30: 300651292 | AD30: 2.9942499e+08 | AE30: 3.0300729e+08 | AF30: 3.0395004e+08 | AG30: 3.0413385e+08 | AH30: 3.0397482e+08 | AI30: 3.0340879e+08 | AJ30: 6.1131962e+08 | AK30: 3.0778556e+08 | AL30: 3.0947256e+08 | AM30: 3.1029977e+08 | AN30: 2.9941578e+08 | AO30: 299415783 | AP30: 299133083 | AQ30: 3.0015413e+08 | AR30: 3.0034698e+08 | AS30: 3.0103638e+08 | AT30: 3.0299842e+08 | AU30: 3.0420888e+08 | AV30: 3.0545849e+08 | AW30: 3.0835283e+08 | AX30: 3.0804278e+08 | AY30: 3.0908405e+08 | AZ30: 3.1139728e+08 | BA30: 3.1167445e+08 | BB30: 3.1167445e+08 | BC30: 3.1363804e+08 | BD30: 3.1487189e+08 | BE30: 3.1541517e+08 | BF30: 3.1665708e+08 | BG30: 3.1696588e+08 | BH30: 3.1802492e+08 | BI30: 3.2061264e+08 | BJ30: 3.2128116e+08 | BK30: 3.2194388e+08 | BL30: 3.2362433e+08 | BM30: 3.2643792e+08 | BN30: 3.2829105e+08 | BO30: 328290550
A31: Total Deposit Liabilities | B31: =SUM(B28:B30) -> 128604214 | C31: =SUM(C28:C30) -> 852237862 | D31: =SUM(D28:D30) -> 8.1086231e+08 | E31: =SUM(E28:E30) -> 7.9473586e+08 | F31: =SUM(F28:F30) -> 7.8189137e+08 | G31: =SUM(G28:G30) -> 7.9755631e+08 | H31: =SUM(H28:H30) -> 7.8718275e+08 | I31: =SUM(I28:I30) -> 7.9521626e+08 | ... BO31: =SUM(BO28:BO30) -> 935024252
A32: Tax Payable | B32: 27231 | C32: -1155539 | D32: 244460.83 | E32: 244460.83 | F32: 244460.83 | G32: 144460.83 | H32: 2074510.1 | I32: 2074510.1 | J32: 697838.03 | K32: 144460.83 | L32: 144460.83 | M32: 508043.78 | N32: 947873.53 | O32: 947873.53 | P32: -452126 | Q32: 947873.53 | R32: 947873.53 | S32: 947873.53 | T32: 947873.53 | U32: 947873.53 | V32: 947873.53 | W32: 947873.53 | X32: 947873.53 | Y32: 947873.53 | Z32: 0 | AA32: 0 | AB32: 0 | AD32: 947873.53 | AE32: 947873.53 | AF32: 947873.53 | AG32: 947873.53 | AH32: 947873.53 | AI32: 947873.53 | AJ32: 1895747.1 | AK32: -146142.47 | AL32: -146142.47 | AM32: 0 | AN32: 947873.53 | AO32: 1194753 | AP32: 2594752.5 | AQ32: 2915940.5 | AR32: 2915940.5 | AS32: 1099999.5 | AT32: 1099999.5 | AU32: -1200000.5 | AV32: -1200000.5 | AW32: -1200000.5 | AX32: -1200000.5 | AY32: -1200000.5 | AZ32: -1200000.5 | BA32: -741279.85 | BC32: -741279.85 | BD32: 6192380 | BE32: 6830565.4 | BF32: 200000.44 | BG32: 200000.44 | BH32: -336842 | BI32: -336842 | BJ32: -336842 | BK32: -1799999.6 | BL32: -1799999.6 | BM32: -1799999.6 | BN32: 2267374.4 | BO32: 7055965
A33: Dividends Payable | B33: 3618123 | C33: 11832183 | D33: 0 | E33: 0 | F33: -14279.5 | G33: 0 | H33: 0 | K33: 0 | L33: 0 | M33: 0 | N33: 0 | O33: 0 | P33: 16504848 | Q33: 0 | R33: 0 | S33: 0 | T33: 0 | U33: 0 | V33: 0 | W33: 0 | X33: 0 | Y33: 0 | Z33: 0 | AA33: 0 | AB33: 0 | AD33: 0 | AE33: 0 | AF33: 0 | AG33: 0 | AH33: 0 | AI33: 0 | AJ33: 0 | AK33: 0 | AL33: 0 | AM33: 0 | AN33: 0 | AO33: 25703527 | AP33: 0 | AQ33: 0 | AR33: 0 | AS33: 0 | AT33: 0 | AU33: 0 | AV33: 0 | AW33: 0 | AX33: 0 | AY33: 0 | AZ33: 0 | BA33: 0 | BC33: 0 | BD33: 0 | BE33: 476614.7 | BF33: 476614.7 | BG33: 0 | BH33: 0 | BI33: 0 | BJ33: 0 | BK33: 0 | BL33: 0 | BM33: 0 | BN33: 17058903 | BO33: 32025371
A34: Deferred Tax Liability | C34: 0 | K34: 0 | L34: 0 | M34: 0 | N34: 0 | O34: 0 | Q34: 0 | R34: 0 | S34: 0 | T34: 0 | U34: 0 | V34: 0 | W34: 0 | X34: 0 | Y34: 0 | Z34: 0 | AA34: 0 | AB34: 0 | AD34: 0 | AE34: 0 | AF34: 0 | AG34: 0 | AH34: 0 | AI34: 0 | AJ34: 0 | AK34: 0 | AL34: 0 | AM34: 0 | AN34: 0 | AO34: 0 | AP34: 0 | AQ34: 0 | AR34: 0 | AS34: 0 | AT34: 0 | AU34: 0 | AV34: 0 | AW34: 0 | AX34: 0 | AY34: 0 | AZ34: 0 | BA34: 0 | BC34: 0 | BD34: 0 | BE34: 0 | BF34: 0 | BG34: 0 | BH34: 0 | BI34: 0 | BJ34: 0 | BK34: 0 | BL34: 0 | BM34: 0 | BN34: 0 | BO34: 1053191
A35: Retirement Benefits Liabilty | K35: 0 | L35: 0 | M35: 0 | N35: 0 | O35: 0 | Q35: 0 | R35: 0 | S35: 0 | T35: 0 | U35: 0 | V35: 0 | W35: 0 | X35: 0 | Y35: 0 | Z35: 54690194 | AA35: 52515513 | AB35: 54074414 | AD35: 0 | AE35: 0 | AF35: 0 | AG35: 0 | AH35: 0 | AI35: 0 | AJ35: 0 | AK35: 0 | AL35: 0 | AM35: 0 | AN35: 0 | AO35: 0 | AP35: 0 | AQ35: 0 | AR35: 0 | AS35: 0 | AT35: 0 | AU35: 0 | AV35: 0 | AW35: 0 | AX35: 0 | AY35: 0 | AZ35: 0 | BA35: 0 | BC35: 0 | BD35: 0 | BE35: 0 | BF35: 0 | BG35: 0 | BH35: 0 | BI35: 0 | BJ35: 0 | BK35: 0 | BL35: 0 | BM35: 0 | BN35: 0
A36: Other Liabilities | B36: 1214920 | C36: 29530170 | D36: 38354319 | E36: 38750659 | F36: 32249819 | G36: 29815638 | H36: 33701925 | I36: 36214135 | J36: 33478650 | K36: 37680707 | L36: 38827300 | M36: 41210207 | N36: 42442242 | O36: 47875036 | P36: =8033846+11026235+13163336+4234713 -> 36458130 | Q36: 42434996 | R36: 53386352 | S36: 41127772 | T36: 38119402 | U36: 41993559 | V36: 62505402 | W36: 46750389 | X36: 46863578 | Y36: 49096994 | Z36: 0 | AA36: 0 | AB36: 0 | AC36: 58203826 | AD36: 55599094 | AE36: 54157729 | AF36: 50874873 | AG36: 52453103 | AH36: 50124334 | AI36: 52002012 | AJ36: 1.1385826e+08 | AK36: 65194387 | AL36: 63973025 | AM36: 68616383 | AN36: 55381277 | AO36: =2290037+17387062+13268843+741975 -> 33687917 | AP36: 53648955 | AQ36: 54639548 | AR36: 47643306 | AS36: 80273722 | AT36: 69731397 | AU36: 67285765 | AV36: 69730489 | AW36: 77720211 | AX36: 75717353 | AY36: 73506560 | AZ36: 75363018 | BA36: 66073392 | BB36: 74736079 | BC36: 68803048 | BD36: 66942588 | BE36: 57579543 | BF36: 60333442 | BG36: 61783095 | BH36: 85990211 | BI36: 97000553 | BJ36: 92508289 | BK36: 85628805 | BL36: 85650102 | BM36: 77427376 | BN36: 79383315 | BO36: =80802464-BO34-BO33-BO32 -> 40667937
A37: External Borrowings | B37: 2291669 | D37: 0 | E37: 0 | F37: 0 | G37: 50000000 | H37: 50000000 | I37: 50000000 | J37: 50000000 | K37: 50000000 | L37: 50000000 | M37: 0 | N37: 0 | O37: 0 | Q37: 0 | R37: 0 | S37: 0 | T37: 0 | U37: 0 | V37: 0 | W37: 0 | X37: 0 | Y37: 0 | Z37: 1.1081053e+09 | AA37: 1.0209035e+09 | AB37: 9.6395552e+08 | AD37: 0 | AE37: 0 | AF37: 0 | AG37: 0 | AH37: 0 | AI37: 0 | AJ37: 0 | AK37: 0 | AL37: 0 | AM37: 0 | AN37: 0 | AO37: 0 | AP37: 0 | AQ37: 0 | AR37: 0 | AS37: 0 | AT37: 0 | AU37: 0 | AV37: 0 | AW37: 0 | AX37: 0 | AY37: 0 | AZ37: 0 | BA37: 0 | BC37: 0 | BD37: 0 | BE37: 0 | BF37: 0 | BG37: 0 | BH37: 0 | BI37: 0 | BJ37: 0 | BK37: 0 | BL37: 0 | BM37: 0 | BN37: 0
A38: Total Liabilities | B38: =SUM(B31:B37) -> 135756157 | C38: =SUM(C31:C37) -> 892444676 | D38: =SUM(D31:D37) -> 8.4946109e+08 | E38: =SUM(E31:E37) -> 8.3373098e+08 | F38: =SUM(F31:F37) -> 8.1437137e+08 | G38: =SUM(G31:G37) -> 8.775164e+08 | H38: =SUM(H31:H37) -> 8.7295918e+08 | I38: =SUM(I31:I37) -> 8.835049e+08 | ... BO38: =SUM(BO31:BO37) -> 1015826716 | BP38: =1015826716-BO38 -> 0
A39: Share Capital | B39: 10494697 | C39: 140665447 | D39: 1.4125438e+08 | E39: 1.4179872e+08 | F39: 1.4241276e+08 | G39: 1.4299761e+08 | H39: 1.4364773e+08 | I39: 1.4424474e+08 | J39: 1.4474297e+08 | K39: 1.452943e+08 | L39: 1.4635976e+08 | M39: 1.5426005e+08 | N39: 1.5549845e+08 | O39: 1.5670017e+08 | P39: 156700172 | Q39: 1.5803147e+08 | R39: 1.5924874e+08 | S39: 1.6071492e+08 | T39: 1.6214125e+08 | U39: 1.6311822e+08 | V39: 1.6443412e+08 | W39: 1.6566442e+08 | X39: 1.6711237e+08 | Y39: 168298212 | Z39: 0 | AA39: 0 | AB39: 0 | AC39: 172698282 | AD39: 174143525 | AE39: 1.7572781e+08 | AF39: 1.7624558e+08 | AG39: 1.767506e+08 | AH39: 1.7721989e+08 | AI39: 1.7766403e+08 | AJ39: 3.5741911e+08 | AK39: 1.7920926e+08 | AL39: 1.8813188e+08 | AM39: 1.8867123e+08 | AN39: 1.8836904e+08 | AO39: 188369039 | AP39: 1.8882198e+08 | AQ39: 1.8919627e+08 | AR39: 1.8999778e+08 | AS39: 1.9117504e+08 | AT39: 1.9208848e+08 | AU39: 1.9292552e+08 | AV39: 1.9358626e+08 | AW39: 1.941248e+08 | AX39: 1.9471572e+08 | AY39: 2.0123239e+08 | AZ39: 2.0185256e+08 | BA39: 2.0256844e+08 | BB39: 2.0256844e+08 | BC39: 2.0336732e+08 | BD39: 2.0401677e+08 | BE39: 2.0542966e+08 | BF39: 2.0635178e+08 | BG39: 2.0748024e+08 | BH39: 2.0840819e+08 | BI39: 2.1261211e+08 | BJ39: 2.1340288e+08 | BK39: 2.1429143e+08 | BL39: 2.1508108e+08 | BM39: 2.1610536e+08 | BN39: 2.1712031e+08 | BO39: 217120114
A40: Capital Grants | B40: 340425 | D40: 0 | E40: 0 | F40: 0 | G40: 0 | H40: 0 | J40: 0 | K40: 0 | L40: 0 | M40: 0 | N40: 0 | O40: 0 | Q40: 0 | R40: 0 | S40: 0 | T40: 0 | U40: 0 | V40: 0 | W40: 0 | X40: 0 | Y40: 0 | Z40: 33206440 | AA40: 33206440 | AB40: 33205440 | AD40: 0 | AE40: 0 | AF40: 0 | AG40: 0 | AH40: 0 | AI40: 0 | AJ40: 0 | AK40: 0 | AL40: 0 | AM40: 0 | AN40: 0 | AO40: 0 | AP40: 0 | AQ40: 0 | AR40: 0 | AS40: 0 | AT40: 0 | AU40: 0 | AV40: 0 | AW40: 0 | AX40: 0 | AY40: 0 | AZ40: 0 | BA40: 0 | BC40: 0 | BD40: 0 | BE40: 0 | BF40: 0 | BG40: 0 | BH40: 0 | BI40: 0 | BJ40: 0 | BK40: 0 | BL40: 0 | BM40: 0 | BN40: 0
A41: Prior Year Retained Earnigs | B41: 351220 | C41: 14978344 | D41: 27664229 | E41: 20813817 | F41: 20813817 | G41: 20813817 | H41: 20813817 | I41: 20813817 | J41: 20813817 | K41: 20813817 | L41: 20813817 | M41: 20813817 | N41: 20813817 | O41: 20813817 | P41: 20813820 | Q41: 44640848 | R41: 33206440 | S41: 33206440 | T41: 33206440 | U41: 33206440 | V41: 33206440 | W41: 33206440 | X41: 33206440 | Y41: 33206440 | Z41: 7594989.2 | AA41: 13282647 | AB41: 21945690 | AC41: 33206443 | AD41: 57730844 | AE41: 44826110 | AF41: 44826110 | AG41: 44826110 | AH41: 44825389 | AI41: 44822491 | AJ41: 89644982 | AK41: 44822491 | AL41: 44822491 | AM41: 44822491 | AN41: 44822491 | AO41: 44825378 | AP41: 72593813 | AQ41: 53317385 | AR41: 53317385 | AS41: 53317385 | AT41: 53317385 | AU41: 53317385 | AV41: 53317385 | AW41: 53317385 | AX41: 53317377 | AY41: 53317377 | AZ41: 53317377 | BA41: 53317373 | BB41: 53317384 | BC41: 75638698 | BD41: 72899349 | BE41: 54195790 | BF41: 54195790 | BG41: 54195790 | BH41: 54195790 | BI41: 54195790 | BJ41: 54195790 | BK41: 54148616 | BL41: 54195790 | BM41: 54195790 | BN41: 32336457 | BO41: 54209976
A42: Current Year Surplus | B42: 3541956 | C42: 5835476 | D42: 9337095 | E42: 6504356.7 | F42: 7436870.6 | G42: 6071812 | H42: 4366474.7 | I42: 4663858 | J42: 4946815.8 | K42: 10990214 | L42: 10296055 | M42: 14289780 | N42: 16311411 | O42: 23827031 | P42: 13061625 | Q42: 3752898.5 | R42: 1222702.7 | S42: 1599641.2 | T42: 2379802.3 | U42: 1972446.1 | V42: 5036313.9 | W42: 1573466.7 | X42: 4704502.7 | Y42: 5175944.2 | Z42: 36468878 | AA42: 36468878 | AB42: 36468878 | AC42: =24523668-8000000-4904734 -> 11618934 | AD42: 4204913.6 | AE42: 3002478 | AF42: 2008460.9 | AG42: 3946586.3 | AH42: 4231703.6 | AI42: 6148706.5 | AJ42: 14872507 | AK42: 5073515.9 | AL42: 9673220 | AM42: 20813588 | AN42: 27034600 | AO42: =27771322-5554264-2888-13465213 -> 8748957 | AP42: 2294299.1 | AQ42: 398257.88 | AR42: 3064887.4 | AS42: 3661793.8 | AT42: 5850402.6 | AU42: 5938418.6 | AV42: 6753168.9 | AW42: 7930110.1 | AX42: 8733514.4 | AY42: 12047730 | AZ42: 15063251 | BA42: 22321321 | BB42: =19582505+-3916501+-5+-14787592 -> 878407 | BC42: 895726.83 | BD42: 1526619.8 | BE42: 2513660.6 | BF42: 4337750.5 | BG42: 5661253.9 | BH42: 6323436.8 | BI42: 8134736.2 | BJ42: 8419733.4 | BK42: 8935840.6 | BL42: 11807850 | BM42: 13189937 | BN42: 24002152 | BO42: =24002152-4800430 -> 19201722
A43: Statutory Reserves | B43: 531274 | C43: 31870722 | D43: 29333544 | E43: 31870722 | F43: 31870722 | G43: 31870722 | H43: 31870722 | I43: 31870722 | J43: 31870722 | K43: 31870722 | L43: 31870722 | M43: 31870722 | N43: 31870722 | O43: 31870722 | P43: 36636128 | Q43: 31870722 | R43: 36468878 | S43: 36468878 | T43: 36468878 | U43: 36468878 | V43: 36468878 | W43: 36468878 | X43: 36468878 | Y43: 36468878 | Z43: 20871074 | AA43: 20871074 | AB43: 20871074 | AC43: 41373612 | AD43: 36468878 | AE43: 41373612 | AF43: 41373612 | AG43: 41373612 | AH43: 41373612 | AI43: 41373612 | AJ43: 82747224 | AK43: 41373612 | AL43: 41373612 | AM43: 41373612 | AN43: 41373612 | AO43: 46927876 | AP43: 41373612 | AQ43: 46863639 | AR43: 46863639 | AS43: 46863639 | AT43: 46863639 | AU43: 46863639 | AV43: 46863639 | AW43: 46863639 | AX43: 46863639 | AY43: 46863639 | AZ43: 46863639 | BA43: 46863639 | BB43: 50780140 | BC43: 46863639 | BD43: 46863639 | BE43: 50780140 | BF43: 50780140 | BG43: 50780140 | BH43: 50780140 | BI43: 50780140 | BJ43: 50780140 | BK43: 50780140 | BL43: 50780140 | BM43: 50780140 | BN43: 55580570 | BO43: 55580570
A44: Other Reserves | C44: 58441770 | D44: 20871074 | E44: 20871074 | F44: 20871074 | G44: 20871074 | H44: 20871074 | I44: 20871074 | J44: 20871074 | K44: 20871074 | L44: 20871074 | M44: 20871074 | N44: 20871074 | O44: 20871074 | P44: 20871074 | Q44: 20871074 | R44: 20871074 | S44: 20871074 | T44: 20871074 | U44: 20871074 | V44: 20871074 | W44: 20871074 | X44: 20871074 | Y44: 20871074 | Z44: 37570696 | AA44: 37570696 | AB44: 37570696 | AC44: 20871074 | AD44: 20871074 | AE44: 20871074 | AF44: 20871074 | AG44: 20871074 | AH44: 20871074 | AI44: 20871074 | AJ44: 41742148 | AK44: 20871074 | AL44: 20871074 | AM44: 20871074 | AN44: 20871074 | AO44: 20871074 | AP44: 20871074 | AQ44: 20871074 | AR44: 20871074 | AS44: 20871074 | AT44: 20871074 | AU44: 20871074 | AV44: 20871074 | AW44: 20871074 | AX44: 20871074 | AY44: 20871074 | AZ44: 20871074 | BA44: 20871074 | BB44: 20871074 | BC44: 20871074 | BD44: 20871074 | BE44: 20871074 | BF44: 20871074 | BG44: 20871074 | BH44: 20871074 | BI44: 20871074 | BJ44: 20871074 | BK44: 20871074 | BL44: 20871074 | BM44: 20871074 | BN44: 20871074 | BO44: 20871074
A45: Revaluation Reserves | D45: 37570696 | E45: 37570696 | F45: 37570696 | G45: 37570696 | H45: 37570696 | I45: 37570696 | J45: 37570696 | K45: 37570696 | L45: 37570696 | M45: 37570696 | N45: 37570696 | O45: 37570696 | P45: 37570696 | Q45: 37570696 | R45: 37570696 | S45: 37570696 | T45: 37570696 | U45: 37570696 | V45: 37570696 | W45: 37570696 | X45: 37570696 | Y45: 37570696 | Z45: 0 | AA45: 0 | AB45: 0 | AC45: 37570696 | AD45: 37570696 | AE45: 37570696 | AF45: 37570696 | AG45: 37570696 | AH45: 37570696 | AI45: 37570696 | AJ45: 75141392 | AK45: 37570696 | AL45: 37570696 | AM45: 37570696 | AN45: 37570696 | AO45: 37570696 | AP45: 37570696 | AQ45: 37570696 | AR45: 37570696 | AS45: 37570696 | AT45: 37570696 | AU45: 37570696 | AV45: 37570696 | AW45: 37570696 | AX45: 37570696 | AY45: 37570696 | AZ45: 37570696 | BA45: 37570696 | BB45: 37570696 | BC45: 37570696 | BD45: 37570696 | BE45: 37570696 | BF45: 37570696 | BG45: 37570696 | BH45: 37570697 | BI45: 37570696 | BJ45: 37570696 | BK45: 37570696 | BL45: 37570696 | BM45: 37570696 | BN45: 37570696 | BO45: 37570696
A46: Proposed Dividends | C46: 4313234 | E46: 4313234 | F46: 0 | G46: 0 | H46: 0 | K46: 0 | L46: 0 | M46: 0 | N46: 0 | O46: 0 | P46: 6000000 | Q46: 0 | R46: 6000000 | S46: 0 | T46: 0 | U46: 0 | V46: 0 | W46: 0 | X46: 0 | Y46: 0 | Z46: 0 | AA46: 0 | AB46: 0 | AC46: 8000000 | AD46: 0 | AE46: 8000000 | AF46: 0 | AG46: 0 | AH46: 0 | AI46: 0 | AJ46: 0 | AK46: 0 | AL46: 0 | AM46: 0 | AN46: 0 | AO46: 13465213 | AP46: 0 | AQ46: 13465213 | AR46: 0 | AS46: 0 | AT46: 78715.6 | AU46: 0 | AV46: 0 | AW46: 0 | AX46: 0 | AY46: 0 | AZ46: 0 | BA46: 0 | BB46: 14787592 | BC46: 0 | BD46: 0 | BE46: 0 | BF46: 0 | BG46: 0 | BH46: 0 | BI46: 0 | BJ46: 0 | BK46: 0 | BL46: 0 | BM46: 0 | BN46: 0
A47: Adjustment To Equity | D47: 0 | E47: 0 | F47: 0 | G47: 0 | H47: 0 | K47: 0 | L47: 0 | M47: 0 | N47: 0 | O47: 0 | Q47: 0 | R47: 0 | S47: 0 | T47: 0 | U47: 0 | V47: 0 | W47: 0 | X47: 0 | Y47: 0 | Z47: 3.0569842e+08 | AA47: 3.1273298e+08 | AB47: 3.2276006e+08 | AD47: 0 | AE47: 0 | AF47: 0 | AG47: 0 | AH47: 0 | AI47: 0 | AJ47: 0 | AK47: 0 | AL47: 0 | AM47: 0 | AN47: 0 | AO47: 0 | AP47: 0 | AQ47: 0 | AR47: 0 | AS47: 0 | AT47: 0 | AU47: 0 | AV47: 0 | AW47: 0 | AX47: 0 | AY47: 0 | AZ47: 0 | BA47: 0 | BC47: 0 | BD47: 0 | BE47: 0 | BF47: 0 | BG47: 0 | BH47: 0 | BI47: 0 | BJ47: 0 | BK47: 0 | BL47: 0 | BM47: 0 | BN47: 0
A48: Total Equity | B48: =SUM(B39:B45) -> 15259572 | C48: =SUM(C39:C45) -> 251791759 | D48: =SUM(D39:D45) -> 2.6603102e+08 | E48: =SUM(E39:E45) -> 2.5942939e+08 | F48: =SUM(F39:F45) -> 2.6097594e+08 | G48: =SUM(G39:G45) -> 2.6019574e+08 | H48: =SUM(H39:H45) -> 2.5914052e+08 | I48: =SUM(I39:I45) -> 2.6003491e+08 | ... O48: =SUM(O39:O45) -> 2.9165351e+08 | P48: =SUM(P39:P47) -> 291653515 | Q48: =SUM(Q39:Q47) -> 2.967377e+08 | R48: =SUM(R39:R47) -> 2.9458853e+08 | S48: =SUM(S39:S47) -> 2.9043165e+08 | T48: =SUM(T39:T47) -> 2.9263814e+08 | U48: =SUM(U39:U47) -> 2.9320775e+08 | V48: =SUM(V39:V47) -> 2.9758752e+08 | W48: =SUM(W39:W47) -> 2.9535497e+08 | ... BO48: =SUM(BO39:BO47) -> 404554152 | BP48: =404554152-BO48 -> 0
A49: Total Liabilities and Equity | B49: =SUM(B38+B48) -> 151015729 | C49: =SUM(C38+C48) -> 1144236435 | D49: =SUM(D38+D48) -> 1.1154921e+09 | E49: =SUM(E38+E48) -> 1.0931604e+09 | F49: =SUM(F38+F48) -> 1.0753473e+09 | G49: =SUM(G38+G48) -> 1.1377121e+09 | H49: =SUM(H38+H48) -> 1.1320997e+09 | I49: =SUM(I38+I48) -> 1.1435398e+09 | ... BO49: =SUM(BO38+BO48) -> 1420380868
K50: 1.1228033e+09 | L50: 1.110947e+09 | M50: 1.4715746e+09
B51: =B49-B27 -> 0 | C51: =C49-C27 -> -4313235 | D51: =D49-D27 -> 0 | E51: =E49-E27 -> -4313234 | F51: =F49-F27 -> 0 | G51: =G49-G27 -> 0 | H51: =H49-H27 -> 0 | I51: =I49-I27 -> 0 | ... AO51: =AO49-AO27 -> 1 | BN51: =SUM(BN39:BN44) -> 3.4991057e+08
BM52: cc | BN52: =BN51-BN13 -> 2.8874109e+08 | BO52: =BN52/BN49 -> 0.20316493
BK53: 2.1429143e+08 | BM53: ica | BN53: =BN52-BN39 -> 71620775 | BO53: =BN53/BN49 -> 0.050394039
BH55: 3.4659385e+08 | BK55: 54148616
BH56: =BH55-BI45-BI39 -> 96411044 | BK56: 8935840.6
BK57: 50780140
BK58: 20871074

Sheet Evolutitve SCI
B2: 2010 Audited | C2: 2017 Audited | D2: 43101 | E2: 43132 | F2: 43160 | G2: 43191 | H2: 43221 | I2: 43252 | J2: 43282 | K2: 43313 | L2: 43344 | M2: 43374 | N2: 43405 | O2: 43435 | P2: Audited 2018 | Q2: 43468 | R2: 43500 | S2: 43529 | T2: 43561 | U2: 43592 | V2: 43624 | W2: 43655 | X2: 43687 | Y2: 43719 | Z2: 43751 | AA2: 43783 | AB2: 43814 | AC2: Audited 2019 | AD2: 43831 | AE2: 43863 | AF2: 43893 | AG2: 43925 | AH2: 43956 | AI2: 43988 | AJ2: 44050 | AK2: 44082 | AL2: 44113 | AM2: 44145 | AN2: 44176 | AO2: AUDITED 2020 | AP2: 44197 | AQ2: 44228 | AR2: 44256 | AS2: 44287 | AT2: 44317 | AU2: 44348 | AV2: 44378 | AW2: 44409 | AX2: 44440 | AY2: 44470 | AZ2: 44501 | BA2: 44531 | BB2: Audited 2021 | BC2: 44562 | BD2: 44593 | BE2: 44621 | BF2: 44652 | BG2: 44682 | BH2: 44713 | BJ2: 44774 | BK2: 44805 | BL2: 44835 | BM2: 44866 | BN2: 44896 | BO2: Audited 2022
A3: Financial Income | B3: =B4+B7 -> 14599.248 | C3: =C4+C7 -> 196687961 | D3: =D4+D7 -> 20632764 | E3: =E4+E7 -> 33797993 | F3: =F4+F7 -> 49279715 | G3: =G4+G7 -> 63359741 | H3: =H4+H7 -> 76929656 | I3: =I4+I7 -> 92872973 | ... BO3: =BO4+BO7 -> 247513451
A4: Financial Income From Loans Portfolio | B4: =SUM(B5:B6) -> 12855.806 | C4: =SUM(C5:C6) -> 101379709 | D4: =SUM(D5:D6) -> 14702682 | E4: =SUM(E5:E6) -> 24866329 | F4: =SUM(F5:F6) -> 34937646 | G4: =SUM(G5:G6) -> 44610248 | H4: =SUM(H5:H6) -> 54494569 | I4: =SUM(I5:I6) -> 64556122 | ... BO4: =SUM(BO5:BO6) -> 110031921
A5: Interest from Loans Portfolio | B5: 11945.435 | C5: 101379709 | D5: 8717884.7 | E5: 16536521 | F5: 24769552 | G5: 33029523 | H5: 41174093 | I5: 49592524 | J5: 58018276 | K5: 66482267 | L5: 75089317 | M5: 84006737 | N5: 91947336 | O5: 99290901 | P5: 99290901 | Q5: 7290707.8 | R5: 14689937 | S5: 22258080 | T5: 29806768 | U5: 37459750 | V5: 44863923 | W5: 52609186 | X5: 60508706 | Y5: 68756023 | Z5: 77040675 | AA5: 86064271 | AB5: 93202279 | AC5: 93202429 | AD5: 8958073.4 | AE5: 17474186 | AF5: 25199720 | AG5: 32915641 | AH5: 38840640 | AI5: 46510236 | AJ5: 1.2375095e+08 | AK5: 69812015 | AL5: 78070441 | AM5: 86279821 | AN5: 93908094 | AO5: =86063537+7844557 -> 93908094 | AP5: 7398131.1 | AQ5: 14908275 | AR5: 22633024 | AS5: 30164131 | AT5: 37845373 | AU5: 45763059 | AV5: 53850210 | AW5: 65242809 | AX5: 70568441 | AY5: 79126544 | AZ5: 87585411 | BA5: 95746455 | BB5: 95746455 | BC5: 8405722.1 | BD5: 16823189 | BE5: 24963077 | BF5: 33817846 | BG5: 42666291 | BH5: 51743615 | BI5: 64292625 | BJ5: 70303509 | BK5: 79458535 | BL5: 88762901 | BM5: 98709165 | BN5: 28685478
A6: Fees&Commision on Loan Portfolio | B6: 910.371 | D6: 5984797.8 | E6: 8329807.6 | F6: 10168094 | G6: 11580725 | H6: 13320476 | I6: 14963597 | J6: 16062461 | K6: 17318213 | L6: 18868826 | M6: 20348148 | N6: 25607478 | O6: 29817360 | P6: =81562736-14561 -> 81548175 | Q6: 3517907.4 | R6: 5535316.8 | S6: 7116614.3 | T6: 8247186.1 | U6: 10079237 | V6: 11251999 | W6: 12505783 | X6: 13766952 | Y6: 15106726 | Z6: 16346488 | AA6: 20822827 | AB6: 21677248 | AD6: 3868442.9 | AE6: 5305052.9 | AF6: 6701819.5 | AG6: 7576018 | AH6: 9051697.2 | AI6: 10693031 | AJ6: 26337947 | AK6: 15210850 | AL6: 17122230 | AM6: 22170483 | AN6: 28188090 | AO6: 0 | AP6: 2711447.5 | AQ6: 4285662.4 | AR6: 6049417.8 | AS6: 6982233.6 | AT6: 9161633.5 | AU6: 10936217 | AV6: 12654073 | AW6: 14648555 | AX6: 16429202 | AY6: 17918241 | AZ6: 23184600 | BA6: 26800583 | BC6: 3298517.3 | BD6: 4866170.7 | BE6: 6441570.8 | BF6: 8737798.7 | BG6: 10575357 | BH6: 12654265 | BI6: 15766921 | BJ6: 18394985 | BK6: 21608192 | BL6: 23346746 | BM6: 26230769 | BN6: 1.1003192e+08 | BO6: 110031921
A7: Financial Income from Investments | B7: =SUM(B8:B11) -> 1743.4416 | C7: =SUM(C8:C11) -> 95308252 | D7: =SUM(D8:D11) -> 5930081.5 | E7: =SUM(E8:E11) -> 8931664 | F7: =SUM(F8:F11) -> 14342069 | G7: =SUM(G8:G11) -> 18749494 | H7: =SUM(H8:H11) -> 22435087 | I7: =SUM(I8:I11) -> 28316851 | ... BO7: =SUM(BO8:BO11) -> 137481530
A8: Government Securities | K8: 0 | L8: 0 | M8: 0 | N8: 0 | O8: 0 | Q8: 0 | R8: 0 | S8: 0 | T8: 0 | U8: 0 | V8: 0 | W8: 0 | X8: 0 | Y8: 0 | Z8: 0 | AA8: 0 | AB8: 0 | AD8: 0 | AE8: 0 | AF8: 0 | AG8: 0 | AH8: 0 | AI8: 0 | AJ8: 0 | AK8: 0 | AL8: 0 | AM8: 0 | AN8: 0 | AO8: 0 | AP8: 0 | AQ8: 0 | AR8: 0 | AS8: 0 | AT8: 0 | AU8: 0 | AV8: 0 | AW8: 0 | AX8: 0 | AY8: 0 | AZ8: 0 | BA8: 0 | BC8: 0 | BD8: 0 | BE8: 0 | BF8: 0 | BG8: 0 | BH8: 0 | BI8: 0 | BJ8: 0 | BK8: 0 | BL8: 0 | BM8: 0 | BN8: 0
A9: Deposits with Banks & other Financial Institutions | K9: 0 | L9: 0 | M9: 0 | N9: 0 | O9: 0 | Q9: 0 | R9: 0 | S9: 0 | T9: 0 | U9: 0 | V9: 0 | W9: 0 | X9: 0 | Y9: 0 | Z9: 0 | AA9: 0 | AB9: 0 | AC9: 49389698 | AD9: 0 | AE9: 0 | AF9: 0 | AG9: 0 | AH9: 0 | AI9: 0 | AJ9: 0 | AK9: 0 | AL9: 0 | AM9: 0 | AN9: 0 | AO9: 50216519 | AP9: 0 | AQ9: 0 | AR9: 0 | AS9: 0 | AT9: 0 | AU9: 0 | AV9: 0 | AW9: 0 | AX9: 0 | AY9: 0 | AZ9: 0 | BA9: 0 | BC9: 0 | BD9: 0 | BE9: 0 | BF9: 0 | BG9: 0 | BH9: 0 | BI9: 0 | BJ9: 0 | BK9: 0 | BL9: 0 | BM9: 0 | BN9: 0
A10: Other Investments | C10: 19742246 | D10: 2073612.1 | E10: 2073612.1 | F10: 2073612.1 | G10: 2073852.1 | H10: 2413278.1 | I10: 4019531.5 | J10: 4019531.5 | K10: 14165171 | L10: 14559868 | M10: 14559868 | N10: 23246698 | O10: 28123641 | P10: 28123641 | Q10: 135 | R10: 0 | S10: 1757713.7 | T10: 2948213.7 | U10: 5316754.8 | V10: 18379672 | W10: 18753829 | X10: 21054332 | Y10: 22147491 | Z10: 35615970 | AA10: 37316963 | AB10: 49378494 | AD10: 0 | AE10: 4016402.3 | AF10: 4016402.3 | AG10: 7096875.7 | AH10: 10055053 | AI10: 10480328 | AJ10: 33546692 | AK10: 16837456 | AL10: 32343986 | AM10: 40336048 | AN10: 46716519 | AO10: 0 | AP10: 312306.55 | AQ10: 4962306.5 | AR10: 6943470.7 | AS10: 7845936.5 | AT10: 12667799 | AU10: 13541286 | AV10: 14335121 | AW10: 13932696 | AX10: 22600503 | AY10: 24157490 | AZ10: 27360204 | BA10: 47900587 | BB10: 50340313 | BC10: 2439726 | BD10: 5138804.2 | BE10: 10949778 | BF10: 13292244 | BG10: 16485515 | BH10: 18689068 | BI10: 21051841 | BJ10: 23294558 | BK10: 23914010 | BL10: 27780586 | BM10: 41904970 | BN10: 56472602 | BO10: 56472602
A11: Other Operating Income | B11: 1743.4416 | C11: 75566006 | D11: 3856469.4 | E11: 6858051.9 | F11: 12268457 | G11: 16675642 | H11: 20021809 | I11: 24297320 | J11: 28136230 | K11: 31429587 | L11: 35566182 | M11: 46594947 | N11: 49615027 | O11: 54807143 | P11: =14561+1204074 -> 1218635 | Q11: 3533749.5 | R11: 6969597 | S11: 12500094 | T11: 16542439 | U11: 19500368 | V11: 28858371 | W11: 31927220 | X11: 34608545 | Y11: 39450604 | Z11: 47520962 | AA11: 51540748 | AB11: 55991653 | AC11: 77650273 | AD11: 3689317.1 | AE11: 6825384.3 | AF11: 12990887 | AG11: 16789994 | AH11: 19752581 | AI11: 25742531 | AJ11: 65666734 | AK11: 37285539 | AL11: 45556794 | AM11: 49486516 | AN11: 53184154 | AO11: =79189255-44923 -> 79144332 | AP11: 4075658.4 | AQ11: 6710279.1 | AR11: 12249415 | AS11: 17079010 | AT11: 20400607 | AU11: 26409070 | AV11: 31669239 | AW11: 34488851 | AX11: 38566517 | AY11: 46578203 | AZ11: 50321413 | BA11: 56024138 | BB11: 79493733 | BC11: 3603748.6 | BD11: 6643209.9 | BE11: 12950968 | BF11: 17310935 | BG11: 20466699 | BH11: 26964862 | BI11: 36975190 | BJ11: 40055598 | BK11: 44272978 | BL11: 47549484 | BM11: 50505872 | BN11: 54002923 | BO11: 81008928
A12: Financial Expenses | B12: =SUM(B13:B18) -> 549.0847 | C12: =SUM(C13:C18) -> 36454183 | D12: =SUM(D13:D18) -> 683422.61 | E12: =SUM(E13:E18) -> 1455171.6 | F12: =SUM(F13:F18) -> 2189689.4 | G12: =SUM(G13:G18) -> 3555682.5 | H12: =SUM(H13:H18) -> 8815417.6 | I12: =SUM(I13:I18) -> 11455361 | ... BO12: =SUM(BO13:BO18) -> 25337212
A13: Interest Expense on Deposits | B13: 185.36 | C13: 14766796 | D13: 588165.55 | E13: 1014759.5 | F13: 1486405.9 | G13: 2076187.8 | H13: 6320227.6 | I13: 8020486.7 | J13: 9694002.1 | K13: 11248585 | L13: 12742101 | M13: 14751978 | N13: 17219789 | O13: 18459704 | P13: =10533194+7926510 -> 18459704 | Q13: 739198.65 | R13: 1257955.4 | S13: 2225826.4 | T13: 2648297.5 | U13: 6818095.1 | V13: 12624926 | W13: 14806184 | X13: 15240192 | Y13: 17435435 | Z13: 23933926 | AA13: 24446528 | AB13: 25491734 | AC13: 25491734 | AD13: 895797.3 | AE13: 3045494.4 | AF13: 5378648.3 | AG13: 6236991.5 | AH13: 8332408.7 | AI13: 10463844 | AJ13: 30343248 | AK13: 17294473 | AL13: 22571873 | AM13: 24964376 | AN13: 20712158 | AO13: =9165820+11546338 -> 20712158 | AP13: 1384244.1 | AQ13: 2668128.3 | AR13: 3535902.8 | AS13: 4013128 | AT13: 6095721.1 | AU13: 9124081.1 | AV13: 11179952 | AW13: 13509786 | AX13: 16647427 | AY13: 18209763 | AZ13: 20523361 | BA13: 23470699 | BB13: 23470699 | BC13: 269373.45 | BD13: 840650.45 | BE13: 3928451.9 | BF13: 5855531.3 | BG13: 7902594 | BH13: 10618873 | BI13: 14894538 | BJ13: 16223641 | BK13: 18112636 | BL13: 20488225 | BM13: 30383393 | BN13: 24699335 | BO13: 24699335
A14: Cost of External Borrowings | B14: 363.7247 | C14: 17546381 | D14: 0 | E14: 0 | F14: 0 | G14: 500000 | H14: 1289041.1 | I14: 1798630.2 | J14: 2291680.9 | K14: 2846576.3 | L14: 3356165.4 | M14: 3865754.5 | N14: 3865754.5 | O14: 3865754.5 | P14: =3365754+500000 -> 3865754 | Q14: 0 | R14: 0 | S14: 0 | T14: 0 | U14: 0 | V14: 0 | W14: 0 | X14: 0 | Y14: 0 | Z14: 0 | AA14: 0 | AB14: 0 | AD14: 0 | AE14: 0 | AF14: 0 | AG14: 0 | AH14: 0 | AI14: 0 | AJ14: 0 | AK14: 0 | AL14: 0 | AM14: 0 | AN14: 0 | AO14: 0 | AP14: 0 | AQ14: 0 | AR14: 0 | AS14: 0 | AT14: 0 | AU14: 0 | AV14: 0 | AW14: 0 | AX14: 0 | AY14: 0 | AZ14: 0 | BA14: 0 | BC14: 0 | BD14: 0 | BE14: 0 | BF14: 0 | BG14: 0 | BH14: 0 | BI14: 0 | BJ14: 0 | BK14: 0 | BL14: 0 | BM14: 0 | BN14: 0 | BO14: 0
A15: Dividend Expenses | D15: 0 | E15: 0 | F15: 0 | G15: 0 | H15: 0 | K15: 0 | L15: 0 | M15: 0 | N15: 0 | O15: 0 | Q15: 0 | R15: 0 | S15: 0 | T15: 0 | U15: 0 | V15: 0 | W15: 0 | X15: 0 | Y15: 0 | Z15: 0 | AA15: 0 | AB15: 0 | AD15: 0 | AE15: 0 | AF15: 0 | AG15: 0 | AH15: 0 | AI15: 0 | AJ15: 0 | AK15: 0 | AL15: 0 | AM15: 0 | AN15: 0 | AO15: 0 | AP15: 0 | AQ15: 0 | AR15: 0 | AS15: 0 | AT15: 0 | AU15: 0 | AV15: 0 | AW15: 0 | AX15: 0 | AY15: 0 | AZ15: 0 | BA15: 0 | BC15: 0 | BD15: 0 | BE15: 0 | BF15: 476614.7 | BG15: 0 | BH15: 0 | BI15: 0 | BJ15: 0 | BK15: 0 | BL15: 0 | BM15: 0 | BN15: 0 | BO15: 0
A16: Other Financial Expense | C16: 4141006 | D16: 0 | E16: 0 | F16: 0 | G16: 0 | H16: 0 | K16: 0 | L16: 0 | M16: 0 | N16: 0 | O16: 0 | P16: =28644578-P21+836253 -> 13321596 | Q16: 0 | R16: 0 | S16: 0 | T16: 0 | U16: 0 | V16: 0 | W16: 0 | X16: 0 | Y16: 0 | Z16: 0 | AA16: 0 | AB16: 0 | AC16: =29510661-275843 -> 29234818 | AD16: 0 | AE16: 0 | AF16: 0 | AG16: 0 | AH16: 0 | AI16: 0 | AJ16: 0 | AK16: 0 | AL16: 0 | AM16: 0 | AN16: 0 | AO16: =1026619+526672+353986+2500000+17940727 -> 22348004 | AP16: 0 | AQ16: 0 | AR16: 0 | AS16: 0 | AT16: 0 | AU16: 0 | AV16: 0 | AW16: 0 | AX16: 0 | AY16: 0 | AZ16: 0 | BA16: 0 | BC16: 0 | BD16: 0 | BE16: 0 | BF16: 0 | BG16: 0 | BH16: 0 | BI16: 0 | BJ16: 0 | BK16: 0 | BL16: 0 | BM16: 0 | BN16: 0 | BO16: 0
A17: Fees & Commision Expense | D17: 95257.06 | E17: 151573.28 | F17: 270025.21 | G17: 388817.05 | H17: 471051.69 | I17: 756727.43 | J17: 853610.7 | K17: 885382.7 | L17: 945141.2 | M17: 1067583.3 | N17: 1149740.7 | O17: 1383204.5 | Q17: 0 | R17: 0 | S17: 189119.2 | T17: 246141.8 | U17: 341687.9 | V17: 405045 | W17: 497679.1 | X17: 526737.1 | Y17: 582970.2 | Z17: 785173.9 | AA17: 894146 | AB17: 1604281.6 | AD17: 99727.3 | AE17: 162411.5 | AF17: 194263.7 | AG17: 242107.7 | AH17: 296072.8 | AI17: 469450.9 | AJ17: 1309287.8 | AK17: 707182.3 | AL17: 845213.2 | AM17: 949919.9 | AN17: 1026619.1 | AO17: 0 | AP17: 29083.9 | AQ17: 58442 | AR17: 194003.4 | AS17: 243478.3 | AT17: 335389.2 | AU17: 369369.6 | AV17: 408135.1 | AW17: 473681.7 | AX17: 520458.6 | AY17: 575900.3 | AZ17: 575405.3 | BA17: 647924.7 | BC17: 15143.1 | BD17: 30352.1 | BE17: 56347 | BF17: 43861.3 | BG17: 104300.7 | BH17: 237564.1 | BI17: 317160 | BJ17: 374448.8 | BK17: 420556.8 | BL17: 474819.2 | BM17: 538653.3 | BN17: 637876.5 | BO17: 637877
A18: Other Expenses | D18: 0 | E18: 288838.86 | F18: 433258.3 | G18: 590677.74 | H18: 735097.18 | I18: 879516.62 | J18: 1852161.1 | K18: 1996580.5 | L18: 2348055.9 | M18: 2492475.4 | N18: 2841765.4 | O18: 2841765.4 | Q18: 101770.2 | R18: 140433.2 | S18: 1278357 | T18: 1278357 | U18: 1278357 | V18: 1278357 | W18: 1278357 | X18: 1278357 | Y18: 1278357 | Z18: 1278357 | AA18: 1278357 | AB18: 1278357 | AD18: 0 | AE18: 1397004 | AF18: 1397004 | AG18: 1397004 | AH18: 1397004 | AI18: 1397004 | AJ18: 2794008 | AK18: 1397004 | AL18: 1871004 | AM18: 1871004 | AN18: 1871004 | AO18: 0 | AP18: 0 | AQ18: 1363400 | AR18: 1363400 | AS18: 1363400 | AT18: 1363400 | AU18: 1363400 | AV18: 1363400 | AW18: 1363400 | AX18: 2163400 | AY18: 2963400 | AZ18: 2963400 | BA18: 7157547.7 | BC18: 1656391 | BD18: 1656391 | BE18: 1656391 | BF18: 1656391 | BG18: 1656391 | BH18: 1656391 | BI18: 1656391 | BJ18: 1656391 | BK18: 1664130 | BL18: 1664130 | BM18: 1664130 | BN18: 1656391
A19: Net Financial Income | B19: =B3-B12 -> 14050.163 | C19: =C3-C12 -> 160233778 | D19: =D3-D12 -> 19949341 | E19: =E3-E12 -> 32342821 | F19: =F3-F12 -> 47090025 | G19: =G3-G12 -> 59804059 | H19: =H3-H12 -> 68114238 | I19: =I3-I12 -> 81417612 | ... BO19: =BO3-BO12 -> 222176239
A20: Allowance for Loan Loss | B20: =B21-B22 -> 0 | C20: =C21-C22 -> 16734938 | D20: =D21-D22 -> 1919351.2 | E20: =E21-E22 -> 5028940.3 | F20: =F21-F22 -> 6948291.5 | G20: =G21-G22 -> 8867642.6 | H20: =H21-H22 -> 10786994 | I20: =I21-I22 -> 12706345 | ... BO20: =BO21-BO22 -> 30683041
A21: Provision for Loan Losses | C21: 16734938 | D21: 1919351.2 | E21: 5028940.3 | F21: 6948291.5 | G21: 8867642.6 | H21: 10786994 | I21: 12706345 | J21: 12706345 | K21: 16557297 | L21: 18476648 | M21: 20749986 | N21: 27088688 | O21: 27261374 | P21: 16159235 | Q21: 0 | R21: 560068.9 | S21: 1120137.7 | T21: 3163955.4 | U21: 3952930.7 | V21: 12262906 | W21: 14306724 | X21: 14306724 | Y21: 16350541 | Z21: 24525812 | AA21: 24525812 | AB21: 27906470 | AC21: 275843 | AD21: 1000000 | AE21: 3043817.7 | AF21: 5087635.4 | AG21: 7278961.2 | AH21: 9322778.9 | AI21: 11366596 | AJ21: 31112464 | AK21: 17600050 | AL21: 23578608 | AM21: 24525812 | AN21: 32017181 | AO21: 11900564 | AP21: 1500000 | AQ21: 2792950.3 | AR21: 3824460.5 | AS21: 5868278.1 | AT21: 7912095.8 | AU21: 9465649.9 | AV21: 11509468 | AW21: 14453285 | AX21: 16497103 | AY21: 19031184 | AZ21: 21075002 | BA21: 25855860 | BB21: 26503785 | BC21: 1535196.2 | BD21: 2700439 | BE21: 4950439 | BF21: 6676462.7 | BG21: 8402486.5 | BH21: 12591368 | BI21: 17410317 | BJ21: 17410317 | BK21: 19022111 | BL21: 20471897 | BM21: 25514524 | BN21: 30683041 | BO21: =27302383+526672+353986+2500000 -> 30683041
A22: Value of Loans Recovered | K22: 0 | L22: 0 | M22: 0 | N22: 0 | O22: 0 | Q22: 0 | R22: 0 | S22: 0 | T22: 0 | U22: 0 | V22: 0 | W22: 0 | X22: 0 | Y22: 0 | Z22: 0 | AA22: 0 | AB22: 0 | AD22: 0 | AE22: 0 | AF22: 0 | AG22: 0 | AH22: 0 | AI22: 0 | AJ22: 0 | AK22: 0 | AL22: 0 | AM22: 0 | AN22: 0 | AO22: 0 | AP22: 0 | AQ22: 0 | AR22: 0 | AS22: 0 | AT22: 0 | AU22: 0 | AV22: 0 | AW22: 0 | AX22: 0 | AY22: 0 | AZ22: 0 | BA22: 0 | BC22: 0 | BD22: 0 | BE22: 0 | BF22: 0 | BG22: 0 | BH22: 0 | BI22: 0 | BJ22: 0 | BK22: 0 | BL22: 0 | BM22: 0 | BN22: 0
A23: Operating Expeses | B23: =SUM(B24:B28) -> 11019.38 | C23: =SUM(C24:C28) -> 130812951 | D23: =SUM(D24:D28) -> 8692895.2 | E23: =SUM(E24:E28) -> 20809524 | F23: =SUM(F24:F28) -> 32704863 | G23: =SUM(G24:G28) -> 44864604 | H23: =SUM(H24:H28) -> 54164844 | I23: =SUM(I24:I28) -> 65251484 | ... BO23: =SUM(BO24:BO28) -> 162423673
A24: Personel Expenses | B24: 3512.444 | C24: 61230228 | D24: 4375132.1 | E24: 8545823.5 | F24: 12695883 | G24: 17940916 | H24: 22693124 | I24: 27385617 | J24: 32052794 | K24: 36832126 | L24: 41488924 | M24: 46583353 | N24: 51561798 | O24: 58317273 | P24: 60101722 | Q24: 4927766 | R24: 10908024 | S24: 16753451 | T24: 22282642 | U24: 27489019 | V24: 32399398 | W24: 37718851 | X24: 43193202 | Y24: 48443426 | Z24: 53956149 | AA24: 59079419 | AB24: 65717026 | AC24: 65625975 | AD24: 5145040.8 | AE24: 10785952 | AF24: 16028193 | AG24: 21439251 | AH24: 26734557 | AI24: 31978631 | AJ24: 85152177 | AK24: 48018619 | AL24: 53806654 | AM24: 59369103 | AN24: 66428622 | AO24: 70178925 | AP24: 5419129.7 | AQ24: 11455330 | AR24: 16517197 | AS24: 22152328 | AT24: 27559094 | AU24: 32966749 | AV24: 38785300 | AW24: 44339047 | AX24: 50243524 | AY24: 56125898 | AZ24: 62046408 | BA24: 69817306 | BB24: 72014081 | BC24: 6339087.8 | BD24: 13115863 | BE24: 19559940 | BF24: 26220730 | BG24: 32586099 | BH24: 38805992 | BI24: 45771193 | BJ24: 52076036 | BK24: 58337686 | BL24: 64923374 | BM24: 71383229 | BN24: 79842190 | BO24: 80431118
A25: Governance Expenses | B25: 401.873 | C25: 10909314 | D25: 188549 | E25: 819238 | F25: 2335517 | G25: 4691486 | H25: 5002840 | I25: 5434993 | J25: 6015668 | K25: 6850677 | L25: 8216819 | M25: 8566707 | N25: 10018234 | O25: 11802298 | P25: 12993803 | Q25: 327406 | R25: 3482103 | S25: 5539592 | T25: 7208522 | U25: 7666416 | V25: 8386134 | W25: 8709441 | X25: 9210162 | Y25: 10512360 | Z25: 10773193 | AA25: 12369039 | AB25: 14071054 | AC25: 15072601 | AD25: 560477 | AE25: 2766516 | AF25: 4450223 | AG25: 4723666 | AH25: 4843968 | AI25: 5022576 | AJ25: 12809966 | AK25: 7912258 | AL25: 9353421 | AM25: 11784105 | AN25: 13876754 | AO25: 14966229 | AP25: 383921 | AQ25: 3445387 | AR25: 6260252 | AS25: 6739644 | AT25: 8048754 | AU25: 8494910 | AV25: 8625914 | AW25: 9266569 | AX25: 10397866 | AY25: 11680417 | AZ25: 13494584 | BA25: 16037502 | BB25: 16847825 | BC25: 1805765 | BD25: 4708870 | BE25: 7797105 | BF25: 8545795 | BG25: 9800610 | BH25: 11743410 | BI25: 13583450 | BJ25: 14602354 | BK25: 16729763 | BL25: 17744963 | BM25: 19635506 | BN25: 22852007 | BO25: 24079712
A26: Marketing Expenses | B26: 919.3528 | C26: 3424962 | D26: 143800 | E26: 305276.06 | F26: 1316691.8 | G26: 1477770.8 | H26: 1575865.8 | I26: 1702690.9 | J26: 2039410.9 | K26: 2117223.9 | L26: 2727907 | M26: 3011172 | N26: 3190098 | O26: 3244998 | P26: 3244998 | Q26: 70800 | R26: 276815 | S26: 502915 | T26: 585355 | U26: 961520 | V26: 1527612 | W26: 1945250 | X26: 1984290 | Y26: 2171014 | Z26: 3110376 | AA26: 3186158 | AB26: 3409858 | AC26: 3409858 | AD26: 414729 | AE26: 584280.02 | AF26: 965641.02 | AG26: 982741.02 | AH26: 985841.02 | AI26: 1009041 | AJ26: 1847082 | AK26: 1102742 | AL26: 1522788 | AM26: 1623828 | AN26: 2492785 | AO26: 2492785 | AP26: 350230 | AQ26: 538235 | AR26: 723959 | AS26: 1106459 | AT26: 1259159 | AU26: 1407710.7 | AV26: 1560707.5 | AW26: 1667469.5 | AX26: 1802336 | AY26: 2042198 | AZ26: 2690324 | BA26: 3598604 | BB26: 3598604 | BC26: 600278 | BD26: 762613 | BE26: 1281501 | BF26: 1358301 | BG26: 2086221 | BH26: 2311073.8 | BI26: 2807121.8 | BJ26: 3149006.8 | BK26: 4065310.8 | BL26: 4761732.8 | BM26: 4899842.8 | BN26: 5195510.8 | BO26: 5195511
A27: Depreciation and Amortization | B27: 1276.981 | C27: 6405372 | D27: 516155 | E27: 1032310 | F27: 1548465 | G27: 2064620 | H27: 2580775 | I27: 3096930 | J27: 3096930 | K27: 4129240 | L27: 4645395 | M27: 5119085.2 | N27: 5918194.1 | O27: 6433979.1 | P27: 6433979 | Q27: 0 | R27: 614690.85 | S27: 614690.85 | T27: 614690.85 | U27: 614690.85 | V27: 3688144.9 | W27: 4302835.7 | X27: 4302835.7 | Y27: 4917526.6 | Z27: 7376290 | AA27: 7376290 | AB27: 6336788 | AC27: 6336788 | AD27: 0 | AE27: 509391.59 | AF27: 1018783.2 | AG27: 1528174.8 | AH27: 2037566.4 | AI27: 2546958 | AJ27: 7131482.3 | AK27: 4075132.7 | AL27: 5603307.5 | AM27: 5603307.5 | AN27: 5143186.9 | AO27: 5032531 | AP27: 398370.09 | AQ27: 532515.12 | AR27: 532515.12 | AS27: 1041906.7 | AT27: 1551298.3 | AU27: 2060689.9 | AV27: 2570081.5 | AW27: 3079473.1 | AX27: 3588864.7 | AY27: 4098256.2 | AZ27: 4607647.8 | BA27: 5565758 | BB27: 4632480 | BC27: 423564.83 | BD27: 847129.66 | BE27: 1211624.8 | BF27: 1428341.3 | BG27: 1674592.7 | BH27: 2098157.5 | BI27: 2876349.3 | BJ27: 3053662.8 | BK27: 3368886.8 | BL27: 3723513.8 | BM27: 4649345 | BN27: 4521880.7 | BO27: 4521881
A28: Administrative Expenses | B28: 4908.7291 | C28: 48843075 | D28: 3469259.1 | E28: 10106877 | F28: 14808307 | G28: 18689811 | H28: 22312239 | I28: 27631252 | J28: 31891154 | K28: 36145408 | L28: 40045056 | M28: 46215900 | N28: 52455140 | O28: 55805737 | P28: 52609783 | Q28: 4422660.3 | R28: 8732057.8 | S28: 13808772 | T28: 17136843 | U28: 21260948 | V28: 25745128 | W28: 30657229 | X28: 35191533 | Y28: 38593270 | Z28: 42865329 | AA28: 46353674 | AB28: 52488416 | AC28: 50271115 | AD28: 4195148.5 | AE28: 8323679.8 | AF28: 12379977 | AG28: 16603046 | AH28: 19518072 | AI28: 23023319 | AJ28: 61930100 | AK28: 35964883 | AL28: 44267362 | AM28: 46767823 | AN28: 51438869 | AO28: 46716597 | AP28: 2738265.6 | AQ28: 7613877 | AR28: 11858750 | AS28: 15880896 | AT28: 20100099 | AU28: 25458653 | AV28: 29752516 | AW28: 32230088 | AX28: 37570169 | AY28: 41005731 | AZ28: 45412244 | BA28: 51999241 | BB28: 47905808 | BC28: 4207187.7 | BD28: 7282435.8 | BE28: 12349934 | BF28: 16569702 | BG28: 20319312 | BH28: 23665544 | BI28: 30635321 | BJ28: 35083060 | BK28: 38596793 | BL28: 41379211 | BM28: 45492215 | BN28: 50035164 | BO28: 48195451
A29: Net Operating Income | B29: =B19-B20-B23 -> 3030.7829 | C29: =C19-C20-C23 -> 12685889 | D29: =D19-D20-D23 -> 9337095 | E29: =E19-E20-E23 -> 6504356.7 | F29: =F19-F20-F23 -> 7436870.6 | G29: =G19-G20-G23 -> 6071812 | H29: =H19-H20-H23 -> 3162400.7 | I29: =I19-I20-I23 -> 3459784 | ... BO29: =BO19-BO20-BO23 -> 29069525
A30: Net Non operating Income/Expense | B30: =(B31-B32) -> 0 | C30: =(C31-C32) -> 0 | D30: =(D31-D32) -> 0 | E30: =(E31-E32) -> 0 | F30: =(F31-F32) -> 0 | G30: =(G31-G32) -> 0 | H30: =(H31-H32) -> 0 | I30: =(I31-I32) -> 1204074 | ... BO30: =(BO31-BO32) -> 0
A31: Non Operating Income | I31: 1204074 | J31: 1204074 | K31: 1204074 | L31: 1204074 | M31: 1204074 | N31: 1204074 | O31: 1204074 | Q31: 0 | R31: 0 | S31: 0 | T31: 0 | U31: 0 | V31: 0 | W31: 0 | X31: 0 | Y31: 0 | Z31: 0 | AA31: 0 | AB31: 0 | AD31: 0 | AE31: 0 | AF31: 0 | AG31: 0 | AH31: 0 | AI31: 0 | AJ31: 0 | AK31: 0 | AL31: 0 | AM31: 0 | AN31: 44922.6 | AO31: 44923 | AP31: 0 | AQ31: 0 | AR31: 0 | AS31: 0 | AT31: 0 | AU31: 0 | AV31: 0 | AW31: 0 | AX31: 0 | AY31: 0 | AZ31: 0 | BA31: 0 | BC31: 0 | BD31: 0 | BE31: 0 | BF31: 10657 | BG31: 0 | BH31: 0 | BI31: 0 | BJ31: 0 | BK31: 0 | BL31: 0 | BM31: 0 | BN31: 0 | BO31: 0
A32: Non Operating Expense | D32: 0 | E32: 0 | F32: 0 | G32: 0 | K32: 0 | L32: 0 | M32: 0 | N32: 0 | O32: 0 | Q32: 0 | R32: 0 | S32: 0 | T32: 0 | U32: 0 | V32: 0 | W32: 0 | X32: 0 | Y32: 0 | Z32: 0 | AA32: 0 | AB32: 0 | AD32: 0 | AE32: 0 | AF32: 0 | AG32: 0 | AH32: 0 | AI32: 0 | AJ32: 0 | AK32: 0 | AL32: 0 | AM32: 0 | AN32: 0 | AO32: 0 | AP32: 0 | AQ32: 0 | AR32: 0 | AS32: 0 | AT32: 0 | AU32: 0 | AV32: 0 | AW32: 0 | AX32: 0 | AY32: 0 | AZ32: 0 | BA32: 0 | BC32: 0 | BD32: 0 | BE32: 0 | BF32: 0 | BG32: 0 | BH32: 0 | BI32: 0 | BJ32: 0 | BK32: 0 | BL32: 0 | BM32: 0 | BN32: 0 | BO32: 0
A33: Net Income(Before Tax & Donations) | B33: =B29+B30 -> 3030.7829 | C33: =C29+C30 -> 12685889 | D33: =D29+D30 -> 9337095 | E33: =E29+E30 -> 6504356.7 | F33: =F29+F30 -> 7436870.6 | G33: =G29+G30 -> 6071812 | H33: =H29+H30 -> 3162400.7 | I33: =I29+I30 -> 4663858 | ... BO33: =BO29+BO30 -> 29069525
A34: Taxes | B34: 20 | D34: 0 | E34: 0 | F34: 0 | G34: 0 | K34: 0 | L34: 0 | M34: 0 | N34: 0 | O34: 0 | Q34: 0 | R34: 0 | S34: 0 | T34: 0 | U34: 0 | V34: 0 | W34: 0 | X34: 0 | Y34: 0 | Z34: 0 | AA34: 0 | AB34: 0 | AD34: 0 | AE34: 0 | AF34: 0 | AG34: 0 | AH34: 0 | AI34: 0 | AJ34: 0 | AK34: 0 | AL34: 0 | AM34: 0 | AN34: 0 | AO34: 1515941 | AP34: 0 | AQ34: 0 | AR34: 0 | AS34: 0 | AT34: 0 | AU34: 0 | AV34: 0 | AW34: 0 | AX34: 0 | AY34: 0 | AZ34: 0 | BA34: 0 | BB34: 4194148 | BC34: 0 | BD34: 0 | BE34: 0 | BF34: 0 | BG34: 0 | BH34: 0 | BI34: 0 | BJ34: 0 | BK34: 0 | BL34: 0 | BM34: 0 | BN34: 5067374 | BO34: 5067374
A35: Net Income(After Tax Before Donations) | B35: =B33-B34 -> 3010.7829 | C35: =C33-C34 -> 12685889 | D35: =D33-D34 -> 9337095 | E35: =E33-E34 -> 6504356.7 | F35: =F33-F34 -> 7436870.6 | G35: =G33-G34 -> 6071812 | H35: =H33-H34 -> 3162400.7 | I35: =I33-I34 -> 4663858 | ... BO35: =BO33-BO34 -> 24002151
A36: Donations | K36: 0 | L36: 0 | M36: 0 | N36: 0 | O36: 0 | Q36: 0 | R36: 0 | S36: 0 | T36: 0 | U36: 0 | V36: 0 | W36: 0 | X36: 0 | Y36: 0 | Z36: 0 | AA36: 0 | AB36: 0 | AD36: 0 | AE36: 0 | AF36: 0 | AG36: 0 | AH36: 0 | AI36: 0 | AJ36: 0 | AK36: 0 | AL36: 0 | AM36: 0 | AN36: 0 | AO36: 0 | AP36: 0 | AQ36: 0 | AR36: 0 | AS36: 0 | AT36: 0 | AU36: 0 | AV36: 0 | AW36: 0 | AX36: 0 | AY36: 0 | AZ36: 0 | BA36: 0 | BC36: 0 | BD36: 0 | BE36: 0 | BF36: 0 | BG36: 0 | BH36: 0 | BI36: 0 | BJ36: 0 | BK36: 0 | BL36: 0 | BM36: 0 | BN36: 0 | BO36: 0
A37: Net Income/(After Tax & Donations) | B37: =B35-B36 -> 3010.7829 | C37: =C35-C36 -> 12685889 | D37: =D35-D36 -> 9337095 | E37: =E35-E36 -> 6504356.7 | F37: =F35-F36 -> 7436870.6 | G37: =G35-G36 -> 6071812 | H37: =H35-H36 -> 3162400.7 | I37: =I35-I36 -> 4663858 | ... BO37: =BO35-BO36 -> 24002151
A39: Total Expenses | B39: =B12+B23 -> 11568.465 | C39: =C12+C23 -> 167267134 | D39: =D12+D23 -> 9376317.8 | E39: =E12+E23 -> 22264696 | F39: =F12+F23 -> 34894553 | G39: =G12+G23 -> 48420287 | H39: =H12+H23 -> 62980261 | I39: =I12+I23 -> 76706844 | ... BO39: =BO12+BO23 -> 187760885
J41: =J39-I39 -> 13080567 | K41: =K39-J39 -> 13264388 | L41: =L39-K39 -> 13463764 | M41: =M39-L39 -> 15158445 | N41: =N39-M39 -> 16546505 | O41: =O39-N39 -> 13934200 | P41: =P39-O39 -> 8876624.9 | Q41: =Q39-P39 -> -1.6044174e+08 | ... Y41: =Y39-X39 -> 13007049

Sheet June Performance Report
A1: WANANCHI SACCO SOCIETY LIMITED CS/NO: 6531
A2: PERFORMANCE AND COMPLIANCE REPORT AS AT : 30TH JUNE , 2018
B3: Prudential Standard | C3: Audited | D3: Returns | F3: Validated | G3: Average for all Licensed Saccos
C4: 2017 | D4: 43160 | E4: 43252
A5: A. CAPITAL ADEQUACY
A6: Core Capital | B6: ≥10M | C6: =C33 -> 218843226 | D6: =D33 -> 1.7075142e+08 | E6: =E33 -> 1.7104689e+08 | F6: =F33 -> 1.7104689e+08 | G6: =G33 -> 6.9326568e+10
A7: Core Capital/Total Assets | B7: ≥10% | C7: =C33/C29 -> 0.19053876 | D7: =D33/D29 -> 0.15878723 | E7: =E33/E29 -> 0.14957668 | F7: =F33/F29 -> 0.14957668 | G7: =G33/G29 -> 0.15142619
A8: Institutional Capital/Total Assets | B8: ≥8% | C8: =C34/C29 -> 0.06806652 | D8: =D34/D29 -> 0.029810922 | E8: =E34/E29 -> 0.025477104 | F8: =F34/F29 -> 0.025477104 | G8: =G34/G29 -> 0.086793277
A9: B. ASSET QUALITY
A10: NPL (Substandard+Doubtful+Loss) | B10: <5% | C10: =C35/C32 -> 0.18390569 | D10: =D35/D32 -> 0.1787696 | E10: =E35/E32 -> 0.22772293 | F10: =F35/F32 -> 0.22772293 | G10: =G35/G32 -> 0.064216556
A11: Non-Earning Assets | B11: <10% | C11: =C36/C29 -> 0.09430328 | D11: =D36/D29 -> 0.11651827 | E11: =E36/E29 -> 0.094447216 | F11: =F36/F29 -> 0.094447216 | G11: =G36/G29 -> 0.21105592
A12: Equity investments/Deposits | B12: <5% | C12: =C38/C31 -> 0.23027257 | D12: =D38/D31 -> 0.062585917 | E12: =E38/E31 -> 0.061725836 | F12: =F38/F31 -> 0.061725836 | G12: =G38/G31 -> 0.041240427
A13: Equity investments/Core capital | B13: <40% | C13: =C38/C33 -> 0.89674697 | D13: =D38/D33 -> 0.28658847 | E13: =E38/E33 -> 0.28697036 | F13: =F38/F33 -> 0.28697036 | G13: =G38/G33 -> 0.19351903
A14: C. EARNINGS RATING
A15: Yield on Gross Loans | C15: =C41/C32 -> 0.19246721 | D15: =D41/D32 -> 0.056680352 | E15: =E41/E32 -> 0.096741622 | F15: =F41/F32 -> 0.096741622 | G15: =G41/G32 -> 0.060128916
A16: Total Expense/Total Income | C16: =C44/C40 -> 0.85041877 | D16: =D44/D40 -> 0.70809161 | E16: =E44/E40 -> 0.81536195 | F16: =F44/F40 -> 0.81536195 | G16: =G44/G40 -> 0.79898157
A17: Net Income/Average Assets | C17: =C42/C30 -> 0.010672534 | D17: =D42/D30 -> 0.006688143 | E17: =E42/E30 -> 0.0040695252 | F17: =F42/F30 -> 0.0040695252 | G17: =G42/G30 -> 0.014471496
A18: Operating Expenses/Total Income (OPEX) | C18: =C45/C40 -> 0.66507859 | D18: =D45/D40 -> 0.66365772 | E18: =E45/E40 -> 0.69359621 | F18: =F45/F40 -> 0.69359621 | G18: =G45/G40 -> 0.33727083
A19: D. LIQUIDITY
A20: Liquid Assets/Short-term Liabilities | B20: >15% | C20: =C46/C47 -> 0.51887129 | D20: =D46/D47 -> 0.33875077 | E20: =E46/E47 -> 0.47501917 | F20: =F46/F47 -> 0.47501917 | G20: =G46/G47 -> 0.53762833
A21: External Borrowing/Total Assets | B21: <25% | C21: =C48/C29 -> 0 | D21: =D48/D29 -> 0 | E21: =E48/E29 -> 0.043723882 | F21: =F48/F29 -> 0.043723882 | G21: =G48/G29 -> 0.048858222
A22: Liquid Assets/Total Assets | C22: =C46/C29 -> 0.2805087 | D22: =D46/D29 -> 0.16984218 | E22: =E46/E29 -> 0.22993072 | F22: =F46/F29 -> 0.22993072 | G22: =G46/G29 -> 0.10366677
A23: E. STRUCTURE/SENSITIVITY TO RISK
A24: Gross loans /Total Assets | B24: 70-80 | C24: =C32/C29 -> 0.724849 | D24: =D32/D29 -> 0.77258742 | E24: =E32/E29 -> 0.73595915 | F24: =F32/F29 -> 0.73595915 | G24: =G32/G29 -> 0.75746736
A25: Gross loans/Deposits | B25: >100% | C25: =C32/C31 -> 0.97686939 | D25: =D32/D31 -> 1.0625514 | E25: =E32/E31 -> 1.0583267 | F25: =F32/F31 -> 1.0583267 | G25: =G32/G31 -> 1.0660128
A26: Financial Investments/Total Assets | C26: =C39/C29 -> 0.18178177 | D26: =D39/D29 -> 0.045506589 | E26: =E39/E29 -> 0.042924075 | F26: =F39/F29 -> 0.042924075 | G26: =G39/G29 -> 0.043658487
A27: Dividends+Interest on Deposits/Total Income | C27: =C43/C40 -> 0.075077274 | D27: =D43/D40 -> 0.030162631 | E27: =E43/E40 -> 0.085254447 | F27: =F43/F40 -> 0.085254447 | G27: =G43/G40 -> 0.27724023
A28: F. KEY FINANCIAL STATISTICS | C28: 2015 | D28: 2016 | E28: 2017 | G28: AGGREGATE
A29: Total Assets | C29: =('Evolutive SFP'!C27) -> 1148549670 | D29: =('Evolutive SFP'!F27) -> 1.0753473e+09 | E29: =('Evolutive SFP'!I27) -> 1.1435398e+09 | F29: 1.1435398e+09 | G29: 4.5782417e+11
A30: Average Assets | C30: =([1]SFP!$S$32+'Evolutive SFP'!C27)/2 -> 1.1886483e+09 | D30: =('Evolutive SFP'!C27+'Evolutive SFP'!F27)/2 -> 1.1119485e+09 | E30: =('Evolutive SFP'!C27+'Evolutive SFP'!I27)/2 -> 1.1460447e+09 | F30: 1.1460447e+09 | G30: 4.5005065e+11
A31: Total Deposits | C31: =('Evolutive SFP'!C31) -> 852237862 | D31: =('Evolutive SFP'!F31) -> 7.8189137e+08 | E31: =('Evolutive SFP'!I31) -> 7.9521626e+08 | F31: 7.9521626e+08 | G31: 3.253121e+11
A32: Gross Loans | C32: =('Evolutive SFP'!C15) -> 832525078 | D32: =('Evolutive SFP'!F15) -> 8.307998e+08 | E32: =('Evolutive SFP'!I15) -> 8.4159859e+08 | F32: 8.4159859e+08 | G32: 3.4678687e+11
A33: Core Capital | C33: =('Evolutive SFP'!C39+'Evolutive SFP'!C40+'Evolutive SFP'!C41+'Evolutive SFP'!C42+'Evolutive SFP'!C43+'Evolutive SFP'!C44)-'Evolutive SFP'!C13 -> 218843226 | D33: =('Evolutive SFP'!F39+'Evolutive SFP'!F40+'Evolutive SFP'!F41+50%*'Evolutive SFP'!F42+'Evolutive SFP'!F43+'Evolutive SFP'!F44)-'Evolutive SFP'!F13 -> 1.7075142e+08 | E33: =('Evolutive SFP'!I39+'Evolutive SFP'!I40+'Evolutive SFP'!I41+50%*'Evolutive SFP'!I42+'Evolutive SFP'!I43+'Evolutive SFP'!I44)-'Evolutive SFP'!I13 -> 1.7104689e+08 | F33: 1.7104689e+08 | G33: 6.9326568e+10
A34: Institutional Capital | C34: =('Evolutive SFP'!C40+'Evolutive SFP'!C41+'Evolutive SFP'!C42+'Evolutive SFP'!C43+'Evolutive SFP'!C44)-'Evolutive SFP'!C13 -> 78177779 | D34: =('Evolutive SFP'!F40+'Evolutive SFP'!F41+'Evolutive SFP'!F42+'Evolutive SFP'!F43+'Evolutive SFP'!F44)-'Evolutive SFP'!F13 -> 32057095 | E34: =('Evolutive SFP'!I40+'Evolutive SFP'!I41+'Evolutive SFP'!I42+'Evolutive SFP'!I43+'Evolutive SFP'!I44)-'Evolutive SFP'!I13 -> 29134083 | F34: 29134083 | G34: 3.973606e+10
A35: Non-performing Loans | C35: =('[1]FORM 4'!$D$112+'[1]FORM 4'!$D$113+'[1]FORM 4'!$D$114) -> 1.531061e+08 | D35: =('FORM 4'!D5+'FORM 4'!D6+'FORM 4'!D7) -> 1.4852175e+08 | E35: =('FORM 4'!D14+'FORM 4'!D15+'FORM 4'!D16) -> 1.9165129e+08 | F35: 1.9165129e+08 | G35: 2.2269458e+10
A36: Non-Earning Assets | C36: =('Evolutive SFP'!C17+'Evolutive SFP'!C23+'Evolutive SFP'!C24+'Evolutive SFP'!C25+'Evolutive SFP'!C26+'Evolutive SFP'!C7) -> 108312001 | D36: =('Evolutive SFP'!F17+'Evolutive SFP'!F23+'Evolutive SFP'!F24+'Evolutive SFP'!F25+'Evolutive SFP'!F26+'Evolutive SFP'!F7) -> 1.2529761e+08 | E36: =('Evolutive SFP'!I17+'Evolutive SFP'!I23+'Evolutive SFP'!I24+'Evolutive SFP'!I25+'Evolutive SFP'!I26+'Evolutive SFP'!I7) -> 1.0800415e+08 | F36: 1.0800415e+08 | G36: 9.66265e+10
A37: Property and Equipment | C37: =('Evolutive SFP'!C21) -> 74636034 | D37: =('Evolutive SFP'!F21) -> 1.0283761e+08 | E37: =('Evolutive SFP'!I21) -> 94868992 | F37: 94868992 | G37: 1.5408701e+10
A38: Equity Investments | C38: ='Evolutive SFP'!C8-'Evolutive SFP'!C11 -> 196247000 | D38: =('Evolutive SFP'!F13) -> 48935388 | E38: =('Evolutive SFP'!I13) -> 49085388 | F38: 49085388 | G38: 1.341601e+10
A39: Financial Investments | C39: =('Evolutive SFP'!C8) -> 208785388 | D39: =('Evolutive SFP'!F8) -> 48935388 | E39: =('Evolutive SFP'!I8) -> 49085388 | F39: 49085388 | G39: 1.9987911e+10
A40: Total Income | C40: =('Evolutitve SCI'!C3+'Evolutitve SCI'!C31) -> 196687961 | D40: =('Evolutitve SCI'!F3+'Evolutitve SCI'!F31) -> 49279715 | E40: =('Evolutitve SCI'!I3+'Evolutitve SCI'!I31) -> 94077047 | F40: 94077047 | G40: 3.2399548e+10
A41: Net Financial Income | C41: =('Evolutitve SCI'!C19) -> 160233778 | D41: =('Evolutitve SCI'!F19) -> 47090025 | E41: =('Evolutitve SCI'!I19) -> 81417612 | F41: 81417612 | G41: 2.0851918e+10
A42: Net Income | C42: =('Evolutitve SCI'!C37) -> 12685889 | D42: =('Evolutitve SCI'!F37) -> 7436870.6 | E42: =('Evolutitve SCI'!I37) -> 4663858 | F42: 4663858 | G42: 6.5129063e+09
A43: Dividends+Interest on Deposits | C43: =('Evolutitve SCI'!C15+'Evolutitve SCI'!C13) -> 14766796 | D43: =('Evolutitve SCI'!F15+'Evolutitve SCI'!F13) -> 1486405.9 | E43: =('Evolutitve SCI'!I15+'Evolutitve SCI'!I13) -> 8020486.7 | F43: 8020486.7 | G43: 8.9824581e+09
A44: Total Expenses | C44: =('Evolutitve SCI'!C39) -> 167267134 | D44: =('Evolutitve SCI'!F39) -> 34894553 | E44: =('Evolutitve SCI'!I39) -> 76706844 | F44: 76706844 | G44: 2.5886642e+10
A45: Operating Expenses | C45: =('Evolutitve SCI'!C23) -> 130812951 | D45: =('Evolutitve SCI'!F23) -> 32704863 | E45: =('Evolutitve SCI'!I23) -> 65251484 | F45: 65251484 | G45: 1.0927422e+10
A46: Liquid Assets | C46: =('Evolutive SFP'!C4+'Evolutive SFP'!C9+'Evolutive SFP'!C10+'Evolutive SFP'!C11) -> 322178177 | D46: =('Evolutive SFP'!F4+'Evolutive SFP'!F9+'Evolutive SFP'!F10+'Evolutive SFP'!F11) -> 1.8263933e+08 | E46: =('Evolutive SFP'!I4+'Evolutive SFP'!I9+'Evolutive SFP'!I10+'Evolutive SFP'!I11) -> 2.6293493e+08 | F46: 2.6293493e+08 | G46: 4.7461153e+10
A47: Short-term (Deposits + liabilities) | C47: =('Evolutive SFP'!C28+'Evolutive SFP'!C29+'Evolutive SFP'!C32+'Evolutive SFP'!C33+'Evolutive SFP'!C34+'Evolutive SFP'!C35+'Evolutive SFP'!C36) -> 620921181 | D47: =('Evolutive SFP'!F28+'Evolutive SFP'!F29+'Evolutive SFP'!F32+'Evolutive SFP'!F33+'Evolutive SFP'!F34+'Evolutive SFP'!F35+'Evolutive SFP'!F36) -> 5.3915546e+08 | E47: =('Evolutive SFP'!I28+'Evolutive SFP'!I29+'Evolutive SFP'!I32+'Evolutive SFP'!I33+'Evolutive SFP'!I34+'Evolutive SFP'!I35+'Evolutive SFP'!I36) -> 5.5352488e+08 | F47: 5.5352488e+08 | G47: 8.8278743e+10
A48: External Borrowing | C48: =('Evolutive SFP'!C37) -> 0 | D48: =('Evolutive SFP'!F37) -> 0 | E48: =('Evolutive SFP'!I37) -> 50000000 | F48: 50000000 | G48: 2.2368475e+10
A49: G. AREAS OF IMPROVEMENT/REGULARTORY CONCERNS
A50: 1.Institutional Capital at 2.5% against minimum 8%
A51: 2.Non performing loan at 22.8% against 5% and below
A52: 3.Equity investment at 6.2%against 5% and below
A54: Prepared by: Masphine Abongo
A56: Checked by: Daniel Mwatu
A58: Approved by: Peter Owira
A60: DISCLAIMER: This report is prepared based on information submitted by the Sacco as at the stated date and may change upon verification by the Authority.

Sheet Sept perfomance report
A1: WANANCHI SACCO SOCIETY LIMITED CS/NO: 6531
A2: PERFORMANCE AND COMPLIANCE REPORT AS AT : 30TH SEPT , 2018
A3: =A1:J60 -> 0 | B3: Prudential Standard | C3: Audited | D3: Returns | I3: Validated | J3: Average for all Licensed Saccos
C4: 2017 | D4: 43160 | E4: 43252 | F4: 43282 | G4: 43313 | H4: 43344
A5: A. CAPITAL ADEQUACY
A6: Core Capital | B6: ≥10M | C6: =C33 -> 218843226 | D6: =D33 -> 1.7075142e+08 | E6: =E33 -> 1.7104689e+08 | F6: =F33 -> 1.716366e+08 | G6: =G33 -> 1.7495963e+08 | H6: =H33 -> 1.7562801e+08 | I6: =I33 -> 1.7104689e+08 | J6: =J33 -> 6.8610901e+10
A7: Core Capital/Total Assets | B7: ≥10% | C7: =C33/C29 -> 0.19053876 | D7: =D33/D29 -> 0.15878723 | E7: =E33/E29 -> 0.14957668 | F7: =F33/F29 -> 0.1515243 | G7: =G33/G29 -> 0.15582393 | H7: =H33/H29 -> 0.15808855 | I7: =I33/I29 -> 0.14957668 | J7: =J33/J29 -> 0.14576061
A8: Institutional Capital/Total Assets | B8: ≥8% | C8: =C34/C29 -> 0.06806652 | D8: =D34/D29 -> 0.029810922 | E8: =E34/E29 -> 0.025477104 | F8: =F34/F29 -> 0.025925823 | G8: =G34/G29 -> 0.031314868 | H8: =H34/H29 -> 0.030979227 | I8: =I34/I29 -> 0.025477104 | J8: =J34/J29 -> 0.080885761
A9: B. ASSET QUALITY
A10: NPL (Substandard+Doubtful+Loss) | B10: <5% | C10: =C35/C32 -> 0.18390569 | D10: =D35/D32 -> 0.1787696 | E10: =E35/E32 -> 0.22772293 | F10: =F35/F32 -> 2.0954219e-09 | G10: =G35/G32 -> 0.18220889 | H10: =H35/H32 -> 0.2237177 | I10: =I35/I32 -> 0.22772293 | J10: =J35/J32 -> 0.073088911
A11: Non-Earning Assets | B11: <10% | C11: =C36/C29 -> 0.09430328 | D11: =D36/D29 -> 0.11651827 | E11: =E36/E29 -> 0.094447216 | F11: =F36/F29 -> 0.097638114 | G11: =G36/G29 -> 0.089925771 | H11: =H36/H29 -> 0.088202014 | I11: =I36/I29 -> 0.094447216 | J11: =J36/J29 -> 0.12029808
A12: Equity investments/Deposits | B12: <5% | C12: =C38/C31 -> 0.23027257 | D12: =D38/D31 -> 0.062585917 | E12: =E38/E31 -> 0.061725836 | F12: =F38/F31 -> 0.06237469 | G12: =G38/G31 -> 0.064340137 | H12: =H38/H31 -> 0.065547385 | I12: =I38/I31 -> 0.061725836 | J12: =J38/J31 -> 0.041108343
A13: Equity investments/Core capital | B13: <40% | C13: =C38/C33 -> 0.89674697 | D13: =D38/D33 -> 0.28658847 | E13: =E38/E33 -> 0.28697036 | F13: =F38/F33 -> 0.2862757 | G13: =G38/G33 -> 0.28226733 | H13: =H38/H33 -> 0.28147781 | I13: =I38/I33 -> 0.28697036 | J13: =J38/J33 -> 0.19682259
A14: C. EARNINGS RATING
A15: Yield on Gross Loans | C15: =C41/C32 -> 0.19246721 | D15: =D41/D32 -> 0.056680352 | E15: =E41/E32 -> 0.096741622 | F15: =F41/F32 -> 0.10961457 | G15: =G41/G32 -> 0.13437488 | H15: =H41/H32 -> 0.14788885 | I15: =I41/I32 -> 0.096741622 | J15: =J41/J32 -> 0.087222558
A16: Total Expense/Total Income | C16: =C44/C40 -> 0.85041877 | D16: =D44/D40 -> 0.70809161 | E16: =E44/E40 -> 0.81536195 | F16: =F44/F40 -> 0.83569372 | G16: =G44/G40 -> 0.78906848 | H16: =H44/H40 -> 0.80196127 | I16: =I44/I40 -> 0.81536195 | J16: =J44/J40 -> 0.78307334
A17: Net Income/Average Assets | C17: =C42/C30 -> 0.010672534 | D17: =D42/D30 -> 0.006688143 | E17: =E42/E30 -> 0.0040695252 | F17: =F42/F30 -> 0.0044006406 | G17: =G42/G30 -> 0.0098998585 | H17: =H42/H30 -> 0.0094187274 | I17: =I42/I30 -> 0.0040695252 | J17: =J42/J30 -> 0.023999817
A18: Operating Expenses/Total Income (OPEX) | C18: =C45/C40 -> 0.66507859 | D18: =D45/D40 -> 0.66365772 | E18: =E45/E40 -> 0.69359621 | F18: =F45/F40 -> 0.69895343 | G18: =G45/G40 -> 0.6590745 | H18: =H45/H40 -> 0.66849239 | I18: =I45/I40 -> 0.69359621 | J18: =J45/J40 -> 0.70205116
A19: D. LIQUIDITY
A20: Liquid Assets/Short-term Liabilities | B20: >15% | C20: =C46/C47 -> 0.51887129 | D20: =D46/D47 -> 0.33875077 | E20: =E46/E47 -> 0.47501917 | F20: =F46/F47 -> 0.47339776 | G20: =G46/G47 -> 0.49250676 | H20: =H46/H47 -> 0.47705628 | I20: =I46/I47 -> 0.47501917 | J20: =J46/J47 -> 0.48580473
A21: External Borrowing/Total Assets | B21: <25% | C21: =C48/C29 -> 0 | D21: =D48/D29 -> 0 | E21: =E48/E29 -> 0.043723882 | F21: =F48/F29 -> 0.044141021 | G21: =G48/G29 -> 0.044531396 | H21: =H48/H29 -> 0.045006646 | I21: =I48/I29 -> 0.043723882 | J21: =J48/J29 -> 0.046924647
A22: Liquid Assets/Total Assets | C22: =C46/C29 -> 0.2805087 | D22: =D46/D29 -> 0.16984218 | E22: =E46/E29 -> 0.22993072 | F22: =F46/F29 -> 0.22593946 | G22: =G46/G29 -> 0.22958834 | H22: =H46/H29 -> 0.21983563 | I22: =I46/I29 -> 0.22993072 | J22: =J46/J29 -> 0.088828763
A23: E. STRUCTURE/SENSITIVITY TO RISK
A24: Gross loans /Total Assets | B24: 70-80 | C24: =C32/C29 -> 0.724849 | D24: =D32/D29 -> 0.77258742 | E24: =E32/E29 -> 0.73595915 | F24: =F32/F29 -> 0.73729101 | G24: =G32/G29 -> 0.74509989 | H24: =H32/H29 -> 0.75894859 | I24: =I32/I29 -> 0.73595915 | J24: =J32/J29 -> 0.76593828
A25: Gross loans/Deposits | B25: >100% | C25: =C32/C31 -> 0.97686939 | D25: =D32/D31 -> 1.0625514 | E25: =E32/E31 -> 1.0583267 | F25: =F32/F31 -> 1.0601824 | G25: =G32/G31 -> 1.0899378 | H25: =H32/H31 -> 1.1179519 | I25: =I32/I31 -> 1.0583267 | J25: =J32/J31 -> 1.0975103
A26: Financial Investments/Total Assets | C26: =C39/C29 -> 0.18178177 | D26: =D39/D29 -> 0.045506589 | E26: =E39/E29 -> 0.042924075 | F26: =F39/F29 -> 0.043377724 | G26: =G39/G29 -> 0.043984005 | H26: =H39/H29 -> 0.044498421 | I26: =I39/I29 -> 0.042924075 | J26: =J39/J29 -> 0.043992097
A27: Dividends+Interest on Deposits/Total Income | C27: =C43/C40 -> 0.075077274 | D27: =D43/D40 -> 0.030162631 | E27: =E43/E40 -> 0.085254447 | F27: =F43/F40 -> 0.090226642 | G27: =G43/G40 -> 0.086130509 | H27: =H43/H40 -> 0.087702199 | I27: =I43/I40 -> 0.085254447 | J27: =J43/J40 -> 0.28301758
A28: F. KEY FINANCIAL STATISTICS | C28: 2015 | D28: 2016 | E28: 2017 | J28: AGGREGATE
A29: Total Assets | C29: =('Evolutive SFP'!C27) -> 1148549670 | D29: =('Evolutive SFP'!F27) -> 1.0753473e+09 | E29: =('Evolutive SFP'!I27) -> 1.1435398e+09 | F29: =('Evolutive SFP'!J27) -> 1.1327332e+09 | G29: =('Evolutive SFP'!K27) -> 1.1228033e+09 | H29: =('Evolutive SFP'!L27) -> 1.110947e+09 | I29: 1.1435398e+09 | J29: 4.7070948e+11
A30: Average Assets | C30: =([1]SFP!$S$32+'Evolutive SFP'!C27)/2 -> 1.1886483e+09 | D30: =('Evolutive SFP'!C27+'Evolutive SFP'!F27)/2 -> 1.1119485e+09 | E30: =('Evolutive SFP'!C27+'Evolutive SFP'!I27)/2 -> 1.1460447e+09 | F30: =('Evolutive SFP'!D27+'Evolutive SFP'!J27)/2 -> 1.1241127e+09 | G30: =('Evolutive SFP'!E27+'Evolutive SFP'!K27)/2 -> 1.1101385e+09 | H30: =('Evolutive SFP'!F27+'Evolutive SFP'!L27)/2 -> 1.0931472e+09 | I30: 1.1460447e+09 | J30: 4.4555583e+11
A31: Total Deposits | C31: =('Evolutive SFP'!C31) -> 852237862 | D31: =('Evolutive SFP'!F31) -> 7.8189137e+08 | E31: =('Evolutive SFP'!I31) -> 7.9521626e+08 | F31: =('Evolutive SFP'!J31) -> 7.8774562e+08 | G31: =('Evolutive SFP'!K31) -> 7.6756735e+08 | H31: =('Evolutive SFP'!L31) -> 7.5419314e+08 | I31: 7.9521626e+08 | J31: 3.2850206e+11
A32: Gross Loans | C32: =('Evolutive SFP'!C15) -> 832525078 | D32: =('Evolutive SFP'!F15) -> 8.307998e+08 | E32: =('Evolutive SFP'!I15) -> 8.4159859e+08 | F32: =('Evolutive SFP'!J15) -> 8.35154e+08 | G32: =('Evolutive SFP'!K15) -> 8.3660065e+08 | H32: =('Evolutive SFP'!L15) -> 8.4315168e+08 | I32: 8.4159859e+08 | J32: 3.6053441e+11
A33: Core Capital | C33: =('Evolutive SFP'!C39+'Evolutive SFP'!C40+'Evolutive SFP'!C41+'Evolutive SFP'!C42+'Evolutive SFP'!C43+'Evolutive SFP'!C44)-'Evolutive SFP'!C13 -> 218843226 | D33: =('Evolutive SFP'!F39+'Evolutive SFP'!F40+'Evolutive SFP'!F41+50%*'Evolutive SFP'!F42+'Evolutive SFP'!F43+'Evolutive SFP'!F44)-'Evolutive SFP'!F13 -> 1.7075142e+08 | E33: =('Evolutive SFP'!I39+'Evolutive SFP'!I40+'Evolutive SFP'!I41+50%*'Evolutive SFP'!I42+'Evolutive SFP'!I43+'Evolutive SFP'!I44)-'Evolutive SFP'!I13 -> 1.7104689e+08 | F33: =('Evolutive SFP'!J39+'Evolutive SFP'!J40+'Evolutive SFP'!J41+50%*'Evolutive SFP'!J42+'Evolutive SFP'!J43+'Evolutive SFP'!J44)-'Evolutive SFP'!J13 -> 1.716366e+08 | G33: =('Evolutive SFP'!K39+'Evolutive SFP'!K40+'Evolutive SFP'!K41+50%*'Evolutive SFP'!K42+'Evolutive SFP'!K43+'Evolutive SFP'!K44)-'Evolutive SFP'!K13 -> 1.7495963e+08 | H33: =('Evolutive SFP'!L39+'Evolutive SFP'!L40+'Evolutive SFP'!L41+50%*'Evolutive SFP'!L42+'Evolutive SFP'!L43+'Evolutive SFP'!L44)-'Evolutive SFP'!L13 -> 1.7562801e+08 | I33: 1.7104689e+08 | J33: 6.8610901e+10
A34: Institutional Capital | C34: =('Evolutive SFP'!C40+'Evolutive SFP'!C41+'Evolutive SFP'!C42+'Evolutive SFP'!C43+'Evolutive SFP'!C44)-'Evolutive SFP'!C13 -> 78177779 | D34: =('Evolutive SFP'!F40+'Evolutive SFP'!F41+'Evolutive SFP'!F42+'Evolutive SFP'!F43+'Evolutive SFP'!F44)-'Evolutive SFP'!F13 -> 32057095 | E34: =('Evolutive SFP'!I40+'Evolutive SFP'!I41+'Evolutive SFP'!I42+'Evolutive SFP'!I43+'Evolutive SFP'!I44)-'Evolutive SFP'!I13 -> 29134083 | F34: =('Evolutive SFP'!J40+'Evolutive SFP'!J41+'Evolutive SFP'!J42+'Evolutive SFP'!J43+'Evolutive SFP'!J44)-'Evolutive SFP'!J13 -> 29367041 | G34: =('Evolutive SFP'!K40+'Evolutive SFP'!K41+'Evolutive SFP'!K42+'Evolutive SFP'!K43+'Evolutive SFP'!K44)-'Evolutive SFP'!K13 -> 35160439 | H34: =('Evolutive SFP'!L40+'Evolutive SFP'!L41+'Evolutive SFP'!L42+'Evolutive SFP'!L43+'Evolutive SFP'!L44)-'Evolutive SFP'!L13 -> 34416280 | I34: 29134083 | J34: 3.8073694e+10
A35: Non-performing Loans | C35: =('[1]FORM 4'!$D$112+'[1]FORM 4'!$D$113+'[1]FORM 4'!$D$114) -> 1.531061e+08 | D35: =('FORM 4'!D5+'FORM 4'!D6+'FORM 4'!D7) -> 1.4852175e+08 | E35: =('FORM 4'!D14+'FORM 4'!D15+'FORM 4'!D16) -> 1.9165129e+08 | F35: =('FORM 4'!E14+'FORM 4'!E15+'FORM 4'!E16) -> 1.75 | G35: =('FORM 4'!F14+'FORM 4'!F15+'FORM 4'!F16) -> 1.5243608e+08 | H35: ='FORM 4'!D23+'FORM 4'!D24+'FORM 4'!D25 -> 1.8862795e+08 | I35: 1.9165129e+08 | J35: 2.6351067e+10
