Workbook

Sheet Evolutive SFP
R1: ='Evolutitve SCI'!R5/'Evolutive SFP'!R14 -> 0.13803271 | S1: ='Evolutitve SCI'!S5/'Evolutive SFP'!S14 -> 0.02154924 | T1: ='Evolutitve SCI'!T5/'Evolutive SFP'!T14 -> 0.042696775 | U1: ='Evolutitve SCI'!U5/'Evolutive SFP'!U14 -> 0.046308651 | V1: ='Evolutitve SCI'!V5/'Evolutive SFP'!V14 -> 0.055089885 | W1: ='Evolutitve SCI'!W5/'Evolutive SFP'!W14 -> 0.050970278 | X1: ='Evolutitve SCI'!X5/'Evolutive SFP'!X14 -> 0.050939453 | Y1: ='Evolutitve SCI'!Y5/'Evolutive SFP'!Y14 -> 0.051560372 | Z1: -1115511.4
R2: =R5+R11 -> 18492812 | S2: =S5+S11 -> 10661536 | T2: =T5+T11 -> 12165835 | U2: =U5+U11 -> 12165835 | V2: =V5+V11 -> 8267864.4 | W2: =W5+W11 -> 8301101.9 | X2: =X5+X11 -> 5053192.3
B3: 2013 Audited | C3: Audited 2014 | D3: Audited 2015 | E3: Audited 2016 | F3: 42736 | G3: 42767 | H3: 42795 | I3: 42826 | J3: 42856 | K3: 42887 | L3: 42917 | M3: 42948 | N3: 42979 | O3: 43009 | P3: 43040 | Q3: 43070 | R3: Audited 2017 | S3: 43101 | T3: 43132 | U3: 43160 | V3: 43191 | W3: 43221 | X3: 43252 | Y3: 43282 | Z3: 43313 | AA3: 43344 | AB3: 43374 | AC3: 43405 | AD3: 43435 | AE3: Audited 2018 | AF3: 43466 | AG3: 43497 | AH3: 43525 | AI3: 43556 | AJ3: 43586 | AK3: 43617 | AL3: 43647 | AM3: 43678 | AN3: 43709 | AO3: 43739 | AP3: 43770 | AQ3: 43800 | AR3: Audited 2019 | AS3: 43831 | AT3: 43862 | AU3: 43891 | AV3: 43922 | AW3: 43952 | AX3: 43983 | AY3: 44013 | AZ3: 44044 | BA3: 44075 | BB3: 44105 | BC3: 44136 | BD3: 44166 | BE3: Audited 2020 | BF3: 44197 | BG3: 44228 | BH3: 44256 | BI3: 44287 | BJ3: 44317 | BK3: 44348 | BL3: 44378 | BM3: 44409 | BN3: 44440 | BO3: 44470 | BP3: 44501 | BQ3: 44531 | BR3: Audited 2021 | BS3: 44562 | BT3: 44593 | BU3: 44621 | BV3: 44652 | BW3: 44682 | BX3: 44713 | BY3: 44743 | BZ3: 44774 | CA3: 44805 | CB3: 44835 | CC3: 44866 | CD3: 44896 | CE3: Audited 2022 | CF3: Variances | CG3: Audited 2022 | CH3: 44927 | CI3: 44958 | CJ3: 44986 | CK3: 45017 | CL3: 45047 | CM3: 45078 | CN3: 45108
A4: Cash & cash Equivalent | B4: =SUM(B5:B6) -> 128444792 | C4: =SUM(C5:C6) -> 87766162 | D4: =SUM(D5:D6) -> 67219689 | E4: =SUM(E5:E6) -> 50284396 | F4: =SUM(F5:F6) -> 31944447 | G4: =SUM(G5:G6) -> 52742299 | H4: =SUM(H5:H6) -> 29959633 | I4: =SUM(I5:I6) -> 22009143 | ... CE4: =SUM(CE5:CE6) -> 18898344 | CF4: =CE4-CD4 -> -2402213 | CG4: =SUM(CG5:CG6) -> 18898344 | CH4: =SUM(CH5:CH6) -> 8787585.8 | CI4: =SUM(CI5:CI6) -> 4671734.2 | CJ4: =SUM(CJ5:CJ6) -> 5650814.7 | CK4: =SUM(CK5:CK6) -> 7733766.8 | CL4: =SUM(CL5:CL6) -> 5242336.9 | CM4: =SUM(CM5:CM6) -> 3685964.3 | CN4: =SUM(CN5:CN6) -> 4142581.5
A5: Cash In Hand | B5: 7138523 | C5: 11411572 | D5: 9130921 | E5: 5767269 | F5: 9147853 | G5: 8825525 | H5: 4413320 | I5: 6043135 | J5: 2550959 | K5: 1538242 | L5: 0 | M5: 0 | N5: 0 | O5: 0 | P5: 0 | Q5: 0 | R5: =589239+136650 -> 725889 | S5: 2839709 | T5: 4344008 | U5: 4344008 | V5: 446037 | W5: 423156 | X5: 1442019 | Y5: 1338199 | Z5: 4264850 | AA5: 3440169 | AB5: 4018646.5 | AC5: 15930450 | AD5: 6128522 | AE5: =31216703-AE6 -> 4894528 | AF5: 1374745.9 | AG5: 5255359.3 | AH5: 2259985.3 | AI5: 1871768.8 | AJ5: 8801131.8 | AK5: 3048258.8 | AL5: 2854110.8 | AM5: 2745621.8 | AN5: 2198232 | AS5: 1067632 | AT5: 52613 | AU5: 477763 | AV5: 475930.5 | AW5: 1235351.4 | AX5: 2923620 | AZ5: 1287257 | BA5: 1159857 | BB5: 2150360.4 | BC5: 1539417 | BD5: 16024918 | BE5: =15938710+26868+2750 -> 15968328 | BF5: 5564428.5 | BG5: 7884585.5 | BH5: 4412600.2 | BI5: 605236.75 | BJ5: 13379871 | BK5: 2451144.2 | BL5: 652865.05 | BM5: 2306736 | BN5: 3637257.4 | BO5: 4042833.8 | BP5: 3656920.9 | BQ5: 3062432.9 | BR5: =2742519+26868 -> 2769387 | BS5: 2610996.9 | BT5: 2350759.5 | BU5: 11381600 | BV5: 1932881.2 | BW5: 10354848 | BX5: 1331190.5 | BY5: 10335366 | BZ5: 2115160.4 | CA5: 3810781.8 | CB5: 7907868.8 | CC5: 2495612.1 | CD5: 1494432.6 | CE5: 744133 | CF5: =CE5-CD5 -> -750299.64 | CG5: 744133 | CH5: 1419181 | CI5: 3229669.6 | CJ5: 2380956.6 | CK5: 2176931.6 | CL5: 638254.6 | CM5: 1548752.6 | CN5: 1552888.6
A6: Cash at Bank | B6: 121306269 | C6: =81650213-5295623 -> 76354590 | D6: =63855087-5766319 -> 58088768 | E6: 44517127 | F6: 22796594 | G6: 43916774 | H6: 25546313 | I6: 15966008 | J6: 9971510 | K6: 3222102 | L6: 0 | M6: 0 | N6: 0 | O6: 0 | P6: 0 | Q6: 0 | R6: 31885175 | S6: 17133362 | T6: 9722175.1 | U6: 9722175.1 | V6: 2556306.3 | W6: 1792082.5 | X6: -418333.7 | Y6: -2453710.4 | Z6: 16273042 | AA6: 18050237 | AB6: 14658377 | AC6: 17529223 | AD6: -9634566.3 | AE6: 26322175 | AF6: -4462315.9 | AG6: 3883904.8 | AH6: 6027077.1 | AI6: -17411200 | AJ6: -17193122 | AK6: -14219783 | AL6: 10442462 | AM6: 8882118 | AN6: 10806090 | AS6: 6100792.8 | AT6: 5674541.6 | AU6: 24303562 | AV6: 20240496 | AW6: 20104363 | AX6: 21140554 | AZ6: 17556876 | BA6: 20597366 | BB6: 25231000 | BC6: 25062799 | BD6: 20625964 | BE6: =20690085 -> 20690085 | BF6: 14977517 | BG6: 17739254 | BH6: 17951706 | BI6: 15128451 | BJ6: 10625185 | BK6: 17696710 | BL6: 10413697 | BM6: 8975081.8 | BN6: 8029532.1 | BO6: 8372558.2 | BP6: 25652344 | BQ6: 16322664 | BR6: 24858953 | BS6: 15163240 | BT6: 19944641 | BU6: 11537229 | BV6: 4477692.1 | BW6: 10636232 | BX6: 11243092 | BY6: 14694832 | BZ6: 9844316.2 | CA6: 13508398 | CB6: 15030807 | CC6: 28946224 | CD6: 19806124 | CE6: 18154211 | CF6: =CE6-CD6 -> -1651913.4 | CG6: 18154211 | CH6: 7368404.8 | CI6: 1442064.6 | CJ6: 3269858.1 | CK6: 5556835.2 | CL6: 4604082.3 | CM6: 2137211.7 | CN6: 2589692.8
A7: Prepayment and Sundry | B7: 52413257 | C7: 41229631 | D7: 17661661 | E7: 24583094 | F7: 31308205 | G7: 23008112 | H7: 25592164 | I7: 25985706 | J7: 27688333 | K7: 26515797 | L7: 0 | M7: 0 | N7: 0 | O7: 0 | P7: 0 | Q7: 0 | R7: 22121089 | S7: 25508717 | T7: 19537047 | U7: 24008788 | V7: 34137255 | W7: 21858216 | X7: 43289021 | Y7: 0 | Z7: 0 | AA7: 0 | AB7: 0 | AC7: 0 | AD7: 0 | AE7: 26596843 | BE7: 6624843 | BF7: 0 | BG7: 0 | BH7: 0 | BI7: 0 | BJ7: 0 | BK7: 0 | BL7: 0 | BM7: 0 | BN7: 0 | BO7: 0 | BP7: 0 | BQ7: 0 | BR7: =1475908+115235871 -> 116711779 | BS7: 0 | BT7: 9478169 | BU7: 9555209.9 | BV7: 9299637 | BW7: 0 | BX7: 0 | BY7: 0 | BZ7: 0 | CA7: 0 | CB7: 0 | CC7: 0 | CD7: 0 | CE7: 10075490 | CF7: =CE7-CD7 -> 10075490 | CG7: 10075490 | CH7: 0 | CI7: 0 | CJ7: 0 | CK7: 0 | CL7: 0 | CM7: 0 | CN7: 0
A8: Financial Investment | B8: =SUM(B9:B12) -> 23235649 | C8: =SUM(C9:C12) -> 23582539 | D8: =SUM(D9:D12) -> 24253235 | E8: =SUM(E9:E12) -> 23630498 | F8: =SUM(F9:F12) -> 19804399 | G8: =SUM(G9:G12) -> 19804399 | H8: =SUM(H9:H12) -> 27179981 | I8: =SUM(I9:I12) -> 27179981 | ... CE8: =SUM(CE9:CE12) -> 14356941 | CF8: =CE8-CD8 -> -0.3 | CG8: =SUM(CG9:CG12) -> 14356941 | CH8: =SUM(CH9:CH12) -> 22744634 | CI8: =SUM(CI9:CI12) -> 22744634 | CJ8: =SUM(CJ9:CJ12) -> 22744634 | CK8: =SUM(CK9:CK12) -> 22744634 | CL8: =SUM(CL9:CL12) -> 22744634 | CM8: =SUM(CM9:CM12) -> 22764634 | CN8: =SUM(CN9:CN12) -> 22764634
A9: Government Security | C9: 0 | F9: 0 | G9: 0 | H9: 0 | I9: 0 | J9: 0 | K9: 0 | L9: 0 | M9: 0 | N9: 0 | O9: 0 | P9: 0 | Q9: 0 | X9: 0 | Y9: 0 | Z9: 0 | AA9: 0 | AB9: 0 | AC9: 0 | AD9: 0 | AE9: 0 | AF9: 0 | AG9: 0 | AH9: 0 | AI9: 0 | AJ9: 0 | AK9: 0 | AL9: 0 | AM9: 0 | AN9: 0 | AS9: 0 | AT9: 0 | AU9: 0 | AV9: 0 | AW9: 0 | AX9: 0 | AZ9: 0 | BA9: 0 | BB9: 0 | BC9: 0 | BD9: 0 | BF9: 0 | BG9: 0 | BH9: 0 | BI9: 0 | BJ9: 0 | BK9: 0 | BL9: 0 | BM9: 0 | BN9: 0 | BO9: 0 | BP9: 0 | BQ9: 0 | BS9: 0 | BT9: 0 | BU9: 0 | BV9: 0 | BW9: 0 | BX9: 0 | BY9: 0 | BZ9: 0 | CA9: 0 | CB9: 0 | CC9: 0 | CD9: 0 | CF9: =CE9-CD9 -> 0 | CH9: 0 | CI9: 0 | CJ9: 0 | CK9: 0 | CL9: 0 | CM9: 0 | CN9: 0
A10: Other Securities | C10: 0 | F10: 1317483.1 | G10: 1317483.1 | H10: 1317483.1 | I10: 1317483.1 | J10: 1317483.1 | K10: 1317483.1 | L10: 0 | M10: 0 | N10: 0 | O10: 0 | P10: 0 | Q10: 0 | X10: 0 | Y10: 24202.71 | Z10: 0 | AA10: 0 | AB10: 0 | AC10: 0 | AD10: 0 | AE10: 0 | AF10: 0 | AG10: 0 | AH10: 0 | AI10: 0 | AJ10: 0 | AK10: 0 | AL10: 0 | AM10: 0 | AN10: 0 | AS10: 0 | AT10: 0 | AU10: 0 | AV10: 0 | AW10: 0 | AX10: 0 | AZ10: 0 | BA10: 0 | BB10: 0 | BC10: 0 | BD10: 0 | BF10: 0 | BG10: 0 | BH10: 0 | BI10: 0 | BJ10: 0 | BK10: 0 | BL10: 0 | BM10: 0 | BN10: 0 | BO10: 0 | BP10: 0 | BQ10: 0 | BS10: 0 | BT10: 0 | BU10: 0 | BV10: 0 | BW10: 0 | BX10: 0 | BY10: 0 | BZ10: 0 | CA10: 0 | CB10: 0 | CC10: 0 | CD10: 0 | CF10: =CE10-CD10 -> 0 | CH10: 0 | CI10: 0 | CJ10: 0 | CK10: 0 | CL10: 0 | CM10: 0 | CN10: 0
A11: Balances with Other Saccos | B11: 5148733 | C11: 5295623 | D11: 5766319 | E11: 5143582 | F11: 0 | G11: 0 | H11: 7375581.5 | I11: 7375581.5 | J11: 7375581.5 | K11: 7375582 | L11: 0 | M11: 0 | N11: 0 | O11: 0 | P11: 0 | Q11: 0 | R11: =14155750+3611173 -> 17766923 | S11: 7821827.4 | T11: 7821827.4 | U11: 7821827.4 | V11: 7821827.4 | W11: 7877945.9 | X11: 3611173.3 | Y11: 3611173.3 | Z11: 0 | AA11: 0 | AB11: 0 | AC11: 0 | AD11: 0 | AE11: 0 | AF11: 7758945.9 | AG11: 7877945.9 | AH11: 0 | AI11: 0 | AJ11: 0 | AK11: 0 | AL11: 0 | AM11: 0 | AN11: 0 | AS11: 0 | AT11: 0 | AU11: 0 | AV11: 0 | AW11: 0 | AX11: 0 | AZ11: 0 | BA11: 0 | BB11: 0 | BC11: 0 | BD11: 0 | BF11: 0 | BG11: 0 | BH11: 0 | BI11: 0 | BJ11: 0 | BK11: 0 | BL11: 0 | BM11: 0 | BN11: 0 | BO11: 0 | BP11: 0 | BQ11: 0 | BS11: 0 | BT11: 0 | BU11: 0 | BV11: 0 | BW11: 0 | BX11: 0 | BY11: 0 | BZ11: 0 | CA11: 0 | CB11: 0 | CC11: 0 | CD11: 0 | CE11: 14356941 | CF11: =CE11-CD11 -> 14356941 | CG11: 14356941 | CH11: 0 | CI11: 0 | CJ11: 0 | CK11: 0 | CL11: 0 | CM11: 0 | CN11: 0
A12: Investment In Companies | B12: 18086916 | C12: =18236916+50000 -> 18286916 | D12: 18486916 | E12: 18486916 | F12: 18486916 | G12: 18486916 | H12: 18486916 | I12: 18486916 | J12: 18486916 | K12: 18486916 | L12: 0 | M12: 0 | N12: 0 | O12: 0 | P12: 0 | Q12: 0 | R12: =312100+37000+10000+492874 -> 851974 | S12: 18618897 | T12: 18618897 | U12: 18618897 | V12: 18618897 | W12: 18618897 | X12: 15007724 | Y12: 15007724 | Z12: 18618897 | AA12: 18618897 | AB12: 18618897 | AC12: 18618897 | AD12: 18618897 | AE12: 18618897 | AF12: 18644139 | AG12: 18618897 | AH12: 18618897 | AI12: 18618897 | AJ12: 18618897 | AK12: 18618897 | AL12: 18618897 | AM12: 18618897 | AN12: 18792655 | AS12: 18792655 | AT12: 18792655 | AU12: 14306941 | AV12: 14306941 | AW12: 14306941 | AX12: 14306941 | AZ12: 14306941 | BA12: 14306941 | BB12: 14306941 | BC12: 14306941 | BD12: 14306941 | BE12: 14306941 | BF12: 22517512 | BG12: 22517512 | BH12: 22517512 | BI12: 22517512 | BJ12: 22517512 | BK12: 22553300 | BL12: 22553300 | BM12: 22553300 | BN12: 22553300 | BO12: 22553300 | BP12: 22553300 | BQ12: 22553300 | BR12: 14306941 | BS12: 22553300 | BT12: 22553300 | BU12: 22553300 | BV12: 22553300 | BW12: 14356941 | BX12: 14356941 | BY12: 14356941 | BZ12: 14356941 | CA12: 14356941 | CB12: 14356941 | CC12: 14456941 | CD12: 14356941 | CF12: =CE12-CD12 -> -14356941 | CH12: 22744634 | CI12: 22744634 | CJ12: 22744634 | CK12: 22744634 | CL12: 22744634 | CM12: 22764634 | CN12: 22764634
A13: Net Loan Portfolio | B13: =B14-B15 -> 100772491 | C13: =C14-C15 -> 108738343 | D13: =D14-D15 -> 153940147 | E13: =E14-E15 -> 163589556 | F13: =F14-F15 -> 1.7133933e+08 | G13: =G14-G15 -> 1.7270349e+08 | H13: =H14-H15 -> 1.7451462e+08 | I13: =I14-I15 -> 1.6695465e+08 | ... CE13: =CE14-CE15 -> 43501127 | CF13: =CE13-CD13 -> 474179.98 | CG13: =CG14-CG15 -> 43501127 | CH13: =CH14-CH15 -> 1.1162795e+08 | CI13: =CI14-CI15 -> 48440087 | CJ13: =CJ14-CJ15 -> 50457085 | CK13: =CK14-CK15 -> 48821138 | CL13: =CL14-CL15 -> 47955121 | CM13: =CM14-CM15 -> 42380986 | CN13: =CN14-CN15 -> 55631257
A14: Gross Loan Portfolio | B14: 103051094 | C14: =103051094+225628493-216786901 -> 111892686 | D14: =153940147+3422873 -> 157363020 | E14: 167629119 | F14: 1.7958764e+08 | G14: 1.766828e+08 | H14: 1.7835008e+08 | I14: 170790111 | J14: 171339210 | K14: 1.718635e+08 | L14: 0 | M14: 0 | N14: 0 | O14: 0 | P14: 0 | Q14: 0 | R14: 1.3199861e+08 | S14: 1.5542763e+08 | T14: 1.6099855e+08 | U14: 1.6099855e+08 | V14: 1.4029934e+08 | W14: 1.5794637e+08 | X14: 1.6052017e+08 | Y14: 1.6053595e+08 | Z14: 1.5200309e+08 | AA14: 1.4614024e+08 | AB14: 1.3571907e+08 | AC14: 1.2630329e+08 | AD14: 1.1733634e+08 | AE14: 136448447 | AF14: 1.2861911e+08 | AG14: 1.3025927e+08 | AH14: 1.2193427e+08 | AI14: 1.2046881e+08 | AJ14: 1.1987045e+08 | AK14: 1.2090525e+08 | AL14: 1.2040948e+08 | AM14: 1.2249544e+08 | AN14: 1.2126987e+08 | AS14: 1.1984667e+08 | AT14: 9219483.9 | AU14: 12582696 | AV14: 12438189 | AW14: 11679979 | AX14: 12356350 | AZ14: 13642435 | BA14: 14076573 | BB14: 1.1637729e+08 | BC14: 1.163982e+08 | BD14: 1.0955832e+08 | BE14: =118974404+23565213-43872986 -> 98666631 | BF14: 1.0443983e+08 | BG14: 1.0291865e+08 | BH14: 1.0316208e+08 | BI14: 1.0513177e+08 | BJ14: 1.0460217e+08 | BK14: 1.0131827e+08 | BL14: 1.0828656e+08 | BM14: 1.0761066e+08 | BN14: 1.073874e+08 | BO14: 1.0770093e+08 | BP14: 1.0683059e+08 | BQ14: 1.0145116e+08 | BR14: 99799936 | BS14: 1.0184615e+08 | BT14: 1.0154812e+08 | BU14: 1.0697351e+08 | BV14: 1.1530025e+08 | BW14: 1.1462132e+08 | BX14: 1.1423782e+08 | BY14: 1.100773e+08 | BZ14: 1.125599e+08 | CA14: 1.1269283e+08 | CB14: 1.0625226e+08 | CC14: 1.0687569e+08 | CD14: 1.1143462e+08 | CE14: 111434614 | CF14: =CE14-CD14 -> -1.58 | CG14: 111434614 | CH14: 1.1162795e+08 | CI14: 1.127038e+08 | CJ14: 1.0881204e+08 | CK14: 1.0593719e+08 | CL14: 1.0725968e+08 | CM14: 1.0808258e+08 | CN14: 1.237537e+08
A15: Allowance For Loan Loss | B15: 2278603 | C15: 3154343 | D15: 3422873 | E15: 4039563 | F15: 8248306 | G15: 3979310.3 | H15: 3835462.4 | I15: 3835462.4 | J15: 3541834 | K15: 3607139.5 | L15: 0 | M15: 0 | N15: 0 | O15: 0 | P15: 0 | Q15: 0 | R15: 8346849 | S15: 9150264 | T15: 9759302 | U15: 13960467 | V15: 18801908 | W15: 40138586 | X15: 7576654 | Y15: 7576654 | Z15: 6945202 | AA15: 7576654 | AB15: 7576654 | AC15: 7576654 | AD15: 7576654 | AE15: 19152690 | AF15: 7576654 | AG15: 3422873 | AH15: 3422873 | AI15: 6945202 | AJ15: 6945202 | AK15: 6945202 | AL15: 6945202 | AM15: 6945202 | AN15: 6945202 | AS15: 1.1079151e+08 | AT15: 0 | AU15: 125826.96 | AV15: 124381.89 | AW15: 116799.8 | AX15: 123563.52 | AZ15: 136424.35 | BA15: 140765.73 | BB15: 1.0175735e+08 | BC15: 1.0175755e+08 | BD15: 98170179 | BE15: 98055147 | BF15: 96038619 | BG15: 1.0345375e+08 | BH15: 1.0216673e+08 | BI15: 1.0216673e+08 | BJ15: 1.0216673e+08 | BK15: 89788130 | BL15: 1.045009e+08 | BM15: 1.0646815e+08 | BN15: 1.0616673e+08 | BO15: 1.24684e+08 | BP15: 1.2335173e+08 | BQ15: 1.0216673e+08 | BR15: =78211545.57-19843602+12727643-191737.57 -> 70903849 | BS15: 1.0216673e+08 | BT15: 1.0216673e+08 | BU15: 1.0216673e+08 | BV15: 1.0216673e+08 | BW15: 77521848 | BX15: 81506090 | BY15: 80264280 | BZ15: 80264280 | CA15: 79027956 | CB15: 75274689 | CC15: 72859667 | CD15: 68407669 | CE15: 67933487 | CF15: =CE15-CD15 -> -474181.56 | CG15: 67933487 | CH15: 0 | CI15: 64263714 | CJ15: 58354957 | CK15: 57116051 | CL15: 59304557 | CM15: 65701593 | CN15: 68122439
A16: Accounts Recievables | B16: =SUM(B17:B19) -> 1014864 | C16: =SUM(C17:C19) -> 633214 | D16: =SUM(D17:D19) -> -1056148 | E16: =SUM(E17:E19) -> -1042683 | F16: =SUM(F17:F19) -> 0 | G16: =SUM(G17:G19) -> 0 | H16: =SUM(H17:H19) -> -1042683 | I16: =SUM(I17:I19) -> -1042683 | ... CE16: =SUM(CE17:CE19) -> 0 | CF16: =CE16-CD16 -> 0 | CG16: =SUM(CG17:CG19) -> 0 | CH16: =SUM(CH17:CH19) -> 7486538.1 | CI16: =SUM(CI17:CI19) -> 6842640 | CJ16: =SUM(CJ17:CJ19) -> 6842640 | CK16: =SUM(CK17:CK19) -> 6826640 | CL16: =SUM(CL17:CL19) -> 6826640 | CM16: =SUM(CM17:CM19) -> 10729369 | CN16: =SUM(CN17:CN19) -> 10721369
A17: Tax Recoverable | B17: 1014864 | C17: 633214 | D17: -1056148 | E17: -1042683 | F17: 0 | G17: 0 | H17: -1042683 | I17: -1042683 | J17: -1042683 | K17: -1042683 | L17: 0 | M17: 0 | N17: 0 | O17: 0 | P17: 0 | Q17: 0 | X17: 0 | Y17: 0 | Z17: 0 | AA17: 0 | AB17: 0 | AC17: 0 | AD17: 0 | AF17: 0 | AG17: 0 | AH17: 0 | AI17: 0 | AJ17: 0 | AK17: 0 | AL17: 0 | AM17: 0 | AN17: 0 | AS17: 0 | AT17: 0 | AU17: 0 | AV17: 0 | AW17: 0 | AX17: 0 | AZ17: 0 | BA17: 0 | BB17: 0 | BC17: 0 | BD17: 0 | BF17: 0 | BG17: 0 | BH17: 0 | BI17: 0 | BJ17: 0 | BK17: 0 | BL17: 0 | BM17: 0 | BN17: 0 | BO17: 0 | BP17: 0 | BQ17: 0 | BS17: 0 | BT17: 0 | BU17: 0 | BV17: 0 | BW17: 0 | CA17: 0 | CB17: 0 | CC17: 0 | CF17: =CE17-CD17 -> 0 | CH17: 0 | CI17: 0 | CJ17: 0 | CK17: 0 | CL17: 0 | CM17: 0 | CN17: 0
A18: Deffered Tax Assets | C18: 0 | F18: 0 | G18: 0 | H18: 0 | I18: 0 | J18: 0 | L18: 0 | M18: 0 | N18: 0 | O18: 0 | P18: 0 | Q18: 0 | X18: 0 | Y18: 0 | Z18: 0 | AA18: 0 | AB18: 0 | AC18: 0 | AD18: 0 | AF18: 0 | AG18: 0 | AH18: 0 | AI18: 0 | AJ18: 0 | AK18: 0 | AL18: 0 | AM18: 0 | AN18: 0 | AS18: 0 | AT18: 0 | AU18: 0 | AV18: 0 | AW18: 0 | AX18: 0 | AZ18: 0 | BA18: 0 | BB18: 0 | BC18: 0 | BD18: 0 | BF18: 0 | BG18: 0 | BH18: 0 | BI18: 0 | BJ18: 0 | BK18: 0 | BL18: 0 | BM18: 0 | BN18: 0 | BO18: 0 | BP18: 0 | BQ18: 0 | BS18: 0 | BT18: 0 | BU18: 0 | BV18: 0 | BW18: 0 | CA18: 0 | CB18: 0 | CC18: 0 | CF18: =CE18-CD18 -> 0 | CH18: 0 | CI18: 0 | CJ18: 0 | CK18: 0 | CL18: 0 | CM18: 0 | CN18: 0
A19: Retirement Benefit Assets | C19: 0 | F19: 0 | G19: 0 | H19: 0 | I19: 0 | L19: 0 | M19: 0 | N19: 0 | O19: 0 | P19: 0 | Q19: 0 | X19: 0 | Y19: 44295800 | Z19: 40950010 | AA19: 40616558 | AB19: 40953250 | AC19: 30430425 | AD19: 69650104 | AF19: 40251206 | AG19: 37086124 | AH19: 37638956 | AI19: 60639568 | AJ19: 55231656 | AK19: 53248170 | AL19: 43322133 | AM19: 46983140 | AN19: 47634678 | AS19: 34518708 | AT19: 1.3023026e+08 | AU19: 1.2274664e+08 | AV19: 1.2330664e+08 | AW19: 1.2668627e+08 | AX19: 1.3186282e+08 | AZ19: 1.2766503e+08 | BA19: 1.2641351e+08 | BB19: 1.2692238e+08 | BC19: 1.2573708e+08 | BD19: 1.25939e+08 | BF19: 14601812 | BG19: 13483515 | BH19: 13979889 | BI19: 13976590 | BJ19: 13977490 | BK19: 11552231 | BL19: 11578081 | BM19: 11610081 | BN19: 9393511.1 | BO19: 9388661.1 | BP19: 9380661.1 | BQ19: 9444799.1 | BR19: 0 | BS19: 9483199 | BT19: 0 | BU19: 0 | BV19: 0 | BW19: 0 | CA19: 24000 | CB19: 275435.67 | CC19: 275435.67 | CF19: =CE19-CD19 -> 0 | CH19: 7486538.1 | CI19: 6842640 | CJ19: 6842640 | CK19: 6826640 | CL19: 6826640 | CM19: 10729369 | CN19: 10721369
A20: Property&Equipments&Other Assets | B20: =SUM(B21:B25) -> 15008730 | C20: =SUM(C21:C25) -> 10355868 | D20: =SUM(D21:D25) -> 23445547 | E20: =SUM(E21:E25) -> 40139932 | F20: =SUM(F21:F25) -> 21382272 | G20: =SUM(G21:G25) -> 37531087 | H20: =SUM(H21:H25) -> 29989620 | I20: =SUM(I21:I25) -> 30668107 | ... CE20: =SUM(CE21:CE25) -> 132955259 | CF20: =CE20-CD20 -> 21909696 | CG20: =SUM(CG21:CG25) -> 132955259 | CH20: =SUM(CH21:CH25) -> 27115991 | CI20: =SUM(CI21:CI25) -> 95105675 | CJ20: =SUM(CJ21:CJ25) -> 85287674 | CK20: =SUM(CK21:CK25) -> 84736741 | CL20: =SUM(CL21:CL25) -> 87184328 | CM20: =SUM(CM21:CM25) -> 95715088 | CN20: =SUM(CN21:CN25) -> 83125110
A21: Investment Properties | C21: 0 | F21: 0 | G21: 0 | H21: 0 | I21: 0 | J21: 0 | K21: 0 | L21: 0 | M21: 0 | N21: 0 | O21: 0 | P21: 0 | Q21: 0 | S21: 0 | T21: 0 | U21: 0 | V21: 0 | W21: 0 | X21: 0 | Y21: 0 | Z21: 0 | AA21: 0 | AB21: 0 | AC21: 0 | AD21: 0 | AF21: 0 | AG21: 0 | AH21: 0 | AI21: 0 | AJ21: 0 | AK21: 0 | AL21: 0 | AM21: 0 | AN21: 0 | AS21: 0 | AT21: 0 | AU21: 0 | AV21: 0 | AW21: 0 | AX21: 0 | AZ21: 0 | BA21: 0 | BB21: 0 | BC21: 0 | BD21: 0 | BF21: 0 | BG21: 0 | BH21: 0 | BI21: 0 | BJ21: 0 | BK21: 0 | BL21: 0 | BM21: 0 | BN21: 0 | BO21: 0 | BP21: 0 | BQ21: 0 | BS21: 0 | BT21: 0 | BU21: 0 | BV21: 0 | BW21: 0 | BX21: 0 | BY21: 0 | BZ21: 0 | CA21: 0 | CB21: 0 | CC21: 0 | CD21: 0 | CF21: =CE21-CD21 -> 0 | CH21: 0 | CI21: 0 | CJ21: 0 | CK21: 0 | CL21: 0 | CM21: 0 | CN21: 0
A22: Property and Equipment | B22: 3110877 | C22: 4576955 | D22: 9907043 | E22: 14921476 | F22: 20113390 | G22: 14923330 | H22: 15050807 | I22: 14976884 | J22: 14902961 | K22: 15096038 | L22: 0 | M22: 0 | N22: 0 | O22: 0 | P22: 0 | Q22: 0 | R22: 15459762 | S22: 15405509 | T22: 15351256 | U22: 15351256 | V22: 15242751 | W22: 15188498 | X22: 4613176.9 | Y22: 4613176.9 | Z22: 4613176.9 | AA22: 4613176.9 | AB22: 4775576.9 | AC22: 4662176.9 | AD22: 4037546.9 | AE22: 14449570 | AF22: 4024046.9 | AG22: 4037546.9 | AH22: 4143213.9 | AI22: 2504641.9 | AJ22: 2507141.9 | AK22: 2509140.9 | AL22: 2509140.9 | AM22: 2509140.9 | AN22: 2509140.9 | AS22: 1834787.8 | AT22: 1834787.8 | AU22: 1848037.8 | AV22: 1848037.8 | AW22: 1860787.8 | AX22: 1860787.8 | AZ22: 1865287.8 | BA22: 1887287.8 | BB22: 1887287.8 | BC22: 1887287.8 | BD22: 1887287.8 | BE22: 14586623 | BF22: 16156930 | BG22: 16156930 | BH22: 16156930 | BI22: 16174640 | BJ22: 16307390 | BK22: 16330247 | BL22: 16579997 | BM22: 16886997 | BN22: 16886997 | BO22: 16886997 | BP22: 16927697 | BQ22: 16943047 | BR22: 14279292 | BS22: 16886997 | BT22: 17010547 | BU22: 17116807 | BV22: 17013247 | BW22: 14279292 | BX22: 13570536 | BY22: 12570536 | BZ22: 14968599 | CA22: 14968599 | CB22: 18763161 | CC22: 18763161 | CD22: 32319997 | CE22: 17192646 | CF22: =CE22-CD22 -> -15127351 | CG22: 17192646 | CH22: 14968599 | CI22: 27073991 | CJ22: 27073991 | CK22: 24197403 | CL22: 24197403 | CM22: 32331926 | CN22: 32331926
A23: Prepaid Lease Rentals | C23: 0 | F23: 0 | G23: 0 | H23: 0 | I23: 0 | J23: 0 | K23: 0 | L23: 0 | M23: 0 | N23: 0 | O23: 0 | P23: 0 | Q23: 0 | S23: 0 | T23: 0 | U23: 0 | V23: 0 | W23: 0 | X23: 0 | Y23: 0 | Z23: 0 | AA23: 0 | AB23: 0 | AC23: 0 | AD23: 0 | AF23: 0 | AG23: 0 | AH23: 0 | AI23: 0 | AJ23: 0 | AK23: 0 | AL23: 0 | AM23: 0 | AN23: 0 | AS23: 0 | AT23: 0 | AU23: 0 | AV23: 0 | AW23: 0 | AX23: 0 | AZ23: 0 | BA23: 0 | BB23: 0 | BC23: 0 | BD23: 0 | BF23: 1.1224273e+08 | BG23: 0 | BH23: 0 | BI23: 1.1067212e+08 | BJ23: 0 | BK23: 0 | BL23: 0 | BM23: 0 | BN23: 0 | BO23: 0 | BP23: 0 | BQ23: 0 | BS23: 0 | BT23: 0 | BU23: 0 | BV23: 0 | BW23: 0 | BX23: 0 | BY23: 0 | CA23: 0 | CB23: 0 | CC23: 0 | CD23: 0 | CF23: =CE23-CD23 -> 0 | CH23: 0 | CI23: 0 | CJ23: 0 | CK23: 0 | CL23: 0 | CM23: 0 | CN23: 0
A24: Intangible Assets | B24: 152185 | C24: 0 | E24: 2148552 | F24: 1268881.9 | G24: 2041124.4 | H24: 1987410.6 | I24: 2082286.8 | J24: 2024446 | K24: 1966604.2 | L24: 0 | M24: 0 | N24: 0 | O24: 0 | P24: 0 | Q24: 0 | R24: 1619556 | S24: 1655392.5 | T24: 1695881.4 | U24: 1695881.4 | V24: 1457600.8 | W24: 1417111.9 | X24: 4120044 | Y24: 4120044 | Z24: 4120044 | AA24: 4120044 | AB24: 4120044 | AC24: 4282444 | AD24: 4282444 | AE24: 4282444 | AF24: 4282444 | AG24: 4282444 | AH24: 4282444 | AI24: 5897348 | AJ24: 5897348 | AK24: 5897348 | AL24: 5897348 | AM24: 5897348 | AN24: 5897348 | AS24: 2142518.7 | AT24: 2142518.7 | AU24: 2142518.7 | AV24: 2142518.7 | AW24: 2142518.7 | AX24: 2404076.7 | AZ24: 2799001.7 | BA24: 2874351.7 | BB24: 2885676.7 | BC24: 2985676.7 | BD24: 2985676.7 | BE24: 2089974 | BF24: 1723461.8 | BG24: 1798461.8 | BH24: 1798461.8 | BI24: 1846661.8 | BJ24: 1846661.8 | BK24: 1846661.8 | BL24: 1846661.8 | BM24: 2118861.8 | BN24: 2118861.8 | BO24: 2118861.8 | BP24: 2158861.8 | BQ24: 2158861.8 | BR24: 1462982 | BS24: 2118861.8 | BT24: 2158861.8 | BU24: 2158861.8 | BV24: 2258861.8 | BW24: 1462982 | BX24: 7110806 | BY24: 9257455.6 | BZ24: 9257455.6 | CA24: 9257455.6 | CB24: 20958247 | CC24: 20958247 | CD24: 8778560.7 | CE24: 2526742 | CF24: =CE24-CD24 -> -6251818.7 | CG24: 2526742 | CH24: 2876587.4 | CI24: 2876587.4 | CJ24: 2876587.4 | CK24: 2876587.4 | CL24: 2876587.4 | CM24: 8778560.7 | CN24: 8778560.7
A25: Other Assets | B25: 11745668 | C25: 5778913 | D25: 13538504 | E25: 23069904 | F25: 0 | G25: 20566633 | H25: 12951403 | I25: 13608936 | J25: =488647+12452420 -> 12941067 | K25: 12838545 | L25: 0 | M25: 0 | N25: 0 | O25: 0 | P25: 0 | Q25: 0 | R25: =389280+25343078 -> 25732358 | S25: 25343078 | T25: 25343078 | U25: 25343078 | V25: 33779943 | W25: 33779943 | X25: 14270892 | Y25: 14270892 | Z25: 14270892 | AA25: 14270892 | AB25: 14270892 | AC25: 14270892 | AD25: 14270892 | AE25: =7753599+227275 -> 7980874 | AF25: 14270892 | AG25: 14270892 | AH25: 14270892 | AI25: 14270892 | AJ25: 14270892 | AK25: 14270892 | AL25: 14270892 | AM25: 14282892 | AN25: 14282892 | AS25: 12716827 | AT25: 12716827 | AU25: 12716827 | AV25: 12730527 | AW25: 12730527 | AX25: 12916527 | AZ25: 12916527 | BA25: 13007127 | BB25: 13007127 | BC25: 13007127 | BD25: 13007127 | BE25: 114835602 | BF25: 0 | BG25: 1.033849e+08 | BH25: 1.1454399e+08 | BI25: 0 | BJ25: 99932503 | BK25: 1.1321627e+08 | BL25: 1.1321627e+08 | BM25: 1.1321627e+08 | BN25: 1.1479619e+08 | BO25: 1.1321627e+08 | BP25: 1.1321627e+08 | BQ25: 1.101776e+08 | BS25: 1.1019373e+08 | BT25: 1.1363024e+08 | BU25: 1.1234745e+08 | BV25: 1.1436147e+08 | BW25: 1.1321627e+08 | BX25: 1.2852308e+08 | BY25: 1.1321627e+08 | BZ25: 1.206091e+08 | CA25: 1.0376415e+08 | CB25: 82311828 | CC25: 82311828 | CD25: 69947006 | CE25: 113235871 | CF25: =CE25-CD25 -> 43288865 | CG25: 113235871 | CH25: 9270804.2 | CI25: 65155097 | CJ25: 55337096 | CK25: 57662750 | CL25: 60110338 | CM25: 54604601 | CN25: 42014623
A26: Total Assets | B26: =B20+B16+B13+B8+B7+B4 -> 320889783 | C26: =C20+C16+C13+C8+C7+C4 -> 272305757 | D26: =D20+D16+D13+D8+D7+D4 -> 285464131 | E26: =E20+E16+E13+E8+E7+E4 -> 301184793 | F26: =F20+F16+F13+F8+F7+F4 -> 2.7577865e+08 | G26: =G20+G16+G13+G8+G7+G4 -> 3.0578939e+08 | H26: =H20+H16+H13+H8+H7+H4 -> 2.8619334e+08 | I26: =I20+I16+I13+I8+I7+I4 -> 2.717549e+08 | ... CE26: =CE20+CE16+CE13+CE8+CE7+CE4 -> 219787161 | CF26: =CE26-CD26 -> 30057152 | CG26: =CG20+CG16+CG13+CG8+CG7+CG4 -> 219787161 | CH26: =CH20+CH16+CH13+CH8+CH7+CH4 -> 1.7776269e+08 | CI26: =CI20+CI16+CI13+CI8+CI7+CI4 -> 1.7780477e+08 | CJ26: =CJ20+CJ16+CJ13+CJ8+CJ7+CJ4 -> 1.7098285e+08 | CK26: =CK20+CK16+CK13+CK8+CK7+CK4 -> 1.7086292e+08 | CL26: =CL20+CL16+CL13+CL8+CL7+CL4 -> 1.6995306e+08 | CM26: =CM20+CM16+CM13+CM8+CM7+CM4 -> 1.7527604e+08 | CN26: =CN20+CN16+CN13+CN8+CN7+CN4 -> 1.7638495e+08
A27: Savings and Deposits | B27: 57969061 | C27: =28636276+1891321+3132613 -> 33660210 | D27: =24367647-7748319 -> 16619328 | E27: 17947544 | F27: -6391944.5 | G27: 5076591 | H27: 4654413.1 | I27: 31282276 | J27: -4342846.4 | K27: -12144473 | L27: 0 | M27: 0 | N27: 0 | O27: 0 | P27: 0 | Q27: 0 | R27: =-31816265 -> -31816265 | S27: -14709982 | T27: -10364619 | U27: -10364619 | V27: -20482011 | W27: -20440729 | X27: -30667169 | Y27: -41219533 | Z27: -27431796 | AA27: -31307044 | AB27: -35640907 | AC27: -26085448 | AD27: -38924042 | AE27: -28293693 | AF27: -38190433 | AG27: -35194936 | AH27: -53133636 | AI27: -54864721 | AJ27: -52818305 | AK27: -49017962 | AL27: -45818016 | AM27: -43282956 | AN27: -42991538 | AS27: -42065362 | AT27: 50344997 | AU27: 42591064 | AV27: 44047927 | AW27: 48511188 | AX27: 54283435 | AZ27: 41897611 | BA27: 41756059 | BB27: 42954285 | BC27: 43763548 | BD27: 44982409 | BE27: 43898703 | BF27: 26898173 | BG27: 32087694 | BH27: 21912102 | BI27: 27076837 | BJ27: 26916313 | BK27: 28129938 | BL27: 26635920 | BM27: 26925027 | BN27: 22789621 | BO27: 23996162 | BP27: 23691500 | BQ27: 24455795 | BR27: 38360675 | BS27: 23748642 | BT27: 28356816 | BU27: 30300776 | BV27: 28660542 | BW27: 42808669 | BX27: 42308175 | BY27: 41499014 | BZ27: 41446926 | CA27: 45245396 | CB27: 42520866 | CC27: 41857694 | CD27: 41053075 | CE27: 41044632 | CF27: =CE27-CD27 -> -8442.56 | CG27: 41044632 | CH27: 43082503 | CI27: 40082532 | CJ27: 36607691 | CK27: 35997992 | CL27: 35020598 | CM27: 35973687 | CN27: 36040154
A28: Short Terrm Deposits | C28: 7112519 | D28: 7748319 | F28: 0 | G28: 16697146 | H28: 13713413 | I28: 2237547 | J28: 2281417 | K28: 2137430.3 | L28: 0 | M28: 0 | N28: 0 | O28: 0 | P28: 0 | Q28: 0 | S28: 11125696 | T28: 476276.34 | U28: 476276.34 | V28: 479276.34 | W28: 465276.34 | X28: 1.5998507e+08 | Y28: 348116.94 | Z28: 424657.25 | AA28: 410624.25 | AB28: 59541.31 | AC28: 213125.25 | AD28: 208708.25 | AF28: 176675.25 | AG28: 144105.95 | AH28: 0 | AI28: 153105.95 | AJ28: 151069.95 | AK28: 151569.95 | AL28: 152069.95 | AM28: 152569.95 | AN28: 153069.95 | AS28: 155069.95 | AT28: 155569.95 | AU28: 156069.95 | AV28: 156569.95 | AW28: 151033.95 | AX28: 151533.95 | AZ28: 155244.35 | BA28: 200321.55 | BB28: 202321.55 | BC28: 198261.55 | BD28: 200701.55 | BF28: 101207.04 | BG28: 101207.04 | BH28: 101207.04 | BI28: 101207.04 | BJ28: 75757.04 | BK28: 45757.04 | BL28: 45757.04 | BM28: 45157.04 | BN28: 45057.04 | BO28: 44957.04 | BP28: 44857.04 | BQ28: 1657.04 | BS28: 1607.04 | BT28: 1557.04 | BU28: 1557.04 | BV28: 1557.04 | BW28: 1557.04 | BX28: 1557.04 | BY28: 1557.04 | BZ28: 1557.04 | CA28: 1557.04 | CB28: 1557.04 | CC28: 1557.04 | CD28: 1557.04 | CF28: =CE28-CD28 -> -1557.04 | CH28: 0 | CI28: 0 | CJ28: 0 | CK28: 0 | CL28: 0 | CM28: 0 | CN28: 0
A29: Non Withdrawable Deposits | B29: 128848216 | C29: 130204762 | D29: 145890587 | E29: 156610517 | F29: 1.5671857e+08 | G29: 1.5838375e+08 | H29: 1.5896245e+08 | I29: 1.3637148e+08 | J29: 161715862 | K29: 1.6185376e+08 | L29: 0 | M29: 0 | N29: 0 | O29: 0 | P29: 0 | Q29: 0 | R29: 161769899 | S29: 1.6178052e+08 | T29: 1.6125205e+08 | U29: 1.6125205e+08 | V29: 1.5995688e+08 | W29: 1.6197022e+08 | X29: 0 | Y29: 1.6004019e+08 | Z29: 1.6148697e+08 | AA29: 1.5409612e+08 | AB29: 1.5120571e+08 | AC29: 1.5312251e+08 | AD29: 1.5502215e+08 | AE29: 157923433 | AF29: 1.5340365e+08 | AG29: 1.5361809e+08 | AH29: 1.5264917e+08 | AI29: 1.5241044e+08 | AJ29: 1.5252124e+08 | AK29: 1.5250097e+08 | AL29: 1.5227467e+08 | AM29: 1.5201312e+08 | AN29: 1.5219687e+08 | AS29: 1.5217194e+08 | AT29: 1.5213616e+08 | AU29: 1.5204878e+08 | AV29: 1.5197089e+08 | AW29: 1.5219423e+08 | AX29: 1.5199217e+08 | AZ29: 1.5447931e+08 | BA29: 1.5222877e+08 | BB29: 1.5113678e+08 | BC29: 1.4955925e+08 | BD29: 1.4987494e+08 | BE29: 149658884 | BF29: 1.6295599e+08 | BG29: 1.6310723e+08 | BH29: 1.6185558e+08 | BI29: 1.5733913e+08 | BJ29: 1.5627358e+08 | BK29: 1.5676967e+08 | BL29: 1.5564191e+08 | BM29: 1.553147e+08 | BN29: 1.553467e+08 | BO29: 1.5548696e+08 | BP29: 1.5478064e+08 | BQ29: 1.5571877e+08 | BR29: 149658884 | BS29: 1.5610297e+08 | BT29: 1.5769099e+08 | BU29: 1.5772671e+08 | BV29: 1.5727119e+08 | BW29: 1.4264036e+08 | BX29: 1.4262557e+08 | BY29: 1.4217613e+08 | BZ29: 1.4222665e+08 | CA29: 1.4248021e+08 | CB29: 1.4268014e+08 | CC29: 1.4320854e+08 | CD29: 1.4412939e+08 | CE29: 144129387 | CF29: =CE29-CD29 -> 0.47999999 | CG29: 144129387 | CH29: 1.4728323e+08 | CI29: 1.4714901e+08 | CJ29: 1.4493057e+08 | CK29: 1.4480849e+08 | CL29: 1.4451672e+08 | CM29: 1.4334142e+08 | CN29: 1.4303848e+08
A30: Total Deposit Liabilities | B30: =SUM(B27:B29) -> 186817277 | C30: =SUM(C27:C29) -> 170977491 | D30: =SUM(D27:D29) -> 170258234 | E30: =SUM(E27:E29) -> 174558061 | F30: =SUM(F27:F29) -> 1.5032662e+08 | G30: =SUM(G27:G29) -> 1.8015749e+08 | H30: =SUM(H27:H29) -> 1.7733028e+08 | I30: =SUM(I27:I29) -> 1.698913e+08 | ... CE30: =SUM(CE27:CE29) -> 185174019 | CF30: =CE30-CD30 -> -9999.12 | CG30: =SUM(CG27:CG29) -> 185174019 | CH30: =SUM(CH27:CH29) -> 1.9036574e+08 | CI30: =SUM(CI27:CI29) -> 1.8723154e+08 | CJ30: =SUM(CJ27:CJ29) -> 1.8153826e+08 | CK30: =SUM(CK27:CK29) -> 1.8080648e+08 | CL30: =SUM(CL27:CL29) -> 1.7953732e+08 | CM30: =SUM(CM27:CM29) -> 1.7931511e+08 | CN30: =SUM(CN27:CN29) -> 1.7907863e+08
A31: Tax Payable | C31: 0 | F31: 0 | G31: 0 | H31: 0 | I31: 0 | J31: 0 | K31: 0 | L31: 0 | M31: 0 | N31: 0 | O31: 0 | P31: 0 | Q31: 0 | R31: 0 | S31: 0 | T31: 0 | U31: 0 | V31: 0 | W31: 1042683 | X31: 0 | Y31: 0 | Z31: 0 | AA31: 0 | AB31: 0 | AC31: 0 | AD31: 0 | AE31: 1042683 | AF31: 0 | AG31: 0 | AH31: 0 | AI31: 0 | AJ31: 0 | AK31: 0 | AL31: 0 | AM31: 0 | AN31: 0 | AS31: 0 | AT31: 0 | AU31: 0 | AV31: 0 | AW31: 0 | AX31: 0 | AZ31: 0 | BA31: 0 | BB31: 0 | BC31: 0 | BD31: 0 | BE31: 136406 | BF31: 0 | BG31: 0 | BH31: 0 | BI31: 0 | BJ31: 0 | BK31: 0 | BL31: 0 | BM31: 0 | BN31: 0 | BO31: 0 | BP31: 0 | BQ31: 0 | BR31: 136406 | BS31: 0 | BT31: 0 | BU31: 0 | BV31: 0 | BW31: 0 | BX31: 0 | BY31: 0 | BZ31: 0 | CA31: 0 | CB31: 0 | CC31: 0 | CD31: 0 | CE31: 136406 | CF31: =CE31-CD31 -> 136406 | CG31: 136406 | CH31: 0 | CI31: 0 | CJ31: 0 | CK31: 0 | CL31: 0 | CM31: 0 | CN31: 0
A32: Dividends Payable | C32: 0 | F32: 0 | G32: 0 | H32: 0 | I32: 0 | L32: 0 | M32: 0 | N32: 0 | O32: 0 | P32: 0 | Q32: 0 | R32: 0 | S32: 1042683 | T32: 1042683 | U32: 1042683 | V32: 1042683 | W32: 0 | X32: 0 | Y32: 0 | Z32: 0 | AA32: 0 | AB32: 0 | AC32: 0 | AD32: 0 | AF32: 0 | AG32: 0 | AH32: 0 | AI32: 0 | AJ32: 0 | AK32: 0 | AL32: 0 | AM32: 0 | AN32: 0 | AS32: 0 | AT32: 0 | AU32: 0 | AV32: 0 | AW32: 0 | AX32: 0 | AZ32: 0 | BA32: 0 | BB32: 0 | BC32: 0 | BD32: 0 | BF32: 0 | BG32: 0 | BH32: 0 | BI32: 0 | BJ32: 0 | BK32: 0 | BL32: 0 | BM32: 0 | BN32: 0 | BO32: 0 | BP32: 0 | BQ32: 0 | BS32: 0 | BT32: 0 | BU32: 0 | BV32: 0 | BW32: 0 | BX32: 0 | BY32: 0 | BZ32: 0 | CA32: 0 | CB32: 0 | CC32: 0 | CD32: 0 | CF32: =CE32-CD32 -> 0 | CH32: 0 | CI32: 0 | CJ32: 0 | CK32: 0 | CL32: 0 | CM32: 0 | CN32: 0
A33: Deferred Tax Liability | C33: 0 | F33: 0 | G33: 0 | H33: 0 | I33: 0 | L33: 0 | M33: 0 | N33: 0 | O33: 0 | P33: 0 | Q33: 0 | R33: 0 | S33: 0 | T33: 0 | U33: 0 | V33: 0 | W33: 0 | X33: 2735015.9 | Y33: 3464782.5 | Z33: 10942375 | AA33: 14519640 | AB33: 10678179 | AC33: -2824086.5 | AD33: 0 | AF33: -9257363.7 | AG33: 6274559.2 | AH33: 8266876.7 | AI33: 0 | AJ33: 5093329.7 | AK33: -2023697.9 | AL33: 9767507.1 | AM33: 8935102 | AN33: 8024562.5 | AS33: 9276903.2 | AT33: 18124506 | AU33: 22870275 | AV33: 18762521 | AW33: 18680443 | AX33: 22314158 | AZ33: 26608336 | BA33: 25262334 | BB33: 27379840 | BC33: 27161524 | BD33: 28891592 | BE33: 0 | BF33: 0 | BG33: 18792412 | BH33: 27538024 | BI33: 0 | BJ33: 14694137 | BK33: 15160895 | BL33: 13992983 | BM33: 14847996 | BN33: 17165913 | BO33: -4532781.4 | BP33: 12881050 | BQ33: 17070839 | BS33: 15110494 | BT33: 0 | BU33: 0 | BV33: 12389089 | BW33: 24548441 | BX33: 15293757 | BY33: 25137339 | BZ33: 25137339 | CA33: 17022136 | CB33: 32641631 | CC33: 41756059 | CD33: 32641631 | CF33: =CE33-CD33 -> -32641631 | CH33: 11227276 | CI33: 14154846 | CJ33: 11305068 | CK33: 10864906 | CL33: 10616199 | CM33: 15732582 | CN33: 16063820
A34: Retirement Benefits Liabilty | C34: 0 | F34: 0 | G34: 0 | H34: 0 | I34: 0 | L34: 0 | M34: 0 | N34: 0 | O34: 0 | P34: 0 | Q34: 0 | R34: 0 | S34: 0 | T34: 0 | U34: 0 | V34: 0 | W34: 0 | X34: 0 | Y34: 0 | Z34: 0 | AA34: 0 | AB34: 0 | AC34: 0 | AD34: 0 | AF34: 0 | AG34: 0 | AH34: 0 | AI34: 0 | AJ34: 0 | AK34: 0 | AL34: 0 | AM34: 0 | AN34: 0 | AS34: 0 | AT34: 0 | AU34: 0 | AV34: 0 | AW34: 0 | AX34: 0 | AZ34: 0 | BA34: 0 | BB34: 0 | BC34: 0 | BD34: 0 | BF34: 0 | BG34: 0 | BH34: 0 | BI34: 0 | BJ34: 0 | BK34: 0 | BL34: 0 | BM34: 0 | BN34: 0 | BO34: 0 | BP34: 0 | BQ34: 0 | BS34: 0 | BT34: 0 | BU34: 0 | BV34: 0 | BW34: 0 | BX34: 0 | BY34: 0 | BZ34: 0 | CA34: 0 | CB34: 0 | CC34: 0 | CD34: 0 | CF34: =CE34-CD34 -> 0 | CH34: 0 | CI34: 0 | CJ34: 0 | CK34: 0 | CL34: 0 | CM34: 0 | CN34: 0
A35: Other Liabilities | B35: 33671151 | C35: 14909432 | D35: 17468618 | E35: 19703464 | F35: 3374285.2 | G35: 22071660 | H35: 6893937.5 | I35: 1626901 | J35: 7979658 | K35: 7466349.9 | L35: 0 | M35: 0 | N35: 0 | O35: 0 | P35: 0 | Q35: 0 | R35: =1042683+8823138 -> 9865821 | S35: 0 | T35: 0 | U35: 4512705.1 | V35: 3836489.6 | W35: 8337542.6 | X35: 0 | Y35: 0 | Z35: 0 | AA35: 0 | AB35: 0 | AC35: 0 | AD35: 4882916.4 | AE35: 16538988 | AF35: 0 | AG35: 0 | AH35: 0 | AI35: 5072297.7 | AJ35: 0 | AK35: 0 | AL35: 0 | AM35: 0 | AN35: 0 | AS35: 0 | AT35: 0 | AU35: 0 | AV35: 0 | AW35: 0 | AX35: 0 | AZ35: 0 | BA35: 0 | BB35: 0 | BC35: 0 | BD35: 0 | BE35: 16707213 | BF35: 22287053 | BG35: 0 | BH35: 0 | BI35: 17881211 | BJ35: 0 | BK35: 0 | BL35: 0 | BM35: 0 | BN35: 0 | BO35: 0 | BP35: 0 | BQ35: 0 | BR35: 17586293 | BS35: 0 | BT35: 16109929 | BU35: 20456018 | BV35: 0 | BW35: 21491853 | BX35: 39174033 | BY35: 25091945 | BZ35: 25091945 | CA35: 215876.44 | CB35: 215876.44 | CC35: 215876.44 | CD35: 215876.44 | CE35: 23456880 | CF35: =CE35-CD35 -> 23241004 | CG35: 23456880 | CH35: 0 | CI35: 0 | CJ35: 0 | CK35: 0 | CL35: 0 | CM35: 0 | CN35: 0
A36: External Borrowings | B36: 5711235 | C36: 3146881 | D36: 18495124 | E36: 29110952 | F36: 28512340 | G36: 28010877 | H36: 24962488 | I36: 24962488 | J36: 23353476 | K36: 23353476 | L36: 0 | M36: 0 | N36: 0 | O36: 0 | P36: 0 | Q36: 0 | R36: 29133453 | S36: 29996387 | T36: 29996387 | U36: 29996387 | V36: 28410979 | W36: 28410979 | X36: 28410979 | Y36: 28410979 | Z36: 28410979 | AA36: 28603585 | AB36: 28410979 | AC36: 24541568 | AD36: 22783568 | AE36: 23403274 | AF36: 23382166 | AG36: 22985845 | AH36: 26089275 | AI36: 22783568 | AJ36: 22783568 | AK36: 22783568 | AL36: 22783568 | AM36: 22783568 | AN36: 27899605 | AS36: 20179593 | AT36: 20179593 | AU36: 23981224 | AV36: 23981224 | AW36: 23981224 | AX36: 23981224 | AZ36: 25384883 | BA36: 25084883 | BB36: 25182043 | BC36: 25032043 | BD36: 25032043 | BE36: 25032043 | BF36: 25032043 | BG36: 26387951 | BH36: 26786652 | BI36: 26187951 | BJ36: 25987951 | BK36: 26174164 | BL36: 26014514 | BM36: 25814514 | BN36: 25814514 | BO36: 25814514 | BP36: 25814514 | BQ36: 25814514 | BR36: 24058606 | BS36: 25814514 | BT36: 25814514 | BU36: 25814514 | BV36: 25814514 | BW36: 25814514 | BX36: 26537750 | BY36: 26597168 | BZ36: 26597168 | CA36: 26597168 | CB36: 26597168 | CC36: 26597168 | CD36: 26597168 | CE36: 26597168 | CF36: =CE36-CD36 -> 0.030000001 | CG36: 26597168 | CH36: 23782824 | CI36: 23685664 | CJ36: 24033302 | CK36: 24033302 | CL36: 24033302 | CM36: 24033302 | CN36: 25789408
A37: Total Liabilities | B37: =SUM(B30:B36) -> 226199663 | C37: =SUM(C30:C36) -> 189033804 | D37: =SUM(D30:D36) -> 206221976 | E37: =SUM(E30:E36) -> 223372477 | F37: =SUM(F30:F36) -> 1.8221325e+08 | G37: =SUM(G30:G36) -> 2.3024003e+08 | H37: =SUM(H30:H36) -> 2.091867e+08 | I37: =SUM(I30:I36) -> 1.9648069e+08 | ... CE37: =SUM(CE30:CE36) -> 235364473 | CF37: =CE37-CD37 -> -9274220.5 | CG37: =SUM(CG30:CG36) -> 235364473 | CH37: =SUM(CH30:CH36) -> 2.2537584e+08 | CI37: =SUM(CI30:CI36) -> 2.2507205e+08 | CJ37: =SUM(CJ30:CJ36) -> 2.1687663e+08 | CK37: =SUM(CK30:CK36) -> 2.1570469e+08 | CL37: =SUM(CL30:CL36) -> 2.1418682e+08 | CM37: =SUM(CM30:CM36) -> 2.19081e+08 | CN37: =SUM(CN30:CN36) -> 2.2093186e+08
A38: Share Capital | B38: 3584500 | C38: 9299642 | D38: 10539885 | E38: 11804277 | F38: 11804277 | G38: 11804277 | H38: 12789238 | I38: 12794938 | J38: 12794938 | K38: 12795398 | L38: 0 | M38: 0 | N38: 0 | O38: 0 | P38: 0 | Q38: 0 | R38: 13382089 | S38: 13383289 | T38: 13384489 | U38: 13364989 | V38: 13364989 | W38: 13408596 | X38: 13408596 | Y38: 0 | Z38: 13408596 | AA38: 13408596 | AB38: 13408596 | AC38: 13418596 | AD38: 13428596 | AE38: 13428596 | AF38: 13468796 | AG38: 13468796 | AH38: 13473796 | AI38: 13473796 | AJ38: 13473796 | AK38: 13473796 | AL38: 13473796 | AM38: 13473796 | AN38: 13473796 | AS38: 13473796 | AT38: 13473796 | AU38: 13473796 | AV38: 13473796 | AW38: 13473796 | AX38: 13473796 | AZ38: 13473796 | BA38: 13580324 | BB38: 13586624 | BC38: 13585924 | BD38: 13613124 | BE38: 13598624 | BF38: 13629924 | BG38: 13629924 | BH38: 13652824 | BI38: 13703324 | BJ38: 13712524 | BK38: 13721824 | BL38: 13721824 | BM38: 13742725 | BN38: 13742724 | BO38: 13742724 | BP38: 13744724 | BQ38: 13747224 | BR38: 13598624 | BS38: 13757224 | BT38: 13763124 | BU38: 13766924 | BV38: 13766924 | BW38: 13766924 | BX38: 13770424 | BY38: 13769924 | BZ38: 13776924 | CA38: 13777924 | CB38: 13793624 | CC38: 13802624 | CD38: 13793624 | CE38: 13824124 | CF38: =CE38-CD38 -> 30499.74 | CG38: 13824124 | CH38: 13849924 | CI38: 13854224 | CJ38: 13854224 | CK38: 13882924 | CL38: 13939124 | CM38: 13939124 | CN38: 13939424
A39: Capital Grants | C39: 0 | F39: 0 | G39: 0 | H39: 0 | I39: 0 | J39: 0 | L39: 0 | M39: 0 | N39: 0 | O39: 0 | P39: 0 | Q39: 0 | R39: 0 | S39: 0 | T39: 0 | U39: 0 | V39: 0 | W39: 0 | X39: 0 | Y39: 13408596 | Z39: 0 | AA39: 0 | AB39: 0 | AC39: 0 | AD39: 0 | AF39: 0 | AG39: 0 | AH39: 0 | AI39: 0 | AJ39: 0 | AK39: 0 | AL39: 0 | AM39: 0 | AN39: 0 | AS39: 0 | AT39: 0 | AU39: 0 | AV39: 0 | AW39: 0 | AX39: 0 | AZ39: 0 | BA39: 0 | BB39: 0 | BC39: 0 | BD39: 0 | BF39: 0 | BG39: 0 | BH39: 0 | BI39: 0 | BJ39: 0 | BK39: 0 | BL39: 0 | BM39: 0 | BN39: 0 | BO39: 0 | BP39: 0 | BQ39: 0 | BS39: 0 | BT39: 0 | BU39: 0 | BV39: 0 | BW39: 0 | BX39: 0 | BY39: 0 | BZ39: 0 | CA39: 0 | CB39: 0 | CC39: 0 | CD39: 0 | CF39: =CE39-CD39 -> 0 | CH39: 0 | CI39: 0 | CJ39: 0 | CK39: 0 | CL39: 0 | CM39: 0 | CN39: 0
A40: Prior Year Retained Earnigs | B40: 45148055 | C40: 22321562 | D40: =22765246-4678446+131265 -> 18218065 | E40: 17898031 | F40: 16488457 | G40: 16418457 | H40: 400110 | I40: 400110 | J40: 14698072 | K40: 14698072 | L40: 0 | M40: 0 | N40: 0 | O40: 0 | P40: 0 | Q40: 0 | R40: 14698071 | S40: 7209735 | T40: 7209735 | U40: 7209735 | V40: 7209735 | W40: 7209735 | X40: 14618579 | Y40: 14618579 | Z40: 14618579 | AA40: 14618579 | AB40: 14618579 | AC40: 14618579 | AD40: 14618579 | AE40: 7209735 | AF40: 14618579 | AG40: 14618579 | AH40: 14618579 | AI40: 14618579 | AJ40: 14618579 | AK40: 14618579 | AL40: 14618579 | AM40: 14618579 | AN40: 14618579 | AS40: -13871946 | AT40: -1.2150779e+08 | AU40: -121507788 | AV40: -121507788 | AW40: -121507788 | AX40: -121507788 | AZ40: -121507788 | BA40: -121507788 | BB40: -121507788 | BC40: -121507788 | BD40: -121507788 | BE40: =-121507788 -> -121507788 | BF40: -1.0417919e+08 | BG40: -121507788 | BH40: -121507788 | BI40: -121507788 | BJ40: -121507788 | BK40: -1.0824497e+08 | BL40: -121507788 | BM40: -121507788 | BN40: -121507788 | BO40: -121507788 | BP40: -121508188 | BQ40: -121508188 | BR40: =-111971756 -> -111971756 | BS40: -121508188 | BT40: -121508188 | BU40: -121507788 | BV40: -121508188 | BW40: -121507788 | BX40: -121507788 | BY40: -121507788 | BZ40: -121507788 | CA40: -121507788 | CB40: -121507788 | CC40: -121507788 | CD40: -121507788 | CE40: =-92767830 -> -92767830 | CF40: =CE40-CD40 -> 28739958 | CG40: =-92767830 -> -92767830 | CH40: -1.1319383e+08 | CI40: -1.1319383e+08 | CJ40: -1.1319383e+08 | CK40: -1.1319383e+08 | CL40: -1.1319383e+08 | CM40: -1.1319383e+08 | CN40: -1.1319383e+08
A41: Current Year Surplus | B41: 826227 | C41: =6949552-1115957-1389910-4000000 -> 443685 | D41: =393099-78620 -> 314479 | E41: 400110 | F41: 139938 | G41: -3983344.2 | H41: -3041115.7 | I41: -2488552.8 | J41: -4736380.4 | K41: -4858783.7 | L41: 0 | M41: 0 | N41: 0 | O41: 0 | P41: 0 | Q41: 0 | R41: =-1516666-5971670 -> -7488336 | S41: 505774.5 | T41: 406666.3 | U41: -3815962.5 | V41: -8530730.8 | W41: -31910424 | X41: 118400.58 | Y41: -1420935.9 | Z41: -4592770.6 | AA41: -2326297 | AB41: -3452331 | AC41: -2823447 | AD41: -5176705.6 | AE41: -21081681 | AF41: -604150.02 | AG41: -714008.62 | AH41: -6480948.6 | AI41: -4001296.7 | AJ41: -5033835.5 | AK41: -5423604.5 | AL41: -6142663.4 | AM41: -3494140 | AN41: -7198998.5 | AS41: -111592353 | AT41: -2512900.4 | AU41: 7115986.7 | AV41: 6210002.5 | AW41: 4876056.3 | AX41: 4689830.8 | AZ41: 1141779.5 | BA41: 7307591.5 | BB41: 11806863 | BC41: 11104460 | BD41: 14808286 | BE41: =11920040-2384008 -> 9536032 | BF41: -809352.05 | BG41: -438323.24 | BH41: -548672.08 | BI41: -246597.19 | BJ41: 585169.09 | BK41: 1135015.3 | BL41: 1741053.9 | BM41: -160769.23 | BN41: 1491229.6 | BO41: 1534461.6 | BP41: 1827781.9 | BQ41: 264768.63 | BR41: =19843602-639677 -> 19203925 | BS41: 295833.46 | BT41: 520505.82 | BU41: -169816.43 | BV41: 1884959.7 | BW41: 1571754 | BX41: 394143.8 | BY41: 1209379.2 | BZ41: 406710.31 | CA41: 2126515.9 | CB41: 3369037.9 | CC41: 6021983 | CD41: 2535725 | CE41: =10278058+434576-86915 -> 10625719 | CF41: =CE41-CD41 -> 8089994 | CG41: =10278058+434576-86915 -> 10625719 | CH41: 1461011.2 | CI41: 1802568.7 | CJ41: 3176068 | CK41: 4199379.1 | CL41: 4751194.3 | CM41: 5179996.5 | CN41: 4437741.8
A42: Statutory Reserves | B42: 35982721 | C42: 37372631 | D42: 37451251 | E42: 37551278 | F42: 37451251 | G42: 37551279 | H42: 37551279 | I42: 37551279 | J42: 37551279 | K42: 37551279 | L42: 0 | M42: 0 | N42: 0 | O42: 0 | P42: 0 | Q42: 0 | R42: 37551279 | S42: 37551279 | T42: 37551279 | U42: 37551279 | V42: 37551279 | W42: 37551279 | X42: 37551279 | Y42: 37551279 | Z42: 37551279 | AA42: 37551279 | AB42: 37551279 | AC42: 37551279 | AD42: 37551279 | AE42: 37551279 | AF42: 37551279 | AG42: 37551279 | AH42: 37551279 | AI42: 37551279 | AJ42: 37551279 | AK42: 37551279 | AL42: 37551279 | AM42: 37551279 | AN42: 37551279 | AS42: 37551279 | AT42: 37551279 | AU42: 37551279 | AV42: 37551279 | AW42: 37551279 | AX42: 37551279 | AZ42: 37551279 | BA42: 37551279 | BB42: 37551279 | BC42: 37551279 | BD42: 37551279 | BE42: 39935287 | BF42: 37551279 | BG42: 37551279 | BH42: 37551279 | BI42: 37551279 | BJ42: 37551279 | BK42: 37551279 | BL42: 37551279 | BM42: 37551279 | BN42: 37551279 | BO42: 37551279 | BP42: 37551279 | BQ42: 37551279 | BR42: 39935287 | BS42: 37551279 | BT42: 37551279 | BU42: 37551279 | BV42: 37551279 | BW42: 37551279 | BX42: 37551279 | BY42: 37551279 | BZ42: 37551279 | CA42: 37551279 | CB42: 37551279 | CC42: 37551279 | CD42: 37551279 | CE42: 40022202 | CF42: =CE42-CD42 -> 2470923 | CG42: 40022202 | CH42: 37551279 | CI42: 37551279 | CJ42: 37551279 | CK42: 37551279 | CL42: 37551279 | CM42: 37551279 | CN42: 37551279
A43: Other Reserves | B43: 8718475 | C43: 12718475 | D43: 12718475 | E43: 12718475 | F43: 27681479 | G43: 13758689 | H43: 29307124 | I43: 27016436 | J43: 12718474 | K43: 12718475 | L43: 0 | M43: 0 | N43: 0 | O43: 0 | P43: 0 | Q43: 0 | R43: 12718475 | S43: 12718475 | T43: 12718475 | U43: 12718475 | V43: 12718475 | W43: 12718475 | X43: 12718475 | Y43: 22584743 | Z43: 13349927 | AA43: 12718475 | AB43: 12718475 | AC43: 12718475 | AD43: 12718475 | AE43: 12718475 | AF43: 12637356 | AG43: 9397207.4 | AH43: 0 | AI43: 12718475 | AJ43: 0 | AK43: 0 | AL43: 0 | AM43: 0 | AN43: 0 | AS43: 0 | AT43: 0 | AU43: 0 | AV43: 0 | AW43: 0 | AX43: 0 | AZ43: 0 | BA43: 0 | BB43: 0 | BC43: 0 | BD43: 0 | BF43: 12718475 | BG43: 0 | BH43: 25015227 | BI43: 25799696 | BJ43: 26733131 | BK43: 26733131 | BL43: 26789066 | BM43: 26236993 | BN43: 26197060 | BO43: 27465932 | BP43: 28196755 | BQ43: 26830473 | BR43: 12718475 | BS43: 27815370 | BT43: 28207375 | BU43: 27517053 | BV43: 29198744 | BW43: 12718475 | BX43: 12718475 | BY43: 12718475 | BZ43: 12718475 | CA43: 29844925 | CB43: 12718475 | CC43: 12718475 | CD43: 12718475 | CE43: 12718475 | CF43: =CE43-CD43 -> 0 | CG43: 12718475 | CH43: 12718475 | CI43: 12718475 | CJ43: 12718475 | CK43: 12718475 | CL43: 12718475 | CM43: 12718475 | CN43: 12718475
A44: Revaluation Reserves | C44: 0 | E44: -3600070 | F44: 0 | G44: 0 | H44: 0 | I44: 0 | K44: 0 | L44: 0 | M44: 0 | N44: 0 | O44: 0 | P44: 0 | Q44: 0 | S44: 0 | T44: 0 | U44: 0 | V44: 0 | W44: 0 | X44: 0 | Y44: 0 | Z44: 0 | AA44: 0 | AB44: 0 | AC44: 0 | AD44: 0 | AF44: 0 | AG44: 0 | AH44: 12718475 | AI44: 0 | AJ44: 12718475 | AK44: 12718475 | AL44: 12718475 | AM44: 12718475 | AN44: 12718475 | AS44: 12718475 | AT44: 12718475 | AU44: 12718475 | AV44: 12718475 | AW44: 12718475 | AX44: 12718475 | AZ44: 12718475 | BA44: 12718475 | BB44: 12718475 | BC44: 12718475 | BD44: 12718475 | BE44: 12718475 | BF44: 0 | BG44: 12718475 | BH44: 0 | BI44: 0 | BJ44: 0 | BK44: 0 | BL44: 0 | BM44: 0 | BN44: 0 | BO44: 0 | BP44: 0 | BQ44: 0 | BS44: 0 | BT44: 0 | BU44: 0 | BV44: 0 | BW44: 0 | BX44: 0 | BY44: 0 | BZ44: 0 | CA44: 0 | CB44: 0 | CC44: 0 | CD44: 0 | CF44: =CE44-CD44 -> 0 | CH44: 0 | CI44: 0 | CJ44: 0 | CK44: 0 | CL44: 0 | CM44: 0 | CN44: 0
A45: Proposed Dividends | B45: 430140 | C45: 1115957 | E45: 1040215 | F45: 0 | G45: 0 | H45: 0 | I45: 0 | K45: 0 | L45: 0 | M45: 0 | N45: 0 | O45: 0 | P45: 0 | Q45: 0 | S45: 0 | T45: 0 | U45: 0 | V45: 0 | W45: 0 | X45: 0 | Y45: 0 | Z45: 0 | AA45: 0 | AB45: 0 | AC45: 0 | AD45: 0 | AF45: 0 | AG45: 0 | AH45: 0 | AI45: 0 | AJ45: 0 | AK45: 0 | AL45: 0 | AM45: 0 | AN45: 0 | AS45: 0 | AT45: 0 | AU45: 0 | AV45: 0 | AW45: 0 | AX45: 0 | AZ45: 0 | BA45: 0 | BB45: 0 | BC45: 0 | BD45: 0 | BF45: 0 | BG45: 0 | BH45: 0 | BI45: 0 | BJ45: 0 | BK45: 0 | BL45: 0 | BM45: 0 | BN45: 0 | BO45: 0 | BP45: 0 | BQ45: 0 | BS45: 0 | BT45: 0 | BU45: 0 | BV45: 0 | BW45: 0 | BX45: 0 | BY45: 0 | BZ45: 0 | CA45: 0 | CB45: 0 | CC45: 0 | CD45: 0 | CF45: =CE45-CD45 -> 0 | CH45: 0 | CI45: 0 | CJ45: 0 | CK45: 0 | CL45: 0 | CM45: 0 | CN45: 0
A46: Adjustment To Equity | C46: 0 | F46: 0 | G46: 0 | H46: 0 | I46: 0 | K46: 0 | L46: 0 | M46: 0 | N46: 0 | O46: 0 | P46: 0 | Q46: 0 | S46: 0 | T46: 0 | U46: 0 | V46: 0 | W46: 0 | X46: 0 | Y46: 0 | Z46: 0 | AA46: 0 | AB46: 0 | AC46: 0 | AD46: 0 | AF46: 0 | AG46: 0 | AH46: 0 | AI46: 0 | AJ46: 0 | AK46: 0 | AL46: 0 | AM46: 0 | AN46: 0 | AS46: 8231685.6 | AT46: 0 | AU46: 0 | AV46: 0 | AW46: 0 | AX46: 0 | AZ46: 0 | BA46: 0 | BB46: 0 | BC46: 0 | BD46: 0 | BF46: 0 | BG46: 0 | BH46: 0 | BI46: 0 | BJ46: 0 | BK46: 0 | BL46: 0 | BM46: 0 | BN46: 0 | BO46: 0 | BP46: 0 | BQ46: 0 | BS46: 0 | BT46: 0 | BU46: 0 | BV46: 0 | BW46: 0 | BX46: 0 | BY46: 0 | BZ46: 0 | CA46: 0 | CB46: 0 | CC46: 0 | CD46: 0 | CF46: =CE46-CD46 -> 0 | CH46: 0 | CI46: 0 | CJ46: 0 | CK46: 0 | CL46: 0 | CM46: 0 | CN46: 0
A47: Total Equity | B47: =SUM(B38:B46) -> 94690118 | C47: =SUM(C38:C46) -> 83271952 | D47: =SUM(D38:D46) -> 79242155 | E47: =SUM(E38:E46) -> 77812316 | F47: =SUM(F38:F46) -> 93565402 | G47: =SUM(G38:G46) -> 75549358 | H47: =SUM(H38:H46) -> 77006635 | I47: =SUM(I38:I46) -> 75274211 | ... CE47: =SUM(CE38:CE46) -> -15577310 | CF47: =CE47-CD47 -> 39331375 | CG47: =SUM(CG38:CG46) -> -15577310 | CH47: =SUM(CH38:CH46) -> -47613141 | CI47: =SUM(CI38:CI46) -> -47267284 | CJ47: =SUM(CJ38:CJ46) -> -45893784 | CK47: =SUM(CK38:CK46) -> -44841773 | CL47: =SUM(CL38:CL46) -> -44233758 | CM47: =SUM(CM38:CM46) -> -43804956 | CN47: =SUM(CN38:CN46) -> -44546911 | CO47: =SUM(CO38:CO46) -> 0
A48: Total Liabilities and Equity | B48: =B47+B37 -> 320889781 | C48: =C47+C37 -> 272305756 | D48: =D47+D37 -> 285464131 | E48: =E47+E37 -> 301184793 | F48: =F47+F37 -> 2.7577865e+08 | G48: =G47+G37 -> 3.0578939e+08 | H48: =H47+H37 -> 2.8619334e+08 | I48: =I47+I37 -> 2.717549e+08 | ... CE48: =CE47+CE37 -> 219787163 | CF48: =CE48-CD48 -> 30057154 | CG48: =CG47+CG37 -> 219787163 | CH48: =CH47+CH37 -> 1.7776269e+08 | CI48: =CI47+CI37 -> 1.7780477e+08 | CJ48: =CJ47+CJ37 -> 1.7098285e+08 | CK48: =CK47+CK37 -> 1.7086292e+08 | CL48: =CL47+CL37 -> 1.6995306e+08 | CM48: =CM47+CM37 -> 1.7527604e+08 | CN48: =CN47+CN37 -> 1.7638495e+08 | CO48: =CO47+CO37 -> 0
AS49: =AS26-AS48 -> 0 | AT49: =AT26-AT48 -> 0 | AU49: =AU26-AU48 -> 0 | AV49: =AV26-AV48 -> 0 | AW49: =AW26-AW48 -> 0 | AX49: =AX26-AX48 -> 0 | AY49: =AY26-AY48 -> 0 | AZ49: =AZ26-AZ48 -> 0 | ... BE49: =BE26-BE48 -> 1 | BR49: =BR48-BR26 -> -2 | BS49: =BS48-BS26 -> 0 | BT49: =BT48-BT26 -> 0 | BU49: =BU48-BU26 -> -0.90000001 | BV49: =BV48-BV26 -> 0 | BW49: =BW48-BW26 -> 0 | BX49: =BX48-BX26 -> 0 | BY49: =BY48-BY26 -> 0 | ... CE49: =CE48-CE26 -> 2 | CF49: =CE49-CD49 -> 2 | CG49: =CG48-CG26 -> 2 | CH49: =CH48-CH26 -> 0 | CI49: =CI48-CI26 -> 0 | CJ49: =CJ48-CJ26 -> 0 | CK49: =CK48-CK26 -> 0 | CL49: =CL48-CL26 -> 0 | CM49: =CM48-CM26 -> 0 | CN49: =CN48-CN26 -> 0 | CO49: =CO48-CO26 -> 0
B50: =B48-B26 -> -2 | C50: =C48-C26 -> -1 | D50: =D48-D26 -> 0 | E50: =E48-E26 -> 0 | F50: =D48-D26 -> 0 | G50: =F48-F26 -> 0.049999952 | H50: =G48-G26 -> 0 | I50: =H48-H26 -> 0 | J50: =I48-I26 -> 0 | K50: =J48-J26 -> 0 | L50: =K48-K26 -> 0 | M50: =L48-L26 -> 0 | N50: =M48-M26 -> 0 | ... S50: =R48-R26 -> 0.59999999 | T50: =T48-T26 -> 0 | U50: =U48-U26 -> 0 | V50: =V48-V26 -> 0 | W50: =W48-W26 -> 0 | X50: =X48-X26 -> 0 | Y50: =Y48-Y26 -> 0 | Z50: =Y48-Y26 -> 0 | AA50: =Z48-Z26 -> 0 | AB50: =AA48-AA26 -> 0 | CF50: =CE50-CD50 -> 0

Sheet Evolutitve SCI
B2: 2013 Audited | C2: Audited 2014 | D2: Audited 2015 | E2: Audited 2016 | F2: 42736 | G2: 42767 | H2: 42795 | I2: 42826 | J2: 42856 | K2: 42887 | L2: 42917 | M2: 42948 | N2: 42979 | O2: 43009 | P2: 43040 | Q2: 43070 | R2: Audit 2017 | S2: 43101 | T2: 43132 | U2: 43160 | V2: 43191 | W2: 43221 | X2: 43252 | Y2: 43282 | Z2: 43313 | AA2: 43344 | AB2: 43374 | AC2: 43405 | AD2: 43435 | AE2: 43466 | AF2: Audited 2018 | AG2: 43466 | AH2: 43497 | AI2: 43525 | AJ2: 43556 | AK2: 43586 | AL2: 43617 | AM2: 43647 | AN2: 43678 | AO2: 43709 | AP2: 43739 | AQ2: 43770 | AR2: 43800 | AS2: Auidted 2019 | AT2: 43831 | AU2: 43862 | AV2: 43891 | AW2: 43922 | AX2: 43952 | AY2: 43983 | AZ2: 44013 | BA2: 44044 | BB2: 44075 | BC2: 44105 | BD2: 44136 | BE2: 44166 | BF2: Audited 2020 | BG2: 44197 | BH2: 44228 | BI2: 44256 | BJ2: 44287 | BK2: 44317 | BL2: 44348 | BM2: 44378 | BN2: 44409 | BO2: 44440 | BP2: 44470 | BQ2: 44501 | BR2: 44531 | BS2: Audited 2021 | BT2: 44562 | BU2: 44593 | BV2: 44621 | BW2: 44652 | BX2: 44682 | BY2: 44713 | BZ2: 44743 | CA2: 44774 | CB2: 44805 | CC2: 44835 | CD2: 44866 | CE2: 44896 | CF2: Audited 2022 | CG2: Variances | CH2: Audited 2022 | CI2: 44927 | CJ2: 44958 | CK2: 44986 | CL2: 45017 | CM2: 45047 | CN2: 45078 | CO2: 45108
A3: Financial Income | B3: =B4+B7 -> 45996799 | C3: =C4+C7 -> 54375159 | D3: =D4+D7 -> 48595560 | E3: =E4+E7 -> 53989254 | F3: =F4+F7 -> 4232315.6 | G3: =G4+G7 -> 8563411.9 | H3: =H4+H7 -> 12434932 | I3: =I4+I7 -> 16148706 | ... AB3: =AB4+AB7 -> 18629345 | AC3: 21674260 | AD3: 24091900 | AE3: 24091900 | AF3: =AF4+AF7 -> 24282938 | AG3: =AG4+AG7 -> 484352.05 | AH3: =AH4+AH7 -> 586883.45 | AI3: =AI4+AI7 -> 2517771.5 | AJ3: =AJ4+AJ7 -> 2774906.4 | AK3: =AK4+AK7 -> 2886183.7 | AL3: =AL4+AL7 -> 2976988.7 | AM3: =AM4+AM7 -> 3640147.8 | ... CF3: =CF4+CF7 -> 25717356 | CG3: =CF3-CE3 -> 0.17 | CH3: =CH4+CH7 -> 25717356 | CI3: =CI4+CI7 -> 3262799.5 | CJ3: =CJ4+CJ7 -> 5776818 | CK3: =CK4+CK7 -> 9110763.5 | CL3: =CL4+CL7 -> 11470956 | CM3: =CM4+CM7 -> 13293140 | CN3: =CN4+CN7 -> 14978316 | CO3: =CO4+CO7 -> 15539423
A4: Financial Income From Loans Portfolio | B4: =SUM(B5:B6) -> 26629812 | C4: =SUM(C5:C6) -> 33720956 | D4: =SUM(D5:D6) -> 31919015 | E4: =SUM(E5:E6) -> 35153610 | F4: =SUM(F5:F6) -> 2793175.3 | G4: =SUM(G5:G6) -> 5647256.6 | H4: =SUM(H5:H6) -> 8610510.9 | I4: =SUM(I5:I6) -> 11276471 | ... AB4: =SUM(AB5:AB6) -> 14358650 | AC4: 17010028 | AD4: 18944497 | AE4: 18944497 | AF4: =AF5+AF6 -> 18223801 | AG4: =AG5+AG6 -> 386158.6 | AH4: =AH5+AH6 -> 384148.6 | AI4: =AI5+AI6 -> 2075992.9 | AJ4: =AJ5+AJ6 -> 2303470.3 | AK4: =AK5+AK6 -> 2402914.5 | AL4: =AL5+AL6 -> 2462600.6 | AM4: =AM5+AM6 -> 2963880.2 | ... CF4: =CF5+CF6 -> 18523663 | CG4: =CF4-CE4 -> -743887.57 | CH4: =CH5+CH6 -> 18523663 | CI4: =CI5+CI6 -> 2754256.8 | CJ4: =CJ5+CJ6 -> 4819209.5 | CK4: =CK5+CK6 -> 7604065.7 | CL4: =CL5+CL6 -> 9624921 | CM4: =CM5+CM6 -> 10020314 | CN4: =CN5+CN6 -> 10608632 | CO4: =CO5+CO6 -> 10948367
A5: Interest from Loans Portfolio | B5: 26629812 | C5: 32831263 | D5: 29010493 | E5: 34153522 | F5: 2541350.3 | G5: 5368816.4 | H5: 8291411 | I5: 10838487 | J5: 11420544 | K5: =11659081 -> 11659081 | R5: 18220126 | S5: 3349347.4 | T5: 6874118.8 | U5: 7455625.7 | V5: 7729074.3 | W5: 8050570.3 | X5: 8176809.5 | Y5: 8277293.4 | Z5: 9369594 | AA5: 10998176 | AB5: 13587714 | AC5: 16179875 | AD5: 18613489 | AF5: 18067672 | AG5: 314008.6 | AH5: 322048.6 | AI5: 1954396.5 | AJ5: 2180423.9 | AK5: 2279868.1 | AL5: 2329154.2 | AM5: 2802385.5 | AN5: 2906964.4 | AO5: 3277435.5 | AT5: 135158.58 | AU5: 229973.02 | AV5: 442819.19 | AW5: 464443.95 | AX5: 520041.95 | AY5: 672981.85 | BA5: 1119392.4 | BB5: 8234682.4 | BC5: 13615592 | BD5: 14195772 | BE5: 19554038 | BF5: 6826396 | BG5: 570980.43 | BH5: 1722009.8 | BI5: 2476006.2 | BJ5: 3919148.7 | BK5: 4935804.8 | BL5: 6338174.8 | BM5: 7295164.2 | BN5: 8282751.8 | BO5: 9228114.3 | BP5: 10281782 | BQ5: 11730040 | BR5: 12871953 | BS5: 12929353 | BT5: 1596459.6 | BU5: 2170273.3 | BV5: 3752634.6 | BW5: 5570810.6 | BX5: 7457810 | BY5: 7955855 | BZ5: 9281787.2 | CA5: 9836172.6 | CB5: 11632675 | CC5: 14563480 | CD5: 17901667 | CE5: 18523663 | CF5: 18523663 | CG5: =CF5-CE5 -> 0 | CH5: 18523663 | CI5: 2674471.8 | CJ5: 4676624.5 | CK5: 7413930.7 | CL5: 9397186 | CM5: 9776479 | CN5: 10352897 | CO5: 10690232
A6: Fees&Commision on Loan Portfolio | C6: =114723+586850+188120 -> 889693 | D6: 2908522 | E6: 1000088 | F6: 251825 | G6: 278440.2 | H6: 319100 | I6: 437983.3 | J6: 511428 | K6: =287980+313492+96170 -> 697642 | S6: 203477.4 | T6: 171458 | U6: 348210.85 | V6: 428009.75 | W6: 398317.43 | X6: 448171.77 | Y6: 462871.77 | Z6: 879571.77 | AA6: 541657.77 | AB6: 770936.08 | AC6: 830152.74 | AD6: 331008 | AF6: 156129 | AG6: 72150 | AH6: 62100 | AI6: 121596.43 | AJ6: 123046.43 | AK6: 123046.43 | AL6: 133446.43 | AM6: 161494.68 | AN6: 164494.68 | AO6: 166644.68 | AT6: 13750 | AU6: 19900 | AV6: 22400 | AW6: 23450 | AX6: 36700 | AY6: 76500 | BA6: 168900 | BB6: 235400 | BC6: 286350 | BD6: 358114 | BE6: 420514 | BF6: 1211724 | BG6: 310066.83 | BH6: 741194.34 | BI6: 1616714.6 | BJ6: 2247477.3 | BK6: 2923979.6 | BL6: 3445004.8 | BM6: 4262910 | BN6: 4575424.3 | BO6: 5114206.1 | BP6: 5590163.9 | BQ6: 6142077 | BR6: 7208654 | BT6: 603098.54 | BU6: 1469848.2 | BV6: 2195845.1 | BW6: 2602022.4 | BX6: 376070 | BY6: 388237.57 | BZ6: 413137.57 | CA6: 463137.57 | CB6: 532187.57 | CC6: 591987.57 | CD6: 669537.57 | CE6: 743887.57 | CG6: =CF6-CE6 -> -743887.57 | CI6: 79785 | CJ6: 142585 | CK6: 190135 | CL6: 227735 | CM6: 243835 | CN6: 255735 | CO6: 258135
A7: Financial Income from Investments | B7: =SUM(B8:B11) -> 19366987 | C7: =SUM(C8:C11) -> 20654203 | D7: =SUM(D8:D11) -> 16676545 | E7: =SUM(E8:E11) -> 18835644 | F7: =SUM(F8:F11) -> 1439140.3 | G7: =SUM(G8:G11) -> 2916155.3 | H7: =SUM(H8:H11) -> 3824420.7 | I7: =SUM(I8:I11) -> 4872235.2 | ... CF7: =SUM(CF8:CF11) -> 7193693 | CG7: =CF7-CE7 -> 743887.74 | CH7: =SUM(CH8:CH11) -> 7193693 | CI7: =SUM(CI8:CI11) -> 508542.67 | CJ7: =SUM(CJ8:CJ11) -> 957608.59 | CK7: =SUM(CK8:CK11) -> 1506697.9 | CL7: =SUM(CL8:CL11) -> 1846035.1 | CM7: =SUM(CM8:CM11) -> 3272826.3 | CN7: =SUM(CN8:CN11) -> 4369683.9 | CO7: =SUM(CO8:CO11) -> 4591055.7
A8: Government Securities | C8: 0 | E8: 0 | F8: 0 | G8: 0 | H8: 0 | I8: 0 | J8: 0 | K8: 0 | S8: 0 | T8: 0 | U8: 0 | V8: 0 | W8: 0 | X8: 0 | Y8: 0 | AC8: 0 | AD8: 0 | AG8: 0 | AH8: 0 | AI8: 0 | AJ8: 0 | AK8: 0 | AL8: 0 | AM8: 0 | AN8: 0 | AO8: 0 | AT8: 0 | AU8: 0 | AV8: 0 | AW8: 0 | AX8: 0 | AY8: 0 | BA8: 0 | BB8: 0 | BC8: 0 | BD8: 0 | BE8: 0 | BG8: 0 | BH8: 0 | BI8: 0 | BJ8: 0 | BK8: 0 | BL8: 0 | BM8: 0 | BN8: 0 | BO8: 0 | BP8: 0 | BQ8: 0 | BR8: 0 | BT8: 0 | BU8: 0 | BV8: 0 | BW8: 0 | BX8: 0 | BY8: 0 | BZ8: 0 | CA8: 0 | CB8: 0 | CC8: 0 | CD8: 0 | CE8: 0 | CG8: =CF8-CE8 -> 0 | CI8: 0 | CJ8: 0 | CK8: 0 | CL8: 0 | CM8: 0 | CN8: 0 | CO8: 0
A9: Deposits with Banks & other Financial Institutions | B9: 2381220 | C9: 595785 | D9: 1366790 | E9: 1851959 | F9: 0 | G9: 376777.54 | H9: 188388.77 | I9: 188388.77 | J9: 188388.77 | K9: 188388.77 | S9: 22387.36 | T9: 22387.36 | U9: 27255.65 | V9: 98971.56 | W9: 155090.06 | X9: 191449.66 | Y9: 0 | Z9: 127834.41 | AA9: 155090.06 | AB9: 155090.06 | AC9: 155090.06 | AD9: 163044.41 | AG9: 0 | AH9: 0 | AI9: 0 | AJ9: 0 | AK9: 0 | AL9: 0 | AM9: 0 | AN9: 0 | AO9: 0 | AT9: 0 | AU9: 0 | AV9: 0 | AW9: 0 | AX9: 0 | AY9: 0 | BA9: 0 | BB9: 0 | BC9: 0 | BD9: 0 | BE9: 0 | BG9: 0 | BH9: 0 | BI9: 0 | BJ9: 0 | BK9: 0 | BL9: 0 | BM9: 0 | BN9: 0 | BO9: 0 | BP9: 0 | BQ9: 0 | BR9: 0 | BS9: =36189+478187+64555 -> 578931 | BT9: 0 | BU9: 0 | BV9: 0 | BW9: 0 | BX9: 0 | BY9: 0 | BZ9: 0 | CA9: 0 | CB9: 0 | CC9: 0 | CD9: 0 | CE9: 0 | CG9: =CF9-CE9 -> 0 | CI9: 0 | CJ9: 0 | CK9: 0 | CL9: 0 | CM9: 0 | CN9: 0 | CO9: 0
A10: Other Investments | C10: =1726071-239557-3825-10500-9000 -> 1463189 | D10: 462867 | E10: 1127954 | F10: 0 | G10: 0 | H10: 244962 | I10: 244962 | J10: 244962 | K10: 244962 | S10: 0 | T10: 0 | U10: 0 | V10: 0 | W10: 36359.6 | X10: 0 | Y10: 63615.25 | Z10: 63615.25 | AA10: 1573214.6 | AB10: 1573214.6 | AC10: 1573214.6 | AD10: 1621268.1 | AG10: 0 | AH10: 0 | AI10: 0 | AJ10: 0 | AK10: 0 | AL10: 0 | AM10: 0 | AN10: 0 | AO10: 4299019.3 | AT10: 0 | AU10: 0 | AV10: 10836886 | AW10: 10836886 | AX10: 10836886 | AY10: 10836886 | BA10: 10836886 | BB10: 10836886 | BC10: 10836886 | BD10: 10836886 | BE10: 10836886 | BF10: 10836886 | BG10: 0 | BH10: 0 | BI10: 0 | BJ10: 478187.2 | BK10: 478187.2 | BL10: 478187.2 | BM10: 478187.2 | BN10: 478187.2 | BO10: 478187.2 | BP10: 478187.2 | BQ10: 478187.2 | BR10: 478187.2 | BT10: 0 | BU10: 0 | BV10: 0 | BW10: 109937.8 | BX10: 109937.8 | BY10: 286772.4 | BZ10: 747774.7 | CA10: 286772.4 | CB10: 739393.54 | CC10: 901831.34 | CD10: 925345.94 | CE10: 925391.78 | CF10: 243190 | CG10: =CF10-CE10 -> -682201.78 | CH10: 243190 | CI10: 0 | CJ10: 0 | CK10: 0 | CL10: 0 | CM10: 1182180.4 | CN10: 1927060.1 | CO10: 1978247.1
A11: Other Operating Income | B11: 16985767 | C11: =239557+3825+10500+9000+19222040-C6 -> 18595229 | D11: 14846888 | E11: 15855731 | F11: 1439140.3 | G11: 2539377.7 | H11: 3391070 | I11: 4438884.4 | J11: 4390882.3 | K11: =4590814+137900+7509+22893 -> 4759116 | R11: =923419+13153284 -> 14076703 | S11: 562706.33 | T11: 1466211.6 | U11: 1621778.9 | V11: 1761114.9 | W11: 2082584 | X11: 1972634.2 | Y11: 2120522.8 | Z11: 1773924.2 | AA11: 2265427.3 | AB11: 2542390 | AC11: 2935927.3 | AD11: 3363091.4 | AF11: 6059137 | AG11: 98193.45 | AH11: 202734.85 | AI11: 441778.58 | AJ11: 471436.1 | AK11: 483269.17 | AL11: 514388.04 | AM11: 676267.61 | AN11: 2787056.1 | AO11: 602544.09 | AT11: 21657.22 | AU11: 36820.54 | AV11: 85505.95 | AW11: 280782.88 | AX11: 495050.86 | AY11: 762460.27 | BA11: 1383936 | BB11: 1875845.9 | BC11: 2328187.6 | BD11: 2612366.6 | BE11: 3171949.9 | BF11: =14421755-BF10-BF6+1500 -> 2374645 | BG11: 2750 | BH11: 2750 | BI11: 47000 | BJ11: 97120 | BK11: 17120 | BL11: 52907 | BM11: 52907 | BN11: 52907 | BO11: 52907 | BP11: 52907 | BQ11: 52907.33 | BR11: 51108.71 | BS11: 7134262 | BT11: 500 | BU11: 1400 | BV11: 2500 | BW11: 2500 | BX11: 2569992.1 | BY11: 2810105.4 | BZ11: 3140857 | CA11: 3415473.2 | CB11: 3840615.5 | CC11: 4429793.3 | CD11: 4862019.8 | CE11: 5524413.5 | CF11: 6950503 | CG11: =CF11-CE11 -> 1426089.5 | CH11: 6950503 | CI11: 508542.67 | CJ11: 957608.59 | CK11: 1506697.9 | CL11: 1846035.1 | CM11: 2090645.9 | CN11: 2442623.8 | CO11: 2612808.5
A12: Financial Expenses | B12: =SUM(B13:B18) -> 18442033 | C12: =SUM(C13:C18) -> 15779774 | D12: =SUM(D13:D18) -> 12975878 | E12: =SUM(E13:E18) -> 16791656 | F12: =SUM(F13:F18) -> 302389.25 | G12: =SUM(G13:G18) -> 1609364.9 | H12: =SUM(H13:H18) -> 1206799.6 | I12: =SUM(I13:I18) -> 3344707.8 | ... CF12: =SUM(CF13:CF18) -> 1936065 | CG12: =CF12-CE12 -> -0.04 | CH12: =SUM(CH13:CH18) -> 1936065 | CI12: =SUM(CI13:CI18) -> 314225.1 | CJ12: =SUM(CJ13:CJ18) -> 661102.1 | CK12: =SUM(CK13:CK18) -> 692430.04 | CL12: =SUM(CL13:CL18) -> 704607.04 | CM12: =SUM(CM13:CM18) -> 438459.04 | CN12: =SUM(CN13:CN18) -> 443039.04 | CO12: =SUM(CO13:CO18) -> 473375.7
A13: Interest Expense on Deposits | B13: 13850551 | C13: =11067405+2038636 -> 13106041 | D13: 9728141 | E13: 11745789 | F13: 0 | G13: 0 | H13: 72000 | I13: 2029631.5 | J13: 2107631.5 | K13: =2936447+71880 -> 3008327 | S13: 0 | T13: 0 | U13: 0 | V13: 0 | W13: 23836.17 | X13: 23836.17 | Y13: 0 | Z13: 0 | AA13: 0 | AB13: 0 | AC13: 0 | AD13: 23836.17 | AG13: 0 | AH13: 0 | AI13: 0 | AJ13: 0 | AK13: 0 | AL13: 0 | AM13: 0 | AN13: 0 | AO13: 0 | AT13: 0 | AU13: 0 | AV13: 0 | AW13: 0 | AX13: 0 | AY13: 0 | BA13: 0 | BB13: 0 | BC13: 0 | BD13: 0 | BE13: 0 | BG13: 0 | BH13: 0 | BI13: 2776 | BJ13: 2776.03 | BK13: 2776 | BL13: 2776 | BM13: 2776.03 | BN13: 2776.03 | BO13: 2776.03 | BP13: 2776.03 | BQ13: 2776.03 | BR13: 2776.03 | BT13: 0 | BU13: 0 | BV13: 0 | BW13: 0 | BX13: 211770.01 | BY13: 0 | BZ13: 0 | CB13: 0 | CC13: 0 | CD13: 0 | CE13: 0 | CG13: =CF13-CE13 -> 0 | CI13: 0 | CJ13: 0 | CK13: 0 | CL13: 0 | CM13: 0 | CN13: 0 | CO13: 0
A14: Cost of External Borrowings | B14: 2151415 | C14: =191540+439562 -> 631102 | D14: 855130 | E14: 1183523 | F14: 60641.25 | G14: 142725.93 | H14: 231860.45 | I14: 231860.45 | J14: 260648 | K14: 260648 | R14: 767778 | S14: 0 | T14: 43345.04 | U14: 72132.22 | V14: 72132.22 | W14: 72132.22 | X14: 72132.22 | Y14: 72132.22 | Z14: 72132.22 | AA14: 52623.35 | AB14: 72132.22 | AC14: 72132.22 | AD14: 72132.22 | AG14: 0 | AH14: 0 | AI14: 3305707 | AJ14: 0 | AK14: 0 | AL14: 0 | AM14: 0 | AN14: 0 | AO14: 5116036.2 | AT14: 0 | AU14: 0 | AV14: 0 | AW14: 0 | AX14: 0 | AY14: 0 | BA14: 1503659 | BB14: 1503659 | BC14: 1503659 | BD14: 1503659 | BE14: 1503659 | BF14: 1503659 | BG14: 0 | BH14: 0 | BI14: 0 | BJ14: 0 | BK14: 0 | BL14: 0 | BM14: 0 | BN14: 0 | BO14: 0 | BP14: 0 | BQ14: 226563 | BR14: 0 | BS14: 226563 | BT14: 0 | BU14: 0 | BV14: 0 | BW14: 0 | BX14: 0 | BY14: 935006.01 | BZ14: 994424.01 | CA14: 935006.01 | CB14: 994424 | CC14: 994424 | CD14: 1118764.2 | CE14: 1118764.2 | CF14: 1118764 | CG14: =CF14-CE14 -> -0.24 | CH14: 1118764 | CI14: 211770.1 | CJ14: 211770.1 | CK14: 222288.04 | CL14: 222288.04 | CM14: 222288.04 | CN14: 222288.04 | CO14: 222288.04
A15: Dividend Expenses | E15: 590214 | F15: 0 | G15: 72000 | H15: 0 | I15: 0 | J15: 0 | K15: 0 | R15: 145720 | S15: 0 | T15: 0 | U15: 0 | V15: 0 | W15: 0 | X15: 0 | Y15: 0 | Z15: 0 | AA15: 0 | AB15: 0 | AC15: 0 | AD15: 0 | AG15: 0 | AH15: 0 | AI15: 0 | AJ15: 0 | AK15: 0 | AL15: 0 | AM15: 0 | AN15: 0 | AO15: 0 | AT15: 0 | AU15: 0 | AV15: 0 | AW15: 0 | AX15: 0 | AY15: 0 | BA15: 0 | BB15: 0 | BC15: 0 | BD15: 0 | BE15: 0 | BG15: 0 | BH15: 0 | BI15: 0 | BJ15: 0 | BK15: 0 | BL15: 0 | BM15: 0 | BN15: 0 | BO15: 0 | BP15: 0 | BQ15: 0 | BR15: 0 | BT15: 0 | BU15: 0 | BV15: 0 | BW15: 0 | BX15: 0 | BY15: 0 | BZ15: 0 | CA15: 0 | CB15: 0 | CC15: 0 | CD15: 0 | CE15: 0 | CG15: =CF15-CE15 -> 0 | CI15: 0 | CJ15: 0 | CK15: 0 | CL15: 0 | CM15: 0 | CN15: 0 | CO15: 0
A16: Other Financial Expense | C16: 2042631 | D16: 2392607 | E16: 733492 | F16: 71490 | G16: 0 | H16: 902939.1 | I16: 1083215.9 | J16: 1372493 | K16: 1307975 | R16: 2654015 | S16: 278166.42 | T16: 1540900.9 | U16: 1550498.4 | V16: 1552498.4 | W16: 1657219.9 | X16: 1784979 | Y16: 2070573.1 | Z16: 600324.96 | AA16: 2305834.7 | AB16: 2335356.9 | AC16: 2335356.9 | AD16: 2421478.3 | AF16: 3401675 | AG16: 52543.8 | AH16: 52543.8 | AI16: 52543.8 | AJ16: 52543.8 | AK16: 89710.8 | AL16: 89710.8 | AM16: 187198.8 | AN16: 187198.8 | AO16: 0 | AT16: 0 | AU16: 0 | AV16: 377400 | AW16: 377400 | AX16: 49870 | AY16: 49870 | BA16: 146350 | BB16: 146350 | BC16: 213774 | BD16: 228494 | BE16: 250494 | BF16: 213774 | BG16: 0 | BH16: 0 | BI16: 49221 | BJ16: 49221 | BK16: 49221 | BL16: 77750 | BM16: 77750 | BN16: 77750 | BO16: 77750 | BP16: 77750 | BQ16: 77750 | BR16: 77750 | BS16: 421216 | BT16: 305620 | BU16: 305620 | BV16: 305620 | BW16: 305620 | BX16: 578484.73 | BY16: 348311 | BZ16: 302987.29 | CA16: 348311 | CB16: 348311 | CC16: 348311 | CD16: 348311 | CE16: 348311 | CF16: 817301 | CG16: =CF16-CE16 -> 468990 | CH16: 817301 | CI16: 73369 | CJ16: 378989 | CK16: 378989 | CL16: 378989 | CM16: 73369 | CN16: 77949 | CO16: 77949
A17: Fees & Commision Expense | B17: 699121 | C17: 0 | F17: 170258 | G17: 0 | H17: 0 | I17: 0 | S17: 0 | T17: 0 | U17: 0 | V17: 0 | W17: 0 | X17: 0 | Y17: 204558 | Z17: 174558 | AA17: 364558 | AB17: 827158 | AC17: 827158 | AD17: 1181649 | AG17: 95500 | AH17: 125500 | AI17: 131000 | AJ17: 125500 | AK17: 125500 | AL17: 125500 | AM17: 125500 | AN17: 125500 | AO17: 246015.71 | AT17: 0 | AU17: 0 | AV17: 0 | AW17: 0 | AX17: 0 | AY17: 0 | BA17: 0 | BB17: 0 | BC17: 0 | BD17: 0 | BE17: 0 | BG17: 300 | BH17: 300 | BI17: 27120 | BJ17: 51909.96 | BK17: 64941.96 | BL17: 83554 | BM17: 88066 | BN17: 114766 | BO17: 137086 | BP17: 137086 | BQ17: 148036 | BR17: 329256.66 | BT17: 205243.33 | BU17: 205243.33 | BV17: 219723.33 | BW17: 227643.33 | BX17: 670000 | BY17: 281219.33 | BZ17: 348311 | CA17: 319689.29 | CB17: 319689.29 | CC17: 386129.29 | CD17: 408569.29 | CE17: 468989.8 | CG17: =CF17-CE17 -> -468989.8 | CI17: 29086 | CJ17: 70343 | CK17: 91153 | CL17: 103330 | CM17: 142802 | CN17: 142802 | CO17: 173138.66
A18: Other Expenses | B18: 1740946 | C18: 0 | E18: 2538638 | F18: 0 | G18: 1394639 | H18: 0 | I18: 0 | S18: 0 | T18: 0 | U18: 0 | V18: 0 | W18: 0 | X18: 0 | Y18: 0 | Z18: 1510248.2 | AA18: 0 | AB18: 0 | AC18: 0 | AD18: 0 | AF18: 2806015 | AG18: 0 | AH18: 0 | AI18: 0 | AJ18: 0 | AK18: 0 | AL18: 0 | AM18: 0 | AN18: 0 | AO18: 0 | AT18: 0 | AU18: 0 | AV18: 0 | AW18: 0 | AX18: 0 | AY18: 0 | BA18: 0 | BB18: 0 | BC18: 0 | BD18: 0 | BE18: 0 | BG18: 0 | BH18: 0 | BI18: 0 | BJ18: 0 | BK18: 0 | BL18: 0 | BM18: 0 | BN18: 0 | BO18: 0 | BP18: 0 | BQ18: 0 | BR18: 225923 | BT18: 0 | BU18: 211770 | BV18: 211770 | BW18: 0 | BX18: 0 | BY18: 0 | BZ18: 0 | CB18: 0 | CC18: 0 | CD18: 0 | CE18: 0 | CG18: =CF18-CE18 -> 0 | CI18: 0 | CJ18: 0 | CK18: 0 | CL18: 0 | CM18: 0 | CN18: 0 | CO18: 0
A19: Net Financial Income | B19: =B3-B12 -> 27554766 | C19: =C3-C12 -> 38595385 | D19: =D3-D12 -> 35619682 | E19: =E3-E12 -> 37197598 | F19: =F3-F12 -> 3929926.3 | G19: =G3-G12 -> 6954047 | H19: =H3-H12 -> 11228132 | I19: =I3-I12 -> 12803998 | ... CF19: =CF3-CF12 -> 23781291 | CG19: =CF19-CE19 -> 0.21 | CH19: =CH3-CH12 -> 23781291 | CI19: =CI3-CI12 -> 2948574.4 | CJ19: =CJ3-CJ12 -> 5115715.9 | CK19: =CK3-CK12 -> 8418333.5 | CL19: =CL3-CL12 -> 10766349 | CM19: =CM3-CM12 -> 12854681 | CN19: =CN3-CN12 -> 14535277 | CO19: =CO3-CO12 -> 15066047
A20: Allowance for Loan Loss | B20: =B21-B22 -> 0 | C20: =C21-C22 -> 2025688 | D20: =D21-D22 -> 3790859 | E20: =E21-E22 -> 616690 | F20: =F21-F22 -> 0 | G20: =G21-G22 -> 3979310.3 | H20: =H21-H22 -> 3835462.4 | I20: =I21-I22 -> 3835462.4 | ... AB20: =AB21-AB22 -> 0 | AC20: 0 | AD20: 0 | AE20: 0 | AF20: =AF21 -> 10805841 | AG20: =AG21 -> 0 | AH20: =AH21 -> 0 | AI20: =AI21 -> 0 | AJ20: =AJ21 -> 0 | AK20: =AK21 -> 0 | AL20: =AL21 -> 0 | AM20: =AM21 -> 0 | ... BR20: =BR21 -> 0 | BS20: =BS21+BS22 -> 0 | BT20: =BT21+BT22 -> 0 | BU20: =BU21+BU22 -> 0 | BV20: =BV21+BV22 -> 0 | BW20: =BW21+BW22 -> 0 | BX20: =BX21+BX22 -> 0 | BY20: =BY21+BY22 -> 0 | BZ20: =BZ21+BZ22 -> 0 | ... CF20: =CF21+CF22 -> 0 | CG20: =CF20-CE20 -> 0 | CH20: =CH21+CH22 -> 0 | CI20: =CI21+CI22 -> 0 | CJ20: =CJ21+CJ22 -> 0 | CK20: =CK21+CK22 -> 0 | CL20: =CL21+CL22 -> 0 | CM20: =CM21+CM22 -> 0 | CN20: =CN21+CN22 -> 0 | CO20: =CO21+CO22 -> 0
A21: Provision for Loan Losses | C21: =1149948+875740 -> 2025688 | D21: 3790859 | E21: 616690 | F21: 0 | G21: 3979310.3 | H21: 3835462.4 | I21: 3835462.4 | J21: 3541834 | K21: 3607139.5 | R21: 4307286 | S21: 803415.12 | T21: 1412453 | U21: 5613617.6 | V21: 10455059 | W21: 31791738 | X21: 0 | AC21: 0 | AD21: 0 | AF21: 10805841 | AT21: 1.1079151e+08 | AU21: 0 | AV21: 125826.96 | AW21: 124381.89 | AX21: 116799.8 | AY21: 123563.52 | BA21: 136424.35 | BB21: 140765.73 | BC21: 147676.17 | BD21: 147885.31 | BE21: 115031.75 | BF21: =-110782790+98055147 -> -12727643 | BG21: 0 | BH21: 0 | BI21: 0 | BJ21: 0 | BK21: 0 | BL21: 0 | BM21: 0 | BN21: 0 | BO21: 0 | BP21: 0 | BQ21: 0 | BR21: 0 | CG21: =CF21-CE21 -> 0 | CI21: 0 | CJ21: 0 | CK21: 0 | CL21: 0 | CM21: 0 | CN21: 0 | CO21: 0
A22: Value of Loans Recovered | C22: 0 | F22: 0 | G22: 0 | H22: 0 | I22: 0 | S22: 0 | T22: 0 | U22: 0 | V22: 0 | W22: 0 | X22: 0 | AC22: 0 | AD22: 0 | AT22: 0 | AU22: 0 | AV22: 0 | AW22: 0 | AX22: 0 | AY22: 0 | BA22: 0 | BB22: 0 | BC22: 0 | BD22: 0 | BE22: 0 | BG22: 0 | BH22: 0 | BI22: 0 | BJ22: 0 | BK22: 0 | BL22: 0 | BM22: 0 | BN22: 0 | BO22: 0 | BP22: 0 | BQ22: 0 | BR22: 0 | CG22: =CF22-CE22 -> 0 | CI22: 0 | CJ22: 0 | CK22: 0 | CL22: 0 | CM22: 0 | CN22: 0 | CO22: 0
A23: Operating Expeses | B23: =SUM(B24:B28) -> 20314717 | C23: =SUM(C24:C28) -> 26181005 | D23: =SUM(D24:D28) -> 29719577 | E23: =SUM(E24:E28) -> 35494235 | F23: =SUM(F24:F28) -> 3789988.4 | G23: =SUM(G24:G28) -> 6958080.9 | H23: =SUM(H24:H28) -> 10433785 | I23: =SUM(I24:I28) -> 12720234 | ... CF23: =SUM(CF24:CF28) -> 23346715 | CG23: =CF23-CE23 -> 2101149.2 | CH23: =SUM(CH24:CH28) -> 23346715 | CI23: =SUM(CI24:CI28) -> 1487563.2 | CJ23: =SUM(CJ24:CJ28) -> 3313147.3 | CK23: =SUM(CK24:CK28) -> 5242265.5 | CL23: =SUM(CL24:CL28) -> 6566970 | CM23: =SUM(CM24:CM28) -> 8103487 | CN23: =SUM(CN24:CN28) -> 9355280.1 | CO23: =SUM(CO24:CO28) -> 10628305
A24: Personel Expenses | B24: 10802000 | C24: 13258699 | D24: 15108365 | E24: 18089870 | F24: 2553507.1 | G24: 3896870.9 | H24: 5633522.2 | I24: 6879313.6 | J24: 8269237 | K24: 8346089 | R24: 17464508 | S24: 1180752 | T24: 2552086.5 | U24: 2672456.1 | V24: 2701716.1 | W24: 4884242 | X24: 4945825 | Y24: 4961005 | Z24: 8617143.4 | AA24: 8810543.4 | AB24: 12118026 | AC24: 13490209 | AD24: 16655609 | AE24: 16655609 | AF24: 16655609 | AG24: 749553.27 | AH24: 796453.27 | AI24: 2942690.9 | AJ24: 3909117.9 | AK24: 4867355 | AL24: 4881355 | AM24: 5645447 | AN24: 4953607 | AO24: 5797949.7 | AT24: 807134.33 | AU24: 2367503 | AV24: 3167917.3 | AW24: 3885851.5 | AX24: 4627142 | AY24: 4586962.1 | BA24: 6329509.9 | BB24: 7002906.9 | BC24: 7820484.4 | BD24: 8717632.2 | BE24: 9663212.2 | BF24: 9663212 | BG24: 1096414.3 | BH24: 1682577.4 | BI24: 2397930.9 | BJ24: 3729731.2 | BK24: 3951352.3 | BL24: 4727087 | BM24: 5353574 | BN24: 7427319 | BO24: 6261594.8 | BP24: 7670318.2 | BQ24: 8484010.1 | BR24: 11043897 | BS24: =11043897 -> 11043897 | BT24: 791191.75 | BU24: 912804.56 | BV24: 2406271.3 | BW24: 2490335.8 | BX24: 3735999.6 | BY24: 4583299.8 | BZ24: 5206099.5 | CA24: 5841999.5 | CB24: 6505268.9 | CC24: 7595085.3 | CD24: 8430816.9 | CE24: 9266761.1 | CF24: =9717331 -> 9717331 | CG24: =CF24-CE24 -> 450569.92 | CH24: =9717331 -> 9717331 | CI24: 650591.57 | CJ24: 1308183.1 | CK24: 1993135.7 | CL24: 2647227.3 | CM24: 3348094 | CN24: 4072895 | CO24: 4759246.1
A25: Governance Expenses | B25: 2558804 | C25: 3781681 | D25: 3696681 | E25: 4225138 | F25: 375788.06 | G25: 729257.06 | H25: 1464526.6 | I25: 2155750.6 | J25: 2173151 | K25: 2173151 | R25: 2921784 | S25: 254015 | T25: 358815.21 | U25: 565317.23 | V25: 566817.23 | W25: 933148.36 | X25: 1048148.4 | Y25: 1252632.4 | Z25: 1818939.6 | AA25: 1838639.6 | AB25: 2247605.1 | AC25: 2405536.1 | AD25: 2411436.1 | AF25: 2411436 | AG25: 23350 | AH25: 25350 | AI25: 564338.4 | AJ25: 626238.4 | AK25: 628138.4 | AL25: 642638.4 | AM25: 860213.4 | AN25: 871513.4 | AO25: 874813.4 | AT25: 21100 | AU25: 23100 | AV25: 25599.12 | AW25: 138728.96 | AX25: 509981.64 | AY25: 829845.69 | BA25: 1179175.7 | BB25: 1729090.1 | BC25: 1830104 | BD25: 1946753.6 | BE25: 2306950 | BF25: 2145871 | BG25: 174934.99 | BH25: 305952.99 | BI25: 666656.01 | BJ25: 867553.19 | BK25: 1131137.3 | BL25: 1339629.4 | BM25: 1537155.1 | BN25: 1990687.1 | BO25: 2130851.8 | BP25: 2348065.4 | BQ25: 2464243.4 | BR25: 2788142 | BS25: 3104342 | BT25: 49100 | BU25: 159250.24 | BV25: 421834.4 | BW25: 693818.84 | BX25: 1098376.8 | BY25: 1100086.3 | BZ25: 1359091.3 | CA25: 1470669.4 | CB25: 1511169.4 | CC25: 2040512.9 | CD25: 2229255 | CE25: 2555947.1 | CF25: 2163297 | CG25: =CF25-CE25 -> -392650.15 | CH25: 2163297 | CI25: 254748.01 | CJ25: 440556.65 | CK25: 551051.75 | CL25: 791988.76 | CM25: 892838.56 | CN25: 1019338.6 | CO25: 1279652.2
A26: Marketing Expenses | C26: 2685781 | D26: 1311825 | E26: 2073958 | F26: 92420 | G26: 593740 | H26: 845896.8 | I26: 1029050.8 | J26: 1254361 | K26: 1199891 | R26: 1774153 | S26: 36595 | T26: 40475 | U26: 40475 | V26: 40475 | W26: 71475 | X26: 70825 | Y26: 71085 | Z26: 72085 | AA26: 87285 | AB26: 90285 | AC26: 90715 | AD26: 93645 | AF26: 203215 | AG26: 0 | AH26: 0 | AI26: 22815 | AJ26: 25615 | AK26: 25615 | AL26: 25615 | AM26: 34875 | AN26: 43275 | AO26: 56595 | AT26: 0 | AU26: 0 | AV26: 0 | AW26: 0 | AX26: 0 | AY26: 0 | BA26: 41000 | BB26: 43000 | BC26: 111380 | BD26: 216430 | BE26: 444905 | BF26: 482855 | BG26: 28200 | BH26: 28200 | BI26: 68223 | BJ26: 109600 | BK26: 115600 | BL26: 137400 | BM26: 162200 | BN26: 187800 | BO26: 228500 | BP26: 235200 | BQ26: 248600 | BR26: 274200 | BS26: 543030 | BT26: 12800 | BU26: 12800 | BV26: 33000 | BW26: 54200 | BX26: 62300 | BY26: 70000 | BZ26: 80100 | CA26: 70000 | CB26: 109100 | CC26: 120800 | CD26: 129400 | CE26: 141700 | CF26: 449080 | CG26: =CF26-CE26 -> 307380 | CH26: 449080 | CI26: 2000 | CJ26: 54920 | CK26: 110140 | CL26: 172790 | CM26: 176790 | CN26: 308240 | CO26: 323640
A27: Depreciation and Amortization | B27: 861797 | C27: 1572032 | D27: 1301066 | E27: 2656400 | F27: 0 | G27: 244673.61 | H27: 382910.42 | I27: 527057.22 | J27: 658822 | K27: =790586 -> 790586 | R27: 1749694 | S27: 94741.62 | T27: 189483 | U27: 284224.86 | V27: 378967 | W27: 473708.1 | X27: 0 | Y27: 0 | Z27: 0 | AA27: 0 | AB27: 0 | AC27: 0 | AD27: 0 | AF27: 2329395 | AG27: 0 | AH27: 0 | AI27: 1979625 | AJ27: 0 | AK27: 0 | AL27: 0 | AM27: 0 | AN27: 0 | AO27: 0 | AT27: 0 | AU27: 0 | AV27: 0 | AW27: 0 | AX27: 0 | AY27: 0 | BA27: 0 | BB27: 0 | BC27: 0 | BD27: 0 | BE27: 0 | BF27: 1295691 | BG27: 0 | BH27: 0 | BI27: 0 | BJ27: 0 | BK27: 0 | BL27: 0 | BM27: 0 | BN27: 0 | BO27: 0 | BP27: 0 | BQ27: 0 | BR27: 0 | BS27: 934322 | BT27: 0 | BU27: 0 | BV27: 0 | BW27: 0 | BX27: 0 | BY27: 0 | BZ27: 0 | CA27: 0 | CB27: 0 | CC27: 0 | CD27: 0 | CE27: 0 | CF27: =765200+1082889 -> 1848089 | CG27: =CF27-CE27 -> 1848089 | CH27: =765200+1082889 -> 1848089 | CI27: 0 | CJ27: 0 | CK27: 0 | CL27: 0 | CM27: 0 | CN27: 0 | CO27: 0
A28: Administrative Expenses | B28: 6092116 | C28: 4882812 | D28: 8301640 | E28: 8448869 | F28: 768273.2 | G28: 1493539.3 | H28: 2106929.4 | I28: 2129061.5 | J28: 2642865 | K28: 2907902 | R28: 6483562 | S28: 1143922.8 | T28: 2227629.8 | U28: 2560119.8 | V28: 2604775.8 | W28: 2642138.8 | X28: 2724918.8 | Y28: 3713253.4 | Z28: 3941878.9 | AA28: 4400378.9 | AB28: 4391112.9 | AC28: 5276599.9 | AD28: 6408819.9 | AF28: 6751431 | AG28: 167555 | AH28: 301045 | AI28: 0 | AJ28: 2037188 | AK28: 2183700 | AL28: 2635774 | AM28: 2929577 | AN28: 3171561 | AO28: 3453232 | AT28: 143172 | AU28: 408991 | AV28: 574881 | AW28: 869198 | AX28: 1708829 | AY28: 2068756 | BA28: 3031216 | BB28: 3309451 | BC28: 3633075 | BD28: 4137825 | BE28: 4890850 | BF28: 6752191 | BG28: 393300 | BH28: 887247 | BI28: 1476466 | BJ28: 2177739 | BK28: 2454894 | BL28: 2811062 | BM28: 3126593.4 | BN28: 3748941.4 | BO28: 4543626.4 | BP28: 4397383 | BQ28: 4923451.4 | BR28: 5603189.4 | BS28: 5008851 | BT28: 540269.55 | BU28: 1313527.6 | BV28: 2522577.1 | BW28: 2628693.1 | BX28: 2585124.7 | BY28: 3728904.1 | BZ28: 4083164.1 | CA28: 4629408.1 | CB28: 4830393.1 | CC28: 5632791.3 | CD28: 5671471.1 | CE28: 9281157.6 | CF28: =7168918+2000000 -> 9168918 | CG28: =CF28-CE28 -> -112239.58 | CH28: =7168918+2000000 -> 9168918 | CI28: 580223.61 | CJ28: 1509487.5 | CK28: 2587938 | CL28: 2954964 | CM28: 3685764.5 | CN28: 3954806.5 | CO28: 4265767
A29: Net Operating Income | B29: =B19-B20-B23 -> 7240049 | C29: =C19-C20-C23 -> 10388692 | D29: =D19-D20-D23 -> 2109246 | E29: =E19-E20-E23 -> 1086673 | F29: =F19-F20-F23 -> 139937.97 | G29: =G19-G20-G23 -> -3983344.2 | H29: =H19-H20-H23 -> -3041115.7 | I29: =I19-I20-I23 -> -3751698.2 | ... CF29: =CF19-CF20-CF23 -> 434575.97 | CG29: =CF29-CE29 -> -2101149 | CH29: =CH19-CH20-CH23 -> 434575.97 | CI29: =CI19-CI20-CI23 -> 1461011.2 | CJ29: =CJ19-CJ20-CJ23 -> 1802568.6 | CK29: =CK19-CK20-CK23 -> 3176068 | CL29: =CL19-CL20-CL23 -> 4199379 | CM29: =CM19-CM20-CM23 -> 4751194.3 | CN29: =CN19-CN20-CN23 -> 5179996.5 | CO29: =CO19-CO20-CO23 -> 4437741.8
A30: Net Non operating Income/Expense | B30: =B31-B32 -> 0 | C30: =C31-C32 -> 0 | D30: =D31-D32 -> 0 | E30: =E31-E32 -> 0 | F30: =F31-F32 -> 0 | G30: =G31-G32 -> 0 | H30: =H31-H32 -> 0 | I30: =I31-I32 -> 1263145.3 | ... CF30: =CF31-CF32 -> 0 | CG30: =CF30-CE30 -> 0 | CH30: =CH31-CH32 -> 0 | CI30: =CI31-CI32 -> 0 | CJ30: =CJ31-CJ32 -> 0 | CK30: =CK31-CK32 -> 0 | CL30: =CL31-CL32 -> 0 | CM30: =CM31-CM32 -> 0 | CN30: =CN31-CN32 -> 0 | CO30: =CO31-CO32 -> 0
A31: Non Operating Income | C31: 0 | F31: 0 | G31: 0 | H31: 0 | I31: 1386618.3 | J31: 950812 | K31: 1520090 | S31: 209664 | T31: 336879 | U31: 217207.67 | V31: 152302.8 | W31: 162492.93 | AC31: 0 | AD31: 0 | CG31: =CF31-CE31 -> 0 | CI31: 0 | CJ31: 0 | CK31: 0 | CL31: 0 | CM31: 0 | CN31: 0 | CO31: 0
A32: Non Operating Expense | C32: 0 | F32: 0 | G32: 0 | H32: 0 | I32: 123473 | J32: 162355 | K32: 326355 | S32: 50200 | T32: 99200 | U32: 127200 | V32: 197200 | W32: 246200 | AC32: 0 | AD32: 0 | CG32: =CF32-CE32 -> 0 | CI32: 0 | CJ32: 0 | CK32: 0 | CL32: 0 | CM32: 0 | CN32: 0 | CO32: 0
A33: Net Income(Before Tax & Donations) | B33: =B29+B30 -> 7240049 | C33: =C29+C30 -> 10388692 | D33: =D29+D30 -> 2109246 | E33: =E29+E30 -> 1086673 | F33: =F29+F30 -> 139937.97 | G33: =G29+G30 -> -3983344.2 | H33: =H29+H30 -> -3041115.7 | I33: =I29+I30 -> -2488552.9 | ... CF33: =CF29+CF30 -> 434575.97 | CG33: =CF33-CE33 -> -2101149 | CH33: =CH29+CH30 -> 434575.97 | CI33: =CI29+CI30 -> 1461011.2 | CJ33: =CJ29+CJ30 -> 1802568.6 | CK33: =CK29+CK30 -> 3176068 | CL33: =CL29+CL30 -> 4199379 | CM33: =CM29+CM30 -> 4751194.3 | CN33: =CN29+CN30 -> 5179996.5 | CO33: =CO29+CO30 -> 4437741.8
A34: Taxes | B34: 666588 | D34: 1716148 | E34: 586535 | F34: 0 | G34: 0 | H34: 0 | I34: 0 | CG34: =CF34-CE34 -> 0 | CI34: 0 | CJ34: 0 | CK34: 0 | CL34: 0 | CM34: 0 | CN34: 0 | CO34: 0
A35: Net Income(After Tax Before Donations) | B35: =B33-B34 -> 6573461 | C35: =C33-C34 -> 10388692 | D35: =D33-D34 -> 393098 | E35: =E33-E34 -> 500138 | F35: =F33-F34 -> 139937.97 | G35: =G33-G34 -> -3983344.2 | H35: =H33-H34 -> -3041115.7 | I35: =I33-I34 -> -2488552.9 | ... CF35: =CF33-CF34 -> 434575.97 | CG35: =CF35-CE35 -> -2101149 | CH35: =CH33-CH34 -> 434575.97 | CI35: =CI33-CI34 -> 1461011.2 | CJ35: =CJ33-CJ34 -> 1802568.6 | CK35: =CK33-CK34 -> 3176068 | CL35: =CL33-CL34 -> 4199379 | CM35: =CM33-CM34 -> 4751194.3 | CN35: =CN33-CN34 -> 5179996.5 | CO35: =CO33-CO34 -> 4437741.8
A36: Donations | B36: 2999 | F36: 0 | G36: 0 | H36: 0 | I36: 0 | CG36: =CF36-CE36 -> 0 | CI36: 0 | CJ36: 0 | CK36: 0 | CL36: 0 | CM36: 0 | CN36: 0 | CO36: 0
A37: Net Income/(After Tax & Donations) | B37: =B35-B36 -> 6570462 | C37: =C35-C36 -> 10388692 | D37: =D35-D36 -> 393098 | E37: =E35-E36 -> 500138 | F37: =F35-F36 -> 139937.97 | G37: =G35-G36 -> -3983344.2 | H37: =H35-H36 -> -3041115.7 | I37: =I35-I36 -> -2488552.9 | ... CF37: =CF35-CF36 -> 434575.97 | CG37: =CF37-CE37 -> -2101149 | CH37: =CH35-CH36 -> 434575.97 | CI37: =CI35-CI36 -> 1461011.2 | CJ37: =CJ35-CJ36 -> 1802568.6 | CK37: =CK35-CK36 -> 3176068 | CL37: =CL35-CL36 -> 4199379 | CM37: =CM35-CM36 -> 4751194.3 | CN37: =CN35-CN36 -> 5179996.5 | CO37: =CO35-CO36 -> 4437741.8 | CP37: =CP35-CP36 -> 0
A39: Total Expenses | B39: =B12+B23 -> 38756750 | C39: =C12+C23 -> 41960779 | D39: =D12+D23 -> 42695455 | F39: =F12+F23 -> 4092377.6 | G39: =G12+G23 -> 8567445.8 | H39: =H12+H23 -> 11640585 | I39: =I12+I23 -> 16064942 | J39: =J12+J23 -> 18739208 | K39: =K12+K23 -> 19994569 | L39: =L12+L23 -> 0 | M39: =M12+M23 -> 0 | ... Q39: =Q12+Q23 -> 0 | R39: =R12+R21+R23 -> 38268500
B41: =B39-A39 -> #VALUE! | C41: =C39-B39 -> 3204029 | D41: =D39-E39 -> 42695455 | F41: =F39-D39 -> -38603077 | G41: =G39-E39 -> 8567445.8 | H41: =H39-F39 -> 7548207.4 | I41: =I39-G39 -> 7497495.8 | J41: =J39-H39 -> 7098623.5 | K41: =K39-I39 -> 3929627.4 | L41: =L39-J39 -> -18739208 | M41: =M39-K39 -> -19994569 | ... Q41: =Q39-O39 -> 0
C42: =C39/'Evolutive SFP'!C48 -> 0.15409435 | D42: =D39/'Evolutive SFP'!#REF! -> #REF! | F42: =F39/'Evolutive SFP'!G48 -> 0.013382994 | G42: =G39/'Evolutive SFP'!H48 -> 0.029935868 | H42: =H39/'Evolutive SFP'!I48 -> 0.042834867 | I42: =I39/'Evolutive SFP'!J48 -> 0.060848836 | J42: =J39/'Evolutive SFP'!K48 -> 0.07332291 | K42: =K39/'Evolutive SFP'!L48 -> #DIV/0! | L42: =L39/'Evolutive SFP'!M48 -> #DIV/0! | M42: =M39/'Evolutive SFP'!N48 -> #DIV/0! | ... P42: =P39/'Evolutive SFP'!Q48 -> #DIV/0!

Sheet Financials
B1: JUMUIKA Sacco Financial Performance
B2: Year | C2: 2013 Audited | D2: 2014 Audited | E2: Audited 2015 | F2: Audited 2016 | G2: 42736 | H2: 42767 | I2: 42795 | J2: 42826 | K2: 42856 | L2: 42887 | M2: 42917 | N2: 42948 | O2: 42979 | P2: 43009 | Q2: 43040 | R2: 43070 | S2: Audit 2017 | T2: 43101 | U2: 43132 | V2: 43160 | W2: 43191 | X2: 43221 | Y2: 43252 | Z2: 43282 | AA2: 43313 | AB2: 43344 | AC2: 43374 | AD2: 43405 | AE2: 43435 | AF2: Audited 2018 | AG2: 43466 | AH2: 43497 | AI2: 43525 | AJ2: 43556 | AK2: 43586 | AL2: 43617 | AM2: 43647 | AN2: 43678 | AO2: 43709 | AP2: 43739 | AQ2: 43770 | AR2: 43800 | AT2: 43831 | AU2: 43862 | AV2: 43891 | AW2: 43922 | AX2: 43952 | AY2: 43983 | AZ2: 44013 | BA2: 44044 | BB2: 44075 | BC2: 44105 | BD2: 44136 | BE2: 44166 | BF2: audited 2020 | BG2: 44197 | BH2: 44228 | BI2: 44256 | BJ2: 44287 | BK2: 44317 | BL2: 44348 | BM2: 44378 | BN2: 44409 | BO2: 44440 | BP2: 44470 | BQ2: 44501 | BR2: 44531 | BS2: Audited 2021 | BT2: 44562 | BU2: 44593 | BV2: 44621 | BW2: 44652 | BX2: 44682 | BY2: 44713 | BZ2: 44743 | CA2: 44774 | CB2: 44805 | CC2: 44835 | CD2: 44866 | CE2: 44896 | CF2: Audited 2022 | CG2: 44927 | CH2: 44958 | CI2: 44986 | CJ2: 45017 | CK2: 45047 | CL2: 45078 | CM2: 45108
A3: 1 | B3: Membership | D3: 1295
A4: 2 | B4: Total Assets | C4: ='Evolutive SFP'!B26 -> 320889783 | D4: ='Evolutive SFP'!C26 -> 272305757 | E4: ='Evolutive SFP'!D26 -> 285464131 | F4: ='Evolutive SFP'!E26 -> 301184793 | G4: ='Evolutive SFP'!F26 -> 2.7577865e+08 | H4: ='Evolutive SFP'!G26 -> 3.0578939e+08 | I4: ='Evolutive SFP'!H26 -> 2.8619334e+08 | J4: ='Evolutive SFP'!I26 -> 2.717549e+08 | ... CM4: ='Evolutive SFP'!CL26 -> 1.6995306e+08
A5: 3 | B5: Total Deposits | C5: ='Evolutive SFP'!B30 -> 186817277 | D5: ='Evolutive SFP'!C30 -> 170977491 | E5: ='Evolutive SFP'!D30 -> 170258234 | F5: ='Evolutive SFP'!E30 -> 174558061 | G5: ='Evolutive SFP'!F30 -> 1.5032662e+08 | H5: ='Evolutive SFP'!G30 -> 1.8015749e+08 | I5: ='Evolutive SFP'!H30 -> 1.7733028e+08 | J5: ='Evolutive SFP'!I30 -> 1.698913e+08 | ... CM5: ='Evolutive SFP'!CL30 -> 1.7953732e+08
A6: 3.1 | B6: Deposits-Members(BOSA) | C6: ='Evolutive SFP'!B29 -> 128848216 | D6: ='Evolutive SFP'!C29 -> 130204762 | E6: ='Evolutive SFP'!D29 -> 145890587 | F6: ='Evolutive SFP'!E29 -> 156610517 | G6: ='Evolutive SFP'!F29 -> 1.5671857e+08 | H6: ='Evolutive SFP'!G29 -> 1.5838375e+08 | I6: ='Evolutive SFP'!H29 -> 1.5896245e+08 | J6: ='Evolutive SFP'!I29 -> 1.3637148e+08 | ... CM6: ='Evolutive SFP'!CL29 -> 1.4451672e+08
A7: 3.2 | B7: Deposits-Customers(FOSA) | C7: =('Evolutive SFP'!B27+'Evolutive SFP'!B28) -> 57969061 | D7: =('Evolutive SFP'!C27+'Evolutive SFP'!C28) -> 40772729 | E7: =('Evolutive SFP'!D27+'Evolutive SFP'!D28) -> 24367647 | F7: =('Evolutive SFP'!E27+'Evolutive SFP'!E28) -> 17947544 | G7: =('Evolutive SFP'!F27+'Evolutive SFP'!F28) -> -6391944.5 | H7: =('Evolutive SFP'!G27+'Evolutive SFP'!G28) -> 21773737 | I7: =('Evolutive SFP'!H27+'Evolutive SFP'!H28) -> 18367826 | J7: =('Evolutive SFP'!I27+'Evolutive SFP'!I28) -> 33519823 | ... CM7: =('Evolutive SFP'!CL27+'Evolutive SFP'!CL28) -> 35020598
A8: 4 | B8: External Borrowing | C8: ='Evolutive SFP'!B36 -> 5711235 | D8: ='Evolutive SFP'!C36 -> 3146881 | E8: ='Evolutive SFP'!D36 -> 18495124 | F8: ='Evolutive SFP'!E36 -> 29110952 | G8: ='Evolutive SFP'!F36 -> 28512340 | H8: ='Evolutive SFP'!G36 -> 28010877 | I8: ='Evolutive SFP'!H36 -> 24962488 | J8: ='Evolutive SFP'!I36 -> 24962488 | ... CM8: ='Evolutive SFP'!CL36 -> 24033302
A10: 5 | B10: Share capital and Reserves
A11: 5.1 | B11: Core Capital | C11: =C14-C22-C26 -> 76173062 | D11: =D14-D22-D26 -> 63869079 | E11: =E14-E22-E26 -> 60755239 | F11: =F14-F22-F26 -> 58285185 | G11: =G14-G22-G26 -> 75078486 | H11: =H14-H22-H26 -> 57062442 | I11: =I14-I22-I26 -> 58519719 | J11: =J14-J22-J26 -> 56787295 | ... CM11: =CM14-CM22-CM26 -> -66978392
A12: 5.2 | B12: Institutional Capital | C12: =C11-C15 -> 72588562 | D12: =D11-D15 -> 54569437 | E12: =E11-E15 -> 50215354 | F12: =F11-F15 -> 46480908 | G12: =G11-G15 -> 63274209 | H12: =H11-H15 -> 45258165 | I12: =I11-I15 -> 45730481 | J12: =J11-J15 -> 43992356 | ... CM12: =CM11-CM15 -> -80917516
A14: 5.3 | B14: Total Capital | C14: =C15+C16+C17+C18+C19+C20+C21 -> 94690118 | D14: =D15+D16+D17+D18+D19+D20+D21 -> 83271952 | E14: =E15+E16+E17+E18+E19+E20+E21 -> 79242155 | F14: =F15+F16+F17+F18+F19+F20+F21 -> 77812316 | G14: =G15+G16+G17+G18+G19+G20+G21 -> 93565402 | H14: =H15+H16+H17+H18+H19+H20+H21 -> 75549358 | I14: =I15+I16+I17+I18+I19+I20+I21 -> 77006635 | J14: =J15+J16+J17+J18+J19+J20+J21 -> 75274211 | ... CM14: =CM15+CM16+CM17+CM18+CM19+CM20+CM21 -> -44233758
A15: 5.3.1 | B15: Members Share Capital | C15: ='Evolutive SFP'!B38 -> 3584500 | D15: ='Evolutive SFP'!C38 -> 9299642 | E15: ='Evolutive SFP'!D38 -> 10539885 | F15: ='Evolutive SFP'!E38 -> 11804277 | G15: ='Evolutive SFP'!F38 -> 11804277 | H15: ='Evolutive SFP'!G38 -> 11804277 | I15: ='Evolutive SFP'!H38 -> 12789238 | J15: ='Evolutive SFP'!I38 -> 12794938 | ... CM15: ='Evolutive SFP'!CL38 -> 13939124
A16: 5.3.2 | B16: Entrance Fees
A17: 5.3.3 | B17: Retained Earnings | C17: ='Evolutive SFP'!B40 -> 45148055 | D17: ='Evolutive SFP'!C40 -> 22321562 | E17: ='Evolutive SFP'!D40 -> 18218065 | F17: ='Evolutive SFP'!E40 -> 17898031 | G17: ='Evolutive SFP'!F40 -> 16488457 | H17: ='Evolutive SFP'!G40 -> 16418457 | I17: ='Evolutive SFP'!H40 -> 400110 | J17: ='Evolutive SFP'!I40 -> 400110 | ... CM17: ='Evolutive SFP'!CL40 -> -1.1319383e+08
A18: 5.3.4 | B18: Appropriation Account | C18: ='Evolutive SFP'!B41 -> 826227 | D18: ='Evolutive SFP'!C41 -> 443685 | E18: ='Evolutive SFP'!D41 -> 314479 | F18: ='Evolutive SFP'!E41 -> 400110 | G18: ='Evolutive SFP'!F41 -> 139938 | H18: ='Evolutive SFP'!G41 -> -3983344.2 | I18: ='Evolutive SFP'!H41 -> -3041115.7 | J18: ='Evolutive SFP'!I41 -> -2488552.8 | ... CM18: ='Evolutive SFP'!CL41 -> 4751194.3
A19: 5.3.5 | B19: Statutory Reserves | C19: ='Evolutive SFP'!B42 -> 35982721 | D19: ='Evolutive SFP'!C42 -> 37372631 | E19: ='Evolutive SFP'!D42 -> 37451251 | F19: ='Evolutive SFP'!E42 -> 37551278 | G19: ='Evolutive SFP'!F42 -> 37451251 | H19: ='Evolutive SFP'!G42 -> 37551279 | I19: ='Evolutive SFP'!H42 -> 37551279 | J19: ='Evolutive SFP'!I42 -> 37551279 | ... CM19: ='Evolutive SFP'!CL42 -> 37551279
A20: 5.3.6 | B20: Capital Reserves | C20: =('Evolutive SFP'!B43+'Evolutive SFP'!B44) -> 8718475 | D20: =('Evolutive SFP'!C43+'Evolutive SFP'!C44) -> 12718475 | E20: =('Evolutive SFP'!D43+'Evolutive SFP'!D44) -> 12718475 | F20: =('Evolutive SFP'!E43+'Evolutive SFP'!E44) -> 9118405 | G20: =('Evolutive SFP'!F43+'Evolutive SFP'!F44) -> 27681479 | H20: =('Evolutive SFP'!G43+'Evolutive SFP'!G44) -> 13758689 | I20: =('Evolutive SFP'!H43+'Evolutive SFP'!H44) -> 29307124 | J20: =('Evolutive SFP'!I43+'Evolutive SFP'!I44) -> 27016436 | ... CM20: =('Evolutive SFP'!CL43+'Evolutive SFP'!CL44) -> 12718475
A21: 5.3.7 | B21: Supplementary Capital & reserves | C21: =C22+C23 -> 430140 | D21: =D22+D23 -> 1115957 | E21: =E22+E23 -> 0 | F21: =F22+F23 -> 1040215 | G21: =G22+G23 -> 0 | H21: =H22+H23 -> 0 | I21: =I22+I23 -> 0 | J21: =J22+J23 -> 0 | ... CM21: =CM22+CM23 -> 0
A22: a | B22: Proposed Dividends | C22: ='Evolutive SFP'!B45 -> 430140 | D22: ='Evolutive SFP'!C45 -> 1115957 | E22: ='Evolutive SFP'!D45 -> 0 | F22: ='Evolutive SFP'!E45 -> 1040215 | G22: ='Evolutive SFP'!F45 -> 0 | H22: ='Evolutive SFP'!G45 -> 0 | I22: ='Evolutive SFP'!H45 -> 0 | J22: ='Evolutive SFP'!I45 -> 0 | ... CM22: ='Evolutive SFP'!CL45 -> 0
A23: b | B23: Risk Mgt Fund
A25: 6 | B25: Investments | C25: =C26+C27+C28 -> 23235649 | D25: =D26+D27+D28 -> 23582539 | E25: =E26+E27+E28 -> 24253235 | F25: =F26+F27+F28 -> 23630498 | G25: =G26+G27+G28 -> 19804399 | H25: =H26+H27+H28 -> 19804399 | I25: =I26+I27+I28 -> 27179981 | J25: =J26+J27+J28 -> 27179981 | ... CM25: =CM26+CM27+CM28 -> 22744634
A26: 6.1 | B26: Shares in Kusco,CIC,Coop Bank | C26: ='Evolutive SFP'!B12 -> 18086916 | D26: ='Evolutive SFP'!C12 -> 18286916 | E26: ='Evolutive SFP'!D12 -> 18486916 | F26: ='Evolutive SFP'!E12 -> 18486916 | G26: ='Evolutive SFP'!F12 -> 18486916 | H26: ='Evolutive SFP'!G12 -> 18486916 | I26: ='Evolutive SFP'!H12 -> 18486916 | J26: ='Evolutive SFP'!I12 -> 18486916 | ... CM26: ='Evolutive SFP'!CL12 -> 22744634
A27: 6.2 | B27: Equity Investments (at cost) | C27: ='Evolutive SFP'!B10 -> 0 | D27: ='Evolutive SFP'!C10 -> 0 | E27: ='Evolutive SFP'!D10 -> 0 | F27: ='Evolutive SFP'!E10 -> 0 | G27: ='Evolutive SFP'!F10 -> 1317483.1 | H27: ='Evolutive SFP'!G10 -> 1317483.1 | I27: ='Evolutive SFP'!H10 -> 1317483.1 | J27: ='Evolutive SFP'!I10 -> 1317483.1 | ... CM27: ='Evolutive SFP'!CL10 -> 0
A28: 6.3 | B28: Deposits in KUSCCO CFP | C28: ='Evolutive SFP'!B11 -> 5148733 | D28: ='Evolutive SFP'!C11 -> 5295623 | E28: ='Evolutive SFP'!D11 -> 5766319 | F28: ='Evolutive SFP'!E11 -> 5143582 | G28: ='Evolutive SFP'!F11 -> 0 | H28: ='Evolutive SFP'!G11 -> 0 | I28: ='Evolutive SFP'!H11 -> 7375581.5 | J28: ='Evolutive SFP'!I11 -> 7375581.5 | ... CM28: ='Evolutive SFP'!CL11 -> 0
A30: 7 | B30: Net Loans & Advances | C30: ='Evolutive SFP'!B13 -> 100772491 | D30: ='Evolutive SFP'!C13 -> 108738343 | E30: ='Evolutive SFP'!D13 -> 153940147 | F30: ='Evolutive SFP'!E13 -> 163589556 | G30: ='Evolutive SFP'!F13 -> 1.7133933e+08 | H30: ='Evolutive SFP'!G13 -> 1.7270349e+08 | I30: ='Evolutive SFP'!H13 -> 1.7451462e+08 | J30: ='Evolutive SFP'!I13 -> 1.6695465e+08 | ... CM30: ='Evolutive SFP'!CL13 -> 47955121
A31: 7.1 | B31: Gross Loans & advances | C31: ='Evolutive SFP'!B14 -> 103051094 | D31: ='Evolutive SFP'!C14 -> 111892686 | E31: ='Evolutive SFP'!D14 -> 157363020 | F31: ='Evolutive SFP'!E14 -> 167629119 | G31: ='Evolutive SFP'!F14 -> 1.7958764e+08 | H31: ='Evolutive SFP'!G14 -> 1.766828e+08 | I31: ='Evolutive SFP'!H14 -> 1.7835008e+08 | J31: ='Evolutive SFP'!I14 -> 170790111 | ... CM31: ='Evolutive SFP'!CL14 -> 1.0725968e+08
A32: 7.2 | B32: Allowance for loan losses | C32: ='Evolutive SFP'!B15 -> 2278603 | D32: ='Evolutive SFP'!C15 -> 3154343 | E32: ='Evolutive SFP'!D15 -> 3422873 | F32: ='Evolutive SFP'!E15 -> 4039563 | G32: ='Evolutive SFP'!F15 -> 8248306 | H32: ='Evolutive SFP'!G15 -> 3979310.3 | I32: ='Evolutive SFP'!H15 -> 3835462.4 | J32: ='Evolutive SFP'!I15 -> 3835462.4 | ... CM32: ='Evolutive SFP'!CL15 -> 59304557
B33: Non-performing loans | CF33: =11286078+2008953+63038754 -> 76333785 | CG33: =11286078+2008953+63038754 -> 76333785 | CH33: =11286078+2008953+63038754 -> 76333785 | CI33: =11286078+2008953+63038754 -> 76333785 | CJ33: =11286078+2008953+63038754 -> 76333785 | CK33: =11286078+2008953+63038754 -> 76333785 | CL33: =11286078+2008953+63038754 -> 76333785 | CM33: =11286078+2008953+63038754 -> 76333785
A34: 8 | B34: Non-Earning Assets | C34: ='Evolutive SFP'!B20+'Evolutive SFP'!B7 -> 67421987 | D34: ='Evolutive SFP'!C20+'Evolutive SFP'!C7 -> 51585499 | E34: ='Evolutive SFP'!D20+'Evolutive SFP'!D7 -> 41107208 | F34: ='Evolutive SFP'!E20+'Evolutive SFP'!E7 -> 64723026 | G34: ='Evolutive SFP'!F20+'Evolutive SFP'!F7 -> 52690477 | H34: ='Evolutive SFP'!G20+'Evolutive SFP'!G7 -> 60539199 | I34: ='Evolutive SFP'!H20+'Evolutive SFP'!H7 -> 55581784 | J34: ='Evolutive SFP'!I20+'Evolutive SFP'!I7 -> 56653813 | ... CM34: ='Evolutive SFP'!CL20+'Evolutive SFP'!CL7 -> 87184328
A35: 8.1 | B35: Property and Equipment | C35: ='Evolutive SFP'!B22 -> 3110877 | D35: ='Evolutive SFP'!C22 -> 4576955 | E35: ='Evolutive SFP'!D22 -> 9907043 | F35: ='Evolutive SFP'!E22 -> 14921476 | G35: ='Evolutive SFP'!F22 -> 20113390 | H35: ='Evolutive SFP'!G22 -> 14923330 | I35: ='Evolutive SFP'!H22 -> 15050807 | J35: ='Evolutive SFP'!I22 -> 14976884 | ... CM35: ='Evolutive SFP'!CL22 -> 24197403
A37: 9 | B37: Turnover | C37: =C38+C39+C40+C41 -> 45996799 | D37: =D38+D39+D40+D41 -> 54375159 | E37: =E38+E39+E40+E41 -> 53989254 | F37: =F38+F39+F40+F41 -> 4232315.6 | G37: =G38+G39+G40+G41 -> 4232315.6 | H37: =H38+H39+H40+H41 -> 8563411.9 | I37: =I38+I39+I40+I41 -> 12434932 | J37: =J38+J39+J40+J41 -> 16148706 | ... CM37: =CM38+CM39+CM40+CM41 -> 11470956
A38: 9.1 | B38: Loan Interest | C38: ='Evolutitve SCI'!B5 -> 26629812 | D38: ='Evolutitve SCI'!C5 -> 32831263 | E38: ='Evolutitve SCI'!E5 -> 34153522 | F38: ='Evolutitve SCI'!F5 -> 2541350.3 | G38: ='Evolutitve SCI'!F5 -> 2541350.3 | H38: ='Evolutitve SCI'!G5 -> 5368816.4 | I38: ='Evolutitve SCI'!H5 -> 8291411 | J38: ='Evolutitve SCI'!I5 -> 10838487 | K38: ='Evolutitve SCI'!J5 -> 11420544 | L38: ='Evolutitve SCI'!K5 -> 11659081 | M38: ='Evolutitve SCI'!L5 -> 0 | N38: ='Evolutitve SCI'!M5 -> 0 | ... CM38: ='Evolutitve SCI'!CL5 -> 9397186
A39: 9.2 | B39: Income from investments | C39: ='Evolutitve SCI'!B7 -> 19366987 | D39: ='Evolutitve SCI'!C7 -> 20654203 | E39: ='Evolutitve SCI'!E7 -> 18835644 | F39: ='Evolutitve SCI'!F7 -> 1439140.3 | G39: ='Evolutitve SCI'!F7 -> 1439140.3 | H39: ='Evolutitve SCI'!G7 -> 2916155.3 | I39: ='Evolutitve SCI'!H7 -> 3824420.7 | J39: ='Evolutitve SCI'!I7 -> 4872235.2 | K39: ='Evolutitve SCI'!J7 -> 4824233.1 | L39: ='Evolutitve SCI'!K7 -> 5192466.8 | M39: ='Evolutitve SCI'!L7 -> 0 | N39: ='Evolutitve SCI'!M7 -> 0 | ... CM39: ='Evolutitve SCI'!CL7 -> 1846035.1
A40: 9.3 | B40: Fees & Commissions | C40: ='Evolutitve SCI'!B6 -> 0 | D40: ='Evolutitve SCI'!C6 -> 889693 | E40: ='Evolutitve SCI'!E6 -> 1000088 | F40: ='Evolutitve SCI'!F6 -> 251825 | G40: ='Evolutitve SCI'!F6 -> 251825 | H40: ='Evolutitve SCI'!G6 -> 278440.2 | I40: ='Evolutitve SCI'!H6 -> 319100 | J40: ='Evolutitve SCI'!I6 -> 437983.3 | K40: ='Evolutitve SCI'!J6 -> 511428 | L40: ='Evolutitve SCI'!K6 -> 697642 | M40: ='Evolutitve SCI'!L6 -> 0 | N40: ='Evolutitve SCI'!M6 -> 0 | ... CM40: ='Evolutitve SCI'!CL6 -> 227735
A41: 9.4 | B41: Average yield on loans
A43: 10 | B43: Financial and Operating costs | C43: =SUM(C44:C47) -> 36316683 | D43: =SUM(D44:D47) -> 41960779 | E43: =SUM(E44:E47) -> 49747253 | F43: =SUM(F44:F47) -> 3922119.6 | G43: =SUM(G44:G47) -> 3922119.6 | H43: =SUM(H44:H47) -> 7172806.8 | I43: =SUM(I44:I47) -> 11640585 | J43: =SUM(J44:J47) -> 16064942 | ... CM43: =SUM(CM44:CM47) -> 7168247
A44: 10.1 | B44: Interest expense on deposits | C44: ='Evolutitve SCI'!B13+'Evolutitve SCI'!B16 -> 13850551 | D44: ='Evolutitve SCI'!C13+'Evolutitve SCI'!C16 -> 15148672 | E44: ='Evolutitve SCI'!E13+'Evolutitve SCI'!E16 -> 12479281 | F44: ='Evolutitve SCI'!F13+'Evolutitve SCI'!F16 -> 71490 | G44: ='Evolutitve SCI'!F13+'Evolutitve SCI'!F16 -> 71490 | H44: ='Evolutitve SCI'!G13+'Evolutitve SCI'!G16 -> 0 | I44: ='Evolutitve SCI'!H13+'Evolutitve SCI'!H16 -> 974939.1 | J44: ='Evolutitve SCI'!I13+'Evolutitve SCI'!I16 -> 3112847.4 | K44: ='Evolutitve SCI'!J13+'Evolutitve SCI'!J16 -> 3480124.5 | L44: ='Evolutitve SCI'!K13+'Evolutitve SCI'!K16 -> 4316302 | M44: ='Evolutitve SCI'!L13+'Evolutitve SCI'!L16 -> 0 | N44: ='Evolutitve SCI'!M13+'Evolutitve SCI'!M16 -> 0 | ... CM44: ='Evolutitve SCI'!CL13+'Evolutitve SCI'!CL16 -> 378989
A45: 10.2 | B45: Dividend expense on share capital | C45: ='Evolutitve SCI'!B15 -> 0 | D45: ='Evolutitve SCI'!C15 -> 0 | E45: ='Evolutitve SCI'!E15 -> 590214 | F45: ='Evolutitve SCI'!F15 -> 0 | G45: ='Evolutitve SCI'!F15 -> 0 | H45: ='Evolutitve SCI'!G15 -> 72000 | I45: ='Evolutitve SCI'!H15 -> 0 | J45: ='Evolutitve SCI'!I15 -> 0 | K45: ='Evolutitve SCI'!J15 -> 0 | L45: ='Evolutitve SCI'!K15 -> 0 | M45: ='Evolutitve SCI'!L15 -> 0 | N45: ='Evolutitve SCI'!M15 -> 0 | ... CM45: ='Evolutitve SCI'!CL15 -> 0
A46: 10.3 | B46: Interest expense on borrowed funds | C46: ='Evolutitve SCI'!B14 -> 2151415 | D46: ='Evolutitve SCI'!C14 -> 631102 | E46: ='Evolutitve SCI'!E14 -> 1183523 | F46: ='Evolutitve SCI'!F14 -> 60641.25 | G46: ='Evolutitve SCI'!F14 -> 60641.25 | H46: ='Evolutitve SCI'!G14 -> 142725.93 | I46: ='Evolutitve SCI'!H14 -> 231860.45 | J46: ='Evolutitve SCI'!I14 -> 231860.45 | K46: ='Evolutitve SCI'!J14 -> 260648 | L46: ='Evolutitve SCI'!K14 -> 260648 | M46: ='Evolutitve SCI'!L14 -> 0 | N46: ='Evolutitve SCI'!M14 -> 0 | ... CM46: ='Evolutitve SCI'!CL14 -> 222288.04
A47: 10.4 | B47: Opperating expenses | C47: ='Evolutitve SCI'!B23 -> 20314717 | D47: ='Evolutitve SCI'!C23 -> 26181005 | E47: ='Evolutitve SCI'!E23 -> 35494235 | F47: ='Evolutitve SCI'!F23 -> 3789988.4 | G47: ='Evolutitve SCI'!F23 -> 3789988.4 | H47: ='Evolutitve SCI'!G23 -> 6958080.9 | I47: ='Evolutitve SCI'!H23 -> 10433785 | J47: ='Evolutitve SCI'!I23 -> 12720234 | K47: ='Evolutitve SCI'!J23 -> 14998436 | L47: ='Evolutitve SCI'!K23 -> 15417619 | M47: ='Evolutitve SCI'!L23 -> 0 | N47: ='Evolutitve SCI'!M23 -> 0 | ... CM47: ='Evolutitve SCI'!CL23 -> 6566970

Sheet FORM 4
D1: 43160
B2: CLASSIFICATION | C2: NO. OF A/Cs | D2: OUTSTANDING LOAN PORTFOLIO(Kshs) | E2: REQUIRED PROVISION | F2: REQUIRED PROVISION AMOUNT(Kshs)
B3: Performing | C3: 762 | D3: 1.434445e+08 | E3: 0.01 | F3: =D3*E3 -> 1434445
B4: Watch | C4: 38 | D4: 2550318 | E4: 0.05 | F4: =D4*E4 -> 127515.9
B5: Substandard | C5: 54 | D5: 2280857.1 | E5: 0.25 | F5: =D5*E5 -> 570214.27
B6: Doubtful | C6: 44 | D6: 1789170.3 | E6: 0.5 | F6: =D6*E6 -> 894585.16
B7: Loss | C7: 311 | D7: 10933706 | E7: 1 | F7: =D7*E7 -> 10933706
B8: subtotal | C8: =SUM(C3:C7) -> 1209 | D8: =SUM(D3:D7) -> 1.6099855e+08 | E8: =SUM(E3:E7) -> 1.81 | F8: =SUM(F3:F7) -> 13960467 | H8: =SUM(D5:D7) -> 15003734
D11: 43252
B12: CLASSIFICATION | C12: NO. OF A/Cs | D12: OUTSTANDING LOAN PORTFOLIO(Kshs) | E12: REQUIRED PROVISION | F12: REQUIRED PROVISION AMOUNT(Kshs)
B13: Performing | E13: 0.01 | F13: =D13*E13 -> 0
B14: Watch | E14: 0.05 | F14: =D14*E14 -> 0
B15: Substandard | E15: 0.25 | F15: =D15*E15 -> 0
B16: Doubtful | E16: 0.5 | F16: =D16*E16 -> 0
B17: Loss | E17: 1 | F17: =D17*E17 -> 0
B18: subtotal | C18: =SUM(C13:C17) -> 0 | D18: =SUM(D13:D17) -> 0 | F18: =SUM(F13:F17) -> 0
E19: =SUM(D15:D17) -> 0
D21: 43344
B22: CLASSIFICATION | C22: NO. OF A/Cs | D22: OUTSTANDING LOAN PORTFOLIO(Kshs) | E22: REQUIRED PROVISION | F22: REQUIRED PROVISION AMOUNT(Kshs)
B23: Performing | C23: 1382 | D23: 1.4983048e+08 | E23: 0.01 | F23: =D23*E23 -> 1498304.8
B24: Watch | C24: 487 | D24: 19364168 | E24: 0.05 | F24: =D24*E24 -> 968208.42
B25: Substandard | C25: 335 | D25: 1609862.4 | E25: 0.25 | F25: =D25*E25 -> 402465.61
B26: Doubtful | C26: 105 | D26: 641664.07 | E26: 0.5 | F26: =D26*E26 -> 320832.03
B27: Loss | C27: 28 | D27: 417328.61 | E27: 1 | F27: =D27*E27 -> 417328.61
B28: GRAND TOTAL | C28: =SUM(C23:C27) -> 2337 | D28: =SUM(D23:D27) -> 1.718635e+08 | E28: 1.81 | F28: =SUM(F23:F27) -> 3607139.5
D31: 43435
B32: CLASSIFICATION | C32: NO. OF A/Cs | D32: OUTSTANDING LOAN PORTFOLIO(Kshs) | E32: REQUIRED PROVISION | F32: REQUIRED PROVISION AMOUNT(Kshs)
B33: Performing | E33: 0.01 | F33: =D33*E33 -> 0
B34: Watch | E34: 0.05 | F34: =D34*E34 -> 0
B35: Substandard | E35: 0.25 | F35: =D35*E35 -> 0
B36: Doubtful | E36: 0.5 | F36: =D36*E36 -> 0
B37: Loss | E37: 1 | F37: =D37*E37 -> 0
B38: subtotal | C38: =SUM(C33:C37) -> 0 | D38: =SUM(D33:D37) -> 0 | E38: 1.81 | F38: =SUM(F33:F37) -> 0
D40: Audited 2018
B41: CLASSIFICATION | C41: NO. OF A/Cs | D41: OUTSTANDING LOAN PORTFOLIO(Kshs) | E41: REQUIRED PROVISION | F41: REQUIRED PROVISION AMOUNT(Kshs)
B42: Performing | E42: 0.01 | F42: =D42*E42 -> 0
B43: Watch | E43: 0.05 | F43: =D43*E43 -> 0
B44: Substandard | E44: 0.25 | F44: =D44*E44 -> 0
B45: Doubtful | E45: 0.5 | F45: =D45*E45 -> 0
B46: Loss | E46: 1 | F46: =D46*E46 -> 0
B47: subtotal | C47: =SUM(C42:C46) -> 0 | D47: =SUM(D42:D46) -> 0 | E47: 1.81 | F47: =SUM(F42:F46) -> 0

Sheet CAELS
A1: JUMUIKA SACCO CAELS
D2: 2013 Audited | E2: 2014 Audited | F2: Audited 2015 | G2: 2016 Audited | H2: 42736 | I2: 42767 | J2: 42795 | K2: 42826 | L2: 42856 | M2: 42887 | N2: 42917 | O2: 42948 | P2: 42979 | Q2: 43009 | R2: 43040 | S2: 43070 | T2: Audit 2017
A3: CAPITAL ADEQUACY | B3: Core Capital | C3: 10 M | D3: =(('Evolutive SFP'!B38+'Evolutive SFP'!B39+'Evolutive SFP'!B40+'Evolutive SFP'!B41+'Evolutive SFP'!B42+'Evolutive SFP'!B43)-'Evolutive SFP'!B12)/1000000 -> 76.173062 | E3: =(('Evolutive SFP'!C38+'Evolutive SFP'!C39+'Evolutive SFP'!C40+'Evolutive SFP'!C41+'Evolutive SFP'!C42+'Evolutive SFP'!C43)-'Evolutive SFP'!C12)/1000000 -> 63.869079 | F3: =(('Evolutive SFP'!D38+'Evolutive SFP'!D39+'Evolutive SFP'!D40+'Evolutive SFP'!D41+'Evolutive SFP'!D42+'Evolutive SFP'!D43)-'Evolutive SFP'!D12)/1000000 -> 60.755239 | G3: =(('Evolutive SFP'!E38+'Evolutive SFP'!E39+'Evolutive SFP'!E40+'Evolutive SFP'!E41+'Evolutive SFP'!E42+'Evolutive SFP'!E43)-'Evolutive SFP'!E12)/1000000 -> 61.885255 | H3: =(('Evolutive SFP'!F38+'Evolutive SFP'!F39+'Evolutive SFP'!F40+'Evolutive SFP'!F41+'Evolutive SFP'!F42+'Evolutive SFP'!F43)-'Evolutive SFP'!F12)/1000000 -> 75.078486 | I3: =(('Evolutive SFP'!G38+'Evolutive SFP'!G39+'Evolutive SFP'!G40+'Evolutive SFP'!G41+'Evolutive SFP'!G42+'Evolutive SFP'!G43)-'Evolutive SFP'!G12)/1000000 -> 57.062442 | J3: =(('Evolutive SFP'!H38+'Evolutive SFP'!H39+'Evolutive SFP'!H40+'Evolutive SFP'!H41+'Evolutive SFP'!H42+'Evolutive SFP'!H43)-'Evolutive SFP'!H12)/1000000 -> 58.519719 | K3: =(('Evolutive SFP'!I38+'Evolutive SFP'!I39+'Evolutive SFP'!I40+'Evolutive SFP'!I41+'Evolutive SFP'!I42+'Evolutive SFP'!I43)-'Evolutive SFP'!I12)/1000000 -> 56.787295 | ... BX3: =(('Evolutive SFP'!BV38+'Evolutive SFP'!BV39+'Evolutive SFP'!BV40+'Evolutive SFP'!BV41+'Evolutive SFP'!BV42+'Evolutive SFP'!BV43)-'Evolutive SFP'!BV12)/1000000 -> -61.659581
B4: CCA | C4: Min 10% | D4: =D3/(('Evolutive SFP'!B26)/1000000) -> 0.23738076 | E4: =E3/(('Evolutive SFP'!C26)/1000000) -> 0.23454913 | F4: =F3/(('Evolutive SFP'!D26)/1000000) -> 0.21282968 | G4: =G3/(('Evolutive SFP'!E26)/1000000) -> 0.20547271 | H4: =H3/(('Evolutive SFP'!F26)/1000000) -> 0.27224184 | I4: =I3/(('Evolutive SFP'!G26)/1000000) -> 0.18660701 | J4: =J3/(('Evolutive SFP'!H26)/1000000) -> 0.20447618 | K4: =K3/(('Evolutive SFP'!I26)/1000000) -> 0.20896512 | ... BX4: =BX3/(('Evolutive SFP'!BV26)/1000000) -> -0.33323989
B5: CCD | C5: Min 8% | D5: =D3/('Evolutive SFP'!B30/1000000) -> 0.40774099 | E5: =E3/('Evolutive SFP'!C30/1000000) -> 0.37355256 | F5: =F3/('Evolutive SFP'!D30/1000000) -> 0.35684171 | G5: =G3/('Evolutive SFP'!E30/1000000) -> 0.35452533 | H5: =H3/('Evolutive SFP'!F30/1000000) -> 0.49943572 | I5: =I3/('Evolutive SFP'!G30/1000000) -> 0.31673644 | J5: =J3/('Evolutive SFP'!H30/1000000) -> 0.33000411 | K5: =K3/('Evolutive SFP'!I30/1000000) -> 0.33425663 | ... BX5: =BX3/('Evolutive SFP'!BV30/1000000) -> -0.33162207
B6: ICA | C6: Min 8% | D6: =((D3*1000000)-'Evolutive SFP'!B38)/'Evolutive SFP'!B26 -> 0.22621026 | E6: =((E3*1000000)-'Evolutive SFP'!C38)/'Evolutive SFP'!C26 -> 0.20039766 | F6: =((F3*1000000)-'Evolutive SFP'!D38)/'Evolutive SFP'!D26 -> 0.17590775 | G6: =((G3*1000000)-'Evolutive SFP'!E38)/'Evolutive SFP'!E26 -> 0.1662799 | H6: =((H3*1000000)-'Evolutive SFP'!F38)/'Evolutive SFP'!F26 -> 0.22943839 | I6: =((I3*1000000)-'Evolutive SFP'!G38)/'Evolutive SFP'!G26 -> 0.14800437 | J6: =((J3*1000000)-'Evolutive SFP'!H38)/'Evolutive SFP'!H26 -> 0.15978877 | K6: =((K3*1000000)-'Evolutive SFP'!I38)/'Evolutive SFP'!I26 -> 0.16188248 | ... BX6: =((BX3*1000000)-'Evolutive SFP'!BV38)/'Evolutive SFP'!BV26 -> -0.40764339
A7: ASSET QUALITY | B7: A/LNPL30
B8: NPL30
A9: EARNINGS | B9: ROA | E9: ='Evolutitve SCI'!C33/(('Evolutive SFP'!B26+'Evolutive SFP'!C26)/2) -> 0.035026197 | F9: ='Evolutitve SCI'!D33/(('Evolutive SFP'!C26+'Evolutive SFP'!D26)/2) -> 0.0075631404 | G9: ='Evolutitve SCI'!E33/(('Evolutive SFP'!D26+'Evolutive SFP'!E26)/2) -> 0.0037046791 | H9: ='Evolutitve SCI'!F33/(('Evolutive SFP'!E26+'Evolutive SFP'!F26)/2) -> 0.00048508435 | I9: ='Evolutitve SCI'!G33/(('Evolutive SFP'!F26+'Evolutive SFP'!G26)/2) -> -0.013698635 | J9: ='Evolutitve SCI'!H33/(('Evolutive SFP'!G26+'Evolutive SFP'!H26)/2) -> -0.010274339 | K9: ='Evolutitve SCI'!I33/(('Evolutive SFP'!H26+'Evolutive SFP'!I26)/2) -> -0.0089203719 | L9: ='Evolutitve SCI'!J33/(('Evolutive SFP'!I26+'Evolutive SFP'!J26)/2) -> -0.017680686 | ... BX9: ='Evolutitve SCI'!BV33/(('Evolutive SFP'!BU26+'Evolutive SFP'!BV26)/2) -> -0.0009021084
B10: Cost Income ratio | D10: ='Evolutitve SCI'!B23/'Evolutitve SCI'!B19 -> 0.73724876 | E10: ='Evolutitve SCI'!C23/'Evolutitve SCI'!C19 -> 0.67834548 | F10: ='Evolutitve SCI'!D23/'Evolutitve SCI'!D19 -> 0.83435829 | G10: ='Evolutitve SCI'!E23/'Evolutitve SCI'!E19 -> 0.95420772 | H10: ='Evolutitve SCI'!F23/'Evolutitve SCI'!F19 -> 0.96439171 | I10: ='Evolutitve SCI'!G23/'Evolutitve SCI'!G19 -> 1.0005801 | J10: ='Evolutitve SCI'!H23/'Evolutitve SCI'!H19 -> 0.92925389 | K10: ='Evolutitve SCI'!I23/'Evolutitve SCI'!I19 -> 0.99345797 | ... BX10: ='Evolutitve SCI'!BV23/'Evolutitve SCI'!BV19 -> 1.0325702
B11: Operating Expense ratio | D11: =('Evolutitve SCI'!B23+'Evolutitve SCI'!B12)/(('Evolutive SFP'!B26+'Evolutive SFP'!C26)/2) -> 0.13067108 | E11: =('Evolutitve SCI'!C23+'Evolutitve SCI'!C12)/(('Evolutive SFP'!C26+'Evolutive SFP'!D26)/2) -> 0.1504591 | F11: =('Evolutitve SCI'!D23+'Evolutitve SCI'!D12)/(('Evolutive SFP'!D26+'Evolutive SFP'!E26)/2) -> 0.14555709 | G11: =('Evolutitve SCI'!E23+'Evolutitve SCI'!E12)/(('Evolutive SFP'!E26+'Evolutive SFP'!F26)/2) -> 0.18124507 | H11: =('Evolutitve SCI'!F23+'Evolutitve SCI'!F12)/(('Evolutive SFP'!F26+'Evolutive SFP'!G26)/2) -> 0.014073599 | I11: =('Evolutitve SCI'!G23+'Evolutitve SCI'!G12)/(('Evolutive SFP'!G26+'Evolutive SFP'!H26)/2) -> 0.028944918 | J11: =('Evolutitve SCI'!H23+'Evolutitve SCI'!H12)/(('Evolutive SFP'!H26+'Evolutive SFP'!I26)/2) -> 0.041726397 | K11: =('Evolutitve SCI'!I23+'Evolutitve SCI'!I12)/(('Evolutive SFP'!I26+'Evolutive SFP'!J26)/2) -> 0.059969674 | ... BX11: =('Evolutitve SCI'!BV23+'Evolutitve SCI'!BV12)/(('Evolutive SFP'!BV26+'Evolutive SFP'!BW26)/2) -> 0.031678135
A12: LIQUIDITY | B12: MIN LIQ ratio | C12: Min 15% | D12: =('Evolutive SFP'!B4)/('Evolutive SFP'!B27+'Evolutive SFP'!B28+'Evolutive SFP'!B31+'Evolutive SFP'!B32+'Evolutive SFP'!B33+'Evolutive SFP'!B34+'Evolutive SFP'!B35) -> 1.4016204 | E12: =('Evolutive SFP'!C4)/('Evolutive SFP'!C27+'Evolutive SFP'!C28+'Evolutive SFP'!C31+'Evolutive SFP'!C32+'Evolutive SFP'!C33+'Evolutive SFP'!C34+'Evolutive SFP'!C35) -> 1.5761989 | F12: =('Evolutive SFP'!D4)/('Evolutive SFP'!D27+'Evolutive SFP'!D28+'Evolutive SFP'!D31+'Evolutive SFP'!D32+'Evolutive SFP'!D33+'Evolutive SFP'!D34+'Evolutive SFP'!D35) -> 1.6067326 | G12: =('Evolutive SFP'!E4)/('Evolutive SFP'!E27+'Evolutive SFP'!E28+'Evolutive SFP'!E31+'Evolutive SFP'!E32+'Evolutive SFP'!E33+'Evolutive SFP'!E34+'Evolutive SFP'!E35) -> 1.3355392 | H12: =('Evolutive SFP'!F4)/('Evolutive SFP'!F27+'Evolutive SFP'!F28+'Evolutive SFP'!F31+'Evolutive SFP'!F32+'Evolutive SFP'!F33+'Evolutive SFP'!F34+'Evolutive SFP'!F35) -> -10.585836 | I12: =('Evolutive SFP'!G4)/('Evolutive SFP'!G27+'Evolutive SFP'!G28+'Evolutive SFP'!G31+'Evolutive SFP'!G32+'Evolutive SFP'!G33+'Evolutive SFP'!G34+'Evolutive SFP'!G35) -> 1.2029153 | J12: =('Evolutive SFP'!H4)/('Evolutive SFP'!H27+'Evolutive SFP'!H28+'Evolutive SFP'!H31+'Evolutive SFP'!H32+'Evolutive SFP'!H33+'Evolutive SFP'!H34+'Evolutive SFP'!H35) -> 1.1859676 | K12: =('Evolutive SFP'!I4)/('Evolutive SFP'!I27+'Evolutive SFP'!I28+'Evolutive SFP'!I31+'Evolutive SFP'!I32+'Evolutive SFP'!I33+'Evolutive SFP'!I34+'Evolutive SFP'!I35) -> 0.62620751 | ... BX12: =('Evolutive SFP'!BV4)/('Evolutive SFP'!BV27+'Evolutive SFP'!BV28+'Evolutive SFP'!BV31+'Evolutive SFP'!BV32+'Evolutive SFP'!BV33+'Evolutive SFP'!BV34+'Evolutive SFP'!BV35) -> 0.15616048
B13: T/LIQ ratio | D13: =('Evolutive SFP'!B4+'Evolutive SFP'!B8)/('Evolutive SFP'!B30+'Evolutive SFP'!B31+'Evolutive SFP'!B32+'Evolutive SFP'!B33+'Evolutive SFP'!B34+'Evolutive SFP'!B35) -> 0.68792926 | E13: =('Evolutive SFP'!C4+'Evolutive SFP'!C8)/('Evolutive SFP'!C30+'Evolutive SFP'!C31+'Evolutive SFP'!C32+'Evolutive SFP'!C33+'Evolutive SFP'!C34+'Evolutive SFP'!C35) -> 0.59901309 | F13: =('Evolutive SFP'!D4+'Evolutive SFP'!D8)/('Evolutive SFP'!D30+'Evolutive SFP'!D31+'Evolutive SFP'!D32+'Evolutive SFP'!D33+'Evolutive SFP'!D34+'Evolutive SFP'!D35) -> 0.48726606 | G13: =('Evolutive SFP'!E4+'Evolutive SFP'!E8)/('Evolutive SFP'!E30+'Evolutive SFP'!E31+'Evolutive SFP'!E32+'Evolutive SFP'!E33+'Evolutive SFP'!E34+'Evolutive SFP'!E35) -> 0.38049168 | H13: =('Evolutive SFP'!F4+'Evolutive SFP'!F8)/('Evolutive SFP'!F30+'Evolutive SFP'!F31+'Evolutive SFP'!F32+'Evolutive SFP'!F33+'Evolutive SFP'!F34+'Evolutive SFP'!F35) -> 0.33668536 | I13: =('Evolutive SFP'!G4+'Evolutive SFP'!G8)/('Evolutive SFP'!G30+'Evolutive SFP'!G31+'Evolutive SFP'!G32+'Evolutive SFP'!G33+'Evolutive SFP'!G34+'Evolutive SFP'!G35) -> 0.35873512 | J13: =('Evolutive SFP'!H4+'Evolutive SFP'!H8)/('Evolutive SFP'!H30+'Evolutive SFP'!H31+'Evolutive SFP'!H32+'Evolutive SFP'!H33+'Evolutive SFP'!H34+'Evolutive SFP'!H35) -> 0.31016343 | K13: =('Evolutive SFP'!I4+'Evolutive SFP'!I8)/('Evolutive SFP'!I30+'Evolutive SFP'!I31+'Evolutive SFP'!I32+'Evolutive SFP'!I33+'Evolutive SFP'!I34+'Evolutive SFP'!I35) -> 0.28678661 | ... BX13: =('Evolutive SFP'!BV4+'Evolutive SFP'!BV8)/('Evolutive SFP'!BV30+'Evolutive SFP'!BV31+'Evolutive SFP'!BV32+'Evolutive SFP'!BV33+'Evolutive SFP'!BV34+'Evolutive SFP'!BV35) -> 0.1460444
B14: EB ratio | C14: Max 25% | D14: ='Evolutive SFP'!B36/'Evolutive SFP'!B26 -> 0.01779812 | E14: ='Evolutive SFP'!C36/'Evolutive SFP'!C26 -> 0.011556425 | F14: ='Evolutive SFP'!D36/'Evolutive SFP'!D26 -> 0.06478966 | G14: ='Evolutive SFP'!E36/'Evolutive SFP'!E26 -> 0.096654787 | H14: ='Evolutive SFP'!F36/'Evolutive SFP'!F26 -> 0.10338849 | I14: ='Evolutive SFP'!G36/'Evolutive SFP'!G26 -> 0.091601863 | J14: ='Evolutive SFP'!H36/'Evolutive SFP'!H26 -> 0.087222464 | K14: ='Evolutive SFP'!I36/'Evolutive SFP'!I26 -> 0.091856624 | ... BX14: ='Evolutive SFP'!BV36/'Evolutive SFP'!BV26 -> 0.13951483
B15: LA to TA ratio | D15: ='Evolutive SFP'!B4/'Evolutive SFP'!B26 -> 0.40027698 | E15: ='Evolutive SFP'!C4/'Evolutive SFP'!C26 -> 0.32230741 | F15: ='Evolutive SFP'!D4/'Evolutive SFP'!D26 -> 0.23547508 | G15: ='Evolutive SFP'!E4/'Evolutive SFP'!E26 -> 0.1669553 | H15: ='Evolutive SFP'!F4/'Evolutive SFP'!F26 -> 0.11583365 | I15: ='Evolutive SFP'!G4/'Evolutive SFP'!G26 -> 0.17247917 | J15: ='Evolutive SFP'!H4/'Evolutive SFP'!H26 -> 0.1046832 | K15: ='Evolutive SFP'!I4/'Evolutive SFP'!I26 -> 0.080988945 | ... BX15: ='Evolutive SFP'!BV4/'Evolutive SFP'!BV26 -> 0.034646015
A16: STRUCTURE | B16: NEA ratio | C16: Max 10% | D16: =('Evolutive SFP'!B7+'Evolutive SFP'!B20)/'Evolutive SFP'!B26 -> 0.21010948 | E16: =('Evolutive SFP'!C7+'Evolutive SFP'!C20)/'Evolutive SFP'!C26 -> 0.18943962 | F16: =('Evolutive SFP'!D7+'Evolutive SFP'!D20)/'Evolutive SFP'!D26 -> 0.14400131 | G16: =('Evolutive SFP'!E7+'Evolutive SFP'!E20)/'Evolutive SFP'!E26 -> 0.21489473 | H16: =('Evolutive SFP'!F7+'Evolutive SFP'!F20)/'Evolutive SFP'!F26 -> 0.19106075 | I16: =('Evolutive SFP'!G7+'Evolutive SFP'!G20)/'Evolutive SFP'!G26 -> 0.19797678 | J16: =('Evolutive SFP'!H7+'Evolutive SFP'!H20)/'Evolutive SFP'!H26 -> 0.19421062 | K16: =('Evolutive SFP'!I7+'Evolutive SFP'!I20)/'Evolutive SFP'!I26 -> 0.20847393 | ... BX16: =('Evolutive SFP'!BV7+'Evolutive SFP'!BV20)/'Evolutive SFP'!BV26 -> 0.77248418
B17: LB ratio | C17: Max 5% | D17: ='Evolutive SFP'!B20/'Evolutive SFP'!B26 -> 0.046772228 | E17: ='Evolutive SFP'!C20/'Evolutive SFP'!C26 -> 0.038030294 | F17: ='Evolutive SFP'!D20/'Evolutive SFP'!D26 -> 0.082131324 | G17: ='Evolutive SFP'!E20/'Evolutive SFP'!E26 -> 0.13327344 | H17: ='Evolutive SFP'!F20/'Evolutive SFP'!F26 -> 0.077534181 | I17: ='Evolutive SFP'!G20/'Evolutive SFP'!G26 -> 0.12273509 | J17: ='Evolutive SFP'!H20/'Evolutive SFP'!H26 -> 0.10478798 | K17: ='Evolutive SFP'!I20/'Evolutive SFP'!I26 -> 0.11285208 | ... BX17: ='Evolutive SFP'!BV20/'Evolutive SFP'!BV26 -> 0.72222419
B18: PI to Deposit ratio | C18: Max 40% | D18: ='Evolutive SFP'!B12/'Evolutive SFP'!B30 -> 0.096816078 | E18: ='Evolutive SFP'!C12/'Evolutive SFP'!C30 -> 0.10695511 | F18: ='Evolutive SFP'!D12/'Evolutive SFP'!D30 -> 0.10858163 | G18: ='Evolutive SFP'!E12/'Evolutive SFP'!E30 -> 0.10590697 | H18: ='Evolutive SFP'!F12/'Evolutive SFP'!F30 -> 0.12297832 | I18: ='Evolutive SFP'!G12/'Evolutive SFP'!G30 -> 0.10261531 | J18: ='Evolutive SFP'!H12/'Evolutive SFP'!H30 -> 0.10425132 | K18: ='Evolutive SFP'!I12/'Evolutive SFP'!I30 -> 0.10881614 | ... BX18: ='Evolutive SFP'!BV12/'Evolutive SFP'!BV30 -> 0.12129781
B19: PI to CC ratio | C19: Max 5% | D19: ='Evolutive SFP'!B12/(CAELS!D3*1000000) -> 0.23744504 | E19: ='Evolutive SFP'!C12/(CAELS!E3*1000000) -> 0.28631877 | F19: ='Evolutive SFP'!D12/(CAELS!F3*1000000) -> 0.30428513 | G19: ='Evolutive SFP'!E12/(CAELS!G3*1000000) -> 0.29872893 | H19: ='Evolutive SFP'!F12/(CAELS!H3*1000000) -> 0.24623453 | I19: ='Evolutive SFP'!G12/(CAELS!I3*1000000) -> 0.32397695 | J19: ='Evolutive SFP'!H12/(CAELS!J3*1000000) -> 0.31590917 | K19: ='Evolutive SFP'!I12/(CAELS!K3*1000000) -> 0.32554669 | ... BX19: ='Evolutive SFP'!BV12/(CAELS!BX3*1000000) -> -0.36577122
B20: Gross loans/TA | D20: ='Evolutive SFP'!B14/'Evolutive SFP'!B26 -> 0.32114171 | E20: ='Evolutive SFP'!C14/'Evolutive SFP'!C26 -> 0.41090826 | F20: ='Evolutive SFP'!D14/'Evolutive SFP'!D26 -> 0.55125322 | G20: ='Evolutive SFP'!E14/'Evolutive SFP'!E26 -> 0.55656568 | H20: ='Evolutive SFP'!F14/'Evolutive SFP'!F26 -> 0.65120209 | I20: ='Evolutive SFP'!G14/'Evolutive SFP'!G26 -> 0.57779245 | J20: ='Evolutive SFP'!H14/'Evolutive SFP'!H26 -> 0.62318042 | K20: ='Evolutive SFP'!I14/'Evolutive SFP'!I26 -> 0.62847113 | ... BX20: ='Evolutive SFP'!BV14/'Evolutive SFP'!BV26 -> 0.62314149
A21: FUNDING MIX | B21: Total Deposits/Total Assets | D21: ='Evolutive SFP'!B30/'Evolutive SFP'!B26 -> 0.58218518 | E21: ='Evolutive SFP'!C30/'Evolutive SFP'!C26 -> 0.6278879 | F21: ='Evolutive SFP'!D30/'Evolutive SFP'!D26 -> 0.59642601 | G21: ='Evolutive SFP'!E30/'Evolutive SFP'!E26 -> 0.5795713 | H21: ='Evolutive SFP'!F30/'Evolutive SFP'!F26 -> 0.54509885 | I21: ='Evolutive SFP'!G30/'Evolutive SFP'!G26 -> 0.58915547 | J21: ='Evolutive SFP'!H30/'Evolutive SFP'!H26 -> 0.61961707 | K21: ='Evolutive SFP'!I30/'Evolutive SFP'!I26 -> 0.62516371 | ... BX21: ='Evolutive SFP'!BV30/'Evolutive SFP'!BV26 -> 1.0048785
B22: BOSA Deposits/Total Assets | D22: ='Evolutive SFP'!B29/'Evolutive SFP'!B26 -> 0.40153418 | E22: ='Evolutive SFP'!C29/'Evolutive SFP'!C26 -> 0.47815648 | F22: ='Evolutive SFP'!D29/'Evolutive SFP'!D26 -> 0.51106451 | G22: ='Evolutive SFP'!E29/'Evolutive SFP'!E26 -> 0.51998149 | H22: ='Evolutive SFP'!F29/'Evolutive SFP'!F26 -> 0.56827665 | I22: ='Evolutive SFP'!G29/'Evolutive SFP'!G26 -> 0.51795046 | J22: ='Evolutive SFP'!H29/'Evolutive SFP'!H26 -> 0.55543728 | K22: ='Evolutive SFP'!I29/'Evolutive SFP'!I26 -> 0.50181792 | ... BX22: ='Evolutive SFP'!BV29/'Evolutive SFP'!BV26 -> 0.8499739
B23: FOSA Deposits/Total Assets | D23: =('Evolutive SFP'!B27+'Evolutive SFP'!B28)/'Evolutive SFP'!B26 -> 0.180651 | E23: =('Evolutive SFP'!C27+'Evolutive SFP'!C28)/'Evolutive SFP'!C26 -> 0.14973142 | F23: =('Evolutive SFP'!D27+'Evolutive SFP'!D28)/'Evolutive SFP'!D26 -> 0.085361502 | G23: =('Evolutive SFP'!E27+'Evolutive SFP'!E28)/'Evolutive SFP'!E26 -> 0.059589808 | H23: =('Evolutive SFP'!F27+'Evolutive SFP'!F28)/'Evolutive SFP'!F26 -> -0.023177807 | I23: =('Evolutive SFP'!G27+'Evolutive SFP'!G28)/'Evolutive SFP'!G26 -> 0.071205013 | J23: =('Evolutive SFP'!H27+'Evolutive SFP'!H28)/'Evolutive SFP'!H26 -> 0.064179783 | K23: =('Evolutive SFP'!I27+'Evolutive SFP'!I28)/'Evolutive SFP'!I26 -> 0.12334579 | ... BX23: =('Evolutive SFP'!BV27+'Evolutive SFP'!BV28)/'Evolutive SFP'!BV26 -> 0.15490463
A24: GROWTH RATIOS | B24: Total Assets | E24: =(Financials!D4-Financials!C4)/Financials!C4 -> -0.15140409 | F24: =(Financials!E4-Financials!D4)/Financials!D4 -> 0.048322056 | G24: =(Financials!F4-Financials!E4)/Financials!E4 -> 0.055070534 | H24: =(Financials!G4-Financials!F4)/Financials!F4 -> -0.084353997 | I24: =(Financials!H4-Financials!G4)/Financials!G4 -> 0.10882181 | J24: =(Financials!I4-Financials!H4)/Financials!H4 -> -0.064083484 | K24: =(Financials!J4-Financials!I4)/Financials!I4 -> -0.050449933 | L24: =(Financials!K4-Financials!J4)/Financials!J4 -> -0.02848505 | ... BX24: =(Financials!BW4-Financials!BV4)/Financials!BV4 -> -0.033566847
B25: Total Deposits | D25: =Financials!D5/Financials!C5-1 -> -0.084787586 | E25: =Financials!#REF!/Financials!D5-1 -> #REF! | F25: =Financials!#REF!/Financials!E5-1 -> #REF! | G25: =Financials!#REF!/Financials!F5-1 -> #REF! | H25: =Financials!#REF!/Financials!G5-1 -> #REF! | I25: =Financials!#REF!/Financials!H5-1 -> #REF! | J25: =Financials!#REF!/Financials!I5-1 -> #REF! | K25: =Financials!#REF!/Financials!J5-1 -> #REF! | L25: =Financials!#REF!/Financials!K5-1 -> #REF! | ... BX25: =Financials!#REF!/Financials!BW5-1 -> #REF!
B26: BOSA Deposits | D26: =Financials!D6/Financials!C6-1 -> 0.010528248 | E26: =Financials!#REF!/Financials!D6-1 -> #REF! | F26: =Financials!#REF!/Financials!E6-1 -> #REF! | G26: =Financials!#REF!/Financials!F6-1 -> #REF! | H26: =Financials!#REF!/Financials!G6-1 -> #REF! | I26: =Financials!#REF!/Financials!H6-1 -> #REF! | J26: =Financials!#REF!/Financials!I6-1 -> #REF! | K26: =Financials!#REF!/Financials!J6-1 -> #REF! | L26: =Financials!#REF!/Financials!K6-1 -> #REF! | ... BX26: =Financials!#REF!/Financials!BW6-1 -> #REF!
B27: FOSA Deposits | D27: =Financials!D7/Financials!C7-1 -> -0.29664672 | E27: =Financials!#REF!/Financials!D7-1 -> #REF! | F27: =Financials!#REF!/Financials!E7-1 -> #REF! | G27: =Financials!#REF!/Financials!F7-1 -> #REF! | H27: =Financials!#REF!/Financials!G7-1 -> #REF! | I27: =Financials!#REF!/Financials!H7-1 -> #REF! | J27: =Financials!#REF!/Financials!I7-1 -> #REF! | K27: =Financials!#REF!/Financials!J7-1 -> #REF! | L27: =Financials!#REF!/Financials!K7-1 -> #REF! | ... BX27: =Financials!#REF!/Financials!BW7-1 -> #REF!
B28: Total Loans & advances | D28: =Financials!D31/Financials!C31-1 -> 0.085798138 | E28: =Financials!#REF!/Financials!D31-1 -> #REF! | F28: =Financials!#REF!/Financials!E31-1 -> #REF! | G28: =Financials!#REF!/Financials!F31-1 -> #REF! | H28: =Financials!#REF!/Financials!G31-1 -> #REF! | I28: =Financials!#REF!/Financials!H31-1 -> #REF! | J28: =Financials!#REF!/Financials!I31-1 -> #REF! | K28: =Financials!#REF!/Financials!J31-1 -> #REF! | L28: =Financials!#REF!/Financials!K31-1 -> #REF! | ... BX28: =Financials!#REF!/Financials!BW31-1 -> #REF!
B29: Core capital | D29: =Financials!D11/Financials!C11-1 -> -0.1615267 | E29: =Financials!#REF!/Financials!D11-1 -> #REF! | F29: =Financials!#REF!/Financials!E11-1 -> #REF! | G29: =Financials!#REF!/Financials!F11-1 -> #REF! | H29: =Financials!#REF!/Financials!G11-1 -> #REF! | I29: =Financials!#REF!/Financials!H11-1 -> #REF! | J29: =Financials!#REF!/Financials!I11-1 -> #REF! | K29: =Financials!#REF!/Financials!J11-1 -> #REF! | L29: =Financials!#REF!/Financials!K11-1 -> #REF! | ... BX29: =Financials!#REF!/Financials!BW11-1 -> #REF!
B30: Turnover | D30: =Financials!D37/Financials!C37-1 -> 0.18215094 | E30: =Financials!#REF!/Financials!D37-1 -> #REF! | F30: =Financials!#REF!/Financials!E37-1 -> #REF! | G30: =Financials!#REF!/Financials!F37-1 -> #REF! | H30: =Financials!#REF!/Financials!G37-1 -> #REF! | I30: =Financials!#REF!/Financials!H37-1 -> #REF! | J30: =Financials!#REF!/Financials!I37-1 -> #REF! | K30: =Financials!#REF!/Financials!J37-1 -> #REF! | L30: =Financials!#REF!/Financials!K37-1 -> #REF! | ... BX30: =Financials!#REF!/Financials!BW37-1 -> #REF!
B31: Membership
B32: Expenses | D32: ='Evolutitve SCI'!C39/'Evolutitve SCI'!B39-1 -> 0.082670219 | E32: ='Evolutitve SCI'!#REF!/'Evolutitve SCI'!C39-1 -> #REF! | F32: ='Evolutitve SCI'!#REF!/'Evolutitve SCI'!D39-1 -> #REF! | G32: ='Evolutitve SCI'!#REF!/'Evolutitve SCI'!E39-1 -> #REF! | H32: ='Evolutitve SCI'!#REF!/'Evolutitve SCI'!F39-1 -> #REF! | I32: ='Evolutitve SCI'!#REF!/'Evolutitve SCI'!G39-1 -> #REF! | J32: ='Evolutitve SCI'!#REF!/'Evolutitve SCI'!H39-1 -> #REF! | K32: ='Evolutitve SCI'!#REF!/'Evolutitve SCI'!I39-1 -> #REF! | L32: ='Evolutitve SCI'!#REF!/'Evolutitve SCI'!J39-1 -> #REF! | ... BX32: ='Evolutitve SCI'!#REF!/'Evolutitve SCI'!BV39-1 -> #REF!
A33: Efficiency Ratios | B33: FinCost-Deposits/Avg Deposits | E33: =Financials!D44/('Evolutive SFP'!B29+'Evolutive SFP'!C29)/2 -> 0.02923856 | F33: =Financials!E44/('Evolutive SFP'!C29+'Evolutive SFP'!D29)/2 -> 0.022599586 | G33: =Financials!F44/('Evolutive SFP'!D29+'Evolutive SFP'!E29)/2 -> 0.00011816486 | H33: =Financials!G44/('Evolutive SFP'!E29+'Evolutive SFP'!F29)/2 -> 0.00011408133 | I33: =Financials!H44/('Evolutive SFP'!F29+'Evolutive SFP'!G29)/2 -> 0 | J33: =Financials!I44/('Evolutive SFP'!G29+'Evolutive SFP'!H29)/2 -> 0.0015360812 | K33: =Financials!J44/('Evolutive SFP'!H29+'Evolutive SFP'!I29)/2 -> 0.005270047 | L33: =Financials!K44/('Evolutive SFP'!I29+'Evolutive SFP'!J29)/2 -> 0.0058374242 | ... BX33: =Financials!BW44/('Evolutive SFP'!BU29+'Evolutive SFP'!BV29)/2 -> 0.00048511435
B34: FinCost-Shares/Avg Share capital | E34: =Financials!D45/('Evolutive SFP'!B38+'Evolutive SFP'!C38)/2 -> 0 | F34: =Financials!E45/('Evolutive SFP'!C38+'Evolutive SFP'!D38)/2 -> 0.014874699 | G34: =Financials!F45/('Evolutive SFP'!D38+'Evolutive SFP'!E38)/2 -> 0 | H34: =Financials!G45/('Evolutive SFP'!E38+'Evolutive SFP'!F38)/2 -> 0 | I34: =Financials!H45/('Evolutive SFP'!F38+'Evolutive SFP'!G38)/2 -> 0.001524871 | J34: =Financials!I45/('Evolutive SFP'!G38+'Evolutive SFP'!H38)/2 -> 0 | K34: =Financials!J45/('Evolutive SFP'!H38+'Evolutive SFP'!I38)/2 -> 0 | L34: =Financials!K45/('Evolutive SFP'!I38+'Evolutive SFP'!J38)/2 -> 0 | ... BX34: =Financials!BW45/('Evolutive SFP'!BU38+'Evolutive SFP'!BV38)/2 -> 0
B35: FinCost-Ext Loans/Avg Ext Loans | E35: =Financials!D46/(Financials!C31+Financials!D31)/2 -> 0.001468063 | F35: =Financials!E46/(Financials!D31+Financials!E31)/2 -> 0.0021977677 | G35: =Financials!F46/(Financials!E31+Financials!F31)/2 -> 9.3296487e-05 | H35: =Financials!G46/(Financials!F31+Financials!G31)/2 -> 8.7324775e-05 | I35: =Financials!H46/(Financials!G31+Financials!H31)/2 -> 0.00020030561 | J35: =Financials!I46/(Financials!H31+Financials!I31)/2 -> 0.00032653377 | K35: =Financials!J46/(Financials!I31+Financials!J31)/2 -> 0.00033204491 | L35: =Financials!K46/(Financials!J31+Financials!K31)/2 -> 0.00038092029 | ... BX35: =Financials!BW46/(Financials!BV31+Financials!BW31)/2 -> 0
B36: OpEx/Average Total Assets | E36: =Financials!D47/(Financials!C4+Financials!D4)/2 -> 0.02206777 | F36: =Financials!E47/(Financials!D4+Financials!E4)/2 -> 0.031817991 | G36: =Financials!F47/(Financials!E4+Financials!F4)/2 -> 0.0032302014 | H36: =Financials!G47/(Financials!F4+Financials!G4)/2 -> 0.0032844268 | I36: =Financials!H47/(Financials!G4+Financials!H4)/2 -> 0.0059821727 | J36: =Financials!I47/(Financials!H4+Financials!I4)/2 -> 0.008812576 | K36: =Financials!J47/(Financials!I4+Financials!J4)/2 -> 0.011399116 | L36: =Financials!K47/(Financials!J4+Financials!K4)/2 -> 0.013997115 | ... BX36: =Financials!BW47/(Financials!BV4+Financials!BW4)/2 -> 0.0071498761
B37: Opex/Turnover | E37: =Financials!D47/Financials!D37 -> 0.48148834 | F37: =Financials!E47/Financials!E37 -> 0.65743148 | G37: =Financials!F47/Financials!F37 -> 0.89548813 | H37: =Financials!G47/Financials!G37 -> 0.89548813 | I37: =Financials!H47/Financials!H37 -> 0.81253605 | J37: =Financials!I47/Financials!I37 -> 0.83907059 | K37: =Financials!J47/Financials!J37 -> 0.7876937 | L37: =Financials!K47/Financials!K37 -> 0.89509742 | ... BX37: =Financials!BW47/Financials!BW37 -> 0.90467168
B38: Avge yield on Net loans | E38: =Financials!D38/('Evolutive SFP'!C13+'Evolutive SFP'!B13)/2 -> 0.078352184 | F38: =Financials!E38/('Evolutive SFP'!D13+'Evolutive SFP'!C13)/2 -> 0.065010123 | G38: =Financials!F38/('Evolutive SFP'!E13+'Evolutive SFP'!D13)/2 -> 0.004001752 | H38: =Financials!G38/('Evolutive SFP'!F13+'Evolutive SFP'!E13)/2 -> 0.0037938655 | I38: =Financials!H38/('Evolutive SFP'!G13+'Evolutive SFP'!F13)/2 -> 0.0078025411 | J38: =Financials!I38/('Evolutive SFP'!H13+'Evolutive SFP'!G13)/2 -> 0.011939773 | K38: =Financials!J38/('Evolutive SFP'!I13+'Evolutive SFP'!H13)/2 -> 0.01587037 | L38: =Financials!K38/('Evolutive SFP'!J13+'Evolutive SFP'!I13)/2 -> 0.017058215 | ... BX38: =Financials!BW38/('Evolutive SFP'!BV13+'Evolutive SFP'!BU13)/2 -> 0.10458679
B39: Avge yield on Gross loans | E39: =Financials!D37/('Evolutive SFP'!C14+'Evolutive SFP'!B14)/2 -> 0.12648693 | F39: =Financials!E37/('Evolutive SFP'!D14+'Evolutive SFP'!C14)/2 -> 0.10025647 | G39: =Financials!F37/('Evolutive SFP'!E14+'Evolutive SFP'!D14)/2 -> 0.0065114122 | H39: =Financials!G37/('Evolutive SFP'!F14+'Evolutive SFP'!E14)/2 -> 0.0060946304 | I39: =Financials!H37/('Evolutive SFP'!G14+'Evolutive SFP'!F14)/2 -> 0.012018134 | J39: =Financials!I37/('Evolutive SFP'!H14+'Evolutive SFP'!G14)/2 -> 0.017512366 | K39: =Financials!J37/('Evolutive SFP'!I14+'Evolutive SFP'!H14)/2 -> 0.023126392 | L39: =Financials!K37/('Evolutive SFP'!J14+'Evolutive SFP'!I14)/2 -> 0.024488116 | ... BX39: =Financials!BW37/('Evolutive SFP'!BV14+'Evolutive SFP'!BU14)/2 -> 0.0133866
A41: ALL/Average Gross Loan portfolio

Sheet CAELS (2)
A1: JUMUIKA CAELS
B2: Financial Performance | C2: Prud. Std | D2: 2013 Audited | E2: 2014 Audited | F2: Audited 2015 | G2: 2016 Audited | H2: 42736 | I2: 42767 | J2: 42795 | K2: 42826 | L2: 42856 | M2: 42887 | N2: 42917 | O2: 42948 | P2: 42979 | Q2: 43009 | R2: 43040 | S2: 43070 | T2: 2017Audited | U2: 43101 | V2: 43132 | W2: 43160 | X2: 43191 | Y2: 43221 | Z2: 43252 | AA2: 43282 | AB2: 43313 | AC2: 43344 | AD2: 43374 | AE2: 43405 | AF2: 43435 | AG2: Audited 2018 | AH2: 43466 | AI2: 43497 | AJ2: 43525 | AK2: 43556 | AL2: 43586 | AM2: 43617 | AN2: 43647 | AO2: 43678 | AP2: 43709 | AQ2: 43739 | AR2: 43770 | AS2: 43800 | AT2: Audited 2019 | AU2: 43831 | AV2: 43862 | AW2: 43891 | AX2: 43922 | AY2: 43952 | AZ2: 43983 | BA2: 44013 | BB2: 44044 | BC2: 44075 | BD2: 44105 | BE2: 44136 | BF2: 44166 | BG2: Audited 2020 | BH2: 44197 | BI2: 44228 | BJ2: 44256 | BK2: 44287 | BL2: 44317 | BM2: 44348 | BN2: 44378 | BO2: 44409 | BP2: 44440 | BQ2: 44470 | BR2: 44501 | BS2: 44531 | BT2: Audited 2021 | BU2: 44562 | BV2: 44593 | BW2: Return March, 2022 | BX2: 44652 | BY2: 44682 | BZ2: Return June, 2022 | CA2: 44743 | CB2: 44774 | CC2: Return September, 2022 | CD2: 44835 | CE2: 44866 | CF2: 44896 | CG2: Audited 2022
A3: CAPITAL ADEQUACY | B3: Core Capital | C3: 10 Million | D3: =(('Evolutive SFP'!B38+'Evolutive SFP'!B39+'Evolutive SFP'!B40+'Evolutive SFP'!B41+'Evolutive SFP'!B42+'Evolutive SFP'!B43)-'Evolutive SFP'!B12)/1000000 -> 76.173062 | E3: =(('Evolutive SFP'!C38+'Evolutive SFP'!C39+'Evolutive SFP'!C40+'Evolutive SFP'!C41+'Evolutive SFP'!C42+'Evolutive SFP'!C43)-'Evolutive SFP'!C12)/1000000 -> 63.869079 | F3: =(('Evolutive SFP'!D38+'Evolutive SFP'!D39+'Evolutive SFP'!D40+'Evolutive SFP'!D41+'Evolutive SFP'!D42+'Evolutive SFP'!D43)-'Evolutive SFP'!D12)/1000000 -> 60.755239 | G3: =(('Evolutive SFP'!E38+'Evolutive SFP'!E39+'Evolutive SFP'!E40+'Evolutive SFP'!E41+'Evolutive SFP'!E42+'Evolutive SFP'!E43)-'Evolutive SFP'!E12)/1000000 -> 61.885255 | H3: =(('Evolutive SFP'!F38+'Evolutive SFP'!F39+'Evolutive SFP'!F40+'Evolutive SFP'!F41+'Evolutive SFP'!F42+'Evolutive SFP'!F43)-'Evolutive SFP'!F12)/1000000 -> 75.078486 | I3: =(('Evolutive SFP'!G38+'Evolutive SFP'!G39+'Evolutive SFP'!G40+'Evolutive SFP'!G41+'Evolutive SFP'!G42+'Evolutive SFP'!G43)-'Evolutive SFP'!G12)/1000000 -> 57.062442 | J3: =(('Evolutive SFP'!H38+'Evolutive SFP'!H39+'Evolutive SFP'!H40+'Evolutive SFP'!H41+'Evolutive SFP'!H42+'Evolutive SFP'!H43)-'Evolutive SFP'!H12)/1000000 -> 58.519719 | K3: =(('Evolutive SFP'!I38+'Evolutive SFP'!I39+'Evolutive SFP'!I40+'Evolutive SFP'!I41+'Evolutive SFP'!I42+'Evolutive SFP'!I43)-'Evolutive SFP'!I12)/1000000 -> 56.787295 | ... CG3: =(('Evolutive SFP'!CE38+'Evolutive SFP'!CE39+'Evolutive SFP'!CE40+'Evolutive SFP'!CE41+'Evolutive SFP'!CE42+'Evolutive SFP'!CE43)-'Evolutive SFP'!CE12)/1000000 -> -15.57731
B4: Core Capital to total Assets | C4: Min 10% | D4: =D3/(('Evolutive SFP'!B26)/1000000) -> 0.23738076 | E4: =E3/(('Evolutive SFP'!C26)/1000000) -> 0.23454913 | F4: =F3/(('Evolutive SFP'!D26)/1000000) -> 0.21282968 | G4: =G3/(('Evolutive SFP'!E26)/1000000) -> 0.20547271 | H4: =H3/(('Evolutive SFP'!F26)/1000000) -> 0.27224184 | I4: =I3/(('Evolutive SFP'!G26)/1000000) -> 0.18660701 | J4: =J3/(('Evolutive SFP'!H26)/1000000) -> 0.20447618 | K4: =K3/(('Evolutive SFP'!I26)/1000000) -> 0.20896512 | ... CG4: =CG3/(('Evolutive SFP'!CE26)/1000000) -> -0.070874522
B5: Core Capital to Total Deposits | C5: Min 8% | D5: =D3/('Evolutive SFP'!B30/1000000) -> 0.40774099 | E5: =E3/('Evolutive SFP'!C30/1000000) -> 0.37355256 | F5: =F3/('Evolutive SFP'!D30/1000000) -> 0.35684171 | G5: =G3/('Evolutive SFP'!E30/1000000) -> 0.35452533 | H5: =H3/('Evolutive SFP'!F30/1000000) -> 0.49943572 | I5: =I3/('Evolutive SFP'!G30/1000000) -> 0.31673644 | J5: =J3/('Evolutive SFP'!H30/1000000) -> 0.33000411 | K5: =K3/('Evolutive SFP'!I30/1000000) -> 0.33425663 | ... CG5: =CG3/('Evolutive SFP'!CE30/1000000) -> -0.084122546
B6: Institutional Capital | C6: Min 8% | D6: =((D3*1000000)-'Evolutive SFP'!B38)/'Evolutive SFP'!B26 -> 0.22621026 | E6: =((E3*1000000)-'Evolutive SFP'!C38)/'Evolutive SFP'!C26 -> 0.20039766 | F6: =((F3*1000000)-'Evolutive SFP'!D38)/'Evolutive SFP'!D26 -> 0.17590775 | G6: =((G3*1000000)-'Evolutive SFP'!E38)/'Evolutive SFP'!E26 -> 0.1662799 | H6: =((H3*1000000)-'Evolutive SFP'!F38)/'Evolutive SFP'!F26 -> 0.22943839 | I6: =((I3*1000000)-'Evolutive SFP'!G38)/'Evolutive SFP'!G26 -> 0.14800437 | J6: =((J3*1000000)-'Evolutive SFP'!H38)/'Evolutive SFP'!H26 -> 0.15978877 | K6: =((K3*1000000)-'Evolutive SFP'!I38)/'Evolutive SFP'!I26 -> 0.16188248 | ... CG6: =((CG3*1000000)-'Evolutive SFP'!CE38)/'Evolutive SFP'!CE26 -> -0.1337723
A7: ASSET QUALITY | B7: Non performing Loans Ratio | F7: ='Evolutive SFP'!D15/('FORM 4'!K15+'FORM 4'!K16+'FORM 4'!K17) -> #DIV/0! | J7: ='Evolutive SFP'!H15/('FORM 4'!D5+'FORM 4'!D6+'FORM 4'!D7) -> 0.25563386 | M7: ='Evolutive SFP'!K15/('FORM 4'!D15+'FORM 4'!D16+'FORM 4'!D17) -> #DIV/0! | O7: ='Evolutive SFP'!M15/('FORM 4'!F15+'FORM 4'!F16+'FORM 4'!F17) -> #DIV/0! | Q7: ='Evolutive SFP'!O15/('FORM 4'!H15+'FORM 4'!H16+'FORM 4'!H17) -> #DIV/0! | S7: ='Evolutive SFP'!Q15/('FORM 4'!J15+'FORM 4'!J16+'FORM 4'!J17) -> #DIV/0! | T7: 0.57579736 | U7: 1.5757974 | V7: 2.5757974 | W7: 3.5757974 | X7: 4.5757974 | Y7: 5.5757974 | Z7: 6.5757974 | AA7: 7.5757974 | AB7: 8.5757974 | AC7: 9.5757974 | AD7: 10.575797 | AE7: 11.575797 | AF7: 12.575797 | AG7: 13.575797 | AH7: 13.575797 | AI7: 13.575797 | AJ7: 13.575797 | AK7: 13.575797 | AL7: 13.575797 | AM7: 13.575797 | AN7: 13.575797 | AO7: 13.575797 | AP7: 13.575797 | AQ7: 13.575797 | AR7: 13.575797 | AS7: 13.575797 | AT7: 13.575797 | AU7: 13.575797 | AV7: 13.575797 | AW7: 13.575797 | AX7: 13.575797 | AY7: 13.575797 | AZ7: 13.575797 | BA7: 13.575797 | BB7: 13.575797 | BC7: 13.575797 | BD7: 13.575797 | BE7: 13.575797 | BF7: 13.575797 | BG7: 0.98 | BH7: 0.98 | BI7: 0.98 | BJ7: 0.98 | BK7: 0.98 | BL7: 0.98 | BM7: 0.98 | BN7: 0.98 | BO7: 0.98 | BP7: 0.98 | BQ7: 0.98 | BR7: 0.98 | BS7: 0.98 | BT7: 0.8 | BU7: 1.8 | BV7: 2.8 | BW7: 0.8 | BX7: 4.8 | BY7: 5.8 | BZ7: 0.8 | CA7: 7.8 | CB7: 8.8 | CC7: 0.84 | CD7: 10.8 | CE7: 11.8 | CF7: 0.78 | CG7: =Financials!CF33/Financials!CF31 -> 0.68500964
B8: NPL30 | F8: =('FORM 4'!K15+'FORM 4'!K16+'FORM 4'!K17)/'Evolutive SFP'!D14 -> 0 | J8: =('FORM 4'!D5+'FORM 4'!D6+'FORM 4'!D7)/'FORM 4'!D8 -> 0.093191731 | M8: =('FORM 4'!D15+'FORM 4'!D16+'FORM 4'!D17)/'FORM 4'!D18 -> #DIV/0! | O8: =('FORM 4'!F15+'FORM 4'!F16+'FORM 4'!F17)/'FORM 4'!F18 -> #DIV/0! | Q8: =('FORM 4'!H15+'FORM 4'!H16+'FORM 4'!H17)/'FORM 4'!H18 -> #DIV/0! | S8: =('FORM 4'!J15+'FORM 4'!J16+'FORM 4'!J17)/'FORM 4'!J18 -> #DIV/0! | T8: 0.10982053 | U8: 1.1098205 | V8: 2.1098205 | W8: 3.1098205 | X8: 4.1098205 | Y8: 5.1098205 | Z8: 6.1098205 | AA8: 7.1098205 | AB8: 8.1098205 | AC8: 9.1098205 | AD8: 10.109821 | AE8: 11.109821 | AF8: 12.109821 | AG8: 13.109821 | AH8: 13.109821 | AI8: 13.109821 | AJ8: 13.109821 | AK8: 13.109821 | AL8: 13.109821 | AM8: 13.109821 | AN8: 13.109821 | AO8: 13.109821 | AP8: 13.109821 | AQ8: 13.109821 | AR8: 13.109821 | AS8: 13.109821 | AT8: 13.109821 | AU8: 13.109821 | AV8: 13.109821 | AW8: 13.109821 | AX8: 13.109821 | AY8: 13.109821 | AZ8: 13.109821 | BA8: 13.109821 | BB8: 13.109821 | BC8: 13.109821 | BD8: 13.109821 | BE8: 13.109821 | BF8: 13.109821 | BG8: 0.98 | BH8: 0.98 | BI8: 0.98 | BJ8: 0.98 | BK8: 0.98 | BL8: 0.98 | BM8: 0.98 | BN8: 0.98 | BO8: 0.98 | BP8: 0.98 | BQ8: 0.98 | BR8: 0.98 | BS8: 0.98 | BT8: =(77126273+313476+1962447)/99799936 -> 0.7956137 | BU8: =(77126273+313476+1962447)/99799936 -> 0.7956137 | BV8: =(77126273+313476+1962447)/99799936 -> 0.7956137 | BW8: =(77126273+313476+1962447)/99799936 -> 0.7956137 | BX8: =(77126273+313476+1962447)/99799936 -> 0.7956137 | BY8: =(77126273+313476+1962447)/99799936 -> 0.7956137 | BZ8: =(77126273+313476+1962447)/99799936 -> 0.7956137 | CA8: =(77126273+313476+1962447)/99799936 -> 0.7956137 | CB8: =(77126273+313476+1962447)/99799936 -> 0.7956137 | CC8: 0.84 | CD8: =(77126273+313476+1962447)/99799936 -> 0.7956137 | CE8: =(77126273+313476+1962447)/99799936 -> 0.7956137 | CF8: =(77126273+313476+1962447)/99799936 -> 0.7956137 | CG8: =(77126273+313476+1962447)/99799936 -> 0.7956137
A9: EARNINGS | B9: Return on Assets | E9: ='Evolutitve SCI'!C33/(('Evolutive SFP'!B26+'Evolutive SFP'!C26)/2) -> 0.035026197 | F9: ='Evolutitve SCI'!E33/(('Evolutive SFP'!#REF!+'Evolutive SFP'!D26)/2) -> #REF! | G9: ='Evolutitve SCI'!E33/(('Evolutive SFP'!D26+'Evolutive SFP'!E26)/2) -> 0.0037046791 | H9: ='Evolutitve SCI'!F33/(('Evolutive SFP'!D26+'Evolutive SFP'!F26)/2) -> 0.00049867178 | I9: ='Evolutitve SCI'!G33/(('Evolutive SFP'!F26+'Evolutive SFP'!G26)/2) -> -0.013698635 | J9: ='Evolutitve SCI'!H33/(('Evolutive SFP'!G26+'Evolutive SFP'!H26)/2) -> -0.010274339 | K9: ='Evolutitve SCI'!I33/(('Evolutive SFP'!H26+'Evolutive SFP'!I26)/2) -> -0.0089203719 | L9: ='Evolutitve SCI'!J33/(('Evolutive SFP'!I26+'Evolutive SFP'!J26)/2) -> -0.017680686 | M9: ='Evolutitve SCI'!K33/(('Evolutive SFP'!J26+'Evolutive SFP'!K26)/2) -> -0.018702558 | N9: ='Evolutitve SCI'!L33/(('Evolutive SFP'!K26+'Evolutive SFP'!L26)/2) -> 0 | O9: ='Evolutitve SCI'!M33/(('Evolutive SFP'!L26+'Evolutive SFP'!M26)/2) -> #DIV/0! | P9: ='Evolutitve SCI'!N33/(('Evolutive SFP'!M26+'Evolutive SFP'!N26)/2) -> #DIV/0! | ... CG9: ='Evolutitve SCI'!CE33/(('Evolutive SFP'!CD26+'Evolutive SFP'!CE26)/2) -> 0.012383974
B10: Cost Income ratio | D10: ='Evolutitve SCI'!B23/'Evolutitve SCI'!B19 -> 0.73724876 | E10: ='Evolutitve SCI'!C23/'Evolutitve SCI'!C19 -> 0.67834548 | F10: ='Evolutitve SCI'!E23/'Evolutitve SCI'!E19 -> 0.95420772 | G10: ='Evolutitve SCI'!E23/'Evolutitve SCI'!E19 -> 0.95420772 | H10: ='Evolutitve SCI'!F23/'Evolutitve SCI'!F19 -> 0.96439171 | I10: ='Evolutitve SCI'!G23/'Evolutitve SCI'!G19 -> 1.0005801 | J10: ='Evolutitve SCI'!H23/'Evolutitve SCI'!H19 -> 0.92925389 | K10: ='Evolutitve SCI'!I23/'Evolutitve SCI'!I19 -> 0.99345797 | L10: ='Evolutitve SCI'!J23/'Evolutitve SCI'!J19 -> 1.1523579 | M10: ='Evolutitve SCI'!K23/'Evolutitve SCI'!K19 -> 1.1885086 | N10: ='Evolutitve SCI'!L23/'Evolutitve SCI'!L19 -> #DIV/0! | ... BF10: ='Evolutitve SCI'!BD23/'Evolutitve SCI'!BD19 -> 0.57168165 | BG10: ='Evolutitve SCI'!BF23/'Evolutitve SCI'!BF19 -> 1.0413472 | BH10: ='Evolutitve SCI'!BG23/'Evolutitve SCI'!BG19 -> 1.9160776 | BI10: ='Evolutitve SCI'!BH23/'Evolutitve SCI'!BH19 -> 1.1777716 | BJ10: ='Evolutitve SCI'!BI23/'Evolutitve SCI'!BI19 -> 1.1351208 | BK10: ='Evolutitve SCI'!BJ23/'Evolutitve SCI'!BJ19 -> 1.0371492 | BL10: ='Evolutitve SCI'!BK23/'Evolutitve SCI'!BK19 -> 0.92896841 | BM10: ='Evolutitve SCI'!BL23/'Evolutitve SCI'!BL19 -> 0.88817796 | BN10: ='Evolutitve SCI'!BM23/'Evolutitve SCI'!BM19 -> 0.85394549 | ... CG10: ='Evolutitve SCI'!CF23/'Evolutitve SCI'!CF19 -> 0.98172614
B11: Operating Expense ratio | D11: =('Evolutitve SCI'!B23+'Evolutitve SCI'!B12)/(('Evolutive SFP'!B26+'Evolutive SFP'!C26)/2) -> 0.13067108 | E11: =('Evolutitve SCI'!C23+'Evolutitve SCI'!C12)/(('Evolutive SFP'!C26+'Evolutive SFP'!D26)/2) -> 0.1504591 | F11: =('Evolutitve SCI'!E23+'Evolutitve SCI'!E12)/(('Evolutive SFP'!D26+'Evolutive SFP'!F26)/2) -> 0.18632183 | G11: =('Evolutitve SCI'!E23+'Evolutitve SCI'!E12)/(('Evolutive SFP'!E26+'Evolutive SFP'!F26)/2) -> 0.18124507 | H11: =('Evolutitve SCI'!F23+'Evolutitve SCI'!F12)/(('Evolutive SFP'!F26+'Evolutive SFP'!G26)/2) -> 0.014073599 | I11: =('Evolutitve SCI'!G23+'Evolutitve SCI'!G12)/(('Evolutive SFP'!G26+'Evolutive SFP'!H26)/2) -> 0.028944918 | J11: =('Evolutitve SCI'!H23+'Evolutitve SCI'!H12)/(('Evolutive SFP'!H26+'Evolutive SFP'!I26)/2) -> 0.041726397 | K11: =('Evolutitve SCI'!I23+'Evolutitve SCI'!I12)/(('Evolutive SFP'!I26+'Evolutive SFP'!J26)/2) -> 0.059969674 | L11: =('Evolutitve SCI'!J23+'Evolutitve SCI'!J12)/(('Evolutive SFP'!J26+'Evolutive SFP'!K26)/2) -> 0.072131454 | M11: =('Evolutitve SCI'!K23+'Evolutitve SCI'!K12)/(('Evolutive SFP'!K26+'Evolutive SFP'!L26)/2) -> 0.15646979 | N11: =('Evolutitve SCI'!L23+'Evolutitve SCI'!L12)/(('Evolutive SFP'!L26+'Evolutive SFP'!M26)/2) -> #DIV/0! | ... BF11: =('Evolutitve SCI'!BD23+'Evolutitve SCI'!BD12)/(('Evolutive SFP'!BD26+'Evolutive SFP'!BE26)/2) -> 0.08462584 | BG11: =('Evolutitve SCI'!BE23+'Evolutitve SCI'!BE12)/(('Evolutive SFP'!BE26+'Evolutive SFP'!BG26)/2) -> 0.10243386 | BH11: =('Evolutitve SCI'!BF23+'Evolutitve SCI'!BF12)/(('Evolutive SFP'!BF26+'Evolutive SFP'!BH26)/2) -> 0.11353856 | BI11: =('Evolutitve SCI'!BG23+'Evolutitve SCI'!BG12)/(('Evolutive SFP'!BG26+'Evolutive SFP'!BI26)/2) -> 0.0092441929 | BJ11: =('Evolutitve SCI'!BH23+'Evolutitve SCI'!BH12)/(('Evolutive SFP'!BH26+'Evolutive SFP'!BJ26)/2) -> 0.015556747 | BK11: =('Evolutitve SCI'!BI23+'Evolutitve SCI'!BI12)/(('Evolutive SFP'!BI26+'Evolutive SFP'!BK26)/2) -> 0.024606921 | BL11: =('Evolutitve SCI'!BJ23+'Evolutitve SCI'!BJ12)/(('Evolutive SFP'!BJ26+'Evolutive SFP'!BL26)/2) -> 0.038648184 | BM11: =('Evolutitve SCI'!BK23+'Evolutitve SCI'!BK12)/(('Evolutive SFP'!BK26+'Evolutive SFP'!BM26)/2) -> 0.041330856 | BN11: =('Evolutitve SCI'!BL23+'Evolutitve SCI'!BL12)/(('Evolutive SFP'!BL26+'Evolutive SFP'!BN26)/2) -> 0.051100518 | ... CG11: =('Evolutitve SCI'!CE23+'Evolutitve SCI'!CE12)/(('Evolutive SFP'!CE26+'Evolutive SFP'!CG26)/2) -> 0.10547309
A12: LIQUIDITY | B12: Liquidity Ratio | C12: Min 15% | D12: =('Evolutive SFP'!B4)/('Evolutive SFP'!B27+'Evolutive SFP'!B28+'Evolutive SFP'!B31+'Evolutive SFP'!B32+'Evolutive SFP'!B33+'Evolutive SFP'!B34+'Evolutive SFP'!B35) -> 1.4016204 | E12: =('Evolutive SFP'!C4)/('Evolutive SFP'!C27+'Evolutive SFP'!C28+'Evolutive SFP'!C31+'Evolutive SFP'!C32+'Evolutive SFP'!C33+'Evolutive SFP'!C34+'Evolutive SFP'!C35) -> 1.5761989 | F12: =('Evolutive SFP'!D4)/('Evolutive SFP'!D27+'Evolutive SFP'!D28+'Evolutive SFP'!D31+'Evolutive SFP'!D32+'Evolutive SFP'!D33+'Evolutive SFP'!D34+'Evolutive SFP'!D35) -> 1.6067326 | G12: =('Evolutive SFP'!E4)/('Evolutive SFP'!E27+'Evolutive SFP'!E28+'Evolutive SFP'!E31+'Evolutive SFP'!E32+'Evolutive SFP'!E33+'Evolutive SFP'!E34+'Evolutive SFP'!E35) -> 1.3355392 | H12: =('Evolutive SFP'!F4)/('Evolutive SFP'!F27+'Evolutive SFP'!F28+'Evolutive SFP'!F31+'Evolutive SFP'!F32+'Evolutive SFP'!F33+'Evolutive SFP'!F34+'Evolutive SFP'!F35) -> -10.585836 | I12: =('Evolutive SFP'!G4)/('Evolutive SFP'!G27+'Evolutive SFP'!G28+'Evolutive SFP'!G31+'Evolutive SFP'!G32+'Evolutive SFP'!G33+'Evolutive SFP'!G34+'Evolutive SFP'!G35) -> 1.2029153 | J12: =('Evolutive SFP'!H4)/('Evolutive SFP'!H27+'Evolutive SFP'!H28+'Evolutive SFP'!H31+'Evolutive SFP'!H32+'Evolutive SFP'!H33+'Evolutive SFP'!H34+'Evolutive SFP'!H35) -> 1.1859676 | K12: =('Evolutive SFP'!I4)/('Evolutive SFP'!I27+'Evolutive SFP'!I28+'Evolutive SFP'!I31+'Evolutive SFP'!I32+'Evolutive SFP'!I33+'Evolutive SFP'!I34+'Evolutive SFP'!I35) -> 0.62620751 | ... CG12: =('Evolutive SFP'!CE4)/('Evolutive SFP'!CE27+'Evolutive SFP'!CE28+'Evolutive SFP'!CE31+'Evolutive SFP'!CE32+'Evolutive SFP'!CE33+'Evolutive SFP'!CE34+'Evolutive SFP'!CE35) -> 0.29237241
B13: T/LIQ ratio | D13: =('Evolutive SFP'!B4+'Evolutive SFP'!B8)/('Evolutive SFP'!B30+'Evolutive SFP'!B31+'Evolutive SFP'!B32+'Evolutive SFP'!B33+'Evolutive SFP'!B34+'Evolutive SFP'!B35) -> 0.68792926 | E13: =('Evolutive SFP'!C4+'Evolutive SFP'!C8)/('Evolutive SFP'!C30+'Evolutive SFP'!C31+'Evolutive SFP'!C32+'Evolutive SFP'!C33+'Evolutive SFP'!C34+'Evolutive SFP'!C35) -> 0.59901309 | F13: =('Evolutive SFP'!D4+'Evolutive SFP'!D8)/('Evolutive SFP'!D30+'Evolutive SFP'!D31+'Evolutive SFP'!D32+'Evolutive SFP'!D33+'Evolutive SFP'!D34+'Evolutive SFP'!D35) -> 0.48726606 | G13: =('Evolutive SFP'!E4+'Evolutive SFP'!E8)/('Evolutive SFP'!E30+'Evolutive SFP'!E31+'Evolutive SFP'!E32+'Evolutive SFP'!E33+'Evolutive SFP'!E34+'Evolutive SFP'!E35) -> 0.38049168 | H13: =('Evolutive SFP'!F4+'Evolutive SFP'!F8)/('Evolutive SFP'!F30+'Evolutive SFP'!F31+'Evolutive SFP'!F32+'Evolutive SFP'!F33+'Evolutive SFP'!F34+'Evolutive SFP'!F35) -> 0.33668536 | I13: =('Evolutive SFP'!G4+'Evolutive SFP'!G8)/('Evolutive SFP'!G30+'Evolutive SFP'!G31+'Evolutive SFP'!G32+'Evolutive SFP'!G33+'Evolutive SFP'!G34+'Evolutive SFP'!G35) -> 0.35873512 | J13: ='Evolutive SFP'!H4/('Evolutive SFP'!H30+'Evolutive SFP'!H35) -> 0.16262593 | K13: ='Evolutive SFP'!I4/('Evolutive SFP'!I30+'Evolutive SFP'!I35) -> 0.12831957 | L13: =('Evolutive SFP'!J4+'Evolutive SFP'!J8)/('Evolutive SFP'!J30+'Evolutive SFP'!J31+'Evolutive SFP'!J32+'Evolutive SFP'!J33+'Evolutive SFP'!J34+'Evolutive SFP'!J35) -> 0.23683995 | M13: ='Evolutive SFP'!K4/('Evolutive SFP'!K30+'Evolutive SFP'!K35) -> 0.029880436 | N13: =('Evolutive SFP'!L4+'Evolutive SFP'!L8)/('Evolutive SFP'!L30+'Evolutive SFP'!L31+'Evolutive SFP'!L32+'Evolutive SFP'!L33+'Evolutive SFP'!L34+'Evolutive SFP'!L35) -> #DIV/0! | O13: ='Evolutive SFP'!M4/('Evolutive SFP'!M30+'Evolutive SFP'!M35) -> #DIV/0! | P13: =('Evolutive SFP'!N4+'Evolutive SFP'!N8)/('Evolutive SFP'!N30+'Evolutive SFP'!N31+'Evolutive SFP'!N32+'Evolutive SFP'!N33+'Evolutive SFP'!N34+'Evolutive SFP'!N35) -> #DIV/0! | Q13: ='Evolutive SFP'!O4/('Evolutive SFP'!O30+'Evolutive SFP'!O35) -> #DIV/0! | R13: =('Evolutive SFP'!P4+'Evolutive SFP'!P8)/('Evolutive SFP'!P30+'Evolutive SFP'!P31+'Evolutive SFP'!P32+'Evolutive SFP'!P33+'Evolutive SFP'!P34+'Evolutive SFP'!P35) -> #DIV/0! | S13: ='Evolutive SFP'!Q4/('Evolutive SFP'!Q30+'Evolutive SFP'!Q35) -> #DIV/0! | T13: =('Evolutive SFP'!R4+'Evolutive SFP'!R8)/('Evolutive SFP'!R30+'Evolutive SFP'!R31+'Evolutive SFP'!R32+'Evolutive SFP'!R33+'Evolutive SFP'!R34+'Evolutive SFP'!R35) -> 0.36640081 | U13: =('Evolutive SFP'!S4+'Evolutive SFP'!S8)/('Evolutive SFP'!S30+'Evolutive SFP'!S31+'Evolutive SFP'!S32+'Evolutive SFP'!S33+'Evolutive SFP'!S34+'Evolutive SFP'!S35) -> 0.29147268 | V13: =('Evolutive SFP'!T4+'Evolutive SFP'!T8)/('Evolutive SFP'!T30+'Evolutive SFP'!T31+'Evolutive SFP'!T32+'Evolutive SFP'!T33+'Evolutive SFP'!T34+'Evolutive SFP'!T35) -> 0.26578222 | W13: =('Evolutive SFP'!U4+'Evolutive SFP'!U8)/('Evolutive SFP'!U30+'Evolutive SFP'!U31+'Evolutive SFP'!U32+'Evolutive SFP'!U33+'Evolutive SFP'!U34+'Evolutive SFP'!U35) -> 0.25813881 | X13: =('Evolutive SFP'!V4+'Evolutive SFP'!V8)/('Evolutive SFP'!V30+'Evolutive SFP'!V31+'Evolutive SFP'!V32+'Evolutive SFP'!V33+'Evolutive SFP'!V34+'Evolutive SFP'!V35) -> 0.20328933 | Y13: =('Evolutive SFP'!W4+'Evolutive SFP'!W8)/('Evolutive SFP'!W30+'Evolutive SFP'!W31+'Evolutive SFP'!W32+'Evolutive SFP'!W33+'Evolutive SFP'!W34+'Evolutive SFP'!W35) -> 0.1896752 | Z13: =('Evolutive SFP'!X4+'Evolutive SFP'!X8)/('Evolutive SFP'!X30+'Evolutive SFP'!X31+'Evolutive SFP'!X32+'Evolutive SFP'!X33+'Evolutive SFP'!X34+'Evolutive SFP'!X35) -> 0.14874781 | AA13: =('Evolutive SFP'!Y4+'Evolutive SFP'!Y8)/('Evolutive SFP'!Y30+'Evolutive SFP'!Y31+'Evolutive SFP'!Y32+'Evolutive SFP'!Y33+'Evolutive SFP'!Y34+'Evolutive SFP'!Y35) -> 0.14292653 | ... CG13: =('Evolutive SFP'!CE4+'Evolutive SFP'!CE8)/('Evolutive SFP'!CE30+'Evolutive SFP'!CE31+'Evolutive SFP'!CE32+'Evolutive SFP'!CE33+'Evolutive SFP'!CE34+'Evolutive SFP'!CE35) -> 0.15929355
B14: External Borrowing ratio | C14: Max 25% | D14: ='Evolutive SFP'!B36/'Evolutive SFP'!B26 -> 0.01779812 | E14: ='Evolutive SFP'!C36/'Evolutive SFP'!C26 -> 0.011556425 | F14: ='Evolutive SFP'!D36/'Evolutive SFP'!D26 -> 0.06478966 | G14: ='Evolutive SFP'!E36/'Evolutive SFP'!E26 -> 0.096654787 | H14: ='Evolutive SFP'!F36/'Evolutive SFP'!F26 -> 0.10338849 | I14: ='Evolutive SFP'!G36/'Evolutive SFP'!G26 -> 0.091601863 | J14: ='Evolutive SFP'!H36/'Evolutive SFP'!H26 -> 0.087222464 | K14: ='Evolutive SFP'!I36/'Evolutive SFP'!I26 -> 0.091856624 | ... CG14: ='Evolutive SFP'!CE36/'Evolutive SFP'!CE26 -> 0.12101329
B15: LA to TA ratio | D15: ='Evolutive SFP'!B4/'Evolutive SFP'!B26 -> 0.40027698 | E15: ='Evolutive SFP'!C4/'Evolutive SFP'!C26 -> 0.32230741 | F15: ='Evolutive SFP'!D4/'Evolutive SFP'!D26 -> 0.23547508 | G15: ='Evolutive SFP'!E4/'Evolutive SFP'!E26 -> 0.1669553 | H15: ='Evolutive SFP'!F4/'Evolutive SFP'!F26 -> 0.11583365 | I15: ='Evolutive SFP'!G4/'Evolutive SFP'!G26 -> 0.17247917 | J15: ='Evolutive SFP'!H4/'Evolutive SFP'!H26 -> 0.1046832 | K15: ='Evolutive SFP'!I4/'Evolutive SFP'!I26 -> 0.080988945 | ... CG15: ='Evolutive SFP'!CE4/'Evolutive SFP'!CE26 -> 0.08598475
A16: STRUCTURE | B16: Non earning Assets Ratio | C16: Max 10% | D16: =('Evolutive SFP'!B7+'Evolutive SFP'!B20)/'Evolutive SFP'!B26 -> 0.21010948 | E16: =('Evolutive SFP'!C7+'Evolutive SFP'!C20)/'Evolutive SFP'!C26 -> 0.18943962 | F16: =('Evolutive SFP'!D7+'Evolutive SFP'!D20)/'Evolutive SFP'!D26 -> 0.14400131 | G16: =('Evolutive SFP'!E7+'Evolutive SFP'!E20)/'Evolutive SFP'!E26 -> 0.21489473 | H16: =('Evolutive SFP'!F7+'Evolutive SFP'!F20)/'Evolutive SFP'!F26 -> 0.19106075 | I16: =('Evolutive SFP'!G7+'Evolutive SFP'!G20)/'Evolutive SFP'!G26 -> 0.19797678 | J16: =('Evolutive SFP'!H7+'Evolutive SFP'!H20)/'Evolutive SFP'!H26 -> 0.19421062 | K16: =('Evolutive SFP'!I7+'Evolutive SFP'!I20)/'Evolutive SFP'!I26 -> 0.20847393 | ... CG16: =('Evolutive SFP'!CE7+'Evolutive SFP'!CE20)/'Evolutive SFP'!CE26 -> 0.65076935
B17: Land and Building Ratios | C17: Max 5% | D17: ='Evolutive SFP'!B20/'Evolutive SFP'!B26 -> 0.046772228 | E17: ='Evolutive SFP'!C20/'Evolutive SFP'!C26 -> 0.038030294 | F17: ='Evolutive SFP'!D20/'Evolutive SFP'!D26 -> 0.082131324 | G17: ='Evolutive SFP'!E20/'Evolutive SFP'!E26 -> 0.13327344 | H17: ='Evolutive SFP'!F20/'Evolutive SFP'!F26 -> 0.077534181 | I17: ='Evolutive SFP'!G20/'Evolutive SFP'!G26 -> 0.12273509 | J17: ='Evolutive SFP'!H20/'Evolutive SFP'!H26 -> 0.10478798 | K17: ='Evolutive SFP'!I20/'Evolutive SFP'!I26 -> 0.11285208 | ... CG17: ='Evolutive SFP'!CE20/'Evolutive SFP'!CE26 -> 0.60492732
B18: PI to Deposit ratio | C18: Max 40% | D18: ='Evolutive SFP'!B12/'Evolutive SFP'!B30 -> 0.096816078 | E18: ='Evolutive SFP'!C12/'Evolutive SFP'!C30 -> 0.10695511 | F18: ='Evolutive SFP'!D12/'Evolutive SFP'!D30 -> 0.10858163 | G18: ='Evolutive SFP'!E12/'Evolutive SFP'!E30 -> 0.10590697 | H18: ='Evolutive SFP'!F12/'Evolutive SFP'!F30 -> 0.12297832 | I18: ='Evolutive SFP'!G12/'Evolutive SFP'!G30 -> 0.10261531 | J18: ='Evolutive SFP'!H12/'Evolutive SFP'!H30 -> 0.10425132 | K18: ='Evolutive SFP'!I12/'Evolutive SFP'!I30 -> 0.10881614 | ... CG18: ='Evolutive SFP'!CE12/'Evolutive SFP'!CE30 -> 0
B19: PI to CC ratio | C19: Max 5% | D19: ='Evolutive SFP'!B12/('CAELS (2)'!D3*1000000) -> 0.23744504 | E19: ='Evolutive SFP'!C12/('CAELS (2)'!E3*1000000) -> 0.28631877 | F19: ='Evolutive SFP'!D12/('CAELS (2)'!F3*1000000) -> 0.30428513 | G19: ='Evolutive SFP'!E12/('CAELS (2)'!G3*1000000) -> 0.29872893 | H19: ='Evolutive SFP'!F12/('CAELS (2)'!H3*1000000) -> 0.24623453 | I19: ='Evolutive SFP'!G12/('CAELS (2)'!I3*1000000) -> 0.32397695 | J19: ='Evolutive SFP'!H12/('CAELS (2)'!J3*1000000) -> 0.31590917 | K19: ='Evolutive SFP'!I12/('CAELS (2)'!K3*1000000) -> 0.32554669 | ... CG19: ='Evolutive SFP'!CE12/('CAELS (2)'!CG3*1000000) -> 0
B20: Loans to total Deposits | BG20: =Financials!BF31/Financials!BF5 -> 0.50975336 | BH20: =Financials!BG31/Financials!BG5 -> 0.54981248 | BI20: =Financials!BH31/Financials!BH5 -> 0.52698766 | BJ20: =Financials!BI31/Financials!BI5 -> 0.56106327 | BK20: =Financials!BJ31/Financials!BJ5 -> 0.56976686 | BL20: =Financials!BK31/Financials!BK5 -> 0.57076802 | BM20: =Financials!BL31/Financials!BL5 -> 0.5478281 | BN20: =Financials!BM31/Financials!BM5 -> 0.59392509 | ... CC20: =Financials!CB31/Financials!CB5 -> 0.60030113
B21: Gross loans to Total Assets | D21: ='Evolutive SFP'!B14/'Evolutive SFP'!B26 -> 0.32114171 | E21: ='Evolutive SFP'!C14/'Evolutive SFP'!C26 -> 0.41090826 | F21: ='Evolutive SFP'!D14/'Evolutive SFP'!D26 -> 0.55125322 | G21: ='Evolutive SFP'!E14/'Evolutive SFP'!E26 -> 0.55656568 | H21: ='Evolutive SFP'!F14/'Evolutive SFP'!F26 -> 0.65120209 | I21: ='Evolutive SFP'!G14/'Evolutive SFP'!G26 -> 0.57779245 | J21: ='Evolutive SFP'!H14/'Evolutive SFP'!H26 -> 0.62318042 | K21: ='Evolutive SFP'!I14/'Evolutive SFP'!I26 -> 0.62847113 | ... CG21: ='Evolutive SFP'!CE14/'Evolutive SFP'!CE26 -> 0.50701148
A22: FUNDING MIX | B22: Total Deposits/Total Assets | D22: ='Evolutive SFP'!B30/'Evolutive SFP'!B26 -> 0.58218518 | E22: ='Evolutive SFP'!C30/'Evolutive SFP'!C26 -> 0.6278879 | F22: ='Evolutive SFP'!D30/'Evolutive SFP'!D26 -> 0.59642601 | G22: ='Evolutive SFP'!E30/'Evolutive SFP'!E26 -> 0.5795713 | H22: ='Evolutive SFP'!F30/'Evolutive SFP'!F26 -> 0.54509885 | I22: ='Evolutive SFP'!G30/'Evolutive SFP'!G26 -> 0.58915547 | J22: ='Evolutive SFP'!H30/'Evolutive SFP'!H26 -> 0.61961707 | K22: ='Evolutive SFP'!I30/'Evolutive SFP'!I26 -> 0.62516371 | ... CF22: ='Evolutive SFP'!CD30/'Evolutive SFP'!CD26 -> 0.97603969
B23: BOSA Deposits/Total Assets | D23: ='Evolutive SFP'!B29/'Evolutive SFP'!B26 -> 0.40153418 | E23: ='Evolutive SFP'!C29/'Evolutive SFP'!C26 -> 0.47815648 | F23: ='Evolutive SFP'!D29/'Evolutive SFP'!D26 -> 0.51106451 | G23: ='Evolutive SFP'!E29/'Evolutive SFP'!E26 -> 0.51998149 | H23: ='Evolutive SFP'!F29/'Evolutive SFP'!F26 -> 0.56827665 | I23: ='Evolutive SFP'!G29/'Evolutive SFP'!G26 -> 0.51795046 | J23: ='Evolutive SFP'!H29/'Evolutive SFP'!H26 -> 0.55543728 | K23: ='Evolutive SFP'!I29/'Evolutive SFP'!I26 -> 0.50181792 | ... CF23: ='Evolutive SFP'!CD29/'Evolutive SFP'!CD26 -> 0.75965519
B24: FOSA Deposits/Total Assets | D24: =('Evolutive SFP'!B27+'Evolutive SFP'!B28)/'Evolutive SFP'!B26 -> 0.180651 | E24: =('Evolutive SFP'!C27+'Evolutive SFP'!C28)/'Evolutive SFP'!C26 -> 0.14973142 | F24: =('Evolutive SFP'!D27+'Evolutive SFP'!D28)/'Evolutive SFP'!D26 -> 0.085361502 | G24: =('Evolutive SFP'!E27+'Evolutive SFP'!E28)/'Evolutive SFP'!E26 -> 0.059589808 | H24: =('Evolutive SFP'!F27+'Evolutive SFP'!F28)/'Evolutive SFP'!F26 -> -0.023177807 | I24: =('Evolutive SFP'!G27+'Evolutive SFP'!G28)/'Evolutive SFP'!G26 -> 0.071205013 | J24: =('Evolutive SFP'!H27+'Evolutive SFP'!H28)/'Evolutive SFP'!H26 -> 0.064179783 | K24: =('Evolutive SFP'!I27+'Evolutive SFP'!I28)/'Evolutive SFP'!I26 -> 0.12334579 | ... CF24: =('Evolutive SFP'!CD27+'Evolutive SFP'!CD28)/'Evolutive SFP'!CD26 -> 0.21638449
A25: GROWTH RATIOS | B25: Total Assets | E25: =(Financials!D4-Financials!C4)/Financials!C4 -> -0.15140409 | F25: =(Financials!E4-Financials!#REF!)/Financials!#REF! -> #REF! | G25: =(Financials!#REF!-Financials!#REF!)/Financials!#REF! -> #REF! | H25: =(Financials!G4-Financials!E4)/Financials!E4 -> -0.033928883 | I25: =(Financials!H4-Financials!G4)/Financials!G4 -> 0.10882181 | J25: =(Financials!I4-Financials!H4)/Financials!H4 -> -0.064083484 | K25: =(Financials!J4-Financials!I4)/Financials!I4 -> -0.050449933 | L25: =(Financials!K4-Financials!J4)/Financials!J4 -> -0.02848505 | M25: =(Financials!L4-Financials!K4)/Financials!K4 -> -0.031979222 | N25: =(Financials!M4-Financials!L4)/Financials!L4 -> -1 | O25: =(Financials!N4-Financials!M4)/Financials!M4 -> #DIV/0! | P25: =(Financials!O4-Financials!N4)/Financials!N4 -> #DIV/0! | ... AS25: =(Financials!AR4-Financials!AQ4)/Financials!AQ4 -> #DIV/0! | AT25: =(Financials!AT4-Financials!AR4)/Financials!AR4 -> #DIV/0! | AU25: =(Financials!AU4-Financials!AT4)/Financials!AT4 -> 1.0951597 | AV25: =(Financials!AV4-Financials!AU4)/Financials!AU4 -> 0.057208351 | AW25: =(Financials!AW4-Financials!AV4)/Financials!AV4 -> -0.019027663 | AX25: =(Financials!AX4-Financials!AW4)/Financials!AW4 -> 0.017426114 | AY25: =(Financials!AY4-Financials!AX4)/Financials!AX4 -> 0.047307223 | AZ25: =(Financials!AZ4-Financials!AY4)/Financials!AY4 -> -1 | BA25: =(Financials!BA4-Financials!AZ4)/Financials!AZ4 -> #DIV/0! | BB25: =(Financials!BB4-Financials!BA4)/Financials!BA4 -> 0.011877475 | ... BT25: =(Financials!BT4-Financials!BS4)/Financials!BS4 -> -0.12099086
B26: Total Deposits | D26: =Financials!D5/Financials!C5-1 -> -0.084787586 | E26: =Financials!#REF!/Financials!D5-1 -> #REF! | F26: =Financials!G5/Financials!E5-1 -> -0.11706693 | G26: =Financials!#REF!/Financials!#REF!-1 -> #REF! | H26: =Financials!H5/Financials!G5-1 -> 0.19844033 | I26: =Financials!I5/Financials!H5-1 -> -0.01569302 | J26: =Financials!J5/Financials!I5-1 -> -0.041949822 | K26: =Financials!K5/Financials!J5-1 -> -0.060255405 | L26: =Financials!L5/Financials!K5-1 -> -0.048903811 | M26: =Financials!M5/Financials!L5-1 -> -1 | N26: =Financials!N5/Financials!M5-1 -> #DIV/0! | O26: =Financials!O5/Financials!N5-1 -> #DIV/0! | ... AR26: =Financials!AR5/Financials!AQ5-1 -> #DIV/0! | AS26: =Financials!AT5/Financials!AR5-1 -> #DIV/0! | AT26: =Financials!AU5/Financials!AT5-1 -> 0.83778076 | AU26: =Financials!AU5/Financials!AT5-1 -> 0.83778076 | AV26: =Financials!AV5/Financials!AU5-1 -> -0.038693947 | AW26: =Financials!AW5/Financials!AV5-1 -> 0.0070816179 | AX26: =Financials!AX5/Financials!AW5-1 -> 0.023861639 | AY26: =Financials!AY5/Financials!AX5-1 -> 0.02773465 | AZ26: =Financials!AZ5/Financials!AY5-1 -> -1 | BA26: =Financials!BA5/Financials!AZ5-1 -> #DIV/0! | BB26: =Financials!BB5/Financials!BA5-1 -> -0.011942144 | ... BT26: =Financials!BT5/Financials!BS5-1 -> -0.04343348
B27: BOSA Deposits | D27: =Financials!D6/Financials!C6-1 -> 0.010528248 | E27: =Financials!#REF!/Financials!D6-1 -> #REF! | F27: =Financials!G6/Financials!E6-1 -> 0.074219882 | G27: =Financials!#REF!/Financials!#REF!-1 -> #REF! | H27: =Financials!H6/Financials!G6-1 -> 0.010625314 | I27: =Financials!I6/Financials!H6-1 -> 0.0036537587 | J27: =Financials!J6/Financials!I6-1 -> -0.14211514 | K27: =Financials!K6/Financials!J6-1 -> 0.18584812 | L27: =Financials!L6/Financials!K6-1 -> 0.00085274746 | M27: =Financials!M6/Financials!L6-1 -> -1 | N27: =Financials!N6/Financials!M6-1 -> #DIV/0! | O27: =Financials!O6/Financials!N6-1 -> #DIV/0! | ... AR27: =Financials!AR6/Financials!AQ6-1 -> #DIV/0! | AS27: =Financials!AT6/Financials!AR6-1 -> #DIV/0! | AT27: =Financials!AU6/Financials!AT6-1 -> -0.00023508934 | AU27: =Financials!AV6/Financials!AU6-1 -> -0.00057436344 | AV27: =Financials!AW6/Financials!AV6-1 -> -0.0005122848 | AW27: =Financials!AX6/Financials!AW6-1 -> 0.0014696329 | AX27: =Financials!AY6/Financials!AX6-1 -> -0.0013276744 | AY27: =Financials!AZ6/Financials!AY6-1 -> -1 | AZ27: =Financials!BA6/Financials!AZ6-1 -> #DIV/0! | BA27: =Financials!BB6/Financials!BA6-1 -> -0.014568554 | ... BT27: =Financials!BU6/Financials!BT6-1 -> 0.010172952
B28: FOSA Deposits | D28: =Financials!D7/Financials!C7-1 -> -0.29664672 | E28: =Financials!#REF!/Financials!D7-1 -> #REF! | F28: =Financials!G7/Financials!E7-1 -> -1.2623128 | G28: =Financials!#REF!/Financials!#REF!-1 -> #REF! | H28: =Financials!H7/Financials!G7-1 -> -4.406434 | I28: =Financials!I7/Financials!H7-1 -> -0.1564229 | J28: =Financials!J7/Financials!I7-1 -> 0.82492053 | K28: =Financials!K7/Financials!J7-1 -> -1.0614988 | L28: =Financials!L7/Financials!K7-1 -> 3.8544192 | M28: =Financials!M7/Financials!L7-1 -> -1 | N28: =Financials!N7/Financials!M7-1 -> #DIV/0! | O28: =Financials!O7/Financials!N7-1 -> #DIV/0! | ... AR28: =Financials!AR7/Financials!AQ7-1 -> #DIV/0! | AS28: =Financials!AT7/Financials!AR7-1 -> #DIV/0! | AT28: =Financials!AU7/Financials!AT7-1 -> -2.2049682 | AU28: =Financials!AV7/Financials!AU7-1 -> -0.15353161 | AV28: =Financials!AW7/Financials!AV7-1 -> 0.034092637 | AW28: =Financials!AX7/Financials!AW7-1 -> 0.10084325 | AX28: =Financials!AY7/Financials!AX7-1 -> 0.11862894 | AY28: =Financials!AZ7/Financials!AY7-1 -> -1 | AZ28: =Financials!BA7/Financials!AZ7-1 -> #DIV/0! | BA28: =Financials!BB7/Financials!BA7-1 -> -0.0022941448 | ... BT28: =Financials!BU7/Financials!BT7-1 -> 0.19402424
B29: Total Loans & advances | D29: =Financials!D31/Financials!C31-1 -> 0.085798138 | E29: =Financials!#REF!/Financials!D31-1 -> #REF! | F29: =Financials!G31/Financials!E31-1 -> 0.1412315 | G29: =Financials!#REF!/Financials!#REF!-1 -> #REF! | H29: =Financials!H31/Financials!G31-1 -> -0.016175039 | I29: =Financials!I31/Financials!H31-1 -> 0.0094366014 | J29: =Financials!J31/Financials!I31-1 -> -0.042388386 | K29: =Financials!K31/Financials!J31-1 -> 0.0032150515 | L29: =Financials!L31/Financials!K31-1 -> 0.0030599629 | M29: =Financials!M31/Financials!L31-1 -> -1 | N29: =Financials!N31/Financials!M31-1 -> #DIV/0! | O29: =Financials!O31/Financials!N31-1 -> #DIV/0! | ... AR29: =Financials!AR31/Financials!AQ31-1 -> #DIV/0! | AS29: =Financials!AT31/Financials!AR31-1 -> #DIV/0! | AT29: =Financials!AU31/Financials!AT31-1 -> -0.92307267 | AU29: =Financials!AV31/Financials!AU31-1 -> 0.36479395 | AV29: =Financials!AW31/Financials!AV31-1 -> -0.011484552 | AW29: =Financials!AX31/Financials!AW31-1 -> -0.060958225 | AX29: =Financials!AY31/Financials!AX31-1 -> 0.057908564 | AY29: =Financials!AZ31/Financials!AY31-1 -> -1 | AZ29: =Financials!BA31/Financials!AZ31-1 -> #DIV/0! | BA29: =Financials!BB31/Financials!BA31-1 -> 0.031822614 | ... BE29: =Financials!BF31/Financials!BE31-1 -> -0.099414552 | BF29: =Financials!#REF!/Financials!BF31-1 -> #REF! | BG29: =Financials!#REF!/Financials!#REF!-1 -> #REF! | BH29: =Financials!#REF!/Financials!#REF!-1 -> #REF! | BI29: =Financials!#REF!/Financials!#REF!-1 -> #REF! | BJ29: =Financials!#REF!/Financials!#REF!-1 -> #REF! | BK29: =Financials!#REF!/Financials!#REF!-1 -> #REF! | BL29: =Financials!#REF!/Financials!#REF!-1 -> #REF! | BM29: =Financials!#REF!/Financials!#REF!-1 -> #REF! | BN29: =Financials!#REF!/Financials!#REF!-1 -> #REF! | ... BT29: =Financials!#REF!/Financials!#REF!-1 -> #REF!
B30: Core capital | D30: =Financials!D11/Financials!C11-1 -> -0.1615267 | E30: =Financials!#REF!/Financials!D11-1 -> #REF! | F30: =Financials!G11/Financials!E11-1 -> 0.23575329 | G30: =Financials!#REF!/Financials!#REF!-1 -> #REF! | H30: =Financials!H11/Financials!G11-1 -> -0.23996281 | I30: =Financials!I11/Financials!H11-1 -> 0.025538297 | J30: =Financials!J11/Financials!I11-1 -> -0.02960412 | K30: =Financials!K11/Financials!J11-1 -> -0.039583284 | L30: =Financials!L11/Financials!K11-1 -> -0.0022358543 | M30: =Financials!M11/Financials!L11-1 -> -1 | N30: =Financials!N11/Financials!M11-1 -> #DIV/0! | O30: =Financials!O11/Financials!N11-1 -> #DIV/0! | ... AR30: =Financials!AR11/Financials!AQ11-1 -> #DIV/0! | AS30: =Financials!AT11/Financials!AR11-1 -> #DIV/0! | AT30: =Financials!AU11/Financials!AT11-1 -> -0.017930071 | AU30: =Financials!AV11/Financials!AU11-1 -> -0.17850813 | AV30: =Financials!AW11/Financials!AV11-1 -> 0.013947835 | AW30: =Financials!AX11/Financials!AW11-1 -> 0.020253906 | AX30: =Financials!AY11/Financials!AX11-1 -> 0.0027714144 | AY30: =Financials!AZ11/Financials!AY11-1 -> -1 | AZ30: =Financials!BA11/Financials!AZ11-1 -> #DIV/0! | BA30: =Financials!BB11/Financials!BA11-1 -> -0.088430746 | ... BE30: =Financials!BF11/Financials!BE11-1 -> 0.050815205 | BF30: =Financials!#REF!/Financials!BF11-1 -> #REF! | BG30: =Financials!#REF!/Financials!#REF!-1 -> #REF! | BH30: =Financials!#REF!/Financials!#REF!-1 -> #REF! | BI30: =Financials!#REF!/Financials!#REF!-1 -> #REF! | BJ30: =Financials!#REF!/Financials!#REF!-1 -> #REF! | BK30: =Financials!#REF!/Financials!#REF!-1 -> #REF! | BL30: =Financials!#REF!/Financials!#REF!-1 -> #REF! | BM30: =Financials!#REF!/Financials!#REF!-1 -> #REF! | BN30: =Financials!#REF!/Financials!#REF!-1 -> #REF! | ... BT30: =Financials!#REF!/Financials!#REF!-1 -> #REF!
B31: Turnover | D31: =Financials!D37/Financials!C37-1 -> 0.18215094 | E31: =Financials!#REF!/Financials!D37-1 -> #REF! | F31: =Financials!G37/Financials!E37-1 -> -0.92160819 | G31: =Financials!#REF!/Financials!#REF!-1 -> #REF! | H31: =Financials!H37/Financials!G37-1 -> 1.0233396 | I31: =Financials!I37/Financials!H37-1 -> 0.45210015 | J31: =Financials!J37/Financials!I37-1 -> 0.29865657 | K31: =Financials!K37/Financials!J37-1 -> 0.03761907 | L31: =Financials!L37/Financials!K37-1 -> 0.047324839 | M31: =Financials!M37/Financials!L37-1 -> -1 | N31: =Financials!N37/Financials!M37-1 -> #DIV/0! | O31: =Financials!O37/Financials!N37-1 -> #DIV/0! | ... AR31: =Financials!AR37/Financials!AQ37-1 -> #DIV/0! | AS31: =Financials!AT37/Financials!AR37-1 -> #DIV/0! | AT31: =Financials!AU37/Financials!AT37-1 -> #DIV/0! | AU31: =Financials!AV37/Financials!AU37-1 -> 0.68083848 | AV31: =Financials!AW37/Financials!AV37-1 -> 38.720499 | AW31: =Financials!AX37/Financials!AW37-1 -> 0.019139369 | AX31: =Financials!AY37/Financials!AX37-1 -> 0.024394851 | AY31: =Financials!AZ37/Financials!AY37-1 -> 0.038704831 | AZ31: =Financials!BA37/Financials!AZ37-1 -> -1 | BA31: =Financials!BB37/Financials!BA37-1 -> #DIV/0! | ... BE31: =Financials!BF37/Financials!BE37-1 -> 0.21355639 | BF31: =Financials!#REF!/Financials!BF37-1 -> #REF! | BG31: =Financials!#REF!/Financials!#REF!-1 -> #REF! | BH31: =Financials!#REF!/Financials!#REF!-1 -> #REF! | BI31: =Financials!#REF!/Financials!#REF!-1 -> #REF! | BJ31: =Financials!#REF!/Financials!#REF!-1 -> #REF! | BK31: =Financials!#REF!/Financials!#REF!-1 -> #REF! | BL31: =Financials!#REF!/Financials!#REF!-1 -> #REF! | BM31: =Financials!#REF!/Financials!#REF!-1 -> #REF! | BN31: =Financials!#REF!/Financials!#REF!-1 -> #REF! | ... BT31: =Financials!#REF!/Financials!#REF!-1 -> #REF!
B32: Membership
B33: Expenses | D33: ='Evolutitve SCI'!C39/'Evolutitve SCI'!B39-1 -> 0.082670219 | E33: ='Evolutitve SCI'!#REF!/'Evolutitve SCI'!C39-1 -> #REF! | F33: ='Evolutitve SCI'!F39/'Evolutitve SCI'!E39-1 -> #DIV/0! | G33: ='Evolutitve SCI'!#REF!/'Evolutitve SCI'!E39-1 -> #REF! | H33: ='Evolutitve SCI'!G39/'Evolutitve SCI'!F39-1 -> 1.093513 | I33: ='Evolutitve SCI'!H39/'Evolutitve SCI'!G39-1 -> 0.35869958 | J33: ='Evolutitve SCI'!I39/'Evolutitve SCI'!H39-1 -> 0.38008027 | K33: ='Evolutitve SCI'!J39/'Evolutitve SCI'!I39-1 -> 0.16646602 | L33: ='Evolutitve SCI'!K39/'Evolutitve SCI'!J39-1 -> 0.066991117 | M33: ='Evolutitve SCI'!L39/'Evolutitve SCI'!K39-1 -> -1 | N33: ='Evolutitve SCI'!M39/'Evolutitve SCI'!L39-1 -> #DIV/0! | O33: ='Evolutitve SCI'!N39/'Evolutitve SCI'!M39-1 -> #DIV/0! | ... BT33: ='Evolutitve SCI'!BS39/'Evolutitve SCI'!BR39-1 -> #DIV/0!
A34: Efficiency Ratios | B34: FinCost-Deposits/Avg Deposits | E34: =Financials!D44/('Evolutive SFP'!B29+'Evolutive SFP'!C29)/2 -> 0.02923856 | F34: =Financials!E44/('Evolutive SFP'!#REF!+'Evolutive SFP'!D29)/2 -> #REF! | G34: =Financials!#REF!/('Evolutive SFP'!D29+'Evolutive SFP'!E29)/2 -> #REF! | H34: =Financials!G44/('Evolutive SFP'!D29+'Evolutive SFP'!F29)/2 -> 0.00011812267 | I34: =Financials!H44/('Evolutive SFP'!F29+'Evolutive SFP'!G29)/2 -> 0 | J34: =Financials!I44/('Evolutive SFP'!G29+'Evolutive SFP'!H29)/2 -> 0.0015360812 | K34: =Financials!J44/('Evolutive SFP'!H29+'Evolutive SFP'!I29)/2 -> 0.005270047 | L34: =Financials!K44/('Evolutive SFP'!I29+'Evolutive SFP'!J29)/2 -> 0.0058374242 | M34: =Financials!L44/('Evolutive SFP'!J29+'Evolutive SFP'!K29)/2 -> 0.0066698195 | N34: =Financials!M44/('Evolutive SFP'!K29+'Evolutive SFP'!L29)/2 -> 0 | O34: =Financials!N44/('Evolutive SFP'!L29+'Evolutive SFP'!M29)/2 -> #DIV/0! | P34: =Financials!O44/('Evolutive SFP'!M29+'Evolutive SFP'!N29)/2 -> #DIV/0! | ... AS34: =Financials!AR44/('Evolutive SFP'!AP29+'Evolutive SFP'!AQ29)/2 -> #DIV/0! | AT34: =Financials!AT44/('Evolutive SFP'!AQ29+'Evolutive SFP'!AR29)/2 -> #DIV/0! | AU34: =Financials!AU44/('Evolutive SFP'!AR29+'Evolutive SFP'!AS29)/2 -> 0 | AV34: =Financials!AV44/('Evolutive SFP'!AS29+'Evolutive SFP'!AT29)/2 -> 0 | AW34: =Financials!AW44/('Evolutive SFP'!AT29+'Evolutive SFP'!AU29)/2 -> 0.00062034628 | AX34: =Financials!AX44/('Evolutive SFP'!AU29+'Evolutive SFP'!AV29)/2 -> 0.00062068352 | AY34: =Financials!AY44/('Evolutive SFP'!AV29+'Evolutive SFP'!AW29)/2 -> 8.1978499e-05 | AZ34: =Financials!AZ44/('Evolutive SFP'!AW29+'Evolutive SFP'!AX29)/2 -> 8.1972765e-05 | BA34: =Financials!BA44/('Evolutive SFP'!AX29+'Evolutive SFP'!AY29)/2 -> 0 | ... BF34: =Financials!BF44/('Evolutive SFP'!BC29+'Evolutive SFP'!BD29)/2 -> 0.00041827889 | BG34: =Financials!#REF!/('Evolutive SFP'!BD29+'Evolutive SFP'!BE29)/2 -> #REF! | BH34: =Financials!#REF!/('Evolutive SFP'!BE29+'Evolutive SFP'!BF29)/2 -> #REF! | BI34: =Financials!#REF!/('Evolutive SFP'!BF29+'Evolutive SFP'!BG29)/2 -> #REF! | BJ34: =Financials!#REF!/('Evolutive SFP'!BG29+'Evolutive SFP'!BH29)/2 -> #REF! | BK34: =Financials!#REF!/('Evolutive SFP'!BH29+'Evolutive SFP'!BI29)/2 -> #REF! | BL34: =Financials!#REF!/('Evolutive SFP'!BI29+'Evolutive SFP'!BJ29)/2 -> #REF! | BM34: =Financials!#REF!/('Evolutive SFP'!BJ29+'Evolutive SFP'!BK29)/2 -> #REF! | BN34: =Financials!#REF!/('Evolutive SFP'!BK29+'Evolutive SFP'!BL29)/2 -> #REF! | ... BT34: =Financials!#REF!/('Evolutive SFP'!BQ29+'Evolutive SFP'!BR29)/2 -> #REF!
B35: FinCost-Shares/Avg Share capital | E35: =Financials!D45/('Evolutive SFP'!B38+'Evolutive SFP'!C38)/2 -> 0 | F35: =Financials!E45/('Evolutive SFP'!#REF!+'Evolutive SFP'!D38)/2 -> #REF! | G35: =Financials!#REF!/('Evolutive SFP'!D38+'Evolutive SFP'!E38)/2 -> #REF! | H35: =Financials!G45/('Evolutive SFP'!D38+'Evolutive SFP'!F38)/2 -> 0 | I35: =Financials!H45/('Evolutive SFP'!F38+'Evolutive SFP'!G38)/2 -> 0.001524871 | J35: =Financials!I45/('Evolutive SFP'!G38+'Evolutive SFP'!H38)/2 -> 0 | K35: =Financials!J45/('Evolutive SFP'!H38+'Evolutive SFP'!I38)/2 -> 0 | L35: =Financials!K45/('Evolutive SFP'!I38+'Evolutive SFP'!J38)/2 -> 0 | M35: =Financials!L45/('Evolutive SFP'!J38+'Evolutive SFP'!K38)/2 -> 0 | N35: =Financials!M45/('Evolutive SFP'!K38+'Evolutive SFP'!L38)/2 -> 0 | O35: =Financials!N45/('Evolutive SFP'!L38+'Evolutive SFP'!M38)/2 -> #DIV/0! | P35: =Financials!O45/('Evolutive SFP'!M38+'Evolutive SFP'!N38)/2 -> #DIV/0! | ... AS35: =Financials!AR45/('Evolutive SFP'!AP38+'Evolutive SFP'!AQ38)/2 -> #DIV/0! | AT35: =Financials!AT45/('Evolutive SFP'!AQ38+'Evolutive SFP'!AR38)/2 -> #DIV/0! | AU35: =Financials!AU45/('Evolutive SFP'!AR38+'Evolutive SFP'!AS38)/2 -> 0 | AV35: =Financials!AV45/('Evolutive SFP'!AS38+'Evolutive SFP'!AT38)/2 -> 0 | AW35: =Financials!AW45/('Evolutive SFP'!AT38+'Evolutive SFP'!AU38)/2 -> 0 | AX35: =Financials!AX45/('Evolutive SFP'!AU38+'Evolutive SFP'!AV38)/2 -> 0 | AY35: =Financials!AY45/('Evolutive SFP'!AV38+'Evolutive SFP'!AW38)/2 -> 0 | AZ35: =Financials!AZ45/('Evolutive SFP'!AW38+'Evolutive SFP'!AX38)/2 -> 0 | BA35: =Financials!BA45/('Evolutive SFP'!AX38+'Evolutive SFP'!AY38)/2 -> 0 | ... BF35: =Financials!BF45/('Evolutive SFP'!BC38+'Evolutive SFP'!BD38)/2 -> 0 | BG35: =Financials!#REF!/('Evolutive SFP'!BD38+'Evolutive SFP'!BE38)/2 -> #REF! | BH35: =Financials!#REF!/('Evolutive SFP'!BE38+'Evolutive SFP'!BF38)/2 -> #REF! | BI35: =Financials!#REF!/('Evolutive SFP'!BF38+'Evolutive SFP'!BG38)/2 -> #REF! | BJ35: =Financials!#REF!/('Evolutive SFP'!BG38+'Evolutive SFP'!BH38)/2 -> #REF! | BK35: =Financials!#REF!/('Evolutive SFP'!BH38+'Evolutive SFP'!BI38)/2 -> #REF! | BL35: =Financials!#REF!/('Evolutive SFP'!BI38+'Evolutive SFP'!BJ38)/2 -> #REF! | BM35: =Financials!#REF!/('Evolutive SFP'!BJ38+'Evolutive SFP'!BK38)/2 -> #REF! | BN35: =Financials!#REF!/('Evolutive SFP'!BK38+'Evolutive SFP'!BL38)/2 -> #REF! | ... BT35: =Financials!#REF!/('Evolutive SFP'!BQ38+'Evolutive SFP'!BR38)/2 -> #REF!
B36: FinCost-Ext Loans/Avg Ext Loans | E36: =Financials!D46/(Financials!C31+Financials!D31)/2 -> 0.001468063 | F36: =Financials!E46/(Financials!#REF!+Financials!E31)/2 -> #REF! | G36: =Financials!#REF!/(Financials!#REF!+Financials!#REF!)/2 -> #REF! | H36: =Financials!G46/(Financials!E31+Financials!G31)/2 -> 8.9985357e-05 | I36: =Financials!H46/(Financials!G31+Financials!H31)/2 -> 0.00020030561 | J36: =Financials!I46/(Financials!H31+Financials!I31)/2 -> 0.00032653377 | K36: =Financials!J46/(Financials!I31+Financials!J31)/2 -> 0.00033204491 | L36: =Financials!K46/(Financials!J31+Financials!K31)/2 -> 0.00038092029 | M36: =Financials!L46/(Financials!K31+Financials!L31)/2 -> 0.00037972893 | N36: =Financials!M46/(Financials!L31+Financials!M31)/2 -> 0 | O36: =Financials!N46/(Financials!M31+Financials!N31)/2 -> #DIV/0! | P36: =Financials!O46/(Financials!N31+Financials!O31)/2 -> #DIV/0! | ... AS36: =Financials!AR46/(Financials!AQ31+Financials!AR31)/2 -> #DIV/0! | AT36: =Financials!AT46/(Financials!AR31+Financials!AT31)/2 -> 0 | AU36: =Financials!AU46/(Financials!AT31+Financials!AU31)/2 -> 0 | AV36: =Financials!AV46/(Financials!AU31+Financials!AV31)/2 -> 0 | AW36: =Financials!AW46/(Financials!AV31+Financials!AW31)/2 -> 0 | AX36: =Financials!AX46/(Financials!AW31+Financials!AX31)/2 -> 0 | AY36: =Financials!AY46/(Financials!AX31+Financials!AY31)/2 -> 0 | AZ36: =Financials!AZ46/(Financials!AY31+Financials!AZ31)/2 -> 0 | BA36: =Financials!BA46/(Financials!AZ31+Financials!BA31)/2 -> 0 | BB36: =Financials!BB46/(Financials!BA31+Financials!BB31)/2 -> 0.027123247 | ... BF36: =Financials!BF46/(Financials!BE31+Financials!BF31)/2 -> 0.0036106599 | BG36: =Financials!#REF!/(Financials!BF31+Financials!#REF!)/2 -> #REF! | BH36: =Financials!#REF!/(Financials!BG31+Financials!#REF!)/2 -> #REF! | BI36: =Financials!#REF!/(Financials!BH31+Financials!#REF!)/2 -> #REF! | BJ36: =Financials!#REF!/(Financials!BI31+Financials!#REF!)/2 -> #REF! | BK36: =Financials!#REF!/(Financials!BJ31+Financials!#REF!)/2 -> #REF! | BL36: =Financials!#REF!/(Financials!BK31+Financials!#REF!)/2 -> #REF! | BM36: =Financials!#REF!/(Financials!BL31+Financials!#REF!)/2 -> #REF! | BN36: =Financials!#REF!/(Financials!BM31+Financials!#REF!)/2 -> #REF! | ... BT36: =Financials!#REF!/(Financials!BS31+Financials!#REF!)/2 -> #REF!
B37: OpEx/Average Total Assets | E37: =Financials!D47/(Financials!C4+Financials!D4)/2 -> 0.02206777 | F37: =Financials!E47/(Financials!#REF!+Financials!E4)/2 -> #REF! | G37: =Financials!#REF!/(Financials!#REF!+Financials!#REF!)/2 -> #REF! | H37: =Financials!G47/(Financials!E4+Financials!G4)/2 -> 0.003376425 | I37: =Financials!H47/(Financials!G4+Financials!H4)/2 -> 0.0059821727 | J37: =Financials!I47/(Financials!H4+Financials!I4)/2 -> 0.008812576 | K37: =Financials!J47/(Financials!I4+Financials!J4)/2 -> 0.011399116 | L37: =Financials!K47/(Financials!J4+Financials!K4)/2 -> 0.013997115 | M37: =Financials!L47/(Financials!K4+Financials!L4)/2 -> 0.014836476 | N37: =Financials!M47/(Financials!L4+Financials!M4)/2 -> 0 | O37: =Financials!N47/(Financials!M4+Financials!N4)/2 -> #DIV/0! | P37: =Financials!O47/(Financials!N4+Financials!O4)/2 -> #DIV/0! | ... AS37: =Financials!AR47/(Financials!AQ4+Financials!AR4)/2 -> #DIV/0! | AT37: =Financials!AT47/(Financials!AR4+Financials!AT4)/2 -> 0 | AU37: =Financials!AU47/(Financials!AT4+Financials!AU4)/2 -> 0.0018198438 | AV37: =Financials!AV47/(Financials!AU4+Financials!AV4)/2 -> 0.0037663086 | AW37: =Financials!AW47/(Financials!AV4+Financials!AW4)/2 -> 0.0049798565 | AX37: =Financials!AX47/(Financials!AW4+Financials!AX4)/2 -> 0.0064733404 | AY37: =Financials!AY47/(Financials!AX4+Financials!AY4)/2 -> 0.0087706095 | AZ37: =Financials!AZ47/(Financials!AY4+Financials!AZ4)/2 -> 0.018746894 | BA37: =Financials!BA47/(Financials!AZ4+Financials!BA4)/2 -> 0 | BB37: =Financials!BB47/(Financials!BA4+Financials!BB4)/2 -> 0.013702807 | ... BF37: =Financials!BF47/(Financials!BE4+Financials!BF4)/2 -> 0.021857588 | BG37: =Financials!#REF!/(Financials!BF4+Financials!#REF!)/2 -> #REF! | BH37: =Financials!#REF!/(Financials!BG4+Financials!#REF!)/2 -> #REF! | BI37: =Financials!#REF!/(Financials!BH4+Financials!#REF!)/2 -> #REF! | BJ37: =Financials!#REF!/(Financials!BI4+Financials!#REF!)/2 -> #REF! | BK37: =Financials!#REF!/(Financials!BJ4+Financials!#REF!)/2 -> #REF! | BL37: =Financials!#REF!/(Financials!BK4+Financials!#REF!)/2 -> #REF! | BM37: =Financials!#REF!/(Financials!BL4+Financials!#REF!)/2 -> #REF! | BN37: =Financials!#REF!/(Financials!BM4+Financials!#REF!)/2 -> #REF! | ... BT37: =Financials!#REF!/(Financials!BS4+Financials!#REF!)/2 -> #REF!
B38: Opex/Turnover | E38: =Financials!D47/Financials!D37 -> 0.48148834 | F38: =Financials!E47/Financials!E37 -> 0.65743148 | G38: =Financials!#REF!/Financials!#REF! -> #REF! | H38: =Financials!G47/Financials!G37 -> 0.89548813 | I38: =Financials!H47/Financials!H37 -> 0.81253605 | J38: =Financials!I47/Financials!I37 -> 0.83907059 | K38: =Financials!J47/Financials!J37 -> 0.7876937 | L38: =Financials!K47/Financials!K37 -> 0.89509742 | M38: =Financials!L47/Financials!L37 -> 0.87853737 | N38: =Financials!M47/Financials!M37 -> #DIV/0! | O38: =Financials!N47/Financials!N37 -> #DIV/0! | ... AS38: =Financials!AR47/Financials!AR37 -> #DIV/0! | AT38: =Financials!AT47/Financials!AT37 -> #DIV/0! | AU38: =Financials!AU47/Financials!AU37 -> 5.6951999 | AV38: =Financials!AV47/Financials!AV37 -> 9.7651094 | AW38: =Financials!AW47/Financials!AW37 -> 0.3309208 | AX38: =Financials!AX47/Financials!AX37 -> 0.42167524 | AY38: =Financials!AY47/Financials!AY37 -> 0.57583797 | AZ38: =Financials!AZ47/Financials!AZ37 -> 0.60617605 | BA38: =Financials!BA47/Financials!BA37 -> #DIV/0! | ... BF38: =Financials!BF47/Financials!BF37 -> 0.50924637 | BG38: =Financials!#REF!/Financials!#REF! -> #REF! | BH38: =Financials!#REF!/Financials!#REF! -> #REF! | BI38: =Financials!#REF!/Financials!#REF! -> #REF! | BJ38: =Financials!#REF!/Financials!#REF! -> #REF! | BK38: =Financials!#REF!/Financials!#REF! -> #REF! | BL38: =Financials!#REF!/Financials!#REF! -> #REF! | BM38: =Financials!#REF!/Financials!#REF! -> #REF! | BN38: =Financials!#REF!/Financials!#REF! -> #REF! | ... BT38: =Financials!#REF!/Financials!#REF! -> #REF!
B39: Avge yield on Net loans | E39: =Financials!D38/('Evolutive SFP'!C13+'Evolutive SFP'!B13)/2 -> 0.078352184 | F39: =Financials!E38/('Evolutive SFP'!D13+'Evolutive SFP'!#REF!)/2 -> #REF! | G39: =Financials!#REF!/('Evolutive SFP'!E13+'Evolutive SFP'!D13)/2 -> #REF! | H39: =Financials!G38/('Evolutive SFP'!F13+'Evolutive SFP'!D13)/2 -> 0.0039064104 | I39: =Financials!H38/('Evolutive SFP'!G13+'Evolutive SFP'!F13)/2 -> 0.0078025411 | J39: =Financials!I38/('Evolutive SFP'!H13+'Evolutive SFP'!G13)/2 -> 0.011939773 | K39: =Financials!J38/('Evolutive SFP'!I13+'Evolutive SFP'!H13)/2 -> 0.01587037 | L39: =Financials!K38/('Evolutive SFP'!J13+'Evolutive SFP'!I13)/2 -> 0.017058215 | M39: =Financials!L38/('Evolutive SFP'!K13+'Evolutive SFP'!J13)/2 -> 0.017347049 | N39: =Financials!M38/('Evolutive SFP'!L13+'Evolutive SFP'!K13)/2 -> 0 | O39: =Financials!N38/('Evolutive SFP'!M13+'Evolutive SFP'!L13)/2 -> #DIV/0! | P39: =Financials!O38/('Evolutive SFP'!N13+'Evolutive SFP'!M13)/2 -> #DIV/0! | ... AS39: =Financials!AR38/('Evolutive SFP'!AQ13+'Evolutive SFP'!AP13)/2 -> #DIV/0! | AT39: =Financials!AT38/('Evolutive SFP'!AR13+'Evolutive SFP'!AQ13)/2 -> #DIV/0! | AU39: =Financials!AU38/('Evolutive SFP'!AS13+'Evolutive SFP'!AR13)/2 -> 0.0074630727 | AV39: =Financials!AV38/('Evolutive SFP'!AT13+'Evolutive SFP'!AS13)/2 -> 0.0062921353 | AW39: =Financials!AW38/('Evolutive SFP'!AU13+'Evolutive SFP'!AT13)/2 -> 0.010214338 | AX39: =Financials!AX38/('Evolutive SFP'!AV13+'Evolutive SFP'!AU13)/2 -> 0.0093748742 | AY39: =Financials!AY38/('Evolutive SFP'!AW13+'Evolutive SFP'!AV13)/2 -> 0.010890025 | AZ39: =Financials!AZ38/('Evolutive SFP'!AX13+'Evolutive SFP'!AW13)/2 -> 0.014140671 | BA39: =Financials!BA38/('Evolutive SFP'!AY13+'Evolutive SFP'!AX13)/2 -> 0 | ... BF39: =Financials!BF38/('Evolutive SFP'!BD13+'Evolutive SFP'!BC13)/2 -> 0.37562328 | BG39: =Financials!#REF!/('Evolutive SFP'!BE13+'Evolutive SFP'!BD13)/2 -> #REF! | BH39: =Financials!#REF!/('Evolutive SFP'!BF13+'Evolutive SFP'!BE13)/2 -> #REF! | BI39: =Financials!#REF!/('Evolutive SFP'!BG13+'Evolutive SFP'!BF13)/2 -> #REF! | BJ39: =Financials!#REF!/('Evolutive SFP'!BH13+'Evolutive SFP'!BG13)/2 -> #REF! | BK39: =Financials!#REF!/('Evolutive SFP'!BI13+'Evolutive SFP'!BH13)/2 -> #REF! | BL39: =Financials!#REF!/('Evolutive SFP'!BJ13+'Evolutive SFP'!BI13)/2 -> #REF! | BM39: =Financials!#REF!/('Evolutive SFP'!BK13+'Evolutive SFP'!BJ13)/2 -> #REF! | BN39: =Financials!#REF!/('Evolutive SFP'!BL13+'Evolutive SFP'!BK13)/2 -> #REF! | ... BT39: =Financials!#REF!/('Evolutive SFP'!BR13+'Evolutive SFP'!BQ13)/2 -> #REF!
B40: Avge yield on Gross loans | E40: =Financials!D37/('Evolutive SFP'!C14+'Evolutive SFP'!B14)/2 -> 0.12648693 | F40: =Financials!E37/('Evolutive SFP'!D14+'Evolutive SFP'!#REF!)/2 -> #REF! | G40: =Financials!#REF!/('Evolutive SFP'!E14+'Evolutive SFP'!D14)/2 -> #REF! | H40: =Financials!G37/('Evolutive SFP'!F14+'Evolutive SFP'!D14)/2 -> 0.0062803196 | I40: =Financials!H37/('Evolutive SFP'!G14+'Evolutive SFP'!F14)/2 -> 0.012018134 | J40: =Financials!I37/('Evolutive SFP'!H14+'Evolutive SFP'!G14)/2 -> 0.017512366 | K40: =Financials!J37/('Evolutive SFP'!I14+'Evolutive SFP'!H14)/2 -> 0.023126392 | L40: =Financials!K37/('Evolutive SFP'!J14+'Evolutive SFP'!I14)/2 -> 0.024488116 | M40: =Financials!L37/('Evolutive SFP'!K14+'Evolutive SFP'!J14)/2 -> 0.025566799 | N40: =Financials!M37/('Evolutive SFP'!L14+'Evolutive SFP'!K14)/2 -> 0 | O40: =Financials!N37/('Evolutive SFP'!M14+'Evolutive SFP'!L14)/2 -> #DIV/0! | P40: =Financials!O37/('Evolutive SFP'!N14+'Evolutive SFP'!M14)/2 -> #DIV/0! | ... AS40: =Financials!AR37/('Evolutive SFP'!AQ14+'Evolutive SFP'!AP14)/2 -> #DIV/0! | AT40: =Financials!AT37/('Evolutive SFP'!AR14+'Evolutive SFP'!AQ14)/2 -> #DIV/0! | AU40: =Financials!AU37/('Evolutive SFP'!AS14+'Evolutive SFP'!AR14)/2 -> 0.00071160009 | AV40: =Financials!AV37/('Evolutive SFP'!AT14+'Evolutive SFP'!AS14)/2 -> 0.0011106458 | AW40: =Financials!AW37/('Evolutive SFP'!AU14+'Evolutive SFP'!AT14)/2 -> 0.26115763 | AX40: =Financials!AX37/('Evolutive SFP'!AV14+'Evolutive SFP'!AU14)/2 -> 0.23191751 | AY40: =Financials!AY37/('Evolutive SFP'!AW14+'Evolutive SFP'!AV14)/2 -> 0.24646728 | AZ40: =Financials!AZ37/('Evolutive SFP'!AX14+'Evolutive SFP'!AW14)/2 -> 0.25687841 | BA40: =Financials!BA37/('Evolutive SFP'!AY14+'Evolutive SFP'!AX14)/2 -> 0 | ... BF40: =Financials!BF37/('Evolutive SFP'!BD14+'Evolutive SFP'!BC14)/2 -> 0.075198954 | BG40: =Financials!#REF!/('Evolutive SFP'!BE14+'Evolutive SFP'!BD14)/2 -> #REF! | BH40: =Financials!#REF!/('Evolutive SFP'!BF14+'Evolutive SFP'!BE14)/2 -> #REF! | BI40: =Financials!#REF!/('Evolutive SFP'!BG14+'Evolutive SFP'!BF14)/2 -> #REF! | BJ40: =Financials!#REF!/('Evolutive SFP'!BH14+'Evolutive SFP'!BG14)/2 -> #REF! | BK40: =Financials!#REF!/('Evolutive SFP'!BI14+'Evolutive SFP'!BH14)/2 -> #REF! | BL40: =Financials!#REF!/('Evolutive SFP'!BJ14+'Evolutive SFP'!BI14)/2 -> #REF! | BM40: =Financials!#REF!/('Evolutive SFP'!BK14+'Evolutive SFP'!BJ14)/2 -> #REF! | BN40: =Financials!#REF!/('Evolutive SFP'!BL14+'Evolutive SFP'!BK14)/2 -> #REF! | ... BT40: =Financials!#REF!/('Evolutive SFP'!BR14+'Evolutive SFP'!BQ14)/2 -> #REF!
A42: ALL/Average Gross Loan portfolio

Sheet Performance
A1: JUMUIKA SACCO SOCIETY LIMITED
A2: PERFORMANCE AND COMPLIANCE REPORT AS AT : 31st August, 2022
B3: Prudential Std | C3: Audited | D3: Returns | K3: Validated | L3: Aggregate for all Licensed Saccos
C4: 2021 | D4: 31st March , 2022 | E4: 30th June , 2022 | F4: 30th July, 2022 | G4: 31st August, 2022 | H4: 30th September 2022 | I4: 31st October 2022 | J4: 30th November 2022
A5: A. CAPITAL ADEQUACY
A6: Core Capital | B6: ≥10M | C6: -40822385 | D6: -65395648 | E6: -71627479 | F6: =F33 -> -70615672 | G6: =G33 -> -71411341 | K6: 0 | L6: 1.1913623e+11
A7: Core Capital/Total Assets | B7: ≥10% | C7: -0.20081315 | D7: -0.34156793 | E7: -0.34293282 | F7: =F6/F29 -> -0.34574101 | G7: =G6/G29 -> -0.35100678 | K7: #DIV/0! | L7: 0.17007848
A8: Institutional Capital/Total Assets | B8: ≥8% | C8: -0.26770739 | D8: -0.41347394 | E8: -0.40886186 | F8: =F34/F29 -> -0.41315986 | G8: =G34/G29 -> -0.41872423 | K8: #DIV/0! | L8: 0.10096958
A9: B. ASSET QUALITY
A10: NPL (Substandard+Doubtful+Loss) | B10: <5% | C10: 0.7956137 | D10: 0.76243011 | E10: 0.93029506 | F10: =F35/F32 -> 0.96545685 | G10: =G35/G32 -> 0.94416297 | K10: #DIV/0! | L10: 0.10428852
A11: Non-Earning Assets | B11: <10% | C11: 0.65156691 | D11: 0.73738833 | E11: 0.71435004 | F11: =F36/F29 -> 0.66118947 | G11: =G36/G29 -> 0.71190541 | K11: #DIV/0! | L11: 0.1015966
A12: Equity investments/Deposits | B12: <5% | C12: 0.076092834 | D12: 0.11994583 | E12: 0.077632237 | F12: =F37/F31 -> 0.1188392 | G12: =G37/G31 -> 0.13189621 | K12: #DIV/0! | L12: 0.028383024
A13: Equity investments/Core capital | B13: <40% | C13: -0.35046803 | D13: -0.34487463 | E13: -0.20043901 | F13: =F39/F33 -> -0.20331098 | G13: =G39/G33 -> -0.20104568 | K13: #DIV/0! | L13: 0.11815537
A14: C. EARNINGS RATING
A15: Yield on Gross Loans | C15: 0.12955272 | D15: 0.055607037 | E15: 0.073041417 | F15: =F48/F32 -> 0.088073787 | G15: =G48/G32 -> 0.091500709 | K15: #DIV/0! | L15: 0.079053241
A16: Total Expense/Total Income | C16: 1.0309882 | D16: 1.0285359 | E16: 0.96554979 | F16: =F49/F44 -> 0.91096741 | G16: =G49/G44 -> 0.97239789 | K16: #DIV/0! | L16: 0.7100904
A17: Net Income/Average Assets (ROA) | C17: -0.0032553493 | D17: -0.00088488991 | E17: 0.0019413843 | F17: =F50/F30 -> 0.0060419929 | G17: =G50/G30 -> 0.0018710308 | K17: #DIV/0! | L17: 0.018440749
A18: Operating Expenses/Financial Income (OPEX) | C18: 0.99960741 | D18: 0.90467168 | E18: 0.82880122 | F18: =F47/F45 -> 0.89869358 | G18: =G47/G45 -> 0.96882922 | K18: #DIV/0! | L18: 0.35649442
A19: D. LIQUIDITY
A20: Liquid Assets/Short-term Liabilities | B20: >15% | C20: 0.49262978 | D20: 0.45152825 | E20: 0.12992979 | F20: =F40/F41 -> 0.27286861 | G20: =G40/G41 -> 0.13045122 | K20: #DIV/0! | L20: 0.68306351
A21: External Borrowing/Total Assets | B21: <25% | C21: 0.1183489 | D21: 0.13483176 | E21: 0.1270555 | F21: =F42/F29 -> 0.13022225 | G21: =G42/G29 -> 0.13073254 | K21: #DIV/0! | L21: 0.034164731
A22: Liquid Assets/Total Assets | C22: 0.13590911 | D22: 0.11970731 | E22: 0.060202235 | F22: =F40/F29 -> 0.12255022 | G22: =G40/G29 -> 0.058784184 | K22: #DIV/0! | L22: 0.12737784
A23: E. STRUCTURE/SENSITIVITY TO RISK
A24: Gross loans /Total Assets | B24: 70-80 | C24: 0.49093504 | D24: 0.55873318 | E24: 0.54693953 | F24: =F32/F29 -> 0.53894887 | G24: =G32/G29 -> 0.55326347 | K24: #DIV/0! | L24: 0.76493348
A25: Gross loans/Deposits | B25: >100% | C25: 0.5307955 | D25: 0.56892012 | E25: 0.61771778 | F25: =F32/F31 -> 0.59929921 | G25: =G32/G31 -> 0.61282055 | K25: #DIV/0! | L25: 1.0803873
A26: Financial Investments/Total Assets | C26: 0.076092834 | D26: 0.11994583 | E26: 0.077632237 | F26: =F39/F29 -> 0.070292943 | G26: =G39/G29 -> 0.070568395 | K26: #DIV/0! | L26: 0.070833834
A27: Dividends+Interest on Deposits/Total Income | C27: 0 | D27: 0 | E27: 0 | F27: =F46/F44 -> 0 | G27: =G46/G44 -> 0 | K27: #DIV/0! | L27: 0.29279965
A28: F. KEY FINANCIAL STATISTICS | C28: 2015 | D28: 2016 | E28: 2017 | L28: AGGREGATE
A29: Total Assets | C29: 203285420 | D29: 1.9145723e+08 | E29: 2.0886738e+08 | F29: ='Evolutive SFP'!BY26 -> 2.0424442e+08 | G29: ='Evolutive SFP'!BZ26 -> 2.0344718e+08 | L29: 7.0047796e+11
A30: Average Assets | C30: 196499650 | D30: 1.9190683e+08 | E30: 2.0302204e+08 | F30: =(D29+E29)/2 -> 2.001623e+08 | G30: =(E29+F29)/2 -> 2.065559e+08 | L30: 6.733706e+11
A31: Total Deposits | C31: 188019559 | D31: 1.8802904e+08 | E31: 1.849353e+08 | F31: ='Evolutive SFP'!BY30 -> 1.836767e+08 | G31: ='Evolutive SFP'!BZ30 -> 1.8367513e+08 | L31: 4.9595087e+11
A32: Gross Loans | C32: 99799936 | D32: 1.0697351e+08 | E32: 1.1423782e+08 | F32: ='Evolutive SFP'!BY14 -> 1.100773e+08 | G32: ='Evolutive SFP'!BZ14 -> 1.125599e+08 | L32: 5.3581904e+11
A33: Core Capital | C33: -40822385 | D33: -65395648 | E33: -71627479 | F33: =Financials!BZ11 -> -70615672 | G33: =Financials!CA11 -> -71411341 | L33: 1.1913623e+11
A34: Institutional Capital | C34: -54421009 | D34: -79162573 | E34: -85397903 | F34: =Financials!BZ12 -> -84385596 | G34: =Financials!CA12 -> -85188265 | L34: 7.0726966e+10
A35: Non-performing Loans | C35: 79402196 | D35: 81559821 | E35: 1.0627488e+08 | F35: 1.0627488e+08 | G35: 1.0627488e+08 | L35: 5.5879774e+10
A36: Non-Earning Assets | C36: 132454052 | D36: 1.4117832e+08 | E36: 1.4920442e+08 | F36: =Financials!BZ34 -> 1.3504426e+08 | G36: =Financials!CA34 -> 1.4483515e+08 | L36: 7.1166178e+10
A37: Property and Equipment | C37: 15742273 | D37: 19275669 | E37: 20681342 | F37: ='Evolutive SFP'!BY22+'Evolutive SFP'!BY21+'Evolutive SFP'!BY23+'Evolutive SFP'!BY24 -> 21827991 | G37: ='Evolutive SFP'!BZ22+'Evolutive SFP'!BZ21+'Evolutive SFP'!BZ23+'Evolutive SFP'!BZ24 -> 24226055 | L37: 2.0023339e+10
A38: Equity Investments | C38: 14306941 | D38: 22553300 | E38: 14356941 | F38: =Financials!BZ25 -> 14356941 | G38: =Financials!CA25 -> 14356941 | L38: 1.4076585e+10
A39: Financial Investments | C39: 14306941 | D39: 22553300 | E39: 14356941 | F39: =Financials!BZ26 -> 14356941 | G39: =Financials!CA26 -> 14356941 | L39: 3.5130101e+10
A40: Liquid Assets | C40: 27628340 | D40: 22918829 | E40: 12574283 | F40: ='Evolutive SFP'!BY4 -> 25030198 | G40: ='Evolutive SFP'!BZ4 -> 11959477 | L40: 8.9225368e+10
A41: Short-term Liabilities) | C41: 56083374 | D41: 50758351 | E41: 96777522 | F41: ='Evolutive SFP'!BY27+'Evolutive SFP'!BY28+'Evolutive SFP'!BY33+'Evolutive SFP'!BY34+'Evolutive SFP'!BY35 -> 91729855 | G41: ='Evolutive SFP'!BZ27+'Evolutive SFP'!BZ28+'Evolutive SFP'!BZ33+'Evolutive SFP'!BZ34+'Evolutive SFP'!BZ35 -> 91677767 | L41: 1.3062529e+11
A42: External Borrowing | C42: 24058606 | D42: 25814514 | E42: 26537750 | F42: ='Evolutive SFP'!BY36 -> 26597168 | G42: ='Evolutive SFP'!BZ36 -> 26597168 | L42: 2.3931641e+10
A43: Average Gross Loans | C43: 99233284 | D43: 1.0506779e+08 | E43: 1.0777805e+08 | F43: =('Evolutive SFP'!BX14+'Evolutive SFP'!BY14)/2 -> 1.1215756e+08 | G43: =('Evolutive SFP'!BY14+'Evolutive SFP'!BZ14)/2 -> 1.113186e+08 | L43: 5.1314057e+11
A44: Total Income | C44: 20642546 | D44: 5950979.7 | E44: 11440970 | F44: ='Evolutitve SCI'!BZ3 -> 13583556 | G44: ='Evolutitve SCI'!CA3 -> 14001556 | L44: 5.0245553e+10
A45: Net Financial Income/Loss | C45: 19994767 | D45: 5213866.3 | E45: 9876434 | F45: ='Evolutitve SCI'!BZ19 -> 11937834 | G45: ='Evolutitve SCI'!CA19 -> 12398549 | L45: 3.2645894e+10
A46: Dividends+Interest on Deposits | C46: 0 | D46: 0 | E46: 0 | F46: ='Evolutitve SCI'!BZ13 -> 0 | G46: ='Evolutitve SCI'!CA13 -> 0 | L46: 1.471188e+10
A47: Operating Expenses | C47: 20634442 | D47: 5383682.8 | E47: 9482290.2 | F47: ='Evolutitve SCI'!BZ23 -> 10728455 | G47: ='Evolutitve SCI'!CA23 -> 12012077 | L47: 1.7912259e+10
A48: Interest on Loan portfolio+Fees&Commission on Loan | C48: 12929353 | D48: 5948479.7 | E48: 8344092.5 | F48: ='Evolutitve SCI'!BZ4 -> 9694924.8 | G48: ='Evolutitve SCI'!CA4 -> 10299310 | L48: 4.2358232e+10
A49: Total Expenses | C49: 21282221 | D49: 6120796.1 | E49: 11046827 | F49: ='Evolutitve SCI'!BZ23+'Evolutitve SCI'!BZ12 -> 12374177 | G49: ='Evolutitve SCI'!CA23+'Evolutitve SCI'!CA12 -> 13615083 | L49: 3.5678885e+10
A50: Net Income | C50: -639675 | D50: -169816.42 | E50: 394143.79 | F50: ='Evolutitve SCI'!BZ37 -> 1209379.2 | G50: ='Evolutitve SCI'!CA37 -> 386472.44 | L50: 1.2417458e+10
A51: G. AREAS OF IMPROVEMENT/REGULATORY CONCERNS
A52: 1
A53: 2
A54: 3
A55: 4
A56: Prepared by:
A58: Checked by:
A60: Approved by:
A62: DISCLAIMER: This report is prepared based on information submitted by the Sacco as at the stated date and may change upon verification by the Authority.
