Workbook
Name BALANCE1_LDA01: '[1]Financial Statements'!$E$112
Name BALANCE1_LDA12: '[1]Financial Statements'!$E$123
Name BALANCE2_LDA01: '[1]Financial Statements'!$F$112
Name BALANCE2_LDA12: '[1]Financial Statements'!$F$123
Name BALANCE3_LDA01: '[1]Financial Statements'!$G$112
Name BALANCE3_LDA12: '[1]Financial Statements'!$G$123
Name BALANCE4_LDA01: '[1]Financial Statements'!$H$112
Name BALANCE4_LDA12: '[1]Financial Statements'!$H$123
Name BALANCE5_LDA01: '[1]Financial Statements'!$I$112
Name BALANCE5_LDA12: '[1]Financial Statements'!$I$123
Name BALANCE6_LDA01: '[1]Financial Statements'!$J$112
Name BALANCE6_LDA12: '[1]Financial Statements'!$J$123
Name NotApplicable: 'Prudential Ratios'!$B$76
Name PEARLS1_LA002: '[1]Financial Statements'!$E$280
Name PEARLS1_LE008: '[1]Financial Statements'!$E$275
Name PEARLS1_LE009: '[1]Financial Statements'!$E$276
Name PEARLS1_LR001: '[1]Financial Statements'!$E$282
Name PEARLS1_LR005: '[1]Financial Statements'!$E$286
Name PEARLS1_LR006: '[1]Financial Statements'!$E$287
Name PEARLS1_LR007: '[1]Financial Statements'!$E$288
Name PEARLS1_LR009: '[1]Financial Statements'!$E$290
Name PEARLS1_LS001: '[1]Financial Statements'!$E$298
Name PEARLS1_LS005: '[1]Financial Statements'!$E$302
Name PEARLS1_LS011: '[1]Financial Statements'!$E$308
Name PEARLS2_LA002: '[1]Financial Statements'!$F$280
Name PEARLS2_LE008: '[1]Financial Statements'!$F$275
Name PEARLS2_LE009: '[1]Financial Statements'!$F$276
Name PEARLS2_LR001: '[1]Financial Statements'!$F$282
Name PEARLS2_LR005: '[1]Financial Statements'!$F$286
Name PEARLS2_LR006: '[1]Financial Statements'!$F$287
Name PEARLS2_LR007: '[1]Financial Statements'!$F$288
Name PEARLS2_LR009: '[1]Financial Statements'!$F$290
Name PEARLS2_LS001: '[1]Financial Statements'!$F$298
Name PEARLS2_LS005: '[1]Financial Statements'!$F$302
Name PEARLS2_LS010: '[1]Financial Statements'!$F$307
Name PEARLS2_LS011: '[1]Financial Statements'!$F$308
Name PEARLS3_LA002: '[1]Financial Statements'!$G$280
Name PEARLS3_LE008: '[1]Financial Statements'!$G$275
Name PEARLS3_LE009: '[1]Financial Statements'!$G$276
Name PEARLS3_LR001: '[1]Financial Statements'!$G$282
Name PEARLS3_LR005: '[1]Financial Statements'!$G$286
Name PEARLS3_LR006: '[1]Financial Statements'!$G$287
Name PEARLS3_LR007: '[1]Financial Statements'!$G$288
Name PEARLS3_LR009: '[1]Financial Statements'!$G$290
Name PEARLS3_LS001: '[1]Financial Statements'!$G$298
Name PEARLS3_LS005: '[1]Financial Statements'!$G$302
Name PEARLS3_LS010: '[1]Financial Statements'!$G$307
Name PEARLS3_LS011: '[1]Financial Statements'!$G$308
Name PEARLS4_LA002: '[1]Financial Statements'!$H$280
Name PEARLS4_LE008: '[1]Financial Statements'!$H$275
Name PEARLS4_LE009: '[1]Financial Statements'!$H$276
Name PEARLS4_LR001: '[1]Financial Statements'!$H$282
Name PEARLS4_LR005: '[1]Financial Statements'!$H$286
Name PEARLS4_LR006: '[1]Financial Statements'!$H$287
Name PEARLS4_LR007: '[1]Financial Statements'!$H$288
Name PEARLS4_LR009: '[1]Financial Statements'!$H$290
Name PEARLS4_LS001: '[1]Financial Statements'!$H$298
Name PEARLS4_LS005: '[1]Financial Statements'!$H$302
Name PEARLS4_LS010: '[1]Financial Statements'!$H$307
Name PEARLS4_LS011: '[1]Financial Statements'!$H$308

Sheet compliance status
B2: audited2017 | C2: 43101 | D2: 43133 | E2: 43165 | F2: 43197 | G2: 43229 | H2: 43261 | I2: 43293 | J2: 43325 | K2: 43357 | L2: 43389 | M2: 43421 | N2: 43453
A3: CORE CAPITAL | B3: =IF('Prudential Ratios'!I6>10,"compliant","not compliant") -> compliant | C3: =IF('Prudential Ratios'!J6>10,"compliant","not compliant") -> compliant | D3: =IF('Prudential Ratios'!K6>10,"compliant","not compliant") -> compliant | E3: =IF('Prudential Ratios'!L6>10,"compliant","not compliant") -> compliant | F3: =IF('Prudential Ratios'!M6>10,"compliant","not compliant") -> compliant | G3: =IF('Prudential Ratios'!N6>10,"compliant","not compliant") -> compliant | H3: =IF('Prudential Ratios'!O6>10,"compliant","not compliant") -> compliant | I3: =IF('Prudential Ratios'!P6>10,"compliant","not compliant") -> compliant | ... N3: =IF('Prudential Ratios'!U6>10,"compliant","not compliant") -> compliant
A4: CCA (Min 10%) | B4: =IF('Prudential Ratios'!I7>10%,"compliant","not compliant") -> compliant | C4: =IF('Prudential Ratios'!J7>10%,"compliant","not compliant") -> compliant | D4: =IF('Prudential Ratios'!K7>10%,"compliant","not compliant") -> compliant | E4: =IF('Prudential Ratios'!L7>10%,"compliant","not compliant") -> compliant | F4: =IF('Prudential Ratios'!M7>10%,"compliant","not compliant") -> compliant | G4: =IF('Prudential Ratios'!N7>10%,"compliant","not compliant") -> compliant | H4: =IF('Prudential Ratios'!O7>10%,"compliant","not compliant") -> compliant | I4: =IF('Prudential Ratios'!P7>10%,"compliant","not compliant") -> compliant | ... N4: =IF('Prudential Ratios'!U7>10%,"compliant","not compliant") -> compliant
A5: ICA (Min 8%) | B5: =IF('Prudential Ratios'!I10>8%,"compliant","not compliant") -> compliant | C5: =IF('Prudential Ratios'!J10>8%,"compliant","not compliant") -> compliant | D5: =IF('Prudential Ratios'!K10>8%,"compliant","not compliant") -> compliant | E5: =IF('Prudential Ratios'!L10>8%,"compliant","not compliant") -> compliant | F5: =IF('Prudential Ratios'!M10>8%,"compliant","not compliant") -> compliant | G5: =IF('Prudential Ratios'!N10>8%,"compliant","not compliant") -> compliant | H5: =IF('Prudential Ratios'!O10>8%,"compliant","not compliant") -> compliant | I5: =IF('Prudential Ratios'!P10>8%,"compliant","not compliant") -> compliant | ... N5: =IF('Prudential Ratios'!U10>8%,"compliant","not compliant") -> compliant
A6: CCD (Min 8%) | B6: =IF('Prudential Ratios'!I8>8%,"compliant","not compliant") -> compliant | C6: =IF('Prudential Ratios'!J8>8%,"compliant","not compliant") -> compliant | D6: =IF('Prudential Ratios'!K8>8%,"compliant","not compliant") -> compliant | E6: =IF('Prudential Ratios'!L8>8%,"compliant","not compliant") -> compliant | F6: =IF('Prudential Ratios'!M8>8%,"compliant","not compliant") -> compliant | G6: =IF('Prudential Ratios'!N8>8%,"compliant","not compliant") -> compliant | H6: =IF('Prudential Ratios'!O8>8%,"compliant","not compliant") -> compliant | I6: =IF('Prudential Ratios'!P8>8%,"compliant","not compliant") -> compliant | ... N6: =IF('Prudential Ratios'!U8>8%,"compliant","not compliant") -> compliant
A7: NPL(5%)
A8: Liquidity(15%) | B8: =IF('Prudential Ratios'!I47>15%,"compliant","not compliant") -> not compliant | C8: =IF('Prudential Ratios'!J47>15%,"compliant","not compliant") -> not compliant | D8: =IF('Prudential Ratios'!K47>15%,"compliant","not compliant") -> not compliant | E8: =IF('Prudential Ratios'!L47>15%,"compliant","not compliant") -> not compliant | F8: =IF('Prudential Ratios'!M47>15%,"compliant","not compliant") -> not compliant | G8: =IF('Prudential Ratios'!N47>15%,"compliant","not compliant") -> not compliant | H8: =IF('Prudential Ratios'!O47>15%,"compliant","not compliant") -> not compliant | I8: =IF('Prudential Ratios'!P47>15%,"compliant","not compliant") -> not compliant | ... N8: =IF('Prudential Ratios'!U47>15%,"compliant","not compliant") -> compliant
A9: NEA (Max 10%) | B9: =IF('Prudential Ratios'!I14<10%,"compliant","not compliant") -> not compliant | C9: =IF('Prudential Ratios'!J14<10%,"compliant","not compliant") -> not compliant | D9: =IF('Prudential Ratios'!K14<10%,"compliant","not compliant") -> not compliant | E9: =IF('Prudential Ratios'!L14<10%,"compliant","not compliant") -> not compliant | F9: =IF('Prudential Ratios'!M14<10%,"compliant","not compliant") -> not compliant | G9: =IF('Prudential Ratios'!N14<10%,"compliant","not compliant") -> not compliant | H9: =IF('Prudential Ratios'!O14<10%,"compliant","not compliant") -> compliant | I9: =IF('Prudential Ratios'!P14<10%,"compliant","not compliant") -> compliant | ... N9: =IF('Prudential Ratios'!U14<10%,"compliant","not compliant") -> compliant
A10: LB ratio (Max 5%) | B10: =IF('Prudential Ratios'!I15<5%,"compliant","not compliant") -> compliant | C10: =IF('Prudential Ratios'!J15<5%,"compliant","not compliant") -> compliant | D10: =IF('Prudential Ratios'!K15<5%,"compliant","not compliant") -> compliant | E10: =IF('Prudential Ratios'!L15<5%,"compliant","not compliant") -> compliant | F10: =IF('Prudential Ratios'!M15<5%,"compliant","not compliant") -> compliant | G10: =IF('Prudential Ratios'!N15<5%,"compliant","not compliant") -> compliant | H10: =IF('Prudential Ratios'!O15<5%,"compliant","not compliant") -> compliant | I10: =IF('Prudential Ratios'!P15<5%,"compliant","not compliant") -> compliant | ... N10: =IF('Prudential Ratios'!U15<5%,"compliant","not compliant") -> compliant
A11: FITD (Max 5%) | B11: =IF('Prudential Ratios'!I19<5%,"compliant","not compliant") -> not compliant | C11: =IF('Prudential Ratios'!J19<5%,"compliant","not compliant") -> not compliant | D11: =IF('Prudential Ratios'!K19<5%,"compliant","not compliant") -> not compliant | E11: =IF('Prudential Ratios'!L19<5%,"compliant","not compliant") -> not compliant | F11: =IF('Prudential Ratios'!M19<5%,"compliant","not compliant") -> not compliant | G11: =IF('Prudential Ratios'!N19<5%,"compliant","not compliant") -> not compliant | H11: =IF('Prudential Ratios'!O19<5%,"compliant","not compliant") -> not compliant | I11: =IF('Prudential Ratios'!P19<5%,"compliant","not compliant") -> not compliant | ... N11: =IF('Prudential Ratios'!U19<5%,"compliant","not compliant") -> not compliant
A12: FICC (Max 40%) | B12: =IF('Prudential Ratios'!I20<40%,"compliant","not compliant") -> not compliant | C12: =IF('Prudential Ratios'!J20<40%,"compliant","not compliant") -> not compliant | D12: =IF('Prudential Ratios'!K20<40%,"compliant","not compliant") -> not compliant | E12: =IF('Prudential Ratios'!L20<40%,"compliant","not compliant") -> not compliant | F12: =IF('Prudential Ratios'!M20<40%,"compliant","not compliant") -> not compliant | G12: =IF('Prudential Ratios'!N20<40%,"compliant","not compliant") -> compliant | H12: =IF('Prudential Ratios'!O20<40%,"compliant","not compliant") -> compliant | I12: =IF('Prudential Ratios'!P20<40%,"compliant","not compliant") -> compliant | ... N12: =IF('Prudential Ratios'!U20<40%,"compliant","not compliant") -> compliant
A13: EB ratio | B13: =IF('Prudential Ratios'!I27<25%,"compliant","not compliant") -> compliant | C13: =IF('Prudential Ratios'!J27<25%,"compliant","not compliant") -> compliant | D13: =IF('Prudential Ratios'!K27<25%,"compliant","not compliant") -> compliant | E13: =IF('Prudential Ratios'!L27<25%,"compliant","not compliant") -> compliant | F13: =IF('Prudential Ratios'!M27<25%,"compliant","not compliant") -> compliant | G13: =IF('Prudential Ratios'!N27<25%,"compliant","not compliant") -> compliant | H13: =IF('Prudential Ratios'!O27<25%,"compliant","not compliant") -> compliant | I13: =IF('Prudential Ratios'!P27<25%,"compliant","not compliant") -> compliant | ... N13: =IF('Prudential Ratios'!U27<25%,"compliant","not compliant") -> compliant
A14: A=S+L | B14: =IF(SFP!#REF!=SFP!#REF!,"balancing","notbalancing") -> #REF! | C14: =IF(SFP!#REF!=SFP!#REF!,"balancing","notbalancing") -> #REF! | D14: =IF(SFP!#REF!=SFP!#REF!,"balancing","notbalancing") -> #REF! | E14: =IF(SFP!#REF!=SFP!#REF!,"balancing","notbalancing") -> #REF! | F14: =IF(SFP!#REF!=SFP!#REF!,"balancing","notbalancing") -> #REF! | G14: =IF(SFP!#REF!=SFP!#REF!,"balancing","notbalancing") -> #REF! | H14: =IF(SFP!#REF!=SFP!#REF!,"balancing","notbalancing") -> #REF! | I14: =IF(SFP!#REF!=SFP!#REF!,"balancing","notbalancing") -> #REF! | ... N14: =IF(SFP!#REF!=SFP!#REF!,"balancing","notbalancing") -> #REF!

Sheet Prudential Ratios
C1: FORTITUDE SACCO SOCIETY LTD
C2: Sacco Financial Performance
C4: FINANCIAL SOUNDNESS INDICATORS | D4: Prude. Std | E4: AUDITED 2013 | F4: AUDITED 2014 | G4: AUDITED 2015 | H4: AUDITED 2016 | I4: AUDITED 2017 | J4: 43101 | K4: 43132 | L4: 43160 | M4: 43191 | N4: 43221 | O4: 43252 | P4: 43282 | Q4: 43313 | R4: 43344 | S4: 43374 | T4: 43405 | U4: 43435 | V4: AUDITED 2018 | W4: 43466 | X4: 43497 | Y4: 43525 | Z4: 43556 | AA4: 43586 | AB4: 43617 | AC4: 43647 | AD4: 43678 | AE4: 43709 | AF4: 43739 | AG4: 43770 | AH4: 43800 | AI4: AUDITED 2019 | AJ4: 43831 | AK4: 43862 | AL4: 43891 | AM4: 43922 | AN4: 43952 | AO4: 43983 | AP4: 44013 | AQ4: 44044 | AR4: 44075 | AS4: 44105 | AT4: 44136 | AU4: 44166 | AV4: 44197 | AW4: 44197 | AX4: 44228 | AY4: 44256 | AZ4: 44287 | BA4: 44317 | BB4: 44348 | BC4: 44378 | BD4: 44409 | BE4: 44440 | BF4: 44470 | BG4: 44501 | BH4: 44531 | BI4: Audited-2021 | BJ4: 44583 | BK4: 44614 | BL4: 44642 | BM4: 44673 | BN4: 44703 | BO4: 44734 | BP4: 44764 | BQ4: 44795 | BR4: 44826 | BS4: 44856 | BT4: 44887 | BU4: 44917 | BV4: Audited-2022 | BW4: 44949 | BX4: 44980 | BY4: 45008 | BZ4: 45039 | CA4: 45069 | CB4: 45100 | CC4: 45130 | CD4: 45161
B5: 1 | C5: CAPITAL ADEQUACY REQUIREMENTS
B6: 1.1 | C6: Core capital | D6: ≥ Ksh.10M | E6: =Financials!C14/1000000 -> 25.989635 | F6: =Financials!D14/1000000 -> 35.288687 | G6: =Financials!E14/1000000 -> 94.944699 | H6: =Financials!F14/1000000 -> 75.269883 | I6: =Financials!G14/1000000 -> 78.35088 | J6: =Financials!H14/1000000 -> 85.261209 | K6: =Financials!I14/1000000 -> 89.373249 | L6: =Financials!J14/1000000 -> 93.106244 | ... AU6: =Financials!AS14/1000000 -> 179.88597 | AW6: =Financials!AU14/1000000 -> 62.318939 | AX6: =Financials!AV14/1000000 -> 62.166031 | AY6: =Financials!AW14/1000000 -> 64.837345 | AZ6: =Financials!AX14/1000000 -> 73.34804 | BA6: =Financials!AY14/1000000 -> 76.554846 | BB6: =Financials!AZ14/1000000 -> 77.700708 | BC6: =Financials!BA14/1000000 -> 79.695653 | BD6: =Financials!BB14/1000000 -> 81.326497 | ... CC6: =Financials!CA14/1000000 -> 0
B7: 1.2 | C7: Core capital /Total Assets | D7: ≥ 10% | E7: =Financials!C14/Financials!C5 -> 0.06345526 | F7: =Financials!D14/Financials!D5 -> 0.083161502 | G7: =Financials!E14/Financials!E5 -> 0.20483458 | H7: =Financials!F14/Financials!F5 -> 0.16493137 | I7: =Financials!G14/Financials!G5 -> 0.17936092 | J7: =Financials!H14/Financials!H5 -> 0.20150658 | K7: =Financials!I14/Financials!I5 -> 0.21135201 | L7: =Financials!J14/Financials!J5 -> 0.22749189 | ... AU7: =Financials!AS14/Financials!AS5 -> 0.24569813 | AW7: =Financials!AU14/Financials!AU5 -> 0.27949299 | AX7: =Financials!AV14/Financials!AV5 -> 0.27821053 | AY7: =Financials!AW14/Financials!AW5 -> 0.28743071 | AZ7: =Financials!AX14/Financials!AX5 -> 0.32214302 | BA7: =Financials!AY14/Financials!AY5 -> 0.3322442 | BB7: =Financials!AZ14/Financials!AZ5 -> 0.33311786 | BC7: =Financials!BA14/Financials!BA5 -> 0.33321642 | BD7: =Financials!BB14/Financials!BB5 -> 0.3314577 | ... CC7: =Financials!CA14/Financials!CA5 -> #DIV/0!
B8: 1.3 | C8: Core capital /Total Deposits | D8: ≥ 8% | E8: =Financials!C14/Financials!C6 -> 0.087708088 | F8: =Financials!D14/Financials!D6 -> 0.10820486 | G8: =Financials!E14/Financials!E6 -> 0.26090139 | H8: =Financials!F14/Financials!F6 -> 0.21334302 | I8: =Financials!G14/Financials!G6 -> 0.22591234 | J8: =Financials!H14/Financials!H6 -> 0.25547967 | K8: =Financials!I14/Financials!I6 -> 0.27117475 | L8: =Financials!J14/Financials!J6 -> 0.29894231 | ... AU8: =Financials!AS14/Financials!AS6 -> 0.33302157 | AW8: =Financials!AU14/Financials!AU6 -> 0.46131948 | AX8: =Financials!AV14/Financials!AV6 -> 0.45505957 | AY8: =Financials!AW14/Financials!AW6 -> 0.47614928 | AZ8: =Financials!AX14/Financials!AX6 -> 0.52261514 | BA8: =Financials!AY14/Financials!AY6 -> 0.54483248 | BB8: =Financials!AZ14/Financials!AZ6 -> 0.54787086 | BC8: =Financials!BA14/Financials!BA6 -> 0.5494075 | BD8: =Financials!BB14/Financials!BB6 -> 0.5440463 | ... CC8: =Financials!CA14/Financials!CA6 -> #DIV/0!
B9: 1.4 | C9: Share Capital/Total Assets | D9: ≤2% | E9: =Financials!C18/Financials!C5 -> 0.019594444 | F9: =Financials!D18/Financials!D5 -> 0.022998192 | G9: =Financials!E18/Financials!E5 -> 0.021441489 | H9: =Financials!F18/Financials!F5 -> 0.021777319 | I9: =Financials!G18/Financials!G5 -> 0.024372395 | J9: =Financials!H18/Financials!H5 -> 0.030581228 | K9: =Financials!I18/Financials!I5 -> 0.034259821 | L9: =Financials!J18/Financials!J5 -> 0.037908675 | ... AU9: =Financials!AS18/Financials!AS5 -> 0.037884342 | AW9: =Financials!AU18/Financials!AU5 -> 0.12436864 | AX9: =Financials!AV18/Financials!AV5 -> 0.12483962 | AY9: =Financials!AW18/Financials!AW5 -> 0.12441108 | AZ9: =Financials!AX18/Financials!AX5 -> 0.12377008 | BA9: =Financials!AY18/Financials!AY5 -> 0.12310058 | BB9: =Financials!AZ18/Financials!AZ5 -> 0.12232881 | BC9: =Financials!BA18/Financials!BA5 -> 0.1200291 | BD9: =Financials!BB18/Financials!BB5 -> 0.11773735 | ... CC9: =Financials!CA18/Financials!CA5 -> #DIV/0!
B10: 1.5 | C10: Institutional Capital/Total Assets | D10: ≥ 8% | E10: =Financials!C15/Financials!C5 -> 0.043860816 | F10: =Financials!D15/Financials!D5 -> 0.06016331 | G10: =Financials!E15/Financials!E5 -> 0.18339309 | H10: =Financials!F15/Financials!F5 -> 0.14315405 | I10: =Financials!G15/Financials!G5 -> 0.15498853 | J10: =Financials!H15/Financials!H5 -> 0.17092535 | K10: =Financials!I15/Financials!I5 -> 0.17709219 | L10: =Financials!J15/Financials!J5 -> 0.18958322 | ... AU10: =Financials!AS15/Financials!AS5 -> 0.20781379 | AW10: =Financials!AU15/Financials!AU5 -> 0.15512435 | AX10: =Financials!AV15/Financials!AV5 -> 0.15337091 | AY10: =Financials!AW15/Financials!AW5 -> 0.16301963 | AZ10: =Financials!AX15/Financials!AX5 -> 0.19837294 | BA10: =Financials!AY15/Financials!AY5 -> 0.20914362 | BB10: =Financials!AZ15/Financials!AZ5 -> 0.21078905 | BC10: =Financials!BA15/Financials!BA5 -> 0.21318733 | BD10: =Financials!BB15/Financials!BB5 -> 0.21372034 | ... CC10: =Financials!CA15/Financials!CA5 -> #DIV/0!
B12: 2 | C12: ASSET MIX AND QUALITY
B13: 2.1 | C13: Non Earning Assets
B14: 2.1.1 | C14: Non earning Assets/Total assets | D14: ≤ 10% | E14: =Financials!C38/Financials!C5 -> 0.13921023 | F14: =Financials!D38/Financials!D5 -> 0.094990974 | G14: =Financials!E38/Financials!E5 -> 0.11800484 | H14: =Financials!F38/Financials!F5 -> 0.12675515 | I14: =Financials!G38/Financials!G5 -> 0.10067358 | J14: =Financials!H38/Financials!H5 -> 0.13039883 | K14: =Financials!I38/Financials!I5 -> 0.1264507 | L14: =Financials!J38/Financials!J5 -> 0.12800998 | ... AU14: =Financials!AS38/Financials!AS5 -> 0.03147327 | AW14: =Financials!AU38/Financials!AU5 -> 0.12843819 | AX14: =Financials!AV38/Financials!AV5 -> 0.12652995 | AY14: =Financials!AW38/Financials!AW5 -> 0.12687347 | AZ14: =Financials!AX38/Financials!AX5 -> 0.11583736 | BA14: =Financials!AY38/Financials!AY5 -> 0.12433636 | BB14: =Financials!AZ38/Financials!AZ5 -> 0.12067688 | BC14: =Financials!BA38/Financials!BA5 -> 0.11768697 | BD14: =Financials!BB38/Financials!BB5 -> 0.12012869 | ... CB14: =Financials!BZ38/Financials!BZ5 -> 0.08297919
B15: 2.1.2 | C15: Property and Equipment/Total Assets | D15: ≤ 5% | E15: =Financials!C39/Financials!C5 -> 0.017833781 | F15: =Financials!D39/Financials!D5 -> 0.01452311 | G15: =Financials!E39/Financials!E5 -> 0.01288188 | H15: =Financials!F39/Financials!F5 -> 0.012663382 | I15: =Financials!G39/Financials!G5 -> 0.013661078 | J15: =Financials!H39/Financials!H5 -> 0.013696816 | K15: =Financials!I39/Financials!I5 -> 0.013297813 | L15: =Financials!J39/Financials!J5 -> 0.013318733 | ... AU15: =Financials!AS39/Financials!AS5 -> 0.0078216417 | AW15: =Financials!AU39/Financials!AU5 -> 0.090453429 | AX15: =Financials!AV39/Financials!AV5 -> 0.089961577 | AY15: =Financials!AW39/Financials!AW5 -> 0.091433653 | AZ15: =Financials!AX39/Financials!AX5 -> 0.090922642 | BA15: =Financials!AY39/Financials!AY5 -> 0.089513999 | BB15: =Financials!AZ39/Financials!AZ5 -> 0.088144287 | BC15: =Financials!BA39/Financials!BA5 -> 0.085622297 | BD15: =Financials!BB39/Financials!BB5 -> 0.083150844 | ... CB15: =Financials!BZ39/Financials!BZ5 -> 0.056581642
B16: 2.1.3 | C16: Non Performing loans/Gross Loans | D16: ≤ 6%
B18: 2.2 | C18: Earning Assets
B19: 2.2.1 | C19: Equities & Investments/Deposits | D19: ≤ 5% | E19: =Financials!C26/Financials!C6 -> 0.060285214 | F19: =Financials!D26/Financials!D6 -> 0.13586799 | G19: =Financials!E26/Financials!E6 -> 0.12176194 | H19: =Financials!F26/Financials!F6 -> 0.11269646 | I19: =Financials!G26/Financials!G6 -> 0.11464343 | J19: =Financials!H26/Financials!H6 -> 0.11914009 | K19: =Financials!I26/Financials!I6 -> 0.12064096 | L19: =Financials!J26/Financials!J6 -> 0.127662 | ... AU19: =Financials!AS26/Financials!AS6 -> 0.0078282924 | AW19: =Financials!AU26/Financials!AU6 -> 0.070609206 | AX19: =Financials!AV26/Financials!AV6 -> 0.069822388 | AY19: =Financials!AW26/Financials!AW6 -> 0.070048282 | AZ19: =Financials!AX26/Financials!AX6 -> 0.067963081 | BA19: =Financials!AY26/Financials!AY6 -> 0.067884385 | BB19: =Financials!AZ26/Financials!AZ6 -> 0.067256274 | BC19: =Financials!BA26/Financials!BA6 -> 0.0667907 | BD19: =Financials!BB26/Financials!BB6 -> 0.064812659 | ... CB19: =Financials!BZ26/Financials!BZ6 -> 0.050172843
B20: 2.2.2 | C20: Equities & Investments/Core Capital | D20: ≤ 40% | E20: =Financials!C26/Financials!C14 -> 0.68733928 | F20: =Financials!D26/Financials!D14 -> 1.2556552 | G20: =Financials!E26/Financials!E14 -> 0.46669717 | H20: =Financials!F26/Financials!F14 -> 0.52824067 | I20: =Financials!G26/Financials!G14 -> 0.50746862 | J20: =Financials!H26/Financials!H14 -> 0.46633884 | K20: =Financials!I26/Financials!I14 -> 0.44488271 | L20: =Financials!J26/Financials!J14 -> 0.42704562 | ... AU20: =Financials!AS26/Financials!AS14 -> 0.023506863 | AW20: =Financials!AU26/Financials!AU14 -> 0.15305923 | AX20: =Financials!AV26/Financials!AV14 -> 0.15343571 | AY20: =Financials!AW26/Financials!AW14 -> 0.14711412 | AZ20: =Financials!AX26/Financials!AX14 -> 0.13004422 | BA20: =Financials!AY26/Financials!AY14 -> 0.1245968 | BB20: =Financials!AZ26/Financials!AZ14 -> 0.12275936 | BC20: =Financials!BA26/Financials!BA14 -> 0.1215686 | BD20: =Financials!BB26/Financials!BB14 -> 0.11913078 | ... CB20: =Financials!BZ26/Financials!BZ14 -> 0.085822356
B21: 2.2.3 | C21: Net Loans & advances /Total assets | D21: NPR | E21: =Financials!C31/Financials!C5 -> 0.76404585 | F21: =Financials!D31/Financials!D5 -> 0.68763307 | G21: =Financials!E31/Financials!E5 -> 0.64642687 | H21: =Financials!F31/Financials!F5 -> 0.67849007 | I21: =Financials!G31/Financials!G5 -> 0.7111169 | J21: =Financials!H31/Financials!H5 -> 0.74479353 | K21: =Financials!I31/Financials!I5 -> 0.73132542 | L21: =Financials!J31/Financials!J5 -> 0.75374882 | ... AU21: =Financials!AS31/Financials!AS5 -> 0.80532255 | AW21: =Financials!AU31/Financials!AU5 -> 0.74028501 | AX21: =Financials!AV31/Financials!AV5 -> 0.72998044 | AY21: =Financials!AW31/Financials!AW5 -> 0.72420355 | AZ21: =Financials!AX31/Financials!AX5 -> 0.71862915 | BA21: =Financials!AY31/Financials!AY5 -> 0.71080982 | BB21: =Financials!AZ31/Financials!AZ5 -> 0.70448937 | BC21: =Financials!BA31/Financials!BA5 -> 0.72125273 | BD21: =Financials!BB31/Financials!BB5 -> 0.70429393 | ... CB21: =Financials!BZ31/Financials!BZ5 -> 0.80124146
B23: 3 | C23: FUNDING MIX
B24: 3.1 | C24: Total Deposits/Total Assets | D24: NPR | E24: =Financials!C6/Financials!C5 -> 0.72348243 | F24: =Financials!D6/Financials!D5 -> 0.76855605 | G24: =Financials!E6/Financials!E5 -> 0.78510346 | H24: =Financials!F6/Financials!F5 -> 0.77308071 | I24: =Financials!G6/Financials!G5 -> 0.79394033 | J24: =Financials!H6/Financials!H5 -> 0.7887382 | K24: =Financials!I6/Financials!I5 -> 0.77939414 | L24: =Financials!J6/Financials!J5 -> 0.76098928 | ... AU24: =Financials!AS6/Financials!AS5 -> 0.73778445 | AW24: =Financials!AU6/Financials!AU5 -> 0.60585559 | AX24: =Financials!AV6/Financials!AV5 -> 0.61137167 | AY24: =Financials!AW6/Financials!AW5 -> 0.60365672 | AZ24: =Financials!AX6/Financials!AX5 -> 0.61640583 | BA24: =Financials!AY6/Financials!AY5 -> 0.60980982 | BB24: =Financials!AZ6/Financials!AZ5 -> 0.60802259 | BC24: =Financials!BA6/Financials!BA5 -> 0.60650141 | BD24: =Financials!BB6/Financials!BB5 -> 0.60924539 | ... CB24: =Financials!BZ6/Financials!BZ5 -> 0.57783879
B25: 3.1.1 | C25: BOSA Deposits/Total Assets | D25: NPR | E25: =Financials!C7/Financials!C5 -> 0.60032314 | F25: =Financials!D7/Financials!D5 -> 0.56787731 | G25: =Financials!E7/Financials!E5 -> 0.5227007 | H25: =Financials!F7/Financials!F5 -> 0.53606475 | I25: =Financials!G7/Financials!G5 -> 0.55681232 | J25: =Financials!H7/Financials!H5 -> 0.56256362 | K25: =Financials!I7/Financials!I5 -> 0.54611909 | L25: =Financials!J7/Financials!J5 -> 0.55267113 | ... AU25: =Financials!AS7/Financials!AS5 -> 0.66533188 | AW25: =Financials!AU7/Financials!AU5 -> 0.55193275 | AX25: =Financials!AV7/Financials!AV5 -> 0.55725721 | AY25: =Financials!AW7/Financials!AW5 -> 0.55615789 | AZ25: =Financials!AX7/Financials!AX5 -> 0.55433576 | BA25: =Financials!AY7/Financials!AY5 -> 0.55238565 | BB25: =Financials!AZ7/Financials!AZ5 -> 0.5492847 | BC25: =Financials!BA7/Financials!BA5 -> 0.54040482 | BD25: =Financials!BB7/Financials!BB5 -> 0.53128651 | ... CB25: =Financials!BZ7/Financials!BZ5 -> 0.51735354
B26: 3.1.2 | C26: FOSA Deposits/Total Assets | D26: NPR | E26: =Financials!C8/Financials!C5 -> 0.12315929 | F26: =Financials!D8/Financials!D5 -> 0.19320636 | G26: =Financials!E8/Financials!E5 -> 0.0087900989 | H26: =Financials!F8/Financials!F5 -> 0.01092182 | I26: =Financials!G8/Financials!G5 -> 0.011620509 | J26: =Financials!H8/Financials!H5 -> 0.016878266 | K26: =Financials!I8/Financials!I5 -> 0.01688339 | L26: =Financials!J8/Financials!J5 -> 0.020765494 | ... AU26: =Financials!AS8/Financials!AS5 -> 0.015541452 | AW26: =Financials!AU8/Financials!AU5 -> 0.053922836 | AX26: =Financials!AV8/Financials!AV5 -> 0.054114463 | AY26: =Financials!AW8/Financials!AW5 -> 0.047498829 | AZ26: =Financials!AX8/Financials!AX5 -> 0.062070074 | BA26: =Financials!AY8/Financials!AY5 -> 0.057424172 | BB26: =Financials!AZ8/Financials!AZ5 -> 0.05873789 | BC26: =Financials!BA8/Financials!BA5 -> 0.066096592 | BD26: =Financials!BB8/Financials!BB5 -> 0.077958881 | ... CB26: =Financials!BZ8/Financials!BZ5 -> 0.060485243
B27: 3.2 | C27: External Borrowing/Total assets | D27: ≤ 25% | E27: =Financials!C9/Financials!C5 -> 0.14272236 | F27: =Financials!D9/Financials!D5 -> 0.0018448707 | G27: =Financials!E9/Financials!E5 -> 0.001688932 | H27: =Financials!F9/Financials!F5 -> 0.0017153851 | I27: =Financials!G9/Financials!G5 -> 0.0017921054 | J27: =Financials!H9/Financials!H5 -> 0.0018501943 | K27: =Financials!I9/Financials!I5 -> 0.001851307 | L27: =Financials!J9/Financials!J5 -> 0.0019127875 | ... AU27: =Financials!AS9/Financials!AS5 -> 0.010282182 | AW27: =Financials!AU9/Financials!AU5 -> 0 | AX27: =Financials!AV9/Financials!AV5 -> 0 | AY27: =Financials!AW9/Financials!AW5 -> 0 | AZ27: =Financials!AX9/Financials!AX5 -> 0 | BA27: =Financials!AY9/Financials!AY5 -> 0 | BB27: =Financials!AZ9/Financials!AZ5 -> 0 | BC27: =Financials!BA9/Financials!BA5 -> 0 | BD27: =Financials!BB9/Financials!BB5 -> 0 | ... CB27: =Financials!BZ9/Financials!BZ5 -> 0.046027731
B29: 4 | C29: GROWTH RATIOS
B30: 4.1 | C30: Total Assets | D30: NPR | E30: =Financials!C5/Financials!B5-1 -> #VALUE! | F30: =Financials!D5/Financials!C5-1 -> 0.036049779 | G30: =Financials!E5/Financials!D5-1 -> 0.092331022 | H30: =Financials!F5/Financials!E5-1 -> -0.015421079 | I30: =Financials!G5/Financials!F5-1 -> -0.042810163 | J30: =Financials!H5/Financials!G5-1 -> -0.031396118 | K30: =Financials!I5/Financials!H5-1 -> -0.00060103252 | L30: =Financials!J5/Financials!I5-1 -> -0.032141825 | ... AU30: =Financials!AS5/Financials!AR5-1 -> 0.021311881 | AW30: =Financials!AU5/Financials!AT5-1 -> -0.69397124 | AX30: =Financials!AV5/Financials!AU5-1 -> 0.0021447072 | AY30: =Financials!AW5/Financials!AV5-1 -> 0.0095143163 | AZ30: =Financials!AX5/Financials!AW5-1 -> 0.0093638189 | BA30: =Financials!AY5/Financials!AX5-1 -> 0.011988304 | BB30: =Financials!AZ5/Financials!AY5-1 -> 0.012305935 | BC30: =Financials!BA5/Financials!AZ5-1 -> 0.025371342 | BD30: =Financials!BB5/Financials!BA5-1 -> 0.025878006 | ... CB30: =Financials!BZ5/Financials!BY5-1 -> 0.040630359
B31: 4.2 | C31: Total Deposits | D31: NPR | E31: =Financials!C6/Financials!B6-1 -> #VALUE! | F31: =Financials!D6/Financials!C6-1 -> 0.10059664 | G31: =Financials!E6/Financials!D6-1 -> 0.11584946 | H31: =Financials!F6/Financials!E6-1 -> -0.03049851 | I31: =Financials!G6/Financials!F6-1 -> -0.016982827 | J31: =Financials!H6/Financials!G6-1 -> -0.037742693 | K31: =Financials!I6/Financials!H6-1 -> -0.012440757 | L31: =Financials!J6/Financials!I6-1 -> -0.054997136 | ... AU31: =Financials!AS6/Financials!AR6-1 -> 0.012195621 | AW31: =Financials!AU6/Financials!AT6-1 -> -0.74982265 | AX31: =Financials!AV6/Financials!AU6-1 -> 0.011268855 | AY31: =Financials!AW6/Financials!AV6-1 -> -0.0032248379 | AZ31: =Financials!AX6/Financials!AW6-1 -> 0.030681386 | BA31: =Financials!AY6/Financials!AX6-1 -> 0.0011592561 | BB31: =Financials!AZ6/Financials!AY6-1 -> 0.0093390731 | BC31: =Financials!BA6/Financials!AZ6-1 -> 0.022806016 | BD31: =Financials!BB6/Financials!BA6-1 -> 0.030519362 | ... CB31: =Financials!BZ6/Financials!BY6-1 -> 0.0075016351
B32: 4.2.1 | C32: FOSA Deposits | D32: NPR | E32: =Financials!C8/Financials!B8-1 -> #VALUE! | F32: =Financials!D8/Financials!C8-1 -> 0.62530497 | G32: =Financials!E8/Financials!D8-1 -> -0.95030341 | H32: =Financials!F8/Financials!E8-1 -> 0.22335302 | I32: =Financials!G8/Financials!F8-1 -> 0.018422997 | J32: =Financials!H8/Financials!G8-1 -> 0.40685358 | K32: =Financials!I8/Financials!H8-1 -> -0.00029768491 | L32: =Financials!J8/Financials!I8-1 -> 0.19040394 | ... AU32: =Financials!AS8/Financials!AR8-1 -> 0.080968024 | AW32: =Financials!AU8/Financials!AT8-1 -> -0.78836591 | AX32: =Financials!AV8/Financials!AU8-1 -> 0.0057060514 | AY32: =Financials!AW8/Financials!AV8-1 -> -0.11390145 | AZ32: =Financials!AX8/Financials!AW8-1 -> 0.31900698 | BA32: =Financials!AY8/Financials!AX8-1 -> -0.063758312 | BB32: =Financials!AZ8/Financials!AY8-1 -> 0.035464906 | BC32: =Financials!BA8/Financials!AZ8-1 -> 0.1538302 | BD32: =Financials!BB8/Financials!BA8-1 -> 0.20999129 | ... CB32: =Financials!BZ8/Financials!BY8-1 -> -0.077330785
B33: 4.2.2 | C33: BOSA Deposits | D33: NPR | E33: =Financials!C7/Financials!B7-1 -> #VALUE! | F33: =Financials!D7/Financials!C7-1 -> -0.019945888 | G33: =Financials!E7/Financials!D7-1 -> 0.0054323143 | H33: =Financials!F7/Financials!E7-1 -> 0.0097519449 | I33: =Financials!G7/Financials!F7-1 -> -0.0057635786 | J33: =Financials!H7/Financials!G7-1 -> -0.021391436 | K33: =Financials!I7/Financials!H7-1 -> -0.029814884 | L33: =Financials!J7/Financials!I7-1 -> -0.020529993 | ... AU33: =Financials!AS7/Financials!AR7-1 -> 0.015944235 | AW33: =Financials!AU7/Financials!AT7-1 -> -0.7452906 | AX33: =Financials!AV7/Financials!AU7-1 -> 0.011812331 | AY33: =Financials!AW7/Financials!AV7-1 -> 0.0075228121 | AZ33: =Financials!AX7/Financials!AW7-1 -> 0.0060568529 | BA33: =Financials!AY7/Financials!AX7-1 -> 0.0084282049 | BB33: =Financials!AZ7/Financials!AY7-1 -> 0.0066231185 | BC33: =Financials!BA7/Financials!AZ7-1 -> 0.0087949143 | BD33: =Financials!BB7/Financials!BA7-1 -> 0.0085682569 | ... CB33: =Financials!BZ7/Financials!BY7-1 -> 0.018449192
B34: 4.3 | C34: Net Loans & advances | D34: NPR | E34: =Financials!C31/Financials!B31-1 -> #VALUE! | F34: =Financials!D31/Financials!C31-1 -> -0.067566311 | G34: =Financials!E31/Financials!D31-1 -> 0.026873422 | H34: =Financials!F31/Financials!E31-1 -> 0.033414684 | I34: =Financials!G31/Financials!F31-1 -> 0.003218627 | J34: =Financials!H31/Financials!G31-1 -> 0.014474421 | K34: =Financials!I31/Financials!H31-1 -> -0.018673179 | L34: =Financials!J31/Financials!I31-1 -> -0.0024660287 | ... AU34: =Financials!AS31/Financials!AR31-1 -> 0.0020600059 | AW34: =Financials!AU31/Financials!AT31-1 -> -0.72004851 | AX34: =Financials!AV31/Financials!AU31-1 -> -0.011804878 | AY34: =Financials!AW31/Financials!AV31-1 -> 0.0015252647 | AZ34: =Financials!AX31/Financials!AW31-1 -> 0.0015944496 | BA34: =Financials!AY31/Financials!AX31-1 -> 0.0009769708 | BB34: =Financials!AZ31/Financials!AY31-1 -> 0.0033046062 | BC34: =Financials!BA31/Financials!AZ31-1 -> 0.049770102 | BD34: =Financials!BB31/Financials!BA31-1 -> 0.0017565645 | ... CB34: =Financials!BZ31/Financials!BY31-1 -> 0.0090317643
B35: 4.4 | C35: Core capital | D35: NPR | E35: =Financials!C14/Financials!B14-1 -> #VALUE! | F35: =Financials!D14/Financials!C14-1 -> 0.35779848 | G35: =Financials!E14/Financials!D14-1 -> 1.6905138 | H35: =Financials!F14/Financials!E14-1 -> -0.20722395 | I35: =Financials!G14/Financials!F14-1 -> 0.040932663 | J35: =Financials!H14/Financials!G14-1 -> 0.088197213 | K35: =Financials!I14/Financials!H14-1 -> 0.048228729 | L35: =Financials!J14/Financials!I14-1 -> 0.041768589 | ... AU35: =Financials!AS14/Financials!AR14-1 -> 0.046783666 | AW35: =Financials!AU14/Financials!AT14-1 -> -0.39979136 | AX35: =Financials!AV14/Financials!AU14-1 -> -0.0024536308 | AY35: =Financials!AW14/Financials!AV14-1 -> 0.042970636 | AZ35: =Financials!AX14/Financials!AW14-1 -> 0.13126224 | BA35: =Financials!AY14/Financials!AX14-1 -> 0.043720401 | BB35: =Financials!AZ14/Financials!AY14-1 -> 0.014967861 | BC35: =Financials!BA14/Financials!AZ14-1 -> 0.025674733 | BD35: =Financials!BB14/Financials!BA14-1 -> 0.020463401 | ... CB35: =Financials!BZ14/Financials!BY14-1 -> 0.13313176
B36: 4.5 | C36: Total Gross Income | D36: NPR | E36: =Financials!C41/Financials!B41-1 -> #VALUE! | F36: =Financials!D41/Financials!C41-1 -> 1.6737639 | G36: =Financials!E41/Financials!D41-1 -> -0.8490746 | H36: =Financials!F41/Financials!E41-1 -> 5.6488554 | I36: =Financials!G41/Financials!F41-1 -> 0.00069450885 | J36: =Financials!H41/Financials!G41-1 -> -0.015117212 | K36: =Financials!I41/Financials!H41-1 -> 0.0014209695 | L36: =Financials!J41/Financials!I41-1 -> 0.0014608583 | ... AU36: =Financials!AS41/Financials!AR41-1 -> 0.042065144 | AW36: =Financials!AU41/Financials!AT41-1 -> -0.30068395 | AX36: =Financials!AV41/Financials!AU41-1 -> 0.38074807 | AY36: =Financials!AW41/Financials!AV41-1 -> 0 | AZ36: =Financials!AX41/Financials!AW41-1 -> 0 | BA36: =Financials!AY41/Financials!AX41-1 -> 0 | BB36: =Financials!AZ41/Financials!AY41-1 -> 0 | BC36: =Financials!BA41/Financials!AZ41-1 -> 0 | BD36: =Financials!BB41/Financials!BA41-1 -> 0 | ... CB36: =Financials!BZ41/Financials!BY41-1 -> -0.00016918768
B37: 4.6 | C37: Membership | D37: NPR | E37: =Financials!C4/Financials!B4-1 -> #VALUE! | F37: =Financials!D4/Financials!C4-1 -> #DIV/0! | G37: =Financials!E4/Financials!D4-1 -> #DIV/0! | H37: =Financials!F4/Financials!E4-1 -> #DIV/0! | I37: =Financials!G4/Financials!F4-1 -> #DIV/0! | J37: =Financials!H4/Financials!G4-1 -> #DIV/0! | K37: =Financials!I4/Financials!H4-1 -> #DIV/0! | L37: =Financials!J4/Financials!I4-1 -> #DIV/0! | ... Q37: =Financials!O4/Financials!N4-1 -> #DIV/0!
B39: 5 | C39: Efficiency Ratios
B40: 5.1 | C40: FinCost-Deposits/Average Deposits | D40: NPR | E40: =Financials!C48/((Financials!C6+Financials!B6)/2) -> #VALUE! | F40: =Financials!D48/((Financials!D6+Financials!C6)/2) -> 0.076341227 | G40: =Financials!E48/((Financials!E6+Financials!D6)/2) -> 0.0071337245 | H40: =Financials!F48/((Financials!F6+Financials!E6)/2) -> 0.0020536809 | I40: =Financials!G48/((Financials!G6+Financials!F6)/2) -> 0.0031188738 | J40: =Financials!H48/((Financials!H6+Financials!G6)/2) -> 0.0042094763 | K40: =Financials!I48/((Financials!I6+Financials!H6)/2) -> 0.0052784953 | L40: =Financials!J48/((Financials!J6+Financials!I6)/2) -> 0.0063742263 | ... AU40: =Financials!AS48/((Financials!AS6+Financials!AR6)/2) -> 0.0026978036 | AW40: =Financials!AU48/((Financials!AU6+Financials!AT6)/2) -> 0.02188751 | AX40: =Financials!AV48/((Financials!AV6+Financials!AU6)/2) -> 0 | AY40: =Financials!AW48/((Financials!AW6+Financials!AV6)/2) -> 0 | AZ40: =Financials!AX48/((Financials!AX6+Financials!AW6)/2) -> 0 | BA40: =Financials!AY48/((Financials!AY6+Financials!AX6)/2) -> 0 | BB40: =Financials!AZ48/((Financials!AZ6+Financials!AY6)/2) -> 0 | BC40: =Financials!BA48/((Financials!BA6+Financials!AZ6)/2) -> 0 | BD40: =Financials!BB48/((Financials!BB6+Financials!BA6)/2) -> 0 | ... CB40: =Financials!BZ48/((Financials!BZ6+Financials!BY6)/2) -> 0
B41: 5.2 | C41: FinCost-Shares/Average Share capital | D41: NPR | E41: =Financials!C49/((Financials!C18+Financials!B18)/2) -> #VALUE! | F41: =Financials!D49/((Financials!D18+Financials!C18)/2) -> 0 | G41: =Financials!E49/((Financials!E18+Financials!D18)/2) -> 0 | H41: =Financials!F49/((Financials!F18+Financials!E18)/2) -> 0 | I41: =Financials!G49/((Financials!G18+Financials!F18)/2) -> 0 | J41: =Financials!H49/((Financials!H18+Financials!G18)/2) -> 0 | K41: =Financials!I49/((Financials!I18+Financials!H18)/2) -> 0 | L41: =Financials!J49/((Financials!J18+Financials!I18)/2) -> 0 | ... AU41: =Financials!AS49/((Financials!AS18+Financials!AR18)/2) -> 0 | AW41: =Financials!AU49/((Financials!AU18+Financials!AT18)/2) -> 0.11899175 | AX41: =Financials!AV49/((Financials!AV18+Financials!AU18)/2) -> 0 | AY41: =Financials!AW49/((Financials!AW18+Financials!AV18)/2) -> 0 | AZ41: =Financials!AX49/((Financials!AX18+Financials!AW18)/2) -> 0 | BA41: =Financials!AY49/((Financials!AY18+Financials!AX18)/2) -> 0 | BB41: =Financials!AZ49/((Financials!AZ18+Financials!AY18)/2) -> 0 | BC41: =Financials!BA49/((Financials!BA18+Financials!AZ18)/2) -> 0 | BD41: =Financials!BB49/((Financials!BB18+Financials!BA18)/2) -> 0 | ... CB41: =Financials!BZ49/((Financials!BZ18+Financials!BY18)/2) -> 0
B42: 5.3 | C42: FinCost-Ext Loans/Average Ext Loans | D42: NPR | E42: =Financials!C50/((Financials!C9+Financials!B9)/2) -> #VALUE! | F42: =Financials!D50/((Financials!D9+Financials!C9)/2) -> 0.20523164 | G42: =Financials!E50/((Financials!E9+Financials!D9)/2) -> 7.2103165 | H42: =Financials!F50/((Financials!F9+Financials!E9)/2) -> 0.081587017 | I42: =Financials!G50/((Financials!G9+Financials!F9)/2) -> 0.097970436 | J42: =Financials!H50/((Financials!H9+Financials!G9)/2) -> 0.14430267 | K42: =Financials!I50/((Financials!I9+Financials!H9)/2) -> 0.24657017 | L42: =Financials!J50/((Financials!J9+Financials!I9)/2) -> 0.30480118 | ... AU42: =Financials!AS50/((Financials!AS9+Financials!AR9)/2) -> 0.0091447684 | AW42: =Financials!AU50/((Financials!AU9+Financials!AT9)/2) -> 0.090580353 | AX42: =Financials!AV50/((Financials!AV9+Financials!AU9)/2) -> #DIV/0! | AY42: =Financials!AW50/((Financials!AW9+Financials!AV9)/2) -> #DIV/0! | AZ42: =Financials!AX50/((Financials!AX9+Financials!AW9)/2) -> #DIV/0! | BA42: =Financials!AY50/((Financials!AY9+Financials!AX9)/2) -> #DIV/0! | BB42: =Financials!AZ50/((Financials!AZ9+Financials!AY9)/2) -> #DIV/0! | BC42: =Financials!BA50/((Financials!BA9+Financials!AZ9)/2) -> #DIV/0! | BD42: =Financials!BB50/((Financials!BB9+Financials!BA9)/2) -> #DIV/0! | ... CB42: =Financials!BZ50/((Financials!BZ9+Financials!BY9)/2) -> 0.064849268
B43: 5.4 | C43: OpEx/Average Total Assets | D43: NPR | E43: =(Financials!C52+Financials!C53)/((Financials!C5+Financials!B5)/2) -> #VALUE! | F43: =(Financials!D52+Financials!D53)/((Financials!D5+Financials!C5)/2) -> 0.026206336 | G43: =(Financials!E52+Financials!E53)/((Financials!E5+Financials!D5)/2) -> 0.017617452 | H43: =(Financials!F52+Financials!F53)/((Financials!F5+Financials!E5)/2) -> 0.0015180532 | I43: =(Financials!G52+Financials!G53)/((Financials!G5+Financials!F5)/2) -> 0.003302234 | J43: =(Financials!H52+Financials!H53)/((Financials!H5+Financials!G5)/2) -> 0.0042012774 | K43: =(Financials!I52+Financials!I53)/((Financials!I5+Financials!H5)/2) -> 0.0049105247 | L43: =(Financials!J52+Financials!J53)/((Financials!J5+Financials!I5)/2) -> 0.006504271 | ... AU43: =(Financials!AS52+Financials!AS53)/((Financials!AS5+Financials!AR5)/2) -> 0.021523732 | AW43: =(Financials!AU52+Financials!AU53)/((Financials!AU5+Financials!AT5)/2) -> 0.024843636 | AX43: =(Financials!AV52+Financials!AV53)/((Financials!AV5+Financials!AU5)/2) -> 0.0058252793 | AY43: =(Financials!AW52+Financials!AW53)/((Financials!AW5+Financials!AV5)/2) -> 0.0091475651 | AZ43: =(Financials!AX52+Financials!AX53)/((Financials!AX5+Financials!AW5)/2) -> 0.010498944 | BA43: =(Financials!AY52+Financials!AY53)/((Financials!AY5+Financials!AX5)/2) -> 0.013498185 | BB43: =(Financials!AZ52+Financials!AZ53)/((Financials!AZ5+Financials!AY5)/2) -> 0.016553811 | BC43: =(Financials!BA52+Financials!BA53)/((Financials!BA5+Financials!AZ5)/2) -> 0.017892709 | BD43: =(Financials!BB52+Financials!BB53)/((Financials!BB5+Financials!BA5)/2) -> 0.020732625 | ... CB43: =(Financials!BZ52+Financials!BZ53)/((Financials!BZ5+Financials!BY5)/2) -> 0.019647727
B44: 5.5 | C44: Avge yield on Net loans | D44: NPR | E44: =Financials!C42/((Financials!C31+Financials!B31)/2) -> #VALUE! | F44: =Financials!D42/((Financials!D31+Financials!C31)/2) -> 0.025609859 | G44: =Financials!E42/((Financials!E31+Financials!D31)/2) -> 0.021452183 | H44: =Financials!F42/((Financials!F31+Financials!E31)/2) -> 0.025418561 | I44: =Financials!G42/((Financials!G31+Financials!F31)/2) -> 0.024967436 | J44: =Financials!H42/((Financials!H31+Financials!G31)/2) -> 0.024748276 | K44: =Financials!I42/((Financials!I31+Financials!H31)/2) -> 0.024803301 | L44: =Financials!J42/((Financials!J31+Financials!I31)/2) -> 0.025070198 | ... AU44: =Financials!AS42/((Financials!AS31+Financials!AR31)/2) -> 0.035811744 | AW44: =Financials!AU42/((Financials!AU31+Financials!AT31)/2) -> 0.028391682 | AX44: =Financials!AV42/((Financials!AV31+Financials!AU31)/2) -> 0.089496305 | AY44: =Financials!AW42/((Financials!AW31+Financials!AV31)/2) -> 0.089962253 | AZ44: =Financials!AX42/((Financials!AX31+Financials!AW31)/2) -> 0.089822141 | BA44: =Financials!AY42/((Financials!AY31+Financials!AX31)/2) -> 0.089706826 | BB44: =Financials!AZ42/((Financials!AZ31+Financials!AY31)/2) -> 0.089515143 | BC44: =Financials!BA42/((Financials!BA31+Financials!AZ31)/2) -> 0.087197802 | BD44: =Financials!BB42/((Financials!BB31+Financials!BA31)/2) -> 0.085056054 | ... CB44: =Financials!BZ42/((Financials!BZ31+Financials!BY31)/2) -> 0.079003776
B46: 6 | C46: Liquidity Ratio
B47: 6.1 | C47: minimum Liquidity | D47: 0.15 | E47: =(SFP!B4+SFP!B11)/(SFP!B31+SFP!B34+SFP!B35+SFP!B36+SFP!B37+SFP!B38) -> 0.12988214 | F47: =(SFP!C4+SFP!C11)/(SFP!C31+SFP!C34+SFP!C35+SFP!C36+SFP!C37+SFP!C38) -> 0.19610163 | G47: =(SFP!D4+SFP!D11)/(SFP!D31+SFP!D34+SFP!D35+SFP!D36+SFP!D37+SFP!D38) -> 0.28117848 | H47: =(SFP!E4+SFP!E11)/(SFP!E31+SFP!E34+SFP!E35+SFP!E36+SFP!E37+SFP!E38) -> 0.1804874 | I47: =(SFP!F4+SFP!F11)/(SFP!F31+SFP!F34+SFP!F35+SFP!F36+SFP!F37+SFP!F38) -> 0.14704211 | J47: =(SFP!G4+SFP!G11)/(SFP!G31+SFP!G34+SFP!G35+SFP!G36+SFP!G37+SFP!G38) -> 0.054056084 | K47: =(SFP!H4+SFP!H11)/(SFP!H31+SFP!H34+SFP!H35+SFP!H36+SFP!H37+SFP!H38) -> 0.08678322 | L47: =(SFP!I4+SFP!I11)/(SFP!I31+SFP!I34+SFP!I35+SFP!I36+SFP!I37+SFP!I38) -> 0.037384218 | ... AU47: =(SFP!AR4+SFP!AR11)/(SFP!AR31+SFP!AR34+SFP!AR35+SFP!AR36+SFP!AR37+SFP!AR38) -> 0.23441974 | AW47: =(SFP!AT4+SFP!AT11)/(SFP!AT31+SFP!AT34+SFP!AT35+SFP!AT36+SFP!AT37+SFP!AT38) -> 0.13809821 | AX47: =(SFP!AU4+SFP!AU11)/(SFP!AU31+SFP!AU34+SFP!AU35+SFP!AU36+SFP!AU37+SFP!AU38) -> 0.15701801 | AY47: =(SFP!AV4+SFP!AV11)/(SFP!AV31+SFP!AV34+SFP!AV35+SFP!AV36+SFP!AV37+SFP!AV38) -> 0.16672167 | AZ47: =(SFP!AW4+SFP!AW11)/(SFP!AW31+SFP!AW34+SFP!AW35+SFP!AW36+SFP!AW37+SFP!AW38) -> 0.20935865 | BA47: =(SFP!AX4+SFP!AX11)/(SFP!AX31+SFP!AX34+SFP!AX35+SFP!AX36+SFP!AX37+SFP!AX38) -> 0.21088948 | BB47: =(SFP!AY4+SFP!AY11)/(SFP!AY31+SFP!AY34+SFP!AY35+SFP!AY36+SFP!AY37+SFP!AY38) -> 0.22953567 | BC47: =(SFP!AZ4+SFP!AZ11)/(SFP!AZ31+SFP!AZ34+SFP!AZ35+SFP!AZ36+SFP!AZ37+SFP!AZ38) -> 0.20904444 | BD47: =(SFP!BA4+SFP!BA11)/(SFP!BA31+SFP!BA34+SFP!BA35+SFP!BA36+SFP!BA37+SFP!BA38) -> 0.23994181 | ... CB47: =(SFP!BY4+SFP!BY11)/(SFP!BY31+SFP!BY34+SFP!BY35+SFP!BY36+SFP!BY37+SFP!BY38) -> 0.1610208
C48: TECHNICAL Liquidity | E48: =(SFP!B4+SFP!B11)/(SFP!B32+SFP!B34+SFP!B35+SFP!B36+SFP!B37+SFP!B38) -> 0.10957701 | F48: =(SFP!C4+SFP!C11)/(SFP!C32+SFP!C34+SFP!C35+SFP!C36+SFP!C37+SFP!C38) -> 0.14876492 | G48: =(SFP!D4+SFP!D11)/(SFP!D32+SFP!D34+SFP!D35+SFP!D36+SFP!D37+SFP!D38) -> 0.18838483 | H48: =(SFP!E4+SFP!E11)/(SFP!E32+SFP!E34+SFP!E35+SFP!E36+SFP!E37+SFP!E38) -> 0.12915454 | I48: =(SFP!F4+SFP!F11)/(SFP!F32+SFP!F34+SFP!F35+SFP!F36+SFP!F37+SFP!F38) -> 0.10373806 | J48: =(SFP!G4+SFP!G11)/(SFP!G32+SFP!G34+SFP!G35+SFP!G36+SFP!G37+SFP!G38) -> 0.038709044 | K48: =(SFP!H4+SFP!H11)/(SFP!H32+SFP!H34+SFP!H35+SFP!H36+SFP!H37+SFP!H38) -> 0.061113504 | L48: =(SFP!I4+SFP!I11)/(SFP!I32+SFP!I34+SFP!I35+SFP!I36+SFP!I37+SFP!I38) -> 0.02730301 | ... AU48: =(SFP!AR4+SFP!AR11)/(SFP!AR32+SFP!AR34+SFP!AR35+SFP!AR36+SFP!AR37+SFP!AR38) -> 0.21159196 | AW48: =(SFP!AT4+SFP!AT11)/(SFP!AT32+SFP!AT34+SFP!AT35+SFP!AT36+SFP!AT37+SFP!AT38) -> 0.12737984 | AX48: =(SFP!AU4+SFP!AU11)/(SFP!AU32+SFP!AU34+SFP!AU35+SFP!AU36+SFP!AU37+SFP!AU38) -> 0.14481139 | AY48: =(SFP!AV4+SFP!AV11)/(SFP!AV32+SFP!AV34+SFP!AV35+SFP!AV36+SFP!AV37+SFP!AV38) -> 0.15519655 | AZ48: =(SFP!AW4+SFP!AW11)/(SFP!AW32+SFP!AW34+SFP!AW35+SFP!AW36+SFP!AW37+SFP!AW38) -> 0.18944732 | BA48: =(SFP!AX4+SFP!AX11)/(SFP!AX32+SFP!AX34+SFP!AX35+SFP!AX36+SFP!AX37+SFP!AX38) -> 0.19205085 | BB48: =(SFP!AY4+SFP!AY11)/(SFP!AY32+SFP!AY34+SFP!AY35+SFP!AY36+SFP!AY37+SFP!AY38) -> 0.20854367 | BC48: =(SFP!AZ4+SFP!AZ11)/(SFP!AZ32+SFP!AZ34+SFP!AZ35+SFP!AZ36+SFP!AZ37+SFP!AZ38) -> 0.18754843 | BD48: =(SFP!BA4+SFP!BA11)/(SFP!BA32+SFP!BA34+SFP!BA35+SFP!BA36+SFP!BA37+SFP!BA38) -> 0.2109472 | ... CB48: =(SFP!BY4+SFP!BY11)/(SFP!BY32+SFP!BY34+SFP!BY35+SFP!BY36+SFP!BY37+SFP!BY38) -> 0.14477411
B49: 7 | C49: Loan Loss Provisions Ratios
B50: 7.1 | C50: Actual LLP / Required LLP | D50: 1
B51: 7.2 | C51: allowance for loan loss/NPL
C52: Loan interest/Net Loans | E52: =SCI!B5/SFP!B14 -> 0.18221795 | F52: =SCI!C5/SFP!C14 -> 0.17887556 | G52: =SCI!D5/SFP!D14 -> 0.18355944 | H52: =SCI!E5/SFP!E14 -> 0.027879872 | I52: =SCI!F5/SFP!F14 -> 0.041473117 | J52: =SCI!G5/SFP!G14 -> 0.054842344 | K52: =SCI!H5/SFP!H14 -> 0.068532488 | L52: =SCI!I5/SFP!I14 -> 0.083915036 | ... O52: =SCI!L5/SFP!L14 -> 0.1231387 | P52: =SCI!M5/SFP!#REF! -> #REF! | Q52: =SCI!N5/SFP!#REF! -> #REF! | R52: =SCI!O5/SFP!#REF! -> #REF! | S52: =SCI!P5/SFP!#REF! -> #REF! | T52: =SCI!Q5/SFP!Q14 -> 0.17700194 | U52: =SCI!R5/SFP!R14 -> 0.19743059 | V52: =SCI!S5/SFP!S14 -> 0.19732612 | W52: =SCI!T5/SFP!T14 -> 0.21110355 | X52: =SCI!U5/SFP!U14 -> 0.22582622 | Y52: =SCI!V5/SFP!V14 -> 0.24499069 | Z52: =SCI!W5/SFP!W14 -> 0.068275434 | AA52: =SCI!X5/SFP!X14 -> 0.085250145 | ... AU52: =SCI!AR5/SFP!AR14 -> 0.17675146 | AW52: =SCI!AT5/SFP!AT14 -> 0.24003847 | AX52: =SCI!AU5/SFP!AU14 -> 0.038282978 | AY52: =SCI!AV5/SFP!AV14 -> 0.058908123 | AZ52: =SCI!AW5/SFP!AW14 -> 0.077882411 | BA52: =SCI!AX5/SFP!AX14 -> 0.097545584 | BB52: =SCI!AY5/SFP!AY14 -> 0.11928978 | BC52: =SCI!AZ5/SFP!AZ14 -> 0.1338818 | BD52: =SCI!BA5/SFP!BA14 -> 0.1536381 | ... CB52: =SCI!BY5/SFP!BY14 -> 0.11776273
C53: Gross loans/Total assets | E53: =Financials!C32/Financials!C5 -> 0.78261577 | F53: =Financials!D32/Financials!D5 -> 0.71113413 | G53: =Financials!E32/Financials!E5 -> 0.66794147 | H53: =Financials!F32/Financials!F5 -> 0.70034164 | I53: =Financials!G32/Financials!G5 -> 0.73394579 | J53: =Financials!H32/Financials!H5 -> 0.76836239 | K53: =Financials!I32/Financials!I5 -> 0.75490845 | L53: =Financials!J32/Financials!J5 -> 0.77811502 | ... AU53: =Financials!AS32/Financials!AS5 -> 0.83846194 | AW53: =Financials!AU32/Financials!AU5 -> 0.74971588 | AX53: =Financials!AV32/Financials!AV5 -> 0.74517579 | AY53: =Financials!AW32/Financials!AW5 -> 0.73685077 | AZ53: =Financials!AX32/Financials!AX5 -> 0.73728427 | BA53: =Financials!AY32/Financials!AY5 -> 0.72445363 | BB53: =Financials!AZ32/Financials!AZ5 -> 0.72357251 | BC53: =Financials!BA32/Financials!BA5 -> 0.7391303 | BD53: =Financials!BB32/Financials!BB5 -> 0.72392697 | ... CB53: =Financials!BZ32/Financials!BZ5 -> 0.83990431
B54: 8 | C54: Earnings
B55: 8.1 | C55: ROA | E55: =SCI!B33/(SFP!A27+SFP!B27/2) -> #REF! | F55: =SCI!C33/(SFP!B27+SFP!C27/2) -> #REF! | G55: =SCI!D33/(SFP!C27+SFP!D27/2) -> #REF! | H55: =SCI!E33/(SFP!D27+SFP!E27/2) -> #REF! | I55: =SCI!F33/(SFP!E27+SFP!F27/2) -> #REF! | J55: =SCI!G33/(SFP!F27+SFP!G27/2) -> #REF! | K55: =SCI!H33/(SFP!G27+SFP!H27/2) -> #REF! | L55: =SCI!I33/(SFP!H27+SFP!I27/2) -> #REF! | ... S55: =SCI!P33/(SFP!O27+SFP!P27/2) -> #REF! | T55: =SCI!Q33/(SFP!#REF!+SFP!Q27/2) -> #REF! | U55: =SCI!R33/(SFP!Q27+SFP!R27/2) -> 0.091718726 | V55: =SCI!S33/(SFP!R27+SFP!S27/2) -> 0.021403287 | W55: =SCI!T33/(SFP!S27+SFP!T27/2) -> 0.086521768 | X55: =SCI!U33/(SFP!T27+SFP!U27/2) -> 0.092418745 | Y55: =SCI!V33/(SFP!U27+SFP!V27/2) -> 0.095308004 | Z55: =SCI!W33/(SFP!V27+SFP!W27/2) -> 0.025179366 | AA55: =SCI!X33/(SFP!W27+SFP!X27/2) -> 0.027427623 | AB55: =SCI!Y33/(SFP!X27+SFP!Y27/2) -> 0.036644694 | ... AU55: =SCI!AR33/(SFP!AQ27+SFP!AR27/2) -> 0.070430829 | AW55: =SCI!AT33/(SFP!AS27+SFP!AT27/2) -> 0.019576663 | AX55: =SCI!AU33/(SFP!AT27+SFP!AU27/2) -> -0.00072002799 | AY55: =SCI!AV33/(SFP!AU27+SFP!AV27/2) -> 0.0067261553 | AZ55: =SCI!AW33/(SFP!AV27+SFP!AW27/2) -> 0.031393134 | BA55: =SCI!AX33/(SFP!AW27+SFP!AX27/2) -> 0.039028305 | BB55: =SCI!AY33/(SFP!AX27+SFP!AY27/2) -> 0.042229527 | BC55: =SCI!AZ33/(SFP!AY27+SFP!AZ27/2) -> 0.04669712 | BD55: =SCI!BA33/(SFP!AZ27+SFP!BA27/2) -> 0.049541918 | ... CB55: =SCI!BY33/(SFP!BX27+SFP!BY27/2) -> 0.053347726
B56: 8.2 | C56: Cost Income Ratio | E56: =SCI!B23/SCI!B19 -> #REF! | F56: =SCI!C23/SCI!C19 -> #REF! | G56: =SCI!D23/SCI!D19 -> #REF! | H56: =SCI!E23/SCI!E19 -> #REF! | I56: =SCI!F23/SCI!F19 -> #REF! | J56: =SCI!G23/SCI!G19 -> #REF! | K56: =SCI!H23/SCI!H19 -> #REF! | L56: =SCI!I23/SCI!I19 -> #REF! | ... AU56: =SCI!AR23/SCI!AR19 -> 0.29795186 | AW56: =SCI!AT23/SCI!AT19 -> 0.55022137 | AX56: =SCI!AU23/SCI!AU19 -> 0.52426377 | AY56: =SCI!AV23/SCI!AV19 -> 0.50223993 | AZ56: =SCI!AW23/SCI!AW19 -> 0.30152521 | BA56: =SCI!AX23/SCI!AX19 -> 0.32426911 | BB56: =SCI!AY23/SCI!AY19 -> 0.33819079 | BC56: =SCI!AZ23/SCI!AZ19 -> 0.35261353 | BD56: =SCI!BA23/SCI!BA19 -> 0.36558806 | ... CB56: =SCI!BY23/SCI!BY19 -> 0.31228585
B57: 8.3 | C57: Operating Expense Ratio | E57: =SCI!B23/SFP!B27 -> 0.085116251 | F57: =SCI!C23/SFP!C27 -> 0.060332293 | G57: =SCI!D23/SFP!D27 -> 0.050864587 | H57: =SCI!E23/SFP!E27 -> 0.006821232 | I57: =SCI!F23/SFP!F27 -> 0.012065152 | J57: =SCI!G23/SFP!G27 -> 0.016300071 | K57: =SCI!H23/SFP!H27 -> 0.019844365 | L57: =SCI!I23/SFP!I27 -> 0.024996546 | ... AU57: =SCI!AR23/SFP!AR27 -> 0.048604404 | AW57: =SCI!AT23/SFP!AT27 -> 0.10176669 | AX57: =SCI!AU23/SFP!AU27 -> 0.015556842 | AY57: =SCI!AV23/SFP!AV27 -> 0.022877119 | AZ57: =SCI!AW23/SFP!AW27 -> 0.02825572 | BA57: =SCI!AX23/SFP!AX27 -> 0.035035275 | BB57: =SCI!AY23/SFP!AY27 -> 0.041858869 | BC57: =SCI!AZ23/SFP!AZ27 -> 0.047260025 | BD57: =SCI!BA23/SFP!BA27 -> 0.053417385 | ... CB57: =SCI!BY23/SFP!BY27 -> 0.041496513
C58: Liquid assets/total assets | E58: =(Financials!C36+Financials!C29)/Financials!C5 -> 0.086323741 | F58: =(Financials!D36+Financials!D29)/Financials!D5 -> 0.12367589 | G58: =(Financials!E36+Financials!E29)/Financials!E5 -> 0.14978838 | H58: =(Financials!F36+Financials!F29)/Financials!F5 -> 0.10763133 | I58: =(Financials!G36+Financials!G29)/Financials!G5 -> 0.083528395 | J58: =(Financials!H36+Financials!H29)/Financials!H5 -> 0.030837288 | K58: =(Financials!I36+Financials!I29)/Financials!I5 -> 0.048197019 | L58: =(Financials!J36+Financials!J29)/Financials!J5 -> 0.021091786 | ... CB58: =(Financials!BZ36+Financials!BZ29)/Financials!BZ5 -> 0.086787531
B76: 0

Sheet CAELS
B1: FORTITUDE SACCO
B2: FINANCIAL SOUNDNESS INDICATORS | C2: Prude. Std | D2: AUDITED 2013 | E2: AUDITED 2014 | F2: AUDITED 2015 | G2: AUDITED 2016 | H2: AUDITED 2017 | I2: 43101 | J2: 43132 | K2: 43160 | L2: 43191 | M2: 43221 | N2: 43252 | O2: 43282 | P2: 43313 | Q2: 43344 | R2: 43374 | S2: 43405 | T2: 43435 | U2: AUDITED 2018 | V2: 43466 | W2: 43497 | X2: 43525 | Y2: 43556 | Z2: 43586 | AA2: 43617 | AB2: 43647 | AC2: 43678 | AD2: 43709 | AE2: 43739 | AF2: 43770 | AG2: 43800 | AH2: AUDITED 2019 | AI2: 43831 | AJ2: 43862 | AK2: 43891 | AL2: 43922 | AM2: 43952 | AN2: 43983 | AO2: 44013 | AP2: 44044 | AQ2: 44075 | AR2: 44105 | AS2: 44136 | AT2: 44166 | AU2: Audited 2020 | AV2: 44197 | AW2: 44228 | AX2: 44256 | AY2: 44287 | AZ2: 44317 | BA2: 44348 | BB2: 44378 | BC2: 44409 | BD2: 44440 | BE2: 44470 | BF2: 44501 | BG2: 44531 | BH2: Audited-2021 | BI2: 44583 | BJ2: 44614 | BK2: 44642 | BL2: 44673 | BM2: 44703 | BN2: 44734 | BO2: 44764 | BP2: 44795 | BQ2: 44826 | BR2: 44856 | BS2: 44887 | BT2: 44917 | BU2: Audited-2022 | BV2: 44949 | BW2: 44980 | BX2: 45008 | BY2: 45039 | BZ2: 45069 | CA2: 45100
B3: CAPITAL
B4: CORE CAPITAL | C4: ≥ Ksh.10M | D4: ='Prudential Ratios'!E6 -> 25.989635 | E4: ='Prudential Ratios'!F6 -> 35.288687 | F4: ='Prudential Ratios'!G6 -> 94.944699 | G4: ='Prudential Ratios'!H6 -> 75.269883 | H4: ='Prudential Ratios'!I6 -> 78.35088 | I4: ='Prudential Ratios'!J6 -> 85.261209 | J4: ='Prudential Ratios'!K6 -> 89.373249 | K4: ='Prudential Ratios'!L6 -> 93.106244 | ... CA4: ='Prudential Ratios'!CB6 -> 116.20579
B5: CCA | C5: ≥ 10% | D5: ='Prudential Ratios'!E7 -> 0.06345526 | E5: ='Prudential Ratios'!F7 -> 0.083161502 | F5: ='Prudential Ratios'!G7 -> 0.20483458 | G5: ='Prudential Ratios'!H7 -> 0.16493137 | H5: ='Prudential Ratios'!I7 -> 0.17936092 | I5: ='Prudential Ratios'!J7 -> 0.20150658 | J5: ='Prudential Ratios'!K7 -> 0.21135201 | K5: ='Prudential Ratios'!L7 -> 0.22749189 | ... CA5: ='Prudential Ratios'!CB7 -> 0.33781192
B6: ICA | C6: ≥ 8% | D6: ='Prudential Ratios'!E10 -> 0.043860816 | E6: ='Prudential Ratios'!F10 -> 0.06016331 | F6: ='Prudential Ratios'!G10 -> 0.18339309 | G6: ='Prudential Ratios'!H10 -> 0.14315405 | H6: ='Prudential Ratios'!I10 -> 0.15498853 | I6: ='Prudential Ratios'!J10 -> 0.17092535 | J6: ='Prudential Ratios'!K10 -> 0.17709219 | K6: ='Prudential Ratios'!L10 -> 0.18958322 | ... CA6: ='Prudential Ratios'!CB10 -> 0.22992606
B7: CCD | C7: ≥ 8% | D7: ='Prudential Ratios'!E8 -> 0.087708088 | E7: ='Prudential Ratios'!F8 -> 0.10820486 | F7: ='Prudential Ratios'!G8 -> 0.26090139 | G7: ='Prudential Ratios'!H8 -> 0.21334302 | H7: ='Prudential Ratios'!I8 -> 0.22591234 | I7: ='Prudential Ratios'!J8 -> 0.25547967 | J7: ='Prudential Ratios'!K8 -> 0.27117475 | K7: ='Prudential Ratios'!L8 -> 0.29894231 | ... CA7: ='Prudential Ratios'!CB8 -> 0.58461275
B8: Asset Quality
B9: NPL | C9: ≤ 6% | Q9: =form4!#REF! -> #REF!
B10: Earnings
B11: ROA | D11: ='Prudential Ratios'!E55 -> #REF! | E11: ='Prudential Ratios'!F55 -> #REF! | F11: ='Prudential Ratios'!G55 -> #REF! | G11: ='Prudential Ratios'!H55 -> #REF! | H11: ='Prudential Ratios'!I55 -> #REF! | I11: ='Prudential Ratios'!J55 -> #REF! | J11: ='Prudential Ratios'!K55 -> #REF! | K11: ='Prudential Ratios'!L55 -> #REF! | ... CA11: ='Prudential Ratios'!CB55 -> 0.053347726
B12: CIR | D12: ='Prudential Ratios'!E56 -> #REF! | E12: ='Prudential Ratios'!F56 -> #REF! | F12: ='Prudential Ratios'!G56 -> #REF! | G12: ='Prudential Ratios'!H56 -> #REF! | H12: ='Prudential Ratios'!I56 -> #REF! | I12: ='Prudential Ratios'!J56 -> #REF! | J12: ='Prudential Ratios'!K56 -> #REF! | K12: ='Prudential Ratios'!L56 -> #REF! | ... CA12: ='Prudential Ratios'!CB56 -> 0.31228585
B13: OER | D13: ='Prudential Ratios'!E57 -> 0.085116251 | E13: ='Prudential Ratios'!F57 -> 0.060332293 | F13: ='Prudential Ratios'!G57 -> 0.050864587 | G13: ='Prudential Ratios'!H57 -> 0.006821232 | H13: ='Prudential Ratios'!I57 -> 0.012065152 | I13: ='Prudential Ratios'!J57 -> 0.016300071 | J13: ='Prudential Ratios'!K57 -> 0.019844365 | K13: ='Prudential Ratios'!L57 -> 0.024996546 | ... CA13: ='Prudential Ratios'!CB57 -> 0.041496513
B14: LIQUIDITY
B15: MIN LIQ | C15: 0.15 | D15: ='Prudential Ratios'!E47 -> 0.12988214 | E15: ='Prudential Ratios'!F47 -> 0.19610163 | F15: ='Prudential Ratios'!G47 -> 0.28117848 | G15: ='Prudential Ratios'!H47 -> 0.1804874 | H15: ='Prudential Ratios'!I47 -> 0.14704211 | I15: ='Prudential Ratios'!J47 -> 0.054056084 | J15: ='Prudential Ratios'!K47 -> 0.08678322 | K15: ='Prudential Ratios'!L47 -> 0.037384218 | ... CA15: ='Prudential Ratios'!CB47 -> 0.1610208
B16: TEC LIQ | D16: ='Prudential Ratios'!E48 -> 0.10957701 | E16: ='Prudential Ratios'!F48 -> 0.14876492 | F16: ='Prudential Ratios'!G48 -> 0.18838483 | G16: ='Prudential Ratios'!H48 -> 0.12915454 | H16: ='Prudential Ratios'!I48 -> 0.10373806 | I16: ='Prudential Ratios'!J48 -> 0.038709044 | J16: ='Prudential Ratios'!K48 -> 0.061113504 | K16: ='Prudential Ratios'!L48 -> 0.02730301 | ... CA16: ='Prudential Ratios'!CB48 -> 0.14477411
B17: EB | C17: ≤ 25% | D17: ='Prudential Ratios'!E27 -> 0.14272236 | E17: ='Prudential Ratios'!F27 -> 0.0018448707 | F17: ='Prudential Ratios'!G27 -> 0.001688932 | G17: ='Prudential Ratios'!H27 -> 0.0017153851 | H17: ='Prudential Ratios'!I27 -> 0.0017921054 | I17: ='Prudential Ratios'!J27 -> 0.0018501943 | J17: ='Prudential Ratios'!K27 -> 0.001851307 | K17: ='Prudential Ratios'!L27 -> 0.0019127875 | ... CA17: ='Prudential Ratios'!CB27 -> 0.046027731
B18: LIQ/TA | D18: ='Prudential Ratios'!E58 -> 0.086323741 | E18: ='Prudential Ratios'!F58 -> 0.12367589 | F18: ='Prudential Ratios'!G58 -> 0.14978838 | G18: ='Prudential Ratios'!H58 -> 0.10763133 | H18: ='Prudential Ratios'!I58 -> 0.083528395 | I18: ='Prudential Ratios'!J58 -> 0.030837288 | J18: ='Prudential Ratios'!K58 -> 0.048197019 | K18: ='Prudential Ratios'!L58 -> 0.021091786 | ... CA18: ='Prudential Ratios'!CB58 -> 0.086787531
B19: STRUCTURE
B20: NEA | C20: ≤ 10% | D20: ='Prudential Ratios'!E14 -> 0.13921023 | E20: ='Prudential Ratios'!F14 -> 0.094990974 | F20: ='Prudential Ratios'!G14 -> 0.11800484 | G20: ='Prudential Ratios'!H14 -> 0.12675515 | H20: ='Prudential Ratios'!I14 -> 0.10067358 | I20: ='Prudential Ratios'!J14 -> 0.13039883 | J20: ='Prudential Ratios'!K14 -> 0.1264507 | K20: ='Prudential Ratios'!L14 -> 0.12800998 | ... CA20: ='Prudential Ratios'!CB14 -> 0.08297919
B21: LB | C21: ≤ 5% | D21: ='Prudential Ratios'!E15 -> 0.017833781 | E21: ='Prudential Ratios'!F15 -> 0.01452311 | F21: ='Prudential Ratios'!G15 -> 0.01288188 | G21: ='Prudential Ratios'!H15 -> 0.012663382 | H21: ='Prudential Ratios'!I15 -> 0.013661078 | I21: ='Prudential Ratios'!J15 -> 0.013696816 | J21: ='Prudential Ratios'!K15 -> 0.013297813 | K21: ='Prudential Ratios'!L15 -> 0.013318733 | ... CA21: ='Prudential Ratios'!CB15 -> 0.056581642
B22: FITD | C22: ≤ 5% | D22: ='Prudential Ratios'!E19 -> 0.060285214 | E22: ='Prudential Ratios'!F19 -> 0.13586799 | F22: ='Prudential Ratios'!G19 -> 0.12176194 | G22: ='Prudential Ratios'!H19 -> 0.11269646 | H22: ='Prudential Ratios'!I19 -> 0.11464343 | I22: ='Prudential Ratios'!J19 -> 0.11914009 | J22: ='Prudential Ratios'!K19 -> 0.12064096 | K22: ='Prudential Ratios'!L19 -> 0.127662 | ... CA22: ='Prudential Ratios'!CB19 -> 0.050172843
B23: FICC | C23: ≤ 40% | D23: ='Prudential Ratios'!E20 -> 0.68733928 | E23: ='Prudential Ratios'!F20 -> 1.2556552 | F23: ='Prudential Ratios'!G20 -> 0.46669717 | G23: ='Prudential Ratios'!H20 -> 0.52824067 | H23: ='Prudential Ratios'!I20 -> 0.50746862 | I23: ='Prudential Ratios'!J20 -> 0.46633884 | J23: ='Prudential Ratios'!K20 -> 0.44488271 | K23: ='Prudential Ratios'!L20 -> 0.42704562 | ... CA23: ='Prudential Ratios'!CB20 -> 0.085822356
BH26: =37194132-32071373 -> 5122759

Sheet Financials
B1: FORTITUDE SACCO SOCIETY
B3: Year | C3: AUDITED 2013 | D3: AUDITED 2014 | E3: AUDITED 2015 | F3: AUDITED 2016 | G3: AUDITED 2017 | H3: 43101 | I3: 43132 | J3: 43160 | K3: 43191 | L3: 43221 | M3: 43252 | N3: 43282 | O3: 43313 | P3: 43344 | Q3: 43374 | R3: 43405 | S3: 43435 | T3: AUDITED 2018 | U3: 43466 | V3: 43497 | W3: 43525 | X3: 43556 | Y3: 43586 | Z3: 43617 | AA3: 43647 | AB3: 43678 | AC3: 43709 | AD3: 43739 | AE3: 43770 | AF3: 43800 | AG3: AUDITED 2019 | AH3: 43831 | AI3: 43862 | AJ3: 43891 | AK3: 43922 | AL3: 43952 | AM3: 43983 | AN3: 44013 | AO3: 44044 | AP3: 44075 | AQ3: 44105 | AR3: 44136 | AS3: 44166 | AT3: AUDITED 2020 | AU3: 44197 | AV3: 44228 | AW3: 44256 | AX3: 44287 | AY3: 44317 | AZ3: 44348 | BA3: 44378 | BB3: 44409 | BC3: 44440 | BD3: 44470 | BE3: 44501 | BF3: 44531 | BG3: Audited-2021 | BH3: 44583 | BI3: 44614 | BJ3: 44642 | BK3: 44673 | BL3: 44703 | BM3: 44734 | BN3: 44764 | BO3: 44795 | BP3: 44826 | BQ3: 44856 | BR3: 44887 | BS3: 44917 | BT3: Audited-2022 | BU3: 44949 | BV3: 44980 | BW3: 45008 | BX3: 45039 | BY3: 45069 | BZ3: 45100
A4: 1 | B4: Membership
A5: 2 | B5: Total Assets | C5: =SFP!B27 -> 409574162 | D5: =SFP!C27 -> 424339220 | E5: =SFP!D27 -> 4.6351889e+08 | F5: =SFP!E27 -> 4.5637093e+08 | G5: =SFP!F27 -> 4.3683362e+08 | H5: =SFP!G27 -> 4.2311874e+08 | I5: =SFP!H27 -> 4.2286443e+08 | J5: =SFP!I27 -> 4.092728e+08 | ... BZ5: =SFP!BY27 -> 3.4399552e+08
A6: 3 | B6: Total Deposits | C6: =SFP!B32 -> 296319708 | D6: =SFP!C32 -> 326128476 | E6: =SFP!D32 -> 3.6391029e+08 | F6: =SFP!E32 -> 3.5281156e+08 | G6: =SFP!F32 -> 3.4681983e+08 | H6: =SFP!G32 -> 3.3372991e+08 | I6: =SFP!H32 -> 3.2957806e+08 | J6: =SFP!I32 -> 3.1145221e+08 | ... BZ6: =SFP!BY32 -> 1.9877396e+08
A7: 3.1 | B7: Deposits-Members(BOSA) | C7: =SFP!B31 -> 245876845 | D7: =SFP!C31 -> 240972613 | E7: =SFP!D31 -> 2.4228165e+08 | F7: =SFP!E31 -> 2.4464437e+08 | G7: =SFP!F31 -> 2.4323434e+08 | H7: =SFP!G31 -> 2.3803121e+08 | I7: =SFP!H31 -> 2.3093434e+08 | J7: =SFP!I31 -> 2.2619326e+08 | ... BZ7: =SFP!BY31 -> 1.779673e+08
A8: 3.2 | B8: Deposits-Customers(FOSA) | C8: =SFP!B29 -> 50442863 | D8: =SFP!C29 -> 81985036 | E8: =SFP!D29 -> 4074376.9 | F8: =SFP!E29 -> 4984401.3 | G8: =SFP!F29 -> 5076228.9 | H8: =SFP!G29 -> 7141510.8 | I8: =SFP!H29 -> 7139384.9 | J8: =SFP!I29 -> 8498751.9 | ... BZ8: =SFP!BY29 -> 20806653
A9: 4 | B9: External Borrowing | C9: =SFP!B39 -> 58455393 | D9: =SFP!C39 -> 782851 | E9: =SFP!D39 -> 782851.88 | F9: =SFP!E39 -> 782851.88 | G9: =SFP!F39 -> 782851.88 | H9: =SFP!G39 -> 782851.88 | I9: =SFP!H39 -> 782851.88 | J9: =SFP!I39 -> 782851.88 | ... BZ9: =SFP!BY39 -> 15833333
A10: 4.1 | B10: Short term Liabilities | C10: =SFP!B34+SFP!B35+SFP!B36+SFP!B37+SFP!B38 -> 26338982 | D10: =SFP!C34+SFP!C35+SFP!C36+SFP!C37+SFP!C38 -> 26646429 | E10: =SFP!D34+SFP!D35+SFP!D36+SFP!D37+SFP!D38 -> 4642444.9 | F10: =SFP!E34+SFP!E35+SFP!E36+SFP!E37+SFP!E38 -> 27506534 | G10: =SFP!F34+SFP!F35+SFP!F36+SFP!F37+SFP!F38 -> 4912342.2 | H10: =SFP!G34+SFP!G35+SFP!G36+SFP!G37+SFP!G38 -> 3344665.9 | I10: =SFP!H34+SFP!H35+SFP!H36+SFP!H37+SFP!H38 -> 3912962.6 | J10: =SFP!I34+SFP!I35+SFP!I36+SFP!I37+SFP!I38 -> 4714182.8 | ... BZ10: =SFP!BY34+SFP!BY35+SFP!BY36+SFP!BY37+SFP!BY38 -> 7440560
A13: 5 | B13: Share capital and Reserves
A14: 5.1 | B14: Core Capital | C14: =C17-C28 -> 25989635 | D14: =D17-D28 -> 35288687 | E14: =E17-E28 -> 94944699 | F14: =F17-F28 -> 75269883 | G14: =G17-G28 -> 78350880 | H14: =H17-H28 -> 85261209 | I14: =I17-I28 -> 89373249 | J14: =J17-J28 -> 93106244 | ... R14: =R17-R28 -> 62725037 | S14: =S17-S26 -> 1.5054802e+08 | T14: =T17-T26 -> 88729697 | U14: =U17-U26 -> 1.5578813e+08 | V14: =V17-V26 -> 1.6340642e+08 | W14: =W17-W26 -> 1.6700553e+08 | X14: =X17-X26 -> 1.1120986e+08 | Y14: =Y17-Y26 -> 1.138181e+08 | Z14: =Z17-Z26 -> 1.231101e+08 | ... AF14: =AF17-AF26 -> 1.6363229e+08 | AG14: =AG17 -> 102637695 | AH14: =AH17 -> 1.7237666e+08 | AI14: =AI17 -> 1.1375632e+08 | AJ14: =AJ17 -> 1.1874227e+08 | AK14: =AK17 -> 1.2874175e+08 | AL14: =AL17 -> 1.3453167e+08 | AM14: =AM17 -> 1.4103633e+08 | AN14: =AN17 -> 0 | ... BZ14: =BZ17 -> 1.1620579e+08
A15: 5.2 | B15: Institutional Capital | C15: =C14-C18 -> 17964257 | D15: =D14-D18 -> 25529652 | E15: =E14-E18 -> 85006164 | F15: =F14-F18 -> 65331348 | G15: =G14-G18 -> 67704199 | H15: =H14-H18 -> 72321719 | I15: =I14-I18 -> 74885989 | J15: =J14-J18 -> 77591254 | ... BZ15: =BZ14-BZ18 -> 79093535
A17: 5.3 | B17: Total Capital | C17: =SUM(C18:C21) -> 25989635 | D17: =SUM(D18:D21) -> 35288687 | E17: =SUM(E18:E21) -> 94944699 | F17: =SUM(F18:F21) -> 75269883 | G17: =SUM(G18:G21) -> 78350880 | H17: =SUM(H18:H21) -> 85261209 | I17: =SUM(I18:I21) -> 89373249 | J17: =SUM(J18:J21) -> 93106244 | ... BZ17: =SUM(BZ18:BZ21) -> 1.1620579e+08
A18: 5.3.1 | B18: Members Share Capital | C18: =SFP!B42 -> 8025378 | D18: =SFP!C42 -> 9759035 | E18: =SFP!D42 -> 9938535.4 | F18: =SFP!E42 -> 9938535.4 | G18: =SFP!F42 -> 10646681 | H18: =SFP!G42 -> 12939491 | I18: =SFP!H42 -> 14487260 | J18: =SFP!I42 -> 15514989 | ... BZ18: =SFP!BY42 -> 37112253
A19: 5.3.3 | B19: Retained Earnings | C19: =SFP!B45 -> 2911424 | D19: =SFP!C45 -> 17652005 | E19: =SFP!D45 -> 78460465 | F19: =SFP!E45 -> 21809944 | G19: =SFP!F45 -> 24152569 | H19: =SFP!G45 -> 29428468 | I19: =SFP!H45 -> 31931789 | J19: =SFP!I45 -> 34574304 | ... BZ19: =SFP!BY45 -> 52261563
A20: 5.3.5 | B20: Statutory Reserves | C20: =SFP!B50 -> 6343633 | D20: =SFP!C50 -> 7743437 | E20: =SFP!D50 -> 6343633 | F20: =SFP!E50 -> 7743437 | G20: =SFP!F50 -> 7743437 | H20: =SFP!G50 -> 7743437 | I20: =SFP!H50 -> 7743437 | J20: =SFP!I50 -> 7743437 | ... BZ20: =SFP!BY50 -> 21677841
A21: 5.3.6 | B21: Capital Reserve | C21: =SFP!B51 -> 8709200 | D21: =SFP!C51 -> 134210 | E21: =SFP!D51 -> 202065.67 | F21: =SFP!E51 -> 35777967 | G21: =SFP!F51 -> 35808193 | H21: =SFP!G51 -> 35149814 | I21: =SFP!H51 -> 35210764 | J21: =SFP!I51 -> 35273514 | ... BZ21: =SFP!BY51 -> 5154131.2
A22: 5.3.7 | B22: Supplementary Capital & reserves
A23: a | B23: Proposed Dividends | C23: =SFP!B53 -> 1302538 | D23: =SFP!C53 -> 0 | E23: =SFP!D53 -> 0 | F23: =SFP!E53 -> 0 | G23: =SFP!F53 -> 0 | H23: =SFP!G53 -> 0 | I23: =SFP!H53 -> 0 | J23: =SFP!I53 -> 0 | ... BZ23: =SFP!BY53 -> 0
A24: b
A26: 6 | B26: Investments | C26: =C27+C28+C29 -> 17863697 | D26: =D27+D28+D29 -> 44310422 | E26: =E27+E28+E29 -> 44310422 | F26: =F27+F28+F29 -> 39760613 | G26: =G27+G28+G29 -> 39760613 | H26: =H27+H28+H29 -> 39760613 | I26: =I27+I28+I29 -> 39760613 | J26: =J27+J28+J29 -> 39760613 | ... BZ26: =BZ27+BZ28+BZ29 -> 9973054.5
A27: 6.1 | B27: Investments in Coop bank, CIC, Kuscco, Kerussu & Codic | C27: =SFP!B13 -> 4267836 | D27: =SFP!C13 -> 39760613 | E27: =SFP!D13 -> 39760613 | F27: =SFP!E13 -> 39760613 | G27: =SFP!F13 -> 39760613 | H27: =SFP!G13 -> 39760613 | I27: =SFP!H13 -> 39760613 | J27: =SFP!I13 -> 39760613 | ... AF27: =SFP!AE13 -> 4228554.9 | AG27: =SFP!AF12 -> 4228556 | AH27: =SFP!AG12 -> 4228554.9 | AI27: =SFP!AH12 -> 4228554.9 | AJ27: =SFP!AI12 -> 4228554.9 | AK27: =SFP!AJ12 -> 4228554.9 | AL27: =SFP!AK12 -> 4228554.9 | AM27: =SFP!AL12 -> 4228554.9 | AN27: =SFP!AM12 -> 0 | ... BZ27: =SFP!BY12 -> 9973054.5
A28: 6.2 | B28: Equity Investments (at cost) | AG28: =SFP!AF13 -> 0 | AH28: =SFP!AG13 -> 0 | AI28: =SFP!AH13 -> 0 | AJ28: =SFP!AI13 -> 0 | AK28: =SFP!AJ13 -> 0 | AL28: =SFP!AK13 -> 0 | AM28: =SFP!AL13 -> 0 | AN28: =SFP!AM13 -> 0 | ... BZ28: =SFP!BY13 -> 0
A29: 6.3 | B29: Deposits in KUSCCO CFP | C29: =SFP!B11 -> 13595861 | D29: =SFP!C11 -> 4549809 | E29: =SFP!D11 -> 4549809 | F29: =SFP!E11 -> 0 | G29: =SFP!F11 -> 0 | H29: =SFP!G11 -> 0 | I29: =SFP!H11 -> 0 | J29: =SFP!I11 -> 0 | ... BZ29: =SFP!BY11 -> 0
A31: 7 | B31: Net Loans & advances | C31: =C32-C33 -> 312933438 | D31: =D32-D33 -> 291789680 | E31: =E32-E33 -> 2.9963107e+08 | F31: =F32-F33 -> 3.0964314e+08 | G31: =G32-G33 -> 3.1063977e+08 | H31: =H32-H33 -> 3.151361e+08 | I31: =I32-I33 -> 3.0925151e+08 | J31: =J32-J33 -> 3.0848889e+08 | ... BZ31: =BZ32-BZ33 -> 2.7562348e+08
A32: 7.1 | B32: Gross Loans & advances | C32: =SFP!B15 -> 320539200 | D32: =SFP!C15 -> 301762103 | E32: =SFP!D15 -> 3.0960349e+08 | F32: =SFP!E15 -> 3.1961557e+08 | G32: =SFP!F15 -> 3.2061219e+08 | H32: =SFP!G15 -> 3.2510852e+08 | I32: =SFP!H15 -> 3.1922393e+08 | J32: =SFP!I15 -> 3.1846131e+08 | ... BZ32: =SFP!BY15 -> 2.8892332e+08
A33: 7.3 | B33: Allowance for loan losses | C33: =SFP!B16 -> 7605762 | D33: =SFP!C16 -> 9972423 | E33: =SFP!D16 -> 9972423.1 | F33: =SFP!E16 -> 9972423.1 | G33: =SFP!F16 -> 9972423.1 | H33: =SFP!G16 -> 9972423.1 | I33: =SFP!H16 -> 9972423.1 | J33: =SFP!I16 -> 9972423.1 | ... BZ33: =SFP!BY16 -> 13299846
A34: 7.4 | B34: Non Performing Loans | C34: =(#REF!+#REF!+#REF!) -> #REF! | D34: =(#REF!+#REF!+#REF!) -> #REF! | E34: =(#REF!+#REF!+#REF!) -> #REF! | F34: =(#REF!+#REF!+#REF!) -> #REF! | G34: =(#REF!+#REF!+#REF!) -> #REF! | H34: =(#REF!+#REF!+#REF!) -> #REF! | I34: =(#REF!+#REF!+#REF!) -> #REF! | J34: =(#REF!+#REF!+#REF!) -> #REF! | ... BZ34: =(#REF!+#REF!+#REF!) -> #REF!
A35: 7.5 | B35: Required loan loss provision | C35: =#REF! -> #REF! | D35: =#REF! -> #REF! | E35: =#REF! -> #REF! | F35: =#REF! -> #REF! | G35: =#REF! -> #REF! | H35: =#REF! -> #REF! | I35: =#REF! -> #REF! | J35: =#REF! -> #REF! | ... BZ35: =#REF! -> #REF!
A36: 7.6 | B36: Cash and Cash equipments | C36: =SFP!B4 -> 21760113 | D36: =SFP!C4 -> 47930722 | E36: =SFP!D4 -> 64879933 | F36: =SFP!E4 -> 49119809 | G36: =SFP!F4 -> 36488011 | H36: =SFP!G4 -> 13047835 | I36: =SFP!H4 -> 20380805 | J36: =SFP!I4 -> 8632294.1 | ... BZ36: =SFP!BY4 -> 29854522
A38: 8 | B38: Non-Earning Assets | C38: =SFP!B7+SFP!B17+SFP!B23+SFP!B24+SFP!B25+SFP!B26 -> 57016914 | D38: =SFP!C7+SFP!C17+SFP!C23+SFP!C24+SFP!C25+SFP!C26 -> 40308396 | E38: =SFP!D7+SFP!D17+SFP!D23+SFP!D24+SFP!D25+SFP!D26 -> 54697472 | F38: =SFP!E7+SFP!E17+SFP!E23+SFP!E24+SFP!E25+SFP!E26 -> 57847366 | G38: =SFP!F7+SFP!F17+SFP!F23+SFP!F24+SFP!F25+SFP!F26 -> 43977606 | H38: =SFP!G7+SFP!G17+SFP!G23+SFP!G24+SFP!G25+SFP!G26 -> 55174190 | I38: =SFP!H7+SFP!H17+SFP!H23+SFP!H24+SFP!H25+SFP!H26 -> 53471504 | J38: =SFP!I7+SFP!I17+SFP!I23+SFP!I24+SFP!I25+SFP!I26 -> 52391004 | ... BZ38: =SFP!BY7+SFP!BY17+SFP!BY23+SFP!BY24+SFP!BY25+SFP!BY26 -> 28544470
A39: 8.1 | B39: Property and Equipment | C39: =SFP!B23 -> 7304256 | D39: =SFP!C23 -> 6162725 | E39: =SFP!D23 -> 5970995 | F39: =SFP!E23 -> 5779199.6 | G39: =SFP!F23 -> 5967618.3 | H39: =SFP!G23 -> 5795379.7 | I39: =SFP!H23 -> 5623172.2 | J39: =SFP!I23 -> 5450995 | ... BZ39: =SFP!BY23 -> 19463831
A41: 9 | B41: Turnover | C41: =C42+C43+C44 -> 16220738 | D41: =D42+D43+D44 -> 43370424 | E41: =E42+E43+E44 -> 6545698.7 | F41: =F42+F43+F44 -> 43521404 | G41: =G42+G43+G44 -> 43551630 | H41: =H42+H43+H44 -> 42893251 | I41: =I42+I43+I44 -> 42954201 | J41: =J42+J43+J44 -> 43016951 | ... BZ41: =BZ42+BZ43+BZ44 -> 32073858
A42: 9.1 | B42: Loan Interest | C42: =SFP!B50 -> 6343633 | D42: =SFP!C50 -> 7743437 | E42: =SFP!D50 -> 6343633 | F42: =SFP!E50 -> 7743437 | G42: =SFP!F50 -> 7743437 | H42: =SFP!G50 -> 7743437 | I42: =SFP!H50 -> 7743437 | J42: =SFP!I50 -> 7743437 | ... BZ42: =SFP!BY50 -> 21677841
B43: Income from investments | C43: =SFP!B51 -> 8709200 | D43: =SFP!C51 -> 134210 | E43: =SFP!D51 -> 202065.67 | F43: =SFP!E51 -> 35777967 | G43: =SFP!F51 -> 35808193 | H43: =SFP!G51 -> 35149814 | I43: =SFP!H51 -> 35210764 | J43: =SFP!I51 -> 35273514 | ... BZ43: =SFP!BY51 -> 5154131.2
A44: 9.2 | B44: Fees & Commissions | C44: =SFP!B52 -> 1167905 | D44: =SFP!C52 -> 35492777 | E44: =SFP!D52 -> 0 | F44: =SFP!E52 -> 0 | G44: =SFP!F52 -> 0 | H44: =SFP!G52 -> 0 | I44: =SFP!H52 -> 0 | J44: =SFP!I52 -> 0 | ... BZ44: =SFP!BY52 -> 5241886
B45: Average yield on loans
A47: 10 | B47: Total Expenses (FinCosts + OpEx) | C47: =SUM(C48:C53) -> 47439181 | D47: =SUM(D48:D53) -> 40764917 | E47: =SUM(E48:E53) -> 22339455 | F47: =SUM(F48:F53) -> 4546921.1 | G47: =SUM(G48:G53) -> 5916993.1 | H47: =SUM(H48:H53) -> 4444001.6 | I47: =SUM(I48:I53) -> 5326077.8 | J47: =SUM(J48:J53) -> 7221113.4 | ... BZ47: =SUM(BZ48:BZ53) -> 8827607
A48: 10.1 | B48: Financial Exp. (Interest on deposits) | C48: =SCI!B13 -> 18861799 | D48: =SCI!C13 -> 23759229 | E48: =SCI!D13 -> 2461273.2 | F48: =SCI!E13 -> 735959 | G48: =SCI!F13 -> 1091031 | H48: =SCI!G13 -> 1432379 | I48: =SCI!H13 -> 1750634 | J48: =SCI!I13 -> 2043036 | ... BZ48: =SCI!BY13 -> 0
A49: 10.2 | B49: Financial Exp. (Dividends) | C49: =SCI!B15 -> 0 | D49: =SCI!C15 -> 0 | E49: =SCI!D15 -> 0 | F49: =SCI!E15 -> 0 | G49: =SCI!F15 -> 0 | H49: =SCI!G15 -> 0 | I49: =SCI!H15 -> 0 | J49: =SCI!I15 -> 0 | ... BZ49: =SCI!BY15 -> 0
A50: 10.3 | B50: Financial Exp. (Interest on bank loans) | C50: =SCI!B14 -> 10401634 | D50: =SCI!C14 -> 6078781 | E50: =SCI!D14 -> 5644606.6 | F50: =SCI!E14 -> 63870.55 | G50: =SCI!F14 -> 76696.34 | H50: =SCI!G14 -> 112967.62 | I50: =SCI!H14 -> 193027.92 | J50: =SCI!I14 -> 238614.18 | ... BZ50: =SCI!BY14 -> 1053800.6
A51: 10.4 | B51: Other Financial Expenses | C51: =SCI!B16+SCI!B17+SCI!B18 -> 1174922 | D51: =SCI!C16+SCI!C17+SCI!C18 -> 0 | E51: =SCI!D16+SCI!D17+SCI!D18 -> 6412676 | F51: =SCI!E16+SCI!E17+SCI!E18 -> 3048870.7 | G51: =SCI!F16+SCI!F17+SCI!F18 -> 3274480.5 | H51: =SCI!G16+SCI!G17+SCI!G18 -> 1092205.7 | I51: =SCI!H16+SCI!H17+SCI!H18 -> 1305305.3 | J51: =SCI!I16+SCI!I17+SCI!I18 -> 2233240.2 | ... M51: =SCI!L16+SCI!L17+SCI!L18 -> 3566537.4 | N51: =SCI!M16+SCI!#REF!+SCI!M18 -> #REF! | O51: =SCI!N16+SCI!N17+SCI!N18 -> 4013674.5 | P51: =SCI!O16+SCI!O17+SCI!O18 -> 4933601.2 | Q51: =SCI!P16+SCI!P17+SCI!P18 -> 642233 | R51: =SCI!Q16+SCI!Q17+SCI!Q18 -> 0 | S51: =SCI!R16+SCI!R17+SCI!R18 -> 2837191.8 | T51: =SCI!S16+SCI!S17+SCI!S18 -> 327276 | U51: =SCI!T16+SCI!T17+SCI!T18 -> 4318395.6 | V51: =SCI!U16+SCI!U17+SCI!U18 -> 4418783.4 | ... BZ51: =SCI!BY16+SCI!BY17+SCI!BY18 -> 1147020.2
A52: 10.5 | B52: Administrative Expenses | C52: =SCI!B28 -> 14920738 | D52: =SCI!C28 -> 8491899 | E52: =SCI!D28 -> 5624661.3 | F52: =SCI!E28 -> 620870.64 | G52: =SCI!F28 -> 1031881.3 | H52: =SCI!G28 -> 1309180.2 | I52: =SCI!H28 -> 1503232 | J52: =SCI!I28 -> 1982196.9 | ... BZ52: =SCI!BY28 -> 4128601.2
A53: 10.6 | B53: Governance Expenses | C53: =SCI!B25 -> 2080088 | D53: =SCI!C25 -> 2435008 | E53: =SCI!D25 -> 2196237.6 | F53: =SCI!E25 -> 77350.2 | G53: =SCI!F25 -> 442903.98 | H53: =SCI!G25 -> 497268.95 | I53: =SCI!H25 -> 573878.63 | J53: =SCI!I25 -> 724026.09 | ... BZ53: =SCI!BY25 -> 2498185
B54: LLP
B56: Net Surplus | C56: =SCI!B37 -> #REF! | D56: =SCI!C37 -> #REF! | E56: =SCI!D37 -> #REF! | F56: =SCI!E37 -> #REF! | G56: =SCI!F37 -> #REF! | H56: =SCI!G37 -> #REF! | I56: =SCI!H37 -> #REF! | J56: =SCI!I37 -> #REF! | ... L56: =SCI!K37 -> #REF! | N56: =SCI!M37 -> #REF! | O56: =SCI!N37 -> #REF! | P56: =SCI!O37 -> #REF! | Q56: =SCI!P37 -> #REF! | R56: =SCI!Q37 -> 11621260 | S56: =SCI!R37 -> 72272510 | T56: =SCI!S37 -> 15782698 | U56: =SCI!T37 -> 77120604 | ... BZ56: =SCI!BY37 -> 24942394

Sheet form4
D3: RISK CLASSIFICATION OF ASSETS AND PROVISIONING | L3: RISK CLASSIFICATION OF ASSETS AND PROVISIONING
D4: SACCO SOCIETY CS NUMBER | L4: SACCO SOCIETY CS NUMBER
D5: FINANCIAL YEAR | L5: FINANCIAL YEAR
D6: START DATE: | L6: START DATE:
D7: END DATE: | L7: END DATE:
D8: PORTFOLIO AGEING REPORT | L8: PORTFOLIO AGEING REPORT
E9: A | F9: B | G9: C | H9: D | M9: A | N9: B | O9: C | P9: D
C10: NO. | D10: CLASSIFICATION | E10: NO. OF A/Cs | F10: OUTSTANDING LOAN PORTFOLIO(Kshs) | G10: REQUIRED PROVISION | H10: REQUIRED PROVISION AMOUNT(Kshs) | K10: NO. | L10: CLASSIFICATION | M10: NO. OF A/Cs | N10: OUTSTANDING LOAN PORTFOLIO(Kshs) | O10: REQUIRED PROVISION | P10: REQUIRED PROVISION AMOUNT(Kshs)
C11: 1 | D11: Performing | K11: 1 | L11: Performing
C12: 2 | D12: Watch | K12: 2 | L12: Watch
C13: 3 | D13: Substandard | K13: 3 | L13: Substandard
C14: 4 | D14: Doubtful | K14: 4 | L14: Doubtful
C15: 5 | D15: Loss | K15: 5 | L15: Loss
D16: subtotal | L16: subtotal | M16: =SUM(M11:M15) -> 0 | N16: =SUM(N11:N15) -> 0 | P16: =SUM(P11:P15) -> 0
D17: Reschedule/Renegotiated loans | L17: Reschedule/Renegotiated loans
C18: 1 | D18: Performing | K18: 1 | L18: Performing | M18: 0 | N18: 0 | O18: 0.01 | P18: =N18*O18 -> 0
C19: 2 | D19: Watch | K19: 2 | L19: Watch | M19: 0 | N19: 0 | O19: 0.05 | P19: =N19*O19 -> 0
C20: 3 | D20: Substandard | K20: 3 | L20: Substandard | M20: 0 | N20: 0 | O20: 0.25 | P20: =N20*O20 -> 0
C21: 4 | D21: Doubtful | K21: 4 | L21: Doubtful | M21: 0 | N21: 0 | O21: 0.5 | P21: =N21*O21 -> 0
C22: 5 | D22: Loss | K22: 5 | L22: Loss | M22: 0 | N22: 0 | O22: 1 | P22: =N22*O22 -> 0
D23: subtotal | E23: =SUM(E17:E22) -> 0 | F23: =SUM(F17:F22) -> 0 | H23: =SUM(H17:H22) -> 0 | L23: subtotal | M23: =SUM(M17:M22) -> 0 | N23: =SUM(N17:N22) -> 0 | P23: =SUM(P17:P22) -> 0
D24: GRAND TOTAL | E24: =E16+E23 -> 0 | F24: =F16+F23 -> 0 | H24: =H16+H23 -> 0 | L24: GRAND TOTAL | M24: =M16+M23 -> 0 | N24: =N16+N23 -> 0 | P24: =P16+P23 -> 0
F26: =F13+F14+F15 -> 0 | N26: =N13+N14+N15 -> 0
F27: =F26/F24 -> #DIV/0! | N27: =N26/N24 -> #DIV/0!
D30: RISK CLASSIFICATION OF ASSETS AND PROVISIONING
D31: SACCO SOCIETY CS NUMBER
D32: FINANCIAL YEAR
D33: START DATE:
D34: END DATE:
D35: PORTFOLIO AGEING REPORT
E36: A | F36: B | G36: C | H36: D
C37: NO. | D37: CLASSIFICATION | E37: NO. OF A/Cs | F37: OUTSTANDING LOAN PORTFOLIO(Kshs) | G37: REQUIRED PROVISION | H37: REQUIRED PROVISION AMOUNT(Kshs)
C38: 1 | D38: Performing
C39: 2 | D39: Watch
C40: 3 | D40: Substandard
C41: 4 | D41: Doubtful
C42: 5 | D42: Loss
D43: subtotal
D44: Reschedule/Renegotiated loans
C45: 1 | D45: Performing | H45: =F45*G45 -> 0
C46: 2 | D46: Watch | H46: =F46*G46 -> 0
C47: 3 | D47: Substandard | H47: =F47*G47 -> 0
C48: 4 | D48: Doubtful | H48: =F48*G48 -> 0
C49: 5 | D49: Loss | H49: =F49*G49 -> 0
D50: subtotal | E50: =SUM(E44:E49) -> 0 | F50: =SUM(F44:F49) -> 0 | H50: =SUM(H44:H49) -> 0
D51: GRAND TOTAL | E51: =E43+E50 -> 0 | F51: =F43+F50 -> 0 | H51: =H43+H50 -> 0
F53: =F40+F41+F42 -> 0
F54: =F53/F51 -> #DIV/0!
D56: RISK CLASSIFICATION OF ASSETS AND PROVISIONING
D57: SACCO SOCIETY CS NUMBER
D58: FINANCIAL YEAR
D59: START DATE:
D60: END DATE:
D61: PORTFOLIO AGEING REPORT
E62: A | F62: B | G62: C | H62: D
C63: NO. | D63: CLASSIFICATION | E63: NO. OF A/Cs | F63: OUTSTANDING LOAN PORTFOLIO(Kshs) | G63: REQUIRED PROVISION | H63: REQUIRED PROVISION AMOUNT(Kshs)
C64: 1 | D64: Performing
C65: 2 | D65: Watch
C66: 3 | D66: Substandard
C67: 4 | D67: Doubtful
C68: 5 | D68: Loss
D69: subtotal | E69: =SUM(E64:E68) -> 0 | F69: =SUM(F64:F68) -> 0 | H69: =SUM(H64:H68) -> 0
D70: Reschedule/Renegotiated loans
C71: 1 | D71: Performing | E71: 0 | F71: 0 | G71: 0.01 | H71: =F71*G71 -> 0
C72: 2 | D72: Watch | E72: 0 | F72: 0 | G72: 0.05 | H72: =F72*G72 -> 0
C73: 3 | D73: Substandard | E73: 0 | F73: 0 | G73: 0.25 | H73: =F73*G73 -> 0
C74: 4 | D74: Doubtful | E74: 0 | F74: 0 | G74: 0.5 | H74: =F74*G74 -> 0
C75: 5 | D75: Loss | E75: 0 | F75: 0 | G75: 1 | H75: =F75*G75 -> 0
D76: subtotal | E76: =SUM(E70:E75) -> 0 | F76: =SUM(F70:F75) -> 0 | H76: =SUM(H70:H75) -> 0
D77: GRAND TOTAL | E77: =E69+E76 -> 0 | F77: =F69+F76 -> 0 | H77: =H69+H76 -> 0
F79: =F66+F67+F68 -> 0
F80: =F79/F77 -> #DIV/0!

Sheet SFP
A1: FORTITUDE SACCO SOCIETY LTD
A2: STATEMENT OF FINANCIAL POSITION
B3: AUDITED 2013 | C3: AUDITED 2014 | D3: AUDITED 2015 | E3: AUDITED 2016 | F3: AUDITED 2017 | G3: 43101 | H3: 43132 | I3: 43160 | J3: 43191 | K3: 43221 | L3: 43252 | M3: 43282 | N3: 43313 | O3: 43344 | P3: 43374 | Q3: 43405 | R3: 43435 | S3: AUDITED 2018 | T3: 43466 | U3: 43497 | V3: 43525 | W3: 43556 | X3: 43586 | Y3: 43617 | Z3: 43647 | AA3: 43678 | AB3: 43709 | AC3: 43739 | AD3: 43770 | AE3: 43800 | AF3: AUDITED 2019 | AG3: 43831 | AH3: 43862 | AI3: 43891 | AJ3: 43922 | AK3: 43952 | AL3: 43983 | AM3: 44013 | AN3: 44044 | AO3: 44075 | AP3: 44105 | AQ3: 44136 | AR3: 44166 | AS3: AUDITED 2020 | AT3: 44197 | AU3: 44228 | AV3: 44256 | AW3: 44287 | AX3: 44317 | AY3: 44348 | AZ3: 44378 | BA3: 44409 | BB3: 44440 | BC3: 44470 | BD3: 44501 | BE3: 44531 | BF3: AUDITED 2021 | BG3: 44562 | BH3: 44593 | BI3: 44621 | BJ3: 44652 | BK3: 44682 | BL3: 44713 | BM3: 44743 | BN3: 44774 | BO3: 44805 | BP3: 44835 | BQ3: 44866 | BR3: 44917 | BS3: Audited-22 | BT3: 44949 | BU3: 44980 | BV3: 45008 | BW3: 45039 | BX3: 45069 | BY3: 45100
A4: Cash & Cash Equivalent | B4: =B5+B6 -> 21760113 | C4: =C5+C6 -> 47930722 | D4: =D5+D6 -> 64879933 | E4: =E5+E6 -> 49119809 | F4: =F5+F6 -> 36488011 | G4: =G5+G6 -> 13047835 | H4: =H5+H6 -> 20380805 | I4: =I5+I6 -> 8632294.1 | ... P4: =P5+P6 -> 43882692 | Q4: =SUM(Q5:Q6) -> 37787619 | R4: =SUM(R5:R6) -> 94364971 | S4: =SUM(S5:S6) -> 86995878 | T4: =SUM(T5:T6) -> 99084094 | U4: =SUM(U5:U6) -> 1.0640245e+08 | V4: =SUM(V5:V6) -> 93263619 | W4: =SUM(W5:W6) -> 81785848 | X4: =SUM(X5:X6) -> 86648914 | ... BY4: =SUM(BY5:BY6) -> 29854522
A5: Cash in hand | B5: 4700000 | C5: 9548142 | D5: 21529033 | E5: 18326302 | F5: 10536954 | G5: 5443531.2 | H5: 10243264 | I5: 5380898.2 | J5: 7735578.5 | K5: 3414885.1 | L5: 5283673.2 | M5: 1999801.9 | N5: 5302812.2 | O5: 11671610 | P5: =4956510+6676387+49537+155 -> 11682589 | Q5: 5304855 | R5: 30705059 | S5: =155+6246243+12553336+4089377+22910 -> 22912021 | T5: 19548426 | U5: 18588929 | V5: 21938312 | W5: 37729503 | X5: 16226050 | Y5: 19818525 | Z5: 13617749 | AA5: 10592778 | AB5: 12350395 | AC5: 16065190 | AD5: 20547387 | AE5: 25430872 | AF5: =7577693+12262452+1535855+48420 -> 21424420 | AG5: 16848329 | AH5: 19850137 | AI5: 24482628 | AJ5: 14583674 | AK5: 19964488 | AL5: 24858543 | AN5: 19682334 | AO5: 27366218 | AP5: 20525200 | AQ5: 20170008 | AR5: 18190237 | AS5: =6055186+7459090+2313734+4493292+6781 -> 20328083 | AT5: 4402731 | AU5: 2424897 | AV5: 2149728 | AW5: 5682106 | AX5: 2316367 | AY5: 4543413 | AZ5: 4660351 | BA5: 5463819 | BB5: 7194414 | BC5: 2043626 | BD5: 7119059 | BE5: 3588193 | BF5: =1501750+2086443 -> 3588193 | BG5: 6054054 | BH5: 2049770 | BI5: 5446693 | BJ5: 5662481 | BK5: 4665434 | BL5: 3195833 | BM5: 5839316 | BN5: 6815965 | BO5: 5338497 | BP5: 3489977 | BQ5: 4250792 | BR5: 5949565 | BS5: =2421995+2233570 -> 4655565 | BT5: 4542013 | BU5: 2758720.1 | BV5: 3343324 | BW5: 2035248 | BX5: 4853225 | BY5: 6882419
A6: Cash at bank | B6: 17060113 | C6: 38382580 | D6: 43350900 | E6: 30793507 | F6: 25951057 | G6: 7604303.3 | H6: 10137541 | I6: 3251395.9 | J6: 13335852 | K6: 8594151.9 | L6: 22232716 | M6: 18397183 | N6: 8355827.2 | O6: 22311987 | P6: =43882692-P5 -> 32200103 | Q6: =32868552-385788 -> 32482764 | R6: 63659912 | S6: =201864+7774336+1619957+375948+54111752 -> 64083857 | T6: 79535668 | U6: 87813525 | V6: 71325306 | W6: 44056345 | X6: 70422864 | Y6: 61840714 | Z6: 54116124 | AA6: 51832940 | AB6: 64442441 | AC6: 77392232 | AD6: 62795804 | AE6: 73006055 | AF6: =212159+16504024+2207009+4294346 -> 23217538 | AG6: 1.0319051e+08 | AH6: 83435426 | AI6: 76130379 | AJ6: 70377582 | AK6: 71870696 | AL6: 86904747 | AN6: 60581856 | AO6: 63290296 | AP6: 66437207 | AQ6: 81612918 | AR6: 97069875 | AS6: =67591097+10085479-1837323-2000+16867340+2313799+212159 -> 95230551 | AT6: 15329751 | AU6: 20099310 | AV6: 21905168 | AW6: 22469365 | AX6: 26130334 | AY6: 26698579 | AZ6: 24172089 | BA6: 27927378 | BB6: 27066466 | BC6: 34468983 | BD6: 29395920 | BE6: 38794721 | BF6: =(63992+327904+27405554+611769+6905673+222706+115607+2100200+1276197)-(234880) -> 38794722 | BG6: 29521771 | BH6: 35778851 | BI6: 28163427 | BJ6: 18407789 | BK6: 16370210 | BL6: 30451014 | BM6: 16415411 | BN6: 8578687.6 | BO6: 10141746 | BP6: 12097474 | BQ6: 9281246.7 | BR6: 6196930.8 | BS6: =12146496-BS5 -> 7490931 | BT6: 8115763.4 | BU6: 10088188 | BV6: 5010056 | BW6: 16976298 | BX6: 13322409 | BY6: 22972103
A7: Prepayments & Sundry Receivables | B7: 49712658 | C7: 33063169 | D7: 32855562 | E7: 50145037 | F7: =29017881.23+7068977.16 -> 36086858 | G7: =39837604.33+7374347.2 -> 47211952 | H7: =38845278.42+6836145.22 -> 45681424 | I7: 44529378 | J7: 35326082 | K7: 43535763 | L7: 29263185 | M7: 31180350 | N7: =31623101.02+5802429.83 -> 37425531 | O7: 26272047 | P7: 29745552 | Q7: 42884406 | R7: 15079165 | S7: 24490991 | T7: 15586568 | U7: 26437764 | V7: 14662750 | W7: 14443239 | X7: 32825524 | Y7: 20255285 | Z7: 18976940 | AA7: 17071907 | AB7: 18291800 | AC7: 16484604 | AD7: 17031508 | AE7: 17827202 | AF7: =150002+17547126+8016663+771428+1222030+20250-957821-2825817-3063619 -> 20880242 | AG7: 16110478 | AH7: 23776422 | AI7: 15300054 | AJ7: 16823842 | AK7: 34594922 | AL7: 17686032 | AN7: 15346788 | AO7: 15274923 | AP7: 13582640 | AQ7: 13386180 | AR7: 13471826 | AS7: 13471826 | AT7: 6251833.1 | AU7: 6012433.1 | AV7: 5906243.3 | AW7: 3662354.5 | AX7: 5960105.3 | AY7: 5719987 | AZ7: 5929386.8 | BA7: 6164882 | BB7: 6272594 | BC7: 6770651.8 | BD7: 6189103.1 | BE7: 140814.35 | BF7: =144814+82957+64000 -> 291771 | BG7: 6718548.7 | BH7: 6733923.5 | BI7: 6095607.7 | BJ7: 6367522.5 | BK7: 6875675.8 | BL7: 343055.45 | BM7: 7560060.1 | BN7: 7632451.2 | BO7: 7616791.8 | BP7: 9209629.5 | BQ7: 11346107 | BR7: 11883844 | BS7: =11119402+70000+25000+764442 -> 11978844 | BT7: 8726217.6 | BU7: 8894993.1 | BV7: 10187426 | BW7: 2435977.6 | BX7: 9289627.2 | BY7: 8642332.2
A8: Financial Investments | B8: =SUM(B9:B13) -> 17863697 | C8: =SUM(C9:C13) -> 44310422 | D8: =SUM(D9:D13) -> 44310422 | E8: =SUM(E9:E13) -> 39760613 | F8: =SUM(F9:F13) -> 39760613 | G8: =SUM(G9:G13) -> 39760613 | H8: =SUM(H9:H13) -> 39760613 | I8: =SUM(I9:I13) -> 39760613 | ... BY8: =SUM(BY9:BY13) -> 9973054.5
A9: Government Securities - Treasury Bills/bonds, | E9: 0 | F9: 0 | AT9: 0 | AU9: 0 | AV9: 0 | AW9: 0 | AX9: 0 | AY9: 0 | AZ9: 0 | BA9: 0 | BB9: 0 | BC9: 0 | BD9: 0 | BE9: 0 | BG9: 0 | BH9: 0 | BI9: 0 | BJ9: 0 | BK9: 0 | BL9: 0 | BM9: 0 | BN9: 0 | BO9: 0 | BP9: 0 | BQ9: 0 | BR9: 0 | BT9: 0 | BU9: 0 | BV9: 0 | BW9: 0 | BX9: 0 | BY9: 0
A10: Other Securities - Commercial papers/Bonds | E10: 0 | F10: 0 | AT10: 0 | AU10: 0 | AV10: 0 | AW10: 0 | AX10: 0 | AY10: 0 | AZ10: 0 | BA10: 0 | BB10: 0 | BC10: 0 | BD10: 0 | BE10: 0 | BG10: 0 | BH10: 0 | BI10: 0 | BJ10: 0 | BK10: 0 | BL10: 0 | BM10: 0 | BN10: 0 | BO10: 0 | BP10: 0 | BQ10: 0 | BR10: 0 | BT10: 0 | BU10: 0 | BV10: 0 | BW10: 0 | BX10: 0 | BY10: 0
A11: Balances in NACCOS (E.g Jungu Kuu, ESS, Savings,Money Market,Coop FD, CFP) | B11: 13595861 | C11: 4549809 | D11: 4549809 | E11: 0 | F11: 0 | G11: 0 | H11: 0 | L11: 0 | M11: 0 | O11: 0 | Q11: 31181179 | R11: 0 | V11: 0 | AA11: 0 | AB11: 0 | AC11: 0 | AD11: 0 | AE11: 0 | AF11: =34795812+9287051+10000000 -> 54082863 | AT11: 0 | AU11: 0 | AV11: 0 | AW11: 0 | AX11: 0 | AY11: 0 | AZ11: 0 | BA11: 0 | BB11: 0 | BC11: 0 | BD11: 0 | BE11: 0 | BG11: 0 | BH11: 0 | BI11: 0 | BJ11: 0 | BK11: 0 | BL11: 0 | BM11: 0 | BN11: 0 | BO11: 0 | BP11: 0 | BQ11: 0 | BR11: 0 | BT11: 0 | BU11: 0 | BV11: 0 | BW11: 0 | BX11: 0 | BY11: 0
A12: Equity Investments in NACCOs(Shares in- CIC, KUSCCO, COOP BANK,CAK, KERUSSU) | AF12: =303024+124103+3789408+12021 -> 4228556 | AG12: 4228554.9 | AH12: 4228554.9 | AI12: 4228554.9 | AJ12: 4228554.9 | AK12: 4228554.9 | AL12: 4228554.9 | AN12: 4228554.9 | AO12: 4228554.9 | AP12: 4228554.9 | AQ12: 4228554.9 | AR12: 4228554.9 | AS12: =303024+124103+3789408+12021 -> 4228556 | AT12: 9538489 | AU12: 9538489 | AV12: 9538489 | AW12: 9538489 | AX12: 9538489 | AY12: 9538489 | AZ12: 9688489 | BA12: 9688489 | BB12: 9688489 | BC12: 9688489 | BD12: 9688489 | BE12: 9688489 | BF12: =8399998+1288491 -> 9688489 | BG12: 9688489 | BH12: 9688489 | BI12: 9688489 | BJ12: 9688489 | BK12: 9788489 | BL12: 9788489 | BM12: 14788489 | BN12: 14829001 | BO12: 14865137 | BP12: 14902882 | BQ12: 14939750 | BR12: 9965004.8 | BS12: 9965005 | BT12: 9966329.1 | BU12: 9966329.1 | BV12: 9966329.1 | BW12: 9970254.5 | BX12: 9971666.1 | BY12: 9973054.5
A13: Equity Investments in companies - shares/stocks | B13: 4267836 | C13: 39760613 | D13: 39760613 | E13: 39760613 | F13: 39760613 | G13: 39760613 | H13: 39760613 | I13: 39760613 | J13: 39760613 | K13: 39760613 | L13: 39760613 | M13: 39760613 | N13: 39760613 | O13: 39760613 | P13: 33323406 | R13: 37575024 | S13: 4228555 | T13: 4228554.9 | U13: 4228554.9 | V13: 4228554.9 | W13: 4228554.9 | X13: 4228554.9 | Y13: 4228554.9 | Z13: 4228554.9 | AA13: 4228554.9 | AB13: 4228554.9 | AC13: 4228554.9 | AD13: 4228554.9 | AE13: 4228554.9
A14: Net Loan Portfolio | B14: =B15-B16 -> 312933438 | C14: =C15-C16 -> 291789680 | D14: =D15-D16 -> 2.9963107e+08 | E14: =E15-E16 -> 3.0964314e+08 | F14: =F15-F16 -> 3.1063977e+08 | G14: =G15-G16 -> 3.151361e+08 | H14: =H15-H16 -> 3.0925151e+08 | I14: =I15-I16 -> 3.0848889e+08 | ... BY14: =BY15-BY16 -> 2.7562348e+08
A15: Gross Loan Portfolio | B15: 320539200 | C15: 301762103 | D15: 3.0960349e+08 | E15: 3.1961557e+08 | F15: 3.2061219e+08 | G15: 3.2510852e+08 | H15: 3.1922393e+08 | I15: 3.1846131e+08 | J15: 3.1627714e+08 | K15: 3.175893e+08 | L15: 3.2594521e+08 | M15: 3.2890168e+08 | N15: 3.33994e+08 | O15: 3.2697845e+08 | P15: =319184009+P16 -> 326978451 | Q15: =326978451+395812430-352922205 -> 369868676 | R15: 478115491 | S15: 478678153 | T15: 4.8413271e+08 | U15: 4.899003e+08 | V15: 4.8760561e+08 | W15: 4.9160208e+08 | X15: 4.9348786e+08 | Y15: 4.9769982e+08 | Z15: 5.4472223e+08 | AA15: 5.499787e+08 | AB15: 5.4739833e+08 | AC15: 5.3818871e+08 | AD15: 5.5187395e+08 | AE15: 5.4606127e+08 | AF15: =467465209+804430482-725748527 -> 546147164 | AG15: 5.5322578e+08 | AH15: 5.477904e+08 | AI15: 5.6784889e+08 | AJ15: 5.7170393e+08 | AK15: 5.5996229e+08 | AL15: 5.6313826e+08 | AN15: 6.0764737e+08 | AO15: 6.0631906e+08 | AP15: 6.1780644e+08 | AQ15: 6.1336698e+08 | AR15: 6.1387337e+08 | AS15: =528337864+783185386-697649877 -> 613873373 | AT15: 1.6716519e+08 | AU15: 1.6650923e+08 | AV15: 1.6621553e+08 | AW15: 1.6787064e+08 | AX15: 1.6692673e+08 | AY15: 1.6877539e+08 | AZ15: 1.7677842e+08 | BA15: 1.776228e+08 | BB15: 1.7987232e+08 | BC15: 1.808871e+08 | BD15: 1.8177738e+08 | BE15: 1.82097e+08 | BF15: =179994187 -> 179994187 | BG15: 1.8487576e+08 | BH15: 1.8441308e+08 | BI15: 1.9478276e+08 | BJ15: 1.9711919e+08 | BK15: 202237618 | BL15: 2.1040646e+08 | BM15: 2.1711623e+08 | BN15: 2.3148359e+08 | BO15: 2.3570741e+08 | BP15: 2.4266684e+08 | BQ15: 2.5026749e+08 | BR15: 2.6912382e+08 | BS15: 263713416 | BT15: 2.8981861e+08 | BU15: 2.9042099e+08 | BV15: 2.9154064e+08 | BW15: 2.9108817e+08 | BX15: 2.8442431e+08 | BY15: 2.8892332e+08
A16: Allowance for Loan Loss | B16: 7605762 | C16: 9972423 | D16: 9972423.1 | E16: 9972423.1 | F16: 9972423.1 | G16: 9972423.1 | H16: 9972423.1 | I16: 9972423.1 | J16: 9972423.1 | K16: 9972423.1 | L16: 9972423.1 | M16: 9972423.1 | N16: 9972423.1 | O16: 9972423.1 | P16: 7794442 | Q16: 10214244 | R16: 11212944 | S16: 11212944 | T16: 11212944 | U16: 11212944 | V16: 11817894 | W16: 12019544 | X16: 12221194 | Y16: 12422844 | Z16: 12624495 | AA16: 12826145 | AB16: 18281219 | AC16: 18482869 | AD16: 18684519 | AE16: 16851478 | AF16: 16851478 | AG16: 17053128 | AH16: 17436783 | AI16: 17759770 | AJ16: 18082757 | AK16: 18405743 | AL16: 18728730 | AN16: 19638814 | AO16: 24623781 | AP16: 23826506 | AQ16: 24968461 | AR16: 24262748 | AS16: 24262748 | AT16: 2102814 | AU16: 3395395.1 | AV16: 2852903.6 | AW16: 4247544.4 | AX16: 3143771 | AY16: 4451197.7 | AZ16: 4275794.9 | BA16: 4817163.8 | BB16: 4865468.4 | BC16: 5253614.1 | BD16: 5305712 | BE16: 6240049.6 | BF16: 6585364 | BG16: 6401128.4 | BH16: 6394196.2 | BI16: 6463925.3 | BJ16: 6678691.2 | BK16: 8186123.5 | BL16: 7874217.8 | BM16: 8643626.5 | BN16: 9319329.4 | BO16: 9594787.3 | BP16: 11263793 | BQ16: 11552860 | BR16: 8674925.8 | BS16: 8674926 | BT16: 14573012 | BU16: 14675486 | BV16: 14276003 | BW16: 13017938 | BX16: 11267918 | BY16: 13299846
A17: Accounts Receivables | B17: =SUM(B18:B20) -> 0 | C17: =SUM(C18:C20) -> 1082502 | D17: =SUM(D18:D20) -> 1923129 | E17: =SUM(E18:E20) -> 1923129 | F17: =SUM(F18:F20) -> 1923129 | G17: =SUM(G18:G20) -> 2166858.8 | H17: =SUM(H18:H20) -> 2166908.4 | I17: =SUM(I18:I20) -> 2410630.3 | ... BY17: =SUM(BY18:BY20) -> 0
A18: Tax Recoverable | C18: 1082502 | D18: 1923129 | E18: 1923129 | F18: 1923129 | G18: 2166858.8 | H18: 2166908.4 | I18: 2410630.3 | J18: 2410733.8 | K18: 2410733.8 | L18: 2658210.1 | M18: 2658210.1 | N18: 2658210.1 | O18: 2901940 | P18: 673721 | R18: 3489191.1 | T18: 3489191.1 | U18: 3489191.1 | V18: 3489191.1 | W18: 2809133.1 | X18: 5288521.1 | Y18: 6135682.1 | Z18: 2384117.4 | AA18: 2384117.4 | AB18: 3231278.4 | AC18: 3231278.4 | AD18: 3231278.4 | AE18: 4078439.4 | AF18: 788143 | AG18: 4078439.4 | AH18: 1271513.4 | AI18: 1271513.4 | AJ18: 1914767.4 | AK18: 1914767.4 | AL18: 2558021.4 | AN18: 2558021.4 | AO18: 3201275.4 | AP18: 3201275.4 | AQ18: 3201275.4 | AR18: 3844529.4 | AT18: 0 | AU18: 0 | AV18: 0 | AW18: 0 | AX18: 0 | AY18: 0 | AZ18: 0 | BA18: 0 | BB18: 0 | BC18: 0 | BD18: 0 | BE18: 0 | BT18: 0 | BU18: 0 | BV18: 0 | BW18: 0 | BX18: 0 | BY18: 0
A19: Deferred Tax Assets | E19: 0 | U19: 0 | AB19: 0 | AE19: 0 | AF19: 0 | AG19: 0 | AH19: 0 | AI19: 0 | AJ19: 0 | AK19: 0 | AL19: 0 | AM19: 0 | AN19: 0 | AO19: 0 | AP19: 0 | AQ19: 0 | AR19: 0 | AS19: 0 | AT19: 0 | AU19: 0 | AV19: 0 | AW19: 0 | AX19: 0 | AY19: 0 | AZ19: 0 | BA19: 0 | BB19: 0 | BC19: 0 | BD19: 0 | BE19: 0 | BT19: 0 | BU19: 0 | BV19: 0 | BW19: 0 | BX19: 0 | BY19: 0
A20: Retirement Benefit Assets | E20: 0 | U20: 0 | AE20: 0 | AF20: 0 | AG20: 0 | AH20: 0 | AI20: 0 | AJ20: 0 | AK20: 0 | AL20: 0 | AM20: 0 | AN20: 0 | AO20: 0 | AP20: 0 | AQ20: 0 | AR20: 0 | AS20: 0 | AT20: 0 | AU20: 0 | AV20: 0 | AW20: 0 | AX20: 0 | AY20: 0 | AZ20: 0 | BA20: 0 | BB20: 0 | BC20: 0 | BD20: 0 | BE20: 0 | BT20: 0 | BU20: 0 | BV20: 0 | BW20: 0 | BX20: 0 | BY20: 0
A21: Property & Equipment & Other assets | B21: =SUM(B22:B26) -> 7304256 | C21: =SUM(C22:C26) -> 6162725 | D21: =SUM(D22:D26) -> 19918781 | E21: =SUM(E22:E26) -> 5779199.7 | F21: =SUM(F22:F26) -> 11935237 | G21: =SUM(G22:G26) -> 5795379.7 | H21: =SUM(H22:H26) -> 5623172.2 | I21: =SUM(I22:I26) -> 5450995.1 | ... BY21: =SUM(BY22:BY26) -> 19902138
A22: Investment Properties | F22: 5967618.3 | W22: 0 | Y22: 0 | Z22: 0 | AG22: 0 | AH22: 0 | AI22: 0 | AJ22: 0 | AK22: 0 | AL22: 0 | AN22: 0 | AO22: 0 | AP22: 0 | AQ22: 0 | AR22: 0 | AT22: 0 | AU22: 0 | AV22: 0 | AW22: 0 | AX22: 0 | AY22: 0 | AZ22: 0 | BA22: 0 | BB22: 0 | BC22: 0 | BD22: 0 | BE22: 0 | BG22: 0 | BH22: 0 | BI22: 0 | BJ22: 0 | BK22: 0 | BL22: 0 | BM22: 0 | BN22: 0 | BO22: 0 | BP22: 0 | BQ22: 0 | BR22: 0 | BT22: 0 | BU22: 0 | BV22: 0 | BW22: 0 | BX22: 0 | BY22: 0
A23: Property & Equipment | B23: 7304256 | C23: 6162725 | D23: 5970995 | E23: 5779199.6 | F23: 5967618.3 | G23: 5795379.7 | H23: 5623172.2 | I23: 5450995 | J23: 5292853.2 | K23: 5140742.3 | L23: 4988659.2 | M23: 4836603 | N23: 4707848 | O23: 4591226.6 | P23: 4412031 | Q23: 4263907 | R23: 7005758.4 | S23: 3048281 | T23: 7005758.3 | U23: 7005758.4 | V23: 6855145.9 | W23: 6223465.2 | X23: 6843368.6 | Y23: 6621497.3 | Z23: 6393407.9 | AA23: 6200784.2 | AB23: 5982262.2 | AC23: 5764844.8 | AD23: 5548403.3 | AE23: 5325780.8 | AF23: 2426053 | AG23: 5309307.4 | AH23: 5454316.2 | AI23: 5337809.3 | AJ23: 5438298.1 | AK23: 5745545.3 | AL23: 6083773.5 | AN23: 5831573 | AO23: 5703357.5 | AP23: 5597291.9 | AQ23: 5867012.4 | AR23: 5726554 | AS23: 3186216 | AT23: 20168526 | AU23: 20101878 | AV23: 20625198 | AW23: 20701978 | AX23: 20625583 | AY23: 20559911 | AZ23: 20478357 | BA23: 20401900 | BB23: 20325444 | BC23: 20248987 | BD23: 20172530 | BE23: 20096073 | BF23: 20096073 | BG23: 20036235 | BH23: 20074313 | BI23: 20013433 | BJ23: 19952553 | BK23: 19983573 | BL23: 19921683 | BM23: 19937426 | BN23: 19873183 | BO23: 19808941 | BP23: 19744698 | BQ23: 19680456 | BR23: 19752713 | BS23: 19752713 | BT23: 19699566 | BU23: 19646419 | BV23: 19593272 | BW23: 19540125 | BX23: 19516978 | BY23: 19463831
A24: Prepaid Lease rentals | E24: 0 | U24: 0 | AE24: 0 | AF24: 0 | AG24: 0 | AH24: 0 | AI24: 0 | AJ24: 0 | AK24: 0 | AL24: 0 | AM24: 0 | AN24: 0 | AO24: 0 | AP24: 0 | AQ24: 0 | AR24: 0 | AS24: 0 | AT24: 0 | AU24: 0 | AV24: 0 | AW24: 0 | AX24: 0 | AY24: 0 | AZ24: 0 | BA24: 0 | BB24: 0 | BC24: 0 | BD24: 0 | BE24: 0 | BG24: 0 | BH24: 0 | BI24: 0 | BJ24: 0 | BK24: 0 | BL24: 0 | BM24: 0 | BN24: 0 | BO24: 0 | BP24: 0 | BQ24: 0 | BR24: 0 | BT24: 0 | BU24: 0 | BV24: 0 | BW24: 0 | BX24: 0 | BY24: 0
A25: Intangible Assets | E25: 0 | P25: 103943 | S25: 3957478 | U25: 0 | AE25: 0 | AF25: 3252874 | AG25: 0 | AH25: 0 | AI25: 0 | AJ25: 0 | AK25: 0 | AL25: 0 | AN25: 0 | AO25: 0 | AP25: 0 | AQ25: 0 | AR25: 0 | AS25: 2540337 | AT25: 2093873.4 | AU25: 2034054.6 | AV25: 1975153.4 | AW25: 1916252.2 | AX25: 1857351 | AY25: 1802376.6 | AZ25: 1739548.6 | BA25: 1680647.4 | BB25: 1621746.2 | BC25: 1562845 | BD25: 1503943.8 | BE25: 1445042.6 | BF25: =1445042 -> 1445042 | BG25: 1386141.4 | BH25: 1327240.2 | BI25: 1268339 | BJ25: 1209437.8 | BK25: 1150536.6 | BL25: 1091635.4 | BM25: 1032734.2 | BN25: 973833.03 | BO25: 914931.83 | BP25: 856030.63 | BQ25: 797129.43 | BR25: 738228.23 | BS25: 738228 | BT25: 679327.03 | BU25: 620425.83 | BV25: 561524.63 | BW25: 502623.43 | BX25: 443722.23 | BY25: 384821.03
A26: Other Assets | D26: 13947786 | E26: 0.06 | F26: 0.06 | G26: 0.06 | H26: 0.06 | I26: 0.06 | L26: 0.06 | M26: 0.06 | N26: 0.06 | O26: 0.06 | T26: 0.06 | U26: 0.06 | V26: 0.06 | W26: 0 | Y26: 0.06 | AA26: 0.06 | AB26: 0.06 | AC26: 0.06 | AE26: 0 | AF26: 0 | AG26: 0 | AH26: 0 | AI26: 0 | AJ26: 0 | AK26: 0 | AL26: 0 | AM26: 0 | AN26: 0 | AO26: 0 | AP26: 0 | AQ26: 0 | AR26: 0 | AS26: 0 | AT26: 123807.61 | AU26: 124700 | AV26: 112959.97 | AW26: 94169.83 | AX26: 206220.55 | AY26: 65958.36 | AZ26: 0 | BA26: 1227358.3 | BB26: 797787.87 | BC26: 581010.23 | BD26: 210116.23 | BE26: 470107.17 | BF26: =323150 -> 323150 | BG26: 252423.22 | BH26: 213264.71 | BI26: 154417.37 | BJ26: 12209.47 | BK26: 16477.75 | BL26: 25806.95 | BM26: 25506.63 | BN26: 38934.63 | BO26: 21862 | BP26: 3000 | BQ26: 73000 | BR26: 96300 | BS26: 1300 | BT26: 580 | BU26: 51808 | BV26: 24010.58 | BW26: 5910 | BX26: 10545.44 | BY26: 53485.18
A27: Total Assets | B27: =B4+B7+B8+B14+B17+B21 -> 409574162 | C27: =C4+C7+C8+C14+C17+C21 -> 424339220 | D27: =D4+D7+D8+D14+D17+D21 -> 4.6351889e+08 | E27: =E4+E7+E8+E14+E17+E21 -> 4.5637093e+08 | F27: =F4+F7+F8+F14+F17+F21 -> 4.3683362e+08 | G27: =G4+G7+G8+G14+G17+G21 -> 4.2311874e+08 | H27: =H4+H7+H8+H14+H17+H21 -> 4.2286443e+08 | I27: =I4+I7+I8+I14+I17+I21 -> 4.092728e+08 | ... BY27: =BY4+BY7+BY8+BY14+BY17+BY21 -> 3.4399552e+08
A28: LIABILITIES
A29: Savings Deposits - Withdrawable deposits - FOSA) | B29: 50442863 | C29: 81985036 | D29: 4074376.9 | E29: 4984401.3 | F29: 5076228.9 | G29: 7141510.8 | H29: 7139384.9 | I29: 8498751.9 | J29: 8563252.2 | K29: 8282780.7 | L29: 8457228.6 | M29: 8336852.1 | N29: 7143096.7 | O29: 7207814.1 | P29: 73876145 | Q29: 71672361 | R29: 13215269 | S29: =63532753+4086192 -> 67618945 | T29: 14363008 | U29: 15611949 | V29: 13612359 | W29: 14419909 | X29: 14679037 | Y29: 13096149 | Z29: 14426180 | AA29: 12510173 | AB29: 11197954 | AC29: 12436036 | AD29: 10911398 | AE29: 13039500 | AF29: =63339626+3748058 -> 67087684 | AG29: 12876481 | AH29: 15546549 | AI29: 15400942 | AJ29: 11309065 | AK29: 11992741 | AL29: 11671577 | AN29: 10238707 | AO29: 11775955 | AP29: 11289463 | AQ29: 10526262 | AR29: 11378553 | AS29: =53045585+3765913 -> 56811498 | AT29: 12023250 | AU29: 12091855 | AV29: 10714575 | AW29: 14132599 | AX29: 13231529 | AY29: 13700784 | AZ29: 15808378 | BA29: 19128000 | BB29: 17936400 | BC29: 17015110 | BD29: 16886416 | BE29: 16286960 | BF29: =16286960 -> 16286960 | BG29: 15255156 | BH29: 15576857 | BI29: 15798800 | BJ29: 18883037 | BK29: 17415071 | BL29: 17333029 | BM29: 19306317 | BN29: 19478401 | BO29: 17776734 | BP29: 20090624 | BQ29: 21861360 | BR29: 24307369 | BS29: 24320707 | BT29: 20123359 | BU29: 19493728 | BV29: 16759664 | BW29: 15974307 | BX29: 22550501 | BY29: 20806653
A30: Short Term Deposits (e.g Fixed deposits, special savings) | C30: 3170827 | D30: 1.1755426e+08 | E30: 1.0318279e+08 | F30: 98509255 | G30: 88557190 | H30: 91504337 | I30: 76760201 | J30: 75977879 | K30: 70651472 | L30: 74935904 | M30: 66071155 | N30: 63485556 | O30: 66668330 | P30: 5943679 | Q30: 5450485 | R30: 50265081 | T30: 50901457 | U30: 58024877 | V30: 67609114 | W30: 54000198 | X30: 74394434 | Y30: 49110765 | Z30: 70378302 | AA30: 57056811 | AB30: 60861314 | AC30: 56850121 | AD30: 52840882 | AE30: 50263285 | AG30: 58177132 | AH30: 84593460 | AI30: 87751657 | AJ30: 62482326 | AK30: 69496910 | AL30: 64081232 | AN30: 53608786 | AO30: 47292863 | AP30: 43653392 | AQ30: 43655896 | AR30: 41667032 | AS30: 0 | AT30: 0 | AU30: 0 | AV30: 0 | AW30: 0 | AX30: 0 | AY30: 0 | AZ30: 0 | BA30: 0 | BB30: 0 | BC30: 0 | BD30: 0 | BE30: 0 | BG30: 0 | BH30: 0 | BI30: 0 | BJ30: 0 | BK30: 0 | BL30: 0 | BM30: 0 | BN30: 0 | BO30: 0 | BP30: 0 | BQ30: 0 | BR30: 0 | BT30: 0 | BU30: 0 | BV30: 0 | BW30: 0 | BX30: 0 | BY30: 0
A31: Non withdrawable deposits (BOSA member deposits) | B31: 245876845 | C31: 240972613 | D31: 2.4228165e+08 | E31: 2.4464437e+08 | F31: 2.4323434e+08 | G31: 2.3803121e+08 | H31: 2.3093434e+08 | I31: 2.2619326e+08 | J31: 2.2403576e+08 | K31: 2.2712554e+08 | L31: 2.2977364e+08 | M31: 2.3239987e+08 | N31: 2.3612108e+08 | O31: 2.3105628e+08 | P31: 225120102 | Q31: 263211841 | R31: 3.6978258e+08 | S31: 365696388 | T31: 3.7313088e+08 | U31: 3.8056337e+08 | V31: 3.899621e+08 | W31: 3.9463998e+08 | X31: 3.9710517e+08 | Y31: 4.0401425e+08 | Z31: 4.0848997e+08 | AA31: 4.1365858e+08 | AB31: 4.1793597e+08 | AC31: 4.1767134e+08 | AD31: 4.198612e+08 | AE31: 4.2368556e+08 | AF31: 419736691 | AG31: 4.273603e+08 | AH31: 4.3742002e+08 | AI31: 4.4224302e+08 | AJ31: 4.5102627e+08 | AK31: 450275511 | AL31: 4.5599404e+08 | AN31: 4.6600575e+08 | AO31: 4.7131127e+08 | AP31: 4.760495e+08 | AQ31: 4.7947272e+08 | AR31: 4.8711755e+08 | AS31: 483159282 | AT31: 1.2306521e+08 | AU31: 1.245189e+08 | AV31: 1.2545563e+08 | AW31: 1.262155e+08 | AX31: 1.2727927e+08 | AY31: 1.2812225e+08 | AZ31: 1.2924908e+08 | BA31: 1.3035652e+08 | BB31: 1.3515057e+08 | BC31: 1.3651715e+08 | BD31: 1.3516666e+08 | BE31: 1.3657143e+08 | BF31: =136571433 -> 136571433 | BG31: 1.361121e+08 | BH31: 1.3747197e+08 | BI31: 1.3402925e+08 | BJ31: 1.3572142e+08 | BK31: 1.3865681e+08 | BL31: 1.4241396e+08 | BM31: 1.4351046e+08 | BN31: 1.4670279e+08 | BO31: 1.4811963e+08 | BP31: 1.5128715e+08 | BQ31: 1.5414907e+08 | BR31: 1.59575e+08 | BS31: 159575005 | BT31: 1.6873705e+08 | BU31: 1.6915542e+08 | BV31: 1.694591e+08 | BW31: 1.7276421e+08 | BX31: 1.7474343e+08 | BY31: 1.779673e+08
A32: Total Deposit liabilities | B32: =SUM(B29:B31) -> 296319708 | C32: =SUM(C29:C31) -> 326128476 | D32: =SUM(D29:D31) -> 3.6391029e+08 | E32: =SUM(E29:E31) -> 3.5281156e+08 | F32: =SUM(F29:F31) -> 3.4681983e+08 | G32: =SUM(G29:G31) -> 3.3372991e+08 | H32: =SUM(H29:H31) -> 3.2957806e+08 | I32: =SUM(I29:I31) -> 3.1145221e+08 | ... BY32: =SUM(BY29:BY31) -> 1.9877396e+08
A33: Accounts Payable & Other Liabilities | B33: =SUM(B34:B39) -> 84794375 | C33: =SUM(C34:C39) -> 27429280 | D33: =SUM(D34:D39) -> 5425296.8 | E33: =SUM(E34:E39) -> 28289386 | F33: =SUM(F34:F39) -> 5695194.1 | G33: =SUM(G34:G39) -> 4127517.7 | H33: =SUM(H34:H39) -> 4695814.4 | I33: =SUM(I34:I39) -> 5497034.6 | ... BY33: =SUM(BY34:BY39) -> 23273893
A34: Tax Payable | B34: 1291123 | D34: -6588.62 | E34: 39791.01 | F34: 120108.06 | G34: 171873.91 | H34: 143208.57 | I34: 230281.64 | J34: -3625.65 | K34: 3486.16 | L34: 47313.25 | M34: -1603.58 | N34: -14975.28 | O34: -4726.98 | Q34: 305759 | R34: -803798.29 | S34: 447171 | T34: -856109.89 | U34: -780762.95 | V34: 1819524.8 | W34: -809289.12 | X34: -808977.3 | Y34: -760902.48 | Z34: -253392.36 | AA34: -244889.96 | AB34: -264112.78 | AC34: -193076.3 | AD34: -199069.84 | AE34: -126781.31 | AG34: -99816.01 | AH34: 3067129.6 | AI34: 253504.87 | AJ34: 151172.45 | AK34: 152875.13 | AL34: 220681 | AN34: 221857.82 | AO34: 71229.77 | AP34: 76026.78 | AQ34: 176558.7 | AR34: 200543.86 | AS34: 584125 | AT34: 0 | AU34: 235626 | AV34: 0 | AW34: 0 | AX34: 0 | AY34: 0 | AZ34: 0 | BA34: 0 | BB34: 0 | BC34: 0 | BD34: 0 | BE34: 260000 | BF34: 478112 | BG34: 260000 | BH34: 478112 | BI34: 478112 | BJ34: 0 | BK34: 0 | BL34: 0 | BM34: 0 | BN34: 0 | BO34: 0 | BP34: 0 | BQ34: 0 | BR34: 0 | BS34: 3451686 | BT34: 4183487 | BU34: 3924108 | BV34: 3664728 | BW34: 685464 | BX34: 0 | BY34: 0
A35: Dividends Payable | C35: 849619 | E35: 22468213 | F35: 162174.45 | G35: 162174.45 | H35: 162174.45 | I35: 162174.45 | J35: 162174.45 | K35: 181264.57 | L35: 181264.57 | M35: 181264.57 | N35: 181264.57 | O35: 181264.57 | P35: 1964383 | R35: 0 | S35: =51769561 -> 51769561 | T35: 361017.2 | U35: 361017.2 | V35: -50208421 | W35: 5056975.3 | X35: 5056975.3 | Y35: 5056975.3 | Z35: 0 | AA35: 0 | AB35: 0 | AC35: 0 | AD35: 0 | AE35: 0 | AF35: 56394279 | AG35: 0 | AH35: -952259.45 | AI35: -952259.45 | AJ35: 0 | AK35: 0 | AL35: 0 | AN35: 0 | AO35: 0 | AP35: 0 | AQ35: 0 | AR35: 0 | AS35: 64690518 | AT35: 10687763 | AU35: 10687763 | AV35: 10687763 | AW35: 0 | AX35: 0 | AY35: 0 | AZ35: 0 | BA35: 0 | BB35: 0 | BC35: 0 | BD35: 0 | BE35: 13111000 | BG35: 13111000 | BH35: 13111000 | BI35: 13111000 | BJ35: 0 | BK35: 0 | BL35: 0 | BM35: 0 | BN35: 0 | BO35: 0 | BP35: 0 | BQ35: 0 | BR35: 0 | BT35: 16705856 | BU35: 16705856 | BV35: 16705856 | BW35: 16705856 | BX35: 0 | BY35: 0
A36: Deferred Tax Liability | E36: 0 | F36: 0 | AG36: 0 | AH36: 0 | AI36: 0 | AJ36: 0 | AK36: 0 | AL36: 0 | AN36: 0 | AO36: 0 | AP36: 0 | AQ36: 0 | AR36: 0 | AS36: 0 | AT36: 0 | AU36: 0 | AV36: 0 | AW36: 0 | AX36: 0 | AY36: 0 | AZ36: 0 | BA36: 0 | BB36: 0 | BC36: 0 | BD36: 0 | BE36: 0 | BG36: 0 | BH36: 0 | BI36: 0 | BJ36: 0 | BK36: 0 | BL36: 0 | BM36: 0 | BN36: 0 | BO36: 0 | BP36: 0 | BQ36: 0 | BR36: 0 | BT36: 0 | BU36: 0 | BV36: 0 | BW36: 0 | BX36: 0 | BY36: 0
A37: Retirement Benefits Liability | E37: 0 | F37: 0 | AG37: 0 | AH37: 0 | AI37: 0 | AJ37: 0 | AK37: 0 | AL37: 0 | AN37: 0 | AO37: 0 | AP37: 0 | AQ37: 0 | AR37: 0 | AS37: 0 | AT37: 0 | AU37: 0 | AV37: 0 | AW37: 0 | AX37: 0 | AY37: 0 | AZ37: 0 | BA37: 0 | BB37: 0 | BC37: 0 | BD37: 0 | BE37: 0 | BG37: 0 | BH37: 0 | BI37: 0 | BJ37: 0 | BK37: 0 | BL37: 0 | BM37: 0 | BN37: 0 | BO37: 0 | BP37: 0 | BQ37: 0 | BR37: 0 | BT37: 0 | BU37: 0 | BV37: 0 | BW37: 0 | BX37: 0 | BY37: 0
A38: Other Liabilities | B38: 25047859 | C38: 25796810 | D38: 4649033.5 | E38: 4998529.8 | F38: 4630059.7 | G38: 3010617.5 | H38: 3607579.5 | I38: 4321726.7 | J38: 3850758.4 | K38: 3803659.7 | L38: 3657365.7 | M38: 4206524.1 | N38: 5370399.2 | O38: 5135560.3 | P38: =32999186+9547496 -> 42546682 | Q38: =32239479+9691631 -> 41931110 | R38: 3834481.5 | S38: =5931075+8722 -> 5939797 | T38: 4397000 | U38: 4835649.1 | V38: 4258215.9 | W38: 6326601.2 | X38: 8628257.2 | Y38: 6321337 | Z38: 4264641.8 | AA38: 3873729.5 | AB38: 4112130.9 | AC38: 4202916.6 | AD38: 4769066.6 | AE38: 4384289.5 | AF38: =8176370 -> 8176370 | AG38: 5247511.4 | AH38: 4938754.8 | AI38: 3400934.3 | AJ38: 3277314.9 | AK38: 4247749.3 | AL38: 4547275.3 | AN38: 4111659.7 | AO38: 4800873.9 | AP38: 3377033.9 | AQ38: 3658646.4 | AR38: 4364535.7 | AS38: =5704302+1952451 -> 7656753 | AT38: 9134338.4 | AU38: 8007536.1 | AV38: 8138365.9 | AW38: 8249791.6 | AX38: 7609877.3 | AY38: 7987275.9 | AZ38: 8675851.6 | BA38: 8807211.2 | BB38: 5146176.4 | BC38: 5069346.9 | BD38: 3515679.8 | BE38: 4402117.6 | BF38: =150000+13988+1582543+101919+13000+22800+39000+60210+600+8744+77137+9519+1725158 -> 3804618 | BG38: 5483026 | BH38: 6223475.7 | BI38: 6267713.3 | BJ38: 6777879.1 | BK38: 6332473.8 | BL38: 6639709.3 | BM38: 7508755.7 | BN38: 8007921.3 | BO38: 8998499.9 | BP38: 8846914.3 | BQ38: 7359667 | BR38: 8884158.5 | BS38: 6566737 | BT38: 7395654.1 | BU38: 7792486.4 | BV38: 6851843.8 | BW38: 7323219.7 | BX38: 8309325.7 | BY38: 7440560
A39: External Borrowings | B39: 58455393 | C39: 782851 | D39: 782851.88 | E39: 782851.88 | F39: 782851.88 | G39: 782851.88 | H39: 782851.88 | I39: 782851.88 | J39: 782851.88 | K39: 0 | M39: 0 | O39: 0 | R39: 0 | W39: 0 | X39: 0 | Y39: 0 | Z39: 0 | AA39: 0 | AC39: 0 | AD39: 0 | AE39: 0 | AF39: 7659 | AG39: 10000000 | AH39: 10000000 | AI39: 10000000 | AJ39: 10000000 | AK39: 9178063 | AL39: 9178063 | AN39: 8354071 | AO39: 8354071 | AP39: 7528019 | AQ39: 7528019 | AR39: 7528019 | AS39: 7528019 | AT39: 0 | AU39: 0 | AV39: 0 | AW39: 0 | AX39: 0 | AY39: 0 | AZ39: 0 | BA39: 0 | BB39: 0 | BC39: 0 | BD39: 0 | BE39: 0 | BG39: 0 | BH39: 0 | BI39: 0 | BJ39: 0 | BK39: 0 | BL39: 0 | BM39: 0 | BN39: 0 | BO39: 0 | BP39: 0 | BQ39: 0 | BR39: 0 | BT39: 20000000 | BU39: 19166667 | BV39: 18333333 | BW39: 17500000 | BX39: 16666667 | BY39: 15833333
A40: Total Liabilities | B40: =B32+B33 -> 381114083 | C40: =C32+C33 -> 353557756 | D40: =D32+D33 -> 3.6933558e+08 | E40: =E32+E33 -> 3.8110095e+08 | F40: =F32+F33 -> 3.5251502e+08 | G40: =G32+G33 -> 3.3785743e+08 | H40: =H32+H33 -> 3.3427387e+08 | I40: =I32+I33 -> 3.1694924e+08 | ... BY40: =BY32+BY33 -> 2.2204785e+08
A41: EQUITY
A42: Share Capital (Members share capital per Bylaws) | B42: 8025378 | C42: 9759035 | D42: 9938535.4 | E42: 9938535.4 | F42: 10646681 | G42: 12939491 | H42: 14487260 | I42: 15514989 | J42: 15584456 | K42: 15844551 | L42: 16022356 | M42: 16132006 | N42: 16243956 | O42: 16369856 | P42: 16369856 | Q42: 18582910 | R42: 23206195 | S42: 23206195 | T42: 23791313 | U42: 23827444 | V42: 24088524 | W42: 24158227 | X42: 24178227 | Y42: 24379769 | Z42: 24483019 | AA42: 24752610 | AB42: 25297166 | AC42: 25582866 | AD42: 25665166 | AE42: 25803603 | AF42: 25804603 | AG42: 25905551 | AH42: 25993219 | AI42: 26241533 | AJ42: 26501567 | AK42: 26609400 | AL42: 26609400 | AN42: 27169339 | AO42: 27316422 | AP42: 27436241 | AQ42: 27556031 | AR42: 27736726 | AS42: 27736726 | AT42: 27730647 | AU42: 27895362 | AV42: 28064101 | AW42: 28180940 | AX42: 28364517 | AY42: 28533551 | AZ42: 28707460 | BA42: 28888050 | BB42: 29065830 | BC42: 29351635 | BD42: 29436391 | BE42: 29600115 | BF42: =(17224694+1687701+10275970+627737)-(129808+85179) -> 29601115 | BG42: 29845050 | BH42: 30058599 | BI42: 35376640 | BJ42: 35699579 | BK42: 35748585 | BL42: 35971347 | BM42: 37295559 | BN42: 37445997 | BO42: 37633653 | BP42: 37840463 | BQ42: 38752686 | BR42: 39481089 | BS42: =(18782587+4974409+10818528+5029744)-(123380+2800) -> 39479088 | BT42: 35071432 | BU42: 35147714 | BV42: 35704988 | BW42: 36089438 | BX42: 36694387 | BY42: 37112253
A43: Capital Grants | E43: 0 | AG43: 0 | AH43: 0 | AI43: 0 | AJ43: 0 | AK43: 0 | AL43: 0 | AN43: 0 | AO43: 0 | AP43: 0 | AQ43: 0 | AR43: 0 | AS43: 0 | AT43: 500000 | AU43: 500000 | AV43: 500000 | AW43: 500000 | AX43: 500000 | AY43: 500000 | AZ43: 500000 | BA43: 500000 | BB43: 500000 | BC43: 500000 | BD43: 500000 | BE43: 500000 | BG43: 500000 | BH43: 500000 | BI43: 500000 | BJ43: 500000 | BK43: 500000 | BL43: 500000 | BM43: 500000 | BN43: 500000 | BO43: 500000 | BP43: 500000 | BQ43: 500000 | BR43: 500000 | BT43: 500000 | BU43: 500000 | BV43: 500000 | BW43: 500000 | BX43: 500000 | BY43: 500000
A45: Retained Earnings | B45: =B46+B47 -> 2911424 | C45: =C46+C47 -> 17652005 | D45: =D46+D47 -> 78460465 | E45: =E46+E47 -> 21809944 | F45: =F46+F47 -> 24152569 | G45: =G46+G47 -> 29428468 | H45: =H46+H47 -> 31931789 | I45: =I46+I47 -> 34574304 | ... P45: =P46+P47 -> 26497005 | Q45: =Q47+Q46 -> 32236241 | R45: =R47+R46 -> 1.1703112e+08 | S45: =S47+S46 -> 51321512 | T45: =T47+T46 -> 1.2146596e+08 | U45: =U47+U46 -> 1.2894913e+08 | V45: =V47+V46 -> 1.3254287e+08 | W45: =W47+W46 -> 74400048 | X45: =X47+X46 -> 76878688 | ... BY45: =BY47+BY46 -> 52261563
A46: Prior Years' Retained Earnings | B46: -78369 | C46: 2911424 | D46: 12896637 | E46: 18532526 | F46: 18532526 | G46: 18532526 | H46: 18532526 | I46: 18532526 | J46: 18532526 | K46: 18532526 | L46: 18532526 | M46: 18532526 | N46: 18532526 | O46: 18532526 | P46: 17652005 | Q46: 26497005 | R46: 44758606 | S46: 44397588 | T46: 44343299 | U46: 44343299 | V46: 44343299 | W46: 52259008 | X46: 52259008 | Y46: 52259008 | Z46: 51150534 | AA46: 49918558 | AB46: 49918558 | AC46: 49918558 | AD46: 49918558 | AE46: 49918558 | AF46: 51321511 | AG46: 49758906 | AH46: 55605600 | AI46: 55605600 | AJ46: 54649705 | AK46: 54649705 | AL46: 54649705 | AN46: 54649705 | AO46: 54649705 | AP46: 54649705 | AQ46: 54649705 | AR46: 54649705 | AS46: 55605601 | AT46: 7838741.7 | AU46: 17723566 | AV46: 17723566 | AW46: 17723566 | AX46: 17723566 | AY46: 17723566 | AZ46: 17723566 | BA46: 17723566 | BB46: 17723566 | BC46: 17779485 | BD46: 17779485 | BE46: 17850603 | BF46: =22965981 -> 22965981 | BG46: 23293179 | BH46: 24629013 | BI46: 24629013 | BJ46: 24090483 | BK46: 24090483 | BL46: 24090483 | BM46: 24090483 | BN46: 24090483 | BO46: 24090483 | BP46: 24090483 | BQ46: 24090483 | BR46: 24090483 | BS46: =33544155 -> 33544155 | BT46: 27319168 | BU46: 27319168 | BV46: 27319168 | BW46: 27319168 | BX46: 27319168 | BY46: 27319168
A47: Current Year's Surplus | B47: 2989793 | C47: 14740581 | D47: 65563828 | E47: 3277418.2 | F47: 5620043.2 | G47: 10895942 | H47: 13399263 | I47: 16041778 | J47: 20383195 | K47: 22904629 | L47: 25343645 | M47: 28624625 | N47: 31822520 | O47: 35952944 | P47: =26497005-P46 -> 8845000 | Q47: =11621261+3834-2324252-360000-600000-2601607 -> 5739236 | R47: 72272510 | S47: =51321512-44397588 -> 6923924 | T47: 77122664 | U47: 84605828 | V47: 88199569 | W47: 22141041 | X47: 24619681 | Y47: 33605942 | Z47: 42034353 | AA47: 49765271 | AB47: 50312065 | AC47: 58030459 | AD47: 64332637 | AE47: 73166962 | AF47: =13984732-1562605-2796946-707219-1008698-3625174 -> 4284090 | AG47: 78577117 | AH47: 11128672 | AI47: 15764299 | AJ47: 26360844 | AK47: 32722049 | AL47: 39127312 | AN47: 51418155 | AO47: 54624460 | AP47: 63215724 | AQ47: 69270034 | AR47: 76272050 | AS47: =7939034-1587807-955895-1000000-1363760-5360405 -> -2328833 | AT47: 16036332 | AU47: -240990.6 | AV47: 2261584.8 | AW47: 10655441 | AX47: 13678670 | AY47: 14655498 | AZ47: 16476534 | BA47: 17926788 | BB47: 20421271 | BC47: 22735379 | BD47: 25436227 | BE47: 9503152.2 | BF47: =13501878-(284144+2700376+3551000+300000+300000+34970) -> 6331388 | BG47: 2216663.2 | BH47: 3243138.5 | BI47: 4275163 | BJ47: 7441043.8 | BK47: 7530931.1 | BL47: 17778742 | BM47: 19237483 | BN47: 22058238 | BO47: 25079034 | BP47: 26428609 | BQ47: 29747361 | BR47: 34577965 | BS47: =(21460930+986972)-(4292186+4737731+400000+400000+3000000) -> 9617985 | BT47: -3967314.3 | BU47: -2339463.1 | BV47: -254798.12 | BW47: 3768297 | BX47: 11701804 | BY47: 24942394
A49: Other Equity Accounts | B49: =SUM(B50:B54) -> 17523276 | C49: =SUM(C50:C54) -> 43370424 | D49: =SUM(D50:D54) -> 6545698.7 | E49: =SUM(E50:E54) -> 43521404 | F49: =SUM(F50:F54) -> 43551630 | G49: =SUM(G50:G54) -> 42893251 | H49: =SUM(H50:H54) -> 42954201 | I49: =SUM(I50:I54) -> 43016951 | ... BY49: =SUM(BY50:BY54) -> 32073858
A50: Statutory Reserve | B50: 6343633 | C50: 7743437 | D50: 6343633 | E50: 7743437 | F50: 7743437 | G50: 7743437 | H50: 7743437 | I50: 7743437 | J50: 7743437 | K50: 7743437 | L50: 7743437 | M50: 7743437 | N50: 7743437 | O50: 7743437 | P50: 10254671 | Q50: 12578932 | R50: 16119086 | S50: 18296335 | T50: 16119086 | U50: 16119086 | V50: 16119086 | W50: 18296335 | X50: 18296335 | Y50: 18296335 | Z50: 18296335 | AA50: 18296335 | AB50: 18296335 | AC50: 18296335 | AD50: 18296335 | AE50: 18296335 | AF50: 21093281 | AG50: 18296335 | AH50: 21093281 | AI50: 21093281 | AJ50: 21093281 | AK50: 21093281 | AL50: 21093281 | AN50: 21093281 | AO50: 21093281 | AP50: 21093281 | AQ50: 21093281 | AR50: 21093281 | AS50: 22681088 | AT50: 10713218 | AU50: 14685279 | AV50: 14685279 | AW50: 14685279 | AX50: 14685279 | AY50: 14685279 | AZ50: 14685279 | BA50: 14685279 | BB50: 14685279 | BC50: 14685279 | BD50: 14685279 | BE50: 14685279 | BF50: =14685280+2700376 -> 17385656 | BG50: 18746385 | BH50: 17350686 | BI50: 17385655 | BJ50: 17385655 | BK50: 17385655 | BL50: 17380606 | BM50: 17380606 | BN50: 17380606 | BO50: 17380606 | BP50: 17380606 | BQ50: 17380606 | BR50: 17380606 | BS50: 21677842 | BT50: 21677841 | BU50: 21677841 | BV50: 21677841 | BW50: 21677841 | BX50: 21677841 | BY50: 21677841
A51: Other Reserves (provide notes on these reserves) | B51: 8709200 | C51: 134210 | D51: 202065.67 | E51: 35777967 | F51: 35808193 | G51: 35149814 | H51: 35210764 | I51: 35273514 | J51: 35336464 | K51: 35400414 | L51: 35465164 | M51: 35535364 | N51: 35603564 | O51: 35672164 | P51: =134210-436946 -> -302736 | Q51: =134210-807256 -> -673046 | R51: 31766646 | S51: =134210 -> 134210 | T51: -1359681.6 | U51: -1260681.6 | V51: -1516397.6 | W51: -1416197.6 | X51: -1306597.6 | Y51: -1202397.7 | Z51: -1455313.7 | AA51: -123537.66 | AB51: -23537.66 | AC51: 76986.12 | AD51: 176186.12 | AE51: 675386.12 | AF51: 134210 | AG51: -161248.12 | AH51: -64448.12 | AI51: 37551.88 | AJ51: 136351.88 | AK51: -542765.12 | AL51: -443365.12 | AN51: -633623.62 | AO51: 530223.62 | AP51: -816282.12 | AQ51: -722682.12 | AR51: 134210.05 | AS51: 134210 | AT51: 0 | AU51: 2102814 | AV51: 2102814 | AW51: 2102814 | AX51: 2102814 | AY51: 2102814 | AZ51: 2102814 | BA51: 2102814 | BB51: 2102814 | BC51: 2102814 | BD51: 2102814 | BE51: 2067844.9 | BF51: =500000 -> 500000 | BG51: 2067845 | BH51: 0 | BI51: 2056012.3 | BJ51: 0 | BK51: 0 | BL51: 0 | BM51: 0 | BN51: 0 | BO51: 0 | BP51: 0 | BQ51: 0 | BR51: 992921.38 | BS51: 500000 | BT51: 3986972.4 | BU51: 3986972.4 | BV51: 3986972.4 | BW51: 3986972.4 | BX51: 5159558.6 | BY51: 5154131.2
A52: Revaluation Reserves (Not part of core capital) | B52: 1167905 | C52: 35492777 | D52: 0 | N52: 0 | O52: 0 | P52: 29055570 | Q52: 26913343 | R52: 0 | T52: 0 | AD52: 0 | AE52: 0 | AF52: 5555996 | AG52: 0 | AH52: 0 | AI52: 0 | AT52: 5241886 | AU52: 5241886 | AV52: 5241886 | AW52: 5241886 | AX52: 5241886 | AY52: 5241886 | AZ52: 5241886 | BA52: 5241886 | BB52: 5241886 | BC52: 5241886 | BD52: 5241886 | BE52: 5241886 | BG52: 5241886 | BH52: 5241886 | BI52: 5241886 | BJ52: 5241886 | BK52: 5241886 | BL52: 5241886 | BM52: 5241886 | BN52: 5241886 | BO52: 5241886 | BP52: 5241886 | BQ52: 5241886 | BR52: 5241886 | BT52: 5241886 | BU52: 5241886 | BV52: 5241886 | BW52: 5241886 | BX52: 5241886 | BY52: 5241886
A53: Proposed Dividends | B53: 1302538 | Q53: 3561607 | S53: 5756280 | AG53: 0 | AH53: 0 | AI53: 0 | AS53: 7916516 | AT53: 0 | AU53: 0 | AV53: 0 | AW53: 0 | AX53: 0 | AY53: 0 | AZ53: 0 | BA53: 0 | BB53: 0 | BC53: 0 | BD53: 0 | BE53: 0 | BF53: =9560000+3551000+300000+300000 -> 13711000 | BG53: 0 | BH53: 0 | BI53: 0 | BJ53: 0 | BK53: 0 | BL53: 0 | BM53: 0 | BN53: 0 | BO53: 0 | BP53: 0 | BQ53: 0 | BR53: 0 | BS53: =11968125+4737731+400000+400000 -> 17505856 | BT53: 0 | BU53: 0 | BV53: 0 | BW53: 0 | BX53: 0 | BY53: 0
A54: Adjustment to Equity | AG54: 0 | AH54: 0 | AI54: 0 | AT54: 0 | AU54: 0 | AV54: 0 | AW54: 0 | AX54: 0 | AY54: 0 | AZ54: 0 | BA54: 0 | BB54: 0 | BC54: 0 | BD54: 0 | BE54: 0 | BG54: 0 | BH54: 0 | BI54: 0 | BJ54: 0 | BK54: 0 | BL54: 0 | BM54: 0 | BN54: 0 | BO54: 0 | BP54: 0 | BQ54: 0 | BR54: 0 | BT54: 0 | BU54: 0 | BV54: 0 | BW54: 0 | BX54: 0 | BY54: 0
A55: Total Equity | B55: =B42+B43+B45+B49 -> 28460078 | C55: =C42+C43+C45+C49 -> 70781464 | D55: =D42+D43+D45+D49 -> 94944699 | E55: =E42+E43+E45+E49 -> 75269883 | F55: =F42+F43+F45+F49 -> 78350880 | G55: =G42+G43+G45+G49 -> 85261209 | H55: =H42+H43+H45+H49 -> 89373249 | I55: =I42+I43+I45+I49 -> 93106244 | ... BY55: =BY42+BY43+BY45+BY49 -> 1.2194767e+08
A56: Total Liabilities and Equity | B56: =B55+B40 -> 409574161 | C56: =C55+C40 -> 424339220 | D56: =D55+D40 -> 4.6428028e+08 | E56: =E55+E40 -> 4.5637083e+08 | F56: =F55+F40 -> 4.308659e+08 | G56: =G55+G40 -> 4.2311864e+08 | H56: =H55+H40 -> 4.2364712e+08 | I56: =I55+I40 -> 4.1005549e+08 | ... P56: =P55+P40 -> 431325357 | Q56: =Q40+Q55 -> 4.7577154e+08 | R56: =R40+R55 -> 6.2441666e+08 | S56: =S40+S55 -> 590186394 | T56: =T40+T55 -> 6.0231394e+08 | U56: =U40+U55 -> 6.2625108e+08 | V56: =V40+V55 -> 5.9828697e+08 | W56: =W40+W55 -> 5.8907278e+08 | X56: =X40+X55 -> 6.1710155e+08 | ... BY56: =BY40+BY55 -> 3.4399552e+08
F57: =F27-F56 -> 5967718.3 | G57: =G27-G56 -> 100.06 | H57: =H27-H56 -> -782691.85 | I57: =I27-I56 -> -782691.85 | J57: =J27-J56 -> -782691.85 | K57: =K27-K56 -> -0.060000002 | L57: =L27-L56 -> 0 | M57: =M27-M56 -> 0 | ... AS57: =AS27-AS56 -> -3579309.3 | BU57: =BU56-BU27 -> 0 | BV57: =BV56-BV27 -> 0 | BW57: =BW56-BW27 -> 0 | BX57: =BX56-BX27 -> 0 | BY57: =BY56-BY27 -> 0

Sheet SCI
A1: FORTITUDE SACCO SOCIETY LTD
A2: STATEMENT OF COMPREHENSIVE INCOME | B2: AUDITED 2013 | C2: AUDITED 2014 | D2: AUDITED 2015 | E2: AUDITED 2016 | F2: AUDITED 2017 | G2: 43101 | H2: 43132 | I2: 43160 | J2: 43191 | K2: 43221 | L2: 43252 | M2: 43282 | N2: 43313 | O2: 43344 | P2: 43374 | Q2: 43405 | R2: 43435 | S2: AUDITED 2018 | T2: 43466 | U2: 43497 | V2: 43525 | W2: 43556 | X2: 43586 | Y2: 43617 | Z2: 43647 | AA2: 43678 | AB2: 43709 | AC2: 43739 | AD2: 43770 | AE2: 43800 | AF2: AUDITED 2019 | AG2: 43831 | AH2: 43862 | AI2: 43891 | AJ2: 43922 | AK2: 43952 | AL2: 43983 | AM2: 44013 | AN2: 44044 | AO2: 44075 | AP2: 44105 | AQ2: 44136 | AR2: 44166 | AS2: AUDITED 2020 | AT2: 44197 | AU2: 44228 | AV2: 44256 | AW2: 44287 | AX2: 44317 | AY2: 44348 | AZ2: 44378 | BA2: 44409 | BB2: 44440 | BC2: 44470 | BD2: 44501 | BE2: 44531 | BF2: Audited 2021 | BG2: 44562 | BH2: 44593 | BI2: 44621 | BJ2: 44652 | BK2: 44682 | BL2: 44713 | BM2: 44743 | BN2: 44774 | BO2: 44805 | BP2: 44835 | BQ2: 44866 | BR2: 44896 | BS2: Audited-22 | BT2: 44949 | BU2: 44980 | BV2: 45008 | BW2: 45039 | BX2: 45069 | BY2: 45100
A3: Financial Income | B3: =B4+B7 -> 74027307 | C3: =C4+C7 -> 65691340 | D3: =D4+D7 -> 1.0610908e+08 | E3: =E4+E7 -> 10405797 | F3: =F4+F7 -> 15582715 | G3: =G4+G7 -> 20763238 | H3: =H4+H7 -> 25456373 | I3: =I4+I7 -> 31287074 | ... BY3: =BY4+BY7 -> 47910913
A4: Financial Income from Loans Portfolio | B4: =B5+B6 -> 62711244 | C4: =C5+C6 -> 52194043 | D4: =D5+D6 -> 56925716 | E4: =E5+E6 -> 9065834.9 | F4: =F5+F6 -> 13347691 | G4: =G5+G6 -> 17843186 | H4: =H5+H6 -> 21802838 | I4: =I5+I6 -> 26712971 | ... P4: =P5+P6 -> 54667658 | Q4: =SUM(Q5:Q6) -> 63659533 | R4: =SUM(R5:R6) -> 94014243 | S4: =SUM(S5:S6) -> 92243098 | T4: =SUM(T5:T6) -> 1.0179529e+08 | U4: =SUM(U5:U6) -> 1.1018467e+08 | V4: =SUM(V5:V6) -> 1.1878281e+08 | W4: =SUM(W5:W6) -> 33276427 | X4: =SUM(X5:X6) -> 41698878 | ... BY4: =SUM(BY5:BY6) -> 34281043
A5: Interest on Loan Portfolio | B5: 57022088 | C5: 52194043 | D5: 55000112 | E5: 8632811.1 | F5: 12883199 | G5: 17282803 | H5: 21193775 | I5: 25886856 | J5: 30190452 | K5: 34176160 | L5: 38908479 | M5: 43550431 | N5: 48388847 | O5: 53491313 | P5: 54667658 | Q5: 63659533 | R5: 92180844 | S5: 92243098 | T5: 99835043 | U5: 1.0810016e+08 | V5: 1.1656356e+08 | W5: 32743706 | X5: 41028053 | Y5: 48910970 | Z5: 57168352 | AA5: 66327442 | AB5: 74789201 | AC5: 83778703 | AD5: 92124775 | AE5: 1.0064683e+08 | AF5: =66338438+34328625 -> 100667063 | AG5: 1.0876101e+08 | AH5: 16320621 | AI5: 24652089 | AJ5: 33203109 | AK5: 41377960 | AL5: 49686714 | AN5: 67396936 | AO5: 76307497 | AP5: 86072414 | AQ5: 94947166 | AR5: 1.0421454e+08 | AS5: =73499431+31198988 -> 104698419 | AT5: 39621320 | AU5: 6244483.3 | AV5: 9623385.6 | AW5: 12743361 | AX5: 15976304 | AY5: 19602197 | AZ5: 23094962 | BA5: 26549529 | BB5: 30058468 | BC5: 33582271 | BD5: 37901113 | BE5: 41538845 | BF5: =20328662+1732493+6274+9024797+10463369 -> 41555595 | BG5: 3590942.7 | BH5: 7075609.4 | BI5: 11174451 | BJ5: 15255063 | BK5: 18612340 | BL5: 22744835 | BM5: 26511504 | BN5: 31002730 | BO5: 35427268 | BP5: 39772390 | BQ5: 44457027 | BR5: 49559112 | BS5: =25630081+23926206 -> 49556287 | BT5: 5300955.1 | BU5: 9875388.1 | BV5: 14446079 | BW5: 18708112 | BX5: 26142035 | BY5: 32458173
A6: Fees & Commission on Loan Portfolio | B6: 5689156 | D6: 1925603.2 | E6: 433023.71 | F6: 464491.84 | G6: 560383.3 | H6: 609062.77 | I6: 826114.71 | J6: 944094.49 | K6: 1034867.3 | L6: 1131292.8 | M6: 1324299.8 | N6: 1450977.2 | O6: 1608294.2 | R6: 1833398.6 | T6: 1960246.6 | U6: 2084511.6 | V6: 2219246.3 | W6: 532720.98 | X6: 670824.7 | Y6: 779039.7 | Z6: 911407.55 | AA6: 1046002.9 | AB6: 1178016.9 | AC6: 1330449.4 | AD6: 1519892.9 | AE6: 1671217.9 | AG6: 1848659.5 | AH6: 464069.7 | AI6: 727906.3 | AJ6: 940925.8 | AK6: 1042270.5 | AL6: 1178396.9 | AN6: 1878747.2 | AO6: 2030985.6 | AP6: 2201258.9 | AQ6: 2313877.6 | AR6: 2497567.1 | AS6: =7313439+1061800+1322492 -> 9697731 | AT6: 2443656.8 | AU6: 214925.6 | AV6: 384561.6 | AW6: 534273.6 | AX6: 687383.6 | AY6: 926419.6 | AZ6: 1214323.3 | BA6: 1408820.3 | BB6: 1620514.3 | BC6: 1818182.3 | BD6: 2056942.3 | BE6: 2286084.3 | BF6: =27992+30970+23880+12298+36960+84307+13380+45600+380955+22250+42861+22550+15626+52000+137660+13590+46500+385286+804729+12440+47400 -> 2259234 | BG6: 201059 | BH6: 364273.1 | BI6: 689359.1 | BJ6: 985370.4 | BK6: 1224155.4 | BL6: 1574691.4 | BM6: 1844282.4 | BN6: 2294659 | BO6: 2589755.1 | BP6: 2873203.4 | BQ6: 3212718.4 | BR6: 3675111.4 | BS6: =3632008 -> 3632008 | BT6: 622850 | BU6: 824773 | BV6: 1040927.4 | BW6: 1211745 | BX6: 1508842.1 | BY6: 1822870.1
A7: Financial Income from Investments in: | B7: =SUM(B8:B11) -> 11316063 | C7: =SUM(C8:C11) -> 13497297 | D7: =SUM(D8:D11) -> 49183360 | E7: =SUM(E8:E11) -> 1339962.3 | F7: =SUM(F8:F11) -> 2235023.7 | G7: =SUM(G8:G11) -> 2920052.5 | H7: =SUM(H8:H11) -> 3653535.2 | I7: =SUM(I8:I11) -> 4574103.8 | ... BY7: =SUM(BY8:BY11) -> 13629870
A8: Government Securities | E8: 0 | F8: 0 | R8: 0 | T8: 0 | AB8: 0 | AD8: 0 | AE8: 0 | AJ8: 0 | AK8: 0 | AL8: 0 | AN8: 0 | AO8: 0 | AP8: 0 | AQ8: 0 | AR8: 0 | AT8: 0 | AU8: 0 | AV8: 0 | AW8: 0 | AX8: 0 | AY8: 0 | AZ8: 0 | BA8: 0 | BB8: 0 | BC8: 0 | BD8: 0 | BE8: 0 | BF8: 0 | BG8: 0 | BH8: 0 | BI8: 0 | BJ8: 0 | BK8: 0 | BL8: 0 | BM8: 0 | BN8: 0 | BO8: 0 | BP8: 0 | BQ8: 0 | BR8: 0 | BT8: 0 | BU8: 0 | BV8: 0 | BW8: 0 | BX8: 0 | BY8: 0
A9: Deposit with Banks and Other Financial Inst. | D9: 354068.62 | E9: 0 | F9: 158161.69 | G9: 158161.69 | H9: 158161.69 | I9: 287104.16 | J9: 287104.16 | K9: 287104.16 | L9: 287104.16 | M9: 391649.98 | N9: 391649.98 | O9: 426334.21 | P9: 426334 | Q9: 39645 | R9: 13896.45 | T9: 13896.45 | U9: 13896.45 | V9: 13896.45 | AA9: 0 | AD9: 0 | AE9: 0 | AJ9: 0 | AK9: 0 | AL9: 0 | AN9: 0 | AO9: 0 | AP9: 0 | AQ9: 0 | AR9: 0 | AT9: 0 | AU9: 0 | AV9: 0 | AW9: 0 | AX9: 0 | AY9: 0 | AZ9: 0 | BA9: 0 | BB9: 0 | BC9: 0 | BD9: 0 | BE9: 0 | BF9: 0 | BG9: 0 | BH9: 0 | BI9: 0 | BJ9: 0 | BK9: 0 | BL9: 0 | BM9: 0 | BN9: 0 | BO9: 0 | BP9: 0 | BQ9: 0 | BR9: 0 | BT9: 0 | BU9: 0 | BV9: 0 | BW9: 0 | BX9: 0 | BY9: 0
A10: Other Investments - dividend & Interest incomes from investments | B10: 2127844 | C10: 2983273 | D10: 2630642.9 | E10: 15925.27 | F10: 43057.78 | G10: 95049.99 | H10: 155757.35 | I10: 260623.56 | J10: 1821772.3 | K10: 1998600.3 | L10: 2183323.5 | M10: 2415547 | N10: 2662484.9 | O10: 2913037.8 | P10: 2913038 | Q10: 3632158 | R10: 6206919.1 | S10: 3407950 | T10: 3705008.8 | U10: 4130602.6 | V10: 4359650.3 | W10: 1282918.3 | X10: 1500051.2 | Y10: 5241139.4 | Z10: 5506887.8 | AA10: 5815685.8 | AB10: 6090360.5 | AC10: 6447802 | AD10: 6745942.2 | AE10: 7085223.2 | AF10: =7085223 -> 7085223 | AG10: 7437525.2 | AH10: 680074.35 | AI10: 869517.81 | AJ10: 4577935.1 | AK10: 4794738.9 | AL10: 5048478.8 | AN10: 5696986.2 | AO10: 6764202.2 | AP10: 7135969.4 | AQ10: 7447287.4 | AR10: 7878483.1 | AS10: 7878483 | AT10: 8351862.7 | AU10: 0 | AV10: 0 | AW10: 7660800 | AX10: 7660800 | AY10: 7660800 | AZ10: 7660800 | BA10: 7660800 | BB10: 8064000 | BC10: 8070274.1 | BD10: 8070274.1 | BE10: 8070274.1 | BG10: 41100 | BH10: 41100 | BI10: 41100 | BJ10: 41100 | BK10: 41100 | BL10: 7815300 | BM10: 7815300 | BN10: 7855811.8 | BO10: 7891948.2 | BP10: 7942502.8 | BQ10: 7979370.9 | BR10: 8056811.3 | BT10: 4554.83 | BU10: 4554.83 | BV10: 4554.83 | BW10: 8480.27 | BX10: 9891.83 | BY10: 11645722
A11: Other Operating Income- Salary processing fees, transaction fees, membership fees | B11: 9188219 | C11: 10514024 | D11: 46198648 | E11: 1324037 | F11: 2033804.2 | G11: 2666840.8 | H11: 3339616.1 | I11: 4026376.1 | J11: 4698876.1 | K11: 5262116.2 | L11: 6022779 | M11: 6708547 | N11: 7424446.7 | O11: 9216036.9 | P11: 9652565 | Q11: 9523886 | R11: 10461491 | S11: 15097041 | T11: 13961530 | U11: 14841525 | V11: 15905132 | W11: 3157751.1 | X11: 3957149.7 | Y11: 4643625.7 | Z11: 5633377.7 | AA11: 6541857.5 | AB11: 7370888.8 | AC11: 8252826.3 | AD11: 9050893 | AE11: 9953701.2 | AF11: =7551102+1222600+103600+836446+1767433+268500 -> 11749681 | AG11: 10830591 | AH11: 1897888.1 | AI11: 2995926.4 | AJ11: 3819708.6 | AK11: 4691876.7 | AL11: 5599516.7 | AN11: 7342211.1 | AO11: 8122578.6 | AP11: 8920363.5 | AQ11: 9713432.1 | AR11: 10726283 | AS11: =819410+1793429+429400 -> 3042239 | AT11: 2560431.4 | AU11: 268843.51 | AV11: 416061.59 | AW11: 616038.57 | AX11: 776518.44 | AY11: 979826.26 | AZ11: 1222157.2 | BA11: 1439772 | BB11: 1694367.4 | BC11: 1864058.7 | BD11: 2036920.5 | BE11: 2256346 | BF11: =10250+51111+381200+116304+27917+228970+7800+500+5800+32120+2800+19670+36799+456019+119980+400+181580+20073+36120+8064000+48701+288000+73967+70484+33120+14420+10000 -> 10338105 | BG11: 188005.73 | BH11: 336804.51 | BI11: 564054.51 | BJ11: 816933.18 | BK11: 1019735.8 | BL11: 1274561 | BM11: 1490999.7 | BN11: 1800328.9 | BO11: 2053670.4 | BP11: 2282885.4 | BQ11: 2569136.4 | BR11: 3018967.3 | BS11: =11105292 -> 11105292 | BT11: 280402.91 | BU11: 568192.43 | BV11: 877754.04 | BW11: 1065661.3 | BX11: 1544082.4 | BY11: 1984147.4
A12: Financial Expense | B12: =B13+B14+B15+B16+#REF!+B17+B18 -> #REF! | C12: =C13+C14+C15+C16+#REF!+C17+C18 -> #REF! | D12: =D13+D14+D15+D16+#REF!+D17+D18 -> #REF! | E12: =E13+E14+E15+E16+#REF!+E17+E18 -> #REF! | F12: =F13+F14+F15+F16+#REF!+F17+F18 -> #REF! | G12: =G13+G14+G15+G16+#REF!+G17+G18 -> #REF! | H12: =H13+H14+H15+H16+#REF!+H17+H18 -> #REF! | I12: =I13+I14+I15+I16+#REF!+I17+I18 -> #REF! | ... P12: =P13+P14+P15+P16+#REF!+P17+P18 -> #REF! | Q12: =Q13+Q14+Q15+Q16+Q17+Q18 -> 35504498 | R12: =R13+R14+R15+R16+R17+R18 -> 4683475.8 | S12: =S13+S14+S15+S16+S17+S18 -> 54389831 | T12: =T13+T14+T15+T16+T17+T18 -> 6205288.6 | U12: =U13+U14+U15+U16+U17+U18 -> 6532489.9 | V12: =V13+V14+V15+V16+V17+V18 -> 6655880.2 | W12: =W13+W14+W15+W16+W17+W18 -> 1786250.9 | X12: =X13+X14+X15+X16+X17+X18 -> 2496763.9 | ... BY12: =BY13+BY14+BY15+BY16+BY17+BY18 -> 2200820.9
A13: Interest Expense on Deposits | B13: 18861799 | C13: 23759229 | D13: 2461273.2 | E13: 735959 | F13: 1091031 | G13: 1432379 | H13: 1750634 | I13: 2043036 | J13: 2334812 | K13: 2621472.6 | L13: 2889934.4 | M13: 3186207.2 | N13: 3439550.5 | O13: 3711558.8 | P13: =24763211+3711559+653805 -> 29128575 | Q13: =31585421+2460835+654058 -> 34700314 | R13: 1845290.7 | S13: =54062555-S14 -> 54061562 | T13: 1884455 | U13: 2111268.5 | V13: 2145794 | W13: 425008.75 | X13: 476081.87 | Y13: 685905.01 | Z13: 838825.6 | AA13: 962149.35 | AB13: 1076271.7 | AC13: 1213484.1 | AD13: 1334765.4 | AE13: 1459761.6 | AF13: =55869551+1459762+524728 -> 57854041 | AG13: 1481019 | AH13: 260451.72 | AI13: 397881.53 | AJ13: 552462.98 | AK13: 690906.31 | AL13: 824276.69 | AN13: 1052889.8 | AO13: 1163567.2 | AP13: 1259030.6 | AQ13: 1346031.1 | AR13: 1448475.1 | AS13: =64163291+1448475+527228 -> 66138994 | AT13: 7387683 | AU13: 0 | AV13: 0 | AW13: 0 | AX13: 0 | AY13: 0 | AZ13: 0 | BA13: 0 | BB13: 0 | BC13: 0 | BD13: 0 | BE13: 9560000 | BF13: =9560000 -> 9560000 | BG13: 0 | BH13: 0 | BI13: 0 | BJ13: 0 | BK13: 0 | BL13: 0 | BM13: 0 | BN13: 0 | BO13: 0 | BP13: 0 | BQ13: 0 | BR13: 0 | BS13: 11968125 | BT13: 0 | BU13: 0 | BV13: 0 | BW13: 0 | BX13: 0 | BY13: 0
A14: Cost of External Borrowings | B14: 10401634 | C14: 6078781 | D14: 5644606.6 | E14: 63870.55 | F14: 76696.34 | G14: 112967.62 | H14: 193027.92 | I14: 238614.18 | J14: 307117.57 | K14: 399098.89 | L14: 486852.72 | M14: 572963.24 | N14: 692145.56 | O14: 819884.79 | P14: 819885 | Q14: 804184 | R14: 993.3 | S14: 993 | T14: 2438.01 | U14: 2438.01 | V14: 2438.01 | W14: 1444.71 | X14: 1444.71 | Y14: 1444.71 | Z14: 1444.71 | AA14: 1444.71 | AB14: 1444.71 | AC14: 1444.71 | AD14: 1486.16 | AE14: 1486.16 | AF14: =1866 -> 1866 | AG14: 1486.2 | AH14: 4.96 | AI14: 0 | AJ14: 25010.73 | AK14: 25010.73 | AL14: 25011.98 | AN14: 47956.98 | AO14: 47956.98 | AP14: 68841.98 | AQ14: 68841.98 | AR14: 68841.99 | AS14: 68842 | AT14: 340945.31 | AU14: 0 | AV14: 0 | AW14: 0 | AX14: 0 | AY14: 0 | AZ14: 0 | BA14: 0 | BB14: 0 | BC14: 0 | BD14: 0 | BE14: 0 | BG14: 0 | BH14: 0 | BI14: 0 | BJ14: 0 | BK14: 0 | BL14: 0 | BM14: 0 | BN14: 0 | BO14: 0 | BP14: 0 | BQ14: 0 | BR14: 0 | BT14: 0 | BU14: 185205.48 | BV14: 394200.92 | BW14: 627762.57 | BX14: 845918.57 | BY14: 1053800.6
A15: Dividend Expenses (on member shares) | E15: 0 | F15: 0 | X15: 0 | AG15: 0 | AH15: 0 | AI15: 0 | AJ15: 0 | AK15: 0 | AL15: 0 | AN15: 0 | AO15: 0 | AP15: 0 | AQ15: 0 | AR15: 0 | AS15: 0 | AT15: 3300080 | AU15: 0 | AV15: 0 | AW15: 0 | AX15: 0 | AY15: 0 | AZ15: 0 | BA15: 0 | BB15: 0 | BC15: 0 | BD15: 0 | BE15: 3551000 | BG15: 0 | BH15: 0 | BI15: 0 | BJ15: 0 | BK15: 0 | BL15: 0 | BM15: 0 | BN15: 0 | BO15: 0 | BP15: 0 | BQ15: 0 | BR15: 0 | BT15: 0 | BU15: 0 | BV15: 0 | BW15: 0 | BX15: 0 | BY15: 0
A16: Other Financial Expense | D16: 3561680.5 | E16: 2751441.5 | F16: 2751441.5 | G16: 366720.99 | H16: 366720.99 | I16: 1117589 | J16: 1117589 | K16: 1117589 | L16: 1839457 | M16: 1839457 | N16: 1840457 | O16: 2559325 | P16: 642233 | R16: 1478991 | S16: 327276 | T16: 2892456.3 | U16: 2892456.3 | V16: 2892456.3 | W16: 986076.38 | X16: 1552262.4 | Y16: 1552262.4 | Z16: 1552262.4 | AA16: 1552262.4 | AB16: 1605262.4 | AC16: 1605262.4 | AD16: 1605262.4 | AE16: 1605262.4 | AF16: =548262+232433 -> 780695 | AG16: 2879910.4 | AH16: 1925666 | AI16: 2178166 | AJ16: 2228166 | AK16: 2528166 | AL16: 2528166 | AN16: 2528166 | AO16: 2531166 | AP16: 2531166 | AQ16: 2531166 | AR16: 3608756.3 | AS16: =2901181+149858 -> 3051039 | AT16: 708689.4 | AU16: 97677.84 | AV16: 149001.32 | AW16: 218004.91 | AX16: 205827.89 | AY16: 298844.52 | AZ16: 1136693.4 | BA16: 1208474.4 | BB16: 1289584.7 | BC16: 1303624.8 | BD16: 1339299 | BE16: 1440490.2 | BG16: 24857.98 | BH16: 39677.98 | BI16: 147107.98 | BJ16: 197641.98 | BK16: 247765.98 | BL16: 325673.98 | BM16: 370309.18 | BN16: 419063.51 | BO16: 472670.14 | BP16: 521830.14 | BQ16: 556940.89 | BR16: 731647.04 | BT16: 791488 | BU16: 816598 | BV16: 854040 | BW16: 968202 | BX16: 1035842.2 | BY16: 1147020.2
A17: Fees & Commission Expense | D17: 2850995.5 | E17: 297429.21 | F17: 523039.01 | G17: 725484.75 | H17: 938584.3 | I17: 1115651.2 | J17: 1336147.9 | K17: 1592592.2 | L17: 1727080.4 | M17: 1968167.5 | N17: 2173217.5 | O17: 2374276.2 | R17: 1358200.8 | T17: 1425939.3 | U17: 1526327.1 | V17: 1615191.9 | W17: 373721.09 | X17: 466974.89 | Y17: 533462.89 | Z17: 614875.27 | AA17: 713613.27 | AB17: 806602.45 | AC17: 909443.89 | AD17: 1062769 | AE17: 1124270.9 | AG17: 1178008.6 | AH17: 107994.8 | AI17: 165246.1 | AJ17: 243504 | AK17: 299243.2 | AL17: 354500 | AN17: 506647.3 | AO17: 561338 | AP17: 615367 | AQ17: 669743.6 | AR17: 757628.2 | AS17: 0 | AT17: 0 | AU17: 0 | AV17: 0 | AW17: 0 | AX17: 0 | AY17: 0 | AZ17: 0 | BA17: 0 | BB17: 0 | BC17: 0 | BD17: 0 | BE17: 0 | BG17: 0 | BH17: 0 | BI17: 0 | BJ17: 0 | BK17: 0 | BL17: 0 | BM17: 0 | BN17: 0 | BO17: 0 | BP17: 0 | BQ17: 0 | BR17: 0 | BT17: 0 | BU17: 0 | BV17: 0 | BW17: 0 | BX17: 0 | BY17: 0
A18: Other Expense | B18: 1174922 | E18: 0 | F18: 0 | G18: 0 | M18: 0 | N18: 0 | U18: 0 | W18: 0 | Y18: 0 | Z18: 0 | AG18: 0 | AH18: 0 | AI18: 0 | AJ18: 0 | AK18: 0 | AL18: 0 | AN18: 0 | AO18: 0 | AP18: 0 | AQ18: 0 | AR18: 0 | AS18: 0 | AT18: 0 | AU18: 0 | AV18: 0 | AW18: 0 | AX18: 0 | AY18: 0 | AZ18: 0 | BA18: 0 | BB18: 0 | BC18: 0 | BD18: 0 | BE18: 0 | BG18: 0 | BH18: 0 | BI18: 0 | BJ18: 0 | BK18: 0 | BL18: 0 | BM18: 0 | BN18: 0 | BO18: 0 | BP18: 0 | BQ18: 0 | BR18: 0 | BT18: 0 | BU18: 0 | BV18: 0 | BW18: 0 | BX18: 0 | BY18: 0
A19: Net Financial Income/(Loss) | B19: =B3-B12 -> #REF! | C19: =C3-C12 -> #REF! | D19: =D3-D12 -> #REF! | E19: =E3-E12 -> #REF! | F19: =F3-F12 -> #REF! | G19: =G3-G12 -> #REF! | H19: =H3-H12 -> #REF! | I19: =I3-I12 -> #REF! | ... BY19: =BY3-BY12 -> 45710092
A20: Allowance for Loan Loss | P20: =P21 -> -2177981 | Q20: =Q21-Q22 -> 2419802 | R20: =R21-R22 -> 3230963.7 | S20: =S21-S22 -> 3230964 | T20: =T21-T22 -> 3230963.7 | U20: =U21-U22 -> 3230963.7 | V20: =V21-V22 -> 3835914.1 | W20: =W21-W22 -> 806600.56 | X20: =X21-X22 -> 1008250.7 | ... BY20: =BY21-BY22 -> 4624920
A21: Provision for Loan Losses | B21: 1509402 | C21: 2366661 | D21: 2449994.6 | E21: 166666.68 | F21: 250000.02 | G21: 333333.36 | H21: 416666.7 | I21: 500000.04 | J21: 583333.38 | K21: 666666.72 | L21: 750000.06 | M21: 833333.4 | N21: 916666.74 | O21: 1000000.1 | P21: -2177981 | Q21: 2419802 | R21: 3230963.7 | S21: 3230964 | T21: 3230963.7 | U21: 3230963.7 | V21: 3835914.1 | W21: 806600.56 | X21: 1008250.7 | Y21: 1209900.8 | Z21: 1411551 | AA21: 1613201.1 | AB21: 7068275.7 | AC21: 7269925.8 | AD21: 7471575.9 | AE21: 5638534.8 | AF21: 5638535 | AG21: 5840184.9 | AH21: 585305.1 | AI21: 908291.7 | AJ21: 1231278.4 | AK21: 1554265 | AL21: 1877251.7 | AN21: 2787335.9 | AO21: 7772302.8 | AP21: 7139544 | AQ21: 8281499.1 | AR21: 7575786.1 | AS21: 7575786 | AT21: 2102814 | AU21: 3395395.1 | AV21: 2852903.6 | AW21: 4247544.4 | AX21: 3439771 | AY21: 4451197.7 | AZ21: 4275794.9 | BA21: 4817163.8 | BB21: 4817163.8 | BC21: 5253614.1 | BD21: 5305712 | BE21: 6240049.6 | BF21: 6585364 | BG21: 161078.83 | BH21: 320417.59 | BI21: 390146.69 | BJ21: 390146.69 | BK21: 1600759.5 | BL21: 1288853.8 | BM21: 2058262.5 | BN21: 2733965.4 | BO21: 3009423.3 | BP21: 4678429 | BQ21: 4967495.7 | BR21: 2089561.8 | BS21: 2089562 | BT21: 5898086 | BU21: 6000560.5 | BV21: 5601077.5 | BW21: 4343012.1 | BX21: 2592992.5 | BY21: 4624920
A22: Value of Loans Recovered | E22: 0 | F22: 0 | N22: 0 | U22: 0 | AJ22: 0 | AK22: 0 | AL22: 0 | AN22: 0 | AO22: 0 | AP22: 0 | AQ22: 0 | AR22: 0 | AS22: 0 | AT22: 0 | AU22: 0 | AV22: 0 | AW22: 0 | AX22: 0 | AY22: 0 | AZ22: 0 | BA22: 0 | BB22: 0 | BC22: 0 | BD22: 0 | BE22: 0 | BF22: 0 | BG22: 0 | BH22: 0 | BI22: 0 | BJ22: 296819.5 | BK22: 0 | BL22: 0 | BM22: 0 | BN22: 0 | BO22: 0 | BP22: 0 | BQ22: 0 | BR22: 0 | BT22: 0 | BU22: 0 | BV22: 0 | BW22: 0 | BX22: 0 | BY22: 0
A23: Operating Expenses | B23: =B24+B25+B26+B27+B28 -> 34861417 | C23: =C24+C25+C26+C27+C28 -> 25601358 | D23: =D24+D25+D26+D27+D28 -> 23576697 | E23: =E24+E25+E26+E27+E28 -> 3113012 | F23: =F24+F25+F26+F27+F28 -> 5270464 | G23: =G24+G25+G26+G27+G28 -> 6896865.3 | H23: =H24+H25+H26+H27+H28 -> 8391476.2 | I23: =I24+I25+I26+I27+I28 -> 10230406 | ... P23: =P24+P25+P26+P27+P28 -> 25156739 | Q23: =SUM(Q24:Q28) -> 25643787 | R23: =SUM(R24:R28) -> 30509600 | S23: =SUM(S24:S28) -> 33446761 | T23: =SUM(T24:T28) -> 32918868 | U23: =SUM(U24:U28) -> 34803473 | V23: =SUM(V24:V28) -> 40372183 | W23: =SUM(W24:W28) -> 12643518 | X23: =SUM(X24:X28) -> 19031383 | ... BY23: =SUM(BY24:BY28) -> 14274615
A24: Personnel Expenses | B24: 15280515 | C24: 12353692 | D24: 13329761 | E24: 2023516.4 | F24: 3226972.6 | G24: 4331571.3 | H24: 5360813.4 | I24: 6389153.9 | J24: 7394594.5 | K24: 8517234 | L24: 9622373.1 | M24: 10741298 | N24: 11867761 | O24: 12926468 | P24: 13269379 | Q24: 13586259 | R24: 16012476 | S24: 16012476 | T24: 17193382 | U24: 18431571 | V24: 21118482 | W24: 6394125.1 | X24: 7666655 | Y24: 9012453.4 | Z24: 10249701 | AA24: 11476521 | AB24: 12903178 | AC24: 14133976 | AD24: 15561327 | AE24: 17191888 | AF24: =13792882+306810+1503186+310942+153545+133700+32900+46800+740973+68682 -> 17090420 | AG24: 18423481 | AH24: 2564580.2 | AI24: 5856853.8 | AJ24: 6787767.1 | AK24: 7993967.5 | AL24: 9262732 | AN24: 11780946 | AO24: 13055867 | AP24: 14432206 | AQ24: 15714161 | AR24: 17464496 | AS24: =13706318+51050+2015183+495167+119752+129230+2375+47800+775937+82089 -> 17424901 | AT24: 8232730.9 | AU24: 1475691.8 | AV24: 2222564.8 | AW24: 2998247.4 | AX24: 3782804.9 | AY24: 4582442.9 | AZ24: 5574903.2 | BA24: 6343689.6 | BB24: 7061362.6 | BC24: 7779307.9 | BD24: 8583538.7 | BE24: 9671326.7 | BF24: =2280054+2948588+3937543 -> 9166185 | BG24: 791430.9 | BH24: 1749233.4 | BI24: 2582000.7 | BJ24: 3352100.2 | BK24: 4168959 | BL24: 5041893.9 | BM24: 5878537.8 | BN24: 6667869.2 | BO24: 7568864.5 | BP24: 8385331.2 | BQ24: 9244262.4 | BR24: 10134325 | BS24: =2389700+3098272+4646354 -> 10134326 | BT24: 899139 | BU24: 1821427.1 | BV24: 2757786.2 | BW24: 3784129.8 | BX24: 4801570.9 | BY24: 5905444.5
A25: Governance Expenses | B25: 2080088 | C25: 2435008 | D25: 2196237.6 | E25: 77350.2 | F25: 442903.98 | G25: 497268.95 | H25: 573878.63 | I25: 724026.09 | J25: 876615.76 | K25: 1050745.1 | L25: 1253139.6 | M25: 1277639.6 | N25: 1859655.7 | O25: 1955338.1 | P25: 2327340 | Q25: 2165084 | R25: 2816087.7 | S25: 2801808 | T25: 3228177.7 | U25: 3269867.7 | V25: 3905059 | W25: 1358405 | X25: 1634544.8 | Y25: 1777428 | Z25: 2170312.1 | AA25: 2465588.9 | AB25: 2572579.4 | AC25: 2649847.7 | AD25: 3265242.7 | AE25: 3344878.2 | AF25: =557475+794622+203765+1345768+439448+300000 -> 3641078 | AG25: 3547637.5 | AH25: 789237.32 | AI25: 1163637.3 | AJ25: 1381037.3 | AK25: 1565737.3 | AL25: 1811737.3 | AN25: 2203347.3 | AO25: 2413347.3 | AP25: 2592347.3 | AQ25: 2939069.3 | AR25: 3439219.3 | AS25: =293232+95850+2355809+694328 -> 3439219 | AT25: 3260146.2 | AU25: 417406.45 | AV25: 951626.45 | AW25: 1155526.4 | AX25: 1352126.4 | AY25: 1551066.4 | AZ25: 1733066.4 | BA25: 1852266.4 | BB25: 1937960.1 | BC25: 2105170.1 | BD25: 2329200.1 | BE25: 3197560.1 | BF25: =32340+133190+1581110+1509975 -> 3256615 | BG25: 244910 | BH25: 764900 | BI25: 1549946.2 | BJ25: 1736687.2 | BK25: 2063347.2 | BL25: 2163117.2 | BM25: 2323097.2 | BN25: 2440407.2 | BO25: 2571627.2 | BP25: 2769434.2 | BQ25: 2923497.2 | BR25: 3732967.2 | BS25: =36000+181221+2061075+1767201 -> 4045497 | BT25: 186910 | BU25: 415940 | BV25: 1761610 | BW25: 1801320 | BX25: 2077785 | BY25: 2498185
A26: Marketing Expenses | B26: 501573 | C26: 620436 | D26: 533886 | E26: 7650 | F26: 11000 | G26: 28900 | H26: 51400 | I26: 60700 | J26: 74750 | K26: 104700 | L26: 122150 | M26: 206800 | N26: 220900 | O26: 235500 | P26: 335400 | Q26: 292519 | R26: 822305 | S26: 807785 | T26: 780015 | U26: 783045 | V26: 1300645 | W26: 599370 | X26: 620940 | Y26: 662140 | Z26: 885385 | AA26: 979735 | AB26: 1020905 | AC26: 1041590 | AD26: 1058430 | AE26: 1085430 | AF26: =1535430+100000 -> 1635430 | AG26: 1570570.1 | AH26: 344040 | AI26: 385948 | AJ26: 509448 | AK26: 514938 | AL26: 528448 | AN26: 787567 | AO26: 849757 | AP26: 936282 | AQ26: 956592 | AR26: 991702 | AS26: 993702 | AT26: 411100 | AU26: 447280 | AV26: 486695 | AW26: 512825 | AX26: 519825 | AY26: 538545 | AZ26: 552505 | BA26: 655307 | BB26: 676787 | BC26: 715717 | BD26: 815157 | BE26: 917957 | BF26: =601622+5000+1000 -> 607622 | BG26: 2000 | BH26: 584978 | BI26: 1043378 | BJ26: 1084183 | BK26: 1237323 | BL26: 1518318 | BM26: 1546598 | BN26: 1644408 | BO26: 1644408 | BP26: 1679098 | BQ26: 1730608 | BR26: 2467408 | BS26: =1754178 -> 1754178 | BT26: 253130 | BU26: 498810 | BV26: 960805 | BW26: 1007605 | BX26: 1047775 | BY26: 1070095
A27: Depreciation and Amortization Charges | B27: 2078503 | C27: 1700323 | D27: 1892150.8 | E27: 383624.76 | F27: 557706.14 | G27: 729944.78 | H27: 902152.23 | I27: 1074329.4 | J27: 1232471.3 | K27: 1384582.1 | L27: 1536665.2 | M27: 1688721.4 | N27: 1817476.5 | O27: 1934097.9 | P27: 1712064 | Q27: 1590337.9 | R27: 2671325.7 | S27: 2671326 | T27: 2671325.7 | U27: 2671325.7 | V27: 2821938.1 | W27: 782293.12 | X27: 977192.83 | Y27: 1199064 | Z27: 1427153.5 | AA27: 1654077.1 | AB27: 1872599.2 | AC27: 2097316.5 | AD27: 2313758.1 | AE27: 2536380.5 | AF27: =663828+1519407 -> 2183235 | AG27: 2552854 | AH27: 224610.26 | AI27: 341117.19 | AJ27: 452908.39 | AK27: 567461.19 | AL27: 711883.01 | AN27: 999423.54 | AO27: 1127639.1 | AP27: 1259184.6 | AQ27: 1394663.1 | AR27: 1535121.5 | AS27: =682585+852537 -> 1535122 | AT27: 2227029.1 | AU27: 252934.78 | AV27: 397515.81 | AW27: 543017.34 | AX27: 678312.87 | AY27: 804959.57 | AZ27: 949341.47 | BA27: 1084699.5 | BB27: 1220057.5 | BC27: 1355415.6 | BD27: 1490773.6 | BE27: 1626131.6 | BF27: =542036+542036+542060 -> 1626132 | BG27: 118739.6 | BH27: 239562.53 | BI27: 359343.8 | BJ27: 479125.07 | BK27: 603955.82 | BL27: 724746.99 | BM27: 862005.66 | BN27: 985149.33 | BO27: 1108293 | BP27: 1231436.7 | BQ27: 1354580.3 | BR27: 1514224 | BS27: =504741+509061 -> 1013802 | BT27: 112048.19 | BU27: 224096.38 | BV27: 336144.57 | BW27: 448192.76 | BX27: 560240.95 | BY27: 672289.14
A28: Administrative Expenses | B28: 14920738 | C28: 8491899 | D28: 5624661.3 | E28: 620870.64 | F28: 1031881.3 | G28: 1309180.2 | H28: 1503232 | I28: 1982196.9 | J28: 2301672.2 | K28: 2502638.5 | L28: 2961680.7 | M28: 3451263 | N28: 3668056.5 | O28: 4185622.9 | P28: =3151354+4361202 -> 7512556 | Q28: =485900+3199971+4323716 -> 8009587 | R28: 8187405.6 | S28: =3489709+7663657 -> 11153366 | T28: 9045968.1 | U28: 9647663.6 | V28: 11226059 | W28: 3509325.1 | X28: 8132050.6 | Y28: 9257271.5 | Z28: 8034161 | AA28: 8547123.3 | AB28: 10189284 | AC28: 10857031 | AD28: 11434249 | AE28: 12202113 | AF28: =402369+230487+592352+152980+307315+659186+16499+34750+318320+60575+191750+16000+806419+1587674+94830+64308+116667+1327040+30000+945697+763123+500000+347290+45050+99805+299486+649842+328700+43760+25000+1920+2825817 -> 13885011 | AG28: 12843118 | AH28: 1432091.1 | AI28: 2083999 | AJ28: 2769251.6 | AK28: 3445102.1 | AL28: 4461787.8 | AN28: 8202445.5 | AO28: 9077861.6 | AP28: 10280312 | AQ28: 11249962 | AR28: 12154796 | AS28: =336367+253271+533017+230000+193640+744018+22887+94224+43125+177040+89795+781764+705442+119007+183333+1318520+22485+2664738+723581+237500+6840+2928359+211770+74753+150950+338688+67427+30000+10000+200000 -> 13492541 | AT28: 8560052.9 | AU28: 882857 | AV28: 1102117 | AW28: 1223867 | AX28: 1739668 | AY28: 2286689 | AZ28: 2493404 | BA28: 3170532.9 | BB28: 3561657.9 | BC28: 3683357.9 | BD28: 4362141.9 | BE28: 7780681.9 | BF28: =(1760924+1851870+7390369)-(1000+542036+5000+542036+542060) -> 9371031 | BG28: 461427 | BH28: 875879 | BI28: 2121878 | BJ28: 2714358 | BK28: 3444290 | BL28: 4179331.1 | BM28: 4997083.2 | BN28: 5615719.2 | BO28: 6119612.2 | BP28: 6788103.2 | BQ28: 7304797.2 | BR28: 5209592.2 | BS28: =(2135695+2176925+3687954)-BS27 -> 6986772 | BT28: 303475 | BU28: 1917933 | BV28: 2226648 | BW28: 2516935 | BX28: 3254481 | BY28: 4128601.2
A29: Net Operating Income | B29: =B19-B20-B23 -> #REF! | C29: =C19-C20-C23 -> #REF! | D29: =D19-D20-D23 -> #REF! | E29: =E19-E20-E23 -> #REF! | F29: =F19-F20-F23 -> #REF! | G29: =G19-G20-G23 -> #REF! | H29: =H19-H20-H23 -> #REF! | I29: =I19-I20-I23 -> #REF! | ... BY29: =BY19-BY20-BY23 -> 26810558
A30: Net Non- Operating Income/ (Expense) | B30: =B31-B32 -> 0 | C30: =C31-C32 -> 0 | D30: =D31-D32 -> 0 | E30: =E31-E32 -> 0 | F30: =F31-F32 -> 0 | G30: =G31-G32 -> 0 | H30: =H31-H32 -> 0 | I30: =I31-I32 -> 0 | ... BY30: =BY31-BY32 -> 0
A31: Non- Operating Income | E31: 0 | F31: 0 | AT31: 0 | AU31: 0 | AV31: 0 | AW31: 0 | AX31: 0 | AY31: 0 | AZ31: 0 | BA31: 0 | BB31: 0 | BC31: 0 | BD31: 0 | BE31: 0 | BT31: 0 | BU31: 0 | BV31: 0 | BW31: 0 | BX31: 0 | BY31: 0
A32: Non- Operating Expense | E32: 0 | F32: 0 | AT32: 0 | AU32: 0 | AV32: 0 | AW32: 0 | AX32: 0 | AY32: 0 | AZ32: 0 | BA32: 0 | BB32: 0 | BC32: 0 | BD32: 0 | BE32: 0 | BT32: 0 | BU32: 0 | BV32: 0 | BW32: 0 | BX32: 0 | BY32: 0
A33: Net Income (Before Taxes and Donations) | B33: =B29+B30 -> #REF! | C33: =C29+C30 -> #REF! | D33: =D29+D30 -> #REF! | E33: =E29+E30 -> #REF! | F33: =F29+F30 -> #REF! | G33: =G29+G30 -> #REF! | H33: =H29+H30 -> #REF! | I33: =I29+I30 -> #REF! | ... BY33: =BY29+BY30 -> 26810558
A34: Taxes (Incomes taxes & Other payable to KRA) | B34: 1852719 | C34: 886290 | P34: 1533973 | Q34: 1665875 | S34: 3897835 | AF34: 2806926 | AS34: 3657691 | AT34: 409668 | AU34: 0 | AV34: 0 | AW34: 0 | AX34: 0 | AY34: 0 | AZ34: 0 | BA34: 0 | BB34: 403200 | BC34: 403200 | BD34: 403200 | BE34: 663200 | BF34: 478112 | BG34: 0 | BH34: 0 | BI34: 0 | BJ34: 0 | BK34: 0 | BL34: 388710 | BM34: 388710 | BN34: 388710 | BO34: 388710 | BP34: 388710 | BQ34: 388710 | BR34: 3852312 | BS34: =4840396 -> 4840396 | BT34: 1731801 | BU34: 1731801 | BV34: 1731801 | BW34: 1731801 | BX34: 1286441 | BY34: 1868163.1
A35: Net Income (After Taxes before Donations) | B35: =B33-B34+#REF! -> #REF! | C35: =C33-C34+#REF! -> #REF! | D35: =D33-D34+#REF! -> #REF! | E35: =E33-E34+#REF! -> #REF! | F35: =F33-F34+#REF! -> #REF! | G35: =G33-G34+#REF! -> #REF! | H35: =H33-H34+#REF! -> #REF! | I35: =I33-I34+#REF! -> #REF! | ... P35: =P33-P34+#REF! -> #REF! | Q35: =Q33-Q34 -> 11621260 | R35: =R33-R34 -> 72272510 | S35: =S33-S34 -> 15782698 | T35: =T33-T34 -> 77120604 | U35: =U33-U34 -> 84603768 | V35: =V33-V34 -> 88197509 | W35: =W33-W34 -> 22480726 | X35: =X33-X34 -> 24619681 | ... BY35: =BY33-BY34 -> 24942394
A36: Donations | AT36: 0 | AU36: 0 | AV36: 0 | AW36: 0 | AX36: 0 | AY36: 0 | AZ36: 0 | BA36: 0 | BB36: 0 | BC36: 0 | BD36: 0 | BE36: 0 | BT36: 0 | BU36: 0 | BV36: 0 | BW36: 0 | BX36: 0 | BY36: 0
A37: Net Income/(After Taxes and Donations) | B37: =B35-B36 -> #REF! | C37: =C35-C36 -> #REF! | D37: =D35-D36 -> #REF! | E37: =E35-E36 -> #REF! | F37: =F35-F36 -> #REF! | G37: =G35-G36 -> #REF! | H37: =H35-H36 -> #REF! | I37: =I35-I36 -> #REF! | ... P37: =P35-P36 -> #REF! | Q37: =Q35+Q36 -> 11621260 | R37: =R35+R36 -> 72272510 | S37: =S35+S36 -> 15782698 | T37: =T35+T36 -> 77120604 | U37: =U35+U36 -> 84603768 | V37: =V35+V36 -> 88197509 | W37: =W35+W36 -> 22480726 | X37: =X35+X36 -> 24619681 | ... AS37: =AS35+AS36 -> 7939035 | AT37: =AT35-AT36 -> 16036332 | AU37: =AU35-AU36 -> -240990.62 | AV37: =AV35-AV36 -> 2261584.8 | AW37: =AW35-AW36 -> 10655441 | AX37: =AX35-AX36 -> 13382670 | AY37: =AY35-AY36 -> 14655498 | AZ37: =AZ35-AZ36 -> 16476534 | BA37: =BA35-BA36 -> 17926788 | ... BY37: =BY35-BY36 -> 24942394

Sheet Sheet1
B2: Year | C2: AUDITED 2015 | D2: AUDITED 2016 | E2: AUDITED 2017 | F2: AUDITED 2018 | G2: 43466 | H2: 43497 | I2: 43525 | J2: 43556 | K2: 43586 | L2: 43617
A3: 2 | B3: Total Assets | C3: 4.6351889e+08 | D3: 4.5637093e+08 | E3: 4.3683362e+08 | F3: 590186392 | G3: 6.0231394e+08 | H3: 6.2625108e+08 | I3: 5.9828697e+08 | J3: 5.8907278e+08 | K3: 6.1710155e+08 | L3: 6.0417723e+08
A4: 3 | B4: Total Deposits | C4: 3.6391029e+08 | D4: 3.5281156e+08 | E4: 3.4681983e+08 | F4: 433315333 | G4: 4.3839535e+08 | H4: 4.542002e+08 | I4: 4.7118357e+08 | J4: 4.6306008e+08 | K4: 4.8617864e+08 | L4: 4.6622117e+08
A5: 3.1 | B5: Deposits-Members(BOSA) | C5: 2.4228165e+08 | D5: 2.4464437e+08 | E5: 2.4323434e+08 | F5: 365696388 | G5: 3.7313088e+08 | H5: 3.8056337e+08 | I5: 3.899621e+08 | J5: 3.9463998e+08 | K5: 3.9710517e+08 | L5: 4.0401425e+08
A6: 3.2 | B6: Deposits-Customers(FOSA) | C6: 4074376.9 | D6: 4984401.3 | E6: 5076228.9 | F6: 67618945 | G6: 14363008 | H6: 15611949 | I6: 13612359 | J6: 14419909 | K6: 14679037 | L6: 13096149
A7: 4 | B7: External Borrowing | C7: 782851.88 | D7: 782851.88 | E7: 782851.88 | F7: 0 | G7: 0 | H7: 0 | I7: 0 | J7: 0 | K7: 0 | L7: 0
A8: 4.1 | B8: Short term Liabilities | C8: 4642444.9 | D8: 27506534 | E8: 4912342.2 | F8: 58156529 | G8: 3901907.3 | H8: 4415903.4 | I8: -44130681 | J8: 10574287 | K8: 12876255 | L8: 10617410
A9: 5.1 | B9: Core Capital | C9: 94944699 | D9: 75269883 | E9: 78350880 | F9: 88729697 | G9: 1.5578813e+08 | H9: 1.6340642e+08 | I9: 1.6700553e+08 | J9: 1.1120986e+08 | K9: 1.138181e+08 | L9: 1.231101e+08
A10: 5.2 | B10: Institutional Capital | C10: 85006164 | D10: 65331348 | E10: 67704199 | F10: 65523502 | G10: 1.3199681e+08 | H10: 1.3957898e+08 | I10: 1.42917e+08 | J10: 87051631 | K10: 89639871 | L10: 98730332
A11: 5.3 | B11: Total Capital | C11: 94944699 | D11: 75269883 | E11: 78350880 | F11: 92958252 | G11: 1.6001668e+08 | H11: 1.6763498e+08 | I11: 1.7123408e+08 | J11: 1.1543841e+08 | K11: 1.1804665e+08 | L11: 1.2733866e+08
A12: 7 | B12: Net Loans & advances | C12: 2.9963107e+08 | D12: 3.0964314e+08 | E12: 3.1063977e+08 | F12: 467465209 | G12: 4.7291977e+08 | H12: 4.7868736e+08 | I12: 4.7578771e+08 | J12: 4.7958254e+08 | K12: 4.8126667e+08 | L12: 4.8527697e+08
A13: 7.1 | B13: Gross Loans & advances | C13: 3.0960349e+08 | D13: 3.1961557e+08 | E13: 3.2061219e+08 | F13: 478678153 | G13: 4.8413271e+08 | H13: 4.899003e+08 | I13: 4.8760561e+08 | J13: 4.9160208e+08 | K13: 4.9348786e+08 | L13: 4.9769982e+08
A14: 7.3 | B14: Allowance for loan losses | C14: 9972423.1 | D14: 9972423.1 | E14: 9972423.1 | F14: 11212944 | G14: 11212944 | H14: 11212944 | I14: 11817894 | J14: 12019544 | K14: 12221194 | L14: 12422844
... A19: 10 | B19: Total Expenses (FinCosts + OpEx) | C19: 22339455 | D19: 4546921.1 | E19: 5916993.1 | F19: 68345005 | G19: 18479434 | H19: 19450021 | I19: 21786998 | J19: 6653981.1 | K19: 12263359 | L19: 13807775
B21: CORE CAPITAL | C21: 94.944699 | D21: 75.269883 | E21: 78.35088 | F21: 88.729697 | G21: 155.78813 | H21: 163.40642 | I21: 167.00553 | J21: 111.20986 | K21: 113.8181 | L21: 123.1101
B22: CCA | C22: 0.20483458 | D22: 0.16493137 | E22: 0.17936092 | F22: 0.15034182 | G22: 0.25864938 | H22: 0.26092797 | I22: 0.2791395 | J22: 0.18878798 | K22: 0.18443982 | L22: 0.20376488
B23: ICA | C23: 0.18339309 | D23: 0.14315405 | E23: 0.15498853 | F23: 0.11102171 | G23: 0.21914952 | H23: 0.22288022 | I23: 0.23887701 | J23: 0.14777738 | K23: 0.14525951 | L23: 0.16341286
B24: CCD | C24: 0.26090139 | D24: 0.21334302 | E24: 0.22591234 | F24: 0.20476935 | G24: 0.3553599 | H24: 0.35976739 | I24: 0.35443835 | J24: 0.24016291 | K24: 0.23410757 | L24: 0.26405944
B25: Asset Quality
B26: NPL
B27: Earnings
B28: ROA | C28: 0.10366402 | D28: 0.0049791285 | E28: 0.0086990958 | F28: 0.021403287 | G28: 0.086521768 | H28: 0.092418745 | I28: 0.095308004 | J28: 0.025179366 | K28: 0.027427623 | L28: 0.036644694
B29: CIR | C29: 0.25741416 | D29: 0.47475461 | E29: 0.47309013 | F29: 0.59346691 | G29: 0.29062189 | H29: 0.28378981 | I29: 0.30491294 | J29: 0.3518848 | K29: 0.42614589 | L29: 0.38569897
B30: OER | C30: 0.050864587 | D30: 0.006821232 | E30: 0.012065152 | F30: 0.056671522 | G30: 0.054654004 | H30: 0.055574311 | I30: 0.067479629 | J30: 0.021463423 | K30: 0.030839954 | L30: 0.036261474
B31: MIN LIQ | C31: 0.28117848 | D31: 0.1804874 | E31: 0.14704211 | F31: 0.20525016 | G31: 0.26279967 | H31: 0.27638489 | I31: 0.26967942 | J31: 0.20183359 | K31: 0.21134839 | L31: 0.19694405
B32: TEC LIQ | C32: 0.18838483 | D32: 0.12915454 | E32: 0.10373806 | F32: 0.1770109 | G32: 0.2240215 | H32: 0.23200767 | I32: 0.21838892 | J32: 0.17267718 | K32: 0.17362602 | L32: 0.17125133
B33: EB | C33: 0.001688932 | D33: 0.0017153851 | E33: 0.0017921054 | F33: 0 | G33: 0 | H33: 0 | I33: 0 | J33: 0 | K33: 0 | L33: 0
B34: LIQ/TA | C34: 0.14978838 | D34: 0.10763133 | E34: 0.083528395 | F34: 0.14740407 | G34: 0.16450573 | H34: 0.16990382 | I34: 0.15588442 | J34: 0.13883827 | K34: 0.14041273 | L34: 0.13515776
B35: NEA | C35: 0.11800484 | D35: 0.12675515 | E35: 0.10067358 | F35: 0.053367462 | G35: 0.043302199 | H35: 0.058974292 | I35: 0.041797813 | J35: 0.039852185 | K35: 0.072852538 | L35: 0.054640365
B36: LB | C36: 0.01288188 | D36: 0.012663382 | E36: 0.013661078 | F36: 0.0051649463 | G36: 0.011631407 | H36: 0.01118682 | I36: 0.011457956 | J36: 0.010564849 | K36: 0.011089534 | L36: 0.010959528
B37: FITD | C37: 0.12176194 | D37: 0.11269646 | E37: 0.11464343 | F37: 0.0097586092 | G37: 0.0096455287 | H37: 0.0093098923 | I37: 0.0089743259 | J37: 0.009131763 | K37: 0.0086975334 | L37: 0.0090698477
B38: FICC | C38: 0.46669717 | D38: 0.52824067 | E38: 0.50746862 | F38: 0.047656592 | G38: 0.027142986 | H38: 0.025877532 | I38: 0.02531985 | J38: 0.038023203 | K38: 0.037151868 | L38: 0.03434775

Sheet DEC 2020
A1: MAGADI SACCO SOCIETY LIMITED
A2: PERFORMANCE AND COMPLIANCE REPORT AS AT : 31st December , 2020
B3: Prudential Standard | C3: Audited | D3: Returns | F3: AUDITED 2020 | G3: Aggregate for all Licensed Saccos
C4: 2019 | D4: 30th September , 2020 | E4: 31st December , 2020
A5: A. CAPITAL ADEQUACY
A6: Core Capital | B6: ≥10M | C6: =C33 -> 98409139 | D6: =D33 -> 1.5398554e+08 | E6: =E33 -> 1.7565742e+08 | F6: =F33 -> 103828792 | G6: =G33 -> 9.281382e+10 | H6: =F6-C6 -> 5419653
A7: Core Capital/Total Assets | B7: ≥10% | C7: =C33/C29 -> 0.149196 | D7: =D33/D29 -> 0.21974079 | E7: =E33/E29 -> 0.23992254 | F7: =F33/F29 -> 0.14250526 | G7: =G33/G29 -> 0.15852844
A8: Institutional Capital/Total Assets | B8: ≥8% | C8: =C34/C29 -> 0.11007419 | D8: =D34/D29 -> 0.18075965 | E8: =E34/E29 -> 0.2020382 | F8: =F34/F29 -> 0.10443654 | G8: =G34/G29 -> 0.092879022
A9: B. ASSET QUALITY
A10: NPL (Substandard+Doubtful+Loss) | B10: <5% | C10: =C35/C32 -> 0 | D10: =D35/D32 -> 0.066804616 | E10: =E35/E32 -> 0.058669004 | F10: =F35/F32 -> 0.058669005 | G10: =G35/G32 -> 0.081923116
A11: Non-Earning Assets | B11: <10% | C11: =C36/C29 -> 0.041460677 | D11: =D36/D29 -> 0.034504765 | E11: =E36/E29 -> 0.03147327 | F11: =F36/F29 -> 0.02634982 | G11: =G36/G29 -> 0.10331964
A12: Equity investments/Deposits | B12: <5% | C12: =C38/C31 -> 0.0086859989 | D12: =D38/D31 -> 0.007972688 | E12: =E38/E31 -> 0.0078282924 | F12: =F38/F31 -> 0.007831083 | G12: =G38/G31 -> 0.033894147
A13: Equity investments/Core capital | B13: <40% | C13: =C38/C33 -> 0.042969139 | D13: =D38/D33 -> 0.027460728 | E13: =E38/E33 -> 0.024072738 | F13: =F38/F33 -> 0.040726237 | G13: =G38/G33 -> 0.14648774
A14: C. EARNINGS RATING
A15: Yield on Gross Loans | C15: =C48/C32 -> 0.18432223 | D15: =D48/D32 -> 0.1292034 | E15: =E48/E32 -> 0.17383407 | F15: =F48/F32 -> 0.10774045 | G15: =G48/G32 -> 0.1744387
A16: Total Expense/Total Income | C16: =C49/C44 -> 0.81230275 | D16: =D49/D44 -> 0.33068826 | E16: =E49/E44 -> 0.33091343 | F16: =F49/F44 -> 0.90746078 | G16: =G49/G44 -> 0.69938821
A17: Net Income/Average Assets (ROA) | C17: =C50/C30 -> 0.02237977 | D17: =D50/D30 -> 0.081626281 | E17: =E50/E30 -> 0.10964544 | F17: =F50/F30 -> 0.011437945 | G17: =G50/G30 -> 0.038410442
A18: Operating Expenses/Financial Income (OPEX) | C18: =C47/C44 -> 0.32162796 | D18: =D47/D44 -> 0.28452022 | E18: =E47/E44 -> 0.28396284 | F18: =F47/F44 -> 0.29433774 | G18: =G47/G44 -> 0.30079837
A19: D. LIQUIDITY
A20: Liquid Assets/Short-term Liabilities | B20: >15% | C20: =C40/C41 -> 0.59313783 | D20: =D40/D41 -> 1.4178168 | E20: =E40/E41 -> 2.0006732 | F20: =F40/F41 -> 0.89067409 | G20: =G40/G41 -> 0.6151057
A21: External Borrowing/Total Assets | B21: <25% | C21: =C42/C29 -> 1.1611647e-05 | D21: =D42/D29 -> 0.011921445 | E21: =E42/E29 -> 0.010282182 | F21: =F42/F29 -> 0.010332224 | G21: =G42/G29 -> 0.036576677
A22: Liquid Assets/Total Assets | C22: =C40/C29 -> 0.067680721 | D22: =D40/D29 -> 0.12936886 | E22: =E40/E29 -> 0.15742859 | F22: =F40/F29 -> 0.1586045 | G22: =G40/G29 -> 0.11724056
A23: E. STRUCTURE/SENSITIVITY TO RISK
A24: Gross loans /Total Assets | B24: 70-80 | C24: =C32/C29 -> 0.82800207 | D24: =D32/D29 -> 0.86523081 | E24: =E32/E29 -> 0.83846194 | F24: =F32/F29 -> 0.84254266 | G24: =G32/G29 -> 0.75523899
A25: Gross loans/Deposits | B25: >100% | C25: =C32/C31 -> 1.1218567 | D25: =D32/D31 -> 1.1431784 | E25: =E32/E31 -> 1.1364592 | F25: =F32/F31 -> 1.1368641 | G25: =G32/G31 -> 1.1023021
A26: Financial Investments/Total Assets | C26: =C39/C31 -> 0.11977917 | D26: =D39/D31 -> 0.007972688 | E26: =E39/E31 -> 0.0078282924 | F26: =F39/F31 -> 0.007831083 | G26: =G39/G31 -> 0.067272667
A27: Dividends+Interest on Deposits/Total Income | C27: =C46/C44 -> 0.48412627 | D27: =D46/D44 -> 0.012481243 | E27: =E46/E44 -> 0.0115585 | F27: =F46/F44 -> 0.52777406 | G27: =G46/G44 -> 0.33833569
A28: F. KEY FINANCIAL STATISTICS | C28: 2015 | D28: 2016 | E28: 2017 | G28: AGGREGATE
A29: Total Assets | C29: 659596375 | D29: 7.0075991e+08 | E29: 7.321422e+08 | F29: =SFP!AS27 -> 7.2859619e+08 | G29: 5.8547109e+11
A30: Average Assets | C30: 6.2488266e+08 | D30: 6.6920187e+08 | E30: 6.9562445e+08 | F30: =(C29+F29)/2 -> 6.9409628e+08 | G30: 5.6966122e+11
A31: Total Deposits | C31: 486824375 | D31: 5.3038009e+08 | E31: 5.4016313e+08 | F31: =SFP!AS32 -> 539970780 | G31: 4.0113376e+11
A32: Gross Loans | C32: 546147164 | D32: 6.0631906e+08 | E32: 6.1387337e+08 | F32: =SFP!AS15 -> 613873373 | G32: 4.421706e+11
A33: Core Capital | C33: 98409139 | D33: 1.5398554e+08 | E33: 1.7565742e+08 | F33: =Financials!AT14 -> 103828792 | G33: 9.281382e+10
A34: Institutional Capital | C34: 72604536 | D34: 1.2666911e+08 | E34: 1.4792069e+08 | F34: =Financials!AT15 -> 76092066 | G34: 5.4377982e+10
A35: Non-performing Loans | C35: 0 | D35: 40504912 | E35: 36015340 | F35: =16172116+14580201+5263023 -> 36015340 | G35: 3.6223993e+10
A36: Non-Earning Assets | C36: 27347312 | D36: 24179556 | E36: 23042909 | F36: =Financials!AT38 -> 19198379 | G36: 6.0490663e+10
A37: Property and Equipment | C37: 5678927 | D37: 5703357.5 | E37: 5726554 | F37: =Financials!AT39 -> 3186216 | G37: 1.7300265e+10
A38: Equity Investments | C38: 4228556 | D38: 4228554.9 | E38: 4228554.9 | F38: =SFP!AS12+SFP!AS13 -> 4228556 | G38: 1.3596086e+10
A39: Financial Investments | C39: 58311419 | D39: 4228554.9 | E39: 4228554.9 | F39: =SFP!AS8 -> 4228556 | G39: 2.6985337e+10
A40: Liquid Assets | C40: 44641958 | D40: 90656514 | E40: 1.1526011e+08 | F40: =SFP!AS4+SFP!AS11 -> 115558634 | G40: 6.8640959e+10
A41: Short-term Liabilities) | C41: 75264054 | D41: 63940921 | E41: 57610665 | F41: =SFP!AS29+SFP!AS30+SFP!AS33-SFP!AS39 -> 129742894 | G41: 1.1159213e+11
A42: External Borrowing | C42: 7659 | D42: 8354071 | E42: 7528019 | F42: =SFP!AS39 -> 7528019 | G42: 2.1414587e+10
A43: Average Gross Loans | C43: 5.1241266e+08 | D43: 5.768587e+08 | E43: 5.7996732e+08 | F43: =(C32+E32)/2 -> 5.8001027e+08 | G43: 4.3131225e+11
A44: Total Income | C44: 119501967 | D44: 93225263 | E44: 1.2531687e+08 | F44: =SCI!AS3 -> 125316872 | G44: 8.9459919e+10
A45: Net Financial Income/Loss | C45: 60865365 | D45: 88921235 | E45: 1.1943317e+08 | F45: =SCI!AS19 -> 56057997 | G45: 5.3897612e+10
A46: Dividends+Interest on Deposits | C46: 57854041 | D46: 1163567.2 | E46: 1448475.1 | F46: =SCI!AS13 -> 66138994 | G46: 3.0267483e+10
A47: Operating Expenses | C47: 38435174 | D47: 26524472 | E47: 35585335 | F47: =SCI!AS23 -> 36885485 | G47: 2.6909398e+10
A48: Interest on Loan portfolio+Fees&Commission on Loan | C48: 100667063 | D48: 78338482 | E48: 1.0671211e+08 | F48: =SCI!AS13+SCI!AS15 -> 66138994 | G48: 7.7131665e+10
A49: Total Expenses | C49: 97071776 | D49: 30828500 | E49: 41469037 | F49: =SCI!AS12+SCI!AS20+SCI!AS23 -> 113720146 | G49: 6.2567213e+10
A50: Net Income | C50: 13984730 | D50: 54624460 | E50: 76272050 | F50: =SCI!AS37 -> 7939035 | G50: 2.1880939e+10
A51: G. AREAS OF IMPROVEMENT/REGULATORY CONCERNS
A52: 1
A53: 2
A54: 3
A55: 4
A56: Prepared by:
A58: Checked by:
A60: Approved by:
A62: DISCLAIMER: This report is prepared based on information submitted by the Sacco as at the stated date and may change upon verification by the Authority.

Sheet DEC 2019 REPORT
A1: EGERTON SACCO SOCIETY LIMITED
A2: PERFORMANCE AND COMPLIANCE REPORT AS AT : 31st December , 2019
B3: Prudential Standard | C3: Audited | D3: Returns | F3: Audited 2019 | G3: Aggregate for all Licensed Saccos
C4: 2018 | D4: 30th September , 2019 | E4: 31st December , 2019
A5: A. CAPITAL ADEQUACY
A6: Core Capital | B6: ≥10M | C6: 92958252 | D6: 1.14416e+08 | E6: 1.2704881e+08 | F6: =F33 -> 102637695 | G6: 8.5391581e+10
A7: Core Capital/Total Assets | B7: ≥10% | C7: 0.15751126 | D7: 0.17943559 | E7: 0.19275909 | F7: =F6/F29 -> 0.15560682 | G7: 0.15597716
A8: Institutional Capital/Total Assets | B8: ≥8% | C8: 0.11818998 | D8: 0.13976271 | E8: 0.15360974 | F8: =F34/F29 -> 0.11648501 | G8: 0.091529477
A9: B. ASSET QUALITY
A10: NPL (Substandard+Doubtful+Loss) | B10: <5% | C10: 0 | D10: 0.057997794 | E10: 0.049062417 | F10: =F35/F32 -> 0.049054699 | G10: 0.073407957
A11: Non-Earning Assets | B11: <10% | C11: 0.05336904 | D11: 0.043135899 | E11: 0.041315651 | F11: =F36/F29 -> 0.041460677 | G11: 0.10567687
A12: Equity investments/Deposits | B12: <5% | C12: 0 | D12: 0.0086297878 | E12: 0.0086830722 | F12: =F38/F31 -> 0.0086859989 | G12: 0.034924323
A13: Equity investments/Core capital | B13: <40% | C13: 0 | D13: 0.036957724 | E13: 0.033282917 | F13: =F38/F33 -> 0.04119886 | G13: 0.15379721
A14: C. EARNINGS RATING
A15: Yield on Gross Loans | C15: 0.1927038 | D15: 0.13877868 | E15: 0.18737466 | F15: =F48/F32 -> 0.18432223 | G15: 0.16090341
A16: Total Expense/Total Income | C16: 0.79311986 | D16: 0.35836605 | E16: 0.33974951 | F16: =F49/F44 -> 0.81230275 | G16: 0.7077997
A17: Net Income/Average Assets (ROA) | C17: 0.027977038 | D17: 0.081818348 | E17: 0.11400955 | F17: =F50/F30 -> 0.02237977 | G17: 0.036975972
A18: Operating Expenses/Financial Income (OPEX) | C18: 0.30200757 | D18: 0.31934513 | E18: 0.30463818 | F18: =F47/F45 -> 0.63147858 | G18: 0.31992697
A19: D. LIQUIDITY
A20: Liquid Assets/Short-term Liabilities | B20: >15% | C20: 1.1755674 | D20: 1.0116662 | E20: 1.4570234 | F20: =F40/F41 -> 0.33907431 | G20: 0.54995224
A21: External Borrowing/Total Assets | B21: <25% | C21: 0 | D21: 0 | E21: 0 | F21: =F42/F29 -> 1.1611647e-05 | G21: 0.039238045
A22: Liquid Assets/Total Assets | C22: 0.14737887 | D22: 0.12043218 | E22: 0.149349 | F22: =F40/F29 -> 0.067680721 | G22: 0.11016896
A23: E. STRUCTURE/SENSITIVITY TO RISK
A24: Gross loans /Total Assets | B24: 70-80 | C24: 0.81108665 | D24: 0.85847035 | E24: 0.82848691 | F24: =F32/F29 -> 0.82800207 | G24: 0.75892188
A25: Gross loans/Deposits | B25: >100% | C25: 1.1046878 | D25: 1.1171503 | E25: 1.1213025 | F25: =F32/F31 -> 1.1218567 | G25: 1.1048812
A26: Financial Investments/Total Assets | C26: 0.0097586092 | D26: 0.0086297878 | E26: 0.0086830722 | F26: =F39/F29 -> 0.088404699 | G26: 0.059782935
A27: Dividends+Interest on Deposits/Total Income | C27: 0.48814819 | D27: 0.012035001 | E27: 0.012230217 | F27: =F46/F44 -> 0.48412627 | G27: 0.32108527
A28: F. KEY FINANCIAL STATISTICS | C28: 2015 | D28: 2016 | E28: 2017 | G28: AGGREGATE
A29: Total Assets | C29: 590168948 | D29: 6.3764384e+08 | E29: 6.5910669e+08 | F29: =SFP!AF27 -> 659596375 | G29: 5.4746207e+11
A30: Average Assets | C30: 5.6413338e+08 | D30: 6.1492399e+08 | E30: 6.4176168e+08 | F30: =(F29+C29)/2 -> 6.2488266e+08 | G30: 5.2079291e+11
A31: Total Deposits | C31: 433315333 | D31: 4.8999524e+08 | E31: 4.8698834e+08 | F31: =SFP!AF32 -> 486824375 | G31: 3.7604128e+11
A32: Gross Loans | C32: 478678153 | D32: 5.4739833e+08 | E32: 5.4606127e+08 | F32: =SFP!AF15 -> 546147164 | G32: 4.1548094e+11
A33: Core Capital | C33: 92958252 | D33: 1.14416e+08 | E33: 1.2704881e+08 | F33: =Financials!AG14 -> 102637695 | G33: 8.5391581e+10
A34: Institutional Capital | C34: 69752057 | D34: 89118833 | E34: 1.0124521e+08 | F34: =Financials!AG15 -> 76833092 | G34: 5.0108917e+10
A35: Non-performing Loans | C35: 0 | D35: 31747895 | E35: 26791086 | F35: =22604726+734025+3452334 -> 26791085 | G35: 3.0499607e+10
A36: Non-Earning Assets | C36: 31496750 | D36: 27505341 | E36: 27231422 | F36: =Financials!AG38 -> 27347312 | G36: 5.7854076e+10
A37: Property and Equipment | C37: 7005759 | D37: 5982262.2 | E37: 5325780.8 | F37: =Financials!AG39 -> 2426053 | G37: 1.7751024e+10
A38: Equity Investments | C38: 0 | D38: 4228554.9 | E38: 4228554.9 | F38: =SFP!AF13+SFP!AF12 -> 4228556 | G38: 1.3132987e+10
A39: Financial Investments | C39: 4228555 | D39: 4228554.9 | E39: 4228554.9 | F39: =SFP!AF8 -> 58311419 | G39: 2.2480852e+10
A40: Liquid Assets | C40: 86978434 | D40: 76792836 | E40: 98436927 | F40: =SFP!AF4 -> 44641958 | G40: 6.031333e+10
A41: Short-term Liabilities) | C41: 73988469 | D41: 75907286 | E41: 67560292 | F41: =SFP!AF29+SFP!AF30+SFP!AF33-SFP!AF39 -> 131658333 | G41: 1.0967012e+11
A42: External Borrowing | C42: 0 | D42: 0 | E42: 0 | F42: =SFP!AF39 -> 7659 | G42: 2.1481341e+10
A43: Average Gross Loans | C43: 445483841 | D43: 5.0462708e+08 | E43: 5.1208838e+08 | F43: =(C32+F32)/2 -> 5.1241266e+08 | G43: 3.9339201e+11
A44: Total Income | C44: 110748089 | D44: 89428467 | E44: 1.1935697e+08 | F44: =SCI!AF3 -> 119501967 | G44: 7.9322865e+10
A45: Net Financial Income/Loss | C45: 56358341 | D45: 85938886 | E45: 1.1516619e+08 | F45: =SCI!AF19 -> 60865365 | G45: 4.6800236e+10
A46: Dividends+Interest on Deposits | C46: 54061479 | D46: 1076271.7 | E46: 1459761.6 | F46: =SCI!AF13 -> 57854041 | G46: 2.5469404e+10
A47: Operating Expenses | C47: 33446761 | D47: 28558545 | E47: 36360690 | F47: =SCI!AF23 -> 38435174 | G47: 2.5377524e+10
A48: Interest on Loan portfolio+Fees&Commission on Loan | C48: 92243098 | D48: 75967218 | E48: 1.0231804e+08 | F48: =SCI!AF4 -> 100667063 | G48: 6.6852299e+10
A49: Total Expenses | C49: 87836509 | D49: 32048126 | E49: 40551471 | F49: =SCI!AF12+SCI!AF23 -> 97071776 | G49: 5.61447e+10
A50: Net Income | C50: 15782781 | D50: 50312065 | E50: 73166962 | F50: =SCI!AF37 -> 13984730 | G50: 1.9256824e+10
A51: G. AREAS OF IMPROVEMENT/REGULATORY CONCERNS
A52: 1
A53: 2
A54: 3
A55: 4
A56: Prepared by:
A58: Checked by: Nelly Kulei
A60: Approved by: Peter Owira
A62: DISCLAIMER: This report is prepared based on information submitted by the Sacco as at the stated date and may change upon verification by the Authority.
C63: 22nd January 2020
