Workbook
Name BALANCE1_LDA01: '[1]Financial Statements'!$E$112
Name BALANCE1_LDA12: '[1]Financial Statements'!$E$123
Name BALANCE2_LDA01: '[1]Financial Statements'!$F$112
Name BALANCE2_LDA12: '[1]Financial Statements'!$F$123
Name BALANCE3_LDA01: '[1]Financial Statements'!$G$112
Name BALANCE3_LDA12: '[1]Financial Statements'!$G$123
Name BALANCE4_LDA01: '[1]Financial Statements'!$H$112
Name BALANCE4_LDA12: '[1]Financial Statements'!$H$123
Name BALANCE5_LDA01: '[1]Financial Statements'!$I$112
Name BALANCE5_LDA12: '[1]Financial Statements'!$I$123
Name BALANCE6_LDA01: '[1]Financial Statements'!$J$112
Name BALANCE6_LDA12: '[1]Financial Statements'!$J$123
Name NotApplicable: 'Prudential Ratios'!$B$76
Name PEARLS1_LA002: '[1]Financial Statements'!$E$280
Name PEARLS1_LE008: '[1]Financial Statements'!$E$275
Name PEARLS1_LE009: '[1]Financial Statements'!$E$276
Name PEARLS1_LR001: '[1]Financial Statements'!$E$282
Name PEARLS1_LR005: '[1]Financial Statements'!$E$286
Name PEARLS1_LR006: '[1]Financial Statements'!$E$287
Name PEARLS1_LR007: '[1]Financial Statements'!$E$288
Name PEARLS1_LR009: '[1]Financial Statements'!$E$290
Name PEARLS1_LS001: '[1]Financial Statements'!$E$298
Name PEARLS1_LS005: '[1]Financial Statements'!$E$302
Name PEARLS1_LS011: '[1]Financial Statements'!$E$308
Name PEARLS2_LA002: '[1]Financial Statements'!$F$280
Name PEARLS2_LE008: '[1]Financial Statements'!$F$275
Name PEARLS2_LE009: '[1]Financial Statements'!$F$276
Name PEARLS2_LR001: '[1]Financial Statements'!$F$282
Name PEARLS2_LR005: '[1]Financial Statements'!$F$286
Name PEARLS2_LR006: '[1]Financial Statements'!$F$287
Name PEARLS2_LR007: '[1]Financial Statements'!$F$288
Name PEARLS2_LR009: '[1]Financial Statements'!$F$290
Name PEARLS2_LS001: '[1]Financial Statements'!$F$298
Name PEARLS2_LS005: '[1]Financial Statements'!$F$302
Name PEARLS2_LS010: '[1]Financial Statements'!$F$307
Name PEARLS2_LS011: '[1]Financial Statements'!$F$308
Name PEARLS3_LA002: '[1]Financial Statements'!$G$280
Name PEARLS3_LE008: '[1]Financial Statements'!$G$275
Name PEARLS3_LE009: '[1]Financial Statements'!$G$276
Name PEARLS3_LR001: '[1]Financial Statements'!$G$282
Name PEARLS3_LR005: '[1]Financial Statements'!$G$286
Name PEARLS3_LR006: '[1]Financial Statements'!$G$287
Name PEARLS3_LR007: '[1]Financial Statements'!$G$288
Name PEARLS3_LR009: '[1]Financial Statements'!$G$290
Name PEARLS3_LS001: '[1]Financial Statements'!$G$298
Name PEARLS3_LS005: '[1]Financial Statements'!$G$302
Name PEARLS3_LS010: '[1]Financial Statements'!$G$307
Name PEARLS3_LS011: '[1]Financial Statements'!$G$308
Name PEARLS4_LA002: '[1]Financial Statements'!$H$280
Name PEARLS4_LE008: '[1]Financial Statements'!$H$275
Name PEARLS4_LE009: '[1]Financial Statements'!$H$276
Name PEARLS4_LR001: '[1]Financial Statements'!$H$282
Name PEARLS4_LR005: '[1]Financial Statements'!$H$286
Name PEARLS4_LR006: '[1]Financial Statements'!$H$287
Name PEARLS4_LR007: '[1]Financial Statements'!$H$288
Name PEARLS4_LR009: '[1]Financial Statements'!$H$290
Name PEARLS4_LS001: '[1]Financial Statements'!$H$298
Name PEARLS4_LS005: '[1]Financial Statements'!$H$302
Name PEARLS4_LS010: '[1]Financial Statements'!$H$307
Name PEARLS4_LS011: '[1]Financial Statements'!$H$308

Sheet compliance status
B2: audited2017 | C2: 43101 | D2: 43133 | E2: 43165 | F2: 43197 | G2: 43229 | H2: 43261 | I2: 43293 | J2: 43325 | K2: 43357 | L2: 43389 | M2: 43421 | N2: 43453
A3: CORE CAPITAL | B3: =IF('Prudential Ratios'!#REF!>10,"compliant","not compliant") -> #REF! | C3: =IF('Prudential Ratios'!#REF!>10,"compliant","not compliant") -> #REF! | D3: =IF('Prudential Ratios'!#REF!>10,"compliant","not compliant") -> #REF! | E3: =IF('Prudential Ratios'!#REF!>10,"compliant","not compliant") -> #REF! | F3: =IF('Prudential Ratios'!#REF!>10,"compliant","not compliant") -> #REF! | G3: =IF('Prudential Ratios'!#REF!>10,"compliant","not compliant") -> #REF! | H3: =IF('Prudential Ratios'!#REF!>10,"compliant","not compliant") -> #REF! | I3: =IF('Prudential Ratios'!#REF!>10,"compliant","not compliant") -> #REF! | ... N3: =IF('Prudential Ratios'!#REF!>10,"compliant","not compliant") -> #REF!
A4: CCA (Min 10%) | B4: =IF('Prudential Ratios'!#REF!>10%,"compliant","not compliant") -> #REF! | C4: =IF('Prudential Ratios'!#REF!>10%,"compliant","not compliant") -> #REF! | D4: =IF('Prudential Ratios'!#REF!>10%,"compliant","not compliant") -> #REF! | E4: =IF('Prudential Ratios'!#REF!>10%,"compliant","not compliant") -> #REF! | F4: =IF('Prudential Ratios'!#REF!>10%,"compliant","not compliant") -> #REF! | G4: =IF('Prudential Ratios'!#REF!>10%,"compliant","not compliant") -> #REF! | H4: =IF('Prudential Ratios'!#REF!>10%,"compliant","not compliant") -> #REF! | I4: =IF('Prudential Ratios'!#REF!>10%,"compliant","not compliant") -> #REF! | ... N4: =IF('Prudential Ratios'!#REF!>10%,"compliant","not compliant") -> #REF!
A5: ICA (Min 8%) | B5: =IF('Prudential Ratios'!#REF!>8%,"compliant","not compliant") -> #REF! | C5: =IF('Prudential Ratios'!#REF!>8%,"compliant","not compliant") -> #REF! | D5: =IF('Prudential Ratios'!#REF!>8%,"compliant","not compliant") -> #REF! | E5: =IF('Prudential Ratios'!#REF!>8%,"compliant","not compliant") -> #REF! | F5: =IF('Prudential Ratios'!#REF!>8%,"compliant","not compliant") -> #REF! | G5: =IF('Prudential Ratios'!#REF!>8%,"compliant","not compliant") -> #REF! | H5: =IF('Prudential Ratios'!#REF!>8%,"compliant","not compliant") -> #REF! | I5: =IF('Prudential Ratios'!#REF!>8%,"compliant","not compliant") -> #REF! | ... N5: =IF('Prudential Ratios'!#REF!>8%,"compliant","not compliant") -> #REF!
A6: CCD (Min 8%) | B6: =IF('Prudential Ratios'!#REF!>8%,"compliant","not compliant") -> #REF! | C6: =IF('Prudential Ratios'!#REF!>8%,"compliant","not compliant") -> #REF! | D6: =IF('Prudential Ratios'!#REF!>8%,"compliant","not compliant") -> #REF! | E6: =IF('Prudential Ratios'!#REF!>8%,"compliant","not compliant") -> #REF! | F6: =IF('Prudential Ratios'!#REF!>8%,"compliant","not compliant") -> #REF! | G6: =IF('Prudential Ratios'!#REF!>8%,"compliant","not compliant") -> #REF! | H6: =IF('Prudential Ratios'!#REF!>8%,"compliant","not compliant") -> #REF! | I6: =IF('Prudential Ratios'!#REF!>8%,"compliant","not compliant") -> #REF! | ... N6: =IF('Prudential Ratios'!#REF!>8%,"compliant","not compliant") -> #REF!
A7: NPL(5%)
A8: Liquidity(15%) | B8: =IF('Prudential Ratios'!#REF!>15%,"compliant","not compliant") -> #REF! | C8: =IF('Prudential Ratios'!#REF!>15%,"compliant","not compliant") -> #REF! | D8: =IF('Prudential Ratios'!#REF!>15%,"compliant","not compliant") -> #REF! | E8: =IF('Prudential Ratios'!#REF!>15%,"compliant","not compliant") -> #REF! | F8: =IF('Prudential Ratios'!#REF!>15%,"compliant","not compliant") -> #REF! | G8: =IF('Prudential Ratios'!#REF!>15%,"compliant","not compliant") -> #REF! | H8: =IF('Prudential Ratios'!#REF!>15%,"compliant","not compliant") -> #REF! | I8: =IF('Prudential Ratios'!#REF!>15%,"compliant","not compliant") -> #REF! | ... N8: =IF('Prudential Ratios'!#REF!>15%,"compliant","not compliant") -> #REF!
A9: NEA (Max 10%) | B9: =IF('Prudential Ratios'!#REF!<10%,"compliant","not compliant") -> #REF! | C9: =IF('Prudential Ratios'!#REF!<10%,"compliant","not compliant") -> #REF! | D9: =IF('Prudential Ratios'!#REF!<10%,"compliant","not compliant") -> #REF! | E9: =IF('Prudential Ratios'!#REF!<10%,"compliant","not compliant") -> #REF! | F9: =IF('Prudential Ratios'!#REF!<10%,"compliant","not compliant") -> #REF! | G9: =IF('Prudential Ratios'!#REF!<10%,"compliant","not compliant") -> #REF! | H9: =IF('Prudential Ratios'!#REF!<10%,"compliant","not compliant") -> #REF! | I9: =IF('Prudential Ratios'!#REF!<10%,"compliant","not compliant") -> #REF! | ... N9: =IF('Prudential Ratios'!#REF!<10%,"compliant","not compliant") -> #REF!
A10: LB ratio (Max 5%) | B10: =IF('Prudential Ratios'!#REF!<5%,"compliant","not compliant") -> #REF! | C10: =IF('Prudential Ratios'!#REF!<5%,"compliant","not compliant") -> #REF! | D10: =IF('Prudential Ratios'!#REF!<5%,"compliant","not compliant") -> #REF! | E10: =IF('Prudential Ratios'!#REF!<5%,"compliant","not compliant") -> #REF! | F10: =IF('Prudential Ratios'!#REF!<5%,"compliant","not compliant") -> #REF! | G10: =IF('Prudential Ratios'!#REF!<5%,"compliant","not compliant") -> #REF! | H10: =IF('Prudential Ratios'!#REF!<5%,"compliant","not compliant") -> #REF! | I10: =IF('Prudential Ratios'!#REF!<5%,"compliant","not compliant") -> #REF! | ... N10: =IF('Prudential Ratios'!#REF!<5%,"compliant","not compliant") -> #REF!
A11: FITD (Max 5%) | B11: =IF('Prudential Ratios'!#REF!<5%,"compliant","not compliant") -> #REF! | C11: =IF('Prudential Ratios'!#REF!<5%,"compliant","not compliant") -> #REF! | D11: =IF('Prudential Ratios'!#REF!<5%,"compliant","not compliant") -> #REF! | E11: =IF('Prudential Ratios'!#REF!<5%,"compliant","not compliant") -> #REF! | F11: =IF('Prudential Ratios'!#REF!<5%,"compliant","not compliant") -> #REF! | G11: =IF('Prudential Ratios'!#REF!<5%,"compliant","not compliant") -> #REF! | H11: =IF('Prudential Ratios'!#REF!<5%,"compliant","not compliant") -> #REF! | I11: =IF('Prudential Ratios'!#REF!<5%,"compliant","not compliant") -> #REF! | ... N11: =IF('Prudential Ratios'!#REF!<5%,"compliant","not compliant") -> #REF!
A12: FICC (Max 40%) | B12: =IF('Prudential Ratios'!#REF!<40%,"compliant","not compliant") -> #REF! | C12: =IF('Prudential Ratios'!#REF!<40%,"compliant","not compliant") -> #REF! | D12: =IF('Prudential Ratios'!#REF!<40%,"compliant","not compliant") -> #REF! | E12: =IF('Prudential Ratios'!#REF!<40%,"compliant","not compliant") -> #REF! | F12: =IF('Prudential Ratios'!#REF!<40%,"compliant","not compliant") -> #REF! | G12: =IF('Prudential Ratios'!#REF!<40%,"compliant","not compliant") -> #REF! | H12: =IF('Prudential Ratios'!#REF!<40%,"compliant","not compliant") -> #REF! | I12: =IF('Prudential Ratios'!#REF!<40%,"compliant","not compliant") -> #REF! | ... N12: =IF('Prudential Ratios'!#REF!<40%,"compliant","not compliant") -> #REF!
A13: EB ratio | B13: =IF('Prudential Ratios'!#REF!<25%,"compliant","not compliant") -> #REF! | C13: =IF('Prudential Ratios'!#REF!<25%,"compliant","not compliant") -> #REF! | D13: =IF('Prudential Ratios'!#REF!<25%,"compliant","not compliant") -> #REF! | E13: =IF('Prudential Ratios'!#REF!<25%,"compliant","not compliant") -> #REF! | F13: =IF('Prudential Ratios'!#REF!<25%,"compliant","not compliant") -> #REF! | G13: =IF('Prudential Ratios'!#REF!<25%,"compliant","not compliant") -> #REF! | H13: =IF('Prudential Ratios'!#REF!<25%,"compliant","not compliant") -> #REF! | I13: =IF('Prudential Ratios'!#REF!<25%,"compliant","not compliant") -> #REF! | ... N13: =IF('Prudential Ratios'!#REF!<25%,"compliant","not compliant") -> #REF!
A14: A=S+L | B14: =IF(SFP!#REF!=SFP!#REF!,"balancing","notbalancing") -> #REF! | C14: =IF(SFP!#REF!=SFP!#REF!,"balancing","notbalancing") -> #REF! | D14: =IF(SFP!#REF!=SFP!#REF!,"balancing","notbalancing") -> #REF! | E14: =IF(SFP!#REF!=SFP!#REF!,"balancing","notbalancing") -> #REF! | F14: =IF(SFP!#REF!=SFP!#REF!,"balancing","notbalancing") -> #REF! | G14: =IF(SFP!#REF!=SFP!#REF!,"balancing","notbalancing") -> #REF! | H14: =IF(SFP!#REF!=SFP!#REF!,"balancing","notbalancing") -> #REF! | I14: =IF(SFP!#REF!=SFP!#REF!,"balancing","notbalancing") -> #REF! | ... N14: =IF(SFP!#REF!=SFP!#REF!,"balancing","notbalancing") -> #REF!

Sheet Prudential Ratios
C1: HOMEBUSINESS SACCO SOCIETY LTD
C2: Sacco Financial Performance
C4: FINANCIAL SOUNDNESS INDICATORS | D4: Prude. Std | E4: Audited 2021 | F4: 44562 | G4: 44593 | H4: 44621 | I4: 44652 | J4: 44682 | K4: 44713 | L4: 44743 | M4: 44774 | N4: 44805 | O4: 44835 | P4: 44866 | Q4: 44896 | R4: Audited-2022 | S4: 44949 | T4: 44980 | U4: 45008 | V4: 45039 | W4: 45069 | X4: 45100 | Y4: 45130
B5: 1 | C5: CAPITAL ADEQUACY REQUIREMENTS
B6: 1.1 | C6: Core capital | D6: ≥ Ksh.10M | E6: =Financials!C14/1000000 -> 46.626056 | F6: =Financials!D14/1000000 -> 63.929101 | G6: =Financials!E14/1000000 -> 65.146114 | H6: =Financials!F14/1000000 -> 52.153999 | I6: =Financials!G14/1000000 -> 53.911683 | J6: =Financials!H14/1000000 -> 53.323831 | K6: =Financials!I14/1000000 -> 55.640039 | L6: =Financials!J14/1000000 -> 56.828389 | ... X6: =Financials!V14/1000000 -> 65.57352
B7: 1.2 | C7: Core capital /Total Assets | D7: ≥ 10% | E7: =Financials!C14/Financials!C5 -> 0.18639784 | F7: =Financials!D14/Financials!D5 -> 0.2444031 | G7: =Financials!E14/Financials!E5 -> 0.24421658 | H7: =Financials!F14/Financials!F5 -> 0.19655486 | I7: =Financials!G14/Financials!G5 -> 0.20646389 | J7: =Financials!H14/Financials!H5 -> 0.20394332 | K7: =Financials!I14/Financials!I5 -> 0.2099938 | L7: =Financials!J14/Financials!J5 -> 0.20989705 | ... X7: =Financials!V14/Financials!V5 -> 0.21625586
B8: 1.3 | C8: Core capital /Total Deposits | D8: ≥ 8% | E8: =Financials!C14/Financials!C6 -> 0.26000906 | F8: =Financials!D14/Financials!D6 -> 0.35074836 | G8: =Financials!E14/Financials!E6 -> 0.34877931 | H8: =Financials!F14/Financials!F6 -> 0.26245345 | I8: =Financials!G14/Financials!G6 -> 0.27833959 | J8: =Financials!H14/Financials!H6 -> 0.27362077 | K8: =Financials!I14/Financials!I6 -> 0.28290224 | L8: =Financials!J14/Financials!J6 -> 0.28430475 | ... X8: =Financials!V14/Financials!V6 -> 0.30906423
B9: 1.4 | C9: Share Capital/Total Assets | D9: ≤2% | E9: =Financials!C18/Financials!C5 -> 0.12888265 | F9: =Financials!D18/Financials!D5 -> 0.12442833 | G9: =Financials!E18/Financials!E5 -> 0.12248038 | H9: =Financials!F18/Financials!F5 -> 0.12345724 | I9: =Financials!G18/Financials!G5 -> 0.12629106 | J9: =Financials!H18/Financials!H5 -> 0.12646556 | K9: =Financials!I18/Financials!I5 -> 0.12498927 | L9: =Financials!J18/Financials!J5 -> 0.12252382 | ... X9: =Financials!V18/Financials!V5 -> 0.13064996
B10: 1.5 | C10: Institutional Capital/Total Assets | D10: ≥ 8% | E10: =Financials!C15/Financials!C5 -> 0.057515195 | F10: =Financials!D15/Financials!D5 -> 0.11997477 | G10: =Financials!E15/Financials!E5 -> 0.1217362 | H10: =Financials!F15/Financials!F5 -> 0.073097615 | I10: =Financials!G15/Financials!G5 -> 0.080172831 | J10: =Financials!H15/Financials!H5 -> 0.077477769 | K10: =Financials!I15/Financials!I5 -> 0.08500453 | L10: =Financials!J15/Financials!J5 -> 0.087373233 | ... X10: =Financials!V15/Financials!V5 -> 0.085605891
B12: 2 | C12: ASSET MIX AND QUALITY
B13: 2.1 | C13: Non Earning Assets
B14: 2.1.1 | C14: Non earning Assets/Total assets | D14: ≤ 10% | E14: =Financials!C38/Financials!C5 -> 0.18803085 | F14: =Financials!D38/Financials!D5 -> 0.18341397 | G14: =Financials!E38/Financials!E5 -> 0.18015585 | H14: =Financials!F38/Financials!F5 -> 0.17464009 | I14: =Financials!G38/Financials!G5 -> 0.17906607 | J14: =Financials!H38/Financials!H5 -> 0.17913743 | K14: =Financials!I38/Financials!I5 -> 0.17867375 | L14: =Financials!J38/Financials!J5 -> 0.17869914 | ... X14: =Financials!V38/Financials!V5 -> 0.16062916
B15: 2.1.2 | C15: Property and Equipment/Total Assets | D15: ≤ 5% | E15: =Financials!C39/Financials!C5 -> 0.13579339 | F15: =Financials!D39/Financials!D5 -> 0.13142559 | G15: =Financials!E39/Financials!E5 -> 0.12948894 | H15: =Financials!F39/Financials!F5 -> 0.13021326 | I15: =Financials!G39/Financials!G5 -> 0.13345626 | J15: =Financials!H39/Financials!H5 -> 0.13392534 | K15: =Financials!I39/Financials!I5 -> 0.13229968 | L15: =Financials!J39/Financials!J5 -> 0.129691 | ... X15: =Financials!V39/Financials!V5 -> 0.12011921
B16: 2.1.3 | C16: Non Performing loans/Gross Loans | D16: ≤ 6%
B18: 2.2 | C18: Earning Assets
B19: 2.2.1 | C19: Equities & Investments/Deposits | D19: ≤ 5% | E19: =Financials!C26/Financials!C6 -> 6.0002877e-05 | F19: =Financials!D26/Financials!D6 -> 5.9034967e-05 | G19: =Financials!E26/Financials!E6 -> 5.7606896e-05 | H19: =Financials!F26/Financials!F6 -> 5.4147316e-05 | I19: =Financials!G26/Financials!G6 -> 5.5552596e-05 | J19: =Financials!H26/Financials!H6 -> 5.5212827e-05 | K19: =Financials!I26/Financials!I6 -> 5.4709308e-05 | L19: =Financials!J26/Financials!J6 -> 5.3830826e-05 | ... X19: =Financials!V26/Financials!V6 -> 5.0714543e-05
B20: 2.2.2 | C20: Equities & Investments/Core Capital | D20: ≤ 40% | E20: =Financials!C26/Financials!C14 -> 0.00023077225 | F20: =Financials!D26/Financials!D14 -> 0.00016831145 | G20: =Financials!E26/Financials!E14 -> 0.00016516718 | H20: =Financials!F26/Financials!F14 -> 0.00020631208 | I20: =Financials!G26/Financials!G14 -> 0.00019958568 | J20: =Financials!H26/Financials!H14 -> 0.00020178595 | K20: =Financials!I26/Financials!I14 -> 0.00019338592 | L20: =Financials!J26/Financials!J14 -> 0.00018934199 | ... X20: =Financials!V26/Financials!V14 -> 0.00016409063
B21: 2.2.3 | C21: Net Loans & advances /Total assets | D21: NPR | E21: =Financials!C31/Financials!C5 -> 0.68373861 | F21: =Financials!D31/Financials!D5 -> 0.68307191 | G21: =Financials!E31/Financials!E5 -> 0.66485886 | H21: =Financials!F31/Financials!F5 -> 0.65686173 | I21: =Financials!G31/Financials!G5 -> 0.65933323 | J21: =Financials!H31/Financials!H5 -> 0.6765483 | K21: =Financials!I31/Financials!I5 -> 0.706967 | L21: =Financials!J31/Financials!J5 -> 0.70402944 | ... X21: =Financials!V31/Financials!V5 -> 0.76635572
B23: 3 | C23: FUNDING MIX
B24: 3.1 | C24: Total Deposits/Total Assets | D24: NPR | E24: =Financials!C6/Financials!C5 -> 0.71688979 | F24: =Financials!D6/Financials!D5 -> 0.69680469 | G24: =Financials!E6/Financials!E5 -> 0.70020374 | H24: =Financials!F6/Financials!F5 -> 0.74891324 | I24: =Financials!G6/Financials!G5 -> 0.74176976 | J24: =Financials!H6/Financials!H5 -> 0.74535032 | K24: =Financials!I6/Financials!I5 -> 0.74228399 | L24: =Financials!J6/Financials!J5 -> 0.73828189 | ... X24: =Financials!V6/Financials!V5 -> 0.6997117
B25: 3.1.1 | C25: BOSA Deposits/Total Assets | D25: NPR | E25: =Financials!C7/Financials!C5 -> 0.64043002 | F25: =Financials!D7/Financials!D5 -> 0.65140261 | G25: =Financials!E7/Financials!E5 -> 0.65006797 | H25: =Financials!F7/Financials!F5 -> 0.66006716 | I25: =Financials!G7/Financials!G5 -> 0.68066203 | J25: =Financials!H7/Financials!H5 -> 0.68989667 | K25: =Financials!I7/Financials!I5 -> 0.68663786 | L25: =Financials!J7/Financials!J5 -> 0.6822771 | ... X25: =Financials!V7/Financials!V5 -> 0.63328271
B26: 3.1.2 | C26: FOSA Deposits/Total Assets | D26: NPR | E26: =Financials!C8/Financials!C5 -> 0.041258365 | F26: =Financials!D8/Financials!D5 -> 0.041836945 | G26: =Financials!E8/Financials!E5 -> 0.045885391 | H26: =Financials!F8/Financials!F5 -> 0.084274991 | I26: =Financials!G8/Financials!G5 -> 0.057358584 | J26: =Financials!H8/Financials!H5 -> 0.051501449 | K26: =Financials!I8/Financials!I5 -> 0.052494655 | L26: =Financials!J8/Financials!J5 -> 0.052876786 | ... X26: =Financials!V8/Financials!V5 -> 0.063486479
B27: 3.2 | C27: External Borrowing/Total assets | D27: ≤ 25% | E27: =Financials!C9/Financials!C5 -> 0.017490018 | F27: =Financials!D9/Financials!D5 -> 0.014336376 | G27: =Financials!E9/Financials!E5 -> 0.011714848 | H27: =Financials!F9/Financials!F5 -> 0.0094218499 | I27: =Financials!G9/Financials!G5 -> 0.0071806289 | J27: =Financials!H9/Financials!H5 -> 0.0047807735 | K27: =Financials!I9/Financials!I5 -> 0.0023588431 | L27: =Financials!J9/Financials!J5 -> 0 | ... X27: =Financials!V9/Financials!V5 -> 0.026399804
B29: 4 | C29: GROWTH RATIOS
B30: 4.1 | C30: Total Assets | D30: NPR | E30: =Financials!C5/Financials!#REF!-1 -> #REF! | F30: =Financials!D5/Financials!C5-1 -> 0.045692713 | G30: =Financials!E5/Financials!D5-1 -> 0.01981521 | H30: =Financials!F5/Financials!E5-1 -> -0.0053037945 | I30: =Financials!G5/Financials!F5-1 -> -0.015909677 | J30: =Financials!H5/Financials!G5-1 -> 0.001320385 | K30: =Financials!I5/Financials!H5-1 -> 0.013372488 | L30: =Financials!J5/Financials!I5-1 -> 0.021828595 | M30: =Financials!K5/Financials!J5-1 -> -0.0049021169 | ... X30: =Financials!V5/Financials!U5-1 -> 0.018521194
B31: 4.2 | C31: Total Deposits | D31: NPR | E31: =Financials!C6/Financials!#REF!-1 -> #REF! | F31: =Financials!D6/Financials!C6-1 -> 0.016395531 | G31: =Financials!E6/Financials!D6-1 -> 0.024789934 | H31: =Financials!F6/Financials!E6-1 -> 0.063891989 | I31: =Financials!G6/Financials!F6-1 -> -0.025296379 | J31: =Financials!H6/Financials!G6-1 -> 0.0061538013 | K31: =Financials!I6/Financials!H6-1 -> 0.009203532 | L31: =Financials!J6/Financials!I6-1 -> 0.016319312 | M31: =Financials!K6/Financials!J6-1 -> -0.011174534 | ... X31: =Financials!V6/Financials!U6-1 -> 0.022758272
B32: 4.2.1 | C32: FOSA Deposits | D32: NPR | E32: =Financials!C8/Financials!#REF!-1 -> #REF! | F32: =Financials!D8/Financials!C8-1 -> 0.060356815 | G32: =Financials!E8/Financials!D8-1 -> 0.11849992 | H32: =Financials!F8/Financials!E8-1 -> 0.82689985 | I32: =Financials!G8/Financials!F8-1 -> -0.33021615 | J32: =Financials!H8/Financials!G8-1 -> -0.10092881 | K32: =Financials!I8/Financials!H8-1 -> 0.032915384 | L32: =Financials!J8/Financials!I8-1 -> 0.029266932 | M32: =Financials!K8/Financials!J8-1 -> -0.10786362 | ... X32: =Financials!V8/Financials!U8-1 -> 0.2636261
B33: 4.2.2 | C33: BOSA Deposits | D33: NPR | E33: =Financials!C7/Financials!#REF!-1 -> #REF! | F33: =Financials!D7/Financials!C7-1 -> 0.063608733 | G33: =Financials!E7/Financials!D7-1 -> 0.017725729 | H33: =Financials!F7/Financials!E7-1 -> 0.009996385 | I33: =Financials!G7/Financials!F7-1 -> 0.014795108 | J33: =Financials!H7/Financials!G7-1 -> 0.014905431 | K33: =Financials!I7/Financials!H7-1 -> 0.0085857032 | L33: =Financials!J7/Financials!I7-1 -> 0.015339079 | M33: =Financials!K7/Financials!J7-1 -> -0.0046878695 | ... X33: =Financials!V7/Financials!U7-1 -> 0.0034953515
B34: 4.3 | C34: Net Loans & advances | D34: NPR | E34: =Financials!C31/Financials!#REF!-1 -> #REF! | F34: =Financials!D31/Financials!C31-1 -> 0.044673081 | G34: =Financials!E31/Financials!D31-1 -> -0.0073765896 | H34: =Financials!F31/Financials!E31-1 -> -0.017268305 | I34: =Financials!G31/Financials!F31-1 -> -0.012206953 | J34: =Financials!H31/Financials!G31-1 -> 0.027464678 | K34: =Financials!I31/Financials!H31-1 -> 0.058935352 | L34: =Financials!J31/Financials!I31-1 -> 0.017582735 | M34: =Financials!K31/Financials!J31-1 -> -0.0072772677 | ... X34: =Financials!V31/Financials!U31-1 -> 0.020817822
B35: 4.4 | C35: Core capital | D35: NPR | E35: =Financials!C14/Financials!#REF!-1 -> #REF! | F35: =Financials!D14/Financials!C14-1 -> 0.37110249 | G35: =Financials!E14/Financials!D14-1 -> 0.019036913 | H35: =Financials!F14/Financials!E14-1 -> -0.19943039 | I35: =Financials!G14/Financials!F14-1 -> 0.033701819 | J35: =Financials!H14/Financials!G14-1 -> -0.010903993 | K35: =Financials!I14/Financials!H14-1 -> 0.043436651 | L35: =Financials!J14/Financials!I14-1 -> 0.021357809 | M35: =Financials!K14/Financials!J14-1 -> 0.013280731 | ... X35: =Financials!V14/Financials!U14-1 -> 0.022346647
B36: 4.5 | C36: Total Gross Income | D36: NPR | E36: =Financials!C41/Financials!#REF!-1 -> #REF! | F36: =Financials!D41/Financials!C41-1 -> -0.13173617 | G36: =Financials!E41/Financials!D41-1 -> 6.9962781e-05 | H36: =Financials!F41/Financials!E41-1 -> 0.17426688 | I36: =Financials!G41/Financials!F41-1 -> -0.0001191516 | J36: =Financials!H41/Financials!G41-1 -> -0.019089884 | K36: =Financials!I41/Financials!H41-1 -> 6.0742464e-05 | L36: =Financials!J41/Financials!I41-1 -> -0.00012147755 | M36: =Financials!K41/Financials!J41-1 -> 0 | ... X36: =Financials!V41/Financials!U41-1 -> -0.00029300132
B37: 4.6 | C37: Membership | D37: NPR
B39: 5 | C39: Efficiency Ratios
B40: 5.1 | C40: FinCost-Deposits/Average Deposits | D40: NPR | E40: =Financials!C48/((Financials!C6+Financials!#REF!)/2) -> #REF! | F40: =Financials!D48/((Financials!D6+Financials!C6)/2) -> 0 | G40: =Financials!E48/((Financials!E6+Financials!D6)/2) -> 0 | H40: =Financials!F48/((Financials!F6+Financials!E6)/2) -> 0 | I40: =Financials!G48/((Financials!G6+Financials!F6)/2) -> 0 | J40: =Financials!H48/((Financials!H6+Financials!G6)/2) -> 0 | K40: =Financials!I48/((Financials!I6+Financials!H6)/2) -> 0 | L40: =Financials!J48/((Financials!J6+Financials!I6)/2) -> 0 | M40: =Financials!K48/((Financials!K6+Financials!J6)/2) -> 0 | ... X40: =Financials!V48/((Financials!V6+Financials!U6)/2) -> 0
B41: 5.2 | C41: FinCost-Shares/Average Share capital | D41: NPR | E41: =Financials!C49/((Financials!C18+Financials!#REF!)/2) -> #REF! | F41: =Financials!D49/((Financials!D18+Financials!C18)/2) -> 0 | G41: =Financials!E49/((Financials!E18+Financials!D18)/2) -> 0 | H41: =Financials!F49/((Financials!F18+Financials!E18)/2) -> 0 | I41: =Financials!G49/((Financials!G18+Financials!F18)/2) -> 0 | J41: =Financials!H49/((Financials!H18+Financials!G18)/2) -> 0 | K41: =Financials!I49/((Financials!I18+Financials!H18)/2) -> 0 | L41: =Financials!J49/((Financials!J18+Financials!I18)/2) -> 0 | M41: =Financials!K49/((Financials!K18+Financials!J18)/2) -> 0 | ... X41: =Financials!V49/((Financials!V18+Financials!U18)/2) -> 0
B42: 5.3 | C42: FinCost-Ext Loans/Average Ext Loans | D42: NPR | E42: =Financials!C50/((Financials!C9+Financials!#REF!)/2) -> #REF! | F42: =Financials!D50/((Financials!D9+Financials!C9)/2) -> 0.010193231 | G42: =Financials!E50/((Financials!E9+Financials!D9)/2) -> 0 | H42: =Financials!F50/((Financials!F9+Financials!E9)/2) -> 0 | I42: =Financials!G50/((Financials!G9+Financials!F9)/2) -> 0.091803886 | J42: =Financials!H50/((Financials!H9+Financials!G9)/2) -> 0.15598144 | K42: =Financials!I50/((Financials!I9+Financials!H9)/2) -> 0.31879671 | L42: =Financials!J50/((Financials!J9+Financials!I9)/2) -> 1.0847101 | M42: =Financials!K50/((Financials!K9+Financials!J9)/2) -> #DIV/0! | ... X42: =Financials!V50/((Financials!V9+Financials!U9)/2) -> 0.048214422
B43: 5.4 | C43: OpEx/Average Total Assets | D43: NPR | E43: =(Financials!C52+Financials!C53)/((Financials!C5+Financials!#REF!)/2) -> #REF! | F43: =(Financials!D52+Financials!D53)/((Financials!D5+Financials!C5)/2) -> 0.0041749133 | G43: =(Financials!E52+Financials!E53)/((Financials!E5+Financials!D5)/2) -> 0.0069932673 | H43: =(Financials!F52+Financials!F53)/((Financials!F5+Financials!E5)/2) -> 0.011626079 | I43: =(Financials!G52+Financials!G53)/((Financials!G5+Financials!F5)/2) -> 0.015012799 | J43: =(Financials!H52+Financials!H53)/((Financials!H5+Financials!G5)/2) -> 0.027130407 | K43: =(Financials!I52+Financials!I53)/((Financials!I5+Financials!H5)/2) -> 0.030779442 | L43: =(Financials!J52+Financials!J53)/((Financials!J5+Financials!I5)/2) -> 0.034689894 | M43: =(Financials!K52+Financials!K53)/((Financials!K5+Financials!J5)/2) -> 0.038942198 | ... X43: =(Financials!V52+Financials!V53)/((Financials!V5+Financials!U5)/2) -> 0.02909345
B44: 5.5 | C44: Avge yield on Net loans | D44: NPR | E44: =Financials!C42/((Financials!C31+Financials!#REF!)/2) -> #REF! | F44: =Financials!D42/((Financials!D31+Financials!C31)/2) -> 0 | G44: =Financials!E42/((Financials!E31+Financials!D31)/2) -> 0 | H44: =Financials!F42/((Financials!F31+Financials!E31)/2) -> 0 | I44: =Financials!G42/((Financials!G31+Financials!F31)/2) -> 0 | J44: =Financials!H42/((Financials!H31+Financials!G31)/2) -> 0 | K44: =Financials!I42/((Financials!I31+Financials!H31)/2) -> 0 | L44: =Financials!J42/((Financials!J31+Financials!I31)/2) -> 0 | M44: =Financials!K42/((Financials!K31+Financials!J31)/2) -> 0.043339561 | ... X44: =Financials!V42/((Financials!V31+Financials!U31)/2) -> 0
B46: 6 | C46: Liquidity Ratio
B47: 6.1 | C47: minimum Liquidity | D47: 0.15 | E47: =(SFP!B4+SFP!B11)/(SFP!B31+SFP!B34+SFP!B35+SFP!B36+SFP!B37+SFP!B38) -> 0.18365786 | F47: =(SFP!C4+SFP!C11)/(SFP!C31+SFP!C34+SFP!C35+SFP!C36+SFP!C37+SFP!C38) -> 0.19181054 | G47: =(SFP!D4+SFP!D11)/(SFP!D31+SFP!D34+SFP!D35+SFP!D36+SFP!D37+SFP!D38) -> 0.22328525 | H47: =(SFP!E4+SFP!E11)/(SFP!E31+SFP!E34+SFP!E35+SFP!E36+SFP!E37+SFP!E38) -> 0.23888694 | I47: =(SFP!F4+SFP!F11)/(SFP!F31+SFP!F34+SFP!F35+SFP!F36+SFP!F37+SFP!F38) -> 0.22276455 | J47: =(SFP!G4+SFP!G11)/(SFP!G31+SFP!G34+SFP!G35+SFP!G36+SFP!G37+SFP!G38) -> 0.19607062 | K47: =(SFP!H4+SFP!H11)/(SFP!H31+SFP!H34+SFP!H35+SFP!H36+SFP!H37+SFP!H38) -> 0.15617273 | L47: =(SFP!I4+SFP!I11)/(SFP!I31+SFP!I34+SFP!I35+SFP!I36+SFP!I37+SFP!I38) -> 0.15969482 | ... X47: =(SFP!U4+SFP!U11)/(SFP!U31+SFP!U34+SFP!U35+SFP!U36+SFP!U37+SFP!U38) -> 0.1053823
C48: TECHNICAL Liquidity | E48: =(SFP!B4+SFP!B11)/(SFP!B32+SFP!B34+SFP!B35+SFP!B36+SFP!B37+SFP!B38) -> 0.16552522 | F48: =(SFP!C4+SFP!C11)/(SFP!C32+SFP!C34+SFP!C35+SFP!C36+SFP!C37+SFP!C38) -> 0.18006218 | G48: =(SFP!D4+SFP!D11)/(SFP!D32+SFP!D34+SFP!D35+SFP!D36+SFP!D37+SFP!D38) -> 0.20824016 | H48: =(SFP!E4+SFP!E11)/(SFP!E32+SFP!E34+SFP!E35+SFP!E36+SFP!E37+SFP!E38) -> 0.21215704 | I48: =(SFP!F4+SFP!F11)/(SFP!F32+SFP!F34+SFP!F35+SFP!F36+SFP!F37+SFP!F38) -> 0.20545351 | J48: =(SFP!G4+SFP!G11)/(SFP!G32+SFP!G34+SFP!G35+SFP!G36+SFP!G37+SFP!G38) -> 0.18232973 | K48: =(SFP!H4+SFP!H11)/(SFP!H32+SFP!H34+SFP!H35+SFP!H36+SFP!H37+SFP!H38) -> 0.14513936 | L48: =(SFP!I4+SFP!I11)/(SFP!I32+SFP!I34+SFP!I35+SFP!I36+SFP!I37+SFP!I38) -> 0.14837518 | ... X48: =(SFP!U4+SFP!U11)/(SFP!U32+SFP!U34+SFP!U35+SFP!U36+SFP!U37+SFP!U38) -> 0.096158471
B49: 7 | C49: Loan Loss Provisions Ratios
B50: 7.1 | C50: Actual LLP / Required LLP | D50: 1
B51: 7.2 | C51: allowance for loan loss/NPL
C52: Loan interest/Net Loans | E52: =SCI!B5/SFP!B14 -> 0.15516547 | F52: =SCI!C5/SFP!C14 -> 0.012729826 | G52: =SCI!D5/SFP!D14 -> 0.021156747 | H52: =SCI!E5/SFP!E14 -> 0.034718172 | I52: =SCI!F5/SFP!F14 -> 0.046740427 | J52: =SCI!G5/SFP!G14 -> 0.057079218 | K52: =SCI!H5/SFP!H14 -> 0.064544449 | L52: =SCI!I5/SFP!I14 -> 0.073785911 | ... X52: =SCI!U5/SFP!U14 -> 0.062115694
C53: Gross loans/Total assets | E53: =Financials!C32/Financials!C5 -> 0.71580215 | F53: =Financials!D32/Financials!D5 -> 0.68307191 | G53: =Financials!E32/Financials!E5 -> 0.66485886 | H53: =Financials!F32/Financials!F5 -> 0.65686173 | I53: =Financials!G32/Financials!G5 -> 0.65933323 | J53: =Financials!H32/Financials!H5 -> 0.6765483 | K53: =Financials!I32/Financials!I5 -> 0.706967 | L53: =Financials!J32/Financials!J5 -> 0.70402944 | ... X53: =Financials!V32/Financials!V5 -> 0.76635572
B54: 8 | C54: Earnings
B55: 8.1 | C55: ROA | E55: =SCI!B33/(SFP!#REF!+SFP!B27/2) -> #REF! | F55: =SCI!C33/(SFP!B27+SFP!C27/2) -> 0.0023535014 | G55: =SCI!D33/(SFP!C27+SFP!D27/2) -> 0.0052377287 | H55: =SCI!E33/(SFP!D27+SFP!E27/2) -> 0.0083831586 | I55: =SCI!F33/(SFP!E27+SFP!F27/2) -> 0.012347456 | J55: =SCI!G33/(SFP!F27+SFP!G27/2) -> 0.011156073 | K55: =SCI!H33/(SFP!G27+SFP!H27/2) -> 0.017683239 | L55: =SCI!I33/(SFP!H27+SFP!I27/2) -> 0.020233592 | M55: =SCI!J33/(SFP!I27+SFP!J27/2) -> 0.021646168 | ... X55: =SCI!U33/(SFP!T27+SFP!U27/2) -> 0.018378753
B56: 8.2 | C56: Cost Income Ratio | E56: =SCI!B23/SCI!B19 -> 0.76315746 | F56: =SCI!C23/SCI!C19 -> 0.68350577 | G56: =SCI!D23/SCI!D19 -> 0.62278962 | H56: =SCI!E23/SCI!E19 -> 0.61327025 | I56: =SCI!F23/SCI!F19 -> 0.58301628 | J56: =SCI!G23/SCI!G19 -> 0.70959922 | K56: =SCI!H23/SCI!H19 -> 0.64173719 | L56: =SCI!I23/SCI!I19 -> 0.64122767 | ... X56: =SCI!U23/SCI!U19 -> 0.62732527
B57: 8.3 | C57: Operating Expense Ratio | E57: =SCI!B23/SFP!B27 -> 0.083971703 | F57: =SCI!C23/SFP!C27 -> 0.0074018939 | G57: =SCI!D23/SFP!D27 -> 0.012803527 | H57: =SCI!E23/SFP!E27 -> 0.020011715 | I57: =SCI!F23/SFP!F27 -> 0.026174963 | J57: =SCI!G23/SFP!G27 -> 0.040854134 | K57: =SCI!H23/SFP!H27 -> 0.04709459 | L57: =SCI!I23/SFP!I27 -> 0.053472204 | ... X57: =SCI!U23/SFP!U27 -> 0.045843
C58: Liquid assets/total assets | E58: =(Financials!C36+Financials!C29)/Financials!C5 -> 0.12818752 | F58: =(Financials!D36+Financials!D29)/Financials!D5 -> 0.13347298 | G58: =(Financials!E36+Financials!E29)/Financials!E5 -> 0.15494496 | H58: =(Financials!F36+Financials!F29)/Financials!F5 -> 0.16845763 | I58: =(Financials!G36+Financials!G29)/Financials!G5 -> 0.16155949 | J58: =(Financials!H36+Financials!H29)/Financials!H5 -> 0.14427312 | K58: =(Financials!I36+Financials!I29)/Financials!I5 -> 0.11431863 | L58: =(Financials!J36+Financials!J29)/Financials!J5 -> 0.11723167 | ... X58: =(Financials!V36+Financials!V29)/Financials!V5 -> 0.072979633
B76: 0

Sheet CAELS
B1: HOMEBUSINESS SACCO
B2: FINANCIAL SOUNDNESS INDICATORS | C2: Prude. Std | D2: Audited 2021 | E2: 44562 | F2: 44593 | G2: 44621 | H2: 44652 | I2: 44682 | J2: 44713 | K2: 44743 | L2: 44774 | M2: 44805 | N2: 44835 | O2: 44866 | P2: 44896 | Q2: Audited-20222 | R2: 44949 | S2: 44980 | T2: 45008 | U2: 45039 | V2: 45069 | W2: 45100 | X2: 45130
B3: CAPITAL
B4: CORE CAPITAL | C4: ≥ Ksh.10M | D4: ='Prudential Ratios'!E6 -> 46.626056 | E4: ='Prudential Ratios'!F6 -> 63.929101 | F4: ='Prudential Ratios'!G6 -> 65.146114 | G4: ='Prudential Ratios'!H6 -> 52.153999 | H4: ='Prudential Ratios'!I6 -> 53.911683 | I4: ='Prudential Ratios'!J6 -> 53.323831 | J4: ='Prudential Ratios'!K6 -> 55.640039 | K4: ='Prudential Ratios'!L6 -> 56.828389 | ... W4: ='Prudential Ratios'!X6 -> 65.57352
B5: CCA | C5: ≥ 10% | D5: ='Prudential Ratios'!E7 -> 0.18639784 | E5: ='Prudential Ratios'!F7 -> 0.2444031 | F5: ='Prudential Ratios'!G7 -> 0.24421658 | G5: ='Prudential Ratios'!H7 -> 0.19655486 | H5: ='Prudential Ratios'!I7 -> 0.20646389 | I5: ='Prudential Ratios'!J7 -> 0.20394332 | J5: ='Prudential Ratios'!K7 -> 0.2099938 | K5: ='Prudential Ratios'!L7 -> 0.20989705 | ... W5: ='Prudential Ratios'!X7 -> 0.21625586
B6: ICA | C6: ≥ 8% | D6: ='Prudential Ratios'!E10 -> 0.057515195 | E6: ='Prudential Ratios'!F10 -> 0.11997477 | F6: ='Prudential Ratios'!G10 -> 0.1217362 | G6: ='Prudential Ratios'!H10 -> 0.073097615 | H6: ='Prudential Ratios'!I10 -> 0.080172831 | I6: ='Prudential Ratios'!J10 -> 0.077477769 | J6: ='Prudential Ratios'!K10 -> 0.08500453 | K6: ='Prudential Ratios'!L10 -> 0.087373233 | ... W6: ='Prudential Ratios'!X10 -> 0.085605891
B7: CCD | C7: ≥ 8% | D7: ='Prudential Ratios'!E8 -> 0.26000906 | E7: ='Prudential Ratios'!F8 -> 0.35074836 | F7: ='Prudential Ratios'!G8 -> 0.34877931 | G7: ='Prudential Ratios'!H8 -> 0.26245345 | H7: ='Prudential Ratios'!I8 -> 0.27833959 | I7: ='Prudential Ratios'!J8 -> 0.27362077 | J7: ='Prudential Ratios'!K8 -> 0.28290224 | K7: ='Prudential Ratios'!L8 -> 0.28430475 | ... W7: ='Prudential Ratios'!X8 -> 0.30906423
B8: Asset Quality
B9: NPL | C9: ≤ 6%
B10: Earnings
B11: ROA | D11: ='Prudential Ratios'!E55 -> #REF! | E11: ='Prudential Ratios'!F55 -> 0.0023535014 | F11: ='Prudential Ratios'!G55 -> 0.0052377287 | G11: ='Prudential Ratios'!H55 -> 0.0083831586 | H11: ='Prudential Ratios'!I55 -> 0.012347456 | I11: ='Prudential Ratios'!J55 -> 0.011156073 | J11: ='Prudential Ratios'!K55 -> 0.017683239 | K11: ='Prudential Ratios'!L55 -> 0.020233592 | ... W11: ='Prudential Ratios'!X55 -> 0.018378753
B12: CIR | D12: ='Prudential Ratios'!E56 -> 0.76315746 | E12: ='Prudential Ratios'!F56 -> 0.68350577 | F12: ='Prudential Ratios'!G56 -> 0.62278962 | G12: ='Prudential Ratios'!H56 -> 0.61327025 | H12: ='Prudential Ratios'!I56 -> 0.58301628 | I12: ='Prudential Ratios'!J56 -> 0.70959922 | J12: ='Prudential Ratios'!K56 -> 0.64173719 | K12: ='Prudential Ratios'!L56 -> 0.64122767 | ... W12: ='Prudential Ratios'!X56 -> 0.62732527
B13: OER | D13: ='Prudential Ratios'!E57 -> 0.083971703 | E13: ='Prudential Ratios'!F57 -> 0.0074018939 | F13: ='Prudential Ratios'!G57 -> 0.012803527 | G13: ='Prudential Ratios'!H57 -> 0.020011715 | H13: ='Prudential Ratios'!I57 -> 0.026174963 | I13: ='Prudential Ratios'!J57 -> 0.040854134 | J13: ='Prudential Ratios'!K57 -> 0.04709459 | K13: ='Prudential Ratios'!L57 -> 0.053472204 | ... W13: ='Prudential Ratios'!X57 -> 0.045843
B14: LIQUIDITY
B15: MIN LIQ | C15: 0.15 | D15: ='Prudential Ratios'!E47 -> 0.18365786 | E15: ='Prudential Ratios'!F47 -> 0.19181054 | F15: ='Prudential Ratios'!G47 -> 0.22328525 | G15: ='Prudential Ratios'!H47 -> 0.23888694 | H15: ='Prudential Ratios'!I47 -> 0.22276455 | I15: ='Prudential Ratios'!J47 -> 0.19607062 | J15: ='Prudential Ratios'!K47 -> 0.15617273 | K15: ='Prudential Ratios'!L47 -> 0.15969482 | ... W15: ='Prudential Ratios'!X47 -> 0.1053823
B16: TEC LIQ | D16: ='Prudential Ratios'!E48 -> 0.16552522 | E16: ='Prudential Ratios'!F48 -> 0.18006218 | F16: ='Prudential Ratios'!G48 -> 0.20824016 | G16: ='Prudential Ratios'!H48 -> 0.21215704 | H16: ='Prudential Ratios'!I48 -> 0.20545351 | I16: ='Prudential Ratios'!J48 -> 0.18232973 | J16: ='Prudential Ratios'!K48 -> 0.14513936 | K16: ='Prudential Ratios'!L48 -> 0.14837518 | ... W16: ='Prudential Ratios'!X48 -> 0.096158471
B17: EB | C17: ≤ 25% | D17: ='Prudential Ratios'!E27 -> 0.017490018 | E17: ='Prudential Ratios'!F27 -> 0.014336376 | F17: ='Prudential Ratios'!G27 -> 0.011714848 | G17: ='Prudential Ratios'!H27 -> 0.0094218499 | H17: ='Prudential Ratios'!I27 -> 0.0071806289 | I17: ='Prudential Ratios'!J27 -> 0.0047807735 | J17: ='Prudential Ratios'!K27 -> 0.0023588431 | K17: ='Prudential Ratios'!L27 -> 0 | ... W17: ='Prudential Ratios'!X27 -> 0.026399804
B18: LIQ/TA | D18: ='Prudential Ratios'!E58 -> 0.12818752 | E18: ='Prudential Ratios'!F58 -> 0.13347298 | F18: ='Prudential Ratios'!G58 -> 0.15494496 | G18: ='Prudential Ratios'!H58 -> 0.16845763 | H18: ='Prudential Ratios'!I58 -> 0.16155949 | I18: ='Prudential Ratios'!J58 -> 0.14427312 | J18: ='Prudential Ratios'!K58 -> 0.11431863 | K18: ='Prudential Ratios'!L58 -> 0.11723167 | ... W18: ='Prudential Ratios'!X58 -> 0.072979633
B19: STRUCTURE
B20: NEA | C20: ≤ 10% | D20: ='Prudential Ratios'!E14 -> 0.18803085 | E20: ='Prudential Ratios'!F14 -> 0.18341397 | F20: ='Prudential Ratios'!G14 -> 0.18015585 | G20: ='Prudential Ratios'!H14 -> 0.17464009 | H20: ='Prudential Ratios'!I14 -> 0.17906607 | I20: ='Prudential Ratios'!J14 -> 0.17913743 | J20: ='Prudential Ratios'!K14 -> 0.17867375 | K20: ='Prudential Ratios'!L14 -> 0.17869914 | ... W20: ='Prudential Ratios'!X14 -> 0.16062916
B21: LB | C21: ≤ 5% | D21: ='Prudential Ratios'!E15 -> 0.13579339 | E21: ='Prudential Ratios'!F15 -> 0.13142559 | F21: ='Prudential Ratios'!G15 -> 0.12948894 | G21: ='Prudential Ratios'!H15 -> 0.13021326 | H21: ='Prudential Ratios'!I15 -> 0.13345626 | I21: ='Prudential Ratios'!J15 -> 0.13392534 | J21: ='Prudential Ratios'!K15 -> 0.13229968 | K21: ='Prudential Ratios'!L15 -> 0.129691 | ... W21: ='Prudential Ratios'!X15 -> 0.12011921
B22: FITD | C22: ≤ 5% | D22: ='Prudential Ratios'!E19 -> 6.0002877e-05 | E22: ='Prudential Ratios'!F19 -> 5.9034967e-05 | F22: ='Prudential Ratios'!G19 -> 5.7606896e-05 | G22: ='Prudential Ratios'!H19 -> 5.4147316e-05 | H22: ='Prudential Ratios'!I19 -> 5.5552596e-05 | I22: ='Prudential Ratios'!J19 -> 5.5212827e-05 | J22: ='Prudential Ratios'!K19 -> 5.4709308e-05 | K22: ='Prudential Ratios'!L19 -> 5.3830826e-05 | ... W22: ='Prudential Ratios'!X19 -> 5.0714543e-05
B23: FICC | C23: ≤ 40% | D23: ='Prudential Ratios'!E20 -> 0.00023077225 | E23: ='Prudential Ratios'!F20 -> 0.00016831145 | F23: ='Prudential Ratios'!G20 -> 0.00016516718 | G23: ='Prudential Ratios'!H20 -> 0.00020631208 | H23: ='Prudential Ratios'!I20 -> 0.00019958568 | I23: ='Prudential Ratios'!J20 -> 0.00020178595 | J23: ='Prudential Ratios'!K20 -> 0.00019338592 | K23: ='Prudential Ratios'!L20 -> 0.00018934199 | ... W23: ='Prudential Ratios'!X20 -> 0.00016409063
D26: =37194132-32071373 -> 5122759

Sheet Financials
B1: HOMEBUSINESS SACCO SOCIETY
B3: Year | C3: Audited 2021 | D3: 44562 | E3: 44593 | F3: 44621 | G3: 44652 | H3: 44682 | I3: 44713 | J3: 44743 | K3: 44774 | L3: 44805 | M3: 44835 | N3: 44866 | O3: 44896 | P3: Audited-2022 | Q3: 44949 | R3: 44980 | S3: 45008 | T3: 45039 | U3: 45069 | V3: 45100 | W3: 45130
A4: 1 | B4: Membership | C4: 7076 | P4: 8492
A5: 2 | B5: Total Assets | C5: =SFP!B27 -> 250142681 | D5: =SFP!C27 -> 2.6157238e+08 | E5: =SFP!D27 -> 2.6675549e+08 | F5: =SFP!E27 -> 2.6534067e+08 | G5: =SFP!F27 -> 2.6111919e+08 | H5: =SFP!G27 -> 2.6146397e+08 | I5: =SFP!H27 -> 2.6496039e+08 | J5: =SFP!I27 -> 2.707441e+08 | ... V5: =SFP!U27 -> 3.0322194e+08
A6: 3 | B6: Total Deposits | C6: =SFP!B32 -> 179324735 | D6: =SFP!C32 -> 1.8226486e+08 | E6: =SFP!D32 -> 1.8678319e+08 | F6: =SFP!E32 -> 1.9871714e+08 | G6: =SFP!F32 -> 1.9369032e+08 | H6: =SFP!G32 -> 1.9488225e+08 | I6: =SFP!H32 -> 1.9667586e+08 | J6: =SFP!I32 -> 1.9988547e+08 | ... V6: =SFP!U32 -> 2.1216794e+08
A7: 3.1 | B7: Deposits-Members(BOSA) | C7: =SFP!B31 -> 160198883 | D7: =SFP!C31 -> 1.7038893e+08 | E7: =SFP!D31 -> 1.734092e+08 | F7: =SFP!E31 -> 1.7514266e+08 | G7: =SFP!F31 -> 1.7773392e+08 | H7: =SFP!G31 -> 1.8038312e+08 | I7: =SFP!H31 -> 1.8193184e+08 | J7: =SFP!I31 -> 1.847225e+08 | ... V7: =SFP!U31 -> 1.9202521e+08
A8: 3.2 | B8: Deposits-Customers(FOSA) | C8: =SFP!B29 -> 10320478 | D8: =SFP!C29 -> 10943389 | E8: =SFP!D29 -> 12240180 | F8: =SFP!E29 -> 22361583 | G8: =SFP!F29 -> 14977427 | H8: =SFP!G29 -> 13465773 | I8: =SFP!H29 -> 13909004 | J8: =SFP!I29 -> 14316078 | ... V8: =SFP!U29 -> 19250493
A9: 4 | B9: External Borrowing | C9: =SFP!B39 -> 4375000 | D9: =SFP!C39 -> 3750000 | E9: =SFP!D39 -> 3125000 | F9: =SFP!E39 -> 2500000 | G9: =SFP!F39 -> 1875000 | H9: =SFP!G39 -> 1250000 | I9: =SFP!H39 -> 625000 | J9: =SFP!I39 -> 0 | ... V9: =SFP!U39 -> 8004999.7
A10: 4.1 | B10: Short term Liabilities | C10: =SFP!B34+SFP!B35+SFP!B36+SFP!B37+SFP!B38 -> 14392985 | D10: =SFP!C34+SFP!C35+SFP!C36+SFP!C37+SFP!C38 -> 11628418 | E10: =SFP!D34+SFP!D35+SFP!D36+SFP!D37+SFP!D38 -> 11701183 | F10: =SFP!E34+SFP!E35+SFP!E36+SFP!E37+SFP!E38 -> 11969532 | G10: =SFP!F34+SFP!F35+SFP!F36+SFP!F37+SFP!F38 -> 11642187 | H10: =SFP!G34+SFP!G35+SFP!G36+SFP!G37+SFP!G38 -> 12007886 | I10: =SFP!H34+SFP!H35+SFP!H36+SFP!H37+SFP!H38 -> 12019496 | J10: =SFP!I34+SFP!I35+SFP!I36+SFP!I37+SFP!I38 -> 14030245 | ... V10: =SFP!U34+SFP!U35+SFP!U36+SFP!U37+SFP!U38 -> 17962859
A13: 5 | B13: Share capital and Reserves
A14: 5.1 | B14: Core Capital | C14: =C17 -> 46626056 | D14: =D17 -> 63929101 | E14: =E17 -> 65146114 | F14: =F17 -> 52153999 | G14: =G17 -> 53911683 | H14: =H17 -> 53323831 | I14: =I17 -> 55640039 | J14: =J17 -> 56828389 | ... V14: =V17 -> 65573520
A15: 5.2 | B15: Institutional Capital | C15: =C14-C18 -> 14387005 | D15: =D14-D18 -> 31382087 | E15: =E14-E18 -> 32473800 | F15: =F14-F18 -> 19395770 | G15: =G14-G18 -> 20934665 | H15: =H14-H18 -> 20257645 | I15: =I14-I18 -> 22522833 | J15: =J14-J18 -> 23655788 | ... V15: =V14-V18 -> 25957584
A17: 5.3 | B17: Total Capital | C17: =SUM(C18:C21) -> 46626056 | D17: =SUM(D18:D21) -> 63929101 | E17: =SUM(E18:E21) -> 65146114 | F17: =SUM(F18:F21) -> 52153999 | G17: =SUM(G18:G21) -> 53911683 | H17: =SUM(H18:H21) -> 53323831 | I17: =SUM(I18:I21) -> 55640039 | J17: =SUM(J18:J21) -> 56828389 | ... V17: =SUM(V18:V21) -> 65573520
A18: 5.3.1 | B18: Members Share Capital | C18: =SFP!B42 -> 32239051 | D18: =SFP!C42 -> 32547014 | E18: =SFP!D42 -> 32672314 | F18: =SFP!E42 -> 32758228 | G18: =SFP!F42 -> 32977019 | H18: =SFP!G42 -> 33066186 | I18: =SFP!H42 -> 33117206 | J18: =SFP!I42 -> 33172601 | ... V18: =SFP!U42 -> 39615935
A19: 5.3.3 | B19: Retained Earnings | C19: =SFP!B45 -> 7656031 | D19: =SFP!C45 -> 24235430 | E19: =SFP!D45 -> 25326643 | F19: =SFP!E45 -> 11003101 | G19: =SFP!F45 -> 12542995 | H19: =SFP!G45 -> 12026171 | I19: =SFP!H45 -> 14290860 | J19: =SFP!I45 -> 15424814 | ... V19: =SFP!U45 -> 16707607
A20: 5.3.5 | B20: Statutory Reserves | C20: =SFP!B50 -> 6730974 | D20: =SFP!C50 -> 0 | E20: =SFP!D50 -> 0 | F20: =SFP!E50 -> 0 | G20: =SFP!F50 -> 0 | H20: =SFP!G50 -> 0 | I20: =SFP!H50 -> 0 | J20: =SFP!I50 -> 0 | ... V20: =SFP!U50 -> 0
A21: 5.3.6 | B21: Capital Reserve | C21: =SFP!B51 -> 0 | D21: =SFP!C51 -> 7146657 | E21: =SFP!D51 -> 7147157 | F21: =SFP!E51 -> 8392669.7 | G21: =SFP!F51 -> 8391669.7 | H21: =SFP!G51 -> 8231473.7 | I21: =SFP!H51 -> 8231973.7 | J21: =SFP!I51 -> 8230973.7 | ... V21: =SFP!U51 -> 9249977.5
A22: 5.3.7 | B22: Supplementary Capital & reserves
A23: a | B23: Proposed Dividends | C23: =SFP!B53 -> 3723905 | D23: =SFP!C53 -> 0 | E23: =SFP!D53 -> 0 | F23: =SFP!E53 -> 0 | G23: =SFP!F53 -> 0 | H23: =SFP!G53 -> 0 | I23: =SFP!H53 -> 0 | J23: =SFP!I53 -> 0 | ... V23: =SFP!U53 -> 0
A24: b
A26: 6 | B26: Investments | C26: =C27+C28+C29 -> 10760 | D26: =D27+D28+D29 -> 10760 | E26: =E27+E28+E29 -> 10760 | F26: =F27+F28+F29 -> 10760 | G26: =G27+G28+G29 -> 10760 | H26: =H27+H28+H29 -> 10760 | I26: =I27+I28+I29 -> 10760 | J26: =J27+J28+J29 -> 10760 | ... V26: =V27+V28+V29 -> 10760
A27: 6.1 | B27: Investments in Coop bank, CIC, Kuscco, Kerussu & Codic | C27: =SFP!B12 -> 10760 | D27: =SFP!C12 -> 10760 | E27: =SFP!D12 -> 10760 | F27: =SFP!E12 -> 10760 | G27: =SFP!F12 -> 10760 | H27: =SFP!G12 -> 10760 | I27: =SFP!H12 -> 10760 | J27: =SFP!I12 -> 10760 | ... V27: =SFP!U12 -> 10760
A28: 6.2 | B28: Equity Investments (at cost) | C28: =SFP!B13 -> 0 | D28: =SFP!C13 -> 0 | E28: =SFP!D13 -> 0 | F28: =SFP!E13 -> 0 | G28: =SFP!F13 -> 0 | H28: =SFP!G13 -> 0 | I28: =SFP!H13 -> 0 | J28: =SFP!I13 -> 0 | ... V28: =SFP!U13 -> 0
A29: 6.3 | B29: Deposits in KUSCCO CFP | C29: =SFP!B11 -> 0 | D29: =SFP!C11 -> 0 | E29: =SFP!D11 -> 0 | F29: =SFP!E11 -> 0 | G29: =SFP!F11 -> 0 | H29: =SFP!G11 -> 0 | I29: =SFP!H11 -> 0 | J29: =SFP!I11 -> 0 | ... V29: =SFP!U11 -> 0
A31: 7 | B31: Net Loans & advances | C31: =C32-C33 -> 171032210 | D31: =D32-D33 -> 1.7867275e+08 | E31: =E32-E33 -> 1.7735475e+08 | F31: =F32-F33 -> 1.7429213e+08 | G31: =G32-G33 -> 1.7216456e+08 | H31: =H32-H33 -> 1.76893e+08 | I31: =I32-I33 -> 1.8731825e+08 | J31: =J32-J33 -> 1.9061182e+08 | ... V31: =V32-V33 -> 2.3237587e+08
A32: 7.1 | B32: Gross Loans & advances | C32: =SFP!B15 -> 179052670 | D32: =SFP!C15 -> 1.7867275e+08 | E32: =SFP!D15 -> 1.7735475e+08 | F32: =SFP!E15 -> 1.7429213e+08 | G32: =SFP!F15 -> 1.7216456e+08 | H32: =SFP!G15 -> 1.76893e+08 | I32: =SFP!H15 -> 1.8731825e+08 | J32: =SFP!I15 -> 1.9061182e+08 | ... V32: =SFP!U15 -> 2.3237587e+08
A33: 7.3 | B33: Allowance for loan losses | C33: =SFP!B16 -> 8020460 | D33: =SFP!C16 -> 0 | E33: =SFP!D16 -> 0 | F33: =SFP!E16 -> 0 | G33: =SFP!F16 -> 0 | H33: =SFP!G16 -> 0 | I33: =SFP!H16 -> 0 | J33: =SFP!I16 -> 0 | ... V33: =SFP!U16 -> 0
A34: 7.4 | B34: Non Performing Loans | C34: =(#REF!+#REF!+#REF!) -> #REF! | D34: =(#REF!+#REF!+#REF!) -> #REF! | E34: =(#REF!+#REF!+#REF!) -> #REF! | F34: =(#REF!+#REF!+#REF!) -> #REF! | G34: =(#REF!+#REF!+#REF!) -> #REF! | H34: =(#REF!+#REF!+#REF!) -> #REF! | I34: =(#REF!+#REF!+#REF!) -> #REF! | J34: =(#REF!+#REF!+#REF!) -> #REF! | ... V34: =(#REF!+#REF!+#REF!) -> #REF!
A35: 7.5 | B35: Required loan loss provision | C35: =#REF! -> #REF! | D35: =#REF! -> #REF! | E35: =#REF! -> #REF! | F35: =#REF! -> #REF! | G35: =#REF! -> #REF! | H35: =#REF! -> #REF! | I35: =#REF! -> #REF! | J35: =#REF! -> #REF! | ... V35: =#REF! -> #REF!
A36: 7.6 | B36: Cash and Cash equipments | C36: =SFP!B4 -> 32065169 | D36: =SFP!C4 -> 34912846 | E36: =SFP!D4 -> 41332419 | F36: =SFP!E4 -> 44698661 | G36: =SFP!F4 -> 42186283 | H36: =SFP!G4 -> 37722223 | I36: =SFP!H4 -> 30289909 | J36: =SFP!I4 -> 31739783 | ... V36: =SFP!U4 -> 22129026
A38: 8 | B38: Non-Earning Assets | C38: =SFP!B7+SFP!B17+SFP!B23+SFP!B24+SFP!B25+SFP!B26 -> 47034542 | D38: =SFP!C7+SFP!C17+SFP!C23+SFP!C24+SFP!C25+SFP!C26 -> 47976027 | E38: =SFP!D7+SFP!D17+SFP!D23+SFP!D24+SFP!D25+SFP!D26 -> 48057561 | F38: =SFP!E7+SFP!E17+SFP!E23+SFP!E24+SFP!E25+SFP!E26 -> 46339119 | G38: =SFP!F7+SFP!F17+SFP!F23+SFP!F24+SFP!F25+SFP!F26 -> 46757588 | H38: =SFP!G7+SFP!G17+SFP!G23+SFP!G24+SFP!G25+SFP!G26 -> 46837982 | I38: =SFP!H7+SFP!H17+SFP!H23+SFP!H24+SFP!H25+SFP!H26 -> 47341468 | J38: =SFP!I7+SFP!I17+SFP!I23+SFP!I24+SFP!I25+SFP!I26 -> 48381740 | ... V38: =SFP!U7+SFP!U17+SFP!U23+SFP!U24+SFP!U25+SFP!U26 -> 48706285
A39: 8.1 | B39: Property and Equipment | C39: =SFP!B23 -> 33967722 | D39: =SFP!C23 -> 34377304 | E39: =SFP!D23 -> 34541884 | F39: =SFP!E23 -> 34550874 | G39: =SFP!F23 -> 34847989 | H39: =SFP!G23 -> 35016649 | I39: =SFP!H23 -> 35054174 | J39: =SFP!I23 -> 35113074 | ... V39: =SFP!U23 -> 36422779
A41: 9 | B41: Turnover | C41: =C42+C43+C44 -> 8230974 | D41: =D42+D43+D44 -> 7146657 | E41: =E42+E43+E44 -> 7147157 | F41: =F42+F43+F44 -> 8392669.7 | G41: =G42+G43+G44 -> 8391669.7 | H41: =H42+H43+H44 -> 8231473.7 | I41: =I42+I43+I44 -> 8231973.7 | J41: =J42+J43+J44 -> 8230973.7 | ... V41: =V42+V43+V44 -> 9249977.5
A42: 9.1 | B42: Loan Interest | C42: =SFP!B50 -> 6730974 | D42: =SFP!C50 -> 0 | E42: =SFP!D50 -> 0 | F42: =SFP!E50 -> 0 | G42: =SFP!F50 -> 0 | H42: =SFP!G50 -> 0 | I42: =SFP!H50 -> 0 | J42: =SFP!I50 -> 0 | ... V42: =SFP!U50 -> 0
B43: Income from investments | C43: =SFP!B51 -> 0 | D43: =SFP!C51 -> 7146657 | E43: =SFP!D51 -> 7147157 | F43: =SFP!E51 -> 8392669.7 | G43: =SFP!F51 -> 8391669.7 | H43: =SFP!G51 -> 8231473.7 | I43: =SFP!H51 -> 8231973.7 | J43: =SFP!I51 -> 8230973.7 | ... V43: =SFP!U51 -> 9249977.5
A44: 9.2 | B44: Fees & Commissions | C44: =SFP!B52 -> 1500000 | D44: =SFP!C52 -> 0 | E44: =SFP!D52 -> 0 | F44: =SFP!E52 -> 0 | G44: =SFP!F52 -> 0 | H44: =SFP!G52 -> 0 | I44: =SFP!H52 -> 0 | J44: =SFP!I52 -> 0 | ... V44: =SFP!U52 -> 0
B45: Average yield on loans
A47: 10 | B47: Total Expenses (FinCosts + OpEx) | C47: =SUM(C48:C53) -> 21321125 | D47: =SUM(D48:D53) -> 1109593 | E47: =SUM(E48:E53) -> 1936049 | F47: =SUM(F48:F53) -> 3253767 | G47: =SUM(G48:G53) -> 4152639 | H47: =SUM(H48:H53) -> 7332668 | I47: =SUM(I48:I53) -> 8400395.9 | J47: =SUM(J48:J53) -> 9630737.9 | ... V47: =SUM(V48:V53) -> 9149617.7
A48: 10.1 | B48: Financial Exp. (Interest on deposits) | C48: =SCI!B13 -> 9682315 | D48: =SCI!C13 -> 0 | E48: =SCI!D13 -> 0 | F48: =SCI!E13 -> 0 | G48: =SCI!F13 -> 0 | H48: =SCI!G13 -> 0 | I48: =SCI!H13 -> 0 | J48: =SCI!I13 -> 0 | ... V48: =SCI!U13 -> 0
A49: 10.2 | B49: Financial Exp. (Dividends) | C49: =SCI!B15 -> 0 | D49: =SCI!C15 -> 0 | E49: =SCI!D15 -> 0 | F49: =SCI!E15 -> 0 | G49: =SCI!F15 -> 0 | H49: =SCI!G15 -> 0 | I49: =SCI!H15 -> 0 | J49: =SCI!I15 -> 0 | ... V49: =SCI!U15 -> 0
A50: 10.3 | B50: Financial Exp. (Interest on bank loans) | C50: =SCI!B14 -> 0 | D50: =SCI!C14 -> 41410 | E50: =SCI!D14 -> 0 | F50: =SCI!E14 -> 0 | G50: =SCI!F14 -> 200821 | H50: =SCI!G14 -> 243721 | I50: =SCI!H14 -> 298871.92 | J50: =SCI!I14 -> 338971.92 | ... V50: =SCI!U14 -> 408054.71
A51: 10.4 | B51: Other Financial Expenses | C51: =SCI!B16+SCI!B17+SCI!B18 -> 282107 | D51: =SCI!C16+SCI!C17+SCI!C18 -> 0 | E51: =SCI!D16+SCI!D17+SCI!D18 -> 88680 | F51: =SCI!E16+SCI!E17+SCI!E18 -> 160671 | G51: =SCI!F16+SCI!F17+SCI!F18 -> 0 | H51: =SCI!G16+SCI!G17+SCI!G18 -> 0 | I51: =SCI!H16+SCI!H17+SCI!H18 -> 0 | J51: =SCI!I16+SCI!I17+SCI!I18 -> 0 | ... V51: =SCI!U16+SCI!U17+SCI!U18 -> 0
A52: 10.5 | B52: Administrative Expenses | C52: =SCI!B28 -> 9236364 | D52: =SCI!C28 -> 817883 | E52: =SCI!D28 -> 1373829 | F52: =SCI!E28 -> 2194916 | G52: =SCI!F28 -> 2834788 | H52: =SCI!G28 -> 5674251 | I52: =SCI!H28 -> 6367478 | J52: =SCI!I28 -> 7204773 | ... V52: =SCI!U28 -> 6906858
A53: 10.6 | B53: Governance Expenses | C53: =SCI!B25 -> 2120339 | D53: =SCI!C25 -> 250300 | E53: =SCI!D25 -> 473540 | F53: =SCI!E25 -> 898180 | G53: =SCI!F25 -> 1117030 | H53: =SCI!G25 -> 1414696 | I53: =SCI!H25 -> 1734046 | J53: =SCI!I25 -> 2086993 | ... V53: =SCI!U25 -> 1834705
B54: LLP
B56: Net Surplus | C56: =SCI!B37 -> 5421586 | D56: =SCI!C37 -> 896516.63 | E56: =SCI!D37 -> 2068641.6 | F56: =SCI!E37 -> 3348450 | G56: =SCI!F37 -> 4888361.1 | H56: =SCI!G37 -> 4371520.4 | I56: =SCI!H37 -> 6966209 | J56: =SCI!I37 -> 8100163.3 | ... V56: =SCI!U37 -> 8257922.8

Sheet form4
D3: RISK CLASSIFICATION OF ASSETS AND PROVISIONING | L3: RISK CLASSIFICATION OF ASSETS AND PROVISIONING
D4: SACCO SOCIETY CS NUMBER | L4: SACCO SOCIETY CS NUMBER
D5: FINANCIAL YEAR | L5: FINANCIAL YEAR
D6: START DATE: | L6: START DATE:
D7: END DATE: | L7: END DATE:
D8: PORTFOLIO AGEING REPORT | L8: PORTFOLIO AGEING REPORT
E9: A | F9: B | G9: C | H9: D | M9: A | N9: B | O9: C | P9: D
C10: NO. | D10: CLASSIFICATION | E10: NO. OF A/Cs | F10: OUTSTANDING LOAN PORTFOLIO(Kshs) | G10: REQUIRED PROVISION | H10: REQUIRED PROVISION AMOUNT(Kshs) | K10: NO. | L10: CLASSIFICATION | M10: NO. OF A/Cs | N10: OUTSTANDING LOAN PORTFOLIO(Kshs) | O10: REQUIRED PROVISION | P10: REQUIRED PROVISION AMOUNT(Kshs)
C11: 1 | D11: Performing | K11: 1 | L11: Performing
C12: 2 | D12: Watch | K12: 2 | L12: Watch
C13: 3 | D13: Substandard | K13: 3 | L13: Substandard
C14: 4 | D14: Doubtful | K14: 4 | L14: Doubtful
C15: 5 | D15: Loss | K15: 5 | L15: Loss
D16: subtotal | L16: subtotal | M16: =SUM(M11:M15) -> 0 | N16: =SUM(N11:N15) -> 0 | P16: =SUM(P11:P15) -> 0
D17: Reschedule/Renegotiated loans | L17: Reschedule/Renegotiated loans
C18: 1 | D18: Performing | K18: 1 | L18: Performing | M18: 0 | N18: 0 | O18: 0.01 | P18: =N18*O18 -> 0
C19: 2 | D19: Watch | K19: 2 | L19: Watch | M19: 0 | N19: 0 | O19: 0.05 | P19: =N19*O19 -> 0
C20: 3 | D20: Substandard | K20: 3 | L20: Substandard | M20: 0 | N20: 0 | O20: 0.25 | P20: =N20*O20 -> 0
C21: 4 | D21: Doubtful | K21: 4 | L21: Doubtful | M21: 0 | N21: 0 | O21: 0.5 | P21: =N21*O21 -> 0
C22: 5 | D22: Loss | K22: 5 | L22: Loss | M22: 0 | N22: 0 | O22: 1 | P22: =N22*O22 -> 0
D23: subtotal | E23: =SUM(E17:E22) -> 0 | F23: =SUM(F17:F22) -> 0 | H23: =SUM(H17:H22) -> 0 | L23: subtotal | M23: =SUM(M17:M22) -> 0 | N23: =SUM(N17:N22) -> 0 | P23: =SUM(P17:P22) -> 0
D24: GRAND TOTAL | E24: =E16+E23 -> 0 | F24: =F16+F23 -> 0 | H24: =H16+H23 -> 0 | L24: GRAND TOTAL | M24: =M16+M23 -> 0 | N24: =N16+N23 -> 0 | P24: =P16+P23 -> 0
F26: =F13+F14+F15 -> 0 | N26: =N13+N14+N15 -> 0
F27: =F26/F24 -> #DIV/0! | N27: =N26/N24 -> #DIV/0!
D30: RISK CLASSIFICATION OF ASSETS AND PROVISIONING
D31: SACCO SOCIETY CS NUMBER
D32: FINANCIAL YEAR
D33: START DATE:
D34: END DATE:
D35: PORTFOLIO AGEING REPORT
E36: A | F36: B | G36: C | H36: D
C37: NO. | D37: CLASSIFICATION | E37: NO. OF A/Cs | F37: OUTSTANDING LOAN PORTFOLIO(Kshs) | G37: REQUIRED PROVISION | H37: REQUIRED PROVISION AMOUNT(Kshs)
C38: 1 | D38: Performing
C39: 2 | D39: Watch
C40: 3 | D40: Substandard
C41: 4 | D41: Doubtful
C42: 5 | D42: Loss
D43: subtotal
D44: Reschedule/Renegotiated loans
C45: 1 | D45: Performing | H45: =F45*G45 -> 0
C46: 2 | D46: Watch | H46: =F46*G46 -> 0
C47: 3 | D47: Substandard | H47: =F47*G47 -> 0
C48: 4 | D48: Doubtful | H48: =F48*G48 -> 0
C49: 5 | D49: Loss | H49: =F49*G49 -> 0
D50: subtotal | E50: =SUM(E44:E49) -> 0 | F50: =SUM(F44:F49) -> 0 | H50: =SUM(H44:H49) -> 0
D51: GRAND TOTAL | E51: =E43+E50 -> 0 | F51: =F43+F50 -> 0 | H51: =H43+H50 -> 0
F53: =F40+F41+F42 -> 0
F54: =F53/F51 -> #DIV/0!
D56: RISK CLASSIFICATION OF ASSETS AND PROVISIONING
D57: SACCO SOCIETY CS NUMBER
D58: FINANCIAL YEAR
D59: START DATE:
D60: END DATE:
D61: PORTFOLIO AGEING REPORT
E62: A | F62: B | G62: C | H62: D
C63: NO. | D63: CLASSIFICATION | E63: NO. OF A/Cs | F63: OUTSTANDING LOAN PORTFOLIO(Kshs) | G63: REQUIRED PROVISION | H63: REQUIRED PROVISION AMOUNT(Kshs)
C64: 1 | D64: Performing
C65: 2 | D65: Watch
C66: 3 | D66: Substandard
C67: 4 | D67: Doubtful
C68: 5 | D68: Loss
D69: subtotal | E69: =SUM(E64:E68) -> 0 | F69: =SUM(F64:F68) -> 0 | H69: =SUM(H64:H68) -> 0
D70: Reschedule/Renegotiated loans
C71: 1 | D71: Performing | E71: 0 | F71: 0 | G71: 0.01 | H71: =F71*G71 -> 0
C72: 2 | D72: Watch | E72: 0 | F72: 0 | G72: 0.05 | H72: =F72*G72 -> 0
C73: 3 | D73: Substandard | E73: 0 | F73: 0 | G73: 0.25 | H73: =F73*G73 -> 0
C74: 4 | D74: Doubtful | E74: 0 | F74: 0 | G74: 0.5 | H74: =F74*G74 -> 0
C75: 5 | D75: Loss | E75: 0 | F75: 0 | G75: 1 | H75: =F75*G75 -> 0
D76: subtotal | E76: =SUM(E70:E75) -> 0 | F76: =SUM(F70:F75) -> 0 | H76: =SUM(H70:H75) -> 0
D77: GRAND TOTAL | E77: =E69+E76 -> 0 | F77: =F69+F76 -> 0 | H77: =H69+H76 -> 0
F79: =F66+F67+F68 -> 0
F80: =F79/F77 -> #DIV/0!

Sheet SFP
A1: HOMEBUSINESS SACCO SOCIETY LTD
A2: STATEMENT OF FINANCIAL POSITION
B3: AUDITED 2021 | C3: 44562 | D3: 44593 | E3: 44621 | F3: 44652 | G3: 44682 | H3: 44713 | I3: 44743 | J3: 44774 | K3: 44805 | L3: 44835 | M3: 44866 | N3: 44896 | O3: Audited-2022 | P3: 44949 | Q3: 44980 | R3: 45008 | S3: 45039 | T3: 45069 | U3: 45100 | V3: 45130 | W3: 45161
A4: Cash & Cash Equivalent | B4: =SUM(B5:B6) -> 32065169 | C4: =SUM(C5:C6) -> 34912846 | D4: =SUM(D5:D6) -> 41332419 | E4: =SUM(E5:E6) -> 44698661 | F4: =SUM(F5:F6) -> 42186283 | G4: =SUM(G5:G6) -> 37722223 | H4: =SUM(H5:H6) -> 30289909 | I4: =SUM(I5:I6) -> 31739783 | ... W4: =SUM(W5:W6) -> 9505274.5
A5: Cash in hand | B5: =2564179 -> 2564179 | C5: 7389364.8 | D5: 5773753.8 | E5: 6398099.8 | F5: 6563170.3 | G5: 6873142.3 | H5: 6532208.3 | I5: 4655373.3 | J5: 4119181.8 | K5: 4880512.3 | L5: 6703389.3 | M5: 6099339.3 | N5: 3746665.8 | O5: =2224896 -> 2224896 | P5: 5024003 | Q5: 8989085.1 | R5: 6610486.1 | S5: 3971152.1 | T5: 5446568.1 | U5: 4387640.8 | V5: 5208069.8 | W5: 3530423.8
A6: Cash at bank | B6: =32065169-B5 -> 29500990 | C6: 27523481 | D6: 35558665 | E6: 38300561 | F6: 35623113 | G6: 30849081 | H6: 23757701 | I6: 27084410 | J6: 26175745 | K6: 21968693 | L6: 12347676 | M6: 5845848.7 | N6: 8932841.4 | O6: =12671204-O5 -> 10446308 | P6: 14032298 | Q6: 4828004 | R6: 5989695.3 | S6: 19900291 | T6: 16321958 | U6: 17741385 | V6: 5660703.1 | W6: 5974850.7
A7: Prepayments & Sundry Receivables | B7: 12164278 | C7: 12269996 | D7: 12203072 | E7: 11833082 | F7: 11978436 | G7: 11886998 | H7: 12382822 | I7: 12380933 | J7: 12384919 | K7: 12700981 | L7: 12724110 | M7: 12666936 | N7: 12882091 | O7: 11749297 | P7: 12918331 | Q7: 12167132 | R7: 11399085 | S7: 11201811 | T7: 11168967 | U7: 11573320 | V7: 11584966 | W7: 11604125
A8: Financial Investments | B8: =SUM(B9:B13) -> 10760 | C8: =SUM(C9:C13) -> 10760 | D8: =SUM(D9:D13) -> 10760 | E8: =SUM(E9:E13) -> 10760 | F8: =SUM(F9:F13) -> 10760 | G8: =SUM(G9:G13) -> 10760 | H8: =SUM(H9:H13) -> 10760 | I8: =SUM(I9:I13) -> 10760 | ... W8: =SUM(W9:W13) -> 10760
A9: Government Securities - Treasury Bills/bonds, | C9: 0 | D9: 0 | E9: 0 | F9: 0 | G9: 0 | H9: 0 | I9: 0 | J9: 0 | K9: 0 | L9: 0 | M9: 0 | N9: 0 | P9: 0 | Q9: 0 | R9: 0 | S9: 0 | T9: 0 | U9: 0 | V9: 0 | W9: 0
A10: Other Securities - Commercial papers/Bonds | C10: 0 | D10: 0 | E10: 0 | F10: 0 | G10: 0 | H10: 0 | I10: 0 | J10: 0 | K10: 0 | L10: 0 | M10: 0 | N10: 0 | P10: 0 | Q10: 0 | R10: 0 | S10: 0 | T10: 0 | U10: 0 | V10: 0 | W10: 0
A11: Balances in NACCOS (E.g Jungu Kuu, ESS, Savings,Money Market,Coop FD, CFP) | C11: 0 | D11: 0 | E11: 0 | F11: 0 | G11: 0 | H11: 0 | I11: 0 | J11: 0 | K11: 0 | L11: 0 | M11: 0 | N11: 0 | P11: 0 | Q11: 0 | R11: 0 | S11: 0 | T11: 0 | U11: 0 | V11: 0 | W11: 0
A12: Equity Investments in NACCOs(Shares in- CIC, KUSCCO, COOP BANK,CAK, KERUSSU) | B12: =10760 -> 10760 | C12: 10760 | D12: 10760 | E12: 10760 | F12: 10760 | G12: 10760 | H12: 10760 | I12: 10760 | J12: 10760 | K12: 10760 | L12: 10760 | M12: 10760 | N12: 10760 | O12: 10760 | P12: 10760 | Q12: 10760 | R12: 10760 | S12: 10760 | T12: 10760 | U12: 10760 | V12: 10760 | W12: 10760
A13: Equity Investments in companies - shares/stocks
A14: Net Loan Portfolio | B14: =B15-B16 -> 171032210 | C14: =C15-C16 -> 1.7867275e+08 | D14: =D15-D16 -> 1.7735475e+08 | E14: =E15-E16 -> 1.7429213e+08 | F14: =F15-F16 -> 1.7216456e+08 | G14: =G15-G16 -> 1.76893e+08 | H14: =H15-H16 -> 1.8731825e+08 | I14: =I15-I16 -> 1.9061182e+08 | ... W14: =W15-W16 -> 2.3963256e+08
A15: Gross Loan Portfolio | B15: =179052670 -> 179052670 | C15: 1.7867275e+08 | D15: 1.7735475e+08 | E15: 1.7429213e+08 | F15: 1.7216456e+08 | G15: 1.76893e+08 | H15: 1.8731825e+08 | I15: 1.9061182e+08 | J15: 1.8922469e+08 | K15: 1.9276088e+08 | L15: 2.0741337e+08 | M15: 2.1833152e+08 | N15: 2.2096466e+08 | O15: =220964660 -> 220964660 | P15: 2.2265824e+08 | Q15: 2.3254746e+08 | R15: 2.3456685e+08 | S15: 2.3155913e+08 | T15: 2.2763696e+08 | U15: 2.3237587e+08 | V15: 2.3910809e+08 | W15: 2.3963256e+08
A16: Allowance for Loan Loss | B16: =8020460 -> 8020460 | C16: 0 | D16: 0 | E16: 0 | F16: 0 | G16: 0 | H16: 0 | I16: 0 | J16: 0 | K16: 0 | L16: 0 | M16: 0 | N16: 0 | O16: =14046909 -> 14046909 | P16: 0 | Q16: 0 | R16: 0 | S16: 0 | T16: 0 | U16: 0 | V16: 0 | W16: 0
A17: Accounts Receivables | C17: =SUM(C18:C20) -> 0 | D17: =SUM(D18:D20) -> 0 | E17: =SUM(E18:E20) -> 0 | F17: =SUM(F18:F20) -> 0 | G17: =SUM(G18:G20) -> 0 | H17: =SUM(H18:H20) -> 0 | I17: =SUM(I18:I20) -> 0 | J17: =SUM(J18:J20) -> 0 | ... U17: =SUM(U18:U20) -> 0
A18: Tax Recoverable | P18: 0 | Q18: 0 | R18: 0 | S18: 0 | T18: 0 | U18: 0 | V18: 0 | W18: 0
A19: Deferred Tax Assets | P19: 0 | Q19: 0 | R19: 0 | S19: 0 | T19: 0 | U19: 0 | V19: 0 | W19: 0
A20: Retirement Benefit Assets | P20: 0 | Q20: 0 | R20: 0 | S20: 0 | T20: 0 | U20: 0 | V20: 0 | W20: 0
A21: Property & Equipment & Other assets | B21: =SUM(B22:B26) -> 34870264 | C21: =SUM(C22:C26) -> 35706031 | D21: =SUM(D22:D26) -> 35854490 | E21: =SUM(E22:E26) -> 34506037 | F21: =SUM(F22:F26) -> 34779152 | G21: =SUM(G22:G26) -> 34950984 | H21: =SUM(H22:H26) -> 34958646 | I21: =SUM(I22:I26) -> 36000806 | ... W21: =SUM(W22:W26) -> 37623127
A22: Investment Properties | C22: 0 | D22: 0 | E22: 0 | F22: 0 | G22: 0 | H22: 0 | I22: 0 | J22: 0 | K22: 0 | L22: 0 | M22: 0 | N22: 0 | P22: 0 | Q22: 0 | R22: 0 | S22: 0 | T22: 0 | U22: 0 | V22: 0 | W22: 0
A23: Property & Equipment | B23: =34855454-B25 -> 33967722 | C23: 34377304 | D23: 34541884 | E23: 34550874 | F23: 34847989 | G23: 35016649 | H23: 35054174 | I23: 35113074 | J23: 36613859 | K23: 36725559 | L23: 36901659 | M23: 36907459 | N23: 36982359 | O23: =36674462-O25 -> 35964276 | P23: 37333764 | Q23: 37529764 | R23: 36482628 | S23: 36482629 | T23: 36412629 | U23: 36422779 | V23: 36831479 | W23: 36912941
A24: Prepaid Lease rentals | C24: 0 | D24: 0 | E24: 0 | F24: 0 | G24: 0 | H24: 0 | I24: 0 | J24: 0 | K24: 0 | L24: 0 | M24: 0 | N24: 0 | P24: 0 | Q24: 0 | R24: 0 | S24: 0 | T24: 0 | U24: 0 | V24: 0 | W24: 0
A25: Intangible Assets | B25: =887732 -> 887732 | C25: 887732 | D25: 887732 | E25: 887732 | F25: 887732 | G25: 887732 | H25: 887732 | I25: 887732 | J25: 0 | K25: 887732 | L25: 887732 | M25: 887732 | N25: 887732 | O25: =710186 -> 710186 | P25: 887732 | Q25: 887732 | R25: 710186 | S25: 710186 | T25: 710186 | U25: 710186 | V25: 710186 | W25: 710186
A26: Other Assets | B26: =14810 -> 14810 | C26: 440995.13 | D26: 424873.13 | E26: -932569.25 | F26: -956569.25 | G26: -953397.25 | H26: -983260.25 | I26: 0 | J26: 887732 | K26: 0 | L26: 0 | M26: 0 | N26: 9400 | O26: =115285+487378 -> 602663 | P26: 9400 | Q26: 9400 | R26: 0 | S26: 0 | T26: 0 | U26: 0 | V26: 0 | W26: 0
A27: Total Assets | B27: =B4+B7+B8+B14+B17+B21 -> 250142681 | C27: =C4+C7+C8+C14+C17+C21 -> 2.6157238e+08 | D27: =D4+D7+D8+D14+D17+D21 -> 2.6675549e+08 | E27: =E4+E7+E8+E14+E17+E21 -> 2.6534067e+08 | F27: =F4+F7+F8+F14+F17+F21 -> 2.6111919e+08 | G27: =G4+G7+G8+G14+G17+G21 -> 2.6146397e+08 | H27: =H4+H7+H8+H14+H17+H21 -> 2.6496039e+08 | I27: =I4+I7+I8+I14+I17+I21 -> 2.707441e+08 | ... W27: =W4+W7+W8+W14+W17+W21 -> 2.9837585e+08
A28: LIABILITIES
A29: Savings Deposits - Withdrawable deposits - FOSA) | B29: =10320478 -> 10320478 | C29: 10943389 | D29: 12240180 | E29: 22361583 | F29: 14977427 | G29: 13465773 | H29: 13909004 | I29: 14316078 | J29: 12771894 | K29: 11764951 | L29: 12405632 | M29: 11518320 | N29: 12841580 | O29: =12861582 -> 12861582 | P29: 14967932 | Q29: 14187865 | R29: 13903629 | S29: 19521092 | T29: 15234327 | U29: 19250493 | V29: 15059851 | W29: 14483966
A30: Short Term Deposits (e.g Fixed deposits, special savings) | B30: =8805374 -> 8805374 | C30: 932539.08 | D30: 1133814.1 | E30: 1212895.8 | F30: 978972.9 | G30: 1033357.9 | H30: 835015.9 | I30: 846889.9 | J30: 1023401.9 | K30: 987128.9 | L30: 1114954.9 | M30: 929122.9 | N30: 969566.9 | O30: =13869896 -> 13869896 | P30: 930371.9 | Q30: 906653.9 | R30: 937279.77 | S30: 844904.77 | T30: 856126.77 | U30: 892233.77 | V30: 980158.77 | W30: 1058663.8
A31: Non withdrawable deposits (BOSA member deposits) | B31: =160198883 -> 160198883 | C31: 1.7038893e+08 | D31: 1.734092e+08 | E31: 1.7514266e+08 | F31: 1.7773392e+08 | G31: 1.8038312e+08 | H31: 1.8193184e+08 | I31: 1.847225e+08 | J31: 1.8385655e+08 | K31: 1.8549063e+08 | L31: 1.8966634e+08 | M31: 1.9186784e+08 | N31: 1.903337e+08 | O31: =177433368 -> 177433368 | P31: 1.8985301e+08 | Q31: 1.9111504e+08 | R31: 1.9193631e+08 | S31: 1.9259483e+08 | T31: 1.9135635e+08 | U31: 1.9202521e+08 | V31: 1.9004509e+08 | W31: 1.8879294e+08
A32: Total Deposit liabilities | B32: =SUM(B29:B31) -> 179324735 | C32: =SUM(C29:C31) -> 1.8226486e+08 | D32: =SUM(D29:D31) -> 1.8678319e+08 | E32: =SUM(E29:E31) -> 1.9871714e+08 | F32: =SUM(F29:F31) -> 1.9369032e+08 | G32: =SUM(G29:G31) -> 1.9488225e+08 | H32: =SUM(H29:H31) -> 1.9667586e+08 | I32: =SUM(I29:I31) -> 1.9988547e+08 | ... W32: =SUM(W29:W31) -> 2.0433557e+08
A33: Accounts Payable & Other Liabilities | B33: =SUM(B34:B39) -> 18767985 | C33: =SUM(C34:C39) -> 15378418 | D33: =SUM(D34:D39) -> 14826183 | E33: =SUM(E34:E39) -> 14469532 | F33: =SUM(F34:F39) -> 13517187 | G33: =SUM(G34:G39) -> 13257886 | H33: =SUM(H34:H39) -> 12644496 | I33: =SUM(I34:I39) -> 14030245 | ... W33: =SUM(W34:W39) -> 24535787
A34: Tax Payable | B34: =645904 -> 645904 | C34: 0 | D34: 0 | E34: 0 | F34: 0 | G34: 0 | H34: 0 | I34: 0 | J34: 0 | K34: 0 | L34: 0 | M34: 0 | N34: 0 | O34: =256750 -> 256750 | P34: 0 | Q34: 0 | R34: 0 | S34: 0 | T34: 0 | U34: 0 | V34: 0 | W34: 0
A35: Dividends Payable | B35: =9611935 -> 9611935 | C35: 0 | D35: 0 | E35: 0 | F35: 0 | G35: 0 | H35: 0 | I35: 0 | J35: 0 | K35: 0 | L35: 0 | M35: 0 | N35: 0 | O35: =3548668 -> 3548668 | P35: 0 | Q35: 0 | R35: 0 | S35: 0 | T35: 0 | U35: 0 | V35: 0 | W35: 0
A36: Deferred Tax Liability | C36: 0 | D36: 0 | E36: 0 | F36: 0 | G36: 0 | H36: 0 | I36: 0 | J36: 0 | K36: 0 | L36: 0 | M36: 0 | N36: 0 | P36: 0 | Q36: 0 | R36: 0 | S36: 0 | T36: 0 | U36: 0 | V36: 0 | W36: 0
A37: Retirement Benefits Liability | C37: 0 | D37: 0 | E37: 0 | F37: 0 | G37: 0 | H37: 0 | I37: 0 | J37: 0 | K37: 0 | L37: 0 | M37: 0 | N37: 0 | P37: 0 | Q37: 0 | R37: 0 | S37: 0 | T37: 0 | U37: 0 | V37: 0 | W37: 0
A38: Other Liabilities | B38: =4135146 -> 4135146 | C38: 11628418 | D38: 11701183 | E38: 11969532 | F38: 11642187 | G38: 12007886 | H38: 12019496 | I38: 14030245 | J38: 14181930 | K38: 12758432 | L38: 13117416 | M38: 13441435 | N38: 8020895 | O38: =1457648 -> 1457648 | P38: 8237847 | Q38: 8513627 | R38: 8820303 | S38: 17917522 | T38: 17687734 | U38: 17962859 | V38: 18217564 | W38: 18364120
A39: External Borrowings | B39: 4375000 | C39: 3750000 | D39: 3125000 | E39: 2500000 | F39: 1875000 | G39: 1250000 | H39: 625000 | I39: 0 | J39: 0 | K39: 0 | L39: 0 | M39: 0 | N39: 0 | P39: 5000000 | Q39: 4583333.3 | R39: 4166666.7 | S39: 9750000 | T39: 8921666.3 | U39: 8004999.7 | V39: 7088333 | W39: 6171666.3
A40: Total Liabilities | B40: =B32+B33 -> 198092720 | C40: =C32+C33 -> 1.9764328e+08 | D40: =D32+D33 -> 2.0160938e+08 | E40: =E32+E33 -> 2.1318668e+08 | F40: =F32+F33 -> 2.0720751e+08 | G40: =G32+G33 -> 2.0814014e+08 | H40: =H32+H33 -> 2.0932035e+08 | I40: =I32+I33 -> 2.1391572e+08 | ... W40: =W32+W33 -> 2.2887135e+08
A41: EQUITY
A42: Share Capital (Members share capital per Bylaws) | B42: =32239051 -> 32239051 | C42: 32547014 | D42: 32672314 | E42: 32758228 | F42: 32977019 | G42: 33066186 | H42: 33117206 | I42: 33172601 | J42: 33250993 | K42: 33322015 | L42: 33385059 | M42: 33477031 | N42: 39083432 | O42: =38883432 -> 38883432 | P42: 39163514 | Q42: 39276555 | R42: 39332467 | S42: 39411108 | T42: 39570143 | U42: 39615935 | V42: 39654601 | W42: 39726614
A43: Capital Grants | B43: 200000 | C43: 0 | D43: 0 | E43: 0 | F43: 0 | G43: 0 | H43: 0 | I43: 0 | J43: 0 | K43: 0 | L43: 0 | M43: 0 | N43: 0 | O43: 200000 | P43: 0 | Q43: 0 | R43: 0 | S43: 0 | T43: 0 | U43: 0 | V43: 0 | W43: 0
A45: Retained Earnings | B45: =B47+B46 -> 7656031 | C45: =C47+C46 -> 24235430 | D45: =D47+D46 -> 25326643 | E45: =E47+E46 -> 11003101 | F45: =F47+F46 -> 12542995 | G45: =G47+G46 -> 12026171 | H45: =H47+H46 -> 14290860 | I45: =I47+I46 -> 15424814 | ... W45: =W47+W46 -> 21030645
A46: Prior Years' Retained Earnings | B46: =7042667 -> 7042667 | C46: 23338914 | D46: 23258002 | E46: 7654650.7 | F46: 7654633.7 | G46: 7654650.7 | H46: 7654650.7 | I46: 7654650.7 | J46: 7654650.7 | K46: 7668450.7 | L46: 7668450.7 | M46: 7668450.7 | N46: 7668450.7 | O46: =7656031 -> 7656031 | P46: 25403742 | Q46: 25403742 | R46: 24022920 | S46: 8449684 | T46: 8449684 | U46: 8449684 | V46: 8449684 | W46: 8449684
A47: Current Year's Surplus | B47: =7656031-B46 -> 613364 | C47: 896516.58 | D47: 2068641.6 | E47: 3348450 | F47: 4888361.1 | G47: 4371520.3 | H47: 6636209 | I47: 7770163.3 | J47: 8446493.8 | K47: 9712544 | L47: 11399873 | M47: 13616424 | N47: 17735291 | O47: =8289159-O46 -> 633128 | P47: 1374519.1 | Q47: 5038925.4 | R47: 4706525.2 | S47: 6360665.7 | T47: 6867685.7 | U47: 8257922.8 | V47: 10871726 | W47: 12580961
A49: Other Equity Accounts | B49: =SUM(B50:B54) -> 11954879 | C49: =SUM(C50:C54) -> 7146657 | D49: =SUM(D50:D54) -> 7147157 | E49: =SUM(E50:E54) -> 8392669.7 | F49: =SUM(F50:F54) -> 8391669.7 | G49: =SUM(G50:G54) -> 8231473.7 | H49: =SUM(H50:H54) -> 8231973.7 | I49: =SUM(I50:I54) -> 8230973.7 | ... W49: =SUM(W50:W54) -> 9234613.8
A50: Statutory Reserve | B50: =6730974 -> 6730974 | C50: 0 | D50: 0 | E50: 0 | F50: 0 | G50: 0 | H50: 0 | I50: 0 | J50: 8230973.7 | K50: 0 | L50: 0 | M50: 0 | N50: 0 | O50: =7534048 -> 7534048 | P50: 0 | Q50: 0 | R50: 8430973.7 | S50: 0 | T50: 0 | U50: 0 | V50: 0 | W50: 0
A51: Other Reserves (provide notes on these reserves) | C51: 7146657 | D51: 7147157 | E51: 8392669.7 | F51: 8391669.7 | G51: 8231473.7 | H51: 8231973.7 | I51: 8230973.7 | J51: 0 | K51: 8230973.7 | L51: 8230973.7 | M51: 8230973.7 | N51: 8230973.7 | P51: 8430973.7 | Q51: 8430973.7 | R51: 0 | S51: 9473534.1 | T51: 9252688.6 | U51: 9249977.5 | V51: 9234625.8 | W51: 9234613.8
A52: Revaluation Reserves (Not part of core capital) | B52: 1500000 | C52: 0 | D52: 0 | E52: 0 | F52: 0 | G52: 0 | H52: 0 | I52: 0 | J52: 0 | K52: 0 | L52: 0 | M52: 0 | N52: 0 | O52: 1700000 | P52: 0 | Q52: 0 | R52: 0 | S52: 0 | T52: 0 | U52: 0 | V52: 0 | W52: 0
A53: Proposed Dividends | B53: =3223905+500000 -> 3723905 | C53: 0 | D53: 0 | E53: 0 | F53: 0 | G53: 0 | H53: 0 | I53: 0 | J53: 0 | K53: 0 | L53: 0 | M53: 0 | N53: 0 | O53: =2333006+258580 -> 2591586 | P53: 0 | Q53: 0 | R53: 0 | S53: 0 | T53: 0 | U53: 0 | V53: 0 | W53: 0
A54: Adjustment to Equity | C54: 0 | D54: 0 | E54: 0 | F54: 0 | G54: 0 | H54: 0 | I54: 0 | J54: 0 | K54: 0 | L54: 0 | M54: 0 | N54: 0 | P54: 0 | Q54: 0 | R54: 0 | S54: 0 | T54: 0 | U54: 0 | V54: 0 | W54: 0
A55: Total Equity | B55: =B42+B43+B45+B49 -> 52049961 | C55: =C42+C43+C45+C49 -> 63929101 | D55: =D42+D43+D45+D49 -> 65146114 | E55: =E42+E43+E45+E49 -> 52153999 | F55: =F42+F43+F45+F49 -> 53911683 | G55: =G42+G43+G45+G49 -> 53323831 | H55: =H42+H43+H45+H49 -> 55640039 | I55: =I42+I43+I45+I49 -> 56828389 | ... W55: =W42+W43+W45+W49 -> 69991873
A56: Total Liabilities and Equity | B56: =B40+B55 -> 250142681 | C56: =C40+C55 -> 2.6157238e+08 | D56: =D40+D55 -> 2.6675549e+08 | E56: =E40+E55 -> 2.6534067e+08 | F56: =F40+F55 -> 2.6111919e+08 | G56: =G40+G55 -> 2.6146397e+08 | H56: =H40+H55 -> 2.6496039e+08 | I56: =I40+I55 -> 2.707441e+08 | ... W56: =W40+W55 -> 2.9886323e+08
B58: =B27-B56 -> 0 | N58: =N27-N56 -> -467379 | O58: =O56-O27 -> 0 | P58: =P56-P27 -> 487379 | Q58: =Q56-Q27 -> 487379 | R58: =R56-R27 -> 487379.5 | S58: =S56-S27 -> 487379 | T58: =T56-T27 -> 488379 | U58: =U56-U27 -> 487379

Sheet SCI
A1: HOMEBUSINESS SACCO SOCIETY LTD
A2: STATEMENT OF COMPREHENSIVE INCOME | B2: Audited 2021 | C2: 44562 | D2: 44593 | E2: 44621 | F2: 44652 | G2: 44682 | H2: 44713 | I2: 44743 | J2: 44774 | K2: 44805 | L2: 44835 | M2: 44866 | N2: 44896 | O2: Audited-2022 | P2: 44949 | Q2: 44980 | R2: 45008 | S2: 45039 | T2: 45069 | U2: 45100 | V2: 45130 | W2: 45161
A3: Financial Income | B3: =B4+B7 -> 37488109 | C3: =C4+C7 -> 2874057.6 | D3: =D4+D7 -> 5572732.6 | E3: =E4+E7 -> 8819043 | F3: =F4+F7 -> 11923967 | G3: =G4+G7 -> 15297125 | H3: =H4+H7 -> 19743282 | I3: =I4+I7 -> 22916419 | ... W3: =W4+W7 -> 30560464
A4: Financial Income from Loans Portfolio | B4: =SUM(B5:B6) -> 33124180 | C4: =SUM(C5:C6) -> 2785070.4 | D4: =SUM(D5:D6) -> 5397465.9 | E4: =SUM(E5:E6) -> 8522774.3 | F4: =SUM(F5:F6) -> 9872564 | G4: =SUM(G5:G6) -> 12680622 | H4: =SUM(H5:H6) -> 15643377 | I4: =SUM(I5:I6) -> 18266935 | ... W4: =SUM(W5:W6) -> 25459501
A5: Interest on Loan Portfolio | B5: =26538293 -> 26538293 | C5: 2274473 | D5: 3752249.6 | E5: 6051104.3 | F5: 8047045 | G5: 10096914 | H5: 12090354 | I5: 14064467 | J5: 15917636 | K5: 17881050 | L5: 20012478 | M5: 22258157 | N5: 24336179 | O5: =24336179 -> 24336179 | P5: 2363783.9 | Q5: 6647319.7 | R5: 7393429 | S5: 9818921.6 | T5: 12146247 | U5: 14434188 | V5: 16928091 | W5: 19390872
A6: Fees & Commission on Loan Portfolio | B6: =560854+147914+357803+4090980+665900+762436 -> 6585887 | C6: 510597.4 | D6: 1645216.3 | E6: 2471670 | F6: 1825519 | G6: 2583708 | H6: 3553023.7 | I6: 4202468.5 | J6: 4752213.3 | K6: 5494298 | L6: 6658341.2 | M6: 7651076.3 | N6: 8324949.7 | O6: =549073+11114+38502+373464+4669620+751100+2904230 -> 9297103 | P6: 615089.9 | Q6: 1923641.2 | R6: 2299739.1 | S6: 2821669.2 | T6: 3406222.4 | U6: 4359401.3 | V6: 5479288.2 | W6: 6068629.4
A7: Financial Income from Investments in: | B7: =SUM(B8:B11) -> 4363929 | C7: =SUM(C8:C11) -> 88987.18 | D7: =SUM(D8:D11) -> 175266.66 | E7: =SUM(E8:E11) -> 296268.76 | F7: =SUM(F8:F11) -> 2051403.1 | G7: =SUM(G8:G11) -> 2616503.1 | H7: =SUM(H8:H11) -> 4099904.6 | I7: =SUM(I8:I11) -> 4649483.8 | ... W7: =SUM(W8:W11) -> 5100963.5
A8: Government Securities | B8: 0 | C8: 0 | D8: 0 | E8: 0 | F8: 0 | G8: 0 | H8: 0 | I8: 0 | J8: 0 | K8: 0 | L8: 0 | M8: 0 | N8: 0 | P8: 0 | Q8: 0 | R8: 0 | S8: 0 | T8: 0 | U8: 0 | V8: 0 | W8: 0
A9: Deposit with Banks and Other Financial Inst. | B9: 0 | C9: 0 | D9: 0 | E9: 0 | F9: 0 | G9: 0 | H9: 0 | I9: 0 | J9: 0 | K9: 0 | L9: 0 | M9: 0 | N9: 0 | P9: 0 | Q9: 0 | R9: 0 | S9: 0 | T9: 0 | U9: 0 | V9: 0 | W9: 0
A10: Other Investments - dividend & Interest incomes from investments | C10: 0 | D10: 0 | E10: 0 | F10: 1643394.1 | G10: 2100760.6 | H10: 3455248.8 | I10: 0 | J10: 0 | K10: 0 | L10: 0 | M10: 0 | N10: 0 | O10: =755827 -> 755827 | P10: 0 | Q10: 0 | R10: 0 | S10: 0 | T10: 0 | U10: 0 | V10: 0 | W10: 0
A11: Other Operating Income- Salary processing fees, transaction fees, membership fees | B11: =10949816-B6 -> 4363929 | C11: 88987.18 | D11: 175266.66 | E11: 296268.76 | F11: 408008.96 | G11: 515742.43 | H11: 644655.83 | I11: 4649483.8 | J11: 5286713.4 | K11: 5932923.5 | L11: 6575476.9 | M11: 7645660.8 | N11: 11511779 | O11: =19080901-O6 -> 9783798 | P11: 575878.41 | Q11: 1574151.8 | R11: 1955884.1 | S11: 2561671.9 | T11: 3209485 | U11: 3772991.1 | V11: 4660156.3 | W11: 5100963.5
A12: Financial Expense | B12: =B13+B14+B15+B16+B17+B18 -> 9964422 | C12: =C13+C14+C15+C16+C17+C18 -> 41410 | D12: =D13+D14+D15+D16+D17+D18 -> 88680 | E12: =E13+E14+E15+E16+E17+E18 -> 160671 | F12: =F13+F14+F15+F16+F17+F18 -> 200821 | G12: =G13+G14+G15+G16+G17+G18 -> 243721 | H12: =H13+H14+H15+H16+H17+H18 -> 298871.92 | I12: =I13+I14+I15+I16+I17+I18 -> 338971.92 | ... W12: =W13+W14+W15+W16+W17+W18 -> 629457.27
A13: Interest Expense on Deposits | B13: =9611935+70380 -> 9682315 | C13: 0 | D13: 0 | E13: 0 | F13: 0 | G13: 0 | H13: 0 | I13: 0 | J13: 0 | K13: 399621.92 | L13: 0 | M13: 0 | N13: 0 | O13: =3548668+79940 -> 3628608 | P13: 0 | Q13: 0 | R13: 0 | S13: 0 | T13: 0 | U13: 0 | V13: 0 | W13: 0
A14: Cost of External Borrowings | C14: 41410 | D14: 0 | E14: 0 | F14: 200821 | G14: 243721 | H14: 298871.92 | I14: 338971.92 | J14: 394331.92 | K14: 0 | L14: 401871.92 | M14: 416091.92 | N14: 433691.92 | P14: 64708 | Q14: 141012.05 | R14: 191376.83 | S14: 244730.81 | T14: 333261.4 | U14: 408054.71 | V14: 492468.69 | W14: 629457.27
A15: Dividend Expenses (on member shares) | C15: 0 | D15: 0 | E15: 0 | F15: 0 | G15: 0 | H15: 0 | I15: 0 | J15: 0 | K15: 0 | L15: 0 | M15: 0 | N15: 0 | P15: 0 | Q15: 0 | R15: 0 | S15: 0 | T15: 0 | U15: 0 | V15: 0 | W15: 0
A16: Other Financial Expense | B16: =352487-70380 -> 282107 | C16: 0 | D16: 88680 | E16: 160671 | F16: 0 | G16: 0 | H16: 0 | I16: 0 | J16: 0 | K16: 0 | L16: 0 | M16: 0 | N16: 0 | O16: =433692-79940 -> 353752 | P16: 0 | Q16: 0 | R16: 0 | S16: 0 | T16: 0 | U16: 0 | V16: 0 | W16: 0
A17: Fees & Commission Expense | C17: 0 | D17: 0 | E17: 0 | F17: 0 | G17: 0 | H17: 0 | I17: 0 | J17: 0 | K17: 0 | L17: 0 | M17: 0 | N17: 0 | P17: 0 | Q17: 0 | R17: 0 | S17: 0 | T17: 0 | U17: 0 | V17: 0 | W17: 0
A18: Other Expense | C18: 0 | D18: 0 | E18: 0 | F18: 0 | G18: 0 | H18: 0 | I18: 0 | J18: 0 | K18: 0 | L18: 0 | M18: 0 | N18: 0 | P18: 0 | Q18: 0 | R18: 0 | S18: 0 | T18: 0 | U18: 0 | V18: 0 | W18: 0
A19: Net Financial Income/(Loss) | B19: =B3-B12 -> 27523687 | C19: =C3-C12 -> 2832647.6 | D19: =D3-D12 -> 5484052.6 | E19: =E3-E12 -> 8658372 | F19: =F3-F12 -> 11723146 | G19: =G3-G12 -> 15053404 | H19: =H3-H12 -> 19444410 | I19: =I3-I12 -> 22577447 | ... W19: =W3-W12 -> 29931007
A20: Allowance for Loan Loss | B20: =B21-B22 -> 51290 | C20: =C21-C22 -> 0 | D20: =D21-D22 -> 0 | E20: =E21-E22 -> 0 | F20: =F21-F22 -> 0 | G20: =G21-G22 -> 0 | H20: =H21-H22 -> 0 | I20: =I21-I22 -> 0 | ... W20: =W21-W22 -> 0
A21: Provision for Loan Losses | B21: =51290 -> 51290 | C21: 0 | D21: 0 | E21: 0 | F21: 0 | G21: 0 | H21: 0 | I21: 0 | J21: 0 | K21: 0 | L21: 0 | M21: 0 | N21: 0 | O21: =7222661 -> 7222661 | P21: 0 | Q21: 0 | R21: 0 | S21: 0 | T21: 0 | U21: 0 | V21: 0 | W21: 0
A22: Value of Loans Recovered | B22: 0 | C22: 0 | D22: 0 | E22: 0 | F22: 0 | G22: 0 | H22: 0 | I22: 0 | J22: 0 | K22: 0 | L22: 0 | M22: 0 | N22: 0 | P22: 0 | Q22: 0 | R22: 0 | S22: 0 | T22: 0 | U22: 0 | V22: 0 | W22: 0
A23: Operating Expenses | B23: =SUM(B24:B28) -> 21004907 | C23: =SUM(C24:C28) -> 1936131 | D23: =SUM(D24:D28) -> 3415411 | E23: =SUM(E24:E28) -> 5309922 | F23: =SUM(F24:F28) -> 6834785 | G23: =SUM(G24:G28) -> 10681884 | H23: =SUM(H24:H28) -> 12478201 | I23: =SUM(I24:I28) -> 14477284 | ... W23: =SUM(W24:W28) -> 17350046
A24: Personnel Expenses | B24: =7312796 -> 7312796 | C24: 640185 | D24: 1290517 | E24: 1892521 | F24: 2537362 | G24: 3183530 | H24: 3835995 | I24: 4558105 | J24: 5510964 | K24: 6287546 | L24: 7049212 | M24: 7837172 | N24: 8604157 | O24: =8604157 -> 8604157 | P24: 871250.2 | Q24: 1772356.2 | R24: 2601556.2 | S24: 3376778.2 | T24: 4143610.2 | U24: 4983806.2 | V24: 5767421.2 | W24: 6634842.2
A25: Governance Expenses | B25: =2120339 -> 2120339 | C25: 250300 | D25: 473540 | E25: 898180 | F25: 1117030 | G25: 1414696 | H25: 1734046 | I25: 2086993 | J25: 2332543 | K25: 2581943 | L25: 2916127 | M25: 3425177 | N25: 4144514 | O25: =3424364 -> 3424364 | P25: 281100 | Q25: 582085 | R25: 919085 | S25: 1357715 | T25: 1594250 | U25: 1834705 | V25: 2049717 | W25: 2232909
A26: Marketing Expenses | B26: =1283281 -> 1283281 | C26: 227763 | D26: 277525 | E26: 324305 | F26: 345605 | G26: 409407 | H26: 540682 | I26: 627413 | J26: 757245 | K26: 808269 | L26: 901468 | M26: 994160 | N26: 1039975 | O26: =1657275 -> 1657275 | P26: 30600 | Q26: 96440 | R26: 123593 | S26: 151734 | T26: 163034 | U26: 175234 | V26: 188564 | W26: 196064
A27: Depreciation and Amortization Charges | B27: =1052127 -> 1052127 | C27: 0 | D27: 0 | E27: 0 | F27: 0 | G27: 0 | H27: 0 | I27: 0 | J27: 0 | K27: 0 | L27: 0 | M27: 0 | N27: 0 | O27: =1380822 -> 1380822 | P27: 0 | Q27: 0 | R27: 0 | S27: 0 | T27: 0 | U27: 0 | V27: 0 | W27: 0
A28: Administrative Expenses | B28: =9236364 -> 9236364 | C28: 817883 | D28: 1373829 | E28: 2194916 | F28: 2834788 | G28: 5674251 | H28: 6367478 | I28: 7204773 | J28: 8184985 | K28: 9188348 | L28: 9808781 | M28: 10496906 | N28: 11446316 | O28: =11709691 -> 11709691 | P28: 932575 | Q28: 2514294 | R28: 3106916 | S28: 3710639 | T28: 5660113 | U28: 6906858 | V28: 7697639 | W28: 8286231
A29: Net Operating Income | B29: =B19-B20-B23 -> 6467490 | C29: =C19-C20-C23 -> 896516.63 | D29: =D19-D20-D23 -> 2068641.6 | E29: =E19-E20-E23 -> 3348450 | F29: =F19-F20-F23 -> 4888361.1 | G29: =G19-G20-G23 -> 4371520.4 | H29: =H19-H20-H23 -> 6966209 | I29: =I19-I20-I23 -> 8100163.3 | ... W29: =W19-W20-W23 -> 12580961
A30: Net Non- Operating Income/ (Expense) | B30: =B31-B32 -> 0 | C30: =C31-C32 -> 0 | D30: =D31-D32 -> 0 | E30: =E31-E32 -> 0 | F30: =F31-F32 -> 0 | G30: =G31-G32 -> 0 | H30: =H31-H32 -> 0 | I30: =I31-I32 -> 0 | ... W30: =W31-W32 -> 0
A31: Non- Operating Income | C31: 0 | D31: 0 | E31: 0 | F31: 0 | G31: 0 | H31: 0 | I31: 0 | J31: 0 | K31: 0 | L31: 0 | M31: 0 | N31: 0 | P31: 0 | Q31: 0 | R31: 0 | S31: 0 | T31: 0 | U31: 0
A32: Non- Operating Expense | C32: 0 | D32: 0 | E32: 0 | F32: 0 | G32: 0 | H32: 0 | I32: 0 | J32: 0 | K32: 0 | L32: 0 | M32: 0 | N32: 0 | P32: 0 | Q32: 0 | R32: 0 | S32: 0 | T32: 0 | U32: 0
A33: Net Income (Before Taxes and Donations) | B33: =B29+B30 -> 6467490 | C33: =C29+C30 -> 896516.63 | D33: =D29+D30 -> 2068641.6 | E33: =E29+E30 -> 3348450 | F33: =F29+F30 -> 4888361.1 | G33: =G29+G30 -> 4371520.4 | H33: =H29+H30 -> 6966209 | I33: =I29+I30 -> 8100163.3 | ... W33: =W29+W30 -> 12580961
A34: Taxes (Incomes taxes & Other payable to KRA) | B34: 1045904 | C34: 0 | D34: 0 | E34: 0 | F34: 0 | G34: 0 | H34: 0 | I34: 0 | J34: 330000 | K34: 330000 | L34: 768963 | M34: 768963 | N34: 768963 | O34: =2176210 -> 2176210 | P34: 0 | Q34: 0 | R34: 0 | S34: 0 | T34: 0 | U34: 0
A35: Net Income (After Taxes before Donations) | B35: =B33-B34 -> 5421586 | C35: =C33-C34 -> 896516.63 | D35: =D33-D34 -> 2068641.6 | E35: =E33-E34 -> 3348450 | F35: =F33-F34 -> 4888361.1 | G35: =G33-G34 -> 4371520.4 | H35: =H33-H34 -> 6966209 | I35: =I33-I34 -> 8100163.3 | ... W35: =W33-W34 -> 12580961
A36: Donations | C36: 0 | D36: 0 | E36: 0 | F36: 0 | G36: 0 | H36: 0 | I36: 0 | J36: 0 | K36: 0 | L36: 0 | M36: 0 | N36: 0 | P36: 0 | Q36: 0 | R36: 0 | S36: 0 | T36: 0 | U36: 0
A37: Net Income/(After Taxes and Donations) | B37: =B35-B36 -> 5421586 | C37: =C35-C36 -> 896516.63 | D37: =D35-D36 -> 2068641.6 | E37: =E35-E36 -> 3348450 | F37: =F35-F36 -> 4888361.1 | G37: =G35-G36 -> 4371520.4 | H37: =H35-H36 -> 6966209 | I37: =I35-I36 -> 8100163.3 | ... W37: =W35-W36 -> 12580961
B38: =5421586-B37 -> 0 | O38: =6963696-O37 -> 2948329

Sheet Sheet1
B2: Year | C2: AUDITED 2015 | D2: AUDITED 2016 | E2: AUDITED 2017 | F2: AUDITED 2018 | G2: 43466 | H2: 43497 | I2: 43525 | J2: 43556 | K2: 43586 | L2: 43617
A3: 2 | B3: Total Assets | C3: 4.6351889e+08 | D3: 4.5637093e+08 | E3: 4.3683362e+08 | F3: 590186392 | G3: 6.0231394e+08 | H3: 6.2625108e+08 | I3: 5.9828697e+08 | J3: 5.8907278e+08 | K3: 6.1710155e+08 | L3: 6.0417723e+08
A4: 3 | B4: Total Deposits | C4: 3.6391029e+08 | D4: 3.5281156e+08 | E4: 3.4681983e+08 | F4: 433315333 | G4: 4.3839535e+08 | H4: 4.542002e+08 | I4: 4.7118357e+08 | J4: 4.6306008e+08 | K4: 4.8617864e+08 | L4: 4.6622117e+08
A5: 3.1 | B5: Deposits-Members(BOSA) | C5: 2.4228165e+08 | D5: 2.4464437e+08 | E5: 2.4323434e+08 | F5: 365696388 | G5: 3.7313088e+08 | H5: 3.8056337e+08 | I5: 3.899621e+08 | J5: 3.9463998e+08 | K5: 3.9710517e+08 | L5: 4.0401425e+08
A6: 3.2 | B6: Deposits-Customers(FOSA) | C6: 4074376.9 | D6: 4984401.3 | E6: 5076228.9 | F6: 67618945 | G6: 14363008 | H6: 15611949 | I6: 13612359 | J6: 14419909 | K6: 14679037 | L6: 13096149
A7: 4 | B7: External Borrowing | C7: 782851.88 | D7: 782851.88 | E7: 782851.88 | F7: 0 | G7: 0 | H7: 0 | I7: 0 | J7: 0 | K7: 0 | L7: 0
A8: 4.1 | B8: Short term Liabilities | C8: 4642444.9 | D8: 27506534 | E8: 4912342.2 | F8: 58156529 | G8: 3901907.3 | H8: 4415903.4 | I8: -44130681 | J8: 10574287 | K8: 12876255 | L8: 10617410
A9: 5.1 | B9: Core Capital | C9: 94944699 | D9: 75269883 | E9: 78350880 | F9: 88729697 | G9: 1.5578813e+08 | H9: 1.6340642e+08 | I9: 1.6700553e+08 | J9: 1.1120986e+08 | K9: 1.138181e+08 | L9: 1.231101e+08
A10: 5.2 | B10: Institutional Capital | C10: 85006164 | D10: 65331348 | E10: 67704199 | F10: 65523502 | G10: 1.3199681e+08 | H10: 1.3957898e+08 | I10: 1.42917e+08 | J10: 87051631 | K10: 89639871 | L10: 98730332
A11: 5.3 | B11: Total Capital | C11: 94944699 | D11: 75269883 | E11: 78350880 | F11: 92958252 | G11: 1.6001668e+08 | H11: 1.6763498e+08 | I11: 1.7123408e+08 | J11: 1.1543841e+08 | K11: 1.1804665e+08 | L11: 1.2733866e+08
A12: 7 | B12: Net Loans & advances | C12: 2.9963107e+08 | D12: 3.0964314e+08 | E12: 3.1063977e+08 | F12: 467465209 | G12: 4.7291977e+08 | H12: 4.7868736e+08 | I12: 4.7578771e+08 | J12: 4.7958254e+08 | K12: 4.8126667e+08 | L12: 4.8527697e+08
A13: 7.1 | B13: Gross Loans & advances | C13: 3.0960349e+08 | D13: 3.1961557e+08 | E13: 3.2061219e+08 | F13: 478678153 | G13: 4.8413271e+08 | H13: 4.899003e+08 | I13: 4.8760561e+08 | J13: 4.9160208e+08 | K13: 4.9348786e+08 | L13: 4.9769982e+08
A14: 7.3 | B14: Allowance for loan losses | C14: 9972423.1 | D14: 9972423.1 | E14: 9972423.1 | F14: 11212944 | G14: 11212944 | H14: 11212944 | I14: 11817894 | J14: 12019544 | K14: 12221194 | L14: 12422844
... A19: 10 | B19: Total Expenses (FinCosts + OpEx) | C19: 22339455 | D19: 4546921.1 | E19: 5916993.1 | F19: 68345005 | G19: 18479434 | H19: 19450021 | I19: 21786998 | J19: 6653981.1 | K19: 12263359 | L19: 13807775
B21: CORE CAPITAL | C21: 94.944699 | D21: 75.269883 | E21: 78.35088 | F21: 88.729697 | G21: 155.78813 | H21: 163.40642 | I21: 167.00553 | J21: 111.20986 | K21: 113.8181 | L21: 123.1101
B22: CCA | C22: 0.20483458 | D22: 0.16493137 | E22: 0.17936092 | F22: 0.15034182 | G22: 0.25864938 | H22: 0.26092797 | I22: 0.2791395 | J22: 0.18878798 | K22: 0.18443982 | L22: 0.20376488
B23: ICA | C23: 0.18339309 | D23: 0.14315405 | E23: 0.15498853 | F23: 0.11102171 | G23: 0.21914952 | H23: 0.22288022 | I23: 0.23887701 | J23: 0.14777738 | K23: 0.14525951 | L23: 0.16341286
B24: CCD | C24: 0.26090139 | D24: 0.21334302 | E24: 0.22591234 | F24: 0.20476935 | G24: 0.3553599 | H24: 0.35976739 | I24: 0.35443835 | J24: 0.24016291 | K24: 0.23410757 | L24: 0.26405944
B25: Asset Quality
B26: NPL
B27: Earnings
B28: ROA | C28: 0.10366402 | D28: 0.0049791285 | E28: 0.0086990958 | F28: 0.021403287 | G28: 0.086521768 | H28: 0.092418745 | I28: 0.095308004 | J28: 0.025179366 | K28: 0.027427623 | L28: 0.036644694
B29: CIR | C29: 0.25741416 | D29: 0.47475461 | E29: 0.47309013 | F29: 0.59346691 | G29: 0.29062189 | H29: 0.28378981 | I29: 0.30491294 | J29: 0.3518848 | K29: 0.42614589 | L29: 0.38569897
B30: OER | C30: 0.050864587 | D30: 0.006821232 | E30: 0.012065152 | F30: 0.056671522 | G30: 0.054654004 | H30: 0.055574311 | I30: 0.067479629 | J30: 0.021463423 | K30: 0.030839954 | L30: 0.036261474
B31: MIN LIQ | C31: 0.28117848 | D31: 0.1804874 | E31: 0.14704211 | F31: 0.20525016 | G31: 0.26279967 | H31: 0.27638489 | I31: 0.26967942 | J31: 0.20183359 | K31: 0.21134839 | L31: 0.19694405
B32: TEC LIQ | C32: 0.18838483 | D32: 0.12915454 | E32: 0.10373806 | F32: 0.1770109 | G32: 0.2240215 | H32: 0.23200767 | I32: 0.21838892 | J32: 0.17267718 | K32: 0.17362602 | L32: 0.17125133
B33: EB | C33: 0.001688932 | D33: 0.0017153851 | E33: 0.0017921054 | F33: 0 | G33: 0 | H33: 0 | I33: 0 | J33: 0 | K33: 0 | L33: 0
B34: LIQ/TA | C34: 0.14978838 | D34: 0.10763133 | E34: 0.083528395 | F34: 0.14740407 | G34: 0.16450573 | H34: 0.16990382 | I34: 0.15588442 | J34: 0.13883827 | K34: 0.14041273 | L34: 0.13515776
B35: NEA | C35: 0.11800484 | D35: 0.12675515 | E35: 0.10067358 | F35: 0.053367462 | G35: 0.043302199 | H35: 0.058974292 | I35: 0.041797813 | J35: 0.039852185 | K35: 0.072852538 | L35: 0.054640365
B36: LB | C36: 0.01288188 | D36: 0.012663382 | E36: 0.013661078 | F36: 0.0051649463 | G36: 0.011631407 | H36: 0.01118682 | I36: 0.011457956 | J36: 0.010564849 | K36: 0.011089534 | L36: 0.010959528
B37: FITD | C37: 0.12176194 | D37: 0.11269646 | E37: 0.11464343 | F37: 0.0097586092 | G37: 0.0096455287 | H37: 0.0093098923 | I37: 0.0089743259 | J37: 0.009131763 | K37: 0.0086975334 | L37: 0.0090698477
B38: FICC | C38: 0.46669717 | D38: 0.52824067 | E38: 0.50746862 | F38: 0.047656592 | G38: 0.027142986 | H38: 0.025877532 | I38: 0.02531985 | J38: 0.038023203 | K38: 0.037151868 | L38: 0.03434775

Sheet DEC 2020
A1: MAGADI SACCO SOCIETY LIMITED
A2: PERFORMANCE AND COMPLIANCE REPORT AS AT : 31st December , 2020
B3: Prudential Standard | C3: Audited | D3: Returns | F3: AUDITED 2020 | G3: Aggregate for all Licensed Saccos
C4: 2019 | D4: 30th September , 2020 | E4: 31st December , 2020
A5: A. CAPITAL ADEQUACY
A6: Core Capital | B6: ≥10M | C6: =C33 -> 98409139 | D6: =D33 -> 1.5398554e+08 | E6: =E33 -> 1.7565742e+08 | F6: =F33 -> #REF! | G6: =G33 -> 9.281382e+10 | H6: =F6-C6 -> #REF!
A7: Core Capital/Total Assets | B7: ≥10% | C7: =C33/C29 -> 0.149196 | D7: =D33/D29 -> 0.21974079 | E7: =E33/E29 -> 0.23992254 | F7: =F33/F29 -> #REF! | G7: =G33/G29 -> 0.15852844
A8: Institutional Capital/Total Assets | B8: ≥8% | C8: =C34/C29 -> 0.11007419 | D8: =D34/D29 -> 0.18075965 | E8: =E34/E29 -> 0.2020382 | F8: =F34/F29 -> #REF! | G8: =G34/G29 -> 0.092879022
A9: B. ASSET QUALITY
A10: NPL (Substandard+Doubtful+Loss) | B10: <5% | C10: =C35/C32 -> 0 | D10: =D35/D32 -> 0.066804616 | E10: =E35/E32 -> 0.058669004 | F10: =F35/F32 -> #REF! | G10: =G35/G32 -> 0.081923116
A11: Non-Earning Assets | B11: <10% | C11: =C36/C29 -> 0.041460677 | D11: =D36/D29 -> 0.034504765 | E11: =E36/E29 -> 0.03147327 | F11: =F36/F29 -> #REF! | G11: =G36/G29 -> 0.10331964
A12: Equity investments/Deposits | B12: <5% | C12: =C38/C31 -> 0.0086859989 | D12: =D38/D31 -> 0.007972688 | E12: =E38/E31 -> 0.0078282924 | F12: =F38/F31 -> #REF! | G12: =G38/G31 -> 0.033894147
A13: Equity investments/Core capital | B13: <40% | C13: =C38/C33 -> 0.042969139 | D13: =D38/D33 -> 0.027460728 | E13: =E38/E33 -> 0.024072738 | F13: =F38/F33 -> #REF! | G13: =G38/G33 -> 0.14648774
A14: C. EARNINGS RATING
A15: Yield on Gross Loans | C15: =C48/C32 -> 0.18432223 | D15: =D48/D32 -> 0.1292034 | E15: =E48/E32 -> 0.17383407 | F15: =F48/F32 -> #REF! | G15: =G48/G32 -> 0.1744387
A16: Total Expense/Total Income | C16: =C49/C44 -> 0.81230275 | D16: =D49/D44 -> 0.33068826 | E16: =E49/E44 -> 0.33091343 | F16: =F49/F44 -> #REF! | G16: =G49/G44 -> 0.69938821
A17: Net Income/Average Assets (ROA) | C17: =C50/C30 -> 0.02237977 | D17: =D50/D30 -> 0.081626281 | E17: =E50/E30 -> 0.10964544 | F17: =F50/F30 -> #REF! | G17: =G50/G30 -> 0.038410442
A18: Operating Expenses/Financial Income (OPEX) | C18: =C47/C44 -> 0.32162796 | D18: =D47/D44 -> 0.28452022 | E18: =E47/E44 -> 0.28396284 | F18: =F47/F44 -> #REF! | G18: =G47/G44 -> 0.30079837
A19: D. LIQUIDITY
A20: Liquid Assets/Short-term Liabilities | B20: >15% | C20: =C40/C41 -> 0.59313783 | D20: =D40/D41 -> 1.4178168 | E20: =E40/E41 -> 2.0006732 | F20: =F40/F41 -> #REF! | G20: =G40/G41 -> 0.6151057
A21: External Borrowing/Total Assets | B21: <25% | C21: =C42/C29 -> 1.1611647e-05 | D21: =D42/D29 -> 0.011921445 | E21: =E42/E29 -> 0.010282182 | F21: =F42/F29 -> #REF! | G21: =G42/G29 -> 0.036576677
A22: Liquid Assets/Total Assets | C22: =C40/C29 -> 0.067680721 | D22: =D40/D29 -> 0.12936886 | E22: =E40/E29 -> 0.15742859 | F22: =F40/F29 -> #REF! | G22: =G40/G29 -> 0.11724056
A23: E. STRUCTURE/SENSITIVITY TO RISK
A24: Gross loans /Total Assets | B24: 70-80 | C24: =C32/C29 -> 0.82800207 | D24: =D32/D29 -> 0.86523081 | E24: =E32/E29 -> 0.83846194 | F24: =F32/F29 -> #REF! | G24: =G32/G29 -> 0.75523899
A25: Gross loans/Deposits | B25: >100% | C25: =C32/C31 -> 1.1218567 | D25: =D32/D31 -> 1.1431784 | E25: =E32/E31 -> 1.1364592 | F25: =F32/F31 -> #REF! | G25: =G32/G31 -> 1.1023021
A26: Financial Investments/Total Assets | C26: =C39/C31 -> 0.11977917 | D26: =D39/D31 -> 0.007972688 | E26: =E39/E31 -> 0.0078282924 | F26: =F39/F31 -> #REF! | G26: =G39/G31 -> 0.067272667
A27: Dividends+Interest on Deposits/Total Income | C27: =C46/C44 -> 0.48412627 | D27: =D46/D44 -> 0.012481243 | E27: =E46/E44 -> 0.0115585 | F27: =F46/F44 -> #REF! | G27: =G46/G44 -> 0.33833569
A28: F. KEY FINANCIAL STATISTICS | C28: 2015 | D28: 2016 | E28: 2017 | G28: AGGREGATE
A29: Total Assets | C29: 659596375 | D29: 7.0075991e+08 | E29: 7.321422e+08 | F29: =SFP!#REF! -> #REF! | G29: 5.8547109e+11
A30: Average Assets | C30: 6.2488266e+08 | D30: 6.6920187e+08 | E30: 6.9562445e+08 | F30: =(C29+F29)/2 -> #REF! | G30: 5.6966122e+11
A31: Total Deposits | C31: 486824375 | D31: 5.3038009e+08 | E31: 5.4016313e+08 | F31: =SFP!#REF! -> #REF! | G31: 4.0113376e+11
A32: Gross Loans | C32: 546147164 | D32: 6.0631906e+08 | E32: 6.1387337e+08 | F32: =SFP!#REF! -> #REF! | G32: 4.421706e+11
A33: Core Capital | C33: 98409139 | D33: 1.5398554e+08 | E33: 1.7565742e+08 | F33: =Financials!#REF! -> #REF! | G33: 9.281382e+10
A34: Institutional Capital | C34: 72604536 | D34: 1.2666911e+08 | E34: 1.4792069e+08 | F34: =Financials!#REF! -> #REF! | G34: 5.4377982e+10
A35: Non-performing Loans | C35: 0 | D35: 40504912 | E35: 36015340 | F35: =16172116+14580201+5263023 -> 36015340 | G35: 3.6223993e+10
A36: Non-Earning Assets | C36: 27347312 | D36: 24179556 | E36: 23042909 | F36: =Financials!#REF! -> #REF! | G36: 6.0490663e+10
A37: Property and Equipment | C37: 5678927 | D37: 5703357.5 | E37: 5726554 | F37: =Financials!#REF! -> #REF! | G37: 1.7300265e+10
A38: Equity Investments | C38: 4228556 | D38: 4228554.9 | E38: 4228554.9 | F38: =SFP!#REF!+SFP!#REF! -> #REF! | G38: 1.3596086e+10
A39: Financial Investments | C39: 58311419 | D39: 4228554.9 | E39: 4228554.9 | F39: =SFP!#REF! -> #REF! | G39: 2.6985337e+10
A40: Liquid Assets | C40: 44641958 | D40: 90656514 | E40: 1.1526011e+08 | F40: =SFP!#REF!+SFP!#REF! -> #REF! | G40: 6.8640959e+10
A41: Short-term Liabilities) | C41: 75264054 | D41: 63940921 | E41: 57610665 | F41: =SFP!#REF!+SFP!#REF!+SFP!#REF!-SFP!#REF! -> #REF! | G41: 1.1159213e+11
A42: External Borrowing | C42: 7659 | D42: 8354071 | E42: 7528019 | F42: =SFP!#REF! -> #REF! | G42: 2.1414587e+10
A43: Average Gross Loans | C43: 5.1241266e+08 | D43: 5.768587e+08 | E43: 5.7996732e+08 | F43: =(C32+E32)/2 -> 5.8001027e+08 | G43: 4.3131225e+11
A44: Total Income | C44: 119501967 | D44: 93225263 | E44: 1.2531687e+08 | F44: =SCI!#REF! -> #REF! | G44: 8.9459919e+10
A45: Net Financial Income/Loss | C45: 60865365 | D45: 88921235 | E45: 1.1943317e+08 | F45: =SCI!#REF! -> #REF! | G45: 5.3897612e+10
A46: Dividends+Interest on Deposits | C46: 57854041 | D46: 1163567.2 | E46: 1448475.1 | F46: =SCI!#REF! -> #REF! | G46: 3.0267483e+10
A47: Operating Expenses | C47: 38435174 | D47: 26524472 | E47: 35585335 | F47: =SCI!#REF! -> #REF! | G47: 2.6909398e+10
A48: Interest on Loan portfolio+Fees&Commission on Loan | C48: 100667063 | D48: 78338482 | E48: 1.0671211e+08 | F48: =SCI!#REF!+SCI!#REF! -> #REF! | G48: 7.7131665e+10
A49: Total Expenses | C49: 97071776 | D49: 30828500 | E49: 41469037 | F49: =SCI!#REF!+SCI!#REF!+SCI!#REF! -> #REF! | G49: 6.2567213e+10
A50: Net Income | C50: 13984730 | D50: 54624460 | E50: 76272050 | F50: =SCI!#REF! -> #REF! | G50: 2.1880939e+10
A51: G. AREAS OF IMPROVEMENT/REGULATORY CONCERNS
A52: 1
A53: 2
A54: 3
A55: 4
A56: Prepared by:
A58: Checked by:
A60: Approved by:
A62: DISCLAIMER: This report is prepared based on information submitted by the Sacco as at the stated date and may change upon verification by the Authority.

Sheet DEC 2019 REPORT
A1: EGERTON SACCO SOCIETY LIMITED
A2: PERFORMANCE AND COMPLIANCE REPORT AS AT : 31st December , 2019
B3: Prudential Standard | C3: Audited | D3: Returns | F3: Audited 2019 | G3: Aggregate for all Licensed Saccos
C4: 2018 | D4: 30th September , 2019 | E4: 31st December , 2019
A5: A. CAPITAL ADEQUACY
A6: Core Capital | B6: ≥10M | C6: 92958252 | D6: 1.14416e+08 | E6: 1.2704881e+08 | F6: =F33 -> #REF! | G6: 8.5391581e+10
A7: Core Capital/Total Assets | B7: ≥10% | C7: 0.15751126 | D7: 0.17943559 | E7: 0.19275909 | F7: =F6/F29 -> #REF! | G7: 0.15597716
A8: Institutional Capital/Total Assets | B8: ≥8% | C8: 0.11818998 | D8: 0.13976271 | E8: 0.15360974 | F8: =F34/F29 -> #REF! | G8: 0.091529477
A9: B. ASSET QUALITY
A10: NPL (Substandard+Doubtful+Loss) | B10: <5% | C10: 0 | D10: 0.057997794 | E10: 0.049062417 | F10: =F35/F32 -> #REF! | G10: 0.073407957
A11: Non-Earning Assets | B11: <10% | C11: 0.05336904 | D11: 0.043135899 | E11: 0.041315651 | F11: =F36/F29 -> #REF! | G11: 0.10567687
A12: Equity investments/Deposits | B12: <5% | C12: 0 | D12: 0.0086297878 | E12: 0.0086830722 | F12: =F38/F31 -> #REF! | G12: 0.034924323
A13: Equity investments/Core capital | B13: <40% | C13: 0 | D13: 0.036957724 | E13: 0.033282917 | F13: =F38/F33 -> #REF! | G13: 0.15379721
A14: C. EARNINGS RATING
A15: Yield on Gross Loans | C15: 0.1927038 | D15: 0.13877868 | E15: 0.18737466 | F15: =F48/F32 -> #REF! | G15: 0.16090341
A16: Total Expense/Total Income | C16: 0.79311986 | D16: 0.35836605 | E16: 0.33974951 | F16: =F49/F44 -> #REF! | G16: 0.7077997
A17: Net Income/Average Assets (ROA) | C17: 0.027977038 | D17: 0.081818348 | E17: 0.11400955 | F17: =F50/F30 -> #REF! | G17: 0.036975972
A18: Operating Expenses/Financial Income (OPEX) | C18: 0.30200757 | D18: 0.31934513 | E18: 0.30463818 | F18: =F47/F45 -> #REF! | G18: 0.31992697
A19: D. LIQUIDITY
A20: Liquid Assets/Short-term Liabilities | B20: >15% | C20: 1.1755674 | D20: 1.0116662 | E20: 1.4570234 | F20: =F40/F41 -> #REF! | G20: 0.54995224
A21: External Borrowing/Total Assets | B21: <25% | C21: 0 | D21: 0 | E21: 0 | F21: =F42/F29 -> #REF! | G21: 0.039238045
A22: Liquid Assets/Total Assets | C22: 0.14737887 | D22: 0.12043218 | E22: 0.149349 | F22: =F40/F29 -> #REF! | G22: 0.11016896
A23: E. STRUCTURE/SENSITIVITY TO RISK
A24: Gross loans /Total Assets | B24: 70-80 | C24: 0.81108665 | D24: 0.85847035 | E24: 0.82848691 | F24: =F32/F29 -> #REF! | G24: 0.75892188
A25: Gross loans/Deposits | B25: >100% | C25: 1.1046878 | D25: 1.1171503 | E25: 1.1213025 | F25: =F32/F31 -> #REF! | G25: 1.1048812
A26: Financial Investments/Total Assets | C26: 0.0097586092 | D26: 0.0086297878 | E26: 0.0086830722 | F26: =F39/F29 -> #REF! | G26: 0.059782935
A27: Dividends+Interest on Deposits/Total Income | C27: 0.48814819 | D27: 0.012035001 | E27: 0.012230217 | F27: =F46/F44 -> #REF! | G27: 0.32108527
A28: F. KEY FINANCIAL STATISTICS | C28: 2015 | D28: 2016 | E28: 2017 | G28: AGGREGATE
A29: Total Assets | C29: 590168948 | D29: 6.3764384e+08 | E29: 6.5910669e+08 | F29: =SFP!#REF! -> #REF! | G29: 5.4746207e+11
A30: Average Assets | C30: 5.6413338e+08 | D30: 6.1492399e+08 | E30: 6.4176168e+08 | F30: =(F29+C29)/2 -> #REF! | G30: 5.2079291e+11
A31: Total Deposits | C31: 433315333 | D31: 4.8999524e+08 | E31: 4.8698834e+08 | F31: =SFP!#REF! -> #REF! | G31: 3.7604128e+11
A32: Gross Loans | C32: 478678153 | D32: 5.4739833e+08 | E32: 5.4606127e+08 | F32: =SFP!#REF! -> #REF! | G32: 4.1548094e+11
A33: Core Capital | C33: 92958252 | D33: 1.14416e+08 | E33: 1.2704881e+08 | F33: =Financials!#REF! -> #REF! | G33: 8.5391581e+10
A34: Institutional Capital | C34: 69752057 | D34: 89118833 | E34: 1.0124521e+08 | F34: =Financials!#REF! -> #REF! | G34: 5.0108917e+10
A35: Non-performing Loans | C35: 0 | D35: 31747895 | E35: 26791086 | F35: =22604726+734025+3452334 -> 26791085 | G35: 3.0499607e+10
A36: Non-Earning Assets | C36: 31496750 | D36: 27505341 | E36: 27231422 | F36: =Financials!#REF! -> #REF! | G36: 5.7854076e+10
A37: Property and Equipment | C37: 7005759 | D37: 5982262.2 | E37: 5325780.8 | F37: =Financials!#REF! -> #REF! | G37: 1.7751024e+10
A38: Equity Investments | C38: 0 | D38: 4228554.9 | E38: 4228554.9 | F38: =SFP!#REF!+SFP!#REF! -> #REF! | G38: 1.3132987e+10
A39: Financial Investments | C39: 4228555 | D39: 4228554.9 | E39: 4228554.9 | F39: =SFP!#REF! -> #REF! | G39: 2.2480852e+10
A40: Liquid Assets | C40: 86978434 | D40: 76792836 | E40: 98436927 | F40: =SFP!#REF! -> #REF! | G40: 6.031333e+10
A41: Short-term Liabilities) | C41: 73988469 | D41: 75907286 | E41: 67560292 | F41: =SFP!#REF!+SFP!#REF!+SFP!#REF!-SFP!#REF! -> #REF! | G41: 1.0967012e+11
A42: External Borrowing | C42: 0 | D42: 0 | E42: 0 | F42: =SFP!#REF! -> #REF! | G42: 2.1481341e+10
A43: Average Gross Loans | C43: 445483841 | D43: 5.0462708e+08 | E43: 5.1208838e+08 | F43: =(C32+F32)/2 -> #REF! | G43: 3.9339201e+11
A44: Total Income | C44: 110748089 | D44: 89428467 | E44: 1.1935697e+08 | F44: =SCI!#REF! -> #REF! | G44: 7.9322865e+10
A45: Net Financial Income/Loss | C45: 56358341 | D45: 85938886 | E45: 1.1516619e+08 | F45: =SCI!#REF! -> #REF! | G45: 4.6800236e+10
A46: Dividends+Interest on Deposits | C46: 54061479 | D46: 1076271.7 | E46: 1459761.6 | F46: =SCI!#REF! -> #REF! | G46: 2.5469404e+10
A47: Operating Expenses | C47: 33446761 | D47: 28558545 | E47: 36360690 | F47: =SCI!#REF! -> #REF! | G47: 2.5377524e+10
A48: Interest on Loan portfolio+Fees&Commission on Loan | C48: 92243098 | D48: 75967218 | E48: 1.0231804e+08 | F48: =SCI!#REF! -> #REF! | G48: 6.6852299e+10
A49: Total Expenses | C49: 87836509 | D49: 32048126 | E49: 40551471 | F49: =SCI!#REF!+SCI!#REF! -> #REF! | G49: 5.61447e+10
A50: Net Income | C50: 15782781 | D50: 50312065 | E50: 73166962 | F50: =SCI!#REF! -> #REF! | G50: 1.9256824e+10
A51: G. AREAS OF IMPROVEMENT/REGULATORY CONCERNS
A52: 1
A53: 2
A54: 3
A55: 4
A56: Prepared by:
A58: Checked by: Nelly Kulei
A60: Approved by: Peter Owira
A62: DISCLAIMER: This report is prepared based on information submitted by the Sacco as at the stated date and may change upon verification by the Authority.
C63: 22nd January 2020
