Workbook

Sheet Evolutive SFP
B3: 2010 Audited | C3: 2020 Audited | D3: 44197 | E3: 44228 | F3: 44256 | G3: 44287 | H3: 44317 | I3: 44348 | J3: 44378 | K3: 44409 | L3: 44440 | M3: 44470 | N3: 44501 | O3: 44531 | P3: Audited 2021 | Q3: 44562 | R3: 44593 | S3: 44621 | T3: 44652 | U3: 44682 | V3: 44713 | W3: 44743 | X3: 44774 | Y3: 44805 | Z3: 44835 | AA3: 44866 | AB3: 44896 | AC3: Audited 2022 | AD3: 44927 | AE3: 44958 | AF3: 44986 | AG3: 45017 | AH3: 45047 | AI3: 45078 | AJ3: 45108 | AK3: 45139 | AL3: 45170 | AM3: 45200 | AN3: 45231 | AO3: 45261
A4: Cash & cash Equivalent | B4: =SUM(B5:B6) -> 19363224 | C4: =SUM(C5:C6) -> 1186661463 | D4: =SUM(D5:D6) -> 1.1993457e+09 | E4: =SUM(E5:E6) -> 1.3654641e+09 | F4: =SUM(F5:F6) -> 1.129074e+09 | G4: =SUM(G5:G6) -> 1.0480622e+09 | H4: =SUM(H5:H6) -> 1.1258064e+09 | I4: =SUM(I5:I6) -> 1.2289676e+09 | ... AO4: =SUM(AO5:AO6) -> 0
A5: Cash In Hand | B5: 19363224 | C5: 71159942 | D5: 71094887 | E5: 64180769 | F5: 82076706 | G5: 82690766 | H5: 71057242 | I5: 86176962 | J5: 48576241 | K5: 86479897 | L5: 43040000 | M5: 78734737 | N5: 59373863 | O5: 57477852 | P5: 57477851 | Q5: 74010359 | R5: 76570519 | S5: 56710281 | T5: 32503472 | U5: 70751510 | V5: 86512499 | W5: 86762865 | X5: 72632957 | Y5: 72761661 | Z5: 73446719 | AA5: 68049375 | AB5: 69909850 | AC5: 69909850 | AD5: 77197705 | AE5: 77878929 | AF5: 92195481 | AG5: 57204240 | AH5: 59786701
A6: Cash at Bank | C6: =1186661463-C5 -> 1115501521 | D6: 1.1282508e+09 | E6: 1.3012833e+09 | F6: 1.0469973e+09 | G6: 9.6537144e+08 | H6: 1.0547492e+09 | I6: 1.1427907e+09 | J6: 1.1300811e+09 | K6: 1.0380675e+09 | L6: 1.0254608e+09 | M6: 8.8940624e+08 | N6: 8.2057544e+08 | O6: 8.0752956e+08 | P6: =893579487-P5 -> 836101636 | Q6: 9.3621139e+08 | R6: 1.0102807e+09 | S6: 6.9644418e+08 | T6: 6.41969e+08 | U6: 5.3956227e+08 | V6: 8.947469e+08 | W6: 8.2544963e+08 | X6: 8.5824059e+08 | Y6: 8.4147679e+08 | Z6: 9.478447e+08 | AA6: 8.7719319e+08 | AB6: 8.3334523e+08 | AC6: =903255082-AC5 -> 833345232 | AD6: 7.2497531e+08 | AE6: 8.5470164e+08 | AF6: 8.1521916e+08 | AG6: 8.9248221e+08 | AH6: 9.5763111e+08
A7: Prepayment and Sundry | B7: 13400392 | C7: 235454944 | D7: 2.2559121e+08 | E7: 91640788 | F7: 2.3765693e+08 | G7: 2.5282469e+08 | H7: 2.977318e+08 | I7: 2.2952571e+08 | J7: 2.4091863e+08 | K7: 2.1094899e+08 | L7: 2.0767968e+08 | M7: 2.4459191e+08 | N7: 2.7724248e+08 | O7: 2.9454533e+08 | P7: 309943753 | Q7: 2.1210391e+08 | R7: 2.118811e+08 | S7: 2.4110865e+08 | T7: 2.3573908e+08 | U7: 2.5816694e+08 | V7: 1.2883274e+08 | W7: 2.1210391e+08 | X7: 2.6617587e+08 | Y7: 2.4756402e+08 | Z7: 2.4337265e+08 | AA7: 2.4949474e+08 | AB7: 2.8242188e+08 | AC7: 341667828 | AD7: 3.2108299e+08 | AE7: 3.5193824e+08 | AF7: 3.0559622e+08 | AG7: 2.9933887e+08 | AH7: 3.1091354e+08
A8: Financial Investment | B8: =SUM(B9:B13) -> 472260 | C8: =SUM(C9:C13) -> 157412388 | D8: =SUM(D9:D13) -> 1.5741239e+08 | E8: =SUM(E9:E13) -> 1.5741239e+08 | F8: =SUM(F9:F13) -> 1.5741239e+08 | G8: =SUM(G9:G13) -> 1.5741239e+08 | H8: =SUM(H9:H13) -> 1.5741239e+08 | I8: =SUM(I9:I13) -> 1.5741239e+08 | ... AO8: =SUM(AO9:AO13) -> 0
A9: Government Securities - Treasury Bills/bonds, | D9: 0 | E9: 0 | F9: 0 | G9: 0 | H9: 0 | I9: 0 | J9: 0 | K9: 0 | L9: 0 | M9: 0 | N9: 0 | O9: 0 | Q9: 0 | R9: 0 | S9: 0 | T9: 0 | U9: 0 | V9: 0 | W9: 0 | X9: 0 | Y9: 0 | Z9: 0 | AA9: 0 | AB9: 0 | AD9: 0 | AE9: 0 | AF9: 0 | AG9: 0 | AH9: 0
A10: Other Securities - Commercial papers/Bonds | D10: 0 | E10: 0 | F10: 0 | G10: 0 | H10: 0 | I10: 0 | J10: 0 | K10: 0 | L10: 0 | M10: 0 | N10: 0 | O10: 0 | Q10: 0 | R10: 0 | S10: 0 | T10: 0 | U10: 0 | V10: 0 | W10: 0 | X10: 0 | Y10: 0 | Z10: 0 | AA10: 0 | AB10: 0 | AD10: 0 | AE10: 0 | AF10: 0 | AG10: 0 | AH10: 0
A11: Balances in NACCOS (E.g Jungu Kuu, ESS, Savings,Money Market,Coop FD, CFP) | C11: 125423070 | D11: 0 | E11: 0 | F11: 0 | G11: 0 | H11: 0 | I11: 0 | J11: 0 | K11: 0 | L11: 0 | M11: 0 | N11: 0 | O11: 0 | Q11: 0 | R11: 0 | S11: 0 | T11: 0 | U11: 0 | V11: 0 | W11: 0 | X11: 0 | Y11: 0 | Z11: 0 | AA11: 0 | AB11: 0 | AD11: 0 | AE11: 0 | AF11: 0 | AG11: 0 | AH11: 0
A12: Equity Investments in NACCOs(Shares in- CIC, KUSCCO, COOP BANK,CAK, KERUSSU) | P12: =59803722+55190200+22842624 -> 137836546 | AC12: =61067405+56821568+22842624 -> 140731597 | AD12: 1.7295931e+08 | AE12: 1.7295931e+08 | AF12: 1.7511853e+08 | AG12: 1.7516794e+08 | AH12: 1.7816794e+08
A13: Equity Investments in companies - shares/stocks | B13: 472260 | C13: 31989318 | D13: 1.5741239e+08 | E13: 1.5741239e+08 | F13: 1.5741239e+08 | G13: 1.5741239e+08 | H13: 1.5741239e+08 | I13: 1.5741239e+08 | J13: 1.5741239e+08 | K13: 1.5741239e+08 | L13: 1.6741239e+08 | M13: 1.6741239e+08 | N13: 1.6741239e+08 | O13: 1.6741857e+08 | P13: =11000+212180+10000000+21783318 -> 32006498 | Q13: 1.6984304e+08 | R13: 1.6984304e+08 | S13: 1.6984304e+08 | T13: 1.6984304e+08 | U13: 1.6984304e+08 | V13: 1.6984304e+08 | W13: 1.6984304e+08 | X13: 1.6984304e+08 | Y13: 1.7294304e+08 | Z13: 1.7187441e+08 | AA13: 1.7187441e+08 | AB13: 1.7295931e+08 | AC13: =11000+433398+10000000+21783318 -> 32227716
A14: Net Loan Portfolio | B14: =B15-B16 -> 112905266 | C14: =C15-C16 -> 7149156133 | D14: =D15-D16 -> 7.2160637e+09 | E14: =E15-E16 -> 7.1948815e+09 | F14: =F15-F16 -> 7.215068e+09 | G14: =G15-G16 -> 7.2856309e+09 | H14: =H15-H16 -> 7.330742e+09 | I14: =I15-I16 -> 7.370498e+09 | ... AO14: =AO15-AO16 -> 0
A15: Gross Loan Portfolio | B15: 112905266 | C15: 7688694111 | D15: 7.7556017e+09 | E15: 7.7344194e+09 | F15: 7.754606e+09 | G15: 7.8251689e+09 | H15: 7.87028e+09 | I15: 7.910036e+09 | J15: 8.1669084e+09 | K15: 8.3936515e+09 | L15: 8.5535783e+09 | M15: 8.7589601e+09 | N15: 8.8866027e+09 | O15: 9.0034511e+09 | P15: =9003451092-47156983 -> 8956294109 | Q15: 9.0557914e+09 | R15: 9.0327801e+09 | S15: 9.1723237e+09 | T15: 9.3345847e+09 | U15: 9.4575521e+09 | V15: 9.5086131e+09 | W15: 9.5457763e+09 | X15: 9.6413399e+09 | Y15: 9.7427157e+09 | Z15: 9.8500429e+09 | AA15: 9.967396e+09 | AB15: 1.0173845e+10 | AC15: =10173845465-24538804 -> 10149306661 | AD15: 1.0379787e+10 | AE15: 1.0441268e+10 | AF15: 1.037734e+10 | AG15: 1.0439485e+10 | AH15: 1.0512103e+10
A16: Allowance For Loan Loss | C16: 539537978 | D16: 5.3953798e+08 | E16: 5.3953798e+08 | F16: 5.3953798e+08 | G16: 5.3953798e+08 | H16: 5.3953798e+08 | I16: 5.3953798e+08 | J16: 5.3953798e+08 | K16: 5.3953798e+08 | L16: 5.8482781e+08 | M16: 5.8482781e+08 | N16: 5.8482781e+08 | O16: 5.8482781e+08 | P16: 584827806 | Q16: 5.8482781e+08 | R16: 5.8482781e+08 | S16: 5.8482781e+08 | T16: 5.8482781e+08 | U16: 5.8482781e+08 | V16: 5.8482781e+08 | W16: 5.8482781e+08 | X16: 5.8482781e+08 | Y16: 5.8482781e+08 | Z16: 5.8482781e+08 | AA16: 5.8482781e+08 | AB16: 6.1661922e+08 | AC16: 616619221 | AD16: 6.1661922e+08 | AE16: 6.1661922e+08 | AF16: 6.1661922e+08 | AG16: 6.1661922e+08 | AH16: 6.1661922e+08
A17: Accounts Recievables | B17: =SUM(B18:B20) -> 0 | C17: =SUM(C18:C20) -> 0 | D17: =SUM(D18:D20) -> 0 | E17: =SUM(E18:E20) -> 0 | F17: =SUM(F18:F20) -> 0 | G17: =SUM(G18:G20) -> 0 | H17: =SUM(H18:H20) -> 0 | I17: =SUM(I18:I20) -> 0 | ... AO17: =SUM(AO18:AO20) -> 0
A18: Tax Recoverable | D18: 0 | E18: 0 | F18: 0 | G18: 0 | H18: 0 | I18: 0 | J18: 0 | K18: 0 | L18: 0 | M18: 0 | N18: 0 | O18: 0 | Q18: 0 | R18: 0 | S18: 0 | T18: 0 | U18: 0 | V18: 0 | W18: 0 | X18: 0 | Y18: 0 | Z18: 0 | AA18: 0 | AB18: 0 | AD18: 0 | AE18: 0 | AF18: 0 | AG18: 0 | AH18: 0
A19: Deffered Tax Assets | D19: 0 | E19: 0 | F19: 0 | G19: 0 | H19: 0 | I19: 0 | J19: 0 | K19: 0 | L19: 0 | M19: 0 | N19: 0 | O19: 0 | Q19: 0 | R19: 0 | S19: 0 | T19: 0 | U19: 0 | V19: 0 | W19: 0 | X19: 0 | Y19: 0 | Z19: 0 | AA19: 0 | AB19: 0 | AD19: 0 | AE19: 0 | AF19: 0 | AG19: 0 | AH19: 0
A20: Retirement Benefit Assets | D20: 0 | E20: 0 | F20: 0 | G20: 0 | H20: 0 | I20: 0 | J20: 0 | K20: 0 | L20: 0 | M20: 0 | N20: 0 | O20: 0 | Q20: 0 | R20: 0 | S20: 0 | T20: 0 | U20: 0 | V20: 0 | W20: 0 | X20: 0 | Y20: 0 | Z20: 0 | AA20: 0 | AB20: 0 | AD20: 0 | AE20: 0 | AF20: 0 | AG20: 0 | AH20: 0
A21: Property&Equipments&Other Assets | B21: =SUM(B22:B26) -> 4874587 | C21: =SUM(C22:C26) -> 607544048 | D21: =SUM(D22:D26) -> 6.1606518e+08 | E21: =SUM(E22:E26) -> 6.2052776e+08 | F21: =SUM(F22:F26) -> 6.2782642e+08 | G21: =SUM(G22:G26) -> 6.697945e+08 | H21: =SUM(H22:H26) -> 6.6972438e+08 | I21: =SUM(I22:I26) -> 6.7010486e+08 | ... AO21: =SUM(AO22:AO26) -> 0
A22: Investment Properties | D22: 0 | E22: 0 | F22: 0 | G22: 0 | H22: 0 | I22: 0 | J22: 0 | K22: 0 | L22: 0 | M22: 0 | N22: 0 | O22: 0 | Q22: 0 | R22: 0 | S22: 0 | T22: 0 | U22: 0 | V22: 0 | W22: 0 | X22: 0 | Y22: 0 | Z22: 0 | AA22: 0 | AB22: 0 | AD22: 0 | AE22: 0 | AF22: 0 | AG22: 0 | AH22: 0
A23: Property and Equipment | B23: 4123114 | C23: 579283128 | D23: 5.8274388e+08 | E23: 5.8720645e+08 | F23: 5.9450511e+08 | G23: 6.3505704e+08 | H23: 6.3498692e+08 | I23: 6.353674e+08 | J23: 6.3358533e+08 | K23: 6.3602331e+08 | L23: 6.3556596e+08 | M23: 6.3111301e+08 | N23: 6.3077416e+08 | O23: 6.402222e+08 | P23: 633753814 | Q23: 6.4384704e+08 | R23: 6.4395363e+08 | S23: 6.5090977e+08 | T23: 6.6184113e+08 | U23: 6.6402104e+08 | V23: 6.6511028e+08 | W23: 6.6402969e+08 | X23: 6.7369624e+08 | Y23: 6.7243864e+08 | Z23: 6.7309274e+08 | AA23: 6.747107e+08 | AB23: 6.3393232e+08 | AC23: 633932317 | AD23: 6.3396572e+08 | AE23: 6.3396712e+08 | AF23: 6.3418647e+08 | AG23: 6.3698501e+08 | AH23: 6.3975022e+08
A24: Prepaid Lease Rentals | B24: 0 | D24: 0 | E24: 0 | F24: 0 | G24: 0 | H24: 0 | I24: 0 | J24: 0 | K24: 0 | L24: 0 | M24: 0 | N24: 0 | O24: 0 | P24: 68525600 | Q24: 0 | R24: 0 | S24: 0 | T24: 0 | U24: 0 | V24: 0 | W24: 0 | X24: 0 | Y24: 0 | Z24: 0 | AA24: 0 | AB24: 0 | AC24: 53084619 | AD24: 0 | AE24: 0 | AF24: 0 | AG24: 0 | AH24: 0
A25: Intangible Assets | B25: 751473 | C25: 28260920 | D25: 33321303 | E25: 33321303 | F25: 33321303 | G25: 34737461 | H25: 34737461 | I25: 34737461 | J25: 34737461 | K25: 40159858 | L25: 40159858 | M25: 40864561 | N25: 43849814 | O25: 39346542 | P25: 33694359 | Q25: 33694358 | R25: 33694358 | S25: 33694358 | T25: 33694358 | U25: 33694358 | V25: 33694358 | W25: 34555661 | X25: 34555661 | Y25: 34555661 | Z25: 34454592 | AA25: 34454592 | AB25: 27563673 | AC25: 27563674 | AD25: 27563673 | AE25: 27969673 | AF25: 29146336 | AG25: 29146336 | AH25: 29146336
A26: Other Assets | D26: 0 | E26: 0 | F26: 0 | G26: 0 | H26: 0 | I26: 0 | J26: 0 | K26: 0 | L26: 0 | M26: 0 | N26: 0 | O26: 0 | Q26: 0 | R26: 0 | S26: 0 | T26: 0 | U26: 0 | V26: 0 | W26: 0 | X26: 0 | Y26: 0 | Z26: 0 | AA26: 0 | AB26: 53084619 | AD26: 53084619 | AE26: 53084619 | AF26: 53084619 | AG26: 53084619 | AH26: 53084619
A27: Total Assets | B27: =B21+B17+B14+B8+B7+B4 -> 151015729 | C27: =C21+C17+C14+C8+C7+C4 -> 9336228976 | D27: =D21+D17+D14+D8+D7+D4 -> 9.4144782e+09 | E27: =E21+E17+E14+E8+E7+E4 -> 9.4299265e+09 | F27: =F21+F17+F14+F8+F7+F4 -> 9.3670378e+09 | G27: =G21+G17+G14+G8+G7+G4 -> 9.4137247e+09 | H27: =H21+H17+H14+H8+H7+H4 -> 9.581417e+09 | I27: =I21+I17+I14+I8+I7+I4 -> 9.6565086e+09 | ... AO27: =AO21+AO17+AO14+AO8+AO7+AO4 -> 0
A28: Savings and Deposits | B28: 8112861 | C28: 1118546479 | D28: 1.0843669e+09 | E28: 1.4050558e+09 | F28: 1.2529135e+09 | G28: 1.1431006e+09 | H28: 1.2169547e+09 | I28: 1.2038998e+09 | J28: 1.2826575e+09 | K28: 1.2938957e+09 | L28: 1.2867665e+09 | M28: 1.3195104e+09 | N28: 1.2592196e+09 | O28: 1.2673884e+09 | P28: 1267293882 | Q28: 1.2750749e+09 | R28: 1.5248446e+09 | S28: 1.4459929e+09 | T28: 1.3720656e+09 | U28: 1.3068513e+09 | V28: 1.3265124e+09 | W28: 1.3498962e+09 | X28: 1.3266615e+09 | Y28: 1.3092713e+09 | Z28: 1.3857114e+09 | AA28: 1.3353798e+09 | AB28: 1.3639084e+09 | AC28: 1363908356 | AD28: 1.3585821e+09 | AE28: 1.3336941e+09 | AF28: 1.5138488e+09 | AG28: 1.4510465e+09 | AH28: 1.3942938e+09
A29: Short Terrm Deposits | B29: 8350444 | C29: 165712109 | D29: 1.7373398e+08 | E29: 1.6442902e+08 | F29: 1.7534657e+08 | G29: 1.8570167e+08 | H29: 1.8210822e+08 | I29: 1.8625198e+08 | J29: 2.0898967e+08 | K29: 2.0717101e+08 | L29: 2.1814953e+08 | M29: 2.1045662e+08 | N29: 2.1220052e+08 | O29: 2.173301e+08 | P29: 217330105 | Q29: 2.1968595e+08 | R29: 2.2087098e+08 | S29: 2.1548053e+08 | T29: 2.3550602e+08 | U29: 2.4532091e+08 | V29: 2.4638285e+08 | W29: 2.5501694e+08 | X29: 2.5814958e+08 | Y29: 2.6603487e+08 | Z29: 2.692215e+08 | AA29: 2.7107526e+08 | AB29: 2.7186715e+08 | AC29: 271867152 | AD29: 2.6683207e+08 | AE29: 2.7553704e+08 | AF29: 2.7158627e+08 | AG29: 2.9326017e+08 | AH29: 3.124133e+08
A30: Non Withdrawable Deposits | B30: 112140909 | C30: 4971582622 | D30: 5.0085457e+09 | E30: 5.0766374e+09 | F30: 5.1343177e+09 | G30: 5.1829369e+09 | H30: 5.2103221e+09 | I30: 5.237309e+09 | J30: 5.2225161e+09 | K30: 5.2612718e+09 | L30: 5300041062 | M30: 5.3365909e+09 | N30: 5.372213e+09 | O30: 5.3695071e+09 | P30: 5369507091 | Q30: 5.4110797e+09 | R30: 5.4520542e+09 | S30: 5.5334779e+09 | T30: 5.6000184e+09 | U30: 5.6598068e+09 | V30: 5.6448613e+09 | W30: 5.6694143e+09 | X30: 5.7066621e+09 | Y30: 5.7661407e+09 | Z30: 5.8261148e+09 | AA30: 5.8652798e+09 | AB30: 5.8489689e+09 | AC30: 5848968899 | AD30: 5.8963193e+09 | AE30: 5.9634304e+09 | AF30: 6.0618108e+09 | AG30: 6.1395274e+09 | AH30: 6.197427e+09
A31: Total Deposit Liabilities | B31: =SUM(B28:B30) -> 128604214 | C31: =SUM(C28:C30) -> 6255841210 | D31: =SUM(D28:D30) -> 6.2666466e+09 | E31: =SUM(E28:E30) -> 6.6461222e+09 | F31: =SUM(F28:F30) -> 6.5625777e+09 | G31: =SUM(G28:G30) -> 6.5117392e+09 | H31: =SUM(H28:H30) -> 6.609385e+09 | I31: =SUM(I28:I30) -> 6.6274607e+09 | ... AO31: =SUM(AO28:AO30) -> 0
A32: Tax Payable | B32: 27231 | D32: -13835405 | E32: 17880614 | F32: -7523073.3 | G32: -13432063 | H32: -13100262 | I32: -20177393 | J32: -17389765 | K32: -14295084 | L32: -17231272 | M32: -16957170 | N32: -14273111 | O32: -14219253 | Q32: -14887838 | R32: 4442710.5 | S32: 29728042 | T32: 798420.33 | U32: -7479120.8 | V32: -11260224 | W32: -15792090 | X32: -12722775 | Y32: -15431861 | Z32: -15495114 | AA32: -11210499 | AB32: -10775825 | AD32: 6029754.8 | AE32: -1498420.1 | AF32: 33744996 | AG32: -3140267.4 | AH32: 5420569.2
A33: Dividends Payable | B33: 3618123 | C33: 401925569 | D33: 4.8580807e+08 | E33: 57580450 | F33: 24253441 | G33: 0 | H33: 0 | I33: 0 | J33: 0 | K33: 0 | L33: 0 | M33: 0 | N33: 0 | O33: 0 | Q33: 73574687 | R33: 73574687 | S33: 0 | T33: 0 | U33: 0 | V33: 0 | W33: 0 | X33: 0 | Y33: 0 | Z33: 0 | AA33: 0 | AB33: 0 | AD33: 558203769 | AE33: 5.5820377e+08 | AF33: 228321.55 | AG33: 0 | AH33: 130358.45
A34: Deferred Tax Liability | D34: 0 | E34: 0 | F34: 0 | G34: 0 | H34: 0 | I34: 0 | J34: 0 | K34: 0 | L34: 0 | M34: 0 | N34: 0 | O34: 0 | Q34: 0 | R34: 0 | S34: 0 | T34: 0 | U34: 0 | V34: 0 | W34: 0 | X34: 0 | Y34: 0 | Z34: 0 | AA34: 0 | AB34: 0 | AD34: 0 | AE34: 0 | AF34: 0 | AG34: 0 | AH34: 0
A35: Retirement Benefits Liabilty | D35: 0 | E35: 0 | F35: 0 | G35: 0 | H35: 0 | I35: 0 | J35: 0 | K35: 0 | L35: 0 | M35: 0 | N35: 0 | O35: 0 | Q35: 0 | R35: 0 | S35: 0 | T35: 0 | U35: 0 | V35: 0 | W35: 0 | X35: 0 | Y35: 0 | Z35: 0 | AA35: 0 | AB35: 0 | AD35: 0 | AE35: 0 | AF35: 0 | AG35: 0 | AH35: 0
A36: Other Liabilities | B36: 1214920 | C36: 123510261 | D36: 1.1061644e+08 | E36: 1.3686272e+08 | F36: 1.1222867e+08 | G36: 1.5682148e+08 | H36: 1.4580487e+08 | I36: 1.8613174e+08 | J36: 1.5496973e+08 | K36: 1.5306707e+08 | L36: 1.5227298e+08 | M36: 1.3008995e+08 | N36: 1.3765938e+08 | O36: 1.3034001e+08 | P36: =162640194+417974099+68370330 -> 648984623 | Q36: 5.5605262e+08 | R36: 2.6105248e+08 | S36: 76247334 | T36: 77405427 | U36: 70802575 | V36: 66803216 | W36: 39976134 | X36: 68051806 | Y36: 1.1686473e+08 | Z36: 81491113 | AA36: 59294320 | AB36: 1.0529982e+08 | AC36: =118249803+453041596+50534282 -> 621825681 | AD36: 1.269311e+08 | AE36: 1.2281647e+08 | AF36: 1.1174483e+08 | AG36: 1.1875776e+08 | AH36: 1.0411862e+08
A37: External Borrowings | B37: 2291669 | C37: 267946962 | D37: 2.6228029e+08 | E37: 2.5661363e+08 | F37: 2.4410948e+08 | G37: 2.3645754e+08 | H37: 2.3277615e+08 | I37: 2.231077e+08 | J37: 2.1569446e+08 | K37: 2.1177437e+08 | L37: 1.9923961e+08 | M37: 1.9357294e+08 | N37: 1.8634212e+08 | O37: 1.7949033e+08 | P37: 179490328 | Q37: 1.7382366e+08 | R37: 1.6815699e+08 | S37: 1.5564523e+08 | T37: 1.4997856e+08 | U37: 1.443119e+08 | V37: 2.8152379e+08 | W37: 2.8152379e+08 | X37: 2.7319046e+08 | Y37: 2.6281033e+08 | Z37: 2.5864366e+08 | AA37: 2.5447699e+08 | AB37: 2.4392589e+08 | AC37: 243925890 | AD37: 2.3975922e+08 | AE37: 3.3559156e+08 | AF37: 3.7457138e+08 | AG37: 3.7040471e+08 | AH37: 4.1623805e+08
A38: Total Liabilities | B38: =SUM(B31:B37) -> 135756157 | C38: =SUM(C31:C37) -> 7049224002 | D38: =SUM(D31:D37) -> 7.111516e+09 | E38: =SUM(E31:E37) -> 7.1150596e+09 | F38: =SUM(F31:F37) -> 6.9356463e+09 | G38: =SUM(G31:G37) -> 6.8915862e+09 | H38: =SUM(H31:H37) -> 6.9748658e+09 | I38: =SUM(I31:I37) -> 7.0165228e+09 | ... AO38: =SUM(AO31:AO37) -> 0
A39: Share Capital | B39: 10494697 | C39: 427075433 | D39: 4.2720733e+08 | E39: 4.283188e+08 | F39: 4.2915738e+08 | G39: 4.2951151e+08 | H39: 4.2973546e+08 | I39: 4.2996121e+08 | J39: 4.7769255e+08 | K39: 4.7819789e+08 | L39: 4.7828621e+08 | M39: 4.7868861e+08 | N39: 4.7878854e+08 | O39: 5.2744065e+08 | P39: 527440648 | Q39: 5.2770646e+08 | R39: 5.2882166e+08 | S39: 5.3392741e+08 | T39: 5.3627147e+08 | U39: 5.3701714e+08 | V39: 6.0871855e+08 | W39: 6.1523682e+08 | X39: 6.2356796e+08 | Y39: 6.2409114e+08 | Z39: 6.2709848e+08 | AA39: 6.2788842e+08 | AB39: 7.2547426e+08 | AC39: 725474265 | AD39: 7.2634853e+08 | AE39: 7.267321e+08 | AF39: 7.2819082e+08 | AG39: 7.3046416e+08 | AH39: 7.314276e+08
A40: Capital Grants | B40: 340425 | D40: 0 | E40: 0 | F40: 0 | G40: 0 | H40: 0 | I40: 0 | J40: 0 | K40: 0 | L40: 0 | M40: 0 | N40: 0 | O40: 0 | Q40: 0 | R40: 0 | S40: 0 | T40: 0 | U40: 0 | V40: 0 | W40: 0 | X40: 0 | Y40: 0 | Z40: 0 | AA40: 0 | AB40: 0 | AD40: 0 | AE40: 0 | AF40: 0 | AG40: 0 | AH40: 0
A41: Prior Year Retained Earnigs | B41: 351220 | C41: 566196154 | D41: 739449224 | E41: 739449224 | F41: 739449224 | G41: 739449224 | H41: 739449224 | I41: 739449224 | J41: 739449224 | K41: 739449224 | L41: 739449224 | M41: 739449224 | N41: 739449224 | O41: 7.3975785e+08 | P41: 739449224 | Q41: 9.6849842e+08 | R41: 934082627 | S41: 934082627 | T41: 934082627 | U41: 934082627 | V41: 934082627 | W41: 934082627 | X41: 934082627 | Y41: 934082627 | Z41: 934082627 | AA41: 934082627 | AB41: 934082627 | AC41: 934082627 | AD41: 1043966058 | AE41: 1043966058 | AF41: 1043966058 | AG41: 1043966058 | AH41: 1043966058
A42: Current Year Surplus | B42: 3541956 | C42: 173253070 | D42: 79610495 | E42: 1.4195739e+08 | F42: 2.1849279e+08 | G42: 3.0423397e+08 | H42: 3.8457498e+08 | I42: 4.6048523e+08 | J42: 5.7342103e+08 | K42: 6.7349342e+08 | L42: 7.0730119e+08 | M42: 7.8268328e+08 | N42: 8.7249037e+08 | O42: 9.3364459e+08 | P42: =934082627-739449224 -> 194633403 | Q42: 82950293 | R42: 1.5443153e+08 | S42: 2.2988154e+08 | T42: 3.2966847e+08 | U42: 4.2125916e+08 | V42: 5.0126191e+08 | W42: 5.6087188e+08 | X42: 6.5651261e+08 | Y42: 7.2941856e+08 | Z42: 8.2219669e+08 | AA42: 8.9564013e+08 | AB42: 8.8893016e+08 | AC42: =1043966058-AC41 -> 109883431 | AD42: 1.0464317e+08 | AE42: 1.8427297e+08 | AF42: 2.5995918e+08 | AG42: 3.4533525e+08 | AH42: 4.3185227e+08
A43: Statutory Reserves | B43: 531274 | C43: 413899587 | D43: 413899587 | E43: 413899587 | F43: 413899587 | G43: 413899587 | H43: 413899587 | I43: 413899587 | J43: 413899587 | K43: 413899587 | L43: 413899587 | M43: 413899587 | N43: 413899587 | O43: 413899587 | P43: 506776281 | Q43: 506776281 | R43: 506776281 | S43: 506776281 | T43: 506776281 | U43: 506776281 | V43: 506776281 | W43: 506776281 | X43: 506776281 | Y43: 506776281 | Z43: 506776281 | AA43: 506776281 | AB43: 506776281 | AC43: 586186303 | AD43: 586186303 | AE43: 586186303 | AF43: 586186303 | AG43: 586186303 | AH43: 586186303
A44: Other Reserves | C44: 577648161 | D44: 5.7364995e+08 | E44: 5.220963e+08 | F44: 5.6124702e+08 | G44: 5.6589871e+08 | H44: 5.6974642e+08 | I44: 5.2704505e+08 | J44: 5.3163586e+08 | K44: 5.3613489e+08 | L44: 5.4074902e+08 | M44: 5.6912521e+08 | N44: 5.7386827e+08 | O44: 5.9143844e+08 | P44: 684514426 | Q44: 6.8876855e+08 | R44: 6.9349685e+08 | S44: 7.0339641e+08 | T44: 7.1120566e+08 | U44: 7.1844383e+08 | V44: 7.2529232e+08 | W44: 7.2188624e+08 | X44: 7.1915433e+08 | Y44: 6.2799895e+08 | Z44: 6.4458942e+08 | AA44: 6.5079202e+08 | AB44: 6.8225179e+08 | AC44: 784131791 | AD44: 7.9046246e+08 | AE44: 7.9848247e+08 | AF44: 8.0969638e+08 | AG44: 8.2073317e+08 | AH44: 8.3075624e+08
A45: Revaluation Reserves | C45: 69145550 | D45: 69145550 | E45: 69145550 | F45: 69145550 | G45: 69145550 | H45: 69145550 | I45: 69145550 | J45: 69145550 | K45: 69145550 | L45: 69145550 | M45: 69145550 | N45: 69145550 | O45: 69145550 | P45: 69733709 | Q45: 71570025 | R45: 71570026 | S45: 71570025 | T45: 71570025 | U45: 71570025 | V45: 71570025 | W45: 71570025 | X45: 71570025 | Y45: 71570025 | Z45: 68870025 | AA45: 68870025 | AB45: 69733709 | AC45: 69733709 | AD45: 69733709 | AE45: 69733709 | AF45: 69733709 | AG45: 69733709 | AH45: 69733709
A46: Proposed Dividends | C46: 59787019 | D46: 0 | E46: 0 | F46: 0 | G46: 0 | H46: 0 | I46: 0 | J46: 0 | K46: 0 | L46: 0 | M46: 0 | N46: 0 | O46: 0 | P46: 73816323 | Q46: 0 | R46: 0 | S46: 0 | T46: 0 | U46: 0 | V46: 0 | W46: 0 | X46: 0 | Y46: 0 | Z46: 0 | AA46: 0 | AB46: 0 | AC46: 105162173 | AD46: 0 | AE46: 0 | AF46: 0 | AG46: 0 | AH46: 0
A47: Adjustment To Equity | D47: 0 | E47: 0 | F47: 0 | G47: 0 | H47: 0 | I47: 0 | J47: 0 | K47: 0 | L47: 0 | M47: 0 | N47: 0 | O47: 0 | Q47: 0 | R47: 0 | S47: 0 | T47: 0 | U47: 0 | V47: 0 | W47: 0 | X47: 0 | Y47: 0 | Z47: 0 | AA47: 0 | AB47: 0 | AD47: 0 | AE47: 0 | AF47: 0 | AG47: 0 | AH47: 0
A48: Total Equity | B48: =SUM(B39:B47) -> 15259572 | C48: =SUM(C39:C47) -> 2287004974 | D48: =SUM(D39:D47) -> 2.3029621e+09 | E48: =SUM(E39:E47) -> 2.3148669e+09 | F48: =SUM(F39:F47) -> 2.4313915e+09 | G48: =SUM(G39:G47) -> 2.5221385e+09 | H48: =SUM(H39:H47) -> 2.6065512e+09 | I48: =SUM(I39:I47) -> 2.6399858e+09 | ... AO48: =SUM(AO39:AO47) -> 0
A49: Total Liabilities and Equity | B49: =B48+B38 -> 151015729 | C49: =C48+C38 -> 9336228976 | D49: =D48+D38 -> 9.4144782e+09 | E49: =E48+E38 -> 9.4299265e+09 | F49: =F48+F38 -> 9.3670378e+09 | G49: =G48+G38 -> 9.4137247e+09 | H49: =H48+H38 -> 9.581417e+09 | I49: =I48+I38 -> 9.6565086e+09 | ... AO49: =AO48+AO38 -> 0
B51: =B49-B27 -> 0 | C51: =C49-C27 -> 0 | D51: =D49-D27 -> 0 | E51: =E49-E27 -> 0 | F51: =F49-F27 -> 0 | G51: =G49-G27 -> 0 | H51: =H49-H27 -> 0 | I51: =I49-I27 -> 0 | ... T51: =T49-T27 -> 0

Sheet Evolutitve SCI
B2: 2010 Audited | C2: 2020 Audited | D2: 44197 | E2: 44229 | F2: 44256 | G2: 44287 | H2: 44317 | I2: 44348 | J2: 44378 | K2: 44409 | L2: 44440 | M2: 44470 | N2: 44501 | O2: 44531 | P2: Audited 2021 | Q2: 44562 | R2: 44594 | S2: 44623 | T2: 44655 | U2: 44686 | V2: 44718 | W2: 44749 | X2: 44781 | Y2: 44813 | Z2: 44844 | AA2: 44876 | AB2: 44907 | AC2: Audited 2022 | AD2: 44927 | AE2: 44958 | AF2: 44986 | AG2: 45017 | AH2: 45047 | AI2: 45078 | AJ2: 45108 | AK2: 45139 | AL2: 45170 | AM2: 45200 | AN2: 45231 | AO2: 45261
A3: Financial Income | B3: =B4+B7 -> 14599.248 | C3: =C4+C7 -> 1503261371 | D3: =D4+D7 -> 1.169427e+08 | E3: =E4+E7 -> 2.3852756e+08 | F3: =F4+F7 -> 3.6201062e+08 | G3: =G4+G7 -> 4.9556922e+08 | H3: =H4+H7 -> 6.2683176e+08 | I3: =I4+I7 -> 7.5305629e+08 | ... AO3: =AO4+AO7 -> 0
A4: Financial Income From Loans Portfolio | B4: =SUM(B5:B6) -> 12855.806 | C4: =SUM(C5:C6) -> 1314774709 | D4: =SUM(D5:D6) -> 1.1038567e+08 | E4: =SUM(E5:E6) -> 2.2393112e+08 | F4: =SUM(F5:F6) -> 3.3557547e+08 | G4: =SUM(G5:G6) -> 4.5158493e+08 | H4: =SUM(H5:H6) -> 5.664239e+08 | I4: =SUM(I5:I6) -> 6.8229315e+08 | ... AO4: =SUM(AO5:AO6) -> 0
A5: Interest from Loans Portfolio | B5: 11945.435 | C5: 1292172434 | D5: 1.0724226e+08 | E5: 2.1674843e+08 | F5: 3.2431578e+08 | G5: 4.3543457e+08 | H5: 5.4532057e+08 | I5: 6.566322e+08 | J5: 7.9034447e+08 | K5: 9.1573935e+08 | L5: 1.0409189e+09 | M5: 1.1501458e+09 | N5: 1.2835108e+09 | O5: 1.4373591e+09 | P5: 1437359142 | Q5: 1.1905529e+08 | R5: 2.3960593e+08 | S5: 3.6212741e+08 | T5: 4.8761182e+08 | U5: 6.1146928e+08 | V5: 7.3394652e+08 | W5: 8.5609378e+08 | X5: 9.8341094e+08 | Y5: 1.1096128e+09 | Z5: 1.2367882e+09 | AA5: 1.3691651e+09 | AB5: 1.5186394e+09 | AC5: 1518639420 | AD5: 1.3731046e+08 | AE5: 2.7003874e+08 | AF5: 4.0377777e+08 | AG5: 5.3500543e+08 | AH5: 6.6883192e+08
A6: Fees&Commision on Loan Portfolio | B6: 910.371 | C6: 22602275 | D6: 3143406 | E6: 7182686 | F6: 11259690 | G6: 16150367 | H6: 21103328 | I6: 25660954 | J6: 36607501 | K6: 44965366 | L6: 52401611 | M6: 59521532 | N6: 65866904 | O6: 72153117 | P6: 26375034 | Q6: 4601895 | R6: 9508398 | S6: 16747201 | T6: 24209782 | U6: 30599874 | V6: 35894338 | W6: 40742974 | X6: 47125633 | Y6: 53385790 | Z6: 59781478 | AA6: 66748978 | AB6: 75227349 | AC6: =32359113 -> 32359113 | AD6: 8192344 | AE6: 13813635 | AF6: 19105782 | AG6: 24812556 | AH6: 30676058
A7: Financial Income from Investments | B7: =SUM(B8:B11) -> 1743.4416 | C7: =SUM(C8:C11) -> 188486662 | D7: =SUM(D8:D11) -> 6557028.2 | E7: =SUM(E8:E11) -> 14596437 | F7: =SUM(F8:F11) -> 26435153 | G7: =SUM(G8:G11) -> 43984291 | H7: =SUM(H8:H11) -> 60407858 | I7: =SUM(I8:I11) -> 70763135 | ... AO7: =SUM(AO8:AO11) -> 0
A8: Government Securities | C8: 0 | D8: 0 | E8: 0 | F8: 0 | G8: 0 | H8: 0 | I8: 0 | J8: 0 | K8: 0 | L8: 0 | M8: 0 | N8: 0 | O8: 0 | Q8: 0 | R8: 0 | S8: 0 | T8: 0 | U8: 0 | V8: 0 | W8: 0 | X8: 0 | Y8: 0 | Z8: 0 | AA8: 0 | AB8: 0 | AD8: 0 | AE8: 0 | AF8: 0 | AG8: 0 | AH8: 0
A9: Deposits with Banks & other Financial Institutions | D9: 0 | E9: 1684493.2 | F9: 5022849.4 | G9: 8151324.8 | H9: 18552624 | I9: 22975340 | J9: 25093182 | K9: 27917517 | L9: 31693896 | M9: 37441438 | N9: 43065188 | O9: 47550759 | Q9: 3111974.9 | R9: 3189587.1 | S9: 5565144.7 | T9: 10152412 | U9: 14663014 | V9: 19885286 | W9: 19975340 | X9: 20066379 | Y9: 20155431 | Z9: 21874818 | AA9: 24804407 | AB9: 33542847 | AD9: 952934.28 | AE9: 4078413.7 | AF9: 6080188.9 | AG9: 9289270.7 | AH9: 13304941
A10: Other Investments | C10: 38218859 | D10: 1149036 | E10: 1149036 | F10: 1149036 | G10: 8519440.6 | H10: 8519440.6 | I10: 8519440.6 | J10: 8519440.6 | K10: 8519440.6 | L10: 8519440.6 | M10: 8519440.6 | N10: 8519440.6 | O10: 8519440.6 | P10: 47550760 | Q10: 0 | R10: 0 | S10: 0 | T10: 0 | U10: 0 | V10: 7105530.7 | W10: 7105530.7 | X10: 7105530.7 | Y10: 7105530.7 | Z10: 8736898.7 | AA10: 8736898.7 | AB10: 8736898.7 | AC10: 33791415 | AD10: 0 | AE10: 0 | AF10: 2159221 | AG10: 2211229 | AH10: 2211229
A11: Other Operating Income | B11: 1743.4416 | C11: 150267803 | D11: 5407992.2 | E11: 11762907 | F11: 20263268 | G11: 27313526 | H11: 33335794 | I11: 39268355 | J11: 46945389 | K11: 53926995 | L11: 61788706 | M11: 68183835 | N11: 76288923 | O11: 82444124 | P11: 195546974 | Q11: 6530062.4 | R11: 13285083 | S11: 23195226 | T11: 31501640 | U11: 39121337 | V11: 46693625 | W11: 54072635 | X11: 61718602 | Y11: 68836494 | Z11: 76778931 | AA11: 84745420 | AB11: 93743365 | AC11: =8429759+74525653+2044000+4153961+8736899+122387880 -> 220278152 | AD11: 7605461.2 | AE11: 15652500 | AF11: 26786403 | AG11: 34921447 | AH11: 41929435
A12: Financial Expenses | B12: =SUM(B13:B18) -> 549.0847 | C12: =SUM(C13:C18) -> 457004342 | D12: =SUM(D13:D18) -> 4509682.5 | E12: =SUM(E13:E18) -> 17119783 | F12: =SUM(F13:F18) -> 19824661 | G12: =SUM(G13:G18) -> 21384560 | H12: =SUM(H13:H18) -> 26789148 | I12: =SUM(I13:I18) -> 34735266 | ... AO12: =SUM(AO13:AO18) -> 0
A13: Interest Expense on Deposits | B13: 185.36 | C13: =225866402+193398543 -> 419264945 | D13: 2146313.2 | E13: 3663638.8 | F13: 4525977.8 | G13: 5891015.3 | H13: 7325482.4 | I13: 7910570.9 | J13: 9430808.1 | K13: 11665318 | L13: 12508983 | M13: 14132791 | N13: 16177607 | O13: 55017171 | P13: =501566450-P14 -> 472991271 | Q13: 3688164 | R13: 5396488.8 | S13: 7419514.4 | T13: 9092610.8 | U13: 11042549 | V13: 12027824 | W13: 14466105 | X13: 16009567 | Y13: 16872491 | Z13: 20375449 | AA13: 22718015 | AB13: 76508952 | AC13: =567822949-AC14 -> 537050550 | AD13: 4022640.5 | AE13: 6157408 | AF13: 7965867.8 | AG13: 10164304 | AH13: 12287093
A14: Cost of External Borrowings | B14: 363.7247 | C14: 37739397 | D14: 2165753.1 | E14: 4271346.4 | F14: 6118834.6 | G14: 6118834.6 | H14: 9967121.7 | I14: 14699521 | J14: 14699521 | K14: 18190731 | L14: 19875205 | M14: 21449064 | N14: 21449064 | O14: 28575179 | P14: 28575179 | Q14: 1445378.3 | R14: 2831812.8 | S14: 4033514.2 | T14: 5069603.2 | U14: 6179163.6 | V14: 17139365 | W14: 19093067 | X14: 22675658 | Y14: 25509767 | Z14: 27757255 | AA14: 30036251 | AB14: 38272399 | AC14: 30772399 | AD14: 3014441.9 | AE14: 10271348 | AF14: 12231565 | AG14: 14668037 | AH14: 23365397
A15: Dividend Expenses | D15: 0 | E15: 0 | F15: 0 | G15: 0 | H15: 0 | I15: 0 | J15: 0 | K15: 0 | L15: 0 | M15: 0 | N15: 0 | O15: 0 | Q15: 0 | R15: 0 | S15: 0 | T15: 0 | U15: 0 | V15: 0 | W15: 0 | X15: 0 | Y15: 0 | Z15: 0 | AA15: 0 | AB15: 0 | AD15: 0 | AE15: 0 | AF15: 0 | AG15: 0 | AH15: 0
A16: Other Financial Expense | D16: 0 | E16: 0 | F16: 0 | G16: 0 | H16: 0 | I16: 0 | J16: 0 | K16: 0 | L16: 0 | M16: 0 | N16: 0 | O16: 0 | Q16: 0 | R16: 0 | S16: 0 | T16: 0 | U16: 0 | V16: 0 | W16: 0 | X16: 0 | Y16: 0 | Z16: 0 | AA16: 0 | AB16: 0 | AD16: 0 | AE16: 0 | AF16: 0 | AG16: 0 | AH16: 0
A17: Fees & Commision Expense | D17: 197616.2 | E17: 361065.8 | F17: 356116.1 | G17: 550978.2 | H17: 672812.2 | I17: 3301441.9 | J17: 5100179.1 | K17: 5357140.1 | L17: 6433419.2 | M17: 7981544 | N17: 8119147.5 | O17: 10203904 | P17: 10755349 | Q17: 672098.1 | R17: 1338605.2 | S17: 2369804.2 | T17: 3028860.6 | U17: 3531434.6 | V17: 3643893.5 | W17: 5181722.9 | X17: 6437597.9 | Y17: 7217515.6 | Z17: 8028629 | AA17: 8740522.5 | AB17: 10027760 | AC17: 10027760 | AD17: 685383 | AE17: 1435112.7 | AF17: 2265817.9 | AG17: 2464470.9 | AH17: 3751727
A18: Other Expenses | D18: 0 | E18: 8823732 | F18: 8823732 | G18: 8823732 | H18: 8823732 | I18: 8823732 | J18: 8823732 | K18: 8823732 | L18: 8823732 | M18: 8823732 | N18: 8823732 | O18: 8823732 | Q18: 10000000 | R18: 10000000 | S18: 10000000 | T18: 10000000 | U18: 10000000 | V18: 10000000 | W18: 10000000 | X18: 10000000 | Y18: 10000000 | Z18: 10000000 | AA18: 10000000 | AB18: 10000000 | AD18: 0 | AE18: 10000000 | AF18: 10000000 | AG18: 10000000 | AH18: 10000000
A19: Net Financial Income | B19: =B3-B12 -> 14050.163 | C19: =C3-C12 -> 1046257029 | D19: =D3-D12 -> 1.1243302e+08 | E19: =E3-E12 -> 2.2140777e+08 | F19: =F3-F12 -> 3.4218596e+08 | G19: =G3-G12 -> 4.7418466e+08 | H19: =H3-H12 -> 6.0004261e+08 | I19: =I3-I12 -> 7.1832102e+08 | ... AO19: =AO3-AO12 -> 0
A20: Allowance for Loan Loss | B20: =B21-B22 -> 0 | C20: =C21-C22 -> 124020372 | D20: =D21-D22 -> 0 | E20: =E21-E22 -> 0 | F20: =F21-F22 -> 0 | G20: =G21-G22 -> 0 | H20: =H21-H22 -> 0 | I20: =I21-I22 -> 0 | ... AO20: =AO21-AO22 -> 0
A21: Provision for Loan Losses | C21: 124020372 | D21: 0 | E21: 0 | F21: 0 | G21: 0 | H21: 0 | I21: 0 | J21: 0 | K21: 0 | L21: 45289828 | M21: 45289828 | N21: 45289828 | O21: 45289828 | P21: 45289828 | Q21: 0 | R21: 0 | S21: 0 | T21: 0 | U21: 0 | V21: 0 | W21: 0 | X21: 0 | Y21: 0 | Z21: 0 | AA21: 0 | AB21: 31791415 | AC21: 31791415 | AD21: 0 | AE21: 0 | AF21: 0 | AG21: 0 | AH21: 0
A22: Value of Loans Recovered | D22: 0 | E22: 0 | F22: 0 | G22: 0 | H22: 0 | I22: 0 | J22: 0 | K22: 0 | L22: 0 | M22: 0 | N22: 0 | O22: 0 | Q22: 0 | R22: 0 | S22: 0 | T22: 0 | U22: 0 | V22: 0 | W22: 0 | X22: 0 | Y22: 0 | Z22: 0 | AA22: 0 | AB22: 0 | AD22: 0 | AE22: 0 | AF22: 0 | AG22: 0 | AH22: 0
A23: Operating Expeses | B23: =SUM(B24:B28) -> 11019.38 | C23: =SUM(C24:C28) -> 558837310 | D23: =SUM(D24:D28) -> 32772521 | E23: =SUM(E24:E28) -> 79332679 | F23: =SUM(F24:F28) -> 1.2354445e+08 | G23: =SUM(G24:G28) -> 1.6978998e+08 | H23: =SUM(H24:H28) -> 2.1530691e+08 | I23: =SUM(I24:I28) -> 2.5762437e+08 | ... AO23: =SUM(AO24:AO28) -> 0
A24: Personel Expenses | B24: 3512.444 | D24: 14222701 | E24: 28370051 | F24: 43250903 | G24: 59156047 | H24: 74207152 | I24: 88794975 | J24: 1.0349582e+08 | K24: 1.184799e+08 | L24: 1.3306966e+08 | M24: 148090620 | N24: 1.6547291e+08 | O24: 1.7737288e+08 | P24: 220750933 | Q24: 16119957 | R24: 30407281 | S24: 46101451 | T24: 62236072 | U24: 77918821 | V24: 94001228 | W24: 1.09838e+08 | X24: 1.2599831e+08 | Y24: 1.419545e+08 | Z24: 1.5763708e+08 | AA24: 1.7361246e+08 | AB24: 1.906484e+08 | AC24: 243081233 | AD24: 19897377 | AE24: 41834178 | AF24: 65347695 | AG24: 95803226 | AH24: 1.2234293e+08
A25: Governance Expenses | B25: 401.873 | C25: 70898673 | D25: 2963220 | E25: 15650145 | F25: 22485095 | G25: 35159870 | H25: 49093785 | I25: 53463598 | J25: 57537098 | K25: 60109630 | L25: 66349022 | M25: 74999338 | N25: 84053664 | O25: 91975794 | P25: 100129831 | Q25: 3441442 | R25: 14046428 | S25: 40051679 | T25: 44895468 | U25: 56076385 | V25: 71686980 | W25: 76376208 | X25: 81322876 | Y25: 88354200 | Z25: 98829244 | AA25: 1.024727e+08 | AB25: 1.1493876e+08 | AC25: 123355210 | AD25: 2055432.5 | AE25: 8043470 | AF25: 41414448 | AG25: 48922662 | AH25: 56186027
A26: Marketing Expenses | B26: 919.3528 | D26: 2636960 | E26: 5503272 | F26: 6852069 | G26: 8508420.8 | H26: 10134083 | I26: 12029465 | J26: 13964788 | K26: 16512544 | L26: 18964131 | M26: 22326013 | N26: 24293931 | O26: 27222380 | P26: 27222380 | Q26: 3647242.6 | R26: 10545704 | S26: 14024416 | T26: 15926398 | U26: 19803982 | V26: 24573771 | W26: 39062521 | X26: 40674298 | Y26: 44652148 | Z26: 47596802 | AA26: 51495360 | AB26: 60839011 | AC26: 60839011 | AD26: 871431 | AE26: 5942602 | AF26: 11220630 | AG26: 13069565 | AH26: 14360272
A27: Depreciation and Amortization | B27: 1276.981 | C27: 141444688 | D27: 0 | E27: 0 | F27: 0 | G27: 0 | H27: 0 | I27: 0 | J27: 0 | K27: 0 | L27: 0 | M27: 0 | N27: 0 | O27: 29874015 | P27: =33747170+8247414+15440981 -> 57435565 | Q27: 0 | R27: 0 | S27: 0 | T27: 0 | U27: 0 | V27: 0 | W27: 0 | X27: 0 | Y27: 0 | Z27: 0 | AA27: 0 | AB27: 56658960 | AC27: =34327060+6890919+15440981 -> 56658960 | AD27: 0 | AE27: 0 | AF27: 0 | AG27: 0 | AH27: 0
A28: Administrative Expenses | B28: 4908.7291 | C28: =346493949 -> 346493949 | D28: 12949640 | E28: 29809212 | F28: 50956387 | G28: 66965640 | H28: 81871892 | I28: 1.0333633e+08 | J28: 1.2079259e+08 | K28: 1.3819184e+08 | L28: 1.7645196e+08 | M28: 1.9774074e+08 | N28: 2.3072583e+08 | O28: 2.3964482e+08 | P28: =412726624-P17-P26-P24-P36+2981166+2111587+17047336+10894672+16547653+8091672+51939062 -> 251228813 | Q28: 11334646 | R28: 36565283 | S28: 53704202 | T28: 73449304 | U28: 89758104 | V28: 1.0878691e+08 | W28: 1.4267534e+08 | X28: 1.5936576e+08 | Y28: 1.9454504e+08 | Z28: 2.1090957e+08 | AA28: 2.5880548e+08 | AB28: 2.4988369e+08 | AC28: =473850763-AC17-AC26-AC24-AC36+342370+4640557+16344651+12260743+16874344+7637690+76952288 -> 293325030 | AD28: 11840121 | AE28: 28584709 | AF28: 40417872 | AG28: 51647029 | AH28: 69348471
A29: Net Operating Income | B29: =B19-B20-B23 -> 3030.7829 | C29: =C19-C20-C23 -> 363399347 | D29: =D19-D20-D23 -> 79660495 | E29: =E19-E20-E23 -> 1.4207509e+08 | F29: =F19-F20-F23 -> 2.1864151e+08 | G29: =G19-G20-G23 -> 3.0439469e+08 | H29: =H19-H20-H23 -> 3.847357e+08 | I29: =I19-I20-I23 -> 4.6069665e+08 | ... AO29: =AO19-AO20-AO23 -> 0
A30: Net Non operating Income/Expense | B30: =B31-B32 -> 0 | C30: =C31-C32 -> 0 | D30: =D31-D32 -> 0 | E30: =E31-E32 -> 0 | F30: =F31-F32 -> 0 | G30: =G31-G32 -> 0 | H30: =H31-H32 -> 0 | I30: =I31-I32 -> 0 | ... AO30: =AO31-AO32 -> 0
A31: Non Operating Income | D31: 0 | E31: 0 | F31: 0 | G31: 0 | H31: 0 | I31: 0 | J31: 0 | K31: 0 | L31: 0 | M31: 0 | N31: 0 | O31: 0 | Q31: 0 | R31: 0 | S31: 0 | T31: 0 | U31: 0 | V31: 0 | W31: 0 | X31: 0 | Y31: 0 | Z31: 0 | AA31: 0 | AB31: 240000 | AD31: 0 | AE31: 0 | AF31: 0 | AG31: 0 | AH31: 724000
A32: Non Operating Expense | D32: 0 | E32: 0 | F32: 0 | G32: 0 | H32: 0 | I32: 0 | J32: 0 | K32: 0 | L32: 0 | M32: 0 | N32: 0 | O32: 0 | Q32: 0 | R32: 0 | S32: 0 | T32: 0 | U32: 0 | V32: 0 | W32: 0 | X32: 0 | Y32: 0 | Z32: 0 | AA32: 0 | AB32: 0 | AD32: 0 | AE32: 0 | AF32: 0 | AG32: 0 | AH32: 0
A33: Net Income(Before Tax & Donations) | B33: =B29+B30 -> 3030.7829 | C33: =C29+C30 -> 363399347 | D33: =D29+D30 -> 79660495 | E33: =E29+E30 -> 1.4207509e+08 | F33: =F29+F30 -> 2.1864151e+08 | G33: =G29+G30 -> 3.0439469e+08 | H33: =H29+H30 -> 3.847357e+08 | I33: =I29+I30 -> 4.6069665e+08 | ... AO33: =AO29+AO30 -> 0
A34: Taxes | B34: 20 | C34: 5713437 | D34: 0 | E34: 0 | F34: 0 | G34: 0 | H34: 0 | I34: 0 | J34: 0 | K34: 0 | L34: 0 | M34: 0 | N34: 0 | O34: 0 | P34: 15686992 | Q34: 0 | R34: 0 | S34: 0 | T34: 0 | U34: 0 | V34: 0 | W34: 0 | X34: 0 | Y34: 0 | Z34: 0 | AA34: 0 | AB34: 0 | AC34: 19237483 | AD34: 0 | AE34: 0 | AF34: 0 | AG34: 0 | AH34: 0
A35: Net Income(After Tax Before Donations) | B35: =B33-B34 -> 3010.7829 | C35: =C33-C34 -> 357685910 | D35: =D33-D34 -> 79660495 | E35: =E33-E34 -> 1.4207509e+08 | F35: =F33-F34 -> 2.1864151e+08 | G35: =G33-G34 -> 3.0439469e+08 | H35: =H33-H34 -> 3.847357e+08 | I35: =I33-I34 -> 4.6069665e+08 | ... AO35: =AO33-AO34 -> 0
A36: Donations | D36: -50000 | E36: -117700 | F36: -148720 | G36: -160720 | H36: -160720 | I36: -211420 | J36: -244417 | K36: -244417 | L36: -255417 | M36: -295137 | N36: -355137 | O36: -382297 | P36: 12382297 | Q36: 0 | R36: -25862 | S36: -48862 | T36: -108862 | U36: -283912 | V36: -403412 | W36: -425412 | X36: -430412 | Y36: -571812 | Z36: -629572 | AA36: -679872 | AB36: -1630372 | AC36: 1630372 | AD36: -7031200 | AE36: -7041485 | AF36: -7086285 | AG36: -14165395 | AH36: -14183395
A37: Net Income/(After Tax & Donations) | B37: =B35-B36 -> 3010.7829 | C37: =C35-C36 -> 357685910 | D37: =D35-D36 -> 79710495 | E37: =E35-E36 -> 1.4219279e+08 | F37: =F35-F36 -> 2.1879023e+08 | G37: =G35-G36 -> 3.0455541e+08 | H37: =H35-H36 -> 3.8489642e+08 | I37: =I35-I36 -> 4.6090807e+08 | ... AO37: =AO35-AO36 -> 0
A39: Total Expenses | B39: =B12+B23 -> 11568.465 | C39: =C12+C23 -> 1015841652 | D39: =D12+D23 -> 37282203 | E39: =E12+E23 -> 96452462 | F39: =F12+F23 -> 1.4336911e+08 | G39: =G12+G23 -> 1.9117454e+08 | H39: =H12+H23 -> 2.4209606e+08 | I39: =I12+I23 -> 2.9235963e+08 | ... AJ39: =AJ12+AJ23 -> 0

Sheet FORM 4
D1: 44256
B2: CLASSIFICATION | C2: NO. OF A/Cs | D2: OUTSTANDING LOAN PORTFOLIO(Kshs) | E2: REQUIRED PROVISION | F2: REQUIRED PROVISION AMOUNT(Kshs)
B3: Performing | C3: 36938 | D3: 5.5347416e+09 | E3: 0.01 | F3: 55347416
B4: Watch | C4: 5907 | D4: 1.2190029e+09 | E4: 0.05 | F4: 60950143 | H4: NPL | I4: 6.6319593e+08
B5: Substandard | C5: 4000 | D5: 398432466 | E5: 0.25 | F5: 99608116 | H5: PAR | I5: =I4/D8 -> 0.089416376
B6: Doubtful | C6: 4232 | D6: 1.9563927e+08 | E6: 0.5 | F6: 97819634
B7: Loss | C7: 1137 | D7: 69124198 | E7: 1 | F7: 69124198
B8: subtotal | C8: 52214 | D8: 7.4169404e+09 | E8: 1.81 | F8: 3.8284951e+08
D10: 44348
B11: CLASSIFICATION | C11: NO. OF A/Cs | D11: OUTSTANDING LOAN PORTFOLIO(Kshs) | E11: REQUIRED PROVISION | F11: REQUIRED PROVISION AMOUNT(Kshs)
B12: Performing | C12: 34627 | D12: 6.2410568e+09 | E12: 0.01 | F12: =D12*E12 -> 62410568
B13: Watch | C13: 5337 | D13: 9.6037038e+08 | E13: 0.05 | F13: =D13*E13 -> 48018519 | H13: NPL | I13: =D14+D15+D16 -> 7.0860885e+08
B14: Substandard | C14: 3421 | D14: 3.0361897e+08 | E14: 0.25 | F14: =D14*E14 -> 75904743 | H14: PAR | I14: =I13/D17 -> 0.089583517
B15: Doubtful | C15: 4852 | D15: 2.2287283e+08 | E15: 0.5 | F15: =D15*E15 -> 1.1143641e+08
B16: Loss | C16: 3022 | D16: 1.8211705e+08 | E16: 1 | F16: =D16*E16 -> 1.8211705e+08
B17: subtotal | C17: =SUM(C12:C16) -> 51259 | D17: =SUM(D12:D16) -> 7.910036e+09 | E17: 1.81 | F17: =SUM(F12:F16) -> 4.7988729e+08
D19: 44440
B20: CLASSIFICATION | C20: NO. OF A/Cs | D20: OUTSTANDING LOAN PORTFOLIO(Kshs) | E20: REQUIRED PROVISION | F20: REQUIRED PROVISION AMOUNT(Kshs)
B21: Performing | C21: 34498 | D21: 6.8128948e+09 | E21: 0.01 | F21: =D21*E21 -> 68128948
B22: Watch | C22: 5610 | D22: 1.0315749e+09 | E22: 0.05 | F22: =D22*E22 -> 51578745 | H22: NPL | I22: =D23+D24+D25 -> 7.0910858e+08
B23: Substandard | C23: 3481 | D23: 2.8518051e+08 | E23: 0.25 | F23: =D23*E23 -> 71295127 | H23: PAR | I23: =I22/D26 -> 0.08290198
B24: Doubtful | C24: 4579 | D24: 2.1890083e+08 | E24: 0.5 | F24: =D24*E24 -> 1.0945041e+08
B25: Loss | C25: 3277 | D25: 2.0502724e+08 | E25: 1 | F25: =D25*E25 -> 2.0502724e+08
B26: subtotal | C26: =SUM(C21:C25) -> 51445 | D26: =SUM(D21:D25) -> 8.5535783e+09 | E26: 1.81 | F26: =SUM(F21:F25) -> 5.0548048e+08
D28: 44531
B29: CLASSIFICATION | C29: NO. OF A/Cs | D29: OUTSTANDING LOAN PORTFOLIO(Kshs) | E29: REQUIRED PROVISION | F29: REQUIRED PROVISION AMOUNT(Kshs)
B30: Performing | C30: 52139 | D30: 7.942182e+09 | E30: 0.01 | F30: =D30*E30 -> 79421820
B31: Watch | C31: 3658 | D31: 5.5876745e+08 | E31: 0.05 | F31: =D31*E31 -> 27938372 | H31: NPL | I31: =D32+D33+D34 -> 5.0250167e+08
B32: Substandard | C32: 2787 | D32: 1.4259675e+08 | E32: 0.25 | F32: =D32*E32 -> 35649187 | H32: PAR | I32: =I31/D35 -> 0.055812117
B33: Doubtful | C33: 3703 | D33: 1.4402815e+08 | E33: 0.5 | F33: =D33*E33 -> 72014075
B34: Loss | C34: 4431 | D34: 2.1587677e+08 | E34: 1 | F34: =D34*E34 -> 2.1587677e+08
B35: subtotal | C35: =SUM(C30:C34) -> 66718 | D35: =SUM(D30:D34) -> 9.0034511e+09 | E35: 1.81 | F35: =SUM(F30:F34) -> 4.3090022e+08
D38: Audited 2021
B39: CLASSIFICATION | C39: NO. OF A/Cs | D39: OUTSTANDING LOAN PORTFOLIO(Kshs) | E39: REQUIRED PROVISION | F39: REQUIRED PROVISION AMOUNT(Kshs)
B40: Performing | C40: 52139 | D40: 7.942182e+09 | E40: 0.01 | F40: =D40*E40 -> 79421820
B41: Watch | C41: 3658 | D41: 5.5876745e+08 | E41: 0.05 | F41: =D41*E41 -> 27938372
B42: Substandard | C42: 2787 | D42: 1.4259675e+08 | E42: 0.25 | F42: =D42*E42 -> 35649187
B43: Doubtful | C43: 3703 | D43: 1.4402815e+08 | E43: 0.5 | F43: =D43*E43 -> 72014075
B44: Loss | C44: 4431 | D44: 2.1587677e+08 | E44: 1 | F44: =D44*E44 -> 2.1587677e+08
B45: subtotal | C45: =SUM(C40:C44) -> 66718 | D45: =SUM(D40:D44) -> 9.0034511e+09 | E45: 1.81 | F45: =SUM(F40:F44) -> 4.3090022e+08
D47: 44621
B48: CLASSIFICATION | C48: NO. OF A/Cs | D48: OUTSTANDING LOAN PORTFOLIO(Kshs) | E48: REQUIRED PROVISION | F48: REQUIRED PROVISION AMOUNT(Kshs)
B49: Performing | C49: 41032 | D49: 7.0941368e+09 | E49: 0.01 | F49: =E49*D49 -> 70941368
B50: Watch | C50: 6797 | D50: 1.3040345e+09 | E50: 0.05 | F50: =E50*D50 -> 65201724
B51: Substandard | C51: 4171 | D51: 3.5999029e+08 | E51: 0.25 | F51: =E51*D51 -> 89997571
B52: Doubtful | C52: 3730 | D52: 1.7469025e+08 | E52: 0.5 | F52: =E52*D52 -> 87345125
B53: Loss | C53: 4868 | D53: 2.3947194e+08 | E53: 1 | F53: =E53*D53 -> 2.3947194e+08
B54: subtotal | C54: =C49+C50+C51+C52+C53 -> 60598 | D54: =SUM(D49:D53) -> 9.1723237e+09 | E54: 1.81 | F54: =SUM(F49:F53) -> 5.5295773e+08
D56: 44713
B57: CLASSIFICATION | C57: NO. OF A/Cs | D57: OUTSTANDING LOAN PORTFOLIO(Kshs) | E57: REQUIRED PROVISION | F57: REQUIRED PROVISION AMOUNT(Kshs)
B58: Performing | C58: 45521 | D58: 8.2240423e+09 | E58: 0.01 | F58: =D58*E58 -> 82240423 | H58: 45521 | I58: 4580 | J58: 3412 | K58: 3979 | L58: 5151 | M58: IMARIKA | N58: 8.2240423e+09 | O58: 7.4022619e+08 | P58: 1.4519581e+08 | Q58: 1.5661265e+08 | R58: 2.4253616e+08 | S58: IMARIKA | U58: 82240423 | W58: 37011309 | X58: 36298953 | Y58: 78306326 | Z58: 2.4253616e+08
B59: Watch | C59: 4580 | D59: 7.4022619e+08 | E59: 0.05 | F59: =D59*E59 -> 37011309
B60: Substandard | C60: 3412 | D60: 1.4519581e+08 | E60: 0.25 | F60: =D60*E60 -> 36298953
B61: Doubtful | C61: 3979 | D61: 1.5661265e+08 | E61: 0.5 | F61: =D61*E61 -> 78306326
B62: Loss | C62: 5151 | D62: 2.4253616e+08 | E62: 1 | F62: =D62*E62 -> 2.4253616e+08
B63: subtotal | C63: =SUM(C58:C62) -> 62643 | D63: =SUM(D58:D62) -> 9.5086131e+09 | E63: 1.81 | F63: =SUM(F58:F62) -> 4.7639317e+08
D65: 44805
B66: CLASSIFICATION | C66: NO. OF A/Cs | D66: OUTSTANDING LOAN PORTFOLIO(Kshs) | E66: REQUIRED PROVISION | F66: REQUIRED PROVISION AMOUNT(Kshs)
B67: Performing | C67: 46029 | D67: 8.1960994e+09 | E67: 0.01 | F67: =D67*E67 -> 81960994
B68: Watch | C68: 5865 | D68: 1.0261455e+09 | E68: 0.05 | F68: =D68*E68 -> 51307275
B69: Substandard | C69: 3828 | D69: 1.4558979e+08 | E69: 0.25 | F69: =D69*E69 -> 36397448
B70: Doubtful | C70: 4371 | D70: 1.2239779e+08 | E70: 0.5 | F70: =D70*E70 -> 61198895
B71: Loss | C71: 5527 | D71: 2.5248317e+08 | E71: 1 | F71: =D71*E71 -> 2.5248317e+08
B72: subtotal | C72: =SUM(C67:C71) -> 65620 | D72: =SUM(D67:D71) -> 9742715677 | E72: 1.81 | F72: =SUM(F67:F71) -> 4.8334778e+08
D74: 44896
B75: CLASSIFICATION | C75: NO. OF A/Cs | D75: OUTSTANDING LOAN PORTFOLIO(Kshs) | E75: REQUIRED PROVISION | F75: REQUIRED PROVISION AMOUNT(Kshs)
B76: Performing | C76: 50989 | D76: 8138168521 | E76: 0.01 | F76: =D76*E76 -> 81381685
B77: Watch | C77: 6877 | D77: 1310842151 | E77: 0.05 | F77: =D77*E77 -> 65542108
B78: Substandard | C78: 4808 | D78: 342265888 | E78: 0.25 | F78: =D78*E78 -> 85566472
B79: Doubtful | C79: 4922 | D79: 131011383 | E79: 0.5 | F79: =D79*E79 -> 65505692
B80: Loss | C80: 6032 | D80: 251557523 | E80: 1 | F80: =D80*E80 -> 251557523
B81: subtotal | C81: =SUM(C76:C80) -> 73628 | D81: =SUM(D76:D80) -> 10173845466 | E81: 1.81 | F81: =SUM(F76:F80) -> 5.4955348e+08
D84: Audited 2022
B85: CLASSIFICATION | C85: NO. OF A/Cs | D85: OUTSTANDING LOAN PORTFOLIO(Kshs) | E85: REQUIRED PROVISION | F85: REQUIRED PROVISION AMOUNT(Kshs)
B86: Performing | C86: 50989 | D86: 8138168521 | E86: 0.01 | F86: =D86*E86 -> 81381685
B87: Watch | C87: 6877 | D87: 1310842151 | E87: 0.05 | F87: =D87*E87 -> 65542108
B88: Substandard | C88: 4808 | D88: 342265888 | E88: 0.25 | F88: =D88*E88 -> 85566472
B89: Doubtful | C89: 4922 | D89: 131011383 | E89: 0.5 | F89: =D89*E89 -> 65505692
B90: Loss | C90: 6032 | D90: 251557523 | E90: 1 | F90: =D90*E90 -> 251557523
B91: subtotal | C91: =SUM(C86:C90) -> 73628 | D91: =SUM(D86:D90) -> 10173845466 | E91: 1.81 | F91: =SUM(F86:F90) -> 5.4955348e+08

Sheet CAELS
A1: IMARIKA SACCO 2022 CAELS
D2: 2010 Audited | E2: 2020Audited | F2: 44198 | G2: 44230 | H2: 44259 | I2: 44291 | J2: 44322 | K2: 44354 | L2: 44385 | M2: 44417 | N2: 44449 | O2: 44480 | P2: 44512 | Q2: 44543 | R2: Audited 2021 | S2: 44576 | T2: 44577 | U2: 44609 | V2: 44638 | W2: 44670 | X2: 44732 | Y2: 44763 | Z2: 44795 | AA2: 44827 | AB2: 44858 | AC2: 44890 | AD2: 44921 | AE2: Audited 2022 | AF2: 44927 | AG2: 44958 | AH2: 44986 | AI2: 45017 | AJ2: 45047 | AK2: 45078 | AL2: 45108 | AM2: 45139 | AN2: 45170 | AO2: 45200 | AP2: 45231 | AQ2: 45261
A3: CAPITAL ADEQUACY | B3: Core Capital | C3: 10 M | D3: =(('Evolutive SFP'!B39+'Evolutive SFP'!B40+'Evolutive SFP'!B41+'Evolutive SFP'!B42+'Evolutive SFP'!B43+'Evolutive SFP'!B44)-'Evolutive SFP'!B10)/1000000 -> 15.259572 | E3: =(('Evolutive SFP'!C39+'Evolutive SFP'!C40+'Evolutive SFP'!C41+'Evolutive SFP'!C42+'Evolutive SFP'!C43+'Evolutive SFP'!C44)-'Evolutive SFP'!C10)/1000000 -> 2158.0724 | F3: =(('Evolutive SFP'!D39+'Evolutive SFP'!D40+'Evolutive SFP'!D41+'Evolutive SFP'!D42+'Evolutive SFP'!D43+'Evolutive SFP'!D44)-'Evolutive SFP'!D10)/1000000 -> 2233.8166 | G3: =(('Evolutive SFP'!E39+'Evolutive SFP'!E40+'Evolutive SFP'!E41+'Evolutive SFP'!E42+'Evolutive SFP'!E43+'Evolutive SFP'!E44)-'Evolutive SFP'!E10)/1000000 -> 2245.7213 | H3: =(('Evolutive SFP'!F39+'Evolutive SFP'!F40+'Evolutive SFP'!F41+'Evolutive SFP'!F42+'Evolutive SFP'!F43+'Evolutive SFP'!F44)-'Evolutive SFP'!F10)/1000000 -> 2362.246 | I3: =(('Evolutive SFP'!G39+'Evolutive SFP'!G40+'Evolutive SFP'!G41+'Evolutive SFP'!G42+'Evolutive SFP'!G43+'Evolutive SFP'!G44)-'Evolutive SFP'!G10)/1000000 -> 2452.993 | J3: =(('Evolutive SFP'!H39+'Evolutive SFP'!H40+'Evolutive SFP'!H41+'Evolutive SFP'!H42+'Evolutive SFP'!H43+'Evolutive SFP'!H44)-'Evolutive SFP'!H10)/1000000 -> 2537.4057 | K3: =(('Evolutive SFP'!I39+'Evolutive SFP'!I40+'Evolutive SFP'!I41+'Evolutive SFP'!I42+'Evolutive SFP'!I43+'Evolutive SFP'!I44)-'Evolutive SFP'!I10)/1000000 -> 2570.8403 | ... AV3: =(('Evolutive SFP'!AT39+'Evolutive SFP'!AT40+'Evolutive SFP'!AT41+'Evolutive SFP'!AT42+'Evolutive SFP'!AT43+'Evolutive SFP'!AT44)-'Evolutive SFP'!AT10)/1000000 -> 0
B4: CCA | C4: Min 10% | D4: =D3/(('Evolutive SFP'!B27)/1000000) -> 0.10104624 | E4: =E3/(('Evolutive SFP'!C27)/1000000) -> 0.23115033 | F4: =F3/(('Evolutive SFP'!D27)/1000000) -> 0.2372746 | G4: =G3/(('Evolutive SFP'!E27)/1000000) -> 0.23814834 | H4: =H3/(('Evolutive SFP'!F27)/1000000) -> 0.25218709 | I4: =I3/(('Evolutive SFP'!G27)/1000000) -> 0.26057624 | J4: =J3/(('Evolutive SFP'!H27)/1000000) -> 0.26482572 | K4: =K3/(('Evolutive SFP'!I27)/1000000) -> 0.26622876 | ... AV4: =AV3/(('Evolutive SFP'!AT27)/1000000) -> #DIV/0!
B5: CCD | C5: Min 8% | D5: =D3/('Evolutive SFP'!B31/1000000) -> 0.1186553 | E5: =E3/('Evolutive SFP'!C31/1000000) -> 0.34496918 | F5: =F3/('Evolutive SFP'!D31/1000000) -> 0.35646123 | G5: =G3/('Evolutive SFP'!E31/1000000) -> 0.33789949 | H5: =H3/('Evolutive SFP'!F31/1000000) -> 0.35995703 | I5: =I3/('Evolutive SFP'!G31/1000000) -> 0.3767032 | J5: =J3/('Evolutive SFP'!H31/1000000) -> 0.38390949 | K5: =K3/('Evolutive SFP'!I31/1000000) -> 0.38790729 | ... AV5: =AV3/('Evolutive SFP'!AT31/1000000) -> #DIV/0!
B6: ICA | C6: Min 8% | D6: =((D3*1000000)-'Evolutive SFP'!B39)/'Evolutive SFP'!B27 -> 0.031552177 | E6: =((E3*1000000)-'Evolutive SFP'!C39)/'Evolutive SFP'!C27 -> 0.18540644 | F6: =((F3*1000000)-'Evolutive SFP'!D39)/'Evolutive SFP'!D27 -> 0.19189691 | G6: =((G3*1000000)-'Evolutive SFP'!E39)/'Evolutive SFP'!E27 -> 0.19272711 | H6: =((H3*1000000)-'Evolutive SFP'!F39)/'Evolutive SFP'!F27 -> 0.20637139 | I6: =((I3*1000000)-'Evolutive SFP'!G39)/'Evolutive SFP'!G27 -> 0.21495014 | J6: =((J3*1000000)-'Evolutive SFP'!H39)/'Evolutive SFP'!H27 -> 0.21997479 | K6: =((K3*1000000)-'Evolutive SFP'!I39)/'Evolutive SFP'!I27 -> 0.22170322 | ... AV6: =((AV3*1000000)-'Evolutive SFP'!AT39)/'Evolutive SFP'!AT27 -> #DIV/0!
A7: ASSET QUALITY | B7: A/LNPL30 | H7: ='Evolutive SFP'!#REF! -> #REF!
B8: NPL30 | H8: =('FORM 4'!D5+'FORM 4'!D6+'FORM 4'!D7) -> 6.6319593e+08 | R8: =('FORM 4'!D42+'FORM 4'!D43+'FORM 4'!D44)/'Evolutive SFP'!P15 -> 0.056105981 | V8: =('FORM 4'!D51+'FORM 4'!D52+'FORM 4'!D53)/'Evolutive SFP'!S15 -> 0.084400911 | X8: =('FORM 4'!D60+'FORM 4'!D61+'FORM 4'!D62)/'Evolutive SFP'!V15 -> 0.057247531 | AA8: =('FORM 4'!D69+'FORM 4'!D70+'FORM 4'!D71)/'Evolutive SFP'!Y15 -> 0.053421528 | AD8: =('FORM 4'!D78+'FORM 4'!D79+'FORM 4'!D80)/'Evolutive SFP'!AB15 -> 0.071244919 | AE8: =('FORM 4'!D88+'FORM 4'!D89+'FORM 4'!D90)/'Evolutive SFP'!AC15 -> 0.071417173
A9: EARNINGS | B9: ROA | E9: ='Evolutitve SCI'!C33/(('Evolutive SFP'!B27+'Evolutive SFP'!C27)/2) -> 0.076607984 | F9: ='Evolutitve SCI'!D33/(('Evolutive SFP'!C27+'Evolutive SFP'!D27)/2) -> 0.0084967991 | G9: ='Evolutitve SCI'!E33/(('Evolutive SFP'!D27+'Evolutive SFP'!E27)/2) -> 0.015078756 | H9: ='Evolutitve SCI'!F33/(('Evolutive SFP'!E27+'Evolutive SFP'!F27)/2) -> 0.023263491 | I9: ='Evolutitve SCI'!G33/(('Evolutive SFP'!F27+'Evolutive SFP'!G27)/2) -> 0.032415583 | J9: ='Evolutitve SCI'!H33/(('Evolutive SFP'!G27+'Evolutive SFP'!H27)/2) -> 0.040508853 | K9: ='Evolutitve SCI'!I33/(('Evolutive SFP'!H27+'Evolutive SFP'!I27)/2) -> 0.047894629 | L9: ='Evolutitve SCI'!J33/(('Evolutive SFP'!I27+'Evolutive SFP'!J27)/2) -> 0.058749537 | ... AV9: ='Evolutitve SCI'!AT33/(('Evolutive SFP'!AS27+'Evolutive SFP'!AT27)/2) -> #DIV/0!
B10: Cost Income ratio | D10: ='Evolutitve SCI'!B23/'Evolutitve SCI'!B19 -> 0.78428841 | E10: ='Evolutitve SCI'!C23/'Evolutitve SCI'!C19 -> 0.53413004 | F10: ='Evolutitve SCI'!D23/'Evolutitve SCI'!D19 -> 0.29148485 | G10: ='Evolutitve SCI'!E23/'Evolutitve SCI'!E19 -> 0.35831027 | H10: ='Evolutitve SCI'!F23/'Evolutitve SCI'!F19 -> 0.36104478 | I10: ='Evolutitve SCI'!G23/'Evolutitve SCI'!G19 -> 0.35806721 | J10: ='Evolutitve SCI'!H23/'Evolutitve SCI'!H19 -> 0.35881937 | K10: ='Evolutitve SCI'!I23/'Evolutitve SCI'!I19 -> 0.35864796 | ... AV10: ='Evolutitve SCI'!AT23/'Evolutitve SCI'!AT19 -> #DIV/0!
B11: Operating Expense ratio | D11: =('Evolutitve SCI'!B23+'Evolutitve SCI'!B12)/(('Evolutive SFP'!B27+'Evolutive SFP'!C27)/2) -> 2.4387406e-06 | E11: =('Evolutitve SCI'!C23+'Evolutitve SCI'!C12)/(('Evolutive SFP'!C27+'Evolutive SFP'!D27)/2) -> 0.10835236 | F11: =('Evolutitve SCI'!D23+'Evolutitve SCI'!D12)/(('Evolutive SFP'!D27+'Evolutive SFP'!E27)/2) -> 0.0039568459 | G11: =('Evolutitve SCI'!E23+'Evolutitve SCI'!E12)/(('Evolutive SFP'!E27+'Evolutive SFP'!F27)/2) -> 0.010262557 | H11: =('Evolutitve SCI'!F23+'Evolutitve SCI'!F12)/(('Evolutive SFP'!F27+'Evolutive SFP'!G27)/2) -> 0.015267656 | I11: =('Evolutitve SCI'!G23+'Evolutitve SCI'!G12)/(('Evolutive SFP'!G27+'Evolutive SFP'!H27)/2) -> 0.020128783 | J11: =('Evolutitve SCI'!H23+'Evolutitve SCI'!H12)/(('Evolutive SFP'!H27+'Evolutive SFP'!I27)/2) -> 0.025168624 | K11: =('Evolutitve SCI'!I23+'Evolutitve SCI'!I12)/(('Evolutive SFP'!I27+'Evolutive SFP'!J27)/2) -> 0.029940784 | ... AV11: =('Evolutitve SCI'!AT23+'Evolutitve SCI'!AT12)/(('Evolutive SFP'!AT27+'Evolutive SFP'!AU27)/2) -> #DIV/0!
A12: LIQUIDITY | B12: MIN LIQ ratio | C12: Min 15% | D12: =('Evolutive SFP'!B4)/('Evolutive SFP'!B28+'Evolutive SFP'!B29+'Evolutive SFP'!B32+'Evolutive SFP'!B33+'Evolutive SFP'!B34+'Evolutive SFP'!B35+'Evolutive SFP'!B36) -> 0.90806632 | E12: =('Evolutive SFP'!C4)/('Evolutive SFP'!C28+'Evolutive SFP'!C29+'Evolutive SFP'!C32+'Evolutive SFP'!C33+'Evolutive SFP'!C34+'Evolutive SFP'!C35+'Evolutive SFP'!C36) -> 0.65572477 | F12: =('Evolutive SFP'!D4)/('Evolutive SFP'!D28+'Evolutive SFP'!D29+'Evolutive SFP'!D32+'Evolutive SFP'!D33+'Evolutive SFP'!D34+'Evolutive SFP'!D35+'Evolutive SFP'!D36) -> 0.65157396 | G12: =('Evolutive SFP'!E4)/('Evolutive SFP'!E28+'Evolutive SFP'!E29+'Evolutive SFP'!E32+'Evolutive SFP'!E33+'Evolutive SFP'!E34+'Evolutive SFP'!E35+'Evolutive SFP'!E36) -> 0.766336 | H12: =('Evolutive SFP'!F4)/('Evolutive SFP'!F28+'Evolutive SFP'!F29+'Evolutive SFP'!F32+'Evolutive SFP'!F33+'Evolutive SFP'!F34+'Evolutive SFP'!F35+'Evolutive SFP'!F36) -> 0.72505793 | I12: =('Evolutive SFP'!G4)/('Evolutive SFP'!G28+'Evolutive SFP'!G29+'Evolutive SFP'!G32+'Evolutive SFP'!G33+'Evolutive SFP'!G34+'Evolutive SFP'!G35+'Evolutive SFP'!G36) -> 0.71190607 | J12: =('Evolutive SFP'!H4)/('Evolutive SFP'!H28+'Evolutive SFP'!H29+'Evolutive SFP'!H32+'Evolutive SFP'!H33+'Evolutive SFP'!H34+'Evolutive SFP'!H35+'Evolutive SFP'!H36) -> 0.73497213 | K12: =('Evolutive SFP'!I4)/('Evolutive SFP'!I28+'Evolutive SFP'!I29+'Evolutive SFP'!I32+'Evolutive SFP'!I33+'Evolutive SFP'!I34+'Evolutive SFP'!I35+'Evolutive SFP'!I36) -> 0.78977109 | ... AV12: =('Evolutive SFP'!AT4)/('Evolutive SFP'!AT28+'Evolutive SFP'!AT29+'Evolutive SFP'!AT32+'Evolutive SFP'!AT33+'Evolutive SFP'!AT34+'Evolutive SFP'!AT35+'Evolutive SFP'!AT36) -> #DIV/0!
B13: T/LIQ ratio | D13: ='Evolutive SFP'!B4/('Evolutive SFP'!B31+'Evolutive SFP'!B36) -> 0.14915539 | E13: ='Evolutive SFP'!C4/('Evolutive SFP'!C31+'Evolutive SFP'!C36) -> 0.186016 | F13: ='Evolutive SFP'!D4/('Evolutive SFP'!D31+'Evolutive SFP'!D36) -> 0.18806589 | G13: ='Evolutive SFP'!E4/('Evolutive SFP'!E31+'Evolutive SFP'!E36) -> 0.20130726 | H13: ='Evolutive SFP'!F4/('Evolutive SFP'!F31+'Evolutive SFP'!F36) -> 0.16915458 | I13: ='Evolutive SFP'!G4/('Evolutive SFP'!G31+'Evolutive SFP'!G36) -> 0.15716468 | J13: ='Evolutive SFP'!H4/('Evolutive SFP'!H31+'Evolutive SFP'!H36) -> 0.166658 | K13: ='Evolutive SFP'!I4/('Evolutive SFP'!I31+'Evolutive SFP'!I36) -> 0.18036999 | ... AV13: ='Evolutive SFP'!AT4/('Evolutive SFP'!AT31+'Evolutive SFP'!AT36) -> #DIV/0!
B14: EB ratio | C14: Max 25% | D14: ='Evolutive SFP'!B37/'Evolutive SFP'!B27 -> 0.015175035 | E14: ='Evolutive SFP'!C37/'Evolutive SFP'!C27 -> 0.028699699 | F14: ='Evolutive SFP'!D37/'Evolutive SFP'!D27 -> 0.027859249 | G14: ='Evolutive SFP'!E37/'Evolutive SFP'!E27 -> 0.027212686 | H14: ='Evolutive SFP'!F37/'Evolutive SFP'!F27 -> 0.026060478 | I14: ='Evolutive SFP'!G37/'Evolutive SFP'!G27 -> 0.025118383 | J14: ='Evolutive SFP'!H37/'Evolutive SFP'!H27 -> 0.024294543 | K14: ='Evolutive SFP'!I37/'Evolutive SFP'!I27 -> 0.023104386 | ... AV14: ='Evolutive SFP'!AT37/'Evolutive SFP'!AT27 -> #DIV/0!
B15: LA to TA ratio | D15: ='Evolutive SFP'!B4/'Evolutive SFP'!B27 -> 0.12821992 | E15: ='Evolutive SFP'!C4/'Evolutive SFP'!C27 -> 0.12710287 | F15: ='Evolutive SFP'!D4/'Evolutive SFP'!D27 -> 0.12739375 | G15: ='Evolutive SFP'!E4/'Evolutive SFP'!E27 -> 0.14480114 | H15: ='Evolutive SFP'!F4/'Evolutive SFP'!F27 -> 0.12053694 | I15: ='Evolutive SFP'!G4/'Evolutive SFP'!G27 -> 0.11133342 | J15: ='Evolutive SFP'!H4/'Evolutive SFP'!H27 -> 0.11749895 | K15: ='Evolutive SFP'!I4/'Evolutive SFP'!I27 -> 0.12726832 | ... AV15: ='Evolutive SFP'!AT4/'Evolutive SFP'!AT27 -> #DIV/0!
A16: STRUCTURE | B16: NEA ratio | C16: Max 10% | D16: =('Evolutive SFP'!B7+'Evolutive SFP'!B21)/'Evolutive SFP'!B27 -> 0.12101375 | E16: =('Evolutive SFP'!C7+'Evolutive SFP'!C21)/'Evolutive SFP'!C27 -> 0.090293307 | F16: =('Evolutive SFP'!D7+'Evolutive SFP'!D21)/'Evolutive SFP'!D27 -> 0.089400218 | G16: =('Evolutive SFP'!E7+'Evolutive SFP'!E21)/'Evolutive SFP'!E27 -> 0.075522174 | H16: =('Evolutive SFP'!F7+'Evolutive SFP'!F21)/'Evolutive SFP'!F27 -> 0.092396696 | I16: =('Evolutive SFP'!G7+'Evolutive SFP'!G21)/'Evolutive SFP'!G27 -> 0.098007878 | J16: =('Evolutive SFP'!H7+'Evolutive SFP'!H21)/'Evolutive SFP'!H27 -> 0.10097214 | K16: =('Evolutive SFP'!I7+'Evolutive SFP'!I21)/'Evolutive SFP'!I27 -> 0.093163131 | ... AV16: =('Evolutive SFP'!AT7+'Evolutive SFP'!AT21)/'Evolutive SFP'!AT27 -> #DIV/0!
B17: LB ratio | C17: Max 5% | D17: ='Evolutive SFP'!B21/'Evolutive SFP'!B27 -> 0.032278671 | E17: ='Evolutive SFP'!C21/'Evolutive SFP'!C27 -> 0.065073816 | F17: ='Evolutive SFP'!D21/'Evolutive SFP'!D27 -> 0.065438059 | G17: ='Evolutive SFP'!E21/'Evolutive SFP'!E27 -> 0.065804093 | H17: ='Evolutive SFP'!F21/'Evolutive SFP'!F27 -> 0.067025076 | I17: ='Evolutive SFP'!G21/'Evolutive SFP'!G27 -> 0.071150848 | J17: ='Evolutive SFP'!H21/'Evolutive SFP'!H27 -> 0.069898261 | K17: ='Evolutive SFP'!I21/'Evolutive SFP'!I27 -> 0.069394114 | ... AV17: ='Evolutive SFP'!AT21/'Evolutive SFP'!AT27 -> #DIV/0!
B18: PI to Deposit ratio | C18: Max 5% | D18: ='Evolutive SFP'!B13/'Evolutive SFP'!B31 -> 0.0036721969 | E18: ='Evolutive SFP'!C13/'Evolutive SFP'!C31 -> 0.0051135118 | F18: ='Evolutive SFP'!D13/'Evolutive SFP'!D31 -> 0.025119078 | G18: ='Evolutive SFP'!E13/'Evolutive SFP'!E31 -> 0.023684847 | H18: ='Evolutive SFP'!F13/'Evolutive SFP'!F31 -> 0.023986366 | I18: ='Evolutive SFP'!G13/'Evolutive SFP'!G31 -> 0.024173632 | J18: ='Evolutive SFP'!H13/'Evolutive SFP'!H31 -> 0.023816495 | K18: ='Evolutive SFP'!I13/'Evolutive SFP'!I31 -> 0.023751538 | ... AV18: ='Evolutive SFP'!AT13/'Evolutive SFP'!AT31 -> #DIV/0!
B19: PI to CC ratio | C19: Max 40% | D19: ='Evolutive SFP'!B13/(CAELS!D3*1000000) -> 0.030948443 | E19: ='Evolutive SFP'!C13/(CAELS!E3*1000000) -> 0.014823098 | F19: ='Evolutive SFP'!D13/(CAELS!F3*1000000) -> 0.070467911 | G19: ='Evolutive SFP'!E13/(CAELS!G3*1000000) -> 0.070094356 | H19: ='Evolutive SFP'!F13/(CAELS!H3*1000000) -> 0.066636747 | I19: ='Evolutive SFP'!G13/(CAELS!I3*1000000) -> 0.06417156 | J19: ='Evolutive SFP'!H13/(CAELS!J3*1000000) -> 0.062036745 | K19: ='Evolutive SFP'!I13/(CAELS!K3*1000000) -> 0.061229937 | ... AV19: ='Evolutive SFP'!AT13/(CAELS!AV3*1000000) -> #DIV/0!
B20: Gross loans/TA | D20: ='Evolutive SFP'!B15/'Evolutive SFP'!B27 -> 0.74763912 | E20: ='Evolutive SFP'!C15/'Evolutive SFP'!C27 -> 0.82353316 | F20: ='Evolutive SFP'!D15/'Evolutive SFP'!D27 -> 0.82379517 | G20: ='Evolutive SFP'!E15/'Evolutive SFP'!E27 -> 0.82019934 | H20: ='Evolutive SFP'!F15/'Evolutive SFP'!F27 -> 0.82786108 | I20: ='Evolutive SFP'!G15/'Evolutive SFP'!G27 -> 0.83125109 | J20: ='Evolutive SFP'!H15/'Evolutive SFP'!H27 -> 0.82141086 | K20: ='Evolutive SFP'!I15/'Evolutive SFP'!I27 -> 0.81914037 | ... AV20: ='Evolutive SFP'!AT15/'Evolutive SFP'!AT27 -> #DIV/0!
A21: FUNDING MIX | B21: Total Deposits/Total Assets | D21: ='Evolutive SFP'!B31/'Evolutive SFP'!B27 -> 0.85159483 | E21: ='Evolutive SFP'!C31/'Evolutive SFP'!C27 -> 0.67006082 | F21: ='Evolutive SFP'!D31/'Evolutive SFP'!D27 -> 0.6656393 | G21: ='Evolutive SFP'!E31/'Evolutive SFP'!E27 -> 0.70479046 | H21: ='Evolutive SFP'!F31/'Evolutive SFP'!F27 -> 0.70060332 | I21: ='Evolutive SFP'!G31/'Evolutive SFP'!G27 -> 0.69172824 | J21: ='Evolutive SFP'!H31/'Evolutive SFP'!H27 -> 0.6898129 | K21: ='Evolutive SFP'!I31/'Evolutive SFP'!I27 -> 0.68632059 | ... AV21: ='Evolutive SFP'!AT31/'Evolutive SFP'!AT27 -> #DIV/0!
B22: BOSA Deposits/Total Assets | D22: ='Evolutive SFP'!B30/'Evolutive SFP'!B27 -> 0.74257768 | E22: ='Evolutive SFP'!C30/'Evolutive SFP'!C27 -> 0.53250436 | F22: ='Evolutive SFP'!D30/'Evolutive SFP'!D27 -> 0.5320046 | G22: ='Evolutive SFP'!E30/'Evolutive SFP'!E27 -> 0.53835387 | H22: ='Evolutive SFP'!F30/'Evolutive SFP'!F27 -> 0.54812608 | I22: ='Evolutive SFP'!G30/'Evolutive SFP'!G27 -> 0.55057239 | J22: ='Evolutive SFP'!H30/'Evolutive SFP'!H27 -> 0.54379453 | K22: ='Evolutive SFP'!I30/'Evolutive SFP'!I27 -> 0.54236051 | ... AV22: ='Evolutive SFP'!AT30/'Evolutive SFP'!AT27 -> #DIV/0!
B23: FOSA Deposits/Total Assets | D23: =('Evolutive SFP'!B28+'Evolutive SFP'!B29)/'Evolutive SFP'!B27 -> 0.10901715 | E23: =('Evolutive SFP'!C28+'Evolutive SFP'!C29)/'Evolutive SFP'!C27 -> 0.13755646 | F23: =('Evolutive SFP'!D28+'Evolutive SFP'!D29)/'Evolutive SFP'!D27 -> 0.13363469 | G23: =('Evolutive SFP'!E28+'Evolutive SFP'!E29)/'Evolutive SFP'!E27 -> 0.16643659 | H23: =('Evolutive SFP'!F28+'Evolutive SFP'!F29)/'Evolutive SFP'!F27 -> 0.15247724 | I23: =('Evolutive SFP'!G28+'Evolutive SFP'!G29)/'Evolutive SFP'!G27 -> 0.14115585 | J23: =('Evolutive SFP'!H28+'Evolutive SFP'!H29)/'Evolutive SFP'!H27 -> 0.14601837 | K23: =('Evolutive SFP'!I28+'Evolutive SFP'!I29)/'Evolutive SFP'!I27 -> 0.14396008 | ... AV23: =('Evolutive SFP'!AT28+'Evolutive SFP'!AT29)/'Evolutive SFP'!AT27 -> #DIV/0!
A24: GROWTH RATIOS | B24: Total Assets | D24: =(Financials!C4-Financials!B4)/Financials!B4 -> #VALUE! | E24: =(Financials!D4-Financials!C4)/Financials!C4 -> 60.822891 | F24: =(Financials!E4-Financials!D4)/Financials!D4 -> 0.0083812423 | G24: =(Financials!F4-Financials!E4)/Financials!E4 -> 0.0016409092 | H24: =(Financials!G4-Financials!F4)/Financials!F4 -> -0.0066690526 | I24: =(Financials!H4-Financials!G4)/Financials!G4 -> 0.00498417 | J24: =(Financials!I4-Financials!H4)/Financials!H4 -> 0.017813595 | K24: =(Financials!J4-Financials!I4)/Financials!I4 -> 0.0078372161 | ... AV24: =(Financials!AU4-Financials!AT4)/Financials!AT4 -> #DIV/0!
B25: Total Deposits | C25: =IF(CAELS!D16<6%,"1",IF) -> #NAME? | D25: =Financials!D5/Financials!C5-1 -> 47.644139 | E25: =Financials!E5/Financials!D5-1 -> 0.0017272531 | F25: =Financials!F5/Financials!E5-1 -> 0.060554808 | G25: =Financials!G5/Financials!F5-1 -> -0.012570409 | H25: =Financials!H5/Financials!G5-1 -> -0.0077467331 | I25: =Financials!I5/Financials!H5-1 -> 0.014995351 | J25: =Financials!J5/Financials!I5-1 -> 0.0027348548 | K25: =Financials!K5/Financials!J5-1 -> 0.013082325 | ... AV25: =Financials!AV5/Financials!AU5-1 -> #DIV/0!
B26: BOSA Deposits | D26: =Financials!D6/Financials!C6-1 -> 43.333354 | E26: =Financials!E6/Financials!D6-1 -> 0.0074348792 | F26: =Financials!F6/Financials!E6-1 -> 0.013595096 | G26: =Financials!G6/Financials!F6-1 -> 0.011361912 | H26: =Financials!H6/Financials!G6-1 -> 0.0094694619 | I26: =Financials!I6/Financials!H6-1 -> 0.0052837217 | J26: =Financials!J6/Financials!I6-1 -> 0.0051794931 | K26: =Financials!K6/Financials!J6-1 -> -0.0028245098 | ... AV26: =Financials!AV6/Financials!AU6-1 -> #DIV/0!
B27: FOSA Deposits | D27: =Financials!D7/Financials!C7-1 -> 77.007337 | E27: =Financials!E7/Financials!D7-1 -> -0.020367935 | F27: =Financials!F7/Financials!E7-1 -> 0.24750314 | G27: =Financials!G7/Financials!F7-1 -> -0.089981616 | H27: =Financials!H7/Financials!G7-1 -> -0.069635614 | I27: =Financials!I7/Financials!H7-1 -> 0.052875151 | J27: =Financials!J7/Financials!I7-1 -> -0.0063693484 | K27: =Financials!K7/Financials!J7-1 -> 0.073010321 | ... AV27: =Financials!AV7/Financials!AU7-1 -> #DIV/0!
B28: Total Loans & advances | D28: =Financials!D31/Financials!C31-1 -> 67.098632 | E28: =Financials!E31/Financials!D31-1 -> 0.0087020722 | F28: =Financials!F31/Financials!E31-1 -> -0.0027312184 | G28: =Financials!G31/Financials!F31-1 -> 0.002609965 | H28: =Financials!H31/Financials!G31-1 -> 0.0090994834 | I28: =Financials!I31/Financials!H31-1 -> 0.0057648676 | J28: =Financials!J31/Financials!I31-1 -> 0.0050514133 | K28: =Financials!K31/Financials!J31-1 -> 0.032474234 | ... AV28: =Financials!AV31/Financials!AU31-1 -> #DIV/0!
B29: Core capital | D29: =Financials!D11/Financials!C11-1 -> 137.48381 | E29: =Financials!E11/Financials!D11-1 -> 0.037859597 | F29: =Financials!F11/Financials!E11-1 -> 0.0057333321 | G29: =Financials!G11/Financials!F11-1 -> 0.055798588 | H29: =Financials!H11/Financials!G11-1 -> 0.04115821 | I29: =Financials!I11/Financials!H11-1 -> 0.036771816 | J29: =Financials!J11/Financials!I11-1 -> 0.014048205 | K29: =Financials!K11/Financials!J11-1 -> 0.068474368 | ... AV29: =Financials!AV11/Financials!AU11-1 -> #DIV/0!
B30: Turnover | D30: =Financials!D37/Financials!C37-1 -> 102967.41 | E30: =Financials!E37/Financials!D37-1 -> -0.92220734 | F30: =Financials!F37/Financials!E37-1 -> 1.039696 | G30: =Financials!G37/Financials!F37-1 -> 0.51768888 | H30: =Financials!H37/Financials!G37-1 -> 0.3689356 | I30: =Financials!I37/Financials!H37-1 -> 0.26487225 | J30: =Financials!J37/Financials!I37-1 -> 0.20136907 | K30: =Financials!K37/Financials!J37-1 -> 0.20510246 | ... AV30: =Financials!AV37/Financials!AU37-1 -> #DIV/0!
B31: Membership
B32: Expenses | D32: ='Evolutitve SCI'!E39/'Evolutitve SCI'!B39-1 -> 8336.5336 | E32: ='Evolutitve SCI'!F39/'Evolutitve SCI'!C39-1 -> -0.85886667 | F32: ='Evolutitve SCI'!G39/'Evolutitve SCI'!D39-1 -> 4.1277694 | G32: ='Evolutitve SCI'!H39/'Evolutitve SCI'!E39-1 -> 1.5100039 | H32: ='Evolutitve SCI'!#REF!/'Evolutitve SCI'!F39-1 -> #REF! | I32: ='Evolutitve SCI'!#REF!/'Evolutitve SCI'!G39-1 -> #REF! | J32: ='Evolutitve SCI'!#REF!/'Evolutitve SCI'!H39-1 -> #REF! | K32: ='Evolutitve SCI'!#REF!/'Evolutitve SCI'!I39-1 -> #REF! | L32: ='Evolutitve SCI'!#REF!/'Evolutitve SCI'!J39-1 -> #REF! | M32: ='Evolutitve SCI'!#REF!/'Evolutitve SCI'!K39-1 -> #REF! | N32: ='Evolutitve SCI'!#REF!/'Evolutitve SCI'!L39-1 -> #REF! | O32: ='Evolutitve SCI'!#REF!/'Evolutitve SCI'!M39-1 -> #REF! | ... AV32: ='Evolutitve SCI'!#REF!/'Evolutitve SCI'!AT39-1 -> #REF!
A33: Efficiency Ratios | B33: FinCost-Deposits/Avg Deposits | H33: =Financials!G44/('Evolutive SFP'!B30+'Evolutive SFP'!F30)/2 -> 0.00043133646
B34: FinCost-Shares/Avg Share capital | H34: =Financials!G45/('Evolutive SFP'!B39+'Evolutive SFP'!F39)/2 -> 0
B35: FinCost-Ext Loans/Avg Ext Loans | H35: =Financials!G46/(Financials!F31+Financials!G31)/2 -> 0.00019752161
B36: OpEx/Average Total Assets | H36: =Financials!G47/(Financials!F4+Financials!G4)/2 -> 0.0032862874
B37: Opex/Turnover | H37: =Financials!G47/Financials!G37 -> 0.34127301
B38: Avge yield on Net loans | H38: =Financials!G38/('Evolutive SFP'!F14+'Evolutive SFP'!B14)/2 -> 0.022128613
B39: Avge yield on Gross loans | H39: =Financials!G37/('Evolutive SFP'!F15+'Evolutive SFP'!B15)/2 -> 0.023006679
A41: ALL/Average Gross Loan portfolio

Sheet Financials
B1: SOLUTION Sacco Financial Performance
B2: Year | C2: 2010 Audited | D2: 2020 Audited | E2: 44197 | F2: 44229 | G2: 44258 | H2: 44290 | I2: 44321 | J2: 44353 | K2: 44384 | L2: 44416 | M2: 44448 | N2: 44479 | O2: 44511 | P2: 44542 | Q2: Audited 2021 | R2: 44582 | S2: 44614 | T2: 44643 | U2: 44675 | V2: 44706 | W2: 44738 | X2: 44769 | Y2: 44801 | Z2: 44833 | AA2: 44864 | AB2: 31-11-2022 | AC2: 44896 | AD2: Audited2022 | AE2: 44927 | AF2: 44958 | AG2: 44986 | AH2: 45017 | AI2: 45047
A3: 1 | B3: Membership
A4: 2 | B4: Total Assets | C4: ='Evolutive SFP'!B27 -> 151015729 | D4: ='Evolutive SFP'!C27 -> 9336228976 | E4: ='Evolutive SFP'!D27 -> 9.4144782e+09 | F4: ='Evolutive SFP'!E27 -> 9.4299265e+09 | G4: ='Evolutive SFP'!F27 -> 9.3670378e+09 | H4: ='Evolutive SFP'!G27 -> 9.4137247e+09 | I4: ='Evolutive SFP'!H27 -> 9.581417e+09 | J4: ='Evolutive SFP'!I27 -> 9.6565086e+09 | ... AY4: ='Evolutive SFP'!AX27 -> 0
A5: 3 | B5: Total Deposits | C5: ='Evolutive SFP'!B31 -> 128604214 | D5: ='Evolutive SFP'!C31 -> 6255841210 | E5: ='Evolutive SFP'!D31 -> 6.2666466e+09 | F5: ='Evolutive SFP'!E31 -> 6.6461222e+09 | G5: ='Evolutive SFP'!F31 -> 6.5625777e+09 | H5: ='Evolutive SFP'!G31 -> 6.5117392e+09 | I5: ='Evolutive SFP'!H31 -> 6.609385e+09 | J5: ='Evolutive SFP'!I31 -> 6.6274607e+09 | ... AY5: ='Evolutive SFP'!AX31 -> 0
A6: 3.1 | B6: Deposits-Members(BOSA) | C6: ='Evolutive SFP'!B30 -> 112140909 | D6: ='Evolutive SFP'!C30 -> 4971582622 | E6: ='Evolutive SFP'!D30 -> 5.0085457e+09 | F6: ='Evolutive SFP'!E30 -> 5.0766374e+09 | G6: ='Evolutive SFP'!F30 -> 5.1343177e+09 | H6: ='Evolutive SFP'!G30 -> 5.1829369e+09 | I6: ='Evolutive SFP'!H30 -> 5.2103221e+09 | J6: ='Evolutive SFP'!I30 -> 5.237309e+09 | ... AY6: ='Evolutive SFP'!AX30 -> 0
A7: 3.2 | B7: Deposits-Customers(FOSA) | C7: =('Evolutive SFP'!B28+'Evolutive SFP'!B29) -> 16463305 | D7: =('Evolutive SFP'!C28+'Evolutive SFP'!C29) -> 1284258588 | E7: =('Evolutive SFP'!D28+'Evolutive SFP'!D29) -> 1.2581009e+09 | F7: =('Evolutive SFP'!E28+'Evolutive SFP'!E29) -> 1.5694848e+09 | G7: =('Evolutive SFP'!F28+'Evolutive SFP'!F29) -> 1.42826e+09 | H7: =('Evolutive SFP'!G28+'Evolutive SFP'!G29) -> 1.3288023e+09 | I7: =('Evolutive SFP'!H28+'Evolutive SFP'!H29) -> 1.3990629e+09 | J7: =('Evolutive SFP'!I28+'Evolutive SFP'!I29) -> 1.3901518e+09 | ... AY7: =('Evolutive SFP'!AX28+'Evolutive SFP'!AX29) -> 0
A8: 4 | B8: External Borrowing | C8: ='Evolutive SFP'!B37 -> 2291669 | D8: ='Evolutive SFP'!C37 -> 267946962 | E8: ='Evolutive SFP'!D37 -> 2.6228029e+08 | F8: ='Evolutive SFP'!E37 -> 2.5661363e+08 | G8: ='Evolutive SFP'!F37 -> 2.4410948e+08 | H8: ='Evolutive SFP'!G37 -> 2.3645754e+08 | I8: ='Evolutive SFP'!H37 -> 2.3277615e+08 | J8: ='Evolutive SFP'!I37 -> 2.231077e+08 | ... AY8: ='Evolutive SFP'!AX37 -> 0
A10: 5 | B10: Share capital and Reserves
A11: 5.1 | B11: Core Capital | C11: =C14-C22-C25 -> 14446887 | D11: =D14-D22-D25 -> 2000660017 | E11: =E14-E22-E25 -> 2.0764042e+09 | F11: =F14-F22-F25 -> 2.0883089e+09 | G11: =G14-G22-G25 -> 2.2048336e+09 | H11: =H14-H22-H25 -> 2.2955806e+09 | I11: =I14-I22-I25 -> 2.3799933e+09 | J11: =J14-J22-J25 -> 2.4134279e+09 | ... AY11: =AY14-AY22-AY25 -> 0
A12: 5.2 | B12: Institutional Capital | C12: =C11-C15 -> 3952190 | D12: =D11-D15 -> 1573584584 | E12: =E11-E15 -> 1.6491969e+09 | F12: =F11-F15 -> 1.6599901e+09 | G12: =G11-G15 -> 1.7756762e+09 | H12: =H11-H15 -> 1.8660691e+09 | I12: =I11-I15 -> 1.9502578e+09 | J12: =J11-J15 -> 1.9834667e+09 | ... AY12: =AY11-AY15 -> 0
A14: 5.3 | B14: Total Capital | C14: =C15+C16+C17+C18+C19+C20+C21 -> 14919147 | D14: =D15+D16+D17+D18+D19+D20+D21 -> 2217859424 | E14: =E15+E16+E17+E18+E19+E20+E21 -> 2.2338166e+09 | F14: =F15+F16+F17+F18+F19+F20+F21 -> 2.2457213e+09 | G14: =G15+G16+G17+G18+G19+G20+G21 -> 2.362246e+09 | H14: =H15+H16+H17+H18+H19+H20+H21 -> 2.452993e+09 | I14: =I15+I16+I17+I18+I19+I20+I21 -> 2.5374057e+09 | J14: =J15+J16+J17+J18+J19+J20+J21 -> 2.5708403e+09 | ... AY14: =AY15+AY16+AY17+AY18+AY19+AY20+AY21 -> 0
A15: 5.3.1 | B15: Members Share Capital | C15: ='Evolutive SFP'!B39 -> 10494697 | D15: ='Evolutive SFP'!C39 -> 427075433 | E15: ='Evolutive SFP'!D39 -> 4.2720733e+08 | F15: ='Evolutive SFP'!E39 -> 4.283188e+08 | G15: ='Evolutive SFP'!F39 -> 4.2915738e+08 | H15: ='Evolutive SFP'!G39 -> 4.2951151e+08 | I15: ='Evolutive SFP'!H39 -> 4.2973546e+08 | J15: ='Evolutive SFP'!I39 -> 4.2996121e+08 | ... AY15: ='Evolutive SFP'!AX39 -> 0
A16: 5.3.2 | B16: Entrance Fees
A17: 5.3.3 | B17: Retained Earnings | C17: ='Evolutive SFP'!B41 -> 351220 | D17: ='Evolutive SFP'!C41 -> 566196154 | E17: ='Evolutive SFP'!D41 -> 739449224 | F17: ='Evolutive SFP'!E41 -> 739449224 | G17: ='Evolutive SFP'!F41 -> 739449224 | H17: ='Evolutive SFP'!G41 -> 739449224 | I17: ='Evolutive SFP'!H41 -> 739449224 | J17: ='Evolutive SFP'!I41 -> 739449224 | ... AY17: ='Evolutive SFP'!AX41 -> 0
A18: 5.3.4 | B18: Appropriation Account | C18: ='Evolutive SFP'!B42 -> 3541956 | D18: ='Evolutive SFP'!C42 -> 173253070 | E18: ='Evolutive SFP'!D42 -> 79610495 | F18: ='Evolutive SFP'!E42 -> 1.4195739e+08 | G18: ='Evolutive SFP'!F42 -> 2.1849279e+08 | H18: ='Evolutive SFP'!G42 -> 3.0423397e+08 | I18: ='Evolutive SFP'!H42 -> 3.8457498e+08 | J18: ='Evolutive SFP'!I42 -> 4.6048523e+08 | ... AY18: ='Evolutive SFP'!AX42 -> 0
A19: 5.3.5 | B19: Statutory Reserves | C19: ='Evolutive SFP'!B43 -> 531274 | D19: ='Evolutive SFP'!C43 -> 413899587 | E19: ='Evolutive SFP'!D43 -> 413899587 | F19: ='Evolutive SFP'!E43 -> 413899587 | G19: ='Evolutive SFP'!F43 -> 413899587 | H19: ='Evolutive SFP'!G43 -> 413899587 | I19: ='Evolutive SFP'!H43 -> 413899587 | J19: ='Evolutive SFP'!I43 -> 413899587 | ... AY19: ='Evolutive SFP'!AX43 -> 0
A20: 5.3.6 | B20: Capital Reserves | C20: =('Evolutive SFP'!B44) -> 0 | D20: =('Evolutive SFP'!C44) -> 577648161 | E20: =('Evolutive SFP'!D44) -> 5.7364995e+08 | F20: =('Evolutive SFP'!E44) -> 5.220963e+08 | G20: =('Evolutive SFP'!F44) -> 5.6124702e+08 | H20: =('Evolutive SFP'!G44) -> 5.6589871e+08 | I20: =('Evolutive SFP'!H44) -> 5.6974642e+08 | J20: =('Evolutive SFP'!I44) -> 5.2704505e+08 | ... AY20: =('Evolutive SFP'!AX44) -> 0
A21: 5.3.7 | B21: Supplementary Capital & reserves | C21: =C22+C23 -> 0 | D21: =D22+D23 -> 59787019 | E21: =E22+E23 -> 0 | F21: =F22+F23 -> 0 | G21: =G22+G23 -> 0 | H21: =H22+H23 -> 0 | I21: =I22+I23 -> 0 | J21: =J22+J23 -> 0 | ... AY21: =AY22+AY23 -> 0
A22: a | B22: Proposed Dividends | C22: ='Evolutive SFP'!B46 -> 0 | D22: ='Evolutive SFP'!C46 -> 59787019 | E22: ='Evolutive SFP'!D46 -> 0 | F22: ='Evolutive SFP'!E46 -> 0 | G22: ='Evolutive SFP'!F46 -> 0 | H22: ='Evolutive SFP'!G46 -> 0 | I22: ='Evolutive SFP'!H46 -> 0 | J22: ='Evolutive SFP'!I46 -> 0 | ... AY22: ='Evolutive SFP'!AX46 -> 0
A23: b | B23: Risk Mgt Fund
A25: 6 | B25: Investments | C25: =C26+C27+C28 -> 472260 | D25: =D26+D27+D28 -> 157412388 | E25: =E26+E27+E28 -> 1.5741239e+08 | F25: =F26+F27+F28 -> 1.5741239e+08 | G25: =G26+G27+G28 -> 1.5741239e+08 | H25: =H26+H27+H28 -> 1.5741239e+08 | I25: =I26+I27+I28 -> 1.5741239e+08 | J25: =J26+J27+J28 -> 1.5741239e+08 | ... AY25: =AY26+AY27+AY28 -> 0
A26: 6.1 | B26: Shares in Kusco,CIC,Coop Bank | C26: ='Evolutive SFP'!B13 -> 472260 | D26: ='Evolutive SFP'!C13 -> 31989318 | E26: ='Evolutive SFP'!D13 -> 1.5741239e+08 | F26: ='Evolutive SFP'!E13 -> 1.5741239e+08 | G26: ='Evolutive SFP'!F13 -> 1.5741239e+08 | H26: ='Evolutive SFP'!G13 -> 1.5741239e+08 | I26: ='Evolutive SFP'!H13 -> 1.5741239e+08 | J26: ='Evolutive SFP'!I13 -> 1.5741239e+08 | ... AY26: ='Evolutive SFP'!AX13 -> 0
A27: 6.2 | B27: Equity Investments (at cost) | C27: ='Evolutive SFP'!B10 -> 0 | D27: ='Evolutive SFP'!C10 -> 0 | E27: ='Evolutive SFP'!D10 -> 0 | F27: ='Evolutive SFP'!E10 -> 0 | G27: ='Evolutive SFP'!F10 -> 0 | H27: ='Evolutive SFP'!G10 -> 0 | I27: ='Evolutive SFP'!H10 -> 0 | J27: ='Evolutive SFP'!I10 -> 0 | ... AY27: ='Evolutive SFP'!AX10 -> 0
A28: 6.3 | B28: Deposits in KUSCCO CFP | C28: ='Evolutive SFP'!B11 -> 0 | D28: ='Evolutive SFP'!C11 -> 125423070 | E28: ='Evolutive SFP'!D11 -> 0 | F28: ='Evolutive SFP'!E11 -> 0 | G28: ='Evolutive SFP'!F11 -> 0 | H28: ='Evolutive SFP'!G11 -> 0 | I28: ='Evolutive SFP'!H11 -> 0 | J28: ='Evolutive SFP'!I11 -> 0 | ... AY28: ='Evolutive SFP'!AX11 -> 0
A30: 7 | B30: Net Loans & Advances | C30: ='Evolutive SFP'!B14 -> 112905266 | D30: ='Evolutive SFP'!C14 -> 7149156133 | E30: ='Evolutive SFP'!D14 -> 7.2160637e+09 | F30: ='Evolutive SFP'!E14 -> 7.1948815e+09 | G30: ='Evolutive SFP'!F14 -> 7.215068e+09 | H30: ='Evolutive SFP'!G14 -> 7.2856309e+09 | I30: ='Evolutive SFP'!H14 -> 7.330742e+09 | J30: ='Evolutive SFP'!I14 -> 7.370498e+09 | ... AY30: ='Evolutive SFP'!AX14 -> 0
A31: 7.1 | B31: Gross Loans & advances | C31: ='Evolutive SFP'!B15 -> 112905266 | D31: ='Evolutive SFP'!C15 -> 7688694111 | E31: ='Evolutive SFP'!D15 -> 7.7556017e+09 | F31: ='Evolutive SFP'!E15 -> 7.7344194e+09 | G31: ='Evolutive SFP'!F15 -> 7.754606e+09 | H31: ='Evolutive SFP'!G15 -> 7.8251689e+09 | I31: ='Evolutive SFP'!H15 -> 7.87028e+09 | J31: ='Evolutive SFP'!I15 -> 7.910036e+09 | ... AY31: ='Evolutive SFP'!AX15 -> 0
A32: 7.2 | B32: Allowance for loan losses | C32: ='Evolutive SFP'!B16 -> 0 | D32: ='Evolutive SFP'!C16 -> 539537978 | E32: ='Evolutive SFP'!D16 -> 5.3953798e+08 | F32: ='Evolutive SFP'!E16 -> 5.3953798e+08 | G32: ='Evolutive SFP'!F16 -> 5.3953798e+08 | H32: ='Evolutive SFP'!G16 -> 5.3953798e+08 | I32: ='Evolutive SFP'!H16 -> 5.3953798e+08 | J32: ='Evolutive SFP'!I16 -> 5.3953798e+08 | ... AY32: ='Evolutive SFP'!AX16 -> 0
A34: 8 | B34: Non-Earning Assets | C34: ='Evolutive SFP'!B21+'Evolutive SFP'!B7 -> 18274979 | D34: ='Evolutive SFP'!C21+'Evolutive SFP'!C7 -> 842998992 | E34: ='Evolutive SFP'!D21+'Evolutive SFP'!D7 -> 8.416564e+08 | F34: ='Evolutive SFP'!E21+'Evolutive SFP'!E7 -> 7.1216854e+08 | G34: ='Evolutive SFP'!F21+'Evolutive SFP'!F7 -> 8.6548334e+08 | H34: ='Evolutive SFP'!G21+'Evolutive SFP'!G7 -> 9.2261918e+08 | I34: ='Evolutive SFP'!H21+'Evolutive SFP'!H7 -> 9.6745618e+08 | J34: ='Evolutive SFP'!I21+'Evolutive SFP'!I7 -> 8.9963058e+08 | ... AY34: ='Evolutive SFP'!AX21+'Evolutive SFP'!AX7 -> 0
A35: 8.1 | B35: Property and Equipment | C35: ='Evolutive SFP'!B23 -> 4123114 | D35: ='Evolutive SFP'!C23 -> 579283128 | E35: ='Evolutive SFP'!D23 -> 5.8274388e+08 | F35: ='Evolutive SFP'!E23 -> 5.8720645e+08 | G35: ='Evolutive SFP'!F23 -> 5.9450511e+08 | H35: ='Evolutive SFP'!G23 -> 6.3505704e+08 | I35: ='Evolutive SFP'!H23 -> 6.3498692e+08 | J35: ='Evolutive SFP'!I23 -> 6.353674e+08 | ... AY35: ='Evolutive SFP'!AX23 -> 0
A37: 9 | B37: Turnover | C37: =C38+C39+C40+C41 -> 14599.248 | D37: =D38+D39+D40+D41 -> 1503261371 | E37: =E38+E39+E40+E41 -> 1.169427e+08 | F37: =F38+F39+F40+F41 -> 2.3852756e+08 | G37: =G38+G39+G40+G41 -> 3.6201062e+08 | H37: =H38+H39+H40+H41 -> 4.9556922e+08 | I37: =I38+I39+I40+I41 -> 6.2683176e+08 | J37: =J38+J39+J40+J41 -> 7.5305629e+08 | ... AY37: =AY38+AY39+AY40+AY41 -> 0
A38: 9.1 | B38: Loan Interest | C38: ='Evolutitve SCI'!B5 -> 11945.435 | D38: ='Evolutitve SCI'!C5 -> 1292172434 | E38: ='Evolutitve SCI'!D5 -> 1.0724226e+08 | F38: ='Evolutitve SCI'!E5 -> 2.1674843e+08 | G38: ='Evolutitve SCI'!F5 -> 3.2431578e+08 | H38: ='Evolutitve SCI'!G5 -> 4.3543457e+08 | I38: ='Evolutitve SCI'!H5 -> 5.4532057e+08 | J38: ='Evolutitve SCI'!I5 -> 6.566322e+08 | ... AY38: ='Evolutitve SCI'!AX5 -> 0
A39: 9.2 | B39: Income from investments | C39: ='Evolutitve SCI'!B7 -> 1743.4416 | D39: ='Evolutitve SCI'!C7 -> 188486662 | E39: ='Evolutitve SCI'!D7 -> 6557028.2 | F39: ='Evolutitve SCI'!E7 -> 14596437 | G39: ='Evolutitve SCI'!F7 -> 26435153 | H39: ='Evolutitve SCI'!G7 -> 43984291 | I39: ='Evolutitve SCI'!H7 -> 60407858 | J39: ='Evolutitve SCI'!I7 -> 70763135 | ... AY39: ='Evolutitve SCI'!AX7 -> 0
A40: 9.3 | B40: Fees & Commissions | C40: ='Evolutitve SCI'!B6 -> 910.371 | D40: ='Evolutitve SCI'!C6 -> 22602275 | E40: ='Evolutitve SCI'!D6 -> 3143406 | F40: ='Evolutitve SCI'!E6 -> 7182686 | G40: ='Evolutitve SCI'!F6 -> 11259690 | H40: ='Evolutitve SCI'!G6 -> 16150367 | I40: ='Evolutitve SCI'!H6 -> 21103328 | J40: ='Evolutitve SCI'!I6 -> 25660954 | ... AY40: ='Evolutitve SCI'!AX6 -> 0
A41: 9.4 | B41: Average yield on loans
A43: 10 | B43: Financial and Operating costs | C43: =SUM(C44:C47) -> 11568.465 | D43: =SUM(D44:D47) -> 1015841652 | E43: =SUM(E44:E47) -> 37084587 | F43: =SUM(F44:F47) -> 87267665 | G43: =SUM(G44:G47) -> 1.3418927e+08 | H43: =SUM(H44:H47) -> 1.8179983e+08 | I43: =SUM(I44:I47) -> 2.3259952e+08 | J43: =SUM(J44:J47) -> 2.8023446e+08 | ... AY43: =SUM(AY44:AY47) -> 0
A44: 10.1 | B44: Interest expense on deposits | C44: ='Evolutitve SCI'!B13+'Evolutitve SCI'!B16 -> 185.36 | D44: ='Evolutitve SCI'!C13+'Evolutitve SCI'!C16 -> 419264945 | E44: ='Evolutitve SCI'!D13+'Evolutitve SCI'!D16 -> 2146313.2 | F44: ='Evolutitve SCI'!E13+'Evolutitve SCI'!E16 -> 3663638.8 | G44: ='Evolutitve SCI'!F13+'Evolutitve SCI'!F16 -> 4525977.8 | H44: ='Evolutitve SCI'!G13+'Evolutitve SCI'!G16 -> 5891015.3 | I44: ='Evolutitve SCI'!H13+'Evolutitve SCI'!H16 -> 7325482.4 | J44: ='Evolutitve SCI'!I13+'Evolutitve SCI'!I16 -> 7910570.9 | ... AY44: ='Evolutitve SCI'!AX13+'Evolutitve SCI'!AX16 -> 0
A45: 10.2 | B45: Dividend expense on share capital | C45: ='Evolutitve SCI'!B15 -> 0 | D45: ='Evolutitve SCI'!C15 -> 0 | E45: ='Evolutitve SCI'!D15 -> 0 | F45: ='Evolutitve SCI'!E15 -> 0 | G45: ='Evolutitve SCI'!F15 -> 0 | H45: ='Evolutitve SCI'!G15 -> 0 | I45: ='Evolutitve SCI'!H15 -> 0 | J45: ='Evolutitve SCI'!I15 -> 0 | ... AY45: ='Evolutitve SCI'!AX15 -> 0
A46: 10.3 | B46: Interest expense on borrowed funds | C46: ='Evolutitve SCI'!B14 -> 363.7247 | D46: ='Evolutitve SCI'!C14 -> 37739397 | E46: ='Evolutitve SCI'!D14 -> 2165753.1 | F46: ='Evolutitve SCI'!E14 -> 4271346.4 | G46: ='Evolutitve SCI'!F14 -> 6118834.6 | H46: ='Evolutitve SCI'!G14 -> 6118834.6 | I46: ='Evolutitve SCI'!H14 -> 9967121.7 | J46: ='Evolutitve SCI'!I14 -> 14699521 | ... AY46: ='Evolutitve SCI'!AX14 -> 0
A47: 10.4 | B47: Opperating expenses | C47: ='Evolutitve SCI'!B23 -> 11019.38 | D47: ='Evolutitve SCI'!C23 -> 558837310 | E47: ='Evolutitve SCI'!D23 -> 32772521 | F47: ='Evolutitve SCI'!E23 -> 79332679 | G47: ='Evolutitve SCI'!F23 -> 1.2354445e+08 | H47: ='Evolutitve SCI'!G23 -> 1.6978998e+08 | I47: ='Evolutitve SCI'!H23 -> 2.1530691e+08 | J47: ='Evolutitve SCI'!I23 -> 2.5762437e+08 | ... AY47: ='Evolutitve SCI'!AX23 -> 0

Sheet CAELS Rating
A2: CAELS RATINGS KINGDOM SACCO
A3: FINANCIAL SOUNDNESS INDICATORS | B3: Prude. Std | C3: 2010 Audited | D3: 2021 Audited | E3: 44197.12 | F3: 44229 | G3: 44258 | H3: 44290 | I3: 44321 | J3: 44353 | K3: 44384 | L3: 44416 | M3: 44448 | N3: 44479 | O3: 44511 | P3: 44542 | Q3: Audited 2021 | R3: 44562 | S3: 44593 | T3: 44621 | U3: 44652
A4: CAPITAL
A5: CORE CAPITAL | B5: ≥ Ksh.10M | C5: =IF(CAELS!D3>10,"1","5") -> 1 | D5: =IF(CAELS!E3>10,"1","5") -> 1 | E5: =IF(CAELS!F3>10,"1","5") -> 1 | F5: =IF(CAELS!G3>10,"1","5") -> 1 | G5: =IF(CAELS!H3>10,"1","5") -> 1 | H5: =IF(CAELS!I3>10,"1","5") -> 1 | I5: =IF(CAELS!J3>10,"1","5") -> 1 | J5: =IF(CAELS!K3>10,"1","5") -> 1 | ... U5: =IF(CAELS!V3>10,"1","5") -> 1
A6: CCA | B6: ≥ 10% | C6: =IF(CAELS!D4>20%,"1",IF(CAELS!D4>15%,"2",IF(CAELS!D4>12%,"3",IF(CAELS!D4>10%,"4","5")))) -> 4 | D6: =IF(CAELS!E4>20%,"1",IF(CAELS!E4>15%,"2",IF(CAELS!E4>12%,"3",IF(CAELS!E4>10%,"4","5")))) -> 1 | E6: =IF(CAELS!F4>20%,"1",IF(CAELS!F4>15%,"2",IF(CAELS!F4>12%,"3",IF(CAELS!F4>10%,"4","5")))) -> 1 | F6: =IF(CAELS!G4>20%,"1",IF(CAELS!G4>15%,"2",IF(CAELS!G4>12%,"3",IF(CAELS!G4>10%,"4","5")))) -> 1 | G6: =IF(CAELS!H4>20%,"1",IF(CAELS!H4>15%,"2",IF(CAELS!H4>12%,"3",IF(CAELS!H4>10%,"4","5")))) -> 1 | H6: =IF(CAELS!I4>20%,"1",IF(CAELS!I4>15%,"2",IF(CAELS!I4>12%,"3",IF(CAELS!I4>10%,"4","5")))) -> 1 | I6: =IF(CAELS!J4>20%,"1",IF(CAELS!J4>15%,"2",IF(CAELS!J4>12%,"3",IF(CAELS!J4>10%,"4","5")))) -> 1 | J6: =IF(CAELS!K4>20%,"1",IF(CAELS!K4>15%,"2",IF(CAELS!K4>12%,"3",IF(CAELS!K4>10%,"4","5")))) -> 1 | ... U6: =IF(CAELS!V4>20%,"1",IF(CAELS!V4>15%,"2",IF(CAELS!V4>12%,"3",IF(CAELS!V4>10%,"4","5")))) -> 1
A7: ICA | B7: ≥ 8% | C7: =IF(CAELS!D6>15%,"1",IF(CAELS!D6>12%,"2",IF(CAELS!D6>10%,"3",IF(CAELS!D6>8,"4","5")))) -> 5 | D7: =IF(CAELS!E6>15%,"1",IF(CAELS!E6>12%,"2",IF(CAELS!E6>10%,"3",IF(CAELS!E6>8,"4","5")))) -> 1 | E7: =IF(CAELS!F6>15%,"1",IF(CAELS!F6>12%,"2",IF(CAELS!F6>10%,"3",IF(CAELS!F6>8,"4","5")))) -> 1 | F7: =IF(CAELS!G6>15%,"1",IF(CAELS!G6>12%,"2",IF(CAELS!G6>10%,"3",IF(CAELS!G6>8,"4","5")))) -> 1 | G7: =IF(CAELS!H6>15%,"1",IF(CAELS!H6>12%,"2",IF(CAELS!H6>10%,"3",IF(CAELS!H6>8,"4","5")))) -> 1 | H7: =IF(CAELS!I6>15%,"1",IF(CAELS!I6>12%,"2",IF(CAELS!I6>10%,"3",IF(CAELS!I6>8,"4","5")))) -> 1 | I7: =IF(CAELS!J6>15%,"1",IF(CAELS!J6>12%,"2",IF(CAELS!J6>10%,"3",IF(CAELS!J6>8,"4","5")))) -> 1 | J7: =IF(CAELS!K6>15%,"1",IF(CAELS!K6>12%,"2",IF(CAELS!K6>10%,"3",IF(CAELS!K6>8,"4","5")))) -> 1 | ... U7: =IF(CAELS!V6>15%,"1",IF(CAELS!V6>12%,"2",IF(CAELS!V6>10%,"3",IF(CAELS!V6>8,"4","5")))) -> 1
A8: CCD | B8: ≥ 8% | C8: =IF(CAELS!D5>20%,"1",IF(CAELS!D5>15%,"2",IF(CAELS!D5>12%,"3",IF(CAELS!D5>10%,"4","5")))) -> 4 | D8: =IF(CAELS!E5>20%,"1",IF(CAELS!E5>15%,"2",IF(CAELS!E5>12%,"3",IF(CAELS!E5>10%,"4","5")))) -> 1 | E8: =IF(CAELS!F5>20%,"1",IF(CAELS!F5>15%,"2",IF(CAELS!F5>12%,"3",IF(CAELS!F5>10%,"4","5")))) -> 1 | F8: =IF(CAELS!G5>20%,"1",IF(CAELS!G5>15%,"2",IF(CAELS!G5>12%,"3",IF(CAELS!G5>10%,"4","5")))) -> 1 | G8: =IF(CAELS!H5>20%,"1",IF(CAELS!H5>15%,"2",IF(CAELS!H5>12%,"3",IF(CAELS!H5>10%,"4","5")))) -> 1 | H8: =IF(CAELS!I5>20%,"1",IF(CAELS!I5>15%,"2",IF(CAELS!I5>12%,"3",IF(CAELS!I5>10%,"4","5")))) -> 1 | I8: =IF(CAELS!J5>20%,"1",IF(CAELS!J5>15%,"2",IF(CAELS!J5>12%,"3",IF(CAELS!J5>10%,"4","5")))) -> 1 | J8: =IF(CAELS!K5>20%,"1",IF(CAELS!K5>15%,"2",IF(CAELS!K5>12%,"3",IF(CAELS!K5>10%,"4","5")))) -> 1 | ... U8: =IF(CAELS!V5>20%,"1",IF(CAELS!V5>15%,"2",IF(CAELS!V5>12%,"3",IF(CAELS!V5>10%,"4","5")))) -> 1
C9: =(C5+C6+C7+C8)/4 -> 3.5 | D9: =(D5+D6+D7+D8)/4 -> 1 | E9: =(E5+E6+E7+E8)/4 -> 1 | F9: =(F5+F6+F7+F8)/4 -> 1 | G9: =(G5+G6+G7+G8)/4 -> 1 | H9: =(H5+H6+H7+H8)/4 -> 1 | I9: =(I5+I6+I7+I8)/4 -> 1 | J9: =(J5+J6+J7+J8)/4 -> 1 | ... U9: =(U5+U6+U7+U8)/4 -> 1
A10: Asset Quality
A11: NPL | B11: ≤ 6% | L11: =IF(CAELS!M8<4%,"1",IF(CAELS!M8<8%,"2",IF(CAELS!M8<12%,"3",IF(CAELS!M8<15%,"4","5")))) -> 1 | O11: =IF(CAELS!P8<4%,"1",IF(CAELS!P8<8%,"2",IF(CAELS!P8<12%,"3",IF(CAELS!P8<15%,"4","5")))) -> 1 | R11: =IF(CAELS!S8<4%,"1",IF(CAELS!S8<8%,"2",IF(CAELS!S8<12%,"3",IF(CAELS!S8<15%,"4","5")))) -> 1 | U11: =IF(CAELS!V8<4%,"1",IF(CAELS!V8<8%,"2",IF(CAELS!V8<12%,"3",IF(CAELS!V8<15%,"4","5")))) -> 3
C12: =C11 -> 0 | D12: =D11 -> 0 | E12: =E11 -> 0 | F12: =F11 -> 0 | G12: =G11 -> 0 | H12: =H11 -> 0 | I12: =I11 -> 0 | J12: =J11 -> 0 | ... U12: =U11 -> 3
A13: Earnings
A14: ROA | D14: =IF(CAELS!E9>6%,"1",IF(CAELS!E9>4%,"2",IF(CAELS!E9>2%,"3",IF(CAELS!E9>0%,"4","5")))) -> 1 | E14: =IF(CAELS!F9>6%,"1",IF(CAELS!F9>4%,"2",IF(CAELS!F9>2%,"3",IF(CAELS!F9>0%,"4","5")))) -> 4 | F14: =IF(CAELS!G9>6%,"1",IF(CAELS!G9>4%,"2",IF(CAELS!G9>2%,"3",IF(CAELS!G9>0%,"4","5")))) -> 4 | G14: =IF(CAELS!H9>6%,"1",IF(CAELS!H9>4%,"2",IF(CAELS!H9>2%,"3",IF(CAELS!H9>0%,"4","5")))) -> 3 | H14: =IF(CAELS!I9>6%,"1",IF(CAELS!I9>4%,"2",IF(CAELS!I9>2%,"3",IF(CAELS!I9>0%,"4","5")))) -> 3 | I14: =IF(CAELS!J9>6%,"1",IF(CAELS!J9>4%,"2",IF(CAELS!J9>2%,"3",IF(CAELS!J9>0%,"4","5")))) -> 2 | J14: =IF(CAELS!K9>6%,"1",IF(CAELS!K9>4%,"2",IF(CAELS!K9>2%,"3",IF(CAELS!K9>0%,"4","5")))) -> 2 | K14: =IF(CAELS!L9>6%,"1",IF(CAELS!L9>4%,"2",IF(CAELS!L9>2%,"3",IF(CAELS!L9>0%,"4","5")))) -> 2 | ... U14: =IF(CAELS!V9>6%,"1",IF(CAELS!V9>4%,"2",IF(CAELS!V9>2%,"3",IF(CAELS!V9>0%,"4","5")))) -> 3
A15: CIR | C15: =IF(CAELS!D10<60%,"1",IF(CAELS!D10<70%,"2",IF(CAELS!D10<80%,"3",IF(CAELS!D10<90%,"4","5")))) -> 3 | D15: =IF(CAELS!E10<60%,"1",IF(CAELS!E10<70%,"2",IF(CAELS!E10<80%,"3",IF(CAELS!E10<90%,"4","5")))) -> 1 | E15: =IF(CAELS!F10<60%,"1",IF(CAELS!F10<70%,"2",IF(CAELS!F10<80%,"3",IF(CAELS!F10<90%,"4","5")))) -> 1 | F15: =IF(CAELS!G10<60%,"1",IF(CAELS!G10<70%,"2",IF(CAELS!G10<80%,"3",IF(CAELS!G10<90%,"4","5")))) -> 1 | G15: =IF(CAELS!H10<60%,"1",IF(CAELS!H10<70%,"2",IF(CAELS!H10<80%,"3",IF(CAELS!H10<90%,"4","5")))) -> 1 | H15: =IF(CAELS!I10<60%,"1",IF(CAELS!I10<70%,"2",IF(CAELS!I10<80%,"3",IF(CAELS!I10<90%,"4","5")))) -> 1 | I15: =IF(CAELS!J10<60%,"1",IF(CAELS!J10<70%,"2",IF(CAELS!J10<80%,"3",IF(CAELS!J10<90%,"4","5")))) -> 1 | J15: =IF(CAELS!K10<60%,"1",IF(CAELS!K10<70%,"2",IF(CAELS!K10<80%,"3",IF(CAELS!K10<90%,"4","5")))) -> 1 | ... U15: =IF(CAELS!V10<60%,"1",IF(CAELS!V10<70%,"2",IF(CAELS!V10<80%,"3",IF(CAELS!V10<90%,"4","5")))) -> 1
A16: OER | C16: =IF(CAELS!D11<4%,"1",IF(CAELS!D11<6%,"2",IF(CAELS!D11<8%,"3",IF(CAELS!D11<10%,"4","5")))) -> 1 | D16: =IF(CAELS!E11<4%,"1",IF(CAELS!E11<6%,"2",IF(CAELS!E11<8%,"3",IF(CAELS!E11<10%,"4","5")))) -> 5 | E16: =IF(CAELS!F11<4%,"1",IF(CAELS!F11<6%,"2",IF(CAELS!F11<8%,"3",IF(CAELS!F11<10%,"4","5")))) -> 1 | F16: =IF(CAELS!G11<4%,"1",IF(CAELS!G11<6%,"2",IF(CAELS!G11<8%,"3",IF(CAELS!G11<10%,"4","5")))) -> 1 | G16: =IF(CAELS!H11<4%,"1",IF(CAELS!H11<6%,"2",IF(CAELS!H11<8%,"3",IF(CAELS!H11<10%,"4","5")))) -> 1 | H16: =IF(CAELS!I11<4%,"1",IF(CAELS!I11<6%,"2",IF(CAELS!I11<8%,"3",IF(CAELS!I11<10%,"4","5")))) -> 1 | I16: =IF(CAELS!J11<4%,"1",IF(CAELS!J11<6%,"2",IF(CAELS!J11<8%,"3",IF(CAELS!J11<10%,"4","5")))) -> 1 | J16: =IF(CAELS!K11<4%,"1",IF(CAELS!K11<6%,"2",IF(CAELS!K11<8%,"3",IF(CAELS!K11<10%,"4","5")))) -> 1 | ... U16: =IF(CAELS!V11<4%,"1",IF(CAELS!V11<6%,"2",IF(CAELS!V11<8%,"3",IF(CAELS!V11<10%,"4","5")))) -> 1
C17: =(C14+C15+C16)/3 -> 1.3333333 | D17: =(D14+D15+D16)/3 -> 2.3333333 | E17: =(E14+E15+E16)/3 -> 2 | F17: =(F14+F15+F16)/3 -> 2 | G17: =(G14+G15+G16)/3 -> 1.6666667 | H17: =(H14+H15+H16)/3 -> 1.6666667 | I17: =(I14+I15+I16)/3 -> 1.3333333 | J17: =(J14+J15+J16)/3 -> 1.3333333 | ... U17: =(U14+U15+U16)/3 -> 1.6666667
A18: LIQUIDITY
A19: MIN LIQ | B19: 0.15 | C19: =IF(CAELS!D12>30%,"1",IF(CAELS!D12>25%,"2",IF(CAELS!D12>20%,"3",IF(CAELS!D12>15%,"4","5")))) -> 1 | D19: =IF(CAELS!E12>30%,"1",IF(CAELS!E12>25%,"2",IF(CAELS!E12>20%,"3",IF(CAELS!E12>15%,"4","5")))) -> 1 | E19: =IF(CAELS!F12>30%,"1",IF(CAELS!F12>25%,"2",IF(CAELS!F12>20%,"3",IF(CAELS!F12>15%,"4","5")))) -> 1 | F19: =IF(CAELS!G12>30%,"1",IF(CAELS!G12>25%,"2",IF(CAELS!G12>20%,"3",IF(CAELS!G12>15%,"4","5")))) -> 1 | G19: =IF(CAELS!H12>30%,"1",IF(CAELS!H12>25%,"2",IF(CAELS!H12>20%,"3",IF(CAELS!H12>15%,"4","5")))) -> 1 | H19: =IF(CAELS!I12>30%,"1",IF(CAELS!I12>25%,"2",IF(CAELS!I12>20%,"3",IF(CAELS!I12>15%,"4","5")))) -> 1 | I19: =IF(CAELS!J12>30%,"1",IF(CAELS!J12>25%,"2",IF(CAELS!J12>20%,"3",IF(CAELS!J12>15%,"4","5")))) -> 1 | J19: =IF(CAELS!K12>30%,"1",IF(CAELS!K12>25%,"2",IF(CAELS!K12>20%,"3",IF(CAELS!K12>15%,"4","5")))) -> 1 | ... U19: =IF(CAELS!V12>30%,"1",IF(CAELS!V12>25%,"2",IF(CAELS!V12>20%,"3",IF(CAELS!V12>15%,"4","5")))) -> 1
A20: TECH LIQ | C20: =IF(CAELS!D13>30%,"1",IF(CAELS!D13>25%,"2",IF(CAELS!D13>20%,"3",IF(CAELS!D13>15%,"4","5")))) -> 5 | D20: =IF(CAELS!E13>30%,"1",IF(CAELS!E13>25%,"2",IF(CAELS!E13>20%,"3",IF(CAELS!E13>15%,"4","5")))) -> 4 | E20: =IF(CAELS!F13>30%,"1",IF(CAELS!F13>25%,"2",IF(CAELS!F13>20%,"3",IF(CAELS!F13>15%,"4","5")))) -> 4 | F20: =IF(CAELS!G13>30%,"1",IF(CAELS!G13>25%,"2",IF(CAELS!G13>20%,"3",IF(CAELS!G13>15%,"4","5")))) -> 3 | G20: =IF(CAELS!H13>30%,"1",IF(CAELS!H13>25%,"2",IF(CAELS!H13>20%,"3",IF(CAELS!H13>15%,"4","5")))) -> 4 | H20: =IF(CAELS!I13>30%,"1",IF(CAELS!I13>25%,"2",IF(CAELS!I13>20%,"3",IF(CAELS!I13>15%,"4","5")))) -> 4 | I20: =IF(CAELS!J13>30%,"1",IF(CAELS!J13>25%,"2",IF(CAELS!J13>20%,"3",IF(CAELS!J13>15%,"4","5")))) -> 4 | J20: =IF(CAELS!K13>30%,"1",IF(CAELS!K13>25%,"2",IF(CAELS!K13>20%,"3",IF(CAELS!K13>15%,"4","5")))) -> 4 | ... U20: =IF(CAELS!V13>30%,"1",IF(CAELS!V13>25%,"2",IF(CAELS!V13>20%,"3",IF(CAELS!V13>15%,"4","5")))) -> 5
A21: EB | B21: ≤ 25% | C21: =IF(CAELS!D14<15%,"1",IF(CAELS!D14<18%,"2",IF(CAELS!D14<22%,"3",IF(CAELS!D14<25%,"4","5")))) -> 1 | D21: =IF(CAELS!E14<15%,"1",IF(CAELS!E14<18%,"2",IF(CAELS!E14<22%,"3",IF(CAELS!E14<25%,"4","5")))) -> 1 | E21: =IF(CAELS!F14<15%,"1",IF(CAELS!F14<18%,"2",IF(CAELS!F14<22%,"3",IF(CAELS!F14<25%,"4","5")))) -> 1 | F21: =IF(CAELS!G14<15%,"1",IF(CAELS!G14<18%,"2",IF(CAELS!G14<22%,"3",IF(CAELS!G14<25%,"4","5")))) -> 1 | G21: =IF(CAELS!H14<15%,"1",IF(CAELS!H14<18%,"2",IF(CAELS!H14<22%,"3",IF(CAELS!H14<25%,"4","5")))) -> 1 | H21: =IF(CAELS!I14<15%,"1",IF(CAELS!I14<18%,"2",IF(CAELS!I14<22%,"3",IF(CAELS!I14<25%,"4","5")))) -> 1 | I21: =IF(CAELS!J14<15%,"1",IF(CAELS!J14<18%,"2",IF(CAELS!J14<22%,"3",IF(CAELS!J14<25%,"4","5")))) -> 1 | J21: =IF(CAELS!K14<15%,"1",IF(CAELS!K14<18%,"2",IF(CAELS!K14<22%,"3",IF(CAELS!K14<25%,"4","5")))) -> 1 | ... U21: =IF(CAELS!V14<15%,"1",IF(CAELS!V14<18%,"2",IF(CAELS!V14<22%,"3",IF(CAELS!V14<25%,"4","5")))) -> 1
A22: LIQ/TA | C22: =IF(CAELS!D15>15%,"1",IF(CAELS!D15>12%,"2",IF(CAELS!D15>9%,"3",IF(CAELS!D15>6%,"4","5")))) -> 2 | D22: =IF(CAELS!E15>15%,"1",IF(CAELS!E15>12%,"2",IF(CAELS!E15>9%,"3",IF(CAELS!E15>6%,"4","5")))) -> 2 | E22: =IF(CAELS!F15>15%,"1",IF(CAELS!F15>12%,"2",IF(CAELS!F15>9%,"3",IF(CAELS!F15>6%,"4","5")))) -> 2 | F22: =IF(CAELS!G15>15%,"1",IF(CAELS!G15>12%,"2",IF(CAELS!G15>9%,"3",IF(CAELS!G15>6%,"4","5")))) -> 2 | G22: =IF(CAELS!H15>15%,"1",IF(CAELS!H15>12%,"2",IF(CAELS!H15>9%,"3",IF(CAELS!H15>6%,"4","5")))) -> 2 | H22: =IF(CAELS!I15>15%,"1",IF(CAELS!I15>12%,"2",IF(CAELS!I15>9%,"3",IF(CAELS!I15>6%,"4","5")))) -> 3 | I22: =IF(CAELS!J15>15%,"1",IF(CAELS!J15>12%,"2",IF(CAELS!J15>9%,"3",IF(CAELS!J15>6%,"4","5")))) -> 3 | J22: =IF(CAELS!K15>15%,"1",IF(CAELS!K15>12%,"2",IF(CAELS!K15>9%,"3",IF(CAELS!K15>6%,"4","5")))) -> 2 | ... U22: =IF(CAELS!V15>15%,"1",IF(CAELS!V15>12%,"2",IF(CAELS!V15>9%,"3",IF(CAELS!V15>6%,"4","5")))) -> 4
C23: =(C19+C20+C21+C22)/4 -> 2.25 | D23: =(D19+D20+D21+D22)/4 -> 2 | E23: =(E19+E20+E21+E22)/4 -> 2 | F23: =(F19+F20+F21+F22)/4 -> 1.75 | G23: =(G19+G20+G21+G22)/4 -> 2 | H23: =(H19+H20+H21+H22)/4 -> 2.25 | I23: =(I19+I20+I21+I22)/4 -> 2.25 | J23: =(J19+J20+J21+J22)/4 -> 2 | ... U23: =(U19+U20+U21+U22)/4 -> 2.75
A24: STRUCTURE
A25: NEA | B25: ≤ 10% | C25: =IF(CAELS!D16<6%,"1",IF(CAELS!D16<7%,"2",IF(CAELS!D16<8%,"3",IF(CAELS!D16<10%,"4","5")))) -> 5 | D25: =IF(CAELS!E16<6%,"1",IF(CAELS!E16<7%,"2",IF(CAELS!E16<8%,"3",IF(CAELS!E16<10%,"4","5")))) -> 4 | E25: =IF(CAELS!F16<6%,"1",IF(CAELS!F16<7%,"2",IF(CAELS!F16<8%,"3",IF(CAELS!F16<10%,"4","5")))) -> 4 | F25: =IF(CAELS!G16<6%,"1",IF(CAELS!G16<7%,"2",IF(CAELS!G16<8%,"3",IF(CAELS!G16<10%,"4","5")))) -> 3 | G25: =IF(CAELS!H16<6%,"1",IF(CAELS!H16<7%,"2",IF(CAELS!H16<8%,"3",IF(CAELS!H16<10%,"4","5")))) -> 4 | H25: =IF(CAELS!I16<6%,"1",IF(CAELS!I16<7%,"2",IF(CAELS!I16<8%,"3",IF(CAELS!I16<10%,"4","5")))) -> 4 | I25: =IF(CAELS!J16<6%,"1",IF(CAELS!J16<7%,"2",IF(CAELS!J16<8%,"3",IF(CAELS!J16<10%,"4","5")))) -> 5 | J25: =IF(CAELS!K16<6%,"1",IF(CAELS!K16<7%,"2",IF(CAELS!K16<8%,"3",IF(CAELS!K16<10%,"4","5")))) -> 4 | ... U25: =IF(CAELS!V16<6%,"1",IF(CAELS!V16<7%,"2",IF(CAELS!V16<8%,"3",IF(CAELS!V16<10%,"4","5")))) -> 4
A26: LB | B26: ≤ 5% | C26: =IF(CAELS!D17<2%,"1",IF(CAELS!D17<3%,"2",IF(CAELS!D17<4%,"3",IF(CAELS!D17<5%,"4","5")))) -> 3 | D26: =IF(CAELS!E17<2%,"1",IF(CAELS!E17<3%,"2",IF(CAELS!E17<4%,"3",IF(CAELS!E17<5%,"4","5")))) -> 5 | E26: =IF(CAELS!F17<2%,"1",IF(CAELS!F17<3%,"2",IF(CAELS!F17<4%,"3",IF(CAELS!F17<5%,"4","5")))) -> 5 | F26: =IF(CAELS!G17<2%,"1",IF(CAELS!G17<3%,"2",IF(CAELS!G17<4%,"3",IF(CAELS!G17<5%,"4","5")))) -> 5 | G26: =IF(CAELS!H17<2%,"1",IF(CAELS!H17<3%,"2",IF(CAELS!H17<4%,"3",IF(CAELS!H17<5%,"4","5")))) -> 5 | H26: =IF(CAELS!I17<2%,"1",IF(CAELS!I17<3%,"2",IF(CAELS!I17<4%,"3",IF(CAELS!I17<5%,"4","5")))) -> 5 | I26: =IF(CAELS!J17<2%,"1",IF(CAELS!J17<3%,"2",IF(CAELS!J17<4%,"3",IF(CAELS!J17<5%,"4","5")))) -> 5 | J26: =IF(CAELS!K17<2%,"1",IF(CAELS!K17<3%,"2",IF(CAELS!K17<4%,"3",IF(CAELS!K17<5%,"4","5")))) -> 5 | ... U26: =IF(CAELS!V17<2%,"1",IF(CAELS!V17<3%,"2",IF(CAELS!V17<4%,"3",IF(CAELS!V17<5%,"4","5")))) -> 5
A27: FITD | B27: ≤ 5% | C27: =IF(CAELS!D18<2%,"1",IF(CAELS!D18<3%,"2",IF(CAELS!D18<4%,"3",IF(CAELS!D18<5%,"4","5")))) -> 1 | D27: =IF(CAELS!E18<2%,"1",IF(CAELS!E18<3%,"2",IF(CAELS!E18<4%,"3",IF(CAELS!E18<5%,"4","5")))) -> 1 | E27: =IF(CAELS!F18<2%,"1",IF(CAELS!F18<3%,"2",IF(CAELS!F18<4%,"3",IF(CAELS!F18<5%,"4","5")))) -> 2 | F27: =IF(CAELS!G18<2%,"1",IF(CAELS!G18<3%,"2",IF(CAELS!G18<4%,"3",IF(CAELS!G18<5%,"4","5")))) -> 2 | G27: =IF(CAELS!H18<2%,"1",IF(CAELS!H18<3%,"2",IF(CAELS!H18<4%,"3",IF(CAELS!H18<5%,"4","5")))) -> 2 | H27: =IF(CAELS!I18<2%,"1",IF(CAELS!I18<3%,"2",IF(CAELS!I18<4%,"3",IF(CAELS!I18<5%,"4","5")))) -> 2 | I27: =IF(CAELS!J18<2%,"1",IF(CAELS!J18<3%,"2",IF(CAELS!J18<4%,"3",IF(CAELS!J18<5%,"4","5")))) -> 2 | J27: =IF(CAELS!K18<2%,"1",IF(CAELS!K18<3%,"2",IF(CAELS!K18<4%,"3",IF(CAELS!K18<5%,"4","5")))) -> 2 | ... U27: =IF(CAELS!V18<2%,"1",IF(CAELS!V18<3%,"2",IF(CAELS!V18<4%,"3",IF(CAELS!V18<5%,"4","5")))) -> 2
A28: FICC | B28: ≤ 40% | C28: =IF(CAELS!D19<20%,"1",IF(CAELS!D19<25%,"2",IF(CAELS!D19<30%,"3",IF(CAELS!D19<40%,"4","5")))) -> 1 | D28: =IF(CAELS!E19<20%,"1",IF(CAELS!E19<25%,"2",IF(CAELS!E19<30%,"3",IF(CAELS!E19<40%,"4","5")))) -> 1 | E28: =IF(CAELS!F19<20%,"1",IF(CAELS!F19<25%,"2",IF(CAELS!F19<30%,"3",IF(CAELS!F19<40%,"4","5")))) -> 1 | F28: =IF(CAELS!G19<20%,"1",IF(CAELS!G19<25%,"2",IF(CAELS!G19<30%,"3",IF(CAELS!G19<40%,"4","5")))) -> 1 | G28: =IF(CAELS!H19<20%,"1",IF(CAELS!H19<25%,"2",IF(CAELS!H19<30%,"3",IF(CAELS!H19<40%,"4","5")))) -> 1 | H28: =IF(CAELS!I19<20%,"1",IF(CAELS!I19<25%,"2",IF(CAELS!I19<30%,"3",IF(CAELS!I19<40%,"4","5")))) -> 1 | I28: =IF(CAELS!J19<20%,"1",IF(CAELS!J19<25%,"2",IF(CAELS!J19<30%,"3",IF(CAELS!J19<40%,"4","5")))) -> 1 | J28: =IF(CAELS!K19<20%,"1",IF(CAELS!K19<25%,"2",IF(CAELS!K19<30%,"3",IF(CAELS!K19<40%,"4","5")))) -> 1 | ... U28: =IF(CAELS!V19<20%,"1",IF(CAELS!V19<25%,"2",IF(CAELS!V19<30%,"3",IF(CAELS!V19<40%,"4","5")))) -> 1
C29: =(C25+C26+C27+C28)/4 -> 2.5 | D29: =(D25+D26+D27+D28)/4 -> 2.75 | E29: =(E25+E26+E27+E28)/4 -> 3 | F29: =(F25+F26+F27+F28)/4 -> 2.75 | G29: =(G25+G26+G27+G28)/4 -> 3 | H29: =(H25+H26+H27+H28)/4 -> 3 | I29: =(I25+I26+I27+I28)/4 -> 3.25 | J29: =(J25+J26+J27+J28)/4 -> 3 | ... U29: =(U25+U26+U27+U28)/4 -> 3
A30: FINAL RATING | C30: =(C9+C12+C17+C23)/4 -> 1.7708333 | D30: =(D9+D12+D17+D23)/4 -> 1.3333333 | E30: =(E9+E12+E17+E23)/4 -> 1.25 | F30: =(F9+F12+F17+F23)/4 -> 1.1875 | G30: =(G9+G12+G17+G23)/4 -> 1.1666667 | H30: =(H9+H12+H17+H23)/4 -> 1.2291667 | I30: =(I9+I12+I17+I23)/4 -> 1.1458333 | J30: =(J9+J12+J17+J23)/4 -> 1.0833333 | ... U30: =(U9+U12+U17+U23)/4 -> 2.1041667

Sheet Compliance Status
B2: 2010 Audited | C2: 2020 audited | D2: 44197 | E2: 44229 | F2: 44258 | G2: 44290 | H2: 44321 | I2: 44353 | J2: 44384 | K2: 44416 | L2: 44448 | M2: 44479 | N2: 44511 | O2: 44542 | P2: AUDITED 2021 | Q2: 44563 | R2: 44595 | S2: 44624 | T2: 44656
A3: CORE CAPITAL | B3: =IF(CAELS!D3>10,"Compliant","Non-Compliant") -> Compliant | C3: =IF(CAELS!E3>10,"Compliant","Non-Compliant") -> Compliant | D3: =IF(CAELS!F3>10,"Compliant","Non-Compliant") -> Compliant | E3: =IF(CAELS!G3>10,"Compliant","Non-Compliant") -> Compliant | F3: =IF(CAELS!H3>10,"Compliant","Non-Compliant") -> Compliant | G3: =IF(CAELS!I3>10,"Compliant","Non-Compliant") -> Compliant | H3: =IF(CAELS!J3>10,"Compliant","Non-Compliant") -> Compliant | I3: =IF(CAELS!K3>10,"Compliant","Non-Compliant") -> Compliant | ... T3: =IF(CAELS!V3>10,"Compliant","Non-Compliant") -> Compliant
A4: CCA (Min 10%) | B4: =IF(CAELS!D4>10%,"Compliant","Non-Compliant") -> Compliant | C4: =IF(CAELS!E4>10%,"Compliant","Non-Compliant") -> Compliant | D4: =IF(CAELS!F4>10%,"Compliant","Non-Compliant") -> Compliant | E4: =IF(CAELS!G4>10%,"Compliant","Non-Compliant") -> Compliant | F4: =IF(CAELS!H4>10%,"Compliant","Non-Compliant") -> Compliant | G4: =IF(CAELS!I4>10%,"Compliant","Non-Compliant") -> Compliant | H4: =IF(CAELS!J4>10%,"Compliant","Non-Compliant") -> Compliant | I4: =IF(CAELS!K4>10%,"Compliant","Non-Compliant") -> Compliant | ... T4: =IF(CAELS!V4>10%,"Compliant","Non-Compliant") -> Compliant
A5: ICA (Min 8%) | B5: =IF(CAELS!D6>8%,"Compliant","Non-Compliant") -> Non-Compliant | C5: =IF(CAELS!E6>8%,"Compliant","Non-Compliant") -> Compliant | D5: =IF(CAELS!F6>8%,"Compliant","Non-Compliant") -> Compliant | E5: =IF(CAELS!G6>8%,"Compliant","Non-Compliant") -> Compliant | F5: =IF(CAELS!H6>8%,"Compliant","Non-Compliant") -> Compliant | G5: =IF(CAELS!I6>8%,"Compliant","Non-Compliant") -> Compliant | H5: =IF(CAELS!J6>8%,"Compliant","Non-Compliant") -> Compliant | I5: =IF(CAELS!K6>8%,"Compliant","Non-Compliant") -> Compliant | ... T5: =IF(CAELS!V6>8%,"Compliant","Non-Compliant") -> Compliant
A6: CCD (Min 8%) | B6: =IF(CAELS!D5>8%,"Compliant","Non-Compiant") -> Compliant | C6: =IF(CAELS!E5>8%,"Compliant","Non-Compiant") -> Compliant | D6: =IF(CAELS!F5>8%,"Compliant","Non-Compiant") -> Compliant | E6: =IF(CAELS!G5>8%,"Compliant","Non-Compiant") -> Compliant | F6: =IF(CAELS!H5>8%,"Compliant","Non-Compiant") -> Compliant | G6: =IF(CAELS!I5>8%,"Compliant","Non-Compiant") -> Compliant | H6: =IF(CAELS!J5>8%,"Compliant","Non-Compiant") -> Compliant | I6: =IF(CAELS!K5>8%,"Compliant","Non-Compiant") -> Compliant | ... T6: =IF(CAELS!V5>8%,"Compliant","Non-Compiant") -> Compliant
A7: NPL(5%)
A8: Liquidity(15%) | B8: =IF(CAELS!D12>15%,"Compliant","Non-Compliant") -> Compliant | C8: =IF(CAELS!E12>15%,"Compliant","Non-Compliant") -> Compliant | D8: =IF(CAELS!F12>15%,"Compliant","Non-Compliant") -> Compliant | E8: =IF(CAELS!G12>15%,"Compliant","Non-Compliant") -> Compliant | F8: =IF(CAELS!H12>15%,"Compliant","Non-Compliant") -> Compliant | G8: =IF(CAELS!I12>15%,"Compliant","Non-Compliant") -> Compliant | H8: =IF(CAELS!J12>15%,"Compliant","Non-Compliant") -> Compliant | I8: =IF(CAELS!K12>15%,"Compliant","Non-Compliant") -> Compliant | ... T8: =IF(CAELS!V12>15%,"Compliant","Non-Compliant") -> Compliant
A9: NEA (Max 10%) | B9: =IF(CAELS!D16<10%,"Compliant","Non-Compliant") -> Non-Compliant | C9: =IF(CAELS!E16<10%,"Compliant","Non-Compliant") -> Compliant | D9: =IF(CAELS!F16<10%,"Compliant","Non-Compliant") -> Compliant | E9: =IF(CAELS!G16<10%,"Compliant","Non-Compliant") -> Compliant | F9: =IF(CAELS!H16<10%,"Compliant","Non-Compliant") -> Compliant | G9: =IF(CAELS!I16<10%,"Compliant","Non-Compliant") -> Compliant | H9: =IF(CAELS!J16<10%,"Compliant","Non-Compliant") -> Non-Compliant | I9: =IF(CAELS!K16<10%,"Compliant","Non-Compliant") -> Compliant | ... T9: =IF(CAELS!V16<10%,"Compliant","Non-Compliant") -> Compliant
A10: LB ratio (Max 5%) | B10: =IF(CAELS!D17<5%,"Compliant","Non-Compliant") -> Compliant | C10: =IF(CAELS!E17<5%,"Compliant","Non-Compliant") -> Non-Compliant | D10: =IF(CAELS!F17<5%,"Compliant","Non-Compliant") -> Non-Compliant | E10: =IF(CAELS!G17<5%,"Compliant","Non-Compliant") -> Non-Compliant | F10: =IF(CAELS!H17<5%,"Compliant","Non-Compliant") -> Non-Compliant | G10: =IF(CAELS!I17<5%,"Compliant","Non-Compliant") -> Non-Compliant | H10: =IF(CAELS!J17<5%,"Compliant","Non-Compliant") -> Non-Compliant | I10: =IF(CAELS!K17<5%,"Compliant","Non-Compliant") -> Non-Compliant | ... T10: =IF(CAELS!V17<5%,"Compliant","Non-Compliant") -> Non-Compliant
A11: FITD (Max 5%) | B11: =IF(CAELS!D18<5%,"Compliant","Non-Compliant") -> Compliant | C11: =IF(CAELS!E18<5%,"Compliant","Non-Compliant") -> Compliant | D11: =IF(CAELS!F18<5%,"Compliant","Non-Compliant") -> Compliant | E11: =IF(CAELS!G18<5%,"Compliant","Non-Compliant") -> Compliant | F11: =IF(CAELS!H18<5%,"Compliant","Non-Compliant") -> Compliant | G11: =IF(CAELS!I18<5%,"Compliant","Non-Compliant") -> Compliant | H11: =IF(CAELS!J18<5%,"Compliant","Non-Compliant") -> Compliant | I11: =IF(CAELS!K18<5%,"Compliant","Non-Compliant") -> Compliant | ... T11: =IF(CAELS!V18<5%,"Compliant","Non-Compliant") -> Compliant
A12: FICC (Max 40%) | B12: =IF(CAELS!D19<40%,"Compliant","Non-Compliant") -> Compliant | C12: =IF(CAELS!E19<40%,"Compliant","Non-Compliant") -> Compliant | D12: =IF(CAELS!F19<40%,"Compliant","Non-Compliant") -> Compliant | E12: =IF(CAELS!G19<40%,"Compliant","Non-Compliant") -> Compliant | F12: =IF(CAELS!H19<40%,"Compliant","Non-Compliant") -> Compliant | G12: =IF(CAELS!I19<40%,"Compliant","Non-Compliant") -> Compliant | H12: =IF(CAELS!J19<40%,"Compliant","Non-Compliant") -> Compliant | I12: =IF(CAELS!K19<40%,"Compliant","Non-Compliant") -> Compliant | ... T12: =IF(CAELS!V19<40%,"Compliant","Non-Compliant") -> Compliant
A13: EB ratio (Max 25%) | B13: =IF(CAELS!D14<25%,"Compliant","Non-Compliant") -> Compliant | C13: =IF(CAELS!E14<25%,"Compliant","Non-Compliant") -> Compliant | D13: =IF(CAELS!F14<25%,"Compliant","Non-Compliant") -> Compliant | E13: =IF(CAELS!G14<25%,"Compliant","Non-Compliant") -> Compliant | F13: =IF(CAELS!H14<25%,"Compliant","Non-Compliant") -> Compliant | G13: =IF(CAELS!I14<25%,"Compliant","Non-Compliant") -> Compliant | H13: =IF(CAELS!J14<25%,"Compliant","Non-Compliant") -> Compliant | I13: =IF(CAELS!K14<25%,"Compliant","Non-Compliant") -> Compliant | ... T13: =IF(CAELS!V14<25%,"Compliant","Non-Compliant") -> Compliant
A14: A=S+L | B14: =IF('Evolutive SFP'!B27='Evolutive SFP'!B49,"BALANCING","NOT BALANCING") -> BALANCING | C14: =IF('Evolutive SFP'!C27='Evolutive SFP'!C49,"BALANCING","NOT BALANCING") -> BALANCING | D14: =IF('Evolutive SFP'!D27='Evolutive SFP'!D49,"BALANCING","NOT BALANCING") -> BALANCING | E14: =IF('Evolutive SFP'!E27='Evolutive SFP'!E49,"BALANCING","NOT BALANCING") -> BALANCING | F14: =IF('Evolutive SFP'!F27='Evolutive SFP'!F49,"BALANCING","NOT BALANCING") -> BALANCING | G14: =IF('Evolutive SFP'!G27='Evolutive SFP'!G49,"BALANCING","NOT BALANCING") -> BALANCING | H14: =IF('Evolutive SFP'!H27='Evolutive SFP'!H49,"BALANCING","NOT BALANCING") -> BALANCING | I14: =IF('Evolutive SFP'!#REF!='Evolutive SFP'!#REF!,"BALANCING","NOT BALANCING") -> #REF! | J14: =IF('Evolutive SFP'!#REF!='Evolutive SFP'!#REF!,"BALANCING","NOT BALANCING") -> #REF! | K14: =IF('Evolutive SFP'!#REF!='Evolutive SFP'!#REF!,"BALANCING","NOT BALANCING") -> #REF! | L14: =IF('Evolutive SFP'!#REF!='Evolutive SFP'!#REF!,"BALANCING","NOT BALANCING") -> #REF! | M14: =IF('Evolutive SFP'!#REF!='Evolutive SFP'!#REF!,"BALANCING","NOT BALANCING") -> #REF! | N14: =IF('Evolutive SFP'!#REF!='Evolutive SFP'!#REF!,"BALANCING","NOT BALANCING") -> #REF! | O14: =IF('Evolutive SFP'!#REF!='Evolutive SFP'!#REF!,"BALANCING","NOT BALANCING") -> #REF! | P14: =IF('Evolutive SFP'!#REF!='Evolutive SFP'!#REF!,"BALANCING","NOT BALANCING") -> #REF! | ... T14: =IF('Evolutive SFP'!#REF!='Evolutive SFP'!#REF!,"BALANCING","NOT BALANCING") -> #REF!

Sheet CashFlow Stmnt
A1: STATEMENT OF CASHFLOWS FOR THE YEAR ENDED 31ST DECEMBER 2020
B2: 2020 | C2: 2021 | D2: Audited -2021 | E2: Variance
A3: Cash flows from operating activities
A4: Interest receipts
A5: Interest Payments | J5: .
A6: Payment to employees and suppliers | J6: .
A7: Other operating income
A8: (Increase)/Decrease in Operating assets | B8: =B4+B5+B6+B7 -> 0 | C8: =SUM(C4:C7) -> 0 | D8: =SUM(D4:D7) -> 0
A9: Net loans to members
A10: Recievables and prepayments
A11: Trade and Other Receivables
A12: Inventories
A13: Short term investments
A14: Increase/(Decrease) in Operating liabilities | B14: =SUM(B9:B13) -> 0 | C14: =SUM(C9:C13) -> 0 | D14: =SUM(D9:D13) -> 0
A15: Deposits from members
A16: Trade and Accrued Expenses
A17: Sundry creditors
A18: Net cashflow from operating activities before income taxes | B18: =B8+B14+B15+B16+B17 -> 0 | C18: =C8+C14+C15+C16+C17 -> 0 | D18: =D8+D14+D15+D16+D17 -> 0
A19: Income tax paid
A20: Net Cash from Operating activities
A22: Cashflow from investing activities
A23: Purchase of Property and equipment
A24: Purchase of intangible assets
A25: Increase in Other Assets
A26: Purchase of Investment Securities
A27: Dividends Received
A28: Net Cash from investing activities | B28: =SUM(B23:B27) -> 0 | C28: =SUM(C23:C27) -> 0 | D28: =SUM(D23:D27) -> 0
A30: Cashflow from financing activities
A31: Share capital contributions
A32: Proceeds from long-term borrowings
A33: Prior Year Adjustments
A34: Housing Contributions Plaza
A35: Repayments of long term borrowings
A36: Dividend paid
A37: Net cash from financing activities | B37: =SUM(B31:B36) -> 0 | C37: =SUM(C31:C36) -> 0 | D37: =SUM(D31:D36) -> 0
A38: Net (Decrease)/Increase in cash and cash equivalent | B38: =B20+B28+B37 -> 0 | C38: =C20+C28+C37 -> 0 | D38: =D20+D28+D37 -> 0
A39: Cash and cash equivalent at the beginning of the year
A40: Cash and cash equivalent at the end of the year | B40: =SUM(B38:B39) -> 0 | C40: =SUM(C38:C39) -> 0 | D40: =SUM(D38:D39) -> 0
