Workbook

Sheet SFP
B1: FORM 6 SASRA2/006
B2: STATEMENT OF FINANCIAL POSITION
B3: FINANCIAL YEAR 2020 | D3: 44216 | E3: 44247 | F3: 44275 | G3: 44306 | H3: 44336 | I3: 44367 | J3: 44428 | K3: 44459 | L3: 44489 | M3: 44520 | N3: 44550 | O3: Aud-20 | P3: 44197 | Q3: 44228 | R3: 44256 | S3: 44287 | T3: 44317 | U3: 44348 | V3: 44378 | W3: 44409 | X3: 44440 | Y3: 44470 | Z3: 44501 | AA3: 44531 | AB3: Audited 2021 | AC3: 44562 | AD3: 44593 | AE3: 44621 | AF3: 44652 | AG3: 44682 | AH3: 44713 | AI3: 44743 | AJ3: 44774 | AK3: 44805 | AL3: 44835 | AM3: 44866 | AN3: 44896 | AO3: Audit 2022 | AP3: 44927 | AQ3: 44958 | AR3: 44986 | AS3: 45017 | AT3: 45047 | AU3: 45078 | AV3: 45108 | AW3: 45139 | AX3: 45170 | AY3: 45200
A4: 1 | B4: Cash & Cash Equivalent | C4: =C5+C6 -> 0 | D4: =D5+D6 -> 1.2852567e+08 | E4: =E5+E6 -> 1.2583726e+08 | F4: =F5+F6 -> 127325237 | G4: =G5+G6 -> 147244793 | H4: =H5+H6 -> 139850149 | I4: =I5+I6 -> 1.5408036e+08 | J4: =J5+J6 -> 1.3930786e+08 | ... AY4: =AY5+AY6 -> 0
A5: 1.1 | B5: Cash in hand(both local and foreign notes and coins) | D5: 10705884 | E5: 10960609 | F5: 11410116 | G5: 11588982 | H5: 14203313 | I5: 17760827 | J5: 12584955 | K5: 14756527 | L5: 11026789 | M5: 11759528 | N5: 16508383 | O5: 16533373 | P5: 8933134 | Q5: 10034450 | R5: 14712626 | S5: 27006260 | T5: 20722983 | U5: 25362699 | V5: 16339040 | W5: 21435254 | X5: 29644947 | Y5: 12217784 | Z5: 25829398 | AA5: 21775012 | AB5: 16071959 | AC5: 20194785 | AD5: 14194175 | AE5: 19358855 | AF5: 15455972 | AG5: 9228481.2 | AH5: 24850142 | AI5: 20439460 | AJ5: 20895079 | AK5: 10455876 | AL5: 17001665 | AM5: 23264769 | AN5: 16657635 | AO5: 16657635 | AP5: 15556685 | AQ5: 14976694 | AR5: 20373488 | AS5: 12844142 | AT5: 24824284 | AU5: 19475788 | AV5: 24804893 | AW5: 17851834 | AX5: 16008888
A6: 1.2 | B6: Cash at bank:(placement with financial institutions) | D6: 1.1781979e+08 | E6: 1.1487665e+08 | F6: 115915121 | G6: 135655811 | H6: 125646836 | I6: 1.3631953e+08 | J6: 1.2672291e+08 | K6: 1.2588431e+08 | L6: 1.3466032e+08 | M6: 1.4519808e+08 | N6: 1.450303e+08 | O6: 1.3074568e+08 | P6: 1.3340356e+08 | Q6: 140528019 | R6: 130337747 | S6: 1.2722956e+08 | T6: 1.3047908e+08 | U6: 1.1984656e+08 | V6: 1.2047866e+08 | W6: 1.1162341e+08 | X6: 1.2695177e+08 | Y6: 1.3143904e+08 | Z6: 1.2760473e+08 | AA6: 1.4884615e+08 | AB6: 1.5272822e+08 | AC6: 1.5575512e+08 | AD6: 1.5597011e+08 | AE6: 1.4253786e+08 | AF6: 1.4495116e+08 | AG6: 1.4598739e+08 | AH6: 1.3269304e+08 | AI6: 1.2719875e+08 | AJ6: 1.3157274e+08 | AK6: 136985110 | AL6: 1.2578774e+08 | AM6: 1.1266017e+08 | AN6: 136774938 | AO6: =47472220+91272185 -> 138744405 | AP6: 1.4564034e+08 | AQ6: 1.4359637e+08 | AR6: 1.4467043e+08 | AS6: 1.534764e+08 | AT6: 1.3346768e+08 | AU6: 1.470939e+08 | AV6: 1.4119886e+08 | AW6: 1.4544258e+08 | AX6: 1.5472896e+08
A7: 2 | B7: Prepayments & Sundry Receivables | D7: 13581763 | E7: 16067702 | F7: 16067702 | G7: 13761849 | H7: 16198284 | I7: 16643350 | J7: 18209237 | K7: 14416004 | L7: 19477813 | M7: 14185515 | N7: 12551389 | O7: 13492229 | P7: 14288363 | Q7: 16393295 | R7: 14979518 | S7: 13075365 | T7: 15666318 | U7: 18420579 | V7: 19898244 | W7: 19898244 | X7: 19898244 | Y7: 19898244 | Z7: 19729590 | AA7: 20089411 | AB7: 20089411 | AC7: 20915947 | AD7: 21893555 | AE7: 23188638 | AF7: 23945990 | AG7: 26565603 | AH7: 28482328 | AI7: 34143112 | AJ7: 32822766 | AK7: 31746536 | AL7: 36860957 | AM7: 32814008 | AN7: 23235686 | AO7: 24165606 | AP7: 23500764 | AQ7: 21077984 | AR7: 22345394 | AS7: 23976993 | AT7: 24865065 | AU7: 26498903 | AV7: 27033554 | AW7: 27601775 | AX7: 27601775
A8: 3 | B8: Financial Investments | C8: =SUM(C9:C12) -> 0 | D8: =SUM(D9:D12) -> 110000 | E8: =SUM(E9:E12) -> 110000 | F8: =SUM(F9:F12) -> 110000 | G8: =SUM(G9:G12) -> 110000 | H8: =SUM(H9:H12) -> 110000 | I8: =SUM(I9:I12) -> 110000 | J8: =SUM(J9:J12) -> 110000 | ... AY8: =SUM(AY9:AY12) -> 0
A9: 3.1 | B9: Government Securities - Treasury Bills/bonds, | D9: 0 | E9: 0 | F9: 0 | G9: 0 | H9: 0 | I9: 0 | J9: 0 | K9: 0 | L9: 0 | M9: 0 | N9: 0 | P9: 0 | Q9: 0 | R9: 0 | S9: 0 | T9: 0 | U9: 0 | V9: 0 | W9: 0 | X9: 0 | Y9: 0 | Z9: 0 | AA9: 0 | AC9: 0 | AD9: 0 | AE9: 0 | AF9: 0 | AG9: 0 | AH9: 0 | AI9: 0 | AJ9: 0 | AK9: 0 | AL9: 0 | AM9: 0 | AN9: 0 | AP9: 0 | AQ9: 0 | AR9: 0 | AS9: 0 | AT9: 0 | AU9: 0 | AV9: 0 | AW9: 0 | AX9: 0
A10: 3.2 | B10: Other Securities - Commercial papers/Bonds | D10: 0 | E10: 0 | F10: 0 | G10: 0 | H10: 0 | I10: 0 | J10: 0 | K10: 0 | L10: 0 | M10: 0 | N10: 0 | P10: 0 | Q10: 0 | R10: 0 | S10: 0 | T10: 0 | U10: 0 | V10: 0 | W10: 0 | X10: 0 | Y10: 0 | Z10: 0 | AA10: 0 | AC10: 0 | AD10: 0 | AE10: 0 | AF10: 0 | AG10: 0 | AH10: 0 | AI10: 0 | AJ10: 0 | AK10: 0 | AL10: 0 | AM10: 0 | AN10: 0 | AP10: 0 | AQ10: 0 | AR10: 0 | AS10: 0 | AT10: 0 | AU10: 0 | AV10: 0 | AW10: 0 | AX10: 0
A11: 3.3a | B11: Balances with other SACCO Societies | D11: 0 | E11: 0 | F11: 0 | G11: 0 | H11: 0 | I11: 0 | J11: 0 | K11: 0 | L11: 0 | M11: 0 | N11: 0 | P11: 0 | Q11: 0 | R11: 0 | S11: 0 | T11: 0 | U11: 0 | V11: 0 | W11: 0 | X11: 0 | Y11: 0 | Z11: 0 | AA11: 0 | AB11: 110000 | AC11: 110000 | AD11: 110000 | AE11: 110000 | AF11: 110000 | AG11: 110000 | AH11: 110000 | AI11: 0 | AJ11: 0 | AK11: 0 | AL11: 0 | AM11: 0 | AN11: 0 | AO11: 115067 | AP11: 0 | AQ11: 0 | AR11: 0 | AS11: 0 | AT11: 0 | AU11: 0 | AV11: 115067 | AW11: 115067 | AX11: 115067
A12: 3.3b | B12: Investments in companies - shares/stocks | D12: 110000 | E12: 110000 | F12: 110000 | G12: 110000 | H12: 110000 | I12: 110000 | J12: 110000 | K12: 110000 | L12: 110000 | M12: 110000 | N12: 110000 | O12: 110000 | P12: 110000 | Q12: 110000 | R12: 110000 | S12: 110000 | T12: 110000 | U12: 110000 | V12: 110000 | W12: 110000 | X12: 110000 | Y12: 110000 | Z12: 110000 | AA12: 110000 | AI12: 110000 | AJ12: 110000 | AK12: 115067 | AL12: 115067 | AM12: 115067 | AN12: 115067 | AP12: 115067 | AQ12: 115067 | AR12: 115067 | AS12: 115067 | AT12: 115067 | AU12: 115067 | AV12: 0 | AW12: 0 | AX12: 0
A13: 4 | B13: Net Loan Portfolio | C13: =C14-C15 -> 0 | D13: =D14-D15 -> 3.5973342e+08 | E13: =E14-E15 -> 3.6839312e+08 | F13: =F14-F15 -> 367009867 | G13: =G14-G15 -> 3.6420159e+08 | H13: =H14-H15 -> 373764060 | I13: =I14-I15 -> 3.5742929e+08 | J13: =J14-J15 -> 3.788466e+08 | ... AY13: =AY14-AY15 -> 0
A14: 4.1 | B14: Gross Loan Portfolio | D14: 3.7674874e+08 | E14: 3.8477979e+08 | F14: 382679093 | G14: 3.8192096e+08 | H14: 394912319 | I14: 3.8261976e+08 | J14: 4.1182284e+08 | K14: 4.2207977e+08 | L14: 4.3239047e+08 | M14: 4.328935e+08 | N14: 4.4311275e+08 | O14: 443356055 | P14: 444621203 | Q14: 4.5417514e+08 | R14: 4.5592278e+08 | S14: 4.560568e+08 | T14: 4.6420778e+08 | U14: 4.6788401e+08 | V14: 4.8287643e+08 | W14: 4.8895263e+08 | X14: 4.8983471e+08 | Y14: 4.9834738e+08 | Z14: 4.985291e+08 | AA14: 4.9528969e+08 | AB14: 4.9528969e+08 | AC14: 4.9740143e+08 | AD14: 4.9724304e+08 | AE14: 5.0183005e+08 | AF14: 5.1434293e+08 | AG14: 5.236461e+08 | AH14: 5.1846625e+08 | AI14: 5.1953845e+08 | AJ14: 5.1103564e+08 | AK14: 5.1236709e+08 | AL14: 5.0972176e+08 | AM14: 5.5378174e+08 | AN14: 5.6082073e+08 | AO14: 560820732 | AP14: 5.6467631e+08 | AQ14: 5.612524e+08 | AR14: 5.6343078e+08 | AS14: 5.6582354e+08 | AT14: 5.7072256e+08 | AU14: 5.724261e+08 | AV14: 5.7234981e+08 | AW14: 5.826879e+08 | AX14: 5.8040932e+08
A15: 4.2 | B15: Allowance for Loan Loss | D15: 17015317 | E15: 16386671 | F15: 15669226 | G15: 17719366 | H15: 21148259 | I15: 25190476 | J15: 32976247 | K15: 31773881 | L15: 29905717 | M15: 27485634 | N15: 18736928 | O15: 18736927 | P15: 20522070 | Q15: 21668569 | R15: 21088389 | S15: 20670875 | T15: 21877180 | U15: 22731513 | V15: 23535356 | W15: 25347328 | X15: 25091874 | Y15: 23143639 | Z15: 22070277 | AA15: 18744202 | AB15: 18744202 | AC15: 22081684 | AD15: 22648160 | AE15: 24372040 | AF15: 29499083 | AG15: 31964709 | AH15: 34646051 | AI15: 36980822 | AJ15: 41366096 | AK15: 42425880 | AL15: 36593374 | AM15: 31488425 | AN15: 21582912 | AO15: 21582912 | AP15: 24224392 | AQ15: 24972845 | AR15: 28456137 | AS15: 32474937 | AT15: 35289401 | AU15: 37080363 | AV15: 37447945 | AW15: 40498318 | AX15: 37771521
A16: 5 | B16: Accounts Receivables | C16: =SUM(C17:C19) -> 0 | D16: =SUM(D17:D19) -> 0 | E16: =SUM(E17:E19) -> 0 | F16: =SUM(F17:F19) -> 0 | G16: =SUM(G17:G19) -> 0 | H16: =SUM(H17:H19) -> 0 | I16: =SUM(I17:I19) -> 0 | J16: =SUM(J17:J19) -> 0 | ... AY16: =SUM(AY17:AY19) -> 0
A17: 5.1 | B17: Tax Recoverable | C17: 0 | D17: 0 | E17: 0 | F17: 0 | G17: 0 | H17: 0 | I17: 0 | J17: 0 | K17: 0 | L17: 0 | M17: 0 | N17: 0 | O17: 0 | P17: 0 | Q17: 0 | R17: 0 | S17: 0 | T17: 0 | U17: 0 | V17: 0 | W17: 0 | X17: 0 | Y17: 0 | Z17: 0 | AA17: 0 | AC17: 0 | AD17: 0 | AE17: 0 | AF17: 0 | AG17: 0 | AH17: 0 | AI17: 0 | AJ17: 0 | AK17: 0 | AL17: 0 | AM17: 0 | AN17: 0 | AP17: 0 | AQ17: 0 | AR17: 0 | AS17: 0 | AT17: 0 | AU17: 0 | AV17: 0 | AW17: 0 | AX17: 0
A18: 5.2 | B18: Deferred Tax Assets | C18: 0 | D18: 0 | E18: 0 | F18: 0 | G18: 0 | H18: 0 | I18: 0 | J18: 0 | K18: 0 | L18: 0 | M18: 0 | N18: 0 | O18: 0 | P18: 0 | Q18: 0 | R18: 0 | S18: 0 | T18: 0 | U18: 0 | V18: 0 | W18: 0 | X18: 0 | Y18: 0 | Z18: 0 | AA18: 0 | AC18: 0 | AD18: 0 | AE18: 0 | AF18: 0 | AG18: 0 | AH18: 0 | AI18: 0 | AJ18: 0 | AK18: 0 | AL18: 0 | AM18: 0 | AN18: 0 | AP18: 0 | AQ18: 0 | AR18: 0 | AS18: 0 | AT18: 0 | AU18: 0 | AV18: 0 | AW18: 0 | AX18: 0
A19: 5.3 | B19: Retirement Benefit Assets | C19: 0 | D19: 0 | E19: 0 | F19: 0 | G19: 0 | H19: 0 | I19: 0 | J19: 0 | K19: 0 | L19: 0 | M19: 0 | N19: 0 | O19: 0 | P19: 0 | Q19: 0 | R19: 0 | S19: 0 | T19: 0 | U19: 0 | V19: 0 | W19: 0 | X19: 0 | Y19: 0 | Z19: 0 | AA19: 0 | AC19: 0 | AD19: 0 | AE19: 0 | AF19: 0 | AG19: 0 | AH19: 0 | AI19: 0 | AJ19: 0 | AK19: 0 | AL19: 0 | AM19: 0 | AN19: 0 | AP19: 0 | AQ19: 0 | AR19: 0 | AS19: 0 | AT19: 0 | AU19: 0 | AV19: 0 | AW19: 0 | AX19: 0
A20: 6 | B20: Property & Equipment & Other assets | C20: =SUM(C21:C25) -> 0 | D20: =SUM(D21:D25) -> 26908963 | E20: =SUM(E21:E25) -> 26908963 | F20: =SUM(F21:F25) -> 27794213 | G20: =SUM(G21:G25) -> 27794213 | H20: =SUM(H21:H25) -> 27899223 | I20: =SUM(I21:I25) -> 26884218 | J20: =SUM(J21:J25) -> 32145040 | ... AY20: =SUM(AY21:AY25) -> 0
A21: 6.1 | B21: Investment Properties | D21: 0 | E21: 0 | F21: 0 | G21: 0 | H21: 0 | I21: 0 | J21: 0 | K21: 0 | L21: 0 | M21: 0 | N21: 0 | P21: 0 | Q21: 0 | R21: 0 | S21: 0 | T21: 0 | U21: 0 | V21: 0 | W21: 0 | X21: 0 | Y21: 0 | Z21: 0 | AA21: 0 | AB21: 6180980 | AC21: 0 | AD21: 0 | AE21: 0 | AF21: 0 | AG21: 0 | AH21: 0 | AI21: 0 | AJ21: 0 | AK21: 0 | AL21: 0 | AM21: 0 | AN21: 0 | AO21: 6251090 | AP21: 0 | AQ21: 0 | AR21: 0 | AS21: 0 | AT21: 0 | AU21: 0 | AV21: 6351090 | AW21: 6351090 | AX21: 6351090
A22: 6.2 | B22: Property & Equipment | D22: 24129088 | E22: 24129088 | F22: 24737942 | G22: 24737942 | H22: 24842952 | I22: 24437943 | J22: 29413165 | K22: 29413165 | L22: 28968837 | M22: 28968837 | N22: 31962614 | O22: 15335938 | P22: 30194240 | Q22: 28747246 | R22: 28747246 | S22: 28747246 | T22: 28747246 | U22: 30315876 | V22: 30497576 | W22: 30497576 | X22: 30497576 | Y22: 30497576 | Z22: 36678556 | AA22: 33884922 | AB22: 14714892 | AC22: 33884922 | AD22: 33884922 | AE22: 33884922 | AF22: 33884922 | AG22: 33884922 | AH22: 33884922 | AI22: 33884922 | AJ22: 33884922 | AK22: 33884922 | AL22: 33884922 | AM22: 34341922 | AN22: 21642868 | AO22: 15391778 | AP22: 34207546 | AQ22: 34574946 | AR22: 35523846 | AS22: 23408164 | AT22: 23512669 | AU22: 24182669 | AV22: 20685339 | AW22: 21704617 | AX22: 21719617
A23: 6.3 | B23: Prepaid Lease rentals | D23: 712740 | E23: 712740 | F23: 989135 | G23: 989135 | H23: 989135 | I23: 379140 | J23: 664740 | K23: 880740 | L23: 1087140 | M23: 687040 | N23: 897640 | P23: 940840 | Q23: 1032640 | R23: 1217440 | S23: 1217440 | T23: 1217440 | U23: 1217440 | V23: 1217440 | W23: 1217440 | X23: 1974240 | Y23: 1974240 | Z23: 1217040 | AA23: 942440 | AC23: 942440 | AD23: 942440 | AE23: 942440 | AF23: 942440 | AG23: 493128 | AH23: 883128 | AI23: 883128 | AJ23: 883128 | AK23: 1099128 | AL23: 1099128 | AM23: 1591128 | AN23: 934227 | AP23: 934227 | AQ23: 934227 | AR23: 1379835 | AS23: 1379835 | AT23: 1379835 | AU23: 1379835 | AV23: 1769835 | AW23: 1769835 | AX23: 1985835
A24: 6.4 | B24: Intangible Assets | D24: 0 | E24: 0 | F24: 0 | G24: 0 | H24: 0 | I24: 0 | J24: 0 | K24: 0 | L24: 0 | M24: 0 | N24: 0 | O24: 14633100 | P24: 0 | Q24: 0 | R24: 0 | S24: 1446994.8 | T24: 1446994.8 | U24: 1446994.8 | V24: 1446994.8 | W24: 1446994.8 | X24: 1446994.8 | Y24: 1446994.7 | Z24: 1446994.7 | AA24: 1177070.8 | AB24: 14166433 | AC24: 1177070.8 | AD24: 1177070.8 | AE24: 1177070.8 | AF24: 1177070.8 | AG24: 1177070.8 | AH24: 1177070.8 | AI24: 1177070.8 | AJ24: 1177070.8 | AK24: 1177070.8 | AL24: 1177070.8 | AM24: 1177070.8 | AN24: 18126486 | AO24: 18126486 | AP24: 5786584.8 | AQ24: 5786584.8 | AR24: 5786584.8 | AS24: 18127472 | AT24: 18327472 | AU24: 18524777 | AV24: 18530277 | AW24: 19125277 | AX24: 20562811
A25: 6.5 | B25: Other Assets | D25: 2067135.8 | E25: 2067135.8 | F25: 2067135.8 | G25: 2067135.8 | H25: 2067135.8 | I25: 2067135.8 | J25: 2067135.8 | K25: 2067135.8 | L25: 2067135.8 | M25: 2067135.8 | N25: 2067135.8 | P25: 1446994 | Q25: 1446994 | R25: 1446994 | S25: 0 | T25: 0 | U25: 0 | V25: 0 | W25: 0 | X25: 0 | Y25: 0 | Z25: 0 | AA25: 0 | AC25: 0 | AD25: 0 | AE25: 0 | AF25: 0 | AG25: 0 | AH25: 0 | AI25: 0 | AJ25: 0 | AK25: 0 | AL25: 0 | AM25: 0 | AN25: 0 | AP25: 0 | AQ25: 0 | AR25: 0 | AS25: 0 | AT25: 0 | AU25: 0 | AV25: 0 | AW25: 0 | AX25: 0
B26: Total Assets | C26: =C4+C7+C8+C13+C16+C20 -> 0 | D26: =D4+D7+D8+D13+D16+D20 -> 5.2885982e+08 | E26: =E4+E7+E8+E13+E16+E20 -> 5.3731704e+08 | F26: =F4+F7+F8+F13+F16+F20 -> 5.3830702e+08 | G26: =G4+G7+G8+G13+G16+G20 -> 5.5311245e+08 | H26: =H4+H7+H8+H13+H16+H20 -> 5.5782172e+08 | I26: =I4+I7+I8+I13+I16+I20 -> 5.5514722e+08 | J26: =J4+J7+J8+J13+J16+J20 -> 5.6861874e+08 | ... AY26: =AY4+AY7+AY8+AY13+AY16+AY20 -> 0
A27: 7 | B27: Savings Deposits - Withdrawable deposits - FOSA) | D27: 18835437 | E27: 19818619 | F27: 20149867 | G27: 20897319 | H27: 23417410 | I27: 22588238 | J27: 31824081 | K27: 30402672 | L27: 37005538 | M27: 37424267 | N27: 1.9659035e+08 | O27: 2.1833223e+08 | P27: 174362944 | Q27: 1.853994e+08 | R27: 1.9973475e+08 | S27: 2.0128806e+08 | T27: 2.0131374e+08 | U27: 192583080 | V27: 1.8451891e+08 | W27: 1.8741987e+08 | X27: 2.0547956e+08 | Y27: 192507556 | Z27: 1.9990598e+08 | AA27: 201623345 | AB27: 233858544 | AC27: 2.0416969e+08 | AD27: 2.2542426e+08 | AE27: 2.1369098e+08 | AF27: 2.1677792e+08 | AG27: 2.1505588e+08 | AH27: 209865045 | AI27: 2.0141945e+08 | AJ27: 1.8887754e+08 | AK27: 1.7920531e+08 | AL27: 1.7120221e+08 | AM27: 1.953233e+08 | AN27: 2.0021544e+08 | AO27: 232980325 | AP27: 1.9686061e+08 | AQ27: 2.1629426e+08 | AR27: 2.1624037e+08 | AS27: 2.091042e+08 | AT27: 1.9793029e+08 | AU27: 2.0092607e+08 | AV27: 1.945143e+08 | AW27: 1.982477e+08 | AX27: 1.8989132e+08
A28: 8 | B28: Short Term Deposits (e.g Fixed deposits, special savings) | D28: 2.0246589e+08 | E28: 2.0507152e+08 | F28: 209058011 | G28: 2.1266323e+08 | H28: 2.1610479e+08 | I28: 2.2052898e+08 | J28: 2.2755211e+08 | K28: 2.3053566e+08 | L28: 2.3443394e+08 | M28: 2.3685726e+08 | N28: 30529981 | P28: 30922064 | Q28: 30534231 | R28: 31624778 | S28: 31925106 | T28: 31601460 | U28: 34433246 | V28: 34525848 | W28: 31795618 | X28: 30053407 | Y28: 32344276 | Z28: 31710191 | AA28: 29845101 | AC28: 30274558 | AD28: 30810758 | AE28: 32578718 | AF28: 33843707 | AG28: 33476311 | AH28: 32001301 | AI28: 33131373 | AJ28: 33711201 | AK28: 34054042 | AL28: 32648488 | AM28: 31423387 | AN28: 32764883 | AO28: 0 | AP28: 35170428 | AQ28: 35733541 | AR28: 35474134 | AS28: 35021385 | AT28: 34571196 | AU28: 34164646 | AV28: 36092718 | AW28: 38159502 | AX28: 38146654
A29: 9 | B29: Non withdrawable deposits (BOSA member deposits) | D29: 3.8381101e+08 | E29: 3.9236899e+08 | F29: 413115060 | G29: 4.228648e+08 | H29: 4.308351e+08 | I29: 4.3265166e+08 | J29: 4.4494902e+08 | K29: 4.4656953e+08 | L29: 4.6581581e+08 | M29: 4.6785032e+08 | N29: 2.3894126e+08 | O29: 2.3907453e+08 | P29: 243479912 | Q29: 2.4892713e+08 | R29: 2.5231797e+08 | S29: 2.5666593e+08 | T29: 260620730 | U29: 2.6503785e+08 | V29: 2.6398417e+08 | W29: 2.6799435e+08 | X29: 2.7125477e+08 | Y29: 273369713 | Z29: 2.7638157e+08 | AA29: 2.7604901e+08 | AB29: 276157579 | AC29: 280837338 | AD29: 2.8692922e+08 | AE29: 2.909181e+08 | AF29: 2.9577585e+08 | AG29: 3.0010805e+08 | AH29: 2.9764262e+08 | AI29: 2.9848368e+08 | AJ29: 3.017162e+08 | AK29: 3.0393686e+08 | AL29: 3.0442152e+08 | AM29: 3.064791e+08 | AN29: 3.0317889e+08 | AO29: 303178892 | AP29: 3.0945933e+08 | AQ29: 3.140452e+08 | AR29: 320307065 | AS29: 3.2440276e+08 | AT29: 3.2557131e+08 | AU29: 3.2883678e+08 | AV29: 3.299785e+08 | AW29: 3.3357515e+08 | AX29: 3.3592359e+08
B30: Total Deposit liabilities | C30: =SUM(C27:C29) -> 0 | D30: =SUM(D27+D29) -> 4.0264645e+08 | E30: =SUM(E27+E29) -> 4.1218761e+08 | F30: =SUM(F27+F29) -> 433264927 | G30: =SUM(G27+G29) -> 4.4376212e+08 | H30: =SUM(H27+H29) -> 4.5425251e+08 | I30: =SUM(I27+I29) -> 4.552399e+08 | J30: =SUM(J27+J29) -> 4.767731e+08 | K30: =SUM(K27+K29) -> 4.769722e+08 | ... M30: =SUM(M27+M29) -> 5.0527459e+08 | N30: =SUM(N27:N29) -> 4.6606159e+08 | O30: =SUM(O27:O29) -> 4.5740677e+08 | P30: =SUM(P27:P29) -> 448764920 | Q30: =SUM(Q27:Q29) -> 4.6486076e+08 | R30: =SUM(R27:R29) -> 4.8367749e+08 | S30: =SUM(S27:S29) -> 4.898791e+08 | T30: =SUM(T27:T29) -> 4.9353593e+08 | U30: =SUM(U27:U29) -> 4.9205417e+08 | ... AY30: =SUM(AY27:AY29) -> 0
A31: 10 | B31: Accounts Payable & Other Liabilities | C31: =SUM(C32:C37) -> 0 | D31: =SUM(D32:D37) -> 3139111.1 | E31: =SUM(E32:E37) -> 1749796 | F31: =SUM(F32:F37) -> 13569693 | G31: =SUM(G32:G37) -> 17121086 | H31: =SUM(H32:H37) -> 1697768.3 | I31: =SUM(I32:I37) -> 274312 | J31: =SUM(J32:J37) -> 1175412.9 | ... AY31: =SUM(AY32:AY37) -> 0
A32: 10.1 | B32: Tax Payable | D32: 0 | E32: 0 | F32: 0 | G32: 0 | H32: 0 | I32: 0 | J32: 0 | K32: 0 | L32: 0 | M32: 0 | N32: 467101.2 | O32: 2502451 | P32: 549156 | Q32: 494222.15 | R32: 800000 | S32: 802990 | T32: 396965.5 | U32: 406179.7 | V32: 415749.2 | W32: 464889.78 | X32: 503335.51 | Y32: 528088.34 | Z32: 523242.23 | AA32: 557429.32 | AB32: 2305046 | AC32: 375280.93 | AD32: 2125610.8 | AE32: 312540.74 | AF32: 354574.44 | AG32: 352871.56 | AH32: 309051.76 | AI32: 313036.77 | AJ32: 278640 | AK32: 311635.18 | AL32: 330659.6 | AM32: 307590.66 | AN32: 0 | AO32: 2148516 | AP32: 2148516 | AQ32: 148516 | AR32: 0 | AS32: 0 | AT32: 0 | AU32: 0 | AV32: 0 | AW32: 0 | AX32: 0
A33: 10.2 | B33: Dividends Payable | P33: 0 | Q33: 0 | S33: 0 | T33: 0 | U33: 0 | V33: 0 | W33: 0 | X33: 0 | Y33: 0 | Z33: 0 | AA33: 0 | AB33: =27065843+600000+7887856 -> 35553699 | AC33: 0 | AD33: 0 | AE33: 0 | AF33: 0 | AG33: 0 | AH33: 0 | AI33: 0 | AJ33: 0 | AK33: 0 | AL33: 0 | AM33: 0 | AN33: 0 | AO33: =24763989+600000+9096803 -> 34460792 | AP33: 0 | AQ33: 0 | AR33: 0 | AS33: 0 | AT33: 0 | AU33: 0 | AV33: 0 | AW33: 0 | AX33: 0
A34: 10.3 | B34: Deferred Tax Liability | D34: 275464.3 | E34: 274313 | F34: 274313 | G34: 548625.2 | H34: 274312 | I34: 274312 | J34: 11542 | K34: 257795.2 | L34: 11543.8 | M34: 266863 | P34: 0 | Q34: 0 | S34: 0 | T34: 0 | U34: 0 | V34: 0 | W34: 0 | X34: 0 | Y34: 0 | Z34: 0 | AA34: 0 | AC34: 0 | AD34: 0 | AE34: 0 | AF34: 0 | AG34: 0 | AH34: 0 | AI34: 0 | AJ34: 0 | AK34: 0 | AL34: 0 | AM34: 0 | AN34: 0 | AP34: 0 | AQ34: 0 | AR34: 0 | AS34: 0 | AT34: 0 | AU34: 0 | AV34: 0 | AW34: 0 | AX34: 0
A35: 10.4 | B35: Retirement Benefits Liability | D35: 2863646.8 | E35: 1475483 | F35: 13295380 | G35: 16572461 | H35: 1423456.3 | I35: 0 | J35: 1163870.9 | K35: 4596806.5 | L35: 1524903 | M35: 2617691.5 | N35: 262084.4 | P35: 255229 | Q35: 483752.93 | R35: 243586.49 | S35: 243586 | T35: 226636.29 | U35: 226636.29 | V35: 239291.69 | W35: 239291.69 | X35: 234842.19 | Y35: 484988.89 | Z35: 226132.09 | AA35: 6388.19 | AC35: 264829.85 | AD35: 264829.85 | AE35: 264829.85 | AF35: 280428.93 | AG35: 249103.49 | AH35: 252338.25 | AI35: 510654.91 | AJ35: 252337.57 | AK35: 238631.33 | AL35: 238630.99 | AM35: 238630.99 | AN35: 0 | AP35: 245077.53 | AQ35: 259681.5 | AR35: 257646.02 | AS35: 259681.5 | AT35: 259681.5 | AU35: 263144.7 | AV35: 259681.5 | AW35: 259681.5 | AX35: 259681.5
A36: 10.5 | B36: Other Liabilities | D36: 0 | E36: 0 | F36: 0 | G36: 0 | H36: 0 | I36: 0 | J36: 0 | K36: 0 | L36: 0 | M36: 0 | N36: 2393252.4 | O36: 28127673 | P36: 1579519 | Q36: 35874406 | R36: 4702326 | S36: 1027884.9 | T36: 807854.95 | U36: 107874.95 | V36: 124387 | W36: 300380 | X36: 120000 | Y36: 135000 | Z36: 128000 | AA36: 134769.13 | AB36: =709086 -> 709086 | AC36: 501302.58 | AD36: 101200 | AE36: 211200 | AF36: 0 | AG36: 0 | AH36: 0 | AI36: 0 | AJ36: 0 | AK36: 0 | AL36: 0 | AM36: 0 | AN36: 1434873 | AO36: 1434872 | AP36: 0 | AQ36: 0 | AR36: 0 | AS36: 2763315.4 | AT36: 5406673.3 | AU36: 5626450.4 | AV36: 5879740.4 | AW36: 1016306.7 | AX36: 6363764.2
A37: 10.6 | B37: External Borrowings | P37: 0 | Q37: 0 | S37: 0 | T37: 0 | U37: 0 | V37: 0 | W37: 0 | X37: 0 | Y37: 0 | Z37: 0 | AA37: 0 | AC37: 0 | AD37: 0 | AE37: 0 | AF37: 0 | AG37: 0 | AH37: 0 | AI37: 0 | AJ37: 0 | AK37: 0 | AL37: 0 | AM37: 0 | AN37: 0 | AP37: 0 | AQ37: 0 | AR37: 0 | AS37: 0 | AT37: 0 | AU37: 0 | AV37: 0 | AW37: 0 | AX37: 0
B38: Total Liabilities | C38: =C30+C31 -> 0 | D38: =D30+D31 -> 4.0578556e+08 | E38: =E30+E31 -> 4.139374e+08 | F38: =F30+F31 -> 4.4683462e+08 | G38: =G30+G31 -> 4.6088321e+08 | H38: =H30+H31 -> 4.5595028e+08 | I38: =I30+I31 -> 4.5551421e+08 | J38: =J30+J31 -> 4.7794851e+08 | ... AY38: =AY30+AY31 -> 0
A39: 11 | B39: Share Capital (Members share capital per Bylaws) | D39: 68778694 | E39: 69235163 | F39: 36509431 | G39: 37574873 | H39: 44323527 | I39: 41789787 | J39: 40727169 | K39: 44073272 | L39: 49668587 | M39: 54774836 | N39: 65584943 | O39: 65584843 | P39: 66350370 | Q39: 66925037 | R39: 67030634 | S39: 68143329 | T39: 68697839 | U39: 69091045 | V39: 75685743 | W39: 76189013 | X39: 76696723 | Y39: 77230445 | Z39: 77733990 | AA39: 84253469 | AB39: 84252269 | AC39: 84883829 | AD39: 85017697 | AE39: 86737789 | AF39: 87494452 | AG39: 88104856 | AH39: 93598607 | AI39: 93598607 | AJ39: 94290447 | AK39: 94398722 | AL39: 94521110 | AM39: 96434299 | AN39: 102243742 | AO39: 102243742 | AP39: 103610152 | AQ39: 1.0368169e+08 | AR39: 1.0478402e+08 | AS39: 1.0625947e+08 | AT39: 1.0739914e+08 | AU39: 1.0815187e+08 | AV39: 1.0887347e+08 | AW39: 1.0976476e+08 | AX39: 1.1048637e+08
A40: 12 | B40: Capital Grants | D40: 0 | E40: 0 | F40: 0 | G40: 0 | H40: 0 | I40: 0 | J40: 0 | K40: 0 | L40: 0 | M40: 0 | N40: 0 | O40: 0 | P40: 0 | Q40: 0 | S40: 0 | T40: 0 | U40: 0 | V40: 0 | W40: 0 | X40: 0 | Y40: 0 | Z40: 0 | AA40: 0 | AC40: 0 | AD40: 0 | AE40: 0 | AF40: 0 | AG40: 0 | AH40: 0 | AI40: 0 | AJ40: 0 | AK40: 0 | AL40: 0 | AM40: 0 | AN40: 0 | AO40: 0 | AP40: 0 | AQ40: 0 | AR40: 0 | AS40: 0 | AT40: 0 | AU40: 0 | AV40: 0 | AW40: 0 | AX40: 0
A41: 13 | B41: Retained Earnings | C41: =SUM(C42+C43) -> 0 | D41: =SUM(D42+D43) -> 14810760 | E41: =SUM(E42+E43) -> 14810760 | F41: =SUM(F42+F43) -> 14810760 | G41: =SUM(G42+G43) -> 14810760 | H41: =SUM(H42+H43) -> 18119348 | I41: =SUM(I42+I43) -> 18119348 | J41: =SUM(J42+J43) -> 18119348 | ... AY41: =SUM(AY42+AY43) -> 0
A42: 13.1 | B42: Prior Years' Retained Earnings | D42: 14810760 | E42: 14810760 | F42: 14810760 | G42: 14810760 | H42: 18119348 | I42: 18119348 | J42: 18119348 | K42: 18119348 | L42: 18119348 | M42: 18119348 | N42: 34136157 | O42: 34136157 | P42: 75103944 | Q42: 40458753 | R42: 40458753 | S42: 40458753 | T42: 40458753 | U42: 40458753 | V42: 40458753 | W42: 40458753 | X42: 40458753 | Y42: 40458753 | Z42: 40458753 | AA42: 40458753 | AB42: 40458752 | AC42: 84249920 | AD42: 43499944 | AE42: 43499944 | AF42: 43499944 | AG42: 43499944 | AH42: 43499944 | AI42: 43499944 | AJ42: 43499944 | AK42: 43499944 | AL42: 43499944 | AM42: 43499944 | AN42: 43499943 | AO42: 43499943 | AP42: 48021913 | AQ42: 48021914 | AR42: 48021914 | AS42: 48021914 | AT42: 48021914 | AU42: 48021914 | AV42: 48021914 | AW42: 48021914 | AX42: 48021914
A43: 13.2 | B43: Current Year's Surplus | D43: 0 | E43: 0 | F43: 0 | G43: 0 | H43: 0 | I43: 0 | J43: 0 | K43: 0 | L43: 0 | M43: 0 | N43: 46478813 | O43: 6322596 | P43: 2693777 | Q43: 3582940.7 | R43: 8084210 | S43: 12274190 | T43: 15207710 | U43: 18139027 | V43: 21544147 | W43: 23583098 | X43: 29076264 | Y43: 34339838 | Z43: 40618306 | AA43: 49053271 | AB43: 3041191 | AC43: 1354314.6 | AD43: 4322405.2 | AE43: 6172466 | AF43: 3013304.8 | AG43: 4009745.4 | AH43: 4460703.2 | AI43: 5166105 | AJ43: 4117721.2 | AK43: 5488564.7 | AL43: 17921149 | AM43: 30279988 | AN43: 42720806 | AO43: =17773464-3554693-9096802-600000 -> 4521969 | AP43: 1995472.9 | AQ43: 4935781.2 | AR43: 5863309.8 | AS43: 6623110 | AT43: 8544195.2 | AU43: 12404964 | AV43: 17549631 | AW43: 18885807 | AX43: 28397704
A44: 14 | B44: Other Equity Accounts | C44: =SUM(C45:C49) -> 0 | D44: =SUM(D45:D49) -> 1.4147723e+08 | E44: =SUM(E45:E49) -> 1.4252356e+08 | F44: =SUM(F45:F49) -> 110211500 | G44: =SUM(G45:G49) -> 1.1178985e+08 | H44: =SUM(H45:H49) -> 1.2395768e+08 | I44: =SUM(I45:I49) -> 1.214971e+08 | J44: =SUM(J45:J49) -> 1.2219561e+08 | ... AY44: =SUM(AY45:AY49) -> 0
B45: Statutory Reserve | D45: 0 | E45: 0 | F45: 0 | G45: 0 | H45: 0 | I45: 0 | J45: 0 | K45: 0 | L45: 0 | M45: 0 | N45: 0 | O45: 18441997 | P45: 15172384 | Q45: 15172384 | R45: 18441997 | S45: 18441997 | T45: 18441997 | U45: 18441997 | V45: 24885077 | W45: 18441997 | X45: 18441997 | Y45: 18441997 | Z45: 18441997 | AA45: 18441997 | AB45: 21324259 | AC45: 18441997 | AD45: 21324259 | AE45: 21324259 | AF45: 21324259 | AG45: 21324259 | AH45: 21324259 | AI45: 21324259 | AJ45: 21324259 | AK45: 21324259 | AL45: 21324259 | AM45: 21324259 | AN45: 21324259 | AO45: 24878951 | AP45: 24878952 | AQ45: 24878952 | AR45: 24878952 | AS45: 24878952 | AT45: 24878952 | AU45: 24878952 | AV45: 24878952 | AW45: 24878952 | AX45: 24878952
B46: Other Reserves (provide notes on these reserves) | N46: 15172384 | P46: 2946964 | Q46: 2946964 | R46: 2946964 | S46: 2946964 | T46: 2946964 | U46: 2946964 | V46: 2946964 | W46: 2946964 | X46: 2946964 | Y46: 2946964 | Z46: 2946964 | AA46: 2946964 | AB46: 2946964 | AC46: 2946964 | AD46: 2946964 | AE46: 2946964 | AF46: 2946964 | AG46: 2946964 | AH46: 2946964 | AI46: 2946964 | AJ46: 2946964 | AK46: 2946964 | AL46: 2946964 | AM46: 2946964 | AN46: 9341885 | AO46: =2946964+6394921 -> 9341885 | AP46: 9341885 | AQ46: 9341885 | AR46: 9341885 | AS46: 9341885 | AT46: 9341885 | AU46: 9341885 | AV46: 9341885 | AW46: 9341885 | AX46: 9341885
B47: Revaluation Reserves (Not part of core capital) | N47: 2946964 | O47: 2946964 | P47: 0 | Q47: 0 | R47: 0 | S47: 0 | T47: 0 | U47: 0 | V47: 0 | W47: 0 | X47: 0 | Y47: 0 | Z47: 0 | AA47: 0 | AC47: 0 | AD47: 0 | AE47: 0 | AF47: 0 | AG47: 0 | AH47: 0 | AI47: 0 | AJ47: 0 | AK47: 0 | AL47: 0 | AM47: 0 | AN47: 0 | AP47: 0 | AQ47: 0 | AR47: 0 | AS47: 0 | AT47: 0 | AU47: 0 | AV47: 0 | AW47: 0 | AX47: 0
B48: Proposed Dividends | D48: 1.4147723e+08 | E48: 1.4252356e+08 | F48: 110211500 | G48: 1.1178985e+08 | H48: 1.2395768e+08 | I48: 1.214971e+08 | J48: 1.2219561e+08 | K48: 1.2610729e+08 | L48: 1.322187e+08 | M48: 1.3732495e+08 | P48: 0 | Q48: 0 | S48: 0 | T48: 0 | U48: 0 | V48: 0 | W48: 0 | X48: 0 | Y48: 0 | Z48: 0 | AA48: 0 | AC48: 0 | AD48: 0 | AE48: 0 | AF48: 0 | AG48: 0 | AH48: 0 | AI48: 0 | AJ48: 0 | AK48: 0 | AP48: 34460791 | AQ48: 0 | AR48: 0 | AS48: 0 | AT48: 0 | AU48: 0 | AV48: 0 | AW48: 0 | AX48: 0
B49: Adjustment to Equity | D49: 0 | E49: 0 | F49: 0 | G49: 0 | H49: 0 | I49: 0 | J49: 0 | K49: 0 | L49: 0 | M49: 0 | N49: 0 | P49: 0 | Q49: 0 | R49: 0 | S49: 0 | T49: 0 | U49: 0 | V49: 0 | W49: 0 | AI49: 0 | AJ49: 0 | AK49: 0 | AP49: 0 | AQ49: 0 | AR49: 0 | AS49: 0 | AT49: 0 | AU49: 0 | AV49: 0 | AW49: 0 | AX49: 0
B50: Total Equity | C50: =SUM(C39+C40+C41+C44) -> 0 | D50: =SUM(D39+D40+D41+D44) -> 2.2506669e+08 | E50: =SUM(E39+E40+E41+E44) -> 2.2656948e+08 | F50: =SUM(F39+F40+F41+F44) -> 161531691 | G50: =SUM(G39+G40+G41+G44) -> 1.6417548e+08 | H50: =SUM(H39+H40+H41+H44) -> 1.8640055e+08 | I50: =SUM(I39+I40+I41+I44) -> 1.8140624e+08 | J50: =SUM(J39+J40+J41+J44) -> 1.8104213e+08 | ... AY50: =SUM(AY39+AY40+AY41+AY44) -> 0
B51: Total Liabilities and Equity | C51: =SUM(C38+C50) -> 0 | D51: =SUM(D38+D50) -> 6.3085224e+08 | E51: =SUM(E38+E50) -> 6.4050688e+08 | F51: =SUM(F38+F50) -> 6.0836631e+08 | G51: =SUM(G38+G50) -> 6.2505869e+08 | H51: =SUM(H38+H50) -> 6.4235083e+08 | I51: =SUM(I38+I50) -> 6.3692045e+08 | J51: =SUM(J38+J50) -> 6.5899064e+08 | ... AY51: =SUM(AY38+AY50) -> 0
D52: =SUM(D39+#REF!) -> #REF! | E52: =SUM(E39+#REF!) -> #REF! | F52: =SUM(F39+#REF!) -> #REF! | G52: =SUM(G39+#REF!) -> #REF! | N52: =N51-N26 -> 0 | O52: =O51-O26 -> 0.33069193 | P52: =P51-P26 -> 0.24000001 | Q52: =Q51-Q26 -> 0 | R52: =R51-R26 -> -0.0099999905 | S52: =S51-S26 -> 0 | T52: =T51-T26 -> 0 | U52: =U51-U26 -> 0 | ... AO52: =AO51-AO26 -> -0.28999996 | AQ52: =AQ51-AQ26 -> 0 | AR52: =AR51-AR26 -> 0 | AS52: =AS51-AS26 -> 0 | AT52: =AT51-AT26 -> 0 | AU52: =AU51-AU26 -> 0 | AV52: =AV51-AV26 -> 0 | AW52: =AW51-AW26 -> 0 | AX52: =AX51-AX26 -> 0
B54: Short term liabilities | O54: =O32+O33+O34+O35+O36+O37+O27+O28 -> 2.4896236e+08 | P54: =P32+P33+P34+P35+P36+P37+P27+P28 -> 207668912 | Q54: =Q32+Q33+Q34+Q35+Q36+Q37+Q27+Q28 -> 2.5278601e+08 | R54: =R32+R33+R34+R35+R36+R37+R27+R28 -> 2.3710544e+08 | S54: =S32+S33+S34+S35+S36+S37+S27+S28 -> 2.3528763e+08 | T54: =T32+T33+T34+T35+T36+T37+T27+T28 -> 2.3434666e+08 | U54: =U32+U33+U34+U35+U36+U37+U27+U28 -> 2.2775702e+08 | V54: =V32+V33+V34+V35+V36+V37+V27+V28 -> 2.1982418e+08 | ... AY54: =AY32+AY33+AY34+AY35+AY36+AY37+AY27+AY28 -> 0

Sheet SCI
A1: FORM 7 SASRA/007
A2: STATEMENT OF COMPREHENSIVE INCOME
D3: 44216 | E3: 44247 | F3: 44275 | G3: 44306 | H3: 44336 | I3: 44367 | J3: 44428 | K3: 44459 | L3: 44489 | M3: 44520 | N3: 44550 | O3: Aud-20 | P3: 44197 | Q3: 44228 | R3: 44256 | S3: 44287 | T3: 44317 | U3: 44348 | V3: 44378 | W3: 44409 | X3: 44440 | Y3: 44470 | Z3: 44501 | AA3: 44531 | AB3: Audited 2021 | AC3: 44562 | AD3: 44593 | AE3: 44621 | AF3: 44652 | AG3: 44682 | AH3: 44713 | AI3: 44743 | AJ3: 44774 | AK3: 44805 | AL3: 44835 | AM3: 44866 | AN3: 44896 | AO3: Audit 2022 | AP3: 44927 | AQ3: 44958 | AR3: 44986 | AS3: 45017 | AT3: 45047 | AU3: 45078 | AV3: 45108 | AW3: 45139 | AX3: 45170 | AY3: 45200 | AZ3: 45231
A4: 1 | B4: Financial Income | C4: =C5+C8 -> 0 | D4: 6043595.3 | E4: 13679359 | F4: 20872470 | G4: 27225463 | H4: 33761960 | I4: 40552952 | J4: 54240850 | K4: 61254761 | L4: 68568629 | M4: 75641832 | N4: 96703209 | O4: =O5+O8 -> 25961510 | P4: =P5+P8 -> 7733033 | Q4: =Q5+Q8 -> 15105750 | R4: =R5+R8 -> 22912608 | S4: =S5+S8 -> 30494903 | T4: =T5+T8 -> 37810544 | U4: =U5+U8 -> 45193916 | V4: =V5+V8 -> 53010040 | ... AZ4: =AZ5+AZ8 -> 0
A5: 2 | B5: Financial Income from Loans Portfolio | D5: =D6+D7 -> 5222453.8 | E5: =E6+E7 -> 10608470 | F5: =F6+F7 -> 15967667 | G5: =G6+G7 -> 21073370 | H5: =H6+H7 -> 26384513 | I5: =I6+I7 -> 31693723 | J5: =J6+J7 -> 42749477 | K5: =K6+K7 -> 48495227 | ... AZ5: =AZ6+AZ7 -> 0
A6: 2.1 | B6: Interest on Loan Portfolio | D6: 4522149.6 | E6: 9208162.9 | F6: 14072634 | G6: 18817449 | H6: 23574404 | I6: 28401575 | J6: 38200406 | K6: 43289790 | L6: 48506554 | M6: 53720913 | N6: 63182271 | P6: 5284408 | Q6: 10697906 | R6: 16202970 | S6: 21756991 | T6: 27146510 | U6: 32608642 | V6: 38228837 | W6: 43987826 | X6: 50015819 | Y6: 55942948 | Z6: 61992281 | AA6: 68337882 | AB6: 77339274 | AC6: 6215531.2 | AD6: 12496488 | AE6: 18566797 | AF6: 23466782 | AG6: 29502401 | AH6: 34600424 | AI6: 40756553 | AJ6: 47285240 | AK6: 53671372 | AL6: 60267927 | AM6: 66747662 | AN6: 88232370 | AO6: 88232371 | AP6: 7087584.5 | AQ6: 14395325 | AR6: 21640227 | AS6: 1.1325468e+08 | AT6: 1.4700601e+08 | AU6: 43973086 | AV6: 52344635 | AW6: 59548816 | AX6: 68233587
A7: 2.2 | B7: Fees & Commission on Loan Portfolio | D7: 700304.2 | E7: 1400307 | F7: 1895033 | G7: 2255920.6 | H7: 2810109.1 | I7: 3292148.1 | J7: 4549071.4 | K7: 5205437 | L7: 5941627.4 | M7: 6524759.8 | N7: 7433230 | P7: 2307065 | Q7: 1293709.8 | R7: 2037222.8 | S7: 2650298 | T7: 3312469.8 | U7: 4020793.6 | V7: 4844352.4 | W7: 5525349.8 | X7: 6223663.2 | Y7: 6994051.6 | Z7: 7692927.3 | AA7: 8303001.6 | AC7: 654828.8 | AD7: 1274727.8 | AE7: 2148373.9 | AF7: 2970183.7 | AG7: 3831749.9 | AH7: 4372497.3 | AI7: 4956143.1 | AJ7: 5362196.1 | AK7: 5915984.1 | AL7: 6489119.1 | AM7: 7563091.5 | AN7: 0 | AO7: 0 | AP7: 802480.4 | AQ7: 1476724.4 | AR7: 2196337.4 | AS7: 468600 | AT7: 620400 | AU7: 5216691.4 | AV7: 6089508.4 | AW7: 7278000.4 | AX7: 8205063.2
A8: 3 | B8: Financial Income from Investments in: | C8: =C9+C10+C11+C12 -> 0 | D8: 93917.85 | E8: 235212.7 | F8: 373017 | G8: 373017 | H8: 319788.05 | I8: 410116.75 | J8: 534966.05 | K8: 561267.3 | L8: 645375.85 | M8: 663458.05 | N8: 9385105.1 | O8: =O9+O10+O11+O12 -> 25961510 | P8: =P9+P10+P11+P12 -> 141560 | Q8: =Q9+Q10+Q11+Q12 -> 3114134 | R8: =R9+R10+R11+R12 -> 4672416 | S8: =S9+S10+S11+S12 -> 6087613.4 | T8: =T9+T10+T11+T12 -> 7351563.4 | U8: =U9+U10+U11+U12 -> 8564480.2 | V8: =V9+V10+V11+V12 -> 9936850.7 | ... AZ8: =AZ9+AZ10+AZ11+AZ12 -> 0
A9: 3.1 | B9: Government Securities | D9: 0 | E9: 0 | F9: 0 | G9: 0 | H9: 0 | I9: 0 | J9: 0 | K9: 0 | L9: 0 | M9: 0 | N9: 0 | P9: 0 | Q9: 0 | R9: 0 | S9: 0 | T9: 0 | U9: 0 | V9: 0 | W9: 0 | X9: 0 | Y9: 0 | Z9: 0 | AA9: 0 | AC9: 0 | AD9: 0 | AE9: 0 | AF9: 0 | AG9: 0 | AH9: 0 | AI9: 0 | AJ9: 0 | AK9: 0 | AL9: 0 | AM9: 0 | AN9: 0 | AP9: 0 | AQ9: 0 | AR9: 0 | AS9: 0 | AT9: 0 | AU9: 0 | AV9: 0 | AW9: 0 | AX9: 0
A10: 3.2 | B10: Deposit with Banks and Other Financial Inst. | D10: 93917.85 | E10: 235212.7 | F10: 373017 | G10: 373017 | H10: 319788.05 | I10: 410116.75 | J10: 534966.05 | K10: 561267.3 | L10: 645375.85 | M10: 663458.05 | N10: 9385105.1 | O10: 9385105.1 | P10: 0 | Q10: 0 | R10: 0 | S10: 163397 | T10: 163397 | U10: 187232.79 | V10: 223890.34 | W10: 223890.34 | X10: 358931.34 | Y10: 391232.04 | Z10: 452875.84 | AA10: 8956142.7 | AB10: 8956143 | AC10: 1315516.3 | AD10: 5067 | AE10: 103368.35 | AF10: 103368.35 | AG10: 189751.85 | AH10: 189751.85 | AI10: 274416.2 | AJ10: 290854.55 | AK10: 318471 | AL10: 318471 | AM10: 318471 | AN10: 8636616.1 | AO10: 10601777 | AP10: 0 | AQ10: 4109.6 | AR10: 10684.95 | AS10: 991028.94 | AT10: 1043751.9 | AU10: 41013.75 | AV10: 41013.75 | AW10: 41013.75 | AX10: 41013.75
A11: 3.3 | B11: Other Investments - dividend & Interest incomes from investments | D11: 0 | E11: 0 | F11: 0 | G11: 0 | H11: 0 | I11: 0 | J11: 0 | K11: 0 | L11: 0 | M11: 0 | N11: 0 | O11: 1205672 | P11: 0 | Q11: 0 | R11: 0 | S11: 0 | T11: 0 | U11: 0 | V11: 0 | W11: 0 | X11: 0 | Y11: 0 | Z11: 0 | AA11: 0 | AC11: 0 | AD11: 0 | AE11: 0 | AF11: 0 | AG11: 0 | AH11: 0 | AI11: 0 | AJ11: 0 | AK11: 0 | AL11: 0 | AM11: 0 | AN11: 0 | AP11: 0 | AQ11: 0 | AR11: 0 | AS11: 0 | AT11: 0 | AU11: 0 | AV11: 0 | AW11: 0 | AX11: 0
A12: 3.4 | B12: Other Operating Income- Salary processing fees, transaction fees, membership fees | D12: 727223.66 | E12: 2835676.5 | F12: 4531786 | G12: 5779076.5 | H12: 7057658.5 | I12: 8449112.5 | J12: 10956407 | K12: 12198267 | L12: 13475073 | M12: 14732701 | N12: 16702603 | O12: 15370733 | P12: 141560 | Q12: 3114134 | R12: 4672416 | S12: 5924216.4 | T12: 7188166.4 | U12: 8377247.4 | V12: 9712960.4 | W12: 11037585 | X12: 12368503 | Y12: 13723217 | Z12: 15688590 | AA12: 15804790 | AB12: 15112604 | AC12: 0 | AD12: 2994938.2 | AE12: 4324006.6 | AF12: 5444755.2 | AG12: 6409155.6 | AH12: 7978978.9 | AI12: 8238592 | AJ12: 9189366.8 | AK12: 10238167 | AL12: 11281831 | AM12: 12417343 | AN12: 13042022 | AO12: 13046147 | AP12: 1234155.4 | AQ12: 2892729.2 | AR12: 4553829.5 | AS12: 9026487.6 | AT12: 9901045.1 | AU12: 8431436.5 | AV12: 9924247.4 | AW12: 11413211
A13: 4 | B13: Financial Expense | C13: =C14+C15+C16+C17+C18+C19 -> 0 | D13: 233117 | E13: 281033 | F13: 429472 | G13: 455886 | H13: 521206.59 | I13: 759467.53 | J13: 972670.53 | K13: 1053514.2 | L13: 1174255.2 | M13: 1274233.7 | N13: 1691237.3 | O13: =O14+O15+O16+O17+O18+O19 -> 23007203 | P13: =P14+P15+P16+P17+P18+P19 -> 358729 | Q13: =Q14+Q15+Q16+Q17+Q18+Q19 -> 622500.15 | R13: =R14+R15+R16+R17+R18+R19 -> 721788.9 | S13: =S14+S15+S16+S17+S18+S19 -> 589158.25 | T13: =T14+T15+T16+T17+T18+T19 -> 743648.25 | U13: =U14+U15+U16+U17+U18+U19 -> 896755.35 | V13: =V14+V15+V16+V17+V18+V19 -> 1110754.3 | ... AZ13: =AZ14+AZ15+AZ16+AZ17+AZ18+AZ19 -> 0
A14: 4.2 | B14: Interest Expense on Deposits | D14: 233117 | E14: 281033 | F14: 373017 | G14: 399431 | H14: 462351.29 | I14: 616370.23 | J14: 829573.23 | K14: 897398.23 | L14: 957370.23 | M14: 1055499.9 | N14: 1457284.9 | O14: 21789409 | P14: 115129 | Q14: 344582.15 | R14: 476988.9 | S14: 586938.45 | T14: 692728.45 | U14: 792352.45 | V14: 985597.45 | W14: 1360067.4 | X14: 1077910.4 | Y14: 1255129.4 | Z14: 1361156.6 | AA14: 2012018.6 | AB14: 29077862 | AC14: 413877 | AD14: 482403 | AE14: 712941 | AF14: 777441.41 | AG14: 838502.41 | AH14: 1055682.4 | AI14: 1223585.4 | AJ14: 1299215.4 | AK14: 1553727.4 | AL14: 1647820.4 | AM14: 1792246.5 | AN14: 1989967.5 | AO14: 26753957 | AP14: 238903.96 | AQ14: 308631.29 | AR14: 487921.58 | AS14: 64479144 | AT14: 65161990 | AU14: 1013484.6 | AV14: 1316846.6 | AW14: 1415772.6 | AX14: 1572212.4
A15: 4.3 | B15: Cost of External Borrowings | D15: 0 | E15: 0 | F15: 0 | G15: 0 | H15: 0 | I15: 0 | J15: 0 | K15: 0 | L15: 0 | M15: 0 | N15: 0 | P15: 0 | Q15: 0 | R15: 0 | S15: 0 | T15: 0 | U15: 0 | V15: 0 | W15: 0 | X15: 0 | Y15: 0 | Z15: 0 | AA15: 0 | AC15: 0 | AD15: 0 | AE15: 0 | AF15: 0 | AG15: 0 | AH15: 0 | AI15: 0 | AJ15: 0 | AK15: 0 | AL15: 0 | AM15: 0 | AN15: 0 | AP15: 0 | AQ15: 0 | AR15: 0 | AS15: 0 | AT15: 0 | AU15: 0 | AV15: 0 | AW15: 0 | AX15: 0
A16: 4.4 | B16: Dividend Expenses (on member shares) | D16: 0 | E16: 0 | F16: 0 | G16: 0 | H16: 0 | I16: 0 | J16: 0 | K16: 0 | L16: 0 | M16: 0 | N16: 0 | P16: 0 | Q16: 0 | R16: 0 | S16: 0 | T16: 0 | U16: 0 | V16: 0 | W16: 0 | X16: 0 | Y16: 0 | Z16: 0 | AA16: 0 | AC16: 0 | AD16: 0 | AE16: 0 | AF16: 0 | AG16: 0 | AH16: 0 | AI16: 0 | AJ16: 0 | AK16: 0 | AL16: 0 | AM16: 0 | AN16: 0 | AP16: 0 | AQ16: 0 | AR16: 0 | AS16: 0 | AT16: 0 | AU16: 0 | AV16: 0 | AW16: 0 | AX16: 0
A17: 4.5 | B17: Other Financial Expense | D17: 0 | E17: 0 | F17: 0 | G17: 0 | H17: 0 | I17: 0 | J17: 0 | K17: 0 | L17: 0 | M17: 0 | N17: 0 | P17: 0 | Q17: 0 | R17: 0 | S17: 0 | T17: 0 | U17: 0 | V17: 0 | W17: 0 | X17: 0 | Y17: 0 | Z17: 0 | AA17: 0 | AB17: 1388877.8 | AC17: 0 | AD17: 0 | AE17: 0 | AF17: 0 | AG17: 0 | AH17: 0 | AI17: 0 | AJ17: 0 | AK17: 0 | AL17: 0 | AM17: 0 | AN17: 0 | AP17: 0 | AQ17: 0 | AR17: 0 | AS17: 0 | AT17: 0 | AU17: 0 | AV17: 0 | AW17: 0 | AX17: 0
A18: 4.6 | B18: Fees & Commission Expense | D18: 0 | E18: 0 | F18: 56455 | G18: 56455 | H18: 58855.3 | I18: 143097.3 | J18: 143097.3 | K18: 156116 | L18: 216885 | M18: 218733.8 | N18: 233952.4 | P18: 243600 | Q18: 277918 | R18: 244800 | S18: 2219.8 | T18: 50919.8 | U18: 104402.9 | V18: 125156.9 | W18: 118726.9 | X18: 152811.3 | Y18: 156178.7 | Z18: 269337.2 | AA18: 304033.8 | AC18: 0 | AD18: 0 | AE18: 718.4 | AF18: 7148.4 | AG18: 47294.4 | AH18: 47294.4 | AI18: 84255.9 | AJ18: 125277.9 | AK18: 125277.9 | AL18: 125277.9 | AM18: 125277.9 | AN18: 266571.6 | AO18: =266572+210053+1073170+1503 -> 1551298 | AP18: 1020.3 | AQ18: 16386.2 | AR18: 34386.2 | AS18: 272121 | AT18: 282543 | AU18: 125932.5 | AV18: 166235.9 | AW18: 187170.9 | AX18: 198419.9
A19: 4.7 | B19: Other Expense | D19: 0 | E19: 0 | F19: 0 | G19: 0 | H19: 0 | I19: 0 | J19: 0 | K19: 0 | L19: 0 | M19: 0 | N19: 0 | O19: 1217794.4 | P19: 0 | Q19: 0 | R19: 0 | S19: 0 | T19: 0 | U19: 0 | V19: 0 | W19: 0 | X19: 0 | Y19: 0 | Z19: 0 | AA19: 0 | AC19: 0 | AD19: 0 | AE19: 0 | AF19: 0 | AG19: 0 | AH19: 0 | AI19: 0 | AJ19: 0 | AK19: 0 | AL19: 0 | AM19: 0 | AN19: 0 | AP19: 0 | AQ19: 0 | AR19: 0 | AS19: 0 | AT19: 0 | AU19: 0 | AV19: 0 | AW19: 0 | AX19: 0
A20: 5 | B20: Net Financial Income/(Loss) | C20: =C4-C13 -> 0 | D20: 5810478.3 | E20: 13398326 | F20: 20442998 | G20: 26769577 | H20: 33240753 | I20: 39793484 | J20: 53268179 | K20: 60201246 | L20: 67394374 | M20: 74367598 | N20: 95011971 | O20: =O4-O13 -> 2954307.1 | P20: =P4-P13 -> 7374304 | Q20: =Q4-Q13 -> 14483250 | R20: =R4-R13 -> 22190819 | S20: =S4-S13 -> 29905744 | T20: =T4-T13 -> 37066895 | U20: =U4-U13 -> 44297160 | V20: =V4-V13 -> 51899286 | ... AZ20: =AZ4-AZ13 -> 0
A21: 6 | B21: Allowance for Loan Loss | C21: =C22-C23 -> 0 | D21: -2332648 | E21: 1704002.6 | F21: 986558 | G21: 3036698.4 | H21: 6465591 | I21: 10507808 | J21: 18293579 | K21: 17091213 | L21: 15223049 | M21: 12802966 | N21: 4054260 | O21: =O22-O23 -> 4054259 | P21: =P22-P23 -> 1785150 | Q21: =Q22-Q23 -> 2931641.4 | R21: =R22-R23 -> 2351461.8 | S21: =S22-S23 -> 1933954 | T21: =T22-T23 -> 3140253 | U21: =U22-U23 -> 3994585.3 | V21: =V22-V23 -> 4798428.6 | ... AZ21: =AZ22-AZ23 -> 0
A22: 6.1 | B22: Provision for Loan Losses | D22: 0 | E22: 1704002.6 | F22: 986558 | G22: 3036698.4 | H22: 6465591 | I22: 10507808 | J22: 18293579 | K22: 17091213 | L22: 15223049 | M22: 12802966 | N22: 4054260 | O22: 4054259 | P22: 1785150 | Q22: 2931641.4 | R22: 2351461.8 | S22: 1933954 | T22: 3140253 | U22: 3994585.3 | V22: 4798428.6 | W22: 6610400.5 | X22: 6354946.7 | Y22: 4406712 | Z22: 3333349.8 | AA22: 7274.7 | AB22: 7274 | AC22: 3337481.9 | AD22: 3903958 | AE22: 5627837.9 | AF22: 10754881 | AG22: 13220507 | AH22: 15901849 | AI22: 18236619 | AJ22: 22621894 | AK22: 22621894 | AL22: 18030304 | AM22: 12744223 | AN22: 2838709.7 | AO22: 2838710 | AP22: 2641480 | AQ22: 3389933.2 | AR22: 6873225.2 | AS22: 0 | AT22: 7703647.9 | AU22: 15497452 | AV22: 15865034 | AW22: 18915406 | AX22: 16188609
A23: 6.2 | B23: Value of Loans Recovered | D23: 2332648 | E23: 0 | F23: 0 | G23: 0 | H23: 0 | I23: 0 | J23: 0 | K23: 0 | L23: 0 | M23: 0 | N23: 0 | P23: 0 | Q23: 0 | R23: 0 | S23: 0 | T23: 0 | U23: 0 | V23: 0 | W23: 0 | X23: 0 | Y23: 0 | Z23: 0 | AA23: 0 | AC23: 0 | AD23: 0 | AE23: 0 | AF23: 0 | AG23: 0 | AH23: 0 | AI23: 0 | AJ23: 0 | AK23: 0 | AL23: 0 | AM23: 0 | AN23: 0 | AP23: 0 | AQ23: 0 | AR23: 0 | AS23: 0 | AT23: 0 | AU23: 0 | AV23: 0 | AW23: 0 | AX23: 0
A24: 7 | B24: Operating Expenses | C24: =C25+C26+C27+C28+C29 -> 0 | D24: 3503215.4 | E24: 6597943.7 | F24: 10180087 | G24: 12935662 | H24: 16587792 | I24: 21632046 | J24: 28383589 | K24: 33172918 | L24: 36638896 | M24: 40925953 | N24: 44478898 | O24: =O25+O26+O27+O28+O29 -> 51931717 | P24: =P25+P26+P27+P28+P29 -> 2895377 | Q24: =Q25+Q26+Q27+Q28+Q29 -> 7968668 | R24: =R25+R26+R27+R28+R29 -> 11755147 | S24: =S25+S26+S27+S28+S29 -> 15697600 | T24: =T25+T26+T27+T28+T29 -> 18718932 | U24: =U25+U26+U27+U28+U29 -> 22163548 | V24: =V25+V26+V27+V28+V29 -> 25556710 | ... AZ24: =AZ25+AZ26+AZ27+AZ28+AZ29 -> 0
A25: 7.1 | B25: Personnel Expenses | D25: 2060020.4 | E25: 4180835.7 | F25: 6568707 | G25: 8624245.3 | H25: 10720557 | I25: 12944257 | J25: 17200534 | K25: 19177311 | L25: 21331668 | M25: 23369342 | N25: 25696889 | O25: 24414792 | P25: 1924654 | Q25: 3891667 | R25: 6335046.4 | S25: 8870800.7 | T25: 10952728 | U25: 13308666 | V25: 15372311 | W25: 17503976 | X25: 19549077 | Y25: 22033970 | Z25: 24139660 | AA25: 26740434 | AB25: 26335240 | AC25: 2137831.8 | AD25: 4442398.5 | AE25: 6638180.5 | AF25: 8840832.3 | AG25: 11125134 | AH25: 13786559 | AI25: 16231473 | AJ25: 18420058 | AK25: 23681678 | AL25: 22787840 | AM25: 23131605 | AN25: 28616324 | AO25: 26925110 | AP25: 2087085.7 | AQ25: 4306364.8 | AR25: 6648726 | AS25: 26415523 | AT25: 30150474 | AU25: 13452959 | AV25: 15966126 | AW25: 18432916 | AX25: 20825440
A26: 7.2 | B26: Governance Expenses | D26: 126600 | E26: 265200 | F26: 460330 | G26: 487530 | H26: 517930 | I26: 599330 | J26: 829030 | K26: 888930 | L26: 1158030 | M26: 1195130 | N26: 1369830 | O26: 5182147 | P26: 131900 | Q26: 339900 | R26: 583195 | S26: 738295 | T26: 835724 | U26: 905224 | V26: 1049024 | W26: 1125824 | X26: 1304274 | Y26: 1501474 | Z26: 1731574 | AA26: 2086674 | AB26: 3289284 | AC26: 128900 | AD26: 502243 | AE26: 970610 | AF26: 1042310 | AG26: 1242210 | AH26: 1452610 | AI26: 1621910 | AJ26: 1774110 | AK26: 1923285 | AL26: 2008685 | AM26: 2152785 | AN26: 2379885 | AO26: 5116292 | AP26: 231710 | AQ26: 356610 | AR26: 678946 | AS26: 17108946 | AT26: 18095006 | AU26: 2221311 | AV26: 2481011 | AW26: 2575611 | AX26: 2757011
A27: 7.3 | B27: Marketing Expenses | D27: 289567 | E27: 357930 | F27: 449795 | G27: 501255 | H27: 507575 | I27: 520655 | J27: 550755 | K27: 1557815 | L27: 1578815 | M27: 1589465 | N27: 1601265 | O27: 1601265 | P27: 175342 | Q27: 446512 | R27: 483187 | S27: 561217 | T27: 704172 | U27: 843262 | V27: 878712 | W27: 891812 | X27: 908842 | Y27: 1046352 | Z27: 1087157 | AA27: 1102487 | AC27: 92540 | AD27: 265185 | AE27: 337045 | AF27: 373235 | AG27: 642695 | AH27: 669165 | AI27: 752745 | AJ27: 924625 | AK27: 940775 | AL27: 997585 | AM27: 1046935 | AN27: 1229525 | AP27: 402785 | AQ27: 458130 | AR27: 594130 | AS27: 1424865 | AT27: 1674985 | AU27: 987565 | AV27: 1328220 | AW27: 1566130 | AX27: 1611480
A28: 7.4 | B28: Depreciation and Amortization Charges | D28: 0 | E28: 0 | F28: 0 | G28: 0 | H28: 0 | I28: 0 | J28: 0 | K28: 0 | L28: 0 | M28: 0 | N28: 0 | O28: 5295193.7 | P28: 0 | Q28: 0 | R28: 0 | S28: 0 | T28: 0 | U28: 0 | V28: 0 | W28: 0 | X28: 1070 | Y28: 1070 | Z28: 1070 | AA28: 4775253 | AB28: 4775252 | AC28: 0 | AD28: 0 | AE28: 0 | AF28: 0 | AG28: 0 | AH28: 0 | AI28: 0 | AJ28: 0 | AK28: 0 | AL28: 3300 | AM28: 3300 | AN28: 7093192 | AO28: 7093281 | AP28: 0 | AQ28: 0 | AR28: 0 | AS28: 0 | AT28: 0 | AU28: 0 | AV28: 0 | AW28: 0 | AX28: 0
A29: 7.5 | B29: Administrative Expenses | D29: 1027028 | E29: 1793978 | F29: 2701255 | G29: 3322632 | H29: 4841730 | I29: 7567804 | J29: 9803270 | K29: 11548862 | L29: 12570382 | M29: 14772016 | N29: 15810914 | O29: 15438320 | P29: 663481 | Q29: 3290589 | R29: 4353719 | S29: 5527287 | T29: 6226308 | U29: 7106396 | V29: 8256663 | W29: 9580746 | X29: 10541721 | Y29: 12310724 | Z29: 13285064 | AA29: 15320370 | AB29: 19817876 | AC29: 720931 | AD29: 2852628 | AE29: 4682747 | AF29: 7175936 | AG29: 8806971 | AH29: 9767789 | AI29: 10909011 | AJ29: 12844756 | AK29: 13808792 | AL29: 14835386 | AM29: 15770208 | AN29: 17970358 | AO29: =1468503+20211165 -> 21679668 | AP29: 1525762.5 | AQ29: 4997051.5 | AR29: 7220434 | AS29: 8594216.1 | AT29: 9806488 | AU29: 11958561 | AV29: 13726301 | AW29: 16302228 | AX29: 17833725
A30: 8 | B30: Net Operating Income | C30: =C20-C21-C24 -> 0 | D30: 4639910.9 | E30: 5096379.8 | F30: 9276353 | G30: 10797217 | H30: 10187370 | I30: 7653630.1 | J30: 6591011.7 | K30: 9937114.6 | L30: 15532430 | M30: 20638679 | N30: =N20-N21-N24 -> 46478813 | O30: =O20-O21-O24 -> -53031669 | P30: =P20-P21-P24 -> 2693777 | Q30: =Q20-Q21-Q24 -> 3582940.7 | R30: =R20-R21-R24 -> 8084210.2 | S30: =S20-S21-S24 -> 12274191 | T30: =T20-T21-T24 -> 15207710 | U30: =U20-U21-U24 -> 18139027 | ... AZ30: =AZ20-AZ21-AZ24 -> 0
A31: 9 | B31: Net Non- Operating Income/ (Expense) | C31: 0 | D31: 0 | E31: 0 | F31: 0 | G31: 0 | H31: 0 | I31: 0 | J31: 0 | K31: 0 | L31: 0 | M31: 0 | N31: 0 | O31: 0 | P31: 0 | Q31: 0 | R31: 0 | S31: 0 | T31: 0 | U31: 0 | V31: 0 | W31: 0 | X31: 0 | Y31: 0 | Z31: 0 | AA31: 0 | AB31: 0 | AC31: 0 | AD31: 0 | AE31: 0 | AF31: 0 | AG31: 0 | AH31: 0 | AI31: 0 | AJ31: 0 | AK31: 0 | AL31: 0 | AM31: 0 | AN31: 0 | AO31: 0 | AP31: 0 | AQ31: 0 | AR31: 0 | AS31: 0 | AT31: 0 | AU31: 0 | AV31: 0 | AW31: 0 | AX31: 0 | AY31: 0 | AZ31: 0
A32: 9.1 | B32: Non- Operating Income | C32: 0 | D32: 0 | E32: 0 | F32: 0 | G32: 0 | H32: 0 | I32: 0 | J32: 0 | K32: 0 | L32: 0 | M32: 0 | N32: 0 | O32: 0 | P32: 0 | Q32: 0 | R32: 0 | S32: 0 | T32: 0 | U32: 0 | V32: 0 | W32: 0 | AC32: 0 | AD32: 0 | AE32: 0 | AF32: 0 | AG32: 0 | AH32: 0 | AI32: 0 | AJ32: 0 | AK32: 0 | AL32: 0 | AM32: 0 | AN32: 0 | AP32: 0 | AQ32: 0 | AR32: 0 | AS32: 0 | AT32: 0 | AU32: 0 | AV32: 0 | AW32: 0 | AX32: 0
A33: 9.2 | B33: Non- Operating Expense | C33: 0 | D33: 0 | E33: 0 | F33: 0 | G33: 0 | H33: 0 | I33: 0 | J33: 0 | K33: 0 | L33: 0 | M33: 0 | N33: 0 | O33: 0 | P33: 0 | Q33: 0 | R33: 0 | S33: 0 | T33: 0 | U33: 0 | V33: 0 | W33: 0 | AI33: 0 | AJ33: 0 | AK33: 0 | AL33: 0 | AM33: 0 | AN33: 0 | AP33: 0 | AQ33: 0 | AR33: 0 | AS33: 0 | AT33: 0 | AU33: 0 | AV33: 0 | AW33: 0 | AX33: 0
A34: 10 | B34: Net Income (Before Taxes and Donations) | C34: =C30+C31 -> 0 | D34: 4639910.9 | E34: 5096379.8 | F34: 9276353 | G34: 10797217 | H34: 10187370 | I34: 7653630.1 | J34: 6591011.7 | K34: 9937114.6 | L34: 15532430 | M34: 20638679 | N34: =N30+N31 -> 46478813 | O34: =O30+O31 -> -53031669 | P34: =P30+P31 -> 2693777 | Q34: =Q30+Q31 -> 3582940.7 | R34: =R30+R31 -> 8084210.2 | S34: =S30+S31 -> 12274191 | T34: =T30+T31 -> 15207710 | U34: =U30+U31 -> 18139027 | ... AZ34: =AZ30+AZ31 -> 0
A35: 11 | B35: Taxes (Incomes taxes & Other payable to KRA) | C35: 0 | D35: 0 | E35: 0 | F35: 0 | G35: 0 | H35: 0 | I35: 0 | J35: 0 | K35: 0 | L35: 0 | M35: 0 | N35: 0 | O35: 2502451 | P35: 0 | Q35: 0 | R35: 0 | S35: 0 | T35: 0 | U35: 0 | V35: 0 | W35: 0 | AB35: 2305046 | AC35: 0 | AD35: 0 | AE35: 0 | AF35: 0 | AG35: 0 | AH35: 0 | AI35: 0 | AJ35: 0 | AK35: 0 | AO35: 2148516 | AP35: 0 | AQ35: 0 | AR35: 0 | AS35: 0 | AT35: 0 | AU35: 0 | AV35: 0 | AW35: 0 | AX35: 0
A36: 12 | B36: Net Income (After Taxes before Donations) | C36: =C34-C35 -> 0 | D36: 4639910.9 | E36: 5096379.8 | F36: 9276353 | G36: 10797217 | H36: 10187370 | I36: 7653630.1 | J36: 6591011.7 | K36: 9937114.6 | L36: 15532430 | M36: 20638679 | N36: 46478813 | O36: =O34-O35 -> -55534120 | P36: =P34-P35 -> 2693777 | Q36: =Q34-Q35 -> 3582940.7 | R36: =R34-R35 -> 8084210.2 | S36: =S34-S35 -> 12274191 | T36: =T34-T35 -> 15207710 | U36: =U34-U35 -> 18139027 | V36: =V34-V35 -> 21544147 | ... BA36: =BA34-BA35 -> 0
A37: 13 | B37: Donations | C37: 0 | D37: 0 | E37: 0 | F37: 0 | G37: 0 | H37: 0 | I37: 0 | J37: 0 | K37: 0 | L37: 0 | M37: 0 | N37: 0 | P37: 0 | Q37: 0 | R37: 0 | S37: 0 | T37: 0 | U37: 0 | V37: 0 | W37: 0 | AC37: 0 | AD37: 0 | AE37: 0 | AF37: 0 | AG37: 0 | AH37: 0 | AI37: 0 | AJ37: 0 | AK37: 0 | AP37: 0 | AQ37: 0 | AR37: 0 | AS37: 0 | AT37: 0 | AU37: 0 | AV37: 0 | AW37: 0 | AX37: 0
A38: 14 | B38: Net Income/(After Taxes and Donations) | C38: =C36-C37 -> 0 | D38: 4639910.9 | E38: 5096379.8 | F38: 9276353 | G38: 10797217 | H38: 10187370 | I38: 7653630.1 | J38: 6591011.7 | K38: 9937114.6 | L38: 15532430 | M38: 20638679 | N38: 46478813 | O38: =O36-O37 -> -55534120 | P38: =P36-P37 -> 2693777 | Q38: =Q36-Q37 -> 3582940.7 | R38: =R36-R37 -> 8084210.2 | S38: =S36-S37 -> 12274191 | T38: =T36-T37 -> 15207710 | U38: =U36-U37 -> 18139027 | V38: =V36-V37 -> 21544147 | ... AZ38: =AZ36-AZ37 -> 0
B40: Total expenses | O40: =O35+O24+O13 -> 77441371 | P40: =P35+P24+P13 -> 3254106 | Q40: =Q35+Q24+Q13 -> 8591168.2 | R40: =R35+R24+R13 -> 12476936 | S40: =S35+S24+S13 -> 16286758 | T40: =T35+T24+T13 -> 19462580 | U40: =U35+U24+U13 -> 23060304 | V40: =V35+V24+V13 -> 26667464 | ... AP40: =AP35+AP24+AP13 -> 4487267.4

Sheet Financials
A1: Nyala Vision SACCO FINANCIALS
A3: Year/month | C3: 44216 | D3: 44247 | E3: 44275 | F3: 44306 | G3: 44336 | H3: 44397 | I3: 44428 | J3: 44459 | K3: 44489 | L3: 44520 | M3: 44550 | N3: Aud-20 | O3: 44197 | P3: 44228 | Q3: 44256 | R3: 44287 | S3: 44317 | T3: 44348 | U3: 44378 | V3: 44409 | W3: 44440 | X3: 44470 | Y3: 44501 | Z3: 44531 | AA3: Aud- 21 | AB3: 44562 | AC3: 44593 | AD3: 44621 | AE3: 44652 | AF3: 44682 | AG3: 44713 | AH3: 44743 | AI3: 44774 | AJ3: 44805 | AK3: 44835 | AL3: 44866 | AM3: 44896 | AN3: Audit 2022 | AO3: 44927 | AP3: 44958 | AQ3: 44986 | AR3: 45017 | AS3: 45047 | AT3: 45078 | AU3: 45108 | AV3: 45139 | AW3: 45170 | AX3: 45200 | AY3: 45231 | AZ3: 45261
A4: Membership | N4: 23855 | AA4: 26571 | AN4: 28994
A5: Total Assets | B5: ='[1]Balance Sheet'!C26 -> 0 | C5: =SFP!D26 -> 5.2885982e+08 | D5: =SFP!E26 -> 5.3731704e+08 | E5: =SFP!F26 -> 5.3830702e+08 | F5: =SFP!G26 -> 5.5311245e+08 | G5: =SFP!H26 -> 5.5782172e+08 | H5: =SFP!I26 -> 5.5514722e+08 | I5: =SFP!J26 -> 5.6861874e+08 | J5: =SFP!K26 -> 5.7783377e+08 | ... AZ5: =SFP!BA26 -> 0
A6: Total Deposits | B6: =B7+B8 -> 0 | C6: =C7+C8 -> 4.0264645e+08 | D6: =D7+D8 -> 4.1218761e+08 | E6: =E7+E8 -> 433264927 | F6: =F7+F8 -> 4.4376212e+08 | G6: =G7+G8 -> 4.5425251e+08 | H6: =H7+H8 -> 4.552399e+08 | I6: =I7+I8 -> 4.767731e+08 | ... AZ6: =AZ7+AZ8 -> 0
A7: Deposits-Members(BOSA) | B7: ='[1]Balance Sheet'!C29 -> 0 | C7: =SFP!D29 -> 3.8381101e+08 | D7: =SFP!E29 -> 3.9236899e+08 | E7: =SFP!F29 -> 413115060 | F7: =SFP!G29 -> 4.228648e+08 | G7: =SFP!H29 -> 4.308351e+08 | H7: =SFP!I29 -> 4.3265166e+08 | I7: =SFP!J29 -> 4.4494902e+08 | J7: =SFP!K29 -> 4.4656953e+08 | ... AZ7: =SFP!BA29 -> 0
A8: Deposits-Customers(FOSA) | B8: ='[1]Balance Sheet'!C27 -> 0 | C8: =SFP!D27 -> 18835437 | D8: =SFP!E27 -> 19818619 | E8: =SFP!F27 -> 20149867 | F8: =SFP!G27 -> 20897319 | G8: =SFP!H27 -> 23417410 | H8: =SFP!I27 -> 22588238 | I8: =SFP!J27 -> 31824081 | J8: =SFP!K27 -> 30402672 | ... AZ8: =SFP!BA27 -> 0
A9: Deposits-Term | B9: ='[1]Balance Sheet'!C28 -> 0 | C9: =SFP!D28 -> 2.0246589e+08 | D9: =SFP!E28 -> 2.0507152e+08 | E9: =SFP!F28 -> 209058011 | F9: =SFP!G28 -> 2.1266323e+08 | G9: =SFP!H28 -> 2.1610479e+08 | H9: =SFP!I28 -> 2.2052898e+08 | I9: =SFP!J28 -> 2.2755211e+08 | J9: =SFP!K28 -> 2.3053566e+08 | ... AZ9: =SFP!BA28 -> 0
A10: External Borrowing | B10: ='[1]Balance Sheet'!C37 -> 0 | C10: =SFP!#REF! -> #REF! | D10: =SFP!#REF! -> #REF! | E10: =SFP!#REF! -> #REF! | F10: =SFP!#REF! -> #REF! | G10: =SFP!#REF! -> #REF! | H10: =SFP!#REF! -> #REF! | I10: =SFP!#REF! -> #REF! | J10: =SFP!#REF! -> #REF! | ... M10: =SFP!#REF! -> #REF! | N10: =SFP!O37 -> 0 | O10: =SFP!P37 -> 0 | P10: =SFP!Q37 -> 0 | Q10: =SFP!R37 -> 0 | R10: =SFP!S37 -> 0 | S10: =SFP!T37 -> 0 | T10: =SFP!U37 -> 0 | U10: =SFP!V37 -> 0 | ... AZ10: =SFP!BA37 -> 0
A12: Share capital and Reserves
A13: Core Capital | B13: =B15-B28 -> 0 | C13: =C15-C19 -> 2.2506669e+08 | D13: =D15-D28 -> 2.2656948e+08 | E13: =E15-E28 -> 161531691 | F13: =F15-F28 -> 1.6417548e+08 | G13: =G15-G28 -> 1.8640055e+08 | H13: =H15-H28 -> 1.8140624e+08 | I13: =I15-I28 -> 1.8104213e+08 | J13: =J15-J28 -> 1.8829991e+08 | K13: =K15-K28 -> 2.0000663e+08 | ... Z13: =Z15-Z28 -> 1.9515445e+08 | AA13: =AA15-AA25 -> 151913435 | AB13: =AB15-AB25 -> 1.7264787e+08 | AC13: =AC15-AC25 -> 1.3351581e+08 | AD13: =AD15-AD25 -> 136160930 | AE13: =AE15-AE25 -> 1.3533801e+08 | AF13: =AF15-AF25 -> 1.577709e+08 | AG13: =AG15-AG25 -> 1.6349013e+08 | AH13: =AH15-AH28 -> 1.6653588e+08 | AI13: =AI15-AI28 -> 1.6617934e+08 | AJ13: =AJ15-AJ28 -> 1.6765845e+08 | AK13: =AK15-AK28 -> 1.8021343e+08 | AL13: =AL15-AL28 -> 1.9448545e+08 | AM13: =AM15-AM28 -> 2.1913064e+08 | AN13: =AN15-AN28 -> 184486490 | AO13: =AO15-AO28 -> 1.8784837e+08 | ... AZ13: =AZ15-AZ28 -> 0
A14: Institutional Capital | B14: =B13-B16 -> 0 | C14: =C13-C16 -> 1.5628799e+08 | D14: =D13-D16 -> 1.5733432e+08 | E14: =E13-E16 -> 125022260 | F14: =F13-F16 -> 1.2660061e+08 | G14: =G13-G16 -> 1.4207703e+08 | H14: =H13-H16 -> 1.3961645e+08 | I14: =I13-I16 -> 1.4031496e+08 | ... AZ14: =AZ13-AZ16 -> 0
A15: Total Capital | B15: =B16+B17+B18+B19+B20+B21 -> 0 | C15: =C16+C17+C18+C19+C20+C21 -> 2.2506669e+08 | D15: =D16+D17+D18+D19+D20+D21 -> 2.2656948e+08 | E15: =E16+E17+E18+E19+E20+E21 -> 161531691 | F15: =F16+F17+F18+F19+F20+F21 -> 1.6417548e+08 | G15: =G16+G17+G18+G19+G20+G21 -> 1.8640055e+08 | H15: =H16+H17+H18+H19+H20+H21 -> 1.8140624e+08 | I15: =I16+I17+I18+I19+I20+I21 -> 1.8104213e+08 | ... AZ15: =AZ16+AZ17+AZ18+AZ19+AZ20+AZ21 -> 0
A16: Members Share Capital | B16: ='[1]Balance Sheet'!C39 -> 0 | C16: =SFP!D39 -> 68778694 | D16: =SFP!E39 -> 69235163 | E16: =SFP!F39 -> 36509431 | F16: =SFP!G39 -> 37574873 | G16: =SFP!H39 -> 44323527 | H16: =SFP!I39 -> 41789787 | I16: =SFP!J39 -> 40727169 | J16: =SFP!K39 -> 44073272 | ... AZ16: =SFP!BA39 -> 0
A17: Entrance Fees
A18: Retained Earnings | B18: ='[1]Balance Sheet'!C41 -> 0 | C18: =SFP!D42 -> 14810760 | D18: =SFP!E42 -> 14810760 | E18: =SFP!F42 -> 14810760 | F18: =SFP!G42 -> 14810760 | G18: =SFP!H42 -> 18119348 | H18: =SFP!I42 -> 18119348 | I18: =SFP!J42 -> 18119348 | J18: =SFP!K42 -> 18119348 | ... M18: =SFP!N42 -> 34136157 | N18: =SFP!O41 -> 40458753 | O18: =SFP!P41 -> 77797721 | P18: =SFP!Q41 -> 44041694 | Q18: =SFP!R41 -> 48542963 | R18: =SFP!S41 -> 52732943 | S18: =SFP!T41 -> 55666463 | T18: =SFP!U41 -> 58597780 | U18: =SFP!V41 -> 62002900 | ... Z18: =SFP!AA41 -> 89512024 | AA18: =SFP!AB42 -> 40458752 | AB18: =SFP!AC42 -> 84249920 | AC18: =SFP!AD42 -> 43499944 | AD18: =SFP!AE42 -> 43499944 | AE18: =SFP!AF42 -> 43499944 | AF18: =SFP!AG42 -> 43499944 | AG18: =SFP!AH42 -> 43499944 | AH18: =SFP!AI42 -> 43499944 | ... AZ18: =SFP!BA42 -> 0
A19: Appropriation Account | B19: ='[1]Balance Sheet'!C42 -> 0 | AA19: =SFP!AB43 -> 3041191 | AB19: =SFP!AC43*0.5 -> 677157.3 | AC19: =SFP!AD43*0.5 -> 2161202.6 | AD19: =SFP!AE43*0.5 -> 3086233 | AE19: =SFP!AF43*0.5 -> 1506652.4 | AF19: =SFP!AG43*0.5 -> 2004872.7 | AG19: =SFP!AH43*0.5 -> 2230351.6 | AH19: =SFP!AI43 -> 5166105 | AI19: =SFP!AJ43 -> 4117721.2 | AJ19: =SFP!AK43 -> 5488564.7 | AK19: =SFP!AL43 -> 17921149 | AL19: =SFP!AM43 -> 30279988 | AM19: =SFP!AN43 -> 42720806 | AN19: =SFP!AO43 -> 4521969 | AO19: =SFP!AP43 -> 1995472.9 | ... AZ19: =SFP!BA43 -> 0
A20: Statutory Reserves | B20: ='[1]Balance Sheet'!C45 -> 0 | C20: =SFP!D48 -> 1.4147723e+08 | D20: =SFP!E48 -> 1.4252356e+08 | E20: =SFP!F48 -> 110211500 | F20: =SFP!G48 -> 1.1178985e+08 | G20: =SFP!H48 -> 1.2395768e+08 | H20: =SFP!I48 -> 1.214971e+08 | I20: =SFP!J48 -> 1.2219561e+08 | J20: =SFP!K48 -> 1.2610729e+08 | ... Q20: =SFP!R48 -> 0 | R20: =SFP!S45 -> 18441997 | S20: =SFP!T45 -> 18441997 | T20: =SFP!U45 -> 18441997 | U20: =SFP!V45 -> 24885077 | V20: =SFP!W45 -> 18441997 | W20: =SFP!X45 -> 18441997 | X20: =SFP!Y45 -> 18441997 | Y20: =SFP!Z45 -> 18441997 | ... AA20: =SFP!AB45 -> 21324259 | AB20: =SFP!AC48 -> 0 | AC20: =SFP!AD48 -> 0 | AD20: =SFP!AE48 -> 0 | AE20: =SFP!AF48 -> 0 | AF20: =SFP!AG45 -> 21324259 | AG20: =SFP!AH45 -> 21324259 | AH20: =SFP!AI45 -> 21324259 | AI20: =SFP!AJ45 -> 21324259 | AJ20: =SFP!AK45 -> 21324259 | AK20: =SFP!AL45 -> 21324259 | AL20: =SFP!AM45 -> 21324259 | AM20: =SFP!AN45 -> 21324259 | ... AZ20: =SFP!BA45 -> 0
A21: Capital Reserves | B21: ='[1]Balance Sheet'!C46 -> 0 | C21: =SFP!D49 -> 0 | D21: =SFP!E49 -> 0 | E21: =SFP!F49 -> 0 | F21: =SFP!G49 -> 0 | G21: =SFP!H49 -> 0 | H21: =SFP!I49 -> 0 | I21: =SFP!J49 -> 0 | J21: =SFP!K49 -> 0 | ... M21: =SFP!N49 -> 0 | N21: =SFP!O46 -> 0 | O21: =SFP!P46 -> 2946964 | P21: =SFP!Q46 -> 2946964 | Q21: =SFP!R46 -> 2946964 | R21: =SFP!S46 -> 2946964 | S21: =SFP!T46 -> 2946964 | T21: =SFP!U46 -> 2946964 | U21: =SFP!V46 -> 2946964 | ... AZ21: =SFP!BA46 -> 0
A22: Supplementary Capital & reserves
A23: Proposed Dividends
A24: Benevolent Fund
A25: Investments | B25: =B26+B27+B29 -> 0 | C25: =C26+C27+C29 -> 110000 | D25: =D26+D27+D29 -> 110000 | E25: =E26+E27+E29 -> 110000 | F25: =F26+F27+F29 -> 110000 | G25: =G26+G27+G29 -> 110000 | H25: =H26+H27+H29 -> 110000 | I25: =I26+I27+I29 -> 110000 | ... AZ25: =AZ26+AZ27+AZ29 -> 0
A26: Govt bills | B26: ='[1]Balance Sheet'!C9 -> 0 | C26: =SFP!D9 -> 0 | D26: =SFP!E9 -> 0 | E26: =SFP!F9 -> 0 | F26: =SFP!G9 -> 0 | G26: =SFP!H9 -> 0 | H26: =SFP!I9 -> 0 | I26: =SFP!J9 -> 0 | J26: =SFP!K9 -> 0 | ... AZ26: =SFP!BA9 -> 0
A27: Investments in naccos | B27: ='[1]Balance Sheet'!C12 -> 0 | C27: =SFP!D12 -> 110000 | D27: =SFP!E12 -> 110000 | E27: =SFP!F12 -> 110000 | F27: =SFP!G12 -> 110000 | G27: =SFP!H12 -> 110000 | H27: =SFP!I12 -> 110000 | I27: =SFP!J12 -> 110000 | J27: =SFP!K12 -> 110000 | ... AZ27: =SFP!BA12 -> 0
A28: Equity Investments (at cost) | B28: ='[1]Balance Sheet'!C10 -> 0 | C28: =SFP!D10 -> 0 | D28: =SFP!E10 -> 0 | E28: =SFP!F10 -> 0 | F28: =SFP!G10 -> 0 | G28: =SFP!H10 -> 0 | H28: =SFP!I10 -> 0 | I28: =SFP!J10 -> 0 | J28: =SFP!K10 -> 0 | ... AZ28: =SFP!BA10 -> 0
A29: Deposits in KUSCCO CFP | B29: ='[1]Balance Sheet'!C11 -> 0 | C29: =SFP!D11 -> 0 | D29: =SFP!E11 -> 0 | E29: =SFP!F11 -> 0 | F29: =SFP!G11 -> 0 | G29: =SFP!H11 -> 0 | H29: =SFP!I11 -> 0 | I29: =SFP!J11 -> 0 | J29: =SFP!K11 -> 0 | ... AZ29: =SFP!BA11 -> 0
A30: Net Loans & Advances | B30: =B31-B32 -> 0 | C30: =C31-C32 -> 3.5973342e+08 | D30: =D31-D32 -> 3.6839312e+08 | E30: =E31-E32 -> 367009867 | F30: =F31-F32 -> 3.6420159e+08 | G30: =G31-G32 -> 373764060 | H30: =H31-H32 -> 3.5742929e+08
A31: Gross Loans & advances | B31: ='[1]Balance Sheet'!C14 -> 0 | C31: =SFP!D14 -> 3.7674874e+08 | D31: =SFP!E14 -> 3.8477979e+08 | E31: =SFP!F14 -> 382679093 | F31: =SFP!G14 -> 3.8192096e+08 | G31: =SFP!H14 -> 394912319 | H31: =SFP!I14 -> 3.8261976e+08 | I31: =SFP!J14 -> 4.1182284e+08 | J31: =SFP!K14 -> 4.2207977e+08 | ... AZ31: =SFP!BA14 -> 0
A32: Allowance for loan losses | B32: ='[1]Balance Sheet'!C15 -> 0 | C32: =SFP!D15 -> 17015317 | D32: =SFP!E15 -> 16386671 | E32: =SFP!F15 -> 15669226 | F32: =SFP!G15 -> 17719366 | G32: =SFP!H15 -> 21148259 | H32: =SFP!I15 -> 25190476 | I32: =SFP!J15 -> 32976247 | J32: =SFP!K15 -> 31773881 | ... AZ32: =SFP!BA15 -> 0
A34: Non-Earning Assets | B34: ='[1]Balance Sheet'!C7+'[1]Balance Sheet'!C16+'[1]Balance Sheet'!C20 -> 0 | C34: =SFP!D7+SFP!D16+SFP!D20 -> 40490726 | D34: =SFP!E7+SFP!E16+SFP!E20 -> 42976665 | E34: =SFP!F7+SFP!F16+SFP!F20 -> 43861915 | F34: =SFP!G7+SFP!G16+SFP!G20 -> 41556062 | G34: =SFP!H7+SFP!H16+SFP!H20 -> 44097507 | H34: =SFP!I7+SFP!I16+SFP!I20 -> 43527568 | I34: =SFP!J7+SFP!J16+SFP!J20 -> 50354277 | J34: =SFP!K7+SFP!K16+SFP!K20 -> 46777044 | ... AZ34: =SFP!BA7+SFP!BA16+SFP!BA20 -> 0
A35: Property and Equipment | B35: ='[1]Balance Sheet'!C20 -> 0 | C35: =SFP!D20 -> 26908963 | D35: =SFP!E20 -> 26908963 | E35: =SFP!F20 -> 27794213 | F35: =SFP!G20 -> 27794213 | G35: =SFP!H20 -> 27899223 | H35: =SFP!I20 -> 26884218 | I35: =SFP!J20 -> 32145040 | J35: =SFP!K20 -> 32361040 | ... AZ35: =SFP!BA20 -> 0
A38: Turnover | B38: =B39+B41+B42 -> 0 | C38: =C39+C41+C42 -> 5316371.6 | D38: =D39+D41+D42 -> 10843683 | E38: =E39+E41+E42 -> 16340684 | F38: =F39+F41+F42 -> 21446387 | G38: =G39+G41+G42 -> 26704302 | H38: =H39+H41+H42 -> 32103839
A39: Loan Interest | B39: ='[1]Income Statement'!C6 -> 0 | C39: =SCI!D6 -> 4522149.6 | D39: =SCI!E6 -> 9208162.9 | E39: =SCI!F6 -> 14072634 | F39: =SCI!G6 -> 18817449 | G39: =SCI!H6 -> 23574404 | H39: =SCI!I6 -> 28401575 | I39: =SCI!J6 -> 38200406 | J39: =SCI!K6 -> 43289790 | ... AZ39: =SCI!BA6 -> 0
A40: Yield on loans | B40: ='[1]Income Statement'!C6/'[1]Income Statement'!C14 -> #DIV/0! | C40: =SCI!D6/SCI!D14 -> 19.398626 | D40: =SCI!E6/SCI!E14 -> 32.765415 | E40: =SCI!F6/SCI!F14 -> 37.726522 | F40: =SCI!G6/SCI!G14 -> 47.110638 | G40: =SCI!H6/SCI!H14 -> 50.98808 | H40: =SCI!I6/SCI!I14 -> 46.078758 | I40: =SCI!J6/SCI!J14 -> 46.048263 | J40: =SCI!K6/SCI!K14 -> 48.239219 | ... AZ40: =SCI!BA6/SCI!BA14 -> #DIV/0!
A41: Income from investments | B41: ='[1]Income Statement'!C8 -> 0 | C41: =SCI!D8 -> 93917.85 | D41: =SCI!E8 -> 235212.7 | E41: =SCI!F8 -> 373017 | F41: =SCI!G8 -> 373017 | G41: =SCI!H8 -> 319788.05 | H41: =SCI!I8 -> 410116.75 | I41: =SCI!J8 -> 534966.05 | J41: =SCI!K8 -> 561267.3 | ... AZ41: =SCI!BA8 -> 0
A42: Fees & Commissions | B42: ='[1]Income Statement'!C7 -> 0 | C42: =SCI!D7 -> 700304.2 | D42: =SCI!E7 -> 1400307 | E42: =SCI!F7 -> 1895033 | F42: =SCI!G7 -> 2255920.6 | G42: =SCI!H7 -> 2810109.1 | H42: =SCI!I7 -> 3292148.1 | I42: =SCI!J7 -> 4549071.4 | J42: =SCI!K7 -> 5205437 | ... AZ42: =SCI!BA7 -> 0
A44: Finanacial and Operating costs | B44: =B45+B46+B47+B48 -> 0 | C44: =C45+C46+C47+C48 -> 4873027.9 | D44: =D45+D46+D47+D48 -> 5377412.8 | E44: =E45+E46+E47+E48 -> 9649370 | F44: =F45+F46+F47+F48 -> 11196648 | G44: =G45+G46+G47+G48 -> 10649722 | H44: =H45+H46+H47+H48 -> 8270000.3
A45: Interest expense on deposits | B45: ='[1]Income Statement'!C14 -> 0 | C45: =SCI!D14 -> 233117 | D45: =SCI!E14 -> 281033 | E45: =SCI!F14 -> 373017 | F45: =SCI!G14 -> 399431 | G45: =SCI!H14 -> 462351.29 | H45: =SCI!I14 -> 616370.23 | I45: =SCI!J14 -> 829573.23 | J45: =SCI!K14 -> 897398.23 | ... AZ45: =SCI!BA14 -> 0
A46: Dividend expense on share capital | B46: ='[1]Income Statement'!C16 -> 0 | C46: =SCI!D16 -> 0 | D46: =SCI!E16 -> 0 | E46: =SCI!F16 -> 0 | F46: =SCI!G16 -> 0 | G46: =SCI!H16 -> 0 | H46: =SCI!I16 -> 0 | I46: =SCI!J16 -> 0 | J46: =SCI!K16 -> 0 | ... AZ46: =SCI!BA16 -> 0
A47: Interest expense on borrowed funds | B47: ='[1]Income Statement'!C15 -> 0 | C47: =SCI!D15 -> 0 | D47: =SCI!E15 -> 0 | E47: =SCI!F15 -> 0 | F47: =SCI!G15 -> 0 | G47: =SCI!H15 -> 0 | H47: =SCI!I15 -> 0 | I47: =SCI!J15 -> 0 | J47: =SCI!K15 -> 0 | ... AZ47: =SCI!BA15 -> 0
A48: Operating expenses | B48: ='[1]Income Statement'!C30 -> 0 | C48: =SCI!D30 -> 4639910.9 | D48: =SCI!E30 -> 5096379.8 | E48: =SCI!F30 -> 9276353 | F48: =SCI!G30 -> 10797217 | G48: =SCI!H30 -> 10187370 | H48: =SCI!I30 -> 7653630.1 | I48: =SCI!J30 -> 6591011.7 | J48: =SCI!K30 -> 9937114.6 | ... AZ48: =SCI!BA30 -> 0
A49: Net Surplus | B49: =B38-B44 -> 0 | C49: =C38-C44 -> 443343.74 | D49: =D38-D44 -> 5466269.8 | E49: =E38-E44 -> 6691314 | F49: =F38-F44 -> 10249739 | G49: =G38-G44 -> 16054580 | H49: =H38-H44 -> 23833839

Sheet FORM 4
C2: Audited 2021 | G2: 44621 | K2: 44713 | O2: 44805 | S2: 44896
B3: CLASSIFICATION | C3: NO. OF A/Cs | D3: OUTSTANDING LOAN PORTFOLIO(Kshs) | E3: REQUIRED PROVISION | F3: REQUIRED PROVISION AMOUNT(Kshs) | G3: NO. OF A/Cs | H3: OUTSTANDING LOAN PORTFOLIO(Kshs) | I3: REQUIRED PROVISION | J3: REQUIRED PROVISION AMOUNT(Kshs) | K3: NO. OF A/Cs | L3: OUTSTANDING LOAN PORTFOLIO(Kshs) | M3: REQUIRED PROVISION | N3: REQUIRED PROVISION AMOUNT(Kshs) | O3: NO. OF A/Cs | P3: OUTSTANDING LOAN PORTFOLIO(Kshs) | Q3: REQUIRED PROVISION | R3: REQUIRED PROVISION AMOUNT(Kshs) | S3: NO. OF A/Cs | T3: OUTSTANDING LOAN PORTFOLIO(Kshs) | U3: REQUIRED PROVISION | V3: REQUIRED PROVISION AMOUNT(Kshs)
B4: Performing | E4: 0.01 | F4: =D4*E4 -> 0 | G4: 8972 | H4: 4.1609031e+08 | I4: 0.01 | J4: =H4*I4 -> 4160903.1 | K4: 8308 | L4: 3.5941134e+08 | M4: 0.01 | N4: =L4*M4 -> 3594113.4 | Q4: 0.01 | R4: =P4*Q4 -> 0 | U4: 0.01 | V4: =T4*U4 -> 0
B5: Watch | E5: 0.05 | F5: =D5*E5 -> 0 | G5: 890 | H5: 51709049 | I5: 0.05 | J5: =H5*I5 -> 2585452.5 | K5: 1654 | L5: 1.0012566e+08 | M5: 0.05 | N5: =L5*M5 -> 5006283.1 | Q5: 0.05 | R5: =P5*Q5 -> 0 | U5: 0.05 | V5: =T5*U5 -> 0
B6: Substandard | E6: 0.25 | F6: =D6*E6 -> 0 | G6: 275 | H6: 18285801 | I6: 0.25 | J6: =H6*I6 -> 4571450.2 | K6: 451 | L6: 37276455 | M6: 0.25 | N6: =L6*M6 -> 9319113.8 | Q6: 0.25 | R6: =P6*Q6 -> 0 | U6: 0.25 | V6: =T6*U6 -> 0
B7: Doubtful | E7: 0.5 | F7: =D7*E7 -> 0 | G7: 111 | H7: 5381298.2 | I7: 0.5 | J7: =H7*I7 -> 2690649.1 | K7: 165 | L7: 9852507.5 | M7: 0.5 | N7: =L7*M7 -> 4926253.7 | Q7: 0.5 | R7: =P7*Q7 -> 0 | U7: 0.5 | V7: =T7*U7 -> 0
B8: Loss | E8: 1 | F8: =D8*E8 -> 0 | G8: 59 | H8: 10363585 | I8: 1 | J8: =H8*I8 -> 10363585 | K8: 78 | L8: 11800287 | M8: 1 | N8: =L8*M8 -> 11800287 | Q8: 1 | R8: =P8*Q8 -> 0 | U8: 1 | V8: =T8*U8 -> 0
B9: subtotal | C9: =SUM(C4:C8) -> 0 | D9: =SUM(D4:D8) -> 0 | F9: =SUM(F4:F8) -> 0 | G9: =SUM(G4:G8) -> 10307 | H9: =SUM(H4:H8) -> 5.0183005e+08 | J9: =SUM(J4:J8) -> 24372040 | K9: =SUM(K4:K8) -> 10656 | L9: =SUM(L4:L8) -> 5.1846625e+08 | N9: =SUM(N4:N8) -> 34646051 | O9: =SUM(O4:O8) -> 0 | P9: =SUM(P4:P8) -> 0 | R9: =SUM(R4:R8) -> 0 | S9: =SUM(S4:S8) -> 0 | T9: =SUM(T4:T8) -> 0 | V9: =SUM(V4:V8) -> 0
B10: Reschedule/Renegotiated loans
B11: Performing | C11: 0 | E11: 0.01 | F11: =D11*E11 -> 0 | G11: 0 | I11: 0.01 | J11: =H11*I11 -> 0 | K11: 0 | M11: 0.01 | N11: =L11*M11 -> 0 | O11: 0 | Q11: 0.01 | R11: =P11*Q11 -> 0 | S11: 0 | U11: 0.01 | V11: =T11*U11 -> 0
B12: Watch | C12: 0 | E12: 0.05 | F12: =D12*E12 -> 0 | G12: 0 | I12: 0.05 | J12: =H12*I12 -> 0 | K12: 0 | M12: 0.05 | N12: =L12*M12 -> 0 | O12: 0 | Q12: 0.05 | R12: =P12*Q12 -> 0 | S12: 0 | U12: 0.05 | V12: =T12*U12 -> 0
B13: Substandard | C13: 0 | E13: 0.25 | F13: =D13*E13 -> 0 | G13: 0 | I13: 0.25 | J13: =H13*I13 -> 0 | K13: 0 | M13: 0.25 | N13: =L13*M13 -> 0 | O13: 0 | Q13: 0.25 | R13: =P13*Q13 -> 0 | S13: 0 | U13: 0.25 | V13: =T13*U13 -> 0
B14: Doubtful | C14: 0 | E14: 0.5 | F14: =D14*E14 -> 0 | G14: 0 | I14: 0.5 | J14: =H14*I14 -> 0 | K14: 0 | M14: 0.5 | N14: =L14*M14 -> 0 | O14: 0 | Q14: 0.5 | R14: =P14*Q14 -> 0 | S14: 0 | U14: 0.5 | V14: =T14*U14 -> 0
B15: Loss | C15: 0 | E15: 1 | F15: =D15*E15 -> 0 | G15: 0 | I15: 1 | J15: =H15*I15 -> 0 | K15: 0 | M15: 1 | N15: =L15*M15 -> 0 | O15: 0 | Q15: 1 | R15: =P15*Q15 -> 0 | S15: 0 | U15: 1 | V15: =T15*U15 -> 0
B16: subtotal | C16: =SUM(C10:C15) -> 0 | D16: =SUM(D10:D15) -> 0 | F16: =SUM(F10:F15) -> 0 | G16: =SUM(G10:G15) -> 0 | H16: =SUM(H10:H15) -> 0 | J16: =SUM(J10:J15) -> 0 | K16: =SUM(K10:K15) -> 0 | L16: =SUM(L10:L15) -> 0 | N16: =SUM(N10:N15) -> 0 | O16: =SUM(O10:O15) -> 0 | P16: =SUM(P10:P15) -> 0 | R16: =SUM(R10:R15) -> 0 | S16: =SUM(S10:S15) -> 0 | T16: =SUM(T10:T15) -> 0 | V16: =SUM(V10:V15) -> 0
B17: GRAND TOTAL | C17: =C9+C16 -> 0 | D17: =D9+D16 -> 0 | F17: =F9+F16 -> 0 | G17: =G9+G16 -> 10307 | H17: =H9+H16 -> 5.0183005e+08 | J17: =J9+J16 -> 24372040 | K17: =K9+K16 -> 10656 | L17: =L9+L16 -> 5.1846625e+08 | N17: =N9+N16 -> 34646051 | O17: =O9+O16 -> 0 | P17: =P9+P16 -> 0 | R17: =R9+R16 -> 0 | S17: =S9+S16 -> 0 | T17: =T9+T16 -> 0 | V17: =V9+V16 -> 0
H18: =SUM(H6:H8) -> 34030684 | L18: =SUM(L6:L8) -> 58929250
H19: =H18/H9 -> 0.067813166 | L19: =L18/L17 -> 0.11366073

Sheet CAEL
A1: NYALA SACCO CAELS 2020
C2: Regulatory Stds | E2: 44216 | F2: 44247 | G2: 44275 | H2: 44306 | I2: 44336 | J2: 44367 | K2: 44428 | L2: 44459 | M2: 44489 | N2: 44520 | O2: 44550 | P2: Aud-20 | Q2: 44216 | R2: 44242 | S2: 44270 | T2: 44301 | U2: 44331 | V2: 44362 | W2: 44392 | X2: 44423 | Y2: 44454 | Z2: 44484 | AA2: 44515 | AB2: 44545 | AC2: Audited 2021 | AD2: 44576 | AE2: 44607 | AF2: 44635 | AG2: 44666 | AH2: 44696 | AI2: 44727 | AJ2: 44757 | AK2: 44788 | AL2: 44819 | AM2: 44849 | AN2: 44880 | AO2: 44910 | AP2: Audited 2022 | AQ2: 44941 | AR2: 44972 | AS2: 45000 | AT2: 45031 | AU2: 45061
A3: CAPITAL ADEQUACY | B3: Core Capital | C3: 10 M | D3: =Financials!B14 -> 0 | E3: =Financials!C14 -> 1.5628799e+08 | F3: =Financials!D14 -> 1.5733432e+08 | G3: =Financials!E14 -> 125022260 | H3: =Financials!F14 -> 1.2660061e+08 | I3: =Financials!G14 -> 1.4207703e+08 | J3: =Financials!H14 -> 1.3961645e+08 | K3: =Financials!I14 -> 1.4031496e+08 | ... BG3: =Financials!BE14 -> 0
B4: CCA | C4: 0.1 | D4: =Financials!B13/Financials!B5 -> #DIV/0! | E4: =Financials!C13/Financials!C5 -> 0.42556965 | F4: =Financials!D13/Financials!D5 -> 0.42166815 | G4: =Financials!E13/Financials!E5 -> 0.30007354 | H4: =Financials!F13/Financials!F5 -> 0.29682117 | I4: =Financials!G13/Financials!G5 -> 0.33415794 | J4: =Financials!H13/Financials!H5 -> 0.32677141 | K4: =Financials!I13/Financials!I5 -> 0.31838931 | ... BG4: =Financials!BE13/Financials!BE5 -> #DIV/0!
B5: CCD | C5: 0.08 | D5: =Financials!B13/Financials!B6 -> #DIV/0! | E5: =Financials!C13/Financials!C6 -> 0.55896852 | F5: =Financials!D13/Financials!D6 -> 0.54967563 | G5: =Financials!E13/Financials!E6 -> 0.3728243 | H5: =Financials!F13/Financials!F6 -> 0.36996281 | I5: =Financials!G13/Financials!G6 -> 0.41034568 | J5: =Financials!H13/Financials!H6 -> 0.39848493 | K5: =Financials!I13/Financials!I6 -> 0.37972387 | ... BG5: =Financials!BE13/Financials!BE6 -> #DIV/0!
B6: ICA | C6: 0.08 | D6: =(Financials!B15-Financials!B16)/Financials!B5 -> #DIV/0! | E6: =(Financials!C15-Financials!C16)/Financials!C5 -> 0.29551875 | F6: =(Financials!D15-Financials!D16)/Financials!D5 -> 0.29281468 | G6: =(Financials!E15-Financials!E16)/Financials!E5 -> 0.23225085 | H6: =(Financials!F15-Financials!F16)/Financials!F5 -> 0.22888766 | I6: =(Financials!G15-Financials!G16)/Financials!G5 -> 0.25469971 | J6: =(Financials!H15-Financials!H16)/Financials!H5 -> 0.25149446 | K6: =(Financials!I15-Financials!I16)/Financials!I5 -> 0.24676457 | ... BG6: =(Financials!BE15-Financials!BE16)/Financials!BE5 -> #DIV/0!
A7: ASSET QUALITY | B7: A/LNPL30
B8: NPL30 | D8: =6.5% -> 0.065 | E8: =6.5% -> 0.065 | F8: =6.5% -> 0.065 | G8: =6.5% -> 0.065 | H8: =6.5% -> 0.065 | I8: =6.5% -> 0.065 | J8: =6.5% -> 0.065 | K8: =6.5% -> 0.065 | ... O8: =6.5% -> 0.065 | P8: ='[1]FORM 4'!F22 -> 0.16358978 | Q8: 0 | R8: 1 | S8: 2 | T8: 3 | U8: 4 | V8: 5 | W8: 6 | X8: 7 | Y8: 8 | Z8: 9 | AA8: 10 | AB8: 11 | AC8: 12 | AD8: 13 | AE8: 14 | AF8: 15 | AG8: 16 | AH8: 17 | AI8: 18 | AJ8: 19 | AK8: 20 | AL8: 21 | AM8: 22 | AN8: 23 | AO8: 24 | AP8: 25 | AQ8: 26 | AR8: 27 | AS8: 28 | AT8: 29 | AU8: 30 | AV8: 31 | AW8: 32 | AX8: 33 | AY8: 34 | AZ8: 35 | BA8: 36 | BB8: 37 | BC8: 38 | BD8: 39 | BE8: 40 | BF8: 41 | BG8: 42
B9: Non-earning Asset ratio | C9: Max 10% | D9: =('[1]Balance Sheet'!C7+'[1]Balance Sheet'!C20)/'[1]Balance Sheet'!C26 -> #DIV/0! | E9: =(SFP!D7+SFP!D20)/SFP!D26 -> 0.076562304 | F9: =(SFP!E7+SFP!E20)/SFP!E26 -> 0.079983813 | G9: =(SFP!F7+SFP!F20)/SFP!F26 -> 0.081481224 | H9: =(SFP!G7+SFP!G20)/SFP!G26 -> 0.075131308 | I9: =(SFP!H7+SFP!H20)/SFP!H26 -> 0.079053048 | J9: =(SFP!I7+SFP!I20)/SFP!I26 -> 0.078407253 | K9: =(SFP!J7+SFP!J20)/SFP!J26 -> 0.08855543 | L9: =(SFP!K7+SFP!K20)/SFP!K26 -> 0.080952424 | ... BG9: =(SFP!BF7+SFP!BF20)/SFP!BF26 -> #DIV/0!
B10: Land and Building ratio | C10: Max 5% | D10: =('[1]Balance Sheet'!C22+'[1]Balance Sheet'!C23)/'[1]Balance Sheet'!C26 -> #DIV/0! | E10: =(SFP!D22+SFP!D23)/SFP!D26 -> 0.046972424 | F10: =(SFP!E22+SFP!E23)/SFP!E26 -> 0.046233091 | G10: =(SFP!F22+SFP!F23)/SFP!F26 -> 0.047792572 | H10: =(SFP!G22+SFP!G23)/SFP!G26 -> 0.046513285 | I10: =(SFP!H22+SFP!H23)/SFP!H26 -> 0.046308859 | J10: =(SFP!I22+SFP!I23)/SFP!I26 -> 0.044703606 | K10: =(SFP!J22+SFP!J23)/SFP!J26 -> 0.052896436 | L10: =(SFP!K22+SFP!K23)/SFP!K26 -> 0.052426678 | ... BG10: =(SFP!BF22+SFP!BF23)/SFP!BF26 -> #DIV/0!
A11: EARNINGS | B11: Non-Government Investment to Deposit ratio | C11: Max 5% | D11: ='[1]Balance Sheet'!C12/'[1]Balance Sheet'!C30 -> #DIV/0! | E11: =SFP!D12/SFP!D30 -> 0.00027319253 | F11: =SFP!E12/SFP!E30 -> 0.00026686877 | G11: =SFP!F12/SFP!F30 -> 0.00025388623 | H11: =SFP!G12/SFP!G30 -> 0.00024788055 | I11: =SFP!H12/SFP!H30 -> 0.00024215606 | J11: =SFP!I12/SFP!I30 -> 0.00024163084 | K11: =SFP!J12/SFP!J30 -> 0.00023071771 | L11: =SFP!K12/SFP!K30 -> 0.00023062141 | ... BG11: =SFP!BF12/SFP!BF30 -> #DIV/0!
B12: Non-Government Investment to Core Capital ratio | C12: Max 40% | D12: ='[1]Balance Sheet'!C12/[1]Financials!B13 -> #DIV/0! | E12: =SFP!D12/Financials!C13 -> 0.00048874403 | F12: =SFP!E12/Financials!D13 -> 0.00048550228 | G12: =SFP!F12/Financials!E13 -> 0.00068098092 | H12: =SFP!G12/Financials!F13 -> 0.00067001478 | I12: =SFP!H12/Financials!G13 -> 0.000590127 | J12: =SFP!I12/Financials!H13 -> 0.00060637386 | K12: =SFP!J12/Financials!I13 -> 0.0006075934 | L12: =SFP!K12/Financials!J13 -> 0.00058417446 | ... BG12: =SFP!BF12/Financials!BE13 -> #DIV/0!
B13: Gross loans/TA | D13: =[1]Financials!B31/[1]Financials!B5 -> #DIV/0! | E13: =Financials!C31/Financials!C5 -> 0.71237921 | F13: =Financials!D31/Financials!D5 -> 0.71611313 | G13: =Financials!E31/Financials!E5 -> 0.71089375 | H13: =Financials!F31/Financials!F5 -> 0.69049424 | I13: =Financials!G31/Financials!G5 -> 0.70795437 | J13: =Financials!H31/Financials!H5 -> 0.68922216 | K13: =Financials!I31/Financials!I5 -> 0.72425127 | L13: =Financials!J31/Financials!J5 -> 0.73045189 | ... BG13: =Financials!BE31/Financials!BE5 -> #DIV/0!
B14: ROA | D14: ='[1]Income Statement'!C38/[1]Financials!B5 -> #DIV/0! | E14: =SCI!D38/Financials!C5 -> 0.008773423 | F14: =SCI!E38/Financials!D5 -> 0.0094848653 | G14: =SCI!F38/Financials!E5 -> 0.017232458 | H14: =SCI!G38/Financials!F5 -> 0.019520835 | I14: =SCI!H38/Financials!G5 -> 0.018262771 | J14: =SCI!I38/Financials!H5 -> 0.013786668 | K14: =SCI!J38/Financials!I5 -> 0.011591267 | L14: =SCI!K38/Financials!J5 -> 0.017197186 | ... BG14: =SCI!BF38/Financials!BE5 -> #DIV/0!
B15: Cost Income ratio | D15: ='[1]Income Statement'!C24/('[1]Income Statement'!C20-'[1]Income Statement'!C22) -> #DIV/0! | E15: =SCI!D24/(SCI!D20-SCI!D22) -> 0.60291343 | F15: =SCI!E24/(SCI!E20-SCI!E22) -> 0.56420055 | G15: =SCI!F24/(SCI!F20-SCI!F22) -> 0.52322455 | H15: =SCI!G24/(SCI!G20-SCI!G22) -> 0.54505238 | I15: =SCI!H24/(SCI!H20-SCI!H22) -> 0.61952162 | J15: =SCI!I24/(SCI!I20-SCI!I22) -> 0.73865619 | K15: =SCI!J24/(SCI!J20-SCI!J22) -> 0.81154862 | L15: =SCI!K24/(SCI!K20-SCI!K22) -> 0.76949416 | ... BG15: =SCI!BF24/(SCI!BF20-SCI!BF22) -> #DIV/0!
B16: Operating Expense ratio | D16: ='[1]Income Statement'!C24/'[1]Income Statement'!C4 -> #DIV/0! | E16: =SCI!D24/SCI!D4 -> 0.57965751 | F16: =SCI!E24/SCI!E4 -> 0.48232842 | G16: =SCI!F24/SCI!F4 -> 0.48772795 | H16: =SCI!G24/SCI!G4 -> 0.47513102 | I16: =SCI!H24/SCI!H4 -> 0.49131602 | J16: =SCI!I24/SCI!I4 -> 0.53342716 | K16: =SCI!J24/SCI!J4 -> 0.52328805 | L16: =SCI!K24/SCI!K4 -> 0.54155658 | ... BG16: =SCI!BF24/SCI!BF4 -> #DIV/0!
A17: LIQUIDITY | B17: MIN LIQ ratio | C17: Min 15% | D17: ='[1]Balance Sheet'!C5/'[1]Balance Sheet'!C28 -> #DIV/0! | E17: =SFP!D5/SFP!D28 -> 0.052877469 | F17: =SFP!E5/SFP!E28 -> 0.053447739 | G17: =SFP!F5/SFP!F28 -> 0.054578707 | H17: =SFP!G5/SFP!G28 -> 0.054494525 | I17: =SFP!H5/SFP!H28 -> 0.065724192 | J17: =SFP!I5/SFP!I28 -> 0.080537382 | K17: =SFP!J5/SFP!J28 -> 0.055305816 | L17: =SFP!K5/SFP!K28 -> 0.064009738 | ... P17: =SFP!O5/SFP!O28 -> #DIV/0! | Q17: =SFP!P5/SFP!P29 -> 0.036689409 | R17: =SFP!Q5/SFP!Q29 -> 0.040310794 | S17: =SFP!R5/SFP!R29 -> 0.058309863 | T17: =SFP!S5/SFP!S29 -> 0.1052195 | U17: =SFP!T5/SFP!T29 -> 0.079513948 | V17: =SFP!U5/SFP!U29 -> 0.095694632 | W17: =SFP!V5/SFP!V29 -> 0.061894015 | X17: =SFP!W5/SFP!W29 -> 0.079983978 | ... BG17: =SFP!BF5/SFP!BF29 -> #DIV/0!
B18: Technical LIQ ratio | D18: ='[1]Balance Sheet'!C5/'[1]Balance Sheet'!C30 -> #DIV/0! | E18: =SFP!D5/SFP!D30 -> 0.026588796 | F18: =SFP!E5/SFP!E30 -> 0.026591311 | G18: =SFP!F5/SFP!F30 -> 0.026335194 | H18: =SFP!G5/SFP!G30 -> 0.026115302 | I18: =SFP!H5/SFP!H30 -> 0.03126744 | J18: =SFP!I5/SFP!I30 -> 0.039014214 | K18: =SFP!J5/SFP!J30 -> 0.02639611 | L18: =SFP!K5/SFP!K30 -> 0.030937918 | ... BG18: =SFP!BF5/SFP!BF30 -> #DIV/0!

Sheet Performance Tool
A1: NYALA VISION SACCO SOCIETY LIMITED
A2: PERFORMANCE AND COMPLIANCE REPORT AS AT : 31st March , 2023
B3: Prudential Standard | C3: Audited | D3: Audited 2021
C4: 2020 | E4: 44562 | F4: 44593 | G4: 44621 | H4: 44652 | I4: 44682 | J4: 44713 | K4: 44743 | L4: 44774 | M4: 44805 | N4: 44835 | O4: 44866 | P4: 44896 | Q4: Audit 2022 | R4: 44927 | S4: 44958 | T4: 44986 | U4: 45017 | V4: 45047 | W4: 45078 | X4: 45108 | Y4: 45139 | Z4: 45170 | AA4: 45200 | AB4: 45231 | AC4: 45261
A5: A. CAPITAL ADEQUACY
A6: Core Capital | B6: ≥10M | C6: =C34 -> 1.2448559e+08 | D6: =D34 -> 152023435 | E6: =E34 -> 1.7264787e+08 | F6: =F34 -> 1.3351581e+08 | G6: =G34 -> 136160930 | H6: =H34 -> 1.3533801e+08 | I6: =I34 -> 1.577709e+08 | J6: =J34 -> 1.6349013e+08 | ... AC6: =AC34 -> 0
A7: Core Capital/Total Assets | B7: ≥10% | C7: =C34/C30 -> 0.20226121 | D7: =D34/D30 -> 0.21698806 | E7: =E34/E30 -> 0.24374963 | F7: =F34/F30 -> 0.18998584 | G7: =G34/G30 -> 0.1948893 | H7: =H34/H30 -> 0.19188406 | I7: =I34/I30 -> 0.22248578 | J7: =J34/J30 -> 0.23160495 | ... AC7: =AC34/AC30 -> #DIV/0!
A8: Core Capital/Total Deposits | D8: =D34/D32 -> 0.29807574 | E8: =E34/E32 -> 0.35596983 | F8: =F34/F32 -> 0.26059315 | G8: =G34/G32 -> 0.26983448 | H8: =H34/H32 -> 0.26404647 | I8: =I34/I32 -> 0.30625377 | J8: =J34/J32 -> 0.32214317 | K8: =K34/K32 -> 0.3331363 | ... AC8: =AC34/AC32 -> #DIV/0!
A9: Institutional Capital/Total Assets | B9: ≥8% | C9: =C35/C30 -> 0.095700526 | D9: =D35/D30 -> 0.096732017 | E9: =E35/E30 -> 0.123908 | F9: =F35/F30 -> 0.069010213 | G9: =G35/G30 -> 0.070740127 | H9: =H35/H30 -> 0.067833244 | I9: =I35/I30 -> 0.098241841 | J9: =J35/J30 -> 0.099010393 | ... AC9: =AC35/AC30 -> #DIV/0!
A10: B. ASSET QUALITY
A11: NPL (Substandard+Doubtful+Loss) | B11: <5% | C11: =C36/C33 -> 0 | D11: =D36/D33 -> 0.040754248 | E11: =E36/E33 -> 0 | F11: =F36/F33 -> 0 | G11: =G36/G33 -> 0.067813166 | H11: =H36/H33 -> 0 | I11: =I36/I33 -> 0 | J11: =J36/J33 -> 0.11366073 | ... AC11: =AC36/AC33 -> #DIV/0!
A12: Non-Earning Assets | B12: <10% | C12: =C37/C30 -> 0.070614823 | D12: =D37/D30 -> 0.078719861 | E12: =E37/E30 -> 0.080361961 | F12: =F37/F30 -> 0.082385734 | G12: =G37/G30 -> 0.084723983 | H12: =H37/H30 -> 0.084998516 | I12: =I37/I30 -> 0.087601567 | J12: =J37/J30 -> 0.091269829 | ... AC12: =AC37/AC30 -> #DIV/0!
A13: Equity investments/Deposits | B13: <5% | C13: =C39/C32 -> 0 | D13: =D39/D32 -> 0.00021567946 | E13: =E39/E32 -> 0 | F13: =F39/F32 -> 0 | G13: =G39/G32 -> 0 | H13: =H39/H32 -> 0 | I13: =I39/I32 -> 0 | J13: =J39/J32 -> 0 | ... AC13: =AC39/AC32 -> #DIV/0!
A14: Equity investments/Core capital | B14: <40% | C14: =C39/C34 -> 0 | D14: =D39/D34 -> 0.00072357265 | E14: =E39/E34 -> 0 | F14: =F39/F34 -> 0 | G14: =G39/G34 -> 0 | H14: =H39/H34 -> 0 | I14: =I39/I34 -> 0 | J14: =J39/J34 -> 0 | ... AC14: =AC39/AC34 -> #DIV/0!
A15: C. EARNINGS RATING
A16: Yield on Gross Loans | C16: =C49/C33 -> 0.16213195 | D16: =D49/D33 -> 0.15614957 | E16: =E49/E33 -> 0.0026447778 | F16: =F49/F33 -> 0.0060332774 | G16: =G49/G33 -> 0.0088224589 | H16: =H49/H33 -> 0.010786818 | I16: =I49/I33 -> 0.012601846 | J16: =J49/J33 -> 0.015755569 | ... AC16: =AC49/AC33 -> #DIV/0!
A17: Total Expense/Total Income | C17: =C50/C45 -> 0.77835078 | D17: =D50/D45 -> 0.84795499 | E17: =E50/E45 -> 0.42684249 | F17: =F50/F45 -> 0.50949526 | G17: =G50/G45 -> 0.53066392 | H17: =H50/H45 -> 0.56954361 | I17: =I50/I45 -> 0.5685216 | J17: =J50/J45 -> 0.56805603 | ... AC17: =AC50/AC45 -> #DIV/0!
A18: Net Income/Average Assets (ROA) | C18: =C51/C31 -> 0.028375656 | D18: =D51/D31 -> 0.021900407 | E18: =E51/E31 -> 0.0019225033 | F18: =F51/F31 -> 0.0061264343 | G18: =G51/G31 -> 0.0088088428 | H18: =H51/H31 -> 0.0042925511 | I18: =I51/I31 -> 0.0056697309 | J18: =J51/J31 -> 0.0063047525 | ... AC18: =AC51/AC31 -> #DIV/0!
A19: Operating Expenses/Financial Income (OPEX) | C19: =C48/C45 -> 0.53076203 | D19: =D48/D45 -> 0.5247874 | E19: =E48/E45 -> 0.3762826 | F19: =F48/F45 -> 0.48073152 | G19: =G48/G45 -> 0.50227939 | H19: =H48/H45 -> 0.54501375 | I19: =I48/I45 -> 0.54633956 | J19: =J48/J45 -> 0.54465895 | ... AC19: =AC48/AC45 -> #DIV/0!
A20: D. LIQUIDITY
A21: Liquid Assets/Short-term Liabilities | B21: >15% | C21: =C41/C42 -> 0.19372841 | D21: =D41/D42 -> 0.61961763 | E21: =E41/E42 -> 0.74686167 | F21: =F41/F42 -> 0.65769906 | G21: =G41/G42 -> 0.6552977 | H21: =H41/H42 -> 0.63841951 | I21: =I41/I42 -> 0.62302122 | J21: =J41/J42 -> 0.64985628 | ... AC21: =AC41/AC42 -> #DIV/0!
A22: External Borrowing/Total Assets | B22: <25% | C22: =C43/C30 -> 0 | D22: =D43/D30 -> 0 | E22: =E43/E30 -> 0 | F22: =F43/F30 -> 0 | G22: =G43/G30 -> 0 | H22: =H43/H30 -> 0 | I22: =I43/I30 -> 0 | J22: =J43/J30 -> 0 | ... AC22: =AC43/AC30 -> #DIV/0!
A23: Liquid Assets/Total Assets | C23: =C41/C30 -> 0.078364706 | D23: =D41/D30 -> 0.24093406 | E23: =E41/E30 -> 0.24841154 | F23: =F41/F30 -> 0.24213466 | G23: =G41/G30 -> 0.23172534 | H23: =H41/H30 -> 0.22742739 | I23: =I41/I30 -> 0.21888273 | J23: =J41/J30 -> 0.22318034 | ... AC23: =AC41/AC30 -> #DIV/0!
A24: E. STRUCTURE/SENSITIVITY TO RISK
A25: Gross loans /Total Assets | B25: 70-80 | C25: =C33/C30 -> 0.72035429 | D25: =D33/D30 -> 0.70694329 | E25: =E33/E30 -> 0.7022468 | F25: =F33/F30 -> 0.7075502 | G25: =G33/G30 -> 0.71827732 | H25: =H33/H30 -> 0.72924233 | I25: =I33/I30 -> 0.73843666 | J25: =J33/J30 -> 0.73447462 | ... AC25: =AC33/AC30 -> #DIV/0!
A26: Gross loans/Deposits | B26: >100% | C26: =C33/C32 -> 0.9692818 | D26: =D33/D32 -> 0.97112555 | E26: =E33/E32 -> 1.0255551 | F26: =F33/F32 -> 0.97050778 | G26: =G33/G32 -> 0.9944927 | H26: =H33/H32 -> 1.0034907 | I26: =I33/I32 -> 1.016465 | J26: =J33/J32 -> 1.0215929 | ... AC26: =AC33/AC32 -> #DIV/0!
A27: Financial Investments/Total Assets | C27: =C40/C32 -> 0.21678291 | D27: =D40/D32 -> 0.00021567946 | E27: =E40/E32 -> 0.00022680083 | F27: =F40/F32 -> 0.00021469553 | G27: =G40/G32 -> 0.00021799053 | H27: =H40/H32 -> 0.00021461163 | I27: =I40/I32 -> 0.00021352426 | J27: =J40/J32 -> 0.00021674549 | ... AC27: =AC40/AC32 -> #DIV/0!
A28: Dividends+Interest on Deposits/Total Income | C28: =C47/C45 -> 0.2226961 | D28: =D47/D45 -> 0.35060046 | E28: =E47/E45 -> 0.050559889 | F28: =F47/F45 -> 0.028763738 | G28: =G47/G45 -> 0.028355959 | H28: =H47/H45 -> 0.02430637 | I28: =I47/I45 -> 0.020997701 | J28: =J47/J45 -> 0.022393836 | ... AC28: =AC47/AC45 -> #DIV/0!
A29: F. KEY FINANCIAL STATISTICS
A30: Total Assets | C30: 6.1546945e+08 | D30: 700607388 | E30: =Financials!AB5 -> 7.0830003e+08 | F30: =Financials!AC5 -> 7.0276715e+08 | G30: =Financials!AD5 -> 6.9865779e+08 | H30: =Financials!AE5 -> 7.053114e+08 | I30: =Financials!AF5 -> 7.0912799e+08 | J30: =Financials!AG5 -> 7.0590083e+08 | K30: =Financials!AH5 -> 7.0039408e+08 | L30: =Financials!AI5 -> 6.9101525e+08 | ... AC30: =Financials!AZ5 -> 0
A31: Average Assets | C31: 5.7612987e+08 | D31: =(D30+C30)/2 -> 6.5803842e+08 | E31: =(E30+D30)/2 -> 7.0445371e+08 | F31: =(F30+E30)/2 -> 7.0553359e+08 | G31: =(G30+F30)/2 -> 7.0071247e+08 | H31: =(H30+G30)/2 -> 7.019846e+08 | I31: =(I30+H30)/2 -> 7.072197e+08 | J31: =(J30+I30)/2 -> 7.0751441e+08 | K31: =(K30+J30)/2 -> 7.0314745e+08 | ... AC31: =(AC30+AB30)/2 -> 0
A32: Total Deposits | C32: 4.5740677e+08 | D32: 510016123 | E32: =Financials!AB6 -> 4.8500703e+08 | F32: =Financials!AC6 -> 5.1235348e+08 | G32: =Financials!AD6 -> 5.0460908e+08 | H32: =Financials!AE6 -> 512553769 | I32: =Financials!AF6 -> 5.1516394e+08 | J32: =Financials!AG6 -> 5.0750766e+08 | K32: =Financials!AH6 -> 4.9990313e+08 | L32: =Financials!AI6 -> 4.9059374e+08 | ... AC32: =Financials!AZ6 -> 0
A33: Gross Loans | C33: 443356055 | D33: 4.9528969e+08 | E33: =SFP!AC14 -> 4.9740143e+08 | F33: =SFP!AD14 -> 4.9724304e+08 | G33: =SFP!AE14 -> 5.0183005e+08 | H33: =SFP!AF14 -> 5.1434293e+08 | I33: =SFP!AG14 -> 5.236461e+08 | J33: =SFP!AH14 -> 5.1846625e+08 | K33: =SFP!AI14 -> 5.1953845e+08 | L33: =SFP!AJ14 -> 5.1103564e+08 | ... AC33: =SFP!BA14 -> 0
A34: Core Capital | C34: 1.2448559e+08 | D34: 152023435 | E34: =Financials!AB13 -> 1.7264787e+08 | F34: =Financials!AC13 -> 1.3351581e+08 | G34: =Financials!AD13 -> 136160930 | H34: =Financials!AE13 -> 1.3533801e+08 | I34: =Financials!AF13 -> 1.577709e+08 | J34: =Financials!AG13 -> 1.6349013e+08 | K34: =Financials!AH13 -> 1.6653588e+08 | L34: =Financials!AI13 -> 1.6617934e+08 | ... AC34: =Financials!AZ13 -> 0
A35: Institutional Capital | C35: 58900750 | D35: 67771166 | E35: =Financials!AB14 -> 87764041 | F35: =Financials!AC14 -> 48498111 | G35: =Financials!AD14 -> 49423141 | H35: =Financials!AE14 -> 47843560 | I35: =Financials!AF14 -> 69666040 | J35: =Financials!AG14 -> 69891519 | K35: =Financials!AH14 -> 72937272 | L35: =Financials!AI14 -> 71888888 | ... AC35: =Financials!AZ14 -> 0
A36: Non-performing Loans | C36: 0 | D36: =6183609.4+6802169.91+7199379.52 -> 20185159 | E36: 0 | F36: 0 | G36: 34030684 | H36: 0 | I36: 0 | J36: 58929250 | K36: 0 | L36: 0 | M36: 0 | N36: 0 | O36: 0 | P36: 0 | Q36: 21887303 | T36: 40441961 | U36: 40441962 | V36: 40441963 | W36: 40441964 | X36: 40441965 | Y36: 40441966 | Z36: 40441967 | AA36: 40441968 | AB36: 40441969 | AC36: 40441970
A37: Non-Earning Assets | C37: 43461266 | D37: 55151716 | E37: =Financials!AB34 -> 56920380 | F37: =Financials!AC34 -> 57897988 | G37: =Financials!AD34 -> 59193071 | H37: =Financials!AE34 -> 59950423 | I37: =Financials!AF34 -> 62120723 | J37: =Financials!AG34 -> 64427448 | K37: =Financials!AH34 -> 70088233 | L37: =Financials!AI34 -> 68767886 | ... AC37: =Financials!AZ34 -> 0
A38: Property and Equipment | C38: 29969037 | D38: 35062305 | E38: =Financials!AB35 -> 36004432 | F38: =Financials!AC35 -> 36004432 | G38: =Financials!AD35 -> 36004432 | H38: =Financials!AE35 -> 36004432 | I38: =Financials!AF35 -> 35555120 | J38: =Financials!AG35 -> 35945120 | K38: =Financials!AH35 -> 35945120 | L38: =Financials!AI35 -> 35945120 | ... AC38: =Financials!AZ35 -> 0
A39: Equity Investments | C39: 0 | D39: 110000 | E39: =Financials!AB28 -> 0 | F39: =Financials!AC28 -> 0 | G39: =Financials!AD28 -> 0 | H39: =Financials!AE28 -> 0 | I39: =Financials!AF28 -> 0 | J39: =Financials!AG28 -> 0 | K39: =Financials!AH28 -> 0 | L39: =Financials!AI28 -> 0 | ... AC39: =Financials!AZ28 -> 0
A40: Financial Investments | C40: 99157972 | D40: 110000 | E40: =Financials!AB25 -> 110000 | F40: =Financials!AC25 -> 110000 | G40: =Financials!AD25 -> 110000 | H40: =Financials!AE25 -> 110000 | I40: =Financials!AF25 -> 110000 | J40: =Financials!AG25 -> 110000 | K40: =Financials!AH25 -> 110000 | L40: =Financials!AI25 -> 110000 | ... AC40: =Financials!AZ25 -> 0
A41: Liquid Assets | C41: 48231082 | D41: 168800184 | E41: =SFP!AC4 -> 1.759499e+08 | F41: =SFP!AD4 -> 1.7016428e+08 | G41: =SFP!AE4 -> 1.6189671e+08 | H41: =SFP!AF4 -> 1.6040713e+08 | I41: =SFP!AG4 -> 1.5521587e+08 | J41: =SFP!AH4 -> 1.5754319e+08 | K41: =SFP!AI4 -> 1.4763821e+08 | L41: =SFP!AJ4 -> 1.5246782e+08 | ... AC41: =SFP!BA4 -> 0
A42: Short-term Liabilities) | C42: 2.4896236e+08 | D42: 272426375 | E42: =SFP!AC27+SFP!AC28+SFP!AC32+SFP!AC35+SFP!AC36 -> 2.3558567e+08 | F42: =SFP!AD27+SFP!AD28+SFP!AD32+SFP!AD35+SFP!AD36 -> 2.5872666e+08 | G42: =SFP!AE27+SFP!AE28+SFP!AE32+SFP!AE35+SFP!AE36 -> 2.4705827e+08 | H42: =SFP!AF27+SFP!AF28+SFP!AF32+SFP!AF35+SFP!AF36 -> 2.5125663e+08 | I42: =SFP!AG27+SFP!AG28+SFP!AG32+SFP!AG35+SFP!AG36 -> 2.4913417e+08 | J42: =SFP!AH27+SFP!AH28+SFP!AH32+SFP!AH35+SFP!AH36 -> 2.4242774e+08 | K42: =SFP!AI27+SFP!AI28+SFP!AI32+SFP!AI35+SFP!AI36 -> 2.3537452e+08 | L42: =SFP!AJ27+SFP!AJ28+SFP!AJ32+SFP!AJ35+SFP!AJ36 -> 2.2311972e+08 | ... AC42: =SFP!BA27+SFP!BA28+SFP!BA32+SFP!BA35+SFP!BA36 -> 0
A43: External Borrowing | C43: 0 | D43: 0 | E43: =SFP!AC37 -> 0 | F43: =SFP!AD37 -> 0 | G43: =SFP!AE37 -> 0 | H43: =SFP!AF37 -> 0 | I43: =SFP!AG37 -> 0 | J43: =SFP!AH37 -> 0 | K43: =SFP!AI37 -> 0 | L43: =SFP!AJ37 -> 0 | ... AC43: =SFP!BA37 -> 0
A44: Average Gross Loans | C44: 4.0572974e+08 | D44: =(D33+C33)/2 -> 4.6932287e+08 | E44: =(E33+D33)/2 -> 4.9634556e+08 | F44: =(F33+E33)/2 -> 4.9732223e+08 | G44: =(G33+F33)/2 -> 4.9953654e+08 | H44: =(H33+G33)/2 -> 5.0808649e+08 | I44: =(I33+H33)/2 -> 5.1899452e+08 | J44: =(J33+I33)/2 -> 5.2105618e+08 | K44: =(K33+J33)/2 -> 5.1900235e+08 | ... AC44: =(AC33+AB33)/2 -> 0
A45: Total Income | C45: 97843694 | D45: 101408021 | E45: =SCI!AC31+SCI!AC4 -> 8185876.3 | F45: =SCI!AD31+SCI!AD4 -> 16771221 | G45: =SCI!AE31+SCI!AE4 -> 25142546 | H45: =SCI!AF31+SCI!AF4 -> 31985089 | I45: =SCI!AG31+SCI!AG4 -> 39933059 | J45: =SCI!AH31+SCI!AH4 -> 47141652 | K45: =SCI!AI31+SCI!AI4 -> 54225704 | L45: =SCI!AJ31+SCI!AJ4 -> 62127657 | ... AC45: =SCI!BA31+SCI!BA4 -> 0
A46: Net Financial Income/Loss | C46: 74836490 | D46: 70941281 | E46: =SCI!AC20 -> 7771999.3 | F46: =SCI!AD20 -> 16288818 | G46: =SCI!AE20 -> 24428886 | H46: =SCI!AF20 -> 31200499 | I46: =SCI!AG20 -> 39047262 | J46: =SCI!AH20 -> 46038675 | K46: =SCI!AI20 -> 52917863 | L46: =SCI!AJ20 -> 60703164 | ... AC46: =SCI!BA20 -> 0
A47: Dividends+Interest on Deposits | C47: 21789409 | D47: 35553699 | E47: =SCI!AC14 -> 413877 | F47: =SCI!AD14 -> 482403 | G47: =SCI!AE14 -> 712941 | H47: =SCI!AF14 -> 777441.41 | I47: =SCI!AG14 -> 838502.41 | J47: =SCI!AH14 -> 1055682.4 | K47: =SCI!AI14 -> 1223585.4 | L47: =SCI!AJ14 -> 1299215.4 | ... AC47: =SCI!BA14 -> 0
A48: Operating Expenses | C48: 51931717 | D48: 53217652 | E48: =SCI!AC24 -> 3080202.8 | F48: =SCI!AD24 -> 8062454.5 | G48: =SCI!AE24 -> 12628582 | H48: =SCI!AF24 -> 17432313 | I48: =SCI!AG24 -> 21817010 | J48: =SCI!AH24 -> 25676123 | K48: =SCI!AI24 -> 29515139 | L48: =SCI!AJ24 -> 33963549 | ... AC48: =SCI!BA24 -> 0
A49: Interest on Loan portfolio+Fees&Commission on Loan | C49: 71882183 | D49: 77339274 | E49: =SCI!AC8 -> 1315516.3 | F49: =SCI!AD8 -> 3000005.2 | G49: =SCI!AE8 -> 4427375 | H49: =SCI!AF8 -> 5548123.5 | I49: =SCI!AG8 -> 6598907.5 | J49: =SCI!AH8 -> 8168730.7 | K49: =SCI!AI8 -> 8513008.2 | L49: =SCI!AJ8 -> 9480221.4 | ... AC49: =SCI!BA8 -> 0
A50: Total Expenses | C50: 76156715 | D50: 85989438 | E50: =SCI!AC40 -> 3494079.8 | F50: =SCI!AD40 -> 8544857.5 | G50: =SCI!AE40 -> 13342242 | H50: =SCI!AF40 -> 18216903 | I50: =SCI!AG40 -> 22702807 | J50: =SCI!AH40 -> 26779100 | K50: =SCI!AI40 -> 30822981 | L50: =SCI!AJ40 -> 35388042 | ... AC50: =SCI!BA40 -> 0
A51: Net Income | C51: 16348063 | D51: 14411309 | E51: =SCI!AC38 -> 1354314.6 | F51: =SCI!AD38 -> 4322405.2 | G51: =SCI!AE38 -> 6172466 | H51: =SCI!AF38 -> 3013304.8 | I51: =SCI!AG38 -> 4009745.4 | J51: =SCI!AH38 -> 4460703.2 | K51: =SCI!AI38 -> 5166104.9 | L51: =SCI!AJ38 -> 4117721.2 | ... AC51: =SCI!BA38 -> 0
A52: G. AREAS OF IMPROVEMENT/REGULATORY CONCERNS
A53: 1
A54: 2
A55: 3
A56: 4
A57: DISCLAIMER: This report is prepared based on information submitted by the Sacco as at the stated date and may change upon verification by the Authority.

Sheet Graphical Analysis
A1: Accounts | B1: Audit 2020 | C1: Audit 2021 | D1: 44562 | E1: 44593 | F1: 44621 | G1: 44652 | H1: 44682 | I1: 44713 | J1: 44743 | K1: 44774 | L1: 44805 | M1: 44835 | N1: 44866 | O1: 44896
A2: Assets | B2: ='Performance Tool'!C30/1000000 -> 615.46945 | C2: ='Performance Tool'!D30/1000000 -> 700.60739 | D2: ='Performance Tool'!E30/1000000 -> 708.30003 | E2: ='Performance Tool'!F30/1000000 -> 702.76715 | F2: ='Performance Tool'!G30/1000000 -> 698.65779 | G2: ='Performance Tool'!H30/1000000 -> 705.3114 | H2: ='Performance Tool'!I30/1000000 -> 709.12799 | I2: ='Performance Tool'!J30/1000000 -> 705.90083 | ... O2: ='Performance Tool'!P30/1000000 -> 756.72473
A3: Deposits | B3: ='Performance Tool'!C32/1000000 -> 457.40677 | C3: ='Performance Tool'!D32/1000000 -> 510.01612 | D3: ='Performance Tool'!E32/1000000 -> 485.00703 | E3: ='Performance Tool'!F32/1000000 -> 512.35348 | F3: ='Performance Tool'!G32/1000000 -> 504.60908 | G3: ='Performance Tool'!H32/1000000 -> 512.55377 | H3: ='Performance Tool'!I32/1000000 -> 515.16394 | I3: ='Performance Tool'!J32/1000000 -> 507.50766 | ... O3: ='Performance Tool'!P32/1000000 -> 503.39433
A4: Gross Loans | B4: ='Performance Tool'!C33/1000000 -> 443.35606 | C4: ='Performance Tool'!D33/1000000 -> 495.28969 | D4: ='Performance Tool'!E33/1000000 -> 497.40143 | E4: ='Performance Tool'!F33/1000000 -> 497.24304 | F4: ='Performance Tool'!G33/1000000 -> 501.83005 | G4: ='Performance Tool'!H33/1000000 -> 514.34293 | H4: ='Performance Tool'!I33/1000000 -> 523.6461 | I4: ='Performance Tool'!J33/1000000 -> 518.46625 | ... O4: ='Performance Tool'!P33/1000000 -> 560.82073

Sheet Sectoral Lending
B1: FORM 4B: | C1: NYALA VISION
C2: SECTORAL LENDING RETURN
B3: Sacco Society CS Number: | D3: 12444
C4: Financial Year | D4: 2022
B6: SASRA/GG/2/2019 : SECTORAL CLASSIFICATION OF CREDIT FINANCING BY DT-SACCOS | D6: 44621
D7: LOANS &
B8: Code | C8: ECONOMIC SECTORS | D8: ADVANCES
B9: 0 | C9: Refinancing | D9: 0
B10: 1000 | C10: AGRICULTURE | D10: 0
C11: 1100 Crop Farming | D11: 0
C12: 1110 Tea | D12: 0
C13: 1120 Coffee | D13: 0
C14: 1130 Sugarcane | D14: 0
C15: 1140 Others, cotton, sisal etc | D15: 9162916.2
C16: 1150 Cereals such as maize, wheat, sorghum. Millet etc | D16: 1098897.6
C17: 1160 Legumes such as beans, peas, snow peas, cow peas, french beans etc | D17: 2380401.5
C18: 1170 Horticulture crops such as vegetables, fruits, flowers | D18: 0
C19: 1180 Roots & tubers such as Irish potatoes, sweet potatoes and cassava | D19: 19597552
C20: 1200 Animal Production | D20: 0
C21: 1210 Dairy farming | D21: 37499.4
C22: 1220 Beef Production | D22: 5641225.4
... C38: 1510 Agro-forestry | D38: 0
B39: 2000 | C39: TRADE | D39: 0
C40: 2100 Wholesale and Retail | D40: 0
C41: 2110 Wholesale | D41: 0
C42: 2120 Retail | D42: 0
C43: 2200 Transport | D43: 0
C44: 2210 Public service transport | D44: 0
C45: 2220 Purchase of motorvehicle accessories | D45: 0
C46: 2230 Transportation of goods | D46: 0
C47: 2300 Hospitality | D47: 0
C48: 2310 Accomodation, restaurants, conference facilities, event planning & outside catering, theme parks (wedding and others) | D48: 0
C49: 2320 Schools and kindergartens | D49: 0
C50: 2330 Medical clinics and equipment | D50: 0
C51: 2400 Foreign Trade | D51: 0
... C53: 2420 Export | D53: 0
B54: 3000 | C54: MANUFACTURING AND SERVICING INDUSTRIES | D54: 0
C55: 3100 Cottage Industry | D55: 0
C56: 3110 Jua kali Industry | D56: 0
C57: 3120 Small scale Agricultural Produce processing | D57: 0
C58: 3130 Dressmaking Industry | D58: 0
C59: 3140 Leather tanning | D59: 0
C60: 3150 Carving and handcrafts | D60: 0
C61: 3200 Servicing Industry | D61: 0
C62: 3210 Motorvehicle repairs | D62: 0
C63: 3220 Professional services such as Barber shops | D63: 6655341.6
C64: 3230 Working capital for learning institutions, churches & business enterprises | D64: 0
C65: 3240 Promotion of local tourism | D65: 0
C66: 3300 Information, Communication and Technology | D66: 0
... C69: 3330 Telecommunication Equipment | D69: 0
B70: 4000 | C70: EDUCATION | D70: 0
C71: 4100 Education and related services | D71: 0
C72: 4110 School fees for primary and secondary schools including shopping and accomodation | D72: 9097698.7
C73: 4120 College fees, University fees, training fees, seminar fees | D73: 0
C74: 4130 Research and scientific activities etc | D74: 0
B75: 5000 | C75: HUMAN HEALTH | D75: 0
C76: 5100 Human health and related services | D76: 0
C77: 5110 Medical Bills, purchase of medicine | D77: 69129.4
C78: 5120 Maternity Bills and expenses | D78: 10662894
B79: 6000 | C79: LAND AND HOUSING | D79: 0
C80: 6100 Land | D80: 0
C81: 6110 Purchase of plots | D81: 0
C82: 6120 Land purchase services such as surveying and valuation | D82: 0
C83: 6200 Housing | D83: 0
C84: 6210 Construction of multiple residential buildings | D84: 0
C85: 6220 Construction of commercial buildings | D85: 19956242
C86: 6230 Construction of single residential dwelling units | D86: 15130223
C87: 6240 Renoivations of the buildings | D87: 0
B88: 7000 | C88: FINANCE, INVESTMENTS AND INSURANCE | D88: 0
C89: 7100 Microfinance | D89: 0
C90: 7110 Payment to microfinance loans | D90: 0
C91: 7200 Commercial Banks | D91: 0
C92: 7210 Payment to Commercial bank loans | D92: 0
C93: 7300 Mortgage Finance | D93: 0
C94: 7310 Purchase of residential property/payments to mortgage loans in other financial institutions | D94: 0
C95: 7400 Insurance | D95: 0
C96: 7410 Payment to insurance policies | D96: 0
C97: 7500 Investments | D97: 0
C98: 7510 Buying of Sacco shares | D98: 0
C99: 7520 purchase of quote shares, unquoted shares, treasury bills & bonds, commercial papers, unit trusts and other quoted public funds | D99: 0
C100: 7530 Paying personal debtsto non-registered institutions | D100: 0
B101: 8000 | C101: CONSUMPTION AND SOCIAL SERVICES | D101: 0
C102: 8100 Utilities | D102: 0
C103: 8110 Expenses incurred relating to car and electronic repairs, bills like electricity, sewer, water, telephone, decoder, personal debts to family members and friends etc. | D103: 0
C104: 8200 Utilities | D104: 0
C105: 8210 Household necessities like food, beverages and basic household products. | D105: 0
C106: 8300 Consumer Durables | D106: 0
C107: 8310 Goods that do not wear out quickly like automobiles(cars), books, household(home appliances, consumer electronics, furniture, tools etc) sports equipment, jewellery, toys etc | D107: 0
C108: 8400 Social and communal expenses | D108: 0
C109: 8410 Burial expenses, wedding expenses, rites of passage expenses. | D109: 0
C110: TOTAL | D110: =SUM(D9:D109) -> 1.2090059e+08
