Workbook

Sheet Evolutive SFP
B3: 2010 Audited | C3: 2011 Audited | D3: 2012 Audited | E3: 2013 Audited | F3: 2014 Audited | G3: 2015 Audited | H3: Audited-2016 | I3: 42736 | J3: 42767 | K3: 42795 | L3: 42826 | M3: 42856 | N3: 42887 | O3: 42917 | P3: 42948 | Q3: 42979 | R3: 43009 | S3: 43040 | T3: 43070 | U3: Audited 2017 | V3: 43101 | W3: 43132 | X3: 43160 | Y3: 43191 | Z3: 43221 | AA3: 43252 | AB3: 43282 | AC3: 43313 | AD3: 43344 | AE3: 43374 | AF3: 43405 | AG3: 43435 | AH3: Audited 2018 | AI3: 43466 | AJ3: 43497 | AK3: 43525 | AL3: 43556 | AM3: 43586 | AN3: 43617 | AO3: 43647 | AP3: 43678 | AQ3: 43709 | AR3: 43739 | AS3: 43770 | AT3: 43800 | AU3: Aud-19 | AV3: 43862 | AW3: 43891 | AX3: 43922 | AY3: 43952 | AZ3: 43983 | BA3: 44013 | BB3: 44044 | BC3: 44075 | BD3: 44105 | BE3: 44136 | BF3: 44166 | BG3: Audited 2020 | BH3: 44197 | BI3: 44228 | BJ3: 44256 | BK3: 44287 | BL3: 44317 | BM3: 44348 | BN3: 44378 | BO3: 44409 | BP3: 44440 | BQ3: 44470 | BR3: 44501 | BS3: 44531 | BT3: AUDITED 2021 | BU3: 44562 | BV3: 44593 | BW3: 44621 | BX3: 44652 | BY3: 44682 | BZ3: 44713 | CA3: 44743 | CB3: 44774 | CC3: 44805 | CD3: 44835 | CE3: 44866 | CF3: 44896 | CG3: Audited 2022 | CH3: 44927 | CI3: 44958 | CJ3: 44986 | CK3: 45017 | CL3: 45047 | CM3: 45078 | CN3: 45108 | CO3: 45139 | CP3: 45170
A4: Cash & cash Equivalent | B4: =SUM(B5:B6) -> 57280489 | C4: =SUM(C5:C6) -> 19846649 | D4: =SUM(D5:D6) -> 12419314 | E4: =SUM(E5:E6) -> 40164453 | F4: =SUM(F5:F6) -> 49731794 | G4: =SUM(G5:G6) -> 72857216 | H4: =SUM(H5:H6) -> 36146766 | I4: =SUM(I5:I6) -> 24906108 | ... CP4: =SUM(CP5:CP6) -> 1.2038067e+08
A5: Cash In Hand | B5: 42792387 | C5: 3657881 | D5: 5498182 | E5: 2528632.8 | F5: 4097074 | G5: 2142692 | H5: 616773 | I5: 1274435.1 | J5: 9622851.9 | K5: 11215420 | L5: 3718678.4 | M5: 3130207.4 | N5: 3057417.1 | O5: 607114.25 | P5: 4984664.2 | Q5: 1307731.6 | R5: 4788129.6 | S5: 2171891.6 | T5: 2275034.6 | U5: 2295202 | V5: 2566469.6 | W5: 659071.6 | X5: 3304159.6 | Y5: 3112409.6 | Z5: 863851.4 | AA5: 5539159.4 | AB5: 5260229.4 | AC5: 8493587.6 | AD5: 4785883.4 | AE5: 4834666.1 | AF5: 3608998.1 | AG5: 5697079.8 | AH5: 5716646.8 | AI5: 5873655.8 | AJ5: 4339155.8 | AK5: 2439301.8 | AL5: 3908512.8 | AM5: 5401982.4 | AN5: 3462266.6 | AO5: 5281359.4 | AP5: 4332265.4 | AQ5: 2000357.4 | AR5: 3160732.4 | AS5: 3938515.4 | AT5: 4423576.4 | AU5: 4470464.5 | AV5: 3697628.4 | AW5: 5093580.6 | AX5: 4414958.6 | AY5: 4487148.6 | AZ5: 2322674.6 | BB5: 30536363 | BC5: 6523160.6 | BD5: 1758342.6 | BE5: 2799575.2 | BF5: 6916205.2 | BG5: =475+6000000+915730+5+1957116 -> 8873326 | BH5: 7868919.2 | BI5: 2464328.2 | BJ5: 3543201.2 | BK5: 4686877.2 | BL5: 3687249.2 | BM5: 5268448.2 | BN5: 3586157.2 | BO5: 5172829.2 | BP5: 4712634.7 | BQ5: 4083501.7 | BR5: 4409943.7 | BS5: 4494213 | BT5: =317+2100000+276861+5+2117030 -> 4494213 | BU5: 4715834.2 | BV5: 3959109.2 | BW5: 5722311.2 | BX5: 2235063.2 | BY5: 5149850.2 | BZ5: 6884467.2 | CA5: 2690159.2 | CB5: 5924509.2 | CC5: 4803588.2 | CD5: 2460256.2 | CE5: 4997653.2 | CF5: 6682379.7 | CG5: 7358553 | CH5: 5464582.2 | CI5: 5945150.2 | CJ5: 4436375.2 | CK5: 6245041.2 | CL5: 6015164.2 | CM5: 3560673.2 | CN5: 6412658.2 | CO5: 3050344.2 | CP5: 3095541.2
A6: Cash at Bank | B6: 14488102 | C6: 16188768 | D6: 6921132 | E6: 37635820 | F6: 45634720 | G6: 70714524 | H6: 35529993 | I6: 23631673 | J6: 50282839 | K6: 39534472 | L6: 13027084 | M6: 37837805 | N6: 28160849 | O6: 38138637 | P6: 22761430 | Q6: 40766447 | R6: 36262575 | S6: 53797792 | T6: 47070062 | U6: 47049895 | V6: 56934852 | W6: 72189384 | X6: 61542081 | Y6: 40231590 | Z6: 42117104 | AA6: 55597424 | AB6: 59298763 | AC6: 44746707 | AD6: 54569798 | AE6: 62131670 | AF6: 58301667 | AG6: 55270669 | AH6: 55250801 | AI6: 60500765 | AJ6: 65508386 | AK6: 64485984 | AL6: 41413490 | AM6: 40781864 | AN6: 64068748 | AO6: 51843260 | AP6: 57422859 | AQ6: 72900408 | AR6: 76367215 | AS6: 65894319 | AT6: 66576836 | AU6: 66577436 | AV6: 94491873 | AW6: 73489004 | AX6: 98687848 | AY6: 1.0721277e+08 | AZ6: 1.1091437e+08 | BB6: 5.5124051e+08 | BC6: 1.0321167e+08 | BD6: 1.0913492e+08 | BE6: 1.1192079e+08 | BF6: 1.0625311e+08 | BG6: =2271280+939631+526483+21879119+17128282+3928427+42456814+16190387-(1024438) -> 104295985 | BH6: 1.1225204e+08 | BI6: 1.0073774e+08 | BJ6: 1.0249473e+08 | BK6: 1.0399239e+08 | BL6: 1.1003877e+08 | BM6: 1.0878372e+08 | BN6: 1.2067191e+08 | BO6: 1.3653578e+08 | BP6: 1.3584375e+08 | BQ6: 1.426082e+08 | BR6: 1.5629014e+08 | BS6: 155848611 | BT6: =160342825-4494213 -> 155848612 | BU6: 1.592191e+08 | BV6: 1.3888693e+08 | BW6: 1.023467e+08 | BX6: 99243027 | BY6: 1.0438703e+08 | BZ6: 1.2767785e+08 | CA6: 1.4275253e+08 | CB6: 1.4336091e+08 | CC6: 1.5841691e+08 | CD6: 1.6940507e+08 | CE6: 1.731117e+08 | CF6: 1.6680488e+08 | CG6: 166128708 | CH6: 1.6962797e+08 | CI6: 1.8485086e+08 | CJ6: 1.4360327e+08 | CK6: 78441494 | CL6: 1.1124177e+08 | CM6: 1.4509659e+08 | CN6: 1.5519755e+08 | CO6: 1.2005299e+08 | CP6: 1.1728513e+08
A7: Prepayment and Sundry | B7: 12265847 | C7: 18760041 | D7: 35908122 | E7: 28737959 | F7: 61660581 | G7: 32276918 | H7: 39005377 | I7: 0 | J7: 0 | K7: 0 | L7: 0 | M7: 0 | N7: 0 | O7: 0 | P7: 0 | Q7: 0 | R7: 0 | S7: 0 | T7: 0 | U7: 18725028 | V7: 0 | W7: 0 | X7: 0 | Y7: 0 | Z7: 0 | AA7: 0 | AB7: 0 | AC7: 0 | AD7: 0 | AE7: 0 | AF7: 0 | AG7: 0 | AH7: 12540117 | AI7: 0 | AJ7: 0 | AK7: 0 | AL7: 0 | AM7: 0 | AN7: 0 | AO7: 0 | AP7: 0 | AQ7: 0 | AR7: 0 | AS7: 0 | AT7: 0 | AU7: 12920590 | AV7: 0 | AW7: 0 | AX7: 0 | AY7: 0 | AZ7: 0 | BB7: 0 | BC7: 0 | BD7: 0 | BE7: 0 | BF7: 0 | BG7: 14085464 | BH7: 0 | BI7: 0 | BJ7: 0 | BK7: 0 | BL7: 0 | BM7: 0 | BN7: 0 | BO7: 0 | BP7: 0 | BQ7: 0 | BR7: 0 | BS7: 0 | BT7: =7618001+5173177-538512 -> 12252666 | BU7: 0 | BV7: 0 | BW7: 0 | BX7: 0 | BY7: 0 | BZ7: 0 | CA7: 0 | CB7: 0 | CC7: 0 | CD7: 0 | CE7: 0 | CF7: 0 | CG7: 1747956 | CH7: 0 | CI7: 0 | CJ7: 0 | CK7: 0 | CL7: 0 | CM7: 0 | CN7: 0 | CO7: 0 | CP7: 0
A8: Financial Investment | B8: =SUM(B9:B13) -> 12265847 | C8: =SUM(C9:C13) -> 13675347 | D8: =SUM(D9:D13) -> 25329658 | E8: =SUM(E9:E13) -> 27684833 | F8: =SUM(F9:F13) -> 14582790 | G8: =SUM(G9:G13) -> 28191601 | H8: =SUM(H9:H13) -> 32411253 | I8: =SUM(I9:I13) -> 39637678 | ... CP8: =SUM(CP9:CP13) -> 1.2930389e+08
A9: Government Security | B9: 3323677 | I9: 0 | J9: 0 | K9: 0 | L9: 0 | M9: 0 | N9: 0 | O9: 0 | P9: 0 | Q9: 0 | R9: 0 | S9: 0 | T9: 0 | V9: 0 | W9: 0 | X9: 0 | Y9: 0 | Z9: 0 | AA9: 0 | AB9: 0 | AC9: 0 | AD9: 0 | AE9: 0 | AF9: 0 | AG9: 0 | AH9: 0 | AI9: 0 | AJ9: 0 | AK9: 0 | AL9: 0 | AM9: 0 | AN9: 0 | AO9: 0 | AP9: 0 | AQ9: 0 | AR9: 0 | AS9: 0 | AT9: 0 | AV9: 0 | AW9: 0 | AX9: 0 | AY9: 0 | AZ9: 0 | BB9: 0 | BC9: 0 | BD9: 0 | BE9: 0 | BF9: 0 | BG9: 0 | BH9: 0 | BI9: 0 | BJ9: 0 | BK9: 0 | BL9: 0 | BM9: 0 | BN9: 0 | BO9: 0 | BP9: 0 | BQ9: 0 | BR9: 0 | BS9: 0 | BU9: 0 | BV9: 0 | BW9: 0 | BX9: 0 | BY9: 0 | BZ9: 0 | CA9: 0 | CB9: 0 | CC9: 0 | CD9: 0 | CE9: 0 | CF9: 0 | CG9: 0 | CH9: 0 | CI9: 0 | CJ9: 0 | CK9: 0 | CL9: 0 | CM9: 0 | CN9: 0 | CO9: 0 | CP9: 0
A10: Other Securities | B10: 8942170 | G10: 139800 | I10: 0 | J10: 0 | K10: 0 | L10: 0 | M10: 0 | N10: 0 | O10: 0 | P10: 0 | Q10: 0 | R10: 0 | S10: 0 | T10: 0 | V10: 0 | W10: 0 | X10: 0 | Y10: 0 | Z10: 0 | AA10: 0 | AB10: 0 | AC10: 0 | AD10: 0 | AE10: 0 | AF10: 0 | AG10: 0 | AH10: 0 | AI10: 0 | AJ10: 0 | AK10: 0 | AL10: 0 | AM10: 0 | AN10: 0 | AO10: 0 | AP10: 0 | AQ10: 0 | AR10: 0 | AS10: 0 | AT10: 0 | AV10: 0 | AW10: 0 | AX10: 0 | AY10: 0 | AZ10: 0 | BB10: 0 | BC10: 0 | BD10: 0 | BE10: 0 | BF10: 0 | BG10: 0 | BH10: 0 | BI10: 0 | BJ10: 0 | BK10: 0 | BL10: 0 | BM10: 0 | BN10: 0 | BO10: 0 | BP10: 0 | BQ10: 0 | BR10: 0 | BS10: 0 | BU10: 0 | BV10: 0 | BW10: 0 | BX10: 0 | BY10: 0 | BZ10: 0 | CA10: 0 | CB10: 0 | CC10: 0 | CD10: 0 | CE10: 0 | CF10: 0 | CG10: 0 | CH10: 0 | CI10: 0 | CJ10: 0 | CK10: 0 | CL10: 0 | CM10: 0 | CN10: 0 | CO10: 0 | CP10: 0
A11: Balances in NACCOS (E.g Jungu Kuu, ESS, Savings,Money Market,Coop FD, CFP) | C11: 3676702 | D11: 15331014 | E11: 17343284 | G11: 12208811 | H11: 6774463 | I11: 13600888 | J11: 7174463.4 | K11: 7374463.4 | L11: 7574463.4 | M11: 7774463.4 | N11: 8036911.8 | O11: 8236911.8 | P11: 8436911.8 | Q11: 8669496.2 | R11: 8869496.2 | S11: 9069496.2 | T11: 9269496.2 | U11: 9269496 | V11: 9572745.6 | W11: 9772745.6 | X11: 9972745.6 | Y11: 10172746 | Z11: 10372746 | AA11: 10572746 | AB11: 10772746 | AC11: 10972746 | AD11: 11172746 | AE11: 11372746 | AF11: 11572746 | AG11: 11809941 | AH11: 11809941 | AI11: 12009941 | AJ11: 12209941 | AK11: 12409941 | AL11: 12609941 | AM11: 12809941 | AN11: 13009941 | AO11: 13209941 | AP11: 13409941 | AQ11: 13609941 | AR11: 13809941 | AS11: 14204391 | AT11: 14254391 | AU11: 46262880 | AV11: 14504391 | AW11: 14704391 | AX11: 9304390.8 | AY11: 9504390.8 | AZ11: 10054391 | BB11: 56415201 | BC11: 11833040 | BD11: 12383040 | BE11: 12933040 | BF11: 13483040 | BG11: =13483040+42334539+558750 -> 56376329 | BH11: 14033040 | BI11: 14583040 | BJ11: 15270413 | BK11: 15820413 | BL11: 16418165 | BM11: 16968165 | BN11: 17518165 | BO11: 10116905 | BP11: 10666905 | BQ11: 11266640 | BR11: 11816640 | BS11: 12416374 | BT11: =10296359+2120015 -> 12416374 | BU11: 0 | BV11: 0 | BW11: 0 | BX11: 0 | BY11: 0 | BZ11: 0 | CA11: 0 | CB11: 0 | CC11: 0 | CD11: 0 | CE11: 0 | CF11: 0 | CG11: 19548923 | CH11: 20098923 | CI11: 20648923 | CJ11: 11628908 | CK11: 42178905 | CL11: 42728908 | CM11: 43606543 | CN11: 44156543 | CO11: 74706543 | CP11: 75259559
A12: Equity Investments in NACCOs(Shares in- CIC, KUSCCO, COOP BANK,CAK, KERUSSU) | BT12: =2232936+18375400+23770019+25000+418950 -> 44822305 | BU12: 12967373 | BV12: 13517373 | BW12: 14067373 | BX12: 14617373 | BY12: 15167373 | BZ12: 15717373 | CA12: 16267373 | CB12: 16817373 | CC12: 17420119 | CD12: 17970119 | CE12: 18520119 | CF12: 19122795 | CG12: 50345579 | CH12: 51324329 | CI12: 51744329 | CJ12: 52164329 | CK12: 52584329 | CL12: 53004329 | CM12: 53424329 | CN12: 53844329 | CO12: 53944329 | CP12: 54044329
A13: Equity Investments in companies - shares/stocks | C13: 9998645 | D13: 9998644 | E13: 10341549 | F13: 14582790 | G13: 15842990 | H13: 25636790 | I13: 26036790 | J13: 26236790 | K13: 26236790 | L13: 26636790 | M13: 26836790 | N13: 27036790 | O13: 27236790 | P13: 27436790 | Q13: 27833289 | R13: 27853289 | S13: 27873289 | T13: 27493289 | U13: =26934539+558750 -> 27493289 | V13: 27513289 | W13: 27533289 | X13: 27553289 | Y13: 27773289 | Z13: 27993289 | AA13: 28213289 | AB13: 28433289 | AC13: 28653289 | AD13: 28873289 | AE13: 29093289 | AF13: 29313289 | AG13: 29533289 | AH13: 29533289 | AI13: 29753289 | AJ13: 29973289 | AK13: 30193289 | AL13: 30413289 | AM13: 30633289 | AN13: 30853289 | AO13: 31073289 | AP13: 31293289 | AQ13: 31513289 | AR13: 31733289 | AS13: 31953289 | AT13: 32173289 | AU13: 164800 | AV13: 32393289 | AW13: 32613289 | AX13: 33033289 | AY13: 33453289 | AZ13: 33873289 | BB13: 173566445 | BC13: 35133289 | BD13: 35553289 | BE13: 35973289 | BF13: 42893298 | BH13: 43313289 | BI13: 43733289 | BJ13: 44153289 | BK13: 44573289 | BL13: 44993289 | BM13: 45413289 | BN13: 45833289 | BO13: 46253289 | BP13: 46673289 | BQ13: 47093289 | BR13: 47513289 | BS13: 43933289 | BT13: =91050+48750 -> 139800 | BU13: 45381106 | BV13: 45801106 | BW13: 46221106 | BX13: 46641106 | BY13: 47061106 | BZ13: 47481106 | CA13: 47901106 | CB13: 48321106 | CC13: 48741106 | CD13: 49161106 | CE13: 49581106 | CF13: 50001106 | CG13: 558750
A14: Net Loan Portfolio | B14: =B15-B16 -> 263143330 | C14: =C15-C16 -> 294845459 | D14: =D15-D16 -> 318026558 | E14: =E15-E16 -> 3.516902e+08 | F14: =F15-F16 -> 350184189 | G14: =G15-G16 -> 376107614 | H14: =H15-H16 -> 468334250 | I14: =I15-I16 -> 4.9099259e+08 | ... CP14: =CP15-CP16 -> 8.5077549e+08
A15: Gross Loan Portfolio | B15: 263143330 | C15: 296918859 | D15: 325298062 | E15: 3.5915199e+08 | F15: 360786989 | G15: 389781182 | H15: 491527931 | I15: 5.0468456e+08 | J15: 4.9688591e+08 | K15: 4.9456015e+08 | L15: 5.046516e+08 | M15: 5.0493288e+08 | N15: 5.0912243e+08 | O15: 5.2653857e+08 | P15: 5.2816045e+08 | Q15: 5.3719316e+08 | R15: 5.5453225e+08 | S15: 5.6042011e+08 | T15: 5.7418481e+08 | U15: 574184811 | V15: 5.7267714e+08 | W15: 5.7280548e+08 | X15: 5.68068e+08 | Y15: 5.7858506e+08 | Z15: 5.8956632e+08 | AA15: 5.9674454e+08 | AB15: 6.0520294e+08 | AC15: 6.2625334e+08 | AD15: 6.3670917e+08 | AE15: 6.3477404e+08 | AF15: 6.5520604e+08 | AG15: 6.6105478e+08 | AH15: 6.6105478e+08 | AI15: 6.6863753e+08 | AJ15: 6.6872501e+08 | AK15: 6.5841062e+08 | AL15: 6.6243866e+08 | AM15: 6.738089e+08 | AN15: 6.7270673e+08 | AO15: 6.7966546e+08 | AP15: 6.9624739e+08 | AQ15: 6.9414492e+08 | AR15: 7.0307924e+08 | AS15: 7.2149301e+08 | AT15: 7.3129182e+08 | AU15: 7.3129182e+08 | AV15: 7.2598822e+08 | AW15: 7.2438179e+08 | AX15: 7.234794e+08 | AY15: 7.1536943e+08 | AZ15: 7.1114084e+08 | BB15: 3.6662176e+09 | BC15: 7.3903284e+08 | BD15: 7.513754e+08 | BE15: 7.5694821e+08 | BF15: 7.6410396e+08 | BG15: 764103964 | BH15: 7.6356731e+08 | BI15: 7.5297719e+08 | BJ15: 7.5821386e+08 | BK15: 7.7349083e+08 | BL15: 7.7601377e+08 | BM15: 7.8583422e+08 | BN15: 8.019999e+08 | BO15: 8.0320065e+08 | BP15: 8.1268225e+08 | BQ15: 8.2255972e+08 | BR15: 8.3008889e+08 | BS15: 8.4131721e+08 | BT15: 841317206 | BU15: 8.358757e+08 | BV15: 8.3215386e+08 | BW15: 8.3838315e+08 | BX15: 8.5671903e+08 | BY15: 8.5332865e+08 | BZ15: 8.4453671e+08 | CA15: 8.48169e+08 | CB15: 8.4600809e+08 | CC15: 8.4261621e+08 | CD15: 8.4413452e+08 | CE15: 8.4763921e+08 | CF15: 8.5151251e+08 | CG15: 8.5151251e+08 | CH15: 85088141 | CI15: 8.515083e+08 | CJ15: 8.4147088e+08 | CK15: 8.6511664e+08 | CL15: 8.4504385e+08 | CM15: 8.4100263e+08 | CN15: 8.4643626e+08 | CO15: 8.5947565e+08 | CP15: 8.7044124e+08
A16: Allowance For Loan Loss | C16: 2073400 | D16: 7271504 | E16: 7461796.2 | F16: 10602800 | G16: 13673568 | H16: 23193681 | I16: 13691966 | J16: 22112854 | K16: 21769492 | L16: 22284323 | M16: 21874658 | N16: 22134292 | O16: 21803919 | P16: 22059516 | Q16: 22755109 | R16: 22755109 | S16: 20824298 | T16: 22244039 | U16: 22244039 | V16: 24843404 | W16: 24175684 | X16: 23266218 | Y16: 22624083 | Z16: 21899472 | AA16: 21845790 | AB16: 21845790 | AC16: 21845790 | AD16: 22931845 | AE16: 21100958 | AF16: 20734413 | AG16: 20226997 | AH16: 20226997 | AI16: 20226997 | AJ16: 20226997 | AK16: 20090269 | AL16: 20090269 | AM16: 19056804 | AN16: 19646297 | AO16: 19646297 | AP16: 22710258 | AQ16: 24299438 | AR16: 24839110 | AS16: 26172473 | AT16: 26887990 | AU16: 26887990 | AV16: 24381963 | AW16: 23109616 | AX16: 24846795 | AY16: 26267745 | AZ16: 29696887 | BB16: 1.5804551e+08 | BC16: 33312188 | BD16: 32764675 | BE16: 39379954 | BF16: 34889602 | BG16: 34889602 | BH16: 30175001 | BI16: 33106988 | BJ16: 32020383 | BK16: 28999942 | BL16: 30535307 | BM16: 29685897 | BN16: 35353837 | BO16: 29230688 | BP16: 28719584 | BQ16: 26083348 | BR16: 26561584 | BS16: 25144187 | BT16: 34889602 | BU16: 34889602 | BV16: 27347683 | BW16: 27778804 | BX16: 26579178 | BY16: 25140574 | BZ16: 19843405 | CA16: 19770002 | CB16: 21248174 | CC16: 18728827 | CD16: 16745986 | CE16: 16713798 | CF16: 26869932 | CG16: 26869932 | CH16: -26869932 | CI16: 16693310 | CJ16: 16071034 | CK16: 15948034 | CL16: 16132261 | CM16: 15166570 | CN16: 19647865 | CO16: 18229323 | CP16: 19665756
A17: Accounts Recievables | E17: =SUM(E18:E20) -> 0 | F17: =SUM(F18:F20) -> 0 | G17: =SUM(G18:G20) -> 0 | H17: =SUM(H18:H20) -> 0 | I17: =SUM(I18:I20) -> 0 | J17: =SUM(J18:J20) -> 0 | K17: =SUM(K18:K20) -> 0 | L17: =SUM(L18:L20) -> 0 | ... CP17: =SUM(CP18:CP20) -> 0
A18: Tax Recoverable | H18: - | I18: 0 | J18: 0 | K18: 0 | L18: 0 | M18: 0 | N18: 0 | O18: 0 | P18: 0 | Q18: 0 | R18: 0 | S18: 0 | T18: 0 | V18: 0 | W18: 0 | X18: 0 | Y18: 0 | Z18: 0 | AA18: 0 | AB18: 0 | AC18: 0 | AD18: 0 | AE18: 0 | AF18: 0 | AG18: 0 | AH18: 0 | AI18: 0 | AJ18: 0 | AK18: 0 | AL18: 0 | AM18: 0 | AN18: 0 | AO18: 0 | AP18: 0 | AQ18: 0 | AR18: 0 | AS18: 0 | AT18: 0 | AU18: 0 | AV18: 0 | AW18: 0 | AX18: 0 | AY18: 0 | AZ18: 0 | BA18: 0 | BB18: 0 | BC18: 0 | BD18: 0 | BE18: 0 | BF18: 0 | BG18: 979706 | BH18: 0 | BI18: 0 | BJ18: 0 | BK18: 0 | BL18: 0 | BM18: 0 | BN18: 0 | BO18: 0 | BP18: 0 | BQ18: 0 | BR18: 0 | BS18: 0 | BT18: 928581 | BU18: 0 | BV18: 0 | BW18: 0 | BX18: 0 | BY18: 0 | BZ18: 0 | CA18: 0 | CB18: 0 | CC18: 0 | CD18: 0 | CE18: 0 | CF18: 0 | CG18: 3538581 | CH18: 0 | CI18: 0 | CJ18: 0 | CK18: 0 | CL18: 0 | CM18: 0 | CN18: 0 | CO18: 0 | CP18: 0
A19: Deffered Tax Assets | H19: - | I19: 0 | J19: 0 | K19: 0 | L19: 0 | M19: 0 | N19: 0 | O19: 0 | P19: 0 | Q19: 0 | R19: 0 | S19: 0 | T19: 0 | V19: 0 | W19: 0 | X19: 0 | Y19: 0 | Z19: 0 | AA19: 0 | AB19: 0 | AC19: 0 | AD19: 0 | AE19: 0 | AF19: 0 | AG19: 0 | AH19: 0 | AI19: 0 | AJ19: 0 | AK19: 0 | AL19: 0 | AM19: 0 | AN19: 0 | AO19: 0 | AP19: 0 | AQ19: 0 | AR19: 0 | AS19: 0 | AT19: 0 | AU19: 0 | AV19: 0 | AW19: 0 | AX19: 0 | AY19: 0 | AZ19: 0 | BA19: 0 | BB19: 0 | BC19: 0 | BD19: 0 | BE19: 0 | BF19: 0 | BG19: 0 | BH19: 0 | BI19: 0 | BJ19: 0 | BK19: 0 | BL19: 0 | BM19: 0 | BN19: 0 | BO19: 0 | BP19: 0 | BQ19: 0 | BR19: 0 | BS19: 0 | BU19: 0 | BV19: 0 | BW19: 0 | BX19: 0 | BY19: 0 | BZ19: 0 | CA19: 0 | CB19: 0 | CC19: 0 | CD19: 0 | CE19: 0 | CF19: 0 | CG19: 0 | CH19: 0 | CI19: 0 | CJ19: 0 | CK19: 0 | CL19: 0 | CM19: 0 | CN19: 0 | CO19: 0 | CP19: 0
A20: Retirement Benefit Assets | H20: - | I20: 0 | J20: 0 | K20: 0 | L20: 0 | M20: 0 | N20: 0 | O20: 0 | P20: 0 | Q20: 0 | R20: 0 | S20: 0 | T20: 0 | V20: 0 | W20: 0 | X20: 0 | Y20: 0 | Z20: 0 | AA20: 0 | AB20: 0 | AC20: 0 | AD20: 0 | AE20: 0 | AF20: 0 | AG20: 0 | AH20: 0 | AI20: 0 | AJ20: 0 | AK20: 0 | AL20: 0 | AM20: 0 | AN20: 0 | AO20: 0 | AP20: 0 | AQ20: 0 | AR20: 0 | AS20: 0 | AT20: 0 | AU20: 0 | AV20: 0 | AW20: 0 | AX20: 0 | AY20: 0 | AZ20: 0 | BA20: 0 | BB20: 0 | BC20: 0 | BD20: 0 | BE20: 0 | BF20: 0 | BG20: 0 | BH20: 0 | BI20: 0 | BJ20: 0 | BK20: 0 | BL20: 0 | BM20: 0 | BN20: 0 | BO20: 0 | BP20: 0 | BQ20: 0 | BR20: 0 | BS20: 0 | BU20: 0 | BV20: 0 | BW20: 0 | BX20: 0 | BY20: 0 | BZ20: 0 | CA20: 0 | CB20: 0 | CC20: 0 | CD20: 0 | CE20: 0 | CF20: 0 | CG20: 0 | CH20: 0 | CI20: 0 | CJ20: 0 | CK20: 0 | CL20: 0 | CM20: 0 | CN20: 0 | CO20: 0 | CP20: 0
A21: Property&Equipments&Other Assets | B21: =SUM(B22:B26) -> 75849622 | C21: =SUM(C22:C26) -> 75797990 | D21: =SUM(D22:D26) -> 62974319 | E21: =SUM(E22:E26) -> 60255949 | F21: =SUM(F22:F26) -> 58284975 | G21: =SUM(G22:G26) -> 94755272 | H21: =SUM(H22:H26) -> 121086191 | I21: =SUM(I22:I26) -> 1.5226473e+08 | ... CP21: =SUM(CP22:CP26) -> 56380373
A22: Investment Properties | G22: 16170871 | H22: 15847454 | I22: 16150520 | J22: 16123569 | K22: 16096617 | L22: 16069666 | M22: 16042714 | N22: 16015763 | O22: 16015763 | P22: 16015763 | Q22: 15961860 | R22: 15934909 | S22: 15907957 | T22: 15881006 | U22: 15530505 | V22: 15504621 | W22: 15478737 | X22: 15452852 | Y22: 15426968 | Z22: 15401084 | AA22: 15375200 | AB22: 15349316 | AC22: 15323432 | AD22: 15297547 | AE22: 15271663 | AF22: 15245779 | AG22: 15219895 | AH22: 15219895 | AI22: 15194529 | AJ22: 15169192 | AK22: 15143826 | AL22: 15118459 | AM22: 15093093 | AN22: 15064726 | AO22: 15042360 | AP22: 15016993 | AQ22: 14991627 | AR22: 14966260 | AS22: 14940894 | AT22: 14915527 | AU22: 14915497 | AV22: 14865809 | AW22: 14840950 | AX22: 14816090 | AY22: 14791231 | AZ22: 14766372 | BB22: 73582819 | BC22: 14691795 | BD22: 14666936 | BE22: 14642076 | BF22: 14617217 | BG22: 14617187 | BH22: 14592825 | BI22: 14568363 | BJ22: 14544001 | BK22: 14519739 | BL22: 14495377 | BM22: 14471015 | BN22: 14291536 | BO22: 14287168 | BP22: 14397929 | BQ22: 14373567 | BR22: 14349205 | BS22: 14324843 | BT22: 14324843 | BU22: 14300968 | BV22: 14277093 | BW22: 14253218 | BX22: 14229343 | BY22: 14205468 | BZ22: 14181593 | CA22: 14157718 | CB22: 14133843 | CC22: 14109968 | CD22: 14231488 | CE22: 14062218 | CF22: 14038343 | CG22: 14038346 | CH22: 14014946 | CI22: 13991549 | CJ22: 13968152 | CK22: 13944754 | CL22: 13921357 | CM22: 13897960 | CN22: 13874563 | CO22: 13851165 | CP22: 13827768
A23: Property and Equipment | B23: 75849622 | C23: 70621990 | D23: 58833519 | E23: 56943309 | F23: 55634863 | G23: 39960484 | H23: 40147340 | I23: 40050734 | J23: 39871668 | K23: 39938621 | L23: 39759555 | M23: 40309490 | N23: 40108424 | O23: 39931107 | P23: 41103170 | Q23: 40503244 | R23: 40307338 | S23: 40229745 | T23: 39762189 | U23: =55643190-U22 -> 40112685 | V23: 39921069 | W23: 39767350 | X23: 39600182 | Y23: 39611875 | Z23: 39775708 | AA23: 39591540 | AB23: 39631731 | AC23: 39455064 | AD23: 39270897 | AE23: 39102430 | AF23: 38918262 | AG23: 38647964 | AH23: 38648263 | AI23: 38542409 | AJ23: 38333876 | AK23: 38435617 | AL23: 38365183 | AM23: 38262942 | AN23: 38100513 | AO23: 37953164 | AP23: 37858275 | AQ23: 37713256 | AR23: 37550857 | AS23: 37388458 | AT23: 37319284 | AU23: 37330512 | AV23: 37491018 | AW23: 37535197 | AX23: 37465949 | AY23: 37396702 | AZ23: 37304455 | BB23: 1.8800401e+08 | BC23: 37687360 | BD23: 37553885 | BE23: 37069518 | BF23: 37026333 | BG23: =51643280-14617187 -> 37026093 | BH23: 36954800 | BI23: 36720311 | BJ23: 36567420 | BK23: 36414529 | BL23: 36351638 | BM23: 36198747 | BN23: 36200974 | BO23: 36147058 | BP23: 35859044 | BQ23: 35855533 | BR23: 35879535 | BS23: 35648339 | BT23: 35648339 | BU23: 35851380 | BV23: 35716983 | BW23: 35814845 | BX23: 35693221 | BY23: 35556597 | BZ23: 35889186 | CA23: 35762685 | CB23: 35624584 | CC23: 35502978 | CD23: 35265405 | CE23: 34960541 | CF23: 34928432 | CG23: 34928424 | CH23: 34804740 | CI23: 34681048 | CJ23: 34542013 | CK23: 34858405 | CL23: 35209810 | CM23: 35086118 | CN23: 35136111 | CO23: 34989220 | CP23: 34966225
A24: Prepaid Lease Rentals | I24: 0 | J24: 0 | K24: 0 | L24: 0 | M24: 0 | N24: 0 | O24: 0 | P24: 0 | Q24: 0 | R24: 0 | S24: 0 | T24: 0 | V24: 0 | W24: 0 | X24: 0 | Y24: 0 | Z24: 0 | AA24: 0 | AB24: 0 | AC24: 0 | AD24: 0 | AE24: 0 | AF24: 0 | AG24: 0 | AI24: 0 | AJ24: 0 | AK24: 0 | AL24: 0 | AM24: 0 | AN24: 0 | AO24: 0 | AP24: 0 | AQ24: 0 | AR24: 0 | AS24: 0 | AT24: 0 | AV24: 0 | AW24: 0 | AX24: 0 | AY24: 0 | AZ24: 0 | BB24: 0 | BC24: 0 | BD24: 0 | BE24: 0 | BF24: 0 | BG24: 0 | BH24: 0 | BI24: 0 | BJ24: 0 | BK24: 0 | BL24: 0 | BM24: 0 | BN24: 0 | BO24: 0 | BP24: 0 | BQ24: 0 | BR24: 0 | BS24: 0 | BU24: 0 | BV24: 0 | BW24: 0 | BX24: 0 | BY24: 0 | BZ24: 0 | CA24: 0 | CB24: 0 | CC24: 0 | CD24: 0 | CE24: 0 | CF24: 0 | CG24: 0 | CH24: 0 | CI24: 0 | CJ24: 0 | CK24: 0 | CL24: 0 | CM24: 0 | CN24: 0 | CO24: 0 | CP24: 0
A25: Intangible Assets | C25: 5176000 | D25: 4140800 | E25: 3312640 | F25: 2650112 | G25: 2120090 | H25: 2108549 | I25: 1660737.2 | J25: 1625402.4 | K25: 1590066.6 | L25: 1554732.7 | M25: 6536465.3 | N25: 6863050.5 | O25: 6827715.6 | P25: 7047207.7 | Q25: 7529686.2 | R25: 7784512.1 | S25: 7678507.6 | T25: 7522411.2 | U25: 7522411 | V25: 7397037.7 | W25: 7271664.2 | X25: 7273704.2 | Y25: 7273704.2 | Z25: 7022957.2 | AA25: 6897583.7 | AB25: 6772210.2 | AC25: 6646836.7 | AD25: 6521463.2 | AE25: 6521463.2 | AF25: 6396089.7 | AG25: 6119858.7 | AH25: 6119859.2 | AI25: 6017861 | AJ25: 5915863.4 | AK25: 5813865.7 | AL25: 5711868.1 | AM25: 5609870.4 | AN25: 5609870.4 | AO25: 5405875.1 | AP25: 5303877.5 | AQ25: 5201879.8 | AR25: 5099882.2 | AS25: 4997884.5 | AT25: 4895886.9 | AU25: 4895879.4 | AV25: 4732690.9 | AW25: 5151092.9 | AX25: 5269495 | AY25: 5187897 | AZ25: 5106299 | BB25: 24715515 | BC25: 4861505.1 | BD25: 4779907.1 | BE25: 4698309.2 | BF25: 4511711.2 | BG25: 4511711 | BH25: 4430113.2 | BI25: 4361320.8 | BJ25: 4286125.6 | BK25: 4210930.4 | BL25: 4135735.2 | BM25: 4060540 | BN25: 3985344.8 | BO25: 3910149.6 | BP25: 3834954.5 | BQ25: 3759759.3 | BR25: 3684564.1 | BS25: 3609368.9 | BT25: 3609369 | BU25: 3564251.9 | BV25: 3519134.9 | BW25: 3474017.9 | BX25: 3474017.9 | BY25: 3428900.9 | BZ25: 3428900.9 | CA25: 3428900.9 | CB25: 3428900.9 | CC25: 3428900.9 | CD25: 3203315.9 | CE25: 3158198.9 | CF25: 2887494.9 | CG25: 2887495 | CH25: 2839370 | CI25: 2791245 | CJ25: 2887888.1 | CK25: 2781855.2 | CL25: 2733730.3 | CM25: 2685605.4 | CN25: 2625499.6 | CO25: 2577374.7 | CP25: 4179249.8
A26: Other Assets | G26: 36503827 | H26: 62982848 | I26: 94402737 | J26: 85918460 | K26: 86835988 | L26: 92226637 | M26: 72775101 | N26: 91438092 | O26: 58856901 | P26: 95306328 | Q26: 82291455 | R26: 83226158 | S26: 80294701 | T26: 84480811 | U26: 65378903 | V26: 84074076 | W26: 82284057 | X26: 82778159 | Y26: 82606696 | Z26: 82597979 | AA26: 82633405 | AB26: 82678372 | AC26: 82728591 | AD26: 82768546 | AE26: 82624442 | AF26: 82493356 | AG26: 77858967 | AH26: 65318850 | AI26: 19906805 | AJ26: 20263406 | AK26: 17479708 | AL26: 18683128 | AM26: 18680711 | AN26: 19126388 | AO26: 21539072 | AP26: 19846391 | AQ26: 20621271 | AR26: 21142069 | AS26: 21233543 | AT26: 14417383 | AU26: 308457.22 | AV26: 14631632 | AW26: 14110254 | AX26: 13122169 | AY26: 12863273 | AZ26: 13772467 | BB26: 74177301 | BC26: 15662679 | BD26: 16221671 | BE26: 16999769 | BF26: 15206340 | BG26: 0 | BH26: 15698612 | BI26: 17467813 | BJ26: 16079587 | BK26: 15080317 | BL26: 14817845 | BM26: 15357171 | BN26: 15576750 | BO26: 15790048 | BP26: 16627988 | BQ26: 16805396 | BR26: 17250362 | BS26: 13181247 | BU26: 14452085 | BV26: 11293713 | BW26: 11018760 | BX26: 10205107 | BY26: 10357300 | BZ26: 9262330.4 | CA26: 9938720.9 | CB26: 6119388.9 | CC26: 6268977.6 | CD26: 7435848.8 | CE26: 7320150.6 | CF26: 5286536 | CH26: 3719690.2 | CI26: 4598842.2 | CJ26: 1951353.9 | CK26: 4117372.1 | CL26: 2827649 | CM26: 2630151.6 | CN26: 2577370.2 | CO26: 2518198.4 | CP26: 3407130.4
A27: Total Assets | B27: =B21+B17+B14+B8+B7+B4 -> 420805135 | C27: =C21+C17+C14+C8+C7+C4 -> 422925486 | D27: =D21+D17+D14+D8+D7+D4 -> 454657971 | E27: =E21+E17+E14+E8+E7+E4 -> 5.0853339e+08 | F27: =F21+F17+F14+F8+F7+F4 -> 534444329 | G27: =G21+G17+G14+G8+G7+G4 -> 604188621 | H27: =H21+H17+H14+H8+H7+H4 -> 696983837 | I27: =I21+I17+I14+I8+I7+I4 -> 7.0780111e+08 | ... CP27: =CP21+CP17+CP14+CP8+CP7+CP4 -> 1.1568404e+09
A28: Savings and Deposits | B28: 19165989 | C28: 235081887 | D28: 260205324 | E28: 2.8541463e+08 | F28: 19567215 | G28: 28830199 | H28: 54834830 | I28: 43919039 | J28: 55039630 | K28: 72708021 | L28: 50526228 | M28: 54138099 | N28: 50634340 | O28: 46788238 | P28: 54745233 | Q28: 50228624 | R28: 56773229 | S28: 61033583 | T28: 62681790 | U28: 64599717 | V28: 60397154 | W28: 61852949 | X28: 85444462 | Y28: 69606051 | Z28: 70386671 | AA28: 72834296 | AB28: 74577505 | AC28: 71697863 | AD28: 80470899 | AE28: 76840380 | AF28: 77750309 | AG28: 70831455 | AH28: 72798561 | AI28: 71956117 | AJ28: 66223067 | AK28: 89842958 | AL28: 67744169 | AM28: 69653590 | AN28: 67632785 | AO28: 61977586 | AP28: 71764765 | AQ28: 74129753 | AR28: 76889878 | AS28: 72938533 | AT28: 71278581 | AU28: 73210629 | AV28: 74781440 | AW28: 91036349 | AX28: 98064264 | AY28: 91550547 | AZ28: 78399939 | BB28: 4.1011584e+08 | BC28: 69749431 | BD28: 73860265 | BE28: 73073009 | BF28: 73990296 | BG28: 75859507 | BH28: 74432409 | BI28: 95573927 | BJ28: 91749622 | BK28: 86264426 | BL28: 85119678 | BM28: 86369092 | BN28: 99663297 | BO28: 95883995 | BP28: 92671215 | BQ28: 96654168 | BR28: 1.0171234e+08 | BS28: 96070398 | BT28: 96070398 | BU28: 87331704 | BV28: 1.3039114e+08 | BW28: 1.0011393e+08 | BX28: 99225297 | BY28: 95577508 | BZ28: 96559931 | CA28: 1.1002575e+08 | CB28: 1.0065431e+08 | CC28: 98093602 | CD28: 96614089 | CE28: 98168404 | CF28: 90703690 | CG28: 92429113 | CH28: 87160714 | CI28: 88445961 | CJ28: 1.0348374e+08 | CK28: 88144694 | CL28: 95035160 | CM28: 1.0054044e+08 | CN28: 1.0344796e+08 | CO28: 98320437 | CP28: 93558472
A29: Short Terrm Deposits | C29: 14522500 | D29: 19478821 | E29: 7732655.5 | F29: 2611021 | G29: 633522 | H29: 5613058 | I29: 3082059 | J29: 2902059 | K29: 2416061.1 | L29: 2925171.5 | M29: 2950383.8 | N29: 2761384.8 | O29: 2167616.1 | P29: 3786713.1 | Q29: 3801771.2 | R29: 3795213.1 | S29: 3801213.1 | T29: 3904555.5 | U29: 3904556 | V29: 6272519.1 | W29: 7143591.5 | X29: 7143591.5 | Y29: 5433591.5 | Z29: 5393591.5 | AA29: 5400678.8 | AB29: 5500678.8 | AC29: 5561878.8 | AD29: 3983114.7 | AE29: 3683114.7 | AF29: 3671914.7 | AG29: 3871914.7 | AH29: 3871914.7 | AI29: 5171914.7 | AJ29: 3271914.5 | AK29: 1769446.1 | AL29: 3809446.1 | AM29: 3809446.1 | AN29: 3609446.1 | AO29: 3074315.5 | AP29: 2274315.5 | AQ29: 2274315.5 | AR29: 2274315.5 | AS29: 2274315.5 | AT29: 2854315.5 | AU29: 2854315.5 | AV29: 4351393.5 | AW29: 3771393.5 | AX29: 6074315.5 | AY29: 9774315.5 | AZ29: 10374315 | BB29: 63584577 | BC29: 13672600 | BD29: 13772600 | BE29: 12272600 | BF29: 14211000 | BG29: 14211000 | BH29: 13511000 | BI29: 14521000 | BJ29: 14521000 | BK29: 13121000 | BL29: 12921000 | BM29: 12421000 | BN29: 13621000 | BO29: 14521000 | BP29: 14521000 | BQ29: 16321000 | BR29: 19971000 | BS29: 22220000 | BT29: 22220000 | BU29: 22420000 | BV29: 21454540 | BW29: 20164500 | BX29: 20764500 | BY29: 22764500 | BZ29: 23112500 | CA29: 21012500 | CB29: 23113478 | CC29: 25451022 | CD29: 25351000 | CE29: 23201000 | CF29: 19126000 | CG29: 19126000 | CH29: 18532000 | CI29: 18082000 | CJ29: 19233000 | CK29: 19233000 | CL29: 20733000 | CM29: 20783000 | CN29: 27093000 | CO29: 26763000 | CP29: 26161978
A30: Non Withdrawable Deposits | B30: 230364164 | C30: 2051000 | D30: 2136500 | E30: 474445.83 | F30: 300022565 | G30: 340939649 | H30: 380380553 | I30: 3.8154286e+08 | J30: 3.8756921e+08 | K30: 3.9012058e+08 | L30: 3.9337815e+08 | M30: 3.9587854e+08 | N30: 3.9903633e+08 | O30: 3.9676322e+08 | P30: 4.0302785e+08 | Q30: 4.0441526e+08 | R30: 4.0763727e+08 | S30: 4.1306786e+08 | T30: 4.1661354e+08 | U30: 414695613 | V30: 4.1875295e+08 | W30: 4.2270146e+08 | X30: 4.275702e+08 | Y30: 4.3270072e+08 | Z30: 4.3723721e+08 | AA30: 4.4186645e+08 | AB30: 4.458657e+08 | AC30: 4.5127342e+08 | AD30: 4.5172315e+08 | AE30: 4.5366494e+08 | AF30: 4.5755527e+08 | AG30: 4.6073869e+08 | AH30: 4.5877158e+08 | AI30: 4.6341671e+08 | AJ30: 4.6786503e+08 | AK30: 4.6919189e+08 | AL30: 4.7193559e+08 | AM30: 4.7443502e+08 | AN30: 4.7855895e+08 | AO30: 4.7912021e+08 | AP30: 4.8296453e+08 | AQ30: 4.855553e+08 | AR30: 4.8908412e+08 | AS30: 4.9199495e+08 | AT30: 4.9379049e+08 | AU30: 4.9185844e+08 | AV30: 4.976021e+08 | AW30: 4.9992735e+08 | AX30: 5.0396971e+08 | AY30: 5.0812073e+08 | AZ30: 5.1163117e+08 | BB30: 2.587018e+09 | BC30: 5.2061708e+08 | BD30: 5.2432741e+08 | BE30: 5.2824784e+08 | BF30: 5.3026791e+08 | BG30: 528398698 | BH30: 5.3429901e+08 | BI30: 5.3664328e+08 | BJ30: 5.4223199e+08 | BK30: 5.4744943e+08 | BL30: 5.5173539e+08 | BM30: 5.5397571e+08 | BN30: 5.5788583e+08 | BO30: 5.6328091e+08 | BP30: 5.6661867e+08 | BQ30: 5.7132642e+08 | BR30: 5.7522614e+08 | BS30: 578555889 | BT30: 578555889 | BU30: 5.8087755e+08 | BV30: 5.8464052e+08 | BW30: 5.9002917e+08 | BX30: 5.9396604e+08 | BY30: 5.9720211e+08 | BZ30: 5.9257098e+08 | CA30: 5.9622446e+08 | CB30: 5.9704795e+08 | CC30: 5.9953102e+08 | CD30: 6.0428353e+08 | CE30: 6.0807958e+08 | CF30: 6.0972224e+08 | CG30: 607996816 | CH30: 6.129141e+08 | CI30: 6.1748143e+08 | CJ30: 6.2145422e+08 | CK30: 624731589 | CL30: 6.3108703e+08 | CM30: 6.3292618e+08 | CN30: 6.3709977e+08 | CO30: 6.4090813e+08 | CP30: 6.4788293e+08
A31: Total Deposit Liabilities | B31: =SUM(B28:B30) -> 249530153 | C31: =SUM(C28:C30) -> 251655387 | D31: =SUM(D28:D30) -> 281820645 | E31: =SUM(E28:E30) -> 2.9362173e+08 | F31: =SUM(F28:F30) -> 322200801 | G31: =SUM(G28:G30) -> 370403370 | H31: =SUM(H28:H30) -> 440828441 | I31: =SUM(I28:I30) -> 4.2854396e+08 | ... CP31: =SUM(CP28:CP30) -> 7.6760338e+08
A32: Tax Payable | B32: 135550 | C32: 140547 | D32: 367209 | E32: 957101.88 | F32: 780541 | G32: 613419 | I32: 0 | J32: 0 | K32: 0 | L32: 0 | M32: 0 | N32: 0 | O32: 0 | P32: 0 | Q32: 0 | R32: 0 | S32: 0 | T32: 0 | U32: =1370163+1872695 -> 3242858 | V32: 0 | W32: 0 | X32: 0 | Y32: 0 | Z32: 0 | AA32: 0 | AB32: 0 | AC32: 0 | AD32: 0 | AE32: 0 | AF32: 0 | AG32: 0 | AH32: 0 | AI32: 0 | AJ32: 0 | AK32: 0 | AL32: 0 | AM32: 0 | AN32: 0 | AO32: 0 | AP32: 0 | AQ32: 0 | AR32: 0 | AS32: 0 | AT32: 0 | AU32: -141169 | AV32: 0 | AW32: 0 | AX32: 0 | AY32: 0 | AZ32: 0 | BB32: 0 | BC32: 0 | BD32: 0 | BE32: 0 | BF32: 0 | BG32: 32123 | BH32: 0 | BI32: 0 | BJ32: 0 | BK32: 0 | BL32: 0 | BM32: 0 | BN32: 0 | BO32: 0 | BP32: 0 | BQ32: 0 | BR32: 0 | BS32: 0 | BT32: 1043645 | BU32: 0 | BV32: 0 | BW32: 0 | BX32: 0 | BY32: 0 | BZ32: 0 | CA32: 0 | CB32: 0 | CC32: 0 | CD32: 0 | CE32: 0 | CF32: 0 | CG32: 2517171 | CH32: 0 | CI32: 0 | CJ32: 0 | CK32: 0 | CL32: 0 | CM32: 0 | CN32: 0 | CO32: 0 | CP32: 0
A33: Dividends Payable | C33: 18506917 | F33: 1 | G33: 35477551 | H33: 37389190 | I33: 0 | J33: 0 | K33: 78235.27 | L33: 0 | M33: 0 | N33: 0 | O33: 0 | P33: 0 | Q33: 0 | R33: 0 | S33: 0 | T33: 0 | U33: 0 | V33: 0 | W33: 0 | X33: 0 | Y33: 0 | Z33: 0 | AA33: 0 | AB33: 0 | AC33: 0 | AD33: 0 | AE33: 0 | AF33: 0 | AG33: 0 | AH33: 0 | AI33: 0 | AJ33: 0 | AK33: 0 | AL33: 0 | AM33: 0 | AN33: 0 | AO33: 0 | AP33: 0 | AQ33: 0 | AR33: 0 | AS33: 0 | AT33: 0 | AV33: 0 | AW33: 0 | AX33: 0 | AY33: 0 | AZ33: 0 | BB33: 0 | BC33: 0 | BD33: 0 | BE33: 0 | BF33: 0 | BG33: 0 | BH33: 0 | BI33: 0 | BJ33: 0 | BK33: 0 | BL33: 0 | BM33: 0 | BN33: 0 | BO33: 0 | BP33: 0 | BQ33: 0 | BR33: 0 | BS33: 0 | BT33: =77767126 -> 77767126 | BU33: 0 | BV33: 0 | BW33: 0 | BX33: 0 | BY33: 0 | BZ33: 0 | CA33: 0 | CB33: 0 | CC33: 0 | CD33: 0 | CE33: 0 | CF33: 0 | CG33: 80985972 | CH33: 0 | CI33: 0 | CJ33: 0 | CK33: 0 | CL33: 0 | CM33: 0 | CN33: 0 | CO33: 0 | CP33: 0
A34: Deferred Tax Liability | I34: 0 | J34: 0 | K34: 0 | L34: 0 | M34: 0 | N34: 0 | O34: 0 | P34: 0 | Q34: 0 | R34: 0 | S34: 0 | T34: 0 | V34: 0 | W34: 0 | X34: 0 | Y34: 0 | Z34: 0 | AA34: 0 | AB34: 0 | AC34: 0 | AD34: 0 | AE34: 0 | AF34: 0 | AG34: 0 | AH34: 0 | AI34: 0 | AJ34: 0 | AK34: 0 | AL34: 0 | AM34: 0 | AN34: 0 | AO34: 0 | AP34: 0 | AQ34: 0 | AR34: 0 | AS34: 0 | AT34: 0 | AV34: 0 | AW34: 0 | AX34: 0 | AY34: 0 | AZ34: 0 | BB34: 0 | BC34: 0 | BD34: 0 | BE34: 0 | BF34: 0 | BG34: 0 | BH34: 0 | BI34: 0 | BJ34: 0 | BK34: 0 | BL34: 0 | BM34: 0 | BN34: 0 | BO34: 0 | BP34: 0 | BQ34: 0 | BR34: 0 | BS34: 0 | BU34: 0 | BV34: 0 | BW34: 0 | BX34: 0 | BY34: 0 | BZ34: 0 | CA34: 0 | CB34: 0 | CC34: 0 | CD34: 0 | CE34: 0 | CF34: 0 | CG34: 0 | CH34: 0 | CI34: 0 | CJ34: 0 | CK34: 0 | CL34: 0 | CM34: 0 | CN34: 0 | CO34: 0 | CP34: 0
A35: Retirement Benefits Liabilty | I35: 0 | J35: 0 | K35: 0 | L35: 0 | M35: 0 | N35: 0 | O35: 0 | P35: 0 | Q35: 0 | R35: 0 | S35: 0 | T35: 0 | V35: 0 | W35: 0 | X35: 0 | Y35: 0 | Z35: 0 | AA35: 0 | AB35: 0 | AC35: 0 | AD35: 0 | AE35: 0 | AF35: 0 | AG35: 0 | AH35: 0 | AI35: 0 | AJ35: 0 | AK35: 0 | AL35: 0 | AM35: 0 | AN35: 0 | AO35: 0 | AP35: 0 | AQ35: 0 | AR35: 0 | AS35: 0 | AT35: 0 | AV35: 0 | AW35: 0 | AX35: 0 | AY35: 0 | AZ35: 0 | BB35: 0 | BC35: 0 | BD35: 0 | BE35: 0 | BF35: 0 | BG35: 0 | BH35: 0 | BI35: 0 | BJ35: 0 | BK35: 0 | BL35: 0 | BM35: 0 | BN35: 0 | BO35: 0 | BP35: 0 | BQ35: 0 | BR35: 0 | BS35: 0 | BU35: 0 | BV35: 0 | BW35: 0 | BX35: 0 | BY35: 0 | BZ35: 0 | CA35: 0 | CB35: 0 | CC35: 0 | CD35: 0 | CE35: 0 | CF35: 0 | CG35: 0 | CH35: 0 | CI35: 0 | CJ35: 0 | CK35: 0 | CL35: 0 | CM35: 0 | CN35: 0 | CO35: 0 | CP35: 0
A36: Other Liabilities | B36: 23813301 | C36: 4745318 | D36: 24806615 | E36: 37504104 | F36: 50368944 | G36: 27658614 | H36: 33476442 | I36: 85762468 | J36: 75420024 | K36: 42081591 | L36: 41771384 | M36: 44542336 | N36: 47583625 | O36: 50005482 | P36: 53568285 | Q36: 56681503 | R36: 61003355 | S36: 64544165 | T36: 97172958 | U36: =99234827-1872695 -> 97362132 | V36: 1.0386365e+08 | W36: 1.058956e+08 | X36: 64613289 | Y36: 66364445 | Z36: 68142261 | AA36: 72179503 | AB36: 76011611 | AC36: 78352881 | AD36: 82757925 | AE36: 85631243 | AF36: 89352891 | AG36: 1.0823349e+08 | AH36: 1.0826054e+08 | AI36: 53958233 | AJ36: 57713691 | AK36: 15868286 | AL36: 17484200 | AM36: 15910659 | AN36: 19949567 | AO36: 20719215 | AP36: 25234579 | AQ36: 28738625 | AR36: 33624447 | AS36: 48141127 | AT36: 59894224 | AU36: 59830495 | AV36: 69178371 | AW36: 28908854 | AX36: 19151176 | AY36: 20696932 | AZ36: 25013434 | BB36: 1.8554206e+08 | BC36: 43147513 | BD36: 49707267 | BE36: 52539744 | BF36: 60950910 | BG36: 60777338 | BH36: 66477412 | BI36: 17834656 | BJ36: 23741301 | BK36: 27703288 | BL36: 31503844 | BM36: 37965513 | BN36: 45501864 | BO36: 51899397 | BP36: 58120447 | BQ36: 61316585 | BR36: 68015118 | BS36: 82540334 | BT36: =3740379 -> 3740379 | BU36: 88322646 | BV36: 21196818 | BW36: 18826454 | BX36: 26886658 | BY36: 32149571 | BZ36: 38707340 | CA36: 41159181 | CB36: 43566772 | CC36: 50323031 | CD36: 58248332 | CE36: 65191920 | CF36: 86141666 | CG36: =2702447 -> 2702447 | CH36: 90353059 | CI36: 96801810 | CJ36: 20654991 | CK36: 29598136 | CL36: 29759881 | CM36: 38537429 | CN36: 47122284 | CO36: 54353885 | CP36: 60722400
A37: External Borrowings | B37: 98196182 | C37: 73980442 | D37: 75498160 | E37: 75604045 | F37: 14235893 | H37: 0 | I37: 0 | J37: 0 | K37: 0 | L37: 0 | M37: 0 | N37: 0 | O37: 0 | P37: 0 | Q37: 0 | R37: 0 | S37: 0 | T37: 0 | V37: 0 | W37: 0 | X37: 0 | Y37: 0 | Z37: 0 | AB37: 0 | AC37: 0 | AD37: 0 | AE37: 0 | AF37: 0 | AG37: 0 | AH37: 0 | AI37: 0 | AJ37: 0 | AK37: 0 | AL37: 0 | AM37: 0 | AN37: 0 | AO37: 0 | AP37: 0 | AQ37: 0 | AR37: 0 | AS37: 0 | AT37: 0 | AV37: 0 | AW37: 0 | AX37: 0 | AY37: 0 | AZ37: 0 | BB37: 0 | BC37: 0 | BD37: 0 | BE37: 0 | BF37: 0 | BG37: 0 | BH37: 0 | BI37: 0 | BJ37: 0 | BK37: 0 | BL37: 0 | BM37: 0 | BN37: 0 | BO37: 0 | BP37: 0 | BQ37: 0 | BR37: 0 | BS37: 0 | BU37: 0 | BV37: 0 | BW37: 0 | BX37: 0 | BY37: 0 | BZ37: 0 | CA37: 0 | CB37: 0 | CC37: 0 | CD37: 0 | CE37: 0 | CF37: 0 | CG37: 0 | CH37: 0 | CI37: 0 | CJ37: 0 | CK37: 0 | CL37: 0 | CM37: 0 | CN37: 0 | CO37: 0 | CP37: 0
A38: Total Liabilities | B38: =SUM(B31:B37) -> 371675186 | C38: =SUM(C31:C37) -> 349028611 | D38: =SUM(D31:D37) -> 382492629 | E38: =SUM(E31:E37) -> 4.0768699e+08 | F38: =SUM(F31:F37) -> 387586180 | G38: =SUM(G31:G37) -> 434152954 | H38: =SUM(H31:H37) -> 511694073 | I38: =SUM(I31:I37) -> 5.1430643e+08 | ... CP38: =SUM(CP31:CP37) -> 8.2832578e+08
A39: Share Capital | B39: 5058510 | C39: 41027979 | D39: 41319195 | E39: 44676737 | F39: 67258769 | G39: 67556532 | H39: 73461221 | I39: 73503822 | J39: 73685122 | K39: 73880951 | L39: 74103901 | M39: 74324907 | N39: 74536157 | O39: 74697357 | P39: 74738057 | Q39: 74882757 | R39: 74901757 | S39: 75043107 | T39: 75112907 | U39: 75112907 | V39: 75199407 | W39: 75263207 | X39: 75291930 | Y39: 75479350 | Z39: 75537150 | AA39: 75550950 | AB39: 75613870 | AC39: 75709870 | AD39: 75727050 | AE39: 76050950 | AF39: 76225450 | AG39: 76348050 | AH39: 76348050 | AI39: 76556815 | AJ39: 76756315 | AK39: 78671845 | AL39: 78779389 | AM39: 79033796 | AN39: 79083296 | AO39: 79167296 | AP39: 79255402 | AQ39: 79406108 | AR39: 79623746 | AS39: 79681767 | AT39: 80370014 | AU39: 80370014 | AV39: 81185589 | AW39: 81282836 | AX39: 81366780 | AY39: 82735268 | AZ39: 83348481 | BB39: 420356850 | BC39: 84224873 | BD39: 84471578 | BE39: 84643828 | BF39: 84738607 | BG39: =39709604+4368593+40660411 -> 84738608 | BH39: 84761007 | BI39: 84996324 | BJ39: 85232930 | BK39: 85548340 | BL39: 85923420 | BM39: 86199470 | BN39: 86369570 | BO39: 86700570 | BP39: 86951558 | BQ39: 87164925 | BR39: 87701751 | BS39: 87852651 | BT39: 87852651 | BU39: 88822455 | BV39: 88951167 | BW39: 89094869 | BX39: 89371617 | BY39: 89534757 | BZ39: 89881934 | CA39: 89947434 | CB39: 90048555 | CC39: 90251549 | CD39: 91231117 | CE39: 91406814 | CF39: 91740614 | CG39: 91740614 | CH39: 91886264 | CI39: 92080154 | CJ39: 92661204 | CK39: 92868404 | CL39: 93156630 | CM39: 93331730 | CN39: 93680930 | CO39: 94227146 | CP39: 94719939
A40: Capital Grants | B40: 5058510 | I40: 0 | J40: 0 | K40: 0 | L40: 0 | M40: 0 | N40: 0 | O40: 0 | P40: 0 | Q40: 0 | R40: 0 | S40: 0 | T40: 0 | U40: 0 | V40: 0 | W40: 0 | X40: 0 | Y40: 0 | Z40: 0 | AB40: 0 | AC40: 0 | AD40: 0 | AE40: 0 | AF40: 0 | AG40: 0 | AH40: 0 | AI40: 0 | AJ40: 0 | AK40: 0 | AL40: 0 | AM40: 0 | AN40: 0 | AO40: 0 | AP40: 0 | AQ40: 0 | AR40: 0 | AS40: 0 | AT40: 0 | AV40: 0 | AW40: 0 | AX40: 0 | AY40: 0 | AZ40: 0 | BB40: 0 | BC40: 0 | BD40: 0 | BE40: 0 | BF40: 0 | BG40: 0 | BH40: 0 | BI40: 0 | BJ40: 0 | BK40: 0 | BL40: 0 | BM40: 0 | BN40: 0 | BO40: 0 | BP40: 0 | BQ40: 0 | BR40: 0 | BS40: 0 | BU40: 0 | BV40: 0 | BW40: 0 | BX40: 0 | BY40: 0 | BZ40: 0 | CA40: 0 | CB40: 0 | CC40: 0 | CD40: 0 | CE40: 0 | CF40: 0 | CG40: 0 | CH40: 0 | CI40: 0 | CJ40: 0 | CK40: 0 | CL40: 0 | CM40: 0 | CN40: 0 | CO40: 0 | CP40: 0
A41: Prior Year Retained Earnigs | B41: 11835925 | C41: 22842014 | D41: 28642685 | E41: 28642685 | F41: 41987254 | G41: 66804781 | H41: 85290511 | I41: 1.0522816e+08 | J41: 92673150 | K41: 87459635 | L41: 87459635 | M41: 87459635 | N41: 87459997 | O41: 87459997 | P41: 87459997 | Q41: 87459997 | R41: 87459997 | S41: 87459997 | T41: 87459997 | U41: =92673511+4241241-9454756 -> 87459996 | V41: 98395373 | W41: 98395373 | X41: 98395373 | Y41: 98395373 | Z41: 98395373 | AA41: 98395373 | AB41: 98395373 | AC41: 98395373 | AD41: 98395373 | AE41: 98395373 | AF41: 98395373 | AG41: 99109747 | AH41: 99117197 | AI41: 1.2674323e+08 | AJ41: 1.2674323e+08 | AK41: 1.2674323e+08 | AL41: 1.266404e+08 | AM41: 1.3185392e+08 | AN41: 1.3185392e+08 | AO41: 1.3185392e+08 | AP41: 1.3185392e+08 | AQ41: 1.3185392e+08 | AR41: 1.3185392e+08 | AS41: 1.3185392e+08 | AT41: 1.266404e+08 | AU41: 1.2674323e+08 | AV41: 1.4538891e+08 | AW41: 1.4538891e+08 | AX41: 1.4538891e+08 | AY41: 1.4538891e+08 | AZ41: 1.4538891e+08 | BB41: 7.2694456e+08 | BC41: 1.4538891e+08 | BD41: 1.4538891e+08 | BE41: 1.4538891e+08 | BF41: 1.4538891e+08 | BG41: 145388913 | BH41: 1.6274497e+08 | BI41: 1.6274497e+08 | BJ41: 1.6274497e+08 | BK41: 1.6274497e+08 | BL41: 1.6274497e+08 | BM41: 1.6274497e+08 | BN41: 1.6274497e+08 | BO41: 1.6274497e+08 | BP41: 1.6274497e+08 | BQ41: 1.6274497e+08 | BR41: 1.6274497e+08 | BS41: 1.6274497e+08 | BT41: 162744967 | BU41: 1.7690475e+08 | BV41: 1.7690475e+08 | BW41: 1.7690475e+08 | BX41: 1.7690475e+08 | BY41: 1.7690475e+08 | BZ41: 1.7690475e+08 | CA41: 1.7690475e+08 | CB41: 1.7690475e+08 | CC41: 1.7690475e+08 | CD41: 1.7690475e+08 | CE41: 1.7697195e+08 | CF41: 1.7703915e+08 | CG41: 176904749 | CH41: 1.7710635e+08 | CI41: 1.7855689e+08 | CJ41: 1.7859189e+08 | CK41: 1.7859189e+08 | CL41: 1.7872629e+08 | CM41: 1.7872629e+08 | CN41: 1.7872629e+08 | CO41: 1.7877329e+08 | CP41: 1.7883049e+08
A42: Current Year Surplus | E42: 13344568 | F42: 19604846 | G42: 18304471 | H42: 7382638 | I42: -2547032.5 | J42: 5184516.2 | K42: 8499121.4 | L42: 8401507.7 | M42: 10638453 | N42: 21324690 | O42: 18334763 | P42: 27498158 | Q42: 37462432 | R42: 40863811 | S42: 47300356 | T42: 18380415 | U42: =104330710+4241241-9454756-U41 -> 11657199 | V42: 439270.18 | W42: 4336331.2 | X42: 5822529.8 | Y42: 6193149 | Z42: 10721731 | AA42: 25094260 | AB42: 27591487 | AC42: 32438939 | AD42: 35982398 | AE42: 42361872 | AF42: 49373027 | AG42: 34568896 | AH42: =126743228-99117196 -> 27626032 | AI42: 4215190.2 | AJ42: 7446296.2 | AK42: 8442656.9 | AL42: 7987493.3 | AM42: 13137787 | AN42: 27479635 | AO42: 31263361 | AP42: 30481937 | AQ42: 32247910 | AR42: 34528368 | AS42: 28795651 | AT42: 24360400 | AU42: 18645686 | AV42: 7048076.5 | AW42: 9615532.4 | AX42: 21852931 | AY42: 16852969 | AZ42: 16523321 | BB42: 92455243 | BC42: 19646034 | BD42: 20255977 | BE42: 19559975 | BF42: 21695270 | BG42: =162745129-BG41 -> 17356216 | BH42: 3092220 | BI42: -1025671.6 | BJ42: -307492.51 | BK42: 17740003 | BL42: 17250304 | BM42: 19775738 | BN42: 15305733 | BO42: 23934423 | BP42: 27733378 | BQ42: 33576266 | BR42: 36131737 | BS42: 26427142 | BT42: =17699727-3539945 -> 14159782 | BU42: 1225.02 | BV42: 1480825.1 | BW42: 1631135.9 | BX42: 2601389.2 | BY42: 2610646.7 | BZ42: 20720815 | CA42: 19266249 | CB42: 20396851 | CC42: 25267096 | CD42: 27310452 | CE42: 26859560 | CF42: 2530653 | CG42: =4368747-873749 -> 3494998 | CH42: 6402410.2 | CI42: 12808217 | CJ42: 4692622.7 | CK42: 1342571.7 | CL42: -1714145.6 | CM42: 11168490 | CN42: 3632321.7 | CO42: 3780132.3 | CP42: 5153741.8
A43: Statutory Reserves | B43: 6638993 | C43: 9477422 | D43: 11070308 | E43: 14182416 | F43: 18007281 | G43: 22583399 | H43: 24368909 | I43: 22523249 | J43: 24368909 | K43: 24368909 | L43: 24368909 | M43: 24368909 | N43: 24368909 | O43: 24368909 | P43: 24368909 | Q43: 24368909 | R43: 24368909 | S43: 24368909 | T43: 24368909 | U43: 27283209 | V43: 27997583 | W43: 27997583 | X43: 27997583 | Y43: 27997583 | Z43: 27997583 | AA43: 27997583 | AB43: 27997583 | AC43: 27997583 | AD43: 27997583 | AE43: 27997583 | AF43: 27997583 | AG43: 27283209 | AH43: 34191579 | AI43: 34191579 | AJ43: 34191579 | AK43: 34191579 | AL43: 34191579 | AM43: 34191579 | AN43: 34191579 | AO43: 34191579 | AP43: 34191579 | AQ43: 34191579 | AR43: 34191579 | AS43: 34191579 | AT43: 34191579 | AU43: 38878707 | AV43: 38878707 | AW43: 38878707 | AX43: 38878707 | AY43: 38878707 | AZ43: 38878707 | BB43: 194393535 | BC43: 38878707 | BD43: 38878707 | BE43: 38878707 | BF43: 38878707 | BG43: =38878707+4339054 -> 43217761 | BH43: 43217923 | BI43: 43217923 | BJ43: 43217923 | BK43: 43217923 | BL43: 43217923 | BM43: 43217923 | BN43: 43217923 | BO43: 43217923 | BP43: 43217923 | BQ43: 43217923 | BR43: 43217923 | BS43: 43217923 | BT43: 46757868 | BU43: 46757868 | BV43: 46757868 | BW43: 46757868 | BX43: 46757868 | BY43: 46757868 | BZ43: 46757868 | CA43: 46757868 | CB43: 46757868 | CC43: 46757868 | CD43: 46757868 | CE43: 46757868 | CF43: 47390531 | CG43: 47631616 | CH43: 46757868 | CI43: 49810467 | CJ43: 49810467 | CK43: 49810467 | CL43: 49810467 | CM43: 49810467 | CN43: 49810467 | CO43: 49810467 | CP43: 49810467
A44: Other Reserves | B44: 27818777 | I44: 0 | J44: 0 | K44: 0 | L44: 0 | M44: 0 | N44: 0 | O44: 0 | P44: 0 | Q44: 0 | R44: 0 | S44: 0 | T44: 0 | V44: 0 | W44: 0 | X44: 0 | Y44: 0 | Z44: 0 | AA44: 0 | AB44: 0 | AC44: 0 | AD44: 0 | AE44: 0 | AF44: 0 | AG44: 0 | AI44: 0 | AJ44: 0 | AK44: 0 | AL44: 0 | AM44: 0 | AN44: 0 | AO44: 0 | AP44: 0 | AQ44: 0 | AR44: 0 | AS44: 0 | AT44: 0 | AV44: 0 | AW44: 0 | AX44: 0 | AY44: 0 | AZ44: 0 | BB44: 0 | BC44: 0 | BD44: 0 | BE44: 0 | BF44: 0 | BG44: 0 | BH44: 0 | BI44: 0 | BJ44: 0 | BK44: 0 | BL44: 0 | BM44: 0 | BN44: 0 | BO44: 0 | BP44: 0 | BQ44: 0 | BR44: 0 | BS44: 0 | BU44: 0 | BV44: 0 | BW44: 0 | BX44: 0 | BY44: 0 | BZ44: 0 | CA44: 0 | CB44: 0 | CC44: 0 | CD44: 0 | CE44: 0 | CF44: 0 | CG44: 0 | CH44: 0 | CI44: 0 | CJ44: 0 | CK44: 0 | CL44: 0 | CM44: 0 | CN44: 0 | CO44: 0 | CP44: 0
A45: Revaluation Reserves | D45: -9454756 | G45: -5213515 | H45: -5213515 | I45: -5213515 | J45: -5213515 | K45: 0 | L45: 0 | M45: 0 | N45: 0 | O45: 0 | P45: 0 | Q45: 0 | R45: 0 | S45: 0 | T45: 0 | V45: 0 | W45: 0 | X45: 0 | Y45: 0 | Z45: 0 | AA45: 0 | AB45: 0 | AC45: 0 | AD45: 0 | AE45: 0 | AF45: 0 | AG45: 0 | AH45: 0 | AI45: 0 | AJ45: 0 | AK45: 0 | AL45: 0 | AM45: 0 | AN45: 0 | AO45: 0 | AP45: 0 | AQ45: 0 | AR45: 0 | AS45: 0 | AT45: 0 | AV45: 0 | AW45: 0 | AX45: 0 | AY45: 0 | AZ45: 0 | BB45: 0 | BC45: 0 | BD45: 0 | BE45: 0 | BF45: 0 | BG45: 0 | BH45: 0 | BI45: 0 | BJ45: 0 | BK45: 0 | BL45: 0 | BM45: 0 | BN45: 0 | BO45: 0 | BP45: 0 | BQ45: 0 | BR45: 0 | BS45: 0 | BU45: 0 | BV45: 0 | BW45: 0 | BX45: 0 | BY45: 0 | BZ45: 0 | CA45: 0 | CB45: 0 | CC45: 0 | CD45: 0 | CE45: 0 | CF45: 0 | CG45: 0 | CH45: 0 | CI45: 0 | CJ45: 0 | CK45: 0 | CL45: 0 | CM45: 0 | CN45: 0 | CO45: 0 | CP45: 0
A46: Proposed Dividends | B46: 0 | C46: 549460 | D46: 587910 | I46: 0 | J46: 0 | K46: 0 | L46: 0 | M46: 0 | N46: 0 | O46: 0 | P46: 0 | Q46: 0 | R46: 0 | S46: 0 | T46: 0 | V46: 0 | W46: 0 | X46: 0 | Y46: 0 | Z46: 0 | AA46: 0 | AB46: 0 | AC46: 0 | AD46: 0 | AE46: 0 | AF46: 0 | AG46: 0 | AH46: 0 | AI46: 0 | AJ46: 0 | AK46: 0 | AL46: 0 | AM46: 0 | AN46: 0 | AO46: 0 | AP46: 0 | AQ46: 0 | AR46: 0 | AS46: 0 | AT46: 0 | AV46: 0 | AW46: 0 | AX46: 0 | AY46: 0 | AZ46: 0 | BB46: 0 | BC46: 0 | BD46: 0 | BE46: 0 | BF46: 0 | BG46: 0 | BH46: 0 | BI46: 0 | BJ46: 0 | BK46: 0 | BL46: 0 | BM46: 0 | BN46: 0 | BO46: 0 | BP46: 0 | BQ46: 0 | BR46: 0 | BS46: 0 | BU46: 0 | BV46: 0 | BW46: 0 | BX46: 0 | BY46: 0 | BZ46: 0 | CA46: 0 | CB46: 0 | CC46: 0 | CD46: 0 | CE46: 0 | CF46: 0 | CG46: 0 | CH46: 0 | CI46: 0 | CJ46: 0 | CK46: 0 | CL46: 0 | CM46: 0 | CN46: 0 | CO46: 0 | CP46: 0
A47: Adjustment To Equity | I47: 0 | J47: 0 | K47: 0 | L47: 0 | M47: 0 | N47: 0 | O47: 0 | P47: 0 | Q47: 0 | R47: 0 | S47: 0 | T47: 0 | V47: 0 | W47: 0 | X47: 0 | Y47: 0 | Z47: 0 | AA47: 0 | AB47: 0 | AC47: 0 | AD47: 0 | AE47: 0 | AF47: 0 | AG47: 0 | AH47: 0 | AI47: 0 | AJ47: 0 | AK47: 0 | AL47: 0 | AM47: 0 | AN47: 0 | AO47: 0 | AP47: 0 | AQ47: 0 | AR47: 0 | AS47: 0 | AT47: 0 | AV47: 0 | AW47: 0 | AX47: 0 | AY47: 0 | AZ47: 0 | BB47: 0 | BC47: 0 | BD47: 0 | BE47: 0 | BF47: 0 | BG47: 0 | BH47: 0 | BI47: 0 | BJ47: 0 | BK47: 0 | BL47: 0 | BM47: 0 | BN47: 0 | BO47: 0 | BP47: 0 | BQ47: 0 | BR47: 0 | BS47: 0 | BU47: 0 | BV47: 0 | BW47: 0 | BX47: 0 | BY47: 0 | BZ47: 0 | CA47: 0 | CB47: 0 | CC47: 0 | CD47: 0 | CE47: 0 | CF47: 0 | CG47: 194400 | CH47: 0 | CI47: 0 | CJ47: 0 | CK47: 0 | CL47: 0 | CM47: 0 | CN47: 0 | CO47: 0 | CP47: 0
A48: Total Equity | B48: =SUM(B39:B47) -> 56410715 | C48: =SUM(C39:C47) -> 73896875 | D48: =SUM(D39:D47) -> 72165342 | E48: =SUM(E39:E47) -> 1.0084641e+08 | F48: =SUM(F39:F47) -> 146858150 | G48: =SUM(G39:G47) -> 170035668 | H48: =SUM(H39:H47) -> 185289764 | I48: =SUM(I39:I47) -> 1.9349468e+08 | ... CP48: =SUM(CP39:CP47) -> 3.2851464e+08
A49: Total Liabilities and Equity | B49: =B48+B38 -> 428085901 | C49: =C48+C38 -> 422925486 | D49: =D48+D38 -> 454657971 | E49: =E48+E38 -> 5.0853339e+08 | F49: =F48+F38 -> 534444330 | G49: =G48+G38 -> 604188622 | H49: =H48+H38 -> 696983837 | I49: =I48+I38 -> 7.0780111e+08 | ... CP49: =CP48+CP38 -> 1.1568404e+09
BG50: =BG49-BG27 -> 1 | BH50: =BH49-BH27 -> 0 | BI50: =BI49-BI27 -> 0 | BJ50: =BJ49-BJ27 -> 0 | BK50: =BK49-BK27 -> 0 | BL50: =BL49-BL27 -> 0 | BM50: =BM49-BM27 -> 0 | BN50: =BN49-BN27 -> 0 | ... BT50: =BT49-BT27 -> -1
B51: =B49-B27 -> 7280766 | C51: =C49-C27 -> 0 | D51: =D49-D27 -> 0 | E51: =E49-E27 -> -0.0049999356 | F51: =F49-F27 -> 1 | G51: =G49-G27 -> 1 | H51: =H49-H27 -> 0 | I51: =I49-I27 -> -3.0000001 | ... U51: =U49-U27 -> 1 | AD51: =AD49-AD27 -> 0 | AE51: =AE49-AE27 -> 0 | AF51: =AF49-AF27 -> 0 | AG51: =AG49-AG27 -> 0 | AH51: =AH49-AH27 -> 3.1070002 | CG51: =CG27-CG49 -> -7.02 | CH51: =CH27-CH49 -> -7.1726014e+08 | CI51: =CI27-CI49 -> 0 | CJ51: =CJ27-CJ49 -> 0 | CK51: =CK27-CK49 -> 6 | CL51: =CL27-CL49 -> 0 | CM51: =CM27-CM49 -> 0 | CN51: =CN27-CN49 -> 0 | ... CP51: =CP27-CP49 -> 0
AH53: =126775228-AH41 -> 27658031

Sheet Evolutitve SCI
B2: 2010 Audited | C2: 2011 Audited | D2: 2012 Audited | E2: 2013 Audited | F2: 2014 Audited | G2: 2015 Audited | H2: Audited-2016 | I2: 42736 | J2: 42767 | K2: 42795 | L2: 42826 | M2: 42856 | N2: 42887 | O2: 42917 | P2: 42948 | Q2: 42979 | R2: 43009 | S2: 43040 | T2: 43070 | U2: Audited 2017 | V2: 43101 | W2: 43132 | X2: 43160 | Y2: 43191 | Z2: 43221 | AA2: 43252 | AB2: 43282 | AC2: 43313 | AD2: 43344 | AE2: 43374 | AF2: 43405 | AG2: 43435 | AH2: Audited 2018 | AI2: 43466 | AJ2: 43497 | AK2: 43525 | AL2: 43556 | AM2: 43586 | AN2: 43617 | AO2: 43647 | AP2: 43678 | AQ2: 43709 | AR2: 43739 | AS2: 43770 | AT2: 43800 | AU2: Audited -19 | AV2: 43831 | AW2: 43862 | AX2: 43891 | AY2: 43922 | AZ2: 43952 | BA2: 43983 | BB2: 44013 | BC2: 44044 | BD2: 44075 | BE2: 44105 | BF2: 44136 | BG2: 44166 | BH2: Audited 2020 | BI2: 44197 | BJ2: 44228 | BK2: 44256 | BL2: 44287 | BM2: 44317 | BN2: 44348 | BO2: 44378 | BP2: 44409 | BQ2: 44440 | BR2: 44470 | BS2: 44501 | BT2: 44531 | BU2: AUDITED 2021 | BV2: 44562 | BW2: 44593 | BX2: 44621 | BY2: 44652 | BZ2: 44682 | CA2: 44713 | CB2: 44743 | CC2: 44774 | CD2: 44805 | CE2: 44835 | CF2: 44866 | CG2: 44896 | CH2: Audited 2022 | CI2: 44927 | CJ2: 44958 | CK2: 44986 | CL2: 45017 | CM2: 45047 | CN2: 45078 | CO2: 45108 | CP2: 45139 | CQ2: 45170
A3: Financial Income | B3: =B4+B7 -> 53102019 | C3: =C4+C7 -> 67876418 | D3: =D4+D7 -> 76649112 | E3: =E4+E7 -> 93967038 | F3: =F4+F7 -> 97400688 | G3: =G4+G7 -> 109849160 | H3: =H4+H7 -> 121408969 | I3: =I4+I7 -> 3091134.1 | ... CQ3: =CQ4+CQ7 -> 1.3218021e+08
A4: Financial Income From Loans Portfolio | B4: =SUM(B5:B6) -> 50952511 | C4: =SUM(C5:C6) -> 64376963 | D4: =SUM(D5:D6) -> 71327939 | E4: =SUM(E5:E6) -> 91151179 | F4: =SUM(F5:F6) -> 96129457 | G4: =SUM(G5:G6) -> 100764347 | H4: =SUM(H5:H6) -> 110622193 | I4: =SUM(I5:I6) -> 3028199.4 | ... CQ4: =SUM(CQ5:CQ6) -> 1.0459137e+08
A5: Interest from Loans Portfolio | B5: 50952511 | C5: 64376963 | D5: 71327939 | E5: 86602624 | F5: 88158935 | G5: 100764347 | H5: 110622193 | I5: 2868188.9 | J5: 14794810 | K5: 24180326 | L5: 31297315 | M5: 41273174 | N5: 49549690 | O5: 53182016 | P5: 68046945 | Q5: 84380465 | R5: 95511940 | S5: 1.0620336e+08 | T5: 1.1721042e+08 | U5: =98585000+19265753 -> 117850753 | V5: 9208005.3 | W5: 18006762 | X5: 26799725 | Y5: 37559024 | Z5: 47882224 | AA5: 57664039 | AB5: 67846813 | AC5: 81255071 | AD5: 92271849 | AE5: 1.0341602e+08 | AF5: 1.1626765e+08 | AG5: 1.340784e+08 | AH5: 1.3507927e+08 | AI5: 10779776 | AJ5: 20634639 | AK5: 29869064 | AL5: 40819244 | AM5: 51565485 | AN5: 61723671 | AO5: 72536460 | AP5: 85936392 | AQ5: 96493685 | AR5: 1.074543e+08 | AS5: 1.2030611e+08 | AT5: 1.3999979e+08 | AU5: =130842649+14178970 -> 145021619 | AV5: 11133372 | AW5: 21508770 | AX5: 32179727 | AY5: 42120329 | AZ5: 51676831 | BA5: 61706603 | BC5: 4.2683181e+08 | BD5: 97119582 | BE5: 1.0886469e+08 | BF5: 1.2376955e+08 | BG5: 1.3553253e+08 | BH5: =127900472+12767459 -> 140667931 | BI5: 10709523 | BJ5: 21229623 | BK5: 32780903 | BL5: 45271098 | BM5: 56726775 | BN5: 69182392 | BO5: 82435360 | BP5: 94223479 | BQ5: 1.0680823e+08 | BR5: 1.1977113e+08 | BS5: 1.3276324e+08 | BT5: 141785212 | BU5: =16202154+473815+2790361+20140471+26083517+931116+65625875+9537904+10679252+6010634 -> 158475099 | BV5: 11517400 | BW5: 23255634 | BX5: 36328633 | BY5: 49802954 | BZ5: 61411495 | CA5: 73628124 | CB5: 85826149 | CC5: 98360828 | CD5: 1.1065672e+08 | CE5: 1.2254381e+08 | CF5: 1.3545411e+08 | CG5: 1.4899086e+08 | CH5: =9125570+503604+2728651+16012771+23253585+2653613+66090976+18588530+14122299 -> 153079599 | CI5: 12585432 | CJ5: 24092713 | CK5: 35041788 | CL5: 45499156 | CM5: 55867888 | CN5: 65409827 | CO5: 75335349 | CP5: 85254974 | CQ5: 96635030
A6: Fees&Commision on Loan Portfolio | E6: 4548555 | F6: 7970522 | I6: 160010.5 | J6: 684903 | K6: 1082892 | L6: 1304579 | M6: 1765514 | N6: 2217595.5 | O6: 2422650 | P6: 3029184.5 | Q6: 3240640.4 | R6: 3659252.9 | S6: 4218798.9 | T6: 4659610.9 | V6: 419236.5 | W6: 739980 | X6: 1137050 | Y6: 1565835.5 | Z6: 1979664 | AA6: 2356294.5 | AB6: 2750586 | AC6: 3182866.5 | AD6: 3559697 | AE6: 3968232.5 | AF6: 4435514.5 | AG6: 4832283.5 | AH6: 1009779.5 | AI6: 356522 | AJ6: 719866 | AK6: 1561042 | AL6: 1962668.5 | AM6: 2432963 | AN6: 2886826 | AO6: 3155796.5 | AP6: 3796119 | AQ6: 4216612.5 | AR6: 4609835.5 | AS6: 5072617.5 | AT6: 5634613.3 | AU6: 15602300 | AV6: 384164 | AW6: 732437.5 | AX6: 1531351.5 | AY6: 1667915.8 | AZ6: 2026809.3 | BA6: 2432941.1 | BC6: 16427884 | BD6: 3946043 | BE6: 4653567.7 | BF6: 4993921 | BG6: 5773405.7 | BH6: 16934119 | BI6: 388395.8 | BJ6: 1343426.5 | BK6: 1587365.5 | BL6: 2358388.3 | BM6: 2866267.8 | BN6: 3450233.5 | BO6: 3927265.5 | BP6: 4314177 | BQ6: 4693065 | BR6: 5112169 | BS6: 5603306 | BT6: 16689886 | BV6: 354136 | BW6: 586116 | BX6: 1312992.5 | BY6: 1689955 | BZ6: 1979843.8 | CA6: 2219442.5 | CB6: 2552272.5 | CC6: 2896134 | CD6: 3236425 | CE6: 3121429 | CF6: 3448774 | CG6: 3807134 | CH6: 0 | CI6: 310464.5 | CJ6: 636643.5 | CK6: 918249 | CL6: 1060765.5 | CM6: 1460989.5 | CN6: 2467715 | CO6: 3868671 | CP6: 6063909.3 | CQ6: 7956337
A7: Financial Income from Investments | B7: =SUM(B8:B11) -> 2149508 | C7: =SUM(C8:C11) -> 3499455 | D7: =SUM(D8:D11) -> 5321173 | E7: =SUM(E8:E11) -> 2815858.9 | F7: =SUM(F8:F11) -> 1271231 | G7: =SUM(G8:G11) -> 9084813 | H7: =SUM(H8:H11) -> 10786776 | I7: =SUM(I8:I11) -> 62934.75 | ... CQ7: =SUM(CQ8:CQ11) -> 27588846
A8: Government Securities | I8: 0 | J8: 0 | K8: 0 | L8: 0 | M8: 0 | N8: 0 | O8: 0 | P8: 0 | Q8: 0 | R8: 0 | S8: 0 | T8: 0 | V8: 0 | W8: 0 | X8: 0 | Y8: 0 | Z8: 0 | AB8: 0 | AC8: 0 | AD8: 0 | AE8: 0 | AF8: 0 | AG8: 0 | AH8: 0 | AI8: 0 | AJ8: 0 | AK8: 0 | AL8: 0 | AM8: 0 | AN8: 0 | AO8: 0 | AP8: 0 | AQ8: 0 | AR8: 0 | AS8: 0 | AT8: 0 | AV8: 0 | AW8: 0 | AX8: 0 | AY8: 0 | AZ8: 0 | BA8: 0 | BC8: 0 | BD8: 0 | BE8: 0 | BF8: 0 | BG8: 0 | BH8: 0 | BI8: 0 | BJ8: 0 | BK8: 0 | BL8: 0 | BM8: 0 | BN8: 0 | BO8: 0 | BP8: 0 | BQ8: 0 | BR8: 0 | BS8: 0 | BT8: 0 | BV8: 0 | BW8: 0 | BX8: 0 | BY8: 0 | BZ8: 0 | CA8: 0 | CB8: 0 | CC8: 0 | CD8: 0 | CE8: 0 | CF8: 0 | CG8: 0 | CH8: 0 | CI8: 0 | CJ8: 0 | CK8: 0 | CL8: 0 | CM8: 0 | CN8: 0 | CO8: 0 | CP8: 0 | CQ8: 0
A9: Deposits with Banks & other Financial Institutions | D9: 192164 | G9: 3023515 | H9: 1911481 | I9: 0 | J9: 0 | K9: 0 | L9: 0 | M9: 0 | N9: 0 | O9: 0 | P9: 0 | Q9: 0 | R9: 0 | S9: 0 | T9: 0 | U9: 2754941 | V9: 0 | W9: 0 | X9: 0 | Y9: 0 | Z9: 0 | AA9: 0 | AB9: 0 | AC9: 0 | AD9: 0 | AE9: 0 | AF9: 0 | AG9: 0 | AH9: 3122591.9 | AI9: 0 | AJ9: 0 | AK9: 0 | AL9: 0 | AM9: 0 | AN9: 0 | AO9: 0 | AP9: 0 | AQ9: 0 | AR9: 0 | AS9: 0 | AT9: 0 | AV9: 0 | AW9: 0 | AX9: 0 | AY9: 0 | AZ9: 0 | BA9: 0 | BC9: 0 | BD9: 0 | BE9: 0 | BF9: 0 | BG9: 0 | BH9: 0 | BI9: 0 | BJ9: 0 | BK9: 0 | BL9: 0 | BM9: 0 | BN9: 0 | BO9: 0 | BP9: 0 | BQ9: 0 | BR9: 0 | BS9: 0 | BT9: 0 | BU9: =5866877+13846281 -> 19713158 | BV9: 0 | BW9: 0 | BX9: 0 | BY9: 0 | BZ9: 0 | CA9: 0 | CB9: 0 | CC9: 0 | CD9: 0 | CE9: 0 | CF9: 0 | CG9: 0 | CH9: =7362474 -> 7362474 | CI9: 0 | CJ9: 0 | CK9: 0 | CL9: 0 | CM9: 0 | CN9: 0 | CO9: 0 | CP9: 0 | CQ9: 0
A10: Other Investments | C10: 2985205 | D10: 3645569 | G10: 5162510 | H10: 7897142 | I10: 0 | J10: 0 | K10: 148904 | L10: 148904 | M10: 148904 | N10: 8322808.2 | O10: 8700967 | P10: 8700967 | Q10: 9499936.7 | R10: 9499936.7 | S10: 9499936.7 | T10: 11323411 | U10: =8568471 -> 8568471 | V10: 103249.31 | W10: 103249.31 | X10: 1117870.6 | Y10: 1161616.7 | Z10: 1161616.7 | AA10: 11514809 | AB10: 11935898 | AC10: 11935898 | AD10: 11935898 | AE10: 13000654 | AF10: 13000654 | AG10: 13896873 | AH10: 10774281 | AI10: 0 | AJ10: 0 | AK10: 405545.5 | AL10: 911783.55 | AM10: 911783.55 | AN10: 14471442 | AO10: 14471442 | AP10: 14471442 | AQ10: 14471442 | AR10: 14471442 | AS10: 15037042 | AT10: 15602300 | AV10: 0 | AW10: 0 | AX10: 661492.71 | AY10: 13634506 | AZ10: 13634506 | BA10: 14013961 | BC10: 72157761 | BD10: 14431552 | BE10: 14431552 | BF10: 15345940 | BG10: 16934119 | BI10: 0 | BJ10: 0 | BK10: 898828.96 | BL10: 14140931 | BM10: 14188683 | BN10: 14238957 | BO10: 15230178 | BP10: 15443936 | BQ10: 15443936 | BR10: 16803423 | BS10: 17176798 | BT10: 18684341 | BV10: 196712.23 | BW10: 368583.64 | BX10: 1794054 | BY10: 1984724.8 | BZ10: 2183937.3 | CA10: 15259034 | CB10: 15458457 | CC10: 15710336 | CD10: 17276219 | CE10: 17835289 | CF10: 18200130 | CG10: 20071347 | CH10: =14038227 -> 14038227 | CI10: 212475.66 | CJ10: 212475.66 | CK10: 2126424.2 | CL10: 2349875.6 | CM10: 2503122 | CN10: 21506463 | CO10: 22321501 | CP10: 22572106 | CQ10: 23831347
A11: Other Operating Income | B11: 2149508 | C11: 514250 | D11: 1483440 | E11: 2815858.9 | F11: 1271231 | G11: 898788 | H11: 978153 | I11: 62934.75 | J11: 134420.75 | K11: 590604.05 | L11: 640168.05 | M11: 689009.05 | N11: 735406.05 | O11: 782221.05 | P11: 850532.05 | Q11: 897139.05 | R11: 942942.05 | S11: 1003607.1 | T11: 1084933.1 | U11: =2352540+1207016+269395+1275263 -> 5104214 | V11: 66166 | W11: 113781 | X11: 694577.03 | Y11: 783282.03 | Z11: 883097.03 | AA11: 948752.03 | AB11: 1066777 | AC11: 1175999 | AD11: 1316779.5 | AE11: 1403479.5 | AF11: 1670776.2 | AG11: 1732964.5 | AH11: =2538450+2029096.49 -> 4567546.5 | AI11: 57671 | AJ11: 168370 | AK11: 338320.9 | AL11: 429615.2 | AM11: 556861.2 | AN11: 676841.2 | AO11: 769827.2 | AP11: 975013.2 | AQ11: 1143198.2 | AR11: 1225373.2 | AS11: 1301493.2 | AT11: 1552888.2 | AU11: 2165674 | AV11: 65745 | AW11: 151880 | AX11: 369402.54 | AY11: 672682.87 | AZ11: 718648.87 | BA11: 865957.87 | BC11: 5106864.3 | BD11: 1186662 | BE11: 1376874.9 | BF11: 1708680.6 | BG11: 1685748.7 | BH11: 2323752 | BI11: 82690 | BJ11: 774111.75 | BK11: 1529008.2 | BL11: 1673600.5 | BM11: 1842394 | BN11: 2018716.2 | BO11: 2208453.2 | BP11: 2418850.2 | BQ11: 2595095.8 | BR11: 2751830.2 | BS11: 3054745.2 | BT11: 4955778 | BU11: =427500+4255971+272308 -> 4955779 | BV11: 65376.5 | BW11: 1424116.5 | BX11: 1573642.8 | BY11: 1677630.2 | BZ11: 1880704.5 | CA11: 2183662.8 | CB11: 2336404.8 | CC11: 2491126.8 | CD11: 2638147.8 | CE11: 3194652.6 | CF11: 3608727.6 | CG11: 4990642 | CH11: =463500+4122116+123720 -> 4709336 | CI11: 112065 | CJ11: 393924 | CK11: 2139993.2 | CL11: 2294733.3 | CM11: 2800013.1 | CN11: 3057545.1 | CO11: 3364952.2 | CP11: 3465649.8 | CQ11: 3757499.2
A12: Financial Expenses | B12: =SUM(B13:B18) -> 24208136 | C12: =SUM(C13:C18) -> 28170518 | D12: =SUM(D13:D18) -> 34989634 | E12: =SUM(E13:E18) -> 39113127 | F12: =SUM(F13:F18) -> 35705528 | G12: =SUM(G13:G18) -> 35360127 | H12: =SUM(H13:H18) -> 37075248 | I12: =SUM(I13:I18) -> 2576230 | ... CQ12: =SUM(CQ13:CQ18) -> 57047544
A13: Interest Expense on Deposits | B13: 24208136 | C13: 16622609 | D13: 18348921 | E13: 23984697 | F13: 28323856 | G13: 33281648 | H13: 35950953 | I13: 2500000 | J13: 5000000 | K13: 7500000 | L13: 10500000 | M13: 13500000 | N13: 16500000 | O13: 19500000 | P13: 22500000 | Q13: 25500000 | R13: 28500000 | S13: 31500000 | T13: 41271904 | U13: 44018009 | V13: 3000000 | W13: 6000000 | X13: 9000000 | Y13: 12000000 | Z13: 15000000 | AA13: 18000000 | AB13: 20998521 | AC13: 23998521 | AD13: 26998521 | AE13: 26998521 | AF13: 32998521 | AG13: 44528105 | AH13: 44528105 | AI13: 3000000 | AJ13: 6000000 | AK13: 9000000 | AL13: 12000000 | AM13: 15000000 | AN13: 18000000 | AO13: 21000000 | AP13: 24000000 | AQ13: 27000000 | AR13: 30000000 | AS13: 43000000 | AT13: 54334919 | AU13: 54408213 | AV13: 3556219.6 | AW13: 7056219.6 | AX13: 10556220 | AY13: 14056220 | AZ13: 17556220 | BA13: 21056220 | BC13: 155281098 | BD13: 36056220 | BE13: 41056220 | BF13: 46056220 | BG13: 52341453 | BH13: 56353562 | BI13: 5000000 | BJ13: 10000000 | BK13: 15000000 | BL13: 20000000 | BM13: 25000000 | BN13: 30000000 | BO13: 35000000 | BP13: 40000000 | BQ13: 45000000 | BR13: 50000000 | BS13: 55000000 | BT13: 75922160 | BU13: =75922160+1158317 -> 77080477 | BV13: 5000000 | BW13: 10000000 | BX13: 15416667 | BY13: 20833334 | BZ13: 26250001 | CA13: 31666668 | CB13: 37083335 | CC13: 42500002 | CD13: 47916669 | CE13: 53333336 | CF13: 58750003 | CG13: 80488582 | CH13: =80488582+1465241 -> 81953823 | CI13: 5416667 | CJ13: 10833334 | CK13: 16250001 | CL13: 22916668 | CM13: 29583335 | CN13: 37215693 | CO13: 43882360 | CP13: 49299027 | CQ13: 54715694
A14: Cost of External Borrowings | C14: 10569123 | D14: 15436251 | E14: 14077264 | F14: 6809774 | G14: 1293620 | I14: 0 | J14: 0 | K14: 0 | L14: 0 | M14: 0 | N14: 0 | O14: 0 | P14: 0 | Q14: 0 | R14: 0 | S14: 0 | T14: 0 | U14: 0 | V14: 0 | W14: 0 | X14: 0 | Y14: 0 | Z14: 0 | AA14: 0 | AB14: 0 | AC14: 0 | AD14: 0 | AE14: 0 | AF14: 0 | AG14: 0 | AH14: -61659.54 | AI14: 0 | AJ14: 0 | AK14: 0 | AL14: 0 | AM14: 0 | AN14: 0 | AO14: 0 | AP14: 0 | AQ14: 0 | AR14: 0 | AS14: 0 | AT14: 0 | AU14: 0 | AV14: 0 | AW14: 0 | AX14: 0 | AY14: 0 | AZ14: 0 | BA14: 0 | BC14: 0 | BD14: 0 | BE14: 0 | BF14: 0 | BG14: 0 | BH14: 0 | BI14: 0 | BJ14: 0 | BK14: 0 | BL14: 0 | BM14: 0 | BN14: 0 | BO14: 0 | BP14: 0 | BQ14: 0 | BR14: 0 | BS14: 0 | BT14: 0 | BV14: 0 | BW14: 0 | BX14: 0 | BY14: 0 | BZ14: 0 | CA14: 0 | CB14: 0 | CC14: 0 | CD14: 0 | CE14: 0 | CF14: 0 | CG14: 0 | CH14: 0 | CI14: 0 | CJ14: 0 | CK14: 0 | CL14: 0 | CM14: 0 | CN14: 0 | CO14: 0 | CP14: 0 | CQ14: 0
A15: Dividend Expenses | I15: 0 | J15: 0 | K15: 0 | L15: 0 | M15: 0 | N15: 0 | O15: 0 | P15: 0 | Q15: 0 | R15: 0 | S15: 0 | T15: 0 | V15: 0 | W15: 0 | X15: 0 | Y15: 0 | Z15: 0 | AA15: 0 | AB15: 0 | AC15: 0 | AD15: 0 | AE15: 0 | AF15: 0 | AG15: 0 | AH15: 0 | AI15: 0 | AJ15: 0 | AK15: 0 | AL15: 0 | AM15: 0 | AN15: 0 | AO15: 0 | AP15: 0 | AQ15: 0 | AR15: 0 | AS15: 0 | AT15: 0 | AU15: 0 | AV15: 0 | AW15: 0 | AX15: 0 | AY15: 0 | AZ15: 0 | BA15: 0 | BC15: 0 | BD15: 0 | BE15: 0 | BF15: 0 | BG15: 0 | BH15: 0 | BI15: 0 | BJ15: 0 | BK15: 0 | BL15: 0 | BM15: 0 | BN15: 0 | BO15: 0 | BP15: 0 | BQ15: 0 | BR15: 0 | BS15: 0 | BT15: 0 | BV15: 0 | BW15: 0 | BX15: 0 | BY15: 0 | BZ15: 0 | CA15: 0 | CB15: 0 | CC15: 0 | CD15: 0 | CE15: 0 | CF15: 0 | CG15: 0 | CH15: 0 | CI15: 0 | CJ15: 0 | CK15: 0 | CL15: 0 | CM15: 0 | CN15: 0 | CO15: 0 | CP15: 0 | CQ15: 0
A16: Other Financial Expense | D16: 1204462 | E16: 1051165.3 | F16: 571898 | G16: 784859 | H16: 1124295 | I16: 76230 | J16: 186707.84 | K16: 219929.84 | L16: 314295.34 | M16: 459617.31 | N16: 492626.31 | O16: 562075.81 | P16: 646703.37 | Q16: 772138.12 | R16: 861243.38 | S16: 954127.88 | T16: 1510545.9 | U16: 1267985 | V16: 32407.26 | W16: 101627.26 | X16: 198168.26 | Y16: 349355.26 | Z16: 384184.76 | AA16: 411961.76 | AB16: 554577.76 | AC16: 607109.76 | AD16: 608863.76 | AE16: 646108.76 | AF16: 797413.76 | AG16: 996501.45 | AH16: 996703.74 | AI16: 56130 | AJ16: 102799 | AK16: 173438 | AL16: 497034.51 | AM16: 602206.25 | AN16: 695390.57 | AO16: 743053.57 | AP16: 1006424.9 | AQ16: 1035262.9 | AR16: 1133930.9 | AS16: 1234740.9 | AT16: 1843087.8 | AV16: 139380.61 | AW16: 169866.61 | AX16: 377071.61 | AY16: 451381.61 | AZ16: 505025.61 | BA16: 722671.61 | BC16: 4594739.1 | BD16: 967698.66 | BE16: 1130376.7 | BF16: 1271147.7 | BG16: 1484200.6 | BH16: =9290500-BH21 -> 1288888.2 | BI16: 44659 | BJ16: 277080 | BK16: 435759.03 | BL16: 534831.99 | BM16: 752659.37 | BN16: 912591.34 | BO16: 960204.34 | BP16: 1135739.6 | BQ16: 1325374.6 | BR16: 1387578.6 | BS16: 1618197.6 | BT16: 2519448 | BU16: 1361131 | BV16: 52440 | BW16: 237298 | BX16: 615045.65 | BY16: 893952.65 | BZ16: 1081672.6 | CA16: 1280877.6 | CB16: 1497006.5 | CC16: 1809049.9 | CD16: 1977916.2 | CE16: 2171780.2 | CF16: 2470034.2 | CG16: 2718497.3 | CH16: 1253256 | CI16: 245384.75 | CJ16: 402528.75 | CK16: 596088.59 | CL16: 893455.45 | CM16: 1102349.5 | CN16: 1478470.5 | CO16: 1767932 | CP16: 2067810.7 | CQ16: 2331850.4
A17: Fees & Commision Expense | C17: 891886 | I17: 0 | J17: 0 | K17: 0 | L17: 0 | M17: 0 | N17: 0 | O17: 0 | P17: 0 | Q17: 0 | R17: 0 | S17: 0 | T17: 0 | V17: 0 | W17: 0 | X17: 0 | Y17: 0 | Z17: 0 | AB17: 0 | AC17: 0 | AD17: 0 | AE17: 0 | AF17: 0 | AG17: 0 | AH17: 0 | AI17: 0 | AJ17: 0 | AK17: 0 | AL17: 0 | AM17: 0 | AN17: 0 | AO17: 0 | AP17: 0 | AQ17: 0 | AR17: 0 | AS17: 0 | AT17: 0 | AU17: 0 | AV17: 0 | AW17: 0 | AX17: 0 | AY17: 0 | AZ17: 0 | BA17: 0 | BC17: 0 | BD17: 0 | BE17: 0 | BF17: 0 | BG17: 0 | BH17: 0 | BI17: 0 | BJ17: 0 | BK17: 0 | BL17: 0 | BM17: 0 | BN17: 0 | BO17: 0 | BP17: 0 | BQ17: 0 | BR17: 0 | BS17: 0 | BT17: 0 | BV17: 0 | BW17: 0 | BX17: 0 | BY17: 0 | BZ17: 0 | CA17: 0 | CB17: 0 | CC17: 0 | CD17: 0 | CE17: 0 | CF17: 0 | CG17: 0 | CH17: 0 | CI17: 0 | CJ17: 0 | CK17: 0 | CL17: 0 | CM17: 0 | CN17: 0 | CO17: 0 | CP17: 0 | CQ17: 0
A18: Other Expenses | C18: 86900 | I18: 0 | J18: 0 | K18: 0 | L18: 0 | M18: 0 | N18: 0 | O18: 0 | P18: 0 | Q18: 0 | R18: 0 | S18: 0 | T18: 0 | V18: 0 | W18: 0 | X18: 0 | Y18: 0 | Z18: 0 | AB18: 0 | AC18: 0 | AD18: 0 | AE18: 0 | AF18: 0 | AG18: 0 | AH18: 0 | AI18: 0 | AJ18: 0 | AK18: 0 | AL18: 0 | AM18: 0 | AN18: 0 | AO18: 0 | AP18: 0 | AQ18: 0 | AR18: 0 | AS18: 0 | AT18: 0 | AU18: 4687128 | AV18: 0 | AW18: 0 | AX18: 0 | AY18: 0 | AZ18: 0 | BA18: 0 | BC18: 0 | BD18: 0 | BE18: 0 | BF18: 0 | BG18: 0 | BH18: 4339054 | BI18: 0 | BJ18: 0 | BK18: 0 | BL18: 0 | BM18: 0 | BN18: 0 | BO18: 0 | BP18: 0 | BQ18: 0 | BR18: 0 | BS18: 0 | BT18: 0 | BV18: 0 | BW18: 0 | BX18: 0 | BY18: 0 | BZ18: 0 | CA18: 0 | CB18: 0 | CC18: 0 | CD18: 0 | CE18: 0 | CF18: 0 | CG18: 0 | CH18: 0 | CI18: 0 | CJ18: 0 | CK18: 0 | CL18: 0 | CM18: 0 | CN18: 0 | CO18: 0 | CP18: 0 | CQ18: 0
A19: Net Financial Income | B19: =B3-B12 -> 28893883 | C19: =C3-C12 -> 39705900 | D19: =D3-D12 -> 41659478 | E19: =E3-E12 -> 54853911 | F19: =F3-F12 -> 61695160 | G19: =G3-G12 -> 74489033 | H19: =H3-H12 -> 84333721 | I19: =I3-I12 -> 514904.11 | ... CQ19: =CQ3-CQ12 -> 75132669
A20: Allowance for Loan Loss | B20: =B21-B22 -> 0 | C20: =C21-C22 -> 2073400 | D20: =D21-D22 -> 5198104 | E20: =E21-E22 -> 190292 | F20: =F21-F22 -> 3141004 | G20: =G21-G22 -> 3070768 | H20: =H21-H22 -> 9520113 | I20: =I21-I22 -> 138917.5 | ... CQ20: =CQ21-CQ22 -> -7204176
A21: Provision for Loan Losses | C21: 2073400 | D21: 5198104 | E21: 190292 | F21: 3141004 | G21: 3070768 | H21: 9520113 | I21: 138917.5 | J21: -1080827.2 | K21: -1424188.5 | L21: -909357.7 | M21: -1319022.9 | N21: -1059388.7 | O21: -1389761.4 | P21: -1134165.1 | Q21: -438572.1 | R21: -438572.1 | S21: -2369382.7 | T21: -949642 | U21: -949642 | V21: 2599365 | W21: 1931645.2 | X21: 1022179.3 | Y21: 380044.5 | Z21: -344567.2 | AA21: -398249.29 | AB21: -398249.3 | AC21: -398249.3 | AD21: 687805.8 | AE21: -1143080.4 | AF21: -1509626.3 | AG21: -2017041.5 | AH21: -2017041.5 | AI21: 0 | AJ21: 0 | AK21: -136728 | AL21: -136728 | AM21: -1170193.5 | AN21: -580700.2 | AO21: -580700.2 | AP21: 2483260.6 | AQ21: 4072440.6 | AR21: 4612112.4 | AS21: 5945475.3 | AT21: 6660992.8 | AU21: 6660993 | AV21: 0 | AW21: -2506027.5 | AX21: -3778374.1 | AY21: -2041194.7 | AZ21: -620245.5 | BA21: 2808897.3 | BC21: 23605564 | BD21: 6424197.8 | BE21: 5876684.6 | BF21: 12491964 | BG21: 8001611.8 | BH21: 8001611.8 | BI21: -4714601 | BJ21: -1782613.6 | BK21: -2869219.2 | BL21: -5889660.3 | BM21: -4354294.8 | BN21: -5203704.8 | BO21: 464235.6 | BP21: -5658914 | BQ21: -6170018.3 | BR21: -8806254.2 | BS21: -8328018.2 | BT21: -9745414.8 | BV21: 0 | BW21: -7541918.8 | BX21: -7110798.1 | BY21: -8310423.8 | BZ21: -9749028.3 | CA21: -15046197 | CB21: -15119600 | CC21: -13641428 | CD21: -16160775 | CE21: -18143616 | CF21: -18175804 | CG21: -6268875.2 | CH21: 0 | CI21: 0 | CJ21: -10176621 | CK21: -10798898 | CL21: -10921898 | CM21: -10737671 | CN21: -11703362 | CO21: -7222066.2 | CP21: -8640609.1 | CQ21: -7204176
A22: Value of Loans Recovered | I22: 0 | J22: 0 | K22: 0 | L22: 0 | M22: 0 | N22: 0 | O22: 0 | P22: 0 | Q22: 0 | R22: 0 | S22: 0 | T22: 0 | V22: 0 | W22: 0 | X22: 0 | Y22: 0 | Z22: 0 | AB22: 0 | AC22: 0 | AD22: 0 | AE22: 0 | AF22: 0 | AG22: 0 | AH22: 0 | AI22: 0 | AJ22: 0 | AK22: 0 | AL22: 0 | AM22: 0 | AN22: 0 | AO22: 0 | AP22: 0 | AQ22: 0 | AR22: 0 | AS22: 0 | AT22: 0 | AU22: 0 | AV22: 0 | AW22: 0 | AX22: 0 | AY22: 0 | AZ22: 0 | BA22: 0 | BB22: 0 | BC22: 0 | BD22: 0 | BE22: 0 | BF22: 0 | BG22: 0 | BH22: 0 | BI22: 0 | BJ22: 0 | BK22: 0 | BL22: 0 | BM22: 0 | BN22: 0 | BO22: 0 | BP22: 0 | BQ22: 0 | BR22: 0 | BS22: 0 | BT22: 0 | BV22: 0 | BW22: 0 | BX22: 0 | BY22: 0 | BZ22: 0 | CA22: 0 | CB22: 0 | CC22: 0 | CD22: 0 | CE22: 0 | CF22: 0 | CG22: 0 | CH22: 8019670 | CI22: 0 | CJ22: 0 | CK22: 0 | CL22: 0 | CM22: 0 | CN22: 0 | CO22: 0 | CP22: 0 | CQ22: 0
A23: Operating Expeses | B23: =SUM(B24:B28) -> 20100930 | C23: =SUM(C24:C28) -> 23299810 | D23: =SUM(D24:D28) -> 28129736 | E23: =SUM(E24:E28) -> 38145978 | F23: =SUM(F24:F28) -> 38649289 | G23: =SUM(G24:G28) -> 48225009 | H23: =SUM(H24:H28) -> 65005570 | I23: =SUM(I24:I28) -> 2923019.1 | ... CQ23: =SUM(CQ24:CQ28) -> 76726170
A24: Personel Expenses | C24: 9045654 | D24: 9375585 | E24: 11911818 | F24: 13893168 | G24: 15300933 | H24: 16492855 | I24: 1043818.2 | J24: 1136318.2 | K24: 3356086.3 | L24: 6052757.1 | M24: 9522323.8 | N24: 10568723 | O24: 12400623 | P24: 13539023 | Q24: 15407469 | R24: 16647939 | S24: 17548300 | T24: 19177251 | U24: 19184551 | V24: 1300252.2 | W24: 2604604 | X24: 4594615.8 | Y24: 9853087.3 | Z24: 11675982 | AA24: 13503510 | AB24: 14968801 | AC24: 16552869 | AD24: 18022759 | AE24: 18352862 | AF24: 20702786 | AG24: 22034715 | AH24: 22043865 | AI24: 1499992.9 | AJ24: 3433227.2 | AK24: 5709069.8 | AL24: 11488002 | AM24: 13485006 | AN24: 16505956 | AO24: 18352508 | AP24: 20508622 | AQ24: 22417581 | AR24: 24320640 | AS24: 26203630 | AT24: 28344011 | AU24: 28356411 | AV24: 2055038.7 | AW24: 4095403.4 | AX24: 8685120.1 | AY24: 11458782 | AZ24: 17563579 | BA24: 19548378 | BC24: 1.2053825e+08 | BD24: 26125923 | BE24: 30072170 | BF24: 32216960 | BG24: 34571522 | BH24: 34593722 | BI24: 2090165.7 | BJ24: 4864953.7 | BK24: 10352588 | BL24: 12888375 | BM24: 15017694 | BN24: 17515079 | BO24: 22543199 | BP24: 24669667 | BQ24: 27030395 | BR24: 29371722 | BS24: 31995376 | BT24: 34231876 | BU24: =15126818+2538437+4479237+2294970+376636+1662165+40800+1493082+4309157+667240+1254000 -> 34242542 | BV24: 2565410.7 | BW24: 10241413 | BX24: 13888031 | BY24: 17792623 | BZ24: 22076076 | CA24: 24751514 | CB24: 27709706 | CC24: 30244794 | CD24: 32870561 | CE24: 35293210 | CF24: 37924980 | CG24: 40514261 | CH24: =17307293+4373562+5149449+2573795+544989+1922000+44600+1647904+4391009+865460+1705000 -> 40525061 | CI24: 2354740 | CJ24: 4983521.4 | CK24: 13247593 | CL24: 16867090 | CM24: 20145847 | CN24: 24518476 | CO24: 27455671 | CP24: 30947147 | CQ24: 34208908
A25: Governance Expenses | B25: 8990937 | C25: 3271895 | D25: 4220753 | E25: 5415126 | F25: 6469083 | G25: 7582971 | H25: 7969188 | I25: 274075 | J25: 656595 | K25: 1926395 | L25: 2508777 | M25: 2901073 | N25: 3222419 | O25: 4390045 | P25: 4695113 | Q25: 4945720 | R25: 5797580 | S25: 7530690 | T25: 9089570 | U25: 9863038 | V25: 292730 | W25: 743850 | X25: 2234704 | Y25: 3331799 | Z25: 3780464 | AA25: 4073029 | AB25: 5309894 | AC25: 6690159 | AD25: 7399049 | AE25: 8462379 | AF25: 9066124 | AG25: 9428534 | AH25: 11136854 | AI25: 611500 | AJ25: 1271810.6 | AK25: 3102505 | AL25: 3503840 | AM25: 4014205 | AN25: 5229995 | AO25: 5645033 | AP25: 8310798 | AQ25: 9099408 | AR25: 9815438 | AS25: 10812673 | AT25: 11223718 | AU25: 13213173 | AV25: 629085 | AW25: 1589430 | AX25: 2404286 | AY25: 2834696 | AZ25: 3467811 | BA25: 3846186 | BC25: 28726680 | BD25: 6410526 | BE25: 7901021 | BF25: 9323185 | BG25: 9915710 | BH25: 11689480 | BI25: 1015735 | BJ25: 4576450 | BK25: 5189628 | BL25: 6137510.8 | BM25: 6748964.8 | BN25: 8936538.8 | BO25: 10365978 | BP25: 11440504 | BQ25: 11962678 | BR25: 13853105 | BS25: 15518932 | BT25: 18064165 | BU25: =2391818+3625378+603012+1388000+511810+10000+4547950+1649800+1500000+1836398 -> 18064166 | BV25: 1039651 | BW25: 4395415 | BX25: 6216352 | BY25: 8133077 | BZ25: 9772474 | CA25: 11642629 | CB25: 13821309 | CC25: 14669966 | CD25: 15772105 | CE25: 16351334 | CF25: 19064564 | CG25: 19395206 | CH25: =2695375+4190927+1281520+1740000+521896+42100+5032034+2124300+1700000+2331050 -> 21659202 | CI25: 108555 | CJ25: 1510710 | CK25: 5660123 | CL25: 6396128 | CM25: 7956743 | CN25: 10464753 | CO25: 12416198 | CP25: 14901243 | CQ25: 15750833
A26: Marketing Expenses | C26: 1226651 | D26: 1473628 | E26: 1361305 | F26: 1465539 | G26: 3168809 | H26: 2675207 | I26: 95680 | J26: 980448 | K26: 1204234 | L26: 1381863 | M26: 1554937 | N26: 2039977 | O26: 2214917 | P26: 2294107 | Q26: 2468011 | R26: 2554860 | S26: 2562940 | T26: 3231915 | U26: 2687767 | V26: 3840 | W26: 28500 | X26: 298040 | Y26: 517180 | Z26: 729240 | AA26: 968315 | AB26: 1498855 | AC26: 1900780 | AD26: 2042140 | AE26: 3163701 | AF26: 3548602.2 | AG26: 4120506.2 | AH26: 3953531 | AI26: 61990 | AJ26: 130170 | AK26: 181075 | AL26: 450790 | AM26: 786670 | AN26: 1339425 | AO26: 1814445 | AP26: 2360575 | AQ26: 2938452 | AR26: 3805052 | AS26: 4319577 | AT26: 5222752 | AU26: 4457347 | AV26: 31097 | AW26: 232807 | AX26: 266897 | AY26: 594497 | AZ26: 916197 | BA26: 923457 | BC26: 6731300 | BD26: 1501955 | BE26: 1621380 | BF26: 1751945 | BG26: 2116680 | BH26: 1935410 | BI26: 43830 | BJ26: 116440 | BK26: 357156 | BL26: 933496 | BM26: 1592229 | BN26: 1649739 | BO26: 2027597 | BP26: 2359757 | BQ26: 2466897 | BR26: 3042172 | BS26: 3317392 | BT26: 3831552 | BU26: =2025004+1806548 -> 3831552 | BV26: 324255 | BW26: 386210 | BX26: 521403 | BY26: 1000443 | BZ26: 1482083 | CA26: 2433933 | CB26: 3548493 | CC26: 3995623 | CD26: 4103263 | CE26: 5181661 | CF26: 5554874 | CG26: 5973091 | CH26: =2009750+3501445 -> 5511195 | CI26: 43660 | CJ26: 92480 | CK26: 733570 | CL26: 814580 | CM26: 1352310 | CN26: 2628362 | CO26: 3599212 | CP26: 3903397 | CQ26: 4397642
A27: Depreciation and Amortization | C27: 3046514 | D27: 3424915 | E27: 3005880.1 | F27: 2794665 | G27: 2777823 | H27: 2791594 | I27: 241352.03 | J27: 482704.06 | K27: 724056.09 | L27: 965408.12 | M27: 1206760.1 | N27: 1448112.2 | O27: 1689464.2 | P27: 1930816.2 | Q27: 2172168.3 | R27: 2413520.3 | S27: 2624069.1 | T27: 3576056.1 | U27: 3576056 | V27: 335425.05 | W27: 670850.1 | X27: 1006275.2 | Y27: 1216326.7 | Z27: 1677125.2 | AA27: 2012550.3 | AB27: 2347975.4 | AC27: 2683400.4 | AD27: 3018825.5 | AE27: 3213177.2 | AF27: 3539121 | AG27: 4648471 | AH27: 4120504 | AI27: 243719.29 | AJ27: 579586.18 | AK27: 869379.27 | AL27: 1159172.4 | AM27: 1448965.4 | AN27: 1636760.9 | AO27: 2028551.6 | AP27: 2318344.7 | AQ27: 2608137.8 | AR27: 2897900.9 | AS27: 3187664 | AT27: 3575739.9 | AU27: 3543217 | AV27: 250204.41 | AW27: 500408.82 | AX27: 750613.22 | AY27: 1000817.6 | AZ27: 1251022 | BA27: 1501226.4 | BC27: 10008176 | BD27: 2251839.6 | BE27: 2503572 | BF27: 3110396.1 | BG27: 3344074.5 | BH27: 3344084 | BI27: 177252.97 | BJ27: 504896.32 | BK27: 757344.48 | BL27: 1009792.6 | BM27: 1262240.8 | BN27: 1514689 | BO27: 1767137.1 | BP27: 2019585.3 | BQ27: 2272033.4 | BR27: 2524481.6 | BS27: 2776929.8 | BT27: 3051580.6 | BU27: 3051580 | BV27: 203389 | BW27: 406778 | BX27: 612394 | BY27: 772893 | BZ27: 978509 | CA27: 1140443 | CB27: 1302419 | CC27: 1464395 | CD27: 1626371 | CE27: 2013912 | CF27: 2458371.2 | CG27: 2784727.3 | CH27: 2784734 | CI27: 195214.48 | CJ27: 390428.97 | CK27: 600984.83 | CL27: 780857.95 | CM27: 976072.44 | CN27: 1171286.9 | CO27: 1429467.2 | CP27: 1647880.4 | CQ27: 1866535.9
A28: Administrative Expenses | B28: 11109993 | C28: 6709096 | D28: 9634855 | E28: 16451849 | F28: 14026834 | G28: 19394473 | H28: 35076726 | I28: 1268093.9 | J28: 3067671.5 | K28: 3997092.4 | L28: 4175716 | M28: 5412460.9 | N28: 6288340.2 | O28: 7385727.3 | P28: 8657872.9 | Q28: 9728814.6 | R28: 12413691 | S28: 13274603 | T28: 38990363 | U28: 38688953 | V28: 1793367.4 | W28: 2546364.9 | X28: 5572709.9 | Y28: 7228816.7 | Z28: 8282442.2 | AA28: 8818516.9 | AB28: 10728212 | AC28: 13076305 | AD28: 14323861 | AE28: 15732847 | AF28: 16858622 | AG28: 36231829 | AH28: 34233640 | AI28: 1505446.5 | AJ28: 2558985.5 | AK28: 4832554.3 | AL28: 7173705.5 | AM28: 8162446.7 | AN28: 9452318.9 | AO28: 10667275 | AP28: 13709005 | AQ28: 14905746 | AR28: 16647509 | AS28: 18217848 | AT28: 27223972 | AU28: 26008845 | AV28: 1191520.9 | AW28: 4206903 | AX28: 5864608.4 | AY28: 7887302.8 | AZ28: 10564217 | BA28: 12089106 | BC28: 78583275 | BD28: 17231073 | BE28: 18909284 | BF28: 19967923 | BG28: 25184070 | BH28: 19820936 | BI28: 4431347.1 | BJ28: 5815626.9 | BK28: 7861340.7 | BL28: 9697810.3 | BM28: 11962464 | BN28: 13118128 | BO28: 14695671 | BP28: 15828179 | BQ28: 17248089 | BR28: 18797422 | BS28: 19875483 | BT28: 25446095 | BU28: =357001+1506585+299300+1238985+1200000+448270+349735+136375+1770074+1377500+1040276+3747582+831671+169848+350000+227730+1005454+777017+1135230+80000+748164+432442+30000+6186857 -> 25446096 | BV28: 2947254 | BW28: 5974807 | BX28: 9072214.4 | BY28: 11288699 | BZ28: 12804269 | CA28: 14550303 | CB28: 16915089 | CC28: 17869895 | CD28: 20285027 | CE28: 23033832 | CF28: 25581096 | CG28: 26413825 | CH28: =24885325 -> 24885325 | CI28: 2822549.3 | CJ28: 4490557.4 | CK28: 9244369 | CL28: 12115076 | CM28: 13850138 | CN28: 15382346 | CO28: 17756518 | CP28: 19277750 | CQ28: 20502252
A29: Net Operating Income | B29: =B19-B20-B23 -> 8792953 | C29: =C19-C20-C23 -> 14332690 | D29: =D19-D20-D23 -> 8331638 | E29: =E19-E20-E23 -> 16517641 | F29: =F19-F20-F23 -> 19904867 | G29: =G19-G20-G23 -> 23193256 | H29: =H19-H20-H23 -> 9808038 | I29: =I19-I20-I23 -> -2547032.5 | ... CQ29: =CQ19-CQ20-CQ23 -> 5610674.6
A30: Net Non operating Income/Expense | B30: =B31-B32 -> 0 | C30: =C31-C32 -> 0 | D30: =D31-D32 -> 0 | E30: =E31-E32 -> 0 | F30: =F31-F32 -> 0 | G30: =G31-G32 -> 0 | H30: =H31-H32 -> 0 | I30: =I31-I32 -> 0 | ... CQ30: =CQ31-CQ32 -> 0
A31: Non Operating Income | I31: 0 | J31: 0 | K31: 0 | L31: 0 | M31: 0 | N31: 0 | O31: 0 | P31: 0 | Q31: 0 | R31: 0 | S31: 0 | T31: 0 | U31: 0 | V31: 0 | W31: 0 | X31: 0 | Y31: 0 | Z31: 0 | AA31: 0 | AB31: 0 | AC31: 0 | AD31: 0 | AE31: 0 | AF31: 0 | AG31: 0 | AH31: 0 | AI31: 0 | AJ31: 0 | AK31: 0 | AL31: 0 | AM31: 0 | AN31: 0 | AO31: 0 | AP31: 0 | AQ31: 0 | AR31: 0 | AS31: 0 | AT31: 0 | AU31: 0 | AV31: 0 | AW31: 0 | AX31: 0 | AY31: 0 | AZ31: 0 | BA31: 0 | BB31: 0 | BC31: 0 | BD31: 0 | BE31: 0 | BF31: 0 | BG31: 0 | BH31: 0 | BI31: 0 | BJ31: 0 | BK31: 0 | BL31: 0 | BM31: 0 | BN31: 0 | BO31: 0 | BP31: 0 | BQ31: 0 | BR31: 0 | BS31: 0 | BT31: 0 | BV31: 0 | BW31: 0 | BX31: 0 | BY31: 0 | BZ31: 0 | CA31: 0 | CB31: 0 | CC31: 0 | CD31: 0 | CE31: 0 | CF31: 0 | CG31: 0 | CH31: 0 | CI31: 0 | CJ31: 0 | CK31: 0 | CL31: 0 | CM31: 0 | CN31: 0 | CO31: 0 | CP31: 0 | CQ31: 0
A32: Non Operating Expense | I32: 0 | J32: 0 | K32: 0 | L32: 0 | M32: 0 | N32: 0 | O32: 0 | P32: 0 | Q32: 0 | R32: 0 | S32: 0 | T32: 0 | U32: 0 | V32: 0 | W32: 0 | X32: 0 | Y32: 0 | Z32: 0 | AA32: 0 | AB32: 0 | AC32: 0 | AD32: 0 | AE32: 0 | AF32: 0 | AG32: 0 | AH32: 0 | AI32: 0 | AJ32: 0 | AK32: 0 | AL32: 0 | AM32: 0 | AN32: 0 | AO32: 0 | AP32: 0 | AQ32: 0 | AR32: 0 | AS32: 0 | AT32: 0 | AU32: 0 | AV32: 0 | AW32: 0 | AX32: 0 | AY32: 0 | AZ32: 0 | BA32: 0 | BB32: 0 | BC32: 0 | BD32: 0 | BE32: 0 | BF32: 0 | BG32: 0 | BH32: 0 | BI32: 0 | BJ32: 0 | BK32: 0 | BL32: 0 | BM32: 0 | BN32: 0 | BO32: 0 | BP32: 0 | BQ32: 0 | BR32: 0 | BS32: 0 | BT32: 0 | BV32: 0 | BW32: 0 | BX32: 0 | BY32: 0 | BZ32: 0 | CA32: 0 | CB32: 0 | CC32: 0 | CD32: 0 | CE32: 0 | CF32: 0 | CG32: 0 | CH32: 0 | CI32: 0 | CJ32: 0 | CK32: 0 | CL32: 0 | CM32: 0 | CN32: 0 | CO32: 0 | CP32: 0 | CQ32: 0
A33: Net Income(Before Tax & Donations) | B33: =B29+B30 -> 8792953 | C33: =C29+C30 -> 14332690 | D33: =D29+D30 -> 8331638 | E33: =E29+E30 -> 16517641 | F33: =F29+F30 -> 19904867 | G33: =G29+G30 -> 23193256 | H33: =H29+H30 -> 9808038 | I33: =I29+I30 -> -2547032.5 | ... CQ33: =CQ29+CQ30 -> 5610674.6
A34: Taxes | B34: 135550 | C34: 140547 | D34: 367209 | E34: 957101.88 | F34: 780541 | G34: 613419 | H34: 579740 | I34: 0 | J34: 0 | K34: 0 | L34: 0 | M34: 0 | N34: 0 | O34: 0 | P34: 0 | Q34: 0 | R34: 0 | S34: 0 | T34: 0 | U34: 1370163 | V34: 0 | W34: 0 | X34: 0 | Y34: 0 | Z34: 0 | AA34: 0 | AB34: 0 | AC34: 0 | AD34: 0 | AE34: 0 | AF34: 0 | AG34: 0 | AH34: 1077117.7 | AI34: 0 | AJ34: 0 | AK34: 0 | AL34: 0 | AM34: 0 | AN34: 0 | AO34: 0 | AP34: 0 | AQ34: 0 | AR34: 0 | AS34: 0 | AT34: 0 | AU34: 0 | AV34: 0 | AW34: 0 | AX34: 0 | AY34: 0 | AZ34: 0 | BA34: 0 | BC34: 0 | BD34: 68373 | BE34: 68373 | BF34: 68373 | BG34: 1271210 | BH34: 1202836 | BI34: 0 | BJ34: 0 | BK34: 19001.2 | BL34: 391858.4 | BM34: 391858.4 | BN34: 671501.2 | BO34: 671501.2 | BP34: 671501.2 | BQ34: 671501.2 | BR34: 692061.2 | BS34: 692061.2 | BT34: 2366615 | BU34: 2366765 | BV34: 0 | BW34: 53622.1 | BX34: 146877.4 | BY34: 149277.4 | BZ34: 149277.4 | CA34: 149277.4 | CB34: 149277.4 | CC34: 149277.4 | CD34: 149277.4 | CE34: 149277.4 | CF34: 224069.5 | CG34: 2677349 | CH34: 2517172 | CI34: 0 | CJ34: 0 | CK34: 0 | CL34: 0 | CM34: 117034.6 | CN34: 117034.6 | CO34: 172861.2 | CP34: 172861.2 | CQ34: 456723.3
A35: Net Income(After Tax Before Donations) | B35: =B33-B34 -> 8657403 | C35: =C33-C34 -> 14192143 | D35: =D33-D34 -> 7964429 | E35: =E33-E34 -> 15560539 | F35: =F33-F34 -> 19124326 | G35: =G33-G34 -> 22579837 | H35: =H33-H34 -> 9228298 | I35: =I33-I34 -> -2547032.5 | ... CQ35: =CQ33-CQ34 -> 5153951.3
A36: Donations | I36: 0 | J36: 0 | K36: 0 | L36: 0 | M36: 0 | N36: 0 | O36: 0 | P36: 0 | Q36: 0 | R36: 0 | S36: 0 | T36: 0 | U36: 0 | V36: 0 | W36: 0 | X36: 0 | Y36: 0 | Z36: 0 | AA36: 0 | AB36: 0 | AC36: 0 | AD36: 0 | AE36: 0 | AF36: 0 | AG36: 0 | AH36: 0 | AI36: 0 | AJ36: 0 | AK36: 0 | AL36: 0 | AM36: 0 | AN36: 0 | AO36: 0 | AP36: 0 | AQ36: 0 | AR36: 0 | AS36: 0 | AT36: 0 | AU36: 0 | AW36: 0 | AX36: 0 | AY36: 0 | AZ36: 0 | BA36: 0 | BC36: 0 | BD36: 0 | BE36: 0 | BF36: 0 | BG36: 0 | BH36: 0 | BI36: 0 | BJ36: 0 | BK36: 0 | BL36: 0 | BM36: 0 | BV36: 0 | BW36: 0 | BX36: 0 | BY36: 0 | BZ36: 0 | CA36: 0 | CB36: 0 | CC36: 0 | CD36: 0 | CE36: 0 | CF36: 0 | CG36: 0 | CH36: 0 | CI36: 0 | CJ36: 0 | CK36: 0 | CL36: 0 | CM36: 0 | CN36: 0 | CO36: 0 | CP36: 0 | CQ36: 0
A37: Net Income/(After Tax & Donations) | B37: =B35-B36 -> 8657403 | C37: =C35-C36 -> 14192143 | D37: =D35-D36 -> 7964429 | E37: =E35-E36 -> 15560539 | F37: =F35-F36 -> 19124326 | G37: =G35-G36 -> 22579837 | H37: =H35-H36 -> 9228298 | I37: =I35-I36 -> -2547032.5 | ... CQ37: =CQ35-CQ36 -> 5153951.3
AA38: =Z37-AA37 -> -14372529 | AB38: =AA37-AB37 -> -2497227.2 | AC38: =AB37-AC37 -> -4847451.2 | AD38: =AC37-AD37 -> -3543459.7 | AE38: =AD37-AE37 -> -10379474 | AF38: =AE37-AF37 -> -3011155.2 | AG38: =AF37-AG37 -> 14804131 | AH38: =AG37-AH37 -> 27046.408 | ... BU38: =BT37-BU37 -> 8727414
A39: Total Expenses | B39: =B12+B23+B20+B34+B36 -> 44444616 | C39: =C12+C23+C20+C34+C36 -> 53684275 | D39: =D12+D23+D20+D34+D36 -> 68684683 | E39: =E12+E23+E20+E34+E36 -> 78406499 | F39: =F12+F23+F20+F34+F36 -> 78276362 | G39: =G12+G23+G20+G34+G36 -> 87269323 | H39: =H12+H23+H20+H34+H36 -> 112180671 | I39: =I12+I23+I20+I34+I36 -> 5638166.6 | ... CQ39: =CQ12+CQ23+CQ20+CQ34+CQ36 -> 1.2702626e+08
J41: =J39-I39 -> 4791450.8 | K41: =K39-J39 -> 7073987.7 | L41: =L39-K39 -> 7485853.7 | M41: =M39-L39 -> 8248690.5 | N41: =N39-M39 -> 6262660.1 | O41: =O39-N39 -> 7252281.7 | P41: =P39-O39 -> 6376379.1 | Q41: =Q39-P39 -> 7426278.8 | ... U41: =U39-T39 -> 3808916.9
X42: =135000*12 -> 1620000

Sheet FORM 4
D1: Audited 2020
B2: CLASSIFICATION | C2: NO. OF A/Cs | D2: OUTSTANDING LOAN PORTFOLIO(Kshs) | E2: REQUIRED PROVISION | F2: REQUIRED PROVISION AMOUNT(Kshs)
B3: Performing | E3: 0.01 | F3: =D3*E3 -> 0
B4: Watch | E4: 0.05 | F4: =D4*E4 -> 0
B5: Substandard | E5: 0.25 | F5: =D5*E5 -> 0
B6: Doubtful | E6: 0.5 | F6: =D6*E6 -> 0
B7: Loss | E7: 1 | F7: =D7*E7 -> 0
B8: subtotal | C8: =SUM(C3:C7) -> 0 | D8: =SUM(D3:D7) -> 0 | F8: =SUM(F3:F7) -> 0
D10: =SUM(D5:D7) -> 0
D11: =D10/D8 -> #DIV/0!
D15: 44256
B16: CLASSIFICATION | C16: NO. OF A/Cs | D16: OUTSTANDING LOAN PORTFOLIO(Kshs) | E16: REQUIRED PROVISION | F16: REQUIRED PROVISION AMOUNT(Kshs)
B17: Performing | C17: 3223 | D17: 6.8363792e+08 | E17: 0.01 | F17: =D17*E17 -> 6836379.2
B18: Watch | C18: 163 | D18: 18912975 | E18: 0.05 | F18: =D18*E18 -> 945648.75
B19: Substandard | C19: 196 | D19: 34944393 | E19: 0.25 | F19: =D19*E19 -> 8736098.2
B20: Doubtful | C20: 86 | D20: 12059531 | E20: 0.5 | F20: =D20*E20 -> 6029765.3
B21: Loss | C21: 379 | D21: 9472491.2 | E21: 1 | F21: =D21*E21 -> 9472491.2
B22: subtotal | C22: =SUM(C17:C21) -> 4047 | D22: =SUM(D17:D21) -> 7.5902731e+08 | F22: =SUM(F17:F21) -> 32020383
C24: NPL | D24: =SUM(D19:D21) -> 56476415
C25: NPL% | D25: =D24/D22 -> 0.074406302

Sheet CAELS
A1: MAFANIKIO SACCO 2017 CAELS
D2: 2010 Audited | E2: 2011 Audited | F2: 2012 Audited | G2: 2013 Audited | H2: 2014 Audited | I2: 2015 Audited | J2: 2016 Audited | K2: 42736 | L2: 42767 | M2: 42795 | N2: 42826 | O2: 42856 | P2: 42887 | Q2: 42917 | R2: 42948 | S2: 42979 | T2: 43009 | U2: 43040 | V2: 43070 | W2: Audited 2017 | X2: 43101 | Y2: 43132 | Z2: 43160 | AA2: 43191 | AB2: 43221 | AC2: 43252 | AD2: 43282 | AE2: 43313 | AF2: 43344 | AG2: 43374 | AH2: 43405 | AI2: 43435 | AJ2: Audited 2018 | AK2: 43466 | AL2: 43497 | AM2: 43525 | AN2: 43556 | AO2: 43586 | AP2: 43617 | AQ2: 43647 | AR2: 43678 | AS2: 43709 | AT2: 43739 | AU2: 43770 | AV2: 43800 | AW2: Audited-19 | AX2: 43831 | AY2: 43862 | AZ2: 43891 | BA2: 43922 | BB2: 43952 | BC2: 43983 | BD2: 44013 | BE2: 44044 | BF2: 44075 | BG2: 44105 | BH2: 44136 | BI2: 44166 | BJ2: Audited 2020 | BK2: 44197 | BL2: 44228 | BM2: 44256 | BN2: 44287 | BO2: 44317 | BP2: 44348 | BQ2: 44378 | BR2: 44409 | BS2: 44440 | BT2: 44470 | BU2: 44501 | BV2: 44531 | BW2: AUDITED 2021 | BX2: 44562 | BY2: 44593 | BZ2: 44621 | CA2: 44652 | CB2: 44682 | CC2: 44713 | CD2: 44743 | CE2: 44774 | CF2: 44805 | CG2: 44835 | CH2: 44866 | CI2: 44896 | CJ2: Audited 2022 | CK2: 44927 | CL2: 44958 | CM2: 44986 | CN2: 45017 | CO2: 45047 | CP2: 45078 | CQ2: 45108 | CR2: 45139 | CS2: 45170
A3: CAPITAL ADEQUACY | B3: Core Capital | C3: 10 M | D3: =(('Evolutive SFP'!B39+'Evolutive SFP'!B40+'Evolutive SFP'!B41+'Evolutive SFP'!B42+'Evolutive SFP'!B43+'Evolutive SFP'!B44)-'Evolutive SFP'!B10)/1000000 -> 47.468545 | E3: =(('Evolutive SFP'!C39+'Evolutive SFP'!C40+'Evolutive SFP'!C41+'Evolutive SFP'!C42+'Evolutive SFP'!C43+'Evolutive SFP'!C44)-'Evolutive SFP'!C10)/1000000 -> 73.347415 | F3: =(('Evolutive SFP'!D39+'Evolutive SFP'!D40+'Evolutive SFP'!D41+'Evolutive SFP'!D42+'Evolutive SFP'!D43+'Evolutive SFP'!D44)-'Evolutive SFP'!D10)/1000000 -> 81.032188 | G3: =(('Evolutive SFP'!E39+'Evolutive SFP'!E40+'Evolutive SFP'!E41+'Evolutive SFP'!E42+'Evolutive SFP'!E43+'Evolutive SFP'!E44)-'Evolutive SFP'!E10)/1000000 -> 100.84641 | H3: =(('Evolutive SFP'!F39+'Evolutive SFP'!F40+'Evolutive SFP'!F41+'Evolutive SFP'!F42+'Evolutive SFP'!F43+'Evolutive SFP'!F44)-'Evolutive SFP'!F10)/1000000 -> 146.85815 | I3: =(('Evolutive SFP'!G39+'Evolutive SFP'!G40+'Evolutive SFP'!G41+'Evolutive SFP'!G42+'Evolutive SFP'!G43+'Evolutive SFP'!G44)-'Evolutive SFP'!G10)/1000000 -> 175.10938 | J3: =(('Evolutive SFP'!H39+'Evolutive SFP'!H40+'Evolutive SFP'!H41+'Evolutive SFP'!H42+'Evolutive SFP'!H43+'Evolutive SFP'!H44)-'Evolutive SFP'!H10)/1000000 -> 190.50328 | K3: =(('Evolutive SFP'!I39+'Evolutive SFP'!I40+'Evolutive SFP'!I41+'Evolutive SFP'!I42+'Evolutive SFP'!I43+'Evolutive SFP'!I44)-'Evolutive SFP'!I10)/1000000 -> 198.7082 | ... AY3: =(('Evolutive SFP'!AW39+'Evolutive SFP'!AW40+'Evolutive SFP'!AW41+'Evolutive SFP'!AW42+'Evolutive SFP'!AW43+'Evolutive SFP'!AW44)-'Evolutive SFP'!AW10)/1000000 -> 275.16599 | AZ3: =(('Evolutive SFP'!AW39+'Evolutive SFP'!AW40+'Evolutive SFP'!AW41+'Evolutive SFP'!AW42+'Evolutive SFP'!AW43+'Evolutive SFP'!AW44)-'Evolutive SFP'!AW10)/1000000 -> 275.16599 | BA3: =(('Evolutive SFP'!AX39+'Evolutive SFP'!AX40+'Evolutive SFP'!AX41+'Evolutive SFP'!AX42+'Evolutive SFP'!AX43+'Evolutive SFP'!AX44)-'Evolutive SFP'!AX10)/1000000 -> 287.48733 | BB3: =(('Evolutive SFP'!AY39+'Evolutive SFP'!AY40+'Evolutive SFP'!AY41+'Evolutive SFP'!AY42+'Evolutive SFP'!AY43+'Evolutive SFP'!AY44)-'Evolutive SFP'!AY10)/1000000 -> 283.85586 | BC3: =(('Evolutive SFP'!AZ39+'Evolutive SFP'!AZ40+'Evolutive SFP'!AZ41+'Evolutive SFP'!AZ42+'Evolutive SFP'!AZ43+'Evolutive SFP'!AZ44)-'Evolutive SFP'!AZ10)/1000000 -> 284.13942 | BD3: =(('Evolutive SFP'!BA39+'Evolutive SFP'!BA40+'Evolutive SFP'!BA41+'Evolutive SFP'!BA42+'Evolutive SFP'!BA43+'Evolutive SFP'!BA44)-'Evolutive SFP'!BA10)/1000000 -> 0 | BE3: =(('Evolutive SFP'!BB39+'Evolutive SFP'!BB40+'Evolutive SFP'!BB41+'Evolutive SFP'!BB42+'Evolutive SFP'!BB43+'Evolutive SFP'!BB44)-'Evolutive SFP'!BB10)/1000000 -> 1434.1502 | BF3: =(('Evolutive SFP'!BC39+'Evolutive SFP'!BC40+'Evolutive SFP'!BC41+'Evolutive SFP'!BC42+'Evolutive SFP'!BC43+'Evolutive SFP'!BC44)-'Evolutive SFP'!BC10)/1000000 -> 288.13853 | BG3: =(('Evolutive SFP'!BD39+'Evolutive SFP'!BD40+'Evolutive SFP'!BD41+'Evolutive SFP'!BD42+'Evolutive SFP'!BD43+'Evolutive SFP'!BD44)-'Evolutive SFP'!BD10)/1000000 -> 288.99517 | ... CS3: =(('Evolutive SFP'!CP39+'Evolutive SFP'!CP40+'Evolutive SFP'!CP41+'Evolutive SFP'!CP42+'Evolutive SFP'!CP43+'Evolutive SFP'!CP44)-'Evolutive SFP'!CP10)/1000000 -> 328.51464
B4: CCA | C4: Min 10% | D4: =D3/(('Evolutive SFP'!B27)/1000000) -> 0.1128041 | E4: =E3/(('Evolutive SFP'!C27)/1000000) -> 0.17342869 | F4: =F3/(('Evolutive SFP'!D27)/1000000) -> 0.1782267 | G4: =G3/(('Evolutive SFP'!E27)/1000000) -> 0.19830833 | H4: =H3/(('Evolutive SFP'!F27)/1000000) -> 0.27478662 | I4: =I3/(('Evolutive SFP'!G27)/1000000) -> 0.28982569 | J4: =J3/(('Evolutive SFP'!H27)/1000000) -> 0.27332525 | K4: =K3/(('Evolutive SFP'!I27)/1000000) -> 0.28074016 | ... AZ4: =AZ3/(('Evolutive SFP'!AX27)/1000000) -> 0.3008111 | BA4: =BA3/(('Evolutive SFP'!AX27)/1000000) -> 0.31428077 | BB4: =BB3/(('Evolutive SFP'!AY27)/1000000) -> 0.31056494 | BC4: =BC3/(('Evolutive SFP'!AZ27)/1000000) -> 0.31239276 | BD4: =BD3/(('Evolutive SFP'!BA27)/1000000) -> #DIV/0! | BE4: =BE3/(('Evolutive SFP'!BB27)/1000000) -> 0.30641549 | BF4: =BF3/(('Evolutive SFP'!BC27)/1000000) -> 0.30806242 | BG4: =BG3/(('Evolutive SFP'!BD27)/1000000) -> 0.30399338 | BH4: =BH3/(('Evolutive SFP'!BE27)/1000000) -> 0.30218943 | ... CS4: =CS3/(('Evolutive SFP'!CP27)/1000000) -> 0.28397576
B5: CCD | C5: Min 8% | D5: =D3/('Evolutive SFP'!B31/1000000) -> 0.1902317 | E5: =E3/('Evolutive SFP'!C31/1000000) -> 0.29145975 | F5: =F3/('Evolutive SFP'!D31/1000000) -> 0.28753106 | G5: =G3/('Evolutive SFP'!E31/1000000) -> 0.34345688 | H5: =H3/('Evolutive SFP'!F31/1000000) -> 0.45579697 | I5: =I3/('Evolutive SFP'!G31/1000000) -> 0.47275321 | J5: =J3/('Evolutive SFP'!H31/1000000) -> 0.43214834 | K5: =K3/('Evolutive SFP'!I31/1000000) -> 0.46368218 | ... BB5: =BB3/('Evolutive SFP'!AZ31/1000000) -> 0.47277364 | BC5: =BC3/('Evolutive SFP'!AZ31/1000000) -> 0.47324593 | BD5: =BD3/('Evolutive SFP'!BA31/1000000) -> #DIV/0! | BE5: =BE3/('Evolutive SFP'!BB31/1000000) -> 0.46856653 | BF5: =BF3/('Evolutive SFP'!BC31/1000000) -> 0.47701965 | BG5: =BG3/('Evolutive SFP'!BD31/1000000) -> 0.47224499 | BH5: =BH3/('Evolutive SFP'!BE31/1000000) -> 0.47013446 | BI5: =BI3/('Evolutive SFP'!BF31/1000000) -> 0.47003391 | BJ5: =BJ3/('Evolutive SFP'!BG31/1000000) -> 0.47003391 | ... CS5: =CS3/('Evolutive SFP'!CP31/1000000) -> 0.42797446
B6: ICA | C6: Min 8% | D6: =((D3*1000000)-'Evolutive SFP'!B39)/'Evolutive SFP'!B27 -> 0.10078307 | E6: =((E3*1000000)-'Evolutive SFP'!C39)/'Evolutive SFP'!C27 -> 0.076418748 | F6: =((F3*1000000)-'Evolutive SFP'!D39)/'Evolutive SFP'!D27 -> 0.087346963 | G6: =((G3*1000000)-'Evolutive SFP'!E39)/'Evolutive SFP'!E27 -> 0.11045424 | H6: =((H3*1000000)-'Evolutive SFP'!F39)/'Evolutive SFP'!F27 -> 0.14893858 | I6: =((I3*1000000)-'Evolutive SFP'!G39)/'Evolutive SFP'!G27 -> 0.17801204 | J6: =((J3*1000000)-'Evolutive SFP'!H39)/'Evolutive SFP'!H27 -> 0.1679265 | K6: =((K3*1000000)-'Evolutive SFP'!I39)/'Evolutive SFP'!I27 -> 0.17689203 | ... BA6: =((BA3*1000000)-'Evolutive SFP'!AY39)/'Evolutive SFP'!AY27 -> 0.22401797 | BB6: =((BB3*1000000)-'Evolutive SFP'!AY39)/'Evolutive SFP'!AY27 -> 0.2200448 | BC6: =((BC3*1000000)-'Evolutive SFP'!AZ39)/'Evolutive SFP'!AZ27 -> 0.22075654 | BD6: =((BD3*1000000)-'Evolutive SFP'!BA39)/'Evolutive SFP'!BA27 -> #DIV/0! | BE6: =((BE3*1000000)-'Evolutive SFP'!BB39)/'Evolutive SFP'!BB27 -> 0.21660352 | BF6: =((BF3*1000000)-'Evolutive SFP'!BC39)/'Evolutive SFP'!BC27 -> 0.21801365 | BG6: =((BG3*1000000)-'Evolutive SFP'!BD39)/'Evolutive SFP'!BD27 -> 0.21513792 | BH6: =((BH3*1000000)-'Evolutive SFP'!BE39)/'Evolutive SFP'!BE27 -> 0.21352044 | BI6: =((BI3*1000000)-'Evolutive SFP'!BF39)/'Evolutive SFP'!BF27 -> 0.21230626 | ... CS6: =((CS3*1000000)-'Evolutive SFP'!CP39)/'Evolutive SFP'!CP27 -> 0.20209763
A7: ASSET QUALITY | B7: A/LNPL30 | M7: ='Evolutive SFP'!K16/('FORM 4'!#REF!+'FORM 4'!#REF!+'FORM 4'!#REF!) -> #REF! | P7: ='Evolutive SFP'!N16/('FORM 4'!#REF!+'FORM 4'!#REF!+'FORM 4'!#REF!) -> #REF! | S7: ='Evolutive SFP'!Q16/('FORM 4'!#REF!+'FORM 4'!#REF!+'FORM 4'!#REF!) -> #REF! | V7: ='Evolutive SFP'!T16/('FORM 4'!#REF!+'FORM 4'!#REF!+'FORM 4'!#REF!) -> #REF! | X7: ='Evolutive SFP'!V16/('FORM 4'!#REF!+'FORM 4'!#REF!+'FORM 4'!#REF!) -> #REF!
B8: NPL30 | M8: =('FORM 4'!#REF!+'FORM 4'!#REF!+'FORM 4'!#REF!)/'Evolutive SFP'!K15 -> #REF! | P8: =('FORM 4'!#REF!+'FORM 4'!#REF!+'FORM 4'!#REF!)/'Evolutive SFP'!N15 -> #REF! | S8: =('FORM 4'!#REF!+'FORM 4'!#REF!+'FORM 4'!#REF!)/'Evolutive SFP'!Q15 -> #REF! | V8: =('FORM 4'!#REF!+'FORM 4'!#REF!+'FORM 4'!#REF!)/'Evolutive SFP'!T15 -> #REF! | W8: =('FORM 4'!#REF!+'FORM 4'!#REF!+'FORM 4'!#REF!)/'Evolutive SFP'!U15 -> #REF! | X8: =('FORM 4'!#REF!+'FORM 4'!#REF!+'FORM 4'!#REF!)/'Evolutive SFP'!V15 -> #REF! | Y8: =('FORM 4'!#REF!+'FORM 4'!#REF!+'FORM 4'!#REF!)/'Evolutive SFP'!W15 -> #REF! | Z8: =SUM('[1]Portfolio Analysis'!$D$12+'[1]Portfolio Analysis'!$D$13+'[1]Portfolio Analysis'!$D$14)/'[1]Portfolio Analysis'!$D$15 -> 0.067903395 | AA8: =('FORM 4'!#REF!+'FORM 4'!#REF!+'FORM 4'!#REF!)/'Evolutive SFP'!Y15 -> #REF! | AB8: =('FORM 4'!#REF!+'FORM 4'!#REF!+'FORM 4'!#REF!)/'Evolutive SFP'!Z15 -> #REF! | AC8: =SUM('[2]Portfolio Analysis'!$D$12+'[2]Portfolio Analysis'!$D$13+'[2]Portfolio Analysis'!$D$14)/'[2]Portfolio Analysis'!$D$15 -> 0.05524959 | AD8: =('FORM 4'!#REF!+'FORM 4'!#REF!+'FORM 4'!#REF!)/'Evolutive SFP'!AB15 -> #REF! | AE8: =('FORM 4'!#REF!+'FORM 4'!#REF!+'FORM 4'!#REF!)/'Evolutive SFP'!AC15 -> #REF! | AF8: =SUM(17474421.05+5860841.49+9041777.98)/636660719.4 -> 0.050854465 | AG8: =SUM(17474421.05+5860841.49+9041777.98)/636660719.4 -> 0.050854465 | AH8: =SUM(17474421.05+5860841.49+9041777.98)/636660719.4 -> 0.050854465 | AI8: =SUM(17474421.05+5860841.49+9041777.98)/636660719.4 -> 0.050854465 | BM8: ='FORM 4'!D25 -> 0.074406302 | BN8: ='FORM 4'!E25 -> 0 | BO8: ='FORM 4'!F25 -> 0 | BP8: ='FORM 4'!G25 -> 0 | BQ8: ='FORM 4'!H25 -> 0 | BR8: ='FORM 4'!I25 -> 0 | BS8: ='FORM 4'!J25 -> 0 | BT8: ='FORM 4'!K25 -> 0 | ... CS8: ='FORM 4'!AJ25 -> 0
A9: EARNINGS | B9: ROA | E9: ='Evolutitve SCI'!C33/(('Evolutive SFP'!B27+'Evolutive SFP'!C27)/2) -> 0.033974564 | F9: ='Evolutitve SCI'!D33/(('Evolutive SFP'!C27+'Evolutive SFP'!D27)/2) -> 0.018987682 | G9: ='Evolutitve SCI'!E33/(('Evolutive SFP'!D27+'Evolutive SFP'!E27)/2) -> 0.034297735 | H9: ='Evolutitve SCI'!F33/(('Evolutive SFP'!E27+'Evolutive SFP'!F27)/2) -> 0.038169304 | I9: ='Evolutitve SCI'!G33/(('Evolutive SFP'!F27+'Evolutive SFP'!G27)/2) -> 0.040738775 | J9: ='Evolutitve SCI'!H33/(('Evolutive SFP'!G27+'Evolutive SFP'!H27)/2) -> 0.015075693 | K9: ='Evolutitve SCI'!I33/(('Evolutive SFP'!H27+'Evolutive SFP'!I27)/2) -> -0.0036262241 | L9: ='Evolutitve SCI'!J33/(('Evolutive SFP'!I27+'Evolutive SFP'!J27)/2) -> 0.0073050667 | ... BB9: ='Evolutitve SCI'!AZ33/(('Evolutive SFP'!AY27+'Evolutive SFP'!AZ27)/2) -> 0.018483626 | BC9: ='Evolutitve SCI'!BA33/(('Evolutive SFP'!AY27+'Evolutive SFP'!AZ27)/2) -> 0.018122081 | BD9: ='Evolutitve SCI'!BB33/(('Evolutive SFP'!AZ27+'Evolutive SFP'!BA27)/2) -> 0 | BE9: ='Evolutitve SCI'!BC33/(('Evolutive SFP'!BA27+'Evolutive SFP'!BB27)/2) -> 0.039507324 | BF9: ='Evolutitve SCI'!BD33/(('Evolutive SFP'!BB27+'Evolutive SFP'!BC27)/2) -> 0.0070211309 | BG9: ='Evolutitve SCI'!BE33/(('Evolutive SFP'!BC27+'Evolutive SFP'!BD27)/2) -> 0.021480495 | BH9: ='Evolutitve SCI'!BF33/(('Evolutive SFP'!BD27+'Evolutive SFP'!BE27)/2) -> 0.0206043 | BI9: ='Evolutitve SCI'!BG33/(('Evolutive SFP'!BE27+'Evolutive SFP'!BF27)/2) -> 0.023864672 | BJ9: ='Evolutitve SCI'!BH33/(('Evolutive SFP'!BF27+'Evolutive SFP'!BG27)/2) -> 0.019132042 | ... CS9: ='Evolutitve SCI'!CQ33/(('Evolutive SFP'!CO27+'Evolutive SFP'!CP27)/2) -> 0.0048708489
B10: Cost Income ratio | D10: ='Evolutitve SCI'!B23/'Evolutitve SCI'!B19 -> 0.69568116 | E10: ='Evolutitve SCI'!C23/'Evolutitve SCI'!C19 -> 0.58680977 | F10: ='Evolutitve SCI'!D23/'Evolutitve SCI'!D19 -> 0.67523016 | G10: ='Evolutitve SCI'!E23/'Evolutitve SCI'!E19 -> 0.69541036 | H10: ='Evolutitve SCI'!F23/'Evolutitve SCI'!F19 -> 0.62645577 | I10: ='Evolutitve SCI'!G23/'Evolutitve SCI'!G19 -> 0.64741086 | J10: ='Evolutitve SCI'!H23/'Evolutitve SCI'!H19 -> 0.77081349 | K10: ='Evolutitve SCI'!I23/'Evolutitve SCI'!I19 -> 5.6768223 | ... CS10: ='Evolutitve SCI'!CQ23/'Evolutitve SCI'!CQ19 -> 1.0212092
B11: Operating Expense ratio | D11: =('Evolutitve SCI'!B23+'Evolutitve SCI'!B12)/(('Evolutive SFP'!B27+'Evolutive SFP'!C27)/2) -> 0.10503131 | E11: =('Evolutitve SCI'!C23+'Evolutitve SCI'!C12)/(('Evolutive SFP'!C27+'Evolutive SFP'!D27)/2) -> 0.11730013 | F11: =('Evolutitve SCI'!D23+'Evolutitve SCI'!D12)/(('Evolutive SFP'!D27+'Evolutive SFP'!E27)/2) -> 0.13106299 | G11: =('Evolutitve SCI'!E23+'Evolutitve SCI'!E12)/(('Evolutive SFP'!E27+'Evolutive SFP'!F27)/2) -> 0.14815102 | H11: =('Evolutitve SCI'!F23+'Evolutitve SCI'!F12)/(('Evolutive SFP'!F27+'Evolutive SFP'!G27)/2) -> 0.13060366 | I11: =('Evolutitve SCI'!G23+'Evolutitve SCI'!G12)/(('Evolutive SFP'!G27+'Evolutive SFP'!H27)/2) -> 0.12847665 | J11: =('Evolutitve SCI'!H23+'Evolutitve SCI'!H12)/(('Evolutive SFP'!H27+'Evolutive SFP'!I27)/2) -> 0.14533302 | K11: =('Evolutitve SCI'!I23+'Evolutitve SCI'!I12)/(('Evolutive SFP'!I27+'Evolutive SFP'!J27)/2) -> 0.0077485304 | ... BG11: =('Evolutitve SCI'!BE23+'Evolutitve SCI'!BE12)/(('Evolutive SFP'!BE27+'Evolutive SFP'!BF27)/2) -> 0.10722982 | BH11: =('Evolutitve SCI'!BF23+'Evolutitve SCI'!BF12)/(('Evolutive SFP'!BE27+'Evolutive SFP'!BF27)/2) -> 0.11814436 | BI11: =('Evolutitve SCI'!BG23+'Evolutitve SCI'!BG12)/(('Evolutive SFP'!BF27+'Evolutive SFP'!BG27)/2) -> 0.13293912 | BJ11: =('Evolutitve SCI'!BH23+'Evolutitve SCI'!BH12)/(('Evolutive SFP'!BG27+'Evolutive SFP'!BH27)/2) -> 0.13660849 | BK11: =('Evolutitve SCI'!BI23+'Evolutitve SCI'!BI12)/(('Evolutive SFP'!BH27+'Evolutive SFP'!BI27)/2) -> 0.013219112 | BL11: =('Evolutitve SCI'!BJ23+'Evolutitve SCI'!BJ12)/(('Evolutive SFP'!BI27+'Evolutive SFP'!BJ27)/2) -> 0.027278807 | BM11: =('Evolutitve SCI'!BK23+'Evolutitve SCI'!BK12)/(('Evolutive SFP'!BJ27+'Evolutive SFP'!BK27)/2) -> 0.041043066 | BN11: =('Evolutitve SCI'!BL23+'Evolutitve SCI'!BL12)/(('Evolutive SFP'!BK27+'Evolutive SFP'!BL27)/2) -> 0.051870797 | BO11: =('Evolutitve SCI'!BM23+'Evolutitve SCI'!BM12)/(('Evolutive SFP'!BL27+'Evolutive SFP'!BM27)/2) -> 0.062552498 | ... CS11: =('Evolutitve SCI'!CQ23+'Evolutitve SCI'!CQ12)/(('Evolutive SFP'!CP27+'Evolutive SFP'!CQ27)/2) -> 0.23127427
A12: LIQUIDITY | B12: MIN LIQ ratio | C12: Min 15% | D12: =('Evolutive SFP'!B4)/('Evolutive SFP'!B28+'Evolutive SFP'!B29+'Evolutive SFP'!B32+'Evolutive SFP'!B33+'Evolutive SFP'!B34+'Evolutive SFP'!B35+'Evolutive SFP'!B36) -> 1.3285562 | E12: =('Evolutive SFP'!C4)/('Evolutive SFP'!C28+'Evolutive SFP'!C29+'Evolutive SFP'!C32+'Evolutive SFP'!C33+'Evolutive SFP'!C34+'Evolutive SFP'!C35+'Evolutive SFP'!C36) -> 0.072699102 | F12: =('Evolutive SFP'!D4)/('Evolutive SFP'!D28+'Evolutive SFP'!D29+'Evolutive SFP'!D32+'Evolutive SFP'!D33+'Evolutive SFP'!D34+'Evolutive SFP'!D35+'Evolutive SFP'!D36) -> 0.040738033 | G12: =('Evolutive SFP'!E4)/('Evolutive SFP'!E28+'Evolutive SFP'!E29+'Evolutive SFP'!E32+'Evolutive SFP'!E33+'Evolutive SFP'!E34+'Evolutive SFP'!E35+'Evolutive SFP'!E36) -> 0.1211201 | H12: =('Evolutive SFP'!F4)/('Evolutive SFP'!F28+'Evolutive SFP'!F29+'Evolutive SFP'!F32+'Evolutive SFP'!F33+'Evolutive SFP'!F34+'Evolutive SFP'!F35+'Evolutive SFP'!F36) -> 0.67821272 | I12: =('Evolutive SFP'!G4)/('Evolutive SFP'!G28+'Evolutive SFP'!G29+'Evolutive SFP'!G32+'Evolutive SFP'!G33+'Evolutive SFP'!G34+'Evolutive SFP'!G35+'Evolutive SFP'!G36) -> 0.7816182 | J12: =('Evolutive SFP'!H4)/('Evolutive SFP'!H28+'Evolutive SFP'!H29+'Evolutive SFP'!H32+'Evolutive SFP'!H33+'Evolutive SFP'!H34+'Evolutive SFP'!H35+'Evolutive SFP'!H36) -> 0.27527071 | K12: =('Evolutive SFP'!I4)/('Evolutive SFP'!I28+'Evolutive SFP'!I29+'Evolutive SFP'!I32+'Evolutive SFP'!I33+'Evolutive SFP'!I34+'Evolutive SFP'!I35+'Evolutive SFP'!I36) -> 0.18759746 | ... BC12: =('Evolutive SFP'!BA4)/('Evolutive SFP'!BA28+'Evolutive SFP'!BA29+'Evolutive SFP'!BA32+'Evolutive SFP'!BA33+'Evolutive SFP'!BA34+'Evolutive SFP'!BA35+'Evolutive SFP'!BA36) -> #DIV/0! | BD12: =('Evolutive SFP'!BA4)/('Evolutive SFP'!BA28+'Evolutive SFP'!BA29+'Evolutive SFP'!BA32+'Evolutive SFP'!BA33+'Evolutive SFP'!BA34+'Evolutive SFP'!BA35+'Evolutive SFP'!BA36) -> #DIV/0! | BE12: =('Evolutive SFP'!BB4)/('Evolutive SFP'!BB28+'Evolutive SFP'!BB29+'Evolutive SFP'!BB32+'Evolutive SFP'!BB33+'Evolutive SFP'!BB34+'Evolutive SFP'!BB35+'Evolutive SFP'!BB36) -> 0.88249301 | BF12: =('Evolutive SFP'!BC4)/('Evolutive SFP'!BC28+'Evolutive SFP'!BC29+'Evolutive SFP'!BC32+'Evolutive SFP'!BC33+'Evolutive SFP'!BC34+'Evolutive SFP'!BC35+'Evolutive SFP'!BC36) -> 0.86699234 | BG12: =('Evolutive SFP'!BD4)/('Evolutive SFP'!BD28+'Evolutive SFP'!BD29+'Evolutive SFP'!BD32+'Evolutive SFP'!BD33+'Evolutive SFP'!BD34+'Evolutive SFP'!BD35+'Evolutive SFP'!BD36) -> 0.80743523 | BH12: =('Evolutive SFP'!BE4)/('Evolutive SFP'!BE28+'Evolutive SFP'!BE29+'Evolutive SFP'!BE32+'Evolutive SFP'!BE33+'Evolutive SFP'!BE34+'Evolutive SFP'!BE35+'Evolutive SFP'!BE36) -> 0.83199818 | BI12: =('Evolutive SFP'!BF4)/('Evolutive SFP'!BF28+'Evolutive SFP'!BF29+'Evolutive SFP'!BF32+'Evolutive SFP'!BF33+'Evolutive SFP'!BF34+'Evolutive SFP'!BF35+'Evolutive SFP'!BF36) -> 0.7587505 | BJ12: =('Evolutive SFP'!BG4)/('Evolutive SFP'!BG28+'Evolutive SFP'!BG29+'Evolutive SFP'!BG32+'Evolutive SFP'!BG33+'Evolutive SFP'!BG34+'Evolutive SFP'!BG35+'Evolutive SFP'!BG36) -> 0.75006187 | BK12: =('Evolutive SFP'!BH4)/('Evolutive SFP'!BH28+'Evolutive SFP'!BH29+'Evolutive SFP'!BH32+'Evolutive SFP'!BH33+'Evolutive SFP'!BH34+'Evolutive SFP'!BH35+'Evolutive SFP'!BH36) -> 0.77788058 | ... CS12: =('Evolutive SFP'!CP4)/('Evolutive SFP'!CP28+'Evolutive SFP'!CP29+'Evolutive SFP'!CP32+'Evolutive SFP'!CP33+'Evolutive SFP'!CP34+'Evolutive SFP'!CP35+'Evolutive SFP'!CP36) -> 0.66714016
B13: T/LIQ ratio | D13: ='Evolutive SFP'!B4/('Evolutive SFP'!B31+'Evolutive SFP'!B36) -> 0.20955501 | E13: ='Evolutive SFP'!C4/('Evolutive SFP'!C31+'Evolutive SFP'!C36) -> 0.077404814 | F13: ='Evolutive SFP'!D4/('Evolutive SFP'!D31+'Evolutive SFP'!D36) -> 0.040502968 | G13: ='Evolutive SFP'!E4/('Evolutive SFP'!E31+'Evolutive SFP'!E36) -> 0.12129664 | H13: ='Evolutive SFP'!F4/('Evolutive SFP'!F31+'Evolutive SFP'!F36) -> 0.13348318 | I13: ='Evolutive SFP'!G4/('Evolutive SFP'!G31+'Evolutive SFP'!G36) -> 0.18302983 | J13: ='Evolutive SFP'!H4/('Evolutive SFP'!H31+'Evolutive SFP'!H36) -> 0.076209981 | K13: ='Evolutive SFP'!I4/('Evolutive SFP'!I31+'Evolutive SFP'!I36) -> 0.048426593 | ... AV13: ='Evolutive SFP'!AT4/('Evolutive SFP'!AT31+'Evolutive SFP'!AT36) -> 0.11309083 | AX13: ='Evolutive SFP'!AU4/('Evolutive SFP'!AU31+'Evolutive SFP'!AU36) -> 0.11317796 | AY13: ='Evolutive SFP'!AV4/('Evolutive SFP'!AV31+'Evolutive SFP'!AV36) -> 0.15201653 | AZ13: ='Evolutive SFP'!AW4/('Evolutive SFP'!AW31+'Evolutive SFP'!AW36) -> 0.12600553 | BA13: ='Evolutive SFP'!AX4/('Evolutive SFP'!AX31+'Evolutive SFP'!AX36) -> 0.16437027 | BB13: ='Evolutive SFP'!AY4/('Evolutive SFP'!AY31+'Evolutive SFP'!AY36) -> 0.17726136 | BC13: ='Evolutive SFP'!AZ4/('Evolutive SFP'!AZ31+'Evolutive SFP'!AZ36) -> 0.18105793 | BD13: ='Evolutive SFP'!BA4/('Evolutive SFP'!BA31+'Evolutive SFP'!BA36) -> #DIV/0! | BE13: ='Evolutive SFP'!BB4/('Evolutive SFP'!BB31+'Evolutive SFP'!BB36) -> 0.17921448 | ... CS13: ='Evolutive SFP'!CP4/('Evolutive SFP'!CP31+'Evolutive SFP'!CP36) -> 0.1453301
B14: EB ratio | C14: Max 25% | D14: ='Evolutive SFP'!B37/'Evolutive SFP'!B27 -> 0.2333531 | E14: ='Evolutive SFP'!C37/'Evolutive SFP'!C27 -> 0.17492548 | F14: ='Evolutive SFP'!D37/'Evolutive SFP'!D27 -> 0.16605485 | G14: ='Evolutive SFP'!E37/'Evolutive SFP'!E27 -> 0.14867076 | H14: ='Evolutive SFP'!F37/'Evolutive SFP'!F27 -> 0.026636812 | I14: ='Evolutive SFP'!G37/'Evolutive SFP'!G27 -> 0 | J14: ='Evolutive SFP'!H37/'Evolutive SFP'!H27 -> 0 | K14: ='Evolutive SFP'!I37/'Evolutive SFP'!I27 -> 0 | ... BA14: ='Evolutive SFP'!AY37/'Evolutive SFP'!AY27 -> 0 | BB14: ='Evolutive SFP'!AY37/'Evolutive SFP'!AY27 -> 0 | BC14: ='Evolutive SFP'!AZ37/'Evolutive SFP'!AZ27 -> 0 | BD14: ='Evolutive SFP'!BA37/'Evolutive SFP'!BA27 -> #DIV/0! | BE14: ='Evolutive SFP'!BB37/'Evolutive SFP'!BB27 -> 0 | BF14: ='Evolutive SFP'!BC37/'Evolutive SFP'!BC27 -> 0 | BG14: ='Evolutive SFP'!BD37/'Evolutive SFP'!BD27 -> 0 | BH14: ='Evolutive SFP'!BE37/'Evolutive SFP'!BE27 -> 0 | BI14: ='Evolutive SFP'!BF37/'Evolutive SFP'!BF27 -> 0 | ... CS14: ='Evolutive SFP'!CP37/'Evolutive SFP'!CP27 -> 0
B15: LA to TA ratio | D15: ='Evolutive SFP'!B4/'Evolutive SFP'!B27 -> 0.13612117 | E15: ='Evolutive SFP'!C4/'Evolutive SFP'!C27 -> 0.046927058 | F15: ='Evolutive SFP'!D4/'Evolutive SFP'!D27 -> 0.027315729 | G15: ='Evolutive SFP'!E4/'Evolutive SFP'!E27 -> 0.078980956 | H15: ='Evolutive SFP'!F4/'Evolutive SFP'!F27 -> 0.093053273 | I15: ='Evolutive SFP'!G4/'Evolutive SFP'!G27 -> 0.12058687 | J15: ='Evolutive SFP'!H4/'Evolutive SFP'!H27 -> 0.051861699 | K15: ='Evolutive SFP'!I4/'Evolutive SFP'!I27 -> 0.035188004 | ... BA15: ='Evolutive SFP'!AY4/'Evolutive SFP'!AY27 -> 0.12221019 | BB15: ='Evolutive SFP'!AY4/'Evolutive SFP'!AY27 -> 0.12221019 | BC15: ='Evolutive SFP'!AZ4/'Evolutive SFP'!AZ27 -> 0.12449675 | BD15: ='Evolutive SFP'!BA4/'Evolutive SFP'!BA27 -> #DIV/0! | BE15: ='Evolutive SFP'!BB4/'Evolutive SFP'!BB27 -> 0.1243004 | BF15: ='Evolutive SFP'!BC4/'Evolutive SFP'!BC27 -> 0.11732265 | BG15: ='Evolutive SFP'!BD4/'Evolutive SFP'!BD27 -> 0.11664838 | BH15: ='Evolutive SFP'!BE4/'Evolutive SFP'!BE27 -> 0.12017579 | BI15: ='Evolutive SFP'!BF4/'Evolutive SFP'!BF27 -> 0.11665477 | ... CS15: ='Evolutive SFP'!CP4/'Evolutive SFP'!CP27 -> 0.10405988
A16: STRUCTURE | B16: NEA ratio | C16: Max 10% | D16: =('Evolutive SFP'!B7+'Evolutive SFP'!B21)/'Evolutive SFP'!B27 -> 0.20939732 | E16: =('Evolutive SFP'!C7+'Evolutive SFP'!C21)/'Evolutive SFP'!C27 -> 0.22358083 | F16: =('Evolutive SFP'!D7+'Evolutive SFP'!D21)/'Evolutive SFP'!D27 -> 0.21748753 | G16: =('Evolutive SFP'!E7+'Evolutive SFP'!E21)/'Evolutive SFP'!E27 -> 0.17500111 | H16: =('Evolutive SFP'!F7+'Evolutive SFP'!F21)/'Evolutive SFP'!F27 -> 0.2244304 | I16: =('Evolutive SFP'!G7+'Evolutive SFP'!G21)/'Evolutive SFP'!G27 -> 0.21025254 | J16: =('Evolutive SFP'!H7+'Evolutive SFP'!H21)/'Evolutive SFP'!H27 -> 0.22969194 | K16: =('Evolutive SFP'!I7+'Evolutive SFP'!I21)/'Evolutive SFP'!I27 -> 0.21512361 | ... BC16: =('Evolutive SFP'!BA7+'Evolutive SFP'!BA21)/'Evolutive SFP'!BA27 -> #DIV/0! | BD16: =('Evolutive SFP'!BA7+'Evolutive SFP'!BA21)/'Evolutive SFP'!BA27 -> #DIV/0! | BE16: =('Evolutive SFP'!BB7+'Evolutive SFP'!BB21)/'Evolutive SFP'!BB27 -> 0.077018815 | BF16: =('Evolutive SFP'!BC7+'Evolutive SFP'!BC21)/'Evolutive SFP'!BC27 -> 0.07794438 | BG16: =('Evolutive SFP'!BD7+'Evolutive SFP'!BD21)/'Evolutive SFP'!BD27 -> 0.077022478 | BH16: =('Evolutive SFP'!BE7+'Evolutive SFP'!BE21)/'Evolutive SFP'!BE27 -> 0.076900605 | BI16: =('Evolutive SFP'!BF7+'Evolutive SFP'!BF21)/'Evolutive SFP'!BF27 -> 0.073559438 | BJ16: =('Evolutive SFP'!BG7+'Evolutive SFP'!BG21)/'Evolutive SFP'!BG27 -> 0.072414321 | BK16: =('Evolutive SFP'!BH7+'Evolutive SFP'!BH21)/'Evolutive SFP'!BH27 -> 0.072950359 | ... CS16: =('Evolutive SFP'!CP7+'Evolutive SFP'!CP21)/'Evolutive SFP'!CP27 -> 0.048736517
B17: LB ratio | C17: Max 5% | D17: ='Evolutive SFP'!B21/'Evolutive SFP'!B27 -> 0.1802488 | E17: ='Evolutive SFP'!C21/'Evolutive SFP'!C27 -> 0.17922304 | F17: ='Evolutive SFP'!D21/'Evolutive SFP'!D27 -> 0.13850922 | G17: ='Evolutive SFP'!E21/'Evolutive SFP'!E27 -> 0.11848966 | H17: ='Evolutive SFP'!F21/'Evolutive SFP'!F27 -> 0.10905715 | I17: ='Evolutive SFP'!G21/'Evolutive SFP'!G27 -> 0.15683061 | J17: ='Evolutive SFP'!H21/'Evolutive SFP'!H27 -> 0.17372884 | K17: ='Evolutive SFP'!I21/'Evolutive SFP'!I27 -> 0.21512361 | ... BB17: ='Evolutive SFP'!AZ21/'Evolutive SFP'!AZ27 -> 0.078004451 | BC17: ='Evolutive SFP'!AZ21/'Evolutive SFP'!AZ27 -> 0.078004451 | BD17: ='Evolutive SFP'!BA21/'Evolutive SFP'!BA27 -> #DIV/0! | BE17: ='Evolutive SFP'!BB21/'Evolutive SFP'!BB27 -> 0.077018815 | BF17: ='Evolutive SFP'!BC21/'Evolutive SFP'!BC27 -> 0.07794438 | BG17: ='Evolutive SFP'!BD21/'Evolutive SFP'!BD27 -> 0.077022478 | BH17: ='Evolutive SFP'!BE21/'Evolutive SFP'!BE27 -> 0.076900605 | BI17: ='Evolutive SFP'!BF21/'Evolutive SFP'!BF27 -> 0.073559438 | BJ17: ='Evolutive SFP'!BG21/'Evolutive SFP'!BG27 -> 0.057892927 | ... CS17: ='Evolutive SFP'!CP21/'Evolutive SFP'!CP27 -> 0.048736517
B18: PI to Deposit ratio | C18: Max 5% | D18: ='Evolutive SFP'!B13/'Evolutive SFP'!B31 -> 0 | E18: ='Evolutive SFP'!C13/'Evolutive SFP'!C31 -> 0.039731496 | F18: ='Evolutive SFP'!D13/'Evolutive SFP'!D31 -> 0.035478749 | G18: ='Evolutive SFP'!E13/'Evolutive SFP'!E31 -> 0.035220652 | H18: ='Evolutive SFP'!F13/'Evolutive SFP'!F31 -> 0.045259943 | I18: ='Evolutive SFP'!G13/'Evolutive SFP'!G31 -> 0.042772262 | J18: ='Evolutive SFP'!H13/'Evolutive SFP'!H31 -> 0.058155935 | K18: ='Evolutive SFP'!I13/'Evolutive SFP'!I31 -> 0.060756404 | ... AZ18: ='Evolutive SFP'!AX13/'Evolutive SFP'!AX31 -> 0.054321392 | BA18: ='Evolutive SFP'!AX13/'Evolutive SFP'!AX31 -> 0.054321392 | BB18: ='Evolutive SFP'!AY13/'Evolutive SFP'!AY31 -> 0.054891346 | BC18: ='Evolutive SFP'!AZ13/'Evolutive SFP'!AZ31 -> 0.05641736 | BD18: ='Evolutive SFP'!BA13/'Evolutive SFP'!BA31 -> #DIV/0! | BE18: ='Evolutive SFP'!BB13/'Evolutive SFP'!BB31 -> 0.056707747 | BF18: ='Evolutive SFP'!BC13/'Evolutive SFP'!BC31 -> 0.058163931 | BG18: ='Evolutive SFP'!BD13/'Evolutive SFP'!BD31 -> 0.058097381 | BH18: ='Evolutive SFP'!BE13/'Evolutive SFP'!BE31 -> 0.058627238 | ... CS18: ='Evolutive SFP'!CP13/'Evolutive SFP'!CP31 -> 0
B19: PI to CC ratio | C19: Max 40% | D19: ='Evolutive SFP'!B13/(CAELS!D3*1000000) -> 0 | E19: ='Evolutive SFP'!C13/(CAELS!E3*1000000) -> 0.13631898 | F19: ='Evolutive SFP'!D13/(CAELS!F3*1000000) -> 0.12339102 | G19: ='Evolutive SFP'!E13/(CAELS!G3*1000000) -> 0.10254752 | H19: ='Evolutive SFP'!F13/(CAELS!H3*1000000) -> 0.099298473 | I19: ='Evolutive SFP'!G13/(CAELS!I3*1000000) -> 0.090474821 | J19: ='Evolutive SFP'!H13/(CAELS!J3*1000000) -> 0.13457401 | K19: ='Evolutive SFP'!I13/(CAELS!K3*1000000) -> 0.13103028 | ... AZ19: ='Evolutive SFP'!AX13/(CAELS!AZ3*1000000) -> 0.12004859 | BA19: ='Evolutive SFP'!AX13/(CAELS!BA3*1000000) -> 0.11490346 | BB19: ='Evolutive SFP'!AY13/(CAELS!BB3*1000000) -> 0.11785309 | BC19: ='Evolutive SFP'!AZ13/(CAELS!BC3*1000000) -> 0.11921362 | BD19: ='Evolutive SFP'!BA13/(CAELS!BD3*1000000) -> #DIV/0! | BE19: ='Evolutive SFP'!BB13/(CAELS!BE3*1000000) -> 0.1210239 | BF19: ='Evolutive SFP'!BC13/(CAELS!BF3*1000000) -> 0.12193194 | BG19: ='Evolutive SFP'!BD13/(CAELS!BG3*1000000) -> 0.12302382 | BH19: ='Evolutive SFP'!BE13/(CAELS!BH3*1000000) -> 0.12470313 | ... CS19: ='Evolutive SFP'!CP13/(CAELS!CS3*1000000) -> 0
B20: Gross loans/TA | D20: ='Evolutive SFP'!B15/'Evolutive SFP'!B27 -> 0.62533298 | E20: ='Evolutive SFP'!C15/'Evolutive SFP'!C27 -> 0.70205951 | F20: ='Evolutive SFP'!D15/'Evolutive SFP'!D27 -> 0.71547863 | G20: ='Evolutive SFP'!E15/'Evolutive SFP'!E27 -> 0.70625056 | H20: ='Evolutive SFP'!F15/'Evolutive SFP'!F27 -> 0.67506936 | I20: ='Evolutive SFP'!G15/'Evolutive SFP'!G27 -> 0.64513162 | J20: ='Evolutive SFP'!H15/'Evolutive SFP'!H27 -> 0.70522142 | K20: ='Evolutive SFP'!I15/'Evolutive SFP'!I27 -> 0.7130316 | ... AZ20: ='Evolutive SFP'!AX15/'Evolutive SFP'!AX27 -> 0.79090673 | BA20: ='Evolutive SFP'!AX15/'Evolutive SFP'!AX27 -> 0.79090673 | BB20: ='Evolutive SFP'!AY15/'Evolutive SFP'!AY27 -> 0.78268128 | BC20: ='Evolutive SFP'!AZ15/'Evolutive SFP'!AZ27 -> 0.78185297 | BD20: ='Evolutive SFP'!BA15/'Evolutive SFP'!BA27 -> #DIV/0! | BE20: ='Evolutive SFP'!BB15/'Evolutive SFP'!BB27 -> 0.78331116 | BF20: ='Evolutive SFP'!BC15/'Evolutive SFP'!BC27 -> 0.79013469 | BG20: ='Evolutive SFP'!BD15/'Evolutive SFP'!BD27 -> 0.79037012 | BH20: ='Evolutive SFP'!BE15/'Evolutive SFP'!BE27 -> 0.79294421 | ... CS20: ='Evolutive SFP'!CP15/'Evolutive SFP'!CP27 -> 0.75242983
A21: FUNDING MIX | B21: Total Deposits/Total Assets | D21: ='Evolutive SFP'!B31/'Evolutive SFP'!B27 -> 0.59298267 | E21: ='Evolutive SFP'!C31/'Evolutive SFP'!C27 -> 0.59503481 | F21: ='Evolutive SFP'!D31/'Evolutive SFP'!D27 -> 0.61985198 | G21: ='Evolutive SFP'!E31/'Evolutive SFP'!E27 -> 0.57738929 | H21: ='Evolutive SFP'!F31/'Evolutive SFP'!F27 -> 0.60287065 | I21: ='Evolutive SFP'!G31/'Evolutive SFP'!G27 -> 0.61305916 | J21: ='Evolutive SFP'!H31/'Evolutive SFP'!H27 -> 0.63248015 | K21: ='Evolutive SFP'!I31/'Evolutive SFP'!I27 -> 0.60545816 | ... BA21: ='Evolutive SFP'!AY31/'Evolutive SFP'!AY27 -> 0.66679067 | BB21: ='Evolutive SFP'!AY31/'Evolutive SFP'!AY27 -> 0.66679067 | BC21: ='Evolutive SFP'!AZ31/'Evolutive SFP'!AZ27 -> 0.66010661 | BD21: ='Evolutive SFP'!BA31/'Evolutive SFP'!BA27 -> #DIV/0! | BE21: ='Evolutive SFP'!BB31/'Evolutive SFP'!BB27 -> 0.65394234 | BF21: ='Evolutive SFP'!BC31/'Evolutive SFP'!BC27 -> 0.64580655 | BG21: ='Evolutive SFP'!BD31/'Evolutive SFP'!BD27 -> 0.64371965 | BH21: ='Evolutive SFP'!BE31/'Evolutive SFP'!BE27 -> 0.64277235 | BI21: ='Evolutive SFP'!BF31/'Evolutive SFP'!BF27 -> 0.63751719 | ... CJ21: ='Evolutive SFP'!CG31/'Evolutive SFP'!CG27 -> 0.63919042
B22: BOSA Deposits/Total Assets | D22: ='Evolutive SFP'!B30/'Evolutive SFP'!B27 -> 0.54743668 | E22: ='Evolutive SFP'!C30/'Evolutive SFP'!C27 -> 0.004849554 | F22: ='Evolutive SFP'!D30/'Evolutive SFP'!D27 -> 0.0046991368 | G22: ='Evolutive SFP'!E30/'Evolutive SFP'!E27 -> 0.00093296888 | H22: ='Evolutive SFP'!F30/'Evolutive SFP'!F27 -> 0.5613729 | I22: ='Evolutive SFP'!G30/'Evolutive SFP'!G27 -> 0.5642934 | J22: ='Evolutive SFP'!H30/'Evolutive SFP'!H27 -> 0.54575233 | K22: ='Evolutive SFP'!I30/'Evolutive SFP'!I27 -> 0.53905377 | ... BA22: ='Evolutive SFP'!AY30/'Evolutive SFP'!AY27 -> 0.55593176 | BB22: ='Evolutive SFP'!AY30/'Evolutive SFP'!AY27 -> 0.55593176 | BC22: ='Evolutive SFP'!AZ30/'Evolutive SFP'!AZ27 -> 0.5625051 | BD22: ='Evolutive SFP'!BA30/'Evolutive SFP'!BA27 -> #DIV/0! | BE22: ='Evolutive SFP'!BB30/'Evolutive SFP'!BB27 -> 0.55273318 | BF22: ='Evolutive SFP'!BC30/'Evolutive SFP'!BC27 -> 0.55661614 | BG22: ='Evolutive SFP'!BD30/'Evolutive SFP'!BD27 -> 0.55153884 | BH22: ='Evolutive SFP'!BE30/'Evolutive SFP'!BE27 -> 0.5533682 | BI22: ='Evolutive SFP'!BF30/'Evolutive SFP'!BF27 -> 0.54659942 | ... CJ22: ='Evolutive SFP'!CG30/'Evolutive SFP'!CG27 -> 0.54009409
B23: FOSA Deposits/Total Assets | D23: =('Evolutive SFP'!B28+'Evolutive SFP'!B29)/'Evolutive SFP'!B27 -> 0.045545996 | E23: =('Evolutive SFP'!C28+'Evolutive SFP'!C29)/'Evolutive SFP'!C27 -> 0.59018526 | F23: =('Evolutive SFP'!D28+'Evolutive SFP'!D29)/'Evolutive SFP'!D27 -> 0.61515285 | G23: =('Evolutive SFP'!E28+'Evolutive SFP'!E29)/'Evolutive SFP'!E27 -> 0.57645632 | H23: =('Evolutive SFP'!F28+'Evolutive SFP'!F29)/'Evolutive SFP'!F27 -> 0.041497748 | I23: =('Evolutive SFP'!G28+'Evolutive SFP'!G29)/'Evolutive SFP'!G27 -> 0.048765766 | J23: =('Evolutive SFP'!H28+'Evolutive SFP'!H29)/'Evolutive SFP'!H27 -> 0.086727819 | K23: =('Evolutive SFP'!I28+'Evolutive SFP'!I29)/'Evolutive SFP'!I27 -> 0.066404387 | ... BB23: =('Evolutive SFP'!AZ28+'Evolutive SFP'!AZ29)/'Evolutive SFP'!AZ27 -> 0.097601503 | BC23: =('Evolutive SFP'!AZ28+'Evolutive SFP'!AZ29)/'Evolutive SFP'!AZ27 -> 0.097601503 | BD23: =('Evolutive SFP'!BA28+'Evolutive SFP'!BA29)/'Evolutive SFP'!BA27 -> #DIV/0! | BE23: =('Evolutive SFP'!BB28+'Evolutive SFP'!BB29)/'Evolutive SFP'!BB27 -> 0.10120917 | BF23: =('Evolutive SFP'!BC28+'Evolutive SFP'!BC29)/'Evolutive SFP'!BC27 -> 0.089190408 | BG23: =('Evolutive SFP'!BD28+'Evolutive SFP'!BD29)/'Evolutive SFP'!BD27 -> 0.092180817 | BH23: =('Evolutive SFP'!BE28+'Evolutive SFP'!BE29)/'Evolutive SFP'!BE27 -> 0.089404145 | BI23: =('Evolutive SFP'!BF28+'Evolutive SFP'!BF29)/'Evolutive SFP'!BF27 -> 0.090917773 | BJ23: =('Evolutive SFP'!BG28+'Evolutive SFP'!BG29)/'Evolutive SFP'!BG27 -> 0.092858092 | ... CJ23: =('Evolutive SFP'!CG28+'Evolutive SFP'!CG29)/'Evolutive SFP'!CG27 -> 0.099096336
A24: GROWTH RATIOS | B24: Total Assets | D24: =(Financials!C4-Financials!B4)/Financials!B4 -> #VALUE! | E24: =(Financials!D4-Financials!C4)/Financials!C4 -> 0.0050387955 | F24: =(Financials!E4-Financials!D4)/Financials!D4 -> 0.075030912 | G24: =(Financials!F4-Financials!E4)/Financials!E4 -> 0.11849659 | H24: =(Financials!G4-Financials!F4)/Financials!F4 -> 0.050952283 | I24: =(Financials!H4-Financials!G4)/Financials!G4 -> 0.1304987 | J24: =(Financials!I4-Financials!H4)/Financials!H4 -> 0.1535865 | K24: =(Financials!J4-Financials!I4)/Financials!I4 -> 0.01552012 | ... CJ24: =(Financials!CI4-Financials!CH4)/Financials!CH4 -> 0.0011822773
B25: Total Deposits | C25: =IF(CAELS!D16<6%,"1",_xludf.IF) -> #NAME? | D25: =Financials!D5/Financials!C5-1 -> 0.0085169426 | E25: =Financials!E5/Financials!D5-1 -> 0.11986732 | F25: =Financials!F5/Financials!E5-1 -> 0.041874468 | G25: =Financials!G5/Financials!F5-1 -> 0.097332939 | H25: =Financials!H5/Financials!G5-1 -> 0.14960413 | I25: =Financials!I5/Financials!H5-1 -> 0.19013075 | J25: =Financials!J5/Financials!I5-1 -> -0.027866811 | K25: =Financials!K5/Financials!J5-1 -> 0.039592064 | ... AU25: =Financials!AU5/Financials!AT5-1 -> 0.0012615997 | AV25: =Financials!AW5/Financials!AU5-1 -> 0.015515375 | AW25: =Financials!AX5/Financials!AV5-1 -> 0.015515375 | AX25: =Financials!AY5/Financials!AW5-1 -> 0.031210464 | AY25: =Financials!AZ5/Financials!AX5-1 -> 0.054398235 | AZ25: =Financials!BA5/Financials!AY5-1 -> 0.024734546 | BA25: =Financials!BB5/Financials!AZ5-1 -> -0.012666933 | BB25: =Financials!BC5/Financials!BA5-1 -> -1 | BC25: =Financials!BD5/Financials!BB5-1 -> 4.0977528 | ... BG25: =Financials!BH5/Financials!BF5-1 -> 0.010636197 | BH25: =Financials!BH5/Financials!BG5-1 -> 0.0079462323 | BI25: =Financials!BI5/Financials!BH5-1 -> -1.455206e-10 | BJ25: =Financials!BJ5/Financials!BI5-1 -> 0.0061008912 | BK25: =Financials!BK5/Financials!BJ5-1 -> 0.039366948 | BL25: =Financials!BL5/Financials!BK5-1 -> 0.0027281674 | BM25: =Financials!BM5/Financials!BL5-1 -> -0.0025717087 | BN25: =Financials!BN5/Financials!BM5-1 -> 0.0045470882 | BO25: =Financials!BO5/Financials!BN5-1 -> 0.0046011776 | ... CH25: =Financials!CH5/Financials!CG5-1 -> -0.013567853 | CI25: =Financials!#REF!/Financials!CH5-1 -> #REF! | CJ25: =Financials!#REF!/Financials!CI5-1 -> #REF!
B26: BOSA Deposits | D26: =Financials!D6/Financials!C6-1 -> -0.99109671 | E26: =Financials!E6/Financials!D6-1 -> 0.041686982 | F26: =Financials!F6/Financials!E6-1 -> -0.77793315 | G26: =Financials!G6/Financials!F6-1 -> 631.36422 | H26: =Financials!H6/Financials!G6-1 -> 0.13638002 | I26: =Financials!I6/Financials!H6-1 -> 0.11568295 | J26: =Financials!J6/Financials!I6-1 -> 0.0030556421 | K26: =Financials!K6/Financials!J6-1 -> 0.015794685 | ... AU26: =Financials!AU6/Financials!AT6-1 -> 0.0036495112 | AV26: =Financials!AW6/Financials!AU6-1 -> 0.0077190782 | AW26: =Financials!AX6/Financials!AV6-1 -> 0.016404945 | AX26: =Financials!AY6/Financials!AW6-1 -> 0.0046729212 | AY26: =Financials!AZ6/Financials!AX6-1 -> 0.0080858964 | AZ26: =Financials!BA6/Financials!AY6-1 -> 0.016389147 | BA26: =Financials!BB6/Financials!AZ6-1 -> 0.015202219 | BB26: =Financials!BC6/Financials!BA6-1 -> -1 | BC26: =Financials!BD6/Financials!BB6-1 -> 4.056412 | BD26: =Financials!BE6/Financials!BC6-1 -> #DIV/0! | BE26: =Financials!BE6/Financials!BD6-1 -> -0.79875785 | BF26: =Financials!BF6/Financials!BE6-1 -> 0.0071267966 | BG26: =Financials!BG6/Financials!BF6-1 -> 0.0074770649 | BH26: =Financials!BH6/Financials!BG6-1 -> 0.0038240935 | BI26: =Financials!BI6/Financials!BH6-1 -> -0.0035250305 | BJ26: =Financials!BJ6/Financials!BI6-1 -> 0.011166399 | BK26: =Financials!BK6/Financials!BJ6-1 -> 0.0043875559 | BL26: =Financials!BL6/Financials!BK6-1 -> 0.010414209 | ... CH26: =Financials!CH6/Financials!CG6-1 -> 0.0027013855 | CI26: =Financials!#REF!/Financials!CH6-1 -> #REF! | CJ26: =Financials!#REF!/Financials!CI6-1 -> #REF!
B27: FOSA Deposits | D27: =Financials!D7/Financials!C7-1 -> 12.023298 | E27: =Financials!E7/Financials!D7-1 -> 0.12050973 | F27: =Financials!F7/Financials!E7-1 -> 0.048136958 | G27: =Financials!G7/Financials!F7-1 -> -0.92434439 | H27: =Financials!H7/Financials!G7-1 -> 0.32849705 | I27: =Financials!I7/Financials!H7-1 -> 1.051604 | J27: =Financials!J7/Financials!I7-1 -> -0.22245259 | K27: =Financials!K7/Financials!J7-1 -> 0.23277308 | ... AU27: =Financials!AU7/Financials!AT7-1 -> -0.014358609 | AV27: =Financials!AW7/Financials!AU7-1 -> 0.067445588 | AW27: =Financials!AX7/Financials!AV7-1 -> 0.24640521 | AX27: =Financials!AY7/Financials!AW7-1 -> 0.19808351 | AY27: =Financials!AZ7/Financials!AX7-1 -> 0.098418505 | AZ27: =Financials!BA7/Financials!AY7-1 -> 0.06874037 | BA27: =Financials!BB7/Financials!AZ7-1 -> -0.1475373 | BB27: =Financials!BC7/Financials!BA7-1 -> -1 | BC27: =Financials!BD7/Financials!BB7-1 -> 4.3360112 | ... BF27: =Financials!BG7/Financials!BE7-1 -> 0.023058391 | BG27: =Financials!BG7/Financials!BF7-1 -> -0.026100439 | BH27: =Financials!BH7/Financials!BG7-1 -> 0.033460268 | BI27: =Financials!BI7/Financials!BH7-1 -> 0.021192551 | BJ27: =Financials!BJ7/Financials!BI7-1 -> -0.023615913 | BK27: =Financials!BK7/Financials!BJ7-1 -> 0.25188378 | BL27: =Financials!BL7/Financials!BK7-1 -> -0.034736433 | BM27: =Financials!BM7/Financials!BL7-1 -> -0.064789269 | BN27: =Financials!BN7/Financials!BM7-1 -> -0.013530639 | ... CH27: =Financials!CH7/Financials!CG7-1 -> -0.095079264 | CI27: =Financials!#REF!/Financials!CH7-1 -> #REF! | CJ27: =Financials!#REF!/Financials!CI7-1 -> #REF!
B28: Total Loans & advances | D28: =Financials!D31/Financials!C31-1 -> 0.12835411 | E28: =Financials!E31/Financials!D31-1 -> 0.095578984 | F28: =Financials!F31/Financials!E31-1 -> 0.1040705 | G28: =Financials!G31/Financials!F31-1 -> 0.0045523755 | H28: =Financials!H31/Financials!G31-1 -> 0.080363743 | I28: =Financials!I31/Financials!H31-1 -> 0.26103556 | J28: =Financials!J31/Financials!I31-1 -> 0.026766801 | K28: =Financials!K31/Financials!J31-1 -> -0.015452518 | ... AU28: =Financials!AU31/Financials!AT31-1 -> 0.01358129 | AV28: =Financials!AW31/Financials!AU31-1 -> -0.0072523762 | AW28: =Financials!AX31/Financials!AV31-1 -> -0.0072523762 | AX28: =Financials!AY31/Financials!AW31-1 -> -0.0022127402 | AY28: =Financials!AZ31/Financials!AX31-1 -> -0.0034557239 | AZ28: =Financials!BA31/Financials!AY31-1 -> -0.01244146 | BA28: =Financials!BB31/Financials!AZ31-1 -> -0.017054479 | BB28: =Financials!BC31/Financials!BA31-1 -> -1 | BC28: =Financials!BD31/Financials!BB31-1 -> 4.1554029 | BD28: =Financials!BE31/Financials!BC31-1 -> #DIV/0! | BE28: =Financials!BE31/Financials!BD31-1 -> -0.7984209 | BF28: =Financials!BF31/Financials!BE31-1 -> 0.016700962 | BG28: =Financials!BG31/Financials!BF31-1 -> 0.007416803 | BH28: =Financials!BH31/Financials!BG31-1 -> 0.0094534322 | BI28: =Financials!BI31/Financials!BH31-1 -> 2.0939561e-10 | BJ28: =Financials!BJ31/Financials!BI31-1 -> -0.00070233096 | BK28: =Financials!BK31/Financials!BJ31-1 -> -0.01386927 | BL28: =Financials!BL31/Financials!BK31-1 -> 0.0069546151 | ... CH28: =Financials!CH31/Financials!CG31-1 -> 0.0045695088 | CI28: =Financials!#REF!/Financials!CH31-1 -> #REF! | CJ28: =Financials!#REF!/Financials!CI31-1 -> #REF!
B29: Core capital | D29: =Financials!D11/Financials!C11-1 -> 0.40702709 | E29: =Financials!E11/Financials!D11-1 -> -0.066522548 | F29: =Financials!F11/Financials!E11-1 -> 0.31343357 | G29: =Financials!G11/Financials!F11-1 -> 0.80798956 | H29: =Financials!H11/Financials!G11-1 -> 0.11175341 | I29: =Financials!I11/Financials!H11-1 -> 0.075034853 | J29: =Financials!J11/Financials!I11-1 -> 0.25691472 | K29: =Financials!K11/Financials!J11-1 -> -0.014073394 | ... AU29: =Financials!AU11/Financials!AT11-1 -> -0.032640329 | AV29: =Financials!AW11/Financials!AU11-1 -> 0.02612904 | AW29: =Financials!AX11/Financials!AV11-1 -> 0.03008226 | AX29: =Financials!AY11/Financials!AW11-1 -> 0.0097786773 | AY29: =Financials!AZ11/Financials!AX11-1 -> 0.054618045 | AZ29: =Financials!BA11/Financials!AY11-1 -> 0.031580462 | BA29: =Financials!BB11/Financials!AZ11-1 -> -0.011645414 | BB29: =Financials!BC11/Financials!BA11-1 -> -1 | BC29: =Financials!BC11/Financials!BB11-1 -> -1 | BD29: =Financials!BD11/Financials!BC11-1 -> #DIV/0! | BE29: =Financials!BE11/Financials!BD11-1 -> -0.79908762 | BF29: =Financials!BF11/Financials!BE11-1 -> 0.0029730428 | BG29: =Financials!BG11/Financials!BF11-1 -> -0.0018123195 | BH29: =Financials!BH11/Financials!BG11-1 -> 0.0077306584 | BI29: =Financials!BI11/Financials!BH11-1 -> 2.9583611e-09 | BJ29: =Financials!BJ11/Financials!BI11-1 -> 0.010714148 | ... CH29: =Financials!CH11/Financials!CG11-1 -> -0.068115507 | CI29: =Financials!#REF!/Financials!CH11-1 -> #REF! | CJ29: =Financials!#REF!/Financials!CI11-1 -> #REF!
B30: Turnover | D30: =Financials!D37/Financials!C37-1 -> 0.27822669 | E30: =Financials!E37/Financials!D37-1 -> 0.12924509 | F30: =Financials!F37/Financials!E37-1 -> 0.22593772 | G30: =Financials!G37/Financials!F37-1 -> 0.036541006 | H30: =Financials!H37/Financials!G37-1 -> 0.12780682 | I30: =Financials!I37/Financials!H37-1 -> 0.10523348 | J30: =Financials!J37/Financials!I37-1 -> -0.97453949 | K30: =Financials!K37/Financials!J37-1 -> 4.0512637 | ... AU30: =Financials!AU37/Financials!AT37-1 -> 0.14869278 | AV30: =Financials!AW37/Financials!AU37-1 -> -0.92884507 | AW30: =Financials!AX37/Financials!AV37-1 -> -0.86244153 | AX30: =Financials!AX37/Financials!AW37-1 -> 0.93322485 | AY30: =Financials!AY37/Financials!AX37-1 -> 0.55145977 | AZ30: =Financials!AZ37/Financials!AY37-1 -> 0.67219723 | BA30: =Financials!BA37/Financials!AZ37-1 -> 0.17146548 | BB30: =Financials!BB37/Financials!BA37-1 -> 0.16108116 | BC30: =Financials!BC37/Financials!BB37-1 -> -1 | BD30: =Financials!BD37/Financials!BC37-1 -> #DIV/0! | BE30: =Financials!BE37/Financials!BD37-1 -> -0.77583403 | ... CH30: =Financials!CH37/Financials!CG37-1 -> 0.10670183 | CI30: =Financials!#REF!/Financials!CH37-1 -> #REF! | CJ30: =Financials!#REF!/Financials!CI37-1 -> #REF!
B31: Membership
B32: Expenses | D32: ='Evolutitve SCI'!E39/'Evolutitve SCI'!B39-1 -> 0.76413941 | E32: ='Evolutitve SCI'!F39/'Evolutitve SCI'!C39-1 -> 0.45808734 | F32: ='Evolutitve SCI'!G39/'Evolutitve SCI'!D39-1 -> 0.2705791 | G32: ='Evolutitve SCI'!H39/'Evolutitve SCI'!E39-1 -> 0.43075731 | H32: ='Evolutitve SCI'!I39/'Evolutitve SCI'!F39-1 -> -0.92797102 | I32: ='Evolutitve SCI'!I39/'Evolutitve SCI'!G39-1 -> -0.93539349 | J32: ='Evolutitve SCI'!I39/'Evolutitve SCI'!H39-1 -> -0.9497403 | K32: ='Evolutitve SCI'!J39/'Evolutitve SCI'!I39-1 -> 0.84982427 | L32: ='Evolutitve SCI'!K39/'Evolutitve SCI'!J39-1 -> 0.67825956 | M32: ='Evolutitve SCI'!L39/'Evolutitve SCI'!K39-1 -> 0.42767497 | N32: ='Evolutitve SCI'!M39/'Evolutitve SCI'!L39-1 -> 0.3300868 | O32: ='Evolutitve SCI'!N39/'Evolutitve SCI'!M39-1 -> 0.18841783 | P32: ='Evolutitve SCI'!O39/'Evolutitve SCI'!N39-1 -> 0.18359831 | Q32: ='Evolutitve SCI'!P39/'Evolutitve SCI'!O39-1 -> 0.13638412 | ... AU32: ='Evolutitve SCI'!AT39/'Evolutitve SCI'!AS39-1 -> 0.22588754 | AV32: ='Evolutitve SCI'!AV39/'Evolutitve SCI'!AT39-1 -> -0.94327391 | AW32: ='Evolutitve SCI'!AW39/'Evolutitve SCI'!AU39-1 -> -0.89142834 | AX32: ='Evolutitve SCI'!AW39/'Evolutitve SCI'!AV39-1 -> 0.9541446 | AY32: ='Evolutitve SCI'!AX39/'Evolutitve SCI'!AW39-1 -> 0.63743395 | AZ32: ='Evolutitve SCI'!AY39/'Evolutitve SCI'!AX39-1 -> 0.44240485 | BA32: ='Evolutitve SCI'!AZ39/'Evolutitve SCI'!AY39-1 -> 0.41281155 | BB32: ='Evolutitve SCI'!BA39/'Evolutitve SCI'!AZ39-1 -> 0.22053657 | BC32: ='Evolutitve SCI'!BB39/'Evolutitve SCI'!BA39-1 -> -1 | BD32: ='Evolutitve SCI'!BC39/'Evolutitve SCI'!BB39-1 -> #DIV/0! | BE32: ='Evolutitve SCI'!BD39/'Evolutitve SCI'!BC39-1 -> -0.77331274 | ... CJ32: ='Evolutitve SCI'!CI39/'Evolutitve SCI'!CH39-1 -> -0.93536278
A33: Efficiency Ratios | B33: FinCost-Deposits/Avg Deposits | H33: =Financials!G44/('Evolutive SFP'!B30+'Evolutive SFP'!F30)/2 -> 0.027240269 | K33: =Financials!J44/('Evolutive SFP'!F30+'Evolutive SFP'!I30)/2 -> 0.001889936 | L33: =Financials!K44/('Evolutive SFP'!I30+'Evolutive SFP'!J30)/2 -> 0.0033718804 | M33: =Financials!L44/('Evolutive SFP'!J30+'Evolutive SFP'!K30)/2 -> 0.0049633736 | N33: =Financials!M44/('Evolutive SFP'!K30+'Evolutive SFP'!L30)/2 -> 0.0069012845 | O33: =Financials!N44/('Evolutive SFP'!L30+'Evolutive SFP'!M30)/2 -> 0.0088435216 | P33: =Financials!O44/('Evolutive SFP'!M30+'Evolutive SFP'!N30)/2 -> 0.010688331 | Q33: =Financials!P44/('Evolutive SFP'!N30+'Evolutive SFP'!O30)/2 -> 0.012604981 | R33: =Financials!Q44/('Evolutive SFP'!O30+'Evolutive SFP'!P30)/2 -> 0.014470469 | S33: =Financials!R44/('Evolutive SFP'!P30+'Evolutive SFP'!Q30)/2 -> 0.016268724 | ... AW33: =Financials!AV44/('Evolutive SFP'!AT30+'Evolutive SFP'!AU30)/2 -> 0.027600199 | AX33: =Financials!AW44/('Evolutive SFP'!AT30+'Evolutive SFP'!AU30)/2 -> 0.0018747041 | AY33: =Financials!AX44/('Evolutive SFP'!AU30+'Evolutive SFP'!AV30)/2 -> 0.0036515283 | AZ33: =Financials!AY44/('Evolutive SFP'!AV30+'Evolutive SFP'!AW30)/2 -> 0.0054801847 | BA33: =Financials!AZ44/('Evolutive SFP'!AW30+'Evolutive SFP'!AX30)/2 -> 0.0072256418 | BB33: =Financials!BA44/('Evolutive SFP'!AX30+'Evolutive SFP'!AY30)/2 -> 0.0089227427 | BC33: =Financials!BB44/('Evolutive SFP'!AY30+'Evolutive SFP'!AZ30)/2 -> 0.010678524 | BD33: =Financials!BC44/('Evolutive SFP'!AZ30+'Evolutive SFP'!BA30)/2 -> 0 | BE33: =Financials!BD44/('Evolutive SFP'!BA30+'Evolutive SFP'!BB30)/2 -> 0.030899638 | ... CJ33: =Financials!CI44/('Evolutive SFP'!CF30+'Evolutive SFP'!CG30)/2 -> 0.034165138
B34: FinCost-Shares/Avg Share capital | H34: =Financials!G45/('Evolutive SFP'!B39+'Evolutive SFP'!F39)/2 -> 0 | K34: =Financials!J45/('Evolutive SFP'!F39+'Evolutive SFP'!I39)/2 -> 0 | L34: =Financials!K45/('Evolutive SFP'!I39+'Evolutive SFP'!J39)/2 -> 0 | M34: =Financials!L45/('Evolutive SFP'!J39+'Evolutive SFP'!K39)/2 -> 0 | N34: =Financials!M45/('Evolutive SFP'!K39+'Evolutive SFP'!L39)/2 -> 0 | O34: =Financials!N45/('Evolutive SFP'!L39+'Evolutive SFP'!M39)/2 -> 0 | P34: =Financials!O45/('Evolutive SFP'!M39+'Evolutive SFP'!N39)/2 -> 0 | Q34: =Financials!P45/('Evolutive SFP'!N39+'Evolutive SFP'!O39)/2 -> 0 | R34: =Financials!Q45/('Evolutive SFP'!O39+'Evolutive SFP'!P39)/2 -> 0 | S34: =Financials!R45/('Evolutive SFP'!P39+'Evolutive SFP'!Q39)/2 -> 0 | ... AW34: =Financials!AV45/('Evolutive SFP'!AT39+'Evolutive SFP'!AU39)/2 -> 0 | AX34: =Financials!AW45/('Evolutive SFP'!AT39+'Evolutive SFP'!AU39)/2 -> 0 | AY34: =Financials!AX45/('Evolutive SFP'!AU39+'Evolutive SFP'!AV39)/2 -> 0 | AZ34: =Financials!AY45/('Evolutive SFP'!AV39+'Evolutive SFP'!AW39)/2 -> 0 | BA34: =Financials!AZ45/('Evolutive SFP'!AW39+'Evolutive SFP'!AX39)/2 -> 0 | BB34: =Financials!BA45/('Evolutive SFP'!AX39+'Evolutive SFP'!AY39)/2 -> 0 | BC34: =Financials!BB45/('Evolutive SFP'!AY39+'Evolutive SFP'!AZ39)/2 -> 0 | BD34: =Financials!BC45/('Evolutive SFP'!AZ39+'Evolutive SFP'!BA39)/2 -> 0 | BE34: =Financials!BD45/('Evolutive SFP'!BA39+'Evolutive SFP'!BB39)/2 -> 0 | ... CJ34: =Financials!CI45/('Evolutive SFP'!CF39+'Evolutive SFP'!CG39)/2 -> 0
B35: FinCost-Ext Loans/Avg Ext Loans | H35: =Financials!G46/(Financials!F31+Financials!G31)/2 -> 0.0047294105 | K35: =Financials!J46/(Financials!G31+Financials!J31)/2 -> 0 | L35: =Financials!K46/(Financials!J31+Financials!K31)/2 -> 0 | M35: =Financials!L46/(Financials!K31+Financials!L31)/2 -> 0 | N35: =Financials!M46/(Financials!L31+Financials!M31)/2 -> 0 | O35: =Financials!N46/(Financials!M31+Financials!N31)/2 -> 0 | P35: =Financials!O46/(Financials!N31+Financials!O31)/2 -> 0 | Q35: =Financials!P46/(Financials!O31+Financials!P31)/2 -> 0 | R35: =Financials!Q46/(Financials!P31+Financials!Q31)/2 -> 0 | S35: =Financials!R46/(Financials!Q31+Financials!R31)/2 -> 0 | ... AW35: =Financials!AV46/(Financials!AU31+Financials!AV31)/2 -> 0 | AX35: =Financials!AW46/(Financials!AU31+Financials!AW31)/2 -> 0 | AY35: =Financials!AX46/(Financials!AW31+Financials!AX31)/2 -> 0 | AZ35: =Financials!AY46/(Financials!AX31+Financials!AY31)/2 -> 0 | BA35: =Financials!AZ46/(Financials!AY31+Financials!AZ31)/2 -> 0 | BB35: =Financials!BA46/(Financials!AZ31+Financials!BA31)/2 -> 0 | BC35: =Financials!BB46/(Financials!BA31+Financials!BB31)/2 -> 0 | BD35: =Financials!BC46/(Financials!BB31+Financials!BC31)/2 -> 0 | BE35: =Financials!BD46/(Financials!BC31+Financials!BD31)/2 -> 0 | BF35: =Financials!BE46/(Financials!BD31+Financials!BE31)/2 -> 0 | ... CJ35: =Financials!CI46/(Financials!CH31+Financials!CI31)/2 -> 0.024061251
B36: OpEx/Average Total Assets | H36: =Financials!G47/(Financials!F4+Financials!G4)/2 -> 0.018528339 | K36: =Financials!J47/(Financials!G4+Financials!J4)/2 -> 0.0011765063 | L36: =Financials!K47/(Financials!J4+Financials!K4)/2 -> 0.0022275617 | M36: =Financials!L47/(Financials!K4+Financials!L4)/2 -> 0.0039653018 | N36: =Financials!M47/(Financials!L4+Financials!M4)/2 -> 0.0054474534 | O36: =Financials!N47/(Financials!M4+Financials!N4)/2 -> 0.0074778588 | P36: =Financials!O47/(Financials!N4+Financials!O4)/2 -> 0.0084049426 | Q36: =Financials!P47/(Financials!O4+Financials!P4)/2 -> 0.009969806 | R36: =Financials!Q47/(Financials!P4+Financials!Q4)/2 -> 0.010881729 | S36: =Financials!R47/(Financials!Q4+Financials!R4)/2 -> 0.011822375 | ... AW36: =Financials!AV47/(Financials!AU4+Financials!AV4)/2 -> 0.021163113 | AX36: =Financials!AW47/(Financials!AU4+Financials!AW4)/2 -> 0.0011471902 | AY36: =Financials!AX47/(Financials!AW4+Financials!AX4)/2 -> 0.0028921993 | AZ36: =Financials!AY47/(Financials!AX4+Financials!AY4)/2 -> 0.0049447728 | BA36: =Financials!AZ47/(Financials!AY4+Financials!AZ4)/2 -> 0.006555101 | BB36: =Financials!BA47/(Financials!AZ4+Financials!BA4)/2 -> 0.0092311454 | BC36: =Financials!BB47/(Financials!BA4+Financials!BB4)/2 -> 0.01039407 | BD36: =Financials!BC47/(Financials!BB4+Financials!BC4)/2 -> 0 | BE36: =Financials!BD47/(Financials!BC4+Financials!BD4)/2 -> 0.026128872 | BF36: =Financials!BE47/(Financials!BD4+Financials!BE4)/2 -> 0.004765299 | ... CJ36: =Financials!CI47/(Financials!CH4+Financials!CI4)/2 -> 0.021191222
B37: Opex/Turnover | H37: =Financials!G47/Financials!G37 -> 0.39680715 | K37: =Financials!J47/Financials!J37 -> 0.94561381 | L37: =Financials!K47/Financials!K37 -> 0.40500081 | M37: =Financials!L47/Financials!L37 -> 0.43102649 | N37: =Financials!M47/Financials!M37 -> 0.45175456 | O37: =Financials!N47/Financials!N37 -> 0.46944281 | P37: =Financials!O47/Financials!O37 -> 0.38746203 | Q37: =Financials!P47/Financials!P37 -> 0.43142883 | R37: =Financials!Q47/Financials!Q37 -> 0.38593386 | ... CJ37: =Financials!CI47/Financials!CI37 -> 0.53220442
B38: Avge yield on Net loans | H38: =Financials!G38/('Evolutive SFP'!F14+'Evolutive SFP'!B14)/2 -> 0.071869378 | K38: =Financials!J38/('Evolutive SFP'!I14+'Evolutive SFP'!F14)/2 -> 0.0017048669 | L38: =Financials!K38/('Evolutive SFP'!J14+'Evolutive SFP'!I14)/2 -> 0.0076596273 | M38: =Financials!L38/('Evolutive SFP'!K14+'Evolutive SFP'!J14)/2 -> 0.012759208 | N38: =Financials!M38/('Evolutive SFP'!L14+'Evolutive SFP'!K14)/2 -> 0.016383319 | O38: =Financials!N38/('Evolutive SFP'!M14+'Evolutive SFP'!L14)/2 -> 0.021375639 | P38: =Financials!O38/('Evolutive SFP'!N14+'Evolutive SFP'!M14)/2 -> 0.025539857 | Q38: =Financials!P38/('Evolutive SFP'!O14+'Evolutive SFP'!N14)/2 -> 0.026812944 | R38: =Financials!Q38/('Evolutive SFP'!P14+'Evolutive SFP'!O14)/2 -> 0.03365876 | S38: =Financials!R38/('Evolutive SFP'!Q14+'Evolutive SFP'!P14)/2 -> 0.041341128 | ... AW38: =Financials!AV38/('Evolutive SFP'!AU14+'Evolutive SFP'!AT14)/2 -> 0.05146963 | AX38: =Financials!AW38/('Evolutive SFP'!AU14+'Evolutive SFP'!AT14)/2 -> 0.0039513457 | AY38: =Financials!AX38/('Evolutive SFP'!AV14+'Evolutive SFP'!AU14)/2 -> 0.0076488675 | AZ38: =Financials!AY38/('Evolutive SFP'!AW14+'Evolutive SFP'!AV14)/2 -> 0.011469179 | BA38: =Financials!AZ38/('Evolutive SFP'!AX14+'Evolutive SFP'!AW14)/2 -> 0.015043998 | BB38: =Financials!BA38/('Evolutive SFP'!AY14+'Evolutive SFP'!AX14)/2 -> 0.018619137 | BC38: =Financials!BB38/('Evolutive SFP'!AZ14+'Evolutive SFP'!AY14)/2 -> 0.022511692 | BD38: =Financials!BC38/('Evolutive SFP'!BA14+'Evolutive SFP'!AZ14)/2 -> 0 | BE38: =Financials!BD38/('Evolutive SFP'!BB14+'Evolutive SFP'!BA14)/2 -> 0.060833934 | ... CJ38: =Financials!CI38/('Evolutive SFP'!CG14+'Evolutive SFP'!CF14)/2 -> 0.046407863
B39: Avge yield on Gross loans | H39: =Financials!G37/('Evolutive SFP'!F15+'Evolutive SFP'!B15)/2 -> 0.078054139 | K39: =Financials!J37/('Evolutive SFP'!I15+'Evolutive SFP'!F15)/2 -> 0.0017858092 | L39: =Financials!K37/('Evolutive SFP'!J15+'Evolutive SFP'!I15)/2 -> 0.0077948252 | M39: =Financials!L37/('Evolutive SFP'!K15+'Evolutive SFP'!J15)/2 -> 0.013113535 | N39: =Financials!M37/('Evolutive SFP'!L15+'Evolutive SFP'!K15)/2 -> 0.016708654 | O39: =Financials!N37/('Evolutive SFP'!M15+'Evolutive SFP'!L15)/2 -> 0.021730029 | P39: =Financials!O37/('Evolutive SFP'!N15+'Evolutive SFP'!M15)/2 -> 0.029991214 | Q39: =Financials!P37/('Evolutive SFP'!O15+'Evolutive SFP'!N15)/2 -> 0.031423339 | R39: =Financials!Q37/('Evolutive SFP'!P15+'Evolutive SFP'!O15)/2 -> 0.038223051 | S39: =Financials!R37/('Evolutive SFP'!Q15+'Evolutive SFP'!P15)/2 -> 0.046002651 | ... AX39: =Financials!AW37/('Evolutive SFP'!AV15+'Evolutive SFP'!AU15)/2 -> 0.0039742812 | AY39: =Financials!AX37/('Evolutive SFP'!AV15+'Evolutive SFP'!AU15)/2 -> 0.0076831792 | AZ39: =Financials!AY37/('Evolutive SFP'!AW15+'Evolutive SFP'!AV15)/2 -> 0.011976935 | BA39: =Financials!AZ37/('Evolutive SFP'!AX15+'Evolutive SFP'!AW15)/2 -> 0.020062501 | BB39: =Financials!BA37/('Evolutive SFP'!AY15+'Evolutive SFP'!AX15)/2 -> 0.023649738 | BC39: =Financials!BB37/('Evolutive SFP'!AZ15+'Evolutive SFP'!AY15)/2 -> 0.027696773 | BD39: =Financials!BC37/('Evolutive SFP'!BA15+'Evolutive SFP'!AZ15)/2 -> 0 | BE39: =Financials!BD37/('Evolutive SFP'!BB15+'Evolutive SFP'!BA15)/2 -> 0.070989284 | BF39: =Financials!BE37/('Evolutive SFP'!BC15+'Evolutive SFP'!BB15)/2 -> 0.013243724 | ... CJ39: =Financials!CI37/('Evolutive SFP'!CG15+'Evolutive SFP'!CF15)/2 -> 0.05260922
A41: ALL/Average Gross Loan portfolio

Sheet Financials
B1: MAFANIKIO Sacco Financial Performance
B2: Year | C2: 2010 Audited | D2: 2011 Audited | E2: 2012 Audited | F2: 2013 Audited | G2: 2014 Audited | H2: 2015 Audited | I2: 2016 Audited | J2: 42736 | K2: 42767 | L2: 42795 | M2: 42826 | N2: 42856 | O2: 42887 | P2: 42917 | Q2: 42948 | R2: 42979 | S2: 43009 | T2: 43040 | U2: 43070 | V2: Audited 2017 | W2: 43101 | X2: 43132 | Y2: 43160 | Z2: 43191 | AA2: 43221 | AB2: 43252 | AC2: 43282 | AD2: 43313 | AE2: 43344 | AF2: 43374 | AG2: 43405 | AH2: 43435 | AI2: Audited-18 | AJ2: 43466 | AK2: 43497 | AL2: 43525 | AM2: 43556 | AN2: 43586 | AO2: 43617 | AP2: 43647 | AQ2: 43678 | AR2: 43709 | AS2: 43739 | AT2: 43770 | AU2: 43800 | AV2: Audited 19 | AW2: 43831 | AX2: 43862 | AY2: 43891 | AZ2: 43922 | BA2: 43952 | BB2: 43983 | BC2: 44013 | BD2: 44044 | BE2: 44075 | BF2: 44105 | BG2: 44136 | BH2: 44166 | BI2: Audited 2020 | BJ2: 44197 | BK2: 44228 | BL2: 44256 | BM2: 44287 | BN2: 44317 | BO2: 44348 | BP2: 44378 | BQ2: 44409 | BR2: 44440 | BS2: 44470 | BT2: 44501 | BU2: 44531 | BV2: AUDITED 2021 | BW2: 44562 | BX2: 44593 | BY2: 44621 | BZ2: 44652 | CA2: 44682 | CB2: 44713 | CC2: 44743 | CD2: 44774 | CE2: 44805 | CF2: 44835 | CG2: 44866 | CH2: 44896 | CI2: Audited 2022 | CJ2: 44927 | CK2: 44958 | CL2: 44986 | CM2: 45017 | CN2: 45047 | CO2: 45078 | CP2: 45108 | CQ2: 45139 | CR2: 45170
A3: 1 | B3: Membership | I3: 4641 | V3: 4895 | W3: 4895 | X3: 4895 | Y3: 4895 | Z3: 4895 | AA3: 4895 | AB3: 4895 | AC3: 4895 | AD3: 4895 | AE3: 4895 | AF3: 4895 | AG3: 4895 | AH3: 4895 | AI3: 4895 | AJ3: 4895 | AK3: 4895 | AL3: 4895 | AM3: 4895 | AN3: 4895 | AO3: 4895 | AP3: 4895 | AQ3: 4895 | AR3: 4895 | AS3: 4895 | AT3: 4895 | AU3: 4895 | AV3: 4895 | AW3: 4895 | AX3: 4895 | AY3: 4895 | AZ3: 4895 | BA3: 4895 | BB3: 4895 | BC3: 4895 | BD3: 4895
A4: 2 | B4: Total Assets | C4: ='Evolutive SFP'!B27 -> 420805135 | D4: ='Evolutive SFP'!C27 -> 422925486 | E4: ='Evolutive SFP'!D27 -> 454657971 | F4: ='Evolutive SFP'!E27 -> 5.0853339e+08 | G4: ='Evolutive SFP'!F27 -> 534444329 | H4: ='Evolutive SFP'!G27 -> 604188621 | I4: ='Evolutive SFP'!H27 -> 696983837 | J4: ='Evolutive SFP'!I27 -> 7.0780111e+08 | ... AW4: ='Evolutive SFP'!AV27 -> 9.1841459e+08 | AX4: ='Evolutive SFP'!AV27 -> 9.1841459e+08 | AY4: ='Evolutive SFP'!AW27 -> 8.9880994e+08 | AZ4: ='Evolutive SFP'!AX27 -> 9.147468e+08 | BA4: ='Evolutive SFP'!AY27 -> 9.1399838e+08 | BB4: ='Evolutive SFP'!AZ27 -> 9.0955827e+08 | BC4: ='Evolutive SFP'!BA27 -> 0 | BD4: ='Evolutive SFP'!BB27 -> 4.6804102e+09 | BE4: ='Evolutive SFP'!BC27 -> 9.3532515e+08 | ... CR4: ='Evolutive SFP'!CP27 -> 1.1568404e+09
A5: 3 | B5: Total Deposits | C5: ='Evolutive SFP'!B31 -> 249530153 | D5: ='Evolutive SFP'!C31 -> 251655387 | E5: ='Evolutive SFP'!D31 -> 281820645 | F5: ='Evolutive SFP'!E31 -> 2.9362173e+08 | G5: ='Evolutive SFP'!F31 -> 322200801 | H5: ='Evolutive SFP'!G31 -> 370403370 | I5: ='Evolutive SFP'!H31 -> 440828441 | J5: ='Evolutive SFP'!I31 -> 4.2854396e+08 | ... AW5: ='Evolutive SFP'!AV31 -> 5.7673493e+08 | AX5: ='Evolutive SFP'!AV31 -> 5.7673493e+08 | AY5: ='Evolutive SFP'!AW31 -> 5.9473509e+08 | AZ5: ='Evolutive SFP'!AX31 -> 6.0810829e+08 | BA5: ='Evolutive SFP'!AY31 -> 6.094456e+08 | BB5: ='Evolutive SFP'!AZ31 -> 6.0040542e+08 | BC5: ='Evolutive SFP'!BA31 -> 0 | BD5: ='Evolutive SFP'!BB31 -> 3.0607184e+09 | BE5: ='Evolutive SFP'!BC31 -> 6.0403911e+08 | ... CR5: ='Evolutive SFP'!CP31 -> 7.6760338e+08
A6: 3.1 | B6: Deposits-Members(BOSA) | C6: ='Evolutive SFP'!B30 -> 230364164 | D6: ='Evolutive SFP'!C30 -> 2051000 | E6: ='Evolutive SFP'!D30 -> 2136500 | F6: ='Evolutive SFP'!E30 -> 474445.83 | G6: ='Evolutive SFP'!F30 -> 300022565 | H6: ='Evolutive SFP'!G30 -> 340939649 | I6: ='Evolutive SFP'!H30 -> 380380553 | J6: ='Evolutive SFP'!I30 -> 3.8154286e+08 | ... AX6: ='Evolutive SFP'!AW30 -> 4.9992735e+08 | AY6: ='Evolutive SFP'!AW30 -> 4.9992735e+08 | AZ6: ='Evolutive SFP'!AX30 -> 5.0396971e+08 | BA6: ='Evolutive SFP'!AY30 -> 5.0812073e+08 | BB6: ='Evolutive SFP'!AZ30 -> 5.1163117e+08 | BC6: ='Evolutive SFP'!BA30 -> 0 | BD6: ='Evolutive SFP'!BB30 -> 2.587018e+09 | BE6: ='Evolutive SFP'!BC30 -> 5.2061708e+08 | BF6: ='Evolutive SFP'!BD30 -> 5.2432741e+08 | ... CR6: ='Evolutive SFP'!CP30 -> 6.4788293e+08
A7: 3.2 | B7: Deposits-Customers(FOSA) | C7: =('Evolutive SFP'!B28+'Evolutive SFP'!B29) -> 19165989 | D7: =('Evolutive SFP'!C28+'Evolutive SFP'!C29) -> 249604387 | E7: =('Evolutive SFP'!D28+'Evolutive SFP'!D29) -> 279684145 | F7: =('Evolutive SFP'!E28+'Evolutive SFP'!E29) -> 2.9314729e+08 | G7: =('Evolutive SFP'!F28+'Evolutive SFP'!F29) -> 22178236 | H7: =('Evolutive SFP'!G28+'Evolutive SFP'!G29) -> 29463721 | I7: =('Evolutive SFP'!H28+'Evolutive SFP'!H29) -> 60447888 | J7: =('Evolutive SFP'!I28+'Evolutive SFP'!I29) -> 47001098 | ... AX7: =('Evolutive SFP'!AW28+'Evolutive SFP'!AW29) -> 94807743 | AY7: =('Evolutive SFP'!AW28+'Evolutive SFP'!AW29) -> 94807743 | AZ7: =('Evolutive SFP'!AX28+'Evolutive SFP'!AX29) -> 1.0413858e+08 | BA7: =('Evolutive SFP'!AY28+'Evolutive SFP'!AY29) -> 1.0132486e+08 | BB7: =('Evolutive SFP'!AZ28+'Evolutive SFP'!AZ29) -> 88774254 | BC7: =('Evolutive SFP'!BA28+'Evolutive SFP'!BA29) -> 0 | BD7: =('Evolutive SFP'!BB28+'Evolutive SFP'!BB29) -> 4.7370041e+08 | BE7: =('Evolutive SFP'!BC28+'Evolutive SFP'!BC29) -> 83422032 | BF7: =('Evolutive SFP'!BD28+'Evolutive SFP'!BD29) -> 87632866 | ... CR7: =('Evolutive SFP'!CP28+'Evolutive SFP'!CP29) -> 1.1972045e+08
A8: 4 | B8: External Borrowing | C8: ='Evolutive SFP'!B37 -> 98196182 | D8: ='Evolutive SFP'!C37 -> 73980442 | E8: ='Evolutive SFP'!D37 -> 75498160 | F8: ='Evolutive SFP'!E37 -> 75604045 | G8: ='Evolutive SFP'!F37 -> 14235893 | H8: ='Evolutive SFP'!G37 -> 0 | I8: ='Evolutive SFP'!H37 -> 0 | J8: ='Evolutive SFP'!I37 -> 0 | ... AU8: ='Evolutive SFP'!AT37 -> 0 | AW8: ='Evolutive SFP'!AU37 -> 0 | AX8: ='Evolutive SFP'!AV37 -> 0 | AY8: ='Evolutive SFP'!AW37 -> 0 | AZ8: ='Evolutive SFP'!AX37 -> 0 | BA8: ='Evolutive SFP'!AY37 -> 0 | BB8: ='Evolutive SFP'!AZ37 -> 0 | BC8: ='Evolutive SFP'!BA37 -> 0 | BD8: ='Evolutive SFP'!BB37 -> 0 | ... CR8: ='Evolutive SFP'!CP37 -> 0
A10: 5 | B10: Share capital and Reserves
A11: 5.1 | B11: Core Capital | C11: =C14-C22-C25 -> 42410035 | D11: =D14-D22-D25 -> 59672068 | E11: =E14-E22-E25 -> 55702530 | F11: =F14-F22-F25 -> 73161573 | G11: =G14-G22-G25 -> 132275360 | H11: =H14-H22-H25 -> 147057582 | I11: =I14-I22-I25 -> 158092026 | J11: =J14-J22 -> 1.987082e+08 | K11: =K14-K22 -> 1.959117e+08 | L11: =L14-L22 -> 1.9420862e+08 | M11: =M14-M22 -> 1.9433395e+08 | N11: =N14-N22 -> 1.967919e+08 | O11: =O14-O22 -> 2.0768975e+08 | P11: =P14-P22 -> 2.0486103e+08 | Q11: =Q14-Q22 -> 2.1406512e+08 | ... CR11: =CR14-CR22 -> 3.2851464e+08
A12: 5.2 | B12: Institutional Capital | C12: =C11-C15 -> 37351525 | D12: =D11-D15 -> 18644089 | E12: =E11-E15 -> 14383335 | F12: =F11-F15 -> 28484836 | G12: =G11-G15 -> 65016591 | H12: =H11-H15 -> 79501050 | I12: =I11-I15 -> 84630805 | J12: =J11-J15 -> 1.2520437e+08 | ... CR12: =CR11-CR15 -> 2.337947e+08
A14: 5.3 | B14: Total Capital | C14: =C15+C16+C17+C18+C19+C20+C21 -> 51352205 | D14: =D15+D16+D17+D18+D19+D20+D21 -> 73896875 | E14: =E15+E16+E17+E18+E19+E20+E21 -> 81620098 | F14: =F15+F16+F17+F18+F19+F20+F21 -> 1.0084641e+08 | G14: =G15+G16+G17+G18+G19+G20+G21 -> 146858150 | H14: =H15+H16+H17+H18+H19+H20+H21 -> 175249183 | I14: =I15+I16+I17+I18+I19+I20+I21 -> 190503279 | J14: =J15+J16+J17+J18+J19+J20+J21 -> 1.987082e+08 | ... CR14: =CR15+CR16+CR17+CR18+CR19+CR20+CR21 -> 3.2851464e+08
A15: 5.3.1 | B15: Members Share Capital | C15: ='Evolutive SFP'!B39 -> 5058510 | D15: ='Evolutive SFP'!C39 -> 41027979 | E15: ='Evolutive SFP'!D39 -> 41319195 | F15: ='Evolutive SFP'!E39 -> 44676737 | G15: ='Evolutive SFP'!F39 -> 67258769 | H15: ='Evolutive SFP'!G39 -> 67556532 | I15: ='Evolutive SFP'!H39 -> 73461221 | J15: ='Evolutive SFP'!I39 -> 73503822 | ... AX15: ='Evolutive SFP'!AW39 -> 81282836 | AY15: ='Evolutive SFP'!AW39 -> 81282836 | AZ15: ='Evolutive SFP'!AX39 -> 81366780 | BA15: ='Evolutive SFP'!AY39 -> 82735268 | BB15: ='Evolutive SFP'!AZ39 -> 83348481 | BC15: ='Evolutive SFP'!BA39 -> 0 | BD15: ='Evolutive SFP'!BB39 -> 420356850 | BE15: ='Evolutive SFP'!BC39 -> 84224873 | BF15: ='Evolutive SFP'!BD39 -> 84471578 | ... CR15: ='Evolutive SFP'!CP39 -> 94719939
A16: 5.3.2 | B16: Entrance Fees
A17: 5.3.3 | B17: Retained Earnings | C17: ='Evolutive SFP'!B41 -> 11835925 | D17: ='Evolutive SFP'!C41 -> 22842014 | E17: ='Evolutive SFP'!D41 -> 28642685 | F17: ='Evolutive SFP'!E41 -> 28642685 | G17: ='Evolutive SFP'!F41 -> 41987254 | H17: ='Evolutive SFP'!G41 -> 66804781 | I17: ='Evolutive SFP'!H41 -> 85290511 | J17: ='Evolutive SFP'!I41 -> 1.0522816e+08 | ... AX17: ='Evolutive SFP'!AW41 -> 1.4538891e+08 | AY17: ='Evolutive SFP'!AW41 -> 1.4538891e+08 | AZ17: ='Evolutive SFP'!AX41 -> 1.4538891e+08 | BA17: ='Evolutive SFP'!AY41 -> 1.4538891e+08 | BB17: ='Evolutive SFP'!AZ41 -> 1.4538891e+08 | BC17: ='Evolutive SFP'!BA41 -> 0 | BD17: ='Evolutive SFP'!BB41 -> 7.2694456e+08 | BE17: ='Evolutive SFP'!BC41 -> 1.4538891e+08 | BF17: ='Evolutive SFP'!BD41 -> 1.4538891e+08 | ... CR17: ='Evolutive SFP'!CP41 -> 1.7883049e+08
A18: 5.3.4 | B18: Appropriation Account | C18: ='Evolutive SFP'!B42 -> 0 | D18: ='Evolutive SFP'!C42 -> 0 | E18: ='Evolutive SFP'!D42 -> 0 | F18: ='Evolutive SFP'!E42 -> 13344568 | G18: ='Evolutive SFP'!F42 -> 19604846 | H18: ='Evolutive SFP'!G42 -> 18304471 | I18: ='Evolutive SFP'!H42 -> 7382638 | J18: ='Evolutive SFP'!I42 -> -2547032.5 | ... AW18: ='Evolutive SFP'!AV42 -> 7048076.5 | AX18: ='Evolutive SFP'!AV42 -> 7048076.5 | AY18: ='Evolutive SFP'!AW42 -> 9615532.4 | AZ18: ='Evolutive SFP'!AX42 -> 21852931 | BA18: ='Evolutive SFP'!AY42 -> 16852969 | BB18: ='Evolutive SFP'!AZ42 -> 16523321 | BC18: ='Evolutive SFP'!BA42 -> 0 | BD18: ='Evolutive SFP'!BB42 -> 92455243 | BE18: ='Evolutive SFP'!BC42 -> 19646034 | ... CR18: ='Evolutive SFP'!CP42 -> 5153741.8
A19: 5.3.5 | B19: Statutory Reserves | C19: ='Evolutive SFP'!B43 -> 6638993 | D19: ='Evolutive SFP'!C43 -> 9477422 | E19: ='Evolutive SFP'!D43 -> 11070308 | F19: ='Evolutive SFP'!E43 -> 14182416 | G19: ='Evolutive SFP'!F43 -> 18007281 | H19: ='Evolutive SFP'!G43 -> 22583399 | I19: ='Evolutive SFP'!H43 -> 24368909 | J19: ='Evolutive SFP'!I43 -> 22523249 | ... AW19: ='Evolutive SFP'!AV43 -> 38878707 | AX19: ='Evolutive SFP'!AV43 -> 38878707 | AY19: ='Evolutive SFP'!AW43 -> 38878707 | AZ19: ='Evolutive SFP'!AX43 -> 38878707 | BA19: ='Evolutive SFP'!AY43 -> 38878707 | BB19: ='Evolutive SFP'!AZ43 -> 38878707 | BC19: ='Evolutive SFP'!BA43 -> 0 | BD19: ='Evolutive SFP'!BB43 -> 194393535 | BE19: ='Evolutive SFP'!BC43 -> 38878707 | ... CR19: ='Evolutive SFP'!CP43 -> 49810467
A20: 5.3.6 | B20: Capital Reserves | C20: =('Evolutive SFP'!B44) -> 27818777 | D20: =('Evolutive SFP'!C44) -> 0 | E20: =('Evolutive SFP'!D44) -> 0 | F20: =('Evolutive SFP'!E44) -> 0 | G20: =('Evolutive SFP'!F44) -> 0 | H20: =('Evolutive SFP'!G44) -> 0 | I20: =('Evolutive SFP'!H44) -> 0 | J20: =('Evolutive SFP'!I44) -> 0 | ... AX20: =('Evolutive SFP'!AW44) -> 0 | AY20: =('Evolutive SFP'!AW44) -> 0 | AZ20: =('Evolutive SFP'!AX44) -> 0 | BA20: =('Evolutive SFP'!AY44) -> 0 | BB20: =('Evolutive SFP'!AZ44) -> 0 | BC20: =('Evolutive SFP'!BA44) -> 0 | BD20: =('Evolutive SFP'!BB44) -> 0 | BE20: =('Evolutive SFP'!BC44) -> 0 | BF20: =('Evolutive SFP'!BD44) -> 0 | ... CR20: =('Evolutive SFP'!CP44) -> 0
A21: 5.3.7 | B21: Supplementary Capital & reserves | C21: =C22+C23 -> 0 | D21: =D22+D23 -> 549460 | E21: =E22+E23 -> 587910 | F21: =F22+F23 -> 0 | G21: =G22+G23 -> 0 | H21: =H22+H23 -> 0 | I21: =I22+I23 -> 0 | J21: =J22+J23 -> 0 | ... CR21: =CR22+CR23 -> 0
A22: a | B22: Proposed Dividends | C22: ='Evolutive SFP'!B46 -> 0 | D22: ='Evolutive SFP'!C46 -> 549460 | E22: ='Evolutive SFP'!D46 -> 587910 | F22: ='Evolutive SFP'!E46 -> 0 | G22: ='Evolutive SFP'!F46 -> 0 | H22: ='Evolutive SFP'!G46 -> 0 | I22: ='Evolutive SFP'!H46 -> 0 | J22: ='Evolutive SFP'!I46 -> 0 | ... AX22: ='Evolutive SFP'!AW46 -> 0 | AY22: ='Evolutive SFP'!AW46 -> 0 | AZ22: ='Evolutive SFP'!AX46 -> 0 | BA22: ='Evolutive SFP'!AY46 -> 0 | BB22: ='Evolutive SFP'!AZ46 -> 0 | BC22: ='Evolutive SFP'!BA46 -> 0 | BD22: ='Evolutive SFP'!BB46 -> 0 | BE22: ='Evolutive SFP'!BC46 -> 0 | BF22: ='Evolutive SFP'!BD46 -> 0 | ... CR22: ='Evolutive SFP'!CP46 -> 0
A23: b | B23: Risk Mgt Fund
A25: 6 | B25: Investments | C25: =C26+C27+C28 -> 8942170 | D25: =D26+D27+D28 -> 13675347 | E25: =E26+E27+E28 -> 25329658 | F25: =F26+F27+F28 -> 27684833 | G25: =G26+G27+G28 -> 14582790 | H25: =H26+H27+H28 -> 28191601 | I25: =I26+I27+I28 -> 32411253 | J25: =J26+J27+J28 -> 39637678 | ... CR25: =CR26+CR27+CR28 -> 75259559
A26: 6.1 | B26: Shares in Kusco,CIC,Coop Bank | C26: ='Evolutive SFP'!B13 -> 0 | D26: ='Evolutive SFP'!C13 -> 9998645 | E26: ='Evolutive SFP'!D13 -> 9998644 | F26: ='Evolutive SFP'!E13 -> 10341549 | G26: ='Evolutive SFP'!F13 -> 14582790 | H26: ='Evolutive SFP'!G13 -> 15842990 | I26: ='Evolutive SFP'!H13 -> 25636790 | J26: ='Evolutive SFP'!I13 -> 26036790 | ... AX26: ='Evolutive SFP'!AW13 -> 32613289 | AY26: ='Evolutive SFP'!AW13 -> 32613289 | AZ26: ='Evolutive SFP'!AX13 -> 33033289 | BA26: ='Evolutive SFP'!AY13 -> 33453289 | BB26: ='Evolutive SFP'!AZ13 -> 33873289 | BC26: ='Evolutive SFP'!BA13 -> 0 | BD26: ='Evolutive SFP'!BB13 -> 173566445 | BE26: ='Evolutive SFP'!BC13 -> 35133289 | BF26: ='Evolutive SFP'!BD13 -> 35553289 | ... CR26: ='Evolutive SFP'!CP13 -> 0
A27: 6.2 | B27: Equity Investments (at cost) | C27: ='Evolutive SFP'!B10 -> 8942170 | D27: ='Evolutive SFP'!C10 -> 0 | E27: ='Evolutive SFP'!D10 -> 0 | F27: ='Evolutive SFP'!E10 -> 0 | G27: ='Evolutive SFP'!F10 -> 0 | H27: ='Evolutive SFP'!G10 -> 139800 | I27: ='Evolutive SFP'!H10 -> 0 | J27: ='Evolutive SFP'!I10 -> 0 | ... AX27: ='Evolutive SFP'!AW10 -> 0 | AY27: ='Evolutive SFP'!AW10 -> 0 | AZ27: ='Evolutive SFP'!AX10 -> 0 | BA27: ='Evolutive SFP'!AY10 -> 0 | BB27: ='Evolutive SFP'!AZ10 -> 0 | BC27: ='Evolutive SFP'!BA10 -> 0 | BD27: ='Evolutive SFP'!BB10 -> 0 | BE27: ='Evolutive SFP'!BC10 -> 0 | BF27: ='Evolutive SFP'!BD10 -> 0 | ... CR27: ='Evolutive SFP'!CP10 -> 0
A28: 6.3 | B28: Deposits in KUSCCO CFP | C28: ='Evolutive SFP'!B11 -> 0 | D28: ='Evolutive SFP'!C11 -> 3676702 | E28: ='Evolutive SFP'!D11 -> 15331014 | F28: ='Evolutive SFP'!E11 -> 17343284 | G28: ='Evolutive SFP'!F11 -> 0 | H28: ='Evolutive SFP'!G11 -> 12208811 | I28: ='Evolutive SFP'!H11 -> 6774463 | J28: ='Evolutive SFP'!I11 -> 13600888 | ... AW28: ='Evolutive SFP'!AV11 -> 14504391 | AX28: ='Evolutive SFP'!AV11 -> 14504391 | AY28: ='Evolutive SFP'!AW11 -> 14704391 | AZ28: ='Evolutive SFP'!AX11 -> 9304390.8 | BA28: ='Evolutive SFP'!AY11 -> 9504390.8 | BB28: ='Evolutive SFP'!AZ11 -> 10054391 | BC28: ='Evolutive SFP'!BA11 -> 0 | BD28: ='Evolutive SFP'!BB11 -> 56415201 | BE28: ='Evolutive SFP'!BC11 -> 11833040 | ... CR28: ='Evolutive SFP'!CP11 -> 75259559
A30: 7 | B30: Net Loans & Advances | C30: ='Evolutive SFP'!B14 -> 263143330 | D30: ='Evolutive SFP'!C14 -> 294845459 | E30: ='Evolutive SFP'!D14 -> 318026558 | F30: ='Evolutive SFP'!E14 -> 3.516902e+08 | G30: ='Evolutive SFP'!F14 -> 350184189 | H30: ='Evolutive SFP'!G14 -> 376107614 | I30: ='Evolutive SFP'!H14 -> 468334250 | J30: ='Evolutive SFP'!I14 -> 4.9099259e+08 | ... AX30: ='Evolutive SFP'!AW14 -> 7.0127218e+08 | AY30: ='Evolutive SFP'!AW14 -> 7.0127218e+08 | AZ30: ='Evolutive SFP'!AX14 -> 6.9863261e+08 | BA30: ='Evolutive SFP'!AY14 -> 6.8910168e+08 | BB30: ='Evolutive SFP'!AZ14 -> 6.8144395e+08 | BC30: ='Evolutive SFP'!BA14 -> 0 | BD30: ='Evolutive SFP'!BB14 -> 3.508172e+09 | BE30: ='Evolutive SFP'!BC14 -> 7.0572065e+08 | BF30: ='Evolutive SFP'!BD14 -> 7.1861073e+08 | ... CR30: ='Evolutive SFP'!CP14 -> 8.5077549e+08
A31: 7.1 | B31: Gross Loans & advances | C31: ='Evolutive SFP'!B15 -> 263143330 | D31: ='Evolutive SFP'!C15 -> 296918859 | E31: ='Evolutive SFP'!D15 -> 325298062 | F31: ='Evolutive SFP'!E15 -> 3.5915199e+08 | G31: ='Evolutive SFP'!F15 -> 360786989 | H31: ='Evolutive SFP'!G15 -> 389781182 | I31: ='Evolutive SFP'!H15 -> 491527931 | J31: ='Evolutive SFP'!I15 -> 5.0468456e+08 | ... AW31: ='Evolutive SFP'!AV15 -> 7.2598822e+08 | AX31: ='Evolutive SFP'!AV15 -> 7.2598822e+08 | AY31: ='Evolutive SFP'!AW15 -> 7.2438179e+08 | AZ31: ='Evolutive SFP'!AX15 -> 7.234794e+08 | BA31: ='Evolutive SFP'!AY15 -> 7.1536943e+08 | BB31: ='Evolutive SFP'!AZ15 -> 7.1114084e+08 | BC31: ='Evolutive SFP'!BA15 -> 0 | BD31: ='Evolutive SFP'!BB15 -> 3.6662176e+09 | BE31: ='Evolutive SFP'!BC15 -> 7.3903284e+08 | ... CR31: ='Evolutive SFP'!CP15 -> 8.7044124e+08
A32: 7.2 | B32: Allowance for loan losses | C32: ='Evolutive SFP'!B16 -> 0 | D32: ='Evolutive SFP'!C16 -> 2073400 | E32: ='Evolutive SFP'!D16 -> 7271504 | F32: ='Evolutive SFP'!E16 -> 7461796.2 | G32: ='Evolutive SFP'!F16 -> 10602800 | H32: ='Evolutive SFP'!G16 -> 13673568 | I32: ='Evolutive SFP'!H16 -> 23193681 | J32: ='Evolutive SFP'!I16 -> 13691966 | ... AX32: ='Evolutive SFP'!AW16 -> 23109616 | AY32: ='Evolutive SFP'!AW16 -> 23109616 | AZ32: ='Evolutive SFP'!AX16 -> 24846795 | BA32: ='Evolutive SFP'!AY16 -> 26267745 | BB32: ='Evolutive SFP'!AZ16 -> 29696887 | BC32: ='Evolutive SFP'!BA16 -> 0 | BD32: ='Evolutive SFP'!BB16 -> 1.5804551e+08 | BE32: ='Evolutive SFP'!BC16 -> 33312188 | BF32: ='Evolutive SFP'!BD16 -> 32764675 | ... CR32: ='Evolutive SFP'!CP16 -> 19665756
A34: 8 | B34: Non-Earning Assets | C34: ='Evolutive SFP'!B21+'Evolutive SFP'!B7 -> 88115469 | D34: ='Evolutive SFP'!C21+'Evolutive SFP'!C7 -> 94558031 | E34: ='Evolutive SFP'!D21+'Evolutive SFP'!D7 -> 98882441 | F34: ='Evolutive SFP'!E21+'Evolutive SFP'!E7 -> 88993908 | G34: ='Evolutive SFP'!F21+'Evolutive SFP'!F7 -> 119945556 | H34: ='Evolutive SFP'!G21+'Evolutive SFP'!G7 -> 127032190 | I34: ='Evolutive SFP'!H21+'Evolutive SFP'!H7 -> 160091568 | J34: ='Evolutive SFP'!I21+'Evolutive SFP'!I7 -> 1.5226473e+08 | ... AW34: ='Evolutive SFP'!AV21+'Evolutive SFP'!AV7 -> 71721149 | AX34: ='Evolutive SFP'!AV21+'Evolutive SFP'!AV7 -> 71721149 | AY34: ='Evolutive SFP'!AW21+'Evolutive SFP'!AW7 -> 71637493 | AZ34: ='Evolutive SFP'!AX21+'Evolutive SFP'!AX7 -> 70673703 | BA34: ='Evolutive SFP'!AY21+'Evolutive SFP'!AY7 -> 70239103 | BB34: ='Evolutive SFP'!AZ21+'Evolutive SFP'!AZ7 -> 70949593 | BC34: ='Evolutive SFP'!BA21+'Evolutive SFP'!BA7 -> 0 | BD34: ='Evolutive SFP'!BB21+'Evolutive SFP'!BB7 -> 3.6047965e+08 | BE34: ='Evolutive SFP'!BC21+'Evolutive SFP'!BC7 -> 72903339 | ... CR34: ='Evolutive SFP'!CP21+'Evolutive SFP'!CP7 -> 56380373
A35: 8.1 | B35: Property and Equipment | C35: ='Evolutive SFP'!B23 -> 75849622 | D35: ='Evolutive SFP'!C23 -> 70621990 | E35: ='Evolutive SFP'!D23 -> 58833519 | F35: ='Evolutive SFP'!E23 -> 56943309 | G35: ='Evolutive SFP'!F23 -> 55634863 | H35: ='Evolutive SFP'!G23 -> 39960484 | I35: ='Evolutive SFP'!H23 -> 40147340 | J35: ='Evolutive SFP'!I23 -> 40050734 | ... AY35: ='Evolutive SFP'!AX23 -> 37465949 | AZ35: ='Evolutive SFP'!AX23 -> 37465949 | BA35: ='Evolutive SFP'!AY23 -> 37396702 | BB35: ='Evolutive SFP'!AZ23 -> 37304455 | BC35: ='Evolutive SFP'!BA23 -> 0 | BD35: ='Evolutive SFP'!BB23 -> 1.8800401e+08 | BE35: ='Evolutive SFP'!BC23 -> 37687360 | BF35: ='Evolutive SFP'!BD23 -> 37553885 | BG35: ='Evolutive SFP'!BE23 -> 37069518 | ... CR35: ='Evolutive SFP'!CP23 -> 34966225
A37: 9 | B37: Turnover | C37: =C38+C39+C40+C41 -> 53102019 | D37: =D38+D39+D40+D41 -> 67876418 | E37: =E38+E39+E40+E41 -> 76649112 | F37: =F38+F39+F40+F41 -> 93967038 | G37: =G38+G39+G40+G41 -> 97400688 | H37: =H38+H39+H40+H41 -> 109849160 | I37: =I38+I39+I40+I41 -> 121408969 | J37: =J38+J39+J40+J41 -> 3091134.1 | ... CR37: =CR38+CR39+CR40+CR41 -> 1.3218021e+08
A38: 9.1 | B38: Loan Interest | C38: ='Evolutitve SCI'!B5 -> 50952511 | D38: ='Evolutitve SCI'!C5 -> 64376963 | E38: ='Evolutitve SCI'!D5 -> 71327939 | F38: ='Evolutitve SCI'!E5 -> 86602624 | G38: ='Evolutitve SCI'!F5 -> 88158935 | H38: ='Evolutitve SCI'!G5 -> 100764347 | I38: ='Evolutitve SCI'!H5 -> 110622193 | J38: ='Evolutitve SCI'!I5 -> 2868188.9 | ... CR38: ='Evolutitve SCI'!CQ5 -> 96635030
A39: 9.2 | B39: Income from investments | C39: ='Evolutitve SCI'!B7 -> 2149508 | D39: ='Evolutitve SCI'!C7 -> 3499455 | E39: ='Evolutitve SCI'!D7 -> 5321173 | F39: ='Evolutitve SCI'!E7 -> 2815858.9 | G39: ='Evolutitve SCI'!F7 -> 1271231 | H39: ='Evolutitve SCI'!G7 -> 9084813 | I39: ='Evolutitve SCI'!H7 -> 10786776 | J39: ='Evolutitve SCI'!I7 -> 62934.75 | ... CR39: ='Evolutitve SCI'!CQ7 -> 27588846
A40: 9.3 | B40: Fees & Commissions | C40: ='Evolutitve SCI'!B6 -> 0 | D40: ='Evolutitve SCI'!C6 -> 0 | E40: ='Evolutitve SCI'!D6 -> 0 | F40: ='Evolutitve SCI'!E6 -> 4548555 | G40: ='Evolutitve SCI'!F6 -> 7970522 | H40: ='Evolutitve SCI'!G6 -> 0 | I40: ='Evolutitve SCI'!H6 -> 0 | J40: ='Evolutitve SCI'!I6 -> 160010.5 | ... CR40: ='Evolutitve SCI'!CQ6 -> 7956337
A41: 9.4 | B41: Average yield on loans
A43: 10 | B43: Financial and Operating costs | C43: =SUM(C44:C47) -> 44309066 | D43: =SUM(D44:D47) -> 50491542 | E43: =SUM(E44:E47) -> 63119370 | F43: =SUM(F44:F47) -> 77259105 | G43: =SUM(G44:G47) -> 74354817 | H43: =SUM(H44:H47) -> 83585136 | I43: =SUM(I44:I47) -> 102080818 | J43: =SUM(J44:J47) -> 5499249.1 | ... CR43: =SUM(CR44:CR47) -> 1.8848941e+08
A44: 10.1 | B44: Interest expense on deposits | C44: ='Evolutitve SCI'!B13+'Evolutitve SCI'!B16 -> 24208136 | D44: ='Evolutitve SCI'!C13+'Evolutitve SCI'!C16 -> 16622609 | E44: ='Evolutitve SCI'!D13+'Evolutitve SCI'!D16 -> 19553383 | F44: ='Evolutitve SCI'!E13+'Evolutitve SCI'!E16 -> 25035863 | G44: ='Evolutitve SCI'!F13+'Evolutitve SCI'!F16 -> 28895754 | H44: ='Evolutitve SCI'!G13+'Evolutitve SCI'!G16 -> 34066507 | I44: ='Evolutitve SCI'!H13+'Evolutitve SCI'!H16 -> 37075248 | J44: ='Evolutitve SCI'!I13+'Evolutitve SCI'!I16 -> 2576230 | ... CR44: ='Evolutitve SCI'!CQ13+'Evolutitve SCI'!CQ16 -> 57047544
A45: 10.2 | B45: Dividend expense on share capital | C45: ='Evolutitve SCI'!B15 -> 0 | D45: ='Evolutitve SCI'!C15 -> 0 | E45: ='Evolutitve SCI'!D15 -> 0 | F45: ='Evolutitve SCI'!E15 -> 0 | G45: ='Evolutitve SCI'!F15 -> 0 | H45: ='Evolutitve SCI'!G15 -> 0 | I45: ='Evolutitve SCI'!H15 -> 0 | J45: ='Evolutitve SCI'!I15 -> 0 | ... CR45: ='Evolutitve SCI'!CQ15 -> 0
A46: 10.3 | B46: Interest expense on borrowed funds | C46: ='Evolutitve SCI'!B14 -> 0 | D46: ='Evolutitve SCI'!C14 -> 10569123 | E46: ='Evolutitve SCI'!D14 -> 15436251 | F46: ='Evolutitve SCI'!E14 -> 14077264 | G46: ='Evolutitve SCI'!F14 -> 6809774 | H46: ='Evolutitve SCI'!G14 -> 1293620 | I46: ='Evolutitve SCI'!H14 -> 0 | J46: ='Evolutitve SCI'!I14 -> 0 | ... BH46: ='Evolutitve SCI'!BG14 -> 0 | BI46: ='Evolutitve SCI'!BH13 -> 56353562 | BJ46: ='Evolutitve SCI'!BI13 -> 5000000 | BK46: ='Evolutitve SCI'!BJ13 -> 10000000 | BL46: ='Evolutitve SCI'!BK13 -> 15000000 | BM46: ='Evolutitve SCI'!BL13 -> 20000000 | BN46: ='Evolutitve SCI'!BM13 -> 25000000 | BO46: ='Evolutitve SCI'!BN13 -> 30000000 | BP46: ='Evolutitve SCI'!BO13 -> 35000000 | ... CR46: ='Evolutitve SCI'!CQ13 -> 54715694
A47: 10.4 | B47: Opperating expenses | C47: ='Evolutitve SCI'!B23 -> 20100930 | D47: ='Evolutitve SCI'!C23 -> 23299810 | E47: ='Evolutitve SCI'!D23 -> 28129736 | F47: ='Evolutitve SCI'!E23 -> 38145978 | G47: ='Evolutitve SCI'!F23 -> 38649289 | H47: ='Evolutitve SCI'!G23 -> 48225009 | I47: ='Evolutitve SCI'!H23 -> 65005570 | J47: ='Evolutitve SCI'!I23 -> 2923019.1 | ... CR47: ='Evolutitve SCI'!CQ23 -> 76726170

Sheet CAELS Rating
D1: APPLIED RATE(All Instances)
A2: CAELS RATINGS ECO-PILLAR SACCO
A3: FINANCIAL SOUNDNESS INDICATORS | B3: Prude. Std | C3: 2010 Audited | D3: 2011 Audited | E3: 2012 Audited | F3: 2013 Audited | G3: 2014 Audited | H3: 2015 Audited | I3: 2016 Audited | J3: 42736 | K3: 42767 | L3: 42795 | M3: 42826 | N3: 42856 | O3: 42887 | P3: 42917 | Q3: 42948 | R3: 42979 | S3: 43009 | T3: 43040 | U3: 43070 | V3: Audited | W3: 43101 | X3: 43132 | Y3: 43160 | Z3: 43191 | AA3: 43221 | AB3: 43252 | AC3: 43282 | AD3: 43313 | AE3: 43344 | AF3: 43374 | AG3: 43405 | AH3: 43435 | AI3: 43466 | AJ3: 43497 | AK3: 43525 | AL3: 43556
A4: CAPITAL
A5: CORE CAPITAL | B5: ≥ Ksh.10M | C5: =IF(CAELS!D3>10,"1","5") -> 1 | D5: =IF(CAELS!E3>10,"1","5") -> 1 | E5: =IF(CAELS!F3>10,"1","5") -> 1 | F5: =IF(CAELS!G3>10,"1","5") -> 1 | G5: =IF(CAELS!H3>10,"1","5") -> 1 | H5: =IF(CAELS!I3>10,"1","5") -> 1 | I5: =IF(CAELS!J3>10,"1","5") -> 1 | J5: =IF(CAELS!K3>10,"1","5") -> 1 | ... AC5: =IF(CAELS!AD3>10,"1","5") -> 1
A6: CCA | B6: ≥ 10% | C6: =IF(CAELS!D4>20%,"1",IF(CAELS!D4>15%,"2",IF(CAELS!D4>12%,"3",IF(CAELS!D4>10%,"4","5")))) -> 4 | D6: =IF(CAELS!E4>20%,"1",IF(CAELS!E4>15%,"2",IF(CAELS!E4>12%,"3",IF(CAELS!E4>10%,"4","5")))) -> 2 | E6: =IF(CAELS!F4>20%,"1",IF(CAELS!F4>15%,"2",IF(CAELS!F4>12%,"3",IF(CAELS!F4>10%,"4","5")))) -> 2 | F6: =IF(CAELS!G4>20%,"1",IF(CAELS!G4>15%,"2",IF(CAELS!G4>12%,"3",IF(CAELS!G4>10%,"4","5")))) -> 2 | G6: =IF(CAELS!H4>20%,"1",IF(CAELS!H4>15%,"2",IF(CAELS!H4>12%,"3",IF(CAELS!H4>10%,"4","5")))) -> 1 | H6: =IF(CAELS!I4>20%,"1",IF(CAELS!I4>15%,"2",IF(CAELS!I4>12%,"3",IF(CAELS!I4>10%,"4","5")))) -> 1 | I6: =IF(CAELS!J4>20%,"1",IF(CAELS!J4>15%,"2",IF(CAELS!J4>12%,"3",IF(CAELS!J4>10%,"4","5")))) -> 1 | J6: =IF(CAELS!K4>20%,"1",IF(CAELS!K4>15%,"2",IF(CAELS!K4>12%,"3",IF(CAELS!K4>10%,"4","5")))) -> 1 | ... AD6: =IF(CAELS!AE4>20%,"1",IF(CAELS!AE4>15%,"2",IF(CAELS!AE4>12%,"3",IF(CAELS!AE4>10%,"4","5")))) -> 1
A7: ICA | B7: ≥ 8% | C7: =IF(CAELS!D6>15%,"1",IF(CAELS!D6>12%,"2",IF(CAELS!D6>10%,"3",IF(CAELS!D6>8,"4","5")))) -> 3 | D7: =IF(CAELS!E6>15%,"1",IF(CAELS!E6>12%,"2",IF(CAELS!E6>10%,"3",IF(CAELS!E6>8,"4","5")))) -> 5 | E7: =IF(CAELS!F6>15%,"1",IF(CAELS!F6>12%,"2",IF(CAELS!F6>10%,"3",IF(CAELS!F6>8,"4","5")))) -> 5 | F7: =IF(CAELS!G6>15%,"1",IF(CAELS!G6>12%,"2",IF(CAELS!G6>10%,"3",IF(CAELS!G6>8,"4","5")))) -> 3 | G7: =IF(CAELS!H6>15%,"1",IF(CAELS!H6>12%,"2",IF(CAELS!H6>10%,"3",IF(CAELS!H6>8,"4","5")))) -> 2 | H7: =IF(CAELS!I6>15%,"1",IF(CAELS!I6>12%,"2",IF(CAELS!I6>10%,"3",IF(CAELS!I6>8,"4","5")))) -> 1 | I7: =IF(CAELS!J6>15%,"1",IF(CAELS!J6>12%,"2",IF(CAELS!J6>10%,"3",IF(CAELS!J6>8,"4","5")))) -> 1 | J7: =IF(CAELS!K6>15%,"1",IF(CAELS!K6>12%,"2",IF(CAELS!K6>10%,"3",IF(CAELS!K6>8,"4","5")))) -> 1 | ... AA7: =IF(CAELS!AB6>15%,"1",IF(CAELS!AB6>12%,"2",IF(CAELS!AB6>10%,"3",IF(CAELS!AB6>8,"4","5")))) -> 1
A8: CCD | B8: ≥ 8% | C8: =IF(CAELS!D5>20%,"1",IF(CAELS!D5>15%,"2",IF(CAELS!D5>12%,"3",IF(CAELS!D5>10%,"4","5")))) -> 2 | D8: =IF(CAELS!E5>20%,"1",IF(CAELS!E5>15%,"2",IF(CAELS!E5>12%,"3",IF(CAELS!E5>10%,"4","5")))) -> 1 | E8: =IF(CAELS!F5>20%,"1",IF(CAELS!F5>15%,"2",IF(CAELS!F5>12%,"3",IF(CAELS!F5>10%,"4","5")))) -> 1 | F8: =IF(CAELS!G5>20%,"1",IF(CAELS!G5>15%,"2",IF(CAELS!G5>12%,"3",IF(CAELS!G5>10%,"4","5")))) -> 1 | G8: =IF(CAELS!H5>20%,"1",IF(CAELS!H5>15%,"2",IF(CAELS!H5>12%,"3",IF(CAELS!H5>10%,"4","5")))) -> 1 | H8: =IF(CAELS!I5>20%,"1",IF(CAELS!I5>15%,"2",IF(CAELS!I5>12%,"3",IF(CAELS!I5>10%,"4","5")))) -> 1 | I8: =IF(CAELS!J5>20%,"1",IF(CAELS!J5>15%,"2",IF(CAELS!J5>12%,"3",IF(CAELS!J5>10%,"4","5")))) -> 1 | J8: =IF(CAELS!K5>20%,"1",IF(CAELS!K5>15%,"2",IF(CAELS!K5>12%,"3",IF(CAELS!K5>10%,"4","5")))) -> 1 | ... AF8: =IF(CAELS!AG5>20%,"1",IF(CAELS!AG5>15%,"2",IF(CAELS!AG5>12%,"3",IF(CAELS!AG5>10%,"4","5")))) -> 1
C9: =(C5+C6+C7+C8)/4 -> 2.5 | D9: =(D5+D6+D7+D8)/4 -> 2.25 | E9: =(E5+E6+E7+E8)/4 -> 2.25 | F9: =(F5+F6+F7+F8)/4 -> 1.75 | G9: =(G5+G6+G7+G8)/4 -> 1.25 | H9: =(H5+H6+H7+H8)/4 -> 1 | I9: =(I5+I6+I7+I8)/4 -> 1 | J9: =(J5+J6+J7+J8)/4 -> 1 | ... AF9: =(AF5+AF6+AF7+AF8)/4 -> 0.25
A10: Asset Quality
A11: NPL | B11: ≤ 6% | L11: =IF(CAELS!M8<4%,"1",IF(CAELS!M8<8%,"2",IF(CAELS!M8<12%,"3",IF(CAELS!M8<15%,"4","5")))) -> #REF! | O11: =IF(CAELS!P8<4%,"1",IF(CAELS!P8<8%,"2",IF(CAELS!P8<12%,"3",IF(CAELS!P8<15%,"4","5")))) -> #REF! | R11: =IF(CAELS!S8<4%,"1",IF(CAELS!S8<8%,"2",IF(CAELS!S8<12%,"3",IF(CAELS!S8<15%,"4","5")))) -> #REF! | S11: =IF(CAELS!T8<4%,"1",IF(CAELS!T8<8%,"2",IF(CAELS!T8<12%,"3",IF(CAELS!T8<15%,"4","5")))) -> 1 | T11: =IF(CAELS!U8<4%,"1",IF(CAELS!U8<8%,"2",IF(CAELS!U8<12%,"3",IF(CAELS!U8<15%,"4","5")))) -> 1 | U11: =IF(CAELS!V8<4%,"1",IF(CAELS!V8<8%,"2",IF(CAELS!V8<12%,"3",IF(CAELS!V8<15%,"4","5")))) -> #REF! | V11: =IF(CAELS!W8<4%,"1",IF(CAELS!W8<8%,"2",IF(CAELS!W8<12%,"3",IF(CAELS!W8<15%,"4","5")))) -> #REF! | W11: =IF(CAELS!X8<4%,"1",IF(CAELS!X8<8%,"2",IF(CAELS!X8<12%,"3",IF(CAELS!X8<15%,"4","5")))) -> #REF! | X11: =IF(CAELS!Y8<4%,"1",IF(CAELS!Y8<8%,"2",IF(CAELS!Y8<12%,"3",IF(CAELS!Y8<15%,"4","5")))) -> #REF! | Y11: =IF(CAELS!Z8<4%,"1",IF(CAELS!Z8<8%,"2",IF(CAELS!Z8<12%,"3",IF(CAELS!Z8<15%,"4","5")))) -> 2 | ... AF11: =IF(CAELS!AG8<4%,"1",IF(CAELS!AG8<8%,"2",IF(CAELS!AG8<12%,"3",IF(CAELS!AG8<15%,"4","5")))) -> 2
C12: =C11 -> 0 | D12: =D11 -> 0 | E12: =E11 -> 0 | F12: =F11 -> 0 | G12: =G11 -> 0 | H12: =H11 -> 0 | I12: =I11 -> 0 | J12: =J11 -> 0 | ... AF12: =AF11 -> 2
A13: Earnings
A14: ROA | D14: =IF(CAELS!E9>6%,"1",IF(CAELS!E9>4%,"2",IF(CAELS!E9>2%,"3",IF(CAELS!E9>0%,"4","5")))) -> 3 | E14: =IF(CAELS!F9>6%,"1",IF(CAELS!F9>4%,"2",IF(CAELS!F9>2%,"3",IF(CAELS!F9>0%,"4","5")))) -> 4 | F14: =IF(CAELS!G9>6%,"1",IF(CAELS!G9>4%,"2",IF(CAELS!G9>2%,"3",IF(CAELS!G9>0%,"4","5")))) -> 3 | G14: =IF(CAELS!H9>6%,"1",IF(CAELS!H9>4%,"2",IF(CAELS!H9>2%,"3",IF(CAELS!H9>0%,"4","5")))) -> 3 | H14: =IF(CAELS!I9>6%,"1",IF(CAELS!I9>4%,"2",IF(CAELS!I9>2%,"3",IF(CAELS!I9>0%,"4","5")))) -> 2 | I14: =IF(CAELS!J9>6%,"1",IF(CAELS!J9>4%,"2",IF(CAELS!J9>2%,"3",IF(CAELS!J9>0%,"4","5")))) -> 4 | J14: =IF(CAELS!K9>6%,"1",IF(CAELS!K9>4%,"2",IF(CAELS!K9>2%,"3",IF(CAELS!K9>0%,"4","5")))) -> 5 | K14: =IF(CAELS!L9>6%,"1",IF(CAELS!L9>4%,"2",IF(CAELS!L9>2%,"3",IF(CAELS!L9>0%,"4","5")))) -> 4 | ... AF14: =IF(CAELS!AG9>6%,"1",IF(CAELS!AG9>4%,"2",IF(CAELS!AG9>2%,"3",IF(CAELS!AG9>0%,"4","5")))) -> 2
A15: CIR | C15: =IF(CAELS!D10<60%,"1",IF(CAELS!D10<70%,"2",IF(CAELS!D10<80%,"3",IF(CAELS!D10<90%,"4","5")))) -> 2 | D15: =IF(CAELS!E10<60%,"1",IF(CAELS!E10<70%,"2",IF(CAELS!E10<80%,"3",IF(CAELS!E10<90%,"4","5")))) -> 1 | E15: =IF(CAELS!F10<60%,"1",IF(CAELS!F10<70%,"2",IF(CAELS!F10<80%,"3",IF(CAELS!F10<90%,"4","5")))) -> 2 | F15: =IF(CAELS!G10<60%,"1",IF(CAELS!G10<70%,"2",IF(CAELS!G10<80%,"3",IF(CAELS!G10<90%,"4","5")))) -> 2 | G15: =IF(CAELS!H10<60%,"1",IF(CAELS!H10<70%,"2",IF(CAELS!H10<80%,"3",IF(CAELS!H10<90%,"4","5")))) -> 2 | H15: =IF(CAELS!I10<60%,"1",IF(CAELS!I10<70%,"2",IF(CAELS!I10<80%,"3",IF(CAELS!I10<90%,"4","5")))) -> 2 | I15: =IF(CAELS!J10<60%,"1",IF(CAELS!J10<70%,"2",IF(CAELS!J10<80%,"3",IF(CAELS!J10<90%,"4","5")))) -> 3 | J15: =IF(CAELS!K10<60%,"1",IF(CAELS!K10<70%,"2",IF(CAELS!K10<80%,"3",IF(CAELS!K10<90%,"4","5")))) -> 5 | ... AF15: =IF(CAELS!AG10<60%,"1",IF(CAELS!AG10<70%,"2",IF(CAELS!AG10<80%,"3",IF(CAELS!AG10<90%,"4","5")))) -> 1
A16: OER | C16: =IF(CAELS!D11<4%,"1",IF(CAELS!D11<6%,"2",IF(CAELS!D11<8%,"3",IF(CAELS!D11<10%,"4","5")))) -> 5 | D16: =IF(CAELS!E11<4%,"1",IF(CAELS!E11<6%,"2",IF(CAELS!E11<8%,"3",IF(CAELS!E11<10%,"4","5")))) -> 5 | E16: =IF(CAELS!F11<4%,"1",IF(CAELS!F11<6%,"2",IF(CAELS!F11<8%,"3",IF(CAELS!F11<10%,"4","5")))) -> 5 | F16: =IF(CAELS!G11<4%,"1",IF(CAELS!G11<6%,"2",IF(CAELS!G11<8%,"3",IF(CAELS!G11<10%,"4","5")))) -> 5 | G16: =IF(CAELS!H11<4%,"1",IF(CAELS!H11<6%,"2",IF(CAELS!H11<8%,"3",IF(CAELS!H11<10%,"4","5")))) -> 5 | H16: =IF(CAELS!I11<4%,"1",IF(CAELS!I11<6%,"2",IF(CAELS!I11<8%,"3",IF(CAELS!I11<10%,"4","5")))) -> 5 | I16: =IF(CAELS!J11<4%,"1",IF(CAELS!J11<6%,"2",IF(CAELS!J11<8%,"3",IF(CAELS!J11<10%,"4","5")))) -> 5 | J16: =IF(CAELS!K11<4%,"1",IF(CAELS!K11<6%,"2",IF(CAELS!K11<8%,"3",IF(CAELS!K11<10%,"4","5")))) -> 1 | ... AF16: =IF(CAELS!AG11<4%,"1",IF(CAELS!AG11<6%,"2",IF(CAELS!AG11<8%,"3",IF(CAELS!AG11<10%,"4","5")))) -> 4
C17: =(C14+C15+C16)/3 -> 2.3333333 | D17: =(D14+D15+D16)/3 -> 3 | E17: =(E14+E15+E16)/3 -> 3.6666667 | F17: =(F14+F15+F16)/3 -> 3.3333333 | G17: =(G14+G15+G16)/3 -> 3.3333333 | H17: =(H14+H15+H16)/3 -> 3 | I17: =(I14+I15+I16)/3 -> 4 | J17: =(J14+J15+J16)/3 -> 3.6666667 | ... AF17: =(AF14+AF15+AF16)/3 -> 2.3333333
A18: LIQUIDITY
A19: MIN LIQ | B19: 0.15 | C19: =IF(CAELS!D12>30%,"1",IF(CAELS!D12>25%,"2",IF(CAELS!D12>20%,"3",IF(CAELS!D12>15%,"4","5")))) -> 1 | D19: =IF(CAELS!E12>30%,"1",IF(CAELS!E12>25%,"2",IF(CAELS!E12>20%,"3",IF(CAELS!E12>15%,"4","5")))) -> 5 | E19: =IF(CAELS!F12>30%,"1",IF(CAELS!F12>25%,"2",IF(CAELS!F12>20%,"3",IF(CAELS!F12>15%,"4","5")))) -> 5 | F19: =IF(CAELS!G12>30%,"1",IF(CAELS!G12>25%,"2",IF(CAELS!G12>20%,"3",IF(CAELS!G12>15%,"4","5")))) -> 5 | G19: =IF(CAELS!H12>30%,"1",IF(CAELS!H12>25%,"2",IF(CAELS!H12>20%,"3",IF(CAELS!H12>15%,"4","5")))) -> 1 | H19: =IF(CAELS!I12>30%,"1",IF(CAELS!I12>25%,"2",IF(CAELS!I12>20%,"3",IF(CAELS!I12>15%,"4","5")))) -> 1 | I19: =IF(CAELS!J12>30%,"1",IF(CAELS!J12>25%,"2",IF(CAELS!J12>20%,"3",IF(CAELS!J12>15%,"4","5")))) -> 2 | J19: =IF(CAELS!K12>30%,"1",IF(CAELS!K12>25%,"2",IF(CAELS!K12>20%,"3",IF(CAELS!K12>15%,"4","5")))) -> 4 | ... AF19: =IF(CAELS!AG12>30%,"1",IF(CAELS!AG12>25%,"2",IF(CAELS!AG12>20%,"3",IF(CAELS!AG12>15%,"4","5")))) -> 1
A20: TECH LIQ | C20: =IF(CAELS!D13>30%,"1",IF(CAELS!D13>25%,"2",IF(CAELS!D13>20%,"3",IF(CAELS!D13>15%,"4","5")))) -> 3 | D20: =IF(CAELS!E13>30%,"1",IF(CAELS!E13>25%,"2",IF(CAELS!E13>20%,"3",IF(CAELS!E13>15%,"4","5")))) -> 5 | E20: =IF(CAELS!F13>30%,"1",IF(CAELS!F13>25%,"2",IF(CAELS!F13>20%,"3",IF(CAELS!F13>15%,"4","5")))) -> 5 | F20: =IF(CAELS!G13>30%,"1",IF(CAELS!G13>25%,"2",IF(CAELS!G13>20%,"3",IF(CAELS!G13>15%,"4","5")))) -> 5 | G20: =IF(CAELS!H13>30%,"1",IF(CAELS!H13>25%,"2",IF(CAELS!H13>20%,"3",IF(CAELS!H13>15%,"4","5")))) -> 5 | H20: =IF(CAELS!I13>30%,"1",IF(CAELS!I13>25%,"2",IF(CAELS!I13>20%,"3",IF(CAELS!I13>15%,"4","5")))) -> 4 | I20: =IF(CAELS!J13>30%,"1",IF(CAELS!J13>25%,"2",IF(CAELS!J13>20%,"3",IF(CAELS!J13>15%,"4","5")))) -> 5 | J20: =IF(CAELS!K13>30%,"1",IF(CAELS!K13>25%,"2",IF(CAELS!K13>20%,"3",IF(CAELS!K13>15%,"4","5")))) -> 5 | ... AF20: =IF(CAELS!AG13>30%,"1",IF(CAELS!AG13>25%,"2",IF(CAELS!AG13>20%,"3",IF(CAELS!AG13>15%,"4","5")))) -> 5
A21: EB | B21: ≤ 25% | C21: =IF(CAELS!D14<15%,"1",IF(CAELS!D14<18%,"2",IF(CAELS!D14<22%,"3",IF(CAELS!D14<25%,"4","5")))) -> 4 | D21: =IF(CAELS!E14<15%,"1",IF(CAELS!E14<18%,"2",IF(CAELS!E14<22%,"3",IF(CAELS!E14<25%,"4","5")))) -> 2 | E21: =IF(CAELS!F14<15%,"1",IF(CAELS!F14<18%,"2",IF(CAELS!F14<22%,"3",IF(CAELS!F14<25%,"4","5")))) -> 2 | F21: =IF(CAELS!G14<15%,"1",IF(CAELS!G14<18%,"2",IF(CAELS!G14<22%,"3",IF(CAELS!G14<25%,"4","5")))) -> 1 | G21: =IF(CAELS!H14<15%,"1",IF(CAELS!H14<18%,"2",IF(CAELS!H14<22%,"3",IF(CAELS!H14<25%,"4","5")))) -> 1 | H21: =IF(CAELS!I14<15%,"1",IF(CAELS!I14<18%,"2",IF(CAELS!I14<22%,"3",IF(CAELS!I14<25%,"4","5")))) -> 1 | I21: =IF(CAELS!J14<15%,"1",IF(CAELS!J14<18%,"2",IF(CAELS!J14<22%,"3",IF(CAELS!J14<25%,"4","5")))) -> 1 | J21: =IF(CAELS!K14<15%,"1",IF(CAELS!K14<18%,"2",IF(CAELS!K14<22%,"3",IF(CAELS!K14<25%,"4","5")))) -> 1 | ... AF21: =IF(CAELS!AG14<15%,"1",IF(CAELS!AG14<18%,"2",IF(CAELS!AG14<22%,"3",IF(CAELS!AG14<25%,"4","5")))) -> 1
A22: LIQ/TA | C22: =IF(CAELS!D15>15%,"1",IF(CAELS!D15>12%,"2",IF(CAELS!D15>9%,"3",IF(CAELS!D15>6%,"4","5")))) -> 2 | D22: =IF(CAELS!E15>15%,"1",IF(CAELS!E15>12%,"2",IF(CAELS!E15>9%,"3",IF(CAELS!E15>6%,"4","5")))) -> 5 | E22: =IF(CAELS!F15>15%,"1",IF(CAELS!F15>12%,"2",IF(CAELS!F15>9%,"3",IF(CAELS!F15>6%,"4","5")))) -> 5 | F22: =IF(CAELS!G15>15%,"1",IF(CAELS!G15>12%,"2",IF(CAELS!G15>9%,"3",IF(CAELS!G15>6%,"4","5")))) -> 4 | G22: =IF(CAELS!H15>15%,"1",IF(CAELS!H15>12%,"2",IF(CAELS!H15>9%,"3",IF(CAELS!H15>6%,"4","5")))) -> 3 | H22: =IF(CAELS!I15>15%,"1",IF(CAELS!I15>12%,"2",IF(CAELS!I15>9%,"3",IF(CAELS!I15>6%,"4","5")))) -> 2 | I22: =IF(CAELS!J15>15%,"1",IF(CAELS!J15>12%,"2",IF(CAELS!J15>9%,"3",IF(CAELS!J15>6%,"4","5")))) -> 5 | J22: =IF(CAELS!K15>15%,"1",IF(CAELS!K15>12%,"2",IF(CAELS!K15>9%,"3",IF(CAELS!K15>6%,"4","5")))) -> 5 | ... AF22: =IF(CAELS!AG15>15%,"1",IF(CAELS!AG15>12%,"2",IF(CAELS!AG15>9%,"3",IF(CAELS!AG15>6%,"4","5")))) -> 4
C23: =(C19+C20+C21+C22)/4 -> 2.5 | D23: =(D19+D20+D21+D22)/4 -> 4.25 | E23: =(E19+E20+E21+E22)/4 -> 4.25 | F23: =(F19+F20+F21+F22)/4 -> 3.75 | G23: =(G19+G20+G21+G22)/4 -> 2.5 | H23: =(H19+H20+H21+H22)/4 -> 2 | I23: =(I19+I20+I21+I22)/4 -> 3.25 | J23: =(J19+J20+J21+J22)/4 -> 3.75 | ... AF23: =(AF19+AF20+AF21+AF22)/4 -> 2.75
A24: STRUCTURE
A25: NEA | B25: ≤ 10% | C25: =IF(CAELS!D16<6%,"1",IF(CAELS!D16<7%,"2",IF(CAELS!D16<8%,"3",IF(CAELS!D16<10%,"4","5")))) -> 5 | D25: =IF(CAELS!E16<6%,"1",IF(CAELS!E16<7%,"2",IF(CAELS!E16<8%,"3",IF(CAELS!E16<10%,"4","5")))) -> 5 | E25: =IF(CAELS!F16<6%,"1",IF(CAELS!F16<7%,"2",IF(CAELS!F16<8%,"3",IF(CAELS!F16<10%,"4","5")))) -> 5 | F25: =IF(CAELS!G16<6%,"1",IF(CAELS!G16<7%,"2",IF(CAELS!G16<8%,"3",IF(CAELS!G16<10%,"4","5")))) -> 5 | G25: =IF(CAELS!H16<6%,"1",IF(CAELS!H16<7%,"2",IF(CAELS!H16<8%,"3",IF(CAELS!H16<10%,"4","5")))) -> 5 | H25: =IF(CAELS!I16<6%,"1",IF(CAELS!I16<7%,"2",IF(CAELS!I16<8%,"3",IF(CAELS!I16<10%,"4","5")))) -> 5 | I25: =IF(CAELS!J16<6%,"1",IF(CAELS!J16<7%,"2",IF(CAELS!J16<8%,"3",IF(CAELS!J16<10%,"4","5")))) -> 5 | J25: =IF(CAELS!K16<6%,"1",IF(CAELS!K16<7%,"2",IF(CAELS!K16<8%,"3",IF(CAELS!K16<10%,"4","5")))) -> 5 | ... AE25: =IF(CAELS!AF16<6%,"1",IF(CAELS!AF16<7%,"2",IF(CAELS!AF16<8%,"3",IF(CAELS!AF16<10%,"4","5")))) -> 5
A26: LB | B26: ≤ 5% | C26: =IF(CAELS!D17<2%,"1",IF(CAELS!D17<3%,"2",IF(CAELS!D17<4%,"3",IF(CAELS!D17<5%,"4","5")))) -> 5 | D26: =IF(CAELS!E17<2%,"1",IF(CAELS!E17<3%,"2",IF(CAELS!E17<4%,"3",IF(CAELS!E17<5%,"4","5")))) -> 5 | E26: =IF(CAELS!F17<2%,"1",IF(CAELS!F17<3%,"2",IF(CAELS!F17<4%,"3",IF(CAELS!F17<5%,"4","5")))) -> 5 | F26: =IF(CAELS!G17<2%,"1",IF(CAELS!G17<3%,"2",IF(CAELS!G17<4%,"3",IF(CAELS!G17<5%,"4","5")))) -> 5 | G26: =IF(CAELS!H17<2%,"1",IF(CAELS!H17<3%,"2",IF(CAELS!H17<4%,"3",IF(CAELS!H17<5%,"4","5")))) -> 5 | H26: =IF(CAELS!I17<2%,"1",IF(CAELS!I17<3%,"2",IF(CAELS!I17<4%,"3",IF(CAELS!I17<5%,"4","5")))) -> 5 | I26: =IF(CAELS!J17<2%,"1",IF(CAELS!J17<3%,"2",IF(CAELS!J17<4%,"3",IF(CAELS!J17<5%,"4","5")))) -> 5 | J26: =IF(CAELS!K17<2%,"1",IF(CAELS!K17<3%,"2",IF(CAELS!K17<4%,"3",IF(CAELS!K17<5%,"4","5")))) -> 5 | ... AE26: =IF(CAELS!AF17<2%,"1",IF(CAELS!AF17<3%,"2",IF(CAELS!AF17<4%,"3",IF(CAELS!AF17<5%,"4","5")))) -> 5
A27: FITD | B27: ≤ 5% | C27: =IF(CAELS!D18<2%,"1",IF(CAELS!D18<3%,"2",IF(CAELS!D18<4%,"3",IF(CAELS!D18<5%,"4","5")))) -> 1 | D27: =IF(CAELS!E18<2%,"1",IF(CAELS!E18<3%,"2",IF(CAELS!E18<4%,"3",IF(CAELS!E18<5%,"4","5")))) -> 3 | E27: =IF(CAELS!F18<2%,"1",IF(CAELS!F18<3%,"2",IF(CAELS!F18<4%,"3",IF(CAELS!F18<5%,"4","5")))) -> 3 | F27: =IF(CAELS!G18<2%,"1",IF(CAELS!G18<3%,"2",IF(CAELS!G18<4%,"3",IF(CAELS!G18<5%,"4","5")))) -> 3 | G27: =IF(CAELS!H18<2%,"1",IF(CAELS!H18<3%,"2",IF(CAELS!H18<4%,"3",IF(CAELS!H18<5%,"4","5")))) -> 4 | H27: =IF(CAELS!I18<2%,"1",IF(CAELS!I18<3%,"2",IF(CAELS!I18<4%,"3",IF(CAELS!I18<5%,"4","5")))) -> 4 | I27: =IF(CAELS!J18<2%,"1",IF(CAELS!J18<3%,"2",IF(CAELS!J18<4%,"3",IF(CAELS!J18<5%,"4","5")))) -> 5 | J27: =IF(CAELS!K18<2%,"1",IF(CAELS!K18<3%,"2",IF(CAELS!K18<4%,"3",IF(CAELS!K18<5%,"4","5")))) -> 5 | ... AF27: =IF(CAELS!AG18<2%,"1",IF(CAELS!AG18<3%,"2",IF(CAELS!AG18<4%,"3",IF(CAELS!AG18<5%,"4","5")))) -> 5
A28: FICC | B28: ≤ 40% | C28: =IF(CAELS!D19<20%,"1",IF(CAELS!D19<25%,"2",IF(CAELS!D19<30%,"3",IF(CAELS!D19<40%,"4","5")))) -> 1 | D28: =IF(CAELS!E19<20%,"1",IF(CAELS!E19<25%,"2",IF(CAELS!E19<30%,"3",IF(CAELS!E19<40%,"4","5")))) -> 1 | E28: =IF(CAELS!F19<20%,"1",IF(CAELS!F19<25%,"2",IF(CAELS!F19<30%,"3",IF(CAELS!F19<40%,"4","5")))) -> 1 | F28: =IF(CAELS!G19<20%,"1",IF(CAELS!G19<25%,"2",IF(CAELS!G19<30%,"3",IF(CAELS!G19<40%,"4","5")))) -> 1 | G28: =IF(CAELS!H19<20%,"1",IF(CAELS!H19<25%,"2",IF(CAELS!H19<30%,"3",IF(CAELS!H19<40%,"4","5")))) -> 1 | H28: =IF(CAELS!I19<20%,"1",IF(CAELS!I19<25%,"2",IF(CAELS!I19<30%,"3",IF(CAELS!I19<40%,"4","5")))) -> 1 | I28: =IF(CAELS!J19<20%,"1",IF(CAELS!J19<25%,"2",IF(CAELS!J19<30%,"3",IF(CAELS!J19<40%,"4","5")))) -> 1 | J28: =IF(CAELS!K19<20%,"1",IF(CAELS!K19<25%,"2",IF(CAELS!K19<30%,"3",IF(CAELS!K19<40%,"4","5")))) -> 1 | ... AE28: =IF(CAELS!AF19<20%,"1",IF(CAELS!AF19<25%,"2",IF(CAELS!AF19<30%,"3",IF(CAELS!AF19<40%,"4","5")))) -> 1
C29: =(C25+C26+C27+C28)/4 -> 3 | D29: =(D25+D26+D27+D28)/4 -> 3.5 | E29: =(E25+E26+E27+E28)/4 -> 3.5 | F29: =(F25+F26+F27+F28)/4 -> 3.5 | G29: =(G25+G26+G27+G28)/4 -> 3.75 | H29: =(H25+H26+H27+H28)/4 -> 3.75 | I29: =(I25+I26+I27+I28)/4 -> 4 | J29: =(J25+J26+J27+J28)/4 -> 4 | ... AE29: =(AE25+AE26+AE27+AE28)/4 -> 4
A30: FINAL RATING | C30: =(C9+C12+C17+C23)/4 -> 1.8333333 | D30: =(D9+D12+D17+D23)/4 -> 2.375 | E30: =(E9+E12+E17+E23)/4 -> 2.5416667 | F30: =(F9+F12+F17+F23)/4 -> 2.2083333 | G30: =(G9+G12+G17+G23)/4 -> 1.7708333 | H30: =(H9+H12+H17+H23)/4 -> 1.5 | I30: =(I9+I12+I17+I23)/4 -> 2.0625 | J30: =(J9+J12+J17+J23)/4 -> 2.1041667 | ... AE30: =(AE9+AE12+AE17+AE23)/4 -> 1.8333333

Sheet Compliance Status
B2: 2010 Audited | C2: 2011 audited | D2: 2012 Audited | E2: 2013 Audited | F2: 2014 Audited | G2: 2015 Audited | H2: 2016 Audited | I2: 42736 | J2: 42767 | K2: 42795 | L2: 42826 | M2: 42856 | N2: 42887 | O2: 42917 | P2: 42948 | Q2: 42979 | R2: 43009 | S2: 43040 | T2: 43070 | U2: Audited
A3: CORE CAPITAL | B3: =IF(CAELS!D3>10,"Compliant","Non-Compliant") -> Compliant | C3: =IF(CAELS!E3>10,"Compliant","Non-Compliant") -> Compliant | D3: =IF(CAELS!F3>10,"Compliant","Non-Compliant") -> Compliant | E3: =IF(CAELS!G3>10,"Compliant","Non-Compliant") -> Compliant | F3: =IF(CAELS!H3>10,"Compliant","Non-Compliant") -> Compliant | G3: =IF(CAELS!I3>10,"Compliant","Non-Compliant") -> Compliant | H3: =IF(CAELS!J3>10,"Compliant","Non-Compliant") -> Compliant | I3: =IF(CAELS!K3>10,"Compliant","Non-Compliant") -> Compliant | ... U3: =IF(CAELS!W3>10,"Compliant","Non-Compliant") -> Compliant
A4: CCA (Min 10%) | B4: =IF(CAELS!D4>10%,"Compliant","Non-Compliant") -> Compliant | C4: =IF(CAELS!E4>10%,"Compliant","Non-Compliant") -> Compliant | D4: =IF(CAELS!F4>10%,"Compliant","Non-Compliant") -> Compliant | E4: =IF(CAELS!G4>10%,"Compliant","Non-Compliant") -> Compliant | F4: =IF(CAELS!H4>10%,"Compliant","Non-Compliant") -> Compliant | G4: =IF(CAELS!I4>10%,"Compliant","Non-Compliant") -> Compliant | H4: =IF(CAELS!J4>10%,"Compliant","Non-Compliant") -> Compliant | I4: =IF(CAELS!K4>10%,"Compliant","Non-Compliant") -> Compliant | ... U4: =IF(CAELS!W4>10%,"Compliant","Non-Compliant") -> Compliant
A5: ICA (Min 8%) | B5: =IF(CAELS!D6>8%,"Compliant","Non-Compliant") -> Compliant | C5: =IF(CAELS!E6>8%,"Compliant","Non-Compliant") -> Non-Compliant | D5: =IF(CAELS!F6>8%,"Compliant","Non-Compliant") -> Compliant | E5: =IF(CAELS!G6>8%,"Compliant","Non-Compliant") -> Compliant | F5: =IF(CAELS!H6>8%,"Compliant","Non-Compliant") -> Compliant | G5: =IF(CAELS!I6>8%,"Compliant","Non-Compliant") -> Compliant | H5: =IF(CAELS!J6>8%,"Compliant","Non-Compliant") -> Compliant | I5: =IF(CAELS!K6>8%,"Compliant","Non-Compliant") -> Compliant | ... U5: =IF(CAELS!W6>8%,"Compliant","Non-Compliant") -> Compliant
A6: CCD (Min 8%) | B6: =IF(CAELS!D5>8%,"Compliant","Non-Compiant") -> Compliant | C6: =IF(CAELS!E5>8%,"Compliant","Non-Compiant") -> Compliant | D6: =IF(CAELS!F5>8%,"Compliant","Non-Compiant") -> Compliant | E6: =IF(CAELS!G5>8%,"Compliant","Non-Compiant") -> Compliant | F6: =IF(CAELS!H5>8%,"Compliant","Non-Compiant") -> Compliant | G6: =IF(CAELS!I5>8%,"Compliant","Non-Compiant") -> Compliant | H6: =IF(CAELS!J5>8%,"Compliant","Non-Compiant") -> Compliant | I6: =IF(CAELS!K5>8%,"Compliant","Non-Compiant") -> Compliant | ... U6: =IF(CAELS!W5>8%,"Compliant","Non-Compiant") -> Compliant
A7: NPL(5%)
A8: Liquidity(15%) | B8: =IF(CAELS!D12>15%,"Compliant","Non-Compliant") -> Compliant | C8: =IF(CAELS!E12>15%,"Compliant","Non-Compliant") -> Non-Compliant | D8: =IF(CAELS!F12>15%,"Compliant","Non-Compliant") -> Non-Compliant | E8: =IF(CAELS!G12>15%,"Compliant","Non-Compliant") -> Non-Compliant | F8: =IF(CAELS!H12>15%,"Compliant","Non-Compliant") -> Compliant | G8: =IF(CAELS!I12>15%,"Compliant","Non-Compliant") -> Compliant | H8: =IF(CAELS!J12>15%,"Compliant","Non-Compliant") -> Compliant | I8: =IF(CAELS!K12>15%,"Compliant","Non-Compliant") -> Compliant | ... U8: =IF(CAELS!W12>15%,"Compliant","Non-Compliant") -> Compliant
A9: NEA (Max 10%) | B9: =IF(CAELS!D16<10%,"Compliant","Non-Compliant") -> Non-Compliant | C9: =IF(CAELS!E16<10%,"Compliant","Non-Compliant") -> Non-Compliant | D9: =IF(CAELS!F16<10%,"Compliant","Non-Compliant") -> Non-Compliant | E9: =IF(CAELS!G16<10%,"Compliant","Non-Compliant") -> Non-Compliant | F9: =IF(CAELS!H16<10%,"Compliant","Non-Compliant") -> Non-Compliant | G9: =IF(CAELS!I16<10%,"Compliant","Non-Compliant") -> Non-Compliant | H9: =IF(CAELS!J16<10%,"Compliant","Non-Compliant") -> Non-Compliant | I9: =IF(CAELS!K16<10%,"Compliant","Non-Compliant") -> Non-Compliant | ... U9: =IF(CAELS!W16<10%,"Compliant","Non-Compliant") -> Non-Compliant
A10: LB ratio (Max 5%) | B10: =IF(CAELS!D17<5%,"Compliant","Non-Compliant") -> Non-Compliant | C10: =IF(CAELS!E17<5%,"Compliant","Non-Compliant") -> Non-Compliant | D10: =IF(CAELS!F17<5%,"Compliant","Non-Compliant") -> Non-Compliant | E10: =IF(CAELS!G17<5%,"Compliant","Non-Compliant") -> Non-Compliant | F10: =IF(CAELS!H17<5%,"Compliant","Non-Compliant") -> Non-Compliant | G10: =IF(CAELS!I17<5%,"Compliant","Non-Compliant") -> Non-Compliant | H10: =IF(CAELS!J17<5%,"Compliant","Non-Compliant") -> Non-Compliant | I10: =IF(CAELS!K17<5%,"Compliant","Non-Compliant") -> Non-Compliant | ... U10: =IF(CAELS!W17<5%,"Compliant","Non-Compliant") -> Non-Compliant
A11: FITD (Max 5%) | B11: =IF(CAELS!D18<5%,"Compliant","Non-Compliant") -> Compliant | C11: =IF(CAELS!E18<5%,"Compliant","Non-Compliant") -> Compliant | D11: =IF(CAELS!F18<5%,"Compliant","Non-Compliant") -> Compliant | E11: =IF(CAELS!G18<5%,"Compliant","Non-Compliant") -> Compliant | F11: =IF(CAELS!H18<5%,"Compliant","Non-Compliant") -> Compliant | G11: =IF(CAELS!I18<5%,"Compliant","Non-Compliant") -> Compliant | H11: =IF(CAELS!J18<5%,"Compliant","Non-Compliant") -> Non-Compliant | I11: =IF(CAELS!K18<5%,"Compliant","Non-Compliant") -> Non-Compliant | ... U11: =IF(CAELS!W18<5%,"Compliant","Non-Compliant") -> Non-Compliant
A12: FICC (Max 40%) | B12: =IF(CAELS!D19<40%,"Compliant","Non-Compliant") -> Compliant | C12: =IF(CAELS!E19<40%,"Compliant","Non-Compliant") -> Compliant | D12: =IF(CAELS!F19<40%,"Compliant","Non-Compliant") -> Compliant | E12: =IF(CAELS!G19<40%,"Compliant","Non-Compliant") -> Compliant | F12: =IF(CAELS!H19<40%,"Compliant","Non-Compliant") -> Compliant | G12: =IF(CAELS!I19<40%,"Compliant","Non-Compliant") -> Compliant | H12: =IF(CAELS!J19<40%,"Compliant","Non-Compliant") -> Compliant | I12: =IF(CAELS!K19<40%,"Compliant","Non-Compliant") -> Compliant | ... U12: =IF(CAELS!W19<40%,"Compliant","Non-Compliant") -> Compliant
A13: EB ratio (Max 25%) | B13: =IF(CAELS!D14<25%,"Compliant","Non-Compliant") -> Compliant | C13: =IF(CAELS!E14<25%,"Compliant","Non-Compliant") -> Compliant | D13: =IF(CAELS!F14<25%,"Compliant","Non-Compliant") -> Compliant | E13: =IF(CAELS!G14<25%,"Compliant","Non-Compliant") -> Compliant | F13: =IF(CAELS!H14<25%,"Compliant","Non-Compliant") -> Compliant | G13: =IF(CAELS!I14<25%,"Compliant","Non-Compliant") -> Compliant | H13: =IF(CAELS!J14<25%,"Compliant","Non-Compliant") -> Compliant | I13: =IF(CAELS!K14<25%,"Compliant","Non-Compliant") -> Compliant | ... U13: =IF(CAELS!W14<25%,"Compliant","Non-Compliant") -> Compliant
A14: A=S+L | B14: =IF('Evolutive SFP'!B27='Evolutive SFP'!B49,"BALANCING","NOT BALANCING") -> NOT BALANCING | C14: =IF('Evolutive SFP'!C27='Evolutive SFP'!C49,"BALANCING","NOT BALANCING") -> BALANCING | D14: =IF('Evolutive SFP'!D27='Evolutive SFP'!D49,"BALANCING","NOT BALANCING") -> BALANCING | E14: =IF('Evolutive SFP'!E27='Evolutive SFP'!E49,"BALANCING","NOT BALANCING") -> NOT BALANCING | F14: =IF('Evolutive SFP'!F27='Evolutive SFP'!F49,"BALANCING","NOT BALANCING") -> NOT BALANCING | G14: =IF('Evolutive SFP'!G27='Evolutive SFP'!G49,"BALANCING","NOT BALANCING") -> NOT BALANCING | H14: =IF('Evolutive SFP'!H27='Evolutive SFP'!H49,"BALANCING","NOT BALANCING") -> BALANCING | I14: =IF('Evolutive SFP'!I27='Evolutive SFP'!I49,"BALANCING","NOT BALANCING") -> NOT BALANCING | ... U14: =IF('Evolutive SFP'!U27='Evolutive SFP'!U49,"BALANCING","NOT BALANCING") -> NOT BALANCING

Sheet CashFlow Stmnt
A1: STATEMENT OF CASHFLOWS FOR THE YEAR ENDED 31ST DECEMBER 2015
B2: Audited -2017 | C2: Audited -2018
A3: Cash flows from operating activities
A4: Interest receipts | B4: 134278378 | C4: 1.5455347e+08
A5: Non interest receipts
A6: Interest Payments | B6: -44018009 | C6: -44466446
A7: Payment to employees and suppliers | B7: -70742652 | C7: -72364594
A8: Prior year adjustment | B8: 362 | C8: -7448.08
A9: (Increase)/Decrease in Operating assets | B9: =SUM(B4:B8) -> 19518079 | C9: =SUM(C4:C8) -> 37714981
A10: Net loans to members | B10: -83606522 | C10: -86869973
A11: Recievables and prepayments
A12: Trade and Other Receivables | B12: 17884294 | C12: 6244962.5
A13: Other Liabilities
A14: Other Assets
A15: Short term investments
A16: Increase/(Decrease) in Operating liabilities | B16: =SUM(B10:B15) -> -65722228 | C16: =SUM(C10:C15) -> -80625010
A17: Deposits from members | B17: 42371444 | C17: 52242174
A18: Trade and Accrued Expenses | B18: 28369195 | C18: 9025708.6
A19: Sundry Creditors
A20: Net cashflow from operating activities before income taxes | B20: =B9+B16+B17+B18+B19 -> 24536490 | C20: =C9+C16+C17+C18+C19 -> 18357854
A21: Income tax paid | C21: 2447067
A22: Net Cash from Operating activities | B22: =B20-B21 -> 24536490 | C22: =C20-C21 -> 15910787 | D22: 100000
A24: Cashflow from investing activities
A25: Purchase of Property and equipment | B25: -2424847 | C25: -815717.95
A26: Purchase of intangible assets | B26: -6213468 | C26: -127413
A27: Increase in Other Assets
A28: Purchase of Investment Securities | B28: -4351532 | C28: -4580444.5
A29: Dividends Received
A30: Net Cash from investing activities | B30: =SUM(B25:B29) -> -12989847 | C30: =SUM(C25:C29) -> -5523575.5
A32: Cashflow from financing activities
A33: Share capital contributions | B33: 1651685 | C33: 1235143
A34: Proceeds from long-term borrowings | B34: 0 | C34: 0
A35: Prior Year Adjustments
A36: Payment of Sinking Fund
A37: Repayments of long term borrowings
A38: Dividend paid
A39: Net cash from financing activities | B39: =SUM(B33:B38) -> 1651685 | C39: =SUM(C33:C38) -> 1235143
A40: Net (Decrease)/Increase in cash and cash equivalent | B40: =B22+B30+B39 -> 13198328 | C40: =C22+C30+C39 -> 11622354
A41: Cash and cash equivalent at the beginning of the year | B41: 36146766 | C41: 49345094
A42: Cash and cash equivalent at the end of the year | B42: =SUM(B40:B41) -> 49345094 | C42: =SUM(C40:C41) -> 60967448

Sheet Sheet1
D4: 2013 | E4: 2014 | F4: 2015 | G4: 2016 | H4: 2017 | I4: 43101 | J4: 43132 | K4: 43160 | L4: 43191 | M4: 43221 | N4: 43252 | O4: 43282 | P4: 43313 | Q4: 43344 | V4: Annual Average growth
C5: FINANCIAL INCOME | D5: 93967038 | E5: 97400688 | F5: 109849160 | G5: 121408969 | H5: 134278379 | I5: 9796657.1 | J5: 18963773 | K5: 29749222 | L5: 41069758 | M5: 51906602 | N5: 72483894 | O5: 83600074 | P5: 97549834 | Q5: 1.0908422e+08 | S5: =(F5-E5)/E5 -> 0.12780682 | T5: =(G5-F5)/F5 -> 0.10523348 | U5: =(H5-G5)/G5 -> 0.10600049 | V5: =(U5+T5+S5)/3 -> 0.11301359
C7: OPERATING EXPENSES | D7: =SUM(D8:D12) -> 38145978 | E7: =SUM(E8:E12) -> 38649289 | F7: =SUM(F8:F12) -> 48225009 | G7: =SUM(G8:G12) -> 65005570 | H7: =SUM(H8:H12) -> 74000365 | I7: =SUM(I8:I12) -> 3725614.6 | J7: =SUM(J8:J12) -> 6594169 | K7: =SUM(K8:K12) -> 13706345 | ... Q7: =SUM(Q8:Q12) -> 44806635 | S7: =(F7-E7)/E7 -> 0.24775928 | T7: =(G7-F7)/F7 -> 0.34796387 | U7: =(H7-G7)/G7 -> 0.1383696 | V7: =(U7+T7+S7)/3 -> 0.24469759
C8: Personnel Expenses | D8: 11911818 | E8: 13893168 | F8: 15300933 | G8: 16492855 | H8: 19184551 | I8: 1300252.2 | J8: 2604604 | K8: 4594615.8 | L8: 9853087.3 | M8: 11675982 | N8: 13503510 | O8: 14968801 | P8: 16552869 | Q8: 18022759 | S8: =(F8-E8)/E8 -> 0.10132786 | T8: =(G8-F8)/F8 -> 0.077898648 | U8: =(H8-G8)/G8 -> 0.16320376 | V8: =(U8+T8+S8)/3 -> 0.11414342
C9: Governance Expenses | D9: 5415126 | E9: 6469083 | F9: 7582971 | G9: 7969188 | H9: 9863038 | I9: 292730 | J9: 743850 | K9: 2234704 | L9: 3331799 | M9: 3780464 | N9: 4073029 | O9: 5309894 | P9: 6690159 | Q9: 7399049 | S9: =(F9-E9)/E9 -> 0.17218638 | T9: =(G9-F9)/F9 -> 0.050932148 | U9: =(H9-G9)/G9 -> 0.23764655 | V9: =(U9+T9+S9)/3 -> 0.15358836
C10: Marketing Expenses | D10: 1361305 | E10: 1465539 | F10: 3168809 | G10: 2675207 | H10: 2687767 | I10: 3840 | J10: 28500 | K10: 298040 | L10: 517180 | M10: 729240 | N10: 968315 | O10: 1498855 | P10: 1900780 | Q10: 2042140 | S10: =(F10-E10)/E10 -> 1.162214 | T10: =(G10-F10)/F10 -> -0.15576893 | U10: =(H10-G10)/G10 -> 0.0046949638 | V10: =(U10+T10+S10)/3 -> 0.33704669
C11: Depreciation and Amortization Charges | D11: 3005880.1 | E11: 2794665 | F11: 2777823 | G11: 2791594 | H11: 3576056 | I11: 335425.05 | J11: 670850.1 | K11: 1006275.2 | L11: 1216326.7 | M11: 1677125.2 | N11: 2012550.3 | O11: 2347975.4 | P11: 2683400.4 | Q11: 3018825.5 | S11: =(F11-E11)/E11 -> -0.0060264826 | T11: =(G11-F11)/F11 -> 0.0049574793 | U11: =(H11-G11)/G11 -> 0.28100863 | V11: =(U11+T11+S11)/3 -> 0.093313208
C12: Administrative Expenses | D12: 16451849 | E12: 14026834 | F12: 19394473 | G12: 35076726 | H12: 38688953 | I12: 1793367.4 | J12: 2546364.9 | K12: 5572709.9 | L12: 7228816.7 | M12: 8282442.2 | N12: 8818516.9 | O12: 10728212 | P12: 13076305 | Q12: 14323861 | S12: =(F12-E12)/E12 -> 0.38266932 | T12: =(G12-F12)/F12 -> 0.80859392 | U12: =(H12-G12)/G12 -> 0.10298073 | V12: =(U12+T12+S12)/3 -> 0.43141466
C14: TOTAL EXPENSES | D14: 78406499 | E14: 78276362 | F14: 87269323 | G14: 112180671 | H14: 119706880 | I14: 9357386.9 | J14: 14627441 | K14: 23926692 | L14: 34876609 | M14: 41184871 | N14: 47389634 | O14: 56008586 | P14: 65110895 | Q14: 73101825 | S14: =(F14-E14)/E14 -> 0.11488731 | T14: =(G14-F14)/F14 -> 0.28545366 | U14: =(H14-G14)/G14 -> 0.067090069 | V14: =(U14+T14+S14)/3 -> 0.15581035
C16: % of Total Income
C17: Personnel Expenses | D17: =D8/D5 -> 0.12676592 | E17: =E8/E5 -> 0.14263932 | F17: =F8/F5 -> 0.1392904 | G17: =G8/G5 -> 0.13584544 | H17: =H8/H5 -> 0.14287148 | I17: =I8/I5 -> 0.13272407 | J17: =J8/J5 -> 0.1373463 | K17: =K8/K5 -> 0.15444491 | ... Q17: =Q8/Q5 -> 0.16521875
C18: Governance Expenses | D18: =D9/D5 -> 0.057627931 | E18: =E9/E5 -> 0.066417221 | F18: =F9/F5 -> 0.06903076 | G18: =G9/G5 -> 0.065639203 | H18: =H9/H5 -> 0.073452168 | I18: =I9/I5 -> 0.029880601 | J18: =J9/J5 -> 0.03922479 | K18: =K9/K5 -> 0.075118065 | ... Q18: =Q9/Q5 -> 0.067828773
C19: Marketing Expenses | D19: =D10/D5 -> 0.014487048 | E19: =E10/E5 -> 0.015046495 | F19: =F10/F5 -> 0.028846912 | G19: =G10/G5 -> 0.022034674 | H19: =H10/H5 -> 0.02001638 | I19: =I10/I5 -> 0.00039197044 | J19: =J10/J5 -> 0.0015028655 | K19: =K10/K5 -> 0.010018413 | ... Q19: =Q10/Q5 -> 0.018720764
C20: Depreciation and Amortization Charges | D20: =D11/D5 -> 0.031988665 | E20: =E11/E5 -> 0.028692456 | F20: =F11/F5 -> 0.025287613 | G20: =G11/G5 -> 0.022993309 | H20: =H11/H5 -> 0.026631659 | I20: =I11/I5 -> 0.034238725 | J20: =J11/J5 -> 0.03537535 | K20: =K11/K5 -> 0.033825259 | ... Q20: =Q11/Q5 -> 0.027674263
C21: Administrative Expenses | D21: =D12/D5 -> 0.17508106 | E21: =E12/E5 -> 0.14401165 | F21: =F12/F5 -> 0.1765555 | G21: =G12/G5 -> 0.2889138 | H21: =H12/H5 -> 0.28812496 | I21: =I12/I5 -> 0.18305911 | J21: =J12/J5 -> 0.13427523 | K21: =K12/K5 -> 0.18732288 | ... Q21: =Q12/Q5 -> 0.13131011
C23: % of Operating Expenses
C24: Personnel Expenses | D24: =D8/D7 -> 0.31226931 | E24: =E8/E7 -> 0.35946762 | F24: =F8/F7 -> 0.31728212 | G24: =G8/G7 -> 0.25371449 | H24: =H8/H7 -> 0.25924941 | I24: =I8/I7 -> 0.34900341 | J24: =J8/J7 -> 0.39498593 | K24: =K8/K7 -> 0.33521817 | ... Q24: =Q8/Q7 -> 0.40223416
C25: Governance Expenses | D25: =D9/D7 -> 0.14195798 | E25: =E9/E7 -> 0.16737909 | F25: =F9/F7 -> 0.15724146 | G25: =G9/G7 -> 0.12259239 | H25: =H9/H7 -> 0.13328364 | I25: =I9/I7 -> 0.078572271 | J25: =J9/J7 -> 0.11280421 | K25: =K9/K7 -> 0.16304157 | ... Q25: =Q9/Q7 -> 0.16513289
C26: Marketing Expenses | D26: =D10/D7 -> 0.035686724 | E26: =E10/E7 -> 0.037918912 | F26: =F10/F7 -> 0.065708832 | G26: =G10/G7 -> 0.041153504 | H26: =H10/H7 -> 0.036320997 | I26: =I10/I7 -> 0.0010307024 | J26: =J10/J7 -> 0.0043220002 | K26: =K10/K7 -> 0.021744674 | ... Q26: =Q10/Q7 -> 0.045576732
C27: Depreciation and Amortization Charges | D27: =D11/D7 -> 0.078799399 | E27: =E11/E7 -> 0.072308316 | F27: =F11/F7 -> 0.057601296 | G27: =G11/G7 -> 0.04294392 | H27: =H11/H7 -> 0.048324843 | I27: =I11/I7 -> 0.090032138 | J27: =J11/J7 -> 0.10173383 | K27: =K11/K7 -> 0.073416739 | ... Q27: =Q11/Q7 -> 0.067374519
C28: Administrative Expenses | D28: =D12/D7 -> 0.43128659 | E28: =E12/E7 -> 0.36292606 | F28: =F12/F7 -> 0.40216629 | G28: =G12/G7 -> 0.5395957 | H28: =H12/H7 -> 0.52282111 | I28: =I12/I7 -> 0.48136148 | J28: =J12/J7 -> 0.38615403 | K28: =K12/K7 -> 0.40657885 | ... Q28: =Q12/Q7 -> 0.3196817
C30: % of Total Expenses
C31: Personnel Expenses | D31: =D8/D14 -> 0.15192386 | E31: =E8/E14 -> 0.17748868 | F31: =F8/F14 -> 0.17533003 | G31: =G8/G14 -> 0.14702047 | H31: =H8/H14 -> 0.16026273 | I31: =I8/I14 -> 0.13895463 | J31: =J8/J14 -> 0.17806286 | K31: =K8/K14 -> 0.19202887 | ... Q31: =Q8/Q14 -> 0.24654321
C32: Governance Expenses | D32: =D9/D14 -> 0.06906476 | E32: =E9/E14 -> 0.082644145 | F32: =F9/F14 -> 0.086891599 | G32: =G9/G14 -> 0.071038869 | H32: =H9/H14 -> 0.082393243 | I32: =I9/I14 -> 0.031283306 | J32: =J9/J14 -> 0.050853049 | K32: =K9/K14 -> 0.093397949 | ... Q32: =Q9/Q14 -> 0.10121565
C33: Marketing Expenses | D33: =D10/D14 -> 0.017362145 | E33: =E10/E14 -> 0.018722625 | F33: =F10/F14 -> 0.036310686 | G33: =G10/G14 -> 0.023847308 | H33: =H10/H14 -> 0.022452903 | I33: =I10/I14 -> 0.00041037098 | J33: =J10/J14 -> 0.0019483927 | K33: =K10/K14 -> 0.012456381 | ... Q33: =Q10/Q14 -> 0.027935554
C34: Depreciation and Amortization Charges | D34: =D11/D14 -> 0.03833713 | E34: =E11/E14 -> 0.035702541 | F34: =F11/F14 -> 0.031830463 | G34: =G11/G14 -> 0.024884804 | H34: =H11/H14 -> 0.029873438 | I34: =I11/I14 -> 0.035846017 | J34: =J11/J14 -> 0.045862436 | K34: =K11/K14 -> 0.042056592 | ... Q34: =Q11/Q14 -> 0.041296171
C35: Administrative Expenses | D35: =D12/D14 -> 0.20982762 | E35: =E12/E14 -> 0.17919629 | F35: =F12/F14 -> 0.22223701 | G35: =G12/G14 -> 0.31268066 | H35: =H12/H14 -> 0.32319741 | I35: =I12/I14 -> 0.19165258 | J35: =J12/J14 -> 0.17408136 | K35: =K12/K14 -> 0.23290766 | ... Q35: =Q12/Q14 -> 0.19594396
