Workbook
Name BALANCE1_LDA01: '[1]Financial Statements'!$E$112
Name BALANCE1_LDA12: '[1]Financial Statements'!$E$123
Name BALANCE2_LDA01: '[1]Financial Statements'!$F$112
Name BALANCE2_LDA12: '[1]Financial Statements'!$F$123
Name BALANCE3_LDA01: '[1]Financial Statements'!$G$112
Name BALANCE3_LDA12: '[1]Financial Statements'!$G$123
Name BALANCE4_LDA01: '[1]Financial Statements'!$H$112
Name BALANCE4_LDA12: '[1]Financial Statements'!$H$123
Name BALANCE5_LDA01: '[1]Financial Statements'!$I$112
Name BALANCE5_LDA12: '[1]Financial Statements'!$I$123
Name BALANCE6_LDA01: '[1]Financial Statements'!$J$112
Name BALANCE6_LDA12: '[1]Financial Statements'!$J$123
Name NotApplicable: 'Prudential Ratios'!#REF!
Name PEARLS1_LA002: '[1]Financial Statements'!$E$280
Name PEARLS1_LE008: '[1]Financial Statements'!$E$275
Name PEARLS1_LE009: '[1]Financial Statements'!$E$276
Name PEARLS1_LR001: '[1]Financial Statements'!$E$282
Name PEARLS1_LR005: '[1]Financial Statements'!$E$286
Name PEARLS1_LR006: '[1]Financial Statements'!$E$287
Name PEARLS1_LR007: '[1]Financial Statements'!$E$288
Name PEARLS1_LR009: '[1]Financial Statements'!$E$290
Name PEARLS1_LS001: '[1]Financial Statements'!$E$298
Name PEARLS1_LS005: '[1]Financial Statements'!$E$302
Name PEARLS1_LS011: '[1]Financial Statements'!$E$308
Name PEARLS2_LA002: '[1]Financial Statements'!$F$280
Name PEARLS2_LE008: '[1]Financial Statements'!$F$275
Name PEARLS2_LE009: '[1]Financial Statements'!$F$276
Name PEARLS2_LR001: '[1]Financial Statements'!$F$282
Name PEARLS2_LR005: '[1]Financial Statements'!$F$286
Name PEARLS2_LR006: '[1]Financial Statements'!$F$287
Name PEARLS2_LR007: '[1]Financial Statements'!$F$288
Name PEARLS2_LR009: '[1]Financial Statements'!$F$290
Name PEARLS2_LS001: '[1]Financial Statements'!$F$298
Name PEARLS2_LS005: '[1]Financial Statements'!$F$302
Name PEARLS2_LS010: '[1]Financial Statements'!$F$307
Name PEARLS2_LS011: '[1]Financial Statements'!$F$308
Name PEARLS3_LA002: '[1]Financial Statements'!$G$280
Name PEARLS3_LE008: '[1]Financial Statements'!$G$275
Name PEARLS3_LE009: '[1]Financial Statements'!$G$276
Name PEARLS3_LR001: '[1]Financial Statements'!$G$282
Name PEARLS3_LR005: '[1]Financial Statements'!$G$286
Name PEARLS3_LR006: '[1]Financial Statements'!$G$287
Name PEARLS3_LR007: '[1]Financial Statements'!$G$288
Name PEARLS3_LR009: '[1]Financial Statements'!$G$290
Name PEARLS3_LS001: '[1]Financial Statements'!$G$298
Name PEARLS3_LS005: '[1]Financial Statements'!$G$302
Name PEARLS3_LS010: '[1]Financial Statements'!$G$307
Name PEARLS3_LS011: '[1]Financial Statements'!$G$308
Name PEARLS4_LA002: '[1]Financial Statements'!$H$280
Name PEARLS4_LE008: '[1]Financial Statements'!$H$275
Name PEARLS4_LE009: '[1]Financial Statements'!$H$276
Name PEARLS4_LR001: '[1]Financial Statements'!$H$282
Name PEARLS4_LR005: '[1]Financial Statements'!$H$286
Name PEARLS4_LR006: '[1]Financial Statements'!$H$287
Name PEARLS4_LR007: '[1]Financial Statements'!$H$288
Name PEARLS4_LR009: '[1]Financial Statements'!$H$290
Name PEARLS4_LS001: '[1]Financial Statements'!$H$298
Name PEARLS4_LS005: '[1]Financial Statements'!$H$302
Name PEARLS4_LS010: '[1]Financial Statements'!$H$307
Name PEARLS4_LS011: '[1]Financial Statements'!$H$308

Sheet SFP
A1: MAGEREZA SACCO SOCIETY
A2: STATEMENT OF FINANCIAL POSITION | N2: Approved | Z2: Restated 2021 | AA2: Variances btw
B3: january | C3: february | D3: march | E3: april | F3: may | G3: june | H3: july | I3: august | J3: september | K3: october | L3: november | M3: december | N3: Audited 2021 | O3: Feb | P3: Mar | Q3: Apr | R3: May | S3: Jun | T3: Jul | U3: Aug | V3: Sep | W3: Oct | X3: Nov | Y3: Dec | Z3: by the Auditor | AA3: Audited & restated 2021 | AB3: Audited 2022 | AC3: 44927 | AD3: 44958 | AE3: 44986 | AF3: 45017 | AG3: 45047 | AH3: 45078 | AI3: 45108 | AJ3: 45139 | AK3: 45170 | AL3: 45200 | AM3: 45231
A4: Cash & Cash Equivalent | B4: =SUM(B5:B6) -> 252652851 | C4: =SUM(C5:C6) -> 2.4646583e+08 | D4: =SUM(D5:D6) -> 2.8979676e+08 | E4: =SUM(E5:E6) -> 1.3139564e+08 | F4: =SUM(F5:F6) -> 4.7950328e+08 | G4: =SUM(G5:G6) -> 7.8374847e+08 | H4: =SUM(H5:H6) -> 4.8954418e+08 | I4: =SUM(I5:I6) -> 7.1282297e+08 | ... Z4: =SUM(Z5:Z6) -> 817345916 | AA4: =N4-Z4 -> 0.45999992 | AB4: =SUM(AB5:AB6) -> 576228117 | AC4: =SUM(AC5:AC6) -> 4.7511467e+08 | AD4: =SUM(AD5:AD6) -> 82486263 | AE4: =SUM(AE5:AE6) -> 2.2994973e+08 | AF4: =SUM(AF5:AF6) -> -1.8637487e+08 | AG4: =SUM(AG5:AG6) -> -1.9792849e+08 | AH4: =SUM(AH5:AH6) -> 4.576633e+08 | AI4: =SUM(AI5:AI6) -> 2.0244814e+08 | ... AM4: =SUM(AM5:AM6) -> 0
A5: Cash in hand | B5: 18470331 | C5: 16028065 | D5: 20227208 | E5: 15726577 | F5: 18747147 | G5: 16139622 | H5: 15034465 | I5: 22294319 | J5: 21418992 | L5: 20328685 | M5: 25406966 | N5: ='[2]Notes 5'!$F$28 -> 23061474 | O5: 29603301 | P5: 23865542 | Q5: 18204276 | R5: 21126692 | S5: 31702211 | T5: 19914594 | U5: 27118225 | V5: 28534340 | W5: 23705535 | X5: 30336093 | Y5: 44433202 | Z5: 23061474 | AA5: =N5-Z5 -> 0 | AB5: 42524958 | AC5: 12531247 | AD5: 35728786 | AE5: 29311432 | AF5: 26645935 | AG5: 20532897 | AH5: 22975898 | AI5: 31097132 | AJ5: 22037542
A6: Cash at bank | B6: 234182520 | C6: 2.3043776e+08 | D6: 2.6956955e+08 | E6: 1.1566906e+08 | F6: 4.6075614e+08 | G6: 7.6760885e+08 | H6: 4.7450971e+08 | I6: 6.9052865e+08 | J6: 4.4602846e+08 | L6: 7.169999e+08 | M6: 7.6036042e+08 | N6: ='[2]Notes 5'!$F$24 -> 7.9428444e+08 | O6: 5.203664e+08 | P6: 6.4949863e+08 | Q6: 1.6956189e+08 | R6: 4.0283222e+08 | S6: 4.7965176e+08 | T6: 4.7530917e+08 | U6: 3.3368232e+08 | V6: 6.0174176e+08 | W6: 3.9919773e+08 | X6: 3.200292e+08 | Y6: 4.9266075e+08 | Z6: 794284442 | AA6: =N6-Z6 -> 0.45999992 | AB6: 533703159 | AC6: 4.6258343e+08 | AD6: 46757478 | AE6: 2.006383e+08 | AF6: -2.1302081e+08 | AG6: -2.1846139e+08 | AH6: 4.346874e+08 | AI6: 1.7135101e+08 | AJ6: 1.8780237e+08
A7: Prepayments & Sundry Receivables | B7: 1.7805848e+09 | C7: 1.8771324e+09 | D7: 1.9104938e+09 | E7: 1.8974844e+09 | F7: 1.8620809e+09 | G7: 1.7166405e+09 | H7: 1.9175792e+09 | I7: 1.6453646e+09 | J7: 1.8845508e+09 | L7: 1.6378464e+09 | M7: 1.642468e+09 | N7: 1784001840 | O7: 0 | P7: 1.678583e+09 | Q7: 1.9955001e+09 | R7: 1.8082348e+09 | S7: 1.7831519e+09 | T7: 1.7969142e+09 | U7: 2.0108035e+09 | V7: 1.7738072e+09 | W7: 2.002785e+09 | X7: 2.0269788e+09 | Y7: 1.819218e+09 | Z7: 1684959514 | AA7: =N7-Z7 -> 99042326 | AB7: 1700774183 | AC7: 1.4577114e+09 | AD7: 1.8347652e+09 | AE7: 1.7864694e+09 | AF7: 2.1464706e+09 | AG7: 2.0513582e+09 | AH7: 1.8177274e+09 | AI7: 0 | AJ7: 2.1508153e+09
A8: Financial Investments | B8: =SUM(B9:B12) -> 486426946 | C8: =SUM(C9:C12) -> 4.183132e+08 | D8: =SUM(D9:D12) -> 4.183132e+08 | E8: =SUM(E9:E12) -> 4.183132e+08 | F8: =SUM(F9:F12) -> 4.183132e+08 | G8: =SUM(G9:G12) -> 4.183132e+08 | H8: =SUM(H9:H12) -> 4.183132e+08 | I8: =SUM(I9:I12) -> 4.183132e+08 | ... Z8: =SUM(Z9:Z12) -> 432468041 | AA8: =N8-Z8 -> -0.19999999 | AB8: =SUM(AB9:AB12) -> 423139325 | AC8: =SUM(AC9:AC12) -> 4.2372582e+08 | AD8: =SUM(AD9:AD12) -> 4.2372582e+08 | AE8: =SUM(AE9:AE12) -> 4.2372582e+08 | AF8: =SUM(AF9:AF12) -> 4.2372582e+08 | AG8: =SUM(AG9:AG12) -> 4.2372582e+08 | AH8: =SUM(AH9:AH12) -> 4.2372582e+08 | AI8: =SUM(AI9:AI12) -> 4.2313932e+08 | ... AM8: =SUM(AM9:AM12) -> 0
A9: Government Securities - Treasury Bills/bonds, | B9: 0 | C9: 0 | D9: 0 | E9: 0 | F9: 0 | G9: 0 | H9: 0 | I9: 0 | J9: 0 | L9: 0 | M9: 0 | N9: ='[2]Note 7'!$F$14 -> 23365868 | O9: 0 | P9: 0 | Q9: 0 | R9: 0 | S9: 0 | T9: 0 | U9: 0 | V9: 0 | W9: 0 | X9: 0 | Y9: 0 | AA9: =N9-Z9 -> 23365868 | AC9: 0 | AD9: 0 | AE9: 0 | AF9: 0 | AG9: 0 | AH9: 0 | AI9: 0 | AJ9: 0
A10: Other Securities - Commercial papers/Bonds | B10: 0 | C10: 0 | D10: 0 | E10: 0 | F10: 0 | G10: 0 | H10: 0 | I10: 0 | J10: 0 | L10: 0 | M10: 0 | O10: 0 | P10: 0 | Q10: 0 | R10: 0 | S10: 0 | T10: 0 | U10: 0 | V10: 0 | W10: 0 | X10: 0 | Y10: 0 | AA10: =N10-Z10 -> 0 | AC10: 0 | AD10: 0 | AE10: 0 | AF10: 0 | AG10: 0 | AH10: 0 | AI10: 0 | AJ10: 0
A11: Balances with other SACCO Societies | B11: 0 | C11: 0 | D11: 0 | E11: 0 | F11: 0 | G11: 0 | H11: 0 | I11: 0 | J11: 0 | L11: 0 | M11: 0 | O11: 0 | P11: 0 | Q11: 0 | R11: 0 | S11: 0 | T11: 0 | U11: 0 | V11: 0 | W11: 0 | X11: 0 | Y11: 0 | Z11: 409102173 | AA11: =N11-Z11 -> -409102173 | AB11: 400359957 | AC11: 0 | AD11: 0 | AE11: 0 | AF11: 0 | AG11: 0 | AH11: 0 | AI11: 0 | AJ11: 0
A12: Investments in companies - shares/stocks | B12: 486426946 | C12: 4.183132e+08 | D12: 4.183132e+08 | E12: 4.183132e+08 | F12: 4.183132e+08 | G12: 4.183132e+08 | H12: 4.183132e+08 | I12: 4.183132e+08 | J12: 4.183132e+08 | L12: 4.183132e+08 | M12: 4.183132e+08 | N12: ='[2]Note 7'!$F$20 -> 409102173 | O12: 4.183132e+08 | P12: 4.183132e+08 | Q12: 4.183132e+08 | R12: 4.183132e+08 | S12: 4.183132e+08 | T12: 4.183132e+08 | U12: 4.183132e+08 | V12: 4.183132e+08 | W12: 4.183132e+08 | X12: 4.183132e+08 | Y12: 4.183132e+08 | Z12: 23365868 | AA12: =N12-Z12 -> 385736305 | AB12: 22779368 | AC12: 4.2372582e+08 | AD12: 4.2372582e+08 | AE12: 4.2372582e+08 | AF12: 4.2372582e+08 | AG12: 4.2372582e+08 | AH12: 4.2372582e+08 | AI12: 4.2313932e+08 | AJ12: 4.2313932e+08
A13: Net Loan Portfolio | B13: =B14-B15 -> 3.3035756e+09 | C13: =C14-C15 -> 3.3794646e+09 | D13: =D14-D15 -> 3.4096313e+09 | E13: =E14-E15 -> 3.3737607e+09 | F13: =F14-F15 -> 3.3803658e+09 | G13: =G14-G15 -> 3.3723653e+09 | H13: =H14-H15 -> 3.4017131e+09 | I13: =I14-I15 -> 3.4401109e+09 | ... Z13: =Z14-Z15 -> 3432988413 | AA13: =N13-Z13 -> 27000000 | AB13: =AB14-AB15 -> 3681831574 | AC13: =AC14-AC15 -> 3.9317585e+09 | AD13: =AD14-AD15 -> 4.0157359e+09 | AE13: =AE14-AE15 -> 4.0616635e+09 | AF13: =AF14-AF15 -> 4.1165596e+09 | AG13: =AG14-AG15 -> 4.3469229e+09 | AH13: =AH14-AH15 -> 4.4442286e+09 | AI13: =AI14-AI15 -> 4.3827476e+09 | ... AM13: =AM14-AM15 -> 0
A14: Gross Loan Portfolio | B14: 3.4379818e+09 | C14: 3.5287339e+09 | D14: 3.5589006e+09 | E14: 3.5230299e+09 | F14: 3.529635e+09 | G14: 3.5216345e+09 | H14: 3.5509824e+09 | I14: 3.5893802e+09 | J14: 3.6260463e+09 | L14: 3.6651374e+09 | M14: 3.6621608e+09 | N14: 3614762641 | O14: 3.7163566e+09 | P14: 3.7370628e+09 | Q14: 3.6753057e+09 | R14: 3.668167e+09 | S14: 3.6660194e+09 | T14: 3.6919383e+09 | U14: 3.667341e+09 | V14: 3.6853384e+09 | W14: 3.7238451e+09 | X14: 3.9271114e+09 | Y14: 3.9533164e+09 | Z14: 3592762641 | AA14: =N14-Z14 -> 22000000 | AB14: 3858442217 | AC14: 4.0915327e+09 | AD14: 4.1755101e+09 | AE14: 4.2214377e+09 | AF14: 4.2931702e+09 | AG14: 4.5066972e+09 | AH14: 4.6040028e+09 | AI14: 4.5593582e+09 | AJ14: 4627367940
A15: Allowance for Loan Loss | B15: 134406232 | C15: 1.4926925e+08 | D15: 1.4926925e+08 | E15: 1.4926925e+08 | F15: 1.4926925e+08 | G15: 1.4926925e+08 | H15: 1.4926925e+08 | I15: 1.4926925e+08 | J15: 1.4926925e+08 | L15: 1.4926925e+08 | M15: 1.4926925e+08 | N15: 154774228 | O15: 1.4926925e+08 | P15: 70086567 | Q15: 70086567 | R15: 70086567 | S15: 70086567 | T15: 70086567 | U15: 70086567 | V15: 70086567 | W15: 70086567 | X15: 70086567 | Y15: 70086567 | Z15: 159774228 | AA15: =N15-Z15 -> -5000000 | AB15: 176610643 | AC15: 1.5977423e+08 | AD15: 1.5977423e+08 | AE15: 1.5977423e+08 | AF15: 176610643 | AG15: 1.5977423e+08 | AH15: 1.5977423e+08 | AI15: 1.7661064e+08 | AJ15: 1.7661064e+08
A16: Accounts Receivables | B16: =SUM(B17:B19) -> 0 | C16: =SUM(C17:C19) -> 0 | D16: =SUM(D17:D19) -> 0 | E16: =SUM(E17:E19) -> 0 | F16: =SUM(F17:F19) -> 0 | G16: =SUM(G17:G19) -> 0 | H16: =SUM(H17:H19) -> 0 | I16: =SUM(I17:I19) -> 0 | J16: =SUM(J17:J19) -> 0 | L16: =SUM(L17:L19) -> 0 | M16: =SUM(M17:M19) -> 0 | N16: =SUM(N17:N19) -> 12781984 | O16: =SUM(O17:O19) -> 0 | P16: =SUM(P17:P19) -> 0 | Q16: =SUM(Q17:Q19) -> 0 | R16: =SUM(R17:R19) -> 0 | S16: =SUM(S17:S19) -> 0 | ... Z16: =SUM(Z17:Z19) -> 12781984 | AA16: =N16-Z16 -> 0 | AB16: =SUM(AB17:AB19) -> 9983559 | AC16: =SUM(AC17:AC19) -> 0 | AD16: =SUM(AD17:AD19) -> 0 | AE16: =SUM(AE17:AE19) -> 0 | AF16: =SUM(AF17:AF19) -> 0 | AG16: =SUM(AG17:AG19) -> 0 | AH16: =SUM(AH17:AH19) -> 0 | AI16: =SUM(AI17:AI19) -> 0 | ... AM16: =SUM(AM17:AM19) -> 0
A17: Tax Recoverable | B17: 0 | C17: 0 | D17: 0 | E17: 0 | F17: 0 | G17: 0 | H17: 0 | I17: 0 | J17: 0 | L17: 0 | M17: 0 | O17: 0 | P17: 0 | Q17: 0 | R17: 0 | S17: 0 | T17: 0 | U17: 0 | V17: 0 | W17: 0 | X17: 0 | Y17: 0 | AA17: =N17-Z17 -> 0 | AC17: 0 | AD17: 0 | AE17: 0 | AF17: 0 | AG17: 0 | AH17: 0 | AI17: 0 | AJ17: 0 | AK17: 0
A18: Deferred Tax Assets | B18: 0 | C18: 0 | D18: 0 | E18: 0 | F18: 0 | G18: 0 | H18: 0 | I18: 0 | J18: 0 | L18: 0 | M18: 0 | N18: 12781984 | O18: 0 | P18: 0 | Q18: 0 | R18: 0 | S18: 0 | T18: 0 | U18: 0 | V18: 0 | W18: 0 | X18: 0 | Y18: 0 | Z18: 12781984 | AA18: =N18-Z18 -> 0 | AB18: 9983559 | AC18: 0 | AD18: 0 | AE18: 0 | AF18: 0 | AG18: 0 | AH18: 0 | AI18: 0 | AJ18: 0 | AK18: 0
A19: Retirement Benefit Assets | B19: 0 | C19: 0 | D19: 0 | E19: 0 | F19: 0 | G19: 0 | H19: 0 | I19: 0 | J19: 0 | L19: 0 | M19: 0 | O19: 0 | P19: 0 | Q19: 0 | R19: 0 | S19: 0 | T19: 0 | U19: 0 | V19: 0 | W19: 0 | X19: 0 | Y19: 0 | AA19: =N19-Z19 -> 0 | AC19: 0 | AD19: 0 | AE19: 0 | AF19: 0 | AG19: 0 | AH19: 0 | AI19: 0 | AJ19: 0 | AK19: 0
A20: Property & Equipment & Other assets | B20: =SUM(B21:B25) -> 5.0699869e+08 | C20: =SUM(C21:C25) -> 5.0685522e+08 | D20: =SUM(D21:D25) -> 5.1526463e+08 | E20: =SUM(E21:E25) -> 5.2143931e+08 | F20: =SUM(F21:F25) -> 5.2143931e+08 | G20: =SUM(G21:G25) -> 5.2154931e+08 | H20: =SUM(H21:H25) -> 5.3081252e+08 | I20: =SUM(I21:I25) -> 5.3082852e+08 | ... Z20: =SUM(Z21:Z25) -> 575846453 | AA20: =N20-Z20 -> 0 | AB20: =SUM(AB21:AB25) -> 657273113 | AC20: =SUM(AC21:AC25) -> 5.1587084e+08 | AD20: =SUM(AD21:AD25) -> 5.1903681e+08 | AE20: =SUM(AE21:AE25) -> 5.1939986e+08 | AF20: =SUM(AF21:AF25) -> 5.1982496e+08 | AG20: =SUM(AG21:AG25) -> 5.2033944e+08 | AH20: =SUM(AH21:AH25) -> 5.2063842e+08 | AI20: =SUM(AI21:AI25) -> 5.17078e+08 | ... AM20: =SUM(AM21:AM25) -> 0
A21: Investment Properties | B21: 4.5244252e+08 | C21: 4.5262816e+08 | D21: 4.5262816e+08 | E21: 4.5262816e+08 | F21: 4.5262816e+08 | G21: 4.5243816e+08 | H21: 4.5243816e+08 | I21: 4.5243816e+08 | J21: 4.5243816e+08 | L21: 4.5243816e+08 | M21: 4.4700768e+08 | O21: 4.4700768e+08 | P21: 4.4702768e+08 | Q21: 4.4702768e+08 | R21: 4.4702768e+08 | S21: 4.4508995e+08 | T21: 4.4508995e+08 | U21: 4.4508995e+08 | V21: 4.4508995e+08 | W21: 4.4524431e+08 | X21: 4.4524431e+08 | Y21: 4.4524431e+08 | Z21: 236778710 | AA21: =N21-Z21 -> -236778710 | AB21: 235015345 | AC21: 4.3998859e+08 | AD21: 4.4041359e+08 | AE21: 4.4047089e+08 | AF21: 4.4008089e+08 | AG21: 4.4008089e+08 | AH21: 4.4024339e+08 | AI21: 4.3594233e+08 | AJ21: 4.3600733e+08
A22: Property & Equipment | B22: 32568033 | C22: 32568034 | D22: 35773639 | E22: 41399718 | F22: 41399718 | G22: 41399718 | H22: 41399718 | I22: 41399718 | J22: 42949558 | L22: 42949558 | M22: 36626402 | N22: 243649762 | O22: 36626402 | P22: 43857269 | Q22: 45916419 | R22: 43239774 | S22: 43514549 | T22: 43563549 | U22: 43566899 | V22: 44499413 | W22: 44622265 | X22: 45576025 | Y22: 45801025 | Z22: 243649762 | AA22: =N22-Z22 -> 0 | AB22: 241918784 | AC22: 36945543 | AD22: 37603603 | AE22: 37621102 | AF22: 37649042 | AG22: 37649042 | AH22: 37785526 | AI22: 37803526 | AJ22: 37803526
A23: Prepaid Lease rentals | B23: 0 | C23: 0 | D23: 0 | E23: 0 | F23: 0 | G23: 0 | H23: 0 | I23: 0 | J23: 0 | L23: 0 | M23: 0 | O23: 0 | P23: 0 | Q23: 0 | R23: 0 | S23: 0 | T23: 0 | U23: 0 | V23: 0 | W23: 0 | X23: 0 | Y23: 0 | AA23: =N23-Z23 -> 0 | AC23: 0 | AD23: 0 | AE23: 0 | AF23: 0 | AG23: 0 | AH23: 0 | AI23: 0 | AJ23: 0
A24: Intangible Assets | B24: 7703332 | C24: 7703332 | D24: 11147720 | E24: 11246320 | F24: 11246320 | G24: 11246320 | H24: 20509536 | I24: 20509536 | J24: 22614240 | L24: 22614240 | M24: 15083698 | N24: 15083698 | O24: 15083698 | P24: 16805892 | Q24: 16805892 | R24: 16805892 | S24: 16805892 | T24: 16805892 | U24: 16805892 | V24: 16805892 | W24: 16805892 | X24: 16805892 | Y24: 17408534 | Z24: 15083698 | AA24: =N24-Z24 -> 0 | AB24: 11611492 | AC24: 11611492 | AD24: 12713840 | AE24: 12713840 | AF24: 12713840 | AG24: 12713840 | AH24: 12713840 | AI24: 12713840 | AJ24: 12713840
A25: Other Assets | B25: 14284804 | C25: 13955693 | D25: 15715110 | E25: 16165110 | F25: 16165110 | G25: 16465110 | H25: 16465110 | I25: 16481110 | J25: 16481110 | L25: 18136395 | M25: 19311815 | N25: =236778710+10250000+10161646+59922637 -> 317112993 | O25: 19627393 | P25: 19190416 | Q25: 19481110 | R25: 20081110 | S25: 20430726 | T25: 20430726 | U25: 20730726 | V25: 21330726 | W25: 21630726 | X25: 21930726 | Y25: 22230726 | Z25: =257190356+59922637-Z21 -> 80334283 | AA25: =N25-Z25 -> 236778710 | AB25: =309016568+94726269-AB21 -> 168727492 | AC25: 27325223 | AD25: 28305777 | AE25: 28594027 | AF25: 29381192 | AG25: 29895667 | AH25: 29895667 | AI25: 30618307 | AJ25: 31014072
A26: Total Assets | B26: =SUM(B4,B7,B8,B13,B16,B20) -> 6.3302389e+09 | C26: =SUM(C4,C7,C8,C13,C16,C20) -> 6.4282313e+09 | D26: =SUM(D4,D7,D8,D13,D16,D20) -> 6.5434997e+09 | E26: =SUM(E4,E7,E8,E13,E16,E20) -> 6.3423933e+09 | F26: =SUM(F4,F7,F8,F13,F16,F20) -> 6.6617024e+09 | G26: =SUM(G4,G7,G8,G13,G16,G20) -> 6.8126167e+09 | H26: =SUM(H4,H7,H8,H13,H16,H20) -> 6.7579623e+09 | I26: =SUM(I4,I7,I8,I13,I16,I20) -> 6.7474402e+09 | ... Z26: =SUM(Z4,Z7,Z8,Z13,Z16,Z20) -> 6956390321 | AA26: =N26-Z26 -> 1.2604233e+08 | AB26: =SUM(AB4,AB7,AB8,AB13,AB16,AB20) -> 7049229871 | AC26: =SUM(AC4,AC7,AC8,AC13,AC16,AC20) -> 6.8041813e+09 | AD26: =SUM(AD4,AD7,AD8,AD13,AD16,AD20) -> 6.8757499e+09 | AE26: =SUM(AE4,AE7,AE8,AE13,AE16,AE20) -> 7.0212083e+09 | AF26: =SUM(AF4,AF7,AF8,AF13,AF16,AF20) -> 7.0202061e+09 | AG26: =SUM(AG4,AG7,AG8,AG13,AG16,AG20) -> 7.1444179e+09 | AH26: =SUM(AH4,AH7,AH8,AH13,AH16,AH20) -> 7.6639835e+09 | AI26: =SUM(AI4,AI7,AI8,AI13,AI16,AI20) -> 5.5254131e+09 | ... AM26: =SUM(AM4,AM7,AM8,AM13,AM16,AM20) -> 0
A27: Savings Deposits - Withdrawable deposits - FOSA) | B27: 1.4508275e+08 | C27: 50126547 | D27: 54986080 | E27: 1.8095028e+08 | F27: 90227798 | G27: 99328975 | H27: 64548910 | I27: 71312236 | J27: 70450183 | L27: 43575722 | M27: 42772812 | N27: ='[2]Note 8'!$D$21 -> 46810692 | O27: 51447487 | P27: 3.8370442e+08 | Q27: 49687100 | R27: 40587004 | S27: 51321682 | T27: 50671163 | U27: 40398537 | V27: 46999007 | W27: 61341126 | X27: 1.7842135e+08 | Y27: 1.1072818e+08 | Z27: 46810692 | AA27: =N27-Z27 -> -0.14 | AB27: 102062910 | AC27: 80180894 | AD27: 69615023 | AE27: 153727806 | AF27: 93009595 | AG27: 71555549 | AH27: 92762960 | AI27: 102437741 | AJ27: 87295854
A28: Short Term Deposits (e.g Fixed deposits, special savings) | B28: 16592130 | C28: 18660130 | D28: 18588038 | E28: 19405538 | F28: 19092538 | G28: 20492538 | H28: 19626038 | I28: 17826038 | J28: 17126038 | L28: 18458038 | M28: 16288038 | N28: ='[2]Note 8'!$D$22 -> 16288038 | O28: 19371038 | P28: 20881638 | Q28: 21254238 | R28: 20144638 | S28: 22654638 | T28: 21483038 | U28: 24084038 | V28: 27266038 | W28: 27270838 | X28: 25548838 | Y28: 25378838 | Z28: 16286038 | AA28: =N28-Z28 -> 1999.55 | AB28: 25378838 | AC28: 23189838 | AD28: 26719838 | AE28: 26617838 | AF28: 28985038 | AG28: 26030552 | AH28: 30039737 | AI28: 31413521 | AJ28: 27147007
A29: Non withdrawable deposits (BOSA member deposits) | B29: 4.4982527e+09 | C29: 4.5415133e+09 | D29: 4.5877737e+09 | E29: 4.6331709e+09 | F29: 4.6708746e+09 | G29: 4.680367e+09 | H29: 4.7062754e+09 | I29: 4.7353454e+09 | J29: 4.7686859e+09 | L29: 4.8458975e+09 | M29: 4.8890807e+09 | N29: =4877606072-16491047 -> 4861115025 | O29: 4.9144309e+09 | P29: 4.9344628e+09 | Q29: 5.000962e+09 | R29: 5.0337356e+09 | S29: 5.025449e+09 | T29: 5.0445175e+09 | U29: 4.8670352e+09 | V29: 4.90337e+09 | W29: 4.9380862e+09 | X29: 4.9784386e+09 | Y29: 5.026152e+09 | Z29: 4891356072 | AA29: =N29-Z29 -> -30241047 | AB29: 5026214141 | AC29: 5.0670606e+09 | AD29: 5.1143677e+09 | AE29: 5.1558569e+09 | AF29: 5.1983355e+09 | AG29: 5.2130773e+09 | AH29: 5.2552684e+09 | AI29: 5.2877776e+09 | AJ29: 5.3325382e+09
A30: Total Deposit liabilities | B30: =SUM(B27:B29) -> 4.6599276e+09 | C30: =SUM(C27:C29) -> 4.6103e+09 | D30: =SUM(D27:D29) -> 4.6613478e+09 | E30: =SUM(E27:E29) -> 4.8335267e+09 | F30: =SUM(F27:F29) -> 4.780195e+09 | G30: =SUM(G27:G29) -> 4.8001885e+09 | H30: =SUM(H27:H29) -> 4.7904504e+09 | I30: =SUM(I27:I29) -> 4.8244837e+09 | ... Z30: =SUM(Z27:Z29) -> 4954452802 | AA30: =N30-Z30 -> -30239048 | AB30: =SUM(AB27:AB29) -> 5153655889 | AC30: =SUM(AC27:AC29) -> 5.1704314e+09 | AD30: =SUM(AD27:AD29) -> 5.2107025e+09 | AE30: =SUM(AE27:AE29) -> 5.3362026e+09 | AF30: =SUM(AF27:AF29) -> 5.3203301e+09 | AG30: =SUM(AG27:AG29) -> 5.3106634e+09 | AH30: =SUM(AH27:AH29) -> 5.3780711e+09 | AI30: =SUM(AI27:AI29) -> 5.4216288e+09 | ... AM30: =SUM(AM27:AM29) -> 0
A31: Accounts Payable & Other Liabilities | B31: =SUM(B32:B37) -> 2.9789071e+08 | C31: =SUM(C32:C37) -> 4.4449013e+08 | D31: =SUM(D32:D37) -> 4.5850111e+08 | E31: =SUM(E32:E37) -> 69029042 | F31: =SUM(F32:F37) -> 4.1622994e+08 | G31: =SUM(G32:G37) -> 4.6526934e+08 | H31: =SUM(H32:H37) -> 4.5949604e+08 | I31: =SUM(I32:I37) -> 4.0028446e+08 | ... Z31: =SUM(Z32:Z37) -> 693958758 | AA31: =N31-Z31 -> 84564484 | AB31: =SUM(AB32:AB37) -> 491262851 | AC31: =SUM(AC32:AC37) -> 2.3467623e+08 | AD31: =SUM(AD32:AD37) -> 2.2864744e+08 | AE31: =SUM(AE32:AE37) -> 2.2194042e+08 | AF31: =SUM(AF32:AF37) -> 1.8761959e+08 | AG31: =SUM(AG32:AG37) -> 2.7833863e+08 | AH31: =SUM(AH32:AH37) -> 6.2749369e+08 | AI31: =SUM(AI32:AI37) -> 6.5566794e+08 | ... AM31: =SUM(AM32:AM37) -> 0
A32: Tax Payable | B32: 10139396 | C32: 14921082 | D32: 10419890 | E32: 9340256.8 | F32: 9939305.7 | G32: 14932245 | H32: 11117248 | I32: 10276918 | J32: 13505270 | L32: 16358812 | M32: 9274006.4 | N32: 16288038 | O32: 3984363.3 | P32: 640368.66 | Q32: 901809.23 | R32: 159596.94 | S32: 498547.2 | T32: 1264060.1 | U32: 844363.14 | V32: 2954710.9 | W32: 977559.23 | X32: 1530107.1 | Y32: 1012717.2 | Z32: 11521899 | AA32: =N32-Z32 -> 4766139 | AB32: 23268815 | AC32: 267507 | AD32: 1001036.1 | AE32: 1493792.4 | AF32: 550863.97 | AG32: 2543127.5 | AH32: 710522.43 | AI32: 218406.04 | AJ32: 1511793.9
A33: Dividends Payable | B33: 0 | C33: 0 | D33: 0 | E33: 0 | F33: 0 | G33: 0 | H33: 0 | I33: 0 | J33: 0 | L33: 0 | M33: 0 | N33: 395841179 | O33: 0 | P33: 0 | Q33: 0 | R33: 0 | S33: 0 | T33: 0 | U33: 0 | V33: 0 | W33: 0 | X33: 0 | Y33: 0 | Z33: 303621910 | AA33: =N33-Z33 -> 92219269 | AB33: 241606685 | AC33: 0 | AD33: 0 | AE33: 0 | AF33: 0 | AG33: 0 | AH33: 0 | AI33: 0 | AJ33: 0
A34: Deferred Tax Liability | B34: 0 | C34: 0 | D34: 0 | E34: 0 | F34: 0 | G34: 0 | H34: 0 | I34: 0 | J34: 0 | L34: 0 | M34: 0 | O34: 0 | P34: 0 | Q34: 0 | R34: 0 | S34: 0 | T34: 0 | U34: 0 | V34: 0 | W34: 0 | X34: 0 | Y34: 0 | AA34: =N34-Z34 -> 0 | AC34: 0 | AD34: 0 | AE34: 0 | AF34: 0 | AG34: 0 | AH34: 0 | AI34: 0 | AJ34: 0
A35: Retirement Benefits Liability | B35: 0 | C35: 0 | D35: 0 | E35: 0 | F35: 0 | G35: 0 | H35: 0 | I35: 0 | J35: 0 | L35: 0 | M35: 0 | O35: 0 | P35: 0 | Q35: 0 | R35: 0 | S35: 0 | T35: 0 | U35: 0 | V35: 0 | W35: 0 | X35: 0 | Y35: 0 | AA35: =N35-Z35 -> 0 | AC35: 0 | AD35: 0 | AE35: 0 | AF35: 0 | AG35: 0 | AH35: 0 | AI35: 0 | AJ35: 0
A36: Other Liabilities | B36: 2.8775132e+08 | C36: 4.2956905e+08 | D36: 4.4808121e+08 | E36: 59688785 | F36: 6290638.8 | G36: 50337100 | H36: 59489906 | I36: 12229761 | J36: 8233461.2 | L36: 345061.23 | M36: 5893691.9 | N36: 33060692 | O36: 9931691.9 | P36: 13869892 | Q36: 4672082.8 | R36: -778282.83 | S36: 703282.83 | T36: 3069117.2 | U36: 10172296 | V36: 13895996 | W36: 17624396 | X36: 21305196 | Y36: 25719447 | Z36: 45481616 | AA36: =N36-Z36 -> -12420924 | AB36: 26387351 | AC36: 45519829 | AD36: 49868629 | AE36: 53779965 | AF36: 31513167 | AG36: 22462167 | AH36: 26783167 | AI36: 72116196 | AJ36: 76304789
A37: External Borrowings | B37: 0 | C37: 0 | D37: 0 | E37: 0 | F37: 400000000 | G37: 400000000 | H37: 3.8888889e+08 | I37: 3.7777778e+08 | J37: 3.6666667e+08 | L37: 3.4444444e+08 | M37: 3.3333333e+08 | N37: 333333333 | O37: 3.2222222e+08 | P37: 3e+08 | Q37: 2.8888889e+08 | R37: 2.7777778e+08 | S37: 2.6666667e+08 | T37: 2.5555556e+08 | U37: 2.4444444e+08 | V37: 2.3333333e+08 | W37: 2.3333333e+08 | X37: 2.1111111e+08 | Y37: 2e+08 | Z37: 333333333 | AA37: =N37-Z37 -> 0 | AB37: 200000000 | AC37: 1.8888889e+08 | AD37: 1.7777778e+08 | AE37: 1.6666667e+08 | AF37: 1.5555556e+08 | AG37: 2.5333333e+08 | AH37: 600000000 | AI37: 5.8333333e+08 | AJ37: 5.6666667e+08
A38: Total Liabilities | B38: =B31+B30 -> 4.9578183e+09 | C38: =C31+C30 -> 5.0547901e+09 | D38: =D31+D30 -> 5.1198489e+09 | E38: =E31+E30 -> 4.9025557e+09 | F38: =F31+F30 -> 5.1964249e+09 | G38: =G31+G30 -> 5.2654578e+09 | H38: =H31+H30 -> 5.2499464e+09 | I38: =I31+I30 -> 5.2247681e+09 | ... Z38: =Z31+Z30 -> 5648411560 | AA38: =N38-Z38 -> 54325436 | AB38: =AB31+AB30 -> 5644918740 | AC38: =AC31+AC30 -> 5.4051076e+09 | AD38: =AD31+AD30 -> 5.43935e+09 | AE38: =AE31+AE30 -> 5.558143e+09 | AF38: =AF31+AF30 -> 5.5079497e+09 | AG38: =AG31+AG30 -> 5.589002e+09 | AH38: =AH31+AH30 -> 6.0055647e+09 | AI38: =AI31+AI30 -> 6.0772968e+09 | ... AM38: =AM31+AM30 -> 0
A39: Share Capital (Members share capital per Bylaws) | B39: 4.4018821e+08 | C39: 4.4018781e+08 | D39: 4.4018741e+08 | E39: 4.4044526e+08 | F39: 4.4044526e+08 | G39: 4.4044746e+08 | H39: 4.4044606e+08 | I39: 4.4045204e+08 | J39: 4.4047334e+08 | L39: 4.4047404e+08 | M39: 4.4047464e+08 | N39: 440474635 | O39: 4.4047544e+08 | P39: 4.405981e+08 | Q39: 4.4051241e+08 | R39: 4.4049201e+08 | S39: 4.4049241e+08 | T39: 4.4049181e+08 | U39: 6.5011093e+08 | V39: 6.5005093e+08 | W39: 6.5007233e+08 | X39: 6.5002059e+08 | Y39: 6.5002199e+08 | Z39: 440474635 | AA39: =N39-Z39 -> 0 | AB39: 650021994 | AC39: 6.4999585e+08 | AD39: 6.4999625e+08 | AE39: 6.5010821e+08 | AF39: 6.5010356e+08 | AG39: 6.5007926e+08 | AH39: 6.5022061e+08 | AI39: 6.5022294e+08 | AJ39: 6.5022244e+08
A40: Capital Grants | B40: 0 | C40: 0 | D40: 0 | E40: 0 | F40: 0 | G40: 0 | H40: 0 | I40: 0 | J40: 0 | L40: 0 | M40: 0 | O40: 0 | P40: 0 | Q40: 0 | R40: 0 | S40: 0 | T40: 0 | U40: 0 | V40: 0 | W40: 0 | X40: 0 | Y40: 0 | AA40: =N40-Z40 -> 0 | AC40: 0 | AD40: 0 | AE40: 0 | AF40: 0 | AG40: 0 | AH40: 0 | AI40: 0 | AJ40: 0
A41: Retained Earnings | B41: =B43+B42 -> 2.0741478e+08 | C41: =C43+C42 -> 2.0843299e+08 | D41: =D43+D42 -> 2.408888e+08 | E41: =E43+E42 -> 3.1321756e+08 | F41: =F43+F42 -> 3.3351507e+08 | G41: =G43+G42 -> 3.6413688e+08 | H41: =H43+H42 -> 3.7625263e+08 | I41: =I43+I42 -> 3.9090287e+08 | ... Z41: =Z43+Z42 -> 111899621 | AA41: =N41-Z41 -> 57375111 | AB41: =AB43+AB42 -> -28220167 | AC41: =AC43+AC42 -> 1.5214932e+08 | AD41: =AD43+AD42 -> 1.894752e+08 | AE41: =AE43+AE42 -> 2.160286e+08 | AF41: =AF43+AF42 -> 2.6522431e+08 | AG41: =AG43+AG42 -> 3.0840813e+08 | AH41: =AH43+AH42 -> 4.1126963e+08 | AI41: =AI43+AI42 -> 3.0840813e+08 | ... AM41: =AM43+AM42 -> 0
A42: Prior Years' Retained Earnings | B42: 176608120 | C42: 151168883 | D42: 1.4695656e+08 | E42: 1.4695656e+08 | F42: 1.4695656e+08 | G42: 1.4695656e+08 | H42: 1.4695656e+08 | I42: 1.4695656e+08 | J42: 1.4695656e+08 | L42: 1.4695656e+08 | M42: 1.4695656e+08 | N42: 146956560 | O42: 1.4695656e+08 | P42: 1.4695656e+08 | Q42: 1.4695656e+08 | R42: 1.4695656e+08 | S42: 1.4695656e+08 | T42: 1.4695656e+08 | U42: 1.4695656e+08 | V42: 1.4695656e+08 | W42: 1.4695656e+08 | X42: 1.4695656e+08 | Y42: 1.4695656e+08 | Z42: 146956560 | AA42: =N42-Z42 -> 0 | AB42: 111899621 | AC42: 1.075312e+08 | AD42: 1.075312e+08 | AE42: 1.075312e+08 | AF42: 1.075312e+08 | AG42: 1.075312e+08 | AH42: 1.075312e+08 | AI42: 1.075312e+08 | AJ42: -588870.14
A43: Current Year's Surplus | B43: 30806663 | C43: 57264111 | D43: 93932236 | E43: 1.66261e+08 | F43: 1.8655851e+08 | G43: 2.1718032e+08 | H43: 2.2929607e+08 | I43: 2.4394631e+08 | J43: 2.5815697e+08 | L43: 2.9766732e+08 | M43: 302078751 | N43: =169274732-146956560 -> 22318172 | O43: 27367307 | P43: 31686882 | Q43: 90877438 | R43: 125349686 | S43: 1.8853308e+08 | T43: 2.0286708e+08 | U43: 2.3800162e+08 | V43: 2.4923066e+08 | W43: 2.5908361e+08 | X43: 2.7758953e+08 | Y43: 3.1125254e+08 | Z43: -35056939 | AA43: =N43-Z43 -> 57375111 | AB43: =84294453-16858891-2000000-65002199-(138621552+1931599) -> -140119788 | AC43: 44618116 | AD43: 81943999 | AE43: 1.084974e+08 | AF43: 1.576931e+08 | AG43: 2.0087693e+08 | AH43: 3.0373843e+08 | AI43: 2.0087693e+08 | AJ43: 3.976158e+08
A44: Other Equity Accounts | B44: =SUM(B45:B49) -> 724817575 | C44: =SUM(C45:C49) -> 724820379 | D44: =SUM(D45:D49) -> 7.4257456e+08 | E44: =SUM(E45:E49) -> 6.9131718e+08 | F44: =SUM(F45:F49) -> 6.9131718e+08 | G44: =SUM(G45:G49) -> 7.4257456e+08 | H44: =SUM(H45:H49) -> 6.9131718e+08 | I44: =SUM(I45:I49) -> 6.9131718e+08 | ... Z44: =SUM(Z45:Z49) -> 755602507 | AA44: =N44-Z44 -> 14343778 | AB44: =SUM(AB45:AB49) -> 782509305 | AC44: =SUM(AC45:AC49) -> 5.9692851e+08 | AD44: =SUM(AD45:AD49) -> 5.9692851e+08 | AE44: =SUM(AE45:AE49) -> 5.9692851e+08 | AF44: =SUM(AF45:AF49) -> 5.9692851e+08 | AG44: =SUM(AG45:AG49) -> 5.9692851e+08 | AH44: =SUM(AH45:AH49) -> 5.9692851e+08 | AI44: =SUM(AI45:AI49) -> 5.9692851e+08 | ... AM44: =SUM(AM45:AM49) -> 0
A45: Statutory Reserve | B45: 90967158 | C45: 108504682 | D45: 108552071 | E45: 108552071 | F45: 108552071 | G45: 108552071 | H45: 108552071 | I45: 108552071 | J45: 108552071 | L45: 108552071 | M45: 108552071 | N45: 126744666 | O45: 108552071 | P45: 108552071 | Q45: 108552071 | R45: 108552071 | S45: 108552071 | T45: 108552071 | U45: 108552071 | V45: 108552071 | W45: 108552071 | X45: 108552071 | Y45: 108552071 | Z45: 112400888 | AA45: =N45-Z45 -> 14343778 | AB45: 129259779 | AC45: 112400889 | AD45: 112400889 | AE45: 112400889 | AF45: 112400889 | AG45: 112400889 | AH45: 112400889 | AI45: 112400889 | AJ45: 129259780
A46: Other Reserves (provide notes on these reserves) | B46: 4500000 | C46: 4500000 | D46: 4500000 | E46: 4500000 | F46: 4500000 | G46: 4500000 | H46: 4500000 | I46: 4500000 | J46: 4500000 | L46: 4500000 | M46: 4500000 | N46: =[2]CiE!$M$52+1434640 -> 5934640 | O46: 4500000 | P46: 4500000 | Q46: 4500000 | R46: 4500000 | S46: 4500000 | T46: 4500000 | U46: 4500000 | V46: 4500000 | W46: 4500000 | X46: 4500000 | Y46: 4500000 | Z46: 5934640 | AA46: =N46-Z46 -> 0 | AB46: 5934640 | AC46: 3538825 | AD46: 3538825 | AE46: 3538825 | AF46: 3538825 | AG46: 3538825 | AH46: 3538825 | AI46: 3538825 | AJ46: 3538825
A47: Revaluation Reserves (Not part of core capital) | B47: 627915777 | C47: 559802030 | D47: 5.7683047e+08 | E47: 5.7683047e+08 | F47: 5.7683047e+08 | G47: 5.7683047e+08 | H47: 5.7683047e+08 | I47: 5.7683047e+08 | J47: 5.7683047e+08 | L47: 5.7683047e+08 | M47: 5.7683047e+08 | N47: =[2]CiE!$I$52 -> 5.8673886e+08 | O47: 5.7683047e+08 | P47: 5.7683047e+08 | Q47: 5.7683047e+08 | R47: 5.7683047e+08 | S47: 5.7683047e+08 | T47: 5.7683047e+08 | U47: 5.7683047e+08 | V47: 5.7683047e+08 | W47: 5.7683047e+08 | X47: 5.7683047e+08 | Y47: 5.7683047e+08 | Z47: 586738856 | AA47: =N47-Z47 -> 0.19999993 | AB47: =586738856-6529659 -> 580209197 | AC47: 4.7955415e+08 | AD47: 4.7955415e+08 | AE47: 4.7955415e+08 | AF47: 4.7955415e+08 | AG47: 4.7955415e+08 | AH47: 4.7955415e+08 | AI47: 4.7955415e+08 | AJ47: 4.791436e+08
A48: Proposed Dividends | B48: 0 | C48: 50579027 | D48: 51257379 | E48: 0 | F48: 0 | G48: 51257379 | H48: 0 | I48: 0 | J48: 0 | L48: 0 | M48: 0 | N48: =[2]CiE!$Q$52 -> 50528123 | O48: 0 | P48: 0 | Q48: 0 | R48: 0 | S48: 0 | T48: 0 | U48: 0 | V48: 0 | W48: 0 | X48: 0 | Y48: 0 | Z48: 50528123 | AA48: =N48-Z48 -> -0.4094 | AB48: 67105689 | AC48: 0 | AD48: 0 | AE48: 0 | AF48: 0 | AG48: 0 | AH48: 0 | AI48: 0 | AJ48: 0
A49: Adjustment to Equity | B49: 1434640 | C49: 1434640 | D49: 1434640 | E49: 1434640 | F49: 1434640 | G49: 1434640 | H49: 1434640 | I49: 1434640 | J49: 1434640 | L49: 1434640 | M49: 1434640 | O49: 1434640 | P49: 1434640 | Q49: 1434640 | R49: 1434640 | S49: 1434640 | T49: 1434640 | U49: 1434640 | V49: 1434640 | W49: 1434640 | X49: 1434640 | Y49: 1434640 | AA49: =N49-Z49 -> 0 | AC49: 1434640 | AD49: 1434640 | AE49: 1434640 | AF49: 1434640 | AG49: 1434640 | AH49: 1434640 | AI49: 1434640 | AJ49: 1434640
A50: Total Equity | B50: =SUM(B39,B40,B41,B44) -> 1.3724206e+09 | C50: =SUM(C39,C40,C41,C44) -> 1.3734412e+09 | D50: =SUM(D39,D40,D41,D44) -> 1.4236508e+09 | E50: =SUM(E39,E40,E41,E44) -> 1.44498e+09 | F50: =SUM(F39,F40,F41,F44) -> 1.4652775e+09 | G50: =SUM(G39,G40,G41,G44) -> 1.5471589e+09 | H50: =SUM(H39,H40,H41,H44) -> 1.5080159e+09 | I50: =SUM(I39,I40,I41,I44) -> 1.5226721e+09 | ... Z50: =SUM(Z39,Z40,Z41,Z44) -> 1307976763 | AA50: =N50-Z50 -> 71718889 | AB50: =SUM(AB39,AB40,AB41,AB44) -> 1404311132 | AC50: =SUM(AC39,AC40,AC41,AC44) -> 1.3990737e+09 | AD50: =SUM(AD39,AD40,AD41,AD44) -> 1436399960 | AE50: =SUM(AE39,AE40,AE41,AE44) -> 1.4630653e+09 | AF50: =SUM(AF39,AF40,AF41,AF44) -> 1.5122564e+09 | AG50: =SUM(AG39,AG40,AG41,AG44) -> 1.5554159e+09 | AH50: =SUM(AH39,AH40,AH41,AH44) -> 1.6584187e+09 | AI50: =SUM(AI39,AI40,AI41,AI44) -> 1.5555596e+09 | ... AM50: =SUM(AM39,AM40,AM41,AM44) -> 0
A51: Total Liabilities and Equity | B51: =SUM(B38,B50) -> 6.3302389e+09 | C51: =SUM(C38,C50) -> 6.4282313e+09 | D51: =SUM(D38,D50) -> 6.5434997e+09 | E51: =SUM(E38,E50) -> 6.3475357e+09 | F51: =SUM(F38,F50) -> 6.6617024e+09 | G51: =SUM(G38,G50) -> 6.8126167e+09 | H51: =SUM(H38,H50) -> 6.7579623e+09 | I51: =SUM(I38,I50) -> 6.7474402e+09 | ... Z51: =SUM(Z38,Z50) -> 6956388323 | AA51: =N51-Z51 -> 1.2604433e+08 | AB51: =SUM(AB38,AB50) -> 7049229872 | AC51: =SUM(AC38,AC50) -> 6.8041813e+09 | AD51: =SUM(AD38,AD50) -> 6.8757499e+09 | AE51: =SUM(AE38,AE50) -> 7.0212083e+09 | AF51: =SUM(AF38,AF50) -> 7.0202061e+09 | AG51: =SUM(AG38,AG50) -> 7.1444179e+09 | AH51: =SUM(AH38,AH50) -> 7.6639835e+09 | AI51: =SUM(AI38,AI50) -> 7.6328564e+09 | ... AM51: =SUM(AM38,AM50) -> 0
AB52: =+AB51-AB26 -> 1 | AC52: =+AC51-AC26 -> 0 | AD52: =+AD51-AD26 -> 0 | AE52: =+AE51-AE26 -> 0 | AF52: =+AF51-AF26 -> 0 | AG52: =+AG51-AG26 -> 0 | AH52: =+AH51-AH26 -> 0 | AI52: =+AI51-AI26 -> 2.1074433e+09 | ... AK52: =+AK51-AK26 -> 0
O53: =2000000+1088757+48452210 -> 51540967
N54: =N51-N26 -> 0.94059944 | O54: =5443784-51540967 -> -46097183
M55: =N51-N26 -> 0.94059944
L56: =N13/N51 -> 0.48853107
O58: =255218036+162988771+781653508 -> 1199860315
O60: =O58/4329137977 -> 0.27715918

Sheet SCI
A1: MAGEREZA SACCO SOCIETY | N1: Approved | Z1: Restated 2021 accounts | AA1: Variances btw
A2: STATEMENT OF COMPREHENSIVE INCOME | B2: Jan | C2: Feb | D2: Mar | E2: Apr | F2: May | G2: Jun | H2: Jul | I2: Aug | J2: Sep | K2: Oct | L2: Nov | M2: Dec | N2: Audited 2021 | O2: Feb | P2: Mar | Q2: Apr | R2: May | S2: Jun | T2: Jul | U2: Aug | V2: Sep | W2: Oct | X2: Nov | Y2: Dec | Z2: by the Auditor | AA2: Audited & restated 2021 | AB2: Audited 2022 | AC2: 44927 | AD2: 44958 | AE2: 44986 | AF2: 45017 | AG2: 45047 | AH2: 45078 | AI2: 45108 | AJ2: 45139 | AK2: 45170 | AL2: 45200 | AM2: 45231
A3: Financial Income | B3: =B4+B7 -> 42188053 | C3: =C4+C7 -> 79467027 | D3: =D4+D7 -> 1.3636454e+08 | E3: =E4+E7 -> 2.3243133e+08 | F3: =F4+F7 -> 2.7570247e+08 | G3: =G4+G7 -> 3.1900522e+08 | H3: =H4+H7 -> 3.6472629e+08 | I3: =I4+I7 -> 4.1137057e+08 | ... Z3: =Z4+Z7 -> 695984292 | AA3: =N3-Z3 -> 123985897 | AB3: =AB4+AB7 -> 712535574 | AC3: =AC4+AC7 -> 71713958 | AD3: =AD4+AD7 -> 1.3948346e+08 | AE3: =AE4+AE7 -> 2.079241e+08 | AF3: =AF4+AF7 -> 2.8314969e+08 | AG3: =AG4+AG7 -> 3.6235572e+08 | AH3: =AH4+AH7 -> 4.9681134e+08 | AI3: =AI4+AI7 -> 5.6393162e+08 | ... AM3: =AM4+AM7 -> 0
A4: Financial Income from Loans Portfolio | B4: =SUM(B5:B6) -> 40277499 | C4: =SUM(C5:C6) -> 75635249 | D4: =SUM(D5:D6) -> 1.2771036e+08 | E4: =SUM(E5:E6) -> 1.8034548e+08 | F4: =SUM(F5:F6) -> 2.2164721e+08 | G4: =SUM(G5:G6) -> 2.6298056e+08 | H4: =SUM(H5:H6) -> 3.0673223e+08 | I4: =SUM(I5:I6) -> 3.5142865e+08 | ... Z4: =SUM(Z5:Z6) -> 604120606 | AA4: =N4-Z4 -> 122564632 | AB4: =SUM(AB5:AB6) -> 580761538 | AC4: =SUM(AC5:AC6) -> 63865677 | AD4: =SUM(AD5:AD6) -> 1.2357749e+08 | AE4: =SUM(AE5:AE6) -> 1.8396e+08 | AF4: =SUM(AF5:AF6) -> 2.4813352e+08 | AG4: =SUM(AG5:AG6) -> 3.1589442e+08 | AH4: =SUM(AH5:AH6) -> 3.7983081e+08 | AI4: =SUM(AI5:AI6) -> 4.4231849e+08 | ... AM4: =SUM(AM5:AM6) -> 0
A5: Interest on Loan Portfolio | B5: 36107004 | C5: 65232689 | D5: 1.1139151e+08 | E5: 1.5394338e+08 | F5: 1.8968719e+08 | G5: 2.25625e+08 | H5: 2.6193996e+08 | I5: 2.9823513e+08 | J5: 3.342758e+08 | L5: 4.1092727e+08 | M5: 4.4854844e+08 | N5: 726685238 | O5: 35374160 | P5: 72718143 | Q5: 1.6425871e+08 | R5: 2.0388566e+08 | S5: 2.4287277e+08 | T5: 2.8137015e+08 | U5: 3.1950499e+08 | V5: 3.5698457e+08 | W5: 3.9552572e+08 | X5: 4.3556905e+08 | Y5: 4.8487513e+08 | Z5: 604120606 | AA5: =N5-Z5 -> 122564632 | AB5: 580761538 | AC5: 50553898 | AD5: 99478832 | AE5: 1.4813856e+08 | AF5: 1.9513279e+08 | AG5: 2.4538686e+08 | AH5: 2.9594335e+08 | AI5: 3.4667195e+08 | AJ5: 3.9587962e+08 | AK5: 4.4690321e+08
A6: Fees & Commission on Loan Portfolio | B6: 4170494.5 | C6: 10402560 | D6: 16318850 | E6: 26402092 | F6: 31960024 | G6: 37355561 | H6: 44792264 | I6: 53193522 | J6: 61349998 | L6: 74424695 | M6: 80965276 | O6: 5612456.5 | P6: 12842913 | Q6: 34515832 | R6: 41963658 | S6: 49454711 | T6: 58247437 | U6: 62566812 | V6: 69725487 | W6: 78794015 | X6: 87117274 | Y6: 95861038 | AA6: =N6-Z6 -> 0 | AC6: 13311779 | AD6: 24098658 | AE6: 35821440 | AF6: 53000729 | AG6: 70507560 | AH6: 83887465 | AI6: 95646535 | AJ6: 1.1228486e+08 | AK6: 1.3161017e+08
A7: Financial Income from Investments in: | B7: =SUM(B8:B11) -> 1910554.4 | C7: =SUM(C8:C11) -> 3831778.5 | D7: =SUM(D8:D11) -> 8654186.4 | E7: =SUM(E8:E11) -> 52085852 | F7: =SUM(F8:F11) -> 54055257 | G7: =SUM(G8:G11) -> 56024662 | H7: =SUM(H8:H11) -> 57994068 | I7: =SUM(I8:I11) -> 59941921 | ... Z7: =SUM(Z8:Z11) -> 91863686 | AA7: =N7-Z7 -> 1421265 | AB7: =SUM(AB8:AB11) -> 131774036 | AC7: =SUM(AC8:AC11) -> 7848281.3 | AD7: =SUM(AD8:AD11) -> 15905966 | AE7: =SUM(AE8:AE11) -> 23964101 | AF7: =SUM(AF8:AF11) -> 35016169 | AG7: =SUM(AG8:AG11) -> 46461297 | AH7: =SUM(AH8:AH11) -> 1.1698053e+08 | AI7: =SUM(AI8:AI11) -> 1.2161313e+08 | ... AM7: =SUM(AM8:AM11) -> 0
A8: Government Securities | B8: 0 | C8: 0 | D8: 0 | E8: 0 | F8: 0 | G8: 0 | H8: 0 | I8: 0 | J8: 0 | L8: 0 | M8: 0 | O8: 0 | P8: 0 | Q8: 0 | R8: 0 | S8: 0 | T8: 0 | U8: 0 | V8: 0 | W8: 0 | X8: 0 | Y8: 0 | AA8: =N8-Z8 -> 0 | AC8: 0 | AD8: 0 | AE8: 0 | AF8: 0 | AG8: 0 | AH8: 0 | AI8: 0 | AJ8: 0 | AK8: 0
A9: Deposit with Banks and Other Financial Inst. | B9: 0 | C9: 0 | D9: 0 | E9: 0 | F9: 0 | G9: 0 | H9: 0 | I9: 0 | J9: 0 | L9: 0 | M9: 0 | O9: 0 | P9: 0 | Q9: 0 | R9: 0 | S9: 0 | T9: 0 | U9: 0 | V9: 0 | W9: 0 | X9: 0 | Y9: 0 | AA9: =N9-Z9 -> 0 | AC9: 0 | AD9: 0 | AE9: 0 | AF9: 0 | AG9: 0 | AH9: 0 | AI9: 0 | AJ9: 0 | AK9: 0
A10: Other Investments - dividend & Interest incomes from investments | B10: 1910554.4 | C10: 3831778.5 | D10: 8654186.4 | E10: 52085852 | F10: 54055257 | G10: 56024662 | H10: 57994068 | I10: 59941921 | J10: 61878568 | L10: 64802401 | M10: 70210576 | N10: 93284951 | O10: 1889232.8 | P10: 1889232.8 | Q10: 6473698.3 | R10: 8396771 | S10: 50412285 | T10: 51801105 | U10: 53189925 | V10: 56258854 | W10: 57647675 | X10: 61389370 | Y10: 67288629 | Z10: 91863686 | AA10: =N10-Z10 -> 1421265 | AB10: 131774036 | AC10: 1948258.6 | AD10: 3924017.2 | AE10: 5927275.9 | AF10: 7875534.5 | AG10: 9048862.1 | AH10: 71751392 | AI10: 72504073 | AJ10: 74831403 | AK10: 75246435
A11: Other Operating Income- Salary processing fees, transaction fees, membership fees | O11: 662881.4 | P11: 2198551.6 | Q11: 4472215.6 | R11: 5383434.5 | S11: 6000214.5 | T11: 6763671.8 | U11: 10368204 | V11: 11421637 | W11: 12416206 | X11: 13925523 | Y11: 18493865 | AA11: =N11-Z11 -> 0 | AC11: 5900022.7 | AD11: 11981949 | AE11: 18036825 | AF11: 27140635 | AG11: 37412435 | AH11: 45229136 | AI11: 49109055 | AJ11: 53206099 | AK11: 58363200
A12: Financial Expense | B12: =B13+B14+B15+B16+B18+B17 -> 450231.88 | C12: =C13+C14+C15+C16+C18+C17 -> 450231.88 | D12: =D13+D14+D15+D16+D18+D17 -> 450231.88 | E12: =E13+E14+E15+E16+E18+E17 -> 450231.88 | F12: =F13+F14+F15+F16+F18+F17 -> 450231.88 | G12: =G13+G14+G15+G16+G18+G17 -> 450231.88 | H12: =H13+H14+H15+H16+H18+H17 -> 450231.88 | I12: =I13+I14+I15+I16+I18+I17 -> 450231.88 | ... Z12: =Z13+Z14+Z15+Z16+Z18+Z17 -> 374662272 | AA12: =N12-Z12 -> 126640917 | AB12: =AB13+AB14+AB15+AB16+AB18+AB17 -> 292711117 | AC12: =AC13+AC14+AC15+AC16+AC18+AC17 -> 2909434 | AD12: =AD13+AD14+AD15+AD16+AD18+AD17 -> 3012836.2 | AE12: =AE13+AE14+AE15+AE16+AE18+AE17 -> 2711641.7 | AF12: =AF13+AF14+AF15+AF16+AF18+AF17 -> 6710641.7 | AG12: =AG13+AG14+AG15+AG16+AG18+AG17 -> 10346656 | AH12: =AH13+AH14+AH15+AH16+AH18+AH17 -> 12844979 | AI12: =AI13+AI14+AI15+AI16+AI18+AI17 -> 13196958 | ... AM12: =AM13+AM14+AM15+AM16+AM18+AM17 -> 0
A13: Interest Expense on Deposits | B13: 368947.88 | C13: 368947.88 | D13: 368947.88 | E13: 368947.88 | F13: 368947.88 | G13: 368947.88 | H13: 368947.88 | I13: 368947.88 | J13: 368947.88 | L13: 1386128.8 | M13: 1410528.8 | N13: 395957045 | O13: 0 | P13: 6000 | Q13: 0 | R13: 0 | S13: 0 | T13: 0 | U13: 0 | V13: 0 | W13: 0 | X13: 0 | Y13: 0 | Z13: 294891893 | AA13: =N13-Z13 -> 101065152 | AB13: 258007684 | AC13: 0 | AD13: 0 | AE13: 0 | AF13: 0 | AG13: 0 | AH13: 0 | AI13: 0 | AJ13: 0 | AK13: 0
A14: Cost of External Borrowings | B14: 0 | C14: 0 | D14: 0 | E14: 0 | F14: 0 | G14: 0 | H14: 0 | I14: 0 | J14: 0 | L14: 0 | M14: 0 | O14: 0 | P14: 0 | Q14: 0 | R14: 0 | S14: 0 | T14: 0 | U14: 0 | V14: 0 | W14: 0 | X14: 0 | Y14: 0 | AA14: =N14-Z14 -> 0 | AC14: 0 | AD14: 0 | AE14: 0 | AF14: 0 | AG14: 0 | AH14: 0 | AI14: 0 | AJ14: 0 | AK14: 0
A15: Dividend Expenses (on member shares) | B15: 0 | C15: 0 | D15: 0 | E15: 0 | F15: 0 | G15: 0 | H15: 0 | I15: 0 | J15: 0 | L15: 0 | M15: 0 | O15: 0 | P15: 0 | Q15: 0 | R15: 0 | S15: 0 | T15: 0 | U15: 0 | V15: 0 | W15: 0 | X15: 0 | Y15: 0 | AA15: =N15-Z15 -> 0 | AC15: 0 | AD15: 0 | AE15: 0 | AF15: 0 | AG15: 0 | AH15: 0 | AI15: 0 | AJ15: 0 | AK15: 0
A16: Other Financial Expense | B16: 0 | C16: 0 | D16: 0 | E16: 0 | F16: 0 | G16: 0 | H16: 0 | I16: 0 | J16: 0 | L16: 0 | M16: 0 | N16: 85275359 | O16: 0 | P16: 0 | Q16: 0 | R16: 0 | S16: 0 | T16: 0 | U16: 0 | V16: 0 | W16: 0 | X16: 0 | Y16: 0 | AA16: =N16-Z16 -> 85275359 | AC16: 0 | AD16: 0 | AE16: 0 | AF16: 0 | AG16: 0 | AH16: 0 | AI16: 0 | AJ16: 0 | AK16: 0
A17: Fees & Commission Expense | B17: 81284 | C17: 81284 | D17: 81284 | E17: 81284 | F17: 81284 | G17: 81284 | H17: 81284 | I17: 81284 | J17: 81284 | L17: 35126853 | M17: 42688238 | N17: 20070785 | O17: 3517081.6 | P17: 6902675.9 | Q17: 11789321 | R17: 18994691 | S17: 22454542 | T17: 26410421 | U17: 26926251 | V17: 33347619 | W17: 33422579 | X17: 38700575 | Y17: 41656113 | AA17: =N17-Z17 -> 20070785 | AC17: 2909434 | AD17: 3012836.2 | AE17: 2711641.7 | AF17: 6710641.7 | AG17: 10346656 | AH17: 12844979 | AI17: 13196958 | AJ17: 14914964 | AK17: 15326565
A18: Other Expense | B18: 0 | C18: 0 | D18: 0 | E18: 0 | F18: 0 | G18: 0 | H18: 0 | I18: 0 | J18: 0 | L18: 0 | M18: 0 | O18: 0 | P18: 0 | Q18: 0 | R18: 0 | S18: 0 | T18: 0 | U18: 0 | V18: 0 | W18: 0 | X18: 0 | Y18: 0 | Z18: 79770379 | AA18: =N18-Z18 -> -79770379 | AB18: 34703433 | AC18: 0 | AD18: 0 | AE18: 0 | AF18: 0 | AG18: 0 | AH18: 0 | AI18: 0 | AJ18: 0 | AK18: 0
A19: Net Financial Income/(Loss) | B19: =B3-B12 -> 41737821 | C19: =C3-C12 -> 79016795 | D19: =D3-D12 -> 1.3591431e+08 | E19: =E3-E12 -> 2.319811e+08 | F19: =F3-F12 -> 2.7525224e+08 | G19: =G3-G12 -> 3.1855499e+08 | H19: =H3-H12 -> 3.6427606e+08 | I19: =I3-I12 -> 4.1092034e+08 | ... Z19: =Z3-Z12 -> 321322020 | AA19: =N19-Z19 -> -2655020 | AB19: =AB3-AB12 -> 419824457 | AC19: =AC3-AC12 -> 68804524 | AD19: =AD3-AD12 -> 1.3647062e+08 | AE19: =AE3-AE12 -> 2.0521246e+08 | AF19: =AF3-AF12 -> 2.7643905e+08 | AG19: =AG3-AG12 -> 3.5200906e+08 | AH19: =AH3-AH12 -> 4.8396636e+08 | AI19: =AI3-AI12 -> 5.5073466e+08 | ... AM19: =AM3-AM12 -> 0
A20: Allowance for Loan Loss | B20: =B21-B22 -> 0 | C20: =C21-C22 -> 0 | D20: =D21-D22 -> 0 | E20: =E21-E22 -> 0 | F20: =F21-F22 -> 0 | G20: =G21-G22 -> 0 | H20: =H21-H22 -> 0 | I20: =I21-I22 -> 0 | ... Z20: =Z21-Z22 -> 10504980 | AA20: =N20-Z20 -> -10504980 | AB20: =AB21-AB22 -> 16836415 | AC20: =AC21-AC22 -> 0 | AD20: =AD21-AD22 -> 0 | AE20: =AE21-AE22 -> 0 | AF20: =AF21-AF22 -> 0 | AG20: =AG21-AG22 -> 0 | AH20: =AH21-AH22 -> 0 | AI20: =AI21-AI22 -> 0 | ... AM20: =AM21-AM22 -> 0
A21: Provision for Loan Losses | B21: 0 | C21: 0 | D21: 0 | E21: 0 | F21: 0 | G21: 0 | H21: 0 | I21: 0 | J21: 0 | L21: 0 | M21: 0 | O21: 0 | P21: 0 | Q21: 0 | R21: 0 | S21: 0 | T21: 0 | U21: 0 | V21: 0 | W21: 0 | X21: 0 | Y21: 0 | Z21: 10504980 | AA21: =N21-Z21 -> -10504980 | AB21: 16836415 | AC21: 0 | AD21: 0 | AE21: 0 | AF21: 0 | AG21: 0 | AH21: 0 | AI21: 0 | AJ21: 0 | AK21: 0
A22: Value of Loans Recovered | B22: 0 | C22: 0 | D22: 0 | E22: 0 | F22: 0 | G22: 0 | H22: 0 | I22: 0 | J22: 0 | L22: 0 | M22: 0 | O22: 0 | P22: 0 | Q22: 0 | R22: 0 | S22: 0 | T22: 0 | U22: 0 | V22: 0 | W22: 0 | X22: 0 | Y22: 0 | AA22: =N22-Z22 -> 0 | AC22: 0 | AD22: 0 | AE22: 0 | AF22: 0 | AG22: 0 | AH22: 0 | AI22: 0 | AJ22: 0 | AK22: 0
A23: Operating Expenses | B23: =SUM(B24:B28) -> 13756948 | C23: =SUM(C24:C28) -> 25907964 | D23: =SUM(D24:D28) -> 46489717 | E23: =SUM(E24:E28) -> 68072060 | F23: =SUM(F24:F28) -> 86624429 | G23: =SUM(G24:G28) -> 98517771 | H23: =SUM(H24:H28) -> 1.2556816e+08 | I23: =SUM(I24:I28) -> 1.5479427e+08 | ... Z23: =SUM(Z24:Z28) -> 287495990 | AA23: =N23-Z23 -> -65800527 | AB23: =SUM(AB24:AB28) -> 300724749 | AC23: =SUM(AC24:AC28) -> 24186407 | AD23: =SUM(AD24:AD28) -> 54526622 | AE23: =SUM(AE24:AE28) -> 96715065 | AF23: =SUM(AF24:AF28) -> 1.1674232e+08 | AG23: =SUM(AG24:AG28) -> 1.4912851e+08 | AH23: =SUM(AH24:AH28) -> 1.7627722e+08 | AI23: =SUM(AI24:AI28) -> 2.013011e+08 | ... AM23: =SUM(AM24:AM28) -> 0
A24: Personnel Expenses | B24: 6130811.9 | C24: 13036341 | D24: 23929473 | E24: 39561446 | F24: 47643865 | G24: 55923812 | H24: 65084878 | I24: 75125662 | J24: 84296752 | L24: 1.0759178e+08 | M24: 116028086 | N24: 108600735 | O24: 3686772 | P24: 19985061 | Q24: 51525599 | R24: 52350417 | S24: 65131762 | T24: 75434334 | U24: 83560110 | V24: 94161024 | W24: 1.0693831e+08 | X24: 1.1658069e+08 | Y24: 1.29601e+08 | Z24: 134808061 | AA24: =N24-Z24 -> -26207326 | AB24: 137994298 | AC24: 10353612 | AD24: 22038937 | AE24: 40457461 | AF24: 53665898 | AG24: 69245108 | AH24: 96163684 | AI24: 1.0791929e+08 | AJ24: 1.203403e+08 | AK24: 1.3441957e+08
A25: Governance Expenses | B25: 4540475 | C25: 8511775 | D25: 12302075 | E25: 14755905 | F25: 17675745 | G25: 20436445 | H25: 34116459 | I25: 39444159 | J25: 50544554 | L25: 66990493 | M25: 69050553 | N25: 51267848 | O25: 3426062.4 | P25: 15059524 | Q25: 29329257 | R25: 32458308 | S25: 36291319 | T25: 48172390 | U25: 50567390 | V25: 63418032 | W25: 67730444 | X25: 70969684 | Y25: 74783498 | Z25: 65790264 | AA25: =N25-Z25 -> -14522416 | AB25: 66558805 | AC25: 4199805 | AD25: 21116265 | AE25: 33710515 | AF25: 36687915 | AG25: 41013032 | AH25: 43822032 | AI25: 51547806 | AJ25: 54062326 | AK25: 57336894
A26: Marketing Expenses | B26: 445500 | C26: 480500 | D26: 515500 | E26: 637674 | F26: 1672674 | G26: 1707674 | H26: 2082674 | I26: 2259330 | J26: 2294330 | L26: 2602330 | M26: 2806929 | O26: 38360 | P26: 325360 | Q26: 587236 | R26: 985543 | S26: 2717543 | T26: 2772463 | U26: 2807463 | V26: 3138683 | W26: 4723407 | X26: 5266506 | Y26: 8652906 | AA26: =N26-Z26 -> 0 | AC26: 262800 | AD26: 294905 | AE26: 510505 | AF26: 650145 | AG26: 794945 | AH26: 2978062 | AI26: 5172622 | AJ26: 5362622 | AK26: 6967872
A27: Depreciation and Amortization Charges | B27: 0 | C27: 0 | D27: 0 | E27: 0 | F27: 0 | G27: 0 | H27: 0 | I27: 0 | J27: 0 | L27: 0 | M27: 20355463 | N27: 20355463 | O27: 0 | P27: 0 | Q27: 0 | R27: 0 | S27: 0 | T27: 0 | U27: 0 | V27: 0 | W27: 0 | X27: 0 | Y27: 0 | Z27: 20355463 | AA27: =N27-Z27 -> 0 | AB27: 19908248 | AC27: 0 | AD27: 0 | AE27: 0 | AF27: 0 | AG27: 0 | AH27: 0 | AI27: 0 | AJ27: 0 | AK27: 0
A28: Administrative Expenses | B28: 2640161.1 | C28: 3879348.1 | D28: 9742668.7 | E28: 13117035 | F28: 19632145 | G28: 20449840 | H28: 24284147 | I28: 37965122 | J28: 45233289 | L28: 52263378 | M28: 55846593 | N28: 41471417 | O28: 5503147.3 | P28: 15683338 | Q28: 23959251 | R28: 27838521 | S28: 30307027 | T28: 39220967 | U28: 40462393 | V28: 46137466 | W28: 67528203 | X28: 83937179 | Y28: 93963190 | Z28: 66542202 | AA28: =N28-Z28 -> -25070785 | AB28: 76263398 | AC28: 9370190 | AD28: 11076515 | AE28: 22036584 | AF28: 25738367 | AG28: 38075425 | AH28: 33313442 | AI28: 36661382 | AJ28: 39955256 | AK28: 46445906
A29: Net Operating Income | B29: =B19-B20-B23 -> 27980873 | C29: =C19-C20-C23 -> 53108832 | D29: =D19-D20-D23 -> 89424595 | E29: =E19-E20-E23 -> 1.6390904e+08 | F29: =F19-F20-F23 -> 1.8862781e+08 | G29: =G19-G20-G23 -> 2.2003722e+08 | H29: =H19-H20-H23 -> 2.387079e+08 | I29: =I19-I20-I23 -> 2.5612606e+08 | ... Z29: =Z19-Z20-Z23 -> 23321050 | AA29: =N29-Z29 -> 73650487 | AB29: =AB19-AB20-AB23 -> 102263293 | AC29: =AC19-AC20-AC23 -> 44618117 | AD29: =AD19-AD20-AD23 -> 81943999 | AE29: =AE19-AE20-AE23 -> 1.084974e+08 | AF29: =AF19-AF20-AF23 -> 1.5969672e+08 | AG29: =AG19-AG20-AG23 -> 2.0288055e+08 | AH29: =AH19-AH20-AH23 -> 3.0768914e+08 | AI29: =AI19-AI20-AI23 -> 3.4943356e+08 | ... AN29: =AN19-AN20-AN23 -> 0
A30: Net Non- Operating Income/ (Expense) | B30: =B31-B32 -> 0 | C30: =C31-C32 -> 0 | D30: =D31-D32 -> 0 | E30: =E31-E32 -> 0 | F30: =F31-F32 -> 0 | G30: =G31-G32 -> 0 | H30: =H31-H32 -> 0 | I30: =I31-I32 -> 0 | ... Z30: =Z31-Z32 -> 0 | AA30: =N30-Z30 -> 0 | AB30: =AB31-AB32 -> 0 | AC30: =AC31-AC32 -> 0 | AD30: =AD31-AD32 -> 0 | AE30: =AE31-AE32 -> 0 | AF30: =AF31-AF32 -> 0 | AG30: =AG31-AG32 -> 0 | AH30: =AH31-AH32 -> 0 | AI30: =AI31-AI32 -> 0 | ... AN30: =AN31-AN32 -> 0
A31: Non- Operating Income | B31: 0 | C31: 0 | D31: 0 | E31: 0 | F31: 0 | G31: 0 | H31: 0 | I31: 0 | J31: 0 | K31: 0 | L31: 0 | M31: 0 | O31: 0 | P31: 0 | Q31: 0 | R31: 0 | S31: 0 | T31: 0 | U31: 0 | V31: 0 | W31: 0 | X31: 0 | Y31: 0 | AA31: =N31-Z31 -> 0 | AC31: 0 | AD31: 0 | AE31: 0 | AF31: 0 | AG31: 0 | AH31: 0 | AI31: 0 | AJ31: 0 | AK31: 0
A32: Non- Operating Expense | B32: 0 | C32: 0 | D32: 0 | E32: 0 | F32: 0 | G32: 0 | H32: 0 | I32: 0 | J32: 0 | K32: 0 | L32: 0 | M32: 0 | O32: 0 | P32: 0 | Q32: 0 | R32: 0 | S32: 0 | T32: 0 | U32: 0 | V32: 0 | W32: 0 | X32: 0 | Y32: 0 | AA32: =N32-Z32 -> 0 | AC32: 0 | AD32: 0 | AE32: 0 | AF32: 0 | AG32: 0 | AH32: 0 | AI32: 0 | AJ32: 0 | AK32: 0
A33: Net Income (Before Taxes and Donations) | B33: =B29+B30 -> 27980873 | C33: =C29+C30 -> 53108832 | D33: =D29+D30 -> 89424595 | E33: =E29+E30 -> 1.6390904e+08 | F33: =F29+F30 -> 1.8862781e+08 | G33: =G29+G30 -> 2.2003722e+08 | H33: =H29+H30 -> 2.387079e+08 | I33: =I29+I30 -> 2.5612606e+08 | ... Z33: =Z29+Z30 -> 23321050 | AA33: =N33-Z33 -> 73650487 | AB33: =AB29+AB30 -> 102263293 | AC33: =AC29+AC30 -> 44618117 | AD33: =AD29+AD30 -> 81943999 | AE33: =AE29+AE30 -> 1.084974e+08 | AF33: =AF29+AF30 -> 1.5969672e+08 | AG33: =AG29+AG30 -> 2.0288055e+08 | AH33: =AH29+AH30 -> 3.0768914e+08 | AI33: =AI29+AI30 -> 3.4943356e+08 | ... AN33: =AN29+AN30 -> 0
A34: Taxes (Incomes taxes & Other payable to KRA) | B34: 0 | C34: 0 | D34: 0 | E34: 1868739 | F34: 1868739 | G34: 3737478 | H34: 3737478 | I34: 3737478 | J34: 5606217 | L34: 5606217 | M34: 7474956 | N34: 6008559 | O34: 0 | P34: 0 | Q34: 1652354 | R34: 1652354 | S34: 3304708 | T34: 3304708 | U34: 3304708 | V34: 4957062 | W34: 4957062 | X34: 4957062 | Y34: 6609416 | AA34: =N34-Z34 -> 6008559 | AC34: 0 | AD34: 0 | AE34: 0 | AF34: 2003620 | AG34: 2003620 | AH34: 3950716 | AI34: 3950716 | AJ34: 3950716 | AK34: 5957786
A35: Net Income (After Taxes before Donations) | B35: =B33-B34 -> 27980873 | C35: =C33-C34 -> 53108832 | D35: =D33-D34 -> 89424595 | E35: =E33-E34 -> 1.620403e+08 | F35: =F33-F34 -> 1.8675907e+08 | G35: =G33-G34 -> 2.1629974e+08 | H35: =H33-H34 -> 2.3497043e+08 | I35: =I33-I34 -> 2.5238859e+08 | ... Z35: =Z33-Z34 -> 23321050 | AA35: =N35-Z35 -> 67641928 | AB35: =AB33-AB34 -> 102263293 | AC35: =AC33-AC34 -> 44618117 | AD35: =AD33-AD34 -> 81943999 | AE35: =AE33-AE34 -> 1.084974e+08 | AF35: =AF33-AF34 -> 1.576931e+08 | AG35: =AG33-AG34 -> 2.0087693e+08 | AH35: =AH33-AH34 -> 3.0373843e+08 | AI35: =AI33-AI34 -> 3.4548285e+08 | ... AN35: =AN33-AN34 -> 0
A36: Donations | B36: 0 | C36: 0 | D36: 0 | E36: 0 | F36: 0 | G36: 0 | H36: 0 | I36: 0 | J36: 0 | K36: 0 | L36: 0 | M36: 0 | O36: 0 | P36: 0 | Q36: 0 | R36: 0 | S36: 0 | T36: 0 | U36: 0 | V36: 0 | W36: 0 | X36: 0 | Y36: 0 | AA36: =N36-Z36 -> 0 | AC36: 0 | AD36: 0 | AE36: 0 | AF36: 0 | AG36: 0 | AH36: 0 | AI36: 0 | AJ36: 0 | AK36: 0 | AL36: 0
A37: Net Income/(After Taxes and Donations) | B37: =B35-B36 -> 27980873 | C37: =C35-C36 -> 53108832 | D37: =D35-D36 -> 89424595 | E37: =E35-E36 -> 1.620403e+08 | F37: =F35-F36 -> 1.8675907e+08 | G37: =G35-G36 -> 2.1629974e+08 | H37: =H35-H36 -> 2.3497043e+08 | I37: =I35-I36 -> 2.5238859e+08 | ... Z37: =Z35-Z36 -> 23321050 | AA37: =N37-Z37 -> 67641928 | AB37: =AB35-AB36 -> 102263293 | AC37: =AC35-AC36 -> 44618117 | AD37: =AD35-AD36 -> 81943999 | AE37: =AE35-AE36 -> 1.084974e+08 | AF37: =AF35-AF36 -> 1.576931e+08 | AG37: =AG35-AG36 -> 2.0087693e+08 | AH37: =AH35-AH36 -> 3.0373843e+08 | AI37: =AI35-AI36 -> 3.4548285e+08 | ... AN37: =AN35-AN36 -> 0

Sheet Financials
B2: ELIMU SACCO SOCIETY
B3: Year | C3: january | D3: february | E3: march | F3: april | G3: may | H3: june | I3: july | J3: august | K3: september | L3: october | M3: november | N3: december | O3: audited 21 | P3: Feb | Q3: Mar | R3: Apr | S3: May | T3: Jun | U3: Jul | V3: Aug | W3: Sep | X3: Oct | Y3: Nov | Z3: Dec | AA3: Restated 2021 | AC3: Aud-22 | AD3: 44927 | AE3: 44958 | AF3: 44986 | AG3: 45017 | AH3: 45047 | AI3: 45078 | AJ3: 45108 | AK3: 45139 | AL3: 45170
A4: 1 | B4: Membership
A5: 2 | B5: Total Assets | C5: =SFP!B26 -> 6.3302389e+09 | D5: =SFP!C26 -> 6.4282313e+09 | E5: =SFP!D26 -> 6.5434997e+09 | F5: =SFP!E26 -> 6.3423933e+09 | G5: =SFP!F26 -> 6.6617024e+09 | H5: =SFP!G26 -> 6.8126167e+09 | I5: =SFP!H26 -> 6.7579623e+09 | J5: =SFP!I26 -> 6.7474402e+09 | ... AL5: =SFP!AK26 -> 0
A6: 3 | B6: Total Deposits | C6: =SFP!B30 -> 4.6599276e+09 | D6: =SFP!C30 -> 4.6103e+09 | E6: =SFP!D30 -> 4.6613478e+09 | F6: =SFP!E30 -> 4.8335267e+09 | G6: =SFP!F30 -> 4.780195e+09 | H6: =SFP!G30 -> 4.8001885e+09 | I6: =SFP!H30 -> 4.7904504e+09 | J6: =SFP!I30 -> 4.8244837e+09 | ... AL6: =SFP!AK30 -> 0
A7: 3.1 | B7: Deposits-Members(BOSA) | C7: =SFP!B29 -> 4.4982527e+09 | D7: =SFP!C29 -> 4.5415133e+09 | E7: =SFP!D29 -> 4.5877737e+09 | F7: =SFP!E29 -> 4.6331709e+09 | G7: =SFP!F29 -> 4.6708746e+09 | H7: =SFP!G29 -> 4.680367e+09 | I7: =SFP!H29 -> 4.7062754e+09 | J7: =SFP!I29 -> 4.7353454e+09 | ... AL7: =SFP!AK29 -> 0
A8: 3.2 | B8: Deposits-Customers(FOSA) | C8: =SFP!B27 -> 1.4508275e+08 | D8: =SFP!C27 -> 50126547 | E8: =SFP!D27 -> 54986080 | F8: =SFP!E27 -> 1.8095028e+08 | G8: =SFP!F27 -> 90227798 | H8: =SFP!G27 -> 99328975 | I8: =SFP!H27 -> 64548910 | J8: =SFP!I27 -> 71312236 | ... AL8: =SFP!AK27 -> 0
A9: 4 | B9: External Borrowing | C9: =SFP!B37 -> 0 | D9: =SFP!C37 -> 0 | E9: =SFP!D37 -> 0 | F9: =SFP!E37 -> 0 | G9: =SFP!F37 -> 400000000 | H9: =SFP!G37 -> 400000000 | I9: =SFP!H37 -> 3.8888889e+08 | J9: =SFP!I37 -> 3.7777778e+08 | ... AL9: =SFP!AK37 -> 0
A10: 4.1 | B10: Short term Liabilities | C10: =SFP!B32+SFP!B33+SFP!B34+SFP!B35+SFP!B36 -> 2.9789071e+08 | D10: =SFP!C32+SFP!C33+SFP!C34+SFP!C35+SFP!C36 -> 4.4449013e+08 | E10: =SFP!D32+SFP!D33+SFP!D34+SFP!D35+SFP!D36 -> 4.5850111e+08 | F10: =SFP!E32+SFP!E33+SFP!E34+SFP!E35+SFP!E36 -> 69029042 | G10: =SFP!F32+SFP!F33+SFP!F34+SFP!F35+SFP!F36 -> 16229944 | H10: =SFP!G32+SFP!G33+SFP!G34+SFP!G35+SFP!G36 -> 65269345 | I10: =SFP!H32+SFP!H33+SFP!H34+SFP!H35+SFP!H36 -> 70607155 | J10: =SFP!I32+SFP!I33+SFP!I34+SFP!I35+SFP!I36 -> 22506679 | ... AL10: =SFP!AK32+SFP!AK33+SFP!AK34+SFP!AK35+SFP!AK36 -> 0
A13: 5 | B13: Share capital and Reserves | C13: =C18+C20+C21 -> 5.3565537e+08 | D13: =D18+D20+D21 -> 5.5319249e+08 | E13: =E18+E20+E21 -> 5.5323948e+08 | F13: =F18+F20+F21 -> 5.5349733e+08 | G13: =G18+G20+G21 -> 5.5349733e+08 | H13: =H18+H20+H21 -> 5.5349953e+08 | I13: =I18+I20+I21 -> 5.5349813e+08 | J13: =J18+J20+J21 -> 5.5350411e+08 | ... AL13: =AL18+AL20+AL21 -> 0
A14: 5.1 | B14: Core Capital | C14: =C17 -> 7.4307015e+08 | D14: =D17 -> 7.6162549e+08 | E14: =E17 -> 7.9412828e+08 | F14: =F17 -> 8.6671489e+08 | G14: =G17 -> 8.870124e+08 | H14: =H17 -> 9.1763641e+08 | I14: =I17 -> 9.2975076e+08 | J14: =J17 -> 9.4440697e+08 | ... AL14: =AL17 -> 0
A15: 5.2 | B15: Institutional Capital | C15: =C14-C18 -> 3.0288194e+08 | D15: =D14-D18 -> 3.2143768e+08 | E15: =E14-E18 -> 3.5394087e+08 | F15: =F14-F18 -> 4.2626963e+08 | G15: =G14-G18 -> 4.4656714e+08 | H15: =H14-H18 -> 4.7718895e+08 | I15: =I14-I18 -> 4.893047e+08 | J15: =J14-J18 -> 5.0395494e+08 | ... AL15: =AL14-AL18 -> 0
A17: 5.3 | B17: Total Capital | C17: =SUM(C18:C21) -> 7.4307015e+08 | D17: =SUM(D18:D21) -> 7.6162549e+08 | E17: =SUM(E18:E21) -> 7.9412828e+08 | F17: =SUM(F18:F21) -> 8.6671489e+08 | G17: =SUM(G18:G21) -> 8.870124e+08 | H17: =SUM(H18:H21) -> 9.1763641e+08 | I17: =SUM(I18:I21) -> 9.2975076e+08 | J17: =SUM(J18:J21) -> 9.4440697e+08 | ... AL17: =SUM(AL18:AL21) -> 0
A18: 5.3.1 | B18: Members Share Capital | C18: =SFP!B39 -> 4.4018821e+08 | D18: =SFP!C39 -> 4.4018781e+08 | E18: =SFP!D39 -> 4.4018741e+08 | F18: =SFP!E39 -> 4.4044526e+08 | G18: =SFP!F39 -> 4.4044526e+08 | H18: =SFP!G39 -> 4.4044746e+08 | I18: =SFP!H39 -> 4.4044606e+08 | J18: =SFP!I39 -> 4.4045204e+08 | ... AL18: =SFP!AK39 -> 0
A19: 5.3.3 | B19: Retained Earnings | C19: =SFP!B41 -> 2.0741478e+08 | D19: =SFP!C41 -> 2.0843299e+08 | E19: =SFP!D41 -> 2.408888e+08 | F19: =SFP!E41 -> 3.1321756e+08 | G19: =SFP!F41 -> 3.3351507e+08 | H19: =SFP!G41 -> 3.6413688e+08 | I19: =SFP!H41 -> 3.7625263e+08 | J19: =SFP!I41 -> 3.9090287e+08 | ... AL19: =SFP!AK41 -> 0
A20: 5.3.5 | B20: Statutory Reserves | C20: =SFP!B45 -> 90967158 | D20: =SFP!C45 -> 108504682 | E20: =SFP!D45 -> 108552071 | F20: =SFP!E45 -> 108552071 | G20: =SFP!F45 -> 108552071 | H20: =SFP!G45 -> 108552071 | I20: =SFP!H45 -> 108552071 | J20: =SFP!I45 -> 108552071 | ... AL20: =SFP!AK45 -> 0
A21: 5.3.6 | B21: Capital Reserve | C21: =SFP!B46 -> 4500000 | D21: =SFP!C46 -> 4500000 | E21: =SFP!D46 -> 4500000 | F21: =SFP!E46 -> 4500000 | G21: =SFP!F46 -> 4500000 | H21: =SFP!G46 -> 4500000 | I21: =SFP!H46 -> 4500000 | J21: =SFP!I46 -> 4500000 | ... AL21: =SFP!AK46 -> 0
A22: 5.3.7 | B22: Supplementary Capital & reserves
A23: a | B23: Proposed Dividends | C23: =SFP!B48 -> 0 | D23: =SFP!C48 -> 50579027 | E23: =SFP!D48 -> 51257379 | F23: =SFP!E48 -> 0 | G23: =SFP!F48 -> 0 | H23: =SFP!G48 -> 51257379 | I23: =SFP!H48 -> 0 | J23: =SFP!I48 -> 0 | ... AL23: =SFP!AK48 -> 0
A24: b
A26: 6 | B26: Investments | C26: =C27+C28+C29 -> 486426946 | D26: =D27+D28+D29 -> 4.183132e+08 | E26: =E27+E28+E29 -> 4.183132e+08 | F26: =F27+F28+F29 -> 4.183132e+08 | G26: =G27+G28+G29 -> 4.183132e+08 | H26: =H27+H28+H29 -> 4.183132e+08 | I26: =I27+I28+I29 -> 4.183132e+08 | J26: =J27+J28+J29 -> 4.183132e+08 | ... AL26: =AL27+AL28+AL29 -> 0
A27: 6.1 | B27: Investments in Coop bank, CIC, Kuscco, Kerussu & Codic | C27: =SFP!B12 -> 486426946 | D27: =SFP!C12 -> 4.183132e+08 | E27: =SFP!D12 -> 4.183132e+08 | F27: =SFP!E12 -> 4.183132e+08 | G27: =SFP!F12 -> 4.183132e+08 | H27: =SFP!G12 -> 4.183132e+08 | I27: =SFP!H12 -> 4.183132e+08 | J27: =SFP!I12 -> 4.183132e+08 | ... AL27: =SFP!AK12 -> 0
A28: 6.2 | B28: Equity Investments (at cost)
A29: 6.3 | B29: Deposits in KUSCCO CFP | C29: =SFP!B11 -> 0 | D29: =SFP!C11 -> 0 | E29: =SFP!D11 -> 0 | F29: =SFP!E11 -> 0 | G29: =SFP!F11 -> 0 | H29: =SFP!G11 -> 0 | I29: =SFP!H11 -> 0 | J29: =SFP!I11 -> 0 | ... AL29: =SFP!AK11 -> 0
A31: 7 | B31: Net Loans & advances | C31: =C32-C33 -> 3.3035756e+09 | D31: =D32-D33 -> 3.3794646e+09 | E31: =E32-E33 -> 3.4096313e+09 | F31: =F32-F33 -> 3.3737607e+09 | G31: =G32-G33 -> 3.3803658e+09 | H31: =H32-H33 -> 3.3723653e+09 | I31: =I32-I33 -> 3.4017131e+09 | J31: =J32-J33 -> 3.4401109e+09 | ... AL31: =AL32-AL33 -> 0
A32: 7.1 | B32: Gross Loans & advances | C32: =SFP!B14 -> 3.4379818e+09 | D32: =SFP!C14 -> 3.5287339e+09 | E32: =SFP!D14 -> 3.5589006e+09 | F32: =SFP!E14 -> 3.5230299e+09 | G32: =SFP!F14 -> 3.529635e+09 | H32: =SFP!G14 -> 3.5216345e+09 | I32: =SFP!H14 -> 3.5509824e+09 | J32: =SFP!I14 -> 3.5893802e+09 | ... AL32: =SFP!AK14 -> 0
A33: 7.3 | B33: Allowance for loan losses | C33: =SFP!B15 -> 134406232 | D33: =SFP!C15 -> 1.4926925e+08 | E33: =SFP!D15 -> 1.4926925e+08 | F33: =SFP!E15 -> 1.4926925e+08 | G33: =SFP!F15 -> 1.4926925e+08 | H33: =SFP!G15 -> 1.4926925e+08 | I33: =SFP!H15 -> 1.4926925e+08 | J33: =SFP!I15 -> 1.4926925e+08 | ... AL33: =SFP!AK15 -> 0
A34: 7.4 | B34: Non Performing Loans | AC34: =162502879+19518299+151715259 -> 333736437 | AD34: =162502879+19518299+151715259 -> 333736437 | AE34: =162502879+19518299+151715259 -> 333736437 | AF34: =162502879+19518299+151715259 -> 333736437 | AG34: =162502879+19518299+151715259 -> 333736437 | AH34: =162502879+19518299+151715259 -> 333736437 | AI34: =162502879+19518299+151715259 -> 333736437 | AJ34: =162502879+19518299+151715259 -> 333736437 | ... AL34: =162502879+19518299+151715259 -> 333736437
A35: 7.5 | B35: Required loan loss provision
A36: 7.6 | B36: Cash and Cash equipments | C36: =SFP!B4 -> 252652851 | D36: =SFP!C4 -> 2.4646583e+08 | E36: =SFP!D4 -> 2.8979676e+08 | F36: =SFP!E4 -> 1.3139564e+08 | G36: =SFP!F4 -> 4.7950328e+08 | H36: =SFP!G4 -> 7.8374847e+08 | I36: =SFP!H4 -> 4.8954418e+08 | J36: =SFP!I4 -> 7.1282297e+08 | ... AL36: =SFP!AK4 -> 0
A38: 8 | B38: Non-Earning Assets | C38: =SFP!B7+SFP!B16+SFP!B22+SFP!B23+SFP!B24+SFP!B25 -> 1.835141e+09 | D38: =SFP!C7+SFP!C16+SFP!C22+SFP!C23+SFP!C24+SFP!C25 -> 1.9313595e+09 | E38: =SFP!D7+SFP!D16+SFP!D22+SFP!D23+SFP!D24+SFP!D25 -> 1.9731302e+09 | F38: =SFP!E7+SFP!E16+SFP!E22+SFP!E23+SFP!E24+SFP!E25 -> 1.9662956e+09 | G38: =SFP!F7+SFP!F16+SFP!F22+SFP!F23+SFP!F24+SFP!F25 -> 1.930892e+09 | H38: =SFP!G7+SFP!G16+SFP!G22+SFP!G23+SFP!G24+SFP!G25 -> 1.7857516e+09 | I38: =SFP!H7+SFP!H16+SFP!H22+SFP!H23+SFP!H24+SFP!H25 -> 1.9959536e+09 | J38: =SFP!I7+SFP!I16+SFP!I22+SFP!I23+SFP!I24+SFP!I25 -> 1.723755e+09 | ... AL38: =SFP!AK7+SFP!AK16+SFP!AK22+SFP!AK23+SFP!AK24+SFP!AK25 -> 0
A39: 8.1 | B39: Property and Equipment | C39: =SFP!B22 -> 32568033 | D39: =SFP!C22 -> 32568034 | E39: =SFP!D22 -> 35773639 | F39: =SFP!E22 -> 41399718 | G39: =SFP!F22 -> 41399718 | H39: =SFP!G22 -> 41399718 | I39: =SFP!H22 -> 41399718 | J39: =SFP!I22 -> 41399718 | ... AL39: =SFP!AK22 -> 0
A41: 9 | B41: Turnover | C41: =C42+C43+C44 -> 42188053 | D41: =D42+D43+D44 -> 79467027 | E41: =E42+E43+E44 -> 1.3636454e+08 | F41: =F42+F43+F44 -> 2.3243133e+08 | G41: =G42+G43+G44 -> 2.7570247e+08 | H41: =H42+H43+H44 -> 3.1900522e+08 | I41: =I42+I43+I44 -> 3.6472629e+08 | J41: =J42+J43+J44 -> 4.1137057e+08 | ... AL41: =AL42+AL43+AL44 -> 7.1212301e+08
A42: 9.1 | B42: Loan Interest | C42: =SCI!B5 -> 36107004 | D42: =SCI!C5 -> 65232689 | E42: =SCI!D5 -> 1.1139151e+08 | F42: =SCI!E5 -> 1.5394338e+08 | G42: =SCI!F5 -> 1.8968719e+08 | H42: =SCI!G5 -> 2.25625e+08 | I42: =SCI!H5 -> 2.6193996e+08 | J42: =SCI!I5 -> 2.9823513e+08 | ... AL42: =SCI!AK5 -> 4.4690321e+08
B43: Income from investments | C43: =SCI!B7 -> 1910554.4 | D43: =SCI!C7 -> 3831778.5 | E43: =SCI!D7 -> 8654186.4 | F43: =SCI!E7 -> 52085852 | G43: =SCI!F7 -> 54055257 | H43: =SCI!G7 -> 56024662 | I43: =SCI!H7 -> 57994068 | J43: =SCI!I7 -> 59941921 | ... AL43: =SCI!AK7 -> 1.3360964e+08
A44: 9.2 | B44: Fees & Commissions | C44: =SCI!B6 -> 4170494.5 | D44: =SCI!C6 -> 10402560 | E44: =SCI!D6 -> 16318850 | F44: =SCI!E6 -> 26402092 | G44: =SCI!F6 -> 31960024 | H44: =SCI!G6 -> 37355561 | I44: =SCI!H6 -> 44792264 | J44: =SCI!I6 -> 53193522 | ... AL44: =SCI!AK6 -> 1.3161017e+08
B45: Average yield on loans | C45: =C42/C32 -> 0.010502384 | D45: =D42/D32 -> 0.018486146 | E45: =E42/E32 -> 0.031299415 | F45: =F42/F32 -> 0.043696303 | G45: =G42/G32 -> 0.053741304 | H45: =H42/H32 -> 0.064068261 | I45: =I42/I32 -> 0.073765492 | J45: =J42/J32 -> 0.083088197 | ... AL45: =AL42/AL32 -> #DIV/0!
A47: 10 | B47: Total Expenses (FinCosts + OpEx) | C47: =SUM(C48:C53) -> #REF! | D47: =SUM(D48:D53) -> #REF! | E47: =SUM(E48:E53) -> #REF! | F47: =SUM(F48:F53) -> #REF! | G47: =SUM(G48:G53) -> #REF! | H47: =SUM(H48:H53) -> #REF! | I47: =SUM(I48:I53) -> #REF! | J47: =SUM(J48:J53) -> #REF! | ... AL47: =SUM(AL48:AL53) -> #REF!
A48: 10.1 | B48: Financial Exp. (Interest on deposits) | C48: =SCI!B13 -> 368947.88 | D48: =SCI!C13 -> 368947.88 | E48: =SCI!D13 -> 368947.88 | F48: =SCI!E13 -> 368947.88 | G48: =SCI!F13 -> 368947.88 | H48: =SCI!G13 -> 368947.88 | I48: =SCI!H13 -> 368947.88 | J48: =SCI!I13 -> 368947.88 | ... AL48: =SCI!AK13 -> 0
A49: 10.2 | B49: Financial Exp. (Dividends) | C49: =SCI!B15 -> 0 | D49: =SCI!C15 -> 0 | E49: =SCI!D15 -> 0 | F49: =SCI!E15 -> 0 | G49: =SCI!F15 -> 0 | H49: =SCI!G15 -> 0 | I49: =SCI!H15 -> 0 | J49: =SCI!I15 -> 0 | ... AL49: =SCI!AK15 -> 0
A50: 10.3 | B50: Financial Exp. (Interest on bank loans) | C50: =SCI!B14 -> 0 | D50: =SCI!C14 -> 0 | E50: =SCI!D14 -> 0 | F50: =SCI!E14 -> 0 | G50: =SCI!F14 -> 0 | H50: =SCI!G14 -> 0 | I50: =SCI!H14 -> 0 | J50: =SCI!I14 -> 0 | ... AL50: =SCI!AK14 -> 0
A51: 10.4 | B51: Other Financial Expenses | C51: =SCI!B16+SCI!B18+SCI!#REF! -> #REF! | D51: =SCI!C16+SCI!C18+SCI!#REF! -> #REF! | E51: =SCI!D16+SCI!D18+SCI!#REF! -> #REF! | F51: =SCI!E16+SCI!E18+SCI!#REF! -> #REF! | G51: =SCI!F16+SCI!F18+SCI!#REF! -> #REF! | H51: =SCI!G16+SCI!G18+SCI!#REF! -> #REF! | I51: =SCI!H16+SCI!H18+SCI!#REF! -> #REF! | J51: =SCI!I16+SCI!I18+SCI!#REF! -> #REF! | ... AL51: =SCI!AK16+SCI!AK18+SCI!#REF! -> #REF!
A52: 10.5 | B52: Administrative Expenses | C52: =SCI!B28 -> 2640161.1 | D52: =SCI!C28 -> 3879348.1 | E52: =SCI!D28 -> 9742668.7 | F52: =SCI!E28 -> 13117035 | G52: =SCI!F28 -> 19632145 | H52: =SCI!G28 -> 20449840 | I52: =SCI!H28 -> 24284147 | J52: =SCI!I28 -> 37965122 | ... AL52: =SCI!AK28 -> 46445906
A53: 10.6 | B53: Governance Expenses | C53: =SCI!B25 -> 4540475 | D53: =SCI!C25 -> 8511775 | E53: =SCI!D25 -> 12302075 | F53: =SCI!E25 -> 14755905 | G53: =SCI!F25 -> 17675745 | H53: =SCI!G25 -> 20436445 | I53: =SCI!H25 -> 34116459 | J53: =SCI!I25 -> 39444159 | ... AL53: =SCI!AK25 -> 57336894
B54: LLP
B56: Net Surplus | C56: =SCI!B37 -> 27980873 | D56: =SCI!C37 -> 53108832 | E56: =SCI!D37 -> 89424595 | F56: =SCI!E37 -> 1.620403e+08 | G56: =SCI!F37 -> 1.8675907e+08 | H56: =SCI!G37 -> 2.1629974e+08 | I56: =SCI!H37 -> 2.3497043e+08 | J56: =SCI!I37 -> 2.5238859e+08 | ... AL56: =SCI!AK37 -> 4.4566842e+08
B57: Liquid Assets | C57: =SFP!B4+SFP!B9+SFP!B10 -> 252652851 | D57: =SFP!C4+SFP!C9+SFP!C10 -> 2.4646583e+08 | E57: =SFP!D4+SFP!D9+SFP!D10 -> 2.8979676e+08 | F57: =SFP!E4+SFP!E9+SFP!E10 -> 1.3139564e+08 | G57: =SFP!F4+SFP!F9+SFP!F10 -> 4.7950328e+08 | H57: =SFP!G4+SFP!G9+SFP!G10 -> 7.8374847e+08 | I57: =SFP!H4+SFP!H9+SFP!H10 -> 4.8954418e+08 | J57: =SFP!I4+SFP!I9+SFP!I10 -> 7.1282297e+08 | ... AL57: =SFP!AK4+SFP!AK9+SFP!AK10 -> 0
B58: Short term Liabilities + deposits | C58: =SFP!B27+SFP!B28+SFP!B32+SFP!B33+SFP!B34+SFP!B35+SFP!B36 -> 4.595656e+08 | D58: =SFP!C27+SFP!C28+SFP!C32+SFP!C33+SFP!C34+SFP!C35+SFP!C36 -> 5.1327681e+08 | E58: =SFP!D27+SFP!D28+SFP!D32+SFP!D33+SFP!D34+SFP!D35+SFP!D36 -> 5.3207522e+08 | F58: =SFP!E27+SFP!E28+SFP!E32+SFP!E33+SFP!E34+SFP!E35+SFP!E36 -> 2.6938485e+08 | G58: =SFP!F27+SFP!F28+SFP!F32+SFP!F33+SFP!F34+SFP!F35+SFP!F36 -> 1.2555028e+08 | H58: =SFP!G27+SFP!G28+SFP!G32+SFP!G33+SFP!G34+SFP!G35+SFP!G36 -> 185090857 | I58: =SFP!H27+SFP!H28+SFP!H32+SFP!H33+SFP!H34+SFP!H35+SFP!H36 -> 1.547821e+08 | J58: =SFP!I27+SFP!I28+SFP!I32+SFP!I33+SFP!I34+SFP!I35+SFP!I36 -> 1.1164495e+08 | ... AL58: =SFP!AK27+SFP!AK28+SFP!AK32+SFP!AK33+SFP!AK34+SFP!AK35+SFP!AK36 -> 0
C59: =(SFP!B39+SFP!B40+SFP!B42+(0.5*SFP!B43)+SFP!B45+SFP!B46) -> 7.2766682e+08 | D59: =(SFP!C39+SFP!C40+SFP!C42+(0.5*SFP!C43)+SFP!C45+SFP!C46) -> 7.3299343e+08 | E59: =(SFP!D39+SFP!D40+SFP!D42+(0.5*SFP!D43)+SFP!D45+SFP!D46) -> 7.4716216e+08 | F59: =(SFP!E39+SFP!E40+SFP!E42+(0.5*SFP!E43)+SFP!E45+SFP!E46) -> 7.8358439e+08 | G59: =(SFP!F39+SFP!F40+SFP!F42+(0.5*SFP!F43)+SFP!F45+SFP!F46) -> 7.9373315e+08 | H59: =(SFP!G39+SFP!G40+SFP!G42+(0.5*SFP!G43)+SFP!G45+SFP!G46) -> 8.0904625e+08 | I59: =(SFP!H39+SFP!H40+SFP!H42+(0.5*SFP!H43)+SFP!H45+SFP!H46) -> 8.1510272e+08 | J59: =(SFP!I39+SFP!I40+SFP!I42+(0.5*SFP!I43)+SFP!I45+SFP!I46) -> 8.2243382e+08 | ... AL59: =(SFP!AK39+SFP!AK40+SFP!AK42+(0.5*SFP!AK43)+SFP!AK45+SFP!AK46) -> 0

Sheet Prudential Ratios
A1: MAGEREZA SACCO SOCIETY LTD
A2: Sacco Financial Performance
O3: Approved | AA3: Restated 2021 accounts
A4: FINANCIAL SOUNDNESS INDICATORS | B4: Prude. Std | C4: january | D4: february | E4: march | F4: april | G4: may | H4: june | I4: july | J4: august | K4: september | L4: october | M4: november | N4: december | O4: Audited 2021 | P4: Feb | Q4: Mar | R4: Apr | S4: May | T4: Jun | U4: Jul | V4: Aug | W4: Sep | X4: Oct | Y4: Nov | Z4: Dec | AA4: by the Auditor | AC4: Audited 2022 | AD4: 44927 | AE4: 44958 | AF4: 44986 | AG4: 45017 | AH4: 45047 | AI4: 45078 | AJ4: 45108 | AK4: 45139 | AL4: 45170
A5: CAPITAL ADEQUACY REQUIREMENTS
A6: Core capital | B6: ≥ Ksh.10M | C6: =Financials!C14/1000000 -> 743.07015 | D6: =Financials!D14/1000000 -> 761.62549 | E6: =Financials!E14/1000000 -> 794.12828 | F6: =Financials!F14/1000000 -> 866.71489 | G6: =Financials!G14/1000000 -> 887.0124 | H6: =Financials!H14/1000000 -> 917.63641 | I6: =Financials!I14/1000000 -> 929.75076 | J6: =Financials!J14/1000000 -> 944.40697 | K6: =Financials!K14/1000000 -> 958.63894 | M6: =Financials!M14/1000000 -> 998.14999 | N6: =Financials!N14/1000000 -> 1002.562 | O6: =Financials!O14/1000000 -> 742.42867 | P6: =Financials!P14/1000000 -> 727.85137 | Q6: =Financials!Q14/1000000 -> 732.29361 | R6: =Financials!R14/1000000 -> 791.39848 | S6: =Financials!S14/1000000 -> 825.85033 | T6: =Financials!T14/1000000 -> 889.03413 | ... AL6: =Financials!AL14/1000000 -> 0
A7: Core capital /Total Assets | B7: ≥ 10% | C7: =Financials!C14/Financials!C5 -> 0.11738422 | D7: =Financials!D14/Financials!D5 -> 0.11848134 | E7: =Financials!E14/Financials!E5 -> 0.1213614 | F7: =Financials!F14/Financials!F5 -> 0.13665423 | G7: =Financials!G14/Financials!G5 -> 0.13315101 | H7: =Financials!H14/Financials!H5 -> 0.13469661 | I7: =Financials!I14/Financials!I5 -> 0.13757857 | J7: =Financials!J14/Financials!J5 -> 0.13996522 | K7: =Financials!K14/Financials!K5 -> 0.14135941 | M7: =Financials!M14/Financials!M5 -> 0.14581123 | N7: =Financials!N14/Financials!N5 -> 0.14577484 | O7: =Financials!O14/Financials!O5 -> 0.10482679 | P7: =Financials!P14/Financials!P5 -> 0.14402302 | Q7: =Financials!Q14/Financials!Q5 -> 0.10515239 | R7: =Financials!R14/Financials!R5 -> 0.11748738 | S7: =Financials!S14/Financials!S5 -> 0.12188338 | T7: =Financials!T14/Financials!T5 -> 0.13007857 | ... AL7: =Financials!AL14/Financials!AL5 -> #DIV/0!
A8: Core capital /Total Deposits | B8: ≥ 8% | C8: =Financials!C14/Financials!C6 -> 0.15945959 | D8: =Financials!D14/Financials!D6 -> 0.16520085 | E8: =Financials!E14/Financials!E6 -> 0.17036452 | F8: =Financials!F14/Financials!F6 -> 0.17931315 | G8: =Financials!G14/Financials!G6 -> 0.18555988 | H8: =Financials!H14/Financials!H6 -> 0.19116675 | I8: =Financials!I14/Financials!I6 -> 0.19408421 | J8: =Financials!J14/Financials!J6 -> 0.19575296 | K8: =Financials!K14/Financials!K6 -> 0.19740264 | M8: =Financials!M14/Financials!M6 -> 0.20337489 | N8: =Financials!N14/Financials!N6 -> 0.20261385 | O8: =Financials!O14/Financials!O6 -> 0.15077101 | P8: =Financials!P14/Financials!P6 -> 0.146001 | Q8: =Financials!Q14/Financials!Q6 -> 0.13715807 | R8: =Financials!R14/Financials!R6 -> 0.1560358 | S8: =Financials!S14/Financials!S6 -> 0.1621073 | T8: =Financials!T14/Financials!T6 -> 0.17434006 | ... AL8: =Financials!AL14/Financials!AL6 -> #DIV/0!
A9: Share Capital/Total Assets | B9: ≤2% | C9: =Financials!C18/Financials!C5 -> 0.069537378 | D9: =Financials!D18/Financials!D5 -> 0.068477283 | E9: =Financials!E18/Financials!E5 -> 0.067270946 | F9: =Financials!F18/Financials!F5 -> 0.069444646 | G9: =Financials!G18/Financials!G5 -> 0.066116021 | H9: =Financials!H18/Financials!H5 -> 0.06465173 | I9: =Financials!I18/Financials!I5 -> 0.065174389 | J9: =Financials!J18/Financials!J5 -> 0.065276908 | K9: =Financials!K18/Financials!K5 -> 0.064951513 | M9: =Financials!M18/Financials!M5 -> 0.064345099 | N9: =Financials!N18/Financials!N5 -> 0.064046031 | O9: =Financials!O18/Financials!O5 -> 0.062192562 | P9: =Financials!P18/Financials!P5 -> 0.087158734 | Q9: =Financials!Q18/Financials!Q5 -> 0.063266893 | R9: =Financials!R18/Financials!R5 -> 0.065396447 | S9: =Financials!S18/Financials!S5 -> 0.065010153 | T9: =Financials!T18/Financials!T5 -> 0.064450422 | ... AL9: =Financials!AL18/Financials!AL5 -> #DIV/0!
A10: Institutional Capital/Total Assets | B10: ≥ 8% | C10: =Financials!C15/Financials!C5 -> 0.047846842 | D10: =Financials!D15/Financials!D5 -> 0.050004062 | E10: =Financials!E15/Financials!E5 -> 0.054090454 | F10: =Financials!F15/Financials!F5 -> 0.067209586 | G10: =Financials!G15/Financials!G5 -> 0.067034988 | H10: =Financials!H15/Financials!H5 -> 0.070044884 | I10: =Financials!I15/Financials!I5 -> 0.072404177 | J10: =Financials!J15/Financials!J5 -> 0.074688315 | K10: =Financials!K15/Financials!K5 -> 0.076407895 | M10: =Financials!M15/Financials!M5 -> 0.081466128 | N10: =Financials!N15/Financials!N5 -> 0.081728805 | O10: =Financials!O15/Financials!O5 -> 0.042634227 | P10: =Financials!P15/Financials!P5 -> 0.05686429 | Q10: =Financials!Q15/Financials!Q5 -> 0.041885494 | R10: =Financials!R15/Financials!R5 -> 0.052090933 | S10: =Financials!S15/Financials!S5 -> 0.056873229 | T10: =Financials!T15/Financials!T5 -> 0.065628152 | ... AL10: =Financials!AL15/Financials!AL5 -> #DIV/0!
A12: ASSET MIX AND QUALITY
A13: Non Earning Assets
A14: Non earning Assets/Total assets | B14: ≤ 10% | C14: =Financials!C38/Financials!C5 -> 0.28990075 | D14: =Financials!D38/Financials!D5 -> 0.3004496 | E14: =Financials!E38/Financials!E5 -> 0.30154051 | F14: =Financials!F38/Financials!F5 -> 0.31002423 | G14: =Financials!G38/Financials!G5 -> 0.28984964 | H14: =Financials!H38/Financials!H5 -> 0.26212419 | I14: =Financials!I38/Financials!I5 -> 0.29534844 | J14: =Financials!J38/Financials!J5 -> 0.25546799 | K14: =Financials!K38/Financials!K5 -> 0.28999114 | M14: =Financials!M38/Financials!M5 -> 0.25148608 | N14: =Financials!N38/Financials!N5 -> 0.24914539 | O14: =Financials!O38/Financials!O5 -> 0.33500217 | P14: =Financials!P38/Financials!P5 -> 0.014115851 | Q14: =Financials!Q38/Financials!Q5 -> 0.25249955 | R14: =Financials!R38/Financials!R5 -> 0.30844631 | S14: =Financials!S38/Financials!S5 -> 0.27869445 | T14: =Financials!T38/Financials!T5 -> 0.27271603 | ... AL14: =Financials!AL38/Financials!AL5 -> #DIV/0!
A15: Property and Equipment/Total Assets | B15: ≤ 5% | C15: =Financials!C39/Financials!C5 -> 0.0051448348 | D15: =Financials!D39/Financials!D5 -> 0.0050664066 | E15: =Financials!E39/Financials!E5 -> 0.0054670498 | F15: =Financials!F39/Financials!F5 -> 0.0065274599 | G15: =Financials!G39/Financials!G5 -> 0.0062145852 | H15: =Financials!H39/Financials!H5 -> 0.0060769187 | I15: =Financials!I39/Financials!I5 -> 0.0061260652 | J15: =Financials!J39/Financials!J5 -> 0.0061356183 | K15: =Financials!K39/Financials!K5 -> 0.006333275 | M15: =Financials!M39/Financials!M5 -> 0.0062741349 | N15: =Financials!N39/Financials!N5 -> 0.0053255636 | O15: =Financials!O39/Financials!O5 -> 0.034401988 | P15: =Financials!P39/Financials!P5 -> 0.0072474209 | Q15: =Financials!Q39/Financials!Q5 -> 0.0062976059 | R15: =Financials!R39/Financials!R5 -> 0.0068165406 | S15: =Financials!S39/Financials!S5 -> 0.0063815558 | T15: =Financials!T39/Financials!T5 -> 0.0063668091 | ... AL15: =Financials!AL39/Financials!AL5 -> #DIV/0!
A16: Non Performing loans/Gross Loans | B16: ≤ 6% | C16: =Financials!C34/Financials!C32 -> 0 | D16: =Financials!D34/Financials!D32 -> 0 | E16: =Financials!E34/Financials!E32 -> 0 | F16: =Financials!F34/Financials!F32 -> 0 | G16: =Financials!G34/Financials!G32 -> 0 | H16: =Financials!H34/Financials!H32 -> 0 | I16: =Financials!I34/Financials!I32 -> 0 | J16: =Financials!J34/Financials!J32 -> 0 | K16: =Financials!K34/Financials!K32 -> 0 | M16: =Financials!M34/Financials!M32 -> 0 | N16: =Financials!N34/Financials!N32 -> 0 | O16: =Financials!O34/Financials!O32 -> 0 | P16: =Financials!P34/Financials!P32 -> 0 | Q16: =Financials!Q34/Financials!Q32 -> 0 | R16: =Financials!R34/Financials!R32 -> 0 | S16: =Financials!S34/Financials!S32 -> 0 | T16: =Financials!T34/Financials!T32 -> 0 | ... AL16: =Financials!AL34/Financials!AL32 -> #DIV/0!
A18: Earning Assets
A19: Equities & Investments/Deposits | B19: ≤ 5% | C19: =Financials!C26/Financials!C6 -> 0.10438509 | D19: =Financials!D26/Financials!D6 -> 0.090734486 | E19: =Financials!E26/Financials!E6 -> 0.089740825 | F19: =Financials!F26/Financials!F6 -> 0.086544096 | G19: =Financials!G26/Financials!G6 -> 0.087509652 | H19: =Financials!H26/Financials!H6 -> 0.087145161 | I19: =Financials!I26/Financials!I6 -> 0.087322312 | J19: =Financials!J26/Financials!J6 -> 0.086706315 | K19: =Financials!K26/Financials!K6 -> 0.086138925 | M19: =Financials!M26/Financials!M6 -> 0.085232081 | N19: =Financials!N26/Financials!N6 -> 0.084539457 | O19: =Financials!O26/Financials!O6 -> 0.083079694 | P19: =Financials!P26/Financials!P6 -> 0.083910185 | Q19: =Financials!Q26/Financials!Q6 -> 0.078349761 | R19: =Financials!R26/Financials!R6 -> 0.082476572 | S19: =Financials!S26/Financials!S6 -> 0.082111274 | T19: =Financials!T26/Financials!T6 -> 0.082031439 | ... AL19: =Financials!AL26/Financials!AL6 -> #DIV/0!
A20: Equities & Investments/Core Capital | B20: ≤ 40% | C20: =Financials!C26/Financials!C14 -> 0.6546178 | D20: =Financials!D26/Financials!D14 -> 0.54923739 | E20: =Financials!E26/Financials!E14 -> 0.52675772 | F20: =Financials!F26/Financials!F14 -> 0.48264222 | G20: =Financials!G26/Financials!G14 -> 0.47159791 | H20: =Financials!H26/Financials!H14 -> 0.45585942 | I20: =Financials!I26/Financials!I14 -> 0.44991972 | J20: =Financials!J26/Financials!J14 -> 0.44293743 | K20: =Financials!K26/Financials!K14 -> 0.43636158 | M20: =Financials!M26/Financials!M14 -> 0.41908852 | N20: =Financials!N26/Financials!N14 -> 0.41724421 | O20: =Financials!O26/Financials!O14 -> 0.55103229 | P20: =Financials!P26/Financials!P14 -> 0.57472338 | Q20: =Financials!Q26/Financials!Q14 -> 0.57123699 | R20: =Financials!R26/Financials!R14 -> 0.52857468 | S20: =Financials!S26/Financials!S14 -> 0.50652423 | T20: =Financials!T26/Financials!T14 -> 0.47052547 | ... AL20: =Financials!AL26/Financials!AL14 -> #DIV/0!
A21: Net Loans & advances /Total assets | B21: NPR | C21: =Financials!C31/Financials!C5 -> 0.52187218 | D21: =Financials!D31/Financials!D5 -> 0.52572231 | E21: =Financials!E31/Financials!E5 -> 0.52107152 | F21: =Financials!F31/Financials!F5 -> 0.53193811 | G21: =Financials!G31/Financials!G5 -> 0.50743271 | H21: =Financials!H31/Financials!H5 -> 0.49501761 | I21: =Financials!I31/Financials!I5 -> 0.50336373 | J21: =Financials!J31/Financials!J5 -> 0.50983941 | K21: =Financials!K31/Financials!K5 -> 0.51268015 | M21: =Financials!M31/Financials!M5 -> 0.51360322 | N21: =Financials!N31/Financials!N5 -> 0.51078256 | O21: =Financials!O31/Financials!O5 -> 0.48853107 | P21: =Financials!P31/Financials!P5 -> 0.70583463 | Q21: =Financials!Q31/Financials!Q5 -> 0.52655286 | R21: =Financials!R31/Financials!R5 -> 0.53521426 | S21: =Financials!S31/Financials!S5 -> 0.53102384 | T21: =Financials!T31/Financials!T5 -> 0.52613708 | ... AL21: =Financials!AL31/Financials!AL5 -> #DIV/0!
A22: NPL
A23: FUNDING MIX
A24: Total Deposits/Total Assets | B24: NPR | C24: =Financials!C6/Financials!C5 -> 0.73613772 | D24: =Financials!D6/Financials!D5 -> 0.71719572 | E24: =Financials!E6/Financials!E5 -> 0.71236311 | F24: =Financials!F6/Financials!F5 -> 0.76209823 | G24: =Financials!G6/Financials!G5 -> 0.71756357 | H24: =Financials!H6/Financials!H5 -> 0.70460275 | I24: =Financials!I6/Financials!I5 -> 0.70886018 | J24: =Financials!J6/Financials!J5 -> 0.71500947 | K24: =Financials!K6/Financials!K5 -> 0.71609686 | M24: =Financials!M6/Financials!M5 -> 0.71695787 | N24: =Financials!N6/Financials!N5 -> 0.71947122 | O24: =Financials!O6/Financials!O5 -> 0.69527153 | P24: =Financials!P6/Financials!P5 -> 0.98645234 | Q24: =Financials!Q6/Financials!Q5 -> 0.76665114 | R24: =Financials!R6/Financials!R5 -> 0.75295145 | S24: =Financials!S6/Financials!S5 -> 0.75186857 | T24: =Financials!T6/Financials!T5 -> 0.74611982 | ... AL24: =Financials!AL6/Financials!AL5 -> #DIV/0!
A25: BOSA Deposits/Total Assets | B25: NPR | C25: =Financials!C7/Financials!C5 -> 0.71059762 | D25: =Financials!D7/Financials!D5 -> 0.706495 | E25: =Financials!E7/Financials!E5 -> 0.70111927 | F25: =Financials!F7/Financials!F5 -> 0.73050829 | G25: =Financials!G7/Financials!G5 -> 0.7011533 | H25: =Financials!H7/Financials!H5 -> 0.68701457 | I25: =Financials!I7/Financials!I5 -> 0.69640451 | J25: =Financials!J7/Financials!J5 -> 0.70179879 | K25: =Financials!K7/Financials!K5 -> 0.70318301 | M25: =Financials!M7/Financials!M5 -> 0.70789589 | N25: =Financials!N7/Financials!N5 -> 0.71088364 | O25: =Financials!O7/Financials!O5 -> 0.68636234 | P25: =Financials!P7/Financials!P5 -> 0.97243918 | Q25: =Financials!Q7/Financials!Q5 -> 0.70855533 | R25: =Financials!R7/Financials!R5 -> 0.74241982 | S25: =Financials!S7/Financials!S5 -> 0.74290547 | T25: =Financials!T7/Financials!T5 -> 0.73529601 | ... AL25: =Financials!AL7/Financials!AL5 -> #DIV/0!
A26: FOSA Deposits/Total Assets | B26: NPR | C26: =Financials!C8/Financials!C5 -> 0.022919001 | D26: =Financials!D8/Financials!D5 -> 0.0077978755 | E26: =Financials!E8/Financials!E5 -> 0.0084031609 | F26: =Financials!F8/Financials!F5 -> 0.028530283 | G26: =Financials!G8/Financials!G5 -> 0.013544255 | H26: =Financials!H8/Financials!H5 -> 0.01458015 | I26: =Financials!I8/Financials!I5 -> 0.0095515346 | J26: =Financials!J8/Financials!J5 -> 0.010568784 | K26: =Financials!K8/Financials!K5 -> 0.010388474 | M26: =Financials!M8/Financials!M5 -> 0.006365606 | N26: =Financials!N8/Financials!N5 -> 0.0062192658 | O26: =Financials!O8/Financials!O5 -> 0.0066094087 | P26: =Financials!P8/Financials!P5 -> 0.010180132 | Q26: =Financials!Q8/Financials!Q5 -> 0.055097347 | R26: =Financials!R8/Financials!R5 -> 0.0073763185 | S26: =Financials!S8/Financials!S5 -> 0.0059900458 | T26: =Financials!T8/Financials!T5 -> 0.0075091058 | ... AL26: =Financials!AL8/Financials!AL5 -> #DIV/0!
A27: External Borrowing/Total assets | B27: ≤ 25% | C27: =Financials!C9/Financials!C5 -> 0 | D27: =Financials!D9/Financials!D5 -> 0 | E27: =Financials!E9/Financials!E5 -> 0 | F27: =Financials!F9/Financials!F5 -> 0 | G27: =Financials!G9/Financials!G5 -> 0.060044711 | H27: =Financials!H9/Financials!H5 -> 0.058714591 | I27: =Financials!I9/Financials!I5 -> 0.057545289 | J27: =Financials!J9/Financials!J5 -> 0.055988311 | K27: =Financials!K9/Financials!K5 -> 0.054068097 | M27: =Financials!M9/Financials!M5 -> 0.050316954 | N27: =Financials!N9/Financials!N5 -> 0.048467438 | O27: =Financials!O9/Financials!O5 -> 0.047064808 | P27: =Financials!P9/Financials!P5 -> 0.063759471 | Q27: =Financials!Q9/Financials!Q5 -> 0.043077962 | R27: =Financials!R9/Financials!R5 -> 0.042887116 | S27: =Financials!S9/Financials!S5 -> 0.040995921 | T27: =Financials!T9/Financials!T5 -> 0.039017197 | ... AL27: =Financials!AL9/Financials!AL5 -> #DIV/0!
A29: GROWTH RATIOS
A30: Total Assets | B30: NPR | C30: =Financials!C5/Financials!#REF!-1 -> #REF! | D30: =Financials!D5/Financials!C5-1 -> 0.015480053 | E30: =Financials!E5/Financials!D5-1 -> 0.017931585 | F30: =Financials!F5/Financials!E5-1 -> -0.030733766 | G30: =Financials!G5/Financials!F5-1 -> 0.050345215 | H30: =Financials!H5/Financials!G5-1 -> 0.022654009 | I30: =Financials!I5/Financials!H5-1 -> -0.0080225318 | J30: =Financials!J5/Financials!I5-1 -> -0.0015569864 | K30: =Financials!K5/Financials!J5-1 -> 0.0050584151 | M30: =Financials!M5/Financials!K5-1 -> 0.0094260076 | N30: =Financials!N5/Financials!M5-1 -> 0.0046709547 | O30: =Financials!O5/Financials!N5-1 -> 0.029802086 | P30: =Financials!P5/Financials!O5-1 -> -0.28644356 | Q30: =Financials!Q5/Financials!P5-1 -> 0.37801939 | R30: =Financials!R5/Financials!Q5-1 -> -0.032751907 | S30: =Financials!S5/Financials!R5-1 -> 0.0058954808 | T30: =Financials!T5/Financials!S5-1 -> 0.0086855835 | U30: =Financials!U5/Financials!T5-1 -> 0.0034530178 | ... AL30: =Financials!AL5/Financials!AK5-1 -> -1
A31: Total Deposits | B31: NPR | C31: =Financials!C6/Financials!#REF!-1 -> #REF! | D31: =Financials!D6/Financials!C6-1 -> -0.010649865 | E31: =Financials!E6/Financials!D6-1 -> 0.01107256 | F31: =Financials!F6/Financials!E6-1 -> 0.036937579 | G31: =Financials!G6/Financials!F6-1 -> -0.011033707 | H31: =Financials!H6/Financials!G6-1 -> 0.0041825668 | I31: =Financials!I6/Financials!H6-1 -> -0.0020286919 | J31: =Financials!J6/Financials!I6-1 -> 0.0071044076 | K31: =Financials!K6/Financials!J6-1 -> 0.0065869115 | M31: =Financials!M6/Financials!K6-1 -> 0.010639702 | N31: =Financials!N6/Financials!M6-1 -> 0.0081929121 | O31: =Financials!O6/Financials!N6-1 -> -0.0048357133 | P31: =Financials!P6/Financials!O6-1 -> 0.012395002 | Q31: =Financials!Q6/Financials!P6-1 -> 0.070969256 | R31: =Financials!R6/Financials!Q6-1 -> -0.050036164 | S31: =Financials!S6/Financials!R6-1 -> 0.0044488181 | T31: =Financials!T6/Financials!S6-1 -> 0.00097322616 | U31: =Financials!U6/Financials!T6-1 -> 0.0033820163 | ... AL31: =Financials!AL6/Financials!AK6-1 -> -1
A32: FOSA Deposits | B32: NPR | C32: =Financials!C7/Financials!#REF!-1 -> #REF! | D32: =Financials!D7/Financials!C7-1 -> 0.0096172021 | E32: =Financials!E7/Financials!D7-1 -> 0.010186116 | F32: =Financials!F7/Financials!E7-1 -> 0.0098952586 | G32: =Financials!G7/Financials!F7-1 -> 0.0081377869 | H32: =Financials!H7/Financials!G7-1 -> 0.0020322336 | I32: =Financials!I7/Financials!H7-1 -> 0.005535562 | J32: =Financials!J7/Financials!I7-1 -> 0.006176856 | K32: =Financials!K7/Financials!J7-1 -> 0.0070407748 | M32: =Financials!M7/Financials!K7-1 -> 0.016191387 | N32: =Financials!N7/Financials!M7-1 -> 0.0089112822 | O32: =Financials!O7/Financials!N7-1 -> -0.0057200271 | P32: =Financials!P7/Financials!O7-1 -> 0.010967822 | Q32: =Financials!Q7/Financials!P7-1 -> 0.0040761408 | R32: =Financials!R7/Financials!Q7-1 -> 0.01347648 | S32: =Financials!S7/Financials!R7-1 -> 0.0065534735 | T32: =Financials!T7/Financials!S7-1 -> -0.0016462148 | U32: =Financials!U7/Financials!T7-1 -> 0.0037943792 | ... AL32: =Financials!AL7/Financials!AK7-1 -> -1
A33: BOSA Deposits | B33: NPR | C33: =Financials!C8/Financials!#REF!-1 -> #REF! | D33: =Financials!D8/Financials!C8-1 -> -0.65449686 | E33: =Financials!E8/Financials!D8-1 -> 0.0969453 | F33: =Financials!F8/Financials!E8-1 -> 2.2908379 | G33: =Financials!G8/Financials!F8-1 -> -0.50136689 | H33: =Financials!H8/Financials!G8-1 -> 0.10086887 | I33: =Financials!I8/Financials!H8-1 -> -0.35015024 | J33: =Financials!J8/Financials!I8-1 -> 0.10477832 | K33: =Financials!K8/Financials!J8-1 -> -0.012088443 | M33: =Financials!M8/Financials!K8-1 -> -0.38146757 | N33: =Financials!N8/Financials!M8-1 -> -0.018425641 | O33: =Financials!O8/Financials!N8-1 -> 0.09440296 | P33: =Financials!P8/Financials!O8-1 -> 0.099054199 | Q33: =Financials!Q8/Financials!P8-1 -> 6.458176 | R33: =Financials!R8/Financials!Q8-1 -> -0.87050683 | S33: =Financials!S8/Financials!R8-1 -> -0.18314807 | T33: =Financials!T8/Financials!S8-1 -> 0.26448562 | U33: =Financials!U8/Financials!T8-1 -> -0.012675331 | ... AL33: =Financials!AL8/Financials!AK8-1 -> -1
A34: Net Loans & advances | B34: NPR | C34: =Financials!C9/Financials!#REF!-1 -> #REF! | D34: =Financials!D9/Financials!C9-1 -> #DIV/0! | E34: =Financials!E9/Financials!D9-1 -> #DIV/0! | F34: =Financials!F9/Financials!E9-1 -> #DIV/0! | G34: =Financials!G9/Financials!F9-1 -> #DIV/0! | H34: =Financials!H9/Financials!G9-1 -> 0 | I34: =Financials!I9/Financials!H9-1 -> -0.027777778 | J34: =Financials!J9/Financials!I9-1 -> -0.028571429 | K34: =Financials!K9/Financials!J9-1 -> -0.029411765 | M34: =Financials!M9/Financials!K9-1 -> -0.060606061 | N34: =Financials!N9/Financials!M9-1 -> -0.032258065 | O34: =Financials!O9/Financials!N9-1 -> -1.02e-09 | P34: =Financials!P9/Financials!O9-1 -> -0.033333332 | Q34: =Financials!Q9/Financials!P9-1 -> -0.068965517 | R34: =Financials!R9/Financials!Q9-1 -> -0.037037037 | S34: =Financials!S9/Financials!R9-1 -> -0.038461538 | T34: =Financials!T9/Financials!S9-1 -> -0.04 | U34: =Financials!U9/Financials!T9-1 -> -0.041666667 | ... AL34: =Financials!AL9/Financials!AK9-1 -> -1
A35: Core capital | B35: NPR | C35: =Financials!C10/Financials!#REF!-1 -> #REF! | D35: =Financials!D10/Financials!C10-1 -> 0.49212484 | E35: =Financials!E10/Financials!D10-1 -> 0.031521443 | F35: =Financials!F10/Financials!E10-1 -> -0.84944629 | G35: =Financials!G10/Financials!F10-1 -> -0.76488237 | H35: =Financials!H10/Financials!G10-1 -> 3.0215384 | I35: =Financials!I10/Financials!H10-1 -> 0.081781273 | J35: =Financials!J10/Financials!I10-1 -> -0.68124082 | K35: =Financials!K10/Financials!J10-1 -> -0.034120858 | M35: =Financials!M10/Financials!K10-1 -> -0.23160773 | N35: =Financials!N10/Financials!M10-1 -> -0.091965196 | O35: =Financials!O10/Financials!N10-1 -> 28.351184 | P35: =Financials!P10/Financials!O10-1 -> -0.96874131 | Q35: =Financials!Q10/Financials!P10-1 -> 0.042699264 | R35: =Financials!R10/Financials!Q10-1 -> -0.61586547 | S35: =Financials!S10/Financials!R10-1 -> -1.1109971 | T35: =Financials!T10/Financials!S10-1 -> -2.9425528 | U35: =Financials!U10/Financials!T10-1 -> 2.6054826 | ... AL35: =Financials!AL10/Financials!AK10-1 -> -1
A36: Total Gross Income | B36: NPR | C36: =Financials!C11/Financials!#REF!-1 -> #REF! | D36: =Financials!D11/Financials!C11-1 -> #DIV/0! | E36: =Financials!E11/Financials!D11-1 -> #DIV/0! | F36: =Financials!F11/Financials!E11-1 -> #DIV/0! | G36: =Financials!G11/Financials!F11-1 -> #DIV/0! | H36: =Financials!H11/Financials!G11-1 -> #DIV/0! | I36: =Financials!I11/Financials!H11-1 -> #DIV/0! | J36: =Financials!J11/Financials!I11-1 -> #DIV/0! | K36: =Financials!K11/Financials!J11-1 -> #DIV/0! | M36: =Financials!M11/Financials!K11-1 -> #DIV/0! | N36: =Financials!N11/Financials!M11-1 -> #DIV/0! | O36: =Financials!O11/Financials!N11-1 -> #DIV/0! | P36: =Financials!P11/Financials!O11-1 -> #DIV/0! | Q36: =Financials!Q11/Financials!P11-1 -> #DIV/0! | R36: =Financials!R11/Financials!Q11-1 -> #DIV/0! | S36: =Financials!S11/Financials!R11-1 -> #DIV/0! | T36: =Financials!T11/Financials!S11-1 -> #DIV/0! | U36: =Financials!U11/Financials!T11-1 -> #DIV/0! | ... AL36: =Financials!AL11/Financials!AK11-1 -> #DIV/0!
A37: Membership | B37: NPR | C37: =Financials!C12/Financials!#REF!-1 -> #REF! | D37: =Financials!D12/Financials!C12-1 -> #DIV/0! | E37: =Financials!E12/Financials!D12-1 -> #DIV/0! | F37: =Financials!F12/Financials!E12-1 -> #DIV/0! | G37: =Financials!G12/Financials!F12-1 -> #DIV/0! | H37: =Financials!H12/Financials!G12-1 -> #DIV/0! | I37: =Financials!I12/Financials!H12-1 -> #DIV/0! | J37: =Financials!J12/Financials!I12-1 -> #DIV/0! | K37: =Financials!K12/Financials!J12-1 -> #DIV/0! | M37: =Financials!M12/Financials!K12-1 -> #DIV/0! | N37: =Financials!N12/Financials!M12-1 -> #DIV/0! | O37: =Financials!O12/Financials!N12-1 -> #DIV/0! | P37: =Financials!P12/Financials!O12-1 -> #DIV/0! | Q37: =Financials!Q12/Financials!P12-1 -> #DIV/0! | R37: =Financials!R12/Financials!Q12-1 -> #DIV/0! | S37: =Financials!S12/Financials!R12-1 -> #DIV/0! | T37: =Financials!T12/Financials!S12-1 -> #DIV/0! | U37: =Financials!U12/Financials!T12-1 -> #DIV/0! | ... AL37: =Financials!AL12/Financials!AK12-1 -> #DIV/0!
A39: Efficiency Ratios
A40: FinCost-Deposits/Average Deposits | B40: NPR | C40: =Financials!C48/((Financials!C6+Financials!#REF!)/2) -> #REF! | D40: =Financials!D48/((Financials!D6+Financials!C6)/2) -> 7.9598452e-05 | E40: =Financials!E48/((Financials!E6+Financials!D6)/2) -> 7.9586259e-05 | F40: =Financials!F48/((Financials!F6+Financials!E6)/2) -> 7.7715167e-05 | G40: =Financials!G48/((Financials!G6+Financials!F6)/2) -> 7.6754433e-05 | H40: =Financials!H48/((Financials!H6+Financials!G6)/2) -> 7.7021527e-05 | I40: =Financials!I48/((Financials!I6+Financials!H6)/2) -> 7.6939167e-05 | J40: =Financials!J48/((Financials!J6+Financials!I6)/2) -> 7.6744755e-05 | K40: =Financials!K48/((Financials!K6+Financials!J6)/2) -> 7.6223028e-05 | M40: =Financials!M48/((Financials!M6+Financials!K6)/2) -> 0.00028392081 | N40: =Financials!N48/((Financials!N6+Financials!M6)/2) -> 0.00028622533 | O40: =Financials!O48/((Financials!O6+Financials!N6)/2) -> 0.080215315 | P40: =Financials!P48/((Financials!P6+Financials!O6)/2) -> 0 | Q40: =Financials!Q48/((Financials!Q6+Financials!P6)/2) -> 1.1623066e-06 | R40: =Financials!R48/((Financials!R6+Financials!Q6)/2) -> 0 | S40: =Financials!S48/((Financials!S6+Financials!R6)/2) -> 0 | T40: =Financials!T48/((Financials!T6+Financials!S6)/2) -> 0 | U40: =Financials!U48/((Financials!U6+Financials!T6)/2) -> 0 | ... AL40: =Financials!AL48/((Financials!AL6+Financials!AK6)/2) -> 0
A41: FinCost-Shares/Average Share capital | B41: NPR | C41: =Financials!C49/((Financials!C7+Financials!#REF!)/2) -> #REF! | D41: =Financials!D49/((Financials!D7+Financials!C7)/2) -> 0 | E41: =Financials!E49/((Financials!E7+Financials!D7)/2) -> 0 | F41: =Financials!F49/((Financials!F7+Financials!E7)/2) -> 0 | G41: =Financials!G49/((Financials!G7+Financials!F7)/2) -> 0 | H41: =Financials!H49/((Financials!H7+Financials!G7)/2) -> 0 | I41: =Financials!I49/((Financials!I7+Financials!H7)/2) -> 0 | J41: =Financials!J49/((Financials!J7+Financials!I7)/2) -> 0 | K41: =Financials!K49/((Financials!K7+Financials!J7)/2) -> 0 | M41: =Financials!M49/((Financials!M7+Financials!K7)/2) -> 0 | N41: =Financials!N49/((Financials!N7+Financials!M7)/2) -> 0 | O41: =Financials!O49/((Financials!O7+Financials!N7)/2) -> 0 | P41: =Financials!P49/((Financials!P7+Financials!O7)/2) -> 0 | Q41: =Financials!Q49/((Financials!Q7+Financials!P7)/2) -> 0 | R41: =Financials!R49/((Financials!R7+Financials!Q7)/2) -> 0 | S41: =Financials!S49/((Financials!S7+Financials!R7)/2) -> 0 | T41: =Financials!T49/((Financials!T7+Financials!S7)/2) -> 0 | U41: =Financials!U49/((Financials!U7+Financials!T7)/2) -> 0 | ... AL41: =Financials!AL49/((Financials!AL7+Financials!AK7)/2) -> 0
A42: FinCost-Ext Loans/Average Ext Loans | B42: NPR | C42: =Financials!C50/((Financials!C8+Financials!#REF!)/2) -> #REF! | D42: =Financials!D50/((Financials!D8+Financials!C8)/2) -> 0 | E42: =Financials!E50/((Financials!E8+Financials!D8)/2) -> 0 | F42: =Financials!F50/((Financials!F8+Financials!E8)/2) -> 0 | G42: =Financials!G50/((Financials!G8+Financials!F8)/2) -> 0 | H42: =Financials!H50/((Financials!H8+Financials!G8)/2) -> 0 | I42: =Financials!I50/((Financials!I8+Financials!H8)/2) -> 0 | J42: =Financials!J50/((Financials!J8+Financials!I8)/2) -> 0 | K42: =Financials!K50/((Financials!K8+Financials!J8)/2) -> 0 | M42: =Financials!M50/((Financials!M8+Financials!K8)/2) -> 0 | N42: =Financials!N50/((Financials!N8+Financials!M8)/2) -> 0 | O42: =Financials!O50/((Financials!O8+Financials!N8)/2) -> 0 | P42: =Financials!P50/((Financials!P8+Financials!O8)/2) -> 0 | Q42: =Financials!Q50/((Financials!Q8+Financials!P8)/2) -> 0 | R42: =Financials!R50/((Financials!R8+Financials!Q8)/2) -> 0 | S42: =Financials!S50/((Financials!S8+Financials!R8)/2) -> 0 | T42: =Financials!T50/((Financials!T8+Financials!S8)/2) -> 0 | U42: =Financials!U50/((Financials!U8+Financials!T8)/2) -> 0 | ... AL42: =Financials!AL50/((Financials!AL8+Financials!AK8)/2) -> 0
A43: OpEx/Average Total Assets | B43: NPR | C43: =Financials!C51/((Financials!C9+Financials!#REF!)/2) -> #REF! | D43: =Financials!D51/((Financials!D9+Financials!C9)/2) -> #REF! | E43: =Financials!E51/((Financials!E9+Financials!D9)/2) -> #REF! | F43: =Financials!F51/((Financials!F9+Financials!E9)/2) -> #REF! | G43: =Financials!G51/((Financials!G9+Financials!F9)/2) -> #REF! | H43: =Financials!H51/((Financials!H9+Financials!G9)/2) -> #REF! | I43: =Financials!I51/((Financials!I9+Financials!H9)/2) -> #REF! | J43: =Financials!J51/((Financials!J9+Financials!I9)/2) -> #REF! | K43: =Financials!K51/((Financials!K9+Financials!J9)/2) -> #REF! | M43: =Financials!M51/((Financials!M9+Financials!K9)/2) -> #REF! | N43: =Financials!N51/((Financials!N9+Financials!M9)/2) -> #REF! | O43: =Financials!O51/((Financials!O9+Financials!N9)/2) -> #REF! | P43: =Financials!P51/((Financials!P9+Financials!O9)/2) -> #REF! | Q43: =Financials!Q51/((Financials!Q9+Financials!P9)/2) -> #REF! | R43: =Financials!R51/((Financials!R9+Financials!Q9)/2) -> #REF! | S43: =Financials!S51/((Financials!S9+Financials!R9)/2) -> #REF! | T43: =Financials!T51/((Financials!T9+Financials!S9)/2) -> #REF! | U43: =Financials!U51/((Financials!U9+Financials!T9)/2) -> #REF! | ... AL43: =Financials!AL51/((Financials!AL9+Financials!AK9)/2) -> #REF!
A44: Avge yield on Net loans | B44: NPR | C44: =Financials!C52/((Financials!C10+Financials!#REF!)/2) -> #REF! | D44: =Financials!D52/((Financials!D10+Financials!C10)/2) -> 0.0104511 | E44: =Financials!E52/((Financials!E10+Financials!D10)/2) -> 0.021578656 | F44: =Financials!F52/((Financials!F10+Financials!E10)/2) -> 0.049729994 | G44: =Financials!G52/((Financials!G10+Financials!F10)/2) -> 0.46052965 | H44: =Financials!H52/((Financials!H10+Financials!G10)/2) -> 0.50184094 | I44: =Financials!I52/((Financials!I10+Financials!H10)/2) -> 0.35744441 | J44: =Financials!J52/((Financials!J10+Financials!I10)/2) -> 0.81545611 | K44: =Financials!K52/((Financials!K10+Financials!J10)/2) -> 2.0446545 | M44: =Financials!M52/((Financials!M10+Financials!K10)/2) -> 2.7190342 | N44: =Financials!N52/((Financials!N10+Financials!M10)/2) -> 3.5044769 | O44: =Financials!O52/((Financials!O10+Financials!N10)/2) -> 0.18017044 | P44: =Financials!P52/((Financials!P10+Financials!O10)/2) -> 0.023973321 | Q44: =Financials!Q52/((Financials!Q10+Financials!P10)/2) -> 1.103438 | R44: =Financials!R52/((Financials!R10+Financials!Q10)/2) -> 2.3858862 | S44: =Financials!S52/((Financials!S10+Financials!R10)/2) -> 11.23607 | T44: =Financials!T52/((Financials!T10+Financials!S10)/2) -> 103.94352 | U44: =Financials!U52/((Financials!U10+Financials!T10)/2) -> 14.171966 | ... AL44: =Financials!AL52/((Financials!AL10+Financials!AK10)/2) -> 1.1937277
A46: Liquidity Ratio
A47: minimum Liquidity | B47: 0.15 | C47: =SFP!B4/(SFP!B29+SFP!B31-SFP!B37) -> 0.052678335 | D47: =SFP!C4/(SFP!C29+SFP!C31-SFP!C37) -> 0.04943154 | E47: =SFP!D4/(SFP!D29+SFP!D31-SFP!D37) -> 0.057427859 | F47: =SFP!E4/(SFP!E29+SFP!E31-SFP!E37) -> 0.02794344 | G47: =SFP!F4/(SFP!F29+SFP!F31-SFP!F37) -> 0.10230266 | H47: =SFP!G4/(SFP!G29+SFP!G31-SFP!G37) -> 0.1651514 | I47: =SFP!H4/(SFP!H29+SFP!H31-SFP!H37) -> 0.10248194 | J47: =SFP!I4/(SFP!I29+SFP!I31-SFP!I37) -> 0.14982033 | K47: =SFP!J4/(SFP!J29+SFP!J31-SFP!J37) -> 0.097579544 | M47: =SFP!L4/(SFP!L29+SFP!L31-SFP!L37) -> 0.15163254 | N47: =SFP!M4/(SFP!M29+SFP!M31-SFP!M37) -> 0.16022177 | O47: =SFP!N4/(SFP!N29+SFP!N31-SFP!N37) -> 0.15403297 | P47: =SFP!O4/(SFP!O29+SFP!O31-SFP!O37) -> 0.11159314 | Q47: =SFP!P4/(SFP!P29+SFP!P31-SFP!P37) -> 0.13606139 | R47: =SFP!Q4/(SFP!Q29+SFP!Q31-SFP!Q37) -> 0.037504209 | S47: =SFP!R4/(SFP!R29+SFP!R31-SFP!R37) -> 0.084233869 | T47: =SFP!S4/(SFP!S29+SFP!S31-SFP!S37) -> 0.10172856 | ... AL47: =SFP!AK4/(SFP!AK29+SFP!AK31-SFP!AK37) -> #DIV/0!
A48: technical Liquidity | C48: =SFP!B4/(SFP!B30+SFP!B31-SFP!B37) -> 0.05096049 | D48: =SFP!C4/(SFP!C30+SFP!C31-SFP!C37) -> 0.048758865 | E48: =SFP!D4/(SFP!D30+SFP!D31-SFP!D37) -> 0.056602599 | F48: =SFP!E4/(SFP!E30+SFP!E31-SFP!E37) -> 0.026801458 | G48: =SFP!F4/(SFP!F30+SFP!F31-SFP!F37) -> 0.099970977 | H48: =SFP!G4/(SFP!G30+SFP!G31-SFP!G37) -> 0.16108422 | I48: =SFP!H4/(SFP!H30+SFP!H31-SFP!H37) -> 0.10070734 | J48: =SFP!I4/(SFP!I30+SFP!I31-SFP!I37) -> 0.14706507 | K48: =SFP!J4/(SFP!J30+SFP!J31-SFP!J37) -> 0.095827669 | M48: =SFP!L4/(SFP!L30+SFP!L31-SFP!L37) -> 0.14972248 | N48: =SFP!M4/(SFP!M30+SFP!M31-SFP!M37) -> 0.15831522 | O48: =SFP!N4/(SFP!N30+SFP!N31-SFP!N37) -> 0.15222285 | P48: =SFP!O4/(SFP!O30+SFP!O31-SFP!O37) -> 0.1100123 | Q48: =SFP!P4/(SFP!P30+SFP!P31-SFP!P37) -> 0.12577879 | R48: =SFP!Q4/(SFP!Q30+SFP!Q31-SFP!Q37) -> 0.036980209 | S48: =SFP!R4/(SFP!R30+SFP!R31-SFP!R37) -> 0.083229587 | T48: =SFP!S4/(SFP!S30+SFP!S31-SFP!S37) -> 0.10025315 | ... AL48: =SFP!AK4/(SFP!AK30+SFP!AK31-SFP!AK37) -> #DIV/0!
A49: Loan Loss Provisions Ratios
A50: Actual LLP / Required LLP | B50: 1
A52: Loan interest/Net Loans | C52: =SCI!B5/SFP!#REF! -> #REF! | D52: =SCI!C5/SFP!#REF! -> #REF! | E52: =SCI!D5/SFP!#REF! -> #REF! | F52: =SCI!E5/SFP!#REF! -> #REF! | G52: =SCI!F5/SFP!B14 -> 0.055173994 | H52: =SCI!G5/SFP!C14 -> 0.063939364 | I52: =SCI!H5/SFP!D14 -> 0.073601371 | J52: =SCI!I5/SFP!E14 -> 0.084653021 | K52: =SCI!J5/SFP!F14 -> 0.094705486 | M52: =SCI!K5/SFP!G14 -> 0 | N52: =SCI!L5/SFP!H14 -> 0.11572214 | O52: =SCI!M5/SFP!I14 -> 0.12496543 | P52: =SCI!N5/SFP!J14 -> 0.20040705 | Q52: =SCI!O5/SFP!K14 -> #DIV/0! | R52: =SCI!P5/SFP!L14 -> 0.019840496 | S52: =SCI!Q5/SFP!M14 -> 0.044852949 | T52: =SCI!R5/SFP!N14 -> 0.056403608 | ... AC52: =SCI!AA5/SFP!W14 -> 0.032913462
A54: RETURN ON ASSETS | C54: =SCI!B33/((SFP!#REF!+SFP!#REF!)/2) -> #REF! | D54: =SCI!C33/((SFP!#REF!+SFP!#REF!)/2) -> #REF! | E54: =SCI!D33/((SFP!#REF!+SFP!#REF!)/2) -> #REF! | F54: =SCI!E33/((SFP!#REF!+SFP!#REF!)/2) -> #REF! | G54: =SCI!F33/((SFP!#REF!+SFP!B26)/2) -> #REF! | H54: =SCI!G33/((SFP!#REF!+SFP!C26)/2) -> #REF! | I54: =SCI!H33/((SFP!#REF!+SFP!D26)/2) -> #REF! | J54: =SCI!I33/((SFP!#REF!+SFP!E26)/2) -> #REF! | K54: =SCI!J33/((SFP!#REF!+SFP!F26)/2) -> #REF! | M54: =SCI!K33/((SFP!#REF!+SFP!G26)/2) -> #REF! | N54: =SCI!L33/((SFP!#REF!+SFP!H26)/2) -> #REF! | O54: =SCI!M33/((SFP!#REF!+SFP!I26)/2) -> #REF! | P54: =SCI!N33/((SFP!#REF!+SFP!J26)/2) -> #REF! | Q54: =SCI!O33/((SFP!#REF!+SFP!K26)/2) -> #REF! | R54: =SCI!P33/((SFP!#REF!+SFP!L26)/2) -> #REF! | S54: =SCI!Q33/((SFP!#REF!+SFP!M26)/2) -> #REF! | T54: =SCI!R33/((SFP!#REF!+SFP!N26)/2) -> #REF! | ... AC54: =SCI!AA33/((SFP!#REF!+SFP!W26)/2) -> #REF!
A55: COST INCOME RATIO | C55: =SCI!B23/SCI!B19 -> 0.32960388 | D55: =SCI!C23/SCI!C19 -> 0.3278792 | E55: =SCI!D23/SCI!D19 -> 0.34205167 | F55: =SCI!E23/SCI!E19 -> 0.29343796 | G55: =SCI!F23/SCI!F19 -> 0.31470926 | H55: =SCI!G23/SCI!G19 -> 0.30926457 | I55: =SCI!H23/SCI!H19 -> 0.34470604 | J55: =SCI!I23/SCI!I19 -> 0.37670142 | K55: =SCI!J23/SCI!J19 -> 0.39900946 | M55: =SCI!K23/SCI!K19 -> #DIV/0! | N55: =SCI!L23/SCI!L19 -> 0.44670853 | O55: =SCI!M23/SCI!M19 -> 0.47529787 | P55: =SCI!N23/SCI!N19 -> 0.69569633 | Q55: =SCI!O23/SCI!O19 -> 0.31618742 | R55: =SCI!P23/SCI!P19 -> 0.61703144 | S55: =SCI!Q23/SCI!Q19 -> 0.53251523 | T55: =SCI!R23/SCI!R19 -> 0.47222087 | ... AC55: =SCI!AA23/SCI!AA19 -> 24.783439
A56: OPERATING EXPENSE RATIO | C56: =SCI!B23/SFP!#REF! -> #REF! | D56: =SCI!C23/SFP!#REF! -> #REF! | E56: =SCI!D23/SFP!#REF! -> #REF! | F56: =SCI!E23/SFP!#REF! -> #REF! | G56: =SCI!F23/SFP!B26 -> 0.013684228 | H56: =SCI!G23/SFP!C26 -> 0.015325798 | I56: =SCI!H23/SFP!D26 -> 0.019189756 | J56: =SCI!I23/SFP!E26 -> 0.024406287 | K56: =SCI!J23/SFP!F26 -> 0.027375724 | M56: =SCI!K23/SFP!G26 -> 0 | N56: =SCI!L23/SFP!H26 -> 0.033952244 | O56: =SCI!M23/SFP!I26 -> 0.039138935 | P56: =SCI!N23/SFP!J26 -> 0.032690868 | Q56: =SCI!O23/SFP!K26 -> #DIV/0! | R56: =SCI!P23/SFP!L26 -> 0.0074579391 | S56: =SCI!Q23/SFP!M26 -> 0.015325599 | T56: =SCI!R23/SFP!N26 -> 0.016044316 | ... AC56: =SCI!AA23/SFP!W26 -> -0.0093652058
A57: LIQUID ASSETS/TOTAL ASSETS | C57: =(Financials!C36+Financials!C29)/Financials!C5 -> 0.039912056 | D57: =(Financials!D36+Financials!D29)/Financials!D5 -> 0.038341157 | E57: =(Financials!E36+Financials!E29)/Financials!E5 -> 0.044287731 | F57: =(Financials!F36+Financials!F29)/Financials!F5 -> 0.020717044 | G57: =(Financials!G36+Financials!G29)/Financials!G5 -> 0.071979091 | H57: =(Financials!H36+Financials!H29)/Financials!H5 -> 0.11504368 | I57: =(Financials!I36+Financials!I29)/Financials!I5 -> 0.072439614 | J57: =(Financials!J36+Financials!J29)/Financials!J5 -> 0.10564347 | K57: =(Financials!K36+Financials!K29)/Financials!K5 -> 0.068929074 | M57: =(Financials!M36+Financials!M29)/Financials!M5 -> 0.10771005 | N57: =(Financials!N36+Financials!N29)/Financials!N5 -> 0.11425239 | O57: =(Financials!O36+Financials!O29)/Financials!O5 -> 0.11540469 | P57: =(Financials!P36+Financials!P29)/Financials!P5 -> 0.10882483 | Q57: =(Financials!Q36+Financials!Q29)/Financials!Q5 -> 0.09669052 | R57: =(Financials!R36+Financials!R29)/Financials!R5 -> 0.027874902 | S57: =(Financials!S36+Financials!S29)/Financials!S5 -> 0.062570111 | T57: =(Financials!T36+Financials!T29)/Financials!T5 -> 0.074818495 | ... AC57: =(Financials!AC36+Financials!AC29)/Financials!AC5 -> 0.13853826
A58: ALLOWANCE FOR LOAN LOSS/NON PERFORMING L0ANS
A59: GROSS LOANS/TOTAL ASSETS | C59: =Financials!C32/Financials!C5 -> 0.54310459 | D59: =Financials!D32/Financials!D5 -> 0.5489432 | E59: =Financials!E32/Financials!E5 -> 0.54388336 | F59: =Financials!F32/Financials!F5 -> 0.55547327 | G59: =Financials!G32/Financials!G5 -> 0.52983979 | H59: =Financials!H32/Financials!H5 -> 0.51692832 | I59: =Financials!I32/Financials!I5 -> 0.52545164 | J59: =Financials!J32/Financials!J5 -> 0.53196176 | K59: =Financials!K32/Financials!K5 -> 0.53469116 | M59: =Financials!M32/Financials!M5 -> 0.53540869 | N59: =Financials!N32/Financials!N5 -> 0.53248665 | O59: =Financials!O32/Financials!O5 -> 0.51038433 | P59: =Financials!P32/Financials!P5 -> 0.73537117 | Q59: =Financials!Q32/Financials!Q5 -> 0.53661682 | R59: =Financials!R32/Financials!R5 -> 0.54561899 | S59: =Financials!S32/Financials!S5 -> 0.54136758 | T59: =Financials!T32/Financials!T5 -> 0.53639176 | ... AC59: =Financials!AC32/Financials!AC5 -> 0.54735656

Sheet form4 
B1: FORM 4 SASRA2/004
B2: RISK CLASSIFICATION OF ASSETS AND PROVISIONING
B3: SACCO SOCIETY CS NUMBER | F3: 2032
B4: FINANCIAL YEAR | F4: 2016
B5: START DATE: | F5: 1/1/2018
B6: END DATE: | F6: 31/3/2018
B7: PORTFOLIO AGEING REPORT
C8: A | D8: B | E8: C | F8: D
A9: NO. | B9: CLASSIFICATION | C9: NO. OF A/Cs | D9: OUTSTANDING LOAN PORTFOLIO(Kshs) | E9: REQUIRED PROVISION | F9: REQUIRED PROVISION AMOUNT(Kshs)
A10: 1 | B10: Performing | C10: 7828 | D10: 4.0796422e+08 | E10: 0.01 | F10: =D10*E10 -> 4079642.2
A11: 2 | B11: Watch | C11: 857 | D11: 1.0609857e+08 | E11: 0.05 | F11: =D11*E11 -> 5304928.5
A12: 3 | B12: Substandard | C12: 353 | D12: 40541696 | E12: 0.25 | F12: =D12*E12 -> 10135424
A13: 4 | B13: Doubtful | C13: 146 | D13: 16738133 | E13: 0.5 | F13: =D13*E13 -> 8369066.6
A14: 5 | B14: Loss | C14: 95 | D14: 19768434 | E14: 1 | F14: =D14*E14 -> 19768434 | G14: =SUM(D12:D14) -> 77048264
B15: subtotal | C15: =SUM(C10:C14) -> 9279 | D15: =SUM(D10:D14) -> 5.9111105e+08 | F15: =SUM(F10:F14) -> 47657496
B16: Reschedule/Renegotiated loans
A17: 1 | B17: Performing | C17: 0 | D17: 0 | E17: 0.01 | F17: =D17*E17 -> 0
A18: 2 | B18: Watch | C18: 0 | E18: 0.05 | F18: =D18*E18 -> 0
A19: 3 | B19: Substandard | E19: 0.25 | F19: =D19*E19 -> 0
A20: 4 | B20: Doubtful | C20: 0 | D20: 0 | E20: 0.5 | F20: =D20*E20 -> 0
A21: 5 | B21: Loss | C21: 0 | D21: 0 | E21: 1 | F21: =D21*E21 -> 0
B22: subtotal | C22: =SUM(C16:C21) -> 0 | D22: =SUM(D16:D21) -> 0 | F22: =SUM(F16:F21) -> 0
B23: GRAND TOTAL | C23: =C15+C22 -> 9279 | D23: =D15+D22 -> 5.9111105e+08 | F23: =F15+F22 -> 47657496
A25: Note: This return should be received on or before the 15th day of the month following end of every quarter
B28: FORM 4 SASRA2/004
B29: RISK CLASSIFICATION OF ASSETS AND PROVISIONING
B30: SACCO SOCIETY CS NUMBER | F30: 2032
B31: FINANCIAL YEAR | F31: 2016
B32: START DATE: | F32: 1/1/2018
B33: END DATE: | F33: 31/6/2018
B34: PORTFOLIO AGEING REPORT
C35: A | D35: B | E35: C | F35: D
A36: NO. | B36: CLASSIFICATION | C36: NO. OF A/Cs | D36: OUTSTANDING LOAN PORTFOLIO(Kshs) | E36: REQUIRED PROVISION | F36: REQUIRED PROVISION AMOUNT(Kshs)
A37: 1 | B37: Performing | C37: 7269 | D37: 3.9579531e+08 | E37: 0.01 | F37: =D37*E37 -> 3957953.1
A38: 2 | B38: Watch | C38: 1041 | D38: 97770529 | E38: 0.05 | F38: =D38*E38 -> 4888526.4
A39: 3 | B39: Substandard | C39: 772 | D39: 51701232 | E39: 0.25 | F39: =D39*E39 -> 12925308
A40: 4 | B40: Doubtful | C40: 377 | D40: 28331436 | E40: 0.5 | F40: =D40*E40 -> 14165718
A41: 5 | B41: Loss | C41: 639 | D41: 26413438 | E41: 1 | F41: =D41*E41 -> 26413438 | G41: =SUM(D39:D41) -> 1.064461e+08
B42: subtotal | C42: =SUM(C37:C41) -> 10098 | D42: =SUM(D37:D41) -> 6.0001195e+08 | F42: =SUM(F37:F41) -> 62350943
B43: Reschedule/Renegotiated loans
A44: 1 | B44: Performing | C44: 0 | D44: 0 | E44: 0.01 | F44: =D44*E44 -> 0
A45: 2 | B45: Watch | C45: 0 | E45: 0.05 | F45: =D45*E45 -> 0
A46: 3 | B46: Substandard | E46: 0.25 | F46: =D46*E46 -> 0 | G46: =SUM(D39:D41) -> 1.064461e+08
A47: 4 | B47: Doubtful | C47: 0 | D47: 0 | E47: 0.5 | F47: =D47*E47 -> 0 | G47: =G46/D42 -> 0.17740664
A48: 5 | B48: Loss | C48: 0 | D48: 0 | E48: 1 | F48: =D48*E48 -> 0
B49: subtotal | C49: =SUM(C43:C48) -> 0 | D49: =SUM(D43:D48) -> 0 | F49: =SUM(F43:F48) -> 0
B50: GRAND TOTAL | C50: =C42+C49 -> 10098 | D50: =D42+D49 -> 6.0001195e+08 | F50: =F42+F49 -> 62350943
A52: Note: This return should be received on or before the 15th day of the month following end of every quarter
B54: FORM 4 SASRA2/004
B55: RISK CLASSIFICATION OF ASSETS AND PROVISIONING
B56: SACCO SOCIETY CS NUMBER | F56: 2032
B57: FINANCIAL YEAR | F57: 2018
B58: START DATE: | F58: 1/1/2018
B59: END DATE: | F59: 30/9/2018
B60: PORTFOLIO AGEING REPORT
C61: A | D61: B | E61: C | F61: D
B62: CLASSIFICATION | C62: NO. OF A/Cs | D62: OUTSTANDING LOAN PORTFOLIO(Kshs) | E62: REQUIRED PROVISION | F62: REQUIRED PROVISION AMOUNT(Kshs)
B63: Performing | C63: 6517 | D63: 3.7477319e+08 | E63: 0.01 | F63: =D63*E63 -> 3747731.9
B64: Watch | C64: 1404 | D64: 1.5133837e+08 | E64: 0.05 | F64: =D64*E64 -> 7566918.7
B65: Substandard | C65: 685 | D65: 60509701 | E65: 0.25 | F65: =D65*E65 -> 15127425
B66: Doubtful | C66: 335 | D66: 25541760 | E66: 0.5 | F66: =D66*E66 -> 12770880
B67: Loss | C67: 543 | D67: 22647916 | E67: 1 | F67: =D67*E67 -> 22647916
B68: subtotal | C68: =SUM(C63:C67) -> 9484 | D68: =SUM(D63:D67) -> 6.3481094e+08 | F68: =SUM(F63:F67) -> 61860872
B69: Reschedule/Renegotiated loans
B70: Performing | C70: 0 | D70: 0 | E70: 0.01 | F70: =D70*E70 -> 0
B71: Watch | C71: 0 | E71: 0.05 | F71: =D71*E71 -> 0
B72: Substandard | E72: 0.25 | F72: =D72*E72 -> 0
B73: Doubtful | C73: 0 | D73: 0 | E73: 0.5 | F73: =D73*E73 -> 0
B74: Loss | C74: 0 | D74: 0 | E74: 1 | F74: =D74*E74 -> 0
B75: subtotal | C75: =SUM(C69:C74) -> 0 | D75: =SUM(D69:D74) -> 0 | F75: =SUM(F69:F74) -> 0
B76: GRAND TOTAL | C76: =C68+C75 -> 9484 | D76: =D68+D75 -> 6.3481094e+08 | F76: =F68+F75 -> 61860872
D79: Aud-2022
C80: A | D80: B | E80: C | F80: D
B81: CLASSIFICATION | C81: NO. OF A/Cs | D81: OUTSTANDING LOAN PORTFOLIO(Kshs) | E81: REQUIRED PROVISION | F81: REQUIRED PROVISION AMOUNT(Kshs)
B82: Performing | D82: 3423909321 | E82: 0.01 | F82: =D82*E82 -> 34239093
B83: Watch | D83: 226552704 | E83: 0.05 | F83: =D83*E83 -> 11327635
B84: Substandard | D84: 162502879 | E84: 0.25 | F84: =D84*E84 -> 40625720
B85: Doubtful | D85: 19518299 | E85: 0.5 | F85: =D85*E85 -> 9759149.5
B86: Loss | D86: 151715259 | E86: 1 | F86: =D86*E86 -> 151715259
B87: subtotal | C87: =SUM(C82:C86) -> 0 | D87: =SUM(D82:D86) -> 3984198462 | F87: =SUM(F82:F86) -> 2.4766686e+08
B88: Reschedule/Renegotiated loans
B89: Performing | C89: 0 | D89: 0 | E89: 0.01 | F89: =D89*E89 -> 0
B90: Watch | C90: 0 | E90: 0.05 | F90: =D90*E90 -> 0
B91: Substandard | E91: 0.25 | F91: =D91*E91 -> 0
B92: Doubtful | C92: 0 | D92: 0 | E92: 0.5 | F92: =D92*E92 -> 0
B93: Loss | C93: 0 | D93: 0 | E93: 1 | F93: =D93*E93 -> 0
B94: subtotal | C94: =SUM(C88:C93) -> 0 | D94: =SUM(D88:D93) -> 0 | F94: =SUM(F88:F93) -> 0
B95: GRAND TOTAL | C95: =C87+C94 -> 0 | D95: =D87+D94 -> 3984198462 | F95: =F87+F94 -> 2.4766686e+08

Sheet Sacco Performance
A1: ELIMU SACCO SOCIETY LIMITED
A2: PERFORMANCE AND COMPLIANCE REPORT AS AT : 30th September , 2018
B3: Prud Std | C3: Audited | D3: Returns | H3: Aggregate for all Licensed Saccos
C4: 2017 | D4: 43177 | E4: 43269 | F4: Validated July 2018 | G4: 43361
A5: A. CAPITAL ADEQUACY
A6: Core Capital | B6: ≥10M | C6: =C33 -> #REF! | D6: =D33 -> 7.3299343e+08 | E6: =E33 -> 7.9373315e+08 | F6: =F33 -> 2.2099178e+08 | G6: =G33 -> 8.2243382e+08 | H6: =H33 -> 68610901181
A7: Core Capital/Total Assets | B7: ≥10% | C7: =C33/C29 -> #REF! | D7: =D33/D29 -> 0.6736286 | E7: =E33/E29 -> 0.7539301 | F7: =F33/F29 -> 0.20503177 | G7: =G33/G29 -> 0.75356327 | H7: =H33/H29 -> 0.14576061
A8: Institutional Capital/Total Assets | B8: ≥8% | C8: =C34/C29 -> #REF! | D8: =D34/D29 -> 0.26909141 | E8: =E34/E29 -> 0.33557169 | F8: =F34/F29 -> 0.095871936 | G8: =G34/G29 -> 0.35023712 | H8: =H34/H29 -> 0.080885761
A9: B. ASSET QUALITY
A10: NPL (Substandard+Doubtful+Loss) | B10: <5% | C10: =C35/C32 -> 0.15518115 | D10: =D35/D32 -> 0 | E10: =E35/E32 -> 0.17740664 | F10: =F35/F32 -> 0.24924475 | G10: =G35/G32 -> 0 | H10: =H35/H32 -> 0.073088911
A11: Non-Earning Assets | B11: <10% | C11: =C36/C29 -> 0.19600848 | D11: =D36/D29 -> 0.22705784 | E11: =E36/E29 -> 0.18079154 | F11: =F36/F29 -> 0.20917825 | G11: =G36/G29 -> 0.21814514 | H11: =H36/H29 -> 0.12029808
A12: Equity investments/Deposits | B12: <5% | C12: =C38/C31 -> 0.18442583 | D12: =D38/D31 -> 0.1891277 | E12: =E38/E31 -> 0.18474351 | F12: =F38/F31 -> 0.1839376 | G12: =G38/G31 -> 0.18073695 | H12: =H38/H31 -> 0.041108343
A13: Equity investments/Core capital | B13: <40% | C13: =C38/C33 -> #REF! | D13: =D38/D33 -> 0.20488614 | E13: =E38/E33 -> 0.18920741 | F13: =F38/F33 -> 0.67957365 | G13: =G38/G33 -> 0.18260459 | H13: =H38/H33 -> 0.19682259
A14: C. EARNINGS RATING
A15: Yield on Gross Loans | C15: =C44/C32 -> 0.22818323 | D15: =D44/D32 -> 0.077318822 | E15: =E44/E32 -> 0.15889458 | F15: =F44/F32 -> 0.18194977 | G15: =G44/G32 -> 0.22085733 | H15: =H44/H32 -> 0.094781906
A16: Total Expense/Total Income | C16: =C47/C43 -> 0.9138699 | D16: =D47/D43 -> 0.70485127 | E16: =E47/E43 -> 0.76136421 | F16: =F47/F43 -> 0.78869343 | G16: =G47/G43 -> 0.68993115 | H16: =H47/H43 -> 0.71962332
A17: Net Income/Average Assets (ROA) | C17: =C48/C30 -> 0.003791183 | D17: =D48/D30 -> 0.0097610884 | E17: =E48/E30 -> 0.016868344 | F17: =F48/F30 -> 0.022524417 | G17: =G48/G30 -> 0.033879707 | H17: =H48/H30 -> 0.02537129
A18: Operating Expenses/Financial Income (OPEX) | C18: =C46/C43 -> 0.7258397 | D18: =D46/D43 -> 0.69047378 | E18: =E46/E43 -> 0.73917345 | F18: =F46/F43 -> 0.70969989 | G18: =G46/G43 -> 0.66759028 | H18: =H46/H43 -> 0.34015828
A19: D. LIQUIDITY
A20: Liquid Assets/Short-term Liabilities | B20: >15% | C20: =C40/C41 -> 1.6100339 | D20: =D40/D41 -> 1.8231656 | E20: =E40/E41 -> 2.8116034 | F20: =F40/F41 -> 2.4337011 | G20: =G40/G41 -> 1.8877413 | H20: =H40/H41 -> 0.48530882
A21: External Borrowing/Total Assets | B21: <25% | C21: =C42/C29 -> 0 | D21: =D42/D29 -> 0 | E21: =E42/E29 -> 0 | F21: =F42/F29 -> 0 | G21: =G42/G29 -> 0 | H21: =H42/H29 -> 0.096313502
A22: Liquid Assets/Total Assets | C22: =C40/C29 -> 0.14699391 | D22: =D40/D29 -> 0.15140203 | E22: =E40/E29 -> 0.1588437 | F22: =F40/F29 -> 0.14013085 | G22: =G40/G29 -> 0.11447686 | H22: =H40/H29 -> 0.089910796
A23: E. STRUCTURE/SENSITIVITY TO RISK
A24: Gross loans /Total Assets | B24: 70-80 | C24: =C32/C29 -> 0.55689684 | D24: =D32/D29 -> 0.52756552 | E24: =E32/E29 -> 0.56992337 | F24: =F32/F29 -> 0.56614222 | G24: =G32/G29 -> 0.58165192 | H24: =H32/H29 -> 0.76593828
A25: Gross loans/Deposits | B25: >100% | C25: =C32/C31 -> 0.74803016 | D25: =D32/D31 -> 0.72293367 | E25: =E32/E31 -> 0.73810209 | F25: =F32/F31 -> 0.74737464 | G25: =G32/G31 -> 0.7639742 | H25: =H32/H31 -> 1.0975103
A26: Financial Investments/Total Assets | C26: =C39/C31 -> 0.20252188 | D26: =D39/D31 -> 0.19891937 | E26: =E39/E31 -> 0.18933826 | F26: =F39/F31 -> 0.18889199 | G26: =G39/G31 -> 0.18635655 | H26: =H39/H31 -> 0.063036125
A27: Dividends+Interest on Deposits/Total Income | C27: =C45/C43 -> 0.18406516 | D27: =D45/D43 -> 0 | E27: =E45/E43 -> 0 | F27: =F45/F43 -> 0.0018601715 | G27: =G45/G43 -> 0 | H27: =H45/H43 -> 0.30223696
A28: F. KEY FINANCIAL STATISTICS
A29: Total Assets | C29: 1041432343 | D29: 1088126951 | E29: 1052794079 | F29: 1.0778417e+09 | G29: 1091393186 | H29: 470709475259
A30: Average Assets | C30: 1.0415699e+09 | D30: 1.0543316e+09 | E30: 1023665177 | F30: 1.0596111e+09 | G30: 1046817819 | H30: 445555825332
A31: Total Deposits | C31: 775330209 | D31: 794067676 | E31: 812911867 | F31: 8.1647361e+08 | G31: 830932439 | H31: 328502062217
A32: Gross Loans | C32: 579970379 | D32: 574058263 | E32: 600011946 | F32: 6.1021167e+08 | G32: 634810944 | H32: 360534406503
A33: Core Capital | C33: =SFP!#REF!+SFP!#REF!+SFP!#REF!+(0.5*SFP!#REF!)+SFP!#REF!+SFP!#REF! -> #REF! | D33: =Financials!D59 -> 7.3299343e+08 | E33: =Financials!G59 -> 7.9373315e+08 | F33: 2.2099178e+08 | G33: =Financials!J59 -> 8.2243382e+08 | H33: 68610901181
A34: Institutional Capital | C34: =C33-SFP!#REF! -> #REF! | D34: =D33-SFP!C39 -> 2.9280562e+08 | E34: =E33-SFP!F39 -> 3.5328789e+08 | F34: 1.0333477e+08 | G34: =G33-SFP!D39 -> 3.8224641e+08 | H34: 38073694210
A35: Non-performing Loans | C35: 90000468 | D35: =Financials!D34 -> 0 | E35: 1.064461e+08 | F35: 152092052 | G35: =Financials!J34 -> 0 | H35: 26351067235
A36: Non-Earning Assets | C36: 204129574 | D36: 247067758 | E36: 190336258 | F36: 2.2546103e+08 | G36: 238082118 | H36: 56625446555
A37: Property and Equipment | C37: 64759978 | D37: 64759978 | E37: 67783475 | F37: 75924160 | G37: 91766559 | H37: 17662274541
A38: Equity Investments | C38: 142990915 | D38: 150180192 | E38: 150180192 | F38: 1.5018019e+08 | G38: 150180192 | H38: 13504175449
A39: Financial Investments | C39: 157021333 | D39: 157955444 | E39: 153915320 | F39: 1.5422532e+08 | G39: 154849705 | H39: 20707496977
A40: Liquid Assets | C40: 153084208 | D40: 164744634 | E40: 167229703 | F40: 1.5103887e+08 | G40: 124939267 | H40: 4.2321864e+10
A41: Short-term Liabilities) | C41: 95081359 | D41: 90361862 | E41: 59478411 | F41: 62061389 | G41: 66184528 | H41: 8.7206046e+10
A42: External Borrowing | C42: 0 | D42: 0 | E42: 0 | F42: 0 | G42: 0 | H42: 4.5335678e+10
A43: Total Income | C43: 162985758 | D43: 45032970 | E43: 97502294 | F43: 1.1295021e+08 | G43: 1.4340648e+08 | H43: 5.518931e+10
A44: Net Financial Income/Loss | C44: 132339514 | D44: 44385509 | E44: 95338643 | F44: 1.1102787e+08 | G44: 1.4020265e+08 | H44: 3.4172138e+10
A45: Dividends+Interest on Deposits | C45: 30000000 | D45: 0 | E45: 0 | F45: 210106.76 | G45: 0 | H45: 1.6680249e+10
A46: Operating Expenses | C46: 118301534 | D46: 31094085 | E46: 72071107 | F46: 80160751 | G46: 95736770 | H46: 1.8773101e+10
A47: Total Expenses | C47: 148947778 | D47: 31741546 | E47: 74234757 | F47: 89083088 | G47: 98940596 | H47: 3.9715514e+10
A48: Net Income | C48: 3948782 | D48: 10291424 | E48: 17267537 | F48: 23867122 | G48: 35465881 | H48: 1.1304326e+10
A49: G. AREAS OF IMPROVEMENT/REGULATORY CONCERNS
A50: High NPL ratio at 17.1%
A51: High Non -earning assets ratio at 21.8%
A52: Non compliance with equity investments to total deposits and core capital ratios
A53: Gross loans to Total assets ratio below the industry standards
A54: Prepared by:
A56: Checked by:
A58: Approved by:
A60: DISCLAIMER: This report is prepared based on information submitted by the Sacco as at the stated date and may change upon verification by the Authority.

Sheet Sheet2
A2: VALIDATED JULY
A3: TB | D3: VALIDATED
A4: =SUM(A5:A6) -> 1.5103887e+08 | D4: =D5+D9 -> 1.1295021e+08
A5: 4845494.6 | D5: =SUM(D6:D7) -> 82211672
A6: 1.4619337e+08 | D6: 68900450
D7: 13311222
A8: 87068294
D9: =SUM(D10:D13) -> 30738538
A10: =SUM(A11:A14) -> 1.5422532e+08
D11: 6596616.2
D12: 9977330.8
A13: 4045128.4 | D13: 14164591
A14: 1.5018019e+08
D15: =D16+D17+D18+D19+D21+D22 -> 1922336.9
A16: =A17-A18 -> 5.4711644e+08 | D16: 210106.76
A17: 6.0681559e+08 | D17: 230221.13
A18: 59699148
D19: 1166669
A20: =SUM(A21:A23) -> 0 | D20: 852788.38
D21: 315340
D24: =D4-D15 -> 1.1102787e+08
A25: =SUM(A26:A30) -> 1.3839274e+08
D26: =D27-D28 -> 7000000
A27: 75924160 | D27: 7000000
A28: 47992406
A29: 14476174
D30: =SUM(D31:D35) -> 80160751
D31: 31647160
A32: =SUM(A4,A8,A10,A16,A20,A25) -> 1.0778417e+09 | D32: 13968033
D33: 4684294
D35: 29861264
A36: 62054614
D37: =D24-D26-D30 -> 23867122
A38: 7.5441899e+08
A39: =SUM(A36:A38) -> 8.1647361e+08 | D39: =D40-D41 -> 0
A41: =SUM(A42:A47) -> 6775.4
A43: 6775.4 | D43: =D37+D39 -> 23867122
D47: =D43-D45 -> 23867122
A48: =SUM(A39,A41) -> 8.1648038e+08
D50: =D47-D48 -> 23867122
A51: 1.1765702e+08
A54: =A56+A55 -> 49798258
A55: 25931136
A56: 23867122
A58: =SUM(A59:A63) -> 81373362
A59: 32938419
A60: 32531651
A61: 15903291
A64: =SUM(A51,A52,A54,A58) -> 2.4882864e+08
A66: =SUM(A48,A64) -> 1.065309e+09
A67: =A32-A66 -> 12532648
