Workbook

Sheet CAELS (2)
A1: PATNAS SACCO CAELS
D2: 2013 Audited | E2: 2014 Audited | F2: 2015 Audited | G2: 42370 | H2: 42370 | I2: 42401 | J2: 42430 | K2: 42461 | L2: 42491 | M2: 42522 | N2: 42552 | O2: 42583 | P2: 42614 | Q2: 42644 | R2: 42675 | S2: 42705 | T2: Audited 2016 | U2: 42736 | V2: 42767 | W2: 42795 | X2: 42826 | Y2: 42856 | Z2: 42887 | AA2: 42917 | AB2: 42948 | AC2: 42979 | AD2: 43009 | AE2: 43040 | AF2: 43070 | AG2: Audited 2017 | AH2: 43101 | AI2: 43132 | AJ2: 43160 | AK2: 43191 | AL2: 43221 | AM2: 43252 | AN2: 43282 | AO2: 43313 | AP2: 43344 | AQ2: 43374 | AR2: 43405 | AS2: 43435 | AT2: Audited 2018 | AU2: 43466 | AV2: 43497 | AW2: 43525 | AX2: 43556 | AY2: 43586 | AZ2: 43617 | BA2: 43647 | BB2: 43678 | BC2: 43709 | BD2: 43739 | BE2: 43770 | BF2: 43800 | BG2: Audited | BH2: 43831 | BI2: 43862 | BJ2: 43891 | BK2: 43922 | BL2: 43952 | BM2: 43983 | BN2: 44013 | BO2: 44044 | BP2: 44075 | BQ2: 44105 | BR2: 44136 | BS2: 44166 | BT2: Audited 2020 | BU2: 44197 | BV2: 44228 | BW2: 44256 | BX2: 44287 | BY2: 44317 | BZ2: 44348 | CA2: 44378 | CB2: 44409 | CC2: 44440 | CD2: 44470 | CE2: 44501 | CF2: 44531 | CG2: Audited 2021 | CH2: 44562 | CI2: 44593 | CJ2: 44621 | CK2: 44652 | CL2: 44682 | CM2: 44713 | CN2: 44743 | CO2: 44774 | CP2: 44805 | CQ2: 44835 | CR2: 44866 | CS2: 44896 | CT2: Audited 2022 | CU2: 44927 | CV2: 44958 | CW2: 44986 | CX2: 45017
A3: CAPITAL ADEQUACY | B3: Core Capital | C3: Ksh10 M | D3: =(('Evolutive SFP'!B38+'Evolutive SFP'!B39+'Evolutive SFP'!B41+'Evolutive SFP'!B42+'Evolutive SFP'!B43+'Evolutive SFP'!B44)-'Evolutive SFP'!B12)/1000000 -> 38.667178 | E3: =('Evolutive SFP'!C38+'Evolutive SFP'!C39+'Evolutive SFP'!C41+'Evolutive SFP'!C42+'Evolutive SFP'!C43+'Evolutive SFP'!C44)/1000000 -> 64.157783 | G3: =('Evolutive SFP'!E38+'Evolutive SFP'!E39+'Evolutive SFP'!E41+'Evolutive SFP'!E42+'Evolutive SFP'!E43+'Evolutive SFP'!E44)/1000000 -> 63.857155 | H3: =('Evolutive SFP'!F38+'Evolutive SFP'!F39+'Evolutive SFP'!F41+'Evolutive SFP'!F42+'Evolutive SFP'!F43+'Evolutive SFP'!F44)/1000000 -> 65.035173 | I3: =('Evolutive SFP'!G38+'Evolutive SFP'!G39+'Evolutive SFP'!G41+'Evolutive SFP'!G42+'Evolutive SFP'!G43+'Evolutive SFP'!G44)/1000000 -> 61.475774 | J3: =('Evolutive SFP'!H38+'Evolutive SFP'!H39+'Evolutive SFP'!H41+'Evolutive SFP'!H42+'Evolutive SFP'!H43+'Evolutive SFP'!H44)/1000000 -> 61.650703 | K3: =('Evolutive SFP'!I38+'Evolutive SFP'!I39+'Evolutive SFP'!I41+'Evolutive SFP'!I42+'Evolutive SFP'!I43+'Evolutive SFP'!I44)/1000000 -> 115.24105 | L3: =('Evolutive SFP'!J38+'Evolutive SFP'!J39+'Evolutive SFP'!J41+'Evolutive SFP'!J42+'Evolutive SFP'!J43+'Evolutive SFP'!J44)/1000000 -> 59.101829 | M3: =('Evolutive SFP'!K38+'Evolutive SFP'!K39+'Evolutive SFP'!K41+'Evolutive SFP'!K42+'Evolutive SFP'!K43+'Evolutive SFP'!K44)/1000000 -> 56.103923 | N3: =('Evolutive SFP'!L38+'Evolutive SFP'!L39+'Evolutive SFP'!L41+'Evolutive SFP'!L42+'Evolutive SFP'!L43+'Evolutive SFP'!L44)/1000000 -> 64.761452 | ... CT3: =('Evolutive SFP'!CR38+'Evolutive SFP'!CR39+'Evolutive SFP'!CR41+'Evolutive SFP'!CR42+'Evolutive SFP'!CR43+'Evolutive SFP'!CR44)/1000000 -> 96.970145 | CU3: =('Evolutive SFP'!CS38+'Evolutive SFP'!CS39+'Evolutive SFP'!CS41+'Evolutive SFP'!CS42+'Evolutive SFP'!CS43+'Evolutive SFP'!CS45)/1000000 -> 269.66136
B4: CCA | C4: Min 10% | D4: =D3/(('Evolutive SFP'!B26)/1000000) -> 0.1169964 | E4: =E3/(('Evolutive SFP'!C26)/1000000) -> 0.18423259 | F4: =F3/(('Evolutive SFP'!D26)/1000000) -> 0 | G4: =G3/(('Evolutive SFP'!E26)/1000000) -> 0.16111582 | H4: =H3/(('Evolutive SFP'!F26)/1000000) -> 0.17156387 | I4: =I3/(('Evolutive SFP'!G26)/1000000) -> 0.15983438 | J4: =J3/(('Evolutive SFP'!H26)/1000000) -> 0.16246825 | K4: =K3/(('Evolutive SFP'!I26)/1000000) -> 0.15593274 | ... CU4: =CU3/(('Evolutive SFP'!CS26)/1000000) -> 0.51918439
B5: CCD | C5: Min 8% | D5: =D3/('Evolutive SFP'!B30/1000000) -> 0.23615494 | E5: =E3/('Evolutive SFP'!C30/1000000) -> 0.51041171 | F5: =F3/('Evolutive SFP'!D30/1000000) -> 0 | G5: =G3/('Evolutive SFP'!E30/1000000) -> 0.49271519 | H5: =H3/('Evolutive SFP'!F30/1000000) -> 0.44298293 | I5: =I3/('Evolutive SFP'!G30/1000000) -> 0.40910939 | J5: =J3/('Evolutive SFP'!H30/1000000) -> 0.42548606 | K5: =K3/('Evolutive SFP'!I30/1000000) -> 0.41387063 | ... CU5: =CU3/('Evolutive SFP'!CS30/1000000) -> 1.3813628
B6: ICA | C6: Min 8% | D6: =((D3*1000000)-'Evolutive SFP'!B38)/'Evolutive SFP'!B26 -> -0.044330441 | E6: =((E3*1000000)-'Evolutive SFP'!C38)/'Evolutive SFP'!C26 -> 0.030380074 | F6: =((F3*1000000)-'Evolutive SFP'!D38)/'Evolutive SFP'!D26 -> -0.1408684 | G6: =((G3*1000000)-'Evolutive SFP'!E38)/'Evolutive SFP'!E26 -> 0.025896831 | H6: =((H3*1000000)-'Evolutive SFP'!F38)/'Evolutive SFP'!F26 -> 0.02799707 | I6: =((I3*1000000)-'Evolutive SFP'!G38)/'Evolutive SFP'!G26 -> 0.018338862 | J6: =((J3*1000000)-'Evolutive SFP'!H38)/'Evolutive SFP'!H26 -> 0.019048637 | K6: =((K3*1000000)-'Evolutive SFP'!I38)/'Evolutive SFP'!I26 -> 0.0081133968 | ... CU6: =((CU3*1000000)-'Evolutive SFP'!CS38)/'Evolutive SFP'!CS26 -> 0.37307979
A7: ASSET QUALITY | B7: NPL30 | J7: ='Evolutitve SCI'!H20/('FORM 4'!D14+'FORM 4'!D15+'FORM 4'!D16) -> 0.0996161 | M7: ='Evolutive SFP'!K15/('FORM 4'!D14+'FORM 4'!D15+'FORM 4'!D16) -> 0.65295388 | P7: ='Evolutive SFP'!N15/('FORM 4'!D23+'FORM 4'!D24+'FORM 4'!D25) -> 0.66699908 | S7: ='Evolutive SFP'!K15/('FORM 4'!D14+'FORM 4'!D15+'FORM 4'!D16) -> 0.65295388 | T7: ='Evolutive SFP'!L15/('FORM 4'!D41+'FORM 4'!D42+'FORM 4'!D43) -> 0.72125888 | U7: ='Evolutive SFP'!M15/('FORM 4'!E41+'FORM 4'!E42+'FORM 4'!E43) -> 9420494.3 | V7: ='Evolutive SFP'!N15/('FORM 4'!F41+'FORM 4'!F42+'FORM 4'!F43) -> 0.91879889 | W7: ='Evolutive SFP'!O15/('FORM 4'!G41+'FORM 4'!G42+'FORM 4'!G43) -> #DIV/0! | X7: ='Evolutive SFP'!P15/('FORM 4'!H41+'FORM 4'!H42+'FORM 4'!H43) -> #DIV/0! | Y7: ='Evolutive SFP'!Q15/('FORM 4'!I41+'FORM 4'!I42+'FORM 4'!I43) -> #DIV/0! | Z7: ='Evolutive SFP'!R15/('FORM 4'!J41+'FORM 4'!J42+'FORM 4'!J43) -> #DIV/0! | AA7: ='Evolutive SFP'!S15/('FORM 4'!K41+'FORM 4'!K42+'FORM 4'!K43) -> #DIV/0! | ... AF7: ='Evolutive SFP'!X15/('FORM 4'!P41+'FORM 4'!P42+'FORM 4'!P43) -> #DIV/0! | AG7: 0 | AH7: 1 | AI7: 2 | AJ7: 3 | AK7: 4 | AL7: 5 | AM7: 6 | AN7: 7 | AO7: 8 | AP7: 9 | AQ7: 10 | AR7: 11 | AS7: 12 | AT7: 13 | AU7: 14 | AV7: 15 | AW7: 16 | AX7: 17 | AY7: 18 | AZ7: 19 | BA7: 20 | BB7: 21 | BC7: 22 | BD7: 23 | BE7: 24 | BF7: 25 | BG7: 26 | BH7: 27 | BI7: 28 | BJ7: 29 | BK7: 30 | BL7: 31 | BM7: 32 | BN7: 33 | BO7: 34 | BP7: 35 | BQ7: 36 | BR7: 37 | BS7: 38 | BT7: 39 | BU7: 40 | BV7: 41 | BW7: 42 | BX7: 43 | BY7: 44 | BZ7: 45 | CA7: 46 | CB7: 47 | CC7: 48 | CD7: 49 | CE7: 50 | CF7: 51 | CG7: 52 | CH7: 53 | CI7: 54 | CJ7: 55 | CK7: 56 | CL7: 57 | CM7: 58 | CN7: 59 | CO7: 60 | CP7: 61 | CQ7: 62 | CR7: 63 | CS7: 64 | CT7: 65 | CU7: 66
A9: EARNINGS | B9: ROA | E9: ='Evolutitve SCI'!C33/(('Evolutive SFP'!B26+'Evolutive SFP'!C26)/2) -> 0.027471151 | F9: ='Evolutitve SCI'!D33/(('Evolutive SFP'!C26+'Evolutive SFP'!D26)/2) -> 0.012565004 | G9: ='Evolutitve SCI'!E33/(('Evolutive SFP'!D26+'Evolutive SFP'!E26)/2) -> -0.00080671348 | H9: ='Evolutitve SCI'!F33/(('Evolutive SFP'!E26+'Evolutive SFP'!F26)/2) -> 8.5797319e-05 | I9: ='Evolutitve SCI'!G33/(('Evolutive SFP'!F26+'Evolutive SFP'!G26)/2) -> -0.0084523794 | J9: ='Evolutitve SCI'!H33/(('Evolutive SFP'!G26+'Evolutive SFP'!H26)/2) -> -0.0079907036 | K9: ='Evolutitve SCI'!I33/(('Evolutive SFP'!H26+'Evolutive SFP'!I26)/2) -> -0.026045327 | L9: ='Evolutitve SCI'!J33/(('Evolutive SFP'!I26+'Evolutive SFP'!J26)/2) -> -0.010553779 | ... CU9: ='Evolutitve SCI'!CS33/(('Evolutive SFP'!CR26+'Evolutive SFP'!CS26)/2) -> 0.004148878
B10: Cost Income ratio | D10: ='Evolutitve SCI'!B23/'Evolutitve SCI'!B19 -> 0.85142686 | E10: ='Evolutitve SCI'!C23/'Evolutitve SCI'!C19 -> 0.8298036 | F10: ='Evolutitve SCI'!D23/'Evolutitve SCI'!D19 -> 0.90824195 | G10: ='Evolutitve SCI'!E23/'Evolutitve SCI'!E19 -> 0.88951046 | H10: ='Evolutitve SCI'!F23/'Evolutitve SCI'!F19 -> 0.64141686 | I10: ='Evolutitve SCI'!G23/'Evolutitve SCI'!G19 -> 1.0851038 | J10: ='Evolutitve SCI'!H23/'Evolutitve SCI'!H19 -> 1.0525412 | K10: ='Evolutitve SCI'!I23/'Evolutitve SCI'!I19 -> 1.5009166 | ... CU10: ='Evolutitve SCI'!CS23/'Evolutitve SCI'!CS19 -> 0.59601911
B11: Operating Expense ratio | D11: =('Evolutitve SCI'!B23+'Evolutitve SCI'!B12)/(('Evolutive SFP'!B26+'Evolutive SFP'!C26)/2) -> 0.16569149 | E11: =('Evolutitve SCI'!C23+'Evolutitve SCI'!C12)/(('Evolutive SFP'!C26+'Evolutive SFP'!D26)/2) -> 0.19354259 | F11: =('Evolutitve SCI'!D23+'Evolutitve SCI'!D12)/(('Evolutive SFP'!D26+'Evolutive SFP'!E26)/2) -> 0.18151855 | G11: =('Evolutitve SCI'!E23+'Evolutitve SCI'!E12)/(('Evolutive SFP'!E26+'Evolutive SFP'!F26)/2) -> 0.01334902 | H11: =('Evolutitve SCI'!F23+'Evolutitve SCI'!F12)/(('Evolutive SFP'!F26+'Evolutive SFP'!G26)/2) -> 0.010920595 | I11: =('Evolutitve SCI'!G23+'Evolutitve SCI'!G12)/(('Evolutive SFP'!G26+'Evolutive SFP'!H26)/2) -> 0.02747963 | J11: =('Evolutitve SCI'!H23+'Evolutitve SCI'!H12)/(('Evolutive SFP'!H26+'Evolutive SFP'!I26)/2) -> 0.025862472 | K11: =('Evolutitve SCI'!I23+'Evolutitve SCI'!I12)/(('Evolutive SFP'!I26+'Evolutive SFP'!J26)/2) -> 0.08180729 | ... CU11: =('Evolutitve SCI'!CS23+'Evolutitve SCI'!CS12)/(('Evolutive SFP'!CS26+'Evolutive SFP'!CT26)/2) -> 0.025259838
A12: LIQUIDITY | B12: MIN LIQ ratio | C12: Min 15% | D12: =('Evolutive SFP'!B4)/('Evolutive SFP'!B27+'Evolutive SFP'!B28+'Evolutive SFP'!B31+'Evolutive SFP'!B32+'Evolutive SFP'!B33+'Evolutive SFP'!B34+'Evolutive SFP'!B35) -> 0.38095275 | E12: =('Evolutive SFP'!C4)/('Evolutive SFP'!C27+'Evolutive SFP'!C28+'Evolutive SFP'!C31+'Evolutive SFP'!C32+'Evolutive SFP'!C33+'Evolutive SFP'!C34+'Evolutive SFP'!C35) -> 0.50360405 | F12: =('Evolutive SFP'!D4)/('Evolutive SFP'!D27+'Evolutive SFP'!D28+'Evolutive SFP'!D31+'Evolutive SFP'!D32+'Evolutive SFP'!D33+'Evolutive SFP'!D34+'Evolutive SFP'!D35) -> 0.77961975 | G12: =('Evolutive SFP'!E4)/('Evolutive SFP'!E27+'Evolutive SFP'!E28+'Evolutive SFP'!E31+'Evolutive SFP'!E32+'Evolutive SFP'!E33+'Evolutive SFP'!E34+'Evolutive SFP'!E35) -> 0.4019944 | H12: =('Evolutive SFP'!F4)/('Evolutive SFP'!F27+'Evolutive SFP'!F28+'Evolutive SFP'!F31+'Evolutive SFP'!F32+'Evolutive SFP'!F33+'Evolutive SFP'!F34+'Evolutive SFP'!F35) -> 0.23629838 | I12: =('Evolutive SFP'!G4)/('Evolutive SFP'!G27+'Evolutive SFP'!G28+'Evolutive SFP'!G31+'Evolutive SFP'!G32+'Evolutive SFP'!G33+'Evolutive SFP'!G34+'Evolutive SFP'!G35) -> 0.19872112 | J12: =('Evolutive SFP'!H4)/('Evolutive SFP'!H27+'Evolutive SFP'!H28+'Evolutive SFP'!H31+'Evolutive SFP'!H32+'Evolutive SFP'!H33+'Evolutive SFP'!H34+'Evolutive SFP'!H35) -> 0.18594944 | K12: =('Evolutive SFP'!I4)/('Evolutive SFP'!I27+'Evolutive SFP'!I28+'Evolutive SFP'!I31+'Evolutive SFP'!I32+'Evolutive SFP'!I33+'Evolutive SFP'!I34+'Evolutive SFP'!I35) -> 0.12341428 | ... CU12: =('Evolutive SFP'!CS4)/('Evolutive SFP'!CS27+'Evolutive SFP'!CS28+'Evolutive SFP'!CS31+'Evolutive SFP'!CS32+'Evolutive SFP'!CS33+'Evolutive SFP'!CS34+'Evolutive SFP'!CS35) -> -0.095478427
B13: T/LIQ ratio | D13: =('Evolutive SFP'!B4+'Evolutive SFP'!B8)/('Evolutive SFP'!B30+'Evolutive SFP'!B31+'Evolutive SFP'!B32+'Evolutive SFP'!B33+'Evolutive SFP'!B34+'Evolutive SFP'!B35) -> 0.48557591 | E13: =('Evolutive SFP'!C4+'Evolutive SFP'!C8)/('Evolutive SFP'!C30+'Evolutive SFP'!C31+'Evolutive SFP'!C32+'Evolutive SFP'!C33+'Evolutive SFP'!C34+'Evolutive SFP'!C35) -> 0.47225695 | F13: =('Evolutive SFP'!D4+'Evolutive SFP'!D8)/('Evolutive SFP'!D30+'Evolutive SFP'!D31+'Evolutive SFP'!D32+'Evolutive SFP'!D33+'Evolutive SFP'!D34+'Evolutive SFP'!D35) -> 0.66754314 | G13: =('Evolutive SFP'!E4+'Evolutive SFP'!E8)/('Evolutive SFP'!E30+'Evolutive SFP'!E31+'Evolutive SFP'!E32+'Evolutive SFP'!E33+'Evolutive SFP'!E34+'Evolutive SFP'!E35) -> 0.51054253 | H13: =('Evolutive SFP'!F4+'Evolutive SFP'!F8)/('Evolutive SFP'!F30+'Evolutive SFP'!F31+'Evolutive SFP'!F32+'Evolutive SFP'!F33+'Evolutive SFP'!F34+'Evolutive SFP'!F35) -> 0.39899382 | I13: =('Evolutive SFP'!G4+'Evolutive SFP'!G8)/('Evolutive SFP'!G30+'Evolutive SFP'!G31+'Evolutive SFP'!G32+'Evolutive SFP'!G33+'Evolutive SFP'!G34+'Evolutive SFP'!G35) -> 0.37183699 | J13: =('Evolutive SFP'!H4+'Evolutive SFP'!H8)/('Evolutive SFP'!H30+'Evolutive SFP'!H31+'Evolutive SFP'!H32+'Evolutive SFP'!H33+'Evolutive SFP'!H34+'Evolutive SFP'!H35) -> 0.3736823 | K13: =('Evolutive SFP'!I4+'Evolutive SFP'!I8)/('Evolutive SFP'!I30+'Evolutive SFP'!I31+'Evolutive SFP'!I32+'Evolutive SFP'!I33+'Evolutive SFP'!I34+'Evolutive SFP'!I35) -> 0.33925681 | ... CU13: =('Evolutive SFP'!CS4+'Evolutive SFP'!CS8)/('Evolutive SFP'!CS30+'Evolutive SFP'!CS31+'Evolutive SFP'!CS32+'Evolutive SFP'!CS33+'Evolutive SFP'!CS34+'Evolutive SFP'!CS35) -> 0.8517802
B14: EB ratio | C14: Max 25% | D14: ='Evolutive SFP'!B36/'Evolutive SFP'!B26 -> 0.27900143 | E14: ='Evolutive SFP'!C36/'Evolutive SFP'!C26 -> 0.41807179 | F14: ='Evolutive SFP'!D36/'Evolutive SFP'!D26 -> 0.42927942 | G14: ='Evolutive SFP'!E36/'Evolutive SFP'!E26 -> 0.47990153 | H14: ='Evolutive SFP'!F36/'Evolutive SFP'!F26 -> 0.43730632 | I14: ='Evolutive SFP'!G36/'Evolutive SFP'!G26 -> 0.43519042 | J14: ='Evolutive SFP'!H36/'Evolutive SFP'!H26 -> 0.44110663 | K14: ='Evolutive SFP'!I36/'Evolutive SFP'!I26 -> 0.45297395 | ... CU14: ='Evolutive SFP'!CS36/'Evolutive SFP'!CS26 -> 0.094702676
B15: LA to TA ratio | D15: ='Evolutive SFP'!B4/'Evolutive SFP'!B26 -> 0.14571754 | E15: ='Evolutive SFP'!C4/'Evolutive SFP'!C26 -> 0.12852377 | F15: ='Evolutive SFP'!D4/'Evolutive SFP'!D26 -> 0.21418621 | G15: ='Evolutive SFP'!E4/'Evolutive SFP'!E26 -> 0.096936938 | H15: ='Evolutive SFP'!F4/'Evolutive SFP'!F26 -> 0.062504337 | I15: ='Evolutive SFP'!G4/'Evolutive SFP'!G26 -> 0.054525095 | J15: ='Evolutive SFP'!H4/'Evolutive SFP'!H26 -> 0.050771498 | K15: ='Evolutive SFP'!I4/'Evolutive SFP'!I26 -> 0.032696043 | ... CU15: ='Evolutive SFP'!CS4/'Evolutive SFP'!CS26 -> -0.025688349
A16: STRUCTURE | B16: NEA ratio | C16: Max 10% | D16: =('Evolutive SFP'!B7+'Evolutive SFP'!B20)/'Evolutive SFP'!B26 -> 0.48806613 | E16: =('Evolutive SFP'!C7+'Evolutive SFP'!C20)/'Evolutive SFP'!C26 -> 0.54543449 | F16: =('Evolutive SFP'!D7+'Evolutive SFP'!D20)/'Evolutive SFP'!D26 -> 0.49515474 | G16: =('Evolutive SFP'!E7+'Evolutive SFP'!E20)/'Evolutive SFP'!E26 -> 0.47894506 | H16: =('Evolutive SFP'!F7+'Evolutive SFP'!F20)/'Evolutive SFP'!F26 -> 0.49839952 | I16: =('Evolutive SFP'!G7+'Evolutive SFP'!G20)/'Evolutive SFP'!G26 -> 0.49030077 | J16: =('Evolutive SFP'!H7+'Evolutive SFP'!H20)/'Evolutive SFP'!H26 -> 0.49605703 | K16: =('Evolutive SFP'!I7+'Evolutive SFP'!I20)/'Evolutive SFP'!I26 -> 0.50848057 | ... CU16: =('Evolutive SFP'!CS7+'Evolutive SFP'!CS20)/'Evolutive SFP'!CS26 -> 0.3011459
B17: LB ratio | C17: Max 5% | D17: ='Evolutive SFP'!B20/'Evolutive SFP'!B26 -> 0.26049891 | E17: ='Evolutive SFP'!C20/'Evolutive SFP'!C26 -> 0.25765617 | F17: ='Evolutive SFP'!D20/'Evolutive SFP'!D26 -> 0.22241994 | G17: ='Evolutive SFP'!E20/'Evolutive SFP'!E26 -> 0.4557139 | H17: ='Evolutive SFP'!F20/'Evolutive SFP'!F26 -> 0.46545298 | I17: ='Evolutive SFP'!G20/'Evolutive SFP'!G26 -> 0.45782955 | J17: ='Evolutive SFP'!H20/'Evolutive SFP'!H26 -> 0.46314439 | K17: ='Evolutive SFP'!I20/'Evolutive SFP'!I26 -> 0.47468246 | ... CU17: ='Evolutive SFP'!CS20/'Evolutive SFP'!CS26 -> 0.22342615
B18: PI to Deposit ratio | C18: Max 5% | D18: ='Evolutive SFP'!B12/'Evolutive SFP'!B30 -> 0.14759472 | E18: ='Evolutive SFP'!C12/'Evolutive SFP'!C30 -> 0.15299229 | F18: ='Evolutive SFP'!D12/'Evolutive SFP'!D30 -> 0.12918835 | G18: ='Evolutive SFP'!E12/'Evolutive SFP'!E30 -> 0.14739939 | H18: ='Evolutive SFP'!F12/'Evolutive SFP'!F30 -> 0.13012118 | I18: ='Evolutive SFP'!G12/'Evolutive SFP'!G30 -> 0.12712904 | J18: ='Evolutive SFP'!H12/'Evolutive SFP'!H30 -> 0.13184286 | K18: ='Evolutive SFP'!I12/'Evolutive SFP'!I30 -> 0.13721346 | ... CP18: ='Evolutive SFP'!CN12/'Evolutive SFP'!CN30 -> 0.00055005525 | CQ18: ='Evolutive SFP'!CO11/'Evolutive SFP'!CO30 -> 0.9233433 | CR18: ='Evolutive SFP'!CP11/'Evolutive SFP'!CP30 -> 0.93371844 | CS18: ='Evolutive SFP'!CQ11/'Evolutive SFP'!CQ30 -> 0.96278858 | CT18: ='Evolutive SFP'!CR12/'Evolutive SFP'!CR30 -> 0.0002299592 | CU18: ='Evolutive SFP'!CS12/'Evolutive SFP'!CS30 -> 0.00058909708
B19: PI to CC ratio | C19: Max 40% | D19: ='Evolutive SFP'!B12/('CAELS (2)'!D3*1000000) -> 0.62499104 | E19: ='Evolutive SFP'!C12/('CAELS (2)'!E3*1000000) -> 0.2997429 | F19: ='Evolutive SFP'!D12/('CAELS (2)'!F3*1000000) -> #DIV/0! | G19: ='Evolutive SFP'!E12/('CAELS (2)'!G3*1000000) -> 0.29915739 | H19: ='Evolutive SFP'!F12/('CAELS (2)'!H3*1000000) -> 0.29373859 | I19: ='Evolutive SFP'!G12/('CAELS (2)'!I3*1000000) -> 0.31074583 | J19: ='Evolutive SFP'!H12/('CAELS (2)'!J3*1000000) -> 0.3098641 | K19: ='Evolutive SFP'!I12/('CAELS (2)'!K3*1000000) -> 0.33153707 | ... CP19: ='Evolutive SFP'!CN12/('CAELS (2)'!CP3*1000000) -> 0.0010606667 | CQ19: ='Evolutive SFP'!CO11/('CAELS (2)'!CQ3*1000000) -> 1.727325 | CR19: ='Evolutive SFP'!CP11/('CAELS (2)'!CR3*1000000) -> 1.8783661 | CS19: ='Evolutive SFP'!CQ11/('CAELS (2)'!CS3*1000000) -> 1.8181813 | CT19: ='Evolutive SFP'!CR12/('CAELS (2)'!CT3*1000000) -> 0.00044905378 | CU19: ='Evolutive SFP'!CS12/('CAELS (2)'!CU3*1000000) -> 0.00042646081
B20: Gross loans/TA | D20: ='Evolutive SFP'!B14/'Evolutive SFP'!B26 -> 0.29265804 | E20: ='Evolutive SFP'!C14/'Evolutive SFP'!C26 -> 0.30746014 | F20: ='Evolutive SFP'!D14/'Evolutive SFP'!D26 -> 0.27422366 | G20: ='Evolutive SFP'!E14/'Evolutive SFP'!E26 -> 0.37189575 | H20: ='Evolutive SFP'!F14/'Evolutive SFP'!F26 -> 0.38419483 | I20: ='Evolutive SFP'!G14/'Evolutive SFP'!G26 -> 0.39952832 | J20: ='Evolutive SFP'!H14/'Evolutive SFP'!H26 -> 0.39635854 | K20: ='Evolutive SFP'!I14/'Evolutive SFP'!I26 -> 0.40018695 | ... CU20: ='Evolutive SFP'!CS14/'Evolutive SFP'!CS26 -> 0.39729413
A21: FUNDING MIX | B21: Total Deposits/Total Assets | D21: ='Evolutive SFP'!B30/'Evolutive SFP'!B26 -> 0.49542222 | E21: ='Evolutive SFP'!C30/'Evolutive SFP'!C26 -> 0.36094899 | F21: ='Evolutive SFP'!D30/'Evolutive SFP'!D26 -> 0.38548435 | G21: ='Evolutive SFP'!E30/'Evolutive SFP'!E26 -> 0.32699584 | H21: ='Evolutive SFP'!F30/'Evolutive SFP'!F26 -> 0.38729228 | I21: ='Evolutive SFP'!G30/'Evolutive SFP'!G26 -> 0.39068862 | J21: ='Evolutive SFP'!H30/'Evolutive SFP'!H26 -> 0.38184154 | K21: ='Evolutive SFP'!I30/'Evolutive SFP'!I26 -> 0.37676687 | ... CU21: ='Evolutive SFP'!CS30/'Evolutive SFP'!CS26 -> 0.37584942
B22: BOSA Deposits/Total Assets | D22: ='Evolutive SFP'!B29/'Evolutive SFP'!B26 -> 0.14232084 | E22: ='Evolutive SFP'!C29/'Evolutive SFP'!C26 -> 0.13387297 | F22: ='Evolutive SFP'!D29/'Evolutive SFP'!D26 -> 0.1207279 | G22: ='Evolutive SFP'!E29/'Evolutive SFP'!E26 -> 0.11784263 | H22: ='Evolutive SFP'!F29/'Evolutive SFP'!F26 -> 0.12661535 | I22: ='Evolutive SFP'!G29/'Evolutive SFP'!G26 -> 0.13059523 | J22: ='Evolutive SFP'!H29/'Evolutive SFP'!H26 -> 0.12338586 | K22: ='Evolutive SFP'!I29/'Evolutive SFP'!I26 -> 0.12616413 | ... CU22: ='Evolutive SFP'!CS29/'Evolutive SFP'!CS26 -> 0.11706421
B23: FOSA Deposits/Total Assets | D23: =('Evolutive SFP'!B27+'Evolutive SFP'!B28)/'Evolutive SFP'!B26 -> 0.35310138 | E23: =('Evolutive SFP'!C27+'Evolutive SFP'!C28)/'Evolutive SFP'!C26 -> 0.22707602 | F23: =('Evolutive SFP'!D27+'Evolutive SFP'!D28)/'Evolutive SFP'!D26 -> 0.26475646 | G23: =('Evolutive SFP'!E27+'Evolutive SFP'!E28)/'Evolutive SFP'!E26 -> 0.20915322 | H23: =('Evolutive SFP'!F27+'Evolutive SFP'!F28)/'Evolutive SFP'!F26 -> 0.26067692 | I23: =('Evolutive SFP'!G27+'Evolutive SFP'!G28)/'Evolutive SFP'!G26 -> 0.26009339 | J23: =('Evolutive SFP'!H27+'Evolutive SFP'!H28)/'Evolutive SFP'!H26 -> 0.25845568 | K23: =('Evolutive SFP'!I27+'Evolutive SFP'!I28)/'Evolutive SFP'!I26 -> 0.25060274 | ... CU23: =('Evolutive SFP'!CS27+'Evolutive SFP'!CS28)/'Evolutive SFP'!CS26 -> 0.2587852
A24: GROWTH RATIOS | B24: Total Assets | E24: =(Financials!D4-Financials!C4)/Financials!C4 -> 0.053690144 | F24: =(Financials!E4-Financials!D4)/Financials!D4 -> 0.10888185 | G24: =(Financials!F4-Financials!E4)/Financials!E4 -> 0.026368251 | H24: =(Financials!G4-Financials!F4)/Financials!F4 -> -0.043574592 | I24: =(Financials!H4-Financials!G4)/Financials!G4 -> 0.014638445 | J24: =(Financials!I4-Financials!H4)/Financials!H4 -> -0.013412214 | K24: =(Financials!J4-Financials!I4)/Financials!I4 -> 0.94760266 | L24: =(Financials!K4-Financials!J4)/Financials!J4 -> -0.512337 | ... CU24: =(Financials!CT4-Financials!CS4)/Financials!CS4 -> 0.0042244376
B25: Total Deposits | D25: =Financials!D5/Financials!C5-1 -> -0.23231463 | E25: =Financials!E5/Financials!D5-1 -> 0.18425766 | F25: =Financials!F5/Financials!E5-1 -> -0.12935985 | G25: =Financials!G5/Financials!F5-1 -> 0.13278556 | H25: =Financials!H5/Financials!G5-1 -> 0.023536278 | I25: =Financials!I5/Financials!H5-1 -> -0.035753337 | J25: =Financials!J5/Financials!I5-1 -> 0.92171906 | K25: =Financials!K5/Financials!J5-1 -> -0.53734598 | ... CU25: =Financials!CU5/Financials!CT5-1 -> -1
B26: BOSA Deposits | D26: =Financials!D6/Financials!C6-1 -> -0.0088547237 | E26: =Financials!G6/Financials!D6-1 -> 0.029515903 | F26: =Financials!H6/Financials!E6-1 -> 0.077420715 | G26: =Financials!I6/Financials!F6-1 -> 0.0024463072 | H26: =Financials!J6/Financials!G6-1 -> 0.9426606 | I26: =Financials!K6/Financials!H6-1 -> -0.11167451 | J26: =Financials!L6/Financials!I6-1 -> -0.046988087 | K26: =Financials!M6/Financials!J6-1 -> -0.51527218 | L26: =Financials!N6/Financials!K6-1 -> 0.013785428 | ... CU26: =Financials!CW6/Financials!CT6-1 -> -1
B27: FOSA Deposits | D27: =Financials!D7/Financials!C7-1 -> -0.32238225 | E27: =Financials!G7/Financials!D7-1 -> 0.24959968 | F27: =Financials!H7/Financials!E7-1 -> -0.021528056 | G27: =Financials!I7/Financials!F7-1 -> 0.18309519 | H27: =Financials!J7/Financials!G7-1 -> 0.87426348 | I27: =Financials!K7/Financials!H7-1 -> -0.15827356 | J27: =Financials!L7/Financials!I7-1 -> -0.17449455 | K27: =Financials!M7/Financials!J7-1 -> -0.57458793 | L27: =Financials!N7/Financials!K7-1 -> -0.069048362 | ... CU27: =Financials!CW7/Financials!CT7-1 -> -1
B28: Total Loans & advances | D28: =Financials!D31/Financials!C31-1 -> 0.10698385 | E28: =Financials!G31/Financials!D31-1 -> 0.36019847 | F28: =Financials!H31/Financials!E31-1 -> 0.45113654 | G28: =Financials!I31/Financials!F31-1 -> 0.020387568 | H28: =Financials!J31/Financials!G31-1 -> 1.030761 | I28: =Financials!K31/Financials!H31-1 -> -0.076395419 | J28: =Financials!L31/Financials!I31-1 -> -0.082465571 | K28: =Financials!M31/Financials!J31-1 -> -0.5351027 | L28: =Financials!N31/Financials!K31-1 -> -0.016640504 | ... CU28: =Financials!CW31/Financials!CT31-1 -> -1
B29: Core capital | D29: =Financials!D11/Financials!C11-1 -> 0.73610117 | E29: =Financials!G11/Financials!D11-1 -> -0.40906467 | F29: =Financials!H11/Financials!E11-1 -> -0.44569956 | G29: =Financials!I11/Financials!F11-1 -> -0.046181999 | H29: =Financials!J11/Financials!G11-1 -> 0.95248053 | I29: =Financials!K11/Financials!H11-1 -> 0.007779852 | J29: =Financials!L11/Financials!I11-1 -> 0.0077720195 | K29: =Financials!M11/Financials!J11-1 -> -0.50750475 | L29: =Financials!N11/Financials!K11-1 -> -0.015001789 | ... CU29: =Financials!CW11/Financials!CT11-1 -> -1
B30: Turnover | D30: =Financials!D37/Financials!C37-1 -> 0.27995599 | E30: =Financials!G37/Financials!D37-1 -> -0.92511335 | F30: =Financials!H37/Financials!E37-1 -> -0.86891384 | G30: =Financials!I37/Financials!F37-1 -> 1.4751376 | H30: =Financials!J37/Financials!G37-1 -> 4.7740024 | I30: =Financials!K37/Financials!H37-1 -> 1.1942473 | J30: =Financials!L37/Financials!I37-1 -> 0.89882119 | K30: =Financials!M37/Financials!J37-1 -> 0.25486461 | L30: =Financials!N37/Financials!K37-1 -> 5.6811849 | ... CU30: =Financials!CW37/Financials!CT37-1 -> -1
B31: Membership
B32: Expenses | D32: ='Evolutitve SCI'!C38/'Evolutitve SCI'!B38-1 -> 0.2638822 | E32: ='Evolutitve SCI'!E38/'Evolutitve SCI'!C38-1 -> -0.92717636 | F32: ='Evolutitve SCI'!F38/'Evolutitve SCI'!D38-1 -> -0.94128374 | G32: ='Evolutitve SCI'!G38/'Evolutitve SCI'!E38-1 -> 1.028469 | H32: ='Evolutitve SCI'!H38/'Evolutitve SCI'!F38-1 -> 2.4685073 | I32: ='Evolutitve SCI'!I38/'Evolutitve SCI'!G38-1 -> 3.2836504 | J32: ='Evolutitve SCI'!J38/'Evolutitve SCI'!H38-1 -> 0.7885561 | K32: ='Evolutitve SCI'!K38/'Evolutitve SCI'!I38-1 -> -0.29528124 | L32: ='Evolutitve SCI'!L38/'Evolutitve SCI'!J38-1 -> 0.57680951 | ... CU32: ='Evolutitve SCI'!CU38/'Evolutitve SCI'!CS38-1 -> #DIV/0!
A33: Efficiency Ratios | B33: FinCost-Deposits/Avg Deposits | E33: =Financials!D44/('Evolutive SFP'!B29+'Evolutive SFP'!C29)/2 -> 0.006732922 | F33: =Financials!E44/('Evolutive SFP'!C29+'Evolutive SFP'!D29)/2 -> 0.0089328521 | G33: =Financials!F44/('Evolutive SFP'!D29+'Evolutive SFP'!E29)/2 -> 0.00036170327 | H33: =Financials!G44/('Evolutive SFP'!E29+'Evolutive SFP'!F29)/2 -> 0.00052585706 | I33: =Financials!H44/('Evolutive SFP'!F29+'Evolutive SFP'!G29)/2 -> 0.0013457461 | J33: =Financials!I44/('Evolutive SFP'!G29+'Evolutive SFP'!H29)/2 -> 0.0023331342 | K33: =Financials!J44/('Evolutive SFP'!H29+'Evolutive SFP'!I29)/2 -> 0.0044338139 | L33: =Financials!K44/('Evolutive SFP'!I29+'Evolutive SFP'!J29)/2 -> 0.0025653532 | ... CU33: =Financials!CT44/('Evolutive SFP'!CR29+'Evolutive SFP'!CS29)/2 -> 0.0037920945
B34: FinCost-Shares/Avg Share capital | E34: =Financials!D45/('Evolutive SFP'!B38+'Evolutive SFP'!C38)/2 -> 0 | F34: =Financials!E45/('Evolutive SFP'!C38+'Evolutive SFP'!D38)/2 -> 0 | G34: =Financials!F45/('Evolutive SFP'!D38+'Evolutive SFP'!E38)/2 -> 0 | H34: =Financials!G45/('Evolutive SFP'!E38+'Evolutive SFP'!F38)/2 -> 0 | I34: =Financials!H45/('Evolutive SFP'!F38+'Evolutive SFP'!G38)/2 -> 0 | J34: =Financials!I45/('Evolutive SFP'!G38+'Evolutive SFP'!H38)/2 -> 0 | K34: =Financials!J45/('Evolutive SFP'!H38+'Evolutive SFP'!I38)/2 -> 0 | L34: =Financials!K45/('Evolutive SFP'!I38+'Evolutive SFP'!J38)/2 -> 0 | ... CU34: =Financials!CT45/('Evolutive SFP'!CR38+'Evolutive SFP'!CS38)/2 -> 0
B35: FinCost-Ext Loans/Avg Ext Loans | E35: =Financials!D46/(Financials!C31+Financials!D31)/2 -> 0.043191523 | F35: =Financials!E46/(Financials!D31+Financials!E31)/2 -> 0.049193375 | G35: =Financials!F46/(Financials!E31+Financials!F31)/2 -> 0.0018100636 | H35: =Financials!G46/(Financials!F31+Financials!G31)/2 -> 0 | I35: =Financials!H46/(Financials!G31+Financials!H31)/2 -> 0.0037408076 | J35: =Financials!I46/(Financials!H31+Financials!I31)/2 -> 0.0035745783 | K35: =Financials!J46/(Financials!I31+Financials!J31)/2 -> 0.013618093 | L35: =Financials!K46/(Financials!J31+Financials!K31)/2 -> 0.0069420411 | ... CU35: =Financials!CT46/(Financials!CS31+Financials!CT31)/2 -> 0
B36: OpEx/Average Total Assets | E36: =Financials!D47/(Financials!C4+Financials!D4)/2 -> 0.037092413 | F36: =Financials!E47/(Financials!D4+Financials!E4)/2 -> 0.031929876 | G36: =Financials!F47/(Financials!E4+Financials!F4)/2 -> 0.0022962286 | H36: =Financials!G47/(Financials!F4+Financials!G4)/2 -> 0.002220937 | I36: =Financials!H47/(Financials!G4+Financials!H4)/2 -> 0.0047383061 | J36: =Financials!I47/(Financials!H4+Financials!I4)/2 -> 0.0071928688 | K36: =Financials!J47/(Financials!I4+Financials!J4)/2 -> 0.013094088 | L36: =Financials!K47/(Financials!J4+Financials!K4)/2 -> 0.0081113195 | ... CU36: =Financials!CT47/(Financials!CS4+Financials!CT4)/2 -> 0.0026913157
B37: Opex/Turnover | E37: =Financials!D47/Financials!D37 -> 0.61860434 | F37: =Financials!E47/Financials!E37 -> 0.61906488 | G37: =Financials!F47/Financials!F37 -> 0.63921757 | H37: =Financials!G47/Financials!G37 -> 0.56505342 | I37: =Financials!H47/Financials!H37 -> 0.72876861 | J37: =Financials!I47/Financials!I37 -> 0.78993505 | K37: =Financials!J47/Financials!J37 -> 0.83225298 | L37: =Financials!K47/Financials!K37 -> 0.81851631 | ... CU37: =Financials!CT47/Financials!CT37 -> 0.53952511
B38: Avge yield on Net loans | E38: =Financials!D38/('Evolutive SFP'!C13+'Evolutive SFP'!B13)/2 -> 0.065646938 | F38: =Financials!E38/('Evolutive SFP'!D13+'Evolutive SFP'!C13)/2 -> 0.07859209 | G38: =Financials!F38/('Evolutive SFP'!E13+'Evolutive SFP'!D13)/2 -> 0.0044953459 | H38: =Financials!G38/('Evolutive SFP'!F13+'Evolutive SFP'!E13)/2 -> 0.0039594886 | I38: =Financials!H38/('Evolutive SFP'!G13+'Evolutive SFP'!F13)/2 -> 0.0069904328 | J38: =Financials!I38/('Evolutive SFP'!H13+'Evolutive SFP'!G13)/2 -> 0.01001621 | K38: =Financials!J38/('Evolutive SFP'!I13+'Evolutive SFP'!H13)/2 -> 0.01767662 | L38: =Financials!K38/('Evolutive SFP'!J13+'Evolutive SFP'!I13)/2 -> 0.011171998 | ... CU38: =Financials!CT38/('Evolutive SFP'!CS13+'Evolutive SFP'!CR13)/2 -> 0.0062371924
B39: Avge yield on Gross loans | E39: =Financials!D37/('Evolutive SFP'!C14+'Evolutive SFP'!B14)/2 -> 0.19970336 | F39: =Financials!E37/('Evolutive SFP'!D14+'Evolutive SFP'!C14)/2 -> 0.17786364 | G39: =Financials!F37/('Evolutive SFP'!E14+'Evolutive SFP'!D14)/2 -> 0.011097628 | H39: =Financials!G37/('Evolutive SFP'!F14+'Evolutive SFP'!E14)/2 -> 0.010400645 | I39: =Financials!H37/('Evolutive SFP'!G14+'Evolutive SFP'!F14)/2 -> 0.01658972 | J39: =Financials!I37/('Evolutive SFP'!H14+'Evolutive SFP'!G14)/2 -> 0.022881144 | K39: =Financials!J37/('Evolutive SFP'!I14+'Evolutive SFP'!H14)/2 -> 0.039442895 | L39: =Financials!K37/('Evolutive SFP'!J14+'Evolutive SFP'!I14)/2 -> 0.024893082 | ... CU39: =Financials!CT37/('Evolutive SFP'!CS14+'Evolutive SFP'!CR14)/2 -> 0.012651805
A41: ALL/Average Gross Loan portfolio

Sheet Evolutive SFP
B3: 2013 Audited | C3: 2014 Audited | D3: 2015 Audited | E3: 2016 Audited | F3: 42370 | G3: 42401 | H3: 42430 | I3: 42461 | J3: 42491 | K3: 42522 | L3: 42552 | M3: 42583 | N3: 42614 | O3: 42644 | P3: 42675 | Q3: 42705 | R3: Audited 2016 | S3: 42736 | T3: 42767 | U3: 42795 | V3: 42826 | W3: 42856 | X3: 42887 | Y3: 42917 | Z3: 42948 | AA3: 42979 | AB3: 43009 | AC3: 43040 | AD3: 43070 | AE3: Audited 2017 | AF3: 43101 | AG3: 43132 | AH3: 43160 | AI3: 43191 | AJ3: 43221 | AK3: 43252 | AL3: 43282 | AM3: 43313 | AN3: 43344 | AO3: 43374 | AP3: 43405 | AQ3: 43435 | AR3: Audited 2018 | AS3: 43466 | AT3: 43497 | AU3: 43525 | AV3: 43556 | AW3: 43586 | AX3: 43617 | AY3: 43647 | AZ3: 43678 | BA3: 43709 | BB3: 43739 | BC3: 43770 | BD3: 43800 | BE3: Audited2019 | BF3: 43831 | BG3: 43862 | BH3: 43891 | BI3: 43922 | BJ3: 43952 | BK3: 43983 | BL3: 44013 | BM3: 44044 | BN3: 44075 | BO3: 44105 | BP3: 44136 | BQ3: 44166 | BR3: Audited 2020 | BS3: 44197 | BT3: 44228 | BU3: 44256 | BV3: 44287 | BW3: 44317 | BX3: 44348 | BY3: 44378 | BZ3: 44409 | CA3: 44440 | CB3: 44470 | CC3: 44501 | CD3: 44531 | CE3: Audited 2021 | CF3: 44562 | CG3: 44593 | CH3: 44621 | CI3: 44652 | CJ3: 44682 | CK3: 44713 | CL3: 44743 | CM3: 44774 | CN3: 44805 | CO3: 44835 | CP3: 44866 | CQ3: 44896 | CR3: Audited 2022 | CS3: 44927 | CT3: 44958 | CU3: 44986 | CV3: 45017 | CW3: 45047
A4: Cash & cash Equivalent | B4: =SUM(B5:B6) -> 48159480 | C4: =SUM(C5:C6) -> 44757556 | D4: =SUM(D5:D6) -> 82710316 | E4: =SUM(E5:E6) -> 38420293 | F4: =SUM(F5:F6) -> 23693686 | G4: =SUM(G5:G6) -> 20971535 | H4: =SUM(H5:H6) -> 19265909 | I4: =SUM(I5:I6) -> 24163791 | ... CS4: =SUM(CS5:CS6) -> -13342379
A5: Cash In Hand | B5: 24191210 | C5: 15917353 | D5: 23182703 | E5: 15600124 | F5: 2905102 | G5: 2165682 | H5: 8964052 | I5: 8445808 | J5: 6460655 | K5: 5358831 | L5: 3892329 | M5: 1340041 | N5: 4158194 | O5: 86264247 | P5: 19156836 | Q5: 23806073 | R5: 23806073 | S5: 19370910 | T5: 14900455 | U5: 4870448.2 | V5: 8128181.7 | W5: 7555033 | X5: 7668864 | Y5: 29856502 | Z5: 9837900 | AA5: 57273755 | AB5: 44876260 | AC5: 27209625 | AD5: 16235537 | AE5: 16235537 | AF5: 9168589 | AG5: 19054403 | AH5: 5232305 | AI5: 5472940 | AJ5: 4071121 | AK5: 6902351 | AL5: 13606854 | AM5: 7085696 | AN5: 3820627 | AO5: 36107033 | AP5: 10370991 | AQ5: 3570118.3 | AR5: 3570118.3 | AS5: 11042681 | AT5: 8746086 | AU5: 6194519 | AV5: 9478302 | AW5: 3582148 | AX5: 7575945 | AY5: 9044277 | AZ5: 10688395 | BA5: 7108894 | BB5: 47364254 | BC5: 10217056 | BD5: 7918205.6 | BF5: 11683321 | BG5: 26020165 | BH5: 17774199 | BI5: 23055336 | BJ5: 18479062 | BK5: 14504890 | BM5: 39804411 | BN5: 21575514 | BO5: 50437171 | BP5: 22003764 | BQ5: 12623076 | BR5: ='[1]Draft accounts 2020'!$D$666 -> 12623076 | BS5: 17226617 | BT5: 19422922 | BU5: 14712181 | BV5: 13111204 | BW5: 20956748 | BX5: 8547077.3 | BY5: 13659649 | BZ5: 8933309.8 | CA5: 8431009.3 | CB5: 30713370 | CE5: 5989569.8 | CF5: 5363580.3 | CG5: 2257388.8 | CH5: 3879988.3 | CI5: 7134057.2 | CJ5: 9334661.4 | CK5: 11535720 | CL5: 40703387 | CM5: 35929261 | CN5: 8236404.4 | CO5: 7769412.3 | CP5: 8728570.1 | CQ5: 7093481.7 | CR5: =7093481.75 -> 7093481.8 | CS5: 6545584.4
A6: Cash at Bank | B6: 23968270 | C6: 28840203 | D6: 59527613 | E6: 22820169 | F6: 20788584 | G6: 18805853 | H6: 10301857 | I6: 15717983 | J6: -635948.28 | K6: 276689.11 | L6: 7069945.1 | M6: 6054457.1 | N6: 2006672.1 | O6: 1.5060728e+08 | P6: 1.5688878e+08 | Q6: 78695582 | R6: =102501655.09-R5 -> 78695582 | S6: 41574234 | T6: 13496336 | U6: 12018613 | V6: 5197794.3 | W6: 4918275.1 | X6: 13719484 | Y6: 48281181 | Z6: 19244293 | AA6: 62609595 | AB6: 7.5472002e+08 | AC6: 2.6938785e+08 | AD6: 62185737 | AE6: =78421274-16235536.85 -> 62185737 | AF6: 25759263 | AG6: 50112752 | AH6: 44487335 | AI6: 37955056 | AJ6: 41679118 | AK6: 60381816 | AL6: 60979482 | AM6: 56576376 | AN6: 59144583 | AO6: 3.0243707e+08 | AP6: 1.303618e+08 | AQ6: 1.4485507e+08 | AR6: =148425186.58-AR5 -> 1.4485507e+08 | AS6: 36488107 | AT6: 24675020 | AU6: 47400767 | AV6: 27939154 | AW6: 18893721 | AX6: 40272807 | AY6: 29758373 | AZ6: 23929398 | BA6: 27586920 | BB6: 39595519 | BC6: 28697762 | BD6: 15225746 | BF6: 14570807 | BG6: 20788975 | BH6: 81826276 | BI6: 93130189 | BJ6: 114086030 | BK6: 112964005 | BM6: 349289460 | BN6: 102782692 | BO6: 206079886 | BP6: 1.3989409e+08 | BQ6: 68539209 | BR6: ='[1]Draft accounts 2020'!$D$672-'[1]Draft accounts 2020'!$D$666 -> 68544209 | BS6: 41422945 | BT6: 85158059 | BU6: 67154357 | BV6: 94592469 | BW6: 69769880 | BX6: 71940530 | BY6: 68772615 | BZ6: 59486947 | CA6: 60672719 | CB6: 1.6503094e+08 | CE6: =9508131.7-5989569.84 -> 3518561.9 | CF6: 2200637.8 | CG6: -7254713.2 | CH6: -11432725 | CI6: -7184616.7 | CJ6: -26867184 | CK6: -13452662 | CL6: 92478670 | CM6: 47255722 | CN6: 32050649 | CO6: 13651718 | CP6: -3496922.9 | CQ6: -18984734 | CR6: =41.46+13286+3130758+1973576.41+388621.39+390956.49+275652.94+30000-15337551.35-9850075.04 -> -18984734 | CS6: -19887964
A7: Prepayment and Sundry | B7: 75210706 | C7: 1.002169e+08 | D7: 1.0531948e+08 | E7: 9207511.9 | F7: 12489133 | G7: 12489133 | H7: 12489133 | I7: 24978266 | J7: 12489133 | K7: 12489133 | L7: 12489133 | M7: 12489133 | N7: 12489133 | O7: 12489133 | P7: 24978266 | Q7: 9256907 | R7: =14420714.59+62098018.01 -> 76518733 | S7: 18513814 | T7: 9256907 | U7: 5250107 | V7: 5250107 | W7: 5250107 | X7: 5250107 | Y7: 15750321 | Z7: 10500214 | AA7: 26250535 | AB7: 10500214 | AC7: 15750321 | AD7: 5952520 | AE7: =6804770.95+49990796.59 -> 56795568 | AF7: 5952520 | AG7: 5952520 | AH7: 5952520 | AI7: 5952520 | AJ7: 5952520 | AK7: 16236716 | AL7: 15892642 | AM7: 16147384 | AN7: 15388577 | AO7: 8154766 | AP7: 8669242 | AQ7: 8411647.9 | AR7: =42204144.62-5000000 -> 37204145 | AS7: 25676409 | AT7: 25614419 | AU7: 25081340 | AV7: 24835164 | AW7: 24111337 | AX7: 22878958 | AY7: 21763057 | AZ7: 20440066 | BA7: 18675689 | BB7: 16617870 | BC7: 24320388 | BD7: 28115888 | BF7: 30105131 | BG7: 28736444 | BH7: 28650811 | BI7: 24094447 | BJ7: 22253974 | BK7: 22493631 | BM7: 51935187 | BN7: 18028296 | BO7: 9006376 | BP7: 28516614 | BQ7: 27523029 | BR7: ='[1]Draft accounts 2020'!$D$744 -> 44279560 | BS7: 28923107 | BT7: 28465473 | BU7: 28084165 | BV7: 26288320 | BW7: 25863394 | BX7: 27555825 | BY7: 27398042 | BZ7: 27423368 | CA7: 26494607 | CB7: 22692549 | CE7: 60916310 | CF7: 31781306 | CG7: 31748484 | CH7: 31542657 | CI7: 32573020 | CJ7: 33766181 | CK7: 34112377 | CL7: 41342289 | CM7: 34452561 | CN7: 35818343 | CO7: 36772945 | CP7: 37562594 | CQ7: 39913960 | CR7: 74737674 | CS7: 40367189
A8: Financial Investment | B8: =SUM(B9:B12) -> 36066278 | C8: =SUM(C9:C12) -> 19230840 | D8: =SUM(D9:D12) -> 19230840 | E8: =SUM(E9:E12) -> 34219862 | F8: =SUM(F9:F12) -> 35463780 | G8: =SUM(G9:G12) -> 36946633 | H8: =SUM(H9:H12) -> 36946633 | I8: =SUM(I9:I12) -> 73893265 | ... CS8: =SUM(CS9:CS12) -> 1.8416248e+08
A9: Government Security | B9: 0 | D9: 0 | E9: 0 | F9: 0 | G9: 0 | H9: 0 | I9: 0 | J9: 0 | K9: 0 | L9: 0 | M9: 0 | N9: 0 | O9: 0 | P9: 0 | Q9: 0 | S9: 0 | T9: 0 | U9: 0 | V9: 0 | W9: 0 | X9: 0 | Y9: 0 | Z9: 0 | AA9: 0 | AB9: 0 | AC9: 0 | AD9: 0 | AF9: 0 | AG9: 0 | AH9: 0 | AI9: 0 | AJ9: 0 | AK9: 0 | AL9: 0 | AM9: 0 | AN9: 0 | AO9: 0 | AP9: 0 | AQ9: 0 | AR9: 0 | AS9: 0 | AT9: 0 | AU9: 0 | AV9: 0 | AW9: 0 | AX9: 0 | AY9: 0 | AZ9: 0 | BA9: 0 | BB9: 0 | BC9: 0 | BD9: 0 | BF9: 0 | BG9: 0 | BH9: 0 | BI9: 0 | BJ9: 0 | BK9: 0 | BM9: 0 | BN9: 0 | BO9: 0 | BP9: 0 | BQ9: 0 | BS9: 0 | BT9: 0 | BU9: 0 | BV9: 0 | BW9: 0 | BX9: 0 | BY9: 0 | BZ9: 0 | CA9: 0 | CB9: 0 | CF9: 0 | CG9: 0 | CH9: 0 | CI9: 0 | CJ9: 0 | CK9: 0 | CL9: 0 | CM9: 0 | CN9: 0 | CO9: 0 | CP9: 0 | CQ9: 0 | CS9: 0
A10: Other Securities | B10: 64200 | D10: 0 | E10: 0 | F10: 0 | G10: 0 | H10: 0 | I10: 0 | J10: 0 | K10: 0 | L10: 0 | M10: 0 | N10: 0 | O10: 0 | P10: 0 | Q10: 0 | S10: 0 | T10: 0 | U10: 0 | V10: 0 | W10: 0 | X10: 0 | Y10: 0 | Z10: 0 | AA10: 0 | AB10: 0 | AC10: 0 | AD10: 0 | AF10: 0 | AG10: 0 | AH10: 0 | AI10: 0 | AJ10: 0 | AK10: 0 | AL10: 0 | AM10: 0 | AN10: 0 | AO10: 0 | AP10: 0 | AQ10: 0 | AR10: 0 | AS10: 0 | AT10: 0 | AU10: 0 | AV10: 0 | AW10: 0 | AX10: 0 | AY10: 0 | AZ10: 0 | BA10: 0 | BB10: 0 | BC10: 0 | BD10: 0 | BF10: 0 | BG10: 0 | BH10: 0 | BI10: 0 | BJ10: 0 | BK10: 0 | BM10: 0 | BN10: 0 | BO10: 0 | BP10: 0 | BQ10: 0 | BS10: 0 | BT10: 0 | BU10: 0 | BV10: 0 | BW10: 0 | BX10: 0 | BY10: 0 | BZ10: 0 | CA10: 0 | CB10: 0 | CF10: 0 | CG10: 0 | CH10: 0 | CI10: 0 | CJ10: 0 | CK10: 0 | CL10: 0 | CM10: 0 | CN10: 0 | CO10: 0 | CP10: 0 | CQ10: 0 | CS10: 0
A11: Balances with Other Saccos | B11: 11835438 | D11: 0 | E11: 15116522 | F11: 16360440 | G11: 17843293 | H11: 17843293 | I11: 35686585 | J11: 17843293 | K11: 17843293 | L11: 18232726 | M11: 18232726 | N11: 18232726 | O11: 18232726 | P11: 255000 | Q11: 127500 | S11: 255000 | T11: 127500 | U11: 127500 | V11: 127500 | W11: 127500 | X11: 127500 | Y11: 382500 | Z11: 255000 | AA11: 637500 | AB11: 255000 | AC11: 382500 | AD11: 127500 | AE11: =115000+11250 -> 126250 | AF11: 127500 | AG11: 127500 | AH11: 127500 | AI11: 127500 | AJ11: 127500 | AK11: 127500 | AL11: 127500 | AM11: 127500 | AN11: 127500 | AO11: 127500 | AP11: 127500 | AQ11: 127500 | AR11: =51000+115000+12500 -> 178500 | AS11: 127500 | AT11: 127500 | AU11: 127500 | AV11: 127500 | AW11: 127500 | AX11: 127500 | AY11: 127500 | AZ11: 127500 | BA11: 127500 | BB11: 127500 | BC11: 127500 | BD11: 127500 | BF11: 127500 | BG11: 127500 | BH11: 127500 | BI11: 127500 | BJ11: 127500 | BK11: 127500 | BM11: 382500 | BN11: 127500 | BO11: 127500 | BP11: 255000 | BQ11: 115000 | BR11: =130896272.03-BR12 -> 1.3089093e+08 | BS11: 115000 | BT11: 115000 | BU11: 115000 | BV11: 115000 | BW11: 115000 | BX11: 115000 | BY11: 115000 | BZ11: 115000 | CA11: 115000 | CB11: 115000 | CE11: =184162473.9-CE12 -> 1.8415966e+08 | CF11: 130781271 | CG11: 130781271 | CH11: 130781271 | CI11: 130781271 | CJ11: 130781271 | CK11: 1.8404748e+08 | CL11: 1.8404748e+08 | CM11: 1.8404748e+08 | CN11: 1.8404748e+08 | CO11: 1.8404748e+08 | CP11: 1.8404748e+08 | CQ11: 1.8404748e+08 | CR11: =187023834+318750.3+51000+115000+12500 -> 1.8752108e+08 | CS11: 1.8404748e+08
A12: Investment In Companies | B12: 24166640 | C12: 19230840 | D12: 19230840 | E12: 19103340 | F12: 19103340 | G12: 19103340 | H12: 19103340 | I12: 38206680 | J12: 19103340 | K12: 19103340 | L12: 19103340 | M12: 19103340 | N12: 19103340 | O12: 19103340 | P12: 38206680 | Q12: 19103340 | R12: 24230840 | S12: 38206680 | T12: 19103340 | U12: 24103340 | V12: 24103340 | W12: 24103340 | X12: 24103340 | Y12: 72310020 | Z12: 48206680 | AA12: 120516700 | AB12: 48206680 | AC12: 72310020 | AD12: 24103340 | AE12: =24230840-AE11 -> 24104590 | AF12: 24103340 | AG12: 24103340 | AH12: 24103340 | AI12: 24103340 | AJ12: 24103340 | AK12: 24103340 | AL12: 19103340 | AM12: 19103340 | AN12: 19103340 | AO12: 19103340 | AP12: 19103340 | AQ12: 19103340 | AR12: =174388650+40450+11250+643940 -> 175084290 | AS12: 19103340 | AT12: 19103340 | AU12: 19103340 | AV12: 19103340 | AW12: 19103340 | AX12: 19103340 | AY12: 19103340 | AZ12: 175135290 | BA12: 175135290 | BB12: 175135290 | BC12: 175135290 | BD12: 175135290 | BF12: 175135290 | BG12: 175135290 | BH12: 184323752 | BI12: 184323752 | BJ12: 184323752 | BK12: 184323752 | BM12: 552971256 | BN12: 184323752 | BO12: 184323752 | BP12: 368647504 | BQ12: 184115313 | BR12: 5342.8 | BS12: 184115313 | BT12: 184115313 | BU12: 184115313 | BV12: 184115313 | BW12: 184115313 | BX12: 130781271 | BY12: 130781271 | BZ12: 130781271 | CA12: 130781271 | CB12: 130781271 | CE12: 2812 | CF12: 115000 | CG12: 115000 | CH12: 115000 | CI12: 115000 | CJ12: 115000 | CK12: 115000 | CL12: 115000 | CM12: 115000 | CN12: 115000 | CO12: 115000 | CP12: 115000 | CQ12: 115000 | CR12: =38933.13+4611.68 -> 43544.81 | CS12: 115000
A13: Net Loan Portfolio | B13: =B14-B15 -> 84967806 | C13: =C14-C15 -> 94311040 | D13: =D14-D15 -> 93010285 | E13: =E14-E15 -> 1.3387641e+08 | F13: =F14-F15 -> 1.3098557e+08 | G13: =G14-G15 -> 1.3812322e+08 | H13: =H14-H15 -> 1.3501521e+08 | I13: =I14-I15 -> 2.6519709e+08 | ... CS13: =CS14-CS15 -> 1.9216066e+08 | CV13: =11891251.95-11887147 -> 4104.95
A14: Gross Loan Portfolio | B14: 96723149 | C14: 1.0707096e+08 | D14: 105894421 | E14: 1.4739834e+08 | F14: 145637760 | G14: 1.5366726e+08 | H14: 150403433 | I14: 295755486 | J14: 141927789 | K14: 138000328 | L14: 137495928 | M14: 139566039 | N14: 137451836 | O14: 73197047 | P14: 1.4885766e+08 | Q14: 55593921 | R14: 55593921 | S14: 2.3821571e+08 | T14: 141015739 | U14: 135436565 | V14: 132727985 | W14: 1.3002279e+08 | X14: 128080317 | Y14: 3.8064001e+08 | Z14: 276746700 | AA14: 676424635 | AB14: 152408112 | AC14: 231992676 | AD14: 68793951 | AE14: 68793951 | AF14: 141381095 | AG14: 141404734 | AH14: 141037223 | AI14: 140863573 | AJ14: 139164157 | AK14: 139797860 | AL14: 141481310 | AM14: 146106598 | AN14: 146675802 | AO14: 82475169 | AP14: 85885819 | AQ14: 79430798 | AR14: =79430797.92 -> 79430798 | AS14: 1.8735835e+08 | AT14: 1.9022386e+08 | AU14: 1.8989368e+08 | AV14: 1.9397416e+08 | AW14: 1.9682868e+08 | AX14: 1.9541412e+08 | AY14: 1.949776e+08 | AZ14: 1.9574019e+08 | BA14: 1.9078437e+08 | BB14: 1.5154295e+08 | BC14: 1.908062e+08 | BD14: 2.0962724e+08 | BF14: 2.2064624e+08 | BG14: 2.2011328e+08 | BH14: 2.1586534e+08 | BI14: 2.1000193e+08 | BJ14: 2.05317e+08 | BK14: 2.0375612e+08 | BM14: 5.9664985e+08 | BN14: 194469461 | BO14: 147931620 | BP14: 3.5427705e+08 | BQ14: 1.8689716e+08 | BR14: 1.879707e+08 | BS14: 2.0154244e+08 | BT14: 2.0331336e+08 | BU14: 2.0543681e+08 | BV14: 2.0304729e+08 | BW14: 2.0437697e+08 | BX14: 1.8181163e+08 | BY14: 185810871 | BZ14: 1.8816687e+08 | CA14: 1.8534577e+08 | CB14: 1.4973473e+08 | CE14: 1.7382977e+08 | CF14: 1.7193674e+08 | CG14: 1.7381435e+08 | CH14: 1.7291744e+08 | CI14: 1.7314388e+08 | CJ14: 1.8207436e+08 | CK14: 1.8562745e+08 | CL14: 163308792 | CM14: 1.7602823e+08 | CN14: 1.8514164e+08 | CO14: 1.9273268e+08 | CP14: 1.9852274e+08 | CQ14: 2.0234575e+08 | CR14: 2.0235575e+08 | CS14: 2.0635227e+08
A15: Allowance For Loan Loss | B15: 11755343 | C15: 12759924 | D15: 12884136 | E15: 13521929 | F15: 14652190 | G15: 15544042 | H15: 15388223 | I15: 30558396 | J15: 14607283 | K15: 16413553 | L15: 16401453 | M15: 16485865 | N15: 16121662 | O15: 14831688 | P15: 28788012 | Q15: 17888755 | R15: 17888756 | S15: 35814064 | T15: 18397974 | U15: 17372183 | V15: 17345097 | W15: 17345097 | X15: 16434025 | Y15: 49119223 | Z15: 33776022 | AA15: 86516519 | AB15: 34084866 | AC15: 51451324 | AD15: 17615426 | AE15: 17615426 | AF15: 16418756 | AG15: 15404995 | AH15: 15393980 | AI15: 15359325 | AJ15: 14347331 | AK15: 14645411 | AL15: 15791635 | AM15: 15675925 | AN15: 15690124 | AO15: 13499682 | AP15: 16405147 | AQ15: 18868723 | AR15: 18868723 | AS15: 15668321 | AT15: 15706616 | AU15: 16146615 | AV15: 16497027 | AW15: 16720527 | AX15: 16568360 | AY15: 16480410 | AZ15: 16674363 | BA15: 16656408 | BB15: 19960914 | BC15: 23970506 | BD15: 21541242 | BF15: 19681992 | BG15: 19500343 | BH15: 27193856 | BI15: 25267198 | BJ15: 23840367 | BK15: 22600296 | BM15: 65973817 | BN15: 20744769 | BO15: 17353245 | BP15: 39348088 | BQ15: 13353313 | BR15: 14426854 | BS15: 12813443 | BT15: 11724251 | BU15: 11758210 | BV15: 12454080 | BW15: 12958427 | BX15: 13180213 | BY15: 13495264 | BZ15: 15795094 | CA15: 15122250 | CB15: 13700800 | CE15: 13421527 | CF15: 15902970 | CG15: 16549098 | CH15: 16690077 | CI15: 16697813 | CJ15: 16919953 | CK15: 20215974 | CL15: 18087960 | CM15: 18560803 | CN15: 18751211 | CO15: 19134182 | CP15: 19858362 | CQ15: 12560097 | CR15: 12560097 | CS15: 14191608
A16: Accounts Recievables | B16: =SUM(B17:B19) -> 0 | C16: =SUM(C17:C19) -> 0 | D16: =SUM(D17:D19) -> 0 | E16: =SUM(E17:E19) -> 0 | F16: =SUM(F17:F19) -> 0 | G16: =SUM(G17:G19) -> 0 | H16: =SUM(H17:H19) -> 0 | I16: =SUM(I17:I19) -> 0 | ... CS16: =SUM(CS17:CS19) -> 0
A17: Tax Recoverable | B17: 0 | D17: 0 | E17: 0 | F17: 0 | G17: 0 | H17: 0 | I17: 0 | J17: 0 | K17: 0 | L17: 0 | M17: 0 | N17: 0 | O17: 0 | P17: 0 | Q17: 0 | R17: 0 | S17: 0 | T17: 0 | U17: 0 | V17: 0 | W17: 0 | X17: 0 | AP17: 0 | AQ17: 0 | BR17: 450000 | BS17: 0 | BT17: 0 | BU17: 0 | BV17: 0 | BW17: 0 | BX17: 0 | BY17: 0 | BZ17: 0 | CA17: 0 | CB17: 0 | CF17: 0 | CG17: 0 | CH17: 0 | CI17: 0 | CJ17: 0 | CK17: 0 | CL17: 0 | CM17: 0 | CN17: 0 | CO17: 0 | CP17: 0 | CQ17: 0 | CR17: 0 | CS17: 0
A18: Deffered Tax Assets | B18: 0 | D18: 0 | E18: 0 | F18: 0 | G18: 0 | H18: 0 | I18: 0 | J18: 0 | K18: 0 | L18: 0 | M18: 0 | N18: 0 | O18: 0 | P18: 0 | Q18: 0 | R18: 0 | S18: 0 | T18: 0 | U18: 0 | V18: 0 | W18: 0 | X18: 0 | AP18: 0 | AQ18: 0 | BS18: 0 | BT18: 0 | BU18: 0 | BV18: 0 | BW18: 0 | BX18: 0 | BY18: 0 | BZ18: 0 | CA18: 0 | CB18: 0 | CF18: 0 | CG18: 0 | CH18: 0 | CI18: 0 | CJ18: 0 | CK18: 0 | CL18: 0 | CM18: 0 | CN18: 0 | CO18: 0 | CP18: 0 | CQ18: 0 | CR18: 0 | CS18: 0
A19: Retirement Benefit Assets | D19: 0 | E19: 0 | F19: 0 | G19: 0 | H19: 0 | I19: 0 | J19: 0 | K19: 0 | L19: 0 | M19: 0 | N19: 0 | O19: 0 | P19: 0 | Q19: 0 | R19: 0 | S19: 0 | T19: 0 | U19: 0 | V19: 0 | W19: 0 | X19: 0 | AP19: 0 | AQ19: 0 | BS19: 0 | BT19: 0 | BU19: 0 | BV19: 0 | BW19: 0 | BX19: 0 | BY19: 0 | BZ19: 0 | CA19: 0 | CB19: 0 | CF19: 0 | CG19: 0 | CH19: 0 | CI19: 0 | CJ19: 0 | CK19: 0 | CL19: 0 | CM19: 0 | CN19: 0 | CO19: 0 | CP19: 0 | CQ19: 0 | CR19: 0 | CS19: 0
A20: Property&Equipments&Other Assets | B20: =SUM(B21:B25) -> 86094595 | C20: =SUM(C21:C25) -> 89727059 | D20: =SUM(D21:D25) -> 85889859 | E20: =SUM(E21:E25) -> 1.8061909e+08 | F20: =SUM(F21:F25) -> 1.764405e+08 | G20: =SUM(G21:G25) -> 1.7609119e+08 | H20: =SUM(H21:H25) -> 1.757462e+08 | I20: =SUM(I21:I25) -> 3.5081089e+08 | ... CS20: =SUM(CS21:CS25) -> 1.1604624e+08 | CU20: 74026832 | CV20: =CU20-CR20 -> -2975742.2
A21: Investment Properties | D21: 0 | E21: 75930282 | F21: 74108533 | G21: 73959025 | H21: 73809828 | I21: 1.4732188e+08 | J21: 76266616 | K21: 76132571 | L21: 76278221 | M21: 76523359 | N21: 76128471 | O21: 75974755 | P21: 1.5164272e+08 | Q21: 75667324 | S21: 1.5102914e+08 | T21: 75362131 | U21: 75210011 | V21: 75058208 | W21: 75058208 | X21: 74906722 | Y21: 2.2426665e+08 | Z21: 1.4920939e+08 | AA21: 372270765 | AB21: 1.4860785e+08 | AC21: 2.2246203e+08 | AD21: 73834258 | AE21: 71489608 | AF21: 73685321 | AG21: 73536695 | AH21: 73388378 | AI21: 73240370 | AJ21: 73092671 | AK21: 72945279 | AL21: 72798194 | AM21: 72651416 | AN21: 72504944 | AO21: 72358777 | AP21: 72212914 | AQ21: 72047018 | AS21: 71901805 | AT21: 71756894 | AU21: 71612285 | AV21: 71467977 | AW21: 71323970 | AX21: 71180264 | AY21: 71036856 | AZ21: 70893747 | BA21: 70750937 | BB21: 70608424 | BC21: 70466207 | BD21: 70304459 | BF21: 70162876 | BG21: 70021588 | BH21: 69880594 | BI21: 69739894 | BJ21: 69599488 | BK21: 69459373 | BM21: 2.0754006e+08 | BN21: 69180020 | BO21: 69040780 | BP21: 140608916 | BQ21: 68605464 | BS21: 68605464 | BT21: 68605464 | BU21: 68605464 | BV21: 68053290 | BW21: 67915247 | BX21: 67779504 | BY21: 67643182 | BZ21: 67506859 | CA21: 67371105 | CB21: 67235633 | CF21: 66830628 | CG21: 66696282 | CH21: 66562216 | CI21: 66428150 | CJ21: 66562216 | CK21: 66160019 | CL21: 66027070 | CM21: 65894399 | CN21: 65762004 | CO21: 65629609 | CP21: 65497766 | CQ21: 65366197 | CR21: =63021547.15+2344650 -> 65366197 | CS21: 65234903 | CU21: 2344650
A22: Property and Equipment | B22: 84021813 | C22: 88181510 | D22: 84809160 | E22: 12175559 | F22: 10374562 | G22: 10201658 | H22: 10032024 | I22: 19731189 | J22: 9702302 | K22: 9542081.9 | L22: 10235386 | M22: 10911810 | N22: 10124623 | O22: 9965700.1 | P22: 20178833 | Q22: 9921377.4 | R22: 85588701 | S22: 19536076 | T22: 9978528.8 | U22: 11257647 | V22: 11078336 | W22: 11084136 | X22: 11308527 | Y22: 33413607 | Z22: 21918021 | AA22: 53917402 | AB22: 21222420 | AC22: 31326395 | AD22: 9577525.4 | AE22: =83411783-71489608 -> 11922175 | AF22: 9432667.7 | AG22: 9293059.1 | AH22: 9153190.8 | AI22: 9015771.7 | AJ22: 8880753.1 | AK22: 8748087.5 | AL22: 8617728.5 | AM22: 8489630.5 | AN22: 8363749.1 | AO22: 8320575.6 | AP22: 8196984.1 | AQ22: 7970556.4 | AR22: 80017575 | AS22: 7852994.2 | AT22: 7737453.9 | AU22: 7623896 | AV22: 7512281.7 | AW22: 7402573 | AX22: 7294732.7 | AY22: 7188724.7 | AZ22: 7084513.2 | BA22: 6982063.5 | BB22: 6911341.6 | BC22: 6811563.9 | BD22: 7542854.8 | BF22: 7438423.4 | BG22: 7337237 | BH22: 7236112 | BI22: 7136609.1 | BJ22: 7038699.9 | BK22: 6990645.9 | BM22: 22188494 | BN22: 7396164.5 | BO22: 7293883.5 | BP22: 16730466 | BQ22: 6942588.8 | BR22: 75544366 | BS22: 6944189.8 | BT22: 9256307.6 | BU22: 9391307.6 | BV22: 8898183.2 | BW22: 8777866.8 | BX22: 8666662.2 | BY22: 8778147.5 | BZ22: 8714498.2 | CA22: 8599916.7 | CB22: 8701620.3 | CE22: 75445572 | CF22: 8370765.6 | CG22: 8262848.7 | CH22: 8156541.8 | CI22: 8055208.1 | CJ22: 8158583 | CK22: 7837621.2 | CL22: 7739505.3 | CM22: 7642792.3 | CN22: 8207148.1 | CO22: 8630411.3 | CP22: 8764183.3 | CQ22: 8660632.3 | CR22: =7019373.03+494423.65+1011935.9+134901.77 -> 8660634.3 | CS22: 8551198.3 | CU22: 63021547
A23: Prepaid Lease Rentals | D23: 0 | E23: 0 | F23: 0 | G23: 0 | H23: 0 | I23: 0 | J23: 0 | K23: 0 | L23: 0 | M23: 0 | N23: 0 | O23: 0 | P23: 0 | Q23: 0 | S23: 0 | T23: 0 | U23: 0 | V23: 0 | W23: 0 | X23: 0 | Y23: 0 | Z23: 0 | AA23: 0 | AB23: 0 | AC23: 0 | AD23: 0 | AF23: 0 | AG23: 0 | AH23: 0 | AI23: 0 | AJ23: 0 | AK23: 0 | AL23: 0 | AM23: 0 | AN23: 0 | AO23: 0 | AP23: 0 | AQ23: 0 | AS23: 0 | AT23: 0 | AU23: 0 | AV23: 0 | AW23: 0 | AX23: 0 | AY23: 0 | AZ23: 0 | BA23: 0 | BB23: 0 | BC23: 0 | BD23: 0 | BF23: 0 | BG23: 0 | BH23: 0 | BI23: 0 | BJ23: 0 | BK23: 0 | BM23: 0 | BN23: 0 | BO23: 0 | BP23: 0 | BQ23: 0 | BR23: 0 | BS23: 0 | BT23: 0 | BU23: 0 | BV23: 0 | BW23: 0 | BX23: 0 | BY23: 0 | BZ23: 0 | CA23: 0 | CB23: 0 | CC23: 0 | CD23: 0 | CE23: 0 | CF23: 0 | CG23: 0 | CH23: 0 | CI23: 0 | CJ23: 0 | CK23: 0 | CL23: 0 | CM23: 0 | CN23: 0 | CO23: 0 | CP23: 0 | CQ23: 0 | CR23: 0 | CS23: 0 | CU23: 494423.65
A24: Intangible Assets | B24: 2028532 | C24: 1495168.6 | D24: 997278.55 | E24: 1453677.8 | F24: 969604.25 | G24: 942697.74 | H24: 916537.87 | I24: 1782207.9 | J24: 866375.81 | K24: 842333.88 | L24: 818959.12 | M24: 796233 | N24: 774136 | O24: 752653.73 | P24: 1463535.2 | Q24: 1032036.7 | R24: 1032036.6 | S24: 2006795.4 | T24: 975553.43 | U24: 948481.83 | V24: 922161.46 | W24: 922161.46 | X24: 920240.29 | Y24: 2684110.9 | Z24: 1739751.2 | AA24: 4228682.7 | AB24: 1644534.7 | AC24: 2398348.3 | AD24: 888469.74 | AE24: 888469.55 | AF24: 863814.7 | AG24: 839843.85 | AH24: 816538.18 | AI24: 793879.25 | AJ24: 771849.1 | AK24: 750430.28 | AL24: 729605.89 | AM24: 709359.28 | AN24: 689674.52 | AO24: 1629174.6 | AP24: 1583965 | AQ24: 1385005.7 | AR24: 1385005.7 | AS24: 1346571.8 | AT24: 1309204.5 | AU24: 1272874 | AV24: 1237551.8 | AW24: 1203209.7 | AX24: 1169820.6 | AY24: 1137358.1 | AZ24: 1105796.4 | BA24: 1075110.6 | BB24: 1045276.3 | BC24: 1016269.8 | BD24: 1394702.7 | BF24: 1355999.7 | BG24: 1318370.8 | BH24: 1281786 | BI24: 1246216.4 | BJ24: 1211633.9 | BK24: 1178011.1 | BM24: 3340615.7 | BN24: 1115730 | BO24: 1084768.5 | BP24: 2789400 | BQ24: 930266.74 | BR24: 930266.74 | BS24: 930266.74 | BT24: 930266.74 | BU24: 930266.74 | BV24: 827007.13 | BW24: 801192.25 | BX24: 4710781.8 | BY24: 4580057.6 | BZ24: 4449334.8 | CA24: 4325866 | CB24: 4205823.2 | CE24: 3889895.2 | CF24: 3781951.2 | CG24: 3677002 | CH24: 3574965.2 | CI24: 3472928.4 | CJ24: 3574965.2 | CK24: 3268854.9 | CL24: 3178144.1 | CM24: 3089951.2 | CN24: 3004205 | CO24: 2918459.1 | CP24: 2837472.1 | CQ24: 2758732.1 | CR24: 2758732.2 | CS24: 2682178.1 | CU24: 7019373
A25: Other Assets | B25: 44250 | C25: 50380 | D25: 83420 | E25: 91059570 | F25: 90987805 | G25: 90987805 | H25: 90987805 | I25: 1.8197561e+08 | J25: 90987805 | K25: 90987805 | L25: 90987805 | M25: 90987805 | N25: 90987805 | O25: 89985792 | P25: 1.7997158e+08 | Q25: 90789876 | R25: 48410 | S25: 1.8136536e+08 | T25: 90682678 | U25: 67395335 | V25: 67395335 | W25: 58298559 | X25: 44300598 | Y25: 1.3290179e+08 | Z25: 94601195 | AA25: 2.3650299e+08 | AB25: 94601195 | AC25: 1.7779709e+08 | AD25: 50903458 | AE25: 68210 | AF25: 50903458 | AG25: 53604357 | AH25: 53290172 | AI25: 53290172 | AJ25: 52209390 | AK25: 52933546 | AL25: 28377798 | AM25: 28377798 | AN25: 28377798 | AO25: 27377798 | AP25: 27980495 | AQ25: 33334808 | AR25: =162360 -> 162360 | AS25: 33954857 | AT25: 33954857 | AU25: 33954857 | AV25: 31818623 | AW25: 32561623 | AX25: 32561623 | AY25: 32561623 | AZ25: 32561623 | BA25: 32561623 | BB25: 32561623 | BC25: 37561623 | BD25: 33404752 | BF25: 34010024 | BG25: 28364844 | BH25: 31713069 | BI25: 28129548 | BJ25: 33639281 | BK25: 35639281 | BM25: 44122401 | BN25: 15406044 | BO25: 15841725 | BP25: 36012626 | BQ25: 17341163 | BR25: 173896 | BS25: 18576742 | BT25: 14125860 | BU25: 14314560 | BV25: 12314560 | BW25: 12314560 | BX25: 41734502 | BY25: 39298909 | BZ25: 45240296 | CA25: 45689994 | CB25: 49794673 | CE25: 194640 | CF25: 49403708 | CG25: 55606066 | CH25: 36192637 | CI25: 36237429 | CJ25: 35044985 | CK25: 31406508 | CL25: 30400911 | CM25: 39949904 | CN25: 39328224 | CO25: 34794856 | CP25: 34450699 | CQ25: 35040714 | CR25: =217010 -> 217010 | CS25: 39577964 | CU25: =SUM(CU21:CU24) -> 72879994
A26: Total Assets | B26: =B20+B16+B13+B8+B7+B4 -> 3.3049886e+08 | C26: =C20+C16+C13+C8+C7+C4 -> 3.482434e+08 | D26: =D20+D16+D13+D8+D7+D4 -> 3.8616078e+08 | E26: =E20+E16+E13+E8+E7+E4 -> 3.9634317e+08 | F26: =F20+F16+F13+F8+F7+F4 -> 3.7907267e+08 | G26: =G20+G16+G13+G8+G7+G4 -> 3.8462171e+08 | H26: =H20+H16+H13+H8+H7+H4 -> 3.7946308e+08 | I26: =I20+I16+I13+I8+I7+I4 -> 739043304 | ... CS26: =CS20+CS16+CS13+CS8+CS7+CS4 -> 5.193942e+08 | CU26: 74026832
A27: Savings and Deposits | B27: 82692444 | C27: 69746223 | D27: 73895934 | E27: 47198708 | F27: 58834512 | G27: 59495528 | H27: 57306603 | I27: 1.0587131e+08 | J27: 45155576 | K27: 42424116 | L27: 38679810 | M27: 37680125 | N27: 37316770 | O27: 2.6523954e+08 | P27: 2.4800679e+08 | Q27: 1.0057772e+08 | R27: =94675309.16+26659720.62 -> 1.2133503e+08 | S27: 1.6768347e+08 | T27: 56007213 | U27: 48529001 | V27: 42966080 | W27: 40687431 | X27: 29913667 | Y27: 1.1725551e+08 | Z27: 72167971 | AA27: 2.0241122e+08 | AB27: 8.0396263e+08 | AC27: 2.880481e+08 | AD27: 54827110 | AE27: =53098512.26+1728598 -> 54827110 | AF27: 58321987 | AG27: 46285448 | AH27: 44903297 | AI27: 42954956 | AJ27: 42218493 | AK27: 32482326 | AL27: 27693034 | AM27: 24434336 | AN27: 23346856 | AO27: 3.1349233e+08 | AP27: 1.1220255e+08 | AQ27: 62524528 | AR27: =58028228.87+4496299.19 -> 62524528 | AS27: 88759001 | AT27: 81521688 | AU27: 99525595 | AV27: 82913368 | AW27: 76055115 | AX27: 76159154 | AY27: 64929812 | AZ27: 58243476 | BA27: 57757115 | BB27: 1.1565401e+08 | BC27: 65905318 | BD27: 78956030 | BF27: 59729887 | BG27: 68821644 | BH27: 47212180 | BI27: 47201742 | BJ27: 48212478 | BK27: 46397911 | BM27: 1.3294717e+08 | BN27: 42322049 | BO27: 1.009443e+08 | BP27: 1.6012346e+08 | BQ27: 65981999 | BR27: =62170125+3811873 -> 65981998 | BS27: 55279905 | BT27: 55814151 | BU27: 40506033 | BV27: 55816435 | BW27: 36501602 | BX27: 35608052 | BY27: 31819466 | BZ27: 30702254 | CA27: 29479348 | CB27: 1.1239381e+08 | CE27: =41714696.89+2263091.16 -> 43977788 | CF27: 39686166 | CG27: 32456511 | CH27: 28856882 | CI27: 35676377 | CJ27: 28393785 | CK27: 28390409 | CL27: 1.2891751e+08 | CM27: 97121983 | CN27: 68574680 | CO27: 57295769 | CP27: 48789391 | CQ27: 43205527 | CR27: 43205527 | CS27: 47238311 | CU27: =CU26-CU25 -> 1146837.7
A28: Short Terrm Deposits | B28: 34007160 | C28: 9331500 | D28: 28342626 | E28: 35697740 | F28: 39980985 | G28: 40542035 | H28: 40767785 | I28: 79334970 | J28: 39048685 | K28: 38536826 | L28: 40109176 | M28: 40709970 | N28: 41492970 | O28: 43093370 | P28: 89083140 | Q28: 41945721 | R28: =15286000+5902412.8 -> 21188413 | S28: 89420841 | T28: 44042621 | U28: 36296012 | V28: 36296012 | W28: 36300962 | X28: 36005612 | Y28: 1.0822714e+08 | Z28: 72165624 | AA28: 1.8543056e+08 | AB28: 75288224 | AC28: 1.1893234e+08 | AD28: 38550412 | AE28: =18524711.85+20025700 -> 38550412 | AF28: 39557112 | AG28: 38996262 | AH28: 39380452 | AI28: 39393401 | AJ28: 40210951 | AK28: 42574748 | AL28: 20243000 | AM28: 20243000 | AN28: 20243000 | AO28: 24989800 | AP28: 25939000 | AQ28: 31271876 | AR28: 31271876 | AS28: 31278323 | AT28: 31231327 | AU28: 37231327 | AV28: 38213247 | AW28: 35659247 | AX28: 36885547 | AY28: 37806047 | AZ28: 40642997 | BA28: 40843947 | BB28: 42018247 | BC28: 44235947 | BD28: 45680597 | BF28: 48127497 | BG28: 50043197 | BH28: 46048454 | BI28: 47673680 | BJ28: 50255694 | BK28: 50692441 | BM28: 1.4997945e+08 | BN28: 49993148 | BO28: 59993148 | BP28: 1.199863e+08 | BQ28: 50011408 | BR28: 51084949 | BS28: 53307152 | BT28: 52473952 | BU28: 53433252 | BV28: 50306227 | BW28: 55739477 | BX28: 55029277 | BY28: 56777777 | BZ28: 57539577 | CA28: 55964777 | CB28: 58904152 | CE28: 57981352 | CF28: 59704696 | CG28: 63256052 | CH28: 71160652 | CI28: 72086048 | CJ28: 71307048 | CK28: 73678248 | CL28: 81278548 | CM28: 83661848 | CN28: 80153098 | CO28: 80738072 | CP28: 86147422 | CQ28: 86819922 | CR28: 86819922 | CS28: 87173222
A29: Non Withdrawable Deposits | B29: 47036877 | C29: 46620378 | D29: 46620379 | E29: 46706120 | F29: 47996421 | G29: 50229762 | H29: 46820378 | I29: 93240756 | J29: 44620378 | K29: 44620378 | L29: 45196388 | M29: 45235489 | N29: 45035489 | O29: 45150989 | P29: 90007010 | Q29: 60614386 | R29: 60614336 | S29: 1.2620243e+08 | T29: 63101214 | U29: 61101214 | V29: 61101214 | W29: 52608838 | X29: 53290738 | Y29: 162059493 | Z29: 109276662 | AA29: 278191655 | AB29: 115276662 | AC29: 172914993 | AD29: 59231544 | AE29: 59231544 | AF29: 60585214 | AG29: 61334423 | AH29: 60986895 | AI29: 61986895 | AJ29: 62986895 | AK29: 60719755 | AL29: 54719755 | AM29: 55306375 | AN29: 55806375 | AO29: 59806375 | AP29: 66634554 | AQ29: 65285855 | AR29: 65285855 | AS29: 67914531 | AT29: 67914531 | AU29: 68914531 | AV29: 70914531 | AW29: 69921687 | AX29: 69921687 | AY29: 69921687 | AZ29: 69918077 | BA29: 67284120 | BB29: 67284120 | BC29: 71365656 | BD29: 70701479 | BF29: 70701479 | BG29: 70701479 | BH29: 70701479 | BI29: 70701479 | BJ29: 70701479 | BK29: 70701479 | BM29: 1.5407184e+08 | BN29: 51357279 | BO29: 51357279 | BP29: 1.0271456e+08 | BQ29: 51313842 | BR29: 51313842 | BS29: 51294476 | BT29: 51364766 | BU29: 51547793 | BV29: 52112760 | BW29: 53047230 | BX29: 53810158 | BY29: 54515112 | BZ29: 55198467 | CA29: 55765306 | CB29: 56973192 | CE29: 51392305 | CF29: 52241662 | CG29: 53084535 | CH29: 53939057 | CI29: 55281779 | CJ29: 56264805 | CK29: 57348971 | CL29: 59069138 | CM29: 59553457 | CN29: 60342129 | CO29: 61293411 | CP29: 62175589 | CQ29: 61135400 | CR29: 59333400 | CS29: 60802471
A30: Total Deposit Liabilities | B30: =SUM(B27:B29) -> 1.6373648e+08 | C30: =SUM(C27:C29) -> 1.256981e+08 | D30: =SUM(D27:D29) -> 1.4885894e+08 | E30: =SUM(E27:E29) -> 1.2960257e+08 | F30: =SUM(F27:F29) -> 1.4681192e+08 | G30: =SUM(G27:G29) -> 1.5026732e+08 | H30: =SUM(H27:H29) -> 1.4489477e+08 | I30: =SUM(I27:I29) -> 2.7844703e+08 | ... CS30: =SUM(CS27:CS29) -> 1.95214e+08
A31: Tax Payable | B31: 726766 | C31: 4201974 | D31: 133661 | E31: 0 | F31: 0 | G31: 0 | H31: 0 | I31: 0 | J31: 0 | K31: 0 | L31: 0 | M31: 0 | N31: 0 | O31: 0 | P31: 0 | Q31: 0 | S31: 0 | T31: 0 | U31: 0 | V31: 0 | W31: 0 | X31: 0 | Y31: 0 | Z31: 0 | AA31: 0 | AB31: 0 | AC31: 0 | AD31: 0 | AF31: 0 | AG31: 0 | AH31: 0 | AI31: 0 | AJ31: 0 | AK31: 0 | AL31: 0 | AM31: 0 | AN31: 0 | AO31: 0 | AP31: 0 | AQ31: 0 | AR31: 0 | AS31: 0 | AT31: 0 | AU31: 0 | AV31: 0 | AW31: 0 | AX31: 0 | AY31: 0 | AZ31: 0 | BA31: 0 | BB31: 0 | BC31: 0 | BD31: 0 | BF31: 0 | BG31: 0 | BH31: 0 | BI31: 0 | BJ31: 0 | BK31: 0 | BM31: 0 | BN31: 0 | BO31: 0 | BP31: 0 | BQ31: 0 | BR31: 0 | BS31: 0 | BT31: 0 | BU31: 0 | BV31: 0 | BW31: 0 | BX31: 0 | BY31: 0 | BZ31: 0 | CA31: 0 | CB31: 0 | CC31: 0 | CD31: 0 | CE31: 0 | CF31: 0 | CG31: 0 | CH31: 0 | CI31: 0 | CJ31: 0 | CK31: 0 | CL31: 0 | CM31: 0 | CN31: 0 | CO31: 0 | CP31: 0 | CQ31: 0 | CR31: 0 | CS31: 0
A32: Dividends Payable | B32: 260087.98 | C32: 260087.7 | D32: 260087.7 | E32: 3260088 | F32: 260087.98 | G32: 3260087.9 | H32: 3260087.9 | I32: 6520175.8 | J32: 3260087.9 | K32: 3260087.9 | L32: 260087.9 | M32: 260087.9 | N32: 260087.9 | O32: 260087.9 | P32: 520175.8 | Q32: 260087.9 | S32: 9800175.8 | T32: 4900087.9 | U32: 900087.9 | V32: 260087.9 | W32: 260087.9 | X32: 260087.9 | Y32: 780263.7 | Z32: 520175.8 | AA32: 1300439.5 | AB32: 520175.8 | AC32: 780263.7 | AD32: 260087.9 | AE32: 0 | AF32: 260087.9 | AG32: 260087.9 | AH32: 260087.9 | AI32: 260087.9 | AJ32: 260087.9 | AK32: 260087.9 | AL32: 260087.9 | AM32: 260087.9 | AN32: 260087.9 | AO32: 260087.9 | AP32: 260087.8 | AQ32: 0 | AR32: 3000000 | AS32: 0 | AT32: 0 | AU32: 0 | AV32: 0 | AW32: 0 | AX32: 0 | AY32: 0 | AZ32: 0 | BA32: 0 | BB32: 0 | BC32: 0 | BD32: 0 | BF32: 0 | BG32: 0 | BH32: 0 | BI32: 0 | BJ32: 0 | BK32: 0 | BM32: 0 | BN32: 0 | BO32: 0 | BP32: 0 | BQ32: 0 | BR32: 0 | BS32: 0 | BT32: 0 | BU32: 0 | BV32: 0 | BW32: 0 | BX32: 0 | BY32: 0 | BZ32: 0 | CA32: 0 | CB32: 0 | CC32: 0 | CD32: 0 | CE32: 0 | CF32: 0 | CG32: 0 | CH32: 0 | CI32: 0 | CJ32: 0 | CK32: 0 | CL32: 0 | CM32: 0 | CN32: 0 | CO32: 0 | CP32: 0 | CQ32: 0 | CR32: 0 | CS32: 0 | CU32: =CR26-CR49 -> -2.5899999
A33: Deferred Tax Liability | E33: 0 | F33: 0 | G33: 0 | H33: 0 | I33: 0 | J33: 0 | K33: 0 | L33: 0 | M33: 0 | N33: 0 | O33: 0 | P33: 0 | Q33: 0 | S33: 0 | T33: 0 | U33: 0 | V33: 0 | W33: 0 | X33: 0 | Y33: 0 | Z33: 0 | AA33: 0 | AB33: 0 | AC33: 0 | AD33: 0 | AF33: 0 | AG33: 0 | AH33: 0 | AI33: 0 | AJ33: 0 | AK33: 0 | AL33: 0 | AM33: 0 | AN33: 0 | AO33: 0 | AP33: 0 | AQ33: 0 | AS33: 0 | AT33: 0 | AU33: 0 | AV33: 0 | AW33: 0 | AX33: 0 | AY33: 0 | AZ33: 0 | BA33: 0 | BB33: 0 | BC33: 0 | BD33: 0 | BF33: 0 | BG33: 0 | BH33: 0 | BI33: 0 | BJ33: 0 | BK33: 0 | BM33: 0 | BN33: 0 | BO33: 0 | BP33: 0 | BQ33: 0 | BR33: 0 | BS33: 0 | BT33: 0 | BU33: 0 | BV33: 0 | BW33: 0 | BX33: 0 | BY33: 0 | BZ33: 0 | CA33: 0 | CB33: 0 | CC33: 0 | CD33: 0 | CE33: 0 | CF33: 0 | CG33: 0 | CH33: 0 | CI33: 0 | CJ33: 0 | CK33: 0 | CL33: 0 | CM33: 0 | CN33: 0 | CO33: 0 | CP33: 0 | CQ33: 0 | CR33: 0 | CS33: 0
A34: Retirement Benefits Liabilty | B34: 21719.65 | C34: 21719.65 | D34: 21719.65 | E34: 21719.65 | F34: 21719.65 | G34: 21719.65 | H34: 21719.65 | I34: 43439.3 | J34: 21719.65 | K34: 21719.65 | L34: 21719.65 | M34: 21719.65 | N34: 21719.65 | O34: 21719.65 | P34: 43439.3 | Q34: 21719.65 | R34: 21719.65 | S34: 43439.3 | T34: 21719.65 | U34: 21719.65 | V34: 21719.65 | W34: 21719.65 | X34: 21719.65 | Y34: 65158.95 | Z34: 43439.3 | AA34: 108598.25 | AB34: 43439.3 | AC34: 65158.95 | AD34: 21719.65 | AE34: 21719.65 | AF34: 21719.65 | AG34: 21719.65 | AH34: 21719.65 | AI34: 21719.65 | AJ34: 21719.65 | AK34: 21719.65 | AL34: 21719.65 | AM34: 21719.65 | AN34: 21719.65 | AO34: 21719.65 | AP34: 21719.65 | AQ34: 0 | AS34: 0 | AT34: 0 | AU34: 0 | AV34: 0 | AW34: 0 | AX34: 0 | AY34: 0 | AZ34: 0 | BA34: 0 | BB34: 0 | BC34: 0 | BD34: 0 | BF34: 0 | BG34: 0 | BH34: 0 | BI34: 0 | BJ34: 0 | BK34: 0 | BM34: 0 | BN34: 0 | BO34: 0 | BP34: 0 | BQ34: 0 | BR34: 0 | BS34: 0 | BT34: 0 | BU34: 0 | BV34: 0 | BW34: 0 | BX34: 0 | BY34: 0 | BZ34: 0 | CA34: 0 | CB34: 0 | CC34: 0 | CD34: 0 | CE34: 0 | CF34: 0 | CG34: 0 | CH34: 0 | CI34: 0 | CJ34: 0 | CK34: 0 | CL34: 0 | CM34: 0 | CN34: 0 | CO34: 0 | CP34: 0 | CQ34: 0 | CR34: 0 | CS34: 0
A35: Other Liabilities | B35: 8710334.4 | C35: 5312991.1 | D35: 3436556.4 | E35: 9395944.1 | F35: 1172898.5 | G35: 2213121.5 | H35: 2252121.5 | I35: 4024243 | J35: 1812121.5 | K35: 1812121.5 | L35: 1812121.5 | M35: 1822121 | N35: 1822121 | O35: 1822121 | P35: 3644242 | Q35: 1565605.5 | R35: =1855213.05-21719.65+1479839.25 -> 3313332.7 | S35: 4810889.5 | T35: 2405444.8 | U35: 2405444.8 | V35: 2218759.2 | W35: 2218759.2 | X35: 2218759.2 | Y35: 7173117.8 | Z35: 4867078.5 | AA35: 12167696 | AB35: 4867078.5 | AC35: 18102913 | AD35: 1005903.8 | AE35: =613322.57+1295511.3-21719.65 -> 1887114.2 | AF35: 1005903.8 | AG35: 1006903.8 | AH35: 1156040.2 | AI35: 1156040.2 | AJ35: 509181.25 | AK35: 509181.25 | AL35: 509181.25 | AM35: 509181.25 | AN35: 509181.25 | AO35: 509181.25 | AP35: 509181.25 | AQ35: 431725.3 | AR35: 3351688.5 | AS35: 398825.3 | AT35: 398825.3 | AU35: 398825.3 | AV35: 398825.3 | AW35: 398825.3 | AX35: 398825.3 | AY35: 398825.3 | AZ35: 398825.3 | BA35: 398825.3 | BB35: 398825.3 | BC35: 398825.3 | BD35: 652944.13 | BF35: 1535601.9 | BG35: 1743891.9 | BH35: 2230487.9 | BI35: 2587813.9 | BJ35: 2867372.9 | BK35: 3206685.9 | BM35: 6348735 | BN35: 2430126 | BO35: 2676345 | BP35: 5322794 | BQ35: 1236204.8 | BR35: 1280470 | BS35: 0 | BT35: 0 | BU35: -3668704 | BV35: -1576039.8 | BW35: -4570956.8 | BX35: 1453023.8 | BY35: 6087331.5 | BZ35: 2720574.2 | CA35: 2009964.2 | CB35: 1723350.2 | CE35: 3312827.5 | CF35: 894774.36 | CG35: 4146540.4 | CH35: 2372648.9 | CI35: 1313617.4 | CJ35: 210459.74 | CK35: 1581147.6 | CL35: 337955.8 | CM35: 194189.42 | CN35: 123440.76 | CO35: 1259753.9 | CP35: 2573067 | CQ35: 7290460.2 | CR35: 7358475.3 | CS35: 5330812.6
A36: External Borrowings | B36: 92209657 | C36: 1.4559074e+08 | D36: 165770876 | E36: 1.9020569e+08 | F36: 165770876 | G36: 167383681 | H36: 167383681 | I36: 334767362 | J36: 167383681 | K36: 167383681 | L36: 169361564 | M36: 169361564 | N36: 169361564 | O36: 97082102 | P36: 140454878 | Q36: 70863642 | R36: 70863642 | S36: 1.4172728e+08 | T36: 1.2086364e+08 | U36: 1.2086364e+08 | V36: 1.2086364e+08 | W36: 1.2086364e+08 | X36: 1.2086364e+08 | Y36: 3.6259093e+08 | Z36: 2.4172728e+08 | AA36: 6.0431821e+08 | AB36: 1.1572728e+08 | AC36: 211971366 | AD36: 70212126 | AE36: 70212126 | AF36: 1.0021213e+08 | AG36: 1.4021213e+08 | AH36: 1.2521213e+08 | AI36: 1.2521213e+08 | AJ36: 1.2521213e+08 | AK36: 1.5021213e+08 | AL36: 1.5021213e+08 | AM36: 1.5021213e+08 | AN36: 1.5021213e+08 | AO36: 39212126 | AP36: 39212126 | AQ36: 89212126 | AR36: 89212126 | AS36: 89212126 | AT36: 89212126 | AU36: 89212126 | AV36: 89212126 | AW36: 89212126 | AX36: 89212126 | AY36: 89212126 | AZ36: 89212126 | BA36: 89212126 | BB36: 33137908 | BC36: 83137908 | BD36: 83909094 | BF36: 113909094 | BG36: 113909094 | BH36: 193909094 | BI36: 193909094 | BJ36: 193909094 | BK36: 190909094 | BM36: 563727282 | BN36: 187909094 | BO36: 181309197 | BP36: 142618394 | BQ36: 1.2223748e+08 | BR36: 1.2223748e+08 | BS36: 1.2223748e+08 | BT36: 1.7223748e+08 | BU36: 1.6893748e+08 | BV36: 1.6893748e+08 | BW36: 1.6893748e+08 | BX36: 1.6563748e+08 | BY36: 1.6563748e+08 | BZ36: 1.6563748e+08 | CA36: 1.6563748e+08 | CB36: 1.6233748e+08 | CE36: 84895865 | CF36: 84895865 | CG36: 81019053 | CH36: 77429199 | CI36: 75217598 | CJ36: 75217598 | CK36: 71179199 | CL36: 67879199 | CM36: 63712532 | CN36: 60412532 | CO36: 55859154 | CP36: 54571354 | CQ36: 49188020 | CR36: 49188020 | CS36: 49188020 | CU36: =780833333-662983882 -> 117849451
A37: Total Liabilities | B37: =SUM(B30:B36) -> 2.6566505e+08 | C37: =SUM(C30:C36) -> 2.8108561e+08 | D37: =SUM(D30:D36) -> 3.1848184e+08 | E37: =SUM(E30:E36) -> 3.3248601e+08 | F37: =SUM(F30:F36) -> 3.140375e+08 | G37: =SUM(G30:G36) -> 3.2314593e+08 | H37: =SUM(H30:H36) -> 3.1781238e+08 | I37: =SUM(I30:I36) -> 6.2380225e+08 | ... CS37: =SUM(CS30:CS36) -> 2.4973284e+08
A38: Share Capital | B38: 53318339 | C38: 53578123 | D38: 54397850 | E38: 53593123 | F38: 54422249 | G38: 54422249 | H38: 54422449 | I38: 109244898 | J38: 54622449 | K38: 54622449 | L38: 54622636 | M38: 54622836 | N38: 54628836 | O38: 54628836 | P38: 109257672 | Q38: 54009356 | R38: =11866000+38166977+3976378.31 -> 54009355 | S38: 1.0803671e+08 | T38: 54027356 | U38: 54027356 | V38: 54027356 | W38: 54027356 | X38: 54029456 | Y38: 1.6208837e+08 | Z38: 1.2626686e+08 | AA38: 3.1566816e+08 | AB38: 1.2626726e+08 | AC38: 1.8945009e+08 | AD38: 63759620 | AE38: =12475588+38210877.56+13073154.58 -> 63759620 | AF38: 63759620 | AG38: 63763720 | AH38: 63763720 | AI38: 63763720 | AJ38: 63766170 | AK38: 63766170 | AL38: 63766970 | AM38: 63766970 | AN38: 63766970 | AO38: 63766970 | AP38: 63771970 | AQ38: 71383883 | AR38: =20087500+51296383.14 -> 71383883 | AS38: 71383883 | AT38: 71383883 | AU38: 71383883 | AV38: 71383883 | AW38: 71383883 | AX38: 71383883 | AY38: 71383883 | AZ38: 71383883 | BA38: 71383883 | BB38: 71383883 | BC38: 71383883 | BD38: 72827883 | BF38: 72827883 | BG38: 72827883 | BH38: 72827883 | BI38: 72827883 | BJ38: 72827883 | BK38: 72827883 | BM38: 2.1848365e+08 | BN38: 72827883 | BO38: 72827883 | BP38: 1.4565577e+08 | BQ38: 72827883 | BR38: =21531500+51296383 -> 72827883 | BS38: 72827883 | BT38: 72827883 | BU38: 72827883 | BV38: 72827883 | BW38: 72827883 | BX38: 72827883 | BY38: 72827883 | BZ38: 72827883 | CA38: 72827883 | CB38: 72827883 | CE38: =22787500+51296383.14 -> 74083883 | CF38: 74083883 | CG38: 74083883 | CH38: 74083883 | CI38: 74083883 | CJ38: 74083883 | CK38: 74083883 | CL38: 74083883 | CM38: 74083883 | CN38: 74083883 | CO38: 74083883 | CP38: 74083883 | CQ38: 74083883 | CR38: =24589500+51296383.14 -> 75885883 | CS38: 75885883
A39: Capital Grants | D39: 0 | E39: 0 | F39: 0 | G39: 0 | H39: 0 | I39: 0 | J39: 0 | K39: 0 | L39: 0 | M39: 0 | N39: 0 | O39: 0 | P39: 0 | Q39: 0 | S39: 0 | T39: 0 | U39: 0 | V39: 0 | W39: 0 | X39: 0 | Y39: 0 | Z39: 0 | AA39: 0 | AB39: 0 | AC39: 0 | AD39: 0 | AF39: 0 | AG39: 0 | AH39: 0 | AI39: 0 | AJ39: 0 | AK39: 0 | AL39: 0 | AM39: 0 | AN39: 0 | AO39: 0 | AP39: 0 | AQ39: 0 | AS39: 0 | AT39: 0 | AU39: 0 | AV39: 0 | AW39: 0 | AX39: 0 | AY39: 0 | AZ39: 0 | BA39: 0 | BB39: 0 | BC39: 0 | BD39: 0 | BF39: 0 | BG39: 0 | BH39: 0 | BI39: 0 | BJ39: 0 | BK39: 0 | BM39: 0 | BN39: 0 | BO39: 0 | BP39: 0 | BQ39: 0 | BR39: 0 | BS39: 0 | BT39: 0 | BU39: 0 | BV39: 0 | BW39: 0 | BX39: 0 | BY39: 0 | BZ39: 0 | CA39: 0 | CB39: 0 | CC39: 0 | CD39: 0 | CE39: 0 | CF39: 0 | CG39: 0 | CH39: 0 | CI39: 0 | CJ39: 0 | CK39: 0 | CL39: 0 | CM39: 0 | CN39: 0 | CO39: 0 | CP39: 0 | CQ39: 0 | CR39: 0 | CS39: 0
A40: Retained Earnings | AE40: =AE41+AE42 -> -4882771 | AF40: =AF41+AF42 -> -8077690 | AG40: =AG41+AG42 -> -644276.4 | AH40: =AH41+AH42 -> -4877609.9 | AI40: =AI41+AI42 -> -10680943 | AJ40: =AJ41+AJ42 -> -10868329 | AK40: =AK41+AK42 -> 6347607.2 | AL40: =AL41+AL42 -> 17109150 | ... BY40: =BY41+BY42 -> 18391355 | CE40: -2188704.5 | CF40: =CF41+CF42 -> 15869503 | CG40: =CG41+CG42 -> 13822241 | CH40: =CH41+CH42 -> -9528477.4 | CI40: =CI41+CI42 -> -6886861.4 | CJ40: =CJ41+CJ42 -> -7138564.5 | CK40: =CK41+CK42 -> 2976060.2 | CL40: =CL41+CL42 -> 18482580 | CM40: =CM41+CM42 -> 16312136 | ... CR40: =CR41+CR42 -> 2211402.9
A41: Prior Year Retained Earnigs | B41: 2589644.6 | C41: 2874282 | D41: 2973626.4 | E41: 2973626 | F41: 2973626 | G41: 2023521 | H41: 2023521 | I41: 4047042 | J41: 2023521 | K41: 2023521 | L41: 2023521 | M41: 2023521 | N41: 2023521 | O41: 2023521 | P41: 4047042 | Q41: 2023521 | R41: 2023571 | S41: 2908840 | T41: 1454420 | U41: -13033020 | V41: -13033020 | W41: -13033020 | X41: -13033020 | Y41: -39099060 | Z41: -26066040 | AA41: -65165100 | AB41: -26066040 | AC41: -39099060 | AD41: -13033020 | AE41: -13033020 | AF41: -13033020 | AG41: -4882771 | AH41: -4882771 | AI41: -4882771 | AJ41: -4882771 | AK41: -4882771 | AL41: 13604669 | AM41: 13604669 | AN41: 13604669 | AO41: 13604669 | AP41: 13604669 | AQ41: 14692229 | AR41: =-4882771 -> -4882771 | AS41: 14692229 | AT41: 6078993 | AU41: 6078993 | AV41: 6078993 | AW41: 6078993 | AX41: 6078993 | AY41: 6078993 | AZ41: 6078993 | BA41: 6078993 | BB41: 6078993 | BC41: 6078993 | BD41: 6078993 | BF41: 6078993 | BG41: 6078993 | BH41: 9048608 | BI41: 9048608 | BJ41: 9048608 | BK41: 9048608 | BM41: 27145824 | BN41: 9048608 | BO41: 9048608 | BP41: 18097216 | BQ41: 9048608.2 | BR41: 9048608.2 | BS41: 16050027 | BT41: 16050027 | BU41: 16050027 | BV41: 16050027 | BW41: 16050027 | BX41: 14976486 | BY41: 14976486 | BZ41: 14976486 | CA41: 14976486 | CB41: 14976486 | CE41: 9048608.2 | CF41: 17197894 | CG41: 17196932 | CH41: -2573343.2 | CI41: -2573511.2 | CJ41: -2188704.5 | CK41: -2188704.5 | CL41: -2188704.5 | CM41: -2188704.5 | CN41: -2188704.5 | CO41: -2188704.5 | CP41: -2188704.5 | CQ41: -2188704.5 | CR41: -2188704.5 | CS41: 10420628
A42: Current Year Surplus | B42: 284637 | C42: 99344 | D42: -950055.4 | E42: -315628.2 | F42: 33264.3 | G42: -3227517.4 | H42: -3052787.5 | I42: -14565932 | J42: -5801662.5 | K42: -8799568.2 | L42: -142226.2 | M42: -475876.3 | N42: -4885325.2 | O42: 4161180.2 | P42: 11232450 | Q42: 5965899.2 | R42: -15056591 | S42: 5000105.2 | T42: 364743.2 | U42: -1178323.5 | V42: -1390731.2 | W42: -1390731.2 | X42: 1068279.1 | Y42: -17711631 | Z42: -21111401 | AA42: -56879062 | AB42: 8445238.2 | AC42: 10461172 | AD42: 10838634 | AE42: 8150249 | AF42: 4955330 | AG42: 4238494.6 | AH42: 5161.13 | AI42: -5798172.2 | AJ42: -5985558.2 | AK42: 11230378 | AL42: 3504481 | AM42: -47085.7 | AN42: -652308.4 | AO42: 17540466 | AP42: 14544258 | AQ42: 5177119.8 | AR42: =10961764.45 -> 10961764 | AS42: 4157581.4 | AT42: 4922408.5 | AU42: -1505076.4 | AV42: -2996179.1 | AW42: -5170540 | AX42: 16092303 | AY42: 15608694 | AZ42: 14243594 | BA42: 10262794 | BB42: 14682965 | BC42: 7772633.3 | BD42: -2461812.6 | BF42: 1732996.3 | BG42: 3426984.5 | BH42: -11112710 | BI42: -8852183.1 | BJ42: 3793329.4 | BK42: 4432695 | BM42: 7686138.4 | BN42: -2847893.8 | BO42: 15037349 | BP42: 14628640 | BQ42: 7001417.9 | BR42: =-1190198.7+7114388.17 -> 5924189.5 | BS42: 3971603.2 | BT42: 395398.1 | BU42: 847338.5 | BV42: 3813663.7 | BW42: 2894890.5 | BX42: 3834131.9 | BY42: 3414868.5 | BZ42: -1866136.8 | CA42: -1242310.9 | CB42: 7882384.9 | CE42: =2608773.13-19770275.29 -> -17161502 | CF42: -1328391 | CG42: -3374691.3 | CH42: -6955134.2 | CI42: -4313350.2 | CJ42: -4949860 | CK42: 5164764.7 | CL42: 20671285 | CM42: 18500841 | CN42: 20254357 | CO42: 18382573 | CP42: 9814743 | CQ42: 13058134 | CR42: 4400107.4 | CS42: 2150370.7
A43: Statutory Reserves | B43: 6641198.1 | C43: 7606034 | D43: 8257520.3 | E43: 7606034 | F43: 7606034 | G43: 8257521 | H43: 8257521 | I43: 16515042 | J43: 8257521 | K43: 8257521 | L43: 8257521 | M43: 8257521 | N43: 8257521 | O43: 8257521 | P43: 16515042 | Q43: 8257521 | R43: 9312732 | S43: 18625464 | T43: 9312732 | U43: 9312732 | V43: 9312732 | W43: 9312732 | X43: 9312732 | Y43: 27938196 | Z43: 18625464 | AA43: 46563660 | AB43: 18625464 | AC43: 27938196 | AD43: 9312732 | AE43: 11387794 | AF43: 9312732 | AG43: 11387794 | AH43: 11387794 | AI43: 11387794 | AJ43: 11387794 | AK43: 11387794 | AL43: 11387794 | AM43: 11387794 | AN43: 11387794 | AO43: 11387794 | AP43: 11387794 | AQ43: 11387794 | AR43: =11387794+'Evolutitve SCI'!AS37 -> 15545375 | AS43: 11387794 | AT43: 14878235 | AU43: 14878235 | AV43: 14878235 | AW43: 14878235 | AX43: 14878235 | AY43: 14878235 | AZ43: 170910185 | BA43: 170910185 | BB43: 170910185 | BC43: 170910185 | BD43: 170910185 | BF43: 170910185 | BG43: 170910185 | BH43: 180620112 | BI43: 180620112 | BJ43: 180620112 | BK43: 180620112 | BM43: 541860336 | BN43: 180620112 | BO43: 180620112 | BP43: 361240224 | BQ43: 1.8062011e+08 | BR43: 15620639 | BS43: 1.8062011e+08 | BT43: 1.8062011e+08 | BU43: 1.8062011e+08 | BV43: 1.8062011e+08 | BW43: 1.8062011e+08 | BX43: 15620639 | BY43: 15620639 | BZ43: 15620639 | CA43: 15620639 | CB43: 15620639 | CE43: 16272832 | CF43: 15620639 | CG43: 15620639 | CH43: 15620639 | CI43: 15620639 | CJ43: 15620639 | CK43: 16272832 | CL43: 16272832 | CM43: 16272832 | CN43: 16272832 | CO43: 16272832 | CP43: 16272832 | CQ43: 16272832 | CR43: 18872858 | CS43: 16272832 | CT43: 2.6615779e+08 | CV43: 3500000
A44: Other Reserves | B44: 0 | D44: 0 | E44: 0 | F44: 0 | G44: 0 | H44: 0 | I44: 0 | J44: 0 | K44: 0 | L44: 0 | M44: 0 | N44: 0 | O44: 0 | P44: 0 | Q44: 0 | S44: 0 | T44: 0 | U44: 0 | V44: 0 | W44: 0 | X44: 0 | Y44: 0 | Z44: 0 | AA44: 0 | AB44: 0 | AC44: 0 | AD44: 0 | AE44: 0 | AF44: 0 | AG44: 0 | AH44: 0 | AI44: 0 | AJ44: 0 | AK44: 0 | AP44: 0 | AQ44: 0 | AS44: 0 | AT44: 0 | AU44: 0 | AV44: 0 | AW44: 0 | AX44: 0 | AY44: 0 | AZ44: 0 | BA44: 0 | BB44: 0 | BC44: 0 | BD44: 0 | BF44: 0 | BG44: 0 | BH44: 0 | BI44: 0 | BJ44: 0 | BK44: 0 | BM44: 0 | BN44: 0 | BO44: 0 | BP44: 0 | BQ44: 0 | BR44: 0 | BS44: 0 | BT44: 0 | BU44: 0 | BV44: 0 | BW44: 0 | BX44: 0 | BY44: 0 | BZ44: 0 | CA44: 0 | CB44: 0 | CC44: 0 | CD44: 0 | CE44: 0 | CN44: 0 | CO44: 0 | CP44: 0 | CQ44: 0 | CR44: 0 | CT44: =CT43-CQ48 -> 0 | CV44: =CV43/10*4% -> 14000
A45: Revaluation Reserves | B45: 0 | D45: 0 | E45: 0 | F45: 0 | G45: 0 | H45: 0 | I45: 0 | J45: 0 | K45: 0 | L45: 0 | M45: 0 | N45: 0 | O45: 0 | P45: 0 | Q45: 0 | S45: 0 | T45: 0 | U45: 0 | V45: 0 | W45: 0 | X45: 0 | Y45: 0 | Z45: 0 | AA45: 0 | AB45: 0 | AC45: 0 | AD45: 0 | AE45: 0 | AF45: 0 | AG45: 0 | AH45: 0 | AI45: 0 | AJ45: 0 | AK45: 0 | AP45: 0 | AQ45: 0 | AR45: 156031950 | AS45: 0 | AT45: 0 | AU45: 0 | AV45: 0 | AW45: 0 | AX45: 0 | AY45: 0 | AZ45: 0 | BA45: 0 | BB45: 0 | BC45: 0 | BD45: 0 | BF45: 0 | BG45: 0 | BH45: 0 | BI45: 0 | BJ45: 0 | BK45: 0 | BM45: 0 | BN45: 0 | BO45: 0 | BP45: 0 | BQ45: 0 | BR45: 1.1166543e+08 | BS45: 0 | BT45: 0 | BU45: 0 | BV45: 0 | BW45: 0 | BX45: 111665431 | BY45: 111665431 | BZ45: 111665431 | CA45: 111665431 | CB45: 111665431 | CE45: 1.6493164e+08 | CF45: 111665431 | CG45: 111665431 | CH45: 111665431 | CI45: 111665431 | CJ45: 111665431 | CK45: 1.6493164e+08 | CL45: 1.6493164e+08 | CM45: 1.6493164e+08 | CN45: 1.6493164e+08 | CO45: 1.6493164e+08 | CP45: 1.6493164e+08 | CQ45: 1.6493164e+08 | CR45: 1.6833379e+08 | CS45: 1.6493164e+08
A46: Proposed Dividends | B46: 2000000 | C46: 3000000 | D46: 3000000 | E46: 0 | F46: 0 | G46: 0 | H46: 0 | I46: 0 | J46: 0 | K46: 0 | L46: 0 | M46: 0 | N46: 0 | O46: 0 | P46: 0 | Q46: 0 | S46: 0 | T46: 0 | U46: 0 | V46: 0 | W46: 0 | X46: 0 | Y46: 0 | Z46: 0 | AA46: 0 | AB46: 0 | AC46: 0 | AD46: 0 | AE46: 0 | AF46: 0 | AG46: 0 | AH46: 0 | AI46: 0 | AJ46: 0 | AK46: 0 | AP46: 0 | AQ46: 0 | AS46: 0 | AT46: 0 | AU46: 0 | AV46: 0 | AW46: 0 | AX46: 0 | AY46: 0 | AZ46: 0 | BA46: 0 | BB46: 0 | BC46: 0 | BD46: 0 | BF46: 0 | BG46: 0 | BH46: 0 | BI46: 0 | BJ46: 0 | BK46: 0 | BM46: 0 | BN46: 0 | BO46: 0 | BP46: 0 | BQ46: 0 | BR46: 0 | BS46: 0 | BT46: 0 | BU46: 0 | BV46: 0 | BW46: 0 | BX46: 0 | BY46: 0 | BZ46: 0 | CA46: 0 | CB46: 0 | CC46: 0 | CD46: 0 | CE46: 0 | CF46: 0 | CG46: 0 | CH46: 0 | CI46: 0 | CJ46: 0 | CK46: 0 | CL46: 0 | CM46: 0 | CN46: 0 | CO46: 0 | CP46: 0 | CQ46: 0 | CR46: =5000000+1000000 -> 6000000 | CS46: 0
A47: Adjustment To Equity | B47: 0 | D47: 0 | E47: 0 | F47: 0 | G47: 0 | H47: 0 | I47: 0 | J47: 0 | K47: 0 | L47: 0 | M47: 0 | N47: 0 | O47: 0 | P47: 0 | Q47: 0 | S47: 0 | T47: 0 | U47: 0 | V47: 0 | W47: 0 | X47: 0 | Y47: 0 | Z47: 0 | AA47: 0 | AB47: 0 | AC47: 0 | AD47: 0 | AE47: 0 | AF47: 0 | AG47: 0 | AH47: 0 | AI47: 0 | AJ47: 0 | AK47: 0 | AL47: 0 | AM47: 0 | AN47: 0 | AO47: 0 | AP47: 0 | AQ47: 0 | AS47: 0 | AT47: 0 | AU47: 0 | AV47: 0 | AW47: 0 | AX47: 0 | AY47: 0 | AZ47: 0 | BA47: 0 | BB47: 0 | BC47: 0 | BD47: 0 | BF47: 0 | BG47: 0 | BH47: 0 | BI47: 0 | BJ47: 0 | BK47: 0 | BM47: 0 | BN47: 0 | BO47: 0 | BP47: 0 | BQ47: 0 | BR47: 0 | BS47: 0 | BT47: 0 | BU47: 0 | BV47: 0 | BW47: 0 | BX47: 0 | BY47: 0 | BZ47: 0 | CA47: 0 | CB47: 0 | CC47: 0 | CD47: 0 | CE47: 0 | CF47: 0 | CG47: 0 | CH47: 0 | CI47: 0 | CJ47: 0 | CK47: 0 | CL47: 0 | CM47: 0 | CN47: 0 | CO47: 0 | CP47: 0 | CQ47: 0 | CR47: 0 | CS47: 0
A48: Total Equity | B48: =SUM(B38:B47) -> 64833818 | C48: =SUM(C38:C47) -> 67157783 | D48: =SUM(D38:D47) -> 67678941 | E48: =SUM(E38:E47) -> 63857155 | F48: =SUM(F38:F47) -> 65035173 | G48: =SUM(G38:G47) -> 61475774 | H48: =SUM(H38:H47) -> 61650704 | I48: =SUM(I38:I47) -> 1.1524105e+08 | ... AD48: =SUM(AD38:AD47) -> 70877966 | AE48: =SUM(AE38+AE39+AE40+AE43+AE44+AE45+AE46) -> 70264643 | AF48: =SUM(AF38+AF39+AF40+AF43+AF44+AF45+AF46) -> 64994662 | AG48: =SUM(AG38+AG39+AG40+AG43+AG44+AG45+AG46) -> 74507238 | AH48: =SUM(AH38+AH39+AH40+AH43+AH44+AH45+AH46) -> 70273904 | AI48: =SUM(AI38+AI39+AI40+AI43+AI44+AI45+AI46) -> 64470571 | AJ48: =SUM(AJ38+AJ39+AJ40+AJ43+AJ44+AJ45+AJ46) -> 64285634 | AK48: =SUM(AK38+AK39+AK40+AK43+AK44+AK45+AK46) -> 81501571 | AL48: =SUM(AL38+AL39+AL40+AL43+AL44+AL45+AL46) -> 92263914 | ... CR48: =SUM(CR38+CR39+CR40+CR43+CR44+CR45+CR46) -> 2.7130393e+08 | CS48: =SUM(CS38:CS47) -> 2.6966136e+08 | CU48: =SUM(CU38+CU39+CU40+CU43+CU44+CU45+CU46) -> 0
A49: Total Liabilities and Equity | B49: =B48+B37 -> 3.3049886e+08 | C49: =C48+C37 -> 3.482434e+08 | D49: =D48+D37 -> 3.8616078e+08 | E49: =E48+E37 -> 3.9634317e+08 | F49: =F48+F37 -> 3.7907267e+08 | G49: =G48+G37 -> 3.8462171e+08 | H49: =H48+H37 -> 3.7946308e+08 | I49: =I48+I37 -> 7.390433e+08 | ... CS49: =CS48+CS37 -> 5.193942e+08
S50: =S49-S26 -> -0.019999862 | T50: =T49-T26 -> 0.049999952 | U50: =U49-U26 -> 0.029999912 | V50: =V49-V26 -> 0.050000012 | W50: =W49-W26 -> 1882767.4 | X50: =X49-X26 -> 0.019999981 | Y50: =Y49-Y26 -> 0 | Z50: =Z49-Z26 -> -0.080000043 | ... AE50: =AE49-AE26 -> 0.029999971 | AG50: =AG49-AG26 -> -0.059999943 | AH50: =AH49-AH26 -> 0 | AI50: =AI49-AI26 -> -0.089999974 | AJ50: =AJ49-AJ26 -> 0 | AK50: =AK49-AK26 -> 0 | AL50: =AL49-AL26 -> -1.0000001 | AM50: =AM49-AM26 -> 0 | AN50: =AN49-AN26 -> 0 | AO50: =AO49-AO26 -> 0 | AR50: =AR49-AR26 -> 667139.53 | AS50: =AS49-AS26 -> 0 | AT50: =AT49-AT26 -> 0 | AU50: =AU49-AU26 -> 0.01000011 | AV50: =AV49-AV26 -> 0 | AW50: =AW49-AW26 -> 0 | AX50: =AX49-AX26 -> 0 | AY50: =AY49-AY26 -> 0 | ... BR50: =BR49-BR26 -> -0.26850003 | CF50: 4.5466262e+08 | CG50: 4.4915488e+08 | CH50: 4.2559991e+08 | CI50: 4.3405851e+08 | CJ50: 4.2562508e+08 | CK50: 4.904424e+08 | CL50: 6.1125329e+08 | CM50: 5.7584451e+08 | CN50: 5.4295989e+08
B51: -0.42000002 | C51: -0.5 | E51: -0.5 | R51: =R26-R49 -> 0 | CE51: 4.9465979e+08 | CF51: =CF26-CF49 -> 0 | CK51: share capital | CL51: 74083883 | CM51: =CL26-CL49 -> 0
G52: =D41-2023571 -> 950055.4 | AR52: =AR38+AR41+AR42+AR43 -> 93008252 | CE52: =CE49-CE51 -> 0 | CK52: capital grants | CL52: 0 | CN52: =CL51+CL55+CL56+CL54 -> 1.088393e+08
CK53: retained earnings | CN53: =CN52-CL59 -> -75208188 | CP53: 1.088393e+08 | CQ53: =277027219.29-CQ38 -> 2.0294334e+08
CK54: prior year surplus | CL54: -2188704.5 | CN54: =CN53+CL60 -> -1.4929207e+08 | CO54: ica | CP54: 1.8404748e+08
CK55: CYS | CL55: 20671285 | CP55: =SUM(CP53:CP54) -> 2.9288678e+08
BX56: l | CK56: statutory reserve | CL56: 16272832 | CN56: =291419665.55-CN38 -> 2.1733578e+08 | CP56: 48318.25
CK57: other reserves | CP57: =CP55-CP56 -> 2.9283846e+08
CL58: =SUM(CL51:CL57) -> 1.088393e+08 | CP58: 292953451
CK59: less investments in Co.. | CL59: 1.8404748e+08 | CM59: =CL58-CL59 -> -75208188 | CP59: =CP58-CP57 -> 114990.04
CK60: less shares and stocks | CL60: =CL57-CL38 -> -74083883
CL64: =CL45 -> 1.6493164e+08 | CO64: =CL48-184047483 -> 89723457
CL65: =CL48-CL45 -> 1.088393e+08
CI79: =CG81/CG95 -> #DIV/0! | CJ79: =CG82/CG95 -> #DIV/0! | CL79: what are these investments
A80: =#REF!/#REF! -> #REF! | B80: =#REF!/#REF! -> #REF! | D80: what are these investments
CL82: revaluation reserves wehat was revalued
D83: revaluation reserves wehat was revalued | CL83: loan products
D84: loan products | CL84: to what extent was this income was realised
D85: to what extent was this income was realised | CL85: what level of dividend income did the sacco make
D86: what level of dividend income did the sacco make | CL86: intest on deposits
D87: intest on deposits
CI94: any b oard member who sits in Cic
A95: any b oard member who sits in Cic | CI95: verify the acuracy of income from loans and investments
A96: verify the acuracy of income from loans and investments | CI96: did the money come in..
A97: did the money come in.. | CI97: dividend checks
A98: dividend checks
CI112: 75323820
A113: 75323820 | CI113: =CI112/CG118 -> #DIV/0!
A114: =A113/#REF! -> #REF!

Sheet Evolutitve SCI
B2: 2013 Audited | C2: 2014 Audited | D2: 2015 Audited | E2: 42005 | F2: 42370 | G2: 42401 | H2: 42430 | I2: 42461 | J2: 42491 | K2: 42522 | L2: 42552 | M2: 42583 | N2: 42614 | O2: 42644 | P2: 42675 | Q2: 42705 | R2: Audited 2016 | S2: 42736 | T2: 42767 | U2: 42795 | V2: 42826 | W2: 42856 | X2: 42887 | Y2: 42917 | Z2: 42948 | AA2: 42979 | AB2: 43009 | AC2: 43040 | AD2: 43070 | AE2: Audited 2017 | AF2: 43101 | AG2: 43132 | AH2: 43160 | AI2: 43191 | AJ2: 43221 | AK2: 43252 | AL2: 43282 | AM2: 43313 | AN2: 43344 | AO2: 43374 | AP2: 43405 | AQ2: 43435 | AR2: Audited 2018 | AS2: 43466 | AT2: 43497 | AU2: 43525 | AV2: 43556 | AW2: 43586 | AX2: 43617 | AY2: 43647 | AZ2: 43678 | BA2: 43709 | BB2: 43739 | BC2: 43770 | BD2: 43800 | BE2: Audited 2019 | BF2: 43831 | BG2: 43862 | BH2: 43891 | BI2: 43922 | BJ2: 43952 | BK2: 43983 | BL2: 44013 | BM2: 44044 | BN2: 44075 | BO2: 44105 | BP2: 44136 | BQ2: 44166 | BR2: Audited 2020 | BS2: 44197 | BT2: 44228 | BU2: 44256 | BV2: 44287 | BW2: 44317 | BX2: 44348 | BY2: 44378 | BZ2: 44409 | CA2: 44440 | CC2: 44501 | CD2: 44531 | CE2: Audited 2021 | CF2: 44562 | CG2: 44593 | CH2: 44621 | CI2: 44652 | CJ2: 44682 | CK2: 44713 | CL2: 44743 | CM2: 44774 | CN2: 44805 | CO2: 44835 | CP2: 44866 | CQ2: 44896 | CR2: Audited 2022 | CS2: 44927 | CT2: 44958 | CU2: 44986 | CV2: 45017 | CW2: 45047 | CX2: 45078
A3: Financial Income | B3: =B4+B7 -> 63593389 | C3: =C4+C7 -> 81396739 | D3: 75757598 | E3: =E4+E7 -> 5621897.8 | F3: =F4+F7 -> 6095529 | G3: =G4+G7 -> 9930772.8 | H3: =H4+H7 -> 13914971 | I3: =I4+I7 -> 35195599 | J3: =J4+J7 -> 21790571 | K3: =K4+K7 -> 26422042 | L3: =L4+L7 -> 44165712 | ... CS3: =CS4+CS7 -> 10341788
A4: Financial Income From Loans Portfolio | B4: =SUM(B5:B6) -> 47173128 | C4: =SUM(C5:C6) -> 47826352 | D4: 57467537 | E4: =SUM(E5:E6) -> 2650456.4 | F4: =SUM(F5:F6) -> 2775420 | G4: =SUM(G5:G6) -> 4477171.8 | H4: =SUM(H5:H6) -> 6200221.5 | I4: =SUM(I5:I6) -> 15706057 | J4: =SUM(J5:J6) -> 9549039.7 | K4: =SUM(K5:K6) -> 11705873 | L4: =SUM(L5:L6) -> 13417425 | ... CS4: =SUM(CS5:CS6) -> 5348140
A5: Interest from Loans Portfolio | B5: 25181369 | C5: 23538214 | D5: 29443949 | E5: 2039868.4 | F5: 2097436 | G5: 3762373.9 | H5: 5471623.5 | I5: 14148801 | J5: 8770411.7 | K5: 10870080 | L5: 12560132 | M5: 43287729 | N5: 16069168 | O5: 22975128 | P5: 47023005 | Q5: 28623657 | R5: 28623657 | S5: 3251748.3 | T5: 3744572.1 | U5: 9894010.3 | V5: 6692411.2 | W5: 8209384 | X5: 9931747.4 | Y5: 35986882 | Z5: 27526637 | AA5: 79000162 | AB5: 40622572 | AC5: 74567253 | AD5: 28045909 | AE5: 28045909 | AF5: 2434413 | AG5: 4225347 | AH5: 5816933 | AI5: 7695589 | AJ5: 8871455 | AK5: 12422417 | AL5: 12422417 | AM5: 17540097 | AN5: 19780076 | AO5: 28953004 | AP5: 30340681 | AQ5: 31745220 | AR5: 31745220 | AS5: 3850476 | AT5: 6061886.4 | AU5: 7922160.4 | AV5: 10177285 | AW5: 13010854 | AX5: 16219392 | AY5: 19332174 | AZ5: 22914704 | BA5: 26191579 | BB5: 34520827 | BC5: 38408096 | BD5: 41522628 | BF5: 3837830 | BG5: 6647370 | BH5: 8208839 | BI5: 12749525 | BJ5: 15194412 | BK5: 18229495 | BM5: 74061501 | BN5: 26967754 | BO5: 35429011 | BP5: 74123784 | BQ5: 41504076 | BR5: 41504076 | BS5: 4836890 | BT5: 6924220 | BU5: 9103670 | BV5: 10555840 | BW5: 12428200 | BX5: 16901782 | BY5: 19418952 | CE5: 43442458 | CF5: 1766980 | CG5: 4038920 | CH5: 6488830 | CI5: 10238620 | CJ5: 14423280 | CK5: 18581520 | CL5: 23620390 | CM5: 27781245 | CN5: 31646785 | CO5: 35339325 | CP5: 39553235 | CQ5: 47019726 | CR5: 47019726 | CS5: 4764670
A6: Fees&Commision on Loan Portfolio | B6: 21991759 | C6: 24288137 | D6: 28023588 | E6: 610588 | F6: 677984 | G6: 714798 | H6: 728598 | I6: 1557256 | J6: 778628 | K6: 835793 | L6: 857293 | M6: 2911161 | N6: 980887 | O6: 986387 | P6: 1999574 | Q6: 1352487 | R6: 39556535 | S6: 1528620 | T6: 811111 | U6: 1570578 | V6: 789789 | W6: 796789 | X6: 803289 | Y6: 2529783 | Z6: 1806556 | AA6: 4536390 | AB6: 1814556 | AC6: 2724987 | AD6: 1239529.5 | AE6: 42029755 | AF6: 751565 | AG6: 805445 | AH6: 836605 | AI6: 869605 | AJ6: 883655 | AK6: 906405 | AL6: 906405 | AM6: 925605 | AN6: 937455 | AO6: 904220 | AP6: 951455 | AQ6: 1265405 | AR6: 49797458 | AS6: 1002022 | AT6: 1074352 | AU6: 1101372 | AV6: 1132522 | AW6: 1190052 | AX6: 1208202 | AY6: 1232932 | AZ6: 1243282 | BA6: 1269732 | BB6: 1579056 | BC6: 2293830 | BD6: 2738684.3 | BF6: 511346 | BG6: 454180 | BH6: 525463 | BI6: 515106 | BJ6: 127860 | BK6: 138640 | BM6: 468960 | BN6: 168380 | BO6: 176800 | BP6: 988140 | BQ6: 3291945.2 | BR6: 46085929 | BS6: 726770 | BT6: 1003215 | BU6: 1109747.9 | BV6: 1064333.2 | BW6: 1216573.2 | BX6: 1343413.2 | BY6: 1538273.2 | CE6: 39881740 | CF6: 165640 | CG6: 338080 | CH6: 504220 | CI6: 801880 | CJ6: 1089100 | CK6: 1291040 | CL6: 1816790 | CM6: 2273110 | CN6: 2695510 | CO6: 2629747 | CP6: 2840634 | CQ6: 3294285 | CR6: 44944882 | CS6: 583470
A7: Financial Income from Investments | B7: =SUM(B8:B11) -> 16420261 | C7: =SUM(C8:C11) -> 33570387 | D7: 18290060 | E7: =SUM(E8:E11) -> 2971441.5 | F7: =SUM(F8:F11) -> 3320109 | G7: =SUM(G8:G11) -> 5453601 | H7: =SUM(H8:H11) -> 7714749.3 | I7: =SUM(I8:I11) -> 19489542 | J7: =SUM(J8:J11) -> 12241532 | K7: =SUM(K8:K11) -> 14716168 | L7: =SUM(L8:L11) -> 30748286 | ... CS7: =SUM(CS8:CS11) -> 4993648.2
A8: Government Securities | E8: 0 | F8: 0 | G8: 0 | H8: 0 | I8: 0 | J8: 0 | K8: 0 | L8: 0 | M8: 0 | N8: 0 | O8: 0 | P8: 0 | Q8: 0 | S8: 0 | T8: 0 | U8: 0 | V8: 0 | W8: 0 | X8: 0 | Y8: 0 | Z8: 0 | AA8: 0 | AB8: 0 | AC8: 0 | AD8: 0 | AJ8: 0 | AK8: 0 | AL8: 0 | AM8: 0 | AN8: 0 | AO8: 0 | AP8: 0 | AQ8: 0 | AS8: 0 | AT8: 0 | AU8: 0 | AV8: 0 | AW8: 0 | AX8: 0 | AY8: 0 | AZ8: 0 | BA8: 0 | BB8: 0 | BC8: 0 | BD8: 0 | BF8: 0 | BG8: 0 | BH8: 0 | BI8: 0 | BJ8: 0 | BK8: 0 | BM8: 0 | BN8: 0 | BO8: 0 | BP8: 0 | BQ8: 0 | BS8: 0 | BT8: 0 | BU8: 0 | BV8: 0 | BW8: 0 | BX8: 0 | BY8: 0 | CF8: 0 | CG8: 0 | CH8: 0 | CI8: 0 | CJ8: 0 | CK8: 0 | CL8: 0 | CM8: 0 | CN8: 0 | CO8: 0 | CP8: 0 | CQ8: 0 | CS8: 0
A9: Deposits with Banks & other Financial Institutions | B9: 779407.88 | C9: 737488 | D9: 389050 | E9: 75752 | F9: 0 | G9: 77332 | H9: 77332 | I9: 154664 | J9: 77332 | K9: 166765 | L9: 166765 | M9: 500295 | N9: 166765 | O9: 166765 | P9: 333530 | Q9: 877038.98 | R9: 877038.98 | S9: 0 | T9: 0 | U9: 0 | V9: 0 | W9: 0 | X9: 0 | Y9: 0 | Z9: 0 | AA9: 0 | AB9: 0 | AC9: 0 | AD9: 0 | AJ9: 0 | AK9: 0 | AL9: 0 | AM9: 0 | AN9: 0 | AO9: 0 | AP9: 0 | AQ9: 1184388.1 | AR9: 1184388.1 | AS9: 0 | AT9: 0 | AU9: 0 | AV9: 0 | AW9: 116090 | AX9: 132864 | AY9: 132864 | AZ9: 132864 | BA9: 147235 | BB9: 147902 | BC9: 152668 | BD9: 152570.13 | BF9: 152570.13 | BG9: 0 | BH9: 0 | BI9: 0 | BJ9: 0 | BK9: 17939 | BM9: 60771 | BN9: 856055 | BO9: 860310 | BP9: 1729152 | BQ9: 1739480.7 | BR9: 1739480.7 | BS9: 0 | BT9: 0 | BU9: 0 | BV9: 170839.85 | BW9: 173755.17 | BX9: 176766.1 | BY9: 176927.28 | CE9: 180424.97 | CF9: 0 | CG9: 0 | CH9: 0 | CI9: 0 | CJ9: 0 | CK9: 0 | CL9: 0 | CM9: 0 | CN9: 0 | CO9: 6730.12 | CP9: 56138.38 | CQ9: 56562.2 | CR9: 56562.2 | CS9: 0
A10: Other Investments | B10: 8480529.1 | C10: 8396992.5 | D10: 10560511 | E10: 0 | F10: 0 | G10: 0 | H10: 0 | I10: 0 | J10: 3552 | K10: 97285 | L10: 13410831 | M10: 40244332 | N10: 13414777 | O10: 13414777 | P10: 33652455 | Q10: 22411691 | R10: 22411691 | S10: 0 | T10: 0 | U10: 0 | V10: 0 | W10: 0 | X10: 16789001 | Y10: 50367002 | Z10: 33578002 | AA10: 83945004 | AB10: 33578002 | AC10: 50367002 | AD10: 16894089 | AE10: 16894089 | AF10: 0 | AG10: 0 | AH10: 0 | AI10: 0 | AJ10: 0 | AK10: 23086021 | AL10: 23086021 | AM10: 21261577 | AN10: 21261577 | AO10: 21261577 | AP10: 21261577 | AQ10: 21261577 | AR10: 21261577 | AS10: 2305 | AT10: 2305 | AU10: 6333 | AV10: 6333 | AW10: 6333 | AX10: 23486626 | AY10: 23486626 | AZ10: 23486626 | BA10: 23486626 | BB10: 23486626 | BC10: 23486626 | BD10: 23496697 | BF10: 0 | BG10: 0 | BH10: 0 | BI10: 0 | BJ10: 24610811 | BK10: 24610811 | BM10: 73832433 | BN10: 24610811 | BO10: 24620811 | BP10: 49241622 | BQ10: 22992088 | BR10: 22975425 | BS10: 0 | BT10: 0 | BU10: 0 | BV10: 23234504 | BW10: 23236809 | BX10: 23236809 | BY10: 23236809 | CE10: =24082503.94+273116.31 -> 24355620 | CF10: 0 | CG10: 0 | CH10: 0 | CI10: 0 | CJ10: 0 | CK10: 22972313 | CL10: 22972313 | CM10: 22972313 | CN10: 22972313 | CO10: 22972313 | CP10: 22972313 | CQ10: 22984397 | CR10: =22972312.66+1528120+1028749.11 -> 25529182 | CS10: 0
A11: Other Operating Income | B11: 7160324.5 | C11: 24435907 | D11: 7340499.5 | E11: 2895689.5 | F11: 3320109 | G11: 5376269 | H11: 7637417.3 | I11: 19334878 | J11: 12160648 | K11: 14452118 | L11: 17170690 | M11: 58643318 | N11: 22297726 | O11: 36468348 | P11: 81790048 | Q11: 43447298 | R11: 5243250.1 | S11: 8697213 | T11: 6667800.9 | U11: 18580917 | V11: 11543445 | W11: 14289416 | X11: 16492426 | Y11: 58093274 | Z11: 43467727 | AA11: 120914248 | AB11: 81740779 | AC11: 1.2800924e+08 | AD11: 43495018 | AE11: 5479965.7 | AF11: 5375545 | AG11: 8271580 | AH11: 11638246 | AI11: 12566175 | AJ11: 16751751 | AK11: 19840980 | AL11: 19840980 | AM11: 26428872 | AN11: 29270594 | AO11: 44692916 | AP11: 50015370 | AQ11: 53289676 | AR11: =26019199.2-AR10+19575000-5000000 -> 19332622 | AS11: 5767657 | AT11: 8868110 | AU11: 11795720 | AV11: 14391474 | AW11: 17358301 | AX11: 19153632 | AY11: 24450592 | AZ11: 27555928 | BA11: 30782518 | BB11: 41011710 | BC11: 43090089 | BD11: 49515252 | BF11: 3332892 | BG11: 6232450 | BH11: 9241795 | BI11: 11732162 | BJ11: 14429052 | BK11: 18157330 | BM11: 75948909 | BN11: 27401896 | BO11: 41594266 | BP11: 93049878 | BQ11: 48642400 | BR11: =694700+16663+5000+5148716.55 -> 5865079.5 | BS11: 3521779.6 | BT11: 6442007.8 | BU11: 9747176.1 | BV11: 13770290 | BW11: 16809071 | BX11: 20788937 | BY11: 24283894 | CE11: =1183680+6333+5500+3412448+1039859.01 -> 5647820 | CF11: 3656390.6 | CG11: 7542420 | CH11: 11249120 | CI11: 15154850 | CJ11: 18749579 | CK11: 22934700 | CL11: 36082813 | CM11: 37993761 | CN11: 41124402 | CO11: 43709930 | CP11: 45840819 | CQ11: 48481045 | CR11: =12084+10000+826898.09+4263579 -> 5112561.1 | CS11: 4993648.2
A12: Financial Expenses | B12: =SUM(B13:B18) -> 14038798 | C12: =SUM(C13:C18) -> 20716867 | D12: =SUM(D13:D18) -> 24120622 | E12: =SUM(E13:E18) -> 1581905 | F12: =SUM(F13:F18) -> 725699 | G12: =SUM(G13:G18) -> 3261148 | H12: =SUM(H13:H18) -> 3471747 | I12: =SUM(I13:I18) -> 15679763 | ... CS12: =SUM(CS13:CS18) -> 980252.16
A13: Interest Expense on Deposits | B13: 205944.15 | C13: 1261174 | D13: 1665811.8 | E13: 67513 | F13: 99600 | G13: 264375 | H13: 452862 | I13: 1242010 | J13: 707325 | K13: 911425 | L13: 1020044 | M13: 3603663 | N13: 1419230 | O13: 1670910 | P13: 3614950.5 | Q13: 1807475.2 | R13: 1807475.2 | S13: 406900 | T13: 435229 | U13: 1062056.6 | V13: 531028.3 | W13: 893002 | X13: 893002 | Y13: 4458837 | Z13: 3320996 | AA13: 9515825 | AB13: 4176960 | AC13: 6966789 | AD13: 2773391.9 | AE13: 2773391 | AF13: 472615 | AG13: 667963 | AH13: 904130 | AI13: 1121360 | AJ13: 1411748 | AK13: 1574681 | AL13: 1574681 | AM13: 2386650 | AN13: 2720208 | AO13: 2977370 | AP13: 3287344 | AQ13: 3534897.2 | AR13: 3534897.2 | AS13: 497358 | AT13: 883839 | AU13: 1229434 | AV13: 1535605 | AW13: 1956946 | AX13: 2301327 | AY13: 2801589 | AZ13: 3164094 | BA13: 3592098 | BB13: 4173610 | BC13: 4636572 | BD13: 5075420.2 | BF13: 538015 | BG13: 1017335 | BH13: 1445490 | BI13: 2134156 | BJ13: 2674598 | BK13: 3054993 | BM13: 12595806 | BN13: 4760846 | BO13: 5667871 | BP13: 12237696 | BQ13: 7052257.2 | BR13: 0 | BS13: 551916.05 | BT13: 940854.92 | BU13: 1585442.5 | BV13: 2575828.8 | BW13: 2917006.2 | BX13: 3538839.6 | BY13: 4408301.2 | CE13: 7539285 | CF13: 1061731.7 | CG13: 1405019.9 | CH13: 1802571.8 | CI13: 3259805.5 | CJ13: 4039643 | CK13: 4548205.2 | CL13: 5534845.6 | CM13: 6473647.1 | CN13: 7172565 | CO13: 8840644.9 | CP13: 9525665.8 | CQ13: 10233640 | CR13: 19227193 | CS13: 911133.16
A14: Cost of External Borrowings | B14: 12726209 | C14: 17604356 | D14: 20952972 | E14: 916952 | F14: 0 | G14: 2239285 | H14: 2173849 | I14: 12151667 | J14: 6076830.6 | K14: 8460065 | L14: 12892735 | M14: 39470373 | N14: 16239500 | O14: 16817555 | P14: 36288774 | Q14: 19731325 | R14: 19731325 | S14: 0 | T14: 946405 | U14: 5572980.1 | V14: 2786490.1 | W14: 3047727.1 | X14: 3047727.1 | Y14: 26013733 | Z14: 23277022 | AA14: 58192555 | AB14: 25772688 | AC14: 38659032 | AD14: 16976293 | AE14: 16976293 | AF14: 0 | AG14: 0 | AH14: 2970377 | AI14: 4543551 | AJ14: 6543551 | AK14: 9922478 | AL14: 9922478 | AM14: 14052865 | AN14: 14052865 | AO14: 16920290 | AP14: 16920290 | AQ14: 17212726 | AR14: 17212726 | AS14: 159529 | AT14: 268815 | AU14: 2364701 | AV14: 3461267 | AW14: 4845959 | AX14: 6261080 | AY14: 7887708 | AZ14: 9236952 | BA14: 12072078 | BB14: 13492131 | BC14: 15240514 | BD14: 21392104 | BF14: 0 | BG14: 0 | BH14: 4327891 | BI14: 4327891 | BJ14: 12374244 | BK14: 13297621 | BM14: 48987030 | BN14: 19360399 | BO14: 20908523 | BP14: 44304900 | BQ14: 29261041 | BR14: 29108298 | BS14: 467729.36 | BT14: 293390.85 | BU14: 678271.96 | BV14: 6044602.2 | BW14: 6044602.2 | BX14: 8894909.9 | BY14: 8894909.9 | CE14: =3175642.44+16495106.79 -> 19670749 | CF14: 0 | CG14: 686142.73 | CH14: 2764678 | CI14: 2743246.4 | CJ14: 4193684.7 | CK14: 6464187.8 | CL14: 6464187.8 | CM14: 7537862.4 | CN14: 7537862.4 | CO14: 7537862.4 | CP14: 11578289 | CQ14: 12542215 | CR14: 4518352.2 | CS14: 0
A15: Dividend Expenses | D15: 0 | E15: 0 | F15: 0 | G15: 0 | H15: 0 | I15: 0 | J15: 0 | K15: 0 | L15: 0 | M15: 0 | N15: 0 | O15: 0 | P15: 0 | Q15: 0 | S15: 0 | T15: 0 | U15: 0 | V15: 0 | W15: 0 | X15: 0 | Y15: 0 | Z15: 0 | AA15: 0 | AB15: 0 | AC15: 0 | AD15: 0 | AF15: 0 | AG15: 0 | AH15: 0 | AI15: 0 | AJ15: 0 | AK15: 0 | AL15: 0 | AM15: 0 | AN15: 0 | AO15: 0 | AP15: 0 | AQ15: 0 | AS15: 0 | AT15: 0 | AU15: 0 | AV15: 0 | AW15: 0 | AX15: 0 | AY15: 0 | AZ15: 0 | BA15: 0 | BB15: 0 | BC15: 0 | BD15: 0 | BF15: 0 | BG15: 0 | BH15: 0 | BI15: 0 | BJ15: 0 | BK15: 0 | BM15: 0 | BN15: 0 | BO15: 0 | BP15: 0 | BQ15: 0 | BS15: 0 | BT15: 0 | BU15: 0 | BV15: 0 | BW15: 0 | BX15: 0 | BY15: 0 | CF15: 0 | CG15: 0 | CH15: 0 | CI15: 0 | CJ15: 0 | CK15: 0 | CL15: 0 | CM15: 0 | CN15: 0 | CO15: 0 | CP15: 0 | CQ15: 0 | CR15: =163308792/23620390 -> 6.9138906 | CS15: 0
A16: Other Financial Expense | D16: 0 | E16: 0 | F16: 0 | G16: 0 | H16: 0 | I16: 0 | J16: 0 | K16: 0 | L16: 0 | M16: 0 | N16: 0 | O16: 0 | P16: 0 | Q16: 0 | S16: 0 | T16: 0 | U16: 0 | V16: 0 | W16: 0 | X16: 0 | Y16: 0 | Z16: 0 | AA16: 0 | AB16: 0 | AC16: 0 | AD16: 0 | AF16: 0 | AG16: 0 | AH16: 0 | AI16: 0 | AJ16: 0 | AK16: 0 | AL16: 0 | AM16: 0 | AN16: 0 | AO16: 0 | AP16: 0 | AQ16: 0 | AS16: 0 | AT16: 0 | AU16: 0 | AV16: 0 | AW16: 0 | AX16: 0 | AY16: 0 | AZ16: 0 | BA16: 0 | BB16: 0 | BC16: 0 | BD16: 0 | BF16: 0 | BG16: 0 | BH16: 0 | BI16: 0 | BJ16: 0 | BK16: 0 | BM16: 0 | BN16: 0 | BO16: 0 | BP16: 0 | BQ16: 0 | BS16: 0 | BT16: 0 | BU16: 0 | BV16: 0 | BW16: 0 | BX16: 0 | BY16: 0 | CF16: 0 | CG16: 0 | CH16: 0 | CI16: 0 | CJ16: 0 | CK16: 0 | CL16: 0 | CM16: 0 | CN16: 0 | CO16: 0 | CP16: 0 | CQ16: 0 | CS16: 0
A17: Fees & Commision Expense | B17: 1069544.6 | C17: 1839436.7 | D17: 1351897.9 | E17: 562440 | F17: 602099 | G17: 654488 | H17: 694536 | I17: 1870086 | J17: 958392 | K17: 459498 | L17: 501031 | M17: 2366601 | N17: 864900 | O17: 893416 | P17: 2334903.4 | Q17: 1786500 | R17: 1786500 | S17: 7042 | T17: 704865 | U17: 1464583.6 | V17: 736608 | W17: 1548636.8 | X17: 1879284 | Y17: 5641243.8 | Z17: 3881046 | AA17: 10015230 | AB17: 4606752 | AC17: 6937335 | AD17: 2605796.4 | AF17: 48406 | AG17: 939856 | AH17: 1977628 | AI17: 2036783 | AJ17: 2079123 | AK17: 2102144 | AL17: 2102144 | AM17: 2126701 | AN17: 2216835 | AO17: 2376632 | AP17: 2441569 | AQ17: 2627299.3 | AR17: 2627299.3 | AS17: 112067 | AT17: 216168 | AU17: 240506 | AV17: 240506 | AW17: 374284 | AX17: 409681 | AY17: 436388 | AZ17: 484972 | BA17: 522311 | BB17: 552609 | BC17: 721641 | BD17: 621216 | BF17: 0 | BG17: 0 | BH17: 0 | BI17: 0 | BJ17: 347429 | BK17: 384305 | BM17: 1464711 | BN17: 608707 | BO17: 647620 | BP17: 1550936 | BQ17: 1015903.7 | BR17: 8220903.9 | BS17: 10072 | BT17: 104817.5 | BU17: 271907.1 | BV17: 183070.1 | BW17: 296721.5 | BX17: 379812 | BY17: 390400.2 | CE17: 6260465.4 | CF17: 0 | CG17: 175295.1 | CH17: 184550.1 | CI17: 283367.9 | CJ17: 290051.9 | CK17: 429573.3 | CL17: 443726.7 | CM17: 669386.69 | CN17: 681689.22 | CO17: 715482.13 | CP17: 888323.44 | CQ17: 1569690 | CS17: 0
A18: Other Expenses | B18: 37100 | C18: 11900 | D18: 149940 | E18: 35000 | F18: 24000 | G18: 103000 | H18: 150500 | I18: 416000 | J18: 290600 | K18: 355760 | L18: 416460 | M18: 1662780 | N18: 650960 | O18: 719460 | P18: 1739120 | Q18: 1038560 | R18: 208120 | S18: 251000 | T18: 255500 | U18: 785000 | V18: 516000 | W18: 709060 | X18: 709060 | Y18: 3324180 | Z18: 2627320 | AA18: 7948300 | AB18: 3556320 | AC18: 6326280 | AD18: 2392260 | AE18: 2646796.4 | AF18: 299000 | AG18: 538500 | AH18: 761500 | AI18: 1041000 | AJ18: 1382500 | AK18: 1788000 | AL18: 1788000 | AM18: 2832860 | AN18: 3291960 | AO18: 3776160 | AP18: 4417660 | AQ18: 4913860 | AR18: 16400 | AS18: 469000 | AT18: 905000 | AU18: 1449400 | AV18: 1839400 | AW18: 2378500 | AX18: 2378500 | AY18: 3205000 | AZ18: 3467500 | BA18: 3822000 | BB18: 4124000 | BC18: 4720585 | BD18: 5354085 | BF18: 5000 | BG18: 33000 | BH18: 55000 | BI18: 102100 | BJ18: 152700 | BK18: 205700 | BM18: 1157007 | BN18: 386075 | BO18: 451375 | BP18: 1022150 | BQ18: 601675 | BS18: 30000 | BT18: 68000 | BU18: 93000 | BV18: 93000 | BW18: 117000 | BX18: 260000 | BY18: 314000 | CF18: 27000 | CG18: 72000 | CH18: 120000 | CI18: 178000 | CJ18: 271000 | CK18: 353000 | CL18: 433500 | CM18: 485500 | CN18: 540500 | CO18: 643500 | CP18: 753500 | CQ18: 858500 | CS18: 69119
A19: Net Financial Income | B19: =B3-B12 -> 49554591 | C19: =C3-C12 -> 60679872 | D19: =D3-D12 -> 51636976 | E19: =E3-E12 -> 4039992.8 | F19: =F3-F12 -> 5369830 | G19: =G3-G12 -> 6669624.8 | H19: =H3-H12 -> 10443224 | I19: =I3-I12 -> 19515836 | ... CS19: =CS3-CS12 -> 9361536.1
A20: Allowance for Loan Loss | B20: =B21-B22 -> 1755343 | C20: =C21-C22 -> 1004580.5 | D20: =D21-D22 -> 124212.38 | E20: =E21-E22 -> 762005.2 | F20: =F21-F22 -> 1892266.2 | G20: =G21-G22 -> 2659906.7 | H20: =H21-H22 -> 2504088.2 | I20: =I21-I22 -> 4790126.4 | ... CS20: =CS21-CS22 -> 1631511
A21: Provision for Loan Losses | B21: 1755343 | C21: 1004580.5 | D21: 124212.38 | E21: 762005.2 | F21: 1892266.2 | G21: 2659906.7 | H21: 2504088.2 | I21: 4790126.4 | J21: 1723148.2 | K21: 3529416.7 | L21: 3517317.7 | M21: 10805190 | N21: 3237527 | O21: 1947553.4 | P21: 3019742.4 | Q21: 5004620.4 | R21: 5004619.4 | S21: 36553.4 | T21: 509219 | U21: 0 | V21: 0 | W21: 0 | X21: 0 | Y21: 0 | Z21: 0 | AA21: 0 | AB21: 0 | AC21: 0 | AD21: 0 | AE21: 0 | AF21: 0 | AG21: 0 | AH21: 0 | AI21: 0 | AJ21: 0 | AK21: 0 | AL21: 0 | AM21: 0 | AN21: 0 | AO21: 0 | AP21: 0 | AQ21: 1253297.3 | AR21: 1253297.3 | AS21: 0 | AT21: 0 | AU21: 0 | AV21: 0 | AW21: 0 | AX21: 0 | AY21: 0 | AZ21: 0 | BA21: 0 | BB21: 0 | BC21: 0 | BD21: 2672519 | BF21: 813268.8 | BG21: 0 | BH21: 5651856.5 | BI21: 3725956.3 | BJ21: 2299125.3 | BK21: 1059053.6 | BM21: 1350091.5 | BN21: -796473.6 | BO21: -4187997.4 | BP21: -3734395.6 | BQ21: -8187928.9 | BR21: 0 | BS21: 0 | BT21: 0 | BU21: 0 | BV21: 0 | BW21: 0 | BX21: 0 | BY21: 0 | CF21: 1477116 | CG21: 2122243.8 | CH21: 2263222.6 | CI21: 2270959 | CJ21: 2493098.6 | CK21: 6828979 | CL21: 0 | CM21: 5173808.2 | CN21: 5364215.7 | CO21: 5747186.9 | CP21: 6471369.8 | CQ21: 0 | CR21: 4948149 | CS21: 1631511
A22: Value of Loans Recovered | D22: 0 | E22: 0 | F22: 0 | G22: 0 | H22: 0 | I22: 0 | J22: 0 | K22: 0 | L22: 0 | M22: 0 | N22: 0 | O22: 0 | P22: 0 | Q22: 0 | S22: 0 | T22: 0 | U22: 1033145.6 | V22: 543658.6 | W22: 1158857.3 | X22: 1454730.1 | Y22: 4547043 | Z22: 2001489 | AA22: 2927258 | AB22: 1692645.2 | AC22: 2214942.6 | AD22: 738314.2 | AE22: 0 | AF22: 1469999.3 | AG22: 2210429.9 | AH22: 2221445 | AI22: 2256100.5 | AJ22: 3268094.5 | AK22: 2970015.3 | AL22: 2970015.3 | AM22: 1939500.6 | AN22: 1925301.6 | AO22: 4115743.9 | AP22: 1210280 | AQ22: 0 | AS22: 1947105.3 | AT22: 3162107.1 | AU22: 2722108.1 | AV22: 2371696.2 | AW22: 2148196.1 | AX22: 2300363.1 | AY22: 2388313.1 | AZ22: 2194360.2 | BA22: 2212315.4 | BB22: -1092190.3 | BC22: -5101782.3 | BD22: 0 | BF22: 0 | BG22: 2040899.5 | BH22: 0 | BI22: 0 | BJ22: 0 | BK22: 0 | BM22: 0 | BN22: 0 | BO22: 0 | BP22: 0 | BQ22: 0 | BS22: 539870 | BT22: 1629062.5 | BU22: 1595103.8 | BV22: 899233.6 | BW22: 394886.6 | BX22: 1246640.9 | BY22: 931589.7 | CF22: 0 | CG22: 0 | CH22: 0 | CI22: 0 | CJ22: 0 | CK22: 0 | CL22: 0 | CM22: 0 | CN22: 0 | CO22: 0 | CP22: 0 | CQ22: 0 | CS22: 0
A23: Operating Expeses | B23: =SUM(B24:B28) -> 42192110 | C23: =SUM(C24:C28) -> 50352376 | D23: =SUM(D24:D28) -> 46898868 | E23: =SUM(E24:E28) -> 3593615.8 | F23: =SUM(F24:F28) -> 3444299.5 | G23: =SUM(G24:G28) -> 7237235.5 | H23: =SUM(H24:H28) -> 10991923 | I23: =SUM(I24:I28) -> 29291642 | ... CS23: =SUM(CS24:CS28) -> 5579654.4
A24: Personel Expenses | B24: 18718901 | C24: 21455848 | D24: 21722045 | E24: 1682837 | F24: 1759985 | G24: 3550620 | H24: 5497805 | I24: 14566880 | J24: 9124075 | K24: 11067570 | L24: 12857930 | M24: 44121945 | N24: 17025501 | O24: 18810336 | P24: 41324142 | Q24: 23268920 | R24: 23268920 | S24: 3987023.2 | T24: 4009873.2 | U24: 12180570 | V24: 8132596.5 | W24: 11093558 | X24: 13075119 | Y24: 45282242 | Z24: 34316483 | AA24: 96642014 | AB24: 42785224 | AC24: 70443360 | AD24: 25737382 | AE24: 25737382 | AF24: 2026859.2 | AG24: 4057060.2 | AH24: 6155920.2 | AI24: 8279661 | AJ24: 10433892 | AK24: 14615094 | AL24: 14615094 | AM24: 19017727 | AN24: 21144569 | AO24: 23592651 | AP24: 25761293 | AQ24: 28210317 | AR24: 28210317 | AS24: 4441696.5 | AT24: 7198303.3 | AU24: 9824948 | AV24: 12420245 | AW24: 15199682 | AX24: 17894088 | AY24: 20756094 | AZ24: 23887200 | BA24: 26634055 | BB24: 29366061 | BC24: 32321827 | BD24: 37630741 | BF24: 2762896 | BG24: 5688112 | BH24: 8568680 | BI24: 13039104 | BJ24: 15519245 | BK24: 18050241 | BM24: 69341349 | BN24: 25588229 | BO24: 28055175 | BP24: 66428502 | BQ24: 37320904 | BR24: 37320904 | BS24: 2325250 | BT24: 7698261.9 | BU24: 10656999 | BV24: 13421236 | BW24: 16245432 | BX24: 19059251 | BY24: 21692988 | CE24: 35424278 | CF24: 1914991.9 | CG24: 5162144.9 | CH24: 7987036.8 | CI24: 10816129 | CJ24: 13565100 | CK24: 21861927 | CL24: 22087244 | CM24: 25194513 | CN24: 27938228 | CO24: 30758975 | CP24: 36294276 | CQ24: 39313463 | CR24: 39313463 | CS24: 3439698.4
A25: Governance Expenses | B25: 5166712 | C25: 4926581 | D25: 4019272 | E25: 296835 | F25: 250500 | G25: 365200 | H25: 628000 | I25: 2401544 | J25: 1341427 | K25: 1653877 | L25: 2606227 | M25: 8874981 | N25: 3345987 | O25: 3546962 | P25: 8601804 | Q25: 6144392 | R25: 5986272 | S25: 340100 | T25: 329760 | U25: 1143240 | V25: 1210060 | W25: 1435722 | X25: 1435722 | Y25: 6634281 | Z25: 5319754 | AA25: 16715885 | AB25: 7350874 | AC25: 14729211 | AD25: 5938557 | AE25: 5897557 | AF25: 270800 | AG25: 733600 | AH25: 1560000 | AI25: 2244660 | AJ25: 2416310 | AK25: 3737710 | AL25: 3737710 | AM25: 8830810 | AN25: 9094010 | AO25: 9366510 | AP25: 9958810 | AQ25: 11307458 | AR25: 11291058 | AS25: 1055455 | AT25: 1516655 | AU25: 2921405 | AV25: 3310195 | AW25: 3721395 | AX25: 4558795 | AY25: 5020165 | AZ25: 5860465 | BA25: 6180865 | BB25: 6773865 | BC25: 7349965 | BD25: 9678765 | BF25: 334000 | BG25: 739200 | BH25: 1556960 | BI25: 1631070 | BJ25: 4329570 | BK25: 4554570 | BM25: 15526539 | BN25: 5539513 | BO25: 5711500 | BP25: 11843140 | BQ25: 4534562.1 | BR25: 5412562.1 | BS25: 304840 | BT25: 661377 | BU25: 1249884 | BV25: 2020876 | BW25: 2297782 | BX25: 2764694 | BY25: 2931494 | CE25: 4957784 | CF25: 188200 | CG25: 433927 | CH25: 691934 | CI25: 1354735 | CJ25: 1919161 | CK25: 2282464 | CL25: 2559625 | CM25: 2878977 | CN25: 3206964 | CO25: 3485190 | CP25: 3842327 | CQ25: 4807305 | CR25: 4807305 | CS25: 342135
A26: Marketing Expenses | B26: 2180982 | C26: 3829929 | D26: 3027922 | E26: 136815 | F26: 264235 | G26: 828703 | H26: 1007013 | I26: 2436706 | J26: 1487843 | K26: 1779374 | L26: 2005578 | M26: 6609978 | N26: 2411011 | O26: 2742296 | P26: 6302472 | Q26: 3617480 | R26: 3617480 | S26: 276750 | T26: 709345 | U26: 1957320 | V26: 1125625 | W26: 1461130 | X26: 1627430 | Y26: 6068085 | Z26: 4395766 | AA26: 11810795 | AB26: 5117028 | AC26: 8857143 | AD26: 4477534 | AE26: 4477534 | AF26: 154098 | AG26: 239793 | AH26: 768753 | AI26: 1186381 | AJ26: 1322346 | AK26: 1507106 | AL26: 1507106 | AM26: 3041021 | AN26: 3412131 | AO26: 3995784 | AP26: 5398146 | AQ26: 6696721.5 | AR26: 6696721.5 | AS26: 148405 | AT26: 292347 | AU26: 483585 | AV26: 589245 | AW26: 1438692 | AX26: 1625492 | AY26: 1954075 | AZ26: 2856693 | BA26: 5023595 | BB26: 8089155 | BC26: 9619031 | BD26: 10408844 | BF26: 614360 | BG26: 1852641 | BH26: 2538717 | BI26: 2854239 | BJ26: 3158264 | BK26: 3579671 | BM26: 14549457 | BN26: 5872994 | BO26: 6587260 | BP26: 15018164 | BQ26: 6377050 | BR26: 5499050 | BS26: 427450 | BT26: 875475 | BU26: 1148825 | BV26: 1371025 | BW26: 1588225 | BX26: 1808425 | BY26: 2102925 | CE26: 2581475 | CF26: 145250 | CG26: 263950 | CH26: 373650 | CI26: 433450 | CJ26: 559350 | CK26: 606450 | CL26: 722800 | CM26: 798450 | CN26: 872650 | CO26: 1046050 | CP26: 1248950 | CQ26: 1495200 | CR26: 1495200 | CS26: 149950
A27: Depreciation and Amortization | B27: 3764898 | C27: 5242641.7 | D27: 4854540 | E27: 399159.84 | F27: 353739.5 | G27: 703058.5 | H27: 1048048.2 | I27: 2777596 | J27: 1388798 | K27: 1727105 | L27: 2073976 | M27: 7281417 | N27: 3124513 | O27: 3458634.4 | P27: 7584200.9 | Q27: 4587050 | R27: 4587050 | S27: 669467.5 | T27: 665624.75 | U27: 2003555.2 | V27: 1359212.6 | W27: 1359212.6 | X27: 1536228.6 | Y27: 5685582.8 | Z27: 4499472.5 | AA27: 12999735 | AB27: 5891828 | AC27: 9863176.4 | AD27: 4616965 | AE27: 4616965 | AF27: 318449 | AG27: 633355 | AH27: 944845.64 | AI27: 1252930.6 | AJ27: 1557678.6 | AK27: 1859154.6 | AL27: 1859154.6 | AM27: 2554277.4 | AN27: 2846315.4 | AO27: 3164755.4 | AP27: 3479418.4 | AQ27: 4273273 | AR27: 4273273 | AS27: 301209.41 | AT27: 599027.78 | AU27: 893524 | AV27: 1184768 | AW27: 1472825 | AX27: 1757761 | AY27: 2039639.1 | AZ27: 2318520 | BA27: 2318520 | BB27: 2591589.4 | BC27: 2862589.4 | BD27: 4007531.6 | BF27: 0 | BG27: 280103 | BH27: 558806 | BI27: 834577.76 | BJ27: 1107476.3 | BK27: 1378067.4 | BM27: 5763577.2 | BN27: 1921192.4 | BO27: 2193675.3 | BP27: 5723008 | BQ27: 3121641 | BR27: 3589764.5 | BS27: 0 | BT27: 0 | BU27: 0 | BV27: 1148557.5 | BW27: 1432732.1 | BX27: 1550604.8 | BY27: 1932666.4 | CE27: 3881936 | CF27: 244178 | CG27: 486440.7 | CH27: 828850.24 | CI27: 1166286 | CJ27: 1488061.5 | CK27: 1447931.6 | CL27: 1678996.4 | CM27: 1908380.4 | CN27: 2239417.2 | CO27: 2398957.4 | CP27: 2643370.4 | CQ27: 2885990.4 | CR27: 4017153.4 | CS27: 240728
A28: Administrative Expenses | B28: 12360616 | C28: 14897376 | D28: 13275089 | E28: 1077969 | F28: 815840 | G28: 1789654 | H28: 2811057 | I28: 7108916 | J28: 4493795 | K28: 5277519 | L28: 6416639 | M28: 22217535 | N28: 8187110 | O28: 17934692 | P28: 40139233 | Q28: 22420909 | R28: 22420981 | S28: 2502640 | T28: 2292920 | U28: 7265992.5 | V28: 4562415 | W28: 5564698 | X28: 20199342 | Y28: 66127431 | Z28: 47853952 | AA28: 124361785 | AB28: 51745642 | AC28: 84639927 | AD28: 16092904 | AE28: 16092904 | AF28: 1485965 | AG28: 3464180 | AH28: 4464914 | AI28: 7479315 | AJ28: 8613365 | AK28: 10889093 | AL28: 10889093 | AM28: 13299826 | AN28: 15048419 | AO28: 16216843 | AP28: 17570575 | AQ28: 18145465 | AR28: 23042947 | AS28: 1227264 | AT28: 2366197 | AU28: 5645267 | AV28: 6494259 | AW28: 7612084 | AX28: 9222053 | AY28: 11314150 | AZ28: 12007775 | BA28: 13661690 | BB28: 15807945 | BC28: 17084169 | BD28: 18402321 | BF28: 1034102 | BG28: 2337524 | BH28: 4385407 | BI28: 5199882 | BJ28: 8606154 | BK28: 11157298 | BM28: 45950868 | BN28: 19311308 | BO28: 20868457 | BP28: 48629056 | BQ28: 27501362 | BR28: 30208706 | BS28: 1536449 | BT28: 4960930 | BU28: 5024030 | BV28: 19023182 | BW28: 20424903 | BX28: 21603679 | BY28: 23503891 | CE28: 29931123 | CF28: 1858934 | CG28: 4486947.2 | CH28: 8180811.2 | CI28: 8002722.2 | CJ28: 10392668 | CK28: 16831948 | CL28: 20234988 | CM28: 22438922 | CN28: 23670420 | CO28: 26141482 | CP28: 28202325 | CQ28: 30950627 | CR28: =36284113.05-4948149 -> 31335964 | CS28: 1407143
A29: Net Operating Income | B29: =B19-B20-B23 -> 5607138.3 | C29: =C19-C20-C23 -> 9322915.5 | D29: =D19-D20-D23 -> 4613895.9 | E29: =E19-E20-E23 -> -315628.24 | F29: =F19-F20-F23 -> 33264.3 | G29: =G19-G20-G23 -> -3227517.4 | H29: =H19-H20-H23 -> -3052787.5 | I29: =I19-I20-I23 -> -14565933 | ... CS29: =CS19-CS20-CS23 -> 2150370.7
A30: Net Non operating Income/Expense | B30: =B31-B32 -> 0 | C30: =C31-C32 -> 0 | D30: =D31-D32 -> 0 | E30: =E31-E32 -> 0 | F30: =F31-F32 -> 0 | G30: =G31-G32 -> 0 | H30: =H31-H32 -> 0 | I30: =I31-I32 -> 0 | ... CS30: =CS31-CS32 -> 0
A31: Non Operating Income | D31: 0 | E31: 0 | F31: 0 | G31: 0 | H31: 0 | I31: 0 | J31: 0 | K31: 0 | L31: 0 | M31: 0 | N31: 0 | O31: 0 | P31: 0 | Q31: 0 | AP31: 0 | AQ31: 0 | AZ31: 0 | BA31: 0 | BB31: 0 | BC31: 0 | BD31: 0 | BF31: 0 | BG31: 0 | BH31: 0 | BI31: 0 | BJ31: 0 | BK31: 0 | BM31: 0 | BN31: 0 | BO31: 0 | BP31: 0 | BQ31: 0 | BS31: 0 | BT31: 0 | BU31: 0 | BV31: 0 | BW31: 0 | BX31: 0 | BY31: 0 | BZ31: 0 | CA31: 0 | CC31: 0 | CD31: 0 | CE31: 0 | CF31: 0 | CG31: 0 | CH31: 0 | CI31: 0 | CJ31: 0 | CK31: 1039859 | CL31: 1039859 | CM31: 1039859 | CN31: 1039859 | CO31: 1039859 | CP31: 0 | CQ31: 826898.09 | CS31: 0
A32: Non Operating Expense | D32: 0 | E32: 0 | F32: 0 | G32: 0 | H32: 0 | I32: 0 | J32: 0 | K32: 0 | L32: 0 | M32: 0 | N32: 50000 | O32: 50000 | P32: 100000 | Q32: 50000 | AP32: 0 | AQ32: 5393830.9 | AZ32: 0 | BA32: 0 | BB32: 0 | BC32: 0 | BD32: 4644097.6 | BF32: 0 | BG32: 0 | BH32: 0 | BI32: 0 | BJ32: 0 | BK32: 0 | BM32: 0 | BN32: 0 | BO32: 0 | BP32: 0 | BQ32: 2570104.2 | BS32: 0 | BT32: 0 | BU32: 0 | BV32: 0 | BW32: 0 | BX32: 0 | BY32: 0 | BZ32: 0 | CA32: 0 | CC32: 0 | CD32: 0 | CE32: 0 | CF32: 0 | CG32: 0 | CH32: 0 | CI32: 0 | CJ32: 0 | CK32: 0 | CL32: 0 | CM32: 0 | CN32: 0 | CO32: 0 | CP32: 0 | CQ32: 4948149.6 | CS32: 0
A33: Net Income(Before Tax & Donations) | B33: =B29+B30 -> 5607138.3 | C33: =C29+C30 -> 9322915.5 | D33: =D29+D30 -> 4613895.9 | E33: =E29+E30 -> -315628.24 | F33: =F29+F30 -> 33264.3 | G33: =G29+G30 -> -3227517.4 | H33: =H29+H30 -> -3052787.5 | I33: =I29+I30 -> -14565933 | ... CS33: =CS29+CS30 -> 2150370.7
A34: Taxes | B34: 2161440 | C34: 4189735 | D34: 733884.15 | E34: 0 | F34: 0 | G34: 0 | H34: 0 | I34: 0 | J34: 0 | K34: 0 | L34: 0 | M34: 0 | N34: 1258410 | O34: 1258410 | P34: 2516820 | Q34: 1289041 | R34: 1978880.2 | AE34: 463322.57 | AR34: 2796263.2 | BF34: 0 | BG34: 0 | BH34: 0 | BI34: 0 | BJ34: 0 | BK34: 0 | BM34: 0 | BN34: 300000 | BO34: 740390 | BP34: 1480780 | BQ34: 0 | BS34: 0 | BT34: 0 | BU34: 0 | BV34: 0 | BW34: 0 | BX34: 1 | BY34: 2 | BZ34: 3 | CA34: 4 | CC34: 6 | CD34: 7 | CE34: 8 | CF34: 0 | CG34: 0 | CH34: 0 | CI34: 0 | CJ34: 0 | CK34: 0 | CL34: 0 | CM34: 0 | CN34: 0 | CO34: 0 | CP34: 0 | CQ34: 0 | CS34: 0
A35: Net Income(After Tax Before Donations) | B35: =B33-B34 -> 3445698.3 | C35: =C33-C34 -> 5133180.5 | D35: =D33-D34 -> 3880011.7 | E35: =E33-E34 -> -315628.24 | F35: =F33-F34 -> 33264.3 | G35: =G33-G34 -> -3227517.4 | H35: =H33-H34 -> -3052787.5 | I35: =I33-I34 -> -14565933 | ... CS35: =CS33-CS34 -> 2150370.7
A36: Donations | B36: 589900 | C36: 309000 | D36: 622580 | E36: 0 | F36: 0 | G36: 0 | H36: 0 | I36: 0 | J36: 0 | K36: 0 | L36: 0 | M36: 0 | N36: 0 | O36: 0 | P36: 0 | Q36: 0 | R36: 1038560 | AE36: 2392260 | AR36: 4913860 | BS36: 0 | BT36: 0 | BU36: 0 | BV36: 0 | BW36: 0 | BX36: 1 | BY36: 2 | BZ36: 3 | CA36: 4 | CC36: 6 | CD36: 7 | CE36: 8 | CF36: 0 | CG36: 0 | CH36: 0 | CI36: 0 | CJ36: 0 | CK36: 0 | CL36: 0 | CM36: 0 | CN36: 0 | CO36: 0 | CP36: 0 | CQ36: 0 | CS36: 0
A37: Net Income/(After Tax & Donations) | B37: =B35-B36 -> 2855798.3 | C37: =C35-C36 -> 4824180.5 | D37: 3257431.7 | E37: =E35-E36 -> -315628.24 | F37: =F35-F36 -> 33264.3 | G37: =G35-G36 -> -3227517.4 | H37: =H35-H36 -> -3052787.5 | I37: =I35-I36 -> -14565933 | J37: =J35-J36 -> -5801662.6 | K37: =K35-K36 -> -8799568.2 | L37: =L35-L36 -> -142226.2 | ... CS37: =CS35-CS36 -> 2150370.7
A38: Total Expenses | B38: =B23+B12 -> 56230908 | C38: =C23+C12 -> 71069243 | D38: =D23+D12 -> 71019490 | E38: =E23+E12 -> 5175520.8 | F38: =F23+F12 -> 4169998.5 | G38: =G23+G12 -> 10498384 | H38: =H23+H12 -> 14463670 | I38: =I23+I12 -> 44971405 | ... AQ38: =AQ23+AQ12 -> 96922018 | AS38: =AR37-AS37 -> 13294624
CE39: 3260966.4
CE40: =CE37-CE39 -> -16.1

Sheet FORM 4
D1: 42430
B2: CLASSIFICATION | C2: NO. OF A/Cs | D2: OUTSTANDING LOAN PORTFOLIO(Kshs) | E2: REQUIRED PROVISION | F2: REQUIRED PROVISION AMOUNT(Kshs)
B3: Performing | D3: 1.1786674e+08 | E3: 0.01 | F3: =D3*E3 -> 1178667.4
B4: Watch | D4: 11392004 | E4: 0.05 | F4: =D4*E4 -> 569600.18
B5: Substandard | D5: 5579841.1 | E5: 0.25 | F5: =D5*E5 -> 1394960.3 | G5: =SUM(D5:D7)/D8 -> 0.14058648
B6: Doubtful | D6: 6639705.9 | E6: 0.5 | F6: =D6*E6 -> 3319853
B7: Loss | D7: 8925142.3 | E7: 1 | F7: =D7*E7 -> 8925142.3
B8: subtotal | C8: =SUM(C3:C7) -> 0 | D8: =SUM(D3:D7) -> 1.5040343e+08 | E8: =SUM(E3:E7) -> 1.81 | F8: =SUM(F3:F7) -> 15388223
D10: 42522
B11: CLASSIFICATION | C11: NO. OF A/Cs | D11: OUTSTANDING LOAN PORTFOLIO(Kshs) | E11: REQUIRED PROVISION | F11: REQUIRED PROVISION AMOUNT(Kshs)
B12: Performing | D12: 1.0386794e+08 | E12: 0.01 | F12: =D12*E12 -> 1038679.4
B13: Watch | D13: 8995003.6 | E13: 0.05 | F13: =D13*E13 -> 449750.18
B14: Substandard | D14: 8424561.1 | E14: 0.25 | F14: =D14*E14 -> 2106140.3
B15: Doubtful | D15: 7787680.9 | E15: 0.5 | F15: =D15*E15 -> 3893840.5 | G15: =SUM(D14:D16)/D17 -> 0.18215453
B16: Loss | D16: 8925142.3 | E16: 1 | F16: =D16*E16 -> 8925142.3
B17: subtotal | C17: =SUM(C12:C16) -> 0 | D17: =SUM(D12:D16) -> 1.3800033e+08 | E17: 1.81 | F17: =SUM(F12:F16) -> 16413553
D19: 42614
B20: CLASSIFICATION | C20: NO. OF A/Cs | D20: OUTSTANDING LOAN PORTFOLIO(Kshs) | E20: REQUIRED PROVISION | F20: REQUIRED PROVISION AMOUNT(Kshs)
B21: Performing | D21: 1.0475357e+08 | E21: 0.01 | F21: =D21*E21 -> 1047535.7
B22: Watch | D22: 8527826.6 | E22: 0.05 | F22: =D22*E22 -> 426391.33 | G22: =SUM(D23:D25)/D26 -> 0.17584662
B23: Substandard | D23: 7571821.1 | E23: 0.25 | F23: =D23*E23 -> 1892955.3
B24: Doubtful | D24: 7687680.9 | E24: 0.5 | F24: =D24*E24 -> 3843840.5
B25: Loss | D25: 8910939.2 | E25: 1 | F25: =D25*E25 -> 8910939.2
B26: subtotal | C26: =SUM(C21:C25) -> 0 | D26: =SUM(D21:D25) -> 1.3745184e+08 | E26: 1.81 | F26: =SUM(F21:F25) -> 16121662
D28: 42705
B29: CLASSIFICATION | C29: NO. OF A/Cs | D29: OUTSTANDING LOAN PORTFOLIO(Kshs) | E29: REQUIRED PROVISION | F29: REQUIRED PROVISION AMOUNT(Kshs)
B30: Performing | C30: 982 | D30: 32509817 | E30: 0.01 | F30: =D30*E30 -> 325098.17
B31: Watch | C31: 27 | D31: 344067.61 | E31: 0.05 | F31: =D31*E31 -> 17203.38
B32: Substandard | C32: 165 | D32: 2499036.2 | E32: 0.25 | F32: =D32*E32 -> 624759.06 | H32: =SUM(D32+D33+D34)/D35 -> 0.40903818
B33: Doubtful | C33: 210 | D33: 6638610.7 | E33: 0.5 | F33: =D33*E33 -> 3319305.4
B34: Loss | C34: 637 | D34: 13602389 | E34: 1 | F34: =D34*E34 -> 13602389
B35: subtotal | C35: =SUM(C30:C34) -> 2021 | D35: =SUM(D30:D34) -> 55593921 | E35: 1.81 | F35: =SUM(F30:F34) -> 17888755
D37: Audited 2016
B38: CLASSIFICATION | C38: NO. OF A/Cs | D38: OUTSTANDING LOAN PORTFOLIO(Kshs) | E38: REQUIRED PROVISION | F38: REQUIRED PROVISION AMOUNT(Kshs)
B39: Performing | D39: 32509817 | E39: 0.01 | F39: =D39*E39 -> 325098.17
B40: Watch | D40: 344067.61 | E40: 0.05 | F40: =D40*E40 -> 17203.38 | H40: =SUM(D41+D42+D43)/D44 -> 0.40903818
B41: Substandard | D41: 2499036.2 | E41: 0.25 | F41: =D41*E41 -> 624759.06
B42: Doubtful | D42: 6638610 | E42: 0.5 | F42: =D42*E42 -> 3319305
B43: Loss | D43: 13602389 | E43: 1 | F43: =D43*E43 -> 13602389
B44: subtotal | C44: =SUM(C39:C43) -> 0 | D44: =SUM(D39:D43) -> 55593920 | E44: 1.81 | F44: =SUM(F39:F43) -> 17888755
D46: 43070
B47: CLASSIFICATION | C47: NO. OF A/Cs | D47: OUTSTANDING LOAN PORTFOLIO(Kshs) | E47: REQUIRED PROVISION | F47: REQUIRED PROVISION AMOUNT(Kshs)
B48: Performing | C48: 1523 | D48: 47249891 | E48: 0.01 | F48: =D48*E48 -> 472498.91
B49: Watch | C49: 82 | D49: 985952.92 | E49: 0.05 | F49: =D49*E49 -> 49297.646
B50: Substandard | C50: 120 | D50: 2323112.9 | E50: 0.25 | F50: =D50*E50 -> 580778.22
B51: Doubtful | C51: 147 | D51: 3443607.1 | E51: 0.5 | F51: =D51*E51 -> 1721803.6
B52: Loss | C52: 702 | D52: 14791388 | E52: 1 | F52: =D52*E52 -> 14791388
B53: subtotal | C53: =SUM(C48:C52) -> 2574 | D53: =SUM(D48:D52) -> 68793952 | F53: =SUM(F48:F52) -> 17615766
B54: Reschedule/Renegotiated loans
B55: Performing | C55: 0 | D55: 0 | E55: 0.01 | F55: =D55*E55 -> 0
B56: Watch | C56: 0 | D56: 0 | E56: 0.05 | F56: =D56*E56 -> 0
B57: Substandard | C57: 0 | D57: 0 | E57: 0.25 | F57: =D57*E57 -> 0
B58: Doubtful | C58: 0 | D58: 0 | E58: 0.5 | F58: =D58*E58 -> 0
B59: Loss | C59: 0 | D59: 0 | E59: 1 | F59: =D59*E59 -> 0
B60: subtotal | C60: =SUM(C54:C59) -> 0 | D60: =SUM(D54:D59) -> 0 | F60: =SUM(F54:F59) -> 0
B61: GRAND TOTAL | C61: =C53+C60 -> 2574 | D61: =D53+D60 -> 68793952 | F61: =F53+F60 -> 17615766
B62: 43160 | H62: 43269 | L62: 43361
C63: A | D63: B | E63: C | F63: D | G63: A | H63: B | I63: C | J63: D | K63: A | L63: B | M63: C | N63: D
A64: NO. | B64: CLASSIFICATION | C64: NO. OF A/Cs | D64: OUTSTANDING LOAN PORTFOLIO(Kshs) | E64: REQUIRED PROVISION | F64: REQUIRED PROVISION AMOUNT(Kshs) | G64: NO. OF A/Cs | H64: OUTSTANDING LOAN PORTFOLIO(Kshs) | I64: REQUIRED PROVISION | J64: REQUIRED PROVISION AMOUNT(Kshs) | K64: NO. OF A/Cs | L64: OUTSTANDING LOAN PORTFOLIO(Kshs) | M64: REQUIRED PROVISION | N64: REQUIRED PROVISION AMOUNT(Kshs)
A65: 1 | B65: Performing | C65: 1523 | D65: 1.2386258e+08 | E65: 0.01 | F65: =D65*E65 -> 1238625.8 | G65: 1554 | H65: 1.2264448e+08 | I65: 0.01 | J65: =H65*I65 -> 1226444.8 | K65: 1554 | L65: 1.2914944e+08 | M65: 0.01 | N65: =L65*M65 -> 1291494.4
A66: 2 | B66: Watch | C66: 82 | D66: 944892.72 | E66: 0.05 | F66: =D66*E66 -> 47244.636 | G66: 182 | H66: 1685875.7 | I66: 0.05 | J66: =H66*I66 -> 84293.786 | K66: 182 | L66: 1415379.7 | M66: 0.05 | N66: =L66*M66 -> 70768.986
A67: 3 | B67: Substandard | C67: 120 | D67: 1613115.9 | E67: 0.25 | F67: =D67*E67 -> 403278.97 | G67: 122 | H67: 1823165.9 | I67: 0.25 | J67: =H67*I67 -> 455791.47 | K67: 122 | L67: 1470165.9 | M67: 0.25 | N67: =L67*M67 -> 367541.47
A68: 4 | B68: Doubtful | C68: 147 | D68: 1823607.1 | E68: 0.5 | F68: =D68*E68 -> 911803.56 | G68: 157 | H68: 1530907.1 | I68: 0.5 | J68: =H68*I68 -> 765453.56 | K68: 157 | L68: 1360997.1 | M68: 0.5 | N68: =L68*M68 -> 680498.56
A69: 5 | B69: Loss | C69: 702 | D69: 12793027 | E69: 1 | F69: =D69*E69 -> 12793027 | G69: 602 | H69: 12113427 | I69: 1 | J69: =H69*I69 -> 12113427 | K69: 602 | L69: 13279821 | M69: 1 | N69: =L69*M69 -> 13279821
B70: subtotal | C70: =SUM(C65:C69) -> 2574 | D70: =SUM(D65:D69) -> 1.4103722e+08 | F70: =SUM(F65:F69) -> 15393980 | G70: =SUM(G65:G69) -> 2617 | H70: =SUM(H65:H69) -> 1.3979786e+08 | J70: =SUM(J65:J69) -> 14645411 | K70: =SUM(K65:K69) -> 2617 | L70: =SUM(L65:L69) -> 1.466758e+08 | N70: =SUM(N65:N69) -> 15690124
B71: Reschedule/Renegotiated loans
A72: 1 | B72: Performing | C72: 0 | D72: 0 | E72: 0.01 | F72: =D72*E72 -> 0 | G72: 0 | H72: 0 | I72: 0.01 | J72: =H72*I72 -> 0 | K72: 0 | L72: 0 | M72: 0.01 | N72: =L72*M72 -> 0
A73: 2 | B73: Watch | C73: 0 | D73: 0 | E73: 0.05 | F73: =D73*E73 -> 0 | G73: 0 | H73: 0 | I73: 0.05 | J73: =H73*I73 -> 0 | K73: 0 | L73: 0 | M73: 0.05 | N73: =L73*M73 -> 0
A74: 3 | B74: Substandard | C74: 0 | D74: 0 | E74: 0.25 | F74: =D74*E74 -> 0 | G74: 0 | H74: 0 | I74: 0.25 | J74: =H74*I74 -> 0 | K74: 0 | L74: 0 | M74: 0.25 | N74: =L74*M74 -> 0
A75: 4 | B75: Doubtful | C75: 0 | D75: 0 | E75: 0.5 | F75: =D75*E75 -> 0 | G75: 0 | H75: 0 | I75: 0.5 | J75: =H75*I75 -> 0 | K75: 0 | L75: 0 | M75: 0.5 | N75: =L75*M75 -> 0
A76: 5 | B76: Loss | C76: 0 | D76: 0 | E76: 1 | F76: =D76*E76 -> 0 | G76: 0 | H76: 0 | I76: 1 | J76: =H76*I76 -> 0 | K76: 0 | L76: 0 | M76: 1 | N76: =L76*M76 -> 0
B77: subtotal | C77: =SUM(C71:C76) -> 0 | D77: =SUM(D71:D76) -> 0 | F77: =SUM(F71:F76) -> 0 | G77: =SUM(G71:G76) -> 0 | H77: =SUM(H71:H76) -> 0 | J77: =SUM(J71:J76) -> 0 | K77: =SUM(K71:K76) -> 0 | L77: =SUM(L71:L76) -> 0 | N77: =SUM(N71:N76) -> 0
B78: GRAND TOTAL | C78: =C70+C77 -> 2574 | D78: =D70+D77 -> 1.4103722e+08 | F78: =F70+F77 -> 15393980 | G78: =G70+G77 -> 2617 | H78: =H70+H77 -> 1.3979786e+08 | J78: =J70+J77 -> 14645411 | K78: =K70+K77 -> 2617 | L78: =L70+L77 -> 1.466758e+08 | N78: =N70+N77 -> 15690124
D80: =D67+D68+D69 -> 16229750 | E80: =D80/D78 -> 0.11507423 | H80: =H67+H68+H69 -> 15467500 | I80: =H80/H78 -> 0.11064189 | L80: =L67+L68+L69 -> 16110984
L81: =L80/L78 -> 0.10984078

Sheet Financials
B1: Financial Performance | CC1: =CA15+CA16+CA17+CA18+CA19+CA20+CA21 -> 88448522
B2: Year | C2: 2012 Audited | D2: 2013 Audited | E2: 2014 Audted | F2: 2015 Audited | G2: 42370 | H2: 42401 | I2: 42430 | J2: 42461 | K2: 42491 | L2: 42522 | M2: 42552 | N2: 42583 | O2: 42614 | P2: 42644 | Q2: 42675 | R2: 42705 | S2: Audited 2016 | T2: 42736 | U2: 42767 | V2: 42795 | W2: 42826 | X2: 42856 | Y2: 42887 | Z2: 42917 | AA2: 42948 | AB2: 42979 | AC2: 43009 | AD2: 43040 | AE2: 43070 | AF2: Audited 2017 | AG2: 43101 | AH2: 43132 | AI2: 43160 | AJ2: 43191 | AK2: 43221 | AL2: 43252 | AM2: 43282 | AN2: 43313 | AO2: 43344 | AP2: 43374 | AQ2: 43405 | AR2: 43435 | AS2: Audited 2018 | AT2: 43466 | AU2: 43497 | AV2: 43525 | AW2: 43556 | AX2: 43586 | AY2: 43617 | AZ2: 43647 | BA2: 43678 | BB2: 43709 | BC2: 43739 | BD2: 43770 | BE2: 43800 | BF2: Audited 2019 | BG2: 43831 | BH2: 43862 | BI2: 43891 | BJ2: 43922 | BK2: 43952 | BL2: 43983 | BM2: 44013 | BN2: 44044 | BO2: 44075 | BP2: 44105 | BQ2: 44136 | BR2: 44166 | BS2: Audited 2020 | BT2: 44197 | BU2: 44228 | BV2: 44256 | BW2: 44287 | BX2: 44317 | BY2: 44348 | BZ2: 44378 | CA2: 44409 | CB2: 44440 | CC2: 44470 | CD2: 44501 | CE2: 44531 | CF2: Audited 2021 | CG2: 44562 | CH2: 44593 | CI2: 44621 | CJ2: 44652 | CK2: 44682 | CL2: 44713 | CM2: 44743 | CN2: 44774 | CO2: 44805 | CP2: 44835 | CQ2: 44866 | CR2: 44896 | CS2: Audited 2022 | CT2: 44927 | CU2: 44958 | CV2: 44986 | CW2: 45017 | CX2: 45047 | CY2: 45078
A3: 1 | B3: Membership
A4: 2 | B4: Total Assets | C4: ='Evolutive SFP'!B26 -> 3.3049886e+08 | D4: ='Evolutive SFP'!C26 -> 3.482434e+08 | E4: ='Evolutive SFP'!D26 -> 3.8616078e+08 | F4: ='Evolutive SFP'!E26 -> 3.9634317e+08 | G4: ='Evolutive SFP'!F26 -> 3.7907267e+08 | H4: ='Evolutive SFP'!G26 -> 3.8462171e+08 | I4: ='Evolutive SFP'!H26 -> 3.7946308e+08 | J4: ='Evolutive SFP'!I26 -> 739043304 | ... CT4: ='Evolutive SFP'!CS26 -> 5.193942e+08
A5: 3 | B5: Total Deposits | C5: ='Evolutive SFP'!B30 -> 1.6373648e+08 | D5: ='Evolutive SFP'!C30 -> 1.256981e+08 | E5: ='Evolutive SFP'!D30 -> 1.4885894e+08 | F5: ='Evolutive SFP'!E30 -> 1.2960257e+08 | G5: ='Evolutive SFP'!F30 -> 1.4681192e+08 | H5: ='Evolutive SFP'!G30 -> 1.5026732e+08 | I5: ='Evolutive SFP'!H30 -> 1.4489477e+08 | J5: ='Evolutive SFP'!I30 -> 2.7844703e+08 | ... CT5: ='Evolutive SFP'!CS30 -> 1.95214e+08
A6: 3.1 | B6: Deposits-Members(BOSA) | C6: ='Evolutive SFP'!B29 -> 47036877 | D6: ='Evolutive SFP'!C29 -> 46620378 | E6: ='Evolutive SFP'!D29 -> 46620379 | F6: ='Evolutive SFP'!E29 -> 46706120 | G6: ='Evolutive SFP'!F29 -> 47996421 | H6: ='Evolutive SFP'!G29 -> 50229762 | I6: ='Evolutive SFP'!H29 -> 46820378 | J6: ='Evolutive SFP'!I29 -> 93240756 | ... CT6: ='Evolutive SFP'!CS29 -> 60802471
A7: 3.2 | B7: Deposits-Customers(FOSA) | C7: =('Evolutive SFP'!B27+'Evolutive SFP'!B28) -> 1.166996e+08 | D7: =('Evolutive SFP'!C27+'Evolutive SFP'!C28) -> 79077723 | E7: =('Evolutive SFP'!D27+'Evolutive SFP'!D28) -> 1.0223856e+08 | F7: =('Evolutive SFP'!E27+'Evolutive SFP'!E28) -> 82896448 | G7: =('Evolutive SFP'!F27+'Evolutive SFP'!F28) -> 98815497 | H7: =('Evolutive SFP'!G27+'Evolutive SFP'!G28) -> 1.0003756e+08 | I7: =('Evolutive SFP'!H27+'Evolutive SFP'!H28) -> 98074388 | J7: =('Evolutive SFP'!I27+'Evolutive SFP'!I28) -> 1.8520628e+08 | ... CT7: =('Evolutive SFP'!CS27+'Evolutive SFP'!CS28) -> 1.3441153e+08
A8: 4 | B8: External Borrowing | C8: ='Evolutive SFP'!B36 -> 92209657 | D8: ='Evolutive SFP'!C36 -> 1.4559074e+08 | E8: ='Evolutive SFP'!D36 -> 165770876 | F8: ='Evolutive SFP'!E36 -> 1.9020569e+08 | G8: ='Evolutive SFP'!F36 -> 165770876 | H8: ='Evolutive SFP'!G36 -> 167383681 | I8: ='Evolutive SFP'!H36 -> 167383681 | J8: ='Evolutive SFP'!I36 -> 334767362 | ... CT8: ='Evolutive SFP'!CS36 -> 49188020
A10: 5 | B10: Share capital and Reserves
A11: 5.1 | B11: Core Capital | C11: =C14-C22-C25 -> 25893259 | D11: =D14-D22-D25 -> 44953317 | E11: =E14-E22-E25 -> 46424530 | F11: =F14-F22-F25 -> 26979295 | G11: =G14-G22-G25 -> 26564503 | H11: =H14-H22-H25 -> 25733137 | I11: =I14-I22-I25 -> 25733337 | J11: =J14-J22-J25 -> 51866675 | ... CN11: =CN14-CN22-CN25 -> -77493632 | CO11: =SUM('Evolutive SFP'!CN38:CN45)-'Evolutive SFP'!CN12 -> 2.9130467e+08 | CP11: =SUM('Evolutive SFP'!CO38:CO45)-'Evolutive SFP'!CO12 -> 2.875611e+08 | CQ11: =SUM('Evolutive SFP'!CP38:CP45)-'Evolutive SFP'!CP12 -> 2.7042544e+08 | CR11: =SUM('Evolutive SFP'!CQ38:CQ45)-'Evolutive SFP'!CQ12 -> 2.7691222e+08 | CS11: =SUM('Evolutive SFP'!CR38:CR45)-'Evolutive SFP'!CR12 -> 2.6747179e+08 | CT11: =CT14-CT22-CT25 -> 72927876
A12: 5.2 | B12: Institutional Capital | C12: =C11-C15 -> -27425080 | D12: =D11-D15 -> -8624806 | E12: =E11-E15 -> -7973319.7 | F12: =F11-F15 -> -26613828 | G12: =G11-G15 -> -27857746 | H12: =H11-H15 -> -28689112 | I12: =I11-I15 -> -28689112 | J12: =J11-J15 -> -57378223 | ... CT12: =CT11-CT15 -> -2958007
A14: 5.3 | B14: Total Capital | C14: =C15+C16+C17+C18+C19+C20+C21 -> 63959537 | D14: =D15+D16+D17+D18+D19+D20+D21 -> 67184157 | E14: =E15+E16+E17+E18+E19+E20+E21 -> 68655370 | F14: =F15+F16+F17+F18+F19+F20+F21 -> 61199157 | G14: =G15+G16+G17+G18+G19+G20+G21 -> 62028283 | H14: =H15+H16+H17+H18+H19+H20+H21 -> 62679770 | I14: =I15+I16+I17+I18+I19+I20+I21 -> 62679970 | J14: =J15+J16+J17+J18+J19+J20+J21 -> 125759940 | ... CT14: =CT15+CT16+CT17+CT18+CT19+CT20+CT21 -> 2.5709036e+08
A15: 5.3.1 | B15: Members Share Capital | C15: ='Evolutive SFP'!B38 -> 53318339 | D15: ='Evolutive SFP'!C38 -> 53578123 | E15: ='Evolutive SFP'!D38 -> 54397850 | F15: ='Evolutive SFP'!E38 -> 53593123 | G15: ='Evolutive SFP'!F38 -> 54422249 | H15: ='Evolutive SFP'!G38 -> 54422249 | I15: ='Evolutive SFP'!H38 -> 54422449 | J15: ='Evolutive SFP'!I38 -> 109244898 | ... CT15: ='Evolutive SFP'!CS38 -> 75885883
A16: 5.3.2 | B16: Entrance Fees
A17: 5.3.3 | B17: Retained Earnings | C17: ='Evolutive SFP'!B40 -> 0 | D17: ='Evolutive SFP'!C40 -> 0 | E17: ='Evolutive SFP'!D40 -> 0 | F17: ='Evolutive SFP'!E40 -> 0 | G17: ='Evolutive SFP'!F40 -> 0 | H17: ='Evolutive SFP'!G40 -> 0 | I17: ='Evolutive SFP'!H40 -> 0 | J17: ='Evolutive SFP'!I40 -> 0 | ... CT17: ='Evolutive SFP'!CS40 -> 0
A18: 5.3.4 | B18: Appropriation Account | C18: ='Evolutive SFP'!B46 -> 2000000 | D18: ='Evolutive SFP'!C46 -> 3000000 | E18: ='Evolutive SFP'!D46 -> 3000000 | F18: ='Evolutive SFP'!E46 -> 0 | G18: ='Evolutive SFP'!F46 -> 0 | H18: ='Evolutive SFP'!G46 -> 0 | I18: ='Evolutive SFP'!H46 -> 0 | J18: ='Evolutive SFP'!I46 -> 0 | ... CS18: ='Evolutive SFP'!CR46 -> 6000000 | CT18: ='Evolutive SFP'!CS47 -> 0
A19: 5.3.5 | B19: Statutory Reserves | C19: ='Evolutive SFP'!B43 -> 6641198.1 | D19: ='Evolutive SFP'!C43 -> 7606034 | E19: ='Evolutive SFP'!D43 -> 8257520.3 | F19: ='Evolutive SFP'!E43 -> 7606034 | G19: ='Evolutive SFP'!F43 -> 7606034 | H19: ='Evolutive SFP'!G43 -> 8257521 | I19: ='Evolutive SFP'!H43 -> 8257521 | J19: ='Evolutive SFP'!I43 -> 16515042 | ... CT19: ='Evolutive SFP'!CS43 -> 16272832
A20: 5.3.6 | B20: Capital Reserves | C20: =('Evolutive SFP'!B44) -> 0 | D20: =('Evolutive SFP'!C44) -> 0 | E20: =('Evolutive SFP'!D44) -> 0 | F20: =('Evolutive SFP'!E44) -> 0 | G20: =('Evolutive SFP'!F44) -> 0 | H20: =('Evolutive SFP'!G44) -> 0 | I20: =('Evolutive SFP'!H44) -> 0 | J20: =('Evolutive SFP'!I44) -> 0 | ... CS20: =('Evolutive SFP'!CR44) -> 0 | CT20: =('Evolutive SFP'!CS45) -> 1.6493164e+08
A21: 5.3.7 | B21: Supplementary Capital & reserves | C21: =C22+C23 -> 2000000 | D21: =D22+D23 -> 3000000 | E21: =E22+E23 -> 3000000 | F21: =F22+F23 -> 0 | G21: =G22+G23 -> 0 | H21: =H22+H23 -> 0 | I21: =I22+I23 -> 0 | J21: =J22+J23 -> 0 | ... CT21: =CT22+CT23 -> 0
A22: a | B22: Proposed Dividends | C22: ='Evolutive SFP'!B46 -> 2000000 | D22: ='Evolutive SFP'!C46 -> 3000000 | E22: ='Evolutive SFP'!D46 -> 3000000 | F22: ='Evolutive SFP'!E46 -> 0 | G22: ='Evolutive SFP'!F46 -> 0 | H22: ='Evolutive SFP'!G46 -> 0 | I22: ='Evolutive SFP'!H46 -> 0 | J22: ='Evolutive SFP'!I46 -> 0 | ... CS22: ='Evolutive SFP'!CR46 -> 6000000 | CT22: ='Evolutive SFP'!CS47 -> 0
A23: b | B23: Risk Mgt Fund
A25: 6 | B25: Investments | C25: =C26+C27+C28 -> 36066278 | D25: =D26+D27+D28 -> 19230840 | E25: =E26+E27+E28 -> 19230840 | F25: =F26+F27+F28 -> 34219862 | G25: =G26+G27+G28 -> 35463780 | H25: =H26+H27+H28 -> 36946633 | I25: =I26+I27+I28 -> 36946633 | J25: =J26+J27+J28 -> 73893265 | ... CT25: =CT26+CT27+CT28 -> 1.8416248e+08
A26: 6.1 | B26: Shares in Kusco,CIC,Coop Bank | C26: ='Evolutive SFP'!B12 -> 24166640 | D26: ='Evolutive SFP'!C12 -> 19230840 | E26: ='Evolutive SFP'!D12 -> 19230840 | F26: ='Evolutive SFP'!E12 -> 19103340 | G26: ='Evolutive SFP'!F12 -> 19103340 | H26: ='Evolutive SFP'!G12 -> 19103340 | I26: ='Evolutive SFP'!H12 -> 19103340 | J26: ='Evolutive SFP'!I12 -> 38206680 | ... CT26: ='Evolutive SFP'!CS12 -> 115000
A27: 6.2 | B27: Equity Investments (at cost) | C27: ='Evolutive SFP'!B10 -> 64200 | D27: ='Evolutive SFP'!C10 -> 0 | E27: ='Evolutive SFP'!D10 -> 0 | F27: ='Evolutive SFP'!E10 -> 0 | G27: ='Evolutive SFP'!F10 -> 0 | H27: ='Evolutive SFP'!G10 -> 0 | I27: ='Evolutive SFP'!H10 -> 0 | J27: ='Evolutive SFP'!I10 -> 0 | ... CT27: ='Evolutive SFP'!CS10 -> 0
A28: 6.3 | B28: Deposits in KUSCCO CFP | C28: ='Evolutive SFP'!B11 -> 11835438 | D28: ='Evolutive SFP'!C11 -> 0 | E28: ='Evolutive SFP'!D11 -> 0 | F28: ='Evolutive SFP'!E11 -> 15116522 | G28: ='Evolutive SFP'!F11 -> 16360440 | H28: ='Evolutive SFP'!G11 -> 17843293 | I28: ='Evolutive SFP'!H11 -> 17843293 | J28: ='Evolutive SFP'!I11 -> 35686585 | ... CT28: ='Evolutive SFP'!CS11 -> 1.8404748e+08
A30: 7 | B30: Net Loans & Advances | C30: ='Evolutive SFP'!B13 -> 84967806 | D30: ='Evolutive SFP'!C13 -> 94311040 | E30: ='Evolutive SFP'!D13 -> 93010285 | F30: ='Evolutive SFP'!E13 -> 1.3387641e+08 | G30: ='Evolutive SFP'!F13 -> 1.3098557e+08 | H30: ='Evolutive SFP'!G13 -> 1.3812322e+08 | I30: ='Evolutive SFP'!H13 -> 1.3501521e+08 | J30: ='Evolutive SFP'!I13 -> 2.6519709e+08 | ... CT30: ='Evolutive SFP'!CS13 -> 1.9216066e+08
A31: 7.1 | B31: Gross Loans & advances | C31: ='Evolutive SFP'!B14 -> 96723149 | D31: ='Evolutive SFP'!C14 -> 1.0707096e+08 | E31: ='Evolutive SFP'!D14 -> 105894421 | F31: ='Evolutive SFP'!E14 -> 1.4739834e+08 | G31: ='Evolutive SFP'!F14 -> 145637760 | H31: ='Evolutive SFP'!G14 -> 1.5366726e+08 | I31: ='Evolutive SFP'!H14 -> 150403433 | J31: ='Evolutive SFP'!I14 -> 295755486 | ... CT31: ='Evolutive SFP'!CS14 -> 2.0635227e+08
A32: 7.2 | B32: Allowance for loan losses | C32: ='Evolutive SFP'!B15 -> 11755343 | D32: ='Evolutive SFP'!C15 -> 12759924 | E32: ='Evolutive SFP'!D15 -> 12884136 | F32: ='Evolutive SFP'!E15 -> 13521929 | G32: ='Evolutive SFP'!F15 -> 14652190 | H32: ='Evolutive SFP'!G15 -> 15544042 | I32: ='Evolutive SFP'!H15 -> 15388223 | J32: ='Evolutive SFP'!I15 -> 30558396 | ... CT32: ='Evolutive SFP'!CS15 -> 14191608
A34: 8 | B34: Non-Earning Assets | C34: ='Evolutive SFP'!B20+'Evolutive SFP'!B7 -> 1.613053e+08 | D34: ='Evolutive SFP'!C20+'Evolutive SFP'!C7 -> 1.8994396e+08 | E34: ='Evolutive SFP'!D20+'Evolutive SFP'!D7 -> 1.9120934e+08 | F34: ='Evolutive SFP'!E20+'Evolutive SFP'!E7 -> 1.898266e+08 | G34: ='Evolutive SFP'!F20+'Evolutive SFP'!F7 -> 1.8892964e+08 | H34: ='Evolutive SFP'!G20+'Evolutive SFP'!G7 -> 1.8858032e+08 | I34: ='Evolutive SFP'!H20+'Evolutive SFP'!H7 -> 1.8823533e+08 | J34: ='Evolutive SFP'!I20+'Evolutive SFP'!I7 -> 3.7578916e+08 | ... CT34: ='Evolutive SFP'!CS20+'Evolutive SFP'!CS7 -> 1.5641343e+08
A35: 8.1 | B35: Property and Equipment | C35: ='Evolutive SFP'!B22 -> 84021813 | D35: ='Evolutive SFP'!C22 -> 88181510 | E35: ='Evolutive SFP'!D22 -> 84809160 | F35: ='Evolutive SFP'!E22 -> 12175559 | G35: ='Evolutive SFP'!F22 -> 10374562 | H35: ='Evolutive SFP'!G22 -> 10201658 | I35: ='Evolutive SFP'!H22 -> 10032024 | J35: ='Evolutive SFP'!I22 -> 19731189 | ... CT35: ='Evolutive SFP'!CS22 -> 8551198.3
A37: 9 | B37: Turnover | C37: =C38+C39+C40+C41 -> 63593389 | D37: =D38+D39+D40+D41 -> 81396739 | E37: =E38+E39+E40+E41 -> 75757598 | F37: =F38+F39+F40+F41 -> 5621897.8 | G37: =G38+G39+G40+G41 -> 6095529 | H37: =H38+H39+H40+H41 -> 9930772.8 | I37: =I38+I39+I40+I41 -> 13914971 | J37: =J38+J39+J40+J41 -> 35195599 | ... CT37: =CT38+CT39+CT40+CT41 -> 10341788
A38: 9.1 | B38: Loan Interest | C38: ='Evolutitve SCI'!B5 -> 25181369 | D38: ='Evolutitve SCI'!C5 -> 23538214 | E38: ='Evolutitve SCI'!D5 -> 29443949 | F38: ='Evolutitve SCI'!E5 -> 2039868.4 | G38: ='Evolutitve SCI'!F5 -> 2097436 | H38: ='Evolutitve SCI'!G5 -> 3762373.9 | I38: ='Evolutitve SCI'!H5 -> 5471623.5 | J38: ='Evolutitve SCI'!I5 -> 14148801 | ... CT38: ='Evolutitve SCI'!CS5 -> 4764670
A39: 9.2 | B39: Income from investments | C39: ='Evolutitve SCI'!B7 -> 16420261 | D39: ='Evolutitve SCI'!C7 -> 33570387 | E39: ='Evolutitve SCI'!D7 -> 18290060 | F39: ='Evolutitve SCI'!E7 -> 2971441.5 | G39: ='Evolutitve SCI'!F7 -> 3320109 | H39: ='Evolutitve SCI'!G7 -> 5453601 | I39: ='Evolutitve SCI'!H7 -> 7714749.3 | J39: ='Evolutitve SCI'!I7 -> 19489542 | ... CT39: ='Evolutitve SCI'!CS7 -> 4993648.2
A40: 9.3 | B40: Fees & Commissions | C40: ='Evolutitve SCI'!B6 -> 21991759 | D40: ='Evolutitve SCI'!C6 -> 24288137 | E40: ='Evolutitve SCI'!D6 -> 28023588 | F40: ='Evolutitve SCI'!E6 -> 610588 | G40: ='Evolutitve SCI'!F6 -> 677984 | H40: ='Evolutitve SCI'!G6 -> 714798 | I40: ='Evolutitve SCI'!H6 -> 728598 | J40: ='Evolutitve SCI'!I6 -> 1557256 | ... CT40: ='Evolutitve SCI'!CS6 -> 583470
A41: 9.4 | B41: Average yield on loans
A43: 10 | B43: Financial and Operating costs | C43: =SUM(C44:C47) -> 55124263 | D43: =SUM(D44:D47) -> 69217906 | E43: =SUM(E44:E47) -> 69517652 | F43: =SUM(F44:F47) -> 4578080.8 | G43: =SUM(G44:G47) -> 3543899.5 | H43: =SUM(H44:H47) -> 9740895.5 | I43: =SUM(I44:I47) -> 13618634 | J43: =SUM(J44:J47) -> 42685319 | ... CT43: =SUM(CT44:CT47) -> 6490787.5
A44: 10.1 | B44: Interest expense on deposits | C44: ='Evolutitve SCI'!B13+'Evolutitve SCI'!B16 -> 205944.15 | D44: ='Evolutitve SCI'!C13+'Evolutitve SCI'!C16 -> 1261174 | E44: ='Evolutitve SCI'!D13+'Evolutitve SCI'!D16 -> 1665811.8 | F44: ='Evolutitve SCI'!E13+'Evolutitve SCI'!E16 -> 67513 | G44: ='Evolutitve SCI'!F13+'Evolutitve SCI'!F16 -> 99600 | H44: ='Evolutitve SCI'!G13+'Evolutitve SCI'!G16 -> 264375 | I44: ='Evolutitve SCI'!H13+'Evolutitve SCI'!H16 -> 452862 | J44: ='Evolutitve SCI'!I13+'Evolutitve SCI'!I16 -> 1242010 | ... CT44: ='Evolutitve SCI'!CS13+'Evolutitve SCI'!CS16 -> 911133.16
A45: 10.2 | B45: Dividend expense on share capital | C45: ='Evolutitve SCI'!B15 -> 0 | D45: ='Evolutitve SCI'!C15 -> 0 | E45: ='Evolutitve SCI'!D15 -> 0 | F45: ='Evolutitve SCI'!E15 -> 0 | G45: ='Evolutitve SCI'!F15 -> 0 | H45: ='Evolutitve SCI'!G15 -> 0 | I45: ='Evolutitve SCI'!H15 -> 0 | J45: ='Evolutitve SCI'!I15 -> 0 | ... CT45: ='Evolutitve SCI'!CS15 -> 0
A46: 10.3 | B46: Interest expense on borrowed funds | C46: ='Evolutitve SCI'!B14 -> 12726209 | D46: ='Evolutitve SCI'!C14 -> 17604356 | E46: ='Evolutitve SCI'!D14 -> 20952972 | F46: ='Evolutitve SCI'!E14 -> 916952 | G46: ='Evolutitve SCI'!F14 -> 0 | H46: ='Evolutitve SCI'!G14 -> 2239285 | I46: ='Evolutitve SCI'!H14 -> 2173849 | J46: ='Evolutitve SCI'!I14 -> 12151667 | ... CT46: ='Evolutitve SCI'!CS14 -> 0
A47: 10.4 | B47: Opperating expenses | C47: ='Evolutitve SCI'!B23 -> 42192110 | D47: ='Evolutitve SCI'!C23 -> 50352376 | E47: ='Evolutitve SCI'!D23 -> 46898868 | F47: ='Evolutitve SCI'!E23 -> 3593615.8 | G47: ='Evolutitve SCI'!F23 -> 3444299.5 | H47: ='Evolutitve SCI'!G23 -> 7237235.5 | I47: ='Evolutitve SCI'!H23 -> 10991923 | J47: ='Evolutitve SCI'!I23 -> 29291642 | ... CT47: ='Evolutitve SCI'!CS23 -> 5579654.4
CM49: =CM44/'Evolutive SFP'!CL30 -> 0.020555369

Sheet Investments
B2: INVESTMENTS
A3: Qourteed Shares | B3: 11,356,700@10- co-operative Bank | C3: 183567000
B4: 1011.25@45 shares in KCB | C4: 45506.25
B5: 1406@2 shares Kenya Airways | C5: 2812
B6: 160985@2.29 shares Cooperative Insurance Co.. | C6: 368655.65
A7: Total | C7: =SUM(C3:C6) -> 1.8398397e+08
A8: Unquorted | B8: 510@100 Shares KUSCCO Ltd. | C8: 51000
B9: 5750 @20 Shares in KERUSSU Ltd. | C9: 115000
B10: 250@50 Shares in NACCHU Ltd. | C10: 12500
A11: Total | C11: =SUM(C8:C10) -> 178500
A13: Both Quorted & Unquorted | C13: =C7+C11 -> 1.8416247e+08
C17: =C4+C5 -> 48318.25
C18: =C13-C17 -> 1.8411416e+08
