Workbook
Name BALANCE1_LDA01: '[1]Financial Statements'!$E$112
Name BALANCE1_LDA12: '[1]Financial Statements'!$E$123
Name BALANCE2_LDA01: '[1]Financial Statements'!$F$112
Name BALANCE2_LDA12: '[1]Financial Statements'!$F$123
Name BALANCE3_LDA01: '[1]Financial Statements'!$G$112
Name BALANCE3_LDA12: '[1]Financial Statements'!$G$123
Name BALANCE4_LDA01: '[1]Financial Statements'!$H$112
Name BALANCE4_LDA12: '[1]Financial Statements'!$H$123
Name BALANCE5_LDA01: '[1]Financial Statements'!$I$112
Name BALANCE5_LDA12: '[1]Financial Statements'!$I$123
Name BALANCE6_LDA01: '[1]Financial Statements'!$J$112
Name BALANCE6_LDA12: '[1]Financial Statements'!$J$123
Name NotApplicable: 'Prudential Ratios'!$B$76
Name PEARLS1_LA002: '[1]Financial Statements'!$E$280
Name PEARLS1_LE008: '[1]Financial Statements'!$E$275
Name PEARLS1_LE009: '[1]Financial Statements'!$E$276
Name PEARLS1_LR001: '[1]Financial Statements'!$E$282
Name PEARLS1_LR005: '[1]Financial Statements'!$E$286
Name PEARLS1_LR006: '[1]Financial Statements'!$E$287
Name PEARLS1_LR007: '[1]Financial Statements'!$E$288
Name PEARLS1_LR009: '[1]Financial Statements'!$E$290
Name PEARLS1_LS001: '[1]Financial Statements'!$E$298
Name PEARLS1_LS005: '[1]Financial Statements'!$E$302
Name PEARLS1_LS011: '[1]Financial Statements'!$E$308
Name PEARLS2_LA002: '[1]Financial Statements'!$F$280
Name PEARLS2_LE008: '[1]Financial Statements'!$F$275
Name PEARLS2_LE009: '[1]Financial Statements'!$F$276
Name PEARLS2_LR001: '[1]Financial Statements'!$F$282
Name PEARLS2_LR005: '[1]Financial Statements'!$F$286
Name PEARLS2_LR006: '[1]Financial Statements'!$F$287
Name PEARLS2_LR007: '[1]Financial Statements'!$F$288
Name PEARLS2_LR009: '[1]Financial Statements'!$F$290
Name PEARLS2_LS001: '[1]Financial Statements'!$F$298
Name PEARLS2_LS005: '[1]Financial Statements'!$F$302
Name PEARLS2_LS010: '[1]Financial Statements'!$F$307
Name PEARLS2_LS011: '[1]Financial Statements'!$F$308
Name PEARLS3_LA002: '[1]Financial Statements'!$G$280
Name PEARLS3_LE008: '[1]Financial Statements'!$G$275
Name PEARLS3_LE009: '[1]Financial Statements'!$G$276
Name PEARLS3_LR001: '[1]Financial Statements'!$G$282
Name PEARLS3_LR005: '[1]Financial Statements'!$G$286
Name PEARLS3_LR006: '[1]Financial Statements'!$G$287
Name PEARLS3_LR007: '[1]Financial Statements'!$G$288
Name PEARLS3_LR009: '[1]Financial Statements'!$G$290
Name PEARLS3_LS001: '[1]Financial Statements'!$G$298
Name PEARLS3_LS005: '[1]Financial Statements'!$G$302
Name PEARLS3_LS010: '[1]Financial Statements'!$G$307
Name PEARLS3_LS011: '[1]Financial Statements'!$G$308
Name PEARLS4_LA002: '[1]Financial Statements'!$H$280
Name PEARLS4_LE008: '[1]Financial Statements'!$H$275
Name PEARLS4_LE009: '[1]Financial Statements'!$H$276
Name PEARLS4_LR001: '[1]Financial Statements'!$H$282
Name PEARLS4_LR005: '[1]Financial Statements'!$H$286
Name PEARLS4_LR006: '[1]Financial Statements'!$H$287
Name PEARLS4_LR007: '[1]Financial Statements'!$H$288
Name PEARLS4_LR009: '[1]Financial Statements'!$H$290
Name PEARLS4_LS001: '[1]Financial Statements'!$H$298
Name PEARLS4_LS005: '[1]Financial Statements'!$H$302
Name PEARLS4_LS010: '[1]Financial Statements'!$H$307
Name PEARLS4_LS011: '[1]Financial Statements'!$H$308

Sheet compliance status
B2: audited2017 | C2: 43101 | D2: 43133 | E2: 43165 | F2: 43197 | G2: 43229 | H2: 43261 | I2: 43293 | J2: 43325 | K2: 43357 | L2: 43389 | M2: 43421 | N2: 43453
A3: CORE CAPITAL | B3: =IF('Prudential Ratios'!#REF!>10,"compliant","not compliant") -> #REF! | C3: =IF('Prudential Ratios'!#REF!>10,"compliant","not compliant") -> #REF! | D3: =IF('Prudential Ratios'!#REF!>10,"compliant","not compliant") -> #REF! | E3: =IF('Prudential Ratios'!#REF!>10,"compliant","not compliant") -> #REF! | F3: =IF('Prudential Ratios'!#REF!>10,"compliant","not compliant") -> #REF! | G3: =IF('Prudential Ratios'!#REF!>10,"compliant","not compliant") -> #REF! | H3: =IF('Prudential Ratios'!#REF!>10,"compliant","not compliant") -> #REF! | I3: =IF('Prudential Ratios'!#REF!>10,"compliant","not compliant") -> #REF! | ... N3: =IF('Prudential Ratios'!#REF!>10,"compliant","not compliant") -> #REF!
A4: CCA (Min 10%) | B4: =IF('Prudential Ratios'!#REF!>10%,"compliant","not compliant") -> #REF! | C4: =IF('Prudential Ratios'!#REF!>10%,"compliant","not compliant") -> #REF! | D4: =IF('Prudential Ratios'!#REF!>10%,"compliant","not compliant") -> #REF! | E4: =IF('Prudential Ratios'!#REF!>10%,"compliant","not compliant") -> #REF! | F4: =IF('Prudential Ratios'!#REF!>10%,"compliant","not compliant") -> #REF! | G4: =IF('Prudential Ratios'!#REF!>10%,"compliant","not compliant") -> #REF! | H4: =IF('Prudential Ratios'!#REF!>10%,"compliant","not compliant") -> #REF! | I4: =IF('Prudential Ratios'!#REF!>10%,"compliant","not compliant") -> #REF! | ... N4: =IF('Prudential Ratios'!#REF!>10%,"compliant","not compliant") -> #REF!
A5: ICA (Min 8%) | B5: =IF('Prudential Ratios'!#REF!>8%,"compliant","not compliant") -> #REF! | C5: =IF('Prudential Ratios'!#REF!>8%,"compliant","not compliant") -> #REF! | D5: =IF('Prudential Ratios'!#REF!>8%,"compliant","not compliant") -> #REF! | E5: =IF('Prudential Ratios'!#REF!>8%,"compliant","not compliant") -> #REF! | F5: =IF('Prudential Ratios'!#REF!>8%,"compliant","not compliant") -> #REF! | G5: =IF('Prudential Ratios'!#REF!>8%,"compliant","not compliant") -> #REF! | H5: =IF('Prudential Ratios'!#REF!>8%,"compliant","not compliant") -> #REF! | I5: =IF('Prudential Ratios'!#REF!>8%,"compliant","not compliant") -> #REF! | ... N5: =IF('Prudential Ratios'!#REF!>8%,"compliant","not compliant") -> #REF!
A6: CCD (Min 8%) | B6: =IF('Prudential Ratios'!#REF!>8%,"compliant","not compliant") -> #REF! | C6: =IF('Prudential Ratios'!#REF!>8%,"compliant","not compliant") -> #REF! | D6: =IF('Prudential Ratios'!#REF!>8%,"compliant","not compliant") -> #REF! | E6: =IF('Prudential Ratios'!#REF!>8%,"compliant","not compliant") -> #REF! | F6: =IF('Prudential Ratios'!#REF!>8%,"compliant","not compliant") -> #REF! | G6: =IF('Prudential Ratios'!#REF!>8%,"compliant","not compliant") -> #REF! | H6: =IF('Prudential Ratios'!#REF!>8%,"compliant","not compliant") -> #REF! | I6: =IF('Prudential Ratios'!#REF!>8%,"compliant","not compliant") -> #REF! | ... N6: =IF('Prudential Ratios'!#REF!>8%,"compliant","not compliant") -> #REF!
A7: NPL(5%)
A8: Liquidity(15%) | B8: =IF('Prudential Ratios'!#REF!>15%,"compliant","not compliant") -> #REF! | C8: =IF('Prudential Ratios'!#REF!>15%,"compliant","not compliant") -> #REF! | D8: =IF('Prudential Ratios'!#REF!>15%,"compliant","not compliant") -> #REF! | E8: =IF('Prudential Ratios'!#REF!>15%,"compliant","not compliant") -> #REF! | F8: =IF('Prudential Ratios'!#REF!>15%,"compliant","not compliant") -> #REF! | G8: =IF('Prudential Ratios'!#REF!>15%,"compliant","not compliant") -> #REF! | H8: =IF('Prudential Ratios'!#REF!>15%,"compliant","not compliant") -> #REF! | I8: =IF('Prudential Ratios'!#REF!>15%,"compliant","not compliant") -> #REF! | ... N8: =IF('Prudential Ratios'!#REF!>15%,"compliant","not compliant") -> #REF!
A9: NEA (Max 10%) | B9: =IF('Prudential Ratios'!#REF!<10%,"compliant","not compliant") -> #REF! | C9: =IF('Prudential Ratios'!#REF!<10%,"compliant","not compliant") -> #REF! | D9: =IF('Prudential Ratios'!#REF!<10%,"compliant","not compliant") -> #REF! | E9: =IF('Prudential Ratios'!#REF!<10%,"compliant","not compliant") -> #REF! | F9: =IF('Prudential Ratios'!#REF!<10%,"compliant","not compliant") -> #REF! | G9: =IF('Prudential Ratios'!#REF!<10%,"compliant","not compliant") -> #REF! | H9: =IF('Prudential Ratios'!#REF!<10%,"compliant","not compliant") -> #REF! | I9: =IF('Prudential Ratios'!#REF!<10%,"compliant","not compliant") -> #REF! | ... N9: =IF('Prudential Ratios'!#REF!<10%,"compliant","not compliant") -> #REF!
A10: LB ratio (Max 5%) | B10: =IF('Prudential Ratios'!#REF!<5%,"compliant","not compliant") -> #REF! | C10: =IF('Prudential Ratios'!#REF!<5%,"compliant","not compliant") -> #REF! | D10: =IF('Prudential Ratios'!#REF!<5%,"compliant","not compliant") -> #REF! | E10: =IF('Prudential Ratios'!#REF!<5%,"compliant","not compliant") -> #REF! | F10: =IF('Prudential Ratios'!#REF!<5%,"compliant","not compliant") -> #REF! | G10: =IF('Prudential Ratios'!#REF!<5%,"compliant","not compliant") -> #REF! | H10: =IF('Prudential Ratios'!#REF!<5%,"compliant","not compliant") -> #REF! | I10: =IF('Prudential Ratios'!#REF!<5%,"compliant","not compliant") -> #REF! | ... N10: =IF('Prudential Ratios'!#REF!<5%,"compliant","not compliant") -> #REF!
A11: FITD (Max 5%) | B11: =IF('Prudential Ratios'!#REF!<5%,"compliant","not compliant") -> #REF! | C11: =IF('Prudential Ratios'!#REF!<5%,"compliant","not compliant") -> #REF! | D11: =IF('Prudential Ratios'!#REF!<5%,"compliant","not compliant") -> #REF! | E11: =IF('Prudential Ratios'!#REF!<5%,"compliant","not compliant") -> #REF! | F11: =IF('Prudential Ratios'!#REF!<5%,"compliant","not compliant") -> #REF! | G11: =IF('Prudential Ratios'!#REF!<5%,"compliant","not compliant") -> #REF! | H11: =IF('Prudential Ratios'!#REF!<5%,"compliant","not compliant") -> #REF! | I11: =IF('Prudential Ratios'!#REF!<5%,"compliant","not compliant") -> #REF! | ... N11: =IF('Prudential Ratios'!#REF!<5%,"compliant","not compliant") -> #REF!
A12: FICC (Max 40%) | B12: =IF('Prudential Ratios'!#REF!<40%,"compliant","not compliant") -> #REF! | C12: =IF('Prudential Ratios'!#REF!<40%,"compliant","not compliant") -> #REF! | D12: =IF('Prudential Ratios'!#REF!<40%,"compliant","not compliant") -> #REF! | E12: =IF('Prudential Ratios'!#REF!<40%,"compliant","not compliant") -> #REF! | F12: =IF('Prudential Ratios'!#REF!<40%,"compliant","not compliant") -> #REF! | G12: =IF('Prudential Ratios'!#REF!<40%,"compliant","not compliant") -> #REF! | H12: =IF('Prudential Ratios'!#REF!<40%,"compliant","not compliant") -> #REF! | I12: =IF('Prudential Ratios'!#REF!<40%,"compliant","not compliant") -> #REF! | ... N12: =IF('Prudential Ratios'!#REF!<40%,"compliant","not compliant") -> #REF!
A13: EB ratio | B13: =IF('Prudential Ratios'!#REF!<25%,"compliant","not compliant") -> #REF! | C13: =IF('Prudential Ratios'!#REF!<25%,"compliant","not compliant") -> #REF! | D13: =IF('Prudential Ratios'!#REF!<25%,"compliant","not compliant") -> #REF! | E13: =IF('Prudential Ratios'!#REF!<25%,"compliant","not compliant") -> #REF! | F13: =IF('Prudential Ratios'!#REF!<25%,"compliant","not compliant") -> #REF! | G13: =IF('Prudential Ratios'!#REF!<25%,"compliant","not compliant") -> #REF! | H13: =IF('Prudential Ratios'!#REF!<25%,"compliant","not compliant") -> #REF! | I13: =IF('Prudential Ratios'!#REF!<25%,"compliant","not compliant") -> #REF! | ... N13: =IF('Prudential Ratios'!#REF!<25%,"compliant","not compliant") -> #REF!
A14: A=S+L | B14: =IF(SFP!#REF!=SFP!#REF!,"balancing","notbalancing") -> #REF! | C14: =IF(SFP!#REF!=SFP!#REF!,"balancing","notbalancing") -> #REF! | D14: =IF(SFP!#REF!=SFP!#REF!,"balancing","notbalancing") -> #REF! | E14: =IF(SFP!#REF!=SFP!#REF!,"balancing","notbalancing") -> #REF! | F14: =IF(SFP!#REF!=SFP!#REF!,"balancing","notbalancing") -> #REF! | G14: =IF(SFP!#REF!=SFP!#REF!,"balancing","notbalancing") -> #REF! | H14: =IF(SFP!#REF!=SFP!#REF!,"balancing","notbalancing") -> #REF! | I14: =IF(SFP!#REF!=SFP!#REF!,"balancing","notbalancing") -> #REF! | ... N14: =IF(SFP!#REF!=SFP!#REF!,"balancing","notbalancing") -> #REF!

Sheet Prudential Ratios
C1: SIRAJI SACCO SOCIETY LTD
C2: Sacco Financial Performance
C4: FINANCIAL SOUNDNESS INDICATORS | D4: Prude. Std | E4: Audited 2020 | F4: 44197 | G4: 44228 | H4: 44256 | I4: 44287 | J4: 44317 | K4: 44348 | L4: 44378 | M4: 44409 | N4: 44440 | O4: 44470 | P4: 44501 | Q4: 44531 | R4: Audited 2021 | S4: 44562 | T4: 44593 | U4: 44621 | V4: 44652 | W4: 44682 | X4: 44713 | Y4: 44743 | Z4: 44774 | AA4: 44805 | AB4: 44835 | AC4: 44866 | AD4: 44896 | AE4: Audited-2022 | AF4: 44949 | AG4: 44980 | AH4: 45008 | AI4: 45039 | AJ4: 45069 | AK4: 45100 | AL4: 45130
B5: 1 | C5: CAPITAL ADEQUACY REQUIREMENTS
B6: 1.1 | C6: Core capital | D6: ≥ Ksh.10M | E6: =Financials!C14/1000000 -> 82.86228 | F6: =Financials!D14/1000000 -> #REF! | G6: =Financials!E14/1000000 -> #REF! | H6: =Financials!F14/1000000 -> #REF! | I6: =Financials!G14/1000000 -> #REF! | J6: =Financials!H14/1000000 -> #REF! | K6: =Financials!I14/1000000 -> #REF! | L6: =Financials!J14/1000000 -> #REF! | ... AK6: =Financials!AI14/1000000 -> 110.76706
B7: 1.2 | C7: Core capital /Total Assets | D7: ≥ 10% | E7: =Financials!C14/Financials!C5 -> 0.18351443 | F7: =Financials!D14/Financials!D5 -> #REF! | G7: =Financials!E14/Financials!E5 -> #REF! | H7: =Financials!F14/Financials!F5 -> #REF! | I7: =Financials!G14/Financials!G5 -> #REF! | J7: =Financials!H14/Financials!H5 -> #REF! | K7: =Financials!I14/Financials!I5 -> #REF! | L7: =Financials!J14/Financials!J5 -> #REF! | ... AK7: =Financials!AI14/Financials!AI5 -> 0.18298427
B8: 1.3 | C8: Core capital /Total Deposits | D8: ≥ 10% | E8: =Financials!C14/Financials!C6 -> 0.23971315 | F8: =Financials!D14/Financials!D6 -> #REF! | G8: =Financials!E14/Financials!E6 -> #REF! | H8: =Financials!F14/Financials!F6 -> #REF! | I8: =Financials!G14/Financials!G6 -> #REF! | J8: =Financials!H14/Financials!H6 -> #REF! | K8: =Financials!I14/Financials!I6 -> #REF! | L8: =Financials!J14/Financials!J6 -> #REF! | ... AK8: =Financials!AI14/Financials!AI6 -> 0.23255829
B9: 1.4 | C9: Share Capital/Total Assets | D9: ≤2% | E9: =Financials!C18/Financials!C5 -> 0.11014337 | F9: =Financials!D18/Financials!D5 -> 0.23514028 | G9: =Financials!E18/Financials!E5 -> 0.21931147 | H9: =Financials!F18/Financials!F5 -> 0.2099177 | I9: =Financials!G18/Financials!G5 -> 0.23720838 | J9: =Financials!H18/Financials!H5 -> 0.22073574 | K9: =Financials!I18/Financials!I5 -> 0.22483873 | L9: =Financials!J18/Financials!J5 -> 0.24465651 | ... AK9: =Financials!AI18/Financials!AI5 -> 0.089128923
B10: 1.5 | C10: Institutional Capital/Total Assets | D10: ≥ 8% | E10: =Financials!C15/Financials!C5 -> 0.073371063 | F10: =Financials!D15/Financials!D5 -> #REF! | G10: =Financials!E15/Financials!E5 -> #REF! | H10: =Financials!F15/Financials!F5 -> #REF! | I10: =Financials!G15/Financials!G5 -> #REF! | J10: =Financials!H15/Financials!H5 -> #REF! | K10: =Financials!I15/Financials!I5 -> #REF! | L10: =Financials!J15/Financials!J5 -> #REF! | ... AK10: =Financials!AI15/Financials!AI5 -> 0.093855346
B12: 2 | C12: ASSET MIX AND QUALITY
B13: 2.1 | C13: Non Earning Assets
B14: 2.1.1 | C14: Non earning Assets/Total assets | D14: ≤ 10% | E14: =Financials!C38/Financials!C5 -> 0.12852222 | F14: =Financials!D38/Financials!D5 -> 10.384985 | G14: =Financials!E38/Financials!E5 -> 9.6357278 | H14: =Financials!F38/Financials!F5 -> 9.6793191 | I14: =Financials!G38/Financials!G5 -> 9.9006137 | J14: =Financials!H38/Financials!H5 -> 10.881615 | K14: =Financials!I38/Financials!I5 -> 10.188674 | L14: =Financials!J38/Financials!J5 -> 10.851818 | ... AK14: =Financials!AI38/Financials!AI5 -> 0.20864098
B15: 2.1.2 | C15: Property and Equipment/Total Assets | D15: ≤ 5% | E15: =Financials!C39/Financials!C5 -> 0.051737546 | F15: =Financials!D39/Financials!D5 -> 0 | G15: =Financials!E39/Financials!E5 -> 0 | H15: =Financials!F39/Financials!F5 -> 0 | I15: =Financials!G39/Financials!G5 -> 0 | J15: =Financials!H39/Financials!H5 -> 0 | K15: =Financials!I39/Financials!I5 -> 0 | L15: =Financials!J39/Financials!J5 -> 0 | ... AK15: =Financials!AI39/Financials!AI5 -> 0.10941436
B16: 2.1.3 | C16: Non Performing loans/Gross Loans | D16: ≤ 6%
B18: 2.2 | C18: Earning Assets
B19: 2.2.1 | C19: Equities & Investments/Deposits | D19: ≤ 5% | E19: =Financials!C26/Financials!C6 -> 0.00029466029 | F19: =Financials!D26/Financials!D6 -> 321254.66 | G19: =Financials!E26/Financials!E6 -> 322432.63 | H19: =Financials!F26/Financials!F6 -> -19.581498 | I19: =Financials!G26/Financials!G6 -> -19.442138 | J19: =Financials!H26/Financials!H6 -> #DIV/0! | K19: =Financials!I26/Financials!I6 -> -5172.7261 | L19: =Financials!J26/Financials!J6 -> -5075.8957 | ... AK19: =Financials!AI26/Financials!AI6 -> 0.00021384929
B20: 2.2.2 | C20: Equities & Investments/Core Capital | D20: ≤ 40% | E20: =Financials!C26/Financials!C14 -> 0.0012292203 | F20: =Financials!D26/Financials!D14 -> #REF! | G20: =Financials!E26/Financials!E14 -> #REF! | H20: =Financials!F26/Financials!F14 -> #REF! | I20: =Financials!G26/Financials!G14 -> #REF! | J20: =Financials!H26/Financials!H14 -> #REF! | K20: =Financials!I26/Financials!I14 -> #REF! | L20: =Financials!J26/Financials!J14 -> #REF! | ... AK20: =Financials!AI26/Financials!AI14 -> 0.00091955136
B21: 2.2.3 | C21: Net Loans & advances /Total assets | D21: NPR | E21: =Financials!C31/Financials!C5 -> 0.69107084 | F21: =Financials!D31/Financials!D5 -> 0.52803041 | G21: =Financials!E31/Financials!E5 -> 0.5035063 | H21: =Financials!F31/Financials!F5 -> 0.49248807 | I21: =Financials!G31/Financials!G5 -> 0.52312284 | J21: =Financials!H31/Financials!H5 -> 0.49704011 | K21: =Financials!I31/Financials!I5 -> 0.51688271 | L21: =Financials!J31/Financials!J5 -> 0.57427201 | ... AK21: =Financials!AI31/Financials!AI5 -> 0.60864165
B23: 3 | C23: FUNDING MIX
B24: 3.1 | C24: Total Deposits/Total Assets | D24: NPR | E24: =Financials!C6/Financials!C5 -> 0.76555846 | F24: =Financials!D6/Financials!D5 -> 2.0320892e-05 | G24: =Financials!E6/Financials!E5 -> 1.8952962e-05 | H24: =Financials!F6/Financials!F5 -> -0.29816243 | I24: =Financials!G6/Financials!G5 -> -0.31016953 | J24: =Financials!H6/Financials!H5 -> 0 | K24: =Financials!I6/Financials!I5 -> -0.0011302723 | L24: =Financials!J6/Financials!J5 -> -0.001285647 | ... AK24: =Financials!AI6/Financials!AI5 -> 0.78683185
B25: 3.1.1 | C25: BOSA Deposits/Total Assets | D25: NPR | E25: =Financials!C7/Financials!C5 -> 0.61077217 | F25: =Financials!D7/Financials!D5 -> -0.00024056007 | G25: =Financials!E7/Financials!E5 -> -0.00019788446 | H25: =Financials!F7/Financials!F5 -> 0.014840195 | I25: =Financials!G7/Financials!G5 -> 0.015450499 | J25: =Financials!H7/Financials!H5 -> -0.0030278266 | K25: =Financials!I7/Financials!I5 -> -0.002984841 | L25: =Financials!J7/Financials!J5 -> -0.0032456664 | ... AK25: =Financials!AI7/Financials!AI5 -> 0.68639561
B26: 3.1.2 | C26: FOSA Deposits/Total Assets | D26: NPR | E26: =Financials!C8/Financials!C5 -> 0.1547863 | F26: =Financials!D8/Financials!D5 -> 6.1771683 | G26: =Financials!E8/Financials!E5 -> 5.8692921 | H26: =Financials!F8/Financials!F5 -> 5.6961449 | I26: =Financials!G8/Financials!G5 -> 5.9791496 | J26: =Financials!H8/Financials!H5 -> 5.6213565 | K26: =Financials!I8/Financials!I5 -> 5.8201966 | L26: =Financials!J8/Financials!J5 -> 6.412814 | ... AK26: =Financials!AI8/Financials!AI5 -> 0.09066444
B27: 3.2 | C27: External Borrowing/Total assets | D27: ≤ 25% | E27: =Financials!C9/Financials!C5 -> 0 | F27: =Financials!D9/Financials!D5 -> 0 | G27: =Financials!E9/Financials!E5 -> 0 | H27: =Financials!F9/Financials!F5 -> 0 | I27: =Financials!G9/Financials!G5 -> 0 | J27: =Financials!H9/Financials!H5 -> 0 | K27: =Financials!I9/Financials!I5 -> 0 | L27: =Financials!J9/Financials!J5 -> 0 | ... AK27: =Financials!AI9/Financials!AI5 -> 0.05092209
B29: 4 | C29: GROWTH RATIOS
B30: 4.1 | C30: Total Assets | D30: NPR | E30: =Financials!C5/Financials!B5-1 -> #VALUE! | F30: =Financials!D5/Financials!C5-1 -> -0.89232186 | G30: =Financials!E5/Financials!D5-1 -> 0.072174986 | H30: =Financials!F5/Financials!E5-1 -> 0.044749802 | I30: =Financials!G5/Financials!F5-1 -> -0.038491617 | J30: =Financials!H5/Financials!G5-1 -> 0.074626111 | K30: =Financials!I5/Financials!H5-1 -> -0.018248613 | L30: =Financials!J5/Financials!I5-1 -> -0.081002464 | ... AK30: =Financials!AI5/Financials!AH5-1 -> 0.0064571113
B31: 4.2 | C31: Total Deposits | D31: NPR | E31: =Financials!C6/Financials!B6-1 -> #VALUE! | F31: =Financials!D6/Financials!C6-1 -> -0.99999714 | G31: =Financials!E6/Financials!D6-1 -> 0 | H31: =Financials!F6/Financials!E6-1 -> -16436.697 | I31: =Financials!G6/Financials!F6-1 -> 0.00022863917 | J31: =Financials!H6/Financials!G6-1 -> -1 | K31: =Financials!I6/Financials!H6-1 -> #DIV/0! | L31: =Financials!J6/Financials!I6-1 -> 0.045328977 | ... AK31: =Financials!AI6/Financials!AH6-1 -> 0.011176951
B32: 4.2.1 | C32: FOSA Deposits | D32: NPR | E32: =Financials!C8/Financials!B8-1 -> #VALUE! | F32: =Financials!D8/Financials!C8-1 -> 3.2971891 | G32: =Financials!E8/Financials!D8-1 -> 0.018736717 | H32: =Financials!F8/Financials!E8-1 -> 0.013929132 | I32: =Financials!G8/Financials!F8-1 -> 0.0092795398 | J32: =Financials!H8/Financials!G8-1 -> 0.010320342 | K32: =Financials!I8/Financials!H8-1 -> 0.016478149 | L32: =Financials!J8/Financials!I8-1 -> 0.01257066 | ... AK32: =Financials!AI8/Financials!AH8-1 -> -0.00066380237
B33: 4.2.2 | C33: BOSA Deposits | D33: NPR | E33: =Financials!C7/Financials!B7-1 -> #VALUE! | F33: =Financials!D7/Financials!C7-1 -> -1.0000424 | G33: =Financials!E7/Financials!D7-1 -> -0.11802999 | H33: =Financials!F7/Financials!E7-1 -> -79.35022 | I33: =Financials!G7/Financials!F7-1 -> 0.0010504884 | J33: =Financials!H7/Financials!G7-1 -> -1.2105939 | K33: =Financials!I7/Financials!H7-1 -> -0.032186409 | L33: =Financials!J7/Financials!I7-1 -> -0.00069738483 | ... AK33: =Financials!AI7/Financials!AH7-1 -> 0.0079402142
B34: 4.3 | C34: Net Loans & advances | D34: NPR | E34: =Financials!C31/Financials!B31-1 -> #VALUE! | F34: =Financials!D31/Financials!C31-1 -> -0.91772576 | G34: =Financials!E31/Financials!D31-1 -> 0.022378353 | H34: =Financials!F31/Financials!E31-1 -> 0.021887546 | I34: =Financials!G31/Financials!F31-1 -> 0.021318139 | J34: =Financials!H31/Financials!G31-1 -> 0.021045611 | K34: =Financials!I31/Financials!H31-1 -> 0.020944393 | L34: =Financials!J31/Financials!I31-1 -> 0.021033509 | ... AK34: =Financials!AI31/Financials!AH31-1 -> -0.0052444762
B35: 4.4 | C35: Core capital | D35: NPR | E35: =Financials!C14/Financials!B14-1 -> #VALUE! | F35: =Financials!D14/Financials!C14-1 -> #REF! | G35: =Financials!E14/Financials!D14-1 -> #REF! | H35: =Financials!F14/Financials!E14-1 -> #REF! | I35: =Financials!G14/Financials!F14-1 -> #REF! | J35: =Financials!H14/Financials!G14-1 -> #REF! | K35: =Financials!I14/Financials!H14-1 -> #REF! | L35: =Financials!J14/Financials!I14-1 -> #REF! | ... AK35: =Financials!AI14/Financials!AH14-1 -> 0.015820469
B36: 4.5 | C36: Total Gross Income | D36: NPR | E36: =Financials!C41/Financials!B41-1 -> #VALUE! | F36: =Financials!D41/Financials!C41-1 -> #REF! | G36: =Financials!E41/Financials!D41-1 -> #REF! | H36: =Financials!F41/Financials!E41-1 -> #REF! | I36: =Financials!G41/Financials!F41-1 -> #REF! | J36: =Financials!H41/Financials!G41-1 -> #REF! | K36: =Financials!I41/Financials!H41-1 -> #REF! | L36: =Financials!J41/Financials!I41-1 -> #REF! | ... AK36: =Financials!AI41/Financials!AH41-1 -> 0
B37: 4.6 | C37: Membership | D37: NPR
B39: 5 | C39: Efficiency Ratios
B40: 5.1 | C40: FinCost-Deposits/Average Deposits | D40: NPR | E40: =Financials!C48/((Financials!C6+Financials!B6)/2) -> #VALUE! | F40: =Financials!D48/((Financials!D6+Financials!C6)/2) -> 0 | G40: =Financials!E48/((Financials!E6+Financials!D6)/2) -> 0 | H40: =Financials!F48/((Financials!F6+Financials!E6)/2) -> 0 | I40: =Financials!G48/((Financials!G6+Financials!F6)/2) -> 0 | J40: =Financials!H48/((Financials!H6+Financials!G6)/2) -> 0 | K40: =Financials!I48/((Financials!I6+Financials!H6)/2) -> 0 | L40: =Financials!J48/((Financials!J6+Financials!I6)/2) -> 0 | ... AK40: =Financials!AI48/((Financials!AI6+Financials!AH6)/2) -> 5.9409834e-06
B41: 5.2 | C41: FinCost-Shares/Average Share capital | D41: NPR | E41: =Financials!C49/((Financials!C18+Financials!B18)/2) -> #VALUE! | F41: =Financials!D49/((Financials!D18+Financials!C18)/2) -> 0 | G41: =Financials!E49/((Financials!E18+Financials!D18)/2) -> 0 | H41: =Financials!F49/((Financials!F18+Financials!E18)/2) -> 0 | I41: =Financials!G49/((Financials!G18+Financials!F18)/2) -> 0 | J41: =Financials!H49/((Financials!H18+Financials!G18)/2) -> 0 | K41: =Financials!I49/((Financials!I18+Financials!H18)/2) -> 0 | L41: =Financials!J49/((Financials!J18+Financials!I18)/2) -> 0 | ... AK41: =Financials!AI49/((Financials!AI18+Financials!AH18)/2) -> 0
B42: 5.3 | C42: FinCost-Ext Loans/Average Ext Loans | D42: NPR | E42: =Financials!C50/((Financials!C9+Financials!B9)/2) -> #VALUE! | F42: =Financials!D50/((Financials!D9+Financials!C9)/2) -> #DIV/0! | G42: =Financials!E50/((Financials!E9+Financials!D9)/2) -> #DIV/0! | H42: =Financials!F50/((Financials!F9+Financials!E9)/2) -> #DIV/0! | I42: =Financials!G50/((Financials!G9+Financials!F9)/2) -> #DIV/0! | J42: =Financials!H50/((Financials!H9+Financials!G9)/2) -> #DIV/0! | K42: =Financials!I50/((Financials!I9+Financials!H9)/2) -> #DIV/0! | L42: =Financials!J50/((Financials!J9+Financials!I9)/2) -> #DIV/0! | ... AK42: =Financials!AI50/((Financials!AI9+Financials!AH9)/2) -> 0.041897038
B43: 5.4 | C43: OpEx/Average Total Assets | D43: NPR | E43: =(Financials!C52+Financials!C53)/((Financials!C5+Financials!B5)/2) -> #VALUE! | F43: =(Financials!D52+Financials!D53)/((Financials!D5+Financials!C5)/2) -> 0 | G43: =(Financials!E52+Financials!E53)/((Financials!E5+Financials!D5)/2) -> 0 | H43: =(Financials!F52+Financials!F53)/((Financials!F5+Financials!E5)/2) -> 0 | I43: =(Financials!G52+Financials!G53)/((Financials!G5+Financials!F5)/2) -> 0 | J43: =(Financials!H52+Financials!H53)/((Financials!H5+Financials!G5)/2) -> 0 | K43: =(Financials!I52+Financials!I53)/((Financials!I5+Financials!H5)/2) -> 0 | L43: =(Financials!J52+Financials!J53)/((Financials!J5+Financials!I5)/2) -> 0 | ... AK43: =(Financials!AI52+Financials!AI53)/((Financials!AI5+Financials!AH5)/2) -> 0.023646161
B44: 5.5 | C44: Avge yield on Net loans | D44: NPR | E44: =Financials!C42/((Financials!C31+Financials!B31)/2) -> #VALUE! | F44: =Financials!D42/((Financials!D31+Financials!C31)/2) -> #REF! | G44: =Financials!E42/((Financials!E31+Financials!D31)/2) -> #REF! | H44: =Financials!F42/((Financials!F31+Financials!E31)/2) -> #REF! | I44: =Financials!G42/((Financials!G31+Financials!F31)/2) -> #REF! | J44: =Financials!H42/((Financials!H31+Financials!G31)/2) -> #REF! | K44: =Financials!I42/((Financials!I31+Financials!H31)/2) -> #REF! | L44: =Financials!J42/((Financials!J31+Financials!I31)/2) -> #REF! | ... AK44: =Financials!AI42/((Financials!AI31+Financials!AH31)/2) -> 0.03832879
B46: 6 | C46: Liquidity Ratio
B47: 6.1 | C47: minimum Liquidity | D47: 0.15 | E47: =(SFP!B4+SFP!B11)/(SFP!B31+SFP!B34+SFP!B35+SFP!B36+SFP!B37+SFP!B38) -> 0.27500842 | F47: =(SFP!C4+SFP!C11)/(SFP!C34+SFP!C37+SFP!C38+SFP!C39+SFP!C40+SFP!C42) -> 0.17418078 | G47: =(SFP!D4+SFP!D11)/(SFP!D34+SFP!D37+SFP!D38+SFP!D39+SFP!D40+SFP!D42) -> 0.22560135 | H47: =(SFP!E4+SFP!E11)/(SFP!E34+SFP!E37+SFP!E38+SFP!E39+SFP!E40+SFP!E42) -> 0.14290454 | I47: =(SFP!F4+SFP!F11)/(SFP!F34+SFP!F37+SFP!F38+SFP!F39+SFP!F40+SFP!F42) -> 0.15814051 | J47: =(SFP!G4+SFP!G11)/(SFP!G34+SFP!G37+SFP!G38+SFP!G39+SFP!G40+SFP!G42) -> 0.15150019 | K47: =(SFP!H4+SFP!H11)/(SFP!H34+SFP!H37+SFP!H38+SFP!H39+SFP!H40+SFP!H42) -> 0.13049517 | L47: =(SFP!I4+SFP!I11)/(SFP!I34+SFP!I37+SFP!I38+SFP!I39+SFP!I40+SFP!I42) -> 0.14078519 | M47: =(SFP!J4+SFP!J11)/(SFP!J34+SFP!J37+SFP!J38+SFP!J39+SFP!J40+SFP!J42) -> 0.14569566 | ... Q47: =(SFP!N4+SFP!N11)/(SFP!N34+SFP!N37+SFP!N38+SFP!N39+SFP!N40+SFP!N42) -> #VALUE! | R47: =(SFP!O4+SFP!O11)/(SFP!O31+SFP!O34+SFP!O35+SFP!O36+SFP!O37+SFP!O38) -> 0.26414536 | S47: =(SFP!P4+SFP!P11)/(SFP!P31+SFP!P34+SFP!P35+SFP!P36+SFP!P37+SFP!P38) -> 0.24603496 | T47: =(SFP!Q4+SFP!Q11)/(SFP!Q31+SFP!Q34+SFP!Q35+SFP!Q36+SFP!Q37+SFP!Q38) -> 0.26302353 | U47: =(SFP!R4+SFP!R11)/(SFP!R31+SFP!R34+SFP!R35+SFP!R36+SFP!R37+SFP!R38) -> 0.23782716 | V47: =(SFP!S4+SFP!S11)/(SFP!S31+SFP!S34+SFP!S35+SFP!S36+SFP!S37+SFP!S38) -> 0.20603022 | W47: =(SFP!T4+SFP!T11)/(SFP!T31+SFP!T34+SFP!T35+SFP!T36+SFP!T37+SFP!T38) -> 0.19224947 | X47: =(SFP!U4+SFP!U11)/(SFP!U31+SFP!U34+SFP!U35+SFP!U36+SFP!U37+SFP!U38) -> 0.24560449 | Y47: =(SFP!V4+SFP!V11)/(SFP!V31+SFP!V34+SFP!V35+SFP!V36+SFP!V37+SFP!V38) -> 0.21240258 | ... AK47: =(SFP!AH4+SFP!AH11)/(SFP!AH31+SFP!AH34+SFP!AH35+SFP!AH36+SFP!AH37+SFP!AH38) -> 0.27423882
C48: TECHNICAL Liquidity | E48: =(SFP!B4+SFP!B11)/(SFP!B32+SFP!B34+SFP!B35+SFP!B36+SFP!B37+SFP!B38) -> 0.22245404 | F48: =(SFP!C4+SFP!C11)/(SFP!C35+SFP!C37+SFP!C38+SFP!C39+SFP!C40+SFP!C42) -> 0.17417498 | G48: =(SFP!D4+SFP!D11)/(SFP!D35+SFP!D37+SFP!D38+SFP!D39+SFP!D40+SFP!D42) -> 0.22559478 | H48: =(SFP!E4+SFP!E11)/(SFP!E35+SFP!E37+SFP!E38+SFP!E39+SFP!E40+SFP!E42) -> 0.14954785 | I48: =(SFP!F4+SFP!F11)/(SFP!F35+SFP!F37+SFP!F38+SFP!F39+SFP!F40+SFP!F42) -> 0.16459833 | J48: =(SFP!G4+SFP!G11)/(SFP!G35+SFP!G37+SFP!G38+SFP!G39+SFP!G40+SFP!G42) -> 0.15143913 | K48: =(SFP!H4+SFP!H11)/(SFP!H35+SFP!H37+SFP!H38+SFP!H39+SFP!H40+SFP!H42) -> 0.13046479 | L48: =(SFP!I4+SFP!I11)/(SFP!I35+SFP!I37+SFP!I38+SFP!I39+SFP!I40+SFP!I42) -> 0.14075303 | M48: =(SFP!J4+SFP!J11)/(SFP!J35+SFP!J37+SFP!J38+SFP!J39+SFP!J40+SFP!J42) -> 0.14566325 | ... Q48: =(SFP!N4+SFP!N11)/(SFP!N35+SFP!N37+SFP!N38+SFP!N39+SFP!N40+SFP!N42) -> #VALUE! | R48: =(SFP!O4+SFP!O11)/(SFP!O32+SFP!O34+SFP!O35+SFP!O36+SFP!O37+SFP!O38) -> 0.21452089 | S48: =(SFP!P4+SFP!P11)/(SFP!P32+SFP!P34+SFP!P35+SFP!P36+SFP!P37+SFP!P38) -> 0.20990175 | T48: =(SFP!Q4+SFP!Q11)/(SFP!Q32+SFP!Q34+SFP!Q35+SFP!Q36+SFP!Q37+SFP!Q38) -> 0.22519501 | U48: =(SFP!R4+SFP!R11)/(SFP!R32+SFP!R34+SFP!R35+SFP!R36+SFP!R37+SFP!R38) -> 0.20035691 | V48: =(SFP!S4+SFP!S11)/(SFP!S32+SFP!S34+SFP!S35+SFP!S36+SFP!S37+SFP!S38) -> 0.17766409 | W48: =(SFP!T4+SFP!T11)/(SFP!T32+SFP!T34+SFP!T35+SFP!T36+SFP!T37+SFP!T38) -> 0.16744604 | X48: =(SFP!U4+SFP!U11)/(SFP!U32+SFP!U34+SFP!U35+SFP!U36+SFP!U37+SFP!U38) -> 0.21296704 | Y48: =(SFP!V4+SFP!V11)/(SFP!V32+SFP!V34+SFP!V35+SFP!V36+SFP!V37+SFP!V38) -> 0.18610578 | ... AK48: =(SFP!AH4+SFP!AH11)/(SFP!AH32+SFP!AH34+SFP!AH35+SFP!AH36+SFP!AH37+SFP!AH38) -> 0.23828562
B49: 7 | C49: Loan Loss Provisions Ratios
B50: 7.1 | C50: Actual LLP / Required LLP | D50: 1
B51: 7.2 | C51: allowance for loan loss/NPL
C52: Loan interest/Net Loans | E52: =SCI!B5/SFP!B14 -> 0.16502879 | F52: =SCI!C5/SFP!C15 -> 0 | G52: =SCI!D5/SFP!D15 -> 0 | H52: =SCI!E5/SFP!E15 -> 0 | I52: =SCI!F5/SFP!F15 -> 0 | J52: =SCI!G5/SFP!G15 -> 0 | K52: =SCI!H5/SFP!H15 -> 0 | L52: =SCI!I5/SFP!I15 -> 0 | M52: =SCI!J5/SFP!J15 -> 0 | ... Q52: =SCI!N5/SFP!N15 -> #VALUE! | R52: =SCI!O5/SFP!O14 -> 0.16916869 | S52: =SCI!P5/SFP!P14 -> 0.011461238 | T52: =SCI!Q5/SFP!Q14 -> 0.02316739 | U52: =SCI!R5/SFP!R14 -> 0.036441116 | V52: =SCI!S5/SFP!S14 -> 0.048553343 | W52: =SCI!T5/SFP!T14 -> 0.060777929 | X52: =SCI!U5/SFP!U14 -> 0.073149818 | Y52: =SCI!V5/SFP!V14 -> 0.084326658 | ... AK52: =SCI!AH5/SFP!AH14 -> 0.078231642
C53: Gross loans/Total assets | E53: =Financials!C32/Financials!C5 -> 0.74666222 | F53: =Financials!D32/Financials!D5 -> 0.52803041 | G53: =Financials!E32/Financials!E5 -> 0.5035063 | H53: =Financials!F32/Financials!F5 -> 0.49248807 | I53: =Financials!G32/Financials!G5 -> 0.52312284 | J53: =Financials!H32/Financials!H5 -> 0.49704011 | K53: =Financials!I32/Financials!I5 -> 0.51688271 | L53: =Financials!J32/Financials!J5 -> 0.57427201 | ... AK53: =Financials!AI32/Financials!AI5 -> 0.68135162
B54: 8 | C54: Earnings
B55: 8.1 | C55: ROA | E55: =SCI!B33/(SFP!A27+SFP!B27/2) -> #VALUE! | F55: =SCI!C33/(SFP!B27+SFP!C29/2) -> 0 | G55: =SCI!D33/(SFP!C29+SFP!D29/2) -> 0 | H55: =SCI!E33/(SFP!D29+SFP!E29/2) -> 0 | I55: =SCI!F33/(SFP!E29+SFP!F29/2) -> 0 | J55: =SCI!G33/(SFP!F29+SFP!G29/2) -> 0 | K55: =SCI!H33/(SFP!G29+SFP!H29/2) -> 0 | L55: =SCI!I33/(SFP!H29+SFP!I29/2) -> 0 | M55: =SCI!J33/(SFP!I29+SFP!J29/2) -> 0 | N55: =SCI!K33/(SFP!J29+SFP!K29/2) -> 0 | ... Q55: =SCI!N33/(SFP!M29+SFP!N29/2) -> 0 | R55: =SCI!O33/(SFP!N29+SFP!O27/2) -> 0.030572563 | S55: =SCI!P33/(SFP!O29+SFP!P27/2) -> 0.0024008826 | T55: =SCI!Q33/(SFP!P29+SFP!Q27/2) -> 0.0069593069 | U55: =SCI!R33/(SFP!Q29+SFP!R27/2) -> 0.016130942 | V55: =SCI!S33/(SFP!R29+SFP!S27/2) -> 0.02139444 | W55: =SCI!T33/(SFP!S29+SFP!T27/2) -> 0.033701331 | X55: =SCI!U33/(SFP!T29+SFP!U27/2) -> 0.038534836 | Y55: =SCI!V33/(SFP!U29+SFP!V27/2) -> 0.044919156 | ... AK55: =SCI!AH33/(SFP!AG29+SFP!AH27/2) -> 0.041423167
B56: 8.2 | C56: Cost Income Ratio | E56: =SCI!B23/SCI!B19 -> 0.72533782 | F56: =SCI!C23/SCI!C19 -> #DIV/0! | G56: =SCI!D23/SCI!D19 -> #DIV/0! | H56: =SCI!E23/SCI!E19 -> #DIV/0! | I56: =SCI!F23/SCI!F19 -> #DIV/0! | J56: =SCI!G23/SCI!G19 -> #DIV/0! | K56: =SCI!H23/SCI!H19 -> #DIV/0! | L56: =SCI!I23/SCI!I19 -> #DIV/0! | ... AK56: =SCI!AH23/SCI!AH19 -> 0.62975189
B57: 8.3 | C57: Operating Expense Ratio | E57: =SCI!B23/SFP!B27 -> 0.087127255 | F57: =SCI!C23/SFP!C29 -> 0 | G57: =SCI!D23/SFP!D29 -> 0 | H57: =SCI!E23/SFP!E29 -> 0 | I57: =SCI!F23/SFP!F29 -> 0 | J57: =SCI!G23/SFP!G29 -> 0 | K57: =SCI!H23/SFP!H29 -> 0 | L57: =SCI!I23/SFP!I29 -> 0 | M57: =SCI!J23/SFP!J29 -> 0 | ... Q57: =SCI!N23/SFP!N29 -> 0 | R57: =SCI!O23/SFP!O27 -> 0.082844321 | S57: =SCI!P23/SFP!P27 -> 0.0089971491 | T57: =SCI!Q23/SFP!Q27 -> 0.016503258 | U57: =SCI!R23/SFP!R27 -> 0.028042619 | V57: =SCI!S23/SFP!S27 -> 0.037161932 | W57: =SCI!T23/SFP!T27 -> 0.044121975 | X57: =SCI!U23/SFP!U27 -> 0.049321328 | Y57: =SCI!V23/SFP!V27 -> 0.057208419 | ... AK57: =SCI!AH23/SFP!AH27 -> 0.053021788
C58: Liquid assets/total assets | E58: =(Financials!C36+Financials!C29)/Financials!C5 -> 0.18018136 | F58: =(Financials!D36+Financials!D29)/Financials!D5 -> 1.3642637 | G58: =(Financials!E36+Financials!E29)/Financials!E5 -> 1.6785874 | H58: =(Financials!F36+Financials!F29)/Financials!F5 -> 1.0069073 | I58: =(Financials!G36+Financials!G29)/Financials!G5 -> 1.3124841 | J58: =(Financials!H36+Financials!H29)/Financials!H5 -> 1.1376105 | K58: =(Financials!I36+Financials!I29)/Financials!I5 -> 1.0389821 | L58: =(Financials!J36+Financials!J29)/Financials!J5 -> 1.2075787 | ... AK58: =(Financials!AI36+Financials!AI29)/Financials!AI5 -> 0.1825491
B76: 0

Sheet CAELS
B1: SIRAJI SACCO
B2: FINANCIAL SOUNDNESS INDICATORS | C2: Prude. Std | D2: AUDITED 2013 | E2: AUDITED 2014 | F2: AUDITED 2015 | G2: AUDITED 2016 | H2: AUDITED 2017 | I2: 43101 | J2: 43132 | K2: 43160 | L2: 43191 | M2: 43221 | N2: 43252 | O2: 43282 | P2: 43313 | Q2: 43344 | R2: 43374 | S2: 43405 | T2: 43435 | U2: AUDITED 2018 | V2: 43466 | W2: 43497 | X2: 43525 | Y2: 43556 | Z2: 43586 | AA2: 43617 | AB2: 43647 | AC2: 43678 | AD2: 43709 | AE2: 43739 | AF2: 43770 | AG2: 43800 | AH2: AUDITED 2019 | AI2: 43831 | AJ2: 43862 | AK2: 43891 | AL2: 43922 | AM2: 43952 | AN2: 43983 | AO2: 44013 | AP2: 44044 | AQ2: 44075 | AR2: 44105 | AS2: 44136 | AT2: 44166 | AU2: Audited 2020 | AV2: 44197 | AW2: 44228 | AX2: 44256 | AY2: 44287 | AZ2: 44317 | BA2: 44348 | BB2: 44378 | BC2: 44409 | BD2: 44440 | BE2: 44470 | BF2: 44501 | BG2: 44531 | BH2: Audited 2021 | BI2: 44562 | BJ2: 44593 | BK2: 44621 | BL2: 44652 | BM2: 44682 | BN2: 44713 | BO2: 44743 | BP2: 44774 | BQ2: 44805 | BR2: 44835 | BS2: 44866 | BT2: 44896 | BU2: Audited-2022 | BV2: 44949 | BW2: 44980 | BX2: 45008 | BY2: 45039 | BZ2: 45069 | CA2: 45100
B3: CAPITAL
B4: CORE CAPITAL | C4: ≥ Ksh.10M | D4: ='Prudential Ratios'!#REF! -> #REF! | E4: ='Prudential Ratios'!#REF! -> #REF! | F4: ='Prudential Ratios'!#REF! -> #REF! | G4: ='Prudential Ratios'!#REF! -> #REF! | H4: ='Prudential Ratios'!#REF! -> #REF! | I4: ='Prudential Ratios'!#REF! -> #REF! | J4: ='Prudential Ratios'!#REF! -> #REF! | K4: ='Prudential Ratios'!#REF! -> #REF! | ... AT4: ='Prudential Ratios'!#REF! -> #REF! | AU4: ='Prudential Ratios'!E6 -> 82.86228 | AV4: ='Prudential Ratios'!F6 -> #REF! | AW4: ='Prudential Ratios'!G6 -> #REF! | AX4: ='Prudential Ratios'!H6 -> #REF! | AY4: ='Prudential Ratios'!I6 -> #REF! | AZ4: ='Prudential Ratios'!J6 -> #REF! | BA4: ='Prudential Ratios'!K6 -> #REF! | BB4: ='Prudential Ratios'!L6 -> #REF! | ... CA4: ='Prudential Ratios'!AK6 -> 110.76706
B5: CCA | C5: ≥ 10% | D5: ='Prudential Ratios'!#REF! -> #REF! | E5: ='Prudential Ratios'!#REF! -> #REF! | F5: ='Prudential Ratios'!#REF! -> #REF! | G5: ='Prudential Ratios'!#REF! -> #REF! | H5: ='Prudential Ratios'!#REF! -> #REF! | I5: ='Prudential Ratios'!#REF! -> #REF! | J5: ='Prudential Ratios'!#REF! -> #REF! | K5: ='Prudential Ratios'!#REF! -> #REF! | ... AT5: ='Prudential Ratios'!#REF! -> #REF! | AU5: ='Prudential Ratios'!E7 -> 0.18351443 | AV5: ='Prudential Ratios'!F7 -> #REF! | AW5: ='Prudential Ratios'!G7 -> #REF! | AX5: ='Prudential Ratios'!H7 -> #REF! | AY5: ='Prudential Ratios'!I7 -> #REF! | AZ5: ='Prudential Ratios'!J7 -> #REF! | BA5: ='Prudential Ratios'!K7 -> #REF! | BB5: ='Prudential Ratios'!L7 -> #REF! | ... CA5: ='Prudential Ratios'!AK7 -> 0.18298427
B6: ICA | C6: ≥ 8% | D6: ='Prudential Ratios'!#REF! -> #REF! | E6: ='Prudential Ratios'!#REF! -> #REF! | F6: ='Prudential Ratios'!#REF! -> #REF! | G6: ='Prudential Ratios'!#REF! -> #REF! | H6: ='Prudential Ratios'!#REF! -> #REF! | I6: ='Prudential Ratios'!#REF! -> #REF! | J6: ='Prudential Ratios'!#REF! -> #REF! | K6: ='Prudential Ratios'!#REF! -> #REF! | ... AT6: ='Prudential Ratios'!#REF! -> #REF! | AU6: ='Prudential Ratios'!E10 -> 0.073371063 | AV6: ='Prudential Ratios'!F10 -> #REF! | AW6: ='Prudential Ratios'!G10 -> #REF! | AX6: ='Prudential Ratios'!H10 -> #REF! | AY6: ='Prudential Ratios'!I10 -> #REF! | AZ6: ='Prudential Ratios'!J10 -> #REF! | BA6: ='Prudential Ratios'!K10 -> #REF! | BB6: ='Prudential Ratios'!L10 -> #REF! | ... CA6: ='Prudential Ratios'!AK10 -> 0.093855346
B7: CCD | C7: ≥ 8% | D7: ='Prudential Ratios'!#REF! -> #REF! | E7: ='Prudential Ratios'!#REF! -> #REF! | F7: ='Prudential Ratios'!#REF! -> #REF! | G7: ='Prudential Ratios'!#REF! -> #REF! | H7: ='Prudential Ratios'!#REF! -> #REF! | I7: ='Prudential Ratios'!#REF! -> #REF! | J7: ='Prudential Ratios'!#REF! -> #REF! | K7: ='Prudential Ratios'!#REF! -> #REF! | ... AT7: ='Prudential Ratios'!#REF! -> #REF! | AU7: ='Prudential Ratios'!E8 -> 0.23971315 | AV7: ='Prudential Ratios'!F8 -> #REF! | AW7: ='Prudential Ratios'!G8 -> #REF! | AX7: ='Prudential Ratios'!H8 -> #REF! | AY7: ='Prudential Ratios'!I8 -> #REF! | AZ7: ='Prudential Ratios'!J8 -> #REF! | BA7: ='Prudential Ratios'!K8 -> #REF! | BB7: ='Prudential Ratios'!L8 -> #REF! | ... CA7: ='Prudential Ratios'!AK8 -> 0.23255829
B8: Asset Quality
B9: NPL | C9: ≤ 6% | Q9: =form4!#REF! -> #REF!
B10: Earnings
B11: ROA | D11: ='Prudential Ratios'!#REF! -> #REF! | E11: ='Prudential Ratios'!#REF! -> #REF! | F11: ='Prudential Ratios'!#REF! -> #REF! | G11: ='Prudential Ratios'!#REF! -> #REF! | H11: ='Prudential Ratios'!#REF! -> #REF! | I11: ='Prudential Ratios'!#REF! -> #REF! | J11: ='Prudential Ratios'!#REF! -> #REF! | K11: ='Prudential Ratios'!#REF! -> #REF! | ... AT11: ='Prudential Ratios'!#REF! -> #REF! | AU11: ='Prudential Ratios'!E55 -> #VALUE! | AV11: ='Prudential Ratios'!F55 -> 0 | AW11: ='Prudential Ratios'!G55 -> 0 | AX11: ='Prudential Ratios'!H55 -> 0 | AY11: ='Prudential Ratios'!I55 -> 0 | AZ11: ='Prudential Ratios'!J55 -> 0 | BA11: ='Prudential Ratios'!K55 -> 0 | BB11: ='Prudential Ratios'!L55 -> 0 | ... CA11: ='Prudential Ratios'!AK55 -> 0.041423167
B12: CIR | D12: ='Prudential Ratios'!#REF! -> #REF! | E12: ='Prudential Ratios'!#REF! -> #REF! | F12: ='Prudential Ratios'!#REF! -> #REF! | G12: ='Prudential Ratios'!#REF! -> #REF! | H12: ='Prudential Ratios'!#REF! -> #REF! | I12: ='Prudential Ratios'!#REF! -> #REF! | J12: ='Prudential Ratios'!#REF! -> #REF! | K12: ='Prudential Ratios'!#REF! -> #REF! | ... AT12: ='Prudential Ratios'!#REF! -> #REF! | AU12: ='Prudential Ratios'!E56 -> 0.72533782 | AV12: ='Prudential Ratios'!F56 -> #DIV/0! | AW12: ='Prudential Ratios'!G56 -> #DIV/0! | AX12: ='Prudential Ratios'!H56 -> #DIV/0! | AY12: ='Prudential Ratios'!I56 -> #DIV/0! | AZ12: ='Prudential Ratios'!J56 -> #DIV/0! | BA12: ='Prudential Ratios'!K56 -> #DIV/0! | BB12: ='Prudential Ratios'!L56 -> #DIV/0! | ... CA12: ='Prudential Ratios'!AK56 -> 0.62975189
B13: OER | D13: ='Prudential Ratios'!#REF! -> #REF! | E13: ='Prudential Ratios'!#REF! -> #REF! | F13: ='Prudential Ratios'!#REF! -> #REF! | G13: ='Prudential Ratios'!#REF! -> #REF! | H13: ='Prudential Ratios'!#REF! -> #REF! | I13: ='Prudential Ratios'!#REF! -> #REF! | J13: ='Prudential Ratios'!#REF! -> #REF! | K13: ='Prudential Ratios'!#REF! -> #REF! | ... AT13: ='Prudential Ratios'!#REF! -> #REF! | AU13: ='Prudential Ratios'!E57 -> 0.087127255 | AV13: ='Prudential Ratios'!F57 -> 0 | AW13: ='Prudential Ratios'!G57 -> 0 | AX13: ='Prudential Ratios'!H57 -> 0 | AY13: ='Prudential Ratios'!I57 -> 0 | AZ13: ='Prudential Ratios'!J57 -> 0 | BA13: ='Prudential Ratios'!K57 -> 0 | BB13: ='Prudential Ratios'!L57 -> 0 | ... CA13: ='Prudential Ratios'!AK57 -> 0.053021788
B14: LIQUIDITY
B15: MIN LIQ | C15: 0.15 | D15: ='Prudential Ratios'!#REF! -> #REF! | E15: ='Prudential Ratios'!#REF! -> #REF! | F15: ='Prudential Ratios'!#REF! -> #REF! | G15: ='Prudential Ratios'!#REF! -> #REF! | H15: ='Prudential Ratios'!#REF! -> #REF! | I15: ='Prudential Ratios'!#REF! -> #REF! | J15: ='Prudential Ratios'!#REF! -> #REF! | K15: ='Prudential Ratios'!#REF! -> #REF! | ... AT15: ='Prudential Ratios'!#REF! -> #REF! | AU15: ='Prudential Ratios'!E47 -> 0.27500842 | AV15: ='Prudential Ratios'!F47 -> 0.17418078 | AW15: ='Prudential Ratios'!G47 -> 0.22560135 | AX15: ='Prudential Ratios'!H47 -> 0.14290454 | AY15: ='Prudential Ratios'!I47 -> 0.15814051 | AZ15: ='Prudential Ratios'!J47 -> 0.15150019 | BA15: ='Prudential Ratios'!K47 -> 0.13049517 | BB15: ='Prudential Ratios'!L47 -> 0.14078519 | ... CA15: ='Prudential Ratios'!AK47 -> 0.27423882
B16: TEC LIQ | D16: ='Prudential Ratios'!#REF! -> #REF! | E16: ='Prudential Ratios'!#REF! -> #REF! | F16: ='Prudential Ratios'!#REF! -> #REF! | G16: ='Prudential Ratios'!#REF! -> #REF! | H16: ='Prudential Ratios'!#REF! -> #REF! | I16: ='Prudential Ratios'!#REF! -> #REF! | J16: ='Prudential Ratios'!#REF! -> #REF! | K16: ='Prudential Ratios'!#REF! -> #REF! | ... AT16: ='Prudential Ratios'!#REF! -> #REF! | AU16: ='Prudential Ratios'!E48 -> 0.22245404 | AV16: ='Prudential Ratios'!F48 -> 0.17417498 | AW16: ='Prudential Ratios'!G48 -> 0.22559478 | AX16: ='Prudential Ratios'!H48 -> 0.14954785 | AY16: ='Prudential Ratios'!I48 -> 0.16459833 | AZ16: ='Prudential Ratios'!J48 -> 0.15143913 | BA16: ='Prudential Ratios'!K48 -> 0.13046479 | BB16: ='Prudential Ratios'!L48 -> 0.14075303 | ... CA16: ='Prudential Ratios'!AK48 -> 0.23828562
B17: EB | C17: ≤ 25% | D17: ='Prudential Ratios'!#REF! -> #REF! | E17: ='Prudential Ratios'!#REF! -> #REF! | F17: ='Prudential Ratios'!#REF! -> #REF! | G17: ='Prudential Ratios'!#REF! -> #REF! | H17: ='Prudential Ratios'!#REF! -> #REF! | I17: ='Prudential Ratios'!#REF! -> #REF! | J17: ='Prudential Ratios'!#REF! -> #REF! | K17: ='Prudential Ratios'!#REF! -> #REF! | ... AT17: ='Prudential Ratios'!#REF! -> #REF! | AU17: ='Prudential Ratios'!E27 -> 0 | AV17: ='Prudential Ratios'!F27 -> 0 | AW17: ='Prudential Ratios'!G27 -> 0 | AX17: ='Prudential Ratios'!H27 -> 0 | AY17: ='Prudential Ratios'!I27 -> 0 | AZ17: ='Prudential Ratios'!J27 -> 0 | BA17: ='Prudential Ratios'!K27 -> 0 | BB17: ='Prudential Ratios'!L27 -> 0 | ... CA17: ='Prudential Ratios'!AK27 -> 0.05092209
B18: LIQ/TA | D18: ='Prudential Ratios'!#REF! -> #REF! | E18: ='Prudential Ratios'!#REF! -> #REF! | F18: ='Prudential Ratios'!#REF! -> #REF! | G18: ='Prudential Ratios'!#REF! -> #REF! | H18: ='Prudential Ratios'!#REF! -> #REF! | I18: ='Prudential Ratios'!#REF! -> #REF! | J18: ='Prudential Ratios'!#REF! -> #REF! | K18: ='Prudential Ratios'!#REF! -> #REF! | ... AT18: ='Prudential Ratios'!#REF! -> #REF! | AU18: ='Prudential Ratios'!E58 -> 0.18018136 | AV18: ='Prudential Ratios'!F58 -> 1.3642637 | AW18: ='Prudential Ratios'!G58 -> 1.6785874 | AX18: ='Prudential Ratios'!H58 -> 1.0069073 | AY18: ='Prudential Ratios'!I58 -> 1.3124841 | AZ18: ='Prudential Ratios'!J58 -> 1.1376105 | BA18: ='Prudential Ratios'!K58 -> 1.0389821 | BB18: ='Prudential Ratios'!L58 -> 1.2075787 | ... CA18: ='Prudential Ratios'!AK58 -> 0.1825491
B19: STRUCTURE
B20: NEA | C20: ≤ 10% | D20: ='Prudential Ratios'!#REF! -> #REF! | E20: ='Prudential Ratios'!#REF! -> #REF! | F20: ='Prudential Ratios'!#REF! -> #REF! | G20: ='Prudential Ratios'!#REF! -> #REF! | H20: ='Prudential Ratios'!#REF! -> #REF! | I20: ='Prudential Ratios'!#REF! -> #REF! | J20: ='Prudential Ratios'!#REF! -> #REF! | K20: ='Prudential Ratios'!#REF! -> #REF! | ... AT20: ='Prudential Ratios'!#REF! -> #REF! | AU20: ='Prudential Ratios'!E14 -> 0.12852222 | AV20: ='Prudential Ratios'!F14 -> 10.384985 | AW20: ='Prudential Ratios'!G14 -> 9.6357278 | AX20: ='Prudential Ratios'!H14 -> 9.6793191 | AY20: ='Prudential Ratios'!I14 -> 9.9006137 | AZ20: ='Prudential Ratios'!J14 -> 10.881615 | BA20: ='Prudential Ratios'!K14 -> 10.188674 | BB20: ='Prudential Ratios'!L14 -> 10.851818 | ... CA20: ='Prudential Ratios'!AK14 -> 0.20864098
B21: LB | C21: ≤ 5% | D21: ='Prudential Ratios'!#REF! -> #REF! | E21: ='Prudential Ratios'!#REF! -> #REF! | F21: ='Prudential Ratios'!#REF! -> #REF! | G21: ='Prudential Ratios'!#REF! -> #REF! | H21: ='Prudential Ratios'!#REF! -> #REF! | I21: ='Prudential Ratios'!#REF! -> #REF! | J21: ='Prudential Ratios'!#REF! -> #REF! | K21: ='Prudential Ratios'!#REF! -> #REF! | ... AT21: ='Prudential Ratios'!#REF! -> #REF! | AU21: ='Prudential Ratios'!E15 -> 0.051737546 | AV21: ='Prudential Ratios'!F15 -> 0 | AW21: ='Prudential Ratios'!G15 -> 0 | AX21: ='Prudential Ratios'!H15 -> 0 | AY21: ='Prudential Ratios'!I15 -> 0 | AZ21: ='Prudential Ratios'!J15 -> 0 | BA21: ='Prudential Ratios'!K15 -> 0 | BB21: ='Prudential Ratios'!L15 -> 0 | ... CA21: ='Prudential Ratios'!AK15 -> 0.10941436
B22: FITD | C22: ≤ 5% | D22: ='Prudential Ratios'!#REF! -> #REF! | E22: ='Prudential Ratios'!#REF! -> #REF! | F22: ='Prudential Ratios'!#REF! -> #REF! | G22: ='Prudential Ratios'!#REF! -> #REF! | H22: ='Prudential Ratios'!#REF! -> #REF! | I22: ='Prudential Ratios'!#REF! -> #REF! | J22: ='Prudential Ratios'!#REF! -> #REF! | K22: ='Prudential Ratios'!#REF! -> #REF! | ... AT22: ='Prudential Ratios'!#REF! -> #REF! | AU22: ='Prudential Ratios'!E19 -> 0.00029466029 | AV22: ='Prudential Ratios'!F19 -> 321254.66 | AW22: ='Prudential Ratios'!G19 -> 322432.63 | AX22: ='Prudential Ratios'!H19 -> -19.581498 | AY22: ='Prudential Ratios'!I19 -> -19.442138 | AZ22: ='Prudential Ratios'!J19 -> #DIV/0! | BA22: ='Prudential Ratios'!K19 -> -5172.7261 | BB22: ='Prudential Ratios'!L19 -> -5075.8957 | ... CA22: ='Prudential Ratios'!AK19 -> 0.00021384929
B23: FICC | C23: ≤ 40% | D23: ='Prudential Ratios'!#REF! -> #REF! | E23: ='Prudential Ratios'!#REF! -> #REF! | F23: ='Prudential Ratios'!#REF! -> #REF! | G23: ='Prudential Ratios'!#REF! -> #REF! | H23: ='Prudential Ratios'!#REF! -> #REF! | I23: ='Prudential Ratios'!#REF! -> #REF! | J23: ='Prudential Ratios'!#REF! -> #REF! | K23: ='Prudential Ratios'!#REF! -> #REF! | ... AT23: ='Prudential Ratios'!#REF! -> #REF! | AU23: ='Prudential Ratios'!E20 -> 0.0012292203 | AV23: ='Prudential Ratios'!F20 -> #REF! | AW23: ='Prudential Ratios'!G20 -> #REF! | AX23: ='Prudential Ratios'!H20 -> #REF! | AY23: ='Prudential Ratios'!I20 -> #REF! | AZ23: ='Prudential Ratios'!J20 -> #REF! | BA23: ='Prudential Ratios'!K20 -> #REF! | BB23: ='Prudential Ratios'!L20 -> #REF! | ... CA23: ='Prudential Ratios'!AK20 -> 0.00091955136

Sheet Financials
B1: SIRAJI SACCO SOCIETY
B3: Year | C3: AUDITED 2020 | D3: 44197 | E3: 44228 | F3: 44256 | G3: 44287 | H3: 44317 | I3: 44348 | J3: 44378 | K3: 44409 | L3: 44440 | M3: 44470 | N3: 44501 | O3: 44531 | P3: Audited 2021 | Q3: 44562 | R3: 44593 | S3: 44621 | T3: 44652 | U3: 44682 | V3: 44713 | W3: 44743 | X3: 44774 | Y3: 44805 | Z3: 44835 | AA3: 44866 | AB3: 44896 | AC3: Audited-2022 | AD3: 44949 | AE3: 44980 | AF3: 45008 | AG3: 45039 | AH3: 45069 | AI3: 45100
A4: 1 | B4: Membership
A5: 2 | B5: Total Assets | C5: =SFP!B27 -> 451530040 | D5: =SFP!C29 -> 48619914 | E5: =SFP!D29 -> 52129056 | F5: =SFP!E29 -> 54461821 | G5: =SFP!F29 -> 52365497 | H5: =SFP!G29 -> 56273331 | I5: =SFP!H29 -> 55246420 | J5: =SFP!I29 -> 50771324 | K5: =SFP!J29 -> 53762394 | ... O5: =SFP!N29 -> 53033455 | P5: =SFP!O27 -> 512833379 | Q5: =SFP!P27 -> 5.0843806e+08 | R5: =SFP!Q27 -> 5.1359248e+08 | S5: =SFP!R27 -> 5.0725105e+08 | T5: =SFP!S27 -> 5.0706242e+08 | U5: =SFP!T27 -> 5.1067156e+08 | V5: =SFP!U27 -> 5.4810082e+08 | W5: =SFP!V27 -> 5.5069305e+08 | ... AI5: =SFP!AH27 -> 6.0533651e+08
A6: 3 | B6: Total Deposits | C6: =SFP!B32 -> 345672644 | D6: =SFP!C35 -> 988 | E6: =SFP!D35 -> 988 | F6: =SFP!E35 -> -16238469 | G6: =SFP!F35 -> -16242182 | H6: =SFP!G35 -> 0 | I6: =SFP!H35 -> -62443.5 | J6: =SFP!I35 -> -65274 | K6: =SFP!J35 -> -67724 | ... O6: =SFP!N35 -> -73198 | P6: =SFP!O32 -> 393860322 | Q6: =SFP!P32 -> 4.0155356e+08 | R6: =SFP!Q32 -> 4.0567966e+08 | S6: =SFP!R32 -> 4.1469122e+08 | T6: =SFP!S32 -> 4.1603844e+08 | U6: =SFP!T32 -> 4.16693e+08 | V6: =SFP!U32 -> 4.223332e+08 | W6: =SFP!V32 -> 4.2260159e+08 | ... AI6: =SFP!AH32 -> 4.7629804e+08
A7: 3.1 | B7: Deposits-Members(BOSA) | C7: =SFP!B31 -> 275781981 | D7: =SFP!C34 -> -11696.01 | E7: =SFP!D34 -> -10315.53 | F7: =SFP!E34 -> 808224.05 | G7: =SFP!F34 -> 809073.08 | H7: =SFP!G34 -> -170385.89 | I7: =SFP!H34 -> -164901.78 | J7: =SFP!I34 -> -164786.78 | K7: =SFP!J34 -> -165862.78 | ... O7: =SFP!N34 -> -131899.24 | P7: =SFP!O31 -> 315654301 | Q7: =SFP!P31 -> 3.4355035e+08 | R7: =SFP!Q31 -> 3.4826146e+08 | S7: =SFP!R31 -> 3.5313295e+08 | T7: =SFP!S31 -> 3.5920512e+08 | U7: =SFP!T31 -> 3.6344925e+08 | V7: =SFP!U31 -> 3.6674926e+08 | W7: =SFP!V31 -> 3.7078928e+08 | ... AI7: =SFP!AH31 -> 4.1550032e+08
A8: 3.2 | B8: Deposits-Customers(FOSA) | C8: =SFP!B29 -> 69890663 | D8: =SFP!C31 -> 3.0033339e+08 | E8: =SFP!D31 -> 3.0596066e+08 | F8: =SFP!E31 -> 3.1022242e+08 | G8: =SFP!F31 -> 3.1310114e+08 | H8: =SFP!G31 -> 3.1633245e+08 | I8: =SFP!H31 -> 3.2154503e+08 | J8: =SFP!I31 -> 3.2558706e+08 | K8: =SFP!J31 -> 3.2888016e+08 | ... O8: =SFP!N31 -> ############ | P8: =SFP!O29 -> 78206021 | Q8: =SFP!P29 -> 54611474 | R8: =SFP!Q29 -> 53486462 | S8: =SFP!R29 -> 58088767 | T8: =SFP!S29 -> 53467624 | U8: =SFP!T29 -> 49573059 | V8: =SFP!U29 -> 51924404 | W8: =SFP!V29 -> 48308772 | ... AI8: =SFP!AH29 -> 54882496
A9: 4 | B9: External Borrowing | C9: =SFP!B39 -> 0 | D9: =SFP!C43 -> 0 | E9: =SFP!D43 -> 0 | F9: =SFP!E43 -> 0 | G9: =SFP!F43 -> 0 | H9: =SFP!G43 -> 0 | I9: =SFP!H43 -> 0 | J9: =SFP!I43 -> 0 | K9: =SFP!J43 -> 0 | ... O9: =SFP!N43 -> 0 | P9: =SFP!O39 -> 3750000 | Q9: =SFP!P39 -> 3125000 | R9: =SFP!Q39 -> 2500000 | S9: =SFP!R39 -> 1875000 | T9: =SFP!S39 -> 1250000 | U9: =SFP!T39 -> 587500 | V9: =SFP!U39 -> 30000000 | W9: =SFP!V39 -> 30145851 | ... AI9: =SFP!AH39 -> 30825000
A10: 4.1 | B10: Short term Liabilities | C10: =SFP!B34+SFP!B35+SFP!B36+SFP!B37+SFP!B38 -> 20053673 | D10: =SFP!C37+SFP!C38+SFP!C39+SFP!C40+SFP!C42 -> 3.8082514e+08 | E10: =SFP!D37+SFP!D38+SFP!D39+SFP!D40+SFP!D42 -> 3.8787667e+08 | F10: =SFP!E37+SFP!E38+SFP!E39+SFP!E40+SFP!E42 -> 3.8293052e+08 | G10: =SFP!F37+SFP!F38+SFP!F39+SFP!F40+SFP!F42 -> 4.3379736e+08 | H10: =SFP!G37+SFP!G38+SFP!G39+SFP!G40+SFP!G42 -> 4.2272516e+08 | I10: =SFP!H37+SFP!H38+SFP!H39+SFP!H40+SFP!H42 -> 4.4002822e+08 | J10: =SFP!I37+SFP!I38+SFP!I39+SFP!I40+SFP!I42 -> 4.3565356e+08 | K10: =SFP!J37+SFP!J38+SFP!J39+SFP!J40+SFP!J42 -> 4.4119219e+08 | ... O10: =SFP!N37+SFP!N38+SFP!N39+SFP!N40+SFP!N42 -> #VALUE! | P10: =SFP!O34+SFP!O35+SFP!O36+SFP!O37+SFP!O38 -> 22421347 | Q10: =SFP!P34+SFP!P35+SFP!P36+SFP!P37+SFP!P38 -> -6603381.5 | R10: =SFP!Q34+SFP!Q35+SFP!Q36+SFP!Q37+SFP!Q38 -> -6448228.2 | S10: =SFP!R34+SFP!R35+SFP!R36+SFP!R37+SFP!R38 -> -23975184 | T10: =SFP!S34+SFP!S35+SFP!S36+SFP!S37+SFP!S38 -> -3243878.3 | U10: =SFP!T34+SFP!T35+SFP!T36+SFP!T37+SFP!T38 -> -4004764.4 | V10: =SFP!U34+SFP!U35+SFP!U36+SFP!U37+SFP!U38 -> -4051046.1 | W10: =SFP!V34+SFP!V35+SFP!V36+SFP!V37+SFP!V38 -> -4106966.3 | ... AI10: =SFP!AH34+SFP!AH35+SFP!AH36+SFP!AH37+SFP!AH38 -> -12553593
A13: 5 | B13: Share capital and Reserves
A14: 5.1 | B14: Core Capital | C14: =C17 -> 82862280 | D14: =D17 -> #REF! | E14: =E17 -> #REF! | F14: =F17 -> #REF! | G14: =G17 -> #REF! | H14: =H17 -> #REF! | I14: =I17 -> #REF! | J14: =J17 -> #REF! | ... AI14: =AI17 -> 110767059
A15: 5.2 | B15: Institutional Capital | C15: =C14-C18 -> 33129239 | D15: =D14-D18 -> #REF! | E15: =E14-E18 -> #REF! | F15: =F14-F18 -> #REF! | G15: =G14-G18 -> #REF! | H15: =H14-H18 -> #REF! | I15: =I14-I18 -> #REF! | J15: =J14-J18 -> #REF! | ... AI15: =AI14-AI18 -> 56814067
A17: 5.3 | B17: Total Capital | C17: =SUM(C18:C21) -> 82862280 | D17: =SUM(D18:D21) -> #REF! | E17: =SUM(E18:E21) -> #REF! | F17: =SUM(F18:F21) -> #REF! | G17: =SUM(G18:G21) -> #REF! | H17: =SUM(H18:H21) -> #REF! | I17: =SUM(I18:I21) -> #REF! | J17: =SUM(J18:J21) -> #REF! | ... AI17: =SUM(AI18:AI21) -> 110767059
A18: 5.3.1 | B18: Members Share Capital | C18: =SFP!B42 -> 49733041 | D18: =SFP!C50 -> 11432500 | E18: =SFP!D50 -> 11432500 | F18: =SFP!E50 -> 11432500 | G18: =SFP!F50 -> 12421535 | H18: =SFP!G50 -> 12421535 | I18: =SFP!H50 -> 12421535 | J18: =SFP!I50 -> 12421535 | K18: =SFP!J50 -> 12421535 | ... O18: =SFP!N50 -> 12421535 | P18: =SFP!O42 -> 51874160 | Q18: =SFP!P42 -> 50143975 | R18: =SFP!Q42 -> 50273068 | S18: =SFP!R42 -> 50290425 | T18: =SFP!S42 -> 50290175 | U18: =SFP!T42 -> 51040285 | V18: =SFP!U42 -> 51303291 | W18: =SFP!V42 -> 51307235 | ... AI18: =SFP!AH42 -> 53952992
A19: 5.3.3 | B19: Retained Earnings | C19: =SFP!B45 -> 20707704 | D19: =SFP!C53 -> 0 | E19: =SFP!D53 -> 0 | F19: =SFP!E53 -> 0 | G19: =SFP!F53 -> 0 | H19: =SFP!G53 -> 0 | I19: =SFP!H53 -> 0 | J19: =SFP!I53 -> 0 | K19: =SFP!J53 -> 0 | ... O19: =SFP!N53 -> 0 | P19: =SFP!O45 -> 23827293 | Q19: =SFP!P45 -> 44855935 | R19: =SFP!Q45 -> 46225004 | S19: =SFP!R45 -> 49006618 | T19: =SFP!S45 -> 27364708 | U19: =SFP!T45 -> 31104762 | V19: =SFP!U45 -> 33152406 | W19: =SFP!V45 -> 35382362 | ... AI19: =SFP!AH45 -> 39713809
A20: 5.3.5 | B20: Statutory Reserves | C20: =SFP!B50 -> 12421535 | D20: =SFP!#REF! -> #REF! | E20: =SFP!#REF! -> #REF! | F20: =SFP!#REF! -> #REF! | G20: =SFP!#REF! -> #REF! | H20: =SFP!#REF! -> #REF! | I20: =SFP!#REF! -> #REF! | J20: =SFP!#REF! -> #REF! | K20: =SFP!#REF! -> #REF! | ... O20: =SFP!#REF! -> #REF! | P20: =SFP!O50 -> 14158817 | Q20: =SFP!P50 -> 12421535 | R20: =SFP!Q50 -> 12421535 | S20: =SFP!R50 -> 12421535 | T20: =SFP!S50 -> 12421535 | U20: =SFP!T50 -> 12421535 | V20: =SFP!U50 -> 12421535 | W20: =SFP!V50 -> 12421535 | ... AI20: =SFP!AH50 -> 14158817
A21: 5.3.6 | B21: Capital Reserve | C21: =SFP!B51 -> 0 | D21: =SFP!#REF! -> #REF! | E21: =SFP!#REF! -> #REF! | F21: =SFP!#REF! -> #REF! | G21: =SFP!#REF! -> #REF! | H21: =SFP!#REF! -> #REF! | I21: =SFP!#REF! -> #REF! | J21: =SFP!#REF! -> #REF! | K21: =SFP!#REF! -> #REF! | ... O21: =SFP!#REF! -> #REF! | P21: =SFP!O51 -> 2941441 | Q21: =SFP!P51 -> 2941441 | R21: =SFP!Q51 -> 2941441 | S21: =SFP!R51 -> 2941441 | T21: =SFP!S51 -> 2941441 | U21: =SFP!T51 -> 2941441 | V21: =SFP!U51 -> 2941441 | W21: =SFP!V51 -> 2941441 | ... AI21: =SFP!AH51 -> 2941441
A22: 5.3.7 | B22: Supplementary Capital & reserves
A23: a | B23: Proposed Dividends | C23: =SFP!B53 -> 0 | D23: =SFP!#REF! -> #REF! | E23: =SFP!#REF! -> #REF! | F23: =SFP!#REF! -> #REF! | G23: =SFP!#REF! -> #REF! | H23: =SFP!#REF! -> #REF! | I23: =SFP!#REF! -> #REF! | J23: =SFP!#REF! -> #REF! | K23: =SFP!#REF! -> #REF! | ... O23: =SFP!#REF! -> #REF! | P23: =SFP!O53 -> 0 | Q23: =SFP!P53 -> 0 | R23: =SFP!Q53 -> 0 | S23: =SFP!R53 -> 0 | T23: =SFP!S53 -> 0 | U23: =SFP!T53 -> 0 | V23: =SFP!U53 -> 0 | W23: =SFP!V53 -> 0 | ... AI23: =SFP!AH53 -> 0
A24: b
A26: 6 | B26: Investments | C26: =C27+C28+C29 -> 101856 | D26: =D27+D28+D29 -> 3.173996e+08 | E26: =E27+E28+E29 -> 3.1856344e+08 | F26: =F27+F28+F29 -> 3.1797356e+08 | G26: =G27+G28+G29 -> 3.1578275e+08 | H26: =H27+H28+H29 -> 3.1804063e+08 | I26: =I27+I28+I29 -> 3.2300312e+08 | J26: =J27+J28+J29 -> 3.3132402e+08 | ... AI26: =AI27+AI28+AI29 -> 101856
A27: 6.1 | B27: Investments in Coop bank, CIC, Kuscco, Kerussu & Codic | C27: =SFP!B12 -> 101856 | D27: =SFP!C12 -> 101856 | E27: =SFP!D12 -> 101856 | F27: =SFP!E12 -> 101856 | G27: =SFP!F12 -> 101856 | H27: =SFP!G12 -> 101856 | I27: =SFP!H12 -> 101856 | J27: =SFP!I12 -> 101856 | ... AI27: =SFP!AH12 -> 101856
A28: 6.2 | B28: Equity Investments (at cost) | C28: =SFP!B13 -> 0 | D28: =SFP!C14 -> 3.1729775e+08 | E28: =SFP!D14 -> 3.1846159e+08 | F28: =SFP!E14 -> 3.178717e+08 | G28: =SFP!F14 -> 3.1568089e+08 | H28: =SFP!G14 -> 3.1793877e+08 | I28: =SFP!H14 -> 3.2290127e+08 | J28: =SFP!I14 -> 3.3122216e+08 | K28: =SFP!J14 -> 3.3725988e+08 | ... O28: =SFP!N14 -> ############ | P28: =SFP!O13 -> 0 | Q28: =SFP!P13 -> 0 | R28: =SFP!Q13 -> 0 | S28: =SFP!R13 -> 0 | T28: =SFP!S13 -> 0 | U28: =SFP!T13 -> 0 | V28: =SFP!U13 -> 0 | W28: =SFP!V13 -> 0 | ... AI28: =SFP!AH13 -> 0
A29: 6.3 | B29: Deposits in KUSCCO CFP | C29: =SFP!B11 -> 0 | D29: =SFP!C11 -> 0 | E29: =SFP!D11 -> 0 | F29: =SFP!E11 -> 0 | G29: =SFP!F11 -> 0 | H29: =SFP!G11 -> 0 | I29: =SFP!H11 -> 0 | J29: =SFP!I11 -> 0 | ... AI29: =SFP!AH11 -> 0
A31: 7 | B31: Net Loans & advances | C31: =C32-C33 -> 312039246 | D31: =D32-D33 -> 25672793 | E31: =E32-E33 -> 26247308 | F31: =F32-F33 -> 26821797 | G31: =G32-G33 -> 27393588 | H31: =H32-H33 -> 27970103 | I31: =I32-I33 -> 28555919 | J31: =J32-J33 -> 29156551 | ... AI31: =AI32-AI33 -> 3.6843301e+08
A32: 7.1 | B32: Gross Loans & advances | C32: =SFP!B15 -> 337140421 | D32: =SFP!C16 -> 25672793 | E32: =SFP!D16 -> 26247308 | F32: =SFP!E16 -> 26821797 | G32: =SFP!F16 -> 27393588 | H32: =SFP!G16 -> 27970103 | I32: =SFP!H16 -> 28555919 | J32: =SFP!I16 -> 29156551 | K32: =SFP!J16 -> 29768264 | ... O32: =SFP!N16 -> 32223482 | P32: =SFP!O15 -> 366288454 | Q32: =SFP!P15 -> 3.682312e+08 | R32: =SFP!Q15 -> 3.6710059e+08 | S32: =SFP!R15 -> 3.7447956e+08 | T32: =SFP!S15 -> 3.7427044e+08 | U32: =SFP!T15 -> 3.8128241e+08 | V32: =SFP!U15 -> 3.8413625e+08 | W32: =SFP!V15 -> 3.8457727e+08 | ... AI32: =SFP!AH15 -> 4.1244701e+08
A33: 7.3 | B33: Allowance for loan losses | C33: =SFP!B16 -> 25101175 | D33: =SFP!C17 -> 0 | E33: =SFP!D17 -> 0 | F33: =SFP!E17 -> 0 | G33: =SFP!F17 -> 0 | H33: =SFP!G17 -> 0 | I33: =SFP!H17 -> 0 | J33: =SFP!I17 -> 0 | K33: =SFP!J17 -> 0 | ... O33: =SFP!N17 -> 0 | P33: =SFP!O16 -> 32223482 | Q33: =SFP!P16 -> 32839426 | R33: =SFP!Q16 -> 33451276 | S33: =SFP!R16 -> 34075409 | T33: =SFP!S16 -> 34699193 | U33: =SFP!T16 -> 35334830 | V33: =SFP!U16 -> 35975058 | W33: =SFP!V16 -> 36616020 | ... AI33: =SFP!AH16 -> 44013998
A34: 7.4 | B34: Non Performing Loans | C34: =(#REF!+#REF!+#REF!) -> #REF! | D34: =(#REF!+#REF!+#REF!) -> #REF! | E34: =(#REF!+#REF!+#REF!) -> #REF! | F34: =(#REF!+#REF!+#REF!) -> #REF! | G34: =(#REF!+#REF!+#REF!) -> #REF! | H34: =(#REF!+#REF!+#REF!) -> #REF! | I34: =(#REF!+#REF!+#REF!) -> #REF! | J34: =(#REF!+#REF!+#REF!) -> #REF! | ... AI34: =(#REF!+#REF!+#REF!) -> #REF!
A35: 7.5 | B35: Required loan loss provision | C35: =#REF! -> #REF! | D35: =#REF! -> #REF! | E35: =#REF! -> #REF! | F35: =#REF! -> #REF! | G35: =#REF! -> #REF! | H35: =#REF! -> #REF! | I35: =#REF! -> #REF! | J35: =#REF! -> #REF! | ... AI35: =#REF! -> #REF!
A36: 7.6 | B36: Cash and Cash equipments | C36: =SFP!B4 -> 81357297 | D36: =SFP!C4 -> 66330383 | E36: =SFP!D4 -> 87503175 | F36: =SFP!E4 -> 54838007 | G36: =SFP!F4 -> 68728884 | H36: =SFP!G4 -> 64017130 | I36: =SFP!H4 -> 57400041 | J36: =SFP!I4 -> 61310370 | ... AI36: =SFP!AH4 -> 1.1050364e+08
A38: 8 | B38: Non-Earning Assets | C38: =SFP!B7+SFP!B17+SFP!B23+SFP!B24+SFP!B25+SFP!B26 -> 58031641 | D38: =SFP!C7+SFP!C18+SFP!C24+SFP!C25+SFP!C26+SFP!C27 -> 5.0491706e+08 | E38: =SFP!D7+SFP!D18+SFP!D24+SFP!D25+SFP!D26+SFP!D27 -> 5.0230139e+08 | F38: =SFP!E7+SFP!E18+SFP!E24+SFP!E25+SFP!E26+SFP!E27 -> 5.2715334e+08 | G38: =SFP!F7+SFP!F18+SFP!F24+SFP!F25+SFP!F26+SFP!F27 -> 5.1845056e+08 | H38: =SFP!G7+SFP!G18+SFP!G24+SFP!G25+SFP!G26+SFP!G27 -> 6.1234474e+08 | I38: =SFP!H7+SFP!H18+SFP!H24+SFP!H25+SFP!H26+SFP!H27 -> 5.6288775e+08 | J38: =SFP!I7+SFP!I18+SFP!I24+SFP!I25+SFP!I26+SFP!I27 -> 5.5096119e+08 | K38: =SFP!J7+SFP!J18+SFP!J24+SFP!J25+SFP!J26+SFP!J27 -> 5.5999342e+08 | ... O38: =SFP!N7+SFP!N18+SFP!N24+SFP!N25+SFP!N26+SFP!N27 -> #VALUE! | P38: =SFP!O7+SFP!O17+SFP!O23+SFP!O24+SFP!O25+SFP!O26 -> 89365438 | Q38: =SFP!P7+SFP!P17+SFP!P23+SFP!P24+SFP!P25+SFP!P26 -> 90043699 | R38: =SFP!Q7+SFP!Q17+SFP!Q23+SFP!Q24+SFP!Q25+SFP!Q26 -> 89936379 | S38: =SFP!R7+SFP!R17+SFP!R23+SFP!R24+SFP!R25+SFP!R26 -> 88462382 | T38: =SFP!S7+SFP!S17+SFP!S23+SFP!S24+SFP!S25+SFP!S26 -> 94050549 | U38: =SFP!T7+SFP!T17+SFP!T23+SFP!T24+SFP!T25+SFP!T26 -> 95519116 | V38: =SFP!U7+SFP!U17+SFP!U23+SFP!U24+SFP!U25+SFP!U26 -> 1.1075746e+08 | W38: =SFP!V7+SFP!V17+SFP!V23+SFP!V24+SFP!V25+SFP!V26 -> 1.2474568e+08 | ... AI38: =SFP!AH7+SFP!AH17+SFP!AH23+SFP!AH24+SFP!AH25+SFP!AH26 -> 1.2629801e+08
A39: 8.1 | B39: Property and Equipment | C39: =SFP!B23 -> 23361056 | D39: =SFP!C24 -> 0 | E39: =SFP!D24 -> 0 | F39: =SFP!E24 -> 0 | G39: =SFP!F24 -> 0 | H39: =SFP!G24 -> 0 | I39: =SFP!H24 -> 0 | J39: =SFP!I24 -> 0 | K39: =SFP!J24 -> 0 | ... O39: =SFP!N24 -> 0 | P39: =SFP!O23 -> 47318410 | Q39: =SFP!P23 -> 46928203 | R39: =SFP!Q23 -> 46733595 | S39: =SFP!R23 -> 47654032 | T39: =SFP!S23 -> 51129629 | U39: =SFP!T23 -> 52253602 | V39: =SFP!U23 -> 57196693 | W39: =SFP!V23 -> 60277774 | ... AI39: =SFP!AH23 -> 66232504
A41: 9 | B41: Turnover | C41: =C42+C43+C44 -> 12421535 | D41: =D42+D43+D44 -> #REF! | E41: =E42+E43+E44 -> #REF! | F41: =F42+F43+F44 -> #REF! | G41: =G42+G43+G44 -> #REF! | H41: =H42+H43+H44 -> #REF! | I41: =I42+I43+I44 -> #REF! | J41: =J42+J43+J44 -> #REF! | ... AI41: =AI42+AI43+AI44 -> 17100258
A42: 9.1 | B42: Loan Interest | C42: =SFP!B50 -> 12421535 | D42: =SFP!#REF! -> #REF! | E42: =SFP!#REF! -> #REF! | F42: =SFP!#REF! -> #REF! | G42: =SFP!#REF! -> #REF! | H42: =SFP!#REF! -> #REF! | I42: =SFP!#REF! -> #REF! | J42: =SFP!#REF! -> #REF! | K42: =SFP!#REF! -> #REF! | ... O42: =SFP!#REF! -> #REF! | P42: =SFP!O50 -> 14158817 | Q42: =SFP!P50 -> 12421535 | R42: =SFP!Q50 -> 12421535 | S42: =SFP!R50 -> 12421535 | T42: =SFP!S50 -> 12421535 | U42: =SFP!T50 -> 12421535 | V42: =SFP!U50 -> 12421535 | W42: =SFP!V50 -> 12421535 | ... AI42: =SFP!AH50 -> 14158817
B43: Income from investments | C43: =SFP!B51 -> 0 | D43: =SFP!#REF! -> #REF! | E43: =SFP!#REF! -> #REF! | F43: =SFP!#REF! -> #REF! | G43: =SFP!#REF! -> #REF! | H43: =SFP!#REF! -> #REF! | I43: =SFP!#REF! -> #REF! | J43: =SFP!#REF! -> #REF! | K43: =SFP!#REF! -> #REF! | ... O43: =SFP!#REF! -> #REF! | P43: =SFP!O51 -> 2941441 | Q43: =SFP!P51 -> 2941441 | R43: =SFP!Q51 -> 2941441 | S43: =SFP!R51 -> 2941441 | T43: =SFP!S51 -> 2941441 | U43: =SFP!T51 -> 2941441 | V43: =SFP!U51 -> 2941441 | W43: =SFP!V51 -> 2941441 | ... AI43: =SFP!AH51 -> 2941441
A44: 9.2 | B44: Fees & Commissions | C44: =SFP!B52 -> 0 | D44: =SFP!#REF! -> #REF! | E44: =SFP!#REF! -> #REF! | F44: =SFP!#REF! -> #REF! | G44: =SFP!#REF! -> #REF! | H44: =SFP!#REF! -> #REF! | I44: =SFP!#REF! -> #REF! | J44: =SFP!#REF! -> #REF! | K44: =SFP!#REF! -> #REF! | ... O44: =SFP!#REF! -> #REF! | P44: =SFP!O52 -> 0 | Q44: =SFP!P52 -> 0 | R44: =SFP!Q52 -> 0 | S44: =SFP!R52 -> 0 | T44: =SFP!S52 -> 0 | U44: =SFP!T52 -> 0 | V44: =SFP!U52 -> 0 | W44: =SFP!V52 -> 0 | ... AI44: =SFP!AH52 -> 0
B45: Average yield on loans
A47: 10 | B47: Total Expenses (FinCosts + OpEx) | C47: =SUM(C48:C53) -> 36889168 | D47: =SUM(D48:D53) -> 0 | E47: =SUM(E48:E53) -> 0 | F47: =SUM(F48:F53) -> 0 | G47: =SUM(G48:G53) -> 0 | H47: =SUM(H48:H53) -> 0 | I47: =SUM(I48:I53) -> 0 | J47: =SUM(J48:J53) -> 0 | ... AJ47: =SUM(AJ48:AJ53) -> 0
A48: 10.1 | B48: Financial Exp. (Interest on deposits) | C48: =SCI!B13 -> 13316672 | D48: =SCI!C13 -> 0 | E48: =SCI!D13 -> 0 | F48: =SCI!E13 -> 0 | G48: =SCI!F13 -> 0 | H48: =SCI!G13 -> 0 | I48: =SCI!H13 -> 0 | J48: =SCI!I13 -> 0 | ... AJ48: =SCI!AI13 -> 0
A49: 10.2 | B49: Financial Exp. (Dividends) | C49: =SCI!B15 -> 0 | D49: =SCI!C15 -> 0 | E49: =SCI!D15 -> 0 | F49: =SCI!E15 -> 0 | G49: =SCI!F15 -> 0 | H49: =SCI!G15 -> 0 | I49: =SCI!H15 -> 0 | J49: =SCI!I15 -> 0 | ... AJ49: =SCI!AI15 -> 0
A50: 10.3 | B50: Financial Exp. (Interest on bank loans) | C50: =SCI!B14 -> 2635950 | D50: =SCI!C14 -> 0 | E50: =SCI!D14 -> 0 | F50: =SCI!E14 -> 0 | G50: =SCI!F14 -> 0 | H50: =SCI!G14 -> 0 | I50: =SCI!H14 -> 0 | J50: =SCI!I14 -> 0 | ... AJ50: =SCI!AI14 -> 0
A51: 10.4 | B51: Other Financial Expenses | C51: =SCI!B16+SCI!B17+SCI!B18 -> 0 | D51: =SCI!C16+SCI!C17+SCI!C18 -> 0 | E51: =SCI!D16+SCI!D17+SCI!D18 -> 0 | F51: =SCI!E16+SCI!E17+SCI!E18 -> 0 | G51: =SCI!F16+SCI!F17+SCI!F18 -> 0 | H51: =SCI!G16+SCI!G17+SCI!G18 -> 0 | I51: =SCI!H16+SCI!H17+SCI!H18 -> 0 | J51: =SCI!I16+SCI!I17+SCI!I18 -> 0 | ... AJ51: =SCI!AI16+SCI!AI17+SCI!AI18 -> 0
A52: 10.5 | B52: Administrative Expenses | C52: =SCI!B28 -> 18314309 | D52: =SCI!C28 -> 0 | E52: =SCI!D28 -> 0 | F52: =SCI!E28 -> 0 | G52: =SCI!F28 -> 0 | H52: =SCI!G28 -> 0 | I52: =SCI!H28 -> 0 | J52: =SCI!I28 -> 0 | ... AJ52: =SCI!AI28 -> 0
A53: 10.6 | B53: Governance Expenses | C53: =SCI!B25 -> 2622237 | D53: =SCI!C25 -> 0 | E53: =SCI!D25 -> 0 | F53: =SCI!E25 -> 0 | G53: =SCI!F25 -> 0 | H53: =SCI!G25 -> 0 | I53: =SCI!H25 -> 0 | J53: =SCI!I25 -> 0 | ... AJ53: =SCI!AI25 -> 0
B54: LLP
B56: Net Surplus | C56: =SCI!B37 -> 4955443 | D56: =SCI!C37 -> 0 | E56: =SCI!D37 -> 0 | F56: =SCI!E37 -> 0 | G56: =SCI!F37 -> 0 | H56: =SCI!G37 -> 0 | I56: =SCI!H37 -> 0 | J56: =SCI!I37 -> 0 | ... P56: =SCI!O37 -> 8679129

Sheet form4
D3: RISK CLASSIFICATION OF ASSETS AND PROVISIONING | L3: RISK CLASSIFICATION OF ASSETS AND PROVISIONING
D4: SACCO SOCIETY CS NUMBER | L4: SACCO SOCIETY CS NUMBER
D5: FINANCIAL YEAR | L5: FINANCIAL YEAR
D6: START DATE: | L6: START DATE:
D7: END DATE: | L7: END DATE:
D8: PORTFOLIO AGEING REPORT | L8: PORTFOLIO AGEING REPORT
E9: A | F9: B | G9: C | H9: D | M9: A | N9: B | O9: C | P9: D
C10: NO. | D10: CLASSIFICATION | E10: NO. OF A/Cs | F10: OUTSTANDING LOAN PORTFOLIO(Kshs) | G10: REQUIRED PROVISION | H10: REQUIRED PROVISION AMOUNT(Kshs) | K10: NO. | L10: CLASSIFICATION | M10: NO. OF A/Cs | N10: OUTSTANDING LOAN PORTFOLIO(Kshs) | O10: REQUIRED PROVISION | P10: REQUIRED PROVISION AMOUNT(Kshs)
C11: 1 | D11: Performing | K11: 1 | L11: Performing
C12: 2 | D12: Watch | K12: 2 | L12: Watch
C13: 3 | D13: Substandard | K13: 3 | L13: Substandard
C14: 4 | D14: Doubtful | K14: 4 | L14: Doubtful
C15: 5 | D15: Loss | K15: 5 | L15: Loss
D16: subtotal | L16: subtotal | M16: =SUM(M11:M15) -> 0 | N16: =SUM(N11:N15) -> 0 | P16: =SUM(P11:P15) -> 0
D17: Reschedule/Renegotiated loans | L17: Reschedule/Renegotiated loans
C18: 1 | D18: Performing | K18: 1 | L18: Performing | M18: 0 | N18: 0 | O18: 0.01 | P18: =N18*O18 -> 0
C19: 2 | D19: Watch | K19: 2 | L19: Watch | M19: 0 | N19: 0 | O19: 0.05 | P19: =N19*O19 -> 0
C20: 3 | D20: Substandard | K20: 3 | L20: Substandard | M20: 0 | N20: 0 | O20: 0.25 | P20: =N20*O20 -> 0
C21: 4 | D21: Doubtful | K21: 4 | L21: Doubtful | M21: 0 | N21: 0 | O21: 0.5 | P21: =N21*O21 -> 0
C22: 5 | D22: Loss | K22: 5 | L22: Loss | M22: 0 | N22: 0 | O22: 1 | P22: =N22*O22 -> 0
D23: subtotal | E23: =SUM(E17:E22) -> 0 | F23: =SUM(F17:F22) -> 0 | H23: =SUM(H17:H22) -> 0 | L23: subtotal | M23: =SUM(M17:M22) -> 0 | N23: =SUM(N17:N22) -> 0 | P23: =SUM(P17:P22) -> 0
D24: GRAND TOTAL | E24: =E16+E23 -> 0 | F24: =F16+F23 -> 0 | H24: =H16+H23 -> 0 | L24: GRAND TOTAL | M24: =M16+M23 -> 0 | N24: =N16+N23 -> 0 | P24: =P16+P23 -> 0
F26: =F13+F14+F15 -> 0 | N26: =N13+N14+N15 -> 0
F27: =F26/F24 -> #DIV/0! | N27: =N26/N24 -> #DIV/0!
D30: RISK CLASSIFICATION OF ASSETS AND PROVISIONING
D31: SACCO SOCIETY CS NUMBER
D32: FINANCIAL YEAR
D33: START DATE:
D34: END DATE:
D35: PORTFOLIO AGEING REPORT
E36: A | F36: B | G36: C | H36: D
C37: NO. | D37: CLASSIFICATION | E37: NO. OF A/Cs | F37: OUTSTANDING LOAN PORTFOLIO(Kshs) | G37: REQUIRED PROVISION | H37: REQUIRED PROVISION AMOUNT(Kshs)
C38: 1 | D38: Performing
C39: 2 | D39: Watch
C40: 3 | D40: Substandard
C41: 4 | D41: Doubtful
C42: 5 | D42: Loss
D43: subtotal
D44: Reschedule/Renegotiated loans
C45: 1 | D45: Performing | H45: =F45*G45 -> 0
C46: 2 | D46: Watch | H46: =F46*G46 -> 0
C47: 3 | D47: Substandard | H47: =F47*G47 -> 0
C48: 4 | D48: Doubtful | H48: =F48*G48 -> 0
C49: 5 | D49: Loss | H49: =F49*G49 -> 0
D50: subtotal | E50: =SUM(E44:E49) -> 0 | F50: =SUM(F44:F49) -> 0 | H50: =SUM(H44:H49) -> 0
D51: GRAND TOTAL | E51: =E43+E50 -> 0 | F51: =F43+F50 -> 0 | H51: =H43+H50 -> 0
F53: =F40+F41+F42 -> 0
F54: =F53/F51 -> #DIV/0!
D56: RISK CLASSIFICATION OF ASSETS AND PROVISIONING
D57: SACCO SOCIETY CS NUMBER
D58: FINANCIAL YEAR
D59: START DATE:
D60: END DATE:
D61: PORTFOLIO AGEING REPORT
E62: A | F62: B | G62: C | H62: D
C63: NO. | D63: CLASSIFICATION | E63: NO. OF A/Cs | F63: OUTSTANDING LOAN PORTFOLIO(Kshs) | G63: REQUIRED PROVISION | H63: REQUIRED PROVISION AMOUNT(Kshs)
C64: 1 | D64: Performing
C65: 2 | D65: Watch
C66: 3 | D66: Substandard
C67: 4 | D67: Doubtful
C68: 5 | D68: Loss
D69: subtotal | E69: =SUM(E64:E68) -> 0 | F69: =SUM(F64:F68) -> 0 | H69: =SUM(H64:H68) -> 0
D70: Reschedule/Renegotiated loans
C71: 1 | D71: Performing | E71: 0 | F71: 0 | G71: 0.01 | H71: =F71*G71 -> 0
C72: 2 | D72: Watch | E72: 0 | F72: 0 | G72: 0.05 | H72: =F72*G72 -> 0
C73: 3 | D73: Substandard | E73: 0 | F73: 0 | G73: 0.25 | H73: =F73*G73 -> 0
C74: 4 | D74: Doubtful | E74: 0 | F74: 0 | G74: 0.5 | H74: =F74*G74 -> 0
C75: 5 | D75: Loss | E75: 0 | F75: 0 | G75: 1 | H75: =F75*G75 -> 0
D76: subtotal | E76: =SUM(E70:E75) -> 0 | F76: =SUM(F70:F75) -> 0 | H76: =SUM(H70:H75) -> 0
D77: GRAND TOTAL | E77: =E69+E76 -> 0 | F77: =F69+F76 -> 0 | H77: =H69+H76 -> 0
F79: =F66+F67+F68 -> 0
F80: =F79/F77 -> #DIV/0!

Sheet SFP
A1: SIRAJI SACCO SOCIETY LTD
A2: STATEMENT OF FINANCIAL POSITION
B3: AUDITED 2020 | C3: 44197 | D3: 44228 | E3: 44256 | F3: 44287 | G3: 44317 | H3: 44348 | I3: 44378 | J3: 44409 | K3: 44440 | L3: 44470 | M3: 44501 | N3: 44531 | O3: AUDITED 2021 | P3: 44562 | Q3: 44593 | R3: 44621 | S3: 44652 | T3: 44682 | U3: 44713 | V3: 44743 | W3: 44774 | X3: 44805 | Y3: 44835 | Z3: 44866 | AA3: 44896 | AB3: Audited-2022 | AC3: 44949 | AD3: 44980 | AE3: 45008 | AF3: 45039 | AG3: 45069 | AH3: 45100
A4: Cash & Cash Equivalent | B4: =SUM(B5:B6) -> 81357297 | C4: 66330383 | D4: 87503175 | E4: 54838007 | F4: 68728884 | G4: 64017130 | H4: 57400041 | I4: 61310370 | J4: 64255623 | K4: 59818023 | L4: 64394347 | M4: 63660748 | N4: 68374034 | O4: =SUM(O5:O6) -> 89301113 | P4: =SUM(P5:P6) -> 82900733 | Q4: =SUM(Q5:Q6) -> 89904925 | R4: =SUM(R5:R6) -> 78282658 | S4: =SUM(S5:S6) -> 73338771 | T4: =SUM(T5:T6) -> 69103011 | U4: =SUM(U5:U6) -> 89080311 | V4: =SUM(V5:V6) -> 77884268 | ... AH4: =SUM(AH5:AH6) -> 1.1050364e+08
A5: Cash in hand | B5: =2741247-37150+10243742 -> 12947839 | C5: 4520760.3 | D5: 5379962.3 | E5: 10208722 | F5: 12026079 | G5: 18646740 | H5: 24335939 | I5: 10051360 | J5: 13355205 | K5: 17341171 | L5: 2637150 | M5: 974314 | N5: 7433428.9 | O5: =15672853-160843+4595329 -> 20107339 | P5: 10626961 | Q5: 11272186 | R5: 8351822.9 | S5: 7939056.9 | T5: 7486303.9 | U5: 9155617.1 | V5: 9790570.9 | W5: 11381232 | X5: 9908890.7 | Y5: 8758718.7 | Z5: 9475047.9 | AA5: 13719504 | AB5: 4893637 | AC5: 12204007 | AD5: 20202580 | AE5: 26722220 | AF5: 19688427 | AG5: 21173912 | AH5: 17348435
A6: Cash at bank | B6: =81357297-12947839 -> 68409458 | C6: 61809623 | D6: 82123213 | E6: 44629284 | F6: 56702806 | G6: 45370390 | H6: 33064102 | I6: 51259010 | J6: 50900418 | K6: 42476852 | L6: 61757197 | M6: 62686434 | N6: 60940605 | O6: =89301113-20107339 -> 69193774 | P6: 72273772 | Q6: 78632739 | R6: 69930835 | S6: 65399714 | T6: 61616707 | U6: 79924694 | V6: 68093697 | W6: 82821766 | X6: 73531850 | Y6: 84200018 | Z6: 80560021 | AA6: 85849458 | AB6: =106793890-AB5 -> 101900253 | AC6: 88560941 | AD6: 1.270304e+08 | AE6: 97205024 | AF6: 1.1099708e+08 | AG6: 96188389 | AH6: 93155201
A7: Prepayments & Sundry Receivables | B7: 34670585 | C7: 47462191 | D7: 34273472 | E7: 62669036 | F7: 52590222 | G7: 1.0103801e+08 | H7: 77402578 | I7: 65466850 | J7: 65832082 | K7: 76051442 | L7: 71182429 | M7: 64090869 | N7: 55998302 | O7: 42047028 | P7: 41211205 | Q7: 41340631 | R7: 38468537 | S7: 40812847 | T7: 41379180 | U7: 51906256 | V7: 62925116 | W7: 41552717 | X7: 42845975 | Y7: 31245021 | Z7: 47579637 | AA7: 35178546 | AB7: =60034124 -> 60034124 | AC7: 45671011 | AD7: 32808762 | AE7: 38811157 | AF7: 38268706 | AG7: 34604457 | AH7: 46790963
A8: Financial Investments | B8: =SUM(B9:B13) -> 101856 | C8: 101856 | D8: 101856 | E8: 101856 | F8: 101856 | G8: 101856 | H8: 101856 | I8: 101856 | J8: 101856 | K8: 101856 | L8: 101856 | M8: 101856 | N8: 101856 | O8: =SUM(O9:O13) -> 101856 | P8: =SUM(P9:P13) -> 101856 | Q8: =SUM(Q9:Q13) -> 101856 | R8: =SUM(R9:R13) -> 101856 | S8: =SUM(S9:S13) -> 101856 | T8: =SUM(T9:T13) -> 101856 | U8: =SUM(U9:U13) -> 101856 | V8: =SUM(V9:V13) -> 101856 | ... AH8: =SUM(AH9:AH13) -> 101856
A9: Government Securities - Treasury Bills/bonds, | C9: 0 | D9: 0 | E9: 0 | F9: 0 | G9: 0 | H9: 0 | I9: 0 | J9: 0 | K9: 0 | L9: 0 | M9: 0 | N9: 0 | P9: 0 | Q9: 0 | R9: 0 | S9: 0 | T9: 0 | U9: 0 | V9: 0 | W9: 0 | X9: 0 | Y9: 0 | Z9: 0 | AA9: 0 | AC9: 0 | AD9: 0 | AE9: 0 | AF9: 0 | AG9: 0 | AH9: 0
A10: Other Securities - Commercial papers/Bonds | C10: 0 | D10: 0 | E10: 0 | F10: 0 | G10: 0 | H10: 0 | I10: 0 | J10: 0 | K10: 0 | L10: 0 | M10: 0 | N10: 0 | P10: 0 | Q10: 0 | R10: 0 | S10: 0 | T10: 0 | U10: 0 | V10: 0 | W10: 0 | X10: 0 | Y10: 0 | Z10: 0 | AA10: 0 | AC10: 0 | AD10: 0 | AE10: 0 | AF10: 0 | AG10: 0 | AH10: 0
A11: Balances in NACCOS (E.g Jungu Kuu, ESS, Savings,Money Market,Coop FD, CFP) | C11: 0 | D11: 0 | E11: 0 | F11: 0 | G11: 0 | H11: 0 | I11: 0 | J11: 0 | K11: 0 | L11: 0 | M11: 0 | N11: 0 | P11: 0 | Q11: 0 | R11: 0 | S11: 0 | T11: 0 | U11: 0 | V11: 0 | W11: 0 | X11: 0 | Y11: 0 | Z11: 0 | AA11: 0 | AC11: 0 | AD11: 0 | AE11: 0 | AF11: 0 | AG11: 0 | AH11: 0
A12: Equity Investments in NACCOs(Shares in- CIC, KUSCCO, COOP BANK,CAK, KERUSSU) | B12: 101856 | C12: 101856 | D12: 101856 | E12: 101856 | F12: 101856 | G12: 101856 | H12: 101856 | I12: 101856 | J12: 101856 | K12: 101856 | L12: 101856 | M12: 101856 | N12: 101856 | O12: 101856 | P12: 101856 | Q12: 101856 | R12: 101856 | S12: 101856 | T12: 101856 | U12: 101856 | V12: 101856 | W12: 101856 | X12: 101856 | Y12: 101856 | Z12: 101856 | AA12: 101856 | AB12: =101856 -> 101856 | AC12: 101856 | AD12: 101856 | AE12: 101856 | AF12: 101856 | AG12: 101856 | AH12: 101856
A13: Equity Investments in companies - shares/stocks
A14: Net Loan Portfolio | B14: =B15-B16 -> 312039246 | C14: 3.1729775e+08 | D14: 3.1846159e+08 | E14: 3.178717e+08 | F14: 3.1568089e+08 | G14: 3.1793877e+08 | H14: 3.2290127e+08 | I14: 3.3122216e+08 | J14: 3.3725988e+08 | K14: 3.3807527e+08 | L14: 3.4029929e+08 | M14: 3.3504146e+08 | N14: ############ | O14: =O15-O16 -> 334064972 | P14: =P15-P16 -> 3.3539177e+08 | Q14: =Q15-Q16 -> 3.3364932e+08 | R14: =R15-R16 -> 3.4040415e+08 | S14: =S15-S16 -> 3.3957124e+08 | T14: =T15-T16 -> 3.4594758e+08 | U14: =U15-U16 -> 3.4816119e+08 | V14: =V15-V16 -> 3.4796125e+08 | ... AH14: =AH15-AH16 -> 3.6843301e+08
A15: Gross Loan Portfolio | B15: 337140421 | C15: 3.4297054e+08 | D15: 3.4470889e+08 | E15: 3.446935e+08 | F15: 3.4307448e+08 | G15: 3.4590887e+08 | H15: 3.5145719e+08 | I15: 3.6037871e+08 | J15: 3.6702814e+08 | K15: 3.6845763e+08 | L15: 3.7130055e+08 | M15: 3.6665382e+08 | N15: ############ | O15: 366288454 | P15: 3.682312e+08 | Q15: 3.6710059e+08 | R15: 3.7447956e+08 | S15: 3.7427044e+08 | T15: 3.8128241e+08 | U15: 3.8413625e+08 | V15: 3.8457727e+08 | W15: 3.9433601e+08 | X15: 4.0420936e+08 | Y15: 4.0806101e+08 | Z15: 3.9517491e+08 | AA15: 4.0230846e+08 | AB15: =385965927 -> 385965927 | AC15: 3.9668119e+08 | AD15: 4.0618297e+08 | AE15: 4.0311315e+08 | AF15: 4.0250802e+08 | AG15: 4.1370203e+08 | AH15: 4.1244701e+08
A16: Allowance for Loan Loss | B16: 25101175 | C16: 25672793 | D16: 26247308 | E16: 26821797 | F16: 27393588 | G16: 27970103 | H16: 28555919 | I16: 29156551 | J16: 29768264 | K16: 30382360 | L16: 31001260 | M16: 31612352 | N16: 32223482 | O16: 32223482 | P16: 32839426 | Q16: 33451276 | R16: 34075409 | S16: 34699193 | T16: 35334830 | U16: 35975058 | V16: 36616020 | W16: 37273246 | X16: 37946929 | Y16: 38627136 | Z16: 39285760 | AA16: 39956275 | AB16: 39956275 | AC16: 40617410 | AD16: 41294381 | AE16: 41966236 | AF16: 42637083 | AG16: 43326586 | AH16: 44013998
A17: Accounts Receivables | B17: =SUM(B18:B20) -> 0 | C17: 0 | D17: 0 | E17: 0 | F17: 0 | G17: 0 | H17: 0 | I17: 0 | J17: 0 | K17: 0 | L17: 0 | M17: 0 | N17: 0 | O17: =SUM(O18:O20) -> 0 | P17: =SUM(P18:P20) -> 0 | Q17: =SUM(Q18:Q20) -> 0 | R17: =SUM(R18:R20) -> 0 | S17: =SUM(S18:S20) -> 0 | T17: =SUM(T18:T20) -> 0 | U17: =SUM(U18:U20) -> 0 | V17: =SUM(V18:V20) -> 0 | ... AH17: =SUM(AH18:AH20) -> 0
A18: Tax Recoverable | C18: 0 | D18: 0 | E18: 0 | F18: 0 | G18: 0 | H18: 0 | I18: 0 | J18: 0 | K18: 0 | L18: 0 | M18: 0 | N18: 0 | P18: 0 | Q18: 0 | R18: 0 | S18: 0 | T18: 0 | U18: 0 | V18: 0 | W18: 0 | X18: 0 | Y18: 0 | Z18: 0 | AA18: 0 | AC18: 0 | AD18: 0 | AE18: 0 | AF18: 0 | AG18: 0 | AH18: 0
A19: Deferred Tax Assets | C19: 0 | D19: 0 | E19: 0 | F19: 0 | G19: 0 | H19: 0 | I19: 0 | J19: 0 | K19: 0 | L19: 0 | M19: 0 | N19: 0 | P19: 0 | Q19: 0 | R19: 0 | S19: 0 | T19: 0 | U19: 0 | V19: 0 | W19: 0 | X19: 0 | Y19: 0 | Z19: 0 | AA19: 0 | AC19: 0 | AD19: 0 | AE19: 0 | AF19: 0 | AG19: 0 | AH19: 0
A20: Retirement Benefit Assets | C20: 0 | D20: 0 | E20: 0 | F20: 0 | G20: 0 | H20: 0 | I20: 0 | J20: 0 | K20: 0 | L20: 0 | M20: 0 | N20: 0 | P20: 0 | Q20: 0 | R20: 0 | S20: 0 | T20: 0 | U20: 0 | V20: 0 | W20: 0 | X20: 0 | Y20: 0 | Z20: 0 | AA20: 0 | AC20: 0 | AD20: 0 | AE20: 0 | AF20: 0 | AG20: 0 | AH20: 0
A21: Property & Equipment & Other assets | B21: =SUM(B22:B26) -> 23361056 | C21: 24531739 | D21: 25445059 | E21: 26427096 | F21: 26336732 | G21: 25995368 | H21: 25670004 | I21: 25459840 | J21: 24995050 | K21: 24509059 | L21: 30529884 | M21: 40476187 | N21: 47830422 | O21: =SUM(O22:O26) -> 47318410 | P21: =SUM(P22:P26) -> 48832495 | Q21: =SUM(Q22:Q26) -> 48595748 | R21: =SUM(R22:R26) -> 49993845 | S21: =SUM(S22:S26) -> 53237702 | T21: =SUM(T22:T26) -> 54139936 | U21: =SUM(U22:U26) -> 58851208 | V21: =SUM(V22:V26) -> 61820560 | ... AH21: =SUM(AH22:AH26) -> 79507042
A22: Investment Properties | C22: 0 | D22: 0 | E22: 0 | F22: 0 | G22: 0 | H22: 0 | I22: 0 | J22: 0 | K22: 0 | L22: 0 | M22: 0 | N22: 0 | P22: 0 | Q22: 0 | R22: 0 | S22: 0 | T22: 0 | U22: 0 | V22: 0 | W22: 0 | X22: 0 | Y22: 0 | Z22: 0 | AA22: 0 | AC22: 0 | AD22: 0 | AE22: 0 | AF22: 0 | AG22: 0 | AH22: 0
A23: Property & Equipment | B23: 23361056 | C23: 22800786 | D23: 23202286 | E23: 23850484 | F23: 23914982 | G23: 23779780 | H23: 23660578 | I23: 23526576 | J23: 23278208 | K23: 23010839 | L23: 29031663 | M23: 38810860 | N23: 46306518 | O23: 47318410 | P23: 46928203 | Q23: 46733595 | R23: 47654032 | S23: 51129629 | T23: 52253602 | U23: 57196693 | V23: 60277774 | W23: 62881900 | X23: 64150851 | Y23: 64252348 | Z23: 64297905 | AA23: 63996962 | AB23: =5986000+46948382+8260089+6626709+2451490+576205+806141 -> 71655016 | AC23: 64234719 | AD23: 64349294 | AE23: 65867678 | AF23: 66077910 | AG23: 66180262 | AH23: 66232504
A24: Prepaid Lease rentals | C24: 0 | D24: 0 | E24: 0 | F24: 0 | G24: 0 | H24: 0 | I24: 0 | J24: 0 | K24: 0 | L24: 0 | M24: 0 | N24: 0 | P24: 0 | Q24: 0 | R24: 0 | S24: 0 | T24: 0 | U24: 0 | V24: 0 | W24: 0 | X24: 0 | Y24: 0 | Z24: 0 | AA24: 0 | AC24: 0 | AD24: 0 | AE24: 0 | AF24: 0 | AG24: 0 | AH24: 0
A25: Intangible Assets | C25: 0 | D25: 0 | E25: 0 | F25: 0 | G25: 0 | H25: 0 | I25: 0 | J25: 0 | K25: 0 | L25: 0 | M25: 0 | N25: 0 | P25: 0 | Q25: 0 | R25: 0 | S25: 0 | T25: 0 | U25: 0 | V25: 0 | W25: 0 | X25: 0 | Y25: 0 | Z25: 0 | AA25: 0 | AC25: 0 | AD25: 0 | AE25: 0 | AF25: 0 | AG25: 0 | AH25: 0
A26: Other Assets | C26: 1730953.2 | D26: 2242773.3 | E26: 2576611.4 | F26: 2421749.5 | G26: 2215587.6 | H26: 2009425.8 | I26: 1933263.9 | J26: 1716842 | K26: 1498220.1 | L26: 1498220.1 | M26: 1665326.3 | N26: 1523904.4 | P26: 1904292.1 | Q26: 1862152.9 | R26: 2339812.6 | S26: 2108073.3 | T26: 1886334 | U26: 1654514.7 | V26: 1542786.1 | W26: 1311036.2 | X26: 1206896.9 | Y26: 1123157.6 | Z26: 1323418.3 | AA26: 1239679.1 | AC26: 7520138.8 | AD26: 7997655.5 | AE26: 8538916.2 | AF26: 10458377 | AG26: 12828548 | AH26: 13274538
A27: Total Assets | B27: =B4+B7+B8+B14+B17+B21 -> 451530040 | C27: 4.5572392e+08 | D27: 4.6578515e+08 | E27: 4.6190769e+08 | F27: 4.6343858e+08 | G27: 5.0909114e+08 | H27: 4.8347574e+08 | I27: 4.8356108e+08 | J27: 4.9244449e+08 | K27: 4.9855565e+08 | L27: 5.065078e+08 | M27: 5.0337112e+08 | N27: ############ | O27: =O4+O7+O8+O14+O17+O21 -> 512833379 | P27: =P4+P7+P8+P14+P17+P21 -> 5.0843806e+08 | Q27: =Q4+Q7+Q8+Q14+Q17+Q21 -> 5.1359248e+08 | R27: =R4+R7+R8+R14+R17+R21 -> 5.0725105e+08 | S27: =S4+S7+S8+S14+S17+S21 -> 5.0706242e+08 | T27: =T4+T7+T8+T14+T17+T21 -> 5.1067156e+08 | U27: =U4+U7+U8+U14+U17+U21 -> 5.4810082e+08 | V27: =V4+V7+V8+V14+V17+V21 -> 5.5069305e+08 | ... AH27: =AH4+AH7+AH8+AH14+AH17+AH21 -> 6.0533651e+08
A28: LIABILITIES
A29: Savings Deposits - Withdrawable deposits - FOSA) | B29: 69890663 | C29: 48619914 | D29: 52129056 | E29: 54461821 | F29: 52365497 | G29: 56273331 | H29: 55246420 | I29: 50771324 | J29: 53762394 | K29: 54101794 | L29: 55895297 | M29: 52253128 | N29: 53033455 | O29: 78206021 | P29: 54611474 | Q29: 53486462 | R29: 58088767 | S29: 53467624 | T29: 49573059 | U29: 51924404 | V29: 48308772 | W29: 54116646 | X29: 49012823 | Y29: 46042983 | Z29: 47797734 | AA29: 45213622 | AB29: =76648463 -> 76648463 | AC29: 49028920 | AD29: 57551288 | AE29: 53386306 | AF29: 54671332 | AG29: 54918951 | AH29: 54882496
A30: Short Term Deposits (e.g Fixed deposits, special savings) | C30: 4717946.3 | D30: 4404841.8 | E30: 4441706.8 | F30: 4510770.8 | G30: 4452334.8 | H30: 3285734.3 | I30: 2981734.3 | J30: 3431734.3 | K30: 2981734.3 | L30: 1488734.3 | M30: 2908734.3 | N30: 3386734.3 | P30: 3391734.3 | Q30: 3931734.3 | R30: 3469497.3 | S30: 3365697.3 | T30: 3670697.3 | U30: 3659534.3 | V30: 3503534.3 | W30: 3404734.3 | X30: 3410534.3 | Y30: 4160534.3 | Z30: 4438546.3 | AA30: 4503546.3 | AC30: 3653546.3 | AD30: 4238546.3 | AE30: 4131546.3 | AF30: 4137226.3 | AG30: 3887226.3 | AH30: 5915226.3
A31: Non withdrawable deposits (BOSA member deposits) | B31: 275781981 | C31: 3.0033339e+08 | D31: 3.0596066e+08 | E31: 3.1022242e+08 | F31: 3.1310114e+08 | G31: 3.1633245e+08 | H31: 3.2154503e+08 | I31: 3.2558706e+08 | J31: 3.2888016e+08 | K31: 3.3295585e+08 | L31: 3.3408892e+08 | M31: 3.3881256e+08 | N31: ############ | O31: 315654301 | P31: 3.4355035e+08 | Q31: 3.4826146e+08 | R31: 3.5313295e+08 | S31: 3.5920512e+08 | T31: 3.6344925e+08 | U31: 3.6674926e+08 | V31: 3.7078928e+08 | W31: 3.7447439e+08 | X31: 3.817659e+08 | Y31: 3.8602082e+08 | Z31: 3.8398291e+08 | AA31: 3.8769208e+08 | AB31: =365405894 -> 365405894 | AC31: 3.9843404e+08 | AD31: 4.0246705e+08 | AE31: 4.0907041e+08 | AF31: 4.1371467e+08 | AG31: 4.1222715e+08 | AH31: 4.1550032e+08
A32: Total Deposit liabilities | B32: =SUM(B29:B31) -> 345672644 | C32: 3.5367125e+08 | D32: 3.6249455e+08 | E32: 3.6912595e+08 | F32: 3.6997741e+08 | G32: 3.7705812e+08 | H32: 3.8007718e+08 | I32: 3.7934012e+08 | J32: 3.8607429e+08 | K32: 3.9003938e+08 | L32: 3.9147295e+08 | M32: 3.9397442e+08 | N32: ############ | O32: =SUM(O29:O31) -> 393860322 | P32: =SUM(P29:P31) -> 4.0155356e+08 | Q32: =SUM(Q29:Q31) -> 4.0567966e+08 | R32: =SUM(R29:R31) -> 4.1469122e+08 | S32: =SUM(S29:S31) -> 4.1603844e+08 | T32: =SUM(T29:T31) -> 4.16693e+08 | U32: =SUM(U29:U31) -> 4.223332e+08 | V32: =SUM(V29:V31) -> 4.2260159e+08 | ... AH32: =SUM(AH29:AH31) -> 4.7629804e+08
A33: Accounts Payable & Other Liabilities | B33: =SUM(B34:B39) -> 20053673 | C33: =SUM(C34:C39) -> -10848325 | D33: =SUM(D34:D39) -> -11733167 | E33: =SUM(E34:E39) -> -25229723 | F33: =SUM(F34:F39) -> -223036.26 | G33: =SUM(G34:G39) -> -1928534.4 | H33: =SUM(H34:H39) -> 5188038.4 | I33: =SUM(I34:I39) -> 3229056.5 | ... AH33: =SUM(AH34:AH39) -> 18271407
A34: Tax Payable | B34: 820709 | C34: -11696.01 | D34: -10315.53 | E34: 808224.05 | F34: 809073.08 | G34: -170385.89 | H34: -164901.78 | I34: -164786.78 | J34: -165862.78 | K34: -162781.58 | L34: -134052.39 | M34: -131899.24 | N34: -131899.24 | O34: 458403 | P34: -131198.51 | Q34: -130837.51 | R34: 803920.86 | S34: -111224 | T34: -109573.67 | U34: -119251.35 | V34: -119251.35 | W34: -135706.09 | X34: -135574.09 | Y34: 0 | Z34: 1506.26 | AA34: 1506.26 | AB34: =56988 -> 56988 | AC34: 3006.26 | AD34: 4700.8 | AE34: 1046422.8 | AF34: -163269.82 | AG34: -160038.44 | AH34: -156776.11
A35: Dividends Payable | B35: 16378056 | C35: 988 | D35: 988 | E35: -16238469 | F35: -16242182 | G35: 0 | H35: -62443.5 | I35: -65274 | J35: -67724 | K35: -68074 | L35: -71914 | M35: -73198 | N35: -73198 | O35: 18880398 | P35: 0 | Q35: -7125 | R35: -18123686 | S35: -18196477 | T35: -18197789 | U35: -18196723 | V35: -18197798 | W35: 0 | X35: -2638 | Y35: 0 | Z35: 0 | AA35: 0 | AB35: =21729256 -> 21729256 | AC35: 0 | AD35: 0 | AE35: -24213627 | AF35: -11125.33 | AG35: -75752.82 | AH35: -91453.98
A36: Deferred Tax Liability | C36: 0 | D36: 0 | E36: 0 | F36: 0 | G36: 0 | H36: 0 | I36: 0 | J36: 0 | K36: 0 | L36: 0 | M36: 0 | N36: 0 | P36: 0 | Q36: 0 | R36: 0 | S36: 0 | T36: 0 | U36: 0 | V36: 0 | W36: 0 | X36: 0 | Y36: 0 | Z36: 0 | AA36: 0 | AC36: 0 | AD36: 0 | AE36: 0 | AF36: 0 | AG36: 0 | AH36: 0
A37: Retirement Benefits Liability | C37: 0 | D37: 0 | E37: 0 | F37: 0 | G37: 0 | H37: 0 | I37: 0 | J37: 0 | K37: 0 | L37: 0 | M37: 0 | N37: 0 | P37: 0 | Q37: 0 | R37: 0 | S37: 0 | T37: 0 | U37: 0 | V37: 0 | W37: 0 | X37: 0 | Y37: 0 | Z37: 0 | AA37: 0 | AC37: 0 | AD37: 0 | AE37: 0 | AF37: 0 | AG37: 0 | AH37: 0
A38: Other Liabilities | B38: 2854908 | C38: -10837617 | D38: -11723840 | E38: -9799478.4 | F38: 15210072 | G38: -1758148.6 | H38: -2084616.3 | I38: -3415882.7 | J38: -4074270.1 | K38: -4600575.4 | L38: 1033513.5 | M38: -4294228 | N38: -4409726.3 | O38: 3082546 | P38: -6472183 | Q38: -6310265.7 | R38: -6655418.5 | S38: 15063823 | T38: 14302599 | U38: 14264929 | V38: 14210083 | W38: -3815799.8 | X38: -4461255.8 | Y38: -5249612.8 | Z38: -10451210 | AA38: -10631053 | AB38: =3624698 -> 3624698 | AC38: 17280886 | AD38: 13523914 | AE38: 14066134 | AF38: -12125154 | AG38: -12096715 | AH38: -12305363
A39: External Borrowings | C39: 0 | D39: 0 | E39: 0 | F39: 0 | G39: 0 | H39: 7500000 | I39: 6875000 | J39: 6875000 | K39: 6250000 | L39: 5625000 | M39: 4375000 | N39: 3750000 | O39: 3750000 | P39: 3125000 | Q39: 2500000 | R39: 1875000 | S39: 1250000 | T39: 587500 | U39: 30000000 | V39: 30145851 | W39: 24965766 | X39: 22665367 | Y39: 20210492 | Z39: 17725088 | AA39: 17843777 | AB39: =15259863 -> 15259863 | AC39: 12211962 | AD39: 39740029 | AE39: 37649095 | AF39: 38449578 | AG39: 33710077 | AH39: 30825000
A40: Total Liabilities | B40: =B32+B33 -> 365726317 | C40: =C32+C33 -> 3.4282293e+08 | D40: =D32+D33 -> 3.5076139e+08 | E40: =E32+E33 -> 3.4389623e+08 | F40: =F32+F33 -> 3.6975438e+08 | G40: =G32+G33 -> 3.7512959e+08 | H40: =H32+H33 -> 3.8526522e+08 | I40: =I32+I33 -> 3.8256918e+08 | ... AH40: =AH32+AH33 -> 4.9456945e+08
A41: EQUITY
A42: Share Capital (Members share capital per Bylaws) | B42: 49733041 | C42: 48839826 | D42: 48839126 | E42: 48833771 | F42: 48832915 | G42: 49353719 | H42: 49347619 | I42: 49625271 | J42: 49750025 | K42: 49751526 | L42: 49837940 | M42: 49834064 | N42: 50054270 | O42: 51874160 | P42: 50143975 | Q42: 50273068 | R42: 50290425 | S42: 50290175 | T42: 51040285 | U42: 51303291 | V42: 51307235 | W42: 51362101 | X42: 51364351 | Y42: 52276240 | Z42: 52276640 | AA42: 52704273 | AB42: =55353403 -> 55353403 | AC42: 52698373 | AD42: 52688333 | AE42: 53075741 | AF42: 53312358 | AG42: 53436217 | AH42: 53952992
A43: Capital Grants | C43: 0 | D43: 0 | E43: 0 | F43: 0 | G43: 0 | H43: 0 | I43: 0 | J43: 0 | K43: 0 | L43: 0 | M43: 0 | N43: 0 | P43: 0 | Q43: 0 | R43: 0 | S43: 0 | T43: 0 | U43: 0 | V43: 0 | W43: 0 | X43: 0 | Y43: 0 | Z43: 0 | AA43: 0 | AC43: 0 | AD43: 0 | AE43: 0 | AF43: 0 | AG43: 0 | AH43: 0
A45: Retained Earnings | B45: =B47+B46 -> 20707704 | C45: =C47+C46 -> 49687221 | D45: =D47+D46 -> 51810696 | E45: =E47+E46 -> 54803755 | F45: =F47+F46 -> 29488319 | G45: =G47+G46 -> 30786332 | H45: =H47+H46 -> 33499930 | I45: =I47+I46 -> 36003656 | ... AH45: =AH47+AH46 -> 39713809
A46: Prior Years' Retained Earnings | B46: 20133729 | C46: 20141940 | D46: 20141940 | E46: 20141940 | F46: 20707704 | G46: 20707704 | H46: 20707704 | I46: 20707704 | J46: 20707704 | K46: 20707704 | L46: 20707704 | M46: 20707704 | N46: 20707704 | O46: 20707704 | P46: 20707704 | Q46: 20707704 | R46: 20707704 | S46: 20707704 | T46: 20707704 | U46: 20707704 | V46: 20707704 | W46: 20707704 | X46: 20707704 | Y46: 20707704 | Z46: 23827293 | AA46: 23827293 | AB46: =23827293 -> 23827293 | AC46: 23827293 | AD46: 23957293 | AE46: 23957293 | AF46: 23957293 | AG46: 23957293 | AH46: 23957293
A47: Current Year's Surplus | B47: =20707704-20133729 -> 573975 | C47: 29545281 | D47: 31668756 | E47: 34661815 | F47: 8780615.2 | G47: 10078628 | H47: 12792226 | I47: 15295952 | J47: 17982356 | K47: 21275493 | L47: 22673684 | M47: 23616286 | N47: 25576670 | O47: =23827293-20707704 -> 3119589 | P47: 24148231 | Q47: 25517300 | R47: 28298914 | S47: 6657004.5 | T47: 10397058 | U47: 12444702 | V47: 14674658 | W47: 16670458 | X47: 18318561 | Y47: 19582859 | Z47: 22528274 | AA47: 24182889 | AB47: =27482766-AB46 -> 3655473 | AC47: 118176.47 | AD47: 6107729.4 | AE47: 9124184.1 | AF47: 12420134 | AG47: 14548196 | AH47: 15756516
A49: Other Equity Accounts | B49: =SUM(B50:B54) -> 12421535 | C49: =SUM(C50:C54) -> 14373941 | D49: =SUM(D50:D54) -> 14373941 | E49: =SUM(E50:E54) -> 14373941 | F49: =SUM(F50:F54) -> 15362976 | G49: =SUM(G50:G54) -> 15362976 | H49: =SUM(H50:H54) -> 15362976 | I49: =SUM(I50:I54) -> 15362976 | O49: =SUM(O50:O54) -> 17100258 | P49: =SUM(P50:P54) -> 15362976 | Q49: =SUM(Q50:Q54) -> 15362976 | R49: =SUM(R50:R54) -> 15362976 | S49: =SUM(S50:S54) -> 15362976 | T49: =SUM(T50:T54) -> 15362976 | U49: =SUM(U50:U54) -> 15362976 | V49: =SUM(V50:V54) -> 15362976 | ... AH49: =SUM(AH50:AH54) -> 17100258
A50: Statutory Reserve | B50: 12421535 | C50: 11432500 | D50: 11432500 | E50: 11432500 | F50: 12421535 | G50: 12421535 | H50: 12421535 | I50: 12421535 | J50: 12421535 | K50: 12421535 | L50: 12421535 | M50: 12421535 | N50: 12421535 | O50: 14158817 | P50: 12421535 | Q50: 12421535 | R50: 12421535 | S50: 12421535 | T50: 12421535 | U50: 12421535 | V50: 12421535 | W50: 12421535 | X50: 12421535 | Y50: 12421535 | Z50: 14158817 | AA50: 14158817 | AB50: 16091766 | AC50: 14158817 | AD50: 14158817 | AE50: 14158817 | AF50: 14158817 | AG50: 14158817 | AH50: 14158817
A51: Other Reserves (provide notes on these reserves) | C51: 2941441 | D51: 2941441 | E51: 2941441 | F51: 2941441 | G51: 2941441 | H51: 2941441 | I51: 2941441 | J51: 2941441 | K51: 2941441 | L51: 2941441 | M51: 2941441 | N51: 2941441 | O51: 2941441 | P51: 2941441 | Q51: 2941441 | R51: 2941441 | S51: 2941441 | T51: 2941441 | U51: 2941441 | V51: 2941441 | W51: 2941441 | X51: 2941441 | Y51: 2941441 | Z51: 2941441 | AA51: 2941441 | AB51: =2941441 -> 2941441 | AC51: 2941441 | AD51: 2941441 | AE51: 2941441 | AF51: 2941441 | AG51: 2941441 | AH51: 2941441
A52: Revaluation Reserves (Not part of core capital) | C52: 0 | D52: 0 | E52: 0 | F52: 0 | G52: 0 | H52: 0 | I52: 0 | J52: 0 | K52: 0 | L52: 0 | M52: 0 | N52: 0 | P52: 0 | Q52: 0 | R52: 0 | S52: 0 | T52: 0 | U52: 0 | V52: 0 | W52: 0 | X52: 0 | Y52: 0 | Z52: 0 | AA52: 0 | AC52: 0 | AD52: 0 | AE52: 0 | AF52: 0 | AG52: 0 | AH52: 0
A53: Proposed Dividends | C53: 0 | D53: 0 | E53: 0 | F53: 0 | G53: 0 | H53: 0 | I53: 0 | J53: 0 | K53: 0 | L53: 0 | M53: 0 | N53: 0 | P53: 0 | Q53: 0 | R53: 0 | S53: 0 | T53: 0 | U53: 0 | V53: 0 | W53: 0 | X53: 0 | Y53: 0 | Z53: 0 | AA53: 0 | AC53: 0 | AD53: 0 | AE53: 0 | AF53: 0 | AG53: 0 | AH53: 0
A54: Adjustment to Equity | C54: 0 | D54: 0 | E54: 0 | F54: 0 | G54: 0 | H54: 0 | I54: 0 | J54: 0 | K54: 0 | L54: 0 | M54: 0 | N54: 0 | P54: 0 | Q54: 0 | R54: 0 | S54: 0 | T54: 0 | U54: 0 | V54: 0 | W54: 0 | X54: 0 | Y54: 0 | Z54: 0 | AA54: 0 | AC54: 0 | AD54: 0 | AE54: 0 | AF54: 0 | AG54: 0 | AH54: 0
A55: Total Equity | B55: =B42+B43+B45+B49 -> 82862280 | C55: =C42+C43+C45+C49 -> 1.1290099e+08 | D55: =D42+D43+D45+D49 -> 1.1502376e+08 | E55: =E42+E43+E45+E49 -> 1.1801147e+08 | F55: =F42+F43+F45+F49 -> 93684210 | G55: =G42+G43+G45+G49 -> 95503026 | H55: =H42+H43+H45+H49 -> 98210524 | I55: =I42+I43+I45+I49 -> 1.009919e+08 | ... AH55: =AH42+AH43+AH45+AH49 -> 110767059
A56: Total Liabilities and Equity | B56: =B40+B55 -> 448588597 | C56: 4.5572392e+08 | D56: 4.6578515e+08 | E56: 4.6190769e+08 | F56: 4.6343858e+08 | G56: 4.7063261e+08 | H56: 4.8347574e+08 | I56: 4.8356108e+08 | J56: 4.9244449e+08 | K56: 4.9855565e+08 | L56: 5.065078e+08 | M56: 5.0337112e+08 | N56: ############ | O56: =O40+O55 -> 512833380 | P56: =P40+P55 -> 5.0843806e+08 | Q56: =Q40+Q55 -> 5.1359248e+08 | R56: =R40+R55 -> 5.0725105e+08 | S56: =S40+S55 -> 5.0706242e+08 | T56: =T40+T55 -> 5.1078376e+08 | U56: =U40+U55 -> 5.4810082e+08 | V56: =V40+V55 -> 5.5069305e+08 | ... AH56: =AH40+AH55 -> 6.0533651e+08
B57: =B27-B56 -> 2941443 | C57: =C27-C56 -> 0 | D57: =D27-D56 -> 0 | E57: =E27-E56 -> 0 | F57: =F27-F56 -> 0 | G57: =G27-G56 -> 38458526 | H57: =H27-H56 -> 0 | I57: =I27-I56 -> 0 | ... O57: =O27-O56 -> -1 | AB57: =AB27-AB56 -> 0 | AC57: =AC27-AC56 -> 0 | AD57: =AD27-AD56 -> 0 | AE57: =AE27-AE56 -> 0 | AF57: =AF27-AF56 -> 0 | AG57: =AG27-AG56 -> 0 | AH57: =AH27-AH56 -> 0

Sheet SCI
A1: SIRAJI SACCO SOCIETY LTD
A2: STATEMENT OF COMPREHENSIVE INCOME | B2: AUDITED 2020 | C2: 44197 | D2: 44228 | E2: 44256 | F2: 44287 | G2: 44317 | H2: 44348 | I2: 44378 | J2: 44409 | K2: 44440 | L2: 44470 | M2: 44501 | N2: 44531 | O2: Audited 2021 | P2: 44562 | Q2: 44593 | R2: 44621 | S2: 44652 | T2: 44682 | U2: 44713 | V2: 44743 | W2: 44774 | X2: 44805 | Y2: 44835 | Z2: 44866 | AA2: 44896 | AB2: Audited-2022 | AC2: 44949 | AD2: 44980 | AE2: 45008 | AF2: 45039 | AG2: 45069 | AH2: 45100
A3: Financial Income | B3: =B4+B7 -> 70190209 | C3: =C4+C7 -> 0 | D3: =D4+D7 -> 0 | E3: =E4+E7 -> 0 | F3: =F4+F7 -> 0 | G3: =G4+G7 -> 0 | H3: =H4+H7 -> 0 | I3: =I4+I7 -> 0 | ... AH3: =AH4+AH7 -> 52767997
A4: Financial Income from Loans Portfolio | B4: =SUM(B5:B6) -> 51495458 | C4: =SUM(C5:C6) -> 0 | D4: =SUM(D5:D6) -> 0 | E4: =SUM(E5:E6) -> 0 | F4: =SUM(F5:F6) -> 0 | G4: =SUM(G5:G6) -> 0 | H4: =SUM(H5:H6) -> 0 | I4: =SUM(I5:I6) -> 0 | ... AH4: =SUM(AH5:AH6) -> 34764523
A5: Interest on Loan Portfolio | B5: 51495458 | O5: 56513335 | P5: 3844004.8 | Q5: 7729784 | R5: 12404707 | S5: 16487319 | T5: 21025977 | U5: 25467928 | V5: 29342409 | W5: 33417144 | X5: 37362424 | Y5: 41867081 | Z5: 47562961 | AA5: 52071648 | AB5: =64179314 -> 64179314 | AC5: 4358170.5 | AD5: 8758899.3 | AE5: 14837953 | AF5: 19550529 | AG5: 24111294 | AH5: 28823120
A6: Fees & Commission on Loan Portfolio | P6: 540962.82 | Q6: 1070484.3 | R6: 1984459.7 | S6: 2854885.7 | T6: 3914697.1 | U6: 4742902.1 | V6: 5539853.9 | W6: 6679555.7 | X6: 8041236.5 | Y6: 8901025.9 | Z6: 9549357.7 | AA6: 10146526 | AC6: 1036416.9 | AD6: 1967467 | AE6: 2766826.4 | AF6: 3605432.2 | AG6: 4952268 | AH6: 5941403.2
A7: Financial Income from Investments in: | B7: =SUM(B8:B11) -> 18694751 | C7: =SUM(C8:C11) -> 0 | D7: =SUM(D8:D11) -> 0 | E7: =SUM(E8:E11) -> 0 | F7: =SUM(F8:F11) -> 0 | G7: =SUM(G8:G11) -> 0 | H7: =SUM(H8:H11) -> 0 | I7: =SUM(I8:I11) -> 0 | ... AH7: =SUM(AH8:AH11) -> 18003474
A8: Government Securities | P8: 0 | Q8: 0 | R8: 0 | S8: 0 | T8: 0 | U8: 0 | V8: 0 | W8: 0 | X8: 0 | Y8: 0 | Z8: 0 | AA8: 0 | AC8: 0 | AD8: 0 | AE8: 0 | AF8: 0 | AG8: 0 | AH8: 0
A9: Deposit with Banks and Other Financial Inst. | P9: 7670.96 | Q9: 119595.92 | R9: 119595.92 | S9: 119595.92 | T9: 119595.92 | U9: 119595.92 | V9: 256308.42 | W9: 256308.42 | X9: 509240.93 | Y9: 943568.04 | Z9: 948949.95 | AA9: 952893.95 | AC9: 14834.59 | AD9: 38322.08 | AE9: 38322.08 | AF9: 113571.56 | AG9: 180968.39 | AH9: 180968.39
A10: Other Investments - dividend & Interest incomes from investments | B10: 1628170 | O10: 1064174 | P10: 0 | Q10: 0 | R10: 0 | S10: 0 | T10: 0 | U10: 0 | V10: 0 | W10: 0 | X10: 0 | Y10: 0 | Z10: 0 | AA10: 0 | AB10: =1088762 -> 1088762 | AC10: 0 | AD10: 0 | AE10: 0 | AF10: 0 | AG10: 0 | AH10: 0
A11: Other Operating Income- Salary processing fees, transaction fees, membership fees | B11: 17066581 | O11: 21039578 | P11: 1639145.5 | Q11: 3049839.8 | R11: 6863554 | S11: 9073080.1 | T11: 11819891 | U11: 14523529 | V11: 17238563 | W11: 20030191 | X11: 22865741 | Y11: 25205252 | Z11: 27492786 | AA11: 30050564 | AB11: =29990976 -> 29990976 | AC11: 2567613.9 | AD11: 5014706.2 | AE11: 9108188.2 | AF11: 12411228 | AG11: 15495570 | AH11: 17822506
A12: Financial Expense | B12: =B13+B14+B15+B16+B17+B18 -> 15952622 | C12: =C13+C14+C15+C16+C17+C18 -> 0 | D12: =D13+D14+D15+D16+D17+D18 -> 0 | E12: =E13+E14+E15+E16+E17+E18 -> 0 | F12: =F13+F14+F15+F16+F17+F18 -> 0 | G12: =G13+G14+G15+G16+G17+G18 -> 0 | H12: =H13+H14+H15+H16+H17+H18 -> 0 | I12: =I13+I14+I15+I16+I17+I18 -> 0 | ... AH12: =AH13+AH14+AH15+AH16+AH17+AH18 -> 1801854.8
A13: Interest Expense on Deposits | B13: 13316672 | O13: 15883566 | P13: 0 | Q13: 0 | R13: 0 | S13: 3089 | T13: 3089 | U13: 3089 | V13: 3089 | W13: 3089 | X13: 3089 | Y13: 3089 | Z13: 3089 | AA13: 3089 | AB13: =17933530 -> 17933530 | AC13: 0 | AD13: 0 | AE13: 0 | AF13: 2754.04 | AG13: 2814.04 | AH13: 2814.04
A14: Cost of External Borrowings | B14: 2635950 | O14: 275000 | P14: 37500 | Q14: 75000 | R14: 112500 | S14: 150000 | T14: 150000 | U14: 777300 | V14: 923150.74 | W14: 923150.74 | X14: 1211643.3 | Y14: 1345660.9 | Z14: 1464349.9 | AA14: 1583038.9 | AB14: 1534256 | AC14: 43480.17 | AD14: 114691.45 | AE14: 616987.58 | AF14: 810663.95 | AG14: 1162908.3 | AH14: 1351914.3
A15: Dividend Expenses (on member shares) | P15: 0 | Q15: 0 | R15: 0 | S15: 0 | T15: 0 | U15: 0 | V15: 0 | W15: 0 | X15: 0 | Y15: 0 | Z15: 0 | AA15: 0 | AC15: 0 | AD15: 0 | AE15: 0 | AF15: 0 | AG15: 0 | AH15: 0
A16: Other Financial Expense | P16: 0 | Q16: 0 | R16: 0 | S16: 0 | T16: 0 | U16: 0 | V16: 0 | W16: 0 | X16: 0 | Y16: 0 | Z16: 0 | AA16: 0 | AC16: 0 | AD16: 0 | AE16: 0 | AF16: 0 | AG16: 0 | AH16: 0
A17: Fees & Commission Expense | P17: 5733.6 | Q17: 23778 | R17: 229235.97 | S17: 395726.17 | T17: 676799.73 | U17: 818152.08 | V17: 853343.98 | W17: 927203.19 | X17: 991363.6 | Y17: 1165187.9 | Z17: 1351671.4 | AA17: 1391455.2 | AC17: 9403.4 | AD17: 86423.26 | AE17: 90397.26 | AF17: 328683.8 | AG17: 418395.47 | AH17: 447126.47
A18: Other Expense | P18: 0 | Q18: 0 | R18: 0 | S18: 0 | T18: 0 | U18: 0 | V18: 0 | W18: 0 | X18: 0 | Y18: 0 | Z18: 0 | AA18: 0 | AC18: 0 | AD18: 0 | AE18: 0 | AF18: 0 | AG18: 0 | AH18: 0
A19: Net Financial Income/(Loss) | B19: =B3-B12 -> 54237587 | C19: =C3-C12 -> 0 | D19: =D3-D12 -> 0 | E19: =E3-E12 -> 0 | F19: =F3-F12 -> 0 | G19: =G3-G12 -> 0 | H19: =H3-H12 -> 0 | I19: =I3-I12 -> 0 | ... AH19: =AH3-AH12 -> 50966142
A20: Allowance for Loan Loss | B20: =B21-B22 -> 9517102 | C20: =C21-C22 -> 0 | D20: =D21-D22 -> 0 | E20: =E21-E22 -> 0 | F20: =F21-F22 -> 0 | G20: =G21-G22 -> 0 | H20: =H21-H22 -> 0 | I20: =I21-I22 -> 0 | ... AH20: =AH21-AH22 -> 4057723.6
A21: Provision for Loan Losses | B21: 9517102 | O21: 10512504 | P21: 615943.97 | Q21: 1227795 | R21: 1851927.6 | S21: 2475711.6 | T21: 3111349 | U21: 3751576 | V21: 4392538.2 | W21: 5049764.8 | X21: 5723447.1 | Y21: 6403654 | Z21: 7062278.8 | AA21: 7732793 | AB21: =7732793 -> 7732793 | AC21: 661135 | AD21: 1338106.6 | AE21: 2009961.9 | AF21: 2680808.6 | AG21: 3370312 | AH21: 4057723.6
A22: Value of Loans Recovered | P22: 0 | Q22: 0 | R22: 0 | S22: 0 | T22: 0 | U22: 0 | V22: 0 | W22: 0 | X22: 0 | Y22: 0 | Z22: 0 | AA22: 0 | AC22: 0 | AD22: 0 | AE22: 0 | AF22: 0 | AG22: 0 | AH22: 0
A23: Operating Expenses | B23: =SUM(B24:B28) -> 39340573 | C23: =SUM(C24:C28) -> 0 | D23: =SUM(D24:D28) -> 0 | E23: =SUM(E24:E28) -> 0 | F23: =SUM(F24:F28) -> 0 | G23: =SUM(G24:G28) -> 0 | H23: =SUM(H24:H28) -> 0 | I23: =SUM(I24:I28) -> 0 | ... AH23: =SUM(AH24:AH28) -> 32096024
A24: Personnel Expenses | B24: 16418976 | O24: 20376651 | P24: 1700220.4 | Q24: 3342068.9 | R24: 5225365.2 | S24: 6840226.4 | T24: 8522515.2 | U24: 10339431 | V24: 12201731 | W24: 14200342 | X24: 16236070 | Y24: 18443876 | Z24: 20593639 | AA24: 23191441 | AB24: =23735441 -> 23735441 | AC24: 2090302 | AD24: 4394560.2 | AE24: 7006559.2 | AF24: 8861280 | AG24: 11162970 | AH24: 13645152
A25: Governance Expenses | B25: 2622237 | O25: 3297054 | P25: 1003210 | Q25: 1549918 | R25: 3587658 | S25: 2942983 | T25: 3098113 | U25: 3331279 | V25: 4113663.5 | W25: 4469378.5 | X25: 5420652.5 | Y25: 6967934.9 | Z25: 7421422.3 | AA25: 7563067.3 | AB25: =7563067 -> 7563067 | AC25: 198550 | AD25: 574414 | AE25: 2788716 | AF25: 2373899 | AG25: 2501609 | AH25: 3174009
A26: Marketing Expenses | B26: 1985051 | O26: 1275153 | P26: 89342 | Q26: 215796 | R26: 398821 | S26: 870956 | T26: 1086256 | U26: 1402843.3 | V26: 1557253.3 | W26: 1761943.3 | X26: 2118921.3 | Y26: 2593386.3 | Z26: 3046311.3 | AA26: 3263701.3 | AB26: =2800096 -> 2800096 | AC26: 97031 | AD26: 324145 | AE26: 637980 | AF26: 865351 | AG26: 1433807 | AH26: 1883721
A27: Depreciation and Amortization Charges | P27: 290207.19 | Q27: 580414.38 | R27: 872972.5 | S27: 1165530.6 | T27: 1466473.7 | U27: 1767416.9 | V27: 2068360 | W27: 2369303.1 | X27: 2670246.2 | Y27: 2971189.3 | Z27: 3272132.5 | AA27: 3573075.6 | AB27: =2466022 -> 2466022 | AC27: 352242.52 | AD27: 734632.54 | AE27: 1101948.8 | AF27: 1501026.8 | AG27: 1900104.7 | AH27: 2299182.7
A28: Administrative Expenses | B28: 18314309 | O28: 17536475 | P28: 1491513.5 | Q28: 2787752 | R28: 4139831.1 | S28: 7023723.3 | T28: 8358480 | U28: 10192090 | V28: 11563271 | W28: 13982491 | X28: 16058574 | Y28: 17351057 | Z28: 18786661 | AA28: 20712855 | AB28: =20907761 -> 20907761 | AC28: 2023828 | AD28: 3097057.5 | AE28: 4366920 | AF28: 6828524.3 | AG28: 9231349.4 | AH28: 11093959
A29: Net Operating Income | B29: =B19-B20-B23 -> 5379912 | C29: =C19-C20-C23 -> 0 | D29: =D19-D20-D23 -> 0 | E29: =E19-E20-E23 -> 0 | F29: =F19-F20-F23 -> 0 | G29: =G19-G20-G23 -> 0 | H29: =H19-H20-H23 -> 0 | I29: =I19-I20-I23 -> 0 | ... AH29: =AH19-AH20-AH23 -> 14812394
A30: Net Non- Operating Income/ (Expense) | B30: =B31-B32 -> 0 | C30: =C31-C32 -> 0 | D30: =D31-D32 -> 0 | E30: =E31-E32 -> 0 | F30: =F31-F32 -> 0 | G30: =G31-G32 -> 0 | H30: =H31-H32 -> 0 | I30: =I31-I32 -> 0 | ... AH30: =AH31-AH32 -> 0
A31: Non- Operating Income | C31: 0 | D31: 0 | E31: 0 | F31: 0 | G31: 0 | H31: 0 | I31: 0 | J31: 0 | K31: 0 | L31: 0 | M31: 0 | N31: 0 | P31: 0 | Q31: 0 | R31: 0 | S31: 0 | T31: 0 | U31: 0 | V31: 0 | W31: 0 | AC31: 0 | AD31: 0 | AE31: 0 | AF31: 0 | AG31: 0 | AH31: 0
A32: Non- Operating Expense | C32: 0 | D32: 0 | E32: 0 | F32: 0 | G32: 0 | H32: 0 | I32: 0 | J32: 0 | K32: 0 | L32: 0 | M32: 0 | N32: 0 | P32: 0 | Q32: 0 | R32: 0 | S32: 0 | T32: 0 | U32: 0 | V32: 0 | W32: 0 | AC32: 0 | AD32: 0 | AE32: 0 | AF32: 0 | AG32: 0 | AH32: 0
A33: Net Income (Before Taxes and Donations) | B33: =B29+B30 -> 5379912 | C33: =C29+C30 -> 0 | D33: =D29+D30 -> 0 | E33: =E29+E30 -> 0 | F33: =F29+F30 -> 0 | G33: =G29+G30 -> 0 | H33: =H29+H30 -> 0 | I33: =I29+I30 -> 0 | ... AH33: =AH29+AH30 -> 14812394
A34: Taxes (Incomes taxes & Other payable to KRA) | B34: 424469 | C34: 0 | D34: 0 | E34: 0 | F34: 0 | G34: 0 | H34: 0 | I34: 0 | J34: 0 | K34: 0 | L34: 0 | M34: 0 | N34: 0 | O34: 781555 | P34: 0 | Q34: 0 | R34: 0 | S34: 0 | T34: 0 | U34: 0 | V34: 0 | W34: 0 | AB34: 921342 | AC34: 0 | AD34: 0 | AE34: 0 | AF34: 0 | AG34: 0 | AH34: 0
A35: Net Income (After Taxes before Donations) | B35: =B33-B34 -> 4955443 | C35: =C33-C34 -> 0 | D35: =D33-D34 -> 0 | E35: =E33-E34 -> 0 | F35: =F33-F34 -> 0 | G35: =G33-G34 -> 0 | H35: =H33-H34 -> 0 | I35: =I33-I34 -> 0 | ... AH35: =AH33-AH34 -> 14812394
A36: Donations | C36: 0 | D36: 0 | E36: 0 | F36: 0 | G36: 0 | H36: 0 | I36: 0 | J36: 0 | K36: 0 | L36: 0 | M36: 0 | N36: 0 | P36: 0 | Q36: 0 | R36: 0 | S36: 0 | T36: 0 | U36: 0 | V36: 0 | W36: 0 | AC36: 0 | AD36: 0 | AE36: 0 | AF36: 0 | AG36: 0 | AH36: 0
A37: Net Income/(After Taxes and Donations) | B37: =B35+B36 -> 4955443 | C37: =C35-C36 -> 0 | D37: =D35-D36 -> 0 | E37: =E35-E36 -> 0 | F37: =F35-F36 -> 0 | G37: =G35-G36 -> 0 | H37: =H35-H36 -> 0 | I37: =I35-I36 -> 0 | J37: =J35-J36 -> 0 | ... AI37: =AI35-AI36 -> 0

Sheet Sheet1
B2: Year | C2: AUDITED 2015 | D2: AUDITED 2016 | E2: AUDITED 2017 | F2: AUDITED 2018 | G2: 43466 | H2: 43497 | I2: 43525 | J2: 43556 | K2: 43586 | L2: 43617
A3: 2 | B3: Total Assets | C3: 4.6351889e+08 | D3: 4.5637093e+08 | E3: 4.3683362e+08 | F3: 590186392 | G3: 6.0231394e+08 | H3: 6.2625108e+08 | I3: 5.9828697e+08 | J3: 5.8907278e+08 | K3: 6.1710155e+08 | L3: 6.0417723e+08
A4: 3 | B4: Total Deposits | C4: 3.6391029e+08 | D4: 3.5281156e+08 | E4: 3.4681983e+08 | F4: 433315333 | G4: 4.3839535e+08 | H4: 4.542002e+08 | I4: 4.7118357e+08 | J4: 4.6306008e+08 | K4: 4.8617864e+08 | L4: 4.6622117e+08
A5: 3.1 | B5: Deposits-Members(BOSA) | C5: 2.4228165e+08 | D5: 2.4464437e+08 | E5: 2.4323434e+08 | F5: 365696388 | G5: 3.7313088e+08 | H5: 3.8056337e+08 | I5: 3.899621e+08 | J5: 3.9463998e+08 | K5: 3.9710517e+08 | L5: 4.0401425e+08
A6: 3.2 | B6: Deposits-Customers(FOSA) | C6: 4074376.9 | D6: 4984401.3 | E6: 5076228.9 | F6: 67618945 | G6: 14363008 | H6: 15611949 | I6: 13612359 | J6: 14419909 | K6: 14679037 | L6: 13096149
A7: 4 | B7: External Borrowing | C7: 782851.88 | D7: 782851.88 | E7: 782851.88 | F7: 0 | G7: 0 | H7: 0 | I7: 0 | J7: 0 | K7: 0 | L7: 0
A8: 4.1 | B8: Short term Liabilities | C8: 4642444.9 | D8: 27506534 | E8: 4912342.2 | F8: 58156529 | G8: 3901907.3 | H8: 4415903.4 | I8: -44130681 | J8: 10574287 | K8: 12876255 | L8: 10617410
A9: 5.1 | B9: Core Capital | C9: 94944699 | D9: 75269883 | E9: 78350880 | F9: 88729697 | G9: 1.5578813e+08 | H9: 1.6340642e+08 | I9: 1.6700553e+08 | J9: 1.1120986e+08 | K9: 1.138181e+08 | L9: 1.231101e+08
A10: 5.2 | B10: Institutional Capital | C10: 85006164 | D10: 65331348 | E10: 67704199 | F10: 65523502 | G10: 1.3199681e+08 | H10: 1.3957898e+08 | I10: 1.42917e+08 | J10: 87051631 | K10: 89639871 | L10: 98730332
A11: 5.3 | B11: Total Capital | C11: 94944699 | D11: 75269883 | E11: 78350880 | F11: 92958252 | G11: 1.6001668e+08 | H11: 1.6763498e+08 | I11: 1.7123408e+08 | J11: 1.1543841e+08 | K11: 1.1804665e+08 | L11: 1.2733866e+08
A12: 7 | B12: Net Loans & advances | C12: 2.9963107e+08 | D12: 3.0964314e+08 | E12: 3.1063977e+08 | F12: 467465209 | G12: 4.7291977e+08 | H12: 4.7868736e+08 | I12: 4.7578771e+08 | J12: 4.7958254e+08 | K12: 4.8126667e+08 | L12: 4.8527697e+08
A13: 7.1 | B13: Gross Loans & advances | C13: 3.0960349e+08 | D13: 3.1961557e+08 | E13: 3.2061219e+08 | F13: 478678153 | G13: 4.8413271e+08 | H13: 4.899003e+08 | I13: 4.8760561e+08 | J13: 4.9160208e+08 | K13: 4.9348786e+08 | L13: 4.9769982e+08
A14: 7.3 | B14: Allowance for loan losses | C14: 9972423.1 | D14: 9972423.1 | E14: 9972423.1 | F14: 11212944 | G14: 11212944 | H14: 11212944 | I14: 11817894 | J14: 12019544 | K14: 12221194 | L14: 12422844
... A19: 10 | B19: Total Expenses (FinCosts + OpEx) | C19: 22339455 | D19: 4546921.1 | E19: 5916993.1 | F19: 68345005 | G19: 18479434 | H19: 19450021 | I19: 21786998 | J19: 6653981.1 | K19: 12263359 | L19: 13807775
B21: CORE CAPITAL | C21: 94.944699 | D21: 75.269883 | E21: 78.35088 | F21: 88.729697 | G21: 155.78813 | H21: 163.40642 | I21: 167.00553 | J21: 111.20986 | K21: 113.8181 | L21: 123.1101
B22: CCA | C22: 0.20483458 | D22: 0.16493137 | E22: 0.17936092 | F22: 0.15034182 | G22: 0.25864938 | H22: 0.26092797 | I22: 0.2791395 | J22: 0.18878798 | K22: 0.18443982 | L22: 0.20376488
B23: ICA | C23: 0.18339309 | D23: 0.14315405 | E23: 0.15498853 | F23: 0.11102171 | G23: 0.21914952 | H23: 0.22288022 | I23: 0.23887701 | J23: 0.14777738 | K23: 0.14525951 | L23: 0.16341286
B24: CCD | C24: 0.26090139 | D24: 0.21334302 | E24: 0.22591234 | F24: 0.20476935 | G24: 0.3553599 | H24: 0.35976739 | I24: 0.35443835 | J24: 0.24016291 | K24: 0.23410757 | L24: 0.26405944
B25: Asset Quality
B26: NPL
B27: Earnings
B28: ROA | C28: 0.10366402 | D28: 0.0049791285 | E28: 0.0086990958 | F28: 0.021403287 | G28: 0.086521768 | H28: 0.092418745 | I28: 0.095308004 | J28: 0.025179366 | K28: 0.027427623 | L28: 0.036644694
B29: CIR | C29: 0.25741416 | D29: 0.47475461 | E29: 0.47309013 | F29: 0.59346691 | G29: 0.29062189 | H29: 0.28378981 | I29: 0.30491294 | J29: 0.3518848 | K29: 0.42614589 | L29: 0.38569897
B30: OER | C30: 0.050864587 | D30: 0.006821232 | E30: 0.012065152 | F30: 0.056671522 | G30: 0.054654004 | H30: 0.055574311 | I30: 0.067479629 | J30: 0.021463423 | K30: 0.030839954 | L30: 0.036261474
B31: MIN LIQ | C31: 0.28117848 | D31: 0.1804874 | E31: 0.14704211 | F31: 0.20525016 | G31: 0.26279967 | H31: 0.27638489 | I31: 0.26967942 | J31: 0.20183359 | K31: 0.21134839 | L31: 0.19694405
B32: TEC LIQ | C32: 0.18838483 | D32: 0.12915454 | E32: 0.10373806 | F32: 0.1770109 | G32: 0.2240215 | H32: 0.23200767 | I32: 0.21838892 | J32: 0.17267718 | K32: 0.17362602 | L32: 0.17125133
B33: EB | C33: 0.001688932 | D33: 0.0017153851 | E33: 0.0017921054 | F33: 0 | G33: 0 | H33: 0 | I33: 0 | J33: 0 | K33: 0 | L33: 0
B34: LIQ/TA | C34: 0.14978838 | D34: 0.10763133 | E34: 0.083528395 | F34: 0.14740407 | G34: 0.16450573 | H34: 0.16990382 | I34: 0.15588442 | J34: 0.13883827 | K34: 0.14041273 | L34: 0.13515776
B35: NEA | C35: 0.11800484 | D35: 0.12675515 | E35: 0.10067358 | F35: 0.053367462 | G35: 0.043302199 | H35: 0.058974292 | I35: 0.041797813 | J35: 0.039852185 | K35: 0.072852538 | L35: 0.054640365
B36: LB | C36: 0.01288188 | D36: 0.012663382 | E36: 0.013661078 | F36: 0.0051649463 | G36: 0.011631407 | H36: 0.01118682 | I36: 0.011457956 | J36: 0.010564849 | K36: 0.011089534 | L36: 0.010959528
B37: FITD | C37: 0.12176194 | D37: 0.11269646 | E37: 0.11464343 | F37: 0.0097586092 | G37: 0.0096455287 | H37: 0.0093098923 | I37: 0.0089743259 | J37: 0.009131763 | K37: 0.0086975334 | L37: 0.0090698477
B38: FICC | C38: 0.46669717 | D38: 0.52824067 | E38: 0.50746862 | F38: 0.047656592 | G38: 0.027142986 | H38: 0.025877532 | I38: 0.02531985 | J38: 0.038023203 | K38: 0.037151868 | L38: 0.03434775

Sheet DEC 2020
A1: MAGADI SACCO SOCIETY LIMITED
A2: PERFORMANCE AND COMPLIANCE REPORT AS AT : 31st December , 2020
B3: Prudential Standard | C3: Audited | D3: Returns | F3: AUDITED 2020 | G3: Aggregate for all Licensed Saccos
C4: 2019 | D4: 30th September , 2020 | E4: 31st December , 2020
A5: A. CAPITAL ADEQUACY
A6: Core Capital | B6: ≥10M | C6: =C33 -> 98409139 | D6: =D33 -> 1.5398554e+08 | E6: =E33 -> 1.7565742e+08 | F6: =F33 -> 82862280 | G6: =G33 -> 9.281382e+10 | H6: =F6-C6 -> -15546859
A7: Core Capital/Total Assets | B7: ≥10% | C7: =C33/C29 -> 0.149196 | D7: =D33/D29 -> 0.21974079 | E7: =E33/E29 -> 0.23992254 | F7: =F33/F29 -> 0.18351443 | G7: =G33/G29 -> 0.15852844
A8: Institutional Capital/Total Assets | B8: ≥8% | C8: =C34/C29 -> 0.11007419 | D8: =D34/D29 -> 0.18075965 | E8: =E34/E29 -> 0.2020382 | F8: =F34/F29 -> 0.073371063 | G8: =G34/G29 -> 0.092879022
A9: B. ASSET QUALITY
A10: NPL (Substandard+Doubtful+Loss) | B10: <5% | C10: =C35/C32 -> 0 | D10: =D35/D32 -> 0.066804616 | E10: =E35/E32 -> 0.058669004 | F10: =F35/F32 -> 0.10682593 | G10: =G35/G32 -> 0.081923116
A11: Non-Earning Assets | B11: <10% | C11: =C36/C29 -> 0.041460677 | D11: =D36/D29 -> 0.034504765 | E11: =E36/E29 -> 0.03147327 | F11: =F36/F29 -> 0.12852222 | G11: =G36/G29 -> 0.10331964
A12: Equity investments/Deposits | B12: <5% | C12: =C38/C31 -> 0.0086859989 | D12: =D38/D31 -> 0.007972688 | E12: =E38/E31 -> 0.0078282924 | F12: =F38/F31 -> 0.00029466029 | G12: =G38/G31 -> 0.033894147
A13: Equity investments/Core capital | B13: <40% | C13: =C38/C33 -> 0.042969139 | D13: =D38/D33 -> 0.027460728 | E13: =E38/E33 -> 0.024072738 | F13: =F38/F33 -> 0.0012292203 | G13: =G38/G33 -> 0.14648774
A14: C. EARNINGS RATING
A15: Yield on Gross Loans | C15: =C48/C32 -> 0.18432223 | D15: =D48/D32 -> 0.1292034 | E15: =E48/E32 -> 0.17383407 | F15: =F48/F32 -> 0.039498889 | G15: =G48/G32 -> 0.1744387
A16: Total Expense/Total Income | C16: =C49/C44 -> 0.81230275 | D16: =D49/D44 -> 0.33068826 | E16: =E49/E44 -> 0.33091343 | F16: =F49/F44 -> 0.92335239 | G16: =G49/G44 -> 0.69938821
A17: Net Income/Average Assets (ROA) | C17: =C50/C30 -> 0.02237977 | D17: =D50/D30 -> 0.081626281 | E17: =E50/E30 -> 0.10964544 | F17: =F50/F30 -> 0.0089196745 | G17: =G50/G30 -> 0.038410442
A18: Operating Expenses/Financial Income (OPEX) | C18: =C47/C44 -> 0.32162796 | D18: =D47/D44 -> 0.28452022 | E18: =E47/E44 -> 0.28396284 | F18: =F47/F44 -> 0.5604852 | G18: =G47/G44 -> 0.30079837
A19: D. LIQUIDITY
A20: Liquid Assets/Short-term Liabilities | B20: >15% | C20: =C40/C41 -> 0.59313783 | D20: =D40/D41 -> 1.4178168 | E20: =E40/E41 -> 2.0006732 | F20: =F40/F41 -> 0.90452941 | G20: =G40/G41 -> 0.6151057
A21: External Borrowing/Total Assets | B21: <25% | C21: =C42/C29 -> 1.1611647e-05 | D21: =D42/D29 -> 0.011921445 | E21: =E42/E29 -> 0.010282182 | F21: =F42/F29 -> 0 | G21: =G42/G29 -> 0.036576677
A22: Liquid Assets/Total Assets | C22: =C40/C29 -> 0.067680721 | D22: =D40/D29 -> 0.12936886 | E22: =E40/E29 -> 0.15742859 | F22: =F40/F29 -> 0.18018136 | G22: =G40/G29 -> 0.11724056
A23: E. STRUCTURE/SENSITIVITY TO RISK
A24: Gross loans /Total Assets | B24: 70-80 | C24: =C32/C29 -> 0.82800207 | D24: =D32/D29 -> 0.86523081 | E24: =E32/E29 -> 0.83846194 | F24: =F32/F29 -> 0.74666222 | G24: =G32/G29 -> 0.75523899
A25: Gross loans/Deposits | B25: >100% | C25: =C32/C31 -> 1.1218567 | D25: =D32/D31 -> 1.1431784 | E25: =E32/E31 -> 1.1364592 | F25: =F32/F31 -> 0.97531704 | G25: =G32/G31 -> 1.1023021
A26: Financial Investments/Total Assets | C26: =C39/C31 -> 0.11977917 | D26: =D39/D31 -> 0.007972688 | E26: =E39/E31 -> 0.0078282924 | F26: =F39/F31 -> 0.00029466029 | G26: =G39/G31 -> 0.067272667
A27: Dividends+Interest on Deposits/Total Income | C27: =C46/C44 -> 0.48412627 | D27: =D46/D44 -> 0.012481243 | E27: =E46/E44 -> 0.0115585 | F27: =F46/F44 -> 0.18972264 | G27: =G46/G44 -> 0.33833569
A28: F. KEY FINANCIAL STATISTICS | C28: 2015 | D28: 2016 | E28: 2017 | G28: AGGREGATE
A29: Total Assets | C29: 659596375 | D29: 7.0075991e+08 | E29: 7.321422e+08 | F29: =SFP!B27 -> 451530040 | G29: 5.8547109e+11
A30: Average Assets | C30: 6.2488266e+08 | D30: 6.6920187e+08 | E30: 6.9562445e+08 | F30: =(C29+F29)/2 -> 5.5556321e+08 | G30: 5.6966122e+11
A31: Total Deposits | C31: 486824375 | D31: 5.3038009e+08 | E31: 5.4016313e+08 | F31: =SFP!B32 -> 345672644 | G31: 4.0113376e+11
A32: Gross Loans | C32: 546147164 | D32: 6.0631906e+08 | E32: 6.1387337e+08 | F32: =SFP!B15 -> 337140421 | G32: 4.421706e+11
A33: Core Capital | C33: 98409139 | D33: 1.5398554e+08 | E33: 1.7565742e+08 | F33: =Financials!C14 -> 82862280 | G33: 9.281382e+10
A34: Institutional Capital | C34: 72604536 | D34: 1.2666911e+08 | E34: 1.4792069e+08 | F34: =Financials!C15 -> 33129239 | G34: 5.4377982e+10
A35: Non-performing Loans | C35: 0 | D35: 40504912 | E35: 36015340 | F35: =16172116+14580201+5263023 -> 36015340 | G35: 3.6223993e+10
A36: Non-Earning Assets | C36: 27347312 | D36: 24179556 | E36: 23042909 | F36: =Financials!C38 -> 58031641 | G36: 6.0490663e+10
A37: Property and Equipment | C37: 5678927 | D37: 5703357.5 | E37: 5726554 | F37: =Financials!C39 -> 23361056 | G37: 1.7300265e+10
A38: Equity Investments | C38: 4228556 | D38: 4228554.9 | E38: 4228554.9 | F38: =SFP!B12+SFP!B13 -> 101856 | G38: 1.3596086e+10
A39: Financial Investments | C39: 58311419 | D39: 4228554.9 | E39: 4228554.9 | F39: =SFP!B8 -> 101856 | G39: 2.6985337e+10
A40: Liquid Assets | C40: 44641958 | D40: 90656514 | E40: 1.1526011e+08 | F40: =SFP!B4+SFP!B11 -> 81357297 | G40: 6.8640959e+10
A41: Short-term Liabilities) | C41: 75264054 | D41: 63940921 | E41: 57610665 | F41: =SFP!B29+SFP!B30+SFP!B33-SFP!B39 -> 89944336 | G41: 1.1159213e+11
A42: External Borrowing | C42: 7659 | D42: 8354071 | E42: 7528019 | F42: =SFP!B39 -> 0 | G42: 2.1414587e+10
A43: Average Gross Loans | C43: 5.1241266e+08 | D43: 5.768587e+08 | E43: 5.7996732e+08 | F43: =(C32+E32)/2 -> 5.8001027e+08 | G43: 4.3131225e+11
A44: Total Income | C44: 119501967 | D44: 93225263 | E44: 1.2531687e+08 | F44: =SCI!B3 -> 70190209 | G44: 8.9459919e+10
A45: Net Financial Income/Loss | C45: 60865365 | D45: 88921235 | E45: 1.1943317e+08 | F45: =SCI!B19 -> 54237587 | G45: 5.3897612e+10
A46: Dividends+Interest on Deposits | C46: 57854041 | D46: 1163567.2 | E46: 1448475.1 | F46: =SCI!B13 -> 13316672 | G46: 3.0267483e+10
A47: Operating Expenses | C47: 38435174 | D47: 26524472 | E47: 35585335 | F47: =SCI!B23 -> 39340573 | G47: 2.6909398e+10
A48: Interest on Loan portfolio+Fees&Commission on Loan | C48: 100667063 | D48: 78338482 | E48: 1.0671211e+08 | F48: =SCI!B13+SCI!B15 -> 13316672 | G48: 7.7131665e+10
A49: Total Expenses | C49: 97071776 | D49: 30828500 | E49: 41469037 | F49: =SCI!B12+SCI!B20+SCI!B23 -> 64810297 | G49: 6.2567213e+10
A50: Net Income | C50: 13984730 | D50: 54624460 | E50: 76272050 | F50: =SCI!B37 -> 4955443 | G50: 2.1880939e+10
A51: G. AREAS OF IMPROVEMENT/REGULATORY CONCERNS
A52: 1
A53: 2
A54: 3
A55: 4
A56: Prepared by:
A58: Checked by:
A60: Approved by:
A62: DISCLAIMER: This report is prepared based on information submitted by the Sacco as at the stated date and may change upon verification by the Authority.

Sheet DEC 2019 REPORT
A1: EGERTON SACCO SOCIETY LIMITED
A2: PERFORMANCE AND COMPLIANCE REPORT AS AT : 31st December , 2019
B3: Prudential Standard | C3: Audited | D3: Returns | F3: Audited 2019 | G3: Aggregate for all Licensed Saccos
C4: 2018 | D4: 30th September , 2019 | E4: 31st December , 2019
A5: A. CAPITAL ADEQUACY
A6: Core Capital | B6: ≥10M | C6: 92958252 | D6: 1.14416e+08 | E6: 1.2704881e+08 | F6: =F33 -> #REF! | G6: 8.5391581e+10
A7: Core Capital/Total Assets | B7: ≥10% | C7: 0.15751126 | D7: 0.17943559 | E7: 0.19275909 | F7: =F6/F29 -> #REF! | G7: 0.15597716
A8: Institutional Capital/Total Assets | B8: ≥8% | C8: 0.11818998 | D8: 0.13976271 | E8: 0.15360974 | F8: =F34/F29 -> #REF! | G8: 0.091529477
A9: B. ASSET QUALITY
A10: NPL (Substandard+Doubtful+Loss) | B10: <5% | C10: 0 | D10: 0.057997794 | E10: 0.049062417 | F10: =F35/F32 -> #REF! | G10: 0.073407957
A11: Non-Earning Assets | B11: <10% | C11: 0.05336904 | D11: 0.043135899 | E11: 0.041315651 | F11: =F36/F29 -> #REF! | G11: 0.10567687
A12: Equity investments/Deposits | B12: <5% | C12: 0 | D12: 0.0086297878 | E12: 0.0086830722 | F12: =F38/F31 -> #REF! | G12: 0.034924323
A13: Equity investments/Core capital | B13: <40% | C13: 0 | D13: 0.036957724 | E13: 0.033282917 | F13: =F38/F33 -> #REF! | G13: 0.15379721
A14: C. EARNINGS RATING
A15: Yield on Gross Loans | C15: 0.1927038 | D15: 0.13877868 | E15: 0.18737466 | F15: =F48/F32 -> #REF! | G15: 0.16090341
A16: Total Expense/Total Income | C16: 0.79311986 | D16: 0.35836605 | E16: 0.33974951 | F16: =F49/F44 -> #REF! | G16: 0.7077997
A17: Net Income/Average Assets (ROA) | C17: 0.027977038 | D17: 0.081818348 | E17: 0.11400955 | F17: =F50/F30 -> #REF! | G17: 0.036975972
A18: Operating Expenses/Financial Income (OPEX) | C18: 0.30200757 | D18: 0.31934513 | E18: 0.30463818 | F18: =F47/F45 -> #REF! | G18: 0.31992697
A19: D. LIQUIDITY
A20: Liquid Assets/Short-term Liabilities | B20: >15% | C20: 1.1755674 | D20: 1.0116662 | E20: 1.4570234 | F20: =F40/F41 -> #REF! | G20: 0.54995224
A21: External Borrowing/Total Assets | B21: <25% | C21: 0 | D21: 0 | E21: 0 | F21: =F42/F29 -> #REF! | G21: 0.039238045
A22: Liquid Assets/Total Assets | C22: 0.14737887 | D22: 0.12043218 | E22: 0.149349 | F22: =F40/F29 -> #REF! | G22: 0.11016896
A23: E. STRUCTURE/SENSITIVITY TO RISK
A24: Gross loans /Total Assets | B24: 70-80 | C24: 0.81108665 | D24: 0.85847035 | E24: 0.82848691 | F24: =F32/F29 -> #REF! | G24: 0.75892188
A25: Gross loans/Deposits | B25: >100% | C25: 1.1046878 | D25: 1.1171503 | E25: 1.1213025 | F25: =F32/F31 -> #REF! | G25: 1.1048812
A26: Financial Investments/Total Assets | C26: 0.0097586092 | D26: 0.0086297878 | E26: 0.0086830722 | F26: =F39/F29 -> #REF! | G26: 0.059782935
A27: Dividends+Interest on Deposits/Total Income | C27: 0.48814819 | D27: 0.012035001 | E27: 0.012230217 | F27: =F46/F44 -> #REF! | G27: 0.32108527
A28: F. KEY FINANCIAL STATISTICS | C28: 2015 | D28: 2016 | E28: 2017 | G28: AGGREGATE
A29: Total Assets | C29: 590168948 | D29: 6.3764384e+08 | E29: 6.5910669e+08 | F29: =SFP!#REF! -> #REF! | G29: 5.4746207e+11
A30: Average Assets | C30: 5.6413338e+08 | D30: 6.1492399e+08 | E30: 6.4176168e+08 | F30: =(F29+C29)/2 -> #REF! | G30: 5.2079291e+11
A31: Total Deposits | C31: 433315333 | D31: 4.8999524e+08 | E31: 4.8698834e+08 | F31: =SFP!#REF! -> #REF! | G31: 3.7604128e+11
A32: Gross Loans | C32: 478678153 | D32: 5.4739833e+08 | E32: 5.4606127e+08 | F32: =SFP!#REF! -> #REF! | G32: 4.1548094e+11
A33: Core Capital | C33: 92958252 | D33: 1.14416e+08 | E33: 1.2704881e+08 | F33: =Financials!#REF! -> #REF! | G33: 8.5391581e+10
A34: Institutional Capital | C34: 69752057 | D34: 89118833 | E34: 1.0124521e+08 | F34: =Financials!#REF! -> #REF! | G34: 5.0108917e+10
A35: Non-performing Loans | C35: 0 | D35: 31747895 | E35: 26791086 | F35: =22604726+734025+3452334 -> 26791085 | G35: 3.0499607e+10
A36: Non-Earning Assets | C36: 31496750 | D36: 27505341 | E36: 27231422 | F36: =Financials!#REF! -> #REF! | G36: 5.7854076e+10
A37: Property and Equipment | C37: 7005759 | D37: 5982262.2 | E37: 5325780.8 | F37: =Financials!#REF! -> #REF! | G37: 1.7751024e+10
A38: Equity Investments | C38: 0 | D38: 4228554.9 | E38: 4228554.9 | F38: =SFP!#REF!+SFP!#REF! -> #REF! | G38: 1.3132987e+10
A39: Financial Investments | C39: 4228555 | D39: 4228554.9 | E39: 4228554.9 | F39: =SFP!#REF! -> #REF! | G39: 2.2480852e+10
A40: Liquid Assets | C40: 86978434 | D40: 76792836 | E40: 98436927 | F40: =SFP!#REF! -> #REF! | G40: 6.031333e+10
A41: Short-term Liabilities) | C41: 73988469 | D41: 75907286 | E41: 67560292 | F41: =SFP!#REF!+SFP!#REF!+SFP!#REF!-SFP!#REF! -> #REF! | G41: 1.0967012e+11
A42: External Borrowing | C42: 0 | D42: 0 | E42: 0 | F42: =SFP!#REF! -> #REF! | G42: 2.1481341e+10
A43: Average Gross Loans | C43: 445483841 | D43: 5.0462708e+08 | E43: 5.1208838e+08 | F43: =(C32+F32)/2 -> #REF! | G43: 3.9339201e+11
A44: Total Income | C44: 110748089 | D44: 89428467 | E44: 1.1935697e+08 | F44: =SCI!#REF! -> #REF! | G44: 7.9322865e+10
A45: Net Financial Income/Loss | C45: 56358341 | D45: 85938886 | E45: 1.1516619e+08 | F45: =SCI!#REF! -> #REF! | G45: 4.6800236e+10
A46: Dividends+Interest on Deposits | C46: 54061479 | D46: 1076271.7 | E46: 1459761.6 | F46: =SCI!#REF! -> #REF! | G46: 2.5469404e+10
A47: Operating Expenses | C47: 33446761 | D47: 28558545 | E47: 36360690 | F47: =SCI!#REF! -> #REF! | G47: 2.5377524e+10
A48: Interest on Loan portfolio+Fees&Commission on Loan | C48: 92243098 | D48: 75967218 | E48: 1.0231804e+08 | F48: =SCI!#REF! -> #REF! | G48: 6.6852299e+10
A49: Total Expenses | C49: 87836509 | D49: 32048126 | E49: 40551471 | F49: =SCI!#REF!+SCI!#REF! -> #REF! | G49: 5.61447e+10
A50: Net Income | C50: 15782781 | D50: 50312065 | E50: 73166962 | F50: =SCI!#REF! -> #REF! | G50: 1.9256824e+10
A51: G. AREAS OF IMPROVEMENT/REGULATORY CONCERNS
A52: 1
A53: 2
A54: 3
A55: 4
A56: Prepared by:
A58: Checked by: Nelly Kulei
A60: Approved by: Peter Owira
A62: DISCLAIMER: This report is prepared based on information submitted by the Sacco as at the stated date and may change upon verification by the Authority.
C63: 22nd January 2020
