Workbook
Name BALANCE1_LDA01: '[1]Financial Statements'!$E$112
Name BALANCE1_LDA12: '[1]Financial Statements'!$E$123
Name BALANCE2_LDA01: '[1]Financial Statements'!$F$112
Name BALANCE2_LDA12: '[1]Financial Statements'!$F$123
Name BALANCE3_LDA01: '[1]Financial Statements'!$G$112
Name BALANCE3_LDA12: '[1]Financial Statements'!$G$123
Name BALANCE4_LDA01: '[1]Financial Statements'!$H$112
Name BALANCE4_LDA12: '[1]Financial Statements'!$H$123
Name BALANCE5_LDA01: '[1]Financial Statements'!$I$112
Name BALANCE5_LDA12: '[1]Financial Statements'!$I$123
Name BALANCE6_LDA01: '[1]Financial Statements'!$J$112
Name BALANCE6_LDA12: '[1]Financial Statements'!$J$123
Name NotApplicable: 'Prudential Ratios'!$A$76
Name PEARLS1_LA002: '[1]Financial Statements'!$E$280
Name PEARLS1_LE008: '[1]Financial Statements'!$E$275
Name PEARLS1_LE009: '[1]Financial Statements'!$E$276
Name PEARLS1_LR001: '[1]Financial Statements'!$E$282
Name PEARLS1_LR005: '[1]Financial Statements'!$E$286
Name PEARLS1_LR006: '[1]Financial Statements'!$E$287
Name PEARLS1_LR007: '[1]Financial Statements'!$E$288
Name PEARLS1_LR009: '[1]Financial Statements'!$E$290
Name PEARLS1_LS001: '[1]Financial Statements'!$E$298
Name PEARLS1_LS005: '[1]Financial Statements'!$E$302
Name PEARLS1_LS011: '[1]Financial Statements'!$E$308
Name PEARLS2_LA002: '[1]Financial Statements'!$F$280
Name PEARLS2_LE008: '[1]Financial Statements'!$F$275
Name PEARLS2_LE009: '[1]Financial Statements'!$F$276
Name PEARLS2_LR001: '[1]Financial Statements'!$F$282
Name PEARLS2_LR005: '[1]Financial Statements'!$F$286
Name PEARLS2_LR006: '[1]Financial Statements'!$F$287
Name PEARLS2_LR007: '[1]Financial Statements'!$F$288
Name PEARLS2_LR009: '[1]Financial Statements'!$F$290
Name PEARLS2_LS001: '[1]Financial Statements'!$F$298
Name PEARLS2_LS005: '[1]Financial Statements'!$F$302
Name PEARLS2_LS010: '[1]Financial Statements'!$F$307
Name PEARLS2_LS011: '[1]Financial Statements'!$F$308
Name PEARLS3_LA002: '[1]Financial Statements'!$G$280
Name PEARLS3_LE008: '[1]Financial Statements'!$G$275
Name PEARLS3_LE009: '[1]Financial Statements'!$G$276
Name PEARLS3_LR001: '[1]Financial Statements'!$G$282
Name PEARLS3_LR005: '[1]Financial Statements'!$G$286
Name PEARLS3_LR006: '[1]Financial Statements'!$G$287
Name PEARLS3_LR007: '[1]Financial Statements'!$G$288
Name PEARLS3_LR009: '[1]Financial Statements'!$G$290
Name PEARLS3_LS001: '[1]Financial Statements'!$G$298
Name PEARLS3_LS005: '[1]Financial Statements'!$G$302
Name PEARLS3_LS010: '[1]Financial Statements'!$G$307
Name PEARLS3_LS011: '[1]Financial Statements'!$G$308
Name PEARLS4_LA002: '[1]Financial Statements'!$H$280
Name PEARLS4_LE008: '[1]Financial Statements'!$H$275
Name PEARLS4_LE009: '[1]Financial Statements'!$H$276
Name PEARLS4_LR001: '[1]Financial Statements'!$H$282
Name PEARLS4_LR005: '[1]Financial Statements'!$H$286
Name PEARLS4_LR006: '[1]Financial Statements'!$H$287
Name PEARLS4_LR007: '[1]Financial Statements'!$H$288
Name PEARLS4_LR009: '[1]Financial Statements'!$H$290
Name PEARLS4_LS001: '[1]Financial Statements'!$H$298
Name PEARLS4_LS005: '[1]Financial Statements'!$H$302
Name PEARLS4_LS010: '[1]Financial Statements'!$H$307
Name PEARLS4_LS011: '[1]Financial Statements'!$H$308

Sheet compliance status
B2: audited2017 | C2: 43101 | D2: 43133 | E2: 43165 | F2: 43197 | G2: 43229 | H2: 43261 | I2: 43293 | J2: 43325 | K2: 43357 | L2: 43389 | M2: 43421 | N2: 43453
A3: CORE CAPITAL | B3: =IF('Prudential Ratios'!#REF!>10,"compliant","not compliant") -> #REF! | C3: =IF('Prudential Ratios'!#REF!>10,"compliant","not compliant") -> #REF! | D3: =IF('Prudential Ratios'!#REF!>10,"compliant","not compliant") -> #REF! | E3: =IF('Prudential Ratios'!#REF!>10,"compliant","not compliant") -> #REF! | F3: =IF('Prudential Ratios'!#REF!>10,"compliant","not compliant") -> #REF! | G3: =IF('Prudential Ratios'!#REF!>10,"compliant","not compliant") -> #REF! | H3: =IF('Prudential Ratios'!#REF!>10,"compliant","not compliant") -> #REF! | I3: =IF('Prudential Ratios'!#REF!>10,"compliant","not compliant") -> #REF! | ... N3: =IF('Prudential Ratios'!#REF!>10,"compliant","not compliant") -> #REF!
A4: CCA (Min 10%) | B4: =IF('Prudential Ratios'!#REF!>10%,"compliant","not compliant") -> #REF! | C4: =IF('Prudential Ratios'!#REF!>10%,"compliant","not compliant") -> #REF! | D4: =IF('Prudential Ratios'!#REF!>10%,"compliant","not compliant") -> #REF! | E4: =IF('Prudential Ratios'!#REF!>10%,"compliant","not compliant") -> #REF! | F4: =IF('Prudential Ratios'!#REF!>10%,"compliant","not compliant") -> #REF! | G4: =IF('Prudential Ratios'!#REF!>10%,"compliant","not compliant") -> #REF! | H4: =IF('Prudential Ratios'!#REF!>10%,"compliant","not compliant") -> #REF! | I4: =IF('Prudential Ratios'!#REF!>10%,"compliant","not compliant") -> #REF! | ... N4: =IF('Prudential Ratios'!#REF!>10%,"compliant","not compliant") -> #REF!
A5: ICA (Min 8%) | B5: =IF('Prudential Ratios'!#REF!>8%,"compliant","not compliant") -> #REF! | C5: =IF('Prudential Ratios'!#REF!>8%,"compliant","not compliant") -> #REF! | D5: =IF('Prudential Ratios'!#REF!>8%,"compliant","not compliant") -> #REF! | E5: =IF('Prudential Ratios'!#REF!>8%,"compliant","not compliant") -> #REF! | F5: =IF('Prudential Ratios'!#REF!>8%,"compliant","not compliant") -> #REF! | G5: =IF('Prudential Ratios'!#REF!>8%,"compliant","not compliant") -> #REF! | H5: =IF('Prudential Ratios'!#REF!>8%,"compliant","not compliant") -> #REF! | I5: =IF('Prudential Ratios'!#REF!>8%,"compliant","not compliant") -> #REF! | ... N5: =IF('Prudential Ratios'!#REF!>8%,"compliant","not compliant") -> #REF!
A6: CCD (Min 8%) | B6: =IF('Prudential Ratios'!#REF!>8%,"compliant","not compliant") -> #REF! | C6: =IF('Prudential Ratios'!#REF!>8%,"compliant","not compliant") -> #REF! | D6: =IF('Prudential Ratios'!#REF!>8%,"compliant","not compliant") -> #REF! | E6: =IF('Prudential Ratios'!#REF!>8%,"compliant","not compliant") -> #REF! | F6: =IF('Prudential Ratios'!#REF!>8%,"compliant","not compliant") -> #REF! | G6: =IF('Prudential Ratios'!#REF!>8%,"compliant","not compliant") -> #REF! | H6: =IF('Prudential Ratios'!#REF!>8%,"compliant","not compliant") -> #REF! | I6: =IF('Prudential Ratios'!#REF!>8%,"compliant","not compliant") -> #REF! | ... N6: =IF('Prudential Ratios'!#REF!>8%,"compliant","not compliant") -> #REF!
A7: NPL(5%)
A8: Liquidity(15%) | B8: =IF('Prudential Ratios'!#REF!>15%,"compliant","not compliant") -> #REF! | C8: =IF('Prudential Ratios'!#REF!>15%,"compliant","not compliant") -> #REF! | D8: =IF('Prudential Ratios'!#REF!>15%,"compliant","not compliant") -> #REF! | E8: =IF('Prudential Ratios'!#REF!>15%,"compliant","not compliant") -> #REF! | F8: =IF('Prudential Ratios'!#REF!>15%,"compliant","not compliant") -> #REF! | G8: =IF('Prudential Ratios'!#REF!>15%,"compliant","not compliant") -> #REF! | H8: =IF('Prudential Ratios'!#REF!>15%,"compliant","not compliant") -> #REF! | I8: =IF('Prudential Ratios'!#REF!>15%,"compliant","not compliant") -> #REF! | ... N8: =IF('Prudential Ratios'!#REF!>15%,"compliant","not compliant") -> #REF!
A9: NEA (Max 10%) | B9: =IF('Prudential Ratios'!#REF!<10%,"compliant","not compliant") -> #REF! | C9: =IF('Prudential Ratios'!#REF!<10%,"compliant","not compliant") -> #REF! | D9: =IF('Prudential Ratios'!#REF!<10%,"compliant","not compliant") -> #REF! | E9: =IF('Prudential Ratios'!#REF!<10%,"compliant","not compliant") -> #REF! | F9: =IF('Prudential Ratios'!#REF!<10%,"compliant","not compliant") -> #REF! | G9: =IF('Prudential Ratios'!#REF!<10%,"compliant","not compliant") -> #REF! | H9: =IF('Prudential Ratios'!#REF!<10%,"compliant","not compliant") -> #REF! | I9: =IF('Prudential Ratios'!#REF!<10%,"compliant","not compliant") -> #REF! | ... N9: =IF('Prudential Ratios'!#REF!<10%,"compliant","not compliant") -> #REF!
A10: LB ratio (Max 5%) | B10: =IF('Prudential Ratios'!#REF!<5%,"compliant","not compliant") -> #REF! | C10: =IF('Prudential Ratios'!#REF!<5%,"compliant","not compliant") -> #REF! | D10: =IF('Prudential Ratios'!#REF!<5%,"compliant","not compliant") -> #REF! | E10: =IF('Prudential Ratios'!#REF!<5%,"compliant","not compliant") -> #REF! | F10: =IF('Prudential Ratios'!#REF!<5%,"compliant","not compliant") -> #REF! | G10: =IF('Prudential Ratios'!#REF!<5%,"compliant","not compliant") -> #REF! | H10: =IF('Prudential Ratios'!#REF!<5%,"compliant","not compliant") -> #REF! | I10: =IF('Prudential Ratios'!#REF!<5%,"compliant","not compliant") -> #REF! | ... N10: =IF('Prudential Ratios'!#REF!<5%,"compliant","not compliant") -> #REF!
A11: FITD (Max 5%) | B11: =IF('Prudential Ratios'!#REF!<5%,"compliant","not compliant") -> #REF! | C11: =IF('Prudential Ratios'!#REF!<5%,"compliant","not compliant") -> #REF! | D11: =IF('Prudential Ratios'!#REF!<5%,"compliant","not compliant") -> #REF! | E11: =IF('Prudential Ratios'!#REF!<5%,"compliant","not compliant") -> #REF! | F11: =IF('Prudential Ratios'!#REF!<5%,"compliant","not compliant") -> #REF! | G11: =IF('Prudential Ratios'!#REF!<5%,"compliant","not compliant") -> #REF! | H11: =IF('Prudential Ratios'!#REF!<5%,"compliant","not compliant") -> #REF! | I11: =IF('Prudential Ratios'!#REF!<5%,"compliant","not compliant") -> #REF! | ... N11: =IF('Prudential Ratios'!#REF!<5%,"compliant","not compliant") -> #REF!
A12: FICC (Max 40%) | B12: =IF('Prudential Ratios'!#REF!<40%,"compliant","not compliant") -> #REF! | C12: =IF('Prudential Ratios'!#REF!<40%,"compliant","not compliant") -> #REF! | D12: =IF('Prudential Ratios'!#REF!<40%,"compliant","not compliant") -> #REF! | E12: =IF('Prudential Ratios'!#REF!<40%,"compliant","not compliant") -> #REF! | F12: =IF('Prudential Ratios'!#REF!<40%,"compliant","not compliant") -> #REF! | G12: =IF('Prudential Ratios'!#REF!<40%,"compliant","not compliant") -> #REF! | H12: =IF('Prudential Ratios'!#REF!<40%,"compliant","not compliant") -> #REF! | I12: =IF('Prudential Ratios'!#REF!<40%,"compliant","not compliant") -> #REF! | ... N12: =IF('Prudential Ratios'!#REF!<40%,"compliant","not compliant") -> #REF!
A13: EB ratio | B13: =IF('Prudential Ratios'!#REF!<25%,"compliant","not compliant") -> #REF! | C13: =IF('Prudential Ratios'!#REF!<25%,"compliant","not compliant") -> #REF! | D13: =IF('Prudential Ratios'!#REF!<25%,"compliant","not compliant") -> #REF! | E13: =IF('Prudential Ratios'!#REF!<25%,"compliant","not compliant") -> #REF! | F13: =IF('Prudential Ratios'!#REF!<25%,"compliant","not compliant") -> #REF! | G13: =IF('Prudential Ratios'!#REF!<25%,"compliant","not compliant") -> #REF! | H13: =IF('Prudential Ratios'!#REF!<25%,"compliant","not compliant") -> #REF! | I13: =IF('Prudential Ratios'!#REF!<25%,"compliant","not compliant") -> #REF! | ... N13: =IF('Prudential Ratios'!#REF!<25%,"compliant","not compliant") -> #REF!
A14: A=S+L | B14: =IF(SFP!#REF!=SFP!#REF!,"balancing","notbalancing") -> #REF! | C14: =IF(SFP!#REF!=SFP!#REF!,"balancing","notbalancing") -> #REF! | D14: =IF(SFP!#REF!=SFP!#REF!,"balancing","notbalancing") -> #REF! | E14: =IF(SFP!#REF!=SFP!#REF!,"balancing","notbalancing") -> #REF! | F14: =IF(SFP!#REF!=SFP!#REF!,"balancing","notbalancing") -> #REF! | G14: =IF(SFP!#REF!=SFP!#REF!,"balancing","notbalancing") -> #REF! | H14: =IF(SFP!#REF!=SFP!#REF!,"balancing","notbalancing") -> #REF! | I14: =IF(SFP!#REF!=SFP!#REF!,"balancing","notbalancing") -> #REF! | ... N14: =IF(SFP!#REF!=SFP!#REF!,"balancing","notbalancing") -> #REF!

Sheet Prudential Ratios
B1: STIMA SACCO SOCIETY LTD
B2: Sacco Financial Performance
B4: FINANCIAL SOUNDNESS INDICATORS | C4: Prude. Std | D4: 44197 | E4: 44197 | F4: 44228 | G4: 44256 | H4: 44287 | I4: 44317 | J4: 44348 | K4: 44378 | L4: 44409 | M4: 44440 | N4: 44470 | O4: 44501 | P4: 44531 | Q4: Audited 2021 | R4: 44562 | S4: 44593 | T4: 44621 | U4: 44652 | V4: 44682 | W4: 44713 | X4: 44743 | Y4: 44774 | Z4: 44805 | AA4: 44835 | AB4: 44866 | AC4: 44896 | AD4: Audited-2022 | AE4: 44949 | AF4: 44980 | AG4: 45008 | AH4: 45039 | AI4: 45069 | AJ4: 45100
A5: 1 | B5: CAPITAL ADEQUACY REQUIREMENTS
A6: 1.1 | B6: Core capital | C6: ≥ Ksh.10M | E6: =Financials!D14/1000000 -> 6578.7089 | F6: =Financials!E14/1000000 -> 6664.0025 | G6: =Financials!F14/1000000 -> 6555.7887 | H6: =Financials!G14/1000000 -> 6722.7782 | I6: =Financials!H14/1000000 -> 6916.5815 | J6: =Financials!I14/1000000 -> 6899.1975 | K6: =Financials!J14/1000000 -> 7079.1033 | L6: =Financials!K14/1000000 -> 7230.3262 | ... AJ6: =Financials!AI14/1000000 -> 8931.2173
A7: 1.2 | B7: Core capital /Total Assets | C7: ≥ 10% | E7: =Financials!D14/Financials!D5 -> 0.15865783 | F7: =Financials!E14/Financials!E5 -> 0.15884834 | G7: =Financials!F14/Financials!F5 -> 0.15934179 | H7: =Financials!G14/Financials!G5 -> 0.16194356 | I7: =Financials!H14/Financials!H5 -> 0.16491152 | J7: =Financials!I14/Financials!I5 -> 0.16266766 | K7: =Financials!J14/Financials!J5 -> 0.16547489 | L7: =Financials!K14/Financials!K5 -> 0.16552831 | ... AJ7: =Financials!AI14/Financials!AI5 -> 0.16449256
A8: 1.3 | B8: Core capital /Total Deposits | C8: ≥ 8% | E8: =Financials!D14/Financials!D6 -> 0.21071153 | F8: =Financials!E14/Financials!E6 -> 0.21273766 | G8: =Financials!F14/Financials!F6 -> 0.2008079 | H8: =Financials!G14/Financials!G6 -> 0.20518068 | I8: =Financials!H14/Financials!H6 -> 0.21123958 | J8: =Financials!I14/Financials!I6 -> 0.20953859 | K8: =Financials!J14/Financials!J6 -> 0.21630414 | L8: =Financials!K14/Financials!K6 -> 0.21829935 | ... AJ8: =Financials!AI14/Financials!AI6 -> 0.21805422
A9: 1.4 | B9: Share Capital/Total Assets | C9: ≤2% | E9: =Financials!D18/Financials!D5 -> 0.049260175 | F9: =Financials!E18/Financials!E5 -> 0.049200162 | G9: =Financials!F18/Financials!F5 -> 0.051796069 | H9: =Financials!G18/Financials!G5 -> 0.051999452 | I9: =Financials!H18/Financials!H5 -> 0.052001158 | J9: =Financials!I18/Financials!I5 -> 0.051987667 | K9: =Financials!J18/Financials!J5 -> 0.052398016 | L9: =Financials!K18/Financials!K5 -> 0.052011355 | ... AJ9: =Financials!AI18/Financials!AI5 -> 0.06010375
A10: 1.5 | B10: Institutional Capital/Total Assets | C10: ≥ 8% | E10: =Financials!D15/Financials!D5 -> 0.10939766 | F10: =Financials!E15/Financials!E5 -> 0.10964818 | G10: =Financials!F15/Financials!F5 -> 0.10754573 | H10: =Financials!G15/Financials!G5 -> 0.10994411 | I10: =Financials!H15/Financials!H5 -> 0.11291037 | J10: =Financials!I15/Financials!I5 -> 0.11067999 | K10: =Financials!J15/Financials!J5 -> 0.11307688 | L10: =Financials!K15/Financials!K5 -> 0.11351696 | ... AJ10: =Financials!AI15/Financials!AI5 -> 0.10438881
A12: 2 | B12: ASSET MIX AND QUALITY
A13: 2.1 | B13: Non Earning Assets
A14: 2.1.1 | B14: Non earning Assets/Total assets | C14: ≤ 10% | E14: =Financials!D38/Financials!D5 -> 0.035368553 | F14: =Financials!E38/Financials!E5 -> 0.040774312 | G14: =Financials!F38/Financials!F5 -> 0.033083895 | H14: =Financials!G38/Financials!G5 -> 0.040344571 | I14: =Financials!H38/Financials!H5 -> 0.039739294 | J14: =Financials!I38/Financials!I5 -> 0.040677021 | K14: =Financials!J38/Financials!J5 -> 0.045702627 | L14: =Financials!K38/Financials!K5 -> 0.045025494 | ... AJ14: =Financials!AI38/Financials!AI5 -> 0.04876996
A15: 2.1.2 | B15: Property and Equipment/Total Assets | C15: ≤ 5% | E15: =Financials!D39/Financials!D5 -> 0.0055126393 | F15: =Financials!E39/Financials!E5 -> 0.0054400205 | G15: =Financials!F39/Financials!F5 -> 0.0055423733 | H15: =Financials!G39/Financials!G5 -> 0.0054591737 | I15: =Financials!H39/Financials!H5 -> 0.0053447843 | J15: =Financials!I39/Financials!I5 -> 0.0052457843 | K15: =Financials!J39/Financials!J5 -> 0.0051669335 | L15: =Financials!K39/Financials!K5 -> 0.0050875012 | ... AJ15: =Financials!AI39/Financials!AI5 -> 0.0081536805
A16: 2.1.3 | B16: Non Performing loans/Gross Loans | C16: ≤ 6%
A18: 2.2 | B18: Earning Assets
A19: 2.2.1 | B19: Equities & Investments/Deposits | C19: ≤ 5% | E19: =Financials!D26/Financials!D6 -> 0.01849949 | F19: =Financials!E26/Financials!E6 -> 0.018438608 | G19: =Financials!F26/Financials!F6 -> 0.01769188 | H19: =Financials!G26/Financials!G6 -> 0.017628083 | I19: =Financials!H26/Financials!H6 -> 0.017640198 | J19: =Financials!I26/Financials!I6 -> 0.017542212 | K19: =Financials!J26/Financials!J6 -> 0.017648467 | L19: =Financials!K26/Financials!K6 -> 0.017438765 | ... AJ19: =Financials!AI26/Financials!AI6 -> 0.01363028
A20: 2.2.2 | B20: Equities & Investments/Core Capital | C20: ≤ 40% | E20: =Financials!D26/Financials!D14 -> 0.087795341 | F20: =Financials!E26/Financials!E14 -> 0.086672984 | G20: =Financials!F26/Financials!F14 -> 0.088103509 | H20: =Financials!G26/Financials!G14 -> 0.085914926 | I20: =Financials!H26/Financials!H14 -> 0.083508014 | J20: =Financials!I26/Financials!I14 -> 0.083718286 | K20: =Financials!J26/Financials!J14 -> 0.081590981 | L20: =Financials!K26/Financials!K14 -> 0.079884637 | ... AJ20: =Financials!AI26/Financials!AI14 -> 0.062508674
A21: 2.2.3 | B21: Net Loans & advances /Total assets | C21: NPR | E21: =Financials!D31/Financials!D5 -> 0.80199739 | F21: =Financials!E31/Financials!E5 -> 0.7958464 | G21: =Financials!F31/Financials!F5 -> 0.80629712 | H21: =Financials!G31/Financials!G5 -> 0.80254472 | I21: =Financials!H31/Financials!H5 -> 0.8008076 | J21: =Financials!I31/Financials!I5 -> 0.79273101 | K21: =Financials!J31/Financials!J5 -> 0.78306191 | L21: =Financials!K31/Financials!K5 -> 0.77305813 | ... AJ21: =Financials!AI31/Financials!AI5 -> 0.76435026
A23: 3 | B23: FUNDING MIX
A24: 3.1 | B24: Total Deposits/Total Assets | C24: NPR | E24: =Financials!D6/Financials!D5 -> 0.75296229 | F24: =Financials!E6/Financials!E5 -> 0.74668653 | G24: =Financials!F6/Financials!F5 -> 0.79350362 | H24: =Financials!G6/Financials!G5 -> 0.78927292 | I24: =Financials!H6/Financials!H5 -> 0.78068477 | J24: =Financials!I6/Financials!I5 -> 0.77631361 | K24: =Financials!J6/Financials!J5 -> 0.76501029 | L24: =Financials!K6/Financials!K5 -> 0.75826294 | ... AJ24: =Financials!AI6/Financials!AI5 -> 0.7543654
A25: 3.1.1 | B25: BOSA Deposits/Total Assets | C25: NPR | E25: =Financials!D7/Financials!D5 -> 0.57644424 | F25: =Financials!E7/Financials!E5 -> 0.57372279 | G25: =Financials!F7/Financials!F5 -> 0.59590923 | H25: =Financials!G7/Financials!G5 -> 0.5961339 | I25: =Financials!H7/Financials!H5 -> 0.59407402 | J25: =Financials!I7/Financials!I5 -> 0.59000274 | K25: =Financials!J7/Financials!J5 -> 0.59246095 | L25: =Financials!K7/Financials!K5 -> 0.58524308 | ... AJ25: =Financials!AI7/Financials!AI5 -> 0.59905723
A26: 3.1.2 | B26: FOSA Deposits/Total Assets | C26: NPR | E26: =Financials!D8/Financials!D5 -> 0.074901097 | F26: =Financials!E8/Financials!E5 -> 0.072759204 | G26: =Financials!F8/Financials!F5 -> 0.09246145 | H26: =Financials!G8/Financials!G5 -> 0.087136285 | I26: =Financials!H8/Financials!H5 -> 0.081448834 | J26: =Financials!I8/Financials!I5 -> 0.082411516 | K26: =Financials!J8/Financials!J5 -> 0.065010692 | L26: =Financials!K8/Financials!K5 -> 0.067431729 | ... AJ26: =Financials!AI8/Financials!AI5 -> 0.067300177
A27: 3.2 | B27: External Borrowing/Total assets | C27: ≤ 25% | E27: =Financials!D9/Financials!D5 -> 0 | F27: =Financials!E9/Financials!E5 -> 0 | G27: =Financials!F9/Financials!F5 -> 0 | H27: =Financials!G9/Financials!G5 -> 0 | I27: =Financials!H9/Financials!H5 -> 0 | J27: =Financials!I9/Financials!I5 -> 0 | K27: =Financials!J9/Financials!J5 -> 0 | L27: =Financials!K9/Financials!K5 -> 0.0015803761 | ... AJ27: =Financials!AI9/Financials!AI5 -> 0.0049804887
A29: 4 | B29: GROWTH RATIOS
A30: 4.1 | B30: Total Assets | C30: NPR | E30: =Financials!D5/Financials!C5-1 -> -0.013550629 | F30: =Financials!E5/Financials!D5-1 -> 0.011750238 | G30: =Financials!F5/Financials!E5-1 -> -0.019285087 | H30: =Financials!G5/Financials!F5-1 -> 0.0089969759 | I30: =Financials!H5/Financials!G5-1 -> 0.010311717 | J30: =Financials!I5/Financials!H5-1 -> 0.011246093 | K30: =Financials!J5/Financials!I5-1 -> 0.0086692807 | L30: =Financials!K5/Financials!J5-1 -> 0.021032264 | ... AJ30: =Financials!AI5/Financials!AH5-1 -> 0.0064651801
A31: 4.2 | B31: Total Deposits | C31: NPR | E31: =Financials!D6/Financials!C6-1 -> 0.0010624492 | F31: =Financials!E6/Financials!D6-1 -> 0.0033175391 | G31: =Financials!F6/Financials!E6-1 -> 0.042205543 | H31: =Financials!G6/Financials!F6-1 -> 0.0036173272 | I31: =Financials!H6/Financials!G6-1 -> -0.00068156983 | J31: =Financials!I6/Financials!H6-1 -> 0.0055839815 | K31: =Financials!J6/Financials!I6-1 -> -0.0060171913 | L31: =Financials!K6/Financials!J6-1 -> 0.01202681 | ... AJ31: =Financials!AI6/Financials!AH6-1 -> -0.00047226909
A32: 4.2.1 | B32: FOSA Deposits | C32: NPR | E32: =Financials!D8/Financials!C8-1 -> -0.19911087 | F32: =Financials!E8/Financials!D8-1 -> -0.01718206 | G32: =Financials!F8/Financials!E8-1 -> 0.24627975 | H32: =Financials!G8/Financials!F8-1 -> -0.049114546 | I32: =Financials!H8/Financials!G8-1 -> -0.055632091 | J32: =Financials!I8/Financials!H8-1 -> 0.023198492 | K32: =Financials!J8/Financials!I8-1 -> -0.20430674 | L32: =Financials!K8/Financials!J8-1 -> 0.059056123 | ... AJ32: =Financials!AI8/Financials!AH8-1 -> -0.003904156
A33: 4.2.2 | B33: BOSA Deposits | C33: NPR | E33: =Financials!D7/Financials!C7-1 -> 0.0080039667 | F33: =Financials!E7/Financials!D7-1 -> 0.0069736637 | G33: =Financials!F7/Financials!E7-1 -> 0.018640146 | H33: =Financials!G7/Financials!F7-1 -> 0.0093773869 | I33: =Financials!H7/Financials!G7-1 -> 0.0068206902 | J33: =Financials!I7/Financials!H7-1 -> 0.0043158649 | K33: =Financials!J7/Financials!I7-1 -> 0.012871849 | L33: =Financials!K7/Financials!J7-1 -> 0.0085931635 | ... AJ33: =Financials!AI7/Financials!AH7-1 -> 0.0032929638
A34: 4.3 | B34: Net Loans & advances | C34: NPR | E34: =Financials!D31/Financials!C31-1 -> -0.088263435 | F34: =Financials!E31/Financials!D31-1 -> 0.0039905402 | G34: =Financials!F31/Financials!E31-1 -> -0.0064067518 | H34: =Financials!G31/Financials!F31-1 -> 0.0043012314 | I34: =Financials!H31/Financials!G31-1 -> 0.0081248777 | J34: =Financials!I31/Financials!H31-1 -> 0.0010471168 | K34: =Financials!J31/Financials!I31-1 -> -0.0036336569 | L34: =Financials!K31/Financials!J31-1 -> 0.0079883641 | ... AJ34: =Financials!AI31/Financials!AH31-1 -> -0.0074728419
A35: 4.4 | B35: Core capital | C35: NPR | E35: =Financials!D14/Financials!C14-1 -> 0.079311473 | F35: =Financials!E14/Financials!D14-1 -> 0.012965105 | G35: =Financials!F14/Financials!E14-1 -> -0.016238569 | H35: =Financials!G14/Financials!F14-1 -> 0.025472071 | I35: =Financials!H14/Financials!G14-1 -> 0.028827866 | J35: =Financials!I14/Financials!H14-1 -> -0.0025133867 | K35: =Financials!J14/Financials!I14-1 -> 0.026076344 | L35: =Financials!K14/Financials!J14-1 -> 0.021361872 | ... AJ35: =Financials!AI14/Financials!AH14-1 -> -0.022885244
A36: 4.5 | B36: Total Gross Income | C36: NPR | E36: =Financials!D41/Financials!C41-1 -> 0.0070642437 | F36: =Financials!E41/Financials!D41-1 -> -0.0070144429 | G36: =Financials!F41/Financials!E41-1 -> 0 | H36: =Financials!G41/Financials!F41-1 -> 0 | I36: =Financials!H41/Financials!G41-1 -> 0 | J36: =Financials!I41/Financials!H41-1 -> 0 | K36: =Financials!J41/Financials!I41-1 -> 0 | L36: =Financials!K41/Financials!J41-1 -> 0 | ... AJ36: =Financials!AI41/Financials!AH41-1 -> 0
A37: 4.6 | B37: Membership | C37: NPR
A39: 5 | B39: Efficiency Ratios
A40: 5.1 | B40: FinCost-Deposits/Average Deposits | C40: NPR | E40: =Financials!D48/((Financials!D6+Financials!C6)/2) -> 0 | F40: =Financials!E48/((Financials!E6+Financials!D6)/2) -> 0 | G40: =Financials!F48/((Financials!F6+Financials!E6)/2) -> 0 | H40: =Financials!G48/((Financials!G6+Financials!F6)/2) -> 0 | I40: =Financials!H48/((Financials!H6+Financials!G6)/2) -> 0 | J40: =Financials!I48/((Financials!I6+Financials!H6)/2) -> 0 | K40: =Financials!J48/((Financials!J6+Financials!I6)/2) -> 0 | L40: =Financials!K48/((Financials!K6+Financials!J6)/2) -> 0 | ... AJ40: =Financials!AI48/((Financials!AI6+Financials!AH6)/2) -> 0.0044478241
A41: 5.2 | B41: FinCost-Shares/Average Share capital | C41: NPR | E41: =Financials!D49/((Financials!D18+Financials!C18)/2) -> 0 | F41: =Financials!E49/((Financials!E18+Financials!D18)/2) -> 0 | G41: =Financials!F49/((Financials!F18+Financials!E18)/2) -> 0 | H41: =Financials!G49/((Financials!G18+Financials!F18)/2) -> 0 | I41: =Financials!H49/((Financials!H18+Financials!G18)/2) -> 0 | J41: =Financials!I49/((Financials!I18+Financials!H18)/2) -> 0 | K41: =Financials!J49/((Financials!J18+Financials!I18)/2) -> 0 | L41: =Financials!K49/((Financials!K18+Financials!J18)/2) -> 0 | ... AJ41: =Financials!AI49/((Financials!AI18+Financials!AH18)/2) -> 0.52278999
A42: 5.3 | B42: FinCost-Ext Loans/Average Ext Loans | C42: NPR | E42: =Financials!D50/((Financials!D9+Financials!C9)/2) -> #DIV/0! | F42: =Financials!E50/((Financials!E9+Financials!D9)/2) -> #DIV/0! | G42: =Financials!F50/((Financials!F9+Financials!E9)/2) -> #DIV/0! | H42: =Financials!G50/((Financials!G9+Financials!F9)/2) -> #DIV/0! | I42: =Financials!H50/((Financials!H9+Financials!G9)/2) -> #DIV/0! | J42: =Financials!I50/((Financials!I9+Financials!H9)/2) -> #DIV/0! | K42: =Financials!J50/((Financials!J9+Financials!I9)/2) -> #DIV/0! | L42: =Financials!K50/((Financials!K9+Financials!J9)/2) -> 0 | ... AJ42: =Financials!AI50/((Financials!AI9+Financials!AH9)/2) -> 0.026946091
A43: 5.4 | B43: OpEx/Average Total Assets | C43: NPR | E43: =(Financials!D52+Financials!D53)/((Financials!D5+Financials!C5)/2) -> 0 | F43: =(Financials!E52+Financials!E53)/((Financials!E5+Financials!D5)/2) -> 0 | G43: =(Financials!F52+Financials!F53)/((Financials!F5+Financials!E5)/2) -> 0 | H43: =(Financials!G52+Financials!G53)/((Financials!G5+Financials!F5)/2) -> 0 | I43: =(Financials!H52+Financials!H53)/((Financials!H5+Financials!G5)/2) -> 0 | J43: =(Financials!I52+Financials!I53)/((Financials!I5+Financials!H5)/2) -> 0 | K43: =(Financials!J52+Financials!J53)/((Financials!J5+Financials!I5)/2) -> 0 | L43: =(Financials!K52+Financials!K53)/((Financials!K5+Financials!J5)/2) -> 0 | ... AJ43: =(Financials!AI52+Financials!AI53)/((Financials!AI5+Financials!AH5)/2) -> 0.0076891635
A44: 5.5 | B44: Avge yield on Net loans | C44: NPR | E44: =Financials!D42/((Financials!D31+Financials!C31)/2) -> 0.033985925 | F44: =Financials!E42/((Financials!E31+Financials!D31)/2) -> 0.035305748 | G44: =Financials!F42/((Financials!F31+Financials!E31)/2) -> 0.035348819 | H44: =Financials!G42/((Financials!G31+Financials!F31)/2) -> 0.035386682 | I44: =Financials!H42/((Financials!H31+Financials!G31)/2) -> 0.035168037 | J44: =Financials!I42/((Financials!I31+Financials!H31)/2) -> 0.035007992 | K44: =Financials!J42/((Financials!J31+Financials!I31)/2) -> 0.035053368 | L44: =Financials!K42/((Financials!K31+Financials!J31)/2) -> 0.034977579 | ... AJ44: =Financials!AI42/((Financials!AI31+Financials!AH31)/2) -> 0.039795862
A46: 6 | B46: Liquidity Ratio
A47: 6.1 | B47: minimum Liquidity | C47: 0.15 | E47: =(SFP!C4+SFP!C11)/(SFP!C31+SFP!C34+SFP!C35+SFP!C36+SFP!C37+SFP!C38) -> 0.1920364 | F47: =(SFP!D4+SFP!D11)/(SFP!D31+SFP!D34+SFP!D35+SFP!D36+SFP!D37+SFP!D38) -> 0.19261706 | G47: =(SFP!E4+SFP!E11)/(SFP!E31+SFP!E34+SFP!E35+SFP!E36+SFP!E37+SFP!E38) -> 0.19469053 | H47: =(SFP!F4+SFP!F11)/(SFP!F31+SFP!F34+SFP!F35+SFP!F36+SFP!F37+SFP!F38) -> 0.17994745 | I47: =(SFP!G4+SFP!G11)/(SFP!G31+SFP!G34+SFP!G35+SFP!G36+SFP!G37+SFP!G38) -> 0.18302274 | J47: =(SFP!H4+SFP!H11)/(SFP!H31+SFP!H34+SFP!H35+SFP!H36+SFP!H37+SFP!H38) -> 0.18969881 | K47: =(SFP!I4+SFP!I11)/(SFP!I31+SFP!I34+SFP!I35+SFP!I36+SFP!I37+SFP!I38) -> 0.19398708 | L47: =(SFP!J4+SFP!J11)/(SFP!J31+SFP!J34+SFP!J35+SFP!J36+SFP!J37+SFP!J38) -> 0.21202262 | ... AJ47: =(SFP!AH4+SFP!AH11)/(SFP!AH31+SFP!AH34+SFP!AH35+SFP!AH36+SFP!AH37+SFP!AH38) -> 0.176209
B48: TECHNICAL Liquidity | E48: =(SFP!C4+SFP!C11)/(SFP!C32+SFP!C34+SFP!C35+SFP!C36+SFP!C37+SFP!C38) -> 0.15173396 | F48: =(SFP!D4+SFP!D11)/(SFP!D32+SFP!D34+SFP!D35+SFP!D36+SFP!D37+SFP!D38) -> 0.15299789 | G48: =(SFP!E4+SFP!E11)/(SFP!E32+SFP!E34+SFP!E35+SFP!E36+SFP!E37+SFP!E38) -> 0.1489151 | H48: =(SFP!F4+SFP!F11)/(SFP!F32+SFP!F34+SFP!F35+SFP!F36+SFP!F37+SFP!F38) -> 0.13846407 | I48: =(SFP!G4+SFP!G11)/(SFP!G32+SFP!G34+SFP!G35+SFP!G36+SFP!G37+SFP!G38) -> 0.14211175 | J48: =(SFP!H4+SFP!H11)/(SFP!H32+SFP!H34+SFP!H35+SFP!H36+SFP!H37+SFP!H38) -> 0.14747728 | K48: =(SFP!I4+SFP!I11)/(SFP!I32+SFP!I34+SFP!I35+SFP!I36+SFP!I37+SFP!I38) -> 0.15386578 | L48: =(SFP!J4+SFP!J11)/(SFP!J32+SFP!J34+SFP!J35+SFP!J36+SFP!J37+SFP!J38) -> 0.16796553 | ... AJ48: =(SFP!AH4+SFP!AH11)/(SFP!AH32+SFP!AH34+SFP!AH35+SFP!AH36+SFP!AH37+SFP!AH38) -> 0.14323737
A49: 7 | B49: Loan Loss Provisions Ratios
A50: 7.1 | B50: Actual LLP / Required LLP | C50: 1
A51: 7.2 | B51: allowance for loan loss/NPL
B52: Loan interest/Net Loans | E52: =SCI!C5/SFP!C14 -> 0 | F52: =SCI!D5/SFP!D14 -> 0 | G52: =SCI!E5/SFP!E14 -> 0 | H52: =SCI!F5/SFP!F14 -> 0 | I52: =SCI!G5/SFP!G14 -> 0 | J52: =SCI!H5/SFP!H14 -> 0 | K52: =SCI!I5/SFP!I14 -> 0 | L52: =SCI!J5/SFP!J14 -> 0 | ... AJ52: =SCI!AH5/SFP!AH14 -> 0.079293844
B53: Gross loans/Total assets | E53: =Financials!D32/Financials!D5 -> 0.8581952 | F53: =Financials!E32/Financials!E5 -> 0.85139155 | G53: =Financials!F32/Financials!F5 -> 0.86624196 | H53: =Financials!G32/Financials!G5 -> 0.86195505 | I53: =Financials!H32/Financials!H5 -> 0.85961155 | J53: =Financials!I32/Financials!I5 -> 0.85408941 | K53: =Financials!J32/Financials!J5 -> 0.84389295 | L53: =Financials!K32/Financials!K5 -> 0.83263611 | ... AJ53: =Financials!AI32/Financials!AI5 -> 0.85657271
A54: 8 | B54: Earnings
A55: 8.1 | B55: ROA | E55: =SCI!C33/(SFP!B27+SFP!C27/2) -> -1.9118409e-10 | F55: =SCI!D33/(SFP!C27+SFP!D27/2) -> -1.7616701e-10 | G55: =SCI!E33/(SFP!D27+SFP!E27/2) -> -1.5994e-10 | H55: =SCI!F33/(SFP!E27+SFP!F27/2) -> -1.4539702e-10 | I55: =SCI!G33/(SFP!F27+SFP!G27/2) -> -1.2803344e-10 | J55: =SCI!H33/(SFP!G27+SFP!H27/2) -> -1.1085143e-10 | K55: =SCI!I33/(SFP!H27+SFP!I27/2) -> -9.4039312e-11 | L55: =SCI!J33/(SFP!I27+SFP!J27/2) -> -7.7374613e-11 | ... AJ55: =SCI!AH33/(SFP!AG27+SFP!AH27/2) -> -0.0019981104
A56: 8.2 | B56: Cost Income Ratio | E56: =SCI!C23/SCI!C19 -> #DIV/0! | F56: =SCI!D23/SCI!D19 -> #DIV/0! | G56: =SCI!E23/SCI!E19 -> #DIV/0! | H56: =SCI!F23/SCI!F19 -> #DIV/0! | I56: =SCI!G23/SCI!G19 -> #DIV/0! | J56: =SCI!H23/SCI!H19 -> #DIV/0! | K56: =SCI!I23/SCI!I19 -> #DIV/0! | L56: =SCI!J23/SCI!J19 -> #DIV/0! | ... AJ56: =SCI!AH23/SCI!AH19 -> 0.48272104
A57: 8.3 | B57: Operating Expense Ratio | E57: =SCI!C23/SFP!C27 -> 0 | F57: =SCI!D23/SFP!D27 -> 0 | G57: =SCI!E23/SFP!E27 -> 0 | H57: =SCI!F23/SFP!F27 -> 0 | I57: =SCI!G23/SFP!G27 -> 0 | J57: =SCI!H23/SFP!H27 -> 0 | K57: =SCI!I23/SFP!I27 -> 0 | L57: =SCI!J23/SFP!J27 -> 0 | ... AJ57: =SCI!AH23/SFP!AH27 -> 0.018698524
B58: Liquid assets/total assets | D58: =(Financials!C36+Financials!C29)/Financials!C5 -> 0.12148195 | E58: =(Financials!D36+Financials!D29)/Financials!D5 -> 0.12762157 | F58: =(Financials!E36+Financials!E29)/Financials!E5 -> 0.12865596 | G58: =(Financials!F36+Financials!F29)/Financials!F5 -> 0.12514852 | H58: =(Financials!G36+Financials!G29)/Financials!G5 -> 0.11600552 | I58: =(Financials!H36+Financials!H29)/Financials!H5 -> 0.11864014 | J58: =(Financials!I36+Financials!I29)/Financials!I5 -> 0.12345082 | K58: =(Financials!J36+Financials!J29)/Financials!J5 -> 0.12836691 | ... AJ58: =(Financials!AI36+Financials!AI29)/Financials!AI5 -> 0.11888809
A76: 0

Sheet CAELS
B1: STIMA SACCO
B2: FINANCIAL SOUNDNESS INDICATORS | C2: Prude. Std | D2: 44136 | E2: 44166 | F2: Audited 2020 | G2: 44197 | H2: 44228 | I2: 44256 | J2: 44287 | K2: 44317 | L2: 44348 | M2: 44378 | N2: 44409 | O2: 44440 | P2: 44470 | Q2: 44501 | R2: 44531 | S2: Audited 2021 | T2: 44562 | U2: 44593 | V2: 44621 | W2: 44652 | X2: 44682 | Y2: 44713 | Z2: 44743 | AA2: 44774 | AB2: 44805 | AC2: 44835 | AD2: 44866 | AE2: 44896 | AF2: Audited-2022 | AG2: 44949 | AH2: 44980 | AI2: 45008 | AJ2: 45039 | AK2: 45069 | AL2: 45100 | AM2: 45130 | AN2: 45161
B3: CAPITAL
B4: CORE CAPITAL | C4: ≥ Ksh.10M | D4: ='Prudential Ratios'!#REF! -> #REF! | E4: ='Prudential Ratios'!#REF! -> #REF! | F4: ='Prudential Ratios'!D6 -> 0 | G4: ='Prudential Ratios'!E6 -> 6578.7089 | H4: ='Prudential Ratios'!F6 -> 6664.0025 | I4: ='Prudential Ratios'!G6 -> 6555.7887 | J4: ='Prudential Ratios'!H6 -> 6722.7782 | K4: ='Prudential Ratios'!I6 -> 6916.5815 | L4: ='Prudential Ratios'!J6 -> 6899.1975 | M4: ='Prudential Ratios'!K6 -> 7079.1033 | ... AL4: ='Prudential Ratios'!AJ6 -> 8931.2173
B5: CCA | C5: ≥ 10% | D5: ='Prudential Ratios'!#REF! -> #REF! | E5: ='Prudential Ratios'!#REF! -> #REF! | F5: ='Prudential Ratios'!D7 -> 0 | G5: ='Prudential Ratios'!E7 -> 0.15865783 | H5: ='Prudential Ratios'!F7 -> 0.15884834 | I5: ='Prudential Ratios'!G7 -> 0.15934179 | J5: ='Prudential Ratios'!H7 -> 0.16194356 | K5: ='Prudential Ratios'!I7 -> 0.16491152 | L5: ='Prudential Ratios'!J7 -> 0.16266766 | M5: ='Prudential Ratios'!K7 -> 0.16547489 | ... AL5: ='Prudential Ratios'!AJ7 -> 0.16449256
B6: ICA | C6: ≥ 8% | D6: ='Prudential Ratios'!#REF! -> #REF! | E6: ='Prudential Ratios'!#REF! -> #REF! | F6: ='Prudential Ratios'!D10 -> 0 | G6: ='Prudential Ratios'!E10 -> 0.10939766 | H6: ='Prudential Ratios'!F10 -> 0.10964818 | I6: ='Prudential Ratios'!G10 -> 0.10754573 | J6: ='Prudential Ratios'!H10 -> 0.10994411 | K6: ='Prudential Ratios'!I10 -> 0.11291037 | L6: ='Prudential Ratios'!J10 -> 0.11067999 | M6: ='Prudential Ratios'!K10 -> 0.11307688 | ... AL6: ='Prudential Ratios'!AJ10 -> 0.10438881
B7: CCD | C7: ≥ 8% | D7: ='Prudential Ratios'!#REF! -> #REF! | E7: ='Prudential Ratios'!#REF! -> #REF! | F7: ='Prudential Ratios'!D8 -> 0 | G7: ='Prudential Ratios'!E8 -> 0.21071153 | H7: ='Prudential Ratios'!F8 -> 0.21273766 | I7: ='Prudential Ratios'!G8 -> 0.2008079 | J7: ='Prudential Ratios'!H8 -> 0.20518068 | K7: ='Prudential Ratios'!I8 -> 0.21123958 | L7: ='Prudential Ratios'!J8 -> 0.20953859 | M7: ='Prudential Ratios'!K8 -> 0.21630414 | ... AL7: ='Prudential Ratios'!AJ8 -> 0.21805422
B8: Asset Quality
B9: NPL | C9: ≤ 6%
B10: Earnings
B11: ROA | D11: ='Prudential Ratios'!#REF! -> #REF! | E11: ='Prudential Ratios'!#REF! -> #REF! | F11: ='Prudential Ratios'!D55 -> 0 | G11: ='Prudential Ratios'!E55 -> -1.9118409e-10 | H11: ='Prudential Ratios'!F55 -> -1.7616701e-10 | I11: ='Prudential Ratios'!G55 -> -1.5994e-10 | J11: ='Prudential Ratios'!H55 -> -1.4539702e-10 | K11: ='Prudential Ratios'!I55 -> -1.2803344e-10 | L11: ='Prudential Ratios'!J55 -> -1.1085143e-10 | M11: ='Prudential Ratios'!K55 -> -9.4039312e-11 | ... AL11: ='Prudential Ratios'!AJ55 -> -0.0019981104
B12: CIR | D12: ='Prudential Ratios'!#REF! -> #REF! | E12: ='Prudential Ratios'!#REF! -> #REF! | F12: ='Prudential Ratios'!D56 -> 0 | G12: ='Prudential Ratios'!E56 -> #DIV/0! | H12: ='Prudential Ratios'!F56 -> #DIV/0! | I12: ='Prudential Ratios'!G56 -> #DIV/0! | J12: ='Prudential Ratios'!H56 -> #DIV/0! | K12: ='Prudential Ratios'!I56 -> #DIV/0! | L12: ='Prudential Ratios'!J56 -> #DIV/0! | M12: ='Prudential Ratios'!K56 -> #DIV/0! | ... AL12: ='Prudential Ratios'!AJ56 -> 0.48272104
B13: OER | D13: ='Prudential Ratios'!#REF! -> #REF! | E13: ='Prudential Ratios'!#REF! -> #REF! | F13: ='Prudential Ratios'!D57 -> 0 | G13: ='Prudential Ratios'!E57 -> 0 | H13: ='Prudential Ratios'!F57 -> 0 | I13: ='Prudential Ratios'!G57 -> 0 | J13: ='Prudential Ratios'!H57 -> 0 | K13: ='Prudential Ratios'!I57 -> 0 | L13: ='Prudential Ratios'!J57 -> 0 | M13: ='Prudential Ratios'!K57 -> 0 | ... AL13: ='Prudential Ratios'!AJ57 -> 0.018698524
B14: LIQUIDITY
B15: MIN LIQ | C15: 0.15 | D15: ='Prudential Ratios'!#REF! -> #REF! | E15: ='Prudential Ratios'!#REF! -> #REF! | F15: ='Prudential Ratios'!D47 -> 0 | G15: ='Prudential Ratios'!E47 -> 0.1920364 | H15: ='Prudential Ratios'!F47 -> 0.19261706 | I15: ='Prudential Ratios'!G47 -> 0.19469053 | J15: ='Prudential Ratios'!H47 -> 0.17994745 | K15: ='Prudential Ratios'!I47 -> 0.18302274 | L15: ='Prudential Ratios'!J47 -> 0.18969881 | M15: ='Prudential Ratios'!K47 -> 0.19398708 | ... AL15: ='Prudential Ratios'!AJ47 -> 0.176209
B16: TEC LIQ | D16: ='Prudential Ratios'!#REF! -> #REF! | E16: ='Prudential Ratios'!#REF! -> #REF! | F16: ='Prudential Ratios'!D48 -> 0 | G16: ='Prudential Ratios'!E48 -> 0.15173396 | H16: ='Prudential Ratios'!F48 -> 0.15299789 | I16: ='Prudential Ratios'!G48 -> 0.1489151 | J16: ='Prudential Ratios'!H48 -> 0.13846407 | K16: ='Prudential Ratios'!I48 -> 0.14211175 | L16: ='Prudential Ratios'!J48 -> 0.14747728 | M16: ='Prudential Ratios'!K48 -> 0.15386578 | ... AL16: ='Prudential Ratios'!AJ48 -> 0.14323737
B17: EB | C17: ≤ 25% | D17: ='Prudential Ratios'!#REF! -> #REF! | E17: ='Prudential Ratios'!#REF! -> #REF! | F17: ='Prudential Ratios'!D27 -> 0 | G17: ='Prudential Ratios'!E27 -> 0 | H17: ='Prudential Ratios'!F27 -> 0 | I17: ='Prudential Ratios'!G27 -> 0 | J17: ='Prudential Ratios'!H27 -> 0 | K17: ='Prudential Ratios'!I27 -> 0 | L17: ='Prudential Ratios'!J27 -> 0 | M17: ='Prudential Ratios'!K27 -> 0 | ... AL17: ='Prudential Ratios'!AJ27 -> 0.0049804887
B18: LIQ/TA | D18: ='Prudential Ratios'!#REF! -> #REF! | E18: ='Prudential Ratios'!#REF! -> #REF! | F18: ='Prudential Ratios'!D58 -> 0.12148195 | G18: ='Prudential Ratios'!E58 -> 0.12762157 | H18: ='Prudential Ratios'!F58 -> 0.12865596 | I18: ='Prudential Ratios'!G58 -> 0.12514852 | J18: ='Prudential Ratios'!H58 -> 0.11600552 | K18: ='Prudential Ratios'!I58 -> 0.11864014 | L18: ='Prudential Ratios'!J58 -> 0.12345082 | M18: ='Prudential Ratios'!K58 -> 0.12836691 | ... AL18: ='Prudential Ratios'!AJ58 -> 0.11888809
B19: STRUCTURE
B20: NEA | C20: ≤ 10% | D20: ='Prudential Ratios'!#REF! -> #REF! | E20: ='Prudential Ratios'!#REF! -> #REF! | F20: ='Prudential Ratios'!D14 -> 0 | G20: ='Prudential Ratios'!E14 -> 0.035368553 | H20: ='Prudential Ratios'!F14 -> 0.040774312 | I20: ='Prudential Ratios'!G14 -> 0.033083895 | J20: ='Prudential Ratios'!H14 -> 0.040344571 | K20: ='Prudential Ratios'!I14 -> 0.039739294 | L20: ='Prudential Ratios'!J14 -> 0.040677021 | M20: ='Prudential Ratios'!K14 -> 0.045702627 | ... AL20: ='Prudential Ratios'!AJ14 -> 0.04876996
B21: LB | C21: ≤ 5% | D21: ='Prudential Ratios'!#REF! -> #REF! | E21: ='Prudential Ratios'!#REF! -> #REF! | F21: ='Prudential Ratios'!D15 -> 0 | G21: ='Prudential Ratios'!E15 -> 0.0055126393 | H21: ='Prudential Ratios'!F15 -> 0.0054400205 | I21: ='Prudential Ratios'!G15 -> 0.0055423733 | J21: ='Prudential Ratios'!H15 -> 0.0054591737 | K21: ='Prudential Ratios'!I15 -> 0.0053447843 | L21: ='Prudential Ratios'!J15 -> 0.0052457843 | M21: ='Prudential Ratios'!K15 -> 0.0051669335 | ... AL21: ='Prudential Ratios'!AJ15 -> 0.0081536805
B22: FITD | C22: ≤ 5% | D22: ='Prudential Ratios'!#REF! -> #REF! | E22: ='Prudential Ratios'!#REF! -> #REF! | F22: ='Prudential Ratios'!D19 -> 0 | G22: ='Prudential Ratios'!E19 -> 0.01849949 | H22: ='Prudential Ratios'!F19 -> 0.018438608 | I22: ='Prudential Ratios'!G19 -> 0.01769188 | J22: ='Prudential Ratios'!H19 -> 0.017628083 | K22: ='Prudential Ratios'!I19 -> 0.017640198 | L22: ='Prudential Ratios'!J19 -> 0.017542212 | M22: ='Prudential Ratios'!K19 -> 0.017648467 | ... AL22: ='Prudential Ratios'!AJ19 -> 0.01363028
B23: FICC | C23: ≤ 40% | D23: ='Prudential Ratios'!#REF! -> #REF! | E23: ='Prudential Ratios'!#REF! -> #REF! | F23: ='Prudential Ratios'!D20 -> 0 | G23: ='Prudential Ratios'!E20 -> 0.087795341 | H23: ='Prudential Ratios'!F20 -> 0.086672984 | I23: ='Prudential Ratios'!G20 -> 0.088103509 | J23: ='Prudential Ratios'!H20 -> 0.085914926 | K23: ='Prudential Ratios'!I20 -> 0.083508014 | L23: ='Prudential Ratios'!J20 -> 0.083718286 | M23: ='Prudential Ratios'!K20 -> 0.081590981 | ... AL23: ='Prudential Ratios'!AJ20 -> 0.062508674

Sheet Financials
B1: STIMA SACCO SOCIETY
B3: Year | C3: AUDITED 2020 | D3: 44197 | E3: 44228 | F3: 44256 | G3: 44287 | H3: 44317 | I3: 44348 | J3: 44378 | K3: 44409 | L3: 44440 | M3: 44470 | N3: 44501 | O3: 44531 | P3: Audited 2021 | Q3: 44562 | R3: 44593 | S3: 44621 | T3: 44652 | U3: 44682 | V3: 44713 | W3: 44743 | X3: 44774 | Y3: 44805 | Z3: 44835 | AA3: 44866 | AB3: 44896 | AC3: Audited-2022 | AD3: 44949 | AE3: 44980 | AF3: 45008 | AG3: 45039 | AH3: 45069 | AI3: 45100 | AJ3: 45130 | AK3: 45161
A4: 1 | B4: Membership
A5: 2 | B5: Total Assets | C5: =SFP!B27 -> 42034351000 | D5: =SFP!C27 -> 4.1464759e+10 | E5: =SFP!D27 -> 4.195198e+10 | F5: =SFP!E27 -> 4.1142932e+10 | G5: =SFP!F27 -> 4.1513094e+10 | H5: =SFP!G27 -> 4.1941166e+10 | I5: =SFP!H27 -> 4.241284e+10 | J5: =SFP!I27 -> 4.2780529e+10 | ... AI5: =SFP!AH27 -> 5.4295569e+10
A6: 3 | B6: Total Deposits | C6: =SFP!B32 -> 31188264000 | D6: =SFP!C32 -> 3.12214e+10 | E6: =SFP!D32 -> 3.1324978e+10 | F6: =SFP!E32 -> 3.2647066e+10 | G6: =SFP!F32 -> 3.2765161e+10 | H6: =SFP!G32 -> 3.2742829e+10 | I6: =SFP!H32 -> 3.2925665e+10 | J6: =SFP!I32 -> 3.2727545e+10 | ... AI6: =SFP!AH32 -> 4.0958699e+10
A7: 3.1 | B7: Deposits-Members(BOSA) | C7: =SFP!B31 -> 23712329000 | D7: =SFP!C31 -> 2.3902122e+10 | E7: =SFP!D31 -> 2.4068807e+10 | F7: =SFP!E31 -> 2.4517453e+10 | G7: =SFP!F31 -> 2.4747363e+10 | H7: =SFP!G31 -> 2.4916157e+10 | I7: =SFP!H31 -> 2.5023692e+10 | J7: =SFP!I31 -> 2.5345793e+10 | ... AI7: =SFP!AH31 -> 3.2526154e+10
A8: 3.2 | B8: Deposits-Customers(FOSA) | C8: =SFP!B29 -> 3877885000 | D8: =SFP!C29 -> 3.105756e+09 | E8: =SFP!D29 -> 3.0523927e+09 | F8: =SFP!E29 -> 3.8041352e+09 | G8: =SFP!F29 -> 3.6172968e+09 | H8: =SFP!G29 -> 3.416059e+09 | I8: =SFP!H29 -> 3.4953064e+09 | J8: =SFP!I29 -> 2.7811918e+09 | ... AI8: =SFP!AH29 -> 3.6541014e+09
A9: 4 | B9: External Borrowing | C9: =SFP!B39 -> 0 | D9: =SFP!C39 -> 0 | E9: =SFP!D39 -> 0 | F9: =SFP!E39 -> 0 | G9: =SFP!F39 -> 0 | H9: =SFP!G39 -> 0 | I9: =SFP!H39 -> 0 | J9: =SFP!I39 -> 0 | ... AI9: =SFP!AH39 -> 2.7041847e+08
A10: 4.1 | B10: Short term Liabilities | C10: =SFP!B34+SFP!B35+SFP!B36+SFP!B37+SFP!B38 -> 3486231000 | D10: =SFP!C34+SFP!C35+SFP!C36+SFP!C37+SFP!C38 -> 3.6541015e+09 | E10: =SFP!D34+SFP!D35+SFP!D36+SFP!D37+SFP!D38 -> 3.9524504e+09 | F10: =SFP!E34+SFP!E35+SFP!E36+SFP!E37+SFP!E38 -> 1.929529e+09 | G10: =SFP!F34+SFP!F35+SFP!F36+SFP!F37+SFP!F38 -> 2.0146064e+09 | H10: =SFP!G34+SFP!G35+SFP!G36+SFP!G37+SFP!G38 -> 2.271206e+09 | I10: =SFP!H34+SFP!H35+SFP!H36+SFP!H37+SFP!H38 -> 2.577429e+09 | J10: =SFP!I34+SFP!I35+SFP!I36+SFP!I37+SFP!I38 -> 2.963332e+09 | ... AI10: =SFP!AH34+SFP!AH35+SFP!AH36+SFP!AH37+SFP!AH38 -> 4.1070282e+09
A13: 5 | B13: Share capital and Reserves
A14: 5.1 | B14: Core Capital | C14: =C17 -> 6095283000 | D14: =D17 -> 6.5787089e+09 | E14: =E17 -> 6.6640025e+09 | F14: =F17 -> 6.5557887e+09 | G14: =G17 -> 6.7227782e+09 | H14: =H17 -> 6.9165815e+09 | I14: =I17 -> 6.8991975e+09 | J14: =J17 -> 7.0791033e+09 | ... AI14: =AI17 -> 8.9312173e+09
A15: 5.2 | B15: Institutional Capital | C15: =C14-C18 -> 4072845000 | D15: =D14-D18 -> 4.5361476e+09 | E15: =E14-E18 -> 4.5999583e+09 | F15: =F14-F18 -> 4.4247465e+09 | G15: =G14-G18 -> 4.56412e+09 | H15: =H14-H18 -> 4.7355924e+09 | I15: =I14-I18 -> 4.6942529e+09 | J15: =J14-J18 -> 4.8374885e+09 | ... AI15: =AI14-AI18 -> 5.6678499e+09
A17: 5.3 | B17: Total Capital | C17: =SUM(C18:C21) -> 6095283000 | D17: =SUM(D18:D21) -> 6.5787089e+09 | E17: =SUM(E18:E21) -> 6.6640025e+09 | F17: =SUM(F18:F21) -> 6.5557887e+09 | G17: =SUM(G18:G21) -> 6.7227782e+09 | H17: =SUM(H18:H21) -> 6.9165815e+09 | I17: =SUM(I18:I21) -> 6.8991975e+09 | J17: =SUM(J18:J21) -> 7.0791033e+09 | ... AI17: =SUM(AI18:AI21) -> 8.9312173e+09
A18: 5.3.1 | B18: Members Share Capital | C18: =SFP!B42 -> 2022438000 | D18: =SFP!C42 -> 2.0425613e+09 | E18: =SFP!D42 -> 2.0640442e+09 | F18: =SFP!E42 -> 2.1310422e+09 | G18: =SFP!F42 -> 2.1586581e+09 | H18: =SFP!G42 -> 2.1809892e+09 | I18: =SFP!H42 -> 2.2049446e+09 | J18: =SFP!I42 -> 2.2416148e+09 | ... AI18: =SFP!AH42 -> 3.2633674e+09
A19: 5.3.3 | B19: Retained Earnings | C19: =SFP!B45 -> 2883949000 | D19: =SFP!C45 -> 3.3387782e+09 | E19: =SFP!D45 -> 3.4110617e+09 | F19: =SFP!E45 -> 3.2358499e+09 | G19: =SFP!F45 -> 3.3752235e+09 | H19: =SFP!G45 -> 3.5466958e+09 | I19: =SFP!H45 -> 3.5053563e+09 | J19: =SFP!I45 -> 3.6485919e+09 | ... AI19: =SFP!AH45 -> 3.9975967e+09
A20: 5.3.5 | B20: Statutory Reserves | C20: =SFP!B50 -> 1188896000 | D20: =SFP!C50 -> 1.184895e+09 | E20: =SFP!D50 -> 1.1764222e+09 | F20: =SFP!E50 -> 1.1764222e+09 | G20: =SFP!F50 -> 1.1764222e+09 | H20: =SFP!G50 -> 1.1764222e+09 | I20: =SFP!H50 -> 1.1764222e+09 | J20: =SFP!I50 -> 1.1764222e+09 | ... AI20: =SFP!AH50 -> 1.6577788e+09
A21: 5.3.6 | B21: Capital Reserve | C21: =SFP!B51 -> 0 | D21: =SFP!C51 -> 12474413 | E21: =SFP!D51 -> 12474413 | F21: =SFP!E51 -> 12474413 | G21: =SFP!F51 -> 12474413 | H21: =SFP!G51 -> 12474413 | I21: =SFP!H51 -> 12474413 | J21: =SFP!I51 -> 12474413 | ... AI21: =SFP!AH51 -> 12474413
A22: 5.3.7 | B22: Supplementary Capital & reserves
A23: a | B23: Proposed Dividends | C23: =SFP!B53 -> 280921000 | D23: =SFP!C53 -> 0 | E23: =SFP!D53 -> 0 | F23: =SFP!E53 -> 0 | G23: =SFP!F53 -> 0 | H23: =SFP!G53 -> 0 | I23: =SFP!H53 -> 0 | J23: =SFP!I53 -> 0 | ... AI23: =SFP!AH53 -> 0
A24: b
A26: 6 | B26: Investments | C26: =C27+C28+C29 -> 1962102000 | D26: =D27+D28+D29 -> 5.7757999e+08 | E26: =E27+E28+E29 -> 5.7758899e+08 | F26: =F27+F28+F29 -> 5.7758799e+08 | G26: =G27+G28+G29 -> 5.7758699e+08 | H26: =H27+H28+H29 -> 5.7758999e+08 | I26: =I27+I28+I29 -> 5.7758899e+08 | J26: =J27+J28+J29 -> 5.7759099e+08 | ... AI26: =AI27+AI28+AI29 -> 5.5827855e+08
A27: 6.1 | B27: Investments in Coop bank, CIC, Kuscco, Kerussu & Codic | C27: =SFP!B12 -> 924989000 | D27: =SFP!C12 -> 5.6111111e+08 | E27: =SFP!D12 -> 5.6112011e+08 | F27: =SFP!E12 -> 5.6111911e+08 | G27: =SFP!F12 -> 5.6111811e+08 | H27: =SFP!G12 -> 5.6112111e+08 | I27: =SFP!H12 -> 5.6112011e+08 | J27: =SFP!I12 -> 5.6112211e+08 | ... AI27: =SFP!AH12 -> 5.4460263e+08
A28: 6.2 | B28: Equity Investments (at cost) | C28: =SFP!B13 -> 1037113000 | D28: =SFP!C13 -> 0 | E28: =SFP!D13 -> 0 | F28: =SFP!E13 -> 0 | G28: =SFP!F13 -> 0 | H28: =SFP!G13 -> 0 | I28: =SFP!H13 -> 0 | J28: =SFP!I13 -> 0 | ... AI28: =SFP!AH13 -> 0
A29: 6.3 | B29: Deposits in KUSCCO CFP | C29: =SFP!B11 -> 0 | D29: =SFP!C11 -> 16468881 | E29: =SFP!D11 -> 16468881 | F29: =SFP!E11 -> 16468881 | G29: =SFP!F11 -> 16468881 | H29: =SFP!G11 -> 16468881 | I29: =SFP!H11 -> 16468881 | J29: =SFP!I11 -> 16468881 | ... AI29: =SFP!AH11 -> 13675921
A31: 7 | B31: Net Loans & advances | C31: =C32-C33 -> 36473944000 | D31: =D32-D33 -> 3.3254628e+10 | E31: =E32-E33 -> 3.3387332e+10 | F31: =F32-F33 -> 3.3173428e+10 | G31: =G32-G33 -> 3.3316115e+10 | H31: =H32-H33 -> 3.3586804e+10 | I31: =I32-I33 -> 3.3621973e+10 | J31: =J32-J33 -> 3.3499803e+10 | ... AI31: =AI32-AI33 -> 4.1500832e+10
A32: 7.1 | B32: Gross Loans & advances | C32: =SFP!B15 -> 38804173000 | D32: =SFP!C15 -> 3.5584857e+10 | E32: =SFP!D15 -> 3.5717561e+10 | F32: =SFP!E15 -> 3.5639734e+10 | G32: =SFP!F15 -> 3.5782421e+10 | H32: =SFP!G15 -> 3.605311e+10 | I32: =SFP!H15 -> 3.6224357e+10 | J32: =SFP!I15 -> 3.6102187e+10 | ... AI32: =SFP!AH15 -> 4.6508103e+10
A33: 7.3 | B33: Allowance for loan losses | C33: =SFP!B16 -> 2330229000 | D33: =SFP!C16 -> 2330229000 | E33: =SFP!D16 -> 2330229000 | F33: =SFP!E16 -> 2466306500 | G33: =SFP!F16 -> 2466306500 | H33: =SFP!G16 -> 2466306500 | I33: =SFP!H16 -> 2602384000 | J33: =SFP!I16 -> 2602384000 | ... AI33: =SFP!AH16 -> 5007270624
A34: 7.4 | B34: Non Performing Loans | C34: =(#REF!+#REF!+#REF!) -> #REF! | D34: =(#REF!+#REF!+#REF!) -> #REF! | E34: =(#REF!+#REF!+#REF!) -> #REF! | F34: =(#REF!+#REF!+#REF!) -> #REF! | G34: =(#REF!+#REF!+#REF!) -> #REF! | H34: =(#REF!+#REF!+#REF!) -> #REF! | I34: =(#REF!+#REF!+#REF!) -> #REF! | J34: =(#REF!+#REF!+#REF!) -> #REF! | ... AI34: =(#REF!+#REF!+#REF!) -> #REF!
A35: 7.5 | B35: Required loan loss provision | C35: =#REF! -> #REF! | D35: =#REF! -> #REF! | E35: =#REF! -> #REF! | F35: =#REF! -> #REF! | G35: =#REF! -> #REF! | H35: =#REF! -> #REF! | I35: =#REF! -> #REF! | J35: =#REF! -> #REF! | ... AI35: =#REF! -> #REF!
A36: 7.6 | B36: Cash and Cash equipments | C36: =SFP!B4 -> 5106415000 | D36: =SFP!C4 -> 5.2753289e+09 | E36: =SFP!D4 -> 5.3809033e+09 | F36: =SFP!E4 -> 5.1325082e+09 | G36: =SFP!F4 -> 4.7992793e+09 | H36: =SFP!G4 -> 4.9594368e+09 | I36: =SFP!H4 -> 5219430959 | J36: =SFP!I4 -> 5.4751356e+09 | ... AI36: =SFP!AH4 -> 6.4414204e+09
A38: 8 | B38: Non-Earning Assets | C38: =SFP!B7+SFP!B17+SFP!B23+SFP!B24+SFP!B25+SFP!B26 -> 2167040000 | D38: =SFP!C7+SFP!C17+SFP!C23+SFP!C24+SFP!C25+SFP!C26 -> 1.4665485e+09 | E38: =SFP!D7+SFP!D17+SFP!D23+SFP!D24+SFP!D25+SFP!D26 -> 1.7105631e+09 | F38: =SFP!E7+SFP!E17+SFP!E23+SFP!E24+SFP!E25+SFP!E26 -> 1.3611685e+09 | G38: =SFP!F7+SFP!F17+SFP!F23+SFP!F24+SFP!F25+SFP!F26 -> 1.674828e+09 | H38: =SFP!G7+SFP!G17+SFP!G23+SFP!G24+SFP!G25+SFP!G26 -> 1.6667123e+09 | I38: =SFP!H7+SFP!H17+SFP!H23+SFP!H24+SFP!H25+SFP!H26 -> 1725227976 | J38: =SFP!I7+SFP!I17+SFP!I23+SFP!I24+SFP!I25+SFP!I26 -> 1.9551825e+09 | ... AI38: =SFP!AH7+SFP!AH17+SFP!AH23+SFP!AH24+SFP!AH25+SFP!AH26 -> 2.6479928e+09
A39: 8.1 | B39: Property and Equipment | C39: =SFP!B23 -> 223605000 | D39: =SFP!C23 -> 2.2858026e+08 | E39: =SFP!D23 -> 2.2821963e+08 | F39: =SFP!E23 -> 2.2802949e+08 | G39: =SFP!F23 -> 2.2662719e+08 | H39: =SFP!G23 -> 2.2416648e+08 | I39: =SFP!H23 -> 2.2248861e+08 | J39: =SFP!I23 -> 2.2104414e+08 | ... AI39: =SFP!AH23 -> 4.4270872e+08
A41: 9 | B41: Turnover | C41: =C42+C43+C44 -> 1199445000 | D41: =D42+D43+D44 -> 1.2079182e+09 | E41: =E42+E43+E44 -> 1.1994453e+09 | F41: =F42+F43+F44 -> 1.1994453e+09 | G41: =G42+G43+G44 -> 1.1994453e+09 | H41: =H42+H43+H44 -> 1.1994453e+09 | I41: =I42+I43+I44 -> 1.1994453e+09 | J41: =J42+J43+J44 -> 1.1994453e+09 | ... AI41: =AI42+AI43+AI44 -> 1.6984598e+09
A42: 9.1 | B42: Loan Interest | C42: =SFP!B50 -> 1188896000 | D42: =SFP!C50 -> 1.184895e+09 | E42: =SFP!D50 -> 1.1764222e+09 | F42: =SFP!E50 -> 1.1764222e+09 | G42: =SFP!F50 -> 1.1764222e+09 | H42: =SFP!G50 -> 1.1764222e+09 | I42: =SFP!H50 -> 1.1764222e+09 | J42: =SFP!I50 -> 1.1764222e+09 | ... AI42: =SFP!AH50 -> 1.6577788e+09
B43: Income from investments | C43: =SFP!B51 -> 0 | D43: =SFP!C51 -> 12474413 | E43: =SFP!D51 -> 12474413 | F43: =SFP!E51 -> 12474413 | G43: =SFP!F51 -> 12474413 | H43: =SFP!G51 -> 12474413 | I43: =SFP!H51 -> 12474413 | J43: =SFP!I51 -> 12474413 | ... AI43: =SFP!AH51 -> 12474413
A44: 9.2 | B44: Fees & Commissions | C44: =SFP!B52 -> 10549000 | D44: =SFP!C52 -> 10548735 | E44: =SFP!D52 -> 10548735 | F44: =SFP!E52 -> 10548735 | G44: =SFP!F52 -> 10548735 | H44: =SFP!G52 -> 10548735 | I44: =SFP!H52 -> 10548735 | J44: =SFP!I52 -> 10548735 | ... AI44: =SFP!AH52 -> 28206616
B45: Average yield on loans
A47: 10 | B47: Total Expenses (FinCosts + OpEx) | C47: =SUM(C48:C53) -> 3620405000 | D47: =SUM(D48:D53) -> 0 | E47: =SUM(E48:E53) -> 0 | F47: =SUM(F48:F53) -> 0 | G47: =SUM(G48:G53) -> 0 | H47: =SUM(H48:H53) -> 0 | I47: =SUM(I48:I53) -> 0 | J47: =SUM(J48:J53) -> 0 | ... AI47: =SUM(AI48:AI53) -> 2.3185099e+09
A48: 10.1 | B48: Financial Exp. (Interest on deposits) | C48: =SCI!B13 -> 2826735000 | D48: =SCI!C13 -> 0 | E48: =SCI!D13 -> 0 | F48: =SCI!E13 -> 0 | G48: =SCI!F13 -> 0 | H48: =SCI!G13 -> 0 | I48: =SCI!H13 -> 0 | J48: =SCI!I13 -> 0 | ... AI48: =SCI!AH13 -> 1.8222013e+08
A49: 10.2 | B49: Financial Exp. (Dividends) | C49: =SCI!B15 -> 0 | D49: =SCI!C15 -> 0 | E49: =SCI!D15 -> 0 | F49: =SCI!E15 -> 0 | G49: =SCI!F15 -> 0 | H49: =SCI!G15 -> 0 | I49: =SCI!H15 -> 0 | J49: =SCI!I15 -> 0 | ... AI49: =SCI!AH15 -> 1.6955508e+09
A50: 10.3 | B50: Financial Exp. (Interest on bank loans) | C50: =SCI!B14 -> 0 | D50: =SCI!C14 -> 0 | E50: =SCI!D14 -> 0 | F50: =SCI!E14 -> 0 | G50: =SCI!F14 -> 0 | H50: =SCI!G14 -> 0 | I50: =SCI!H14 -> 0 | J50: =SCI!I14 -> 0 | ... AI50: =SCI!AH14 -> 7314724
A51: 10.4 | B51: Other Financial Expenses | C51: =SCI!B16+SCI!B17+SCI!B18 -> 192704000 | D51: =SCI!C16+SCI!C17+SCI!C18 -> 0 | E51: =SCI!D16+SCI!D17+SCI!D18 -> 0 | F51: =SCI!E16+SCI!E17+SCI!E18 -> 0 | G51: =SCI!F16+SCI!F17+SCI!F18 -> 0 | H51: =SCI!G16+SCI!G17+SCI!G18 -> 0 | I51: =SCI!H16+SCI!H17+SCI!H18 -> 0 | J51: =SCI!I16+SCI!I17+SCI!I18 -> 0 | ... AI51: =SCI!AH16+SCI!AH17+SCI!AH18 -> 17277706
A52: 10.5 | B52: Administrative Expenses | C52: =SCI!B28 -> 600966000 | D52: =SCI!C28 -> 0 | E52: =SCI!D28 -> 0 | F52: =SCI!E28 -> 0 | G52: =SCI!F28 -> 0 | H52: =SCI!G28 -> 0 | I52: =SCI!H28 -> 0 | J52: =SCI!I28 -> 0 | ... AI52: =SCI!AH28 -> 3.9107732e+08
A53: 10.6 | B53: Governance Expenses | C53: =SCI!B25 -> 0 | D53: =SCI!C25 -> 0 | E53: =SCI!D25 -> 0 | F53: =SCI!E25 -> 0 | G53: =SCI!F25 -> 0 | H53: =SCI!G25 -> 0 | I53: =SCI!H25 -> 0 | J53: =SCI!I25 -> 0 | ... AI53: =SCI!AH25 -> 25069293
B54: LLP
B56: Net Surplus | C56: =SCI!B37 -> 1021122000 | D56: =SCI!C37 -> -12 | E56: =SCI!D37 -> -11 | F56: =SCI!E37 -> -10 | G56: =SCI!F37 -> -9 | H56: =SCI!G37 -> -8 | I56: =SCI!H37 -> -7 | J56: =SCI!I37 -> -6 | ... P56: =SCI!O37 -> 1424512000

Sheet form4
D3: RISK CLASSIFICATION OF ASSETS AND PROVISIONING | L3: RISK CLASSIFICATION OF ASSETS AND PROVISIONING
D4: SACCO SOCIETY CS NUMBER | L4: SACCO SOCIETY CS NUMBER
D5: FINANCIAL YEAR | L5: FINANCIAL YEAR
D6: START DATE: | L6: START DATE:
D7: END DATE: | L7: END DATE:
D8: PORTFOLIO AGEING REPORT | L8: PORTFOLIO AGEING REPORT
E9: A | F9: B | G9: C | H9: D | M9: A | N9: B | O9: C | P9: D
C10: NO. | D10: CLASSIFICATION | E10: NO. OF A/Cs | F10: OUTSTANDING LOAN PORTFOLIO(Kshs) | G10: REQUIRED PROVISION | H10: REQUIRED PROVISION AMOUNT(Kshs) | K10: NO. | L10: CLASSIFICATION | M10: NO. OF A/Cs | N10: OUTSTANDING LOAN PORTFOLIO(Kshs) | O10: REQUIRED PROVISION | P10: REQUIRED PROVISION AMOUNT(Kshs)
C11: 1 | D11: Performing | K11: 1 | L11: Performing
C12: 2 | D12: Watch | K12: 2 | L12: Watch
C13: 3 | D13: Substandard | K13: 3 | L13: Substandard
C14: 4 | D14: Doubtful | K14: 4 | L14: Doubtful
C15: 5 | D15: Loss | K15: 5 | L15: Loss
D16: subtotal | L16: subtotal | M16: =SUM(M11:M15) -> 0 | N16: =SUM(N11:N15) -> 0 | P16: =SUM(P11:P15) -> 0
D17: Reschedule/Renegotiated loans | L17: Reschedule/Renegotiated loans
C18: 1 | D18: Performing | K18: 1 | L18: Performing | M18: 0 | N18: 0 | O18: 0.01 | P18: =N18*O18 -> 0
C19: 2 | D19: Watch | K19: 2 | L19: Watch | M19: 0 | N19: 0 | O19: 0.05 | P19: =N19*O19 -> 0
C20: 3 | D20: Substandard | K20: 3 | L20: Substandard | M20: 0 | N20: 0 | O20: 0.25 | P20: =N20*O20 -> 0
C21: 4 | D21: Doubtful | K21: 4 | L21: Doubtful | M21: 0 | N21: 0 | O21: 0.5 | P21: =N21*O21 -> 0
C22: 5 | D22: Loss | K22: 5 | L22: Loss | M22: 0 | N22: 0 | O22: 1 | P22: =N22*O22 -> 0
D23: subtotal | E23: =SUM(E17:E22) -> 0 | F23: =SUM(F17:F22) -> 0 | H23: =SUM(H17:H22) -> 0 | L23: subtotal | M23: =SUM(M17:M22) -> 0 | N23: =SUM(N17:N22) -> 0 | P23: =SUM(P17:P22) -> 0
D24: GRAND TOTAL | E24: =E16+E23 -> 0 | F24: =F16+F23 -> 0 | H24: =H16+H23 -> 0 | L24: GRAND TOTAL | M24: =M16+M23 -> 0 | N24: =N16+N23 -> 0 | P24: =P16+P23 -> 0
F26: =F13+F14+F15 -> 0 | N26: =N13+N14+N15 -> 0
F27: =F26/F24 -> #DIV/0! | N27: =N26/N24 -> #DIV/0!
D30: RISK CLASSIFICATION OF ASSETS AND PROVISIONING
D31: SACCO SOCIETY CS NUMBER
D32: FINANCIAL YEAR
D33: START DATE:
D34: END DATE:
D35: PORTFOLIO AGEING REPORT
E36: A | F36: B | G36: C | H36: D
C37: NO. | D37: CLASSIFICATION | E37: NO. OF A/Cs | F37: OUTSTANDING LOAN PORTFOLIO(Kshs) | G37: REQUIRED PROVISION | H37: REQUIRED PROVISION AMOUNT(Kshs)
C38: 1 | D38: Performing
C39: 2 | D39: Watch
C40: 3 | D40: Substandard
C41: 4 | D41: Doubtful
C42: 5 | D42: Loss
D43: subtotal
D44: Reschedule/Renegotiated loans
C45: 1 | D45: Performing | H45: =F45*G45 -> 0
C46: 2 | D46: Watch | H46: =F46*G46 -> 0
C47: 3 | D47: Substandard | H47: =F47*G47 -> 0
C48: 4 | D48: Doubtful | H48: =F48*G48 -> 0
C49: 5 | D49: Loss | H49: =F49*G49 -> 0
D50: subtotal | E50: =SUM(E44:E49) -> 0 | F50: =SUM(F44:F49) -> 0 | H50: =SUM(H44:H49) -> 0
D51: GRAND TOTAL | E51: =E43+E50 -> 0 | F51: =F43+F50 -> 0 | H51: =H43+H50 -> 0
F53: =F40+F41+F42 -> 0
F54: =F53/F51 -> #DIV/0!
D56: RISK CLASSIFICATION OF ASSETS AND PROVISIONING
D57: SACCO SOCIETY CS NUMBER
D58: FINANCIAL YEAR
D59: START DATE:
D60: END DATE:
D61: PORTFOLIO AGEING REPORT
E62: A | F62: B | G62: C | H62: D
C63: NO. | D63: CLASSIFICATION | E63: NO. OF A/Cs | F63: OUTSTANDING LOAN PORTFOLIO(Kshs) | G63: REQUIRED PROVISION | H63: REQUIRED PROVISION AMOUNT(Kshs)
C64: 1 | D64: Performing
C65: 2 | D65: Watch
C66: 3 | D66: Substandard
C67: 4 | D67: Doubtful
C68: 5 | D68: Loss
D69: subtotal | E69: =SUM(E64:E68) -> 0 | F69: =SUM(F64:F68) -> 0 | H69: =SUM(H64:H68) -> 0
D70: Reschedule/Renegotiated loans
C71: 1 | D71: Performing | E71: 0 | F71: 0 | G71: 0.01 | H71: =F71*G71 -> 0
C72: 2 | D72: Watch | E72: 0 | F72: 0 | G72: 0.05 | H72: =F72*G72 -> 0
C73: 3 | D73: Substandard | E73: 0 | F73: 0 | G73: 0.25 | H73: =F73*G73 -> 0
C74: 4 | D74: Doubtful | E74: 0 | F74: 0 | G74: 0.5 | H74: =F74*G74 -> 0
C75: 5 | D75: Loss | E75: 0 | F75: 0 | G75: 1 | H75: =F75*G75 -> 0
D76: subtotal | E76: =SUM(E70:E75) -> 0 | F76: =SUM(F70:F75) -> 0 | H76: =SUM(H70:H75) -> 0
D77: GRAND TOTAL | E77: =E69+E76 -> 0 | F77: =F69+F76 -> 0 | H77: =H69+H76 -> 0
F79: =F66+F67+F68 -> 0
F80: =F79/F77 -> #DIV/0!

Sheet SFP
A1: STIMA SACCO SOCIETY LTD
A2: STATEMENT OF FINANCIAL POSITION
B3: AUDITED 2020 | C3: 44197 | D3: 44228 | E3: 44256 | F3: 44287 | G3: 44317 | H3: 44348 | I3: 44378 | J3: 44409 | K3: 44440 | L3: 44470 | M3: 44501 | N3: 44531 | O3: AUDITED 2021 | P3: 44562 | Q3: 44593 | R3: 44621 | S3: 44652 | T3: 44682 | U3: 44713 | V3: 44743 | W3: 44774 | X3: 44805 | Y3: 44835 | Z3: 44866 | AA3: 44896 | AB3: Audited -22 | AC3: 44949 | AD3: 44980 | AE3: 45008 | AF3: 45039 | AG3: 45069 | AH3: 45100
A4: Cash & Cash Equivalent | B4: =SUM(B5:B6) -> 5106415000 | C4: =SUM(C5:C6) -> 5.2753289e+09 | D4: =SUM(D5:D6) -> 5.3809033e+09 | E4: =SUM(E5:E6) -> 5.1325082e+09 | F4: =SUM(F5:F6) -> 4.7992793e+09 | G4: =SUM(G5:G6) -> 4.9594368e+09 | H4: =SUM(H5:H6) -> 5219430959 | I4: =SUM(I5:I6) -> 5.4751356e+09 | ... AH4: =SUM(AH5:AH6) -> 6.4414204e+09
A5: Cash in hand | B5: 115892000 | C5: 1.2857947e+08 | D5: 1.4539753e+08 | E5: 1.0764315e+08 | F5: 1.2684321e+08 | G5: 1.2715288e+08 | H5: 1.2741211e+08 | I5: 1.290845e+08 | J5: 1.1183393e+08 | K5: 1.2843841e+08 | L5: 92938974 | M5: 1.2180419e+08 | N5: 1.1512263e+08 | O5: 115123000 | P5: 1.2455236e+08 | Q5: 1.3098178e+08 | R5: 99421740 | S5: 1.2105228e+08 | T5: 1.3777943e+08 | U5: 1.5470299e+08 | V5: 1.0156356e+08 | W5: 1.1877878e+08 | X5: 1.1681214e+08 | Y5: 1.1187792e+08 | Z5: 1.2039432e+08 | AA5: 1.0461845e+08 | AB5: 104618000 | AC5: 1.0521098e+08 | AD5: 69241337 | AE5: 1.5946773e+08 | AF5: 33049673 | AG5: 1.0279947e+08 | AH5: 1.0152892e+08
A6: Cash at bank | B6: =5106415000-115892000 -> 4990523000 | C6: 5.1467494e+09 | D6: 5.2355058e+09 | E6: 5.024865e+09 | F6: 4.6724361e+09 | G6: 4.8322839e+09 | H6: 5.0920188e+09 | I6: 5.3460511e+09 | J6: 5.9806698e+09 | K6: 5.7526138e+09 | L6: 5.0572624e+09 | M6: 5.1602138e+09 | N6: 4.9851885e+09 | O6: =5248820000-115123000 -> 5133697000 | P6: 5.4495063e+09 | Q6: 5.484205e+09 | R6: 5.0250617e+09 | S6: 5.1299777e+09 | T6: 4.7500073e+09 | U6: 5.2939674e+09 | V6: 5.5052828e+09 | W6: 5.4253844e+09 | X6: 5.8645242e+09 | Y6: 6.2292458e+09 | Z6: 6.5652845e+09 | AA6: 6.8228885e+09 | AB6: =94752000+588343000+10715000+8254000+2203000+588000-83000 -> 704772000 | AC6: 6.2410809e+09 | AD6: 7.2221189e+09 | AE6: 5.8632351e+09 | AF6: 5.5734798e+09 | AG6: 6.3907114e+09 | AH6: 6.3398915e+09
A7: Prepayments & Sundry Receivables | B7: 1156972000 | C7: 1.0200832e+09 | D7: 1.2543818e+09 | E7: 9.1428282e+08 | F7: 1.2226418e+09 | G7: 1.2262497e+09 | H7: 1.1420761e+09 | I7: 1.2819257e+09 | J7: 1.2483361e+09 | K7: 1.2901823e+09 | L7: 1.4158393e+09 | M7: 1.4645113e+09 | N7: 1.4535664e+09 | O7: 1377736000 | P7: 1.5514241e+09 | Q7: 1.7013963e+09 | R7: 1.5219573e+09 | S7: 1.6257412e+09 | T7: 1.6863316e+09 | U7: 1.6144922e+09 | V7: 1.6497037e+09 | W7: 1.6645516e+09 | X7: 1.6258434e+09 | Y7: 1853990948 | Z7: 1.807304e+09 | AA7: 1.7059784e+09 | AB7: 1036206000 | AC7: 1.9178279e+09 | AD7: 1.7504475e+09 | AE7: 1.3604844e+09 | AF7: 1.3109253e+09 | AG7: 1.0200696e+09 | AH7: 1.685916e+09
A8: Financial Investments | B8: =SUM(B9:B13) -> 1962102000 | C8: =SUM(C9:C13) -> 9.8105109e+08 | D8: =SUM(D9:D13) -> 9.8597887e+08 | E8: =SUM(E9:E13) -> 9.8862547e+08 | F8: =SUM(F9:F13) -> 1.2356702e+09 | G8: =SUM(G9:G13) -> 1.2410103e+09 | H8: =SUM(H9:H13) -> 1.3590054e+09 | I8: =SUM(I9:I13) -> 1.3623358e+09 | ... AH8: =SUM(AH9:AH13) -> 3.2149851e+09
A9: Government Securities - Treasury Bills/bonds, | C9: 0 | D9: 0 | E9: 0 | F9: 303108000 | G9: 303108000 | H9: 3.48308e+08 | I9: 3.48308e+08 | J9: 3.48308e+08 | K9: 5.2506809e+08 | L9: 1.0615231e+09 | M9: 1.0171573e+09 | N9: 1.0263505e+09 | O9: 1003586000 | P9: 1.003586e+09 | Q9: 1.0097287e+09 | R9: 1.0129561e+09 | S9: 9.9713107e+08 | T9: 1.4968042e+09 | U9: 1.5071375e+09 | V9: 1.5178153e+09 | W9: 2.0534723e+09 | X9: 2.0638056e+09 | Y9: 2.0289286e+09 | Z9: 2.0058347e+09 | AA9: 2.0458448e+09 | AB9: 1967562000 | AC9: 2.0671796e+09 | AD9: 2.0081672e+09 | AE9: 2.0295021e+09 | AF9: 1.9686331e+09 | AG9: 1.9486215e+09 | AH9: 1.9692668e+09
A10: Other Securities - Commercial papers/Bonds | C10: 4.034711e+08 | D10: 4.0838988e+08 | E10: 4.1103748e+08 | F10: 3.5497523e+08 | G10: 3.6031231e+08 | H10: 4.3310845e+08 | I10: 4.364368e+08 | J10: 4.3968587e+08 | K10: 4.8802929e+08 | L10: 4.9130687e+08 | M10: 4.9454073e+08 | N10: 4.980682e+08 | P10: 5.0149874e+08 | Q10: 5.0429854e+08 | R10: 5.0809669e+08 | S10: 5.1183239e+08 | T10: 6.1601819e+08 | U10: 6.1800901e+08 | V10: 6.2564911e+08 | W10: 6.2734547e+08 | X10: 6.5193995e+08 | Y10: 6.5672389e+08 | Z10: 6.6139289e+08 | AA10: 6.6613926e+08 | AB10: 45462000 | AC10: 6.6656346e+08 | AD10: 6.743477e+08 | AE10: 6.7925418e+08 | AF10: 6.844069e+08 | AG10: 6.896248e+08 | AH10: 6.8743978e+08
A11: Balances in NACCOS (E.g Jungu Kuu, ESS, Savings,Money Market,Coop FD, CFP) | C11: 16468881 | D11: 16468881 | E11: 16468881 | F11: 16468881 | G11: 16468881 | H11: 16468881 | I11: 16468881 | J11: 16468881 | K11: 16468881 | L11: 16468881 | M11: 16468881 | N11: 16468881 | O11: 10000 | P11: 12702354 | Q11: 12702354 | R11: 12702354 | S11: 12702354 | T11: 12702354 | U11: 12702354 | V11: 12702354 | W11: 12702354 | X11: 12702354 | Y11: 12702354 | Z11: 12702354 | AA11: 13675921 | AB11: 6085171000 | AC11: 13675921 | AD11: 13675921 | AE11: 13675921 | AF11: 13675921 | AG11: 13675921 | AH11: 13675921
A12: Equity Investments in NACCOs(Shares in- CIC, KUSCCO, COOP BANK,CAK, KERUSSU) | B12: =577580000+347409000 -> 924989000 | C12: 5.6111111e+08 | D12: 5.6112011e+08 | E12: 5.6111911e+08 | F12: 5.6111811e+08 | G12: 5.6112111e+08 | H12: 5.6112011e+08 | I12: 5.6112211e+08 | J12: 5.6112311e+08 | K12: 5.6112311e+08 | L12: 5.6112311e+08 | M12: 5.6112111e+08 | N12: 5.7999758e+08 | O12: =589890000+452762000 -> 1042652000 | AB12: =453035000+13676000+20000000+91568000+599452000 -> 1177731000 | AC12: 5.4460263e+08 | AD12: 5.4460263e+08 | AE12: 5.4460263e+08 | AF12: 5.4460263e+08 | AG12: 5.4460263e+08 | AH12: 5.4460263e+08
A13: Equity Investments in companies - shares/stocks | B13: =56062000+981051000 -> 1037113000 | O13: =44302000+1086954000 -> 1131256000 | P13: 5.7719795e+08 | Q13: 5.7719795e+08 | R13: 5.7719695e+08 | S13: 5.7719645e+08 | T13: 5.7719595e+08 | U13: 5.7719895e+08 | V13: 5.7719495e+08 | W13: 5.7719795e+08 | X13: 5.5718795e+08 | Y13: 5.5718595e+08 | Z13: 5.5718295e+08 | AA13: 5.4460363e+08
A14: Net Loan Portfolio | B14: 32798794000 | C14: =C15-C16 -> 3.3254628e+10 | D14: =D15-D16 -> 3.3387332e+10 | E14: =E15-E16 -> 3.3173428e+10 | F14: =F15-F16 -> 3.3316115e+10 | G14: =G15-G16 -> 3.3586804e+10 | H14: =H15-H16 -> 3.3621973e+10 | I14: =I15-I16 -> 3.3499803e+10 | J14: =J15-J16 -> 3.3767411e+10 | ... AH14: =AH15-AH16 -> 4.1500832e+10
A15: Gross Loan Portfolio | B15: 38804173000 | C15: 3.5584857e+10 | D15: 3.5717561e+10 | E15: 3.5639734e+10 | F15: 3.5782421e+10 | G15: 3.605311e+10 | H15: 3.6224357e+10 | I15: 3.6102187e+10 | J15: 3.6369795e+10 | K15: 3.7405147e+10 | L15: 3.822606e+10 | M15: 3.8822364e+10 | N15: 3.9378377e+10 | O15: 39378377000 | P15: 3.9737589e+10 | Q15: 3.9729955e+10 | R15: 4.0167638e+10 | S15: 4.0630238e+10 | T15: 4.1039026e+10 | U15: 4.1295258e+10 | V15: 4.1720723e+10 | W15: 4.2008374e+10 | X15: 4.2449225e+10 | Y15: 4.317657e+10 | Z15: 4.3801547e+10 | AA15: 4.4495267e+10 | AB15: 45074284000 | AC15: 4.5587899e+10 | AD15: 4.5807592e+10 | AE15: 4.5927722e+10 | AF15: 4.6366126e+10 | AG15: 4.6318317e+10 | AH15: 4.6508103e+10
A16: Allowance for Loan Loss | B16: 2330229000 | C16: 2330229000 | D16: 2330229000 | E16: 2466306500 | F16: 2466306500 | G16: 2466306500 | H16: 2602384000 | I16: 2602384000 | J16: 2602384000 | K16: 2602384000 | L16: 2602384000 | M16: 2602384000 | N16: 2602384000 | O16: 3026922000 | P16: 3.026922e+09 | Q16: 3.026922e+09 | R16: 3.026922e+09 | S16: 2.776922e+09 | T16: 2.776922e+09 | U16: 3.069077e+09 | V16: 3.069077e+09 | W16: 3.069077e+09 | X16: 3.069077e+09 | Y16: 3314707132 | Z16: 3314707132 | AA16: 3314707132 | AB16: 3757306000 | AC16: 3721489293 | AD16: 3757306340 | AE16: 4505020512 | AF16: 4505020512 | AG16: 4505020512 | AH16: 5007270624
A17: Accounts Receivables | B17: =SUM(B18:B20) -> 56052000 | C17: =SUM(C18:C20) -> 0 | D17: =SUM(D18:D20) -> 0 | E17: =SUM(E18:E20) -> 0 | F17: =SUM(F18:F20) -> 0 | G17: =SUM(G18:G20) -> 0 | H17: =SUM(H18:H20) -> 0 | I17: =SUM(I18:I20) -> 0 | ... AH17: =SUM(AH18:AH20) -> 1.1614682e+08
A18: Tax Recoverable | C18: 0 | D18: 0 | E18: 0 | F18: 0 | G18: 0 | H18: 0 | I18: 0 | J18: 0 | K18: 0 | L18: 0 | M18: 0 | N18: 0 | O18: 5768000 | P18: 0 | Q18: 0 | R18: 0 | S18: 0 | T18: 0 | U18: 0 | V18: 0 | W18: 0 | X18: 0 | Y18: 0 | Z18: 0 | AA18: 0 | AB18: 4393000 | AC18: 0 | AD18: 19393041 | AE18: 19393041 | AF18: 40561795 | AG18: 40561795 | AH18: 67662224
A19: Deferred Tax Assets | B19: 56052000 | C19: 0 | D19: 0 | E19: 0 | F19: 0 | G19: 0 | H19: 0 | I19: 0 | J19: 0 | K19: 0 | L19: 0 | M19: 0 | N19: 0 | O19: 50390000 | P19: 0 | Q19: 0 | R19: 0 | S19: 0 | T19: 0 | U19: 0 | V19: 0 | W19: 0 | X19: 0 | Y19: 0 | Z19: 0 | AA19: 0 | AB19: 48485000 | AC19: 0 | AD19: 48484600 | AE19: 48484600 | AF19: 48484600 | AG19: 48484600 | AH19: 48484600
A20: Retirement Benefit Assets | C20: 0 | D20: 0 | E20: 0 | F20: 0 | G20: 0 | H20: 0 | I20: 0 | J20: 0 | K20: 0 | L20: 0 | M20: 0 | N20: 0 | P20: 0 | Q20: 0 | R20: 0 | S20: 0 | T20: 0 | U20: 0 | V20: 0 | W20: 0 | X20: 0 | Y20: 0 | Z20: 0 | AA20: 0 | AC20: 0 | AD20: 0 | AE20: 0 | AF20: 0 | AG20: 0 | AH20: 0
A21: Property & Equipment & Other assets | B21: =SUM(B22:B26) -> 954016000 | C21: =SUM(C22:C26) -> 9.3366748e+08 | D21: =SUM(D22:D26) -> 9.4338353e+08 | E21: =SUM(E22:E26) -> 9.3408781e+08 | F21: =SUM(F22:F26) -> 9.3938837e+08 | G21: =SUM(G22:G26) -> 9.2766476e+08 | H21: =SUM(H22:H26) -> 1.070354e+09 | I21: =SUM(I22:I26) -> 1.161329e+09 | ... AH21: =SUM(AH22:AH26) -> 1.3362687e+09
A22: Investment Properties | C22: 4.8720217e+08 | D22: 4.8720217e+08 | E22: 4.8720217e+08 | F22: 4.8720217e+08 | G22: 4.8720217e+08 | H22: 4.8720217e+08 | I22: 4.8807217e+08 | J22: 4.8807217e+08 | K22: 4.8807217e+08 | L22: 4.8822317e+08 | M22: 4.8834822e+08 | N22: 4.8834822e+08 | P22: 4.8837697e+08 | Q22: 4.8837697e+08 | R22: 4.8837697e+08 | S22: 4.8838697e+08 | T22: 4.8838697e+08 | U22: 4.8838697e+08 | V22: 4.8840297e+08 | W22: 4.8840297e+08 | X22: 4.8840297e+08 | Y22: 4.8841997e+08 | Z22: 4.8841997e+08 | AA22: 4.8931317e+08 | AB22: =10000+15880000 -> 15890000 | AC22: 4.8931317e+08 | AD22: 4.8931317e+08 | AE22: 4.8931317e+08 | AF22: 4.8931317e+08 | AG22: 4.8931317e+08 | AH22: 4.9033879e+08
A23: Property & Equipment | B23: 223605000 | C23: 2.2858026e+08 | D23: 2.2821963e+08 | E23: 2.2802949e+08 | F23: 2.2662719e+08 | G23: 2.2416648e+08 | H23: 2.2248861e+08 | I23: 2.2104414e+08 | J23: 2.2222358e+08 | K23: 2.3793936e+08 | L23: 2.3598405e+08 | M23: 2.3489336e+08 | N23: 3.7633233e+08 | O23: 376216000 | P23: 3.7610459e+08 | Q23: 3.7671656e+08 | R23: 3.6536353e+08 | S23: 3.6369892e+08 | T23: 3.6204798e+08 | U23: 3.5972837e+08 | V23: 3.5442388e+08 | W23: 3.4953015e+08 | X23: 3.4453095e+08 | Y23: 3.4137894e+08 | Z23: 3.5025941e+08 | AA23: 3.4423025e+08 | AB23: 343630000 | AC23: 3.9464292e+08 | AD23: 4.0205115e+08 | AE23: 4.0877791e+08 | AF23: 4.2240079e+08 | AG23: 4.3157961e+08 | AH23: 4.4270872e+08
A24: Prepaid Lease rentals | B24: 19222000 | C24: 1.3640845e+08 | D24: 1.336838e+08 | E24: 1.3063254e+08 | F24: 1.2802787e+08 | G24: 1.2484646e+08 | H24: 1.2196381e+08 | I24: 2.055955e+08 | J24: 2.0083733e+08 | K24: 1.9621064e+08 | L24: 1.9161496e+08 | M24: 1.3697213e+08 | N24: 1.3252428e+08 | O24: 11640000 | P24: 1.2835442e+08 | Q24: 1.2428959e+08 | R24: 1.2044044e+08 | S24: 1.1661205e+08 | T24: 1.1305988e+08 | U24: 1.0893451e+08 | V24: 1.052225e+08 | W24: 1.0155578e+08 | X24: 1.5061518e+08 | Y24: 1.4612593e+08 | Z24: 1.4184234e+08 | AA24: 1.7261962e+08 | AB24: 4059000 | AC24: 1.7258131e+08 | AD24: 1.7254672e+08 | AE24: 1.6005413e+08 | AF24: 1.5600069e+08 | AG24: 1.5220924e+08 | AH24: 1.4847101e+08
A25: Intangible Assets | B25: 76620000 | C25: 74809438 | D25: 82910973 | E25: 80909735 | F25: 86574574 | G25: 84484907 | H25: 2.3314411e+08 | I25: 2.4090569e+08 | J25: 289772193 | K25: 2.8883735e+08 | L25: 2.8635804e+08 | M25: 2.8946756e+08 | N25: 3.2073196e+08 | O25: 320732000 | P25: 3.1718376e+08 | Q25: 3.1405262e+08 | R25: 3.1174248e+08 | S25: 3.0851747e+08 | T25: 3.0621514e+08 | U25: 2.806252e+08 | V25: 2.8525269e+08 | W25: 2.8130288e+08 | X25: 2.7351599e+08 | Y25: 2.7150034e+08 | Z25: 2.7418332e+08 | AA25: 2.6871134e+08 | AB25: 268711000 | AC25: 2.622254e+08 | AD25: 2.6122994e+08 | AE25: 2.693449e+08 | AF25: 2.6305092e+08 | AG25: 2.6052109e+08 | AH25: 2.544333e+08
A26: Other Assets | B26: =5629000+487202000+120869000+20869000 -> 634569000 | C26: 6667150.8 | D26: 11366948 | E26: 7313867.5 | F26: 10956560 | G26: 6964738.5 | H26: 5555338.3 | I26: 5711537.1 | J26: 5557855.6 | K26: 4581548.2 | L26: 6585446.7 | M26: 5110903.6 | N26: 4719291.9 | O26: =4719000+488348000+120884000+12721000 -> 626672000 | P26: 4646894.6 | Q26: 5568917.3 | R26: 4363769.5 | S26: 4669649.5 | T26: 5459705.2 | U26: 4189176.4 | V26: 1014676.3 | W26: 2313423.1 | X26: 848579.65 | Y26: 2351207.2 | Z26: 2724186.1 | AA26: 2038466.3 | AB26: =2038000+489313174+168561000 -> 659912174 | AC26: 4581559.6 | AD26: 3617564.1 | AE26: 3456573.4 | AF26: 1702448.5 | AG26: 722423.83 | AH26: 316883.74
A27: Total Assets | B27: =B4+B7+B8+B14+B17+B21 -> 42034351000 | C27: =C4+C7+C8+C14+C17+C21 -> 4.1464759e+10 | D27: =D4+D7+D8+D14+D17+D21 -> 4.195198e+10 | E27: =E4+E7+E8+E14+E17+E21 -> 4.1142932e+10 | F27: =F4+F7+F8+F14+F17+F21 -> 4.1513094e+10 | G27: =G4+G7+G8+G14+G17+G21 -> 4.1941166e+10 | H27: =H4+H7+H8+H14+H17+H21 -> 4.241284e+10 | I27: =I4+I7+I8+I14+I17+I21 -> 4.2780529e+10 | ... AH27: =AH4+AH7+AH8+AH14+AH17+AH21 -> 5.4295569e+10
A28: LIABILITIES
A29: Savings Deposits - Withdrawable deposits - FOSA) | B29: 3877885000 | C29: 3.105756e+09 | D29: 3.0523927e+09 | E29: 3.8041352e+09 | F29: 3.6172968e+09 | G29: 3.416059e+09 | H29: 3.4953064e+09 | I29: 2.7811918e+09 | J29: 2.9454382e+09 | K29: 3.1010843e+09 | L29: 3.0050711e+09 | M29: 2.9810064e+09 | N29: 2.81013e+09 | O29: 3436932000 | P29: 2.883488e+09 | Q29: 4.557818e+09 | R29: 3.5660796e+09 | S29: 3.2910068e+09 | T29: 3.1879902e+09 | U29: 3.1518593e+09 | V29: 2.9916339e+09 | W29: 3.0147199e+09 | X29: 2.9649438e+09 | Y29: 3.0260073e+09 | Z29: 3.0965723e+09 | AA29: 3.1547584e+09 | AB29: 3778833000 | AC29: 3.1308191e+09 | AD29: 3.1608187e+09 | AE29: 4.4278127e+09 | AF29: 4.0006137e+09 | AG29: 3.6684235e+09 | AH29: 3.6541014e+09
A30: Short Term Deposits (e.g Fixed deposits, special savings) | B30: 3598050000 | C30: 4.2135223e+09 | D30: 4.2037784e+09 | E30: 4.3254776e+09 | F30: 4.4005014e+09 | G30: 4.4106133e+09 | H30: 4.4066665e+09 | I30: 4.60056e+09 | J30: 4.612121e+09 | K30: 4.6788181e+09 | L30: 4.7245943e+09 | M30: 4.6933599e+09 | N30: 4.5643307e+09 | O30: 3937529000 | P30: 4.5858748e+09 | Q30: 4.8781823e+09 | R30: 4905778925 | S30: 5.0912962e+09 | T30: 5.0880618e+09 | U30: 5.0916107e+09 | V30: 5.0072042e+09 | W30: 5.0035417e+09 | X30: 5.1428716e+09 | Y30: 5.1270208e+09 | Z30: 5.1123796e+09 | AA30: 5.1682958e+09 | AB30: 4544221000 | AC30: 5.1422229e+09 | AD30: 5.2489514e+09 | AE30: 5.1470315e+09 | AF30: 4.9676935e+09 | AG30: 4.8902304e+09 | AH30: 4.7784439e+09
A31: Non withdrawable deposits (BOSA member deposits) | B31: 23712329000 | C31: 2.3902122e+10 | D31: 2.4068807e+10 | E31: 2.4517453e+10 | F31: 2.4747363e+10 | G31: 2.4916157e+10 | H31: 2.5023692e+10 | I31: 2.5345793e+10 | J31: 2.5563593e+10 | K31: 2.5913927e+10 | L31: 2.6220909e+10 | M31: 2.6537308e+10 | N31: 2.6838406e+10 | O31: 26838406000 | P31: 2.7097713e+10 | Q31: 2.7600391e+10 | R31: 2.8037034e+10 | S31: 2.8335793e+10 | T31: 2.8649694e+10 | U31: 2.8958043e+10 | V31: 2.9303266e+10 | W31: 2.9658593e+10 | X31: 2.9975848e+10 | Y31: 3.0386509e+10 | Z31: 3.0784895e+10 | AA31: 3.1105871e+10 | AB31: 31105871000 | AC31: 3.1291206e+10 | AD31: 3.1616031e+10 | AE31: 3.1946103e+10 | AF31: 3.2176417e+10 | AG31: 3.2419398e+10 | AH31: 3.2526154e+10
A32: Total Deposit liabilities | B32: =SUM(B29:B31) -> 31188264000 | C32: =SUM(C29:C31) -> 3.12214e+10 | D32: =SUM(D29:D31) -> 3.1324978e+10 | E32: =SUM(E29:E31) -> 3.2647066e+10 | F32: =SUM(F29:F31) -> 3.2765161e+10 | G32: =SUM(G29:G31) -> 3.2742829e+10 | H32: =SUM(H29:H31) -> 3.2925665e+10 | I32: =SUM(I29:I31) -> 3.2727545e+10 | ... AH32: =SUM(AH29:AH31) -> 4.0958699e+10
A33: Accounts Payable & Other Liabilities | B33: =SUM(B34:B39) -> 3486231000 | C33: =SUM(C34:C39) -> 3.6541015e+09 | D33: =SUM(D34:D39) -> 3.9524504e+09 | E33: =SUM(E34:E39) -> 1.929529e+09 | F33: =SUM(F34:F39) -> 2.0146064e+09 | G33: =SUM(G34:G39) -> 2.271206e+09 | H33: =SUM(H34:H39) -> 2.577429e+09 | I33: =SUM(I34:I39) -> 2.963332e+09 | ... AH33: =SUM(AH34:AH39) -> 4.3774467e+09
A34: Tax Payable | B34: 11751000 | C34: 0 | D34: 0 | E34: 0 | F34: 0 | G34: 0 | H34: 0 | I34: 0 | J34: 0 | K34: 0 | L34: 0 | M34: 0 | N34: 0 | P34: 0 | Q34: 0 | R34: 0 | S34: 0 | T34: 0 | U34: 0 | V34: 0 | W34: 0 | X34: 0 | Y34: 0 | Z34: 0 | AA34: 0 | AC34: 0 | AD34: 25079349 | AE34: 2.0322051e+08 | AF34: 26504046 | AG34: 23082367 | AH34: 30701527
A35: Dividends Payable | B35: =2440942000+8536000 -> 2449478000 | C35: 2.6005708e+09 | D35: 2.8737077e+09 | E35: 649148676 | F35: 865531568 | G35: 1081914460 | H35: 1298297352 | I35: 1514680244 | J35: 1.7663678e+09 | K35: 1.9871806e+09 | L35: 2.2079934e+09 | M35: 2.4288062e+09 | N35: 2.6917399e+09 | O35: =2691740000+9057000 -> 2700797000 | P35: 2.942969e+09 | Q35: 502458124 | R35: 753687186 | S35: 1004916248 | T35: 1256145310 | U35: 1507374372 | V35: 1758603434 | W35: 2009832496 | X35: 2261061558 | Y35: 2512290620 | Z35: 2763519682 | AA35: 3.0952293e+09 | AB35: 3167211000 | AC35: 3.3778211e+09 | AD35: 3.7323949e+09 | AE35: 8.7568561e+08 | AF35: 1.1303674e+09 | AG35: 1.4129592e+09 | AH35: 1.695551e+09
A36: Deferred Tax Liability | C36: 0 | D36: 0 | E36: 0 | F36: 0 | G36: 0 | H36: 0 | I36: 0 | J36: 0 | K36: 0 | L36: 0 | M36: 0 | N36: 0 | P36: 0 | Q36: 0 | R36: 0 | S36: 0 | T36: 0 | U36: 0 | V36: 0 | W36: 0 | X36: -50389600 | Y36: -50389600 | Z36: -50389600 | AA36: -50389600 | AC36: -50389600 | AD36: 0 | AE36: 0 | AF36: 0 | AG36: 0 | AH36: 0
A37: Retirement Benefits Liability | C37: 0 | D37: 0 | E37: 0 | F37: 0 | G37: 0 | H37: 0 | I37: 0 | J37: 0 | K37: 0 | L37: 0 | M37: 0 | N37: 0 | P37: 0 | Q37: 0 | R37: 0 | S37: 0 | T37: 0 | U37: 0 | V37: 0 | W37: 0 | X37: 6750494 | Y37: 7606066 | Z37: 8033852 | AA37: 8461638 | AC37: 8461638 | AD37: 8461638 | AE37: 8461638 | AF37: 8461638 | AG37: 8461638 | AH37: 8461638
A38: Other Liabilities | B38: =885714000+139288000 -> 1025002000 | C38: 1.0535307e+09 | D38: 1.0787428e+09 | E38: 1.2803803e+09 | F38: 1.1490748e+09 | G38: 1.1892916e+09 | H38: 1.2791316e+09 | I38: 1.4486517e+09 | J38: 1.4828734e+09 | K38: 1.5345363e+09 | L38: 1.5705568e+09 | M38: 1.5653026e+09 | N38: 1.5512879e+09 | O38: =1364987000+143395000 -> 1508382000 | P38: 1.4834194e+09 | Q38: 1.7290307e+09 | R38: 1.5910558e+09 | S38: 1.5507789e+09 | T38: 1.5695872e+09 | U38: 1.5642798e+09 | V38: 1.6317716e+09 | W38: 1.5628125e+09 | X38: 1.6431587e+09 | Y38: 1.9110587e+09 | Z38: 1.7343289e+09 | AA38: 1.6435299e+09 | AB38: =1438012000+195095000+9786000 -> 1642893000 | AC38: 1.5808198e+09 | AD38: 1.9230015e+09 | AE38: 1.8440147e+09 | AF38: 1.9294285e+09 | AG38: 2.0831379e+09 | AH38: 2.3723141e+09
A39: External Borrowings | C39: 0 | D39: 0 | E39: 0 | F39: 0 | G39: 0 | H39: 0 | I39: 0 | J39: 69031304 | K39: 69031304 | L39: 68280500 | M39: 66778891 | N39: 66778891 | O39: 66769000 | P39: 65255267 | Q39: 65245869 | R39: 64479292 | S39: 1.4167152e+08 | T39: 1.4089854e+08 | U39: 1.3958668e+08 | V39: 1.3826935e+08 | W39: 1.3694428e+08 | X39: 1.356182e+08 | Y39: 1.3428434e+08 | Z39: 2.8410048e+08 | AA39: 2.8275548e+08 | AB39: 282755000 | AC39: 2.8072148e+08 | AD39: 2.7867866e+08 | AE39: 2.7658577e+08 | AF39: 2.7448381e+08 | AG39: 2.7249693e+08 | AH39: 2.7041847e+08
A40: Total Liabilities | B40: =B32+B33 -> 34674495000 | C40: =C32+C33 -> 3.4875501e+10 | D40: =D32+D33 -> 3.5277429e+10 | E40: =E32+E33 -> 3.4576595e+10 | F40: =F32+F33 -> 3.4779767e+10 | G40: =G32+G33 -> 3.5014035e+10 | H40: =H32+H33 -> 3.5503094e+10 | I40: =I32+I33 -> 3.5690877e+10 | ... AH40: =AH32+AH33 -> 4.5336146e+10
A41: EQUITY
A42: Share Capital (Members share capital per Bylaws) | B42: 2022438000 | C42: 2.0425613e+09 | D42: 2.0640442e+09 | E42: 2.1310422e+09 | F42: 2.1586581e+09 | G42: 2.1809892e+09 | H42: 2.2049446e+09 | I42: 2.2416148e+09 | J42: 2.2718716e+09 | K42: 2.2983126e+09 | L42: 2.3269686e+09 | M42: 2.3534984e+09 | N42: 2.3827789e+09 | O42: 2382779000 | P42: 2.4100236e+09 | Q42: 2.4831996e+09 | R42: 2.5223253e+09 | S42: 2.5582254e+09 | T42: 2.5956911e+09 | U42: 2.6423172e+09 | V42: 2.6976084e+09 | W42: 2.75299e+09 | X42: 2.8176801e+09 | Y42: 2.8777359e+09 | Z42: 2.9332646e+09 | AA42: 2.9870009e+09 | AB42: 2987001000 | AC42: 3.0254679e+09 | AD42: 3.0548295e+09 | AE42: 3.1234925e+09 | AF42: 3.1720102e+09 | AG42: 3.223179e+09 | AH42: 3.2633674e+09
A43: Capital Grants | C43: 0 | D43: 0 | E43: 0 | F43: 0 | G43: 0 | H43: 0 | I43: 0 | J43: 0 | K43: 0 | L43: 0 | M43: 0 | N43: 0 | P43: 0 | Q43: 0 | R43: 0 | S43: 0 | T43: 0 | U43: 0 | V43: 0 | W43: 0 | X43: 0 | Y43: 0 | Z43: 0 | AA43: 0 | AC43: 0 | AD43: 0 | AE43: 0 | AF43: 0 | AG43: 0 | AH43: 0
A45: Retained Earnings | B45: =B47+B46 -> 2883949000 | C45: =C47+C46 -> 3.3387782e+09 | D45: =D47+D46 -> 3.4110617e+09 | E45: =E47+E46 -> 3.2358499e+09 | F45: =F47+F46 -> 3.3752235e+09 | G45: =G47+G46 -> 3.5466958e+09 | H45: =H47+H46 -> 3.5053563e+09 | I45: =I47+I46 -> 3.6485919e+09 | ... AH45: =AH47+AH46 -> 3.9975967e+09
A46: Prior Years' Retained Earnings | B46: 2273805000 | C46: 3.2059351e+09 | D46: 3.1567918e+09 | E46: 2.875871e+09 | F46: 2.875871e+09 | G46: 2.875871e+09 | H46: 2.875871e+09 | I46: 2.875871e+09 | J46: 2.875871e+09 | K46: 2.875871e+09 | L46: 2.875871e+09 | M46: 2.875871e+09 | N46: 2978292307 | O46: 2883949000 | P46: 4.1314427e+09 | Q46: 3.8110966e+09 | R46: 3.8110966e+09 | S46: 3.8110966e+09 | T46: 3.8110966e+09 | U46: 3.8110966e+09 | V46: 3.8110966e+09 | W46: 3.8110966e+09 | X46: 3.8110966e+09 | Y46: 3.8110966e+09 | Z46: 3.8110966e+09 | AA46: 3.8809696e+09 | AB46: 3811104000 | AC46: 5.006887e+09 | AD46: 4.1806998e+09 | AE46: 4.1806998e+09 | AF46: 4.1806998e+09 | AG46: 4.1806998e+09 | AH46: 4.1806998e+09
A47: Current Year's Surplus | B47: =2883949000-2273805000 -> 610144000 | C47: 1.3284303e+08 | D47: 2.5426998e+08 | E47: 3.5997898e+08 | F47: 4.993525e+08 | G47: 6.7082483e+08 | H47: 6.2948536e+08 | I47: 7.7272098e+08 | J47: 8.9368712e+08 | K47: 1.1221224e+09 | L47: 1.3292142e+09 | M47: 1.5092121e+09 | N47: 1.6680896e+09 | O47: =3826798000-2883949000 -> 942849000 | P47: 1.7563484e+08 | Q47: 3.3464514e+08 | R47: 4.6637904e+08 | S47: 8.5556945e+08 | T47: 1.0444669e+09 | U47: 9.0960592e+08 | V47: 1.0659395e+09 | W47: 1.2208237e+09 | X47: 1.3517574e+09 | Y47: 1.3485942e+09 | Z47: 1.5260821e+09 | AA47: 1.6037442e+09 | AB47: =4180700000-AB46 -> 369596000 | AC47: 2.7440213e+08 | AD47: 4.0638248e+08 | AE47: -2.5981917e+08 | AF47: -153747070 | AG47: 66265594 | AH47: -183103016
A49: Other Equity Accounts | B49: =SUM(B50:B54) -> 1480366000 | C49: =SUM(C50:C54) -> 1.2079182e+09 | D49: =SUM(D50:D54) -> 1.1994453e+09 | E49: =SUM(E50:E54) -> 1.1994453e+09 | F49: =SUM(F50:F54) -> 1.1994453e+09 | G49: =SUM(G50:G54) -> 1.1994453e+09 | H49: =SUM(H50:H54) -> 1.1994453e+09 | I49: =SUM(I50:I54) -> 1.1994453e+09 | ... AH49: =SUM(AH50:AH54) -> 1.6984598e+09
A50: Statutory Reserve | B50: 1188896000 | C50: 1.184895e+09 | D50: 1.1764222e+09 | E50: 1.1764222e+09 | F50: 1.1764222e+09 | G50: 1.1764222e+09 | H50: 1.1764222e+09 | I50: 1.1764222e+09 | J50: 1.1764222e+09 | K50: 1.1764222e+09 | L50: 1.1764222e+09 | M50: 1.1764222e+09 | N50: 1.1764222e+09 | O50: 1473792000 | P50: 1.4608242e+09 | Q50: 1.4613245e+09 | R50: 1.4613245e+09 | S50: 1.4613245e+09 | T50: 1.4613245e+09 | U50: 1.4613245e+09 | V50: 1.4613245e+09 | W50: 1.4613245e+09 | X50: 1.4613245e+09 | Y50: 1.4613245e+09 | Z50: 1.4613245e+09 | AA50: 1.4613171e+09 | AB50: 1670253000 | AC50: 1.6577786e+09 | AD50: 1.6577788e+09 | AE50: 1.6577788e+09 | AF50: 1.6577788e+09 | AG50: 1.6577788e+09 | AH50: 1.6577788e+09
A51: Other Reserves (provide notes on these reserves) | C51: 12474413 | D51: 12474413 | E51: 12474413 | F51: 12474413 | G51: 12474413 | H51: 12474413 | I51: 12474413 | J51: 12474413 | K51: 12474413 | L51: 12474413 | M51: 12474413 | N51: 12474413 | P51: 12474413 | Q51: 12474413 | R51: 12474413 | S51: 12474413 | T51: 12474413 | U51: 12474413 | V51: 12474413 | W51: 12474413 | X51: 12474413 | Y51: 12474413 | Z51: 12474413 | AA51: 12474413 | AC51: 12474413 | AD51: 12474413 | AE51: 12474413 | AF51: 12474413 | AG51: 12474413 | AH51: 12474413
A52: Revaluation Reserves (Not part of core capital) | B52: 10549000 | C52: 10548735 | D52: 10548735 | E52: 10548735 | F52: 10548735 | G52: 10548735 | H52: 10548735 | I52: 10548735 | J52: 10548735 | K52: 10548735 | L52: 10548735 | M52: 10548735 | N52: 32680614 | O52: -3317000 | P52: -3317825.7 | Q52: -3317826.2 | R52: -3317826.2 | S52: -3317826.2 | T52: -3317826.2 | U52: -3317826.2 | V52: -3317826.2 | W52: -3317826.2 | X52: -3317826.2 | Y52: -3317826.2 | Z52: -3317826.2 | AA52: 7203680.7 | AB52: 28207000 | AC52: 7203680.7 | AD52: 28206616 | AE52: 28206616 | AF52: 28206616 | AG52: 28206616 | AH52: 28206616
A53: Proposed Dividends | B53: 280921000 | C53: 0 | D53: 0 | E53: 0 | F53: 0 | G53: 0 | H53: 0 | I53: 0 | J53: 0 | K53: 0 | L53: 0 | M53: 0 | N53: 0 | O53: 280921000 | P53: 0 | Q53: 0 | R53: 0 | S53: 0 | T53: 0 | U53: 0 | V53: 0 | W53: 0 | X53: 0 | Y53: 0 | Z53: 0 | AA53: 0 | AB53: 395734000 | AC53: 0 | AD53: 395734025 | AE53: 0 | AF53: 0 | AG53: 0 | AH53: 0
A54: Adjustment to Equity | C54: 0 | D54: 0 | E54: 0 | F54: 0 | G54: 0 | H54: 0 | I54: 0 | J54: 0 | K54: 0 | L54: 0 | M54: 0 | N54: 0 | P54: 0 | Q54: 0 | R54: 0 | S54: 0 | T54: 0 | U54: 0 | V54: 0 | W54: 0 | X54: 0 | Y54: 0 | Z54: 0 | AA54: 0 | AC54: 0 | AD54: 0 | AE54: 0 | AF54: 0 | AG54: 0 | AH54: 0
A55: Total Equity | B55: =B42+B43+B45+B49 -> 6386753000 | C55: =C42+C43+C45+C49 -> 6.5892576e+09 | D55: =D42+D43+D45+D49 -> 6.6745513e+09 | E55: =E42+E43+E45+E49 -> 6.5663374e+09 | F55: =F42+F43+F45+F49 -> 6.7333269e+09 | G55: =G42+G43+G45+G49 -> 6.9271303e+09 | H55: =H42+H43+H45+H49 -> 6.9097462e+09 | I55: =I42+I43+I45+I49 -> 7.0896521e+09 | ... AH55: =AH42+AH43+AH45+AH49 -> 8.9594239e+09
A56: Total Liabilities and Equity | B56: =B40+B55 -> 41061248000 | C56: =C40+C55 -> 4.1464759e+10 | D56: =D40+D55 -> 4.195198e+10 | E56: =E40+E55 -> 4.1142932e+10 | F56: =F40+F55 -> 4.1513094e+10 | G56: =G40+G55 -> 4.1941166e+10 | H56: =H40+H55 -> 4.241284e+10 | I56: =I40+I55 -> 4.2780529e+10 | ... AH56: =AH40+AH55 -> 5.4295569e+10
B57: =B27-B56 -> 973103000 | C57: =C27-C56 -> 0 | D57: =D27-D56 -> 0 | E57: =E27-E56 -> 0 | F57: =F27-F56 -> 0 | G57: =G27-G56 -> 0 | H57: =H27-H56 -> 0 | I57: =I27-I56 -> 0 | ... AH57: =AH27-AH56 -> 0

Sheet SCI
A1: STIMA SACCO SOCIETY LTD
A2: STATEMENT OF COMPREHENSIVE INCOME | B2: AUDITED 2020 | C2: 44197 | D2: 44228 | E2: 44256 | F2: 44287 | G2: 44317 | H2: 44348 | I2: 44378 | J2: 44409 | K2: 44440 | L2: 44470 | M2: 44501 | N2: 44531 | O2: Audited 2021 | P2: 44562 | Q2: 44593 | R2: 44621 | S2: 44652 | T2: 44682 | U2: 44713 | V2: 44743 | W2: 44774 | X2: 44805 | Y2: 44835 | Z2: 44866 | AA2: 44896 | AB2: Audited-22 | AC2: 44949 | AD2: 44980 | AE2: 45008 | AF2: 45039 | AG2: 45069 | AH2: 45100
A3: Financial Income | B3: =B4+B7 -> 5873701000 | C3: =C4+C7 -> 0 | D3: =D4+D7 -> 0 | E3: =E4+E7 -> 0 | F3: =F4+F7 -> 0 | G3: =G4+G7 -> 0 | H3: =H4+H7 -> 0 | I3: =I4+I7 -> 0 | ... AH3: =AH4+AH7 -> 4.0055387e+09
A4: Financial Income from Loans Portfolio | B4: =SUM(B5:B6) -> 5027362000 | C4: =SUM(C5:C6) -> 0 | D4: =SUM(D5:D6) -> 0 | E4: =SUM(E5:E6) -> 0 | F4: =SUM(F5:F6) -> 0 | G4: =SUM(G5:G6) -> 0 | H4: =SUM(H5:H6) -> 0 | I4: =SUM(I5:I6) -> 0 | ... AH4: =SUM(AH5:AH6) -> 3.3057117e+09
A5: Interest on Loan Portfolio | B5: 5027362000 | O5: 5820317000 | P5: 5.2386397e+08 | Q5: 9.9781509e+08 | R5: 1.5193106e+09 | S5: 2.0339776e+09 | T5: 2.5608299e+09 | U5: 3.0726492e+09 | V5: 3.6188266e+09 | W5: 4.159014e+09 | X5: 4.6910735e+09 | Y5: 5.2585654e+09 | Z5: 5.8170355e+09 | AA5: 6.3942758e+09 | AB5: =1015082000+5190873000+70109000 -> 6276064000 | AC5: 6.2599612e+08 | AD5: 1.1344527e+09 | AE5: 1.6367526e+09 | AF5: 2.1535629e+09 | AG5: 2.7203291e+09 | AH5: 3.2907605e+09
A6: Fees & Commission on Loan Portfolio | P6: 5038905.8 | Q6: 10052080 | R6: 15376000 | S6: 20465972 | T6: 25731220 | U6: 31046185 | V6: 36315302 | W6: 41586772 | X6: 46971014 | Y6: 52552876 | Z6: 58373729 | AA6: 64087118 | AB6: =72951000 -> 72951000 | AC6: 6905666.1 | AD6: 8087216.5 | AE6: 9030324.3 | AF6: 12689648 | AG6: 14236196 | AH6: 14951163
A7: Financial Income from Investments in: | B7: =SUM(B8:B11) -> 846339000 | C7: =SUM(C8:C11) -> 0 | D7: =SUM(D8:D11) -> 0 | E7: =SUM(E8:E11) -> 0 | F7: =SUM(F8:F11) -> 0 | G7: =SUM(G8:G11) -> 0 | H7: =SUM(H8:H11) -> 0 | I7: =SUM(I8:I11) -> 0 | ... AH7: =SUM(AH8:AH11) -> 6.9982701e+08
A8: Government Securities | B8: 0 | C8: 0 | D8: 0 | E8: 0 | F8: 0 | G8: 0 | H8: 0 | I8: 0 | J8: 0 | K8: 0 | L8: 0 | M8: 0 | N8: 0 | O8: 0 | P8: 0 | Q8: 6949973 | R8: 10177455 | S8: 13352881 | T8: 51414113 | U8: 61747445 | V8: 72425221 | W8: 83102997 | X8: 93436329 | Y8: 140298795 | Z8: 161065552 | AA8: 181305254 | AC8: 18531529 | AD8: 40604965 | AE8: 61939777 | AF8: 82810313 | AG8: 104265290 | AH8: 124910592
A9: Deposit with Banks and Other Financial Inst. | B9: 0 | C9: 0 | D9: 0 | E9: 0 | F9: 0 | G9: 0 | H9: 0 | I9: 0 | J9: 0 | K9: 0 | L9: 0 | M9: 0 | N9: 0 | O9: 0 | P9: 37718265 | Q9: 78406972 | R9: 1.1181517e+08 | S9: 1.4865218e+08 | T9: 1.8204838e+08 | U9: 2.2041046e+08 | V9: 2.6081322e+08 | W9: 2.9997307e+08 | X9: 3.4098024e+08 | Y9: 3.8522801e+08 | Z9: 4.308128e+08 | AA9: 4.9471455e+08 | AB9: 495662000 | AC9: 54144050 | AD9: 99200969 | AE9: 1.5194216e+08 | AF9: 1.9705837e+08 | AG9: 2.5047821e+08 | AH9: 3.1836527e+08
A10: Other Investments - dividend & Interest incomes from investments | P10: 0 | Q10: 0 | R10: 0 | S10: 0 | T10: 0 | U10: 55322216 | V10: 55322216 | W10: 55322216 | X10: 55322216 | Y10: 55322216 | Z10: 56323719 | AA10: 56323719 | AB10: 181305000 | AC10: 0 | AD10: 0 | AE10: 0 | AF10: 0 | AG10: 0 | AH10: 86070576
A11: Other Operating Income- Salary processing fees, transaction fees, membership fees | B11: 846339000 | O11: 1015945000 | P11: 26135053 | Q11: 64706312 | R11: 92215187 | S11: 1.1965465e+08 | T11: 1.477685e+08 | U11: 1.7169212e+08 | V11: 1.9988474e+08 | W11: 2.2376825e+08 | X11: 2.5238255e+08 | Y11: 2.8043257e+08 | Z11: 3.0928167e+08 | AA11: 3.3883366e+08 | AB11: =110932000+265503000 -> 376435000 | AC11: 24571726 | AD11: 51448437 | AE11: 88091337 | AF11: 1.1216365e+08 | AG11: 1.4174815e+08 | AH11: 1.7048057e+08
A12: Financial Expense | B12: =B13+B14+B15+B16+B17+B18 -> 3019439000 | C12: =C13+C14+C15+C16+C17+C18 -> 0 | D12: =D13+D14+D15+D16+D17+D18 -> 0 | E12: =E13+E14+E15+E16+E17+E18 -> 0 | F12: =F13+F14+F15+F16+F17+F18 -> 0 | G12: =G13+G14+G15+G16+G17+G18 -> 0 | H12: =H13+H14+H15+H16+H17+H18 -> 0 | I12: =I13+I14+I15+I16+I17+I18 -> 0 | ... AH12: =AH13+AH14+AH15+AH16+AH17+AH18 -> 1.9023633e+09
A13: Interest Expense on Deposits | B13: 2826735000 | O13: 3098705000 | P13: 34492975 | Q13: 63405947 | R13: 1.0072759e+08 | S13: 1.3725472e+08 | T13: 1.7263119e+08 | U13: 2.0905404e+08 | V13: 2.4856692e+08 | W13: 2.8684839e+08 | X13: 3.3494726e+08 | Y13: 3.6734359e+08 | Z13: 4.1109974e+08 | AA13: 4.6831828e+08 | AB13: =3097346000+405863000+41353000+21103000 -> 3565665000 | AC13: 28305191 | AD13: 70173627 | AE13: 1.202423e+08 | AF13: 1.6332059e+08 | AG13: 1.4853513e+08 | AH13: 1.8222013e+08
A14: Cost of External Borrowings | O14: 853000 | P14: 553244.82 | Q14: 553244.82 | R14: 825102.61 | S14: 1093766.3 | T14: 1359222.7 | U14: 1946299.9 | V14: 2527911 | W14: 3101782.7 | X14: 3674643.8 | Y14: 4239719.7 | Z14: 4799237.7 | AA14: 5353174.9 | AB14: 5353000 | AC14: 1253725.6 | AD14: 2498634.5 | AE14: 3693462.3 | AF14: 4851164.5 | AG14: 6105466.9 | AH14: 7314724
A15: Dividend Expenses (on member shares) | P15: 251229062 | Q15: 5.0248257e+08 | R15: 753687186 | S15: 1.0050733e+09 | T15: 1.2563049e+09 | U15: 1.507534e+09 | V15: 1.758763e+09 | W15: 2.0099921e+09 | X15: 2.2612212e+09 | Y15: 2.5124611e+09 | Z15: 2763519682 | AA15: 3.0952293e+09 | AC15: 2.8260439e+08 | AD15: 5.6518358e+08 | AE15: 8.4697543e+08 | AF15: 1.1303672e+09 | AG15: 1.412959e+09 | AH15: 1.6955508e+09
A16: Other Financial Expense | B16: 175569000 | O16: -134546000 | P16: 1352909.3 | Q16: 2814814.1 | R16: 4167512.9 | S16: 5533496.5 | T16: 6781649.5 | U16: 8068673.3 | V16: 9344417.4 | W16: 10513489 | X16: 16848069 | Y16: 18597253 | Z16: 20244165 | AA16: 22647083 | AC16: 883 | AD16: 1161 | AE16: 5743927.5 | AF16: 7601049.9 | AG16: 9395924.3 | AH16: 11171627
A17: Fees & Commission Expense | P17: 924426.04 | Q17: 1756176.4 | R17: 2750175.7 | S17: 3437359.5 | T17: 4135101 | U17: 4803842.3 | V17: 2301467 | W17: 6010118.4 | X17: 6557649.5 | Y17: 7033418.9 | Z17: 8333205.1 | AA17: 8887088.1 | AC17: 141619.07 | AD17: 847756.39 | AE17: 2186560.7 | AF17: 2685509.7 | AG17: 3879167.8 | AH17: 6106079
A18: Other Expense | B18: 17135000 | O18: 19673000 | P18: 0 | Q18: 0 | R18: 0 | S18: 0 | T18: 0 | U18: 0 | V18: 0 | W18: 0 | X18: 0 | Y18: 0 | Z18: 0 | AA18: 0 | AB18: 22620000 | AC18: 0 | AD18: 0 | AE18: 0 | AF18: 0 | AG18: 0 | AH18: 0
A19: Net Financial Income/(Loss) | B19: =B3-B12 -> 2854262000 | C19: =C3-C12 -> 0 | D19: =D3-D12 -> 0 | E19: =E3-E12 -> 0 | F19: =F3-F12 -> 0 | G19: =G3-G12 -> 0 | H19: =H3-H12 -> 0 | I19: =I3-I12 -> 0 | ... AH19: =AH3-AH12 -> 2.1031754e+09
A20: Allowance for Loan Loss | B20: =B21-B22 -> 544310000 | C20: =C21-C22 -> 12 | D20: =D21-D22 -> 11 | E20: =E21-E22 -> 10 | F20: =F21-F22 -> 9 | G20: =G21-G22 -> 8 | H20: =H21-H22 -> 7 | I20: =I21-I22 -> 6 | ... AH20: =AH21-AH22 -> 1249964284
A21: Provision for Loan Losses | B21: 544310000 | O21: 696693000 | P21: 0 | Q21: 0 | R21: 0 | S21: -250000000 | T21: -250000000 | U21: 42155000 | V21: 42155000 | W21: 42155000 | X21: 42155000 | Y21: 2.8778518e+08 | Z21: 2.8778518e+08 | AA21: 2.8778518e+08 | AB21: =797997000+23288000 -> 821285000 | AC21: 0 | AD21: 0 | AE21: 747714172 | AF21: 747714172 | AG21: 747714172 | AH21: 1249964284
A22: Value of Loans Recovered | C22: -12 | D22: -11 | E22: -10 | F22: -9 | G22: -8 | H22: -7 | I22: -6 | J22: -5 | K22: -4 | L22: -3 | M22: -2 | N22: -1 | O22: 0 | P22: 0 | Q22: 0 | R22: 0 | S22: 0 | T22: 0 | U22: 0 | V22: 0 | W22: 0 | X22: 0 | Y22: 0 | Z22: 0 | AA22: 0 | AC22: 0 | AD22: 0 | AE22: 0 | AF22: 0 | AG22: 0 | AH22: 0
A23: Operating Expenses | B23: =SUM(B24:B28) -> 1213299000 | C23: =SUM(C24:C28) -> 0 | D23: =SUM(D24:D28) -> 0 | E23: =SUM(E24:E28) -> 0 | F23: =SUM(F24:F28) -> 0 | G23: =SUM(G24:G28) -> 0 | H23: =SUM(H24:H28) -> 0 | I23: =SUM(I24:I28) -> 0 | ... AH23: =SUM(AH24:AH28) -> 1.015247e+09
A24: Personnel Expenses | B24: 612333000 | O24: 751115000 | P24: 54074663 | Q24: 1.0939328e+08 | R24: 1.789708e+08 | S24: 2.6074033e+08 | T24: 3.2977406e+08 | U24: 3.977846e+08 | V24: 4.6227934e+08 | W24: 5.363785e+08 | X24: 6.1714689e+08 | Y24: 6.9350278e+08 | Z24: 7.5902102e+08 | AA24: 8.4188322e+08 | AB24: =591368000+56600000+184911000 -> 832879000 | AC24: 60232701 | AD24: 1.280897e+08 | AE24: 1.9404309e+08 | AF24: 2.6471817e+08 | AG24: 3.3628322e+08 | AH24: 4.3793401e+08
A25: Governance Expenses | P25: 4316207.5 | Q25: 10028541 | R25: 14997709 | S25: 21399508 | T25: 31899598 | U25: 58095512 | V25: 85922723 | W25: 91896503 | X25: 1.0192832e+08 | Y25: 1.0902043e+08 | Z25: 1.2481795e+08 | AA25: 1.3144802e+08 | AB25: =6858000+6753000+30828000 -> 44439000 | AC25: 3715324.5 | AD25: 6988165 | AE25: 10944929 | AF25: 14932512 | AG25: 20779726 | AH25: 25069293
A26: Marketing Expenses | P26: 2557890.9 | Q26: 5939263.5 | R26: 18513215 | S26: 25470363 | T26: 33960667 | U26: 48377057 | V26: 73496539 | W26: 83746428 | X26: 91257476 | Y26: 99836476 | Z26: 1.1014826e+08 | AA26: 1.1574713e+08 | AB26: 117204000 | AC26: 5306997 | AD26: 9284771 | AE26: 18289015 | AF26: 28937363 | AG26: 39709090 | AH26: 50267690
A27: Depreciation and Amortization Charges | P27: 11023048 | Q27: 21247563 | R27: 41830010 | S27: 55451956 | T27: 69369269 | U27: 1.0634624e+08 | V27: 1.2540822e+08 | W27: 1.4313904e+08 | X27: 1.6750208e+08 | Y27: 1.8662384e+08 | Z27: 2.070259e+08 | AA27: 2.2746651e+08 | AB27: =81057000+48820000+7581000+89832000 -> 227290000 | AC27: 13199613 | AD27: 25601281 | AE27: 52914867 | AF27: 71624588 | AG27: 91366461 | AH27: 1.1089869e+08
A28: Administrative Expenses | B28: 600966000 | O28: 865015000 | P28: 49690855 | Q28: 88342800 | R28: 1.4287846e+08 | S28: 1.8203832e+08 | T28: 2.2698597e+08 | U28: 2.7422517e+08 | V28: 3.1451398e+08 | W28: 3.6897138e+08 | X28: 4.2226554e+08 | Y28: 4.7010772e+08 | Z28: 5.3843316e+08 | AA28: 5.9561766e+08 | AB28: =27884000+7052000+249512000+6322000+42866000+82816000+136825000+24300000+96571000 -> 674148000 | AC28: 52992191 | AD28: 1.1009161e+08 | AE28: 1.9615237e+08 | AF28: 2.6140742e+08 | AG28: 3.2798108e+08 | AH28: 3.9107732e+08
A29: Net Operating Income | B29: =B19-B20-B23 -> 1096653000 | C29: =C19-C20-C23 -> -12 | D29: =D19-D20-D23 -> -11 | E29: =E19-E20-E23 -> -10 | F29: =F19-F20-F23 -> -9 | G29: =G19-G20-G23 -> -8 | H29: =H19-H20-H23 -> -7 | I29: =I19-I20-I23 -> -6 | ... AH29: =AH19-AH20-AH23 -> -1.6203592e+08
A30: Net Non- Operating Income/ (Expense) | B30: =B31-B32 -> 0 | C30: =C31-C32 -> 0 | D30: =D31-D32 -> 0 | E30: =E31-E32 -> 0 | F30: =F31-F32 -> 0 | G30: =G31-G32 -> 0 | H30: =H31-H32 -> 0 | I30: =I31-I32 -> 0 | ... O30: =O31-O32 -> 0 | AB30: =AB31-AB32 -> 7365000 | AC30: =AC31-AC32 -> 0 | AD30: =AD31-AD32 -> 0 | AE30: =AE31-AE32 -> 0 | AF30: =AF31-AF32 -> 0 | AG30: =AG31-AG32 -> 0 | AH30: =AH31-AH32 -> 0
A31: Non- Operating Income | P31: 0 | Q31: 0 | R31: 0 | S31: 0 | T31: 0 | U31: 0 | V31: 0 | W31: 0 | X31: 0 | Y31: 0 | Z31: 0 | AA31: 0 | AB31: 10521000 | AC31: 0 | AD31: 0 | AE31: 0 | AF31: 0 | AG31: 0 | AH31: 0
A32: Non- Operating Expense | P32: 0 | Q32: 0 | R32: 0 | S32: 0 | T32: 0 | U32: 0 | V32: 0 | W32: 0 | X32: 0 | Y32: 0 | Z32: 0 | AA32: 0 | AB32: 3156000 | AC32: 0 | AD32: 0 | AE32: 0 | AF32: 0 | AG32: 0 | AH32: 0
A33: Net Income (Before Taxes and Donations) | B33: =B29+B30 -> 1096653000 | C33: =C29+C30 -> -12 | D33: =D29+D30 -> -11 | E33: =E29+E30 -> -10 | F33: =F29+F30 -> -9 | G33: =G29+G30 -> -8 | H33: =H29+H30 -> -7 | I33: =I29+I30 -> -6 | ... AH33: =AH29+AH30 -> -1.6203592e+08
A34: Taxes (Incomes taxes & Other payable to KRA) | B34: 75531000 | O34: 114242000 | P34: 6906071.5 | Q34: 17321095 | R34: 23167563 | S34: 33040704 | T34: 40123496 | U34: 44871297 | V34: 52368257 | W34: 59190847 | X34: 62904325 | Y34: 67254223 | Z34: 71583349 | AA34: 1.2541328e+08 | AB34: 109229000 | AC34: 7994317.4 | AD34: 8651545 | AE34: 8675235.9 | AF34: 13872208 | AG34: 20082910 | AH34: 21067096
A35: Net Income (After Taxes before Donations) | B35: =B33-B34 -> 1021122000 | C35: =C33-C34 -> -12 | D35: =D33-D34 -> -11 | E35: =E33-E34 -> -10 | F35: =F33-F34 -> -9 | G35: =G33-G34 -> -8 | H35: =H33-H34 -> -7 | I35: =I33-I34 -> -6 | ... AH35: =AH33-AH34 -> -1.8310302e+08
A36: Donations | P36: 0 | Q36: 0 | R36: 0 | S36: 0 | T36: 0 | U36: 0 | V36: 0 | W36: 0 | X36: 0 | Y36: 0 | Z36: 0 | AA36: 0 | AC36: 0 | AD36: 0 | AE36: 0 | AF36: 0 | AG36: 0 | AH36: 0
A37: Net Income/(After Taxes and Donations) | B37: =B35-B36 -> 1021122000 | C37: =C35-C36 -> -12 | D37: =D35-D36 -> -11 | E37: =E35-E36 -> -10 | F37: =F35-F36 -> -9 | G37: =G35-G36 -> -8 | H37: =H35-H36 -> -7 | I37: =I35-I36 -> -6 | ... AH37: =AH35-AH36 -> -1.8310302e+08

Sheet Sheet1
B2: Year | C2: AUDITED 2015 | D2: AUDITED 2016 | E2: AUDITED 2017 | F2: AUDITED 2018 | G2: 43466 | H2: 43497 | I2: 43525 | J2: 43556 | K2: 43586 | L2: 43617
A3: 2 | B3: Total Assets | C3: 4.6351889e+08 | D3: 4.5637093e+08 | E3: 4.3683362e+08 | F3: 590186392 | G3: 6.0231394e+08 | H3: 6.2625108e+08 | I3: 5.9828697e+08 | J3: 5.8907278e+08 | K3: 6.1710155e+08 | L3: 6.0417723e+08
A4: 3 | B4: Total Deposits | C4: 3.6391029e+08 | D4: 3.5281156e+08 | E4: 3.4681983e+08 | F4: 433315333 | G4: 4.3839535e+08 | H4: 4.542002e+08 | I4: 4.7118357e+08 | J4: 4.6306008e+08 | K4: 4.8617864e+08 | L4: 4.6622117e+08
A5: 3.1 | B5: Deposits-Members(BOSA) | C5: 2.4228165e+08 | D5: 2.4464437e+08 | E5: 2.4323434e+08 | F5: 365696388 | G5: 3.7313088e+08 | H5: 3.8056337e+08 | I5: 3.899621e+08 | J5: 3.9463998e+08 | K5: 3.9710517e+08 | L5: 4.0401425e+08
A6: 3.2 | B6: Deposits-Customers(FOSA) | C6: 4074376.9 | D6: 4984401.3 | E6: 5076228.9 | F6: 67618945 | G6: 14363008 | H6: 15611949 | I6: 13612359 | J6: 14419909 | K6: 14679037 | L6: 13096149
A7: 4 | B7: External Borrowing | C7: 782851.88 | D7: 782851.88 | E7: 782851.88 | F7: 0 | G7: 0 | H7: 0 | I7: 0 | J7: 0 | K7: 0 | L7: 0
A8: 4.1 | B8: Short term Liabilities | C8: 4642444.9 | D8: 27506534 | E8: 4912342.2 | F8: 58156529 | G8: 3901907.3 | H8: 4415903.4 | I8: -44130681 | J8: 10574287 | K8: 12876255 | L8: 10617410
A9: 5.1 | B9: Core Capital | C9: 94944699 | D9: 75269883 | E9: 78350880 | F9: 88729697 | G9: 1.5578813e+08 | H9: 1.6340642e+08 | I9: 1.6700553e+08 | J9: 1.1120986e+08 | K9: 1.138181e+08 | L9: 1.231101e+08
A10: 5.2 | B10: Institutional Capital | C10: 85006164 | D10: 65331348 | E10: 67704199 | F10: 65523502 | G10: 1.3199681e+08 | H10: 1.3957898e+08 | I10: 1.42917e+08 | J10: 87051631 | K10: 89639871 | L10: 98730332
A11: 5.3 | B11: Total Capital | C11: 94944699 | D11: 75269883 | E11: 78350880 | F11: 92958252 | G11: 1.6001668e+08 | H11: 1.6763498e+08 | I11: 1.7123408e+08 | J11: 1.1543841e+08 | K11: 1.1804665e+08 | L11: 1.2733866e+08
A12: 7 | B12: Net Loans & advances | C12: 2.9963107e+08 | D12: 3.0964314e+08 | E12: 3.1063977e+08 | F12: 467465209 | G12: 4.7291977e+08 | H12: 4.7868736e+08 | I12: 4.7578771e+08 | J12: 4.7958254e+08 | K12: 4.8126667e+08 | L12: 4.8527697e+08
A13: 7.1 | B13: Gross Loans & advances | C13: 3.0960349e+08 | D13: 3.1961557e+08 | E13: 3.2061219e+08 | F13: 478678153 | G13: 4.8413271e+08 | H13: 4.899003e+08 | I13: 4.8760561e+08 | J13: 4.9160208e+08 | K13: 4.9348786e+08 | L13: 4.9769982e+08
A14: 7.3 | B14: Allowance for loan losses | C14: 9972423.1 | D14: 9972423.1 | E14: 9972423.1 | F14: 11212944 | G14: 11212944 | H14: 11212944 | I14: 11817894 | J14: 12019544 | K14: 12221194 | L14: 12422844
... A19: 10 | B19: Total Expenses (FinCosts + OpEx) | C19: 22339455 | D19: 4546921.1 | E19: 5916993.1 | F19: 68345005 | G19: 18479434 | H19: 19450021 | I19: 21786998 | J19: 6653981.1 | K19: 12263359 | L19: 13807775
B21: CORE CAPITAL | C21: 94.944699 | D21: 75.269883 | E21: 78.35088 | F21: 88.729697 | G21: 155.78813 | H21: 163.40642 | I21: 167.00553 | J21: 111.20986 | K21: 113.8181 | L21: 123.1101
B22: CCA | C22: 0.20483458 | D22: 0.16493137 | E22: 0.17936092 | F22: 0.15034182 | G22: 0.25864938 | H22: 0.26092797 | I22: 0.2791395 | J22: 0.18878798 | K22: 0.18443982 | L22: 0.20376488
B23: ICA | C23: 0.18339309 | D23: 0.14315405 | E23: 0.15498853 | F23: 0.11102171 | G23: 0.21914952 | H23: 0.22288022 | I23: 0.23887701 | J23: 0.14777738 | K23: 0.14525951 | L23: 0.16341286
B24: CCD | C24: 0.26090139 | D24: 0.21334302 | E24: 0.22591234 | F24: 0.20476935 | G24: 0.3553599 | H24: 0.35976739 | I24: 0.35443835 | J24: 0.24016291 | K24: 0.23410757 | L24: 0.26405944
B25: Asset Quality
B26: NPL
B27: Earnings
B28: ROA | C28: 0.10366402 | D28: 0.0049791285 | E28: 0.0086990958 | F28: 0.021403287 | G28: 0.086521768 | H28: 0.092418745 | I28: 0.095308004 | J28: 0.025179366 | K28: 0.027427623 | L28: 0.036644694
B29: CIR | C29: 0.25741416 | D29: 0.47475461 | E29: 0.47309013 | F29: 0.59346691 | G29: 0.29062189 | H29: 0.28378981 | I29: 0.30491294 | J29: 0.3518848 | K29: 0.42614589 | L29: 0.38569897
B30: OER | C30: 0.050864587 | D30: 0.006821232 | E30: 0.012065152 | F30: 0.056671522 | G30: 0.054654004 | H30: 0.055574311 | I30: 0.067479629 | J30: 0.021463423 | K30: 0.030839954 | L30: 0.036261474
B31: MIN LIQ | C31: 0.28117848 | D31: 0.1804874 | E31: 0.14704211 | F31: 0.20525016 | G31: 0.26279967 | H31: 0.27638489 | I31: 0.26967942 | J31: 0.20183359 | K31: 0.21134839 | L31: 0.19694405
B32: TEC LIQ | C32: 0.18838483 | D32: 0.12915454 | E32: 0.10373806 | F32: 0.1770109 | G32: 0.2240215 | H32: 0.23200767 | I32: 0.21838892 | J32: 0.17267718 | K32: 0.17362602 | L32: 0.17125133
B33: EB | C33: 0.001688932 | D33: 0.0017153851 | E33: 0.0017921054 | F33: 0 | G33: 0 | H33: 0 | I33: 0 | J33: 0 | K33: 0 | L33: 0
B34: LIQ/TA | C34: 0.14978838 | D34: 0.10763133 | E34: 0.083528395 | F34: 0.14740407 | G34: 0.16450573 | H34: 0.16990382 | I34: 0.15588442 | J34: 0.13883827 | K34: 0.14041273 | L34: 0.13515776
B35: NEA | C35: 0.11800484 | D35: 0.12675515 | E35: 0.10067358 | F35: 0.053367462 | G35: 0.043302199 | H35: 0.058974292 | I35: 0.041797813 | J35: 0.039852185 | K35: 0.072852538 | L35: 0.054640365
B36: LB | C36: 0.01288188 | D36: 0.012663382 | E36: 0.013661078 | F36: 0.0051649463 | G36: 0.011631407 | H36: 0.01118682 | I36: 0.011457956 | J36: 0.010564849 | K36: 0.011089534 | L36: 0.010959528
B37: FITD | C37: 0.12176194 | D37: 0.11269646 | E37: 0.11464343 | F37: 0.0097586092 | G37: 0.0096455287 | H37: 0.0093098923 | I37: 0.0089743259 | J37: 0.009131763 | K37: 0.0086975334 | L37: 0.0090698477
B38: FICC | C38: 0.46669717 | D38: 0.52824067 | E38: 0.50746862 | F38: 0.047656592 | G38: 0.027142986 | H38: 0.025877532 | I38: 0.02531985 | J38: 0.038023203 | K38: 0.037151868 | L38: 0.03434775

Sheet DEC 2020
A1: MAGADI SACCO SOCIETY LIMITED
A2: PERFORMANCE AND COMPLIANCE REPORT AS AT : 31st December , 2020
B3: Prudential Standard | C3: Audited | D3: Returns | F3: AUDITED 2020 | G3: Aggregate for all Licensed Saccos
C4: 2019 | D4: 30th September , 2020 | E4: 31st December , 2020
A5: A. CAPITAL ADEQUACY
A6: Core Capital | B6: ≥10M | C6: =C33 -> 98409139 | D6: =D33 -> 1.5398554e+08 | E6: =E33 -> 1.7565742e+08 | F6: =F33 -> 6095283000 | G6: =G33 -> 9.281382e+10 | H6: =F6-C6 -> 5996873861
A7: Core Capital/Total Assets | B7: ≥10% | C7: =C33/C29 -> 0.149196 | D7: =D33/D29 -> 0.21974079 | E7: =E33/E29 -> 0.23992254 | F7: =F33/F29 -> 0.14500719 | G7: =G33/G29 -> 0.15852844
A8: Institutional Capital/Total Assets | B8: ≥8% | C8: =C34/C29 -> 0.11007419 | D8: =D34/D29 -> 0.18075965 | E8: =E34/E29 -> 0.2020382 | F8: =F34/F29 -> 0.096893253 | G8: =G34/G29 -> 0.092879022
A9: B. ASSET QUALITY
A10: NPL (Substandard+Doubtful+Loss) | B10: <5% | C10: =C35/C32 -> 0 | D10: =D35/D32 -> 0.066804616 | E10: =E35/E32 -> 0.058669004 | F10: =F35/F32 -> 0.00092813059 | G10: =G35/G32 -> 0.081923116
A11: Non-Earning Assets | B11: <10% | C11: =C36/C29 -> 0.041460677 | D11: =D36/D29 -> 0.034504765 | E11: =E36/E29 -> 0.03147327 | F11: =F36/F29 -> 0.051554025 | G11: =G36/G29 -> 0.10331964
A12: Equity investments/Deposits | B12: <5% | C12: =C38/C31 -> 0.0086859989 | D12: =D38/D31 -> 0.007972688 | E12: =E38/E31 -> 0.0078282924 | F12: =F38/F31 -> 0.062911549 | G12: =G38/G31 -> 0.033894147
A13: Equity investments/Core capital | B13: <40% | C13: =C38/C33 -> 0.042969139 | D13: =D38/D33 -> 0.027460728 | E13: =E38/E33 -> 0.024072738 | F13: =F38/F33 -> 0.32190499 | G13: =G38/G33 -> 0.14648774
A14: C. EARNINGS RATING
A15: Yield on Gross Loans | C15: =C48/C32 -> 0.18432223 | D15: =D48/D32 -> 0.1292034 | E15: =E48/E32 -> 0.17383407 | F15: =F48/F32 -> 0.07284616 | G15: =G48/G32 -> 0.1744387
A16: Total Expense/Total Income | C16: =C49/C44 -> 0.81230275 | D16: =D49/D44 -> 0.33068826 | E16: =E49/E44 -> 0.33091343 | F16: =F49/F44 -> 0.81329438 | G16: =G49/G44 -> 0.69938821
A17: Net Income/Average Assets (ROA) | C17: =C50/C30 -> 0.02237977 | D17: =D50/D30 -> 0.081626281 | E17: =E50/E30 -> 0.10964544 | F17: =F50/F30 -> 0.047834509 | G17: =G50/G30 -> 0.038410442
A18: Operating Expenses/Financial Income (OPEX) | C18: =C47/C44 -> 0.32162796 | D18: =D47/D44 -> 0.28452022 | E18: =E47/E44 -> 0.28396284 | F18: =F47/F44 -> 0.20656465 | G18: =G47/G44 -> 0.30079837
A19: D. LIQUIDITY
A20: Liquid Assets/Short-term Liabilities | B20: >15% | C20: =C40/C41 -> 0.59313783 | D20: =D40/D41 -> 1.4178168 | E20: =E40/E41 -> 2.0006732 | F20: =F40/F41 -> 0.46582172 | G20: =G40/G41 -> 0.6151057
A21: External Borrowing/Total Assets | B21: <25% | C21: =C42/C29 -> 1.1611647e-05 | D21: =D42/D29 -> 0.011921445 | E21: =E42/E29 -> 0.010282182 | F21: =F42/F29 -> 0 | G21: =G42/G29 -> 0.036576677
A22: Liquid Assets/Total Assets | C22: =C40/C29 -> 0.067680721 | D22: =D40/D29 -> 0.12936886 | E22: =E40/E29 -> 0.15742859 | F22: =F40/F29 -> 0.12148195 | G22: =G40/G29 -> 0.11724056
A23: E. STRUCTURE/SENSITIVITY TO RISK
A24: Gross loans /Total Assets | B24: 70-80 | C24: =C32/C29 -> 0.82800207 | D24: =D32/D29 -> 0.86523081 | E24: =E32/E29 -> 0.83846194 | F24: =F32/F29 -> 0.92315385 | G24: =G32/G29 -> 0.75523899
A25: Gross loans/Deposits | B25: >100% | C25: =C32/C31 -> 1.1218567 | D25: =D32/D31 -> 1.1431784 | E25: =E32/E31 -> 1.1364592 | F25: =F32/F31 -> 1.2441915 | G25: =G32/G31 -> 1.1023021
A26: Financial Investments/Total Assets | C26: =C39/C31 -> 0.11977917 | D26: =D39/D31 -> 0.007972688 | E26: =E39/E31 -> 0.0078282924 | F26: =F39/F31 -> 0.062911549 | G26: =G39/G31 -> 0.067272667
A27: Dividends+Interest on Deposits/Total Income | C27: =C46/C44 -> 0.48412627 | D27: =D46/D44 -> 0.012481243 | E27: =E46/E44 -> 0.0115585 | F27: =F46/F44 -> 0.48125279 | G27: =G46/G44 -> 0.33833569
A28: F. KEY FINANCIAL STATISTICS | C28: 2015 | D28: 2016 | E28: 2017 | G28: AGGREGATE
A29: Total Assets | C29: 659596375 | D29: 7.0075991e+08 | E29: 7.321422e+08 | F29: =SFP!B27 -> 42034351000 | G29: 5.8547109e+11
A30: Average Assets | C30: 6.2488266e+08 | D30: 6.6920187e+08 | E30: 6.9562445e+08 | F30: =(C29+F29)/2 -> 2.1346974e+10 | G30: 5.6966122e+11
A31: Total Deposits | C31: 486824375 | D31: 5.3038009e+08 | E31: 5.4016313e+08 | F31: =SFP!B32 -> 31188264000 | G31: 4.0113376e+11
A32: Gross Loans | C32: 546147164 | D32: 6.0631906e+08 | E32: 6.1387337e+08 | F32: =SFP!B15 -> 38804173000 | G32: 4.421706e+11
A33: Core Capital | C33: 98409139 | D33: 1.5398554e+08 | E33: 1.7565742e+08 | F33: =Financials!C14 -> 6095283000 | G33: 9.281382e+10
A34: Institutional Capital | C34: 72604536 | D34: 1.2666911e+08 | E34: 1.4792069e+08 | F34: =Financials!C15 -> 4072845000 | G34: 5.4377982e+10
A35: Non-performing Loans | C35: 0 | D35: 40504912 | E35: 36015340 | F35: =16172116+14580201+5263023 -> 36015340 | G35: 3.6223993e+10
A36: Non-Earning Assets | C36: 27347312 | D36: 24179556 | E36: 23042909 | F36: =Financials!C38 -> 2167040000 | G36: 6.0490663e+10
A37: Property and Equipment | C37: 5678927 | D37: 5703357.5 | E37: 5726554 | F37: =Financials!C39 -> 223605000 | G37: 1.7300265e+10
A38: Equity Investments | C38: 4228556 | D38: 4228554.9 | E38: 4228554.9 | F38: =SFP!B12+SFP!B13 -> 1962102000 | G38: 1.3596086e+10
A39: Financial Investments | C39: 58311419 | D39: 4228554.9 | E39: 4228554.9 | F39: =SFP!B8 -> 1962102000 | G39: 2.6985337e+10
A40: Liquid Assets | C40: 44641958 | D40: 90656514 | E40: 1.1526011e+08 | F40: =SFP!B4+SFP!B11 -> 5106415000 | G40: 6.8640959e+10
A41: Short-term Liabilities) | C41: 75264054 | D41: 63940921 | E41: 57610665 | F41: =SFP!B29+SFP!B30+SFP!B33-SFP!B39 -> 10962166000 | G41: 1.1159213e+11
A42: External Borrowing | C42: 7659 | D42: 8354071 | E42: 7528019 | F42: =SFP!B39 -> 0 | G42: 2.1414587e+10
A43: Average Gross Loans | C43: 5.1241266e+08 | D43: 5.768587e+08 | E43: 5.7996732e+08 | F43: =(C32+E32)/2 -> 5.8001027e+08 | G43: 4.3131225e+11
A44: Total Income | C44: 119501967 | D44: 93225263 | E44: 1.2531687e+08 | F44: =SCI!B3 -> 5873701000 | G44: 8.9459919e+10
A45: Net Financial Income/Loss | C45: 60865365 | D45: 88921235 | E45: 1.1943317e+08 | F45: =SCI!B19 -> 2854262000 | G45: 5.3897612e+10
A46: Dividends+Interest on Deposits | C46: 57854041 | D46: 1163567.2 | E46: 1448475.1 | F46: =SCI!B13 -> 2826735000 | G46: 3.0267483e+10
A47: Operating Expenses | C47: 38435174 | D47: 26524472 | E47: 35585335 | F47: =SCI!B23 -> 1213299000 | G47: 2.6909398e+10
A48: Interest on Loan portfolio+Fees&Commission on Loan | C48: 100667063 | D48: 78338482 | E48: 1.0671211e+08 | F48: =SCI!B13+SCI!B15 -> 2826735000 | G48: 7.7131665e+10
A49: Total Expenses | C49: 97071776 | D49: 30828500 | E49: 41469037 | F49: =SCI!B12+SCI!B20+SCI!B23 -> 4777048000 | G49: 6.2567213e+10
A50: Net Income | C50: 13984730 | D50: 54624460 | E50: 76272050 | F50: =SCI!B37 -> 1021122000 | G50: 2.1880939e+10
A51: G. AREAS OF IMPROVEMENT/REGULATORY CONCERNS
A52: 1
A53: 2
A54: 3
A55: 4
A56: Prepared by:
A58: Checked by:
A60: Approved by:
A62: DISCLAIMER: This report is prepared based on information submitted by the Sacco as at the stated date and may change upon verification by the Authority.

Sheet DEC 2019 REPORT
A1: EGERTON SACCO SOCIETY LIMITED
A2: PERFORMANCE AND COMPLIANCE REPORT AS AT : 31st December , 2019
B3: Prudential Standard | C3: Audited | D3: Returns | F3: Audited 2019 | G3: Aggregate for all Licensed Saccos
C4: 2018 | D4: 30th September , 2019 | E4: 31st December , 2019
A5: A. CAPITAL ADEQUACY
A6: Core Capital | B6: ≥10M | C6: 92958252 | D6: 1.14416e+08 | E6: 1.2704881e+08 | F6: =F33 -> #REF! | G6: 8.5391581e+10
A7: Core Capital/Total Assets | B7: ≥10% | C7: 0.15751126 | D7: 0.17943559 | E7: 0.19275909 | F7: =F6/F29 -> #REF! | G7: 0.15597716
A8: Institutional Capital/Total Assets | B8: ≥8% | C8: 0.11818998 | D8: 0.13976271 | E8: 0.15360974 | F8: =F34/F29 -> #REF! | G8: 0.091529477
A9: B. ASSET QUALITY
A10: NPL (Substandard+Doubtful+Loss) | B10: <5% | C10: 0 | D10: 0.057997794 | E10: 0.049062417 | F10: =F35/F32 -> #REF! | G10: 0.073407957
A11: Non-Earning Assets | B11: <10% | C11: 0.05336904 | D11: 0.043135899 | E11: 0.041315651 | F11: =F36/F29 -> #REF! | G11: 0.10567687
A12: Equity investments/Deposits | B12: <5% | C12: 0 | D12: 0.0086297878 | E12: 0.0086830722 | F12: =F38/F31 -> #REF! | G12: 0.034924323
A13: Equity investments/Core capital | B13: <40% | C13: 0 | D13: 0.036957724 | E13: 0.033282917 | F13: =F38/F33 -> #REF! | G13: 0.15379721
A14: C. EARNINGS RATING
A15: Yield on Gross Loans | C15: 0.1927038 | D15: 0.13877868 | E15: 0.18737466 | F15: =F48/F32 -> #REF! | G15: 0.16090341
A16: Total Expense/Total Income | C16: 0.79311986 | D16: 0.35836605 | E16: 0.33974951 | F16: =F49/F44 -> #REF! | G16: 0.7077997
A17: Net Income/Average Assets (ROA) | C17: 0.027977038 | D17: 0.081818348 | E17: 0.11400955 | F17: =F50/F30 -> #REF! | G17: 0.036975972
A18: Operating Expenses/Financial Income (OPEX) | C18: 0.30200757 | D18: 0.31934513 | E18: 0.30463818 | F18: =F47/F45 -> #REF! | G18: 0.31992697
A19: D. LIQUIDITY
A20: Liquid Assets/Short-term Liabilities | B20: >15% | C20: 1.1755674 | D20: 1.0116662 | E20: 1.4570234 | F20: =F40/F41 -> #REF! | G20: 0.54995224
A21: External Borrowing/Total Assets | B21: <25% | C21: 0 | D21: 0 | E21: 0 | F21: =F42/F29 -> #REF! | G21: 0.039238045
A22: Liquid Assets/Total Assets | C22: 0.14737887 | D22: 0.12043218 | E22: 0.149349 | F22: =F40/F29 -> #REF! | G22: 0.11016896
A23: E. STRUCTURE/SENSITIVITY TO RISK
A24: Gross loans /Total Assets | B24: 70-80 | C24: 0.81108665 | D24: 0.85847035 | E24: 0.82848691 | F24: =F32/F29 -> #REF! | G24: 0.75892188
A25: Gross loans/Deposits | B25: >100% | C25: 1.1046878 | D25: 1.1171503 | E25: 1.1213025 | F25: =F32/F31 -> #REF! | G25: 1.1048812
A26: Financial Investments/Total Assets | C26: 0.0097586092 | D26: 0.0086297878 | E26: 0.0086830722 | F26: =F39/F29 -> #REF! | G26: 0.059782935
A27: Dividends+Interest on Deposits/Total Income | C27: 0.48814819 | D27: 0.012035001 | E27: 0.012230217 | F27: =F46/F44 -> #REF! | G27: 0.32108527
A28: F. KEY FINANCIAL STATISTICS | C28: 2015 | D28: 2016 | E28: 2017 | G28: AGGREGATE
A29: Total Assets | C29: 590168948 | D29: 6.3764384e+08 | E29: 6.5910669e+08 | F29: =SFP!#REF! -> #REF! | G29: 5.4746207e+11
A30: Average Assets | C30: 5.6413338e+08 | D30: 6.1492399e+08 | E30: 6.4176168e+08 | F30: =(F29+C29)/2 -> #REF! | G30: 5.2079291e+11
A31: Total Deposits | C31: 433315333 | D31: 4.8999524e+08 | E31: 4.8698834e+08 | F31: =SFP!#REF! -> #REF! | G31: 3.7604128e+11
A32: Gross Loans | C32: 478678153 | D32: 5.4739833e+08 | E32: 5.4606127e+08 | F32: =SFP!#REF! -> #REF! | G32: 4.1548094e+11
A33: Core Capital | C33: 92958252 | D33: 1.14416e+08 | E33: 1.2704881e+08 | F33: =Financials!#REF! -> #REF! | G33: 8.5391581e+10
A34: Institutional Capital | C34: 69752057 | D34: 89118833 | E34: 1.0124521e+08 | F34: =Financials!#REF! -> #REF! | G34: 5.0108917e+10
A35: Non-performing Loans | C35: 0 | D35: 31747895 | E35: 26791086 | F35: =22604726+734025+3452334 -> 26791085 | G35: 3.0499607e+10
A36: Non-Earning Assets | C36: 31496750 | D36: 27505341 | E36: 27231422 | F36: =Financials!#REF! -> #REF! | G36: 5.7854076e+10
A37: Property and Equipment | C37: 7005759 | D37: 5982262.2 | E37: 5325780.8 | F37: =Financials!#REF! -> #REF! | G37: 1.7751024e+10
A38: Equity Investments | C38: 0 | D38: 4228554.9 | E38: 4228554.9 | F38: =SFP!#REF!+SFP!#REF! -> #REF! | G38: 1.3132987e+10
A39: Financial Investments | C39: 4228555 | D39: 4228554.9 | E39: 4228554.9 | F39: =SFP!#REF! -> #REF! | G39: 2.2480852e+10
A40: Liquid Assets | C40: 86978434 | D40: 76792836 | E40: 98436927 | F40: =SFP!#REF! -> #REF! | G40: 6.031333e+10
A41: Short-term Liabilities) | C41: 73988469 | D41: 75907286 | E41: 67560292 | F41: =SFP!#REF!+SFP!#REF!+SFP!#REF!-SFP!#REF! -> #REF! | G41: 1.0967012e+11
A42: External Borrowing | C42: 0 | D42: 0 | E42: 0 | F42: =SFP!#REF! -> #REF! | G42: 2.1481341e+10
A43: Average Gross Loans | C43: 445483841 | D43: 5.0462708e+08 | E43: 5.1208838e+08 | F43: =(C32+F32)/2 -> #REF! | G43: 3.9339201e+11
A44: Total Income | C44: 110748089 | D44: 89428467 | E44: 1.1935697e+08 | F44: =SCI!#REF! -> #REF! | G44: 7.9322865e+10
A45: Net Financial Income/Loss | C45: 56358341 | D45: 85938886 | E45: 1.1516619e+08 | F45: =SCI!#REF! -> #REF! | G45: 4.6800236e+10
A46: Dividends+Interest on Deposits | C46: 54061479 | D46: 1076271.7 | E46: 1459761.6 | F46: =SCI!#REF! -> #REF! | G46: 2.5469404e+10
A47: Operating Expenses | C47: 33446761 | D47: 28558545 | E47: 36360690 | F47: =SCI!#REF! -> #REF! | G47: 2.5377524e+10
A48: Interest on Loan portfolio+Fees&Commission on Loan | C48: 92243098 | D48: 75967218 | E48: 1.0231804e+08 | F48: =SCI!#REF! -> #REF! | G48: 6.6852299e+10
A49: Total Expenses | C49: 87836509 | D49: 32048126 | E49: 40551471 | F49: =SCI!#REF!+SCI!#REF! -> #REF! | G49: 5.61447e+10
A50: Net Income | C50: 15782781 | D50: 50312065 | E50: 73166962 | F50: =SCI!#REF! -> #REF! | G50: 1.9256824e+10
A51: G. AREAS OF IMPROVEMENT/REGULATORY CONCERNS
A52: 1
A53: 2
A54: 3
A55: 4
A56: Prepared by:
A58: Checked by: Nelly Kulei
A60: Approved by: Peter Owira
A62: DISCLAIMER: This report is prepared based on information submitted by the Sacco as at the stated date and may change upon verification by the Authority.
C63: 22nd January 2020
