Workbook
Name BALANCE1_LDA01: '[1]Financial Statements'!$E$112
Name BALANCE1_LDA12: '[1]Financial Statements'!$E$123
Name BALANCE2_LDA01: '[1]Financial Statements'!$F$112
Name BALANCE2_LDA12: '[1]Financial Statements'!$F$123
Name BALANCE3_LDA01: '[1]Financial Statements'!$G$112
Name BALANCE3_LDA12: '[1]Financial Statements'!$G$123
Name BALANCE4_LDA01: '[1]Financial Statements'!$H$112
Name BALANCE4_LDA12: '[1]Financial Statements'!$H$123
Name BALANCE5_LDA01: '[1]Financial Statements'!$I$112
Name BALANCE5_LDA12: '[1]Financial Statements'!$I$123
Name BALANCE6_LDA01: '[1]Financial Statements'!$J$112
Name BALANCE6_LDA12: '[1]Financial Statements'!$J$123
Name PEARLS1_LA002: '[1]Financial Statements'!$E$280
Name PEARLS1_LE008: '[1]Financial Statements'!$E$275
Name PEARLS1_LE009: '[1]Financial Statements'!$E$276
Name PEARLS1_LR001: '[1]Financial Statements'!$E$282
Name PEARLS1_LR005: '[1]Financial Statements'!$E$286
Name PEARLS1_LR006: '[1]Financial Statements'!$E$287
Name PEARLS1_LR007: '[1]Financial Statements'!$E$288
Name PEARLS1_LR009: '[1]Financial Statements'!$E$290
Name PEARLS1_LS001: '[1]Financial Statements'!$E$298
Name PEARLS1_LS005: '[1]Financial Statements'!$E$302
Name PEARLS1_LS011: '[1]Financial Statements'!$E$308
Name PEARLS2_LA002: '[1]Financial Statements'!$F$280
Name PEARLS2_LE008: '[1]Financial Statements'!$F$275
Name PEARLS2_LE009: '[1]Financial Statements'!$F$276
Name PEARLS2_LR001: '[1]Financial Statements'!$F$282
Name PEARLS2_LR005: '[1]Financial Statements'!$F$286
Name PEARLS2_LR006: '[1]Financial Statements'!$F$287
Name PEARLS2_LR007: '[1]Financial Statements'!$F$288
Name PEARLS2_LR009: '[1]Financial Statements'!$F$290
Name PEARLS2_LS001: '[1]Financial Statements'!$F$298
Name PEARLS2_LS005: '[1]Financial Statements'!$F$302
Name PEARLS2_LS010: '[1]Financial Statements'!$F$307
Name PEARLS2_LS011: '[1]Financial Statements'!$F$308
Name PEARLS3_LA002: '[1]Financial Statements'!$G$280
Name PEARLS3_LE008: '[1]Financial Statements'!$G$275
Name PEARLS3_LE009: '[1]Financial Statements'!$G$276
Name PEARLS3_LR001: '[1]Financial Statements'!$G$282
Name PEARLS3_LR005: '[1]Financial Statements'!$G$286
Name PEARLS3_LR006: '[1]Financial Statements'!$G$287
Name PEARLS3_LR007: '[1]Financial Statements'!$G$288
Name PEARLS3_LR009: '[1]Financial Statements'!$G$290
Name PEARLS3_LS001: '[1]Financial Statements'!$G$298
Name PEARLS3_LS005: '[1]Financial Statements'!$G$302
Name PEARLS3_LS010: '[1]Financial Statements'!$G$307
Name PEARLS3_LS011: '[1]Financial Statements'!$G$308
Name PEARLS4_LA002: '[1]Financial Statements'!$H$280
Name PEARLS4_LE008: '[1]Financial Statements'!$H$275
Name PEARLS4_LE009: '[1]Financial Statements'!$H$276
Name PEARLS4_LR001: '[1]Financial Statements'!$H$282
Name PEARLS4_LR005: '[1]Financial Statements'!$H$286
Name PEARLS4_LR006: '[1]Financial Statements'!$H$287
Name PEARLS4_LR007: '[1]Financial Statements'!$H$288
Name PEARLS4_LR009: '[1]Financial Statements'!$H$290
Name PEARLS4_LS001: '[1]Financial Statements'!$H$298
Name PEARLS4_LS005: '[1]Financial Statements'!$H$302
Name PEARLS4_LS010: '[1]Financial Statements'!$H$307
Name PEARLS4_LS011: '[1]Financial Statements'!$H$308
Name PEARLS5_LA002: '[1]Financial Statements'!$I$280

Sheet Evolutive SFP
B3: AUDITED 2019 | C3: 43831 | D3: 43862 | E3: 43891 | F3: 43922 | G3: 43952 | H3: 43983 | I3: 44044 | J3: 44075 | K3: 44105 | L3: 44136 | M3: 44166 | N3: Audited 2020 | O3: 44197 | P3: 44228 | Q3: 44256 | R3: 44287 | S3: 44317 | T3: 44348 | U3: 44378 | V3: 44409 | W3: 44440 | X3: 44470 | Y3: 44501 | Z3: 44531 | AA3: AUDITED 2021 | AB3: 44562 | AC3: 44593 | AD3: 44621 | AE3: 44652 | AF3: 44682 | AG3: 44713 | AH3: 44743 | AI3: 44774 | AJ3: 44805 | AK3: 44835 | AL3: 44866 | AM3: 44896 | AN3: AUDITED 2022 | AO3: 44927 | AP3: 44958 | AQ3: 44986 | AR3: 45017 | AS3: 45047 | AT3: 45078 | AU3: 45108 | AV3: 45139
A4: Cash & cash Equivalent | B4: =(B5+B6) -> 60942574 | C4: =(C5+C6) -> 561024.02 | D4: =(D5+D6) -> 611197.36 | E4: =(E5+E6) -> 606233.06 | F4: =(F5+F6) -> 675951.44 | G4: =(G5+G6) -> 807920.76 | H4: =(H5+H6) -> 874010.45 | I4: =(I5+I6) -> 813996.37 | ... AV4: =(AV5+AV6) -> 7.5559238e+08
A5: Cash In Hand | B5: =1162643.9+734230 -> 1896873.9 | C5: 8563.6 | D5: 3071.76 | E5: 4222.11 | F5: 3757.31 | G5: 2627.48 | H5: 818.9 | I5: 235.72 | J5: 1089.42 | K5: 857.98 | L5: 1286.58 | M5: 307.54 | N5: =307542 -> 307542 | O5: 2093.34 | P5: 3397.41 | Q5: 3247.9 | R5: 1321.57 | S5: 2447.67 | T5: 3347.33 | U5: 1517.75 | V5: 608.93 | W5: 1257.06 | X5: 2537.21 | Y5: 3164.44 | Z5: 4092.18 | AA5: 4092180 | AB5: 2218350 | AC5: 2406493 | AD5: 3885985 | AE5: 1832448 | AF5: 4398483 | AG5: 2003607 | AH5: 3395790 | AI5: 1437868 | AJ5: 1981939 | AK5: 2234037 | AL5: 2635973 | AM5: 1113513 | AN5: =1137278+1804064+47533789+15376525+19583 -> 65871239 | AO5: 2612139 | AP5: 1820465 | AQ5: 1513765 | AR5: 837550 | AS5: 1582832 | AT5: 1959660 | AU5: 3347156 | AV5: 1466424
A6: Cash at Bank | B6: =15822167+4245336+223711.48+118700+34335785.65+4300000 -> 59045700 | C6: 552460.42 | D6: 608125.6 | E6: 602010.95 | F6: 672194.13 | G6: 805293.28 | H6: 873191.55 | I6: 813760.65 | J6: 762569.29 | K6: 747062.31 | L6: 783261.38 | M6: 781259.81 | N6: =783294992-N5 -> 782987450 | O6: 812649.63 | P6: 832063.54 | Q6: 783482.37 | R6: 799991.6 | S6: 803861.63 | T6: 803938.96 | U6: 819617.7 | V6: 819738.05 | W6: 835448.09 | X6: 919272.4 | Y6: 967121.33 | Z6: 1014635.1 | AA6: =1021706818-AA5 -> 1017614638 | AB6: 1.0334949e+09 | AC6: 1.0716266e+09 | AD6: 1.0184484e+09 | AE6: 1.0130524e+09 | AF6: 1.0425861e+09 | AG6: 1.0943449e+09 | AH6: 1.0902105e+09 | AI6: 1.2022465e+09 | AJ6: 1.26715e+09 | AK6: 1.2993252e+09 | AL6: 1.3471162e+09 | AM6: 1.3641671e+09 | AN6: =1366906242-AN5 -> 1301035003 | AO6: 1.3650328e+09 | AP6: 1.4371146e+09 | AQ6: 1.3491084e+09 | AR6: 1.3444305e+09 | AS6: 1364318038 | AT6: 1.0546844e+09 | AU6: 9.2487427e+08 | AV6: 7.5412596e+08
A7: Prepayment and Sundry | B7: =734299+7607765+1608382+1262141+451626 -> 11664213 | C7: 0 | D7: 0 | E7: 0 | F7: 0 | G7: 0 | H7: 0 | I7: 0 | J7: 0 | K7: 0 | L7: 0 | M7: 0 | N7: =16398297+1605749+10000+4475468+806444 -> 23295958 | O7: 0 | P7: 0 | Q7: 0 | R7: 0 | S7: 0 | T7: 0 | U7: 0 | V7: 0 | W7: 0 | X7: 0 | Y7: 0 | Z7: 0 | AA7: 43313613 | AB7: 0 | AC7: 0 | AD7: 0 | AE7: 0 | AF7: 0 | AG7: 0 | AH7: 0 | AI7: 0 | AJ7: 0 | AK7: 0 | AL7: 0 | AM7: 0 | AN7: 75065390 | AO7: 0 | AP7: 0 | AQ7: 0 | AR7: 0 | AS7: 0 | AT7: 0 | AU7: 0 | AV7: 0
A8: Financial Investment | B8: =(B9+B10+B11+B13+B12) -> 115855 | C8: =(C9+C10+C11+C13+C12) -> 213810.42 | D8: =(D9+D10+D11+D13+D12) -> 213810.42 | E8: =(E9+E10+E11+E13+E12) -> 216168.92 | F8: =(F9+F10+F11+F13+F12) -> 216168.92 | G8: =(G9+G10+G11+G13+G12) -> 216168.92 | H8: =(H9+H10+H11+H13+H12) -> 216168.92 | I8: =(I9+I10+I11+I13+I12) -> 216418.92 | ... AV8: =(AV9+AV10+AV11+AV13+AV12) -> 7.9164262e+08
A9: Government Security | C9: 0 | D9: 0 | E9: 0 | F9: 0 | G9: 0 | H9: 0 | I9: 0 | J9: 0 | K9: 0 | L9: 0 | M9: 0 | O9: 0 | P9: 0 | Q9: 0 | R9: 0 | S9: 0 | U9: 0 | V9: 0 | AB9: 0 | AC9: 0 | AD9: 0 | AE9: 0 | AF9: 0 | AG9: 0 | AH9: 0 | AI9: 0 | AJ9: 0 | AK9: 0 | AL9: 0 | AM9: 0 | AO9: 0 | AP9: 0 | AQ9: 0 | AR9: 0 | AS9: 0 | AT9: 350000000 | AU9: 507249295 | AV9: 5.6950697e+08
A10: Other Securities | C10: 0 | D10: 0 | E10: 0 | F10: 0 | G10: 0 | H10: 0 | I10: 0 | J10: 0 | K10: 0 | L10: 0 | M10: 0 | O10: 0 | P10: 0 | Q10: 0 | R10: 0 | S10: 0 | U10: 0 | V10: 0 | W10: 0 | X10: 0 | Y10: 0 | Z10: 0 | AB10: 0 | AC10: 0 | AD10: 0 | AE10: 0 | AF10: 0 | AG10: 0 | AH10: 0 | AI10: 0 | AJ10: 0 | AK10: 0 | AL10: 0 | AM10: 0 | AO10: 0 | AP10: 0 | AQ10: 0 | AR10: 0 | AS10: 0 | AT10: 0 | AU10: 0 | AV10: 0
A11: Balances in NACCOS (E.g Jungu Kuu, ESS, Savings,Money Market,Coop FD, CFP) | B11: =115855 -> 115855 | C11: 8093.93 | D11: 8093.93 | E11: 10452.43 | F11: 10452.43 | G11: 10452.43 | H11: 10452.43 | I11: 10702.43 | J11: 10764.36 | K11: 10764.36 | L11: 10920.91 | M11: 10970.91 | O11: 10970.91 | P11: 10977.85 | Q11: 11027.85 | R11: 11177.85 | S11: 11177.85 | T11: 11177.85 | W11: 0 | X11: 0 | Y11: 0 | Z11: 0 | AB11: 11651040 | AC11: 11701040 | AD11: 11701040 | AE11: 11801040 | AF11: 11801040 | AG11: 11918472 | AH11: 11918472 | AI11: 12018472 | AJ11: 12068472 | AK11: 12118472 | AL11: 12168472 | AM11: 12218472 | AO11: 12297602 | AP11: 12347602 | AQ11: 12347602 | AR11: 12447602 | AS11: 12447602 | AT11: 12547602 | AU11: 12547602 | AV11: 12547602
A12: Equity Investments in NACCOs(Shares in- CIC, KUSCCO, COOP BANK,CAK, KERUSSU) | C12: 205716.49 | D12: 205716.49 | E12: 205716.49 | F12: 205716.49 | G12: 205716.49 | H12: 205716.49 | I12: 205716.49 | J12: 205716.49 | K12: 205716.49 | L12: 205716.49 | M12: 205716.49 | N12: =53232144+895992+8093928 -> 62222064 | U12: 11342.92 | V12: 11392.92 | W12: 11442.92 | X12: 11501.04 | Y12: 11551.04 | Z12: 11601.04 | AA12: =53232144+895992+8093928 -> 62222064 | AB12: 2.0627727e+08 | AC12: 2.0627727e+08 | AD12: 2.0627727e+08 | AE12: 2.0627727e+08 | AF12: 2.0627727e+08 | AG12: 2.0627727e+08 | AH12: 2.0627727e+08 | AI12: 2.0627727e+08 | AJ12: 2.0627727e+08 | AK12: 2.0627727e+08 | AL12: 2.0627727e+08 | AM12: 2.0627727e+08 | AN12: =53232144+895992+8093928 -> 62222064 | AO12: 2.0627727e+08 | AP12: 2.0542227e+08 | AQ12: 2.0542227e+08 | AR12: 2.0542227e+08 | AS12: 2.0542227e+08 | AT12: 2.0958805e+08 | AU12: 2.0958805e+08 | AV12: 2.0958805e+08
A13: Equity Investments in companies - shares/stocks | N13: =4339+25001118+126582900 -> 151588357 | O13: 205716.49 | P13: 205716.49 | Q13: 205716.49 | R13: 205716.49 | S13: 205716.49 | T13: 205716.49 | U13: 205716.49 | V13: 205716.49 | W13: 206277.27 | X13: 206277.27 | Y13: 206277.27 | Z13: 206277.27 | AA13: =4339+25001118+127143680 -> 152149137 | AB13: 0 | AC13: 0 | AD13: 0 | AE13: 0 | AF13: 0 | AG13: 0 | AH13: 0 | AI13: 0 | AJ13: 0 | AK13: 0 | AL13: 0 | AM13: 0 | AN13: =126288680+25001144+4339 -> 151294163
A14: Net Loan Portfolio | B14: =(B15-B16) -> 216882733 | C14: =(C15-C16) -> 2218881.5 | D14: =(D15-D16) -> 2194730.5 | E14: =(E15-E16) -> 2142502.8 | F14: =(F15-F16) -> 2083076.2 | G14: =(G15-G16) -> 2085200.9 | H14: =(H15-H16) -> 2041178.1 | I14: =(I15-I16) -> 2220959.6 | ... AV14: =(AV15-AV16) -> 3.615259e+09
A15: Gross Loan Portfolio | B15: 238201977 | C15: 2254469.6 | D15: 2281291.9 | E15: 2236181.1 | F15: 2187772 | G15: 2148831.4 | H15: 2152614.9 | I15: 2334271.6 | J15: 2423796.5 | K15: 2482872.8 | L15: 2516422.2 | M15: 2564682.8 | N15: 2564485165 | O15: 2578503.4 | P15: 2602511.1 | Q15: 2595432.2 | R15: 2656255.8 | S15: 2698251.6 | T15: 2757238.4 | U15: 2792413.3 | V15: 2817998.9 | W15: 2816968.3 | X15: 2834290.1 | Y15: 2851108.5 | Z15: 2876131.2 | AA15: =2800698147+75353662 -> 2876051809 | AB15: 2.9031672e+09 | AC15: 2.9126159e+09 | AD15: 2.8807684e+09 | AE15: 2.9029136e+09 | AF15: 2.940416e+09 | AG15: 3.0248702e+09 | AH15: 3.0395705e+09 | AI15: 3.0685491e+09 | AJ15: 3.0779728e+09 | AK15: 3.1243903e+09 | AL15: 3.1446427e+09 | AM15: 3.2164272e+09 | AN15: =535593771+796044441+196669398+17584351+59907125+43671628+45944280+924150+2980750+39500+9731035+6426737+1280530506+225500+3338973+190127173+26490921 -> 3216230239 | AO15: 3.3045163e+09 | AP15: 3.3387625e+09 | AQ15: 3.3257418e+09 | AR15: 3.3656027e+09 | AS15: 3.4175862e+09 | AT15: 3.5386404e+09 | AU15: 3.6148066e+09 | AV15: 3.7167025e+09
A16: Allowance For Loan Loss | B16: 21319244 | C16: 35588.07 | D16: 86561.44 | E16: 93678.35 | F16: 104695.77 | G16: 63630.49 | H16: 111436.78 | I16: 113312 | J16: 114071.49 | K16: 103511.29 | L16: 111435.61 | M16: 85987.1 | N16: 85903641 | O16: 99014.08 | P16: 120641.95 | Q16: 106261.39 | R16: 111017.86 | S16: 110627.56 | T16: 115170.15 | U16: 114891.84 | V16: 105537.78 | W16: 93116.44 | X16: 88087.98 | Y16: 83155.08 | Z16: 75326.59 | AA16: 75353662 | AB16: 75326586 | AC16: 68721030 | AD16: 71173495 | AE16: 73096033 | AF16: 74387282 | AG16: 82500293 | AH16: 87734372 | AI16: 87658260 | AJ16: 82875504 | AK16: 82900121 | AL16: 87868954 | AM16: 64619598 | AN16: 64617629 | AO16: 72025254 | AP16: 73129447 | AQ16: 69450211 | AR16: 69796664 | AS16: 70210239 | AT16: 80153645 | AU16: 94182368 | AV16: 101443565
A17: Accounts Recievables | B17: =(B18+B19+B20) -> 0 | C17: =(C18+C19+C20) -> 6806.19 | D17: =(D18+D19+D20) -> -428.76 | E17: =(E18+E19+E20) -> -428.76 | F17: =(F18+F19+F20) -> 4501.59 | G17: =(G18+G19+G20) -> 4501.59 | H17: =(H18+H19+H20) -> 7698.28 | I17: =(I18+I19+I20) -> 7698.28 | ... AV17: =(AV18+AV19+AV20) -> 120186.72
A18: Tax Recoverable | C18: 6806.19 | D18: -428.76 | E18: -428.76 | F18: 4501.59 | G18: 4501.59 | H18: 7698.28 | I18: 7698.28 | J18: 10845.55 | K18: 10845.55 | L18: 10845.55 | M18: 13947.5 | N18: 5044613 | O18: 13947.5 | P18: 5044.61 | Q18: 5044.61 | R18: 7960.02 | S18: 7960.02 | T18: 4258.4 | U18: 4258.4 | V18: 4258.4 | W18: 2915.41 | X18: 2915.41 | Y18: 7173.82 | Z18: 10089.23 | AA18: 5044614 | AB18: 5044613.7 | AC18: 5044613.7 | AD18: 5044613.7 | AE18: 3986441.3 | AF18: 0 | AG18: 329986.72 | AH18: 329986.72 | AI18: 329986.72 | AJ18: 4626676.7 | AK18: 4626676.7 | AL18: 4626676.7 | AM18: 8923366.7 | AO18: 8923366.7 | AP18: 0 | AQ18: 0 | AR18: 0 | AS18: 0 | AT18: 0 | AU18: 120186.72 | AV18: 120186.72
A19: Deffered Tax Assets | C19: 0 | D19: 0 | E19: 0 | F19: 0 | G19: 0 | H19: 0 | I19: 0 | J19: 0 | K19: 0 | L19: 0 | M19: 0 | O19: 0 | P19: 0 | Q19: 0 | R19: 0 | S19: 0 | T19: 0 | U19: 0 | V19: 0 | W19: 0 | X19: 0 | Y19: 0 | Z19: 0 | AB19: 0 | AC19: 0 | AD19: 0 | AE19: 0 | AF19: 0 | AG19: 0 | AH19: 0 | AI19: 0 | AJ19: 0 | AK19: 0 | AL19: 0 | AM19: 0 | AO19: 0 | AP19: 0 | AQ19: 0 | AR19: 0 | AS19: 0 | AT19: 0 | AU19: 0 | AV19: 0
A20: Retirement Benefit Assets | C20: 0 | D20: 0 | E20: 0 | F20: 0 | G20: 0 | H20: 0 | I20: 0 | J20: 0 | K20: 0 | L20: 0 | M20: 0 | O20: 0 | P20: 0 | Q20: 0 | R20: 0 | S20: 0 | T20: 0 | U20: 0 | V20: 0 | W20: 0 | X20: 0 | Y20: 0 | Z20: 0 | AB20: 0 | AC20: 0 | AD20: 0 | AE20: 0 | AF20: 0 | AG20: 0 | AH20: 0 | AI20: 0 | AJ20: 0 | AK20: 0 | AL20: 0 | AM20: 0 | AO20: 0 | AP20: 0 | AQ20: 0 | AR20: 0 | AS20: 0 | AT20: 0 | AU20: 0 | AV20: 0
A21: Property&Equipments&Other Assets | B21: =(B22+B23+B24+B25+B26) -> 3806303 | C21: =(C22+C23+C24+C25+C26) -> 165873.14 | D21: =(D22+D23+D24+D25+D26) -> 139478.98 | E21: =(E22+E23+E24+E25+E26) -> 134978.1 | F21: =(F22+F23+F24+F25+F26) -> 188305.43 | G21: =(G22+G23+G24+G25+G26) -> 136868.63 | H21: =(H22+H23+H24+H25+H26) -> 138808.23 | I21: =(I22+I23+I24+I25+I26) -> 137972.94 | ... AV21: =(AV22+AV23+AV24+AV25+AV26) -> 2.2707614e+08
A22: Investment Properties | C22: 0 | D22: 0 | E22: 0 | F22: 0 | G22: 0 | H22: 0 | I22: 0 | J22: 0 | K22: 0 | L22: 0 | M22: 0 | O22: 0 | P22: 0 | Q22: 0 | R22: 0 | S22: 0 | T22: 0 | U22: 0 | V22: 0 | W22: 0 | X22: 0 | Y22: 0 | Z22: 0 | AB22: 0 | AC22: 0 | AD22: 0 | AE22: 0 | AF22: 0 | AG22: 0 | AH22: 0 | AI22: 0 | AJ22: 0 | AK22: 0 | AL22: 0 | AM22: 0 | AO22: 0 | AP22: 0 | AQ22: 0 | AR22: 0 | AS22: 0 | AT22: 0 | AU22: 0 | AV22: 0
A23: Property and Equipment | B23: 3806303 | C23: 109066.07 | D23: 108792.8 | E23: 108491.82 | F23: 108202.08 | G23: 108014.06 | H23: 107724.2 | I23: 109023.81 | J23: 111726.02 | K23: 111386.02 | L23: 111058.25 | M23: 110720.85 | N23: =110878048 -> 110878048 | O23: 110558.85 | P23: 110271.65 | Q23: 110081.29 | R23: 109775.86 | S23: 109461.41 | T23: 111584.85 | U23: 112504.36 | V23: 111877.42 | W23: 111526.01 | X23: 111311.28 | Y23: 110961.91 | Z23: 110601.93 | AA23: 110601955 | AB23: 1.1027097e+08 | AC23: 1.0997291e+08 | AD23: 1.0964385e+08 | AE23: 1.0933462e+08 | AF23: 1.100231e+08 | AG23: 1.1217761e+08 | AH23: 1.1220486e+08 | AI23: 1.1192003e+08 | AJ23: 1.1158541e+08 | AK23: 1.112405e+08 | AL23: 1.1172903e+08 | AM23: 1.1018137e+08 | AN23: 110181392 | AO23: 1.0966489e+08 | AP23: 1.0919909e+08 | AQ23: 1.0943138e+08 | AR23: 1.0936253e+08 | AS23: 1.0884716e+08 | AT23: 1.1000761e+08 | AU23: 1.1014786e+08 | AV23: 1.1003592e+08
A24: Prepaid Lease Rentals | C24: 0 | D24: 0 | E24: 0 | F24: 0 | G24: 0 | H24: 0 | I24: 0 | J24: 0 | K24: 0 | L24: 0 | M24: 0 | O24: 0 | P24: 0 | Q24: 0 | R24: 0 | S24: 0 | T24: 0 | U24: 0 | V24: 0 | W24: 0 | X24: 0 | Y24: 0 | Z24: 0 | AB24: 0 | AC24: 0 | AD24: 0 | AE24: 0 | AF24: 0 | AG24: 0 | AH24: 0 | AI24: 0 | AJ24: 0 | AK24: 0 | AL24: 0 | AM24: 0 | AO24: 0 | AP24: 0 | AQ24: 0 | AR24: 0 | AS24: 0 | AT24: 0 | AU24: 0 | AV24: 0
A25: Intangible Assets | C25: 4451.05 | D25: 4372.52 | E25: 4293.99 | F25: 4215.47 | G25: 4136.94 | H25: 3884.8 | I25: 3363.7 | J25: 3111.56 | K25: 2851.02 | L25: 2642.93 | M25: 2642.93 | N25: =2642935 -> 2642935 | O25: 2642.93 | P25: 2642.93 | Q25: 2642.93 | R25: 2642.93 | S25: 2642.93 | T25: 4320.67 | U25: 4320.67 | V25: 4320.67 | W25: 4320.67 | X25: 4053.38 | Y25: 4027 | Z25: 3999.75 | AA25: 3999746 | AB25: 3972489.3 | AC25: 3947870.2 | AD25: 3920613.4 | AE25: 3894235.9 | AF25: 3866979 | AG25: 3840601.5 | AH25: 3813344.7 | AI25: 3786087.9 | AJ25: 3759710 | AK25: 4124638.3 | AL25: 3626547.9 | AM25: 3473383.1 | AN25: 3473383 | AO25: 3446126.3 | AP25: 3421507.3 | AQ25: 4601748.6 | AR25: 4541360.1 | AS25: 6263969.4 | AT25: 6153303.4 | AU25: 6038948.6 | AV25: 5924593.7
A26: Other Assets | C26: 52356.02 | D26: 26313.66 | E26: 22192.29 | F26: 75887.88 | G26: 24717.63 | H26: 27199.23 | I26: 25585.43 | J26: 23008.49 | K26: 27642.83 | L26: 24541.89 | M26: 23989.72 | O26: 26575.07 | P26: 30370.36 | Q26: 29088.12 | R26: 26474.01 | S26: 28579.35 | T26: 35216.58 | U26: 36558.79 | V26: 34230.01 | W26: 93711.04 | X26: 43605 | Y26: 41374.17 | Z26: 53457.54 | AB26: 51094552 | AC26: 56087448 | AD26: 61706771 | AE26: 45109413 | AF26: 50824107 | AG26: 61727035 | AH26: 1.0717167e+08 | AI26: 49962054 | AJ26: 58822117 | AK26: 66090539 | AL26: 81203521 | AM26: 69816798 | AO26: 84571319 | AP26: 95168223 | AQ26: 87127046 | AR26: 69346508 | AS26: 92458202 | AT26: 85201085 | AU26: 62988298 | AV26: 1.1111563e+08
A27: Total Assets | B27: =(B21+B17+B14+B8+B7+B4) -> 2.9341168e+08 | C27: =(C21+C17+C14+C8+C7+C4) -> 3166395.3 | D27: =(D21+D17+D14+D8+D7+D4) -> 3158788.5 | E27: =(E21+E17+E14+E8+E7+E4) -> 3099454.1 | F27: =(F21+F17+F14+F8+F7+F4) -> 3168003.6 | G27: =(G21+G17+G14+G8+G7+G4) -> 3250660.8 | H27: =(H21+H17+H14+H8+H7+H4) -> 3277864 | I27: =(I21+I17+I14+I8+I7+I4) -> 3397046.1 | ... AV27: =(AV21+AV17+AV14+AV8+AV7+AV4) -> 5.3896903e+09
A28: Savings and Deposits | B28: =779515+307095 -> 1086610 | C28: 193470.46 | D28: 186159.48 | E28: 254375.76 | F28: 293204.33 | G28: 237548.07 | H28: 240820.5 | I28: 258173.25 | J28: 249034.45 | K28: 230501.03 | L28: 225764.21 | M28: 216919.81 | N28: =240216344 -> 240216344 | O28: 237906.65 | P28: 244165.3 | Q28: 363250.51 | R28: 335920.07 | S28: 302635.39 | T28: 296376.24 | U28: 296183.6 | V28: 264760.15 | W28: 266605.84 | X28: 257457.54 | Y28: 251394.13 | Z28: 256477.4 | AA28: 264135882 | AB28: 264135882 | AC28: 264135882 | AD28: 264135882 | AE28: 264135882 | AF28: 264135882 | AG28: 264135882 | AH28: 264135882 | AI28: 264135882 | AJ28: 264135882 | AK28: 264135882 | AL28: 264135882 | AM28: 264135882 | AN28: 272831599 | AO28: 2.9743839e+08 | AP28: 2.9890028e+08 | AQ28: 4.351719e+08 | AR28: 3.7422596e+08 | AS28: 3.774042e+08 | AT28: 3.7495113e+08 | AU28: 3.7244122e+08 | AV28: 3.4328912e+08
A29: Short Terrm Deposits | B29: =257941+920333.21+11500+708204 -> 1897978.2 | C29: 40185.32 | D29: 40369.84 | E29: 40369.84 | F29: 6526.47 | G29: 42141.29 | H29: 42141.29 | I29: 31714.15 | J29: 33185 | K29: 33185 | L29: 33185 | M29: 33185 | N29: 33185000 | O29: 29000 | P29: 29000 | Q29: 29000 | R29: 25650 | S29: 25650 | T29: 25650 | U29: 19073.89 | V29: 19073.89 | W29: 19073.89 | X29: 9300 | Y29: 9300 | Z29: 9300 | AO29: 0 | AP29: 0 | AQ29: 0 | AR29: 0 | AS29: 0 | AT29: 0 | AU29: 0 | AV29: 0
A30: Non Withdrawable Deposits | B30: =254720687 -> 254720687 | C30: 1945035.4 | D30: 1977350.3 | E30: 2031574.3 | F30: 2045230 | G30: 2077883.4 | H30: 2112548 | I30: 2167038.2 | J30: 2178440.6 | K30: 2210562.7 | L30: 2242846.7 | M30: 2264393.9 | N30: =2251239383+13294425 -> 2264533808 | O30: 2286736.1 | P30: 2314451.3 | Q30: 2362532.9 | R30: 2404573 | S30: 2456518.2 | T30: 2498819.3 | U30: 2526891.5 | V30: 2556991.1 | W30: 2590046.2 | X30: 2628051.8 | Y30: 2653805 | Z30: 2694159.3 | AA30: 2694094259 | AB30: 2694094259 | AC30: 2694094259 | AD30: 2694094259 | AE30: 2694094259 | AF30: 2694094259 | AG30: 2694094259 | AH30: 2694094259 | AI30: 2694094259 | AJ30: 2694094259 | AK30: 2694094259 | AL30: 2694094259 | AM30: 2694094259 | AN30: 3251984807 | AO30: 3.2939133e+09 | AP30: 3.362329e+09 | AQ30: 3.4387689e+09 | AR30: 3.5016863e+09 | AS30: 3.5511053e+09 | AT30: 3.5977609e+09 | AU30: 3.649411e+09 | AV30: 3.6912037e+09
A31: Total Deposit Liabilities | B31: =SUM(B28:B30) -> 2.5770528e+08 | C31: =SUM(C28:C30) -> 2178691.2 | D31: =SUM(D28:D30) -> 2203879.6 | E31: =SUM(E28:E30) -> 2326319.9 | F31: =SUM(F28:F30) -> 2344960.8 | G31: =SUM(G28:G30) -> 2357572.7 | H31: =SUM(H28:H30) -> 2395509.8 | I31: =SUM(I28:I30) -> 2456925.6 | ... AV31: =SUM(AV28:AV30) -> 4.0344928e+09
A32: Tax Payable | B32: 14602 | C32: 0 | D32: 0 | E32: 0 | F32: 0 | G32: 0 | H32: 0 | I32: 0 | J32: 0 | K32: 0 | L32: 0 | M32: 0 | O32: 0 | P32: 0 | Q32: 0 | R32: 0 | S32: 0 | T32: 0 | U32: 0 | V32: 0 | W32: 0 | X32: 0 | Y32: 0 | Z32: 0 | AD32: 0 | AE32: 0 | AF32: 0 | AG32: 0 | AH32: 3966703.3 | AI32: 0 | AJ32: 0 | AK32: 0 | AL32: 0 | AM32: 0 | AN32: 5221111 | AO32: 0 | AP32: 0 | AQ32: 0 | AR32: 0 | AS32: 0 | AT32: 0 | AU32: 0 | AV32: 0
A33: Dividends Payable | C33: 0 | D33: 0 | E33: 0 | F33: 0 | G33: 0 | H33: 0 | I33: 0 | J33: 0 | K33: 0 | L33: 0 | M33: 0 | N33: =233587603+13868910+2413564 -> 249870077 | O33: 0 | P33: 0 | Q33: 0 | R33: 0 | S33: 0 | T33: 0 | U33: 0 | V33: 224885.07 | W33: 213050.42 | X33: 238508.38 | Y33: 275168.39 | Z33: 280308.32 | AA33: 287852165 | AB33: 287852166 | AC33: 287852167 | AD33: 3.1791429e+08 | AE33: 3.7828525e+08 | AF33: 82018662 | AG33: 173759.36 | AH33: 1.7724943e+08 | AI33: 161383260 | AJ33: 184461930 | AK33: 234092200 | AL33: 270460340 | AM33: 3.0807989e+08 | AN33: =344439618+42749380 -> 387188998 | AO33: 3.6557808e+08 | AP33: 3.9891973e+08 | AQ33: 1.0032708e+08 | AR33: 1.3834822e+08 | AS33: 1.7508835e+08 | AT33: 2.1804705e+08 | AU33: 2.4658673e+08 | AV33: 2.7595401e+08
A34: Deferred Tax Liability | C34: 0 | D34: 0 | E34: 0 | F34: 0 | G34: 0 | H34: 0 | I34: 0 | J34: 0 | K34: 0 | L34: 0 | M34: 0 | O34: 0 | P34: 0 | Q34: 0 | R34: 0 | S34: 0 | T34: 0 | U34: 0 | V34: 0 | W34: 0 | X34: 0 | Y34: 0 | Z34: 0 | AD34: 0 | AE34: 0 | AF34: 0 | AG34: 0 | AH34: 0 | AI34: 0 | AJ34: 0 | AK34: 0 | AL34: 0 | AM34: 0 | AO34: 0 | AP34: 0 | AQ34: 0 | AR34: 0 | AS34: 0 | AT34: 0 | AU34: 0 | AV34: 0
A35: Retirement Benefits Liabilty | C35: 0 | D35: 0 | E35: 0 | F35: 0 | G35: 0 | H35: 0 | I35: 0 | J35: 0 | K35: 0 | L35: 0 | M35: 0 | O35: 0 | P35: 0 | Q35: 0 | R35: 0 | S35: 0 | T35: 0 | U35: 0 | V35: 0 | W35: 0 | X35: 0 | Y35: 0 | Z35: 0 | AD35: 0 | AE35: 0 | AF35: 0 | AG35: 0 | AH35: 0 | AI35: 0 | AJ35: 0 | AK35: 0 | AL35: 0 | AM35: 0 | AO35: 0 | AP35: 0 | AQ35: 0 | AR35: 0 | AS35: 0 | AT35: 0 | AU35: 0 | AV35: 0
A36: Other Liabilities | B36: =348519+50000 -> 398519 | C36: 296589.86 | D36: 312712.62 | E36: 132547.52 | F36: 131340.2 | G36: 153270.03 | H36: 184267.37 | I36: 222326.61 | J36: 247837.32 | K36: 276810.27 | L36: 309841.09 | M36: 334588.4 | N36: =8987436+7593662+1429711+3383752+(22529647) -> 43924208 | O36: 366554.49 | P36: 367425.41 | Q36: 143958.96 | R36: 146538.2 | S36: 172038.61 | T36: 171532.99 | U36: 221259.99 | V36: 35163.28 | W36: 39835.68 | X36: 41817.26 | Y36: 41991.36 | Z36: 50581.09 | AA36: =23307476+16247642 -> 39555118 | AB36: =23307476+16247642 -> 39555118 | AC36: =23307476+16247642 -> 39555118 | AD36: 60216648 | AE36: 42686351 | AF36: 69061236 | AG36: 152654546 | AH36: 0 | AI36: 51531221 | AJ36: 57841412 | AK36: 55314342 | AL36: 38865029 | AM36: 38179297 | AN36: =23413633+24422444 -> 47836077 | AO36: 49316020 | AP36: 54416902 | AQ36: 61008874 | AR36: 32350329 | AS36: 29754894 | AT36: 33607793 | AU36: 14028019 | AV36: 16055590
A37: External Borrowings | C37: 0 | D37: 0 | E37: 0 | F37: 0 | G37: 0 | H37: 0 | I37: 0 | J37: 0 | K37: 0 | L37: 0 | M37: 0 | O37: 0 | P37: 0 | Q37: 0 | R37: 0 | S37: 0 | T37: 0 | U37: 0 | V37: 0 | W37: 0 | X37: 0 | Y37: 0 | Z37: 0 | AD37: 0 | AE37: 0 | AF37: 0 | AG37: 0 | AH37: 0 | AI37: 0 | AJ37: 0 | AK37: 0 | AL37: 0 | AM37: 0 | AO37: 0 | AP37: 0 | AQ37: 0 | AR37: 0 | AS37: 0 | AT37: 0 | AU37: 0 | AV37: 0
A38: Total Liabilities | B38: =SUM(B31:B37) -> 2.581184e+08 | C38: =SUM(C31:C37) -> 2475281.1 | D38: =SUM(D31:D37) -> 2516592.2 | E38: =SUM(E31:E37) -> 2458867.4 | F38: =SUM(F31:F37) -> 2476301 | G38: =SUM(G31:G37) -> 2510842.8 | H38: =SUM(H31:H37) -> 2579777.2 | I38: =SUM(I31:I37) -> 2679252.2 | ... AV38: =SUM(AV31:AV37) -> 4.3265024e+09
A39: Share Capital | B39: =7840346+11129788 -> 18970134 | C39: 182486.39 | D39: 183425.59 | E39: 184649.41 | F39: 184691.41 | G39: 185829 | H39: 186876.42 | I39: 188826.42 | J39: 189342.42 | K39: 190311.74 | L39: 190771.94 | M39: 191310.14 | N39: =181839389+9448550 -> 191287939 | O39: 192296.14 | P39: 192676.34 | Q39: 193182.94 | R39: 194221.94 | S39: 195341.47 | T39: 196489.31 | U39: 197709.31 | V39: 198169.31 | W39: 200492.12 | X39: 201143.69 | Y39: 202339.19 | Z39: 204354.23 | AA39: 204354229 | AB39: 204394229 | AC39: 205224229 | AD39: 208952661 | AE39: 210951661 | AF39: 2.1131438e+08 | AG39: 2.1131438e+08 | AH39: 2.1439877e+08 | AI39: 2.1594627e+08 | AJ39: 2.1711901e+08 | AK39: 2.1839841e+08 | AL39: 2.1936741e+08 | AM39: 2.2087941e+08 | AN39: 220601770 | AO39: 2.2184141e+08 | AP39: 2.2346577e+08 | AQ39: 2.2724738e+08 | AR39: 2.2817728e+08 | AS39: 2.2995828e+08 | AT39: 2.3102896e+08 | AU39: 2.3310239e+08 | AV39: 2.3391689e+08
A40: Capital Grants | C40: 0 | D40: 0 | E40: 0 | F40: 0 | G40: 0 | H40: 0 | I40: 0 | J40: 0 | K40: 0 | L40: 0 | M40: 0 | O40: 0 | P40: 0 | Q40: 0 | R40: 0 | S40: 0 | T40: 0 | U40: 0 | V40: 0 | W40: 0 | X40: 0 | Y40: 0 | Z40: 0 | AB40: 0 | AC40: 0 | AD40: 0 | AE40: 0 | AF40: 0 | AG40: 0 | AH40: 0 | AI40: 0 | AJ40: 0 | AK40: 0 | AL40: 0 | AM40: 0 | AO40: 0 | AP40: 0 | AQ40: 0 | AR40: 0 | AS40: 0 | AT40: 0 | AU40: 0 | AV40: 0
A41: Prior Year Retained Earnigs | B41: 10520537 | C41: 361564.84 | D41: 274938.86 | E41: 274938.86 | F41: 274938.86 | G41: 274938.86 | H41: 274938.86 | I41: 274938.86 | J41: 274938.86 | K41: 274938.86 | L41: 274938.86 | M41: 274938.86 | N41: 274955772 | O41: 401563.2 | P41: 361219.33 | Q41: 361219.33 | R41: 361219.33 | S41: 361219.33 | T41: 361219.33 | U41: 361219.33 | V41: 361219.33 | W41: 361219.33 | X41: 361219.33 | Y41: 361219.33 | Z41: 361219.33 | AA41: 361237243 | AB41: 4.7721447e+08 | AC41: 442110065 | AD41: 442110065 | AE41: 442110065 | AF41: 442110065 | AG41: 442110065 | AH41: 442110065 | AI41: 4.2449384e+08 | AJ41: 4.2449384e+08 | AK41: 4.2449384e+08 | AL41: 4.2449384e+08 | AM41: 3.817791e+08 | AN41: =442110173-9866173 -> 432244000 | AO41: 5.1464148e+08 | AP41: 4.6674494e+08 | AQ41: 4.6674494e+08 | AR41: 4.6674494e+08 | AS41: 4.6674494e+08 | AT41: 4.6674494e+08 | AU41: 4.6674494e+08 | AV41: 4.6674494e+08
A42: Current Year Surplus | B42: 17320 | C42: -929.2 | D42: 16583.6 | E42: 10631.9 | F42: 58625.5 | G42: 102430.4 | H42: 56449.79 | I42: 67717.8 | J42: 76242.2 | K42: 87325.8 | L42: 81803.9 | M42: 113519.3 | N42: =157859891-(31571978+37440175+2574774+16879) -> 86256085 | O42: -13751.5 | P42: -25718.6 | Q42: -12777.2 | R42: 36515.3 | S42: 37077.6 | T42: 59180.9 | U42: 35242.5 | V42: 25206.89 | W42: 77640.7 | X42: 83940.8 | Y42: 94579.2 | Z42: 126955.31 | AA42: =159056344-31811269-39505233-3261503 -> 84478339 | AB42: 15529500 | AC42: 16361200 | AD42: 6339279.3 | AE42: 5871320 | AF42: -2066494.3 | AG42: 43633198 | AH42: 37091553 | AI42: 43141259 | AJ42: 48515771 | AK42: 46993755 | AL42: 42563466 | AM42: 1.0554661e+08 | AN42: =121663493-24332699-4074234-5864891-42749380 -> 44642289 | AO42: 12122.9 | AP42: 16148758 | AQ42: 23907360 | AR42: 24144811 | AS42: 28192041 | AT42: 82080067 | AU42: 77451672 | AV42: 77160421
A43: Statutory Reserves | B43: 5785290 | C43: 96887.35 | D43: 113070.67 | E43: 113070.67 | F43: 113070.67 | G43: 113070.67 | H43: 113070.67 | I43: 113070.67 | J43: 113070.67 | K43: 113070.67 | L43: 113070.67 | M43: 113070.67 | N43: =113070667+31571978 -> 144642645 | O43: 113070.67 | P43: 144648.99 | Q43: 144648.99 | R43: 144648.99 | S43: 144648.99 | T43: 144648.99 | U43: 144648.99 | V43: 144648.99 | W43: 144648.99 | X43: 144648.99 | Y43: 144648.99 | Z43: 144648.99 | AA43: 176460261 | AB43: 144648991 | AC43: 176460260 | AD43: 176460260 | AE43: 176460260 | AF43: 176460260 | AG43: 176460260 | AH43: 176460260 | AI43: 176460260 | AJ43: 176460260 | AK43: 176460260 | AL43: 176460260 | AM43: 176460260 | AN43: 200792959 | AO43: 176460260 | AP43: 198645752 | AQ43: 198645752 | AR43: 198645752 | AS43: 198645752 | AT43: 198645752 | AU43: 198645752 | AV43: 198645752
A44: Other Reserves | C44: 0 | D44: 0 | E44: 0 | F44: 0 | G44: 0 | H44: 0 | I44: 0 | J44: 0 | K44: 0 | L44: 0 | M44: 0 | N44: =40906816 -> 40906816 | O44: 0 | P44: 0 | Q44: 0 | R44: 0 | S44: 0 | T44: 0 | U44: 0 | V44: 0 | W44: 0 | X44: 0 | Y44: 0 | Z44: 0 | AA44: 40906816 | AB44: 0 | AC44: 0 | AD44: 0 | AE44: 0 | AF44: 0 | AG44: 0 | AH44: 0 | AI44: 0 | AJ44: 0 | AK44: 0 | AL44: 0 | AM44: 0 | AN44: =40906816 -> 40906816 | AO44: 0 | AP44: 0 | AQ44: 0 | AR44: 0 | AS44: 0 | AT44: 0 | AU44: 0 | AV44: 0
A45: Revaluation Reserves | C45: 48063.37 | D45: 48063.37 | E45: 48063.37 | F45: 48063.37 | G45: 48063.37 | H45: 48063.37 | I45: 48063.37 | J45: 48063.37 | K45: 48063.37 | L45: 48063.37 | M45: 48063.37 | N45: =7156548 -> 7156548 | O45: 48063.37 | P45: 48063.37 | Q45: 48063.37 | R45: 48063.37 | S45: 48063.37 | T45: 48063.37 | U45: 48063.37 | V45: 48063.37 | W45: 48063.37 | X45: 48063.37 | Y45: 48063.37 | Z45: 48063.37 | AA45: 7156548 | AB45: 48063368 | AC45: 48063368 | AD45: 48063368 | AE45: 48063368 | AF45: 48063368 | AG45: 48063368 | AH45: 48063368 | AI45: 48063368 | AJ45: 48063368 | AK45: 52030326 | AL45: 52030326 | AM45: 56082525 | AN45: 7156548 | AO45: 59668815 | AP45: 60357364 | AQ45: 62659030 | AR45: 62659030 | AS45: 62659030 | AT45: 62659030 | AU45: 71918919 | AV45: 55530926
A46: Proposed Dividends | C46: 3041.44 | D46: 6114.19 | E46: 9232.47 | F46: 12312.76 | G46: 15485.78 | H46: 18687.64 | I46: 25176.86 | J46: 28401.36 | K46: 31718.62 | L46: 34974.86 | M46: 38262.03 | N46: =37440175 -> 37440175 | O46: 3204.94 | P46: 6422.54 | Q46: 6422.54 | R46: 12948.13 | S46: 16278.46 | T46: 19648.93 | U46: 23066.09 | V46: 26422.58 | W46: 30073.82 | X46: 33523.95 | Y46: 37095.52 | Z46: 39491.27 | AA46: 39505233 | AB46: 3406570.5 | AC46: 6840807.6 | AD46: 10447633 | AE46: 14063444 | AF46: 17609532 | AG46: 21332877 | AH46: 25013190 | AI46: 28792836 | AJ46: 32567851 | AK46: 32567851 | AL46: 40217358 | AM46: 42749380 | AN46: 9348352 | AO46: 46446737 | AP46: 50198239 | AQ46: 11362639 | AR46: 15211819 | AS46: 19163190 | AT46: 23102896 | AU46: 27195279 | AV46: 31188919
A47: Adjustment To Equity | C47: 0 | D47: 0 | E47: 0 | F47: 0 | G47: 0 | H47: 0 | I47: 0 | J47: 0 | K47: 0 | L47: 0 | M47: 0 | O47: 0 | P47: 0 | Q47: 0 | R47: 0 | S47: 0 | T47: 0 | U47: 0 | V47: 0 | W47: 0 | X47: 0 | Y47: 0 | Z47: 0 | AB47: 0 | AC47: 0 | AD47: 0 | AE47: 0 | AF47: 0 | AG47: 0 | AH47: 0 | AI47: 0 | AJ47: 0 | AK47: 0 | AL47: 0 | AM47: 0 | AO47: 0 | AP47: 0 | AQ47: 0 | AR47: 0 | AS47: 0 | AT47: 0 | AU47: 0 | AV47: 0
A48: Total Equity | B48: =SUM(B39:B47) -> 35293281 | C48: =SUM(C39:C47) -> 691114.19 | D48: =SUM(D39:D47) -> 642196.28 | E48: =SUM(E39:E47) -> 640586.68 | F48: =SUM(F39:F47) -> 691702.57 | G48: =SUM(G39:G47) -> 739818.08 | H48: =SUM(H39:H47) -> 698086.75 | I48: =SUM(I39:I47) -> 717793.98 | ... AV48: =SUM(AV39:AV47) -> 1.0631879e+09
A49: Total Liabilities and Equity | B49: =SUM(B48+B38) -> 2.9341168e+08 | C49: =SUM(C48+C38) -> 3166395.3 | D49: =SUM(D48+D38) -> 3158788.5 | E49: =SUM(E48+E38) -> 3099454.1 | F49: =SUM(F48+F38) -> 3168003.6 | G49: =SUM(G48+G38) -> 3250660.8 | H49: =SUM(H48+H38) -> 3277864 | I49: =SUM(I48+I38) -> 3397046.1 | ... AV49: =SUM(AV48+AV38) -> 5.3896903e+09
B51: =B49-B27 -> -0.81999993 | C51: =C49-C27 -> 0.0099999993 | D51: =D49-D27 -> 0.03 | E51: =E49-E27 -> 0.01 | F51: =F49-F27 -> 0.02 | G51: =G49-G27 -> 0.0099999998 | H51: =H49-H27 -> -0.01 | I51: =I49-I27 -> 0.02 | ... AV51: =AV49-AV27 -> 0

Sheet Evolutitve SCI
B1: "000"
B2: Audited 2019 | C2: 43831 | D2: 43862 | E2: 43891 | F2: 43922 | G2: 43952 | H2: 43983 | I2: 44044 | J2: 44075 | K2: 44105 | L2: 44136 | M2: 44166 | N2: Audited 2020 | O2: 44197 | P2: 44228 | Q2: 44256 | R2: 44287 | S2: 44317 | T2: 44348 | U2: 44378 | V2: 44409 | W2: 44440 | X2: 44470 | Y2: 44501 | Z2: 44531 | AA2: AUDITED 2021 | AB2: 44562 | AC2: 44593 | AD2: 44621 | AE2: 44652 | AF2: 44682 | AG2: 44713 | AH2: 44743 | AI2: 44774 | AJ2: 44805 | AK2: 44835 | AL2: 44866 | AM2: 44896 | AN2: AUDITED 2022 | AO2: 44927 | AP2: 44958 | AQ2: 44986 | AR2: 45017 | AS2: 45047 | AT2: 45078 | AU2: 45108 | AV2: 45139
A3: Financial Income | B3: =B4+B7 -> 34090071 | C3: =C4+C7 -> 29420.2 | D3: =D4+D7 -> 61985.58 | E3: =E4+E7 -> 97033.22 | F3: =F4+F7 -> 186241.79 | G3: =G4+G7 -> 219204.82 | H3: =H4+H7 -> 251569.3 | I3: =I4+I7 -> 331911.58 | ... AV3: =AV4+AV7 -> 4.9090132e+08
A4: Financial Income From Loans Portfolio | B4: =SUM(B5:B6) -> 30319703 | C4: =SUM(C5:C6) -> 27930.98 | D4: =SUM(D5:D6) -> 54999.58 | E4: =SUM(E5:E6) -> 84817.46 | F4: =SUM(F5:F6) -> 112824.84 | G4: =SUM(G5:G6) -> 138803.67 | H4: =SUM(H5:H6) -> 164850.92 | I4: =SUM(I5:I6) -> 218686.3 | ... AV4: =SUM(AV5:AV6) -> 3.1602035e+08
A5: Interest from Loans Portfolio | B5: 29009435 | C5: 27556.48 | D5: 52711.18 | E5: 80152.96 | F5: 107236.44 | G5: 132726.17 | H5: 158047.62 | I5: 210504.7 | J5: 239816.08 | K5: 270226.24 | L5: 298209.19 | M5: 329605.24 | N5: =313623358+15818648 -> 329442006 | O5: 29095.27 | P5: 56168.57 | Q5: 87302.88 | R5: 118136.3 | S5: 147823.89 | T5: 178267.76 | U5: 208794.15 | V5: 208794.15 | W5: 276987.24 | X5: 308149.63 | Y5: 342176.15 | Z5: 372917.87 | AA5: 31487658 | AB5: 31487658 | AC5: 63529.73 | AD5: 95819982 | AE5: 1.2801487e+08 | AF5: 1.6100454e+08 | AG5: 1.9598459e+08 | AH5: 231577996 | AI5: 2.6667779e+08 | AJ5: 3.0230107e+08 | AK5: 3.3654439e+08 | AL5: 3.7183863e+08 | AM5: 4.079927e+08 | AN5: 408125862 | AO5: 35529348 | AP5: 71630081 | AQ5: 1.0984821e+08 | AR5: 1.4542265e+08 | AS5: 1.8481578e+08 | AT5: 2.2142798e+08 | AU5: 2.6430095e+08 | AV5: 3.069356e+08
A6: Fees&Commision on Loan Portfolio | B6: =623888+686380 -> 1310268 | C6: 374.5 | D6: 2288.4 | E6: 4664.5 | F6: 5588.4 | G6: 6077.5 | H6: 6803.3 | I6: 8181.6 | J6: 8674.4 | K6: 9282.2 | L6: 9987.1 | M6: 10897.5 | N6: =10964559+20806578 -> 31771137 | O6: 817.2 | P6: 1646.2 | Q6: 4076.3 | R6: 5087.5 | S6: 5869.9 | T6: 6638.6 | U6: 7737.3 | V6: 8312.6 | W6: 8950.4 | X6: 9743.8 | Y6: 10775.3 | Z6: 11630.3 | AA6: 1178205.6 | AB6: 1178205.6 | AC6: 1788.1 | AD6: 4236571 | AE6: 5203429.3 | AF6: 5871896.5 | AG6: 6578538.2 | AH6: 7363378.8 | AI6: 8274196.8 | AJ6: 9085881.5 | AK6: 10359564 | AL6: 12137161 | AM6: 14467436 | AO6: 1468499 | AP6: 2733633.8 | AQ6: 3098251 | AR6: 4083034.1 | AS6: 5119772.2 | AT6: 6650726.1 | AU6: 7689683.4 | AV6: 9084749.8
A7: Financial Income from Investments | B7: =SUM(B8:B11) -> 3770368 | C7: =SUM(C8:C11) -> 1489.22 | D7: =SUM(D8:D11) -> 6986 | E7: =SUM(E8:E11) -> 12215.76 | F7: =SUM(F8:F11) -> 73416.95 | G7: =SUM(G8:G11) -> 80401.15 | H7: =SUM(H8:H11) -> 86718.38 | I7: =SUM(I8:I11) -> 113225.28 | ... AV7: =SUM(AV8:AV11) -> 1.7488096e+08
A8: Government Securities | C8: 0 | D8: 0 | E8: 0 | F8: 0 | G8: 0 | H8: 0 | I8: 0 | J8: 0 | K8: 0 | L8: 0 | M8: 0 | N8: 0 | O8: 0 | P8: 0 | Q8: 0 | R8: 0 | S8: 0 | T8: 0 | U8: 0 | V8: 0 | W8: 0 | X8: 0 | Y8: 0 | Z8: 0 | AB8: 0 | AC8: 0 | AD8: 0 | AE8: 0 | AF8: 0 | AG8: 0 | AH8: 0 | AI8: 0 | AJ8: 0 | AK8: 0 | AL8: 0 | AM8: 0 | AO8: 0 | AP8: 0 | AQ8: 0 | AR8: 0 | AS8: 0 | AT8: 0 | AU8: 0 | AV8: 0
A9: Deposits with Banks & other Financial Institutions | C9: 0 | D9: 0 | E9: 0 | F9: 0 | G9: 0 | H9: 0 | I9: 0 | J9: 0 | K9: 0 | L9: 0 | M9: 0 | N9: 0 | O9: 0 | P9: 0 | Q9: 0 | R9: 0 | S9: 0 | T9: 0 | U9: 0 | V9: 0 | W9: 0 | X9: 0 | Y9: 0 | Z9: 0 | AA9: =67087378+47961448 -> 115048826 | AB9: 0 | AC9: 0 | AD9: 0 | AE9: 0 | AF9: 0 | AG9: 0 | AH9: 0 | AI9: 0 | AJ9: 0 | AK9: 0 | AL9: 0 | AM9: 0 | AN9: =96765393+50042492 -> 146807885 | AO9: 0 | AP9: 0 | AQ9: 0 | AR9: 0 | AS9: 0 | AT9: 0 | AU9: 0 | AV9: 0
A10: Other Investments | B10: 1255802 | C10: 0 | D10: 5776.27 | E10: 9523.11 | F10: 69979.97 | G10: 74865.62 | H10: 80146.73 | I10: 91534.75 | J10: 96736.99 | K10: 101839.05 | L10: 105888.06 | M10: 109457.8 | N10: =48056583+25426+5057818+56353713 -> 109493540 | O10: 0 | P10: 10524.62 | Q10: 15195.45 | R10: 67539.8 | S10: 72727.87 | T10: 78247.02 | U10: 83611.62 | V10: 89299.33 | W10: 94653.74 | X10: 100448.13 | Y10: 107094.59 | Z10: 115048.83 | AB10: 7388347.1 | AC10: 14514.92 | AD10: 21875757 | AE10: 29441494 | AF10: 30648930 | AG10: 93957764 | AH10: 1.0150256e+08 | AI10: 1.0958698e+08 | AJ10: 1.1804885e+08 | AK10: 1.2754967e+08 | AL10: 1.3659422e+08 | AM10: 1.4677876e+08 | AO10: 10202579 | AP10: 19575990 | AQ10: 30235184 | AR10: 40802577 | AS10: 51202678 | AT10: 1.2853841e+08 | AU10: 1.4394338e+08 | AV10: 1.5794439e+08
A11: Other Operating Income | B11: =231000+2283566 -> 2514566 | C11: 1489.22 | D11: 1209.73 | E11: 2692.65 | F11: 3436.98 | G11: 5535.53 | H11: 6571.65 | I11: 21690.53 | J11: 22924.03 | K11: 24304.62 | L11: 25469.13 | M11: 32005.59 | N11: =2779021+1042767+3905955+104297+455629 -> 8287669 | O11: 876.43 | P11: 2926.32 | Q11: 6699.94 | R11: 8270.3 | S11: 9883.55 | T11: 11193.31 | U11: 12651.87 | V11: 22995.27 | W11: 24813.78 | X11: 26130.32 | Y11: 27747.54 | Z11: 29486.94 | AA11: =90017405-47961448 -> 42055957 | AB11: 552855.63 | AC11: 1957.51 | AD11: 2951912.7 | AE11: 3635563.6 | AF11: 5661977.7 | AG11: 6807840.2 | AH11: 7756174.8 | AI11: 8857340.3 | AJ11: 10479402 | AK11: 11550490 | AL11: 12705533 | AM11: 18852621 | AN11: 45873121 | AO11: 1746220.9 | AP11: 3551220.4 | AQ11: 7682085.7 | AR11: 9539708.3 | AS11: 11970768 | AT11: 11911048 | AU11: 15656451 | AV11: 16936576
A12: Financial Expenses | B12: =SUM(B13:B18) -> 138384 | C12: =SUM(C13:C18) -> 23525.59 | D12: =SUM(D13:D18) -> 45462.8 | E12: =SUM(E13:E18) -> 69909.76 | F12: =SUM(F13:F18) -> 92941.56 | G12: =SUM(G13:G18) -> 119422.38 | H12: =SUM(H13:H18) -> 145581.66 | I12: =SUM(I13:I18) -> 199320.28 | ... AV12: =SUM(AV13:AV18) -> 3.1751517e+08
A13: Interest Expense on Deposits | C13: 20484.15 | D13: 39348.61 | E13: 60677.29 | F13: 80628.8 | G13: 103936.6 | H13: 126894.02 | I13: 174143.42 | J13: 193015.06 | K13: 221026.63 | L13: 246299.48 | M13: 273668.94 | N13: =233587603+13868910+2628623+4796304 -> 254881440 | O13: 23108.37 | P13: 45962.63 | Q13: 69987.94 | R13: 94619.13 | S13: 120511.16 | T13: 123741.87 | U13: 174070.54 | V13: 201215.55 | W13: 228913.75 | X13: 257774.86 | Y13: 286245.52 | Z13: 292462.95 | AA13: 292462951 | AB13: 26601299 | AC13: 53530.55 | AD13: 82320061 | AE13: 1.1074201e+08 | AF13: 1.4101066e+08 | AG13: 1.7267667e+08 | AH13: 2.0380943e+08 | AI13: 2.362702e+08 | AJ13: 2.7083582e+08 | AK13: 3.0642597e+08 | AL13: 3.4196366e+08 | AM13: 3.4607061e+08 | AN13: 346443817 | AO13: 32058914 | AP13: 65400568 | AQ13: 1.0032708e+08 | AR13: 1.3618518e+08 | AS13: 1.7245004e+08 | AT13: 2.0947263e+08 | AU13: 2.4634636e+08 | AV13: 2.8558766e+08
A14: Cost of External Borrowings | C14: 0 | D14: 0 | E14: 0 | F14: 0 | G14: 0 | H14: 0 | I14: 0 | J14: 0 | K14: 0 | L14: 0 | M14: 0 | N14: 0 | O14: 0 | P14: 0 | Q14: 0 | R14: 0 | S14: 0 | T14: 0 | U14: 0 | V14: 0 | W14: 0 | X14: 0 | Y14: 0 | Z14: 0 | AB14: 0 | AC14: 0 | AD14: 0 | AE14: 0 | AF14: 0 | AG14: 0 | AH14: 0 | AI14: 0 | AJ14: 0 | AK14: 0 | AL14: 0 | AM14: 0 | AO14: 0 | AP14: 0 | AQ14: 0 | AR14: 0 | AS14: 0 | AT14: 0 | AU14: 0 | AV14: 0
A15: Dividend Expenses | C15: 3041.44 | D15: 6114.19 | E15: 9232.47 | F15: 12312.76 | G15: 15485.78 | H15: 18687.64 | I15: 25176.86 | J15: 28401.36 | K15: 31721.96 | L15: 34974.86 | M15: 38262.03 | N15: 0 | O15: 3204.94 | P15: 6422.54 | Q15: 9659.15 | R15: 12948.13 | S15: 16278.46 | T15: 19648.93 | U15: 23066.09 | V15: 26422.58 | W15: 30073.82 | X15: 33523.95 | Y15: 37095.52 | Z15: 39491.27 | AB15: 3406570.5 | AC15: 6840.81 | AD15: 10447633 | AE15: 14063444 | AF15: 17609532 | AG15: 21332877 | AH15: 25013190 | AI15: 28792836 | AJ15: 32567851 | AK15: 36399734 | AL15: 40217358 | AM15: 42749380 | AO15: 3697356.8 | AP15: 7448859 | AQ15: 11362369 | AR15: 15211819 | AS15: 19163190 | AT15: 23102896 | AU15: 27195279 | AV15: 31188919
A16: Other Financial Expense | C16: 0 | D16: 0 | E16: 0 | F16: 0 | G16: 0 | H16: 0 | I16: 0 | J16: 0 | K16: 0 | L16: 0 | M16: 0 | N16: 0 | O16: 0 | P16: 0 | Q16: 0 | R16: 0 | S16: 0 | T16: 0 | U16: 0 | V16: 0 | W16: 0 | X16: 0 | Y16: 0 | Z16: 884.79 | AB16: 45465.96 | AC16: 106.22 | AD16: 97109.79 | AE16: 237261.39 | AF16: 317953.45 | AG16: 386008.75 | AH16: 453370.75 | AI16: 556946.25 | AJ16: 623675.53 | AK16: 694617.19 | AL16: 752969.19 | AM16: 860813.15 | AN16: 888057 | AO16: 90702 | AP16: 235502.35 | AQ16: 121836.35 | AR16: 315536.63 | AS16: 348005.08 | AT16: 531072.93 | AU16: 600408.93 | AV16: 738584.11
A17: Fees & Commision Expense | B17: =109986+28398 -> 138384 | C17: 0 | D17: 0 | E17: 0 | F17: 0 | G17: 0 | H17: 0 | I17: 0 | J17: 0 | K17: 0 | L17: 0 | M17: 0 | N17: 0 | O17: 0 | P17: 0 | Q17: 0 | R17: 0 | S17: 0 | T17: 0 | U17: 0 | V17: 0 | W17: 0 | X17: 0 | Y17: 0 | Z17: 0 | AB17: 0 | AC17: 0 | AD17: 0 | AE17: 0 | AF17: 0 | AG17: 0 | AH17: 0 | AI17: 0 | AJ17: 0 | AK17: 0 | AL17: 0 | AM17: 0 | AO17: 0 | AP17: 0 | AQ17: 0 | AR17: 0 | AS17: 0 | AT17: 0 | AU17: 0 | AV17: 0
A18: Other Expenses | C18: 0 | D18: 0 | E18: 0 | F18: 0 | G18: 0 | H18: 0 | I18: 0 | J18: 0 | K18: 0 | L18: 0 | M18: 0 | N18: 0 | O18: 0 | P18: 0 | Q18: 0 | R18: 0 | S18: 0 | T18: 0 | U18: 0 | V18: 0 | W18: 0 | X18: 0 | Y18: 0 | Z18: 0 | AB18: 0 | AC18: 0 | AD18: 0 | AE18: 0 | AF18: 0 | AG18: 0 | AH18: 0 | AI18: 0 | AJ18: 0 | AK18: 0 | AL18: 0 | AM18: 0 | AO18: 0 | AP18: 0 | AQ18: 0 | AR18: 0 | AS18: 0 | AT18: 0 | AU18: 0 | AV18: 0
A19: Net Financial Income | B19: =B3-B12 -> 33951687 | C19: =C3-C12 -> 5894.61 | D19: =D3-D12 -> 16522.78 | E19: =E3-E12 -> 27123.46 | F19: =F3-F12 -> 93300.23 | G19: =G3-G12 -> 99782.44 | H19: =H3-H12 -> 105987.64 | I19: =I3-I12 -> 132591.3 | ... AV19: =AV3-AV12 -> 1.7338615e+08
A20: Allowance for Loan Loss | B20: =B21-B22 -> 19858888 | C20: =C21-C22 -> 1974 | D20: =D21-D22 -> -9320.6 | E20: =E21-E22 -> -2203.7 | F20: =F21-F22 -> 7950.9 | G20: =G21-G22 -> -33114.4 | H20: =H21-H22 -> 14691.9 | I20: =I21-I22 -> 16567.1 | ... AV20: =AV21-AV22 -> 26089903
A21: Provision for Loan Losses | B21: 19858888 | C21: 1974 | D21: 0 | E21: 0 | F21: 7950.9 | G21: 0 | H21: 14691.9 | I21: 16567.1 | J21: 17326.6 | K21: 6766.4 | L21: 14690.7 | M21: -10757.8 | N21: -10841221 | O21: 13027 | P21: 34770 | Q21: 20389.5 | R21: 25146 | S21: 24755.6 | T21: 24755.6 | U21: 29019.9 | V21: 19665.9 | W21: 7244.5 | X21: 2216.1 | Y21: -2716.8 | Z21: -10545.3 | AA21: -10518248 | AB21: -10545310 | AC21: -6605.6 | AD21: -4153090.9 | AE21: -2230552.6 | AF21: -939303.4 | AG21: 7173707.5 | AH21: 12407786 | AI21: 12331674 | AJ21: 7548918.1 | AK21: 7573535.4 | AL21: 12542368 | AM21: -10706988 | AO21: 7405655.6 | AP21: 7405655.6 | AQ21: -5903451.3 | AR21: -5556997.7 | AS21: -5143422.8 | AT21: 4799982.7 | AU21: 18828706 | AV21: 26089903
A22: Value of Loans Recovered | C22: 0 | D22: 9320.6 | E22: 2203.7 | F22: 0 | G22: 33114.4 | H22: 0 | I22: 0 | J22: 0 | K22: 0 | L22: 0 | M22: 0 | N22: 0 | O22: 0 | P22: 0 | Q22: 0 | R22: 0 | S22: 0 | T22: 0 | U22: 0 | V22: 0 | W22: 0 | X22: 0 | Y22: 0 | Z22: 0 | AB22: 0 | AC22: 0 | AD22: 0 | AE22: 0 | AF22: 0 | AG22: 0 | AH22: 0 | AI22: 0 | AJ22: 0 | AK22: 0 | AL22: 0 | AM22: 0 | AO22: 0 | AP22: 0 | AQ22: 0 | AR22: 0 | AS22: 0 | AT22: 0 | AU22: 0 | AV22: 0
A23: Operating Expeses | B23: =SUM(B24:B28) -> 14056548 | C23: =SUM(C24:C28) -> 4849.74 | D23: =SUM(D24:D28) -> 9259.8 | E23: =SUM(E24:E28) -> 18695.19 | F23: =SUM(F24:F28) -> 26723.84 | G23: =SUM(G24:G28) -> 30466.41 | H23: =SUM(H24:H28) -> 34845.96 | I23: =SUM(I24:I28) -> 48306.38 | ... AV23: =SUM(AV24:AV28) -> 70135827
A24: Personel Expenses | B24: =5461132+192375+127300 -> 5780807 | C24: 1702 | D24: 3752.1 | E24: 6141 | F24: 12427.9 | G24: 14214.6 | H24: 16329.7 | I24: 22415.8 | J24: 24701.8 | K24: 26974.9 | L24: 28377.2 | M24: 31011.4 | N24: =22423701+1890459+969721+18680+2077296+32200+3599332+818200 -> 31829589 | O24: 2138.6 | P24: 4491.5 | Q24: 11730.7 | R24: 14274.7 | S24: 18170.7 | T24: 21148.3 | U24: 24084.4 | V24: 26668.3 | W24: 29258.7 | X24: 31829.3 | Y24: 34238.7 | Z24: 37473.8 | AA24: 39627677 | AB24: 2620938 | AC24: 5201.7 | AD24: 13757819 | AE24: 18483484 | AF24: 21461384 | AG24: 24548611 | AH24: 28492716 | AI24: 31715516 | AJ24: 35576164 | AK24: 38702340 | AL24: 42794064 | AM24: 46791541 | AN24: 53961102 | AO24: 3086648.5 | AP24: 6760836 | AQ24: 11247666 | AR24: 15109860 | AS24: 19005634 | AT24: 23909127 | AU24: 27415375 | AV24: 31419810
A25: Governance Expenses | B25: =133506+438192+683920+1371094 -> 2626712 | C25: 165 | D25: 1040.6 | E25: 5565.93 | F25: 5715.93 | G25: 5985.93 | H25: 6315.11 | I25: 6709.11 | J25: 7378.11 | K25: 7714.11 | L25: 8165.71 | M25: 9210.51 | N25: =2243174+2634000+1160217 -> 6037391 | O25: 429.63 | P25: 477 | Q25: 6036.25 | R25: 6232.25 | S25: 6588.25 | T25: 6814.25 | U25: 7121.86 | V25: 8391.86 | W25: 9086.36 | X25: 9329.36 | Y25: 10145.91 | Z25: 10769.47 | AA25: 6427970 | AB25: 120000 | AC25: 515.3 | AD25: 6421123 | AE25: 6829389.8 | AF25: 7321847 | AG25: 7853647 | AH25: 9090640 | AI25: 6102737 | AJ25: 7506487 | AK25: 10081787 | AL25: 10400850 | AM25: 11314010 | AN25: 10121714 | AO25: 343800 | AP25: 718600 | AQ25: 3642301 | AR25: 4528076 | AS25: 4966076 | AT25: 5318076 | AU25: 5807076 | AV25: 6270278
A26: Marketing Expenses | B26: =90080 -> 90080 | C26: 152.86 | D26: 161.36 | E26: 301.16 | F26: 311.16 | G26: 411.16 | H26: 501.16 | I26: 442.36 | J26: 745.36 | K26: 785.36 | L26: 785.36 | M26: 836.79 | N26: 0 | O26: 246.95 | P26: 278.95 | Q26: 533.88 | R26: 533.88 | S26: 563.88 | T26: 563.88 | U26: 573.88 | V26: 965.34 | W26: 982.84 | X26: 1102.84 | Y26: 1102.84 | Z26: 1703.09 | AA26: =532748+763294 -> 1296042 | AB26: 229000 | AC26: 617.99 | AD26: 1367630 | AE26: 1373630 | AF26: 4575426 | AG26: 8391294.9 | AH26: 8460334.9 | AI26: 9048734.9 | AJ26: 9450984.9 | AK26: 9677484.9 | AL26: 9682383.9 | AM26: 10285884 | AN26: 8306151 | AO26: 483060 | AP26: 497060 | AQ26: 1238690 | AR26: 1446690 | AS26: 1692330 | AT26: 1711330 | AU26: 1846330 | AV26: 1962480
A27: Depreciation and Amortization | B27: =543202.33 -> 543202.33 | C27: 525.66 | D27: 877.45 | E27: 1256.96 | F27: 1625.23 | G27: 2017.17 | H27: 2559.18 | I27: 4050.65 | J27: 4633.13 | K27: 5233.68 | L27: 5769.53 | M27: 6106.93 | N27: 0 | O27: 319.17 | P27: 606.37 | Q27: 923.17 | R27: 1228.61 | S27: 1543.05 | T27: 1798.93 | U27: 2128.09 | V27: 2785.02 | W27: 3136.42 | X27: 3765.77 | Y27: 4141.51 | Z27: 4528.76 | AA27: =320927+4207829 -> 4528756 | AB27: 358210.84 | AC27: 680.89 | AD27: 1037211.9 | AE27: 1372815.2 | AF27: 1743849.1 | AG27: 2106710.5 | AH27: 2480764.3 | AI27: 2807748.2 | AJ27: 3168741.1 | AK27: 3665171.3 | AL27: 4636658.2 | AM27: 5337679.2 | AN27: 5337678 | AO27: 543761.2 | AP27: 1034181.9 | AQ27: 1612792.9 | AR27: 2172680.8 | AS27: 2802398.3 | AT27: 3501761.4 | AU27: 4231605.4 | AV27: 4960686.9
A28: Administrative Expenses | B28: =49200+61443+67825+177326+79656+59878+190056.14+30096+50000+85000+137100+427336+143797+15000+53172.19+1793226+29000+259063.86+47571+1260000 -> 5015746.2 | C28: 2304.22 | D28: 3428.29 | E28: 5430.14 | F28: 6643.62 | G28: 7837.55 | H28: 9140.81 | I28: 14688.46 | J28: 15707.73 | K28: 18103.23 | L28: 18686.76 | M28: 23089.71 | N28: =30429990 -> 30429990 | O28: 2065.75 | P28: 3975.29 | Q28: 6791.22 | R28: 7535.88 | S28: 10816.43 | T28: 12151.47 | U28: 17487.64 | V28: 18080.01 | W28: 19067.96 | X28: 20988.86 | Y28: 22961.15 | Z28: 25359.78 | AA28: =31314924-AA27-AA26 -> 25490126 | AB28: 2241391.8 | AC28: 4541.15 | AD28: 7249445.7 | AE28: 9552546.4 | AF28: 12152491 | AG28: 15226013 | AH28: 20900327 | AI28: 22628646 | AJ28: 24120787 | AK28: 25789715 | AL28: 27721778 | AM28: 29841976 | AN28: =39949285-AN26 -> 31643134 | AO28: 1224625.6 | AP28: 1470775.2 | AQ28: 3307083 | AR28: 6290312.6 | AS28: 9632702.9 | AT28: 14101223 | AU28: 21867653 | AV28: 25522572
A29: Net Operating Income | B29: =B19-B20-B23 -> 36251.48 | C29: =C19-C20-C23 -> -929.13 | D29: =D19-D20-D23 -> 16583.58 | E29: =E19-E20-E23 -> 10631.97 | F29: =F19-F20-F23 -> 58625.49 | G29: =G19-G20-G23 -> 102430.43 | H29: =H19-H20-H23 -> 56449.78 | I29: =I19-I20-I23 -> 67717.82 | ... AV29: =AV19-AV20-AV23 -> 77160421
A30: Net Non operating Income/Expense | B30: =B31-B32 -> 0 | C30: =C31-C32 -> 0 | D30: =D31-D32 -> 0 | E30: =E31-E32 -> 0 | F30: =F31-F32 -> 0 | G30: =G31-G32 -> 0 | H30: =H31-H32 -> 0 | I30: =I31-I32 -> 0 | ... AV30: =AV31-AV32 -> 0
A31: Non Operating Income | C31: 0 | D31: 0 | E31: 0 | F31: 0 | G31: 0 | H31: 0 | I31: 0 | J31: 0 | K31: 0 | L31: 0 | M31: 0 | N31: 0 | O31: 0 | P31: 0 | Q31: 0 | R31: 0 | S31: 0 | T31: 0 | U31: 0 | V31: 0 | W31: 0 | X31: 0 | Y31: 0 | Z31: 0 | AA31: 0 | AB31: 0 | AC31: 0 | AD31: 0 | AE31: 0 | AF31: 0 | AG31: 0 | AH31: 0 | AI31: 0 | AJ31: 0 | AK31: 0 | AL31: 0 | AM31: 0 | AN31: 0 | AO31: 0 | AP31: 0 | AQ31: 0 | AR31: 0 | AS31: 0 | AT31: 0 | AU31: 0 | AV31: 0
A32: Non Operating Expense | C32: 0 | D32: 0 | E32: 0 | F32: 0 | G32: 0 | H32: 0 | I32: 0 | J32: 0 | K32: 0 | L32: 0 | M32: 0 | N32: 0 | O32: 0 | P32: 0 | Q32: 0 | R32: 0 | S32: 0 | T32: 0 | U32: 0 | V32: 0 | W32: 0 | X32: 0 | Y32: 0 | Z32: 0 | AA32: 0 | AB32: 0 | AC32: 0 | AD32: 0 | AE32: 0 | AF32: 0 | AG32: 0 | AH32: 0 | AI32: 0 | AJ32: 0 | AK32: 0 | AL32: 0 | AM32: 0 | AN32: 0 | AO32: 0 | AP32: 0 | AQ32: 0 | AR32: 0 | AS32: 0 | AT32: 0 | AU32: 0 | AV32: 0
A33: Net Income(Before Tax & Donations) | B33: =B29+B30 -> 36251.48 | C33: =C29+C30 -> -929.13 | D33: =D29+D30 -> 16583.58 | E33: =E29+E30 -> 10631.97 | F33: =F29+F30 -> 58625.49 | G33: =G29+G30 -> 102430.43 | H33: =H29+H30 -> 56449.78 | I33: =I29+I30 -> 67717.82 | ... AV33: =AV29+AV30 -> 77160421
A34: Taxes | B34: 14602 | C34: 0 | D34: 0 | E34: 0 | F34: 0 | G34: 0 | H34: 0 | I34: 0 | J34: 0 | K34: 0 | L34: 0 | M34: 0 | N34: 8797271 | O34: 0 | P34: 0 | Q34: 0 | R34: 0 | S34: 0 | T34: 0 | U34: 0 | V34: 0 | AA34: 11661643 | AB34: 0 | AC34: 0 | AD34: 0 | AE34: 0 | AF34: 0 | AG34: 0 | AH34: 0 | AI34: 0 | AJ34: 0 | AK34: 0 | AL34: 0 | AM34: 0 | AN34: 22441722 | AO34: 0 | AP34: 0 | AQ34: 0 | AR34: 0 | AS34: 0 | AT34: 0 | AU34: 0 | AV34: 0
A35: Net Income(After Tax Before Donations) | B35: =B33-B34 -> 21649.48 | C35: =C33-C34 -> -929.13 | D35: =D33-D34 -> 16583.58 | E35: =E33-E34 -> 10631.97 | F35: =F33-F34 -> 58625.49 | G35: =G33-G34 -> 102430.43 | H35: =H33-H34 -> 56449.78 | I35: =I33-I34 -> 67717.82 | ... AV35: =AV33-AV34 -> 77160421
A36: Donations | C36: 0 | D36: 0 | E36: 0 | F36: 0 | G36: 0 | H36: 0 | I36: 0 | J36: 0 | K36: 0 | L36: 0 | M36: 0 | N36: 0 | O36: 0 | P36: 0 | Q36: 0 | R36: 0 | S36: 0 | T36: 0 | U36: 0 | V36: 0 | AO36: 0 | AP36: 0 | AQ36: 0 | AR36: 0 | AS36: 0 | AT36: 0 | AU36: 0 | AV36: 0
A37: Net Income/(After Tax & Donations) | B37: =B35-B36 -> 21649.48 | C37: =C35-C36 -> -929.13 | D37: =D35-D36 -> 16583.58 | E37: =E35-E36 -> 10631.97 | F37: =F35-F36 -> 58625.49 | G37: =G35-G36 -> 102430.43 | H37: =H35-H36 -> 56449.78 | I37: =I35-I36 -> 67717.82 | ... AV37: =AV35-AV36 -> 77160421
A39: Total Expenses | B39: =B12+B23 -> 14194932 | C39: =C12+C23 -> 28375.33 | D39: =D12+D23 -> 54722.6 | E39: =E12+E23 -> 88604.95 | F39: =F12+F23 -> 119665.4 | G39: =G12+G23 -> 149888.79 | H39: =H12+H23 -> 180427.62 | I39: =I12+I23 -> 247626.66 | ... AV39: =AV12+AV23 -> 3.8765099e+08
O44: =O37-164292468.04 -> -1.6430622e+08

Sheet Dec 2019 report
A1: STIMA SACCO SOCIETY LIMITED
A2: PERFORMANCE AND COMPLIANCE REPORT AS AT : 31st December , 2019
B3: Prudential Standard | C3: Audited | D3: Returns | F3: Audited 2019 | G3: Aggregate for all Licensed Saccos
C4: 2018 | D4: 30th September , 2019 | E4: 31st December , 2019
A5: A. CAPITAL ADEQUACY
A6: Core Capital | B6: ≥10M | C6: 4057843000 | D6: 3.9340926e+09 | E6: 4.252452e+09 | F6: =F33 -> 35293281 | G6: 8.5755077e+10
A7: Core Capital/Total Assets | B7: ≥10% | C7: 0.12567652 | D7: 0.11408248 | E7: 0.11481094 | F7: =F6/F29 -> 0.12028588 | G7: 0.15609442
A8: Institutional Capital/Total Assets | B8: ≥8% | C8: 0.079393471 | D8: 0.064591681 | E8: 0.067244176 | F8: =F34/F29 -> 0.055632234 | G8: 0.091531093
A9: B. ASSET QUALITY
A10: NPL (Substandard+Doubtful+Loss) | B10: <5% | C10: 0 | D10: 0.054329847 | E10: 0.047637752 | F10: =F35/F32 -> 0 | G10: 0.07434801
A11: Non-Earning Assets | B11: <10% | C11: 0.035863732 | D11: 0.035724114 | E11: 0.037274684 | F11: =F36/F29 -> 0.052726313 | G11: 0.10558073
A12: Equity investments/Deposits | B12: <5% | C12: 0 | D12: 0.024842844 | E12: 0.023590605 | F12: =F38/F31 -> 0 | G12: 0.034793574
A13: Equity investments/Core capital | B13: <40% | C13: 0 | D13: 0.16950928 | E13: 0.1568204 | F13: =F38/F33 -> 0 | G13: 0.15319582
A14: C. EARNINGS RATING
A15: Yield on Gross Loans | C15: 0.15191121 | D15: 0.11822952 | E15: 0.1455451 | F15: =F48/F32 -> 0.12728569 | G15: 0.16355249
A16: Total Expense/Total Income | C16: 0.75439892 | D16: 0.75528666 | E16: 0.7186639 | F16: =F49/F44 -> 0.41639489 | G16: 0.70158636
A17: Net Income/Average Assets (ROA) | C17: 0.0278967 | D17: 0.020089744 | E17: 0.031914696 | F17: =F50/F30 -> 1.3289469e-06 | G17: 0.038444702
A18: Operating Expenses/Financial Income (OPEX) | C18: 0.25221239 | D18: 0.25235898 | E18: 0.24257735 | F18: =F47/F45 -> 0.41401617 | G18: 0.31925833
A19: D. LIQUIDITY
A20: Liquid Assets/Short-term Liabilities | B20: >15% | C20: 0.22714378 | D20: 0.72775006 | E20: 0.53145529 | F20: =F40/F41 -> 0.23756555 | G20: 0.5504023
A21: External Borrowing/Total Assets | B21: <25% | C21: 0.01020404 | D21: 0 | E21: 0 | F21: =F42/F29 -> 0 | G21: 0.03910423
A22: Liquid Assets/Total Assets | C22: 0.060313562 | D22: 0.18011196 | E22: 0.14005067 | F22: =F40/F29 -> 0.20809816 | G22: 0.11043073
A23: E. STRUCTURE/SENSITIVITY TO RISK
A24: Gross loans /Total Assets | B24: 70-80 | C24: 0.79999743 | D24: 0.7800437 | E24: 0.82085193 | F24: =F32/F29 -> 0.81183537 | G24: 0.75950448
A25: Gross loans/Deposits | B25: >100% | C25: 1.0373556 | D25: 1.0020925 | E25: 1.0755191 | F25: =F32/F31 -> 0.92431937 | G25: 1.1050835
A26: Financial Investments/Total Assets | C26: 0.18797701 | D26: 0.034489796 | E26: 0.033529934 | F26: =F38/F29 -> 0 | G26: 0.059615079
A27: Dividends+Interest on Deposits/Total Income | C27: 0.49156615 | D27: 0.49594541 | E27: 0.47078017 | F27: =F46/F44 -> 0 | G27: 0.3152237
A28: F. KEY FINANCIAL STATISTICS | C28: 2015 | D28: 2016 | E28: 2017 | G28: AGGREGATE
A29: Total Assets | C29: 32287995000 | D29: 3.4484633e+10 | E29: 3.7038736e+10 | F29: ='Evolutive SFP'!B27 -> 2.9341168e+08 | G29: 5.4937953e+11
A30: Average Assets | C30: 30426610000 | D30: 3.2935177e+10 | E30: 3.4818536e+10 | F30: =(C29+F29)/2 -> 1.6290703e+10 | G30: 5.2175164e+11
A31: Total Deposits | C31: 24900152000 | D31: 2.6843352e+10 | E31: 2.8268507e+10 | F31: ='Evolutive SFP'!B31 -> 2.5770528e+08 | G31: 3.775789e+11
A32: Gross Loans | C32: 25830313000 | D32: 2.6899521e+10 | E32: 3.0403318e+10 | F32: ='Evolutive SFP'!B15 -> 238201977 | G32: 4.1725622e+11
A33: Core Capital | C33: 4057843000 | D33: 3.9340926e+09 | E33: 4.252452e+09 | F33: =Financials!AS11 -> 35293281 | G33: 8.5755077e+10
A34: Institutional Capital | C34: 2563456000 | D34: 2.2274204e+09 | E34: 2.4906393e+09 | F34: =Financials!AS12 -> 16323147 | G34: 5.0285309e+10
A35: Non-performing Loans | C35: 0 | D35: 1.4614469e+09 | E35: 1.4483457e+09 | G35: 3.1022169e+10
A36: Non-Earning Assets | C36: 1157968000 | D36: 1.231933e+09 | E36: 1.3806072e+09 | F36: =Financials!AS34 -> 15470516 | G36: 5.8003891e+10
A37: Property and Equipment | C37: 320370000 | D37: 3.0385145e+08 | E37: 3.017075e+08 | F37: =Financials!AS35 -> 3806303 | G37: 1.780879e+10
A38: Equity Investments | C38: 0 | D38: 6.6686521e+08 | E38: 6.6687121e+08 | F38: ='Evolutive SFP'!B12+'Evolutive SFP'!B13 -> 0 | G38: 1.3137319e+10
A39: Financial Investments | C39: 4680656000 | D39: 9.2582174e+08 | E39: 9.4784119e+08 | F39: ='Evolutive SFP'!B8 -> 115855 | G39: 2.2509396e+10
A40: Liquid Assets | C40: 1947404000 | D40: 6.2110949e+09 | E40: 5.1872997e+09 | F40: ='Evolutive SFP'!B4+'Evolutive SFP'!B11+'Evolutive SFP'!B10+'Evolutive SFP'!B9 -> 61058429 | G40: 6.0668383e+10
A41: Short-term Liabilities) | C41: 8573442000 | D41: 8.5346539e+09 | E41: 9.7605571e+09 | F41: ='Evolutive SFP'!B29+'Evolutive SFP'!B30+'Evolutive SFP'!B33+'Evolutive SFP'!B34+'Evolutive SFP'!B35+'Evolutive SFP'!B36+'Evolutive SFP'!B37 -> 2.5701718e+08 | G41: 1.1022553e+11
A42: External Borrowing | C42: 329468000 | D42: 0 | E42: 0 | F42: ='Evolutive SFP'!B37 -> 0 | G42: 2.1483063e+10
A43: Average Gross Loans | C43: 24572016000 | D43: 2.585491e+10 | E43: 2.8116816e+10 | F43: =(C43+F32)/2 -> 1.2405109e+10 | G43: 3.9427965e+11
A44: Total Income | C44: 4601812000 | D44: 3.6674475e+09 | E44: 5.2364454e+09 | F44: ='Evolutitve SCI'!B3 -> 34090071 | G44: 8.0901352e+10
A45: Net Financial Income/Loss | C45: 2290844000 | D45: 1.8229867e+09 | E45: 2.7434442e+09 | F45: ='Evolutitve SCI'!B19 -> 33951687 | G45: 4.8226248e+10
A46: Dividends+Interest on Deposits | C46: 2262095000 | D46: 1.8188538e+09 | E46: 2.4652146e+09 | F46: ='Evolutitve SCI'!B14+'Evolutitve SCI'!B16 -> 0 | G46: 2.5502023e+10
A47: Operating Expenses | C47: 1160634000 | D47: 9.2551333e+08 | E47: 1.2702431e+09 | F47: ='Evolutitve SCI'!B23 -> 14056548 | G47: 2.5828431e+10
A48: Interest on Loan portfolio+Fees&Commission on Loan | C48: 3923914000 | D48: 3.1803174e+09 | E48: 4425053884 | F48: ='Evolutitve SCI'!B4 -> 30319703 | G48: 6.8243292e+10
A49: Total Expenses | C49: 3471602000 | D49: 2.7699742e+09 | E49: 3.7632443e+09 | F49: ='Evolutitve SCI'!B23+'Evolutitve SCI'!B12 -> 14194932 | G49: 5.6759285e+10
A50: Net Income | C50: 848802000 | D50: 6.6165929e+08 | E50: 1.111223e+09 | F50: ='Evolutitve SCI'!B37 -> 21649.48 | G50: 2.0058586e+10
A51: G. AREAS OF IMPROVEMENT/REGULATORY CONCERNS
A52: 1
A53: 2
A54: 3
A55: 4
A56: Prepared by:
A58: Checked by:
A60: Approved by:
A62: DISCLAIMER: This report is prepared based on information submitted by the Sacco as at the stated date and may change upon verification by the Authority.

Sheet FORM 4
D1: 42795
B2: CLASSIFICATION | C2: NO. OF A/Cs | D2: OUTSTANDING LOAN PORTFOLIO(Kshs) | E2: REQUIRED PROVISION | F2: REQUIRED PROVISION AMOUNT(Kshs)
B3: Performing | C3: 56175 | D3: 1.993701e+10 | E3: 0 | F3: =D3*E3 -> 0
B4: Watch | C4: 342 | D4: 6.0964609e+08 | E4: 0.05 | F4: =D4*E4 -> 30482304
B5: Substandard | C5: 721 | D5: 5.3176756e+08 | E5: 0.25 | F5: =D5*E5 -> 1.3294189e+08
B6: Doubtful | C6: 182 | D6: 1.3302199e+08 | E6: 0.5 | F6: =D6*E6 -> 66510994
B7: Loss | C7: 285 | D7: 53640300 | E7: 1 | F7: =D7*E7 -> 53640300
B8: subtotal | C8: =SUM(C3:C7) -> 57705 | D8: =SUM(D3:D7) -> 2.1265086e+10 | F8: =SUM(F3:F7) -> 2.8357549e+08
D10: 42887
B11: CLASSIFICATION | C11: NO. OF A/Cs | D11: OUTSTANDING LOAN PORTFOLIO(Kshs) | E11: REQUIRED PROVISION | F11: REQUIRED PROVISION AMOUNT(Kshs)
B12: Performing | C12: 52931 | D12: 2.0932769e+10 | E12: 0.01 | F12: =D12*E12 -> 2.0932769e+08
B13: Watch | C13: 1072 | D13: 6.9302846e+08 | E13: 0.05 | F13: =D13*E13 -> 34651423
B14: Substandard | C14: 237 | D14: 2.1101418e+08 | E14: 0.25 | F14: =D14*E14 -> 52753546
B15: Doubtful | C15: 75 | D15: 31560414 | E15: 0.5 | F15: =D15*E15 -> 15780207
B16: Loss | C16: 16 | D16: 4449341.3 | E16: 1 | F16: =D16*E16 -> 4449341.3
B17: subtotal | C17: =SUM(C12:C16) -> 54331 | D17: =SUM(D12:D16) -> 2.1872821e+10 | E17: 1.81 | F17: =SUM(F12:F16) -> 3.169622e+08
C18: NPL | D18: =SUM(D14:D16) -> 2.4702394e+08
C19: PAR | D19: =D18/D17 -> 0.011293648
D21: 42979
B22: CLASSIFICATION | C22: NO. OF A/Cs | D22: OUTSTANDING LOAN PORTFOLIO(Kshs) | E22: REQUIRED PROVISION | F22: REQUIRED PROVISION AMOUNT(Kshs)
B23: Performing | C23: 48840 | D23: 19551006671 | E23: 0.01
B24: Watch | C24: 2088 | D24: 1.0437061e+09 | E24: 0.05 | F24: =D24*E24 -> 52185307
B25: Substandard | C25: 4389 | D25: 1.5125185e+09 | E25: 0.25 | F25: =D25*E25 -> 3.7812962e+08
B26: Doubtful | C26: 927 | D26: 4.2115024e+08 | E26: 0.5 | F26: =D26*E26 -> 2.1057512e+08
B27: Loss | C27: 1102 | D27: 229316298 | E27: 1 | F27: =D27*E27 -> 229316298
B28: subtotal | C28: =SUM(C23:C27) -> 57346 | D28: =SUM(D23:D27) -> 2.2757698e+10 | F28: =SUM(F23:F27) -> 8.7020635e+08
C29: NPL | D29: =SUM(D25:D27) -> 2.162985e+09
C30: PAR | D30: =D29/D28 -> 0.095044105
D32: 43070
B33: CLASSIFICATION | C33: NO. OF A/Cs | D33: OUTSTANDING LOAN PORTFOLIO(Kshs) | E33: REQUIRED PROVISION | F33: REQUIRED PROVISION AMOUNT(Kshs)
B34: Performing | C34: 50625 | D34: 2.0056569e+10 | E34: 0 | F34: =D34*E34 -> 0
B35: Watch | C35: 1985 | D35: 817339191 | E35: 0.05 | F35: =D35*E35 -> 40866960
B36: Substandard | C36: 4389 | D36: 1.2107046e+09 | E36: 0.25 | F36: =D36*E36 -> 3.0267616e+08
B37: Doubtful | C37: 1012 | D37: 6.4041824e+08 | E37: 0.5 | F37: =D37*E37 -> 3.2020912e+08
B38: Loss | C38: 1121 | D38: 4.8124864e+08 | E38: 1 | F38: =D38*E38 -> 4.8124864e+08
B39: subtotal | C39: =SUM(C34:C38) -> 59132 | D39: =SUM(D34:D38) -> 2.320628e+10 | E39: 1.81 | F39: =SUM(F34:F38) -> 1.1450009e+09
C40: NPL | D40: =SUM(D36:D38) -> 2.3323715e+09
C41: PAR | D41: =D40/D39 -> 0.10050605
D43: Audited 2017
B44: CLASSIFICATION | C44: NO. OF A/Cs | D44: OUTSTANDING LOAN PORTFOLIO(Kshs) | E44: REQUIRED PROVISION | F44: REQUIRED PROVISION AMOUNT(Kshs)
B45: Performing | E45: 0 | F45: =D45*E45 -> 0
B46: Watch | E46: 0.05 | F46: 6739000
B47: Substandard | E47: 0.25 | F47: 54183000 | H47: =SUM(D47:D49)/D50 -> #DIV/0!
B48: Doubtful | E48: 0.5 | F48: 33315000
B49: Loss | E49: 1 | F49: 11377000
B50: subtotal | C50: =SUM(C45:C49) -> 0 | D50: =SUM(D45:D49) -> 0 | E50: 1.81 | F50: =SUM(F45:F49) -> 105614000
D53: 43160
B54: CLASSIFICATION | C54: NO. OF A/Cs | D54: OUTSTANDING LOAN PORTFOLIO(Kshs) | E54: REQUIRED PROVISION | F54: REQUIRED PROVISION AMOUNT(Kshs)
B55: Performing | C55: 47697 | D55: 2.1205447e+10 | E55: 0 | F55: =D55*E55 -> 0
B56: Watch | C56: 26917 | D56: 6.7933412e+08 | E56: 0.05 | F56: =D56*E56 -> 33966706
B57: Substandard | C57: 3726 | D57: 1.003759e+09 | E57: 0.25 | F57: =D57*E57 -> 2.5093975e+08
B58: Doubtful | C58: 2799 | D58: 3.4918089e+08 | E58: 0.5 | F58: =D58*E58 -> 1.7459044e+08
B59: Loss | C59: 1768 | D59: 2.9192251e+08 | E59: 1 | F59: =D59*E59 -> 2.9192251e+08
B60: subtotal | C60: 82907 | D60: 2.3529643e+10 | F60: =SUM(F55:F59) -> 7.5141941e+08 | H60: NPL | I60: =(D57+D58+D59)/D60 -> 0.069905965
D62: 43252
B63: CLASSIFICATION | C63: NO. OF A/Cs | D63: OUTSTANDING LOAN PORTFOLIO(Kshs) | E63: REQUIRED PROVISION | F63: REQUIRED PROVISION AMOUNT(Kshs)
B64: Performing | C64: 49406 | D64: 2.1905084e+10 | E64: 0.01
B65: Watch | C65: 3346 | D65: 6.4285512e+08 | E65: 0.05 | F65: =D65*E65 -> 32142756
B66: Substandard | C66: 4337 | D66: 9.8318969e+08 | E66: 0.25 | F66: =D66*E66 -> 2.4579742e+08
B67: Doubtful | C67: 1945 | D67: 2.0661378e+08 | E67: 0.5 | F67: =D67*E67 -> 1.0330689e+08
B68: Loss | C68: 2419 | D68: 3.5525437e+08 | E68: 1 | F68: =D68*E68 -> 3.5525437e+08
B69: subtotal | C69: =SUM(C64:C68) -> 61453 | D69: =SUM(D64:D68) -> 2.4092997e+10 | F69: =SUM(F64:F68) -> 7.3650143e+08 | H69: NPL | I69: =(D66+D67+D68)/D69 -> 0.064128919
C70: NPL | D70: =SUM(D66:D68) -> 1.5450578e+09
C71: PAR | D71: =D70/D69 -> 0.064128919
D73: 43344
B74: CLASSIFICATION | C74: NO. OF A/Cs | D74: OUTSTANDING LOAN PORTFOLIO(Kshs) | E74: REQUIRED PROVISION | F74: REQUIRED PROVISION AMOUNT(Kshs)
B75: Performing | C75: 52325 | D75: 2.3771723e+10 | E75: 0.01
B76: Watch | C76: 3425 | D76: 5.7053399e+08 | E76: 0.05 | F76: =D76*E76 -> 28526700
B77: Substandard | C77: 3825 | D77: 2.9021825e+08 | E77: 0.25 | F77: =D77*E77 -> 72554563
B78: Doubtful | C78: 1852 | D78: 27072771 | E78: 0.5 | F78: =D78*E78 -> 13536386
B79: Loss | C79: 2325 | D79: 1.5075147e+08 | E79: 1 | F79: =D79*E79 -> 1.5075147e+08
B80: subtotal | C80: 63752 | D80: 2.4810299e+10 | F80: =SUM(F75:F79) -> 2.6536911e+08 | H80: NPL | I80: =(D77+D78+D79)/D80 -> 0.018864847
C81: NPL | D81: =SUM(D77:D79) -> 4.6804249e+08
C82: PAR | D82: =D81/D80 -> 0.018864847
D84: 43435
B85: CLASSIFICATION | C85: NO. OF A/Cs | D85: OUTSTANDING LOAN PORTFOLIO(Kshs) | E85: REQUIRED PROVISION | F85: REQUIRED PROVISION AMOUNT(Kshs)
B86: Performing | E86: 0 | F86: =D86*E86 -> 0
B87: Watch | E87: 0.05 | F87: =D87*E87 -> 0
B88: Substandard | E88: 0.25 | F88: =D88*E88 -> 0
B89: Doubtful | E89: 0.5 | F89: =D89*E89 -> 0
B90: Loss | E90: 1 | F90: =D90*E90 -> 0
B91: subtotal | E91: 1.81 | F91: =SUM(F86:F90) -> 0 | H91: NPL | I91: =(D88+D89+D90)/D91 -> #DIV/0!
C92: NPL | D92: =SUM(D88:D90) -> 0
C93: PAR | D93: =D92/D91 -> #DIV/0!
D95: Audited 2018
B96: CLASSIFICATION | C96: NO. OF A/Cs | D96: OUTSTANDING LOAN PORTFOLIO(Kshs) | E96: REQUIRED PROVISION | F96: REQUIRED PROVISION AMOUNT(Kshs)
B97: Performing | C97: 61808 | D97: 23864790000 | E97: 0 | F97: =D97*E97 -> 0
B98: Watch | C98: 2558 | D98: 543816000 | E98: 0.05 | F98: 6739000
B99: Substandard | C99: 3972 | D99: 838253000 | E99: 0.25 | F99: 54183000
B100: Doubtful | C100: 2510 | D100: 373254000 | E100: 0.5 | F100: 33315000
B101: Loss | C101: 2139 | D101: 210209000 | E101: 1 | F101: 11377000
B102: subtotal | C102: =SUM(C97:C101) -> 72987 | D102: =SUM(D97:D101) -> 25830322000 | E102: 1.81 | F102: =SUM(F97:F101) -> 105614000 | H102: NPL | I102: =(D99+D100+D101)/D102 -> 0.055040584
C103: NPL | D103: =SUM(D99:D101) -> 1421716000
C104: PAR | D104: =D103/D102 -> 0.055040584
D107: 44075
B108: CLASSIFICATION | C108: NO. OF A/Cs | D108: OUTSTANDING LOAN PORTFOLIO(Kshs) | E108: REQUIRED PROVISION | F108: REQUIRED PROVISION AMOUNT(Kshs)
B109: Performing | C109: 56618 | D109: 3.1475041e+10 | E109: 0.01 | F109: =D109*E109 -> 3.1475041e+08
B110: Watch | C110: 2064 | D110: 4.7265764e+08 | E110: 0.05 | F110: =D110*E110 -> 23632882
B111: Substandard | C111: 4931 | D111: 8.0013981e+08 | E111: 0.25 | F111: =D111*E111 -> 2.0003495e+08
B112: Doubtful | C112: 2310 | D112: 1.3164484e+08 | E112: 0.5 | F112: =D112*E112 -> 65822422
...

Sheet CAELS
A1: STIMA SACCO 2017 CAELS
D2: 2013 Audited | E2: 2014 Audited | F2: 2015 Audited | G2: 2016 Audited | H2: 42736 | I2: 42767 | J2: 42795 | K2: 42826 | L2: 42856 | M2: 42887 | N2: 42917 | O2: 42948 | P2: 42979 | Q2: 43009 | R2: 43040 | S2: 43070 | T2: Audited 2017 | U2: 43101 | V2: 43132 | W2: 43160 | X2: 43191 | Y2: 43221 | Z2: 43252 | AA2: 43282 | AB2: 43313 | AC2: 43344 | AD2: 43374 | AE2: 43405 | AF2: 43435 | AG2: Audited 2018 | AH2: 43466 | AI2: 43497 | AJ2: 43525 | AK2: 43556 | AL2: 43586 | AM2: 43617 | AN2: 43647 | AO2: 43678 | AP2: 43709 | AQ2: 43739 | AR2: 43770 | AS2: 43800 | AT2: Audited 2019 | AU2: 43831 | AV2: 43862 | AW2: 43891 | AX2: 43922 | AY2: 43952 | AZ2: 43983 | BA2: 44013 | BB2: 44044 | BC2: 44075 | BD2: 44105 | BE2: 44136 | BF2: 44166 | BG2: Audited 2020 | BH2: 44197 | BI2: 44228 | BJ2: 44256 | BK2: 44287 | BL2: 44317 | BM2: 44348 | BN2: 44378 | BO2: 44409 | BP2: 44440 | BQ2: 44470 | BR2: 44501 | BS2: 44531 | BT2: Audited 2021 | BU2: 44562 | BV2: 44593 | BW2: 44621 | BX2: 44652 | BY2: 44682 | BZ2: 44713 | CA2: 44743 | CB2: 44774 | CC2: 44805 | CD2: 44835 | CE2: 44866 | CF2: 44896 | CG2: Audited 2022 | CH2: 44927 | CI2: 44958 | CJ2: 44986 | CK2: 45017 | CL2: 45047 | CM2: 45078 | CN2: 45108 | CO2: 45139
A3: CAPITAL ADEQUACY | B3: Core Capital | C3: 10 M | D3: =(('Evolutive SFP'!#REF!+'Evolutive SFP'!#REF!+'Evolutive SFP'!#REF!+'Evolutive SFP'!#REF!+'Evolutive SFP'!#REF!+'Evolutive SFP'!#REF!)-'Evolutive SFP'!#REF!)/1000000 -> #REF! | E3: =(('Evolutive SFP'!#REF!+'Evolutive SFP'!#REF!+'Evolutive SFP'!#REF!+'Evolutive SFP'!#REF!+'Evolutive SFP'!#REF!+'Evolutive SFP'!#REF!)-'Evolutive SFP'!#REF!)/1000000 -> #REF! | F3: =(('Evolutive SFP'!#REF!+'Evolutive SFP'!#REF!+'Evolutive SFP'!#REF!+'Evolutive SFP'!#REF!+'Evolutive SFP'!#REF!+'Evolutive SFP'!#REF!)-'Evolutive SFP'!#REF!)/1000000 -> #REF! | G3: =(('Evolutive SFP'!#REF!+'Evolutive SFP'!#REF!+'Evolutive SFP'!#REF!+'Evolutive SFP'!#REF!+'Evolutive SFP'!#REF!+'Evolutive SFP'!#REF!)-'Evolutive SFP'!#REF!)/1000000 -> #REF! | H3: =(('Evolutive SFP'!#REF!+'Evolutive SFP'!#REF!+'Evolutive SFP'!#REF!+'Evolutive SFP'!#REF!+'Evolutive SFP'!#REF!+'Evolutive SFP'!#REF!)-'Evolutive SFP'!#REF!)/1000000 -> #REF! | I3: =(('Evolutive SFP'!#REF!+'Evolutive SFP'!#REF!+'Evolutive SFP'!#REF!+'Evolutive SFP'!#REF!+'Evolutive SFP'!#REF!+'Evolutive SFP'!#REF!)-'Evolutive SFP'!#REF!)/1000000 -> #REF! | J3: =(('Evolutive SFP'!#REF!+'Evolutive SFP'!#REF!+'Evolutive SFP'!#REF!+'Evolutive SFP'!#REF!+'Evolutive SFP'!#REF!+'Evolutive SFP'!#REF!)-'Evolutive SFP'!#REF!)/1000000 -> #REF! | K3: =(('Evolutive SFP'!#REF!+'Evolutive SFP'!#REF!+'Evolutive SFP'!#REF!+'Evolutive SFP'!#REF!+'Evolutive SFP'!#REF!+'Evolutive SFP'!#REF!)-'Evolutive SFP'!#REF!)/1000000 -> #REF! | ... AS3: =(('Evolutive SFP'!#REF!+'Evolutive SFP'!#REF!+'Evolutive SFP'!#REF!+'Evolutive SFP'!#REF!+'Evolutive SFP'!#REF!+'Evolutive SFP'!#REF!)-'Evolutive SFP'!#REF!)/1000000 -> #REF! | AT3: =(('Evolutive SFP'!B39+'Evolutive SFP'!B40+'Evolutive SFP'!B41+'Evolutive SFP'!B42+'Evolutive SFP'!B43+'Evolutive SFP'!B44)-'Evolutive SFP'!B10)/1000000 -> 35.293281 | AU3: =(('Evolutive SFP'!C39+'Evolutive SFP'!C40+'Evolutive SFP'!C41+'Evolutive SFP'!C42+'Evolutive SFP'!C43+'Evolutive SFP'!C44)-'Evolutive SFP'!C10)/1000000 -> 0.64000938 | AV3: =(('Evolutive SFP'!D39+'Evolutive SFP'!D40+'Evolutive SFP'!D41+'Evolutive SFP'!D42+'Evolutive SFP'!D43+'Evolutive SFP'!D44)-'Evolutive SFP'!D10)/1000000 -> 0.58801872 | AW3: =(('Evolutive SFP'!E39+'Evolutive SFP'!E40+'Evolutive SFP'!E41+'Evolutive SFP'!E42+'Evolutive SFP'!E43+'Evolutive SFP'!E44)-'Evolutive SFP'!E10)/1000000 -> 0.58329084 | AX3: =(('Evolutive SFP'!F39+'Evolutive SFP'!F40+'Evolutive SFP'!F41+'Evolutive SFP'!F42+'Evolutive SFP'!F43+'Evolutive SFP'!F44)-'Evolutive SFP'!F10)/1000000 -> 0.63132644 | AY3: =(('Evolutive SFP'!G39+'Evolutive SFP'!G40+'Evolutive SFP'!G41+'Evolutive SFP'!G42+'Evolutive SFP'!G43+'Evolutive SFP'!G44)-'Evolutive SFP'!G10)/1000000 -> 0.67626893 | AZ3: =(('Evolutive SFP'!H39+'Evolutive SFP'!H40+'Evolutive SFP'!H41+'Evolutive SFP'!H42+'Evolutive SFP'!H43+'Evolutive SFP'!H44)-'Evolutive SFP'!H10)/1000000 -> 0.63133574 | BA3: =(('Evolutive SFP'!#REF!+'Evolutive SFP'!#REF!+'Evolutive SFP'!#REF!+'Evolutive SFP'!#REF!+'Evolutive SFP'!#REF!+'Evolutive SFP'!#REF!)-'Evolutive SFP'!#REF!)/1000000 -> #REF! | BB3: =(('Evolutive SFP'!I39+'Evolutive SFP'!I40+'Evolutive SFP'!I41+'Evolutive SFP'!I42+'Evolutive SFP'!I43+'Evolutive SFP'!I44)-'Evolutive SFP'!I10)/1000000 -> 0.64455375 | BC3: =(('Evolutive SFP'!J39+'Evolutive SFP'!J40+'Evolutive SFP'!J41+'Evolutive SFP'!J42+'Evolutive SFP'!J43+'Evolutive SFP'!J44)-'Evolutive SFP'!J10)/1000000 -> 0.65359415 | BD3: =(('Evolutive SFP'!K39+'Evolutive SFP'!K40+'Evolutive SFP'!K41+'Evolutive SFP'!K42+'Evolutive SFP'!K43+'Evolutive SFP'!K44)-'Evolutive SFP'!K10)/1000000 -> 0.66564707 | BE3: =(('Evolutive SFP'!L39+'Evolutive SFP'!L40+'Evolutive SFP'!L41+'Evolutive SFP'!L42+'Evolutive SFP'!L43+'Evolutive SFP'!L44)-'Evolutive SFP'!L10)/1000000 -> 0.66058537 | BF3: =(('Evolutive SFP'!M39+'Evolutive SFP'!M40+'Evolutive SFP'!M41+'Evolutive SFP'!M42+'Evolutive SFP'!M43+'Evolutive SFP'!M44)-'Evolutive SFP'!M10)/1000000 -> 0.69283897 | BG3: =(('Evolutive SFP'!N39+'Evolutive SFP'!N40+'Evolutive SFP'!N41+'Evolutive SFP'!N42+'Evolutive SFP'!N43+'Evolutive SFP'!N44)-'Evolutive SFP'!N10)/1000000 -> 738.04926 | BH3: =(('Evolutive SFP'!O39+'Evolutive SFP'!O40+'Evolutive SFP'!O41+'Evolutive SFP'!O42+'Evolutive SFP'!O43+'Evolutive SFP'!O44)-'Evolutive SFP'!O10)/1000000 -> 0.69317851 | BI3: =(('Evolutive SFP'!P39+'Evolutive SFP'!P40+'Evolutive SFP'!P41+'Evolutive SFP'!P42+'Evolutive SFP'!P43+'Evolutive SFP'!P44)-'Evolutive SFP'!P10)/1000000 -> 0.67282606 | ... CO3: =(('Evolutive SFP'!AV39+'Evolutive SFP'!AV40+'Evolutive SFP'!AV41+'Evolutive SFP'!AV42+'Evolutive SFP'!AV43+'Evolutive SFP'!AV44)-'Evolutive SFP'!AV10)/1000000 -> 976.46801
B4: CCA | C4: Min 10% | D4: =D3/(('Evolutive SFP'!#REF!)/1000000) -> #REF! | E4: =E3/(('Evolutive SFP'!#REF!)/1000000) -> #REF! | F4: =F3/(('Evolutive SFP'!#REF!)/1000000) -> #REF! | G4: =G3/(('Evolutive SFP'!#REF!)/1000000) -> #REF! | H4: =H3/(('Evolutive SFP'!#REF!)/1000000) -> #REF! | I4: =I3/(('Evolutive SFP'!#REF!)/1000000) -> #REF! | J4: =J3/(('Evolutive SFP'!#REF!)/1000000) -> #REF! | K4: =K3/(('Evolutive SFP'!#REF!)/1000000) -> #REF! | ... AS4: =AS3/(('Evolutive SFP'!#REF!)/1000000) -> #REF! | AT4: =AT3/(('Evolutive SFP'!B27)/1000000) -> 0.12028588 | AU4: =AU3/(('Evolutive SFP'!C27)/1000000) -> 0.20212555 | AV4: =AV3/(('Evolutive SFP'!D27)/1000000) -> 0.18615324 | AW4: =AW3/(('Evolutive SFP'!E27)/1000000) -> 0.18819148 | AX4: =AX3/(('Evolutive SFP'!F27)/1000000) -> 0.19928211 | AY4: =AY3/(('Evolutive SFP'!G27)/1000000) -> 0.20804045 | AZ4: =AZ3/(('Evolutive SFP'!H27)/1000000) -> 0.19260584 | BA4: =BA3/(('Evolutive SFP'!#REF!)/1000000) -> #REF! | BB4: =BB3/(('Evolutive SFP'!I27)/1000000) -> 0.18973948 | BC4: =BC3/(('Evolutive SFP'!J27)/1000000) -> 0.19007808 | BD4: =BD3/(('Evolutive SFP'!K27)/1000000) -> 0.1903759 | BE4: =BE3/(('Evolutive SFP'!L27)/1000000) -> 0.18580505 | BF4: =BF3/(('Evolutive SFP'!M27)/1000000) -> 0.19095671 | BG4: =BG3/(('Evolutive SFP'!N27)/1000000) -> 0.20401917 | BH4: =BH3/(('Evolutive SFP'!O27)/1000000) -> 0.18915303 | BI4: =BI3/(('Evolutive SFP'!P27)/1000000) -> 0.18271629 | ... CO4: =CO3/(('Evolutive SFP'!AV27)/1000000) -> 0.18117331
B5: CCD | C5: Min 8% | D5: =D3/('Evolutive SFP'!#REF!/1000000) -> #REF! | E5: =E3/('Evolutive SFP'!#REF!/1000000) -> #REF! | F5: =F3/('Evolutive SFP'!#REF!/1000000) -> #REF! | G5: =G3/('Evolutive SFP'!#REF!/1000000) -> #REF! | H5: =H3/('Evolutive SFP'!#REF!/1000000) -> #REF! | I5: =I3/('Evolutive SFP'!#REF!/1000000) -> #REF! | J5: =J3/('Evolutive SFP'!#REF!/1000000) -> #REF! | K5: =K3/('Evolutive SFP'!#REF!/1000000) -> #REF! | ... AS5: =AS3/('Evolutive SFP'!#REF!/1000000) -> #REF! | AT5: =AT3/('Evolutive SFP'!B31/1000000) -> 0.13695211 | AU5: =AU3/('Evolutive SFP'!C31/1000000) -> 0.29375864 | AV5: =AV3/('Evolutive SFP'!D31/1000000) -> 0.26681073 | AW5: =AW3/('Evolutive SFP'!E31/1000000) -> 0.25073544 | AX5: =AX3/('Evolutive SFP'!F31/1000000) -> 0.26922686 | AY5: =AY3/('Evolutive SFP'!G31/1000000) -> 0.28684966 | AZ5: =AZ3/('Evolutive SFP'!H31/1000000) -> 0.26354963 | BA5: =BA3/('Evolutive SFP'!#REF!/1000000) -> #REF! | BB5: =BB3/('Evolutive SFP'!I31/1000000) -> 0.26234159 | BC5: =BC3/('Evolutive SFP'!J31/1000000) -> 0.26561741 | BD5: =BD3/('Evolutive SFP'!K31/1000000) -> 0.26902997 | BE5: =BE3/('Evolutive SFP'!L31/1000000) -> 0.26404446 | BF5: =BF3/('Evolutive SFP'!M31/1000000) -> 0.27553761 | BG5: =BG3/('Evolutive SFP'!N31/1000000) -> 0.29080698 | BH5: =BH3/('Evolutive SFP'!O31/1000000) -> 0.27144694 | BI5: =BI3/('Evolutive SFP'!P31/1000000) -> 0.26001768 | ... CO5: =CO3/('Evolutive SFP'!AV31/1000000) -> 0.24202993
B6: ICA | C6: Min 8% | D6: =((D3*1000000)-'Evolutive SFP'!#REF!)/'Evolutive SFP'!#REF! -> #REF! | E6: =((E3*1000000)-'Evolutive SFP'!#REF!)/'Evolutive SFP'!#REF! -> #REF! | F6: =((F3*1000000)-'Evolutive SFP'!#REF!)/'Evolutive SFP'!#REF! -> #REF! | G6: =((G3*1000000)-'Evolutive SFP'!#REF!)/'Evolutive SFP'!#REF! -> #REF! | H6: =((H3*1000000)-'Evolutive SFP'!#REF!)/'Evolutive SFP'!#REF! -> #REF! | I6: =((I3*1000000)-'Evolutive SFP'!#REF!)/'Evolutive SFP'!#REF! -> #REF! | J6: =((J3*1000000)-'Evolutive SFP'!#REF!)/'Evolutive SFP'!#REF! -> #REF! | K6: =((K3*1000000)-'Evolutive SFP'!#REF!)/'Evolutive SFP'!#REF! -> #REF! | ... AS6: =((AS3*1000000)-'Evolutive SFP'!#REF!)/'Evolutive SFP'!#REF! -> #REF! | AT6: =((AT3*1000000)-'Evolutive SFP'!B39)/'Evolutive SFP'!B27 -> 0.055632234 | AU6: =((AU3*1000000)-'Evolutive SFP'!C39)/'Evolutive SFP'!C27 -> 0.14449333 | AV6: =((AV3*1000000)-'Evolutive SFP'!D39)/'Evolutive SFP'!D27 -> 0.12808491 | AW6: =((AW3*1000000)-'Evolutive SFP'!E39)/'Evolutive SFP'!E27 -> 0.12861666 | AX6: =((AX3*1000000)-'Evolutive SFP'!F39)/'Evolutive SFP'!F27 -> 0.14098312 | AY6: =((AY3*1000000)-'Evolutive SFP'!G39)/'Evolutive SFP'!G27 -> 0.15087392 | AZ6: =((AZ3*1000000)-'Evolutive SFP'!H39)/'Evolutive SFP'!H27 -> 0.13559419 | BA6: =((BA3*1000000)-'Evolutive SFP'!#REF!)/'Evolutive SFP'!#REF! -> #REF! | BB6: =((BB3*1000000)-'Evolutive SFP'!I39)/'Evolutive SFP'!I27 -> 0.134154 | BC6: =((BC3*1000000)-'Evolutive SFP'!J39)/'Evolutive SFP'!J27 -> 0.13501356 | BD6: =((BD3*1000000)-'Evolutive SFP'!K39)/'Evolutive SFP'!K27 -> 0.1359465 | BE6: =((BE3*1000000)-'Evolutive SFP'!L39)/'Evolutive SFP'!L27 -> 0.13214599 | BF6: =((BF3*1000000)-'Evolutive SFP'!M39)/'Evolutive SFP'!M27 -> 0.1382288 | BG6: =((BG3*1000000)-'Evolutive SFP'!N39)/'Evolutive SFP'!N27 -> 0.15114139 | BH6: =((BH3*1000000)-'Evolutive SFP'!O39)/'Evolutive SFP'!O27 -> 0.13667968 | BI6: =((BI3*1000000)-'Evolutive SFP'!P39)/'Evolutive SFP'!P27 -> 0.13039206 | ... CO6: =((CO3*1000000)-'Evolutive SFP'!AV39)/'Evolutive SFP'!AV27 -> 0.1377725
A7: ASSET QUALITY | B7: A/LNPL30 | F7: 0.36 | G7: 0.52149977 | J7: ='Evolutive SFP'!#REF!/('FORM 4'!D5+'FORM 4'!D6+'FORM 4'!D7) -> #REF! | M7: ='Evolutive SFP'!#REF!/('FORM 4'!D14+'FORM 4'!D15+'FORM 4'!D16) -> #REF! | P7: ='Evolutive SFP'!#REF!/('FORM 4'!D25+'FORM 4'!D26+'FORM 4'!D27) -> #REF! | S7: ='Evolutive SFP'!#REF!/('FORM 4'!D36+'FORM 4'!D37+'FORM 4'!D38) -> #REF! | T7: ='Evolutive SFP'!#REF!/('FORM 4'!E36+'FORM 4'!E37+'FORM 4'!E38) -> #REF! | U7: ='Evolutive SFP'!#REF!/('FORM 4'!F36+'FORM 4'!F37+'FORM 4'!F38) -> #REF! | V7: ='Evolutive SFP'!#REF!/('FORM 4'!G36+'FORM 4'!G37+'FORM 4'!G38) -> #REF! | W7: ='Evolutive SFP'!#REF!/('FORM 4'!H36+'FORM 4'!H37+'FORM 4'!H38) -> #REF! | X7: ='Evolutive SFP'!#REF!/('FORM 4'!I36+'FORM 4'!I37+'FORM 4'!I38) -> #REF! | Y7: ='Evolutive SFP'!#REF!/('FORM 4'!J36+'FORM 4'!J37+'FORM 4'!J38) -> #REF! | Z7: ='Evolutive SFP'!#REF!/('FORM 4'!#REF!+'FORM 4'!#REF!+'FORM 4'!#REF!) -> #REF! | AA7: ='Evolutive SFP'!#REF!/('FORM 4'!K36+'FORM 4'!K37+'FORM 4'!K38) -> #REF! | AB7: ='Evolutive SFP'!#REF!/('FORM 4'!L36+'FORM 4'!L37+'FORM 4'!L38) -> #REF! | AC7: ='Evolutive SFP'!#REF!/('FORM 4'!M36+'FORM 4'!M37+'FORM 4'!M38) -> #REF! | AD7: ='Evolutive SFP'!#REF!/('FORM 4'!N36+'FORM 4'!N37+'FORM 4'!N38) -> #REF! | AE7: ='Evolutive SFP'!#REF!/('FORM 4'!O36+'FORM 4'!O37+'FORM 4'!O38) -> #REF! | AF7: ='Evolutive SFP'!#REF!/('FORM 4'!P36+'FORM 4'!P37+'FORM 4'!P38) -> #REF! | AG7: ='Evolutive SFP'!#REF!/('FORM 4'!Q36+'FORM 4'!Q37+'FORM 4'!Q38) -> #REF! | AH7: ='Evolutive SFP'!#REF!/('FORM 4'!R36+'FORM 4'!R37+'FORM 4'!R38) -> #REF! | ... AP7: ='Evolutive SFP'!#REF!/('FORM 4'!Z36+'FORM 4'!Z37+'FORM 4'!Z38) -> #REF!
B8: NPL30 | F8: 0.02 | G8: 0.051294614 | J8: =('FORM 4'!D5+'FORM 4'!D6+'FORM 4'!D7)/'Evolutive SFP'!#REF! -> #REF! | M8: =('FORM 4'!D14+'FORM 4'!D15+'FORM 4'!D16)/'Evolutive SFP'!#REF! -> #REF! | P8: =('FORM 4'!D25+'FORM 4'!D26+'FORM 4'!D27)/'Evolutive SFP'!#REF! -> #REF! | S8: =('FORM 4'!D36+'FORM 4'!D37+'FORM 4'!D38)/'Evolutive SFP'!#REF! -> #REF! | T8: =('FORM 4'!E36+'FORM 4'!E37+'FORM 4'!E38)/'Evolutive SFP'!#REF! -> #REF! | U8: =('FORM 4'!F36+'FORM 4'!F37+'FORM 4'!F38)/'Evolutive SFP'!#REF! -> #REF! | V8: =('FORM 4'!G36+'FORM 4'!G37+'FORM 4'!G38)/'Evolutive SFP'!#REF! -> #REF! | W8: =('FORM 4'!H36+'FORM 4'!H37+'FORM 4'!H38)/'Evolutive SFP'!#REF! -> #REF! | X8: =('FORM 4'!I36+'FORM 4'!I37+'FORM 4'!I38)/'Evolutive SFP'!#REF! -> #REF! | Y8: =('FORM 4'!J36+'FORM 4'!J37+'FORM 4'!J38)/'Evolutive SFP'!#REF! -> #REF! | Z8: =('FORM 4'!#REF!+'FORM 4'!#REF!+'FORM 4'!#REF!)/'Evolutive SFP'!#REF! -> #REF! | AA8: =('FORM 4'!K36+'FORM 4'!K37+'FORM 4'!K38)/'Evolutive SFP'!#REF! -> #REF! | AB8: =('FORM 4'!L36+'FORM 4'!L37+'FORM 4'!L38)/'Evolutive SFP'!#REF! -> #REF! | AC8: =('FORM 4'!M36+'FORM 4'!M37+'FORM 4'!M38)/'Evolutive SFP'!#REF! -> #REF! | AD8: =('FORM 4'!N36+'FORM 4'!N37+'FORM 4'!N38)/'Evolutive SFP'!#REF! -> #REF! | AE8: =('FORM 4'!O36+'FORM 4'!O37+'FORM 4'!O38)/'Evolutive SFP'!#REF! -> #REF! | AF8: =('FORM 4'!P36+'FORM 4'!P37+'FORM 4'!P38)/'Evolutive SFP'!#REF! -> #REF! | AG8: =('FORM 4'!Q36+'FORM 4'!Q37+'FORM 4'!Q38)/'Evolutive SFP'!#REF! -> #REF! | AH8: =('FORM 4'!R36+'FORM 4'!R37+'FORM 4'!R38)/'Evolutive SFP'!#REF! -> #REF! | ... AS8: =('FORM 4'!AC36+'FORM 4'!AC37+'FORM 4'!AC38)/'Evolutive SFP'!#REF! -> #REF! | AT8: =('FORM 4'!AD36+'FORM 4'!AD37+'FORM 4'!AD38)/'Evolutive SFP'!B15 -> 0 | AU8: =('FORM 4'!AE36+'FORM 4'!AE37+'FORM 4'!AE38)/'Evolutive SFP'!C15 -> 0 | AV8: =('FORM 4'!AF36+'FORM 4'!AF37+'FORM 4'!AF38)/'Evolutive SFP'!D15 -> 0 | AW8: =('FORM 4'!AG36+'FORM 4'!AG37+'FORM 4'!AG38)/'Evolutive SFP'!E15 -> 0 | AX8: =('FORM 4'!AH36+'FORM 4'!AH37+'FORM 4'!AH38)/'Evolutive SFP'!F15 -> 0 | AY8: =('FORM 4'!AI36+'FORM 4'!AI37+'FORM 4'!AI38)/'Evolutive SFP'!G15 -> 0 | AZ8: =('FORM 4'!AJ36+'FORM 4'!AJ37+'FORM 4'!AJ38)/'Evolutive SFP'!H15 -> 0 | BA8: =('FORM 4'!AK36+'FORM 4'!AK37+'FORM 4'!AK38)/'Evolutive SFP'!#REF! -> #REF! | BB8: =('FORM 4'!AL36+'FORM 4'!AL37+'FORM 4'!AL38)/'Evolutive SFP'!I15 -> 0 | BC8: =('FORM 4'!AM36+'FORM 4'!AM37+'FORM 4'!AM38)/'Evolutive SFP'!J15 -> 0 | BD8: =('FORM 4'!AN36+'FORM 4'!AN37+'FORM 4'!AN38)/'Evolutive SFP'!K15 -> 0 | BE8: =('FORM 4'!AO36+'FORM 4'!AO37+'FORM 4'!AO38)/'Evolutive SFP'!L15 -> 0 | BF8: =('FORM 4'!AP36+'FORM 4'!AP37+'FORM 4'!AP38)/'Evolutive SFP'!M15 -> 0 | BG8: =('FORM 4'!AQ36+'FORM 4'!AQ37+'FORM 4'!AQ38)/'Evolutive SFP'!N15 -> 0 | BH8: =('FORM 4'!AR36+'FORM 4'!AR37+'FORM 4'!AR38)/'Evolutive SFP'!O15 -> 0 | BI8: =('FORM 4'!AS36+'FORM 4'!AS37+'FORM 4'!AS38)/'Evolutive SFP'!P15 -> 0 | ... CO8: =('FORM 4'!BY36+'FORM 4'!BY37+'FORM 4'!BY38)/'Evolutive SFP'!AV15 -> 0
A9: EARNINGS | B9: ROA | E9: ='Evolutitve SCI'!#REF!/(('Evolutive SFP'!#REF!+'Evolutive SFP'!#REF!)/2) -> #REF! | H9: ='Evolutitve SCI'!#REF!/(('Evolutive SFP'!#REF!+'Evolutive SFP'!#REF!)/2) -> #REF! | I9: ='Evolutitve SCI'!#REF!/(('Evolutive SFP'!#REF!+'Evolutive SFP'!#REF!)/2) -> #REF! | J9: ='Evolutitve SCI'!#REF!/(('Evolutive SFP'!#REF!+'Evolutive SFP'!#REF!)/2) -> #REF! | K9: ='Evolutitve SCI'!#REF!/(('Evolutive SFP'!#REF!+'Evolutive SFP'!#REF!)/2) -> #REF! | L9: ='Evolutitve SCI'!#REF!/(('Evolutive SFP'!#REF!+'Evolutive SFP'!#REF!)/2) -> #REF! | M9: ='Evolutitve SCI'!#REF!/(('Evolutive SFP'!#REF!+'Evolutive SFP'!#REF!)/2) -> #REF! | N9: ='Evolutitve SCI'!#REF!/(('Evolutive SFP'!#REF!+'Evolutive SFP'!#REF!)/2) -> #REF! | O9: ='Evolutitve SCI'!#REF!/(('Evolutive SFP'!#REF!+'Evolutive SFP'!#REF!)/2) -> #REF! | ... AS9: ='Evolutitve SCI'!#REF!/(('Evolutive SFP'!#REF!+'Evolutive SFP'!#REF!)/2) -> #REF! | AT9: ='Evolutitve SCI'!B33/(('Evolutive SFP'!#REF!+'Evolutive SFP'!B27)/2) -> #REF! | AU9: ='Evolutitve SCI'!C33/(('Evolutive SFP'!B27+'Evolutive SFP'!C27)/2) -> -6.2656689e-06 | AV9: ='Evolutitve SCI'!D33/(('Evolutive SFP'!C27+'Evolutive SFP'!D27)/2) -> 0.0052436675 | AW9: ='Evolutitve SCI'!E33/(('Evolutive SFP'!D27+'Evolutive SFP'!E27)/2) -> 0.0033977494 | AX9: ='Evolutitve SCI'!F33/(('Evolutive SFP'!E27+'Evolutive SFP'!F27)/2) -> 0.018707901 | AY9: ='Evolutitve SCI'!G33/(('Evolutive SFP'!F27+'Evolutive SFP'!G27)/2) -> 0.031916431 | AZ9: ='Evolutitve SCI'!H33/(('Evolutive SFP'!G27+'Evolutive SFP'!H27)/2) -> 0.017293273 | BA9: ='Evolutitve SCI'!#REF!/(('Evolutive SFP'!H27+'Evolutive SFP'!#REF!)/2) -> #REF! | BB9: ='Evolutitve SCI'!I33/(('Evolutive SFP'!#REF!+'Evolutive SFP'!I27)/2) -> #REF! | BC9: ='Evolutitve SCI'!J33/(('Evolutive SFP'!I27+'Evolutive SFP'!J27)/2) -> 0.022307427 | BD9: ='Evolutitve SCI'!K33/(('Evolutive SFP'!J27+'Evolutive SFP'!K27)/2) -> 0.025183931 | BE9: ='Evolutitve SCI'!L33/(('Evolutive SFP'!K27+'Evolutive SFP'!L27)/2) -> 0.02320102 | BF9: ='Evolutitve SCI'!M33/(('Evolutive SFP'!L27+'Evolutive SFP'!M27)/2) -> 0.03077537 | BG9: ='Evolutitve SCI'!N33/(('Evolutive SFP'!M27+'Evolutive SFP'!N27)/2) -> 0.09204586 | BH9: ='Evolutitve SCI'!O33/(('Evolutive SFP'!N27+'Evolutive SFP'!O27)/2) -> -7.5949741e-06 | BI9: ='Evolutitve SCI'!P33/(('Evolutive SFP'!O27+'Evolutive SFP'!P27)/2) -> -0.0070011099 | BJ9: ='Evolutitve SCI'!Q33/(('Evolutive SFP'!P27+'Evolutive SFP'!Q27)/2) -> -0.0034901641 | ... CO9: ='Evolutitve SCI'!AV33/(('Evolutive SFP'!AU27+'Evolutive SFP'!AV27)/2) -> 0.014359146
B10: Cost Income ratio | D10: ='Evolutitve SCI'!#REF!/'Evolutitve SCI'!#REF! -> #REF! | E10: ='Evolutitve SCI'!#REF!/'Evolutitve SCI'!#REF! -> #REF! | F10: ='Evolutitve SCI'!#REF!/'Evolutitve SCI'!#REF! -> #REF! | G10: ='Evolutitve SCI'!#REF!/'Evolutitve SCI'!#REF! -> #REF! | H10: ='Evolutitve SCI'!#REF!/'Evolutitve SCI'!#REF! -> #REF! | I10: ='Evolutitve SCI'!#REF!/'Evolutitve SCI'!#REF! -> #REF! | J10: ='Evolutitve SCI'!#REF!/'Evolutitve SCI'!#REF! -> #REF! | K10: ='Evolutitve SCI'!#REF!/'Evolutitve SCI'!#REF! -> #REF! | ... AS10: ='Evolutitve SCI'!#REF!/'Evolutitve SCI'!#REF! -> #REF! | AT10: ='Evolutitve SCI'!B23/'Evolutitve SCI'!B19 -> 0.41401617 | AU10: ='Evolutitve SCI'!C23/'Evolutitve SCI'!C19 -> 0.82274145 | AV10: ='Evolutitve SCI'!D23/'Evolutitve SCI'!D19 -> 0.56042627 | AW10: ='Evolutitve SCI'!E23/'Evolutitve SCI'!E19 -> 0.68926273 | AX10: ='Evolutitve SCI'!F23/'Evolutitve SCI'!F19 -> 0.28642845 | AY10: ='Evolutitve SCI'!G23/'Evolutitve SCI'!G19 -> 0.30532837 | AZ10: ='Evolutitve SCI'!H23/'Evolutitve SCI'!H19 -> 0.32877381 | BA10: ='Evolutitve SCI'!#REF!/'Evolutitve SCI'!#REF! -> #REF! | BB10: ='Evolutitve SCI'!I23/'Evolutitve SCI'!I19 -> 0.36432541 | BC10: ='Evolutitve SCI'!J23/'Evolutitve SCI'!J19 -> 0.36232733 | BD10: ='Evolutitve SCI'!K23/'Evolutitve SCI'!K19 -> 0.38462999 | BE10: ='Evolutitve SCI'!L23/'Evolutitve SCI'!L19 -> 0.39035188 | BF10: ='Evolutitve SCI'!M23/'Evolutitve SCI'!M19 -> 0.41318125 | BG10: ='Evolutitve SCI'!N23/'Evolutitve SCI'!N19 -> 0.30474357 | BH10: ='Evolutitve SCI'!O23/'Evolutitve SCI'!O19 -> 1.1618803 | BI10: ='Evolutitve SCI'!P23/'Evolutitve SCI'!P19 -> 0.52059475 | ... CO10: ='Evolutitve SCI'!AV23/'Evolutitve SCI'!AV19 -> 0.40450651
B11: Operating Expense ratio | D11: =('Evolutitve SCI'!#REF!+'Evolutitve SCI'!#REF!)/(('Evolutive SFP'!#REF!+'Evolutive SFP'!#REF!)/2) -> #REF! | E11: =('Evolutitve SCI'!#REF!+'Evolutitve SCI'!#REF!)/(('Evolutive SFP'!#REF!+'Evolutive SFP'!#REF!)/2) -> #REF! | F11: =('Evolutitve SCI'!#REF!+'Evolutitve SCI'!#REF!)/(('Evolutive SFP'!#REF!+'Evolutive SFP'!#REF!)/2) -> #REF! | G11: =('Evolutitve SCI'!#REF!+'Evolutitve SCI'!#REF!)/(('Evolutive SFP'!#REF!+'Evolutive SFP'!#REF!)/2) -> #REF! | H11: =('Evolutitve SCI'!#REF!+'Evolutitve SCI'!#REF!)/(('Evolutive SFP'!#REF!+'Evolutive SFP'!#REF!)/2) -> #REF! | I11: =('Evolutitve SCI'!#REF!+'Evolutitve SCI'!#REF!)/(('Evolutive SFP'!#REF!+'Evolutive SFP'!#REF!)/2) -> #REF! | J11: =('Evolutitve SCI'!#REF!+'Evolutitve SCI'!#REF!)/(('Evolutive SFP'!#REF!+'Evolutive SFP'!#REF!)/2) -> #REF! | K11: =('Evolutitve SCI'!#REF!+'Evolutitve SCI'!#REF!)/(('Evolutive SFP'!#REF!+'Evolutive SFP'!#REF!)/2) -> #REF! | ... AQ11: =('Evolutitve SCI'!#REF!+'Evolutitve SCI'!#REF!)/(('Evolutive SFP'!#REF!+'Evolutive SFP'!#REF!)/2) -> #REF! | AR11: =('Evolutitve SCI'!#REF!+'Evolutitve SCI'!#REF!)/(('Evolutive SFP'!#REF!+'Evolutive SFP'!B27)/2) -> #REF! | AS11: =('Evolutitve SCI'!#REF!+'Evolutitve SCI'!#REF!)/(('Evolutive SFP'!#REF!+'Evolutive SFP'!C27)/2) -> #REF! | AT11: =('Evolutitve SCI'!B23+'Evolutitve SCI'!B12)/(('Evolutive SFP'!B27+'Evolutive SFP'!D27)/2) -> 0.095727209 | AU11: =('Evolutitve SCI'!C23+'Evolutitve SCI'!C12)/(('Evolutive SFP'!C27+'Evolutive SFP'!E27)/2) -> 0.0090571377 | AV11: =('Evolutitve SCI'!D23+'Evolutitve SCI'!D12)/(('Evolutive SFP'!D27+'Evolutive SFP'!F27)/2) -> 0.017298688 | AW11: =('Evolutitve SCI'!E23+'Evolutitve SCI'!E12)/(('Evolutive SFP'!E27+'Evolutive SFP'!G27)/2) -> 0.027906566 | AX11: =('Evolutitve SCI'!F23+'Evolutitve SCI'!F12)/(('Evolutive SFP'!F27+'Evolutive SFP'!H27)/2) -> 0.037129339 | AY11: =('Evolutitve SCI'!G23+'Evolutitve SCI'!G12)/(('Evolutive SFP'!G27+'Evolutive SFP'!#REF!)/2) -> #REF! | AZ11: =('Evolutitve SCI'!H23+'Evolutitve SCI'!H12)/(('Evolutive SFP'!H27+'Evolutive SFP'!I27)/2) -> 0.054061438 | BA11: =('Evolutitve SCI'!#REF!+'Evolutitve SCI'!#REF!)/(('Evolutive SFP'!#REF!+'Evolutive SFP'!J27)/2) -> #REF! | BB11: =('Evolutitve SCI'!I23+'Evolutitve SCI'!I12)/(('Evolutive SFP'!I27+'Evolutive SFP'!K27)/2) -> 0.071843166 | BC11: =('Evolutitve SCI'!J23+'Evolutitve SCI'!J12)/(('Evolutive SFP'!J27+'Evolutive SFP'!#REF!)/2) -> #REF! | BD11: =('Evolutitve SCI'!K23+'Evolutitve SCI'!K12)/(('Evolutive SFP'!K27+'Evolutive SFP'!#REF!)/2) -> #REF! | BE11: =('Evolutitve SCI'!L23+'Evolutitve SCI'!L12)/(('Evolutive SFP'!L27+'Evolutive SFP'!#REF!)/2) -> #REF! | BF11: =('Evolutitve SCI'!M23+'Evolutitve SCI'!M12)/(('Evolutive SFP'!M27+'Evolutive SFP'!#REF!)/2) -> #REF! | BG11: =('Evolutitve SCI'!N23+'Evolutitve SCI'!N12)/(('Evolutive SFP'!N27+'Evolutive SFP'!#REF!)/2) -> #REF! | BH11: =('Evolutitve SCI'!O23+'Evolutitve SCI'!O12)/(('Evolutive SFP'!O27+'Evolutive SFP'!#REF!)/2) -> #REF! | BI11: =('Evolutitve SCI'!P23+'Evolutitve SCI'!P12)/(('Evolutive SFP'!P27+'Evolutive SFP'!#REF!)/2) -> #REF! | BJ11: =('Evolutitve SCI'!Q23+'Evolutitve SCI'!Q12)/(('Evolutive SFP'!Q27+'Evolutive SFP'!#REF!)/2) -> #REF! | ... CO11: =('Evolutitve SCI'!AV23+'Evolutitve SCI'!AV12)/(('Evolutive SFP'!AV27+'Evolutive SFP'!#REF!)/2) -> #REF!
A12: LIQUIDITY | B12: MIN LIQ ratio | C12: Min 15% | D12: =('Evolutive SFP'!#REF!)/('Evolutive SFP'!#REF!+'Evolutive SFP'!#REF!+'Evolutive SFP'!#REF!+'Evolutive SFP'!#REF!+'Evolutive SFP'!#REF!+'Evolutive SFP'!#REF!+'Evolutive SFP'!#REF!) -> #REF! | E12: =('Evolutive SFP'!#REF!)/('Evolutive SFP'!#REF!+'Evolutive SFP'!#REF!+'Evolutive SFP'!#REF!+'Evolutive SFP'!#REF!+'Evolutive SFP'!#REF!+'Evolutive SFP'!#REF!+'Evolutive SFP'!#REF!) -> #REF! | F12: =('Evolutive SFP'!#REF!)/('Evolutive SFP'!#REF!+'Evolutive SFP'!#REF!+'Evolutive SFP'!#REF!+'Evolutive SFP'!#REF!+'Evolutive SFP'!#REF!+'Evolutive SFP'!#REF!+'Evolutive SFP'!#REF!) -> #REF! | G12: =('Evolutive SFP'!#REF!)/('Evolutive SFP'!#REF!+'Evolutive SFP'!#REF!+'Evolutive SFP'!#REF!+'Evolutive SFP'!#REF!+'Evolutive SFP'!#REF!+'Evolutive SFP'!#REF!+'Evolutive SFP'!#REF!) -> #REF! | H12: =('Evolutive SFP'!#REF!)/('Evolutive SFP'!#REF!+'Evolutive SFP'!#REF!+'Evolutive SFP'!#REF!+'Evolutive SFP'!#REF!+'Evolutive SFP'!#REF!+'Evolutive SFP'!#REF!+'Evolutive SFP'!#REF!) -> #REF! | I12: =('Evolutive SFP'!#REF!)/('Evolutive SFP'!#REF!+'Evolutive SFP'!#REF!+'Evolutive SFP'!#REF!+'Evolutive SFP'!#REF!+'Evolutive SFP'!#REF!+'Evolutive SFP'!#REF!+'Evolutive SFP'!#REF!) -> #REF! | J12: =('Evolutive SFP'!#REF!)/('Evolutive SFP'!#REF!+'Evolutive SFP'!#REF!+'Evolutive SFP'!#REF!+'Evolutive SFP'!#REF!+'Evolutive SFP'!#REF!+'Evolutive SFP'!#REF!+'Evolutive SFP'!#REF!) -> #REF! | K12: =('Evolutive SFP'!#REF!)/('Evolutive SFP'!#REF!+'Evolutive SFP'!#REF!+'Evolutive SFP'!#REF!+'Evolutive SFP'!#REF!+'Evolutive SFP'!#REF!+'Evolutive SFP'!#REF!+'Evolutive SFP'!#REF!) -> #REF! | ... AS12: =('Evolutive SFP'!#REF!)/('Evolutive SFP'!#REF!+'Evolutive SFP'!#REF!+'Evolutive SFP'!#REF!+'Evolutive SFP'!#REF!+'Evolutive SFP'!#REF!+'Evolutive SFP'!#REF!+'Evolutive SFP'!#REF!) -> #REF! | AT12: =('Evolutive SFP'!B4)/('Evolutive SFP'!B28+'Evolutive SFP'!B29+'Evolutive SFP'!B32+'Evolutive SFP'!B33+'Evolutive SFP'!B34+'Evolutive SFP'!B35+'Evolutive SFP'!B36) -> 17.936371 | AU12: =('Evolutive SFP'!C4)/('Evolutive SFP'!C28+'Evolutive SFP'!C29+'Evolutive SFP'!C32+'Evolutive SFP'!C33+'Evolutive SFP'!C34+'Evolutive SFP'!C35+'Evolutive SFP'!C36) -> 1.0580455 | AV12: =('Evolutive SFP'!D4)/('Evolutive SFP'!D28+'Evolutive SFP'!D29+'Evolutive SFP'!D32+'Evolutive SFP'!D33+'Evolutive SFP'!D34+'Evolutive SFP'!D35+'Evolutive SFP'!D36) -> 1.1334381 | AW12: =('Evolutive SFP'!E4)/('Evolutive SFP'!E28+'Evolutive SFP'!E29+'Evolutive SFP'!E32+'Evolutive SFP'!E33+'Evolutive SFP'!E34+'Evolutive SFP'!E35+'Evolutive SFP'!E36) -> 1.4187756 | AX12: =('Evolutive SFP'!F4)/('Evolutive SFP'!F28+'Evolutive SFP'!F29+'Evolutive SFP'!F32+'Evolutive SFP'!F33+'Evolutive SFP'!F34+'Evolutive SFP'!F35+'Evolutive SFP'!F36) -> 1.5680745 | AY12: =('Evolutive SFP'!G4)/('Evolutive SFP'!G28+'Evolutive SFP'!G29+'Evolutive SFP'!G32+'Evolutive SFP'!G33+'Evolutive SFP'!G34+'Evolutive SFP'!G35+'Evolutive SFP'!G36) -> 1.8660428 | AZ12: =('Evolutive SFP'!H4)/('Evolutive SFP'!H28+'Evolutive SFP'!H29+'Evolutive SFP'!H32+'Evolutive SFP'!H33+'Evolutive SFP'!H34+'Evolutive SFP'!H35+'Evolutive SFP'!H36) -> 1.8706248 | BA12: =('Evolutive SFP'!#REF!)/('Evolutive SFP'!#REF!+'Evolutive SFP'!#REF!+'Evolutive SFP'!#REF!+'Evolutive SFP'!#REF!+'Evolutive SFP'!#REF!+'Evolutive SFP'!#REF!+'Evolutive SFP'!#REF!) -> #REF! | BB12: =('Evolutive SFP'!I4)/('Evolutive SFP'!I28+'Evolutive SFP'!I29+'Evolutive SFP'!I32+'Evolutive SFP'!I33+'Evolutive SFP'!I34+'Evolutive SFP'!I35+'Evolutive SFP'!I36) -> 1.5891724 | BC12: =('Evolutive SFP'!J4)/('Evolutive SFP'!J28+'Evolutive SFP'!J29+'Evolutive SFP'!J32+'Evolutive SFP'!J33+'Evolutive SFP'!J34+'Evolutive SFP'!J35+'Evolutive SFP'!J36) -> 1.4407112 | BD12: =('Evolutive SFP'!K4)/('Evolutive SFP'!K28+'Evolutive SFP'!K29+'Evolutive SFP'!K32+'Evolutive SFP'!K33+'Evolutive SFP'!K34+'Evolutive SFP'!K35+'Evolutive SFP'!K36) -> 1.3837658 | BE12: =('Evolutive SFP'!L4)/('Evolutive SFP'!L28+'Evolutive SFP'!L29+'Evolutive SFP'!L32+'Evolutive SFP'!L33+'Evolutive SFP'!L34+'Evolutive SFP'!L35+'Evolutive SFP'!L36) -> 1.3793272 | BF12: =('Evolutive SFP'!M4)/('Evolutive SFP'!M28+'Evolutive SFP'!M29+'Evolutive SFP'!M32+'Evolutive SFP'!M33+'Evolutive SFP'!M34+'Evolutive SFP'!M35+'Evolutive SFP'!M36) -> 1.3367136 | BG12: =('Evolutive SFP'!N4)/('Evolutive SFP'!N28+'Evolutive SFP'!N29+'Evolutive SFP'!N32+'Evolutive SFP'!N33+'Evolutive SFP'!N34+'Evolutive SFP'!N35+'Evolutive SFP'!N36) -> 1.3809962 | BH12: =('Evolutive SFP'!O4)/('Evolutive SFP'!O28+'Evolutive SFP'!O29+'Evolutive SFP'!O32+'Evolutive SFP'!O33+'Evolutive SFP'!O34+'Evolutive SFP'!O35+'Evolutive SFP'!O36) -> 1.2861767 | BI12: =('Evolutive SFP'!P4)/('Evolutive SFP'!P28+'Evolutive SFP'!P29+'Evolutive SFP'!P32+'Evolutive SFP'!P33+'Evolutive SFP'!P34+'Evolutive SFP'!P35+'Evolutive SFP'!P36) -> 1.304204 | ... CO12: =('Evolutive SFP'!AV4)/('Evolutive SFP'!AV28+'Evolutive SFP'!AV29+'Evolutive SFP'!AV32+'Evolutive SFP'!AV33+'Evolutive SFP'!AV34+'Evolutive SFP'!AV35+'Evolutive SFP'!AV36) -> 1.1893498
B13: T/LIQ ratio | D13: =('Evolutive SFP'!#REF!+'Evolutive SFP'!#REF!)/('Evolutive SFP'!#REF!+'Evolutive SFP'!#REF!+'Evolutive SFP'!#REF!+'Evolutive SFP'!#REF!+'Evolutive SFP'!#REF!+'Evolutive SFP'!#REF!) -> #REF! | E13: =('Evolutive SFP'!#REF!+'Evolutive SFP'!#REF!)/('Evolutive SFP'!#REF!+'Evolutive SFP'!#REF!+'Evolutive SFP'!#REF!+'Evolutive SFP'!#REF!+'Evolutive SFP'!#REF!+'Evolutive SFP'!#REF!) -> #REF! | F13: =('Evolutive SFP'!#REF!+'Evolutive SFP'!#REF!)/('Evolutive SFP'!#REF!+'Evolutive SFP'!#REF!+'Evolutive SFP'!#REF!+'Evolutive SFP'!#REF!+'Evolutive SFP'!#REF!+'Evolutive SFP'!#REF!) -> #REF! | G13: =('Evolutive SFP'!#REF!+'Evolutive SFP'!#REF!)/('Evolutive SFP'!#REF!+'Evolutive SFP'!#REF!+'Evolutive SFP'!#REF!+'Evolutive SFP'!#REF!+'Evolutive SFP'!#REF!+'Evolutive SFP'!#REF!) -> #REF! | H13: =('Evolutive SFP'!#REF!+'Evolutive SFP'!#REF!)/('Evolutive SFP'!#REF!+'Evolutive SFP'!#REF!+'Evolutive SFP'!#REF!+'Evolutive SFP'!#REF!+'Evolutive SFP'!#REF!+'Evolutive SFP'!#REF!) -> #REF! | I13: =('Evolutive SFP'!#REF!+'Evolutive SFP'!#REF!)/('Evolutive SFP'!#REF!+'Evolutive SFP'!#REF!+'Evolutive SFP'!#REF!+'Evolutive SFP'!#REF!+'Evolutive SFP'!#REF!+'Evolutive SFP'!#REF!) -> #REF! | J13: =('Evolutive SFP'!#REF!+'Evolutive SFP'!#REF!)/('Evolutive SFP'!#REF!+'Evolutive SFP'!#REF!+'Evolutive SFP'!#REF!+'Evolutive SFP'!#REF!+'Evolutive SFP'!#REF!+'Evolutive SFP'!#REF!) -> #REF! | K13: =('Evolutive SFP'!#REF!+'Evolutive SFP'!#REF!)/('Evolutive SFP'!#REF!+'Evolutive SFP'!#REF!+'Evolutive SFP'!#REF!+'Evolutive SFP'!#REF!+'Evolutive SFP'!#REF!+'Evolutive SFP'!#REF!) -> #REF! | ... O13: =('Evolutive SFP'!#REF!+'Evolutive SFP'!#REF!)/('Evolutive SFP'!#REF!+'Evolutive SFP'!#REF!+'Evolutive SFP'!#REF!+'Evolutive SFP'!#REF!+'Evolutive SFP'!#REF!+'Evolutive SFP'!#REF!) -> #REF! | P13: ='Evolutive SFP'!#REF!/('Evolutive SFP'!#REF!+'Evolutive SFP'!#REF!) -> #REF! | Q13: ='Evolutive SFP'!#REF!/('Evolutive SFP'!#REF!+'Evolutive SFP'!#REF!) -> #REF! | R13: ='Evolutive SFP'!#REF!/('Evolutive SFP'!#REF!+'Evolutive SFP'!#REF!) -> #REF! | S13: ='Evolutive SFP'!#REF!/('Evolutive SFP'!#REF!+'Evolutive SFP'!#REF!) -> #REF! | T13: ='Evolutive SFP'!#REF!/('Evolutive SFP'!#REF!+'Evolutive SFP'!#REF!) -> #REF! | U13: ='Evolutive SFP'!#REF!/('Evolutive SFP'!#REF!+'Evolutive SFP'!#REF!) -> #REF! | V13: ='Evolutive SFP'!#REF!/('Evolutive SFP'!#REF!+'Evolutive SFP'!#REF!) -> #REF! | W13: ='Evolutive SFP'!#REF!/('Evolutive SFP'!#REF!+'Evolutive SFP'!#REF!) -> #REF! | ... AS13: ='Evolutive SFP'!#REF!/('Evolutive SFP'!#REF!+'Evolutive SFP'!#REF!) -> #REF! | AT13: ='Evolutive SFP'!B4/('Evolutive SFP'!B31+'Evolutive SFP'!B36) -> 0.23611654 | AU13: ='Evolutive SFP'!C4/('Evolutive SFP'!C31+'Evolutive SFP'!C36) -> 0.22665063 | AV13: ='Evolutive SFP'!D4/('Evolutive SFP'!D31+'Evolutive SFP'!D36) -> 0.24286706 | AW13: ='Evolutive SFP'!E4/('Evolutive SFP'!E31+'Evolutive SFP'!E36) -> 0.24654972 | AX13: ='Evolutive SFP'!F4/('Evolutive SFP'!F31+'Evolutive SFP'!F36) -> 0.2729682 | AY13: ='Evolutive SFP'!G4/('Evolutive SFP'!G31+'Evolutive SFP'!G36) -> 0.32177274 | AZ13: ='Evolutive SFP'!H4/('Evolutive SFP'!H31+'Evolutive SFP'!H36) -> 0.338793 | BA13: ='Evolutive SFP'!#REF!/('Evolutive SFP'!#REF!+'Evolutive SFP'!#REF!) -> #REF! | BB13: ='Evolutive SFP'!I4/('Evolutive SFP'!I31+'Evolutive SFP'!I36) -> 0.30381477 | BC13: ='Evolutive SFP'!J4/('Evolutive SFP'!J31+'Evolutive SFP'!J36) -> 0.28194922 | BD13: ='Evolutive SFP'!K4/('Evolutive SFP'!K31+'Evolutive SFP'!K36) -> 0.27186632 | BE13: ='Evolutive SFP'!L4/('Evolutive SFP'!L31+'Evolutive SFP'!L36) -> 0.279036 | BF13: ='Evolutive SFP'!M4/('Evolutive SFP'!M31+'Evolutive SFP'!M36) -> 0.27432203 | BG13: ='Evolutive SFP'!N4/('Evolutive SFP'!N31+'Evolutive SFP'!N36) -> 0.30338407 | BH13: ='Evolutive SFP'!O4/('Evolutive SFP'!O31+'Evolutive SFP'!O36) -> 0.27900272 | BI13: ='Evolutive SFP'!P4/('Evolutive SFP'!P31+'Evolutive SFP'!P36) -> 0.28272388 | ... CO13: ='Evolutive SFP'!AV4/('Evolutive SFP'!AV31+'Evolutive SFP'!AV36) -> 0.18654076
B14: EB ratio | C14: Max 25% | D14: ='Evolutive SFP'!#REF!/'Evolutive SFP'!#REF! -> #REF! | E14: ='Evolutive SFP'!#REF!/'Evolutive SFP'!#REF! -> #REF! | F14: ='Evolutive SFP'!#REF!/'Evolutive SFP'!#REF! -> #REF! | G14: ='Evolutive SFP'!#REF!/'Evolutive SFP'!#REF! -> #REF! | H14: ='Evolutive SFP'!#REF!/'Evolutive SFP'!#REF! -> #REF! | I14: ='Evolutive SFP'!#REF!/'Evolutive SFP'!#REF! -> #REF! | J14: ='Evolutive SFP'!#REF!/'Evolutive SFP'!#REF! -> #REF! | K14: ='Evolutive SFP'!#REF!/'Evolutive SFP'!#REF! -> #REF! | ... AS14: ='Evolutive SFP'!#REF!/'Evolutive SFP'!#REF! -> #REF! | AT14: ='Evolutive SFP'!B37/'Evolutive SFP'!B27 -> 0 | AU14: ='Evolutive SFP'!C37/'Evolutive SFP'!C27 -> 0 | AV14: ='Evolutive SFP'!D37/'Evolutive SFP'!D27 -> 0 | AW14: ='Evolutive SFP'!E37/'Evolutive SFP'!E27 -> 0 | AX14: ='Evolutive SFP'!F37/'Evolutive SFP'!F27 -> 0 | AY14: ='Evolutive SFP'!G37/'Evolutive SFP'!G27 -> 0 | AZ14: ='Evolutive SFP'!H37/'Evolutive SFP'!H27 -> 0 | BA14: ='Evolutive SFP'!#REF!/'Evolutive SFP'!#REF! -> #REF! | BB14: ='Evolutive SFP'!I37/'Evolutive SFP'!I27 -> 0 | BC14: ='Evolutive SFP'!J37/'Evolutive SFP'!J27 -> 0 | BD14: ='Evolutive SFP'!K37/'Evolutive SFP'!K27 -> 0 | BE14: ='Evolutive SFP'!L37/'Evolutive SFP'!L27 -> 0 | BF14: ='Evolutive SFP'!M37/'Evolutive SFP'!M27 -> 0 | BG14: ='Evolutive SFP'!N37/'Evolutive SFP'!N27 -> 0 | BH14: ='Evolutive SFP'!O37/'Evolutive SFP'!O27 -> 0 | BI14: ='Evolutive SFP'!P37/'Evolutive SFP'!P27 -> 0 | ... CO14: ='Evolutive SFP'!AV37/'Evolutive SFP'!AV27 -> 0
B15: LA to TA ratio | D15: ='Evolutive SFP'!#REF!/'Evolutive SFP'!#REF! -> #REF! | E15: ='Evolutive SFP'!#REF!/'Evolutive SFP'!#REF! -> #REF! | F15: ='Evolutive SFP'!#REF!/'Evolutive SFP'!#REF! -> #REF! | G15: ='Evolutive SFP'!#REF!/'Evolutive SFP'!#REF! -> #REF! | H15: ='Evolutive SFP'!#REF!/'Evolutive SFP'!#REF! -> #REF! | I15: ='Evolutive SFP'!#REF!/'Evolutive SFP'!#REF! -> #REF! | J15: ='Evolutive SFP'!#REF!/'Evolutive SFP'!#REF! -> #REF! | K15: ='Evolutive SFP'!#REF!/'Evolutive SFP'!#REF! -> #REF! | ... AS15: ='Evolutive SFP'!#REF!/'Evolutive SFP'!#REF! -> #REF! | AT15: ='Evolutive SFP'!B4/'Evolutive SFP'!B27 -> 0.2077033 | AU15: ='Evolutive SFP'!C4/'Evolutive SFP'!C27 -> 0.17718067 | AV15: ='Evolutive SFP'!D4/'Evolutive SFP'!D27 -> 0.19349107 | AW15: ='Evolutive SFP'!E4/'Evolutive SFP'!E27 -> 0.1955935 | AX15: ='Evolutive SFP'!F4/'Evolutive SFP'!F27 -> 0.21336827 | AY15: ='Evolutive SFP'!G4/'Evolutive SFP'!G27 -> 0.24854047 | AZ15: ='Evolutive SFP'!H4/'Evolutive SFP'!H27 -> 0.26664024 | BA15: ='Evolutive SFP'!#REF!/'Evolutive SFP'!#REF! -> #REF! | BB15: ='Evolutive SFP'!I4/'Evolutive SFP'!I27 -> 0.23961887 | BC15: ='Evolutive SFP'!J4/'Evolutive SFP'!J27 -> 0.22208702 | BD15: ='Evolutive SFP'!K4/'Evolutive SFP'!K27 -> 0.21390615 | BE15: ='Evolutive SFP'!L4/'Evolutive SFP'!L27 -> 0.22067242 | BF15: ='Evolutive SFP'!M4/'Evolutive SFP'!M27 -> 0.21541157 | BG15: ='Evolutive SFP'!N4/'Evolutive SFP'!N27 -> 0.21652647 | BH15: ='Evolutive SFP'!O4/'Evolutive SFP'!O27 -> 0.22232527 | BI15: ='Evolutive SFP'!P4/'Evolutive SFP'!P27 -> 0.2268823 | ... CO15: ='Evolutive SFP'!AV4/'Evolutive SFP'!AV27 -> 0.14019217
A16: STRUCTURE | B16: NEA ratio | C16: Max 10% | D16: =('Evolutive SFP'!#REF!+'Evolutive SFP'!#REF!)/'Evolutive SFP'!#REF! -> #REF! | E16: =('Evolutive SFP'!#REF!+'Evolutive SFP'!#REF!)/'Evolutive SFP'!#REF! -> #REF! | F16: =('Evolutive SFP'!#REF!+'Evolutive SFP'!#REF!)/'Evolutive SFP'!#REF! -> #REF! | G16: =('Evolutive SFP'!#REF!+'Evolutive SFP'!#REF!)/'Evolutive SFP'!#REF! -> #REF! | H16: =('Evolutive SFP'!#REF!+'Evolutive SFP'!#REF!)/'Evolutive SFP'!#REF! -> #REF! | I16: =('Evolutive SFP'!#REF!+'Evolutive SFP'!#REF!)/'Evolutive SFP'!#REF! -> #REF! | J16: =('Evolutive SFP'!#REF!+'Evolutive SFP'!#REF!)/'Evolutive SFP'!#REF! -> #REF! | K16: =('Evolutive SFP'!#REF!+'Evolutive SFP'!#REF!)/'Evolutive SFP'!#REF! -> #REF! | ... AS16: =('Evolutive SFP'!#REF!+'Evolutive SFP'!#REF!)/'Evolutive SFP'!#REF! -> #REF! | AT16: =('Evolutive SFP'!B7+'Evolutive SFP'!B21)/'Evolutive SFP'!B27 -> 0.052726313 | AU16: =('Evolutive SFP'!C7+'Evolutive SFP'!C21)/'Evolutive SFP'!C27 -> 0.052385481 | AV16: =('Evolutive SFP'!D7+'Evolutive SFP'!D21)/'Evolutive SFP'!D27 -> 0.044155847 | AW16: =('Evolutive SFP'!E7+'Evolutive SFP'!E21)/'Evolutive SFP'!E27 -> 0.043548992 | AX16: =('Evolutive SFP'!F7+'Evolutive SFP'!F21)/'Evolutive SFP'!F27 -> 0.059439778 | AY16: =('Evolutive SFP'!G7+'Evolutive SFP'!G21)/'Evolutive SFP'!G27 -> 0.042104863 | AZ16: =('Evolutive SFP'!H7+'Evolutive SFP'!H21)/'Evolutive SFP'!H27 -> 0.04234716 | BA16: =('Evolutive SFP'!#REF!+'Evolutive SFP'!#REF!)/'Evolutive SFP'!#REF! -> #REF! | BB16: =('Evolutive SFP'!I7+'Evolutive SFP'!I21)/'Evolutive SFP'!I27 -> 0.040615563 | BC16: =('Evolutive SFP'!J7+'Evolutive SFP'!J21)/'Evolutive SFP'!J27 -> 0.040088357 | BD16: =('Evolutive SFP'!K7+'Evolutive SFP'!K21)/'Evolutive SFP'!K27 -> 0.040577822 | BE16: =('Evolutive SFP'!L7+'Evolutive SFP'!L21)/'Evolutive SFP'!L27 -> 0.038884089 | BF16: =('Evolutive SFP'!M7+'Evolutive SFP'!M21)/'Evolutive SFP'!M27 -> 0.037856665 | BG16: =('Evolutive SFP'!N7+'Evolutive SFP'!N21)/'Evolutive SFP'!N27 -> 0.037820347 | BH16: =('Evolutive SFP'!O7+'Evolutive SFP'!O21)/'Evolutive SFP'!O27 -> 0.038142 | BI16: =('Evolutive SFP'!P7+'Evolutive SFP'!P21)/'Evolutive SFP'!P27 -> 0.038911235 | ... CO16: =('Evolutive SFP'!AV7+'Evolutive SFP'!AV21)/'Evolutive SFP'!AV27 -> 0.042131575
B17: LB ratio | C17: Max 5% | D17: ='Evolutive SFP'!#REF!/'Evolutive SFP'!#REF! -> #REF! | E17: ='Evolutive SFP'!#REF!/'Evolutive SFP'!#REF! -> #REF! | F17: ='Evolutive SFP'!#REF!/'Evolutive SFP'!#REF! -> #REF! | G17: ='Evolutive SFP'!#REF!/'Evolutive SFP'!#REF! -> #REF! | H17: ='Evolutive SFP'!#REF!/'Evolutive SFP'!#REF! -> #REF! | I17: ='Evolutive SFP'!#REF!/'Evolutive SFP'!#REF! -> #REF! | J17: ='Evolutive SFP'!#REF!/'Evolutive SFP'!#REF! -> #REF! | K17: ='Evolutive SFP'!#REF!/'Evolutive SFP'!#REF! -> #REF! | ... AS17: ='Evolutive SFP'!#REF!/'Evolutive SFP'!#REF! -> #REF! | AT17: ='Evolutive SFP'!B21/'Evolutive SFP'!B27 -> 0.012972568 | AU17: ='Evolutive SFP'!C21/'Evolutive SFP'!C27 -> 0.052385481 | AV17: ='Evolutive SFP'!D21/'Evolutive SFP'!D27 -> 0.044155847 | AW17: ='Evolutive SFP'!E21/'Evolutive SFP'!E27 -> 0.043548992 | AX17: ='Evolutive SFP'!F21/'Evolutive SFP'!F27 -> 0.059439778 | AY17: ='Evolutive SFP'!G21/'Evolutive SFP'!G27 -> 0.042104863 | AZ17: ='Evolutive SFP'!H21/'Evolutive SFP'!H27 -> 0.04234716 | BA17: ='Evolutive SFP'!#REF!/'Evolutive SFP'!#REF! -> #REF! | BB17: ='Evolutive SFP'!I21/'Evolutive SFP'!I27 -> 0.040615563 | BC17: ='Evolutive SFP'!J21/'Evolutive SFP'!J27 -> 0.040088357 | BD17: ='Evolutive SFP'!K21/'Evolutive SFP'!K27 -> 0.040577822 | BE17: ='Evolutive SFP'!L21/'Evolutive SFP'!L27 -> 0.038884089 | BF17: ='Evolutive SFP'!M21/'Evolutive SFP'!M27 -> 0.037856665 | BG17: ='Evolutive SFP'!N21/'Evolutive SFP'!N27 -> 0.031380639 | BH17: ='Evolutive SFP'!O21/'Evolutive SFP'!O27 -> 0.038142 | BI17: ='Evolutive SFP'!P21/'Evolutive SFP'!P27 -> 0.038911235 | ... CO17: ='Evolutive SFP'!AV21/'Evolutive SFP'!AV27 -> 0.042131575
B18: PI to Deposit ratio | C18: Max 5% | D18: ='Evolutive SFP'!#REF!/'Evolutive SFP'!#REF! -> #REF! | E18: ='Evolutive SFP'!#REF!/'Evolutive SFP'!#REF! -> #REF! | F18: ='Evolutive SFP'!#REF!/'Evolutive SFP'!#REF! -> #REF! | G18: ='Evolutive SFP'!#REF!/'Evolutive SFP'!#REF! -> #REF! | H18: ='Evolutive SFP'!#REF!/'Evolutive SFP'!#REF! -> #REF! | I18: ='Evolutive SFP'!#REF!/'Evolutive SFP'!#REF! -> #REF! | J18: ='Evolutive SFP'!#REF!/'Evolutive SFP'!#REF! -> #REF! | K18: ='Evolutive SFP'!#REF!/'Evolutive SFP'!#REF! -> #REF! | ... AS18: ='Evolutive SFP'!#REF!/'Evolutive SFP'!#REF! -> #REF! | AT18: ='Evolutive SFP'!B13/'Evolutive SFP'!B31 -> 0 | AU18: ='Evolutive SFP'!C13/'Evolutive SFP'!C31 -> 0 | AV18: ='Evolutive SFP'!D13/'Evolutive SFP'!D31 -> 0 | AW18: ='Evolutive SFP'!E13/'Evolutive SFP'!E31 -> 0 | AX18: ='Evolutive SFP'!F13/'Evolutive SFP'!F31 -> 0 | AY18: ='Evolutive SFP'!G13/'Evolutive SFP'!G31 -> 0 | AZ18: ='Evolutive SFP'!H13/'Evolutive SFP'!H31 -> 0 | BA18: ='Evolutive SFP'!#REF!/'Evolutive SFP'!#REF! -> #REF! | BB18: ='Evolutive SFP'!I13/'Evolutive SFP'!I31 -> 0 | BC18: ='Evolutive SFP'!J13/'Evolutive SFP'!J31 -> 0 | BD18: ='Evolutive SFP'!K13/'Evolutive SFP'!K31 -> 0 | BE18: ='Evolutive SFP'!L13/'Evolutive SFP'!L31 -> 0 | BF18: ='Evolutive SFP'!M13/'Evolutive SFP'!M31 -> 0 | BG18: ='Evolutive SFP'!N13/'Evolutive SFP'!N31 -> 0.059729011 | BH18: ='Evolutive SFP'!O13/'Evolutive SFP'!O31 -> 0.080558055 | BI18: ='Evolutive SFP'!P13/'Evolutive SFP'!P31 -> 0.079500375 | ... CO18: ='Evolutive SFP'!AV13/'Evolutive SFP'!AV31 -> 0
B19: PI to CC ratio | C19: Max 40% | D19: ='Evolutive SFP'!#REF!/(CAELS!D3*1000000) -> #REF! | E19: ='Evolutive SFP'!#REF!/(CAELS!E3*1000000) -> #REF! | F19: ='Evolutive SFP'!#REF!/(CAELS!F3*1000000) -> #REF! | G19: ='Evolutive SFP'!#REF!/(CAELS!G3*1000000) -> #REF! | H19: ='Evolutive SFP'!#REF!/(CAELS!H3*1000000) -> #REF! | I19: ='Evolutive SFP'!#REF!/(CAELS!I3*1000000) -> #REF! | J19: ='Evolutive SFP'!#REF!/(CAELS!J3*1000000) -> #REF! | K19: ='Evolutive SFP'!#REF!/(CAELS!K3*1000000) -> #REF! | ... AS19: ='Evolutive SFP'!#REF!/(CAELS!AS3*1000000) -> #REF! | AT19: ='Evolutive SFP'!B13/(CAELS!AT3*1000000) -> 0 | AU19: ='Evolutive SFP'!C13/(CAELS!AU3*1000000) -> 0 | AV19: ='Evolutive SFP'!D13/(CAELS!AV3*1000000) -> 0 | AW19: ='Evolutive SFP'!E13/(CAELS!AW3*1000000) -> 0 | AX19: ='Evolutive SFP'!F13/(CAELS!AX3*1000000) -> 0 | AY19: ='Evolutive SFP'!G13/(CAELS!AY3*1000000) -> 0 | AZ19: ='Evolutive SFP'!H13/(CAELS!AZ3*1000000) -> 0 | BA19: ='Evolutive SFP'!#REF!/(CAELS!BA3*1000000) -> #REF! | BB19: ='Evolutive SFP'!I13/(CAELS!BB3*1000000) -> 0 | BC19: ='Evolutive SFP'!J13/(CAELS!BC3*1000000) -> 0 | BD19: ='Evolutive SFP'!K13/(CAELS!BD3*1000000) -> 0 | BE19: ='Evolutive SFP'!L13/(CAELS!BE3*1000000) -> 0 | BF19: ='Evolutive SFP'!M13/(CAELS!BF3*1000000) -> 0 | BG19: ='Evolutive SFP'!N13/(CAELS!BG3*1000000) -> 0.20539057 | BH19: ='Evolutive SFP'!O13/(CAELS!BH3*1000000) -> 0.29677275 | BI19: ='Evolutive SFP'!P13/(CAELS!BI3*1000000) -> 0.30574988 | ... CO19: ='Evolutive SFP'!AV13/(CAELS!CO3*1000000) -> 0
B20: Gross loans/TA | D20: ='Evolutive SFP'!#REF!/'Evolutive SFP'!#REF! -> #REF! | E20: ='Evolutive SFP'!#REF!/'Evolutive SFP'!#REF! -> #REF! | F20: ='Evolutive SFP'!#REF!/'Evolutive SFP'!#REF! -> #REF! | G20: ='Evolutive SFP'!#REF!/'Evolutive SFP'!#REF! -> #REF! | H20: ='Evolutive SFP'!#REF!/'Evolutive SFP'!#REF! -> #REF! | I20: ='Evolutive SFP'!#REF!/'Evolutive SFP'!#REF! -> #REF! | J20: ='Evolutive SFP'!#REF!/'Evolutive SFP'!#REF! -> #REF! | K20: ='Evolutive SFP'!#REF!/'Evolutive SFP'!#REF! -> #REF! | ... AS20: ='Evolutive SFP'!#REF!/'Evolutive SFP'!#REF! -> #REF! | AT20: ='Evolutive SFP'!B15/'Evolutive SFP'!B27 -> 0.81183537 | AU20: ='Evolutive SFP'!C15/'Evolutive SFP'!C27 -> 0.71199878 | AV20: ='Evolutive SFP'!D15/'Evolutive SFP'!D27 -> 0.72220471 | AW20: ='Evolutive SFP'!E15/'Evolutive SFP'!E27 -> 0.7214758 | AX20: ='Evolutive SFP'!F15/'Evolutive SFP'!F27 -> 0.69058381 | AY20: ='Evolutive SFP'!G15/'Evolutive SFP'!G27 -> 0.66104449 | AZ20: ='Evolutive SFP'!H15/'Evolutive SFP'!H27 -> 0.65671269 | BA20: ='Evolutive SFP'!#REF!/'Evolutive SFP'!#REF! -> #REF! | BB20: ='Evolutive SFP'!I15/'Evolutive SFP'!I27 -> 0.68714746 | BC20: ='Evolutive SFP'!J15/'Evolutive SFP'!J27 -> 0.70488786 | BD20: ='Evolutive SFP'!K15/'Evolutive SFP'!K27 -> 0.71010475 | BE20: ='Evolutive SFP'!L15/'Evolutive SFP'!L27 -> 0.70780247 | BF20: ='Evolutive SFP'!M15/'Evolutive SFP'!M27 -> 0.70686468 | BG20: ='Evolutive SFP'!N15/'Evolutive SFP'!N27 -> 0.70890139 | BH20: ='Evolutive SFP'!O15/'Evolutive SFP'!O27 -> 0.70361633 | BI20: ='Evolutive SFP'!P15/'Evolutive SFP'!P27 -> 0.70675201 | ... CO20: ='Evolutive SFP'!AV15/'Evolutive SFP'!AV27 -> 0.68959482
A21: FUNDING MIX | B21: Total Deposits/Total Assets | D21: ='Evolutive SFP'!#REF!/'Evolutive SFP'!#REF! -> #REF! | E21: ='Evolutive SFP'!#REF!/'Evolutive SFP'!#REF! -> #REF! | F21: ='Evolutive SFP'!#REF!/'Evolutive SFP'!#REF! -> #REF! | G21: ='Evolutive SFP'!#REF!/'Evolutive SFP'!#REF! -> #REF! | H21: ='Evolutive SFP'!#REF!/'Evolutive SFP'!#REF! -> #REF! | I21: ='Evolutive SFP'!#REF!/'Evolutive SFP'!#REF! -> #REF! | J21: ='Evolutive SFP'!#REF!/'Evolutive SFP'!#REF! -> #REF! | K21: ='Evolutive SFP'!#REF!/'Evolutive SFP'!#REF! -> #REF! | ... AS21: ='Evolutive SFP'!#REF!/'Evolutive SFP'!#REF! -> #REF! | AT21: ='Evolutive SFP'!B31/'Evolutive SFP'!B27 -> 0.87830613 | AU21: ='Evolutive SFP'!C31/'Evolutive SFP'!C27 -> 0.68806673 | AV21: ='Evolutive SFP'!D31/'Evolutive SFP'!D27 -> 0.69769775 | AW21: ='Evolutive SFP'!E31/'Evolutive SFP'!E27 -> 0.75055795 | AX21: ='Evolutive SFP'!F31/'Evolutive SFP'!F27 -> 0.74020145 | AY21: ='Evolutive SFP'!G31/'Evolutive SFP'!G27 -> 0.72525953 | AZ21: ='Evolutive SFP'!H31/'Evolutive SFP'!H27 -> 0.73081429 | BA21: ='Evolutive SFP'!#REF!/'Evolutive SFP'!#REF! -> #REF! | BB21: ='Evolutive SFP'!I31/'Evolutive SFP'!I27 -> 0.72325352 | BC21: ='Evolutive SFP'!J31/'Evolutive SFP'!J27 -> 0.71560849 | BD21: ='Evolutive SFP'!K31/'Evolutive SFP'!K27 -> 0.70763826 | BE21: ='Evolutive SFP'!L31/'Evolutive SFP'!L27 -> 0.70368848 | BF21: ='Evolutive SFP'!M31/'Evolutive SFP'!M27 -> 0.69303319 | BG21: ='Evolutive SFP'!N31/'Evolutive SFP'!N27 -> 0.70156217 | BH21: ='Evolutive SFP'!O31/'Evolutive SFP'!O27 -> 0.69683241 | BI21: ='Evolutive SFP'!P31/'Evolutive SFP'!P27 -> 0.70270719 | ... CO21: ='Evolutive SFP'!AV31/'Evolutive SFP'!AV27 -> 0.74855745
B22: BOSA Deposits/Total Assets | D22: ='Evolutive SFP'!#REF!/'Evolutive SFP'!#REF! -> #REF! | E22: ='Evolutive SFP'!#REF!/'Evolutive SFP'!#REF! -> #REF! | F22: ='Evolutive SFP'!#REF!/'Evolutive SFP'!#REF! -> #REF! | G22: ='Evolutive SFP'!#REF!/'Evolutive SFP'!#REF! -> #REF! | H22: ='Evolutive SFP'!#REF!/'Evolutive SFP'!#REF! -> #REF! | I22: ='Evolutive SFP'!#REF!/'Evolutive SFP'!#REF! -> #REF! | J22: ='Evolutive SFP'!#REF!/'Evolutive SFP'!#REF! -> #REF! | K22: ='Evolutive SFP'!#REF!/'Evolutive SFP'!#REF! -> #REF! | ... AS22: ='Evolutive SFP'!#REF!/'Evolutive SFP'!#REF! -> #REF! | AT22: ='Evolutive SFP'!B30/'Evolutive SFP'!B27 -> 0.86813411 | AU22: ='Evolutive SFP'!C30/'Evolutive SFP'!C27 -> 0.61427437 | AV22: ='Evolutive SFP'!D30/'Evolutive SFP'!D27 -> 0.62598376 | AW22: ='Evolutive SFP'!E30/'Evolutive SFP'!E27 -> 0.65546197 | AX22: ='Evolutive SFP'!F30/'Evolutive SFP'!F27 -> 0.64558956 | AY22: ='Evolutive SFP'!G30/'Evolutive SFP'!G27 -> 0.63921876 | AZ22: ='Evolutive SFP'!H30/'Evolutive SFP'!H27 -> 0.64448924 | BA22: ='Evolutive SFP'!#REF!/'Evolutive SFP'!#REF! -> #REF! | BB22: ='Evolutive SFP'!I30/'Evolutive SFP'!I27 -> 0.63791838 | BC22: ='Evolutive SFP'!J30/'Evolutive SFP'!J27 -> 0.63353351 | BD22: ='Evolutive SFP'!K30/'Evolutive SFP'!K27 -> 0.63222372 | BE22: ='Evolutive SFP'!L30/'Evolutive SFP'!L27 -> 0.63085297 | BF22: ='Evolutive SFP'!M30/'Evolutive SFP'!M27 -> 0.62410059 | BG22: ='Evolutive SFP'!N30/'Evolutive SFP'!N27 -> 0.62598575 | BH22: ='Evolutive SFP'!O30/'Evolutive SFP'!O27 -> 0.62399951 | BI22: ='Evolutive SFP'!P30/'Evolutive SFP'!P27 -> 0.62852494 | ... CO22: ='Evolutive SFP'!AV30/'Evolutive SFP'!AV27 -> 0.68486379
B23: FOSA Deposits/Total Assets | D23: =('Evolutive SFP'!#REF!+'Evolutive SFP'!#REF!)/'Evolutive SFP'!#REF! -> #REF! | E23: =('Evolutive SFP'!#REF!+'Evolutive SFP'!#REF!)/'Evolutive SFP'!#REF! -> #REF! | F23: =('Evolutive SFP'!#REF!+'Evolutive SFP'!#REF!)/'Evolutive SFP'!#REF! -> #REF! | G23: =('Evolutive SFP'!#REF!+'Evolutive SFP'!#REF!)/'Evolutive SFP'!#REF! -> #REF! | H23: =('Evolutive SFP'!#REF!+'Evolutive SFP'!#REF!)/'Evolutive SFP'!#REF! -> #REF! | I23: =('Evolutive SFP'!#REF!+'Evolutive SFP'!#REF!)/'Evolutive SFP'!#REF! -> #REF! | J23: =('Evolutive SFP'!#REF!+'Evolutive SFP'!#REF!)/'Evolutive SFP'!#REF! -> #REF! | K23: =('Evolutive SFP'!#REF!+'Evolutive SFP'!#REF!)/'Evolutive SFP'!#REF! -> #REF! | ... AS23: =('Evolutive SFP'!#REF!+'Evolutive SFP'!#REF!)/'Evolutive SFP'!#REF! -> #REF! | AT23: =('Evolutive SFP'!B28+'Evolutive SFP'!B29)/'Evolutive SFP'!B27 -> 0.010172016 | AU23: =('Evolutive SFP'!C28+'Evolutive SFP'!C29)/'Evolutive SFP'!C27 -> 0.07379236 | AV23: =('Evolutive SFP'!D28+'Evolutive SFP'!D29)/'Evolutive SFP'!D27 -> 0.071713989 | AW23: =('Evolutive SFP'!E28+'Evolutive SFP'!E29)/'Evolutive SFP'!E27 -> 0.095095973 | AX23: =('Evolutive SFP'!F28+'Evolutive SFP'!F29)/'Evolutive SFP'!F27 -> 0.094611888 | AY23: =('Evolutive SFP'!G28+'Evolutive SFP'!G29)/'Evolutive SFP'!G27 -> 0.08604077 | AZ23: =('Evolutive SFP'!H28+'Evolutive SFP'!H29)/'Evolutive SFP'!H27 -> 0.086325056 | BA23: =('Evolutive SFP'!#REF!+'Evolutive SFP'!#REF!)/'Evolutive SFP'!#REF! -> #REF! | BB23: =('Evolutive SFP'!I28+'Evolutive SFP'!I29)/'Evolutive SFP'!I27 -> 0.085335138 | BC23: =('Evolutive SFP'!J28+'Evolutive SFP'!J29)/'Evolutive SFP'!J27 -> 0.082074985 | BD23: =('Evolutive SFP'!K28+'Evolutive SFP'!K29)/'Evolutive SFP'!K27 -> 0.075414537 | BE23: =('Evolutive SFP'!L28+'Evolutive SFP'!L29)/'Evolutive SFP'!L27 -> 0.072835507 | BF23: =('Evolutive SFP'!M28+'Evolutive SFP'!M29)/'Evolutive SFP'!M27 -> 0.068932601 | BG23: =('Evolutive SFP'!N28+'Evolutive SFP'!N29)/'Evolutive SFP'!N27 -> 0.075576414 | BH23: =('Evolutive SFP'!O28+'Evolutive SFP'!O29)/'Evolutive SFP'!O27 -> 0.0728329 | BI23: =('Evolutive SFP'!P28+'Evolutive SFP'!P29)/'Evolutive SFP'!P27 -> 0.074182249 | ... CO23: =('Evolutive SFP'!AV28+'Evolutive SFP'!AV29)/'Evolutive SFP'!AV27 -> 0.063693663
A24: GROWTH RATIOS | B24: Total Assets | E24: =(Financials!D4-Financials!C4)/Financials!C4 -> #REF! | H24: =(Financials!G4-Financials!D4)/Financials!D4 -> #REF! | I24: =(Financials!H4-Financials!G4)/Financials!G4 -> #REF! | J24: =(Financials!I4-Financials!H4)/Financials!H4 -> #REF! | K24: =(Financials!J4-Financials!I4)/Financials!I4 -> #REF! | L24: =(Financials!K4-Financials!J4)/Financials!J4 -> #REF! | M24: =(Financials!L4-Financials!K4)/Financials!K4 -> #REF! | N24: =(Financials!M4-Financials!L4)/Financials!L4 -> #REF! | O24: =(Financials!N4-Financials!M4)/Financials!M4 -> #REF! | P24: =(Financials!O4-Financials!N4)/Financials!N4 -> #REF! | ... CO24: =(Financials!CN4-Financials!CM4)/Financials!CM4 -> 0.0060035871
B25: Total Deposits | D25: =Financials!D5/Financials!C5-1 -> #REF! | E25: =Financials!G5/Financials!D5-1 -> #REF! | F25: =Financials!H5/Financials!G5-1 -> #REF! | G25: =Financials!H5/Financials!G5-1 -> #REF! | H25: =Financials!H5/Financials!G5-1 -> #REF! | I25: =Financials!I5/Financials!H5-1 -> #REF! | J25: =Financials!J5/Financials!I5-1 -> #REF! | K25: =Financials!K5/Financials!J5-1 -> #REF! | L25: =Financials!L5/Financials!K5-1 -> #REF! | M25: =Financials!M5/Financials!L5-1 -> #REF! | N25: =Financials!N5/Financials!M5-1 -> #REF! | O25: =Financials!O5/Financials!N5-1 -> #REF! | ... R25: =Financials!R5/Financials!Q5-1 -> #REF! | S25: =Financials!#REF!/Financials!R5-1 -> #REF! | T25: =Financials!#REF!/Financials!S5-1 -> #REF! | U25: =Financials!#REF!/Financials!T5-1 -> #REF! | V25: =Financials!#REF!/Financials!U5-1 -> #REF! | W25: =Financials!#REF!/Financials!V5-1 -> #REF! | X25: =Financials!#REF!/Financials!W5-1 -> #REF! | Y25: =Financials!#REF!/Financials!X5-1 -> #REF! | Z25: =Financials!#REF!/Financials!Y5-1 -> #REF! | ... CO25: =Financials!#REF!/Financials!CN5-1 -> #REF!
B26: BOSA Deposits | D26: =Financials!D6/Financials!C6-1 -> #REF! | E26: =Financials!G6/Financials!D6-1 -> #REF! | F26: =Financials!H6/Financials!G6-1 -> #REF! | G26: =Financials!H6/Financials!G6-1 -> #REF! | H26: =Financials!H6/Financials!G6-1 -> #REF! | I26: =Financials!I6/Financials!H6-1 -> #REF! | J26: =Financials!J6/Financials!I6-1 -> #REF! | K26: =Financials!K6/Financials!J6-1 -> #REF! | L26: =Financials!L6/Financials!K6-1 -> #REF! | M26: =Financials!M6/Financials!L6-1 -> #REF! | N26: =Financials!N6/Financials!M6-1 -> #REF! | O26: =Financials!O6/Financials!N6-1 -> #REF! | ... R26: =Financials!R6/Financials!Q6-1 -> #REF! | S26: =Financials!#REF!/Financials!R6-1 -> #REF! | T26: =Financials!#REF!/Financials!S6-1 -> #REF! | U26: =Financials!#REF!/Financials!T6-1 -> #REF! | V26: =Financials!#REF!/Financials!U6-1 -> #REF! | W26: =Financials!#REF!/Financials!V6-1 -> #REF! | X26: =Financials!#REF!/Financials!W6-1 -> #REF! | Y26: =Financials!#REF!/Financials!X6-1 -> #REF! | Z26: =Financials!#REF!/Financials!Y6-1 -> #REF! | ... CO26: =Financials!#REF!/Financials!CN6-1 -> #REF!
B27: FOSA Deposits | D27: =Financials!D7/Financials!C7-1 -> #REF! | E27: =Financials!G7/Financials!D7-1 -> #REF! | F27: =Financials!H7/Financials!G7-1 -> #REF! | G27: =Financials!H7/Financials!G7-1 -> #REF! | H27: =Financials!H7/Financials!G7-1 -> #REF! | I27: =Financials!I7/Financials!H7-1 -> #REF! | J27: =Financials!J7/Financials!I7-1 -> #REF! | K27: =Financials!K7/Financials!J7-1 -> #REF! | L27: =Financials!L7/Financials!K7-1 -> #REF! | M27: =Financials!M7/Financials!L7-1 -> #REF! | N27: =Financials!N7/Financials!M7-1 -> #REF! | O27: =Financials!O7/Financials!N7-1 -> #REF! | ... R27: =Financials!R7/Financials!Q7-1 -> #REF! | S27: =Financials!#REF!/Financials!R7-1 -> #REF! | T27: =Financials!#REF!/Financials!S7-1 -> #REF! | U27: =Financials!#REF!/Financials!T7-1 -> #REF! | V27: =Financials!#REF!/Financials!U7-1 -> #REF! | W27: =Financials!#REF!/Financials!V7-1 -> #REF! | X27: =Financials!#REF!/Financials!W7-1 -> #REF! | Y27: =Financials!#REF!/Financials!X7-1 -> #REF! | Z27: =Financials!#REF!/Financials!Y7-1 -> #REF! | ... CO27: =Financials!#REF!/Financials!CN7-1 -> #REF!
B28: Total Loans & advances | D28: =Financials!D31/Financials!C31-1 -> #REF! | E28: =Financials!G31/Financials!D31-1 -> #REF! | F28: =Financials!H31/Financials!G31-1 -> #REF! | G28: =Financials!H31/Financials!G31-1 -> #REF! | H28: =Financials!H31/Financials!G31-1 -> #REF! | I28: =Financials!I31/Financials!H31-1 -> #REF! | J28: =Financials!J31/Financials!I31-1 -> #REF! | K28: =Financials!K31/Financials!J31-1 -> #REF! | L28: =Financials!L31/Financials!K31-1 -> #REF! | M28: =Financials!M31/Financials!L31-1 -> #REF! | N28: =Financials!N31/Financials!M31-1 -> #REF! | O28: =Financials!O31/Financials!N31-1 -> #REF! | ... R28: =Financials!R31/Financials!Q31-1 -> #REF! | S28: =Financials!#REF!/Financials!R31-1 -> #REF! | T28: =Financials!#REF!/Financials!S31-1 -> #REF! | U28: =Financials!#REF!/Financials!T31-1 -> #REF! | V28: =Financials!#REF!/Financials!U31-1 -> #REF! | W28: =Financials!#REF!/Financials!V31-1 -> #REF! | X28: =Financials!#REF!/Financials!W31-1 -> #REF! | Y28: =Financials!#REF!/Financials!X31-1 -> #REF! | Z28: =Financials!#REF!/Financials!Y31-1 -> #REF! | ... CO28: =Financials!#REF!/Financials!CN31-1 -> #REF!
B29: Core capital | D29: =Financials!D11/Financials!C11-1 -> #REF! | E29: =Financials!G11/Financials!D11-1 -> #REF! | F29: =Financials!H11/Financials!G11-1 -> #REF! | G29: =Financials!H11/Financials!G11-1 -> #REF! | H29: =Financials!H11/Financials!G11-1 -> #REF! | I29: =Financials!I11/Financials!H11-1 -> #REF! | J29: =Financials!J11/Financials!I11-1 -> #REF! | K29: =Financials!K11/Financials!J11-1 -> #REF! | L29: =Financials!L11/Financials!K11-1 -> #REF! | M29: =Financials!M11/Financials!L11-1 -> #REF! | N29: =Financials!N11/Financials!M11-1 -> #REF! | O29: =Financials!O11/Financials!N11-1 -> #REF! | ... R29: =Financials!R11/Financials!Q11-1 -> #REF! | S29: =Financials!#REF!/Financials!R11-1 -> #REF! | T29: =Financials!#REF!/Financials!S11-1 -> #REF! | U29: =Financials!#REF!/Financials!T11-1 -> #REF! | V29: =Financials!#REF!/Financials!U11-1 -> #REF! | W29: =Financials!#REF!/Financials!V11-1 -> #REF! | X29: =Financials!#REF!/Financials!W11-1 -> #REF! | Y29: =Financials!#REF!/Financials!X11-1 -> #REF! | Z29: =Financials!#REF!/Financials!Y11-1 -> #REF! | ... CO29: =Financials!#REF!/Financials!CN11-1 -> #REF!
B30: Turnover | D30: =Financials!D37/Financials!C37-1 -> #REF! | E30: =Financials!G37/Financials!D37-1 -> #REF! | F30: =Financials!H37/Financials!G37-1 -> #REF! | G30: =Financials!H37/Financials!G37-1 -> #REF! | H30: =Financials!H37/Financials!G37-1 -> #REF! | I30: =Financials!I37/Financials!H37-1 -> #REF! | J30: =Financials!J37/Financials!I37-1 -> #REF! | K30: =Financials!K37/Financials!J37-1 -> #REF! | L30: =Financials!L37/Financials!K37-1 -> #REF! | M30: =Financials!M37/Financials!L37-1 -> #REF! | N30: =Financials!N37/Financials!M37-1 -> #REF! | O30: =Financials!O37/Financials!N37-1 -> #REF! | ... R30: =Financials!R37/Financials!Q37-1 -> #REF! | S30: =Financials!#REF!/Financials!R37-1 -> #REF! | T30: =Financials!#REF!/Financials!S37-1 -> #REF! | U30: =Financials!#REF!/Financials!T37-1 -> #REF! | V30: =Financials!#REF!/Financials!U37-1 -> #REF! | W30: =Financials!#REF!/Financials!V37-1 -> #REF! | X30: =Financials!#REF!/Financials!W37-1 -> #REF! | Y30: =Financials!#REF!/Financials!X37-1 -> #REF! | Z30: =Financials!#REF!/Financials!Y37-1 -> #REF! | ... CO30: =Financials!#REF!/Financials!CN37-1 -> #REF!
B31: Membership
B32: Expenses | D32: ='Evolutitve SCI'!#REF!/'Evolutitve SCI'!#REF!-1 -> #REF! | E32: ='Evolutitve SCI'!#REF!/'Evolutitve SCI'!#REF!-1 -> #REF! | F32: ='Evolutitve SCI'!#REF!/'Evolutitve SCI'!#REF!-1 -> #REF! | G32: ='Evolutitve SCI'!#REF!/'Evolutitve SCI'!#REF!-1 -> #REF! | H32: ='Evolutitve SCI'!#REF!/'Evolutitve SCI'!#REF!-1 -> #REF! | I32: ='Evolutitve SCI'!#REF!/'Evolutitve SCI'!#REF!-1 -> #REF! | J32: ='Evolutitve SCI'!#REF!/'Evolutitve SCI'!#REF!-1 -> #REF! | K32: ='Evolutitve SCI'!#REF!/'Evolutitve SCI'!#REF!-1 -> #REF! | ... AS32: ='Evolutitve SCI'!#REF!/'Evolutitve SCI'!#REF!-1 -> #REF! | AT32: ='Evolutitve SCI'!#REF!/'Evolutitve SCI'!B39-1 -> #REF! | AU32: ='Evolutitve SCI'!#REF!/'Evolutitve SCI'!C39-1 -> #REF! | AV32: ='Evolutitve SCI'!#REF!/'Evolutitve SCI'!D39-1 -> #REF! | AW32: ='Evolutitve SCI'!#REF!/'Evolutitve SCI'!E39-1 -> #REF! | AX32: ='Evolutitve SCI'!#REF!/'Evolutitve SCI'!F39-1 -> #REF! | AY32: ='Evolutitve SCI'!#REF!/'Evolutitve SCI'!G39-1 -> #REF! | AZ32: ='Evolutitve SCI'!#REF!/'Evolutitve SCI'!H39-1 -> #REF! | BA32: ='Evolutitve SCI'!#REF!/'Evolutitve SCI'!#REF!-1 -> #REF! | BB32: ='Evolutitve SCI'!#REF!/'Evolutitve SCI'!I39-1 -> #REF! | BC32: ='Evolutitve SCI'!#REF!/'Evolutitve SCI'!J39-1 -> #REF! | BD32: ='Evolutitve SCI'!#REF!/'Evolutitve SCI'!K39-1 -> #REF! | BE32: ='Evolutitve SCI'!#REF!/'Evolutitve SCI'!L39-1 -> #REF! | BF32: ='Evolutitve SCI'!#REF!/'Evolutitve SCI'!M39-1 -> #REF! | BG32: ='Evolutitve SCI'!#REF!/'Evolutitve SCI'!N39-1 -> #REF! | BH32: ='Evolutitve SCI'!#REF!/'Evolutitve SCI'!O39-1 -> #REF! | BI32: ='Evolutitve SCI'!#REF!/'Evolutitve SCI'!P39-1 -> #REF! | ... CO32: ='Evolutitve SCI'!#REF!/'Evolutitve SCI'!AV39-1 -> #REF!
A33: Efficiency Ratios | B33: FinCost-Deposits/Avg Deposits | E33: =Financials!D44/('Evolutive SFP'!#REF!+'Evolutive SFP'!#REF!)/2 -> #REF! | H33: =Financials!G44/('Evolutive SFP'!#REF!+'Evolutive SFP'!#REF!)/2 -> #REF! | I33: =Financials!H44/('Evolutive SFP'!#REF!+'Evolutive SFP'!#REF!)/2 -> #REF! | J33: =Financials!I44/('Evolutive SFP'!#REF!+'Evolutive SFP'!#REF!)/2 -> #REF! | K33: =Financials!J44/('Evolutive SFP'!#REF!+'Evolutive SFP'!#REF!)/2 -> #REF! | L33: =Financials!K44/('Evolutive SFP'!#REF!+'Evolutive SFP'!#REF!)/2 -> #REF! | M33: =Financials!L44/('Evolutive SFP'!#REF!+'Evolutive SFP'!#REF!)/2 -> #REF! | N33: =Financials!M44/('Evolutive SFP'!#REF!+'Evolutive SFP'!#REF!)/2 -> #REF! | O33: =Financials!N44/('Evolutive SFP'!#REF!+'Evolutive SFP'!#REF!)/2 -> #REF! | ... AS33: =Financials!AR44/('Evolutive SFP'!#REF!+'Evolutive SFP'!#REF!)/2 -> #REF! | AT33: =Financials!AS44/('Evolutive SFP'!#REF!+'Evolutive SFP'!B30)/2 -> #REF! | AU33: =Financials!AT44/('Evolutive SFP'!B30+'Evolutive SFP'!C30)/2 -> 3.9904335e-05 | AV33: =Financials!AU44/('Evolutive SFP'!C30+'Evolutive SFP'!D30)/2 -> 0.0050159027 | AW33: =Financials!AV44/('Evolutive SFP'!D30+'Evolutive SFP'!E30)/2 -> 0.0075677765 | AX33: =Financials!AW44/('Evolutive SFP'!E30+'Evolutive SFP'!F30)/2 -> 0.0098887258 | AY33: =Financials!AX44/('Evolutive SFP'!F30+'Evolutive SFP'!G30)/2 -> 0.01260414 | AZ33: =Financials!AY44/('Evolutive SFP'!G30+'Evolutive SFP'!H30)/2 -> 0.015140926 | BA33: =Financials!AZ44/('Evolutive SFP'!H30+'Evolutive SFP'!#REF!)/2 -> #REF! | BB33: =Financials!BA44/('Evolutive SFP'!#REF!+'Evolutive SFP'!I30)/2 -> #REF! | BC33: =Financials!BB44/('Evolutive SFP'!I30+'Evolutive SFP'!J30)/2 -> 0.022208722 | BD33: =Financials!BC44/('Evolutive SFP'!J30+'Evolutive SFP'!K30)/2 -> 0.025179593 | BE33: =Financials!BD44/('Evolutive SFP'!K30+'Evolutive SFP'!L30)/2 -> 0.027652912 | BF33: =Financials!BE44/('Evolutive SFP'!L30+'Evolutive SFP'!M30)/2 -> 0.030358812 | BG33: =Financials!BF44/('Evolutive SFP'!M30+'Evolutive SFP'!N30)/2 -> 0.056220585 | BH33: =Financials!BG44/('Evolutive SFP'!N30+'Evolutive SFP'!O30)/2 -> 5.0970885e-06 | BI33: =Financials!BH44/('Evolutive SFP'!O30+'Evolutive SFP'!P30)/2 -> 0.0049946488 | BJ33: =Financials!BI44/('Evolutive SFP'!P30+'Evolutive SFP'!Q30)/2 -> 0.0074821655 | ... CO33: =Financials!CN44/('Evolutive SFP'!AU30+'Evolutive SFP'!AV30)/2 -> 0.019502879
B34: FinCost-Shares/Avg Share capital | E34: =Financials!D45/('Evolutive SFP'!#REF!+'Evolutive SFP'!#REF!)/2 -> #REF! | H34: =Financials!G45/('Evolutive SFP'!#REF!+'Evolutive SFP'!#REF!)/2 -> #REF! | I34: =Financials!H45/('Evolutive SFP'!#REF!+'Evolutive SFP'!#REF!)/2 -> #REF! | J34: =Financials!I45/('Evolutive SFP'!#REF!+'Evolutive SFP'!#REF!)/2 -> #REF! | K34: =Financials!J45/('Evolutive SFP'!#REF!+'Evolutive SFP'!#REF!)/2 -> #REF! | L34: =Financials!K45/('Evolutive SFP'!#REF!+'Evolutive SFP'!#REF!)/2 -> #REF! | M34: =Financials!L45/('Evolutive SFP'!#REF!+'Evolutive SFP'!#REF!)/2 -> #REF! | N34: =Financials!M45/('Evolutive SFP'!#REF!+'Evolutive SFP'!#REF!)/2 -> #REF! | O34: =Financials!N45/('Evolutive SFP'!#REF!+'Evolutive SFP'!#REF!)/2 -> #REF! | ... AS34: =Financials!AR45/('Evolutive SFP'!#REF!+'Evolutive SFP'!#REF!)/2 -> #REF! | AT34: =Financials!AS45/('Evolutive SFP'!#REF!+'Evolutive SFP'!B39)/2 -> #REF! | AU34: =Financials!AT45/('Evolutive SFP'!B39+'Evolutive SFP'!C39)/2 -> 7.9400101e-05 | AV34: =Financials!AU45/('Evolutive SFP'!C39+'Evolutive SFP'!D39)/2 -> 0.0083547278 | AW34: =Financials!AV45/('Evolutive SFP'!D39+'Evolutive SFP'!E39)/2 -> 0.012541561 | AX34: =Financials!AW45/('Evolutive SFP'!E39+'Evolutive SFP'!F39)/2 -> 0.016668561 | AY34: =Financials!AX45/('Evolutive SFP'!F39+'Evolutive SFP'!G39)/2 -> 0.020897337 | AZ34: =Financials!AY45/('Evolutive SFP'!G39+'Evolutive SFP'!H39)/2 -> 0.025070255 | BA34: =Financials!AZ45/('Evolutive SFP'!H39+'Evolutive SFP'!#REF!)/2 -> #REF! | BB34: =Financials!BA45/('Evolutive SFP'!#REF!+'Evolutive SFP'!I39)/2 -> #REF! | BC34: =Financials!BB45/('Evolutive SFP'!I39+'Evolutive SFP'!J39)/2 -> 0.037551164 | BD34: =Financials!BC45/('Evolutive SFP'!J39+'Evolutive SFP'!K39)/2 -> 0.041777443 | BE34: =Financials!BD45/('Evolutive SFP'!K39+'Evolutive SFP'!L39)/2 -> 0.045888688 | BF34: =Financials!BE45/('Evolutive SFP'!L39+'Evolutive SFP'!M39)/2 -> 0.050070433 | BG34: =Financials!BF45/('Evolutive SFP'!M39+'Evolutive SFP'!N39)/2 -> 0 | BH34: =Financials!BG45/('Evolutive SFP'!N39+'Evolutive SFP'!O39)/2 -> 8.3688533e-06 | BI34: =Financials!BH45/('Evolutive SFP'!O39+'Evolutive SFP'!P39)/2 -> 0.0083415573 | BJ34: =Financials!BI45/('Evolutive SFP'!P39+'Evolutive SFP'!Q39)/2 -> 0.012516415 | ... CO34: =Financials!CN45/('Evolutive SFP'!AU39+'Evolutive SFP'!AV39)/2 -> 0.033391468
B35: FinCost-Ext Loans/Avg Ext Loans | E35: =Financials!D46/(Financials!C31+Financials!D31)/2 -> #REF! | H35: =Financials!G46/(Financials!D31+Financials!G31)/2 -> #REF! | I35: =Financials!H46/(Financials!G31+Financials!H31)/2 -> #REF! | J35: =Financials!I46/(Financials!H31+Financials!I31)/2 -> #REF! | K35: =Financials!J46/(Financials!I31+Financials!J31)/2 -> #REF! | L35: =Financials!K46/(Financials!J31+Financials!K31)/2 -> #REF! | M35: =Financials!L46/(Financials!K31+Financials!L31)/2 -> #REF! | N35: =Financials!M46/(Financials!L31+Financials!M31)/2 -> #REF! | O35: =Financials!N46/(Financials!M31+Financials!N31)/2 -> #REF! | P35: =Financials!O46/(Financials!N31+Financials!O31)/2 -> #REF! | ... CO35: =Financials!CN46/(Financials!CM31+Financials!CN31)/2 -> 0
B36: OpEx/Average Total Assets | E36: =Financials!D47/(Financials!C4+Financials!D4)/2 -> #REF! | H36: =Financials!G47/(Financials!D4+Financials!G4)/2 -> #REF! | I36: =Financials!H47/(Financials!G4+Financials!H4)/2 -> #REF! | J36: =Financials!I47/(Financials!H4+Financials!I4)/2 -> #REF! | K36: =Financials!J47/(Financials!I4+Financials!J4)/2 -> #REF! | L36: =Financials!K47/(Financials!J4+Financials!K4)/2 -> #REF! | M36: =Financials!L47/(Financials!K4+Financials!L4)/2 -> #REF! | N36: =Financials!M47/(Financials!L4+Financials!M4)/2 -> #REF! | O36: =Financials!N47/(Financials!M4+Financials!N4)/2 -> #REF! | P36: =Financials!O47/(Financials!N4+Financials!O4)/2 -> #REF! | ... CO36: =Financials!CN47/(Financials!CM4+Financials!CN4)/2 -> 0.0032629764
B37: Opex/Turnover | E37: =Financials!D47/Financials!D37 -> #REF! | H37: =Financials!G47/Financials!G37 -> #REF! | I37: =Financials!H47/Financials!H37 -> #REF! | J37: =Financials!I47/Financials!I37 -> #REF! | K37: =Financials!J47/Financials!J37 -> #REF! | L37: =Financials!K47/Financials!K37 -> #REF! | M37: =Financials!L47/Financials!L37 -> #REF! | N37: =Financials!M47/Financials!M37 -> #REF! | O37: =Financials!N47/Financials!N37 -> #REF! | ... CO37: =Financials!CN47/Financials!CN37 -> 0.14287154
B38: Avge yield on Net loans | E38: =Financials!D38/('Evolutive SFP'!#REF!+'Evolutive SFP'!#REF!)/2 -> #REF! | H38: =Financials!G38/('Evolutive SFP'!#REF!+'Evolutive SFP'!#REF!)/2 -> #REF! | I38: =Financials!H38/('Evolutive SFP'!#REF!+'Evolutive SFP'!#REF!)/2 -> #REF! | J38: =Financials!I38/('Evolutive SFP'!#REF!+'Evolutive SFP'!#REF!)/2 -> #REF! | K38: =Financials!J38/('Evolutive SFP'!#REF!+'Evolutive SFP'!#REF!)/2 -> #REF! | L38: =Financials!K38/('Evolutive SFP'!#REF!+'Evolutive SFP'!#REF!)/2 -> #REF! | M38: =Financials!L38/('Evolutive SFP'!#REF!+'Evolutive SFP'!#REF!)/2 -> #REF! | N38: =Financials!M38/('Evolutive SFP'!#REF!+'Evolutive SFP'!#REF!)/2 -> #REF! | O38: =Financials!N38/('Evolutive SFP'!#REF!+'Evolutive SFP'!#REF!)/2 -> #REF! | ... AS38: =Financials!AR38/('Evolutive SFP'!#REF!+'Evolutive SFP'!#REF!)/2 -> #REF! | AT38: =Financials!AS38/('Evolutive SFP'!B14+'Evolutive SFP'!#REF!)/2 -> #REF! | AU38: =Financials!AT38/('Evolutive SFP'!C14+'Evolutive SFP'!B14)/2 -> 6.288516e-05 | AV38: =Financials!AU38/('Evolutive SFP'!D14+'Evolutive SFP'!C14)/2 -> 0.0059714334 | AW38: =Financials!AV38/('Evolutive SFP'!E14+'Evolutive SFP'!D14)/2 -> 0.0092401026 | AX38: =Financials!AW38/('Evolutive SFP'!F14+'Evolutive SFP'!E14)/2 -> 0.012688964 | AY38: =Financials!AX38/('Evolutive SFP'!G14+'Evolutive SFP'!F14)/2 -> 0.015920987 | AZ38: =Financials!AY38/('Evolutive SFP'!H14+'Evolutive SFP'!G14)/2 -> 0.019150885 | BA38: =Financials!AZ38/('Evolutive SFP'!#REF!+'Evolutive SFP'!H14)/2 -> #REF! | BB38: =Financials!BA38/('Evolutive SFP'!I14+'Evolutive SFP'!#REF!)/2 -> #REF! | BC38: =Financials!BB38/('Evolutive SFP'!J14+'Evolutive SFP'!I14)/2 -> 0.026465766 | BD38: =Financials!BC38/('Evolutive SFP'!K14+'Evolutive SFP'!J14)/2 -> 0.02881438 | BE38: =Financials!BD38/('Evolutive SFP'!L14+'Evolutive SFP'!K14)/2 -> 0.031165081 | BF38: =Financials!BE38/('Evolutive SFP'!M14+'Evolutive SFP'!L14)/2 -> 0.033745565 | BG38: =Financials!BF38/('Evolutive SFP'!N14+'Evolutive SFP'!M14)/2 -> 0.066391376 | BH38: =Financials!BG38/('Evolutive SFP'!O14+'Evolutive SFP'!N14)/2 -> 5.8634733e-06 | BI38: =Financials!BH38/('Evolutive SFP'!P14+'Evolutive SFP'!O14)/2 -> 0.005660604 | BJ38: =Financials!BI38/('Evolutive SFP'!Q14+'Evolutive SFP'!P14)/2 -> 0.0087811486 | ... CO38: =Financials!CN38/('Evolutive SFP'!AV14+'Evolutive SFP'!AU14)/2 -> 0.02150649
B39: Avge yield on Gross loans | E39: =Financials!D37/('Evolutive SFP'!#REF!+'Evolutive SFP'!#REF!)/2 -> #REF! | H39: =Financials!G37/('Evolutive SFP'!#REF!+'Evolutive SFP'!#REF!)/2 -> #REF! | I39: =Financials!H37/('Evolutive SFP'!#REF!+'Evolutive SFP'!#REF!)/2 -> #REF! | J39: =Financials!I37/('Evolutive SFP'!#REF!+'Evolutive SFP'!#REF!)/2 -> #REF! | K39: =Financials!J37/('Evolutive SFP'!#REF!+'Evolutive SFP'!#REF!)/2 -> #REF! | L39: =Financials!K37/('Evolutive SFP'!#REF!+'Evolutive SFP'!#REF!)/2 -> #REF! | M39: =Financials!L37/('Evolutive SFP'!#REF!+'Evolutive SFP'!#REF!)/2 -> #REF! | N39: =Financials!M37/('Evolutive SFP'!#REF!+'Evolutive SFP'!#REF!)/2 -> #REF! | O39: =Financials!N37/('Evolutive SFP'!#REF!+'Evolutive SFP'!#REF!)/2 -> #REF! | ... AS39: =Financials!AR37/('Evolutive SFP'!#REF!+'Evolutive SFP'!#REF!)/2 -> #REF! | AT39: =Financials!AS37/('Evolutive SFP'!B15+'Evolutive SFP'!#REF!)/2 -> #REF! | AU39: =Financials!AT37/('Evolutive SFP'!C15+'Evolutive SFP'!B15)/2 -> 6.1175761e-05 | AV39: =Financials!AU37/('Evolutive SFP'!D15+'Evolutive SFP'!C15)/2 -> 0.0068329875 | AW39: =Financials!AV37/('Evolutive SFP'!E15+'Evolutive SFP'!D15)/2 -> 0.010739772 | AX39: =Financials!AW37/('Evolutive SFP'!F15+'Evolutive SFP'!E15)/2 -> 0.021049256 | AY39: =Financials!AX37/('Evolutive SFP'!G15+'Evolutive SFP'!F15)/2 -> 0.025273799 | AZ39: =Financials!AY37/('Evolutive SFP'!H15+'Evolutive SFP'!G15)/2 -> 0.029242417 | BA39: =Financials!AZ37/('Evolutive SFP'!#REF!+'Evolutive SFP'!H15)/2 -> #REF! | BB39: =Financials!BA37/('Evolutive SFP'!I15+'Evolutive SFP'!#REF!)/2 -> #REF! | BC39: =Financials!BB37/('Evolutive SFP'!J15+'Evolutive SFP'!I15)/2 -> 0.038687088 | BD39: =Financials!BC37/('Evolutive SFP'!K15+'Evolutive SFP'!J15)/2 -> 0.041336821 | BE39: =Financials!BD37/('Evolutive SFP'!L15+'Evolutive SFP'!K15)/2 -> 0.043961558 | BF39: =Financials!BE37/('Evolutive SFP'!M15+'Evolutive SFP'!L15)/2 -> 0.047427307 | BG39: =Financials!BF37/('Evolutive SFP'!N15+'Evolutive SFP'!M15)/2 -> 0.09329666 | BH39: =Financials!BG37/('Evolutive SFP'!O15+'Evolutive SFP'!N15)/2 -> 5.9969123e-06 | BI39: =Financials!BH37/('Evolutive SFP'!P15+'Evolutive SFP'!O15)/2 -> 0.0068775847 | BJ39: =Financials!BI37/('Evolutive SFP'!Q15+'Evolutive SFP'!P15)/2 -> 0.010896099 | ... CO39: =Financials!CN37/('Evolutive SFP'!AV15+'Evolutive SFP'!AU15)/2 -> 0.033478872
A41: ALL/Average Gross Loan portfolio

Sheet Financials
B1: TEMBO Sacco Financial
B2: Year | C2: 2013 Audited | D2: 2014 Audited | E2: 2015 Audited | F2: 2016 Audited | G2: 42736 | H2: 42767 | I2: 42795 | J2: 42826 | K2: 42856 | L2: 42887 | M2: 42917 | N2: 42948 | O2: 42979 | P2: 43009 | Q2: 43040 | R2: 43070 | S2: Audited 2017 | T2: 43101 | U2: 43132 | V2: 43160 | W2: 43191 | X2: 43221 | Y2: 43252 | Z2: 43282 | AA2: 43313 | AB2: 43344 | AC2: 43374 | AD2: 43405 | AE2: 43435 | AF2: Audited 2018 | AG2: 43466 | AH2: 43497 | AI2: 43525 | AJ2: 43556 | AK2: 43586 | AL2: 43617 | AM2: 43647 | AN2: 43678 | AO2: 43709 | AP2: 43739 | AQ2: 43770 | AR2: 43800 | AS2: Audited 2019 | AT2: 43831 | AU2: 43862 | AV2: 43891 | AW2: 43922 | AX2: 43952 | AY2: 43983 | AZ2: 44013 | BA2: 44044 | BB2: 44075 | BC2: 44105 | BD2: 44136 | BE2: 44166 | BF2: Audited 2020 | BG2: 44197 | BH2: 44228 | BI2: 44256 | BJ2: 44287 | BK2: 44317 | BL2: 44348 | BM2: 44378 | BN2: 44409 | BO2: 44440 | BP2: 44470 | BQ2: 44501 | BR2: 44531 | BS2: AUDITED 2021 | BT2: 44562 | BU2: 44593 | BV2: 44621 | BW2: 44652 | BX2: 44682 | BY2: 44713 | BZ2: 44743 | CA2: 44774 | CB2: 44805 | CC2: 44835 | CD2: 44866 | CE2: 44896 | CF2: AUDITED 2022 | CG2: 44927 | CH2: 44958 | CI2: 44986 | CJ2: 45017 | CK2: 45047 | CL2: 45078 | CM2: 45108 | CN2: 45139
A3: 1 | B3: Membership | D3: 39898 | E3: 55854
A4: 2 | B4: Total Assets | C4: ='Evolutive SFP'!#REF! -> #REF! | D4: ='Evolutive SFP'!#REF! -> #REF! | E4: ='Evolutive SFP'!#REF! -> #REF! | F4: ='Evolutive SFP'!#REF! -> #REF! | G4: ='Evolutive SFP'!#REF! -> #REF! | H4: ='Evolutive SFP'!#REF! -> #REF! | I4: ='Evolutive SFP'!#REF! -> #REF! | J4: ='Evolutive SFP'!#REF! -> #REF! | ... AR4: ='Evolutive SFP'!#REF! -> #REF! | AS4: ='Evolutive SFP'!B27 -> 2.9341168e+08 | AT4: ='Evolutive SFP'!C27 -> 3166395.3 | AU4: ='Evolutive SFP'!D27 -> 3158788.5 | AV4: ='Evolutive SFP'!E27 -> 3099454.1 | AW4: ='Evolutive SFP'!F27 -> 3168003.6 | AX4: ='Evolutive SFP'!G27 -> 3250660.8 | AY4: ='Evolutive SFP'!H27 -> 3277864 | AZ4: ='Evolutive SFP'!#REF! -> #REF! | BA4: ='Evolutive SFP'!I27 -> 3397046.1 | BB4: ='Evolutive SFP'!J27 -> 3438556.2 | BC4: ='Evolutive SFP'!K27 -> 3496488.1 | BD4: ='Evolutive SFP'!L27 -> 3555260.6 | BE4: ='Evolutive SFP'!M27 -> 3628251.5 | BF4: ='Evolutive SFP'!N27 -> 3617548491 | BG4: ='Evolutive SFP'!O27 -> 3664644 | BH4: ='Evolutive SFP'!P27 -> 3682354 | ... CN4: ='Evolutive SFP'!AV27 -> 5.3896903e+09
A5: 3 | B5: Total Deposits | C5: ='Evolutive SFP'!#REF! -> #REF! | D5: ='Evolutive SFP'!#REF! -> #REF! | E5: ='Evolutive SFP'!#REF! -> #REF! | F5: ='Evolutive SFP'!#REF! -> #REF! | G5: ='Evolutive SFP'!#REF! -> #REF! | H5: ='Evolutive SFP'!#REF! -> #REF! | I5: ='Evolutive SFP'!#REF! -> #REF! | J5: ='Evolutive SFP'!#REF! -> #REF! | ... AR5: ='Evolutive SFP'!#REF! -> #REF! | AS5: ='Evolutive SFP'!B31 -> 2.5770528e+08 | AT5: ='Evolutive SFP'!C31 -> 2178691.2 | AU5: ='Evolutive SFP'!D31 -> 2203879.6 | AV5: ='Evolutive SFP'!E31 -> 2326319.9 | AW5: ='Evolutive SFP'!F31 -> 2344960.8 | AX5: ='Evolutive SFP'!G31 -> 2357572.7 | AY5: ='Evolutive SFP'!H31 -> 2395509.8 | AZ5: ='Evolutive SFP'!#REF! -> #REF! | BA5: ='Evolutive SFP'!I31 -> 2456925.6 | BB5: ='Evolutive SFP'!J31 -> 2460660 | BC5: ='Evolutive SFP'!K31 -> 2474248.7 | BD5: ='Evolutive SFP'!L31 -> 2501795.9 | BE5: ='Evolutive SFP'!M31 -> 2514498.7 | BF5: ='Evolutive SFP'!N31 -> 2537935152 | BG5: ='Evolutive SFP'!O31 -> 2553642.7 | BH5: ='Evolutive SFP'!P31 -> 2587616.6 | ... CN5: ='Evolutive SFP'!AV31 -> 4.0344928e+09
A6: 3.1 | B6: Deposits-Members(BOSA) | C6: ='Evolutive SFP'!#REF! -> #REF! | D6: ='Evolutive SFP'!#REF! -> #REF! | E6: ='Evolutive SFP'!#REF! -> #REF! | F6: ='Evolutive SFP'!#REF! -> #REF! | G6: ='Evolutive SFP'!#REF! -> #REF! | H6: ='Evolutive SFP'!#REF! -> #REF! | I6: ='Evolutive SFP'!#REF! -> #REF! | J6: ='Evolutive SFP'!#REF! -> #REF! | ... AR6: ='Evolutive SFP'!#REF! -> #REF! | AS6: ='Evolutive SFP'!B30 -> 254720687 | AT6: ='Evolutive SFP'!C30 -> 1945035.4 | AU6: ='Evolutive SFP'!D30 -> 1977350.3 | AV6: ='Evolutive SFP'!E30 -> 2031574.3 | AW6: ='Evolutive SFP'!F30 -> 2045230 | AX6: ='Evolutive SFP'!G30 -> 2077883.4 | AY6: ='Evolutive SFP'!H30 -> 2112548 | AZ6: ='Evolutive SFP'!#REF! -> #REF! | BA6: ='Evolutive SFP'!I30 -> 2167038.2 | BB6: ='Evolutive SFP'!J30 -> 2178440.6 | BC6: ='Evolutive SFP'!K30 -> 2210562.7 | BD6: ='Evolutive SFP'!L30 -> 2242846.7 | BE6: ='Evolutive SFP'!M30 -> 2264393.9 | BF6: ='Evolutive SFP'!N30 -> 2264533808 | BG6: ='Evolutive SFP'!O30 -> 2286736.1 | BH6: ='Evolutive SFP'!P30 -> 2314451.3 | ... CN6: ='Evolutive SFP'!AV30 -> 3.6912037e+09
A7: 3.2 | B7: Deposits-Customers(FOSA) | C7: =('Evolutive SFP'!#REF!+'Evolutive SFP'!#REF!) -> #REF! | D7: =('Evolutive SFP'!#REF!+'Evolutive SFP'!#REF!) -> #REF! | E7: =('Evolutive SFP'!#REF!+'Evolutive SFP'!#REF!) -> #REF! | F7: =('Evolutive SFP'!#REF!+'Evolutive SFP'!#REF!) -> #REF! | G7: =('Evolutive SFP'!#REF!+'Evolutive SFP'!#REF!) -> #REF! | H7: =('Evolutive SFP'!#REF!+'Evolutive SFP'!#REF!) -> #REF! | I7: =('Evolutive SFP'!#REF!+'Evolutive SFP'!#REF!) -> #REF! | J7: =('Evolutive SFP'!#REF!+'Evolutive SFP'!#REF!) -> #REF! | ... AR7: =('Evolutive SFP'!#REF!+'Evolutive SFP'!#REF!) -> #REF! | AS7: =('Evolutive SFP'!B28+'Evolutive SFP'!B29) -> 2984588.2 | AT7: =('Evolutive SFP'!C28+'Evolutive SFP'!C29) -> 233655.78 | AU7: =('Evolutive SFP'!D28+'Evolutive SFP'!D29) -> 226529.32 | AV7: =('Evolutive SFP'!E28+'Evolutive SFP'!E29) -> 294745.6 | AW7: =('Evolutive SFP'!F28+'Evolutive SFP'!F29) -> 299730.8 | AX7: =('Evolutive SFP'!G28+'Evolutive SFP'!G29) -> 279689.36 | AY7: =('Evolutive SFP'!H28+'Evolutive SFP'!H29) -> 282961.79 | AZ7: =('Evolutive SFP'!#REF!+'Evolutive SFP'!#REF!) -> #REF! | BA7: =('Evolutive SFP'!I28+'Evolutive SFP'!I29) -> 289887.4 | BB7: =('Evolutive SFP'!J28+'Evolutive SFP'!J29) -> 282219.45 | BC7: =('Evolutive SFP'!K28+'Evolutive SFP'!K29) -> 263686.03 | BD7: =('Evolutive SFP'!L28+'Evolutive SFP'!L29) -> 258949.21 | BE7: =('Evolutive SFP'!M28+'Evolutive SFP'!M29) -> 250104.81 | BF7: =('Evolutive SFP'!N28+'Evolutive SFP'!N29) -> 273401344 | BG7: =('Evolutive SFP'!O28+'Evolutive SFP'!O29) -> 266906.65 | BH7: =('Evolutive SFP'!P28+'Evolutive SFP'!P29) -> 273165.3 | ... CN7: =('Evolutive SFP'!AV28+'Evolutive SFP'!AV29) -> 3.4328912e+08
A8: 4 | B8: External Borrowing | C8: ='Evolutive SFP'!#REF! -> #REF! | D8: ='Evolutive SFP'!#REF! -> #REF! | E8: ='Evolutive SFP'!#REF! -> #REF! | F8: ='Evolutive SFP'!#REF! -> #REF! | G8: ='Evolutive SFP'!#REF! -> #REF! | H8: ='Evolutive SFP'!#REF! -> #REF! | I8: ='Evolutive SFP'!#REF! -> #REF! | J8: ='Evolutive SFP'!#REF! -> #REF! | ... AR8: ='Evolutive SFP'!#REF! -> #REF! | AS8: ='Evolutive SFP'!B37 -> 0 | AT8: ='Evolutive SFP'!C37 -> 0 | AU8: ='Evolutive SFP'!D37 -> 0 | AV8: ='Evolutive SFP'!E37 -> 0 | AW8: ='Evolutive SFP'!F37 -> 0 | AX8: ='Evolutive SFP'!G37 -> 0 | AY8: ='Evolutive SFP'!H37 -> 0 | AZ8: ='Evolutive SFP'!#REF! -> #REF! | BA8: ='Evolutive SFP'!I37 -> 0 | BB8: ='Evolutive SFP'!J37 -> 0 | BC8: ='Evolutive SFP'!K37 -> 0 | BD8: ='Evolutive SFP'!L37 -> 0 | BE8: ='Evolutive SFP'!M37 -> 0 | BF8: ='Evolutive SFP'!N37 -> 0 | BG8: ='Evolutive SFP'!O37 -> 0 | BH8: ='Evolutive SFP'!P37 -> 0 | ... CN8: ='Evolutive SFP'!AV37 -> 0
B9: Short term Liabilities | D9: =SUM('Evolutive SFP'!#REF!) -> #REF! | E9: =SUM('Evolutive SFP'!#REF!) -> #REF! | F9: =SUM('Evolutive SFP'!#REF!) -> #REF! | G9: =SUM('Evolutive SFP'!#REF!) -> #REF! | H9: =SUM('Evolutive SFP'!#REF!) -> #REF! | I9: =SUM('Evolutive SFP'!#REF!) -> #REF! | J9: =SUM('Evolutive SFP'!#REF!) -> #REF! | K9: =SUM('Evolutive SFP'!#REF!) -> #REF! | ... AR9: =SUM('Evolutive SFP'!#REF!) -> #REF! | AS9: =SUM('Evolutive SFP'!B32:B36) -> 413121 | AT9: =SUM('Evolutive SFP'!C32:C36) -> 296589.86 | AU9: =SUM('Evolutive SFP'!D32:D36) -> 312712.62 | AV9: =SUM('Evolutive SFP'!E32:E36) -> 132547.52 | AW9: =SUM('Evolutive SFP'!F32:F36) -> 131340.2 | AX9: =SUM('Evolutive SFP'!G32:G36) -> 153270.03 | AY9: =SUM('Evolutive SFP'!H32:H36) -> 184267.37 | AZ9: =SUM('Evolutive SFP'!#REF!) -> #REF! | BA9: =SUM('Evolutive SFP'!I32:I36) -> 222326.61 | BB9: =SUM('Evolutive SFP'!J32:J36) -> 247837.32 | BC9: =SUM('Evolutive SFP'!K32:K36) -> 276810.27 | BD9: =SUM('Evolutive SFP'!L32:L36) -> 309841.09 | BE9: =SUM('Evolutive SFP'!M32:M36) -> 334588.4 | BF9: =SUM('Evolutive SFP'!N32:N36) -> 293794285 | BG9: =SUM('Evolutive SFP'!O32:O36) -> 366554.49 | BH9: =SUM('Evolutive SFP'!P32:P36) -> 367425.41 | ... CN9: =SUM('Evolutive SFP'!AV32:AV36) -> 2.920096e+08
A10: 5 | B10: Share capital and Reserves
A11: 5.1 | B11: Core Capital | C11: =C14-C22-C26-C27 -> #REF! | D11: =D14-D22-D26-D27 -> #REF! | E11: =E14-E22-E26-E27 -> #REF! | F11: =F14-F22-F26-F27 -> #REF! | G11: =G14-G22-G26-G27 -> #REF! | H11: =H14-H22-H26-H27 -> #REF! | I11: =I14-I22-I26-I27 -> #REF! | J11: =J14-J22-J26-J27 -> #REF! | ... R11: =R14-R22-R26-R27 -> #REF! | S11: =S14-S22-S27 -> #REF! | T11: =T14-T22-T27 -> #REF! | U11: =U14-U22-U27 -> #REF! | V11: =V14-V22 -> #REF! | W11: =W14-W22 -> #REF! | X11: =X14-X22 -> #REF! | Y11: =Y14-Y22 -> #REF! | Z11: =Z14-Z22 -> #REF! | AA11: =AA14-AA22 -> #REF! | AB11: =AB14-AB22 -> #REF! | AC11: =AC14-AC22 -> #REF! | ... CN11: =CN14-CN22 -> 9.7646801e+08
A12: 5.2 | B12: Institutional Capital | C12: =C11-C15 -> #REF! | D12: =D11-D15 -> #REF! | E12: =E11-E15 -> #REF! | F12: =F11-F15 -> #REF! | G12: =G11-G15 -> #REF! | H12: =H11-H15 -> #REF! | I12: =I11-I15 -> #REF! | J12: =J11-J15 -> #REF! | ... CN12: =CN11-CN15 -> 7.4255112e+08
A14: 5.3 | B14: Total Capital | C14: =C15+C16+C17+C18+C19+C20+C21 -> #REF! | D14: =D15+D16+D17+D18+D19+D20+D21 -> #REF! | E14: =E15+E16+E17+E18+E19+E20+E21 -> #REF! | F14: =F15+F16+F17+F18+F19+F20+F21 -> #REF! | G14: =G15+G16+G17+G18+G19+G20+G21 -> #REF! | H14: =H15+H16+H17+H18+H19+H20+H21 -> #REF! | I14: =I15+I16+I17+I18+I19+I20+I21 -> #REF! | J14: =J15+J16+J17+J18+J19+J20+J21 -> #REF! | ... CN14: =CN15+CN16+CN17+CN18+CN19+CN20+CN21 -> 1.0076569e+09
A15: 5.3.1 | B15: Members Share Capital | C15: ='Evolutive SFP'!#REF! -> #REF! | D15: ='Evolutive SFP'!#REF! -> #REF! | E15: ='Evolutive SFP'!#REF! -> #REF! | F15: ='Evolutive SFP'!#REF! -> #REF! | G15: ='Evolutive SFP'!#REF! -> #REF! | H15: ='Evolutive SFP'!#REF! -> #REF! | I15: ='Evolutive SFP'!#REF! -> #REF! | J15: ='Evolutive SFP'!#REF! -> #REF! | ... AR15: ='Evolutive SFP'!#REF! -> #REF! | AS15: ='Evolutive SFP'!B39 -> 18970134 | AT15: ='Evolutive SFP'!C39 -> 182486.39 | AU15: ='Evolutive SFP'!D39 -> 183425.59 | AV15: ='Evolutive SFP'!E39 -> 184649.41 | AW15: ='Evolutive SFP'!F39 -> 184691.41 | AX15: ='Evolutive SFP'!G39 -> 185829 | AY15: ='Evolutive SFP'!H39 -> 186876.42 | AZ15: ='Evolutive SFP'!#REF! -> #REF! | BA15: ='Evolutive SFP'!I39 -> 188826.42 | BB15: ='Evolutive SFP'!J39 -> 189342.42 | BC15: ='Evolutive SFP'!K39 -> 190311.74 | BD15: ='Evolutive SFP'!L39 -> 190771.94 | BE15: ='Evolutive SFP'!M39 -> 191310.14 | BF15: ='Evolutive SFP'!N39 -> 191287939 | BG15: ='Evolutive SFP'!O39 -> 192296.14 | BH15: ='Evolutive SFP'!P39 -> 192676.34 | ... CN15: ='Evolutive SFP'!AV39 -> 2.3391689e+08
A16: 5.3.2 | B16: Entrance Fees
A17: 5.3.3 | B17: Retained Earnings | C17: ='Evolutive SFP'!#REF! -> #REF! | D17: ='Evolutive SFP'!#REF! -> #REF! | E17: ='Evolutive SFP'!#REF! -> #REF! | F17: ='Evolutive SFP'!#REF! -> #REF! | G17: ='Evolutive SFP'!#REF! -> #REF! | H17: ='Evolutive SFP'!#REF! -> #REF! | I17: ='Evolutive SFP'!#REF! -> #REF! | J17: ='Evolutive SFP'!#REF! -> #REF! | ... AR17: ='Evolutive SFP'!#REF! -> #REF! | AS17: ='Evolutive SFP'!B41 -> 10520537 | AT17: ='Evolutive SFP'!C41 -> 361564.84 | AU17: ='Evolutive SFP'!D41 -> 274938.86 | AV17: ='Evolutive SFP'!E41 -> 274938.86 | AW17: ='Evolutive SFP'!F41 -> 274938.86 | AX17: ='Evolutive SFP'!G41 -> 274938.86 | AY17: ='Evolutive SFP'!H41 -> 274938.86 | AZ17: ='Evolutive SFP'!#REF! -> #REF! | BA17: ='Evolutive SFP'!I41 -> 274938.86 | BB17: ='Evolutive SFP'!J41 -> 274938.86 | BC17: ='Evolutive SFP'!K41 -> 274938.86 | BD17: ='Evolutive SFP'!L41 -> 274938.86 | BE17: ='Evolutive SFP'!M41 -> 274938.86 | BF17: ='Evolutive SFP'!N41 -> 274955772 | BG17: ='Evolutive SFP'!O41 -> 401563.2 | BH17: ='Evolutive SFP'!P41 -> 361219.33 | ... CN17: ='Evolutive SFP'!AV41 -> 4.6674494e+08
A18: 5.3.4 | B18: Appropriation Account | C18: ='Evolutive SFP'!#REF! -> #REF! | D18: ='Evolutive SFP'!#REF! -> #REF! | E18: ='Evolutive SFP'!#REF! -> #REF! | F18: ='Evolutive SFP'!#REF! -> #REF! | G18: ='Evolutive SFP'!#REF! -> #REF! | H18: ='Evolutive SFP'!#REF! -> #REF! | I18: ='Evolutive SFP'!#REF! -> #REF! | J18: ='Evolutive SFP'!#REF! -> #REF! | ... AR18: ='Evolutive SFP'!#REF! -> #REF! | AS18: ='Evolutive SFP'!B42 -> 17320 | AT18: ='Evolutive SFP'!C42 -> -929.2 | AU18: ='Evolutive SFP'!D42 -> 16583.6 | AV18: ='Evolutive SFP'!E42 -> 10631.9 | AW18: ='Evolutive SFP'!F42 -> 58625.5 | AX18: ='Evolutive SFP'!G42 -> 102430.4 | AY18: ='Evolutive SFP'!H42 -> 56449.79 | AZ18: ='Evolutive SFP'!#REF! -> #REF! | BA18: ='Evolutive SFP'!I42 -> 67717.8 | BB18: ='Evolutive SFP'!J42 -> 76242.2 | BC18: ='Evolutive SFP'!K42 -> 87325.8 | BD18: ='Evolutive SFP'!L42 -> 81803.9 | BE18: ='Evolutive SFP'!M42 -> 113519.3 | BF18: ='Evolutive SFP'!N42 -> 86256085 | BG18: ='Evolutive SFP'!O42 -> -13751.5 | BH18: ='Evolutive SFP'!P42 -> -25718.6 | ... CN18: ='Evolutive SFP'!AV42 -> 77160421
A19: 5.3.5 | B19: Statutory Reserves | C19: ='Evolutive SFP'!#REF! -> #REF! | D19: ='Evolutive SFP'!#REF! -> #REF! | E19: ='Evolutive SFP'!#REF! -> #REF! | F19: ='Evolutive SFP'!#REF! -> #REF! | G19: ='Evolutive SFP'!#REF! -> #REF! | H19: ='Evolutive SFP'!#REF! -> #REF! | I19: ='Evolutive SFP'!#REF! -> #REF! | J19: ='Evolutive SFP'!#REF! -> #REF! | ... AR19: ='Evolutive SFP'!#REF! -> #REF! | AS19: ='Evolutive SFP'!B43 -> 5785290 | AT19: ='Evolutive SFP'!C43 -> 96887.35 | AU19: ='Evolutive SFP'!D43 -> 113070.67 | AV19: ='Evolutive SFP'!E43 -> 113070.67 | AW19: ='Evolutive SFP'!F43 -> 113070.67 | AX19: ='Evolutive SFP'!G43 -> 113070.67 | AY19: ='Evolutive SFP'!H43 -> 113070.67 | AZ19: ='Evolutive SFP'!#REF! -> #REF! | BA19: ='Evolutive SFP'!I43 -> 113070.67 | BB19: ='Evolutive SFP'!J43 -> 113070.67 | BC19: ='Evolutive SFP'!K43 -> 113070.67 | BD19: ='Evolutive SFP'!L43 -> 113070.67 | BE19: ='Evolutive SFP'!M43 -> 113070.67 | BF19: ='Evolutive SFP'!N43 -> 144642645 | BG19: ='Evolutive SFP'!O43 -> 113070.67 | BH19: ='Evolutive SFP'!P43 -> 144648.99 | ... CN19: ='Evolutive SFP'!AV43 -> 198645752
A20: 5.3.6 | B20: Capital Reserves | C20: =('Evolutive SFP'!#REF!) -> #REF! | D20: =('Evolutive SFP'!#REF!) -> #REF! | E20: =('Evolutive SFP'!#REF!) -> #REF! | F20: =('Evolutive SFP'!#REF!) -> #REF! | G20: =('Evolutive SFP'!#REF!) -> #REF! | H20: =('Evolutive SFP'!#REF!) -> #REF! | I20: =('Evolutive SFP'!#REF!) -> #REF! | J20: =('Evolutive SFP'!#REF!) -> #REF! | ... AR20: =('Evolutive SFP'!#REF!) -> #REF! | AS20: =('Evolutive SFP'!B44) -> 0 | AT20: =('Evolutive SFP'!C44) -> 0 | AU20: =('Evolutive SFP'!D44) -> 0 | AV20: =('Evolutive SFP'!E44) -> 0 | AW20: =('Evolutive SFP'!F44) -> 0 | AX20: =('Evolutive SFP'!G44) -> 0 | AY20: =('Evolutive SFP'!H44) -> 0 | AZ20: =('Evolutive SFP'!#REF!) -> #REF! | BA20: =('Evolutive SFP'!I44) -> 0 | BB20: =('Evolutive SFP'!J44) -> 0 | BC20: =('Evolutive SFP'!K44) -> 0 | BD20: =('Evolutive SFP'!L44) -> 0 | BE20: =('Evolutive SFP'!M44) -> 0 | BF20: =('Evolutive SFP'!N44) -> 40906816 | BG20: =('Evolutive SFP'!O44) -> 0 | BH20: =('Evolutive SFP'!P44) -> 0 | ... CN20: =('Evolutive SFP'!AV44) -> 0
A21: 5.3.7 | B21: Supplementary Capital & reserves | C21: =C22+C23 -> #REF! | D21: =D22+D23 -> #REF! | E21: =E22+E23 -> #REF! | F21: =F22+F23 -> #REF! | G21: =G22+G23 -> #REF! | H21: =H22+H23 -> #REF! | I21: =I22+I23 -> #REF! | J21: =J22+J23 -> #REF! | ... CN21: =CN22+CN23 -> 31188919
A22: a | B22: Proposed Dividends | C22: ='Evolutive SFP'!#REF! -> #REF! | D22: ='Evolutive SFP'!#REF! -> #REF! | E22: ='Evolutive SFP'!#REF! -> #REF! | F22: ='Evolutive SFP'!#REF! -> #REF! | G22: ='Evolutive SFP'!#REF! -> #REF! | H22: ='Evolutive SFP'!#REF! -> #REF! | I22: ='Evolutive SFP'!#REF! -> #REF! | J22: ='Evolutive SFP'!#REF! -> #REF! | ... AR22: ='Evolutive SFP'!#REF! -> #REF! | AS22: ='Evolutive SFP'!B46 -> 0 | AT22: ='Evolutive SFP'!C46 -> 3041.44 | AU22: ='Evolutive SFP'!D46 -> 6114.19 | AV22: ='Evolutive SFP'!E46 -> 9232.47 | AW22: ='Evolutive SFP'!F46 -> 12312.76 | AX22: ='Evolutive SFP'!G46 -> 15485.78 | AY22: ='Evolutive SFP'!H46 -> 18687.64 | AZ22: ='Evolutive SFP'!#REF! -> #REF! | BA22: ='Evolutive SFP'!I46 -> 25176.86 | BB22: ='Evolutive SFP'!J46 -> 28401.36 | BC22: ='Evolutive SFP'!K46 -> 31718.62 | BD22: ='Evolutive SFP'!L46 -> 34974.86 | BE22: ='Evolutive SFP'!M46 -> 38262.03 | BF22: ='Evolutive SFP'!N46 -> 37440175 | BG22: ='Evolutive SFP'!O46 -> 3204.94 | BH22: ='Evolutive SFP'!P46 -> 6422.54 | ... CN22: ='Evolutive SFP'!AV46 -> 31188919
A23: b | B23: Risk Mgt Fund
A25: 6 | B25: Investments | C25: =C26+C27+C28 -> #REF! | D25: =D26+D27+D28 -> #REF! | E25: =E26+E27+E28 -> #REF! | F25: =F26+F27+F28 -> #REF! | G25: =G26+G27+G28 -> #REF! | H25: =H26+H27+H28 -> #REF! | I25: =I26+I27+I28 -> #REF! | J25: =J26+J27+J28 -> #REF! | ... CN25: =CN26+CN27+CN28 -> 12547602
A26: 6.1 | B26: Shares in Kusco,CIC,Coop Bank | C26: ='Evolutive SFP'!#REF! -> #REF! | D26: ='Evolutive SFP'!#REF! -> #REF! | E26: ='Evolutive SFP'!#REF! -> #REF! | F26: ='Evolutive SFP'!#REF! -> #REF! | G26: ='Evolutive SFP'!#REF! -> #REF! | H26: ='Evolutive SFP'!#REF! -> #REF! | I26: ='Evolutive SFP'!#REF! -> #REF! | J26: ='Evolutive SFP'!#REF! -> #REF! | ... AR26: ='Evolutive SFP'!#REF! -> #REF! | AS26: ='Evolutive SFP'!B13 -> 0 | AT26: ='Evolutive SFP'!C13 -> 0 | AU26: ='Evolutive SFP'!D13 -> 0 | AV26: ='Evolutive SFP'!E13 -> 0 | AW26: ='Evolutive SFP'!F13 -> 0 | AX26: ='Evolutive SFP'!G13 -> 0 | AY26: ='Evolutive SFP'!H13 -> 0 | AZ26: ='Evolutive SFP'!#REF! -> #REF! | BA26: ='Evolutive SFP'!I13 -> 0 | BB26: ='Evolutive SFP'!J13 -> 0 | BC26: ='Evolutive SFP'!K13 -> 0 | BD26: ='Evolutive SFP'!L13 -> 0 | BE26: ='Evolutive SFP'!M13 -> 0 | BF26: ='Evolutive SFP'!N13 -> 151588357 | BG26: ='Evolutive SFP'!O13 -> 205716.49 | BH26: ='Evolutive SFP'!P13 -> 205716.49 | ... CN26: ='Evolutive SFP'!AV13 -> 0
A27: 6.2 | B27: Equity Investments (at cost) | C27: ='Evolutive SFP'!#REF! -> #REF! | D27: ='Evolutive SFP'!#REF! -> #REF! | E27: ='Evolutive SFP'!#REF! -> #REF! | F27: ='Evolutive SFP'!#REF! -> #REF! | G27: ='Evolutive SFP'!#REF! -> #REF! | H27: ='Evolutive SFP'!#REF! -> #REF! | I27: ='Evolutive SFP'!#REF! -> #REF! | J27: ='Evolutive SFP'!#REF! -> #REF! | ... R27: ='Evolutive SFP'!#REF! -> #REF! | S27: ='Evolutive SFP'!#REF!+'Evolutive SFP'!#REF! -> #REF! | T27: ='Evolutive SFP'!#REF!+'Evolutive SFP'!#REF! -> #REF! | U27: ='Evolutive SFP'!#REF!+'Evolutive SFP'!#REF! -> #REF! | V27: ='Evolutive SFP'!#REF!+'Evolutive SFP'!#REF! -> #REF! | W27: ='Evolutive SFP'!#REF!+'Evolutive SFP'!#REF! -> #REF! | X27: ='Evolutive SFP'!#REF!+'Evolutive SFP'!#REF! -> #REF! | Y27: ='Evolutive SFP'!#REF!+'Evolutive SFP'!#REF! -> #REF! | Z27: ='Evolutive SFP'!#REF!+'Evolutive SFP'!#REF! -> #REF! | ... AR27: ='Evolutive SFP'!#REF!+'Evolutive SFP'!#REF! -> #REF! | AS27: ='Evolutive SFP'!B10+'Evolutive SFP'!B13 -> 0 | AT27: ='Evolutive SFP'!C10+'Evolutive SFP'!C13 -> 0 | AU27: ='Evolutive SFP'!D10+'Evolutive SFP'!D13 -> 0 | AV27: ='Evolutive SFP'!E10+'Evolutive SFP'!E13 -> 0 | AW27: ='Evolutive SFP'!F10+'Evolutive SFP'!F13 -> 0 | AX27: ='Evolutive SFP'!G10+'Evolutive SFP'!G13 -> 0 | AY27: ='Evolutive SFP'!H10+'Evolutive SFP'!H13 -> 0 | AZ27: ='Evolutive SFP'!#REF!+'Evolutive SFP'!#REF! -> #REF! | BA27: ='Evolutive SFP'!I10+'Evolutive SFP'!I13 -> 0 | BB27: ='Evolutive SFP'!J10+'Evolutive SFP'!J13 -> 0 | BC27: ='Evolutive SFP'!K10+'Evolutive SFP'!K13 -> 0 | BD27: ='Evolutive SFP'!L10+'Evolutive SFP'!L13 -> 0 | BE27: ='Evolutive SFP'!M10+'Evolutive SFP'!M13 -> 0 | BF27: ='Evolutive SFP'!N10+'Evolutive SFP'!N13 -> 151588357 | BG27: ='Evolutive SFP'!O10+'Evolutive SFP'!O13 -> 205716.49 | BH27: ='Evolutive SFP'!P10+'Evolutive SFP'!P13 -> 205716.49 | ... CN27: ='Evolutive SFP'!AV10+'Evolutive SFP'!AV13 -> 0
A28: 6.3 | B28: Deposits in KUSCCO CFP | C28: ='Evolutive SFP'!#REF! -> #REF! | D28: ='Evolutive SFP'!#REF! -> #REF! | E28: ='Evolutive SFP'!#REF! -> #REF! | F28: ='Evolutive SFP'!#REF! -> #REF! | G28: ='Evolutive SFP'!#REF! -> #REF! | H28: ='Evolutive SFP'!#REF! -> #REF! | I28: ='Evolutive SFP'!#REF! -> #REF! | J28: ='Evolutive SFP'!#REF! -> #REF! | ... AR28: ='Evolutive SFP'!#REF! -> #REF! | AS28: ='Evolutive SFP'!B11 -> 115855 | AT28: ='Evolutive SFP'!C11 -> 8093.93 | AU28: ='Evolutive SFP'!D11 -> 8093.93 | AV28: ='Evolutive SFP'!E11 -> 10452.43 | AW28: ='Evolutive SFP'!F11 -> 10452.43 | AX28: ='Evolutive SFP'!G11 -> 10452.43 | AY28: ='Evolutive SFP'!H11 -> 10452.43 | AZ28: ='Evolutive SFP'!#REF! -> #REF! | BA28: ='Evolutive SFP'!I11 -> 10702.43 | BB28: ='Evolutive SFP'!J11 -> 10764.36 | BC28: ='Evolutive SFP'!K11 -> 10764.36 | BD28: ='Evolutive SFP'!L11 -> 10920.91 | BE28: ='Evolutive SFP'!M11 -> 10970.91 | BF28: ='Evolutive SFP'!N11 -> 0 | BG28: ='Evolutive SFP'!O11 -> 10970.91 | BH28: ='Evolutive SFP'!P11 -> 10977.85 | ... CN28: ='Evolutive SFP'!AV11 -> 12547602
A30: 7 | B30: Net Loans & Advances | C30: ='Evolutive SFP'!#REF! -> #REF! | D30: ='Evolutive SFP'!#REF! -> #REF! | E30: ='Evolutive SFP'!#REF! -> #REF! | F30: ='Evolutive SFP'!#REF! -> #REF! | G30: ='Evolutive SFP'!#REF! -> #REF! | H30: ='Evolutive SFP'!#REF! -> #REF! | I30: ='Evolutive SFP'!#REF! -> #REF! | J30: ='Evolutive SFP'!#REF! -> #REF! | ... AR30: ='Evolutive SFP'!#REF! -> #REF! | AS30: ='Evolutive SFP'!B14 -> 216882733 | AT30: ='Evolutive SFP'!C14 -> 2218881.5 | AU30: ='Evolutive SFP'!D14 -> 2194730.5 | AV30: ='Evolutive SFP'!E14 -> 2142502.8 | AW30: ='Evolutive SFP'!F14 -> 2083076.2 | AX30: ='Evolutive SFP'!G14 -> 2085200.9 | AY30: ='Evolutive SFP'!H14 -> 2041178.1 | AZ30: ='Evolutive SFP'!#REF! -> #REF! | BA30: ='Evolutive SFP'!I14 -> 2220959.6 | BB30: ='Evolutive SFP'!J14 -> 2309725 | BC30: ='Evolutive SFP'!K14 -> 2379361.5 | BD30: ='Evolutive SFP'!L14 -> 2404986.6 | BE30: ='Evolutive SFP'!M14 -> 2478695.7 | BF30: ='Evolutive SFP'!N14 -> 2478581524 | BG30: ='Evolutive SFP'!O14 -> 2479489.3 | BH30: ='Evolutive SFP'!P14 -> 2481869.1 | ... CN30: ='Evolutive SFP'!AV14 -> 3.615259e+09
A31: 7.1 | B31: Gross Loans & advances | C31: ='Evolutive SFP'!#REF! -> #REF! | D31: ='Evolutive SFP'!#REF! -> #REF! | E31: ='Evolutive SFP'!#REF! -> #REF! | F31: ='Evolutive SFP'!#REF! -> #REF! | G31: ='Evolutive SFP'!#REF! -> #REF! | H31: ='Evolutive SFP'!#REF! -> #REF! | I31: ='Evolutive SFP'!#REF! -> #REF! | J31: ='Evolutive SFP'!#REF! -> #REF! | ... AR31: ='Evolutive SFP'!#REF! -> #REF! | AS31: ='Evolutive SFP'!B15 -> 238201977 | AT31: ='Evolutive SFP'!C15 -> 2254469.6 | AU31: ='Evolutive SFP'!D15 -> 2281291.9 | AV31: ='Evolutive SFP'!E15 -> 2236181.1 | AW31: ='Evolutive SFP'!F15 -> 2187772 | AX31: ='Evolutive SFP'!G15 -> 2148831.4 | AY31: ='Evolutive SFP'!H15 -> 2152614.9 | AZ31: ='Evolutive SFP'!#REF! -> #REF! | BA31: ='Evolutive SFP'!I15 -> 2334271.6 | BB31: ='Evolutive SFP'!J15 -> 2423796.5 | BC31: ='Evolutive SFP'!K15 -> 2482872.8 | BD31: ='Evolutive SFP'!L15 -> 2516422.2 | BE31: ='Evolutive SFP'!M15 -> 2564682.8 | BF31: ='Evolutive SFP'!N15 -> 2564485165 | BG31: ='Evolutive SFP'!O15 -> 2578503.4 | BH31: ='Evolutive SFP'!P15 -> 2602511.1 | ... CN31: ='Evolutive SFP'!AV15 -> 3.7167025e+09
A32: 7.2 | B32: Allowance for loan losses | C32: ='Evolutive SFP'!#REF! -> #REF! | D32: ='Evolutive SFP'!#REF! -> #REF! | E32: ='Evolutive SFP'!#REF! -> #REF! | F32: ='Evolutive SFP'!#REF! -> #REF! | G32: ='Evolutive SFP'!#REF! -> #REF! | H32: ='Evolutive SFP'!#REF! -> #REF! | I32: ='Evolutive SFP'!#REF! -> #REF! | J32: ='Evolutive SFP'!#REF! -> #REF! | ... AR32: ='Evolutive SFP'!#REF! -> #REF! | AS32: ='Evolutive SFP'!B16 -> 21319244 | AT32: ='Evolutive SFP'!C16 -> 35588.07 | AU32: ='Evolutive SFP'!D16 -> 86561.44 | AV32: ='Evolutive SFP'!E16 -> 93678.35 | AW32: ='Evolutive SFP'!F16 -> 104695.77 | AX32: ='Evolutive SFP'!G16 -> 63630.49 | AY32: ='Evolutive SFP'!H16 -> 111436.78 | AZ32: ='Evolutive SFP'!#REF! -> #REF! | BA32: ='Evolutive SFP'!I16 -> 113312 | BB32: ='Evolutive SFP'!J16 -> 114071.49 | BC32: ='Evolutive SFP'!K16 -> 103511.29 | BD32: ='Evolutive SFP'!L16 -> 111435.61 | BE32: ='Evolutive SFP'!M16 -> 85987.1 | BF32: ='Evolutive SFP'!N16 -> 85903641 | BG32: ='Evolutive SFP'!O16 -> 99014.08 | BH32: ='Evolutive SFP'!P16 -> 120641.95 | ... CN32: ='Evolutive SFP'!AV16 -> 101443565
A34: 8 | B34: Non-Earning Assets | C34: ='Evolutive SFP'!#REF!+'Evolutive SFP'!#REF! -> #REF! | D34: ='Evolutive SFP'!#REF!+'Evolutive SFP'!#REF! -> #REF! | E34: ='Evolutive SFP'!#REF!+'Evolutive SFP'!#REF! -> #REF! | F34: ='Evolutive SFP'!#REF!+'Evolutive SFP'!#REF! -> #REF! | G34: ='Evolutive SFP'!#REF!+'Evolutive SFP'!#REF! -> #REF! | H34: ='Evolutive SFP'!#REF!+'Evolutive SFP'!#REF! -> #REF! | I34: ='Evolutive SFP'!#REF!+'Evolutive SFP'!#REF! -> #REF! | J34: ='Evolutive SFP'!#REF!+'Evolutive SFP'!#REF! -> #REF! | ... AR34: ='Evolutive SFP'!#REF!+'Evolutive SFP'!#REF! -> #REF! | AS34: ='Evolutive SFP'!B21+'Evolutive SFP'!B7 -> 15470516 | AT34: ='Evolutive SFP'!C21+'Evolutive SFP'!C7 -> 165873.14 | AU34: ='Evolutive SFP'!D21+'Evolutive SFP'!D7 -> 139478.98 | AV34: ='Evolutive SFP'!E21+'Evolutive SFP'!E7 -> 134978.1 | AW34: ='Evolutive SFP'!F21+'Evolutive SFP'!F7 -> 188305.43 | AX34: ='Evolutive SFP'!G21+'Evolutive SFP'!G7 -> 136868.63 | AY34: ='Evolutive SFP'!H21+'Evolutive SFP'!H7 -> 138808.23 | AZ34: ='Evolutive SFP'!#REF!+'Evolutive SFP'!#REF! -> #REF! | BA34: ='Evolutive SFP'!I21+'Evolutive SFP'!I7 -> 137972.94 | BB34: ='Evolutive SFP'!J21+'Evolutive SFP'!J7 -> 137846.07 | BC34: ='Evolutive SFP'!K21+'Evolutive SFP'!K7 -> 141879.87 | BD34: ='Evolutive SFP'!L21+'Evolutive SFP'!L7 -> 138243.07 | BE34: ='Evolutive SFP'!M21+'Evolutive SFP'!M7 -> 137353.5 | BF34: ='Evolutive SFP'!N21+'Evolutive SFP'!N7 -> 136816941 | BG34: ='Evolutive SFP'!O21+'Evolutive SFP'!O7 -> 139776.85 | BH34: ='Evolutive SFP'!P21+'Evolutive SFP'!P7 -> 143284.94 | ... CN34: ='Evolutive SFP'!AV21+'Evolutive SFP'!AV7 -> 2.2707614e+08
A35: 8.1 | B35: Property and Equipment | C35: ='Evolutive SFP'!#REF! -> #REF! | D35: ='Evolutive SFP'!#REF! -> #REF! | E35: ='Evolutive SFP'!#REF! -> #REF! | F35: ='Evolutive SFP'!#REF! -> #REF! | G35: ='Evolutive SFP'!#REF! -> #REF! | H35: ='Evolutive SFP'!#REF! -> #REF! | I35: ='Evolutive SFP'!#REF! -> #REF! | J35: ='Evolutive SFP'!#REF! -> #REF! | ... AR35: ='Evolutive SFP'!#REF! -> #REF! | AS35: ='Evolutive SFP'!B23 -> 3806303 | AT35: ='Evolutive SFP'!C23 -> 109066.07 | AU35: ='Evolutive SFP'!D23 -> 108792.8 | AV35: ='Evolutive SFP'!E23 -> 108491.82 | AW35: ='Evolutive SFP'!F23 -> 108202.08 | AX35: ='Evolutive SFP'!G23 -> 108014.06 | AY35: ='Evolutive SFP'!H23 -> 107724.2 | AZ35: ='Evolutive SFP'!#REF! -> #REF! | BA35: ='Evolutive SFP'!I23 -> 109023.81 | BB35: ='Evolutive SFP'!J23 -> 111726.02 | BC35: ='Evolutive SFP'!K23 -> 111386.02 | BD35: ='Evolutive SFP'!L23 -> 111058.25 | BE35: ='Evolutive SFP'!M23 -> 110720.85 | BF35: ='Evolutive SFP'!N23 -> 110878048 | BG35: ='Evolutive SFP'!O23 -> 110558.85 | BH35: ='Evolutive SFP'!P23 -> 110271.65 | ... CN35: ='Evolutive SFP'!AV23 -> 1.1003592e+08
B36: Cash & Cash Equivalents | D36: ='Evolutive SFP'!#REF! -> #REF! | E36: ='Evolutive SFP'!#REF! -> #REF! | F36: ='Evolutive SFP'!#REF! -> #REF! | G36: ='Evolutive SFP'!#REF! -> #REF! | H36: ='Evolutive SFP'!#REF! -> #REF! | I36: ='Evolutive SFP'!#REF! -> #REF! | J36: ='Evolutive SFP'!#REF! -> #REF! | K36: ='Evolutive SFP'!#REF! -> #REF! | ... M36: ='Evolutive SFP'!#REF! -> #REF!
A37: 9 | B37: Turnover | C37: =C38+C39+C40+C41 -> #REF! | D37: =D38+D39+D40+D41 -> #REF! | E37: =E38+E39+E40+E41 -> #REF! | F37: =F38+F39+F40+F41 -> #REF! | G37: =G38+G39+G40+G41 -> #REF! | H37: =H38+H39+H40+H41 -> #REF! | I37: =I38+I39+I40+I41 -> #REF! | J37: =J38+J39+J40+J41 -> #REF! | ... CN37: =CN38+CN39+CN40+CN41 -> 4.9090132e+08
A38: 9.1 | B38: Loan Interest | C38: ='Evolutitve SCI'!#REF! -> #REF! | D38: ='Evolutitve SCI'!#REF! -> #REF! | E38: ='Evolutitve SCI'!#REF! -> #REF! | F38: ='Evolutitve SCI'!#REF! -> #REF! | G38: ='Evolutitve SCI'!#REF! -> #REF! | H38: ='Evolutitve SCI'!#REF! -> #REF! | I38: ='Evolutitve SCI'!#REF! -> #REF! | J38: ='Evolutitve SCI'!#REF! -> #REF! | ... AR38: ='Evolutitve SCI'!#REF! -> #REF! | AS38: ='Evolutitve SCI'!B5 -> 29009435 | AT38: ='Evolutitve SCI'!C5 -> 27556.48 | AU38: ='Evolutitve SCI'!D5 -> 52711.18 | AV38: ='Evolutitve SCI'!E5 -> 80152.96 | AW38: ='Evolutitve SCI'!F5 -> 107236.44 | AX38: ='Evolutitve SCI'!G5 -> 132726.17 | AY38: ='Evolutitve SCI'!H5 -> 158047.62 | AZ38: ='Evolutitve SCI'!#REF! -> #REF! | BA38: ='Evolutitve SCI'!I5 -> 210504.7 | BB38: ='Evolutitve SCI'!J5 -> 239816.08 | BC38: ='Evolutitve SCI'!K5 -> 270226.24 | BD38: ='Evolutitve SCI'!L5 -> 298209.19 | BE38: ='Evolutitve SCI'!M5 -> 329605.24 | BF38: ='Evolutitve SCI'!N5 -> 329442006 | BG38: ='Evolutitve SCI'!O5 -> 29095.27 | BH38: ='Evolutitve SCI'!P5 -> 56168.57 | ... CN38: ='Evolutitve SCI'!AV5 -> 3.069356e+08
A39: 9.2 | B39: Income from investments | C39: ='Evolutitve SCI'!#REF! -> #REF! | D39: ='Evolutitve SCI'!#REF! -> #REF! | E39: ='Evolutitve SCI'!#REF! -> #REF! | F39: ='Evolutitve SCI'!#REF! -> #REF! | G39: ='Evolutitve SCI'!#REF! -> #REF! | H39: ='Evolutitve SCI'!#REF! -> #REF! | I39: ='Evolutitve SCI'!#REF! -> #REF! | J39: ='Evolutitve SCI'!#REF! -> #REF! | ... AR39: ='Evolutitve SCI'!#REF! -> #REF! | AS39: ='Evolutitve SCI'!B7 -> 3770368 | AT39: ='Evolutitve SCI'!C7 -> 1489.22 | AU39: ='Evolutitve SCI'!D7 -> 6986 | AV39: ='Evolutitve SCI'!E7 -> 12215.76 | AW39: ='Evolutitve SCI'!F7 -> 73416.95 | AX39: ='Evolutitve SCI'!G7 -> 80401.15 | AY39: ='Evolutitve SCI'!H7 -> 86718.38 | AZ39: ='Evolutitve SCI'!#REF! -> #REF! | BA39: ='Evolutitve SCI'!I7 -> 113225.28 | BB39: ='Evolutitve SCI'!J7 -> 119661.02 | BC39: ='Evolutitve SCI'!K7 -> 126143.67 | BD39: ='Evolutitve SCI'!L7 -> 131357.19 | BE39: ='Evolutitve SCI'!M7 -> 141463.39 | BF39: ='Evolutitve SCI'!N7 -> 117781209 | BG39: ='Evolutitve SCI'!O7 -> 876.43 | BH39: ='Evolutitve SCI'!P7 -> 13450.94 | ... CN39: ='Evolutitve SCI'!AV7 -> 1.7488096e+08
A40: 9.3 | B40: Fees & Commissions | C40: ='Evolutitve SCI'!#REF! -> #REF! | D40: ='Evolutitve SCI'!#REF! -> #REF! | E40: ='Evolutitve SCI'!#REF! -> #REF! | F40: ='Evolutitve SCI'!#REF! -> #REF! | G40: ='Evolutitve SCI'!#REF! -> #REF! | H40: ='Evolutitve SCI'!#REF! -> #REF! | I40: ='Evolutitve SCI'!#REF! -> #REF! | J40: ='Evolutitve SCI'!#REF! -> #REF! | ... AR40: ='Evolutitve SCI'!#REF! -> #REF! | AS40: ='Evolutitve SCI'!B6 -> 1310268 | AT40: ='Evolutitve SCI'!C6 -> 374.5 | AU40: ='Evolutitve SCI'!D6 -> 2288.4 | AV40: ='Evolutitve SCI'!E6 -> 4664.5 | AW40: ='Evolutitve SCI'!F6 -> 5588.4 | AX40: ='Evolutitve SCI'!G6 -> 6077.5 | AY40: ='Evolutitve SCI'!H6 -> 6803.3 | AZ40: ='Evolutitve SCI'!#REF! -> #REF! | BA40: ='Evolutitve SCI'!I6 -> 8181.6 | BB40: ='Evolutitve SCI'!J6 -> 8674.4 | BC40: ='Evolutitve SCI'!K6 -> 9282.2 | BD40: ='Evolutitve SCI'!L6 -> 9987.1 | BE40: ='Evolutitve SCI'!M6 -> 10897.5 | BF40: ='Evolutitve SCI'!N6 -> 31771137 | BG40: ='Evolutitve SCI'!O6 -> 817.2 | BH40: ='Evolutitve SCI'!P6 -> 1646.2 | ... CN40: ='Evolutitve SCI'!AV6 -> 9084749.8
A41: 9.4 | B41: Average yield on loans | S41: =S38/S31 -> #REF! | T41: =T38/T31 -> #REF! | U41: =U38/U31 -> #REF! | V41: =V38/V31 -> #REF! | W41: =W38/W31 -> #REF! | X41: =X38/X31 -> #REF! | Y41: =Y38/Y31 -> #REF! | Z41: =Z38/Z31 -> #REF! | ... CN41: =CN38/CN31 -> 0.082582773
A43: 10 | B43: Financial and Operating costs | C43: =SUM(C44:C47) -> #REF! | D43: =SUM(D44:D47) -> #REF! | E43: =SUM(E44:E47) -> #REF! | F43: =SUM(F44:F47) -> #REF! | G43: =SUM(G44:G47) -> #REF! | H43: =SUM(H44:H47) -> #REF! | I43: =SUM(I44:I47) -> #REF! | J43: =SUM(J44:J47) -> #REF! | ... CN43: =SUM(CN44:CN47) -> 3.8765099e+08
A44: 10.1 | B44: Interest expense on deposits | C44: ='Evolutitve SCI'!#REF!+'Evolutitve SCI'!#REF! -> #REF! | D44: ='Evolutitve SCI'!#REF!+'Evolutitve SCI'!#REF! -> #REF! | E44: ='Evolutitve SCI'!#REF!+'Evolutitve SCI'!#REF! -> #REF! | F44: ='Evolutitve SCI'!#REF!+'Evolutitve SCI'!#REF! -> #REF! | G44: ='Evolutitve SCI'!#REF!+'Evolutitve SCI'!#REF! -> #REF! | H44: ='Evolutitve SCI'!#REF!+'Evolutitve SCI'!#REF! -> #REF! | I44: ='Evolutitve SCI'!#REF!+'Evolutitve SCI'!#REF! -> #REF! | J44: ='Evolutitve SCI'!#REF!+'Evolutitve SCI'!#REF! -> #REF! | ... AR44: ='Evolutitve SCI'!#REF!+'Evolutitve SCI'!#REF! -> #REF! | AS44: ='Evolutitve SCI'!B13+'Evolutitve SCI'!B16 -> 0 | AT44: ='Evolutitve SCI'!C13+'Evolutitve SCI'!C16 -> 20484.15 | AU44: ='Evolutitve SCI'!D13+'Evolutitve SCI'!D16 -> 39348.61 | AV44: ='Evolutitve SCI'!E13+'Evolutitve SCI'!E16 -> 60677.29 | AW44: ='Evolutitve SCI'!F13+'Evolutitve SCI'!F16 -> 80628.8 | AX44: ='Evolutitve SCI'!G13+'Evolutitve SCI'!G16 -> 103936.6 | AY44: ='Evolutitve SCI'!H13+'Evolutitve SCI'!H16 -> 126894.02 | AZ44: ='Evolutitve SCI'!#REF!+'Evolutitve SCI'!#REF! -> #REF! | BA44: ='Evolutitve SCI'!I13+'Evolutitve SCI'!I16 -> 174143.42 | BB44: ='Evolutitve SCI'!J13+'Evolutitve SCI'!J16 -> 193015.06 | BC44: ='Evolutitve SCI'!K13+'Evolutitve SCI'!K16 -> 221026.63 | BD44: ='Evolutitve SCI'!L13+'Evolutitve SCI'!L16 -> 246299.48 | BE44: ='Evolutitve SCI'!M13+'Evolutitve SCI'!M16 -> 273668.94 | BF44: ='Evolutitve SCI'!N13+'Evolutitve SCI'!N16 -> 254881440 | BG44: ='Evolutitve SCI'!O13+'Evolutitve SCI'!O16 -> 23108.37 | BH44: ='Evolutitve SCI'!P13+'Evolutitve SCI'!P16 -> 45962.63 | ... CN44: ='Evolutitve SCI'!AV13+'Evolutitve SCI'!AV16 -> 2.8632625e+08
A45: 10.2 | B45: Dividend expense on share capital | C45: ='Evolutitve SCI'!#REF! -> #REF! | D45: ='Evolutitve SCI'!#REF! -> #REF! | E45: ='Evolutitve SCI'!#REF! -> #REF! | F45: ='Evolutitve SCI'!#REF! -> #REF! | G45: ='Evolutitve SCI'!#REF! -> #REF! | H45: ='Evolutitve SCI'!#REF! -> #REF! | I45: ='Evolutitve SCI'!#REF! -> #REF! | J45: ='Evolutitve SCI'!#REF! -> #REF! | ... AR45: ='Evolutitve SCI'!#REF! -> #REF! | AS45: ='Evolutitve SCI'!B15 -> 0 | AT45: ='Evolutitve SCI'!C15 -> 3041.44 | AU45: ='Evolutitve SCI'!D15 -> 6114.19 | AV45: ='Evolutitve SCI'!E15 -> 9232.47 | AW45: ='Evolutitve SCI'!F15 -> 12312.76 | AX45: ='Evolutitve SCI'!G15 -> 15485.78 | AY45: ='Evolutitve SCI'!H15 -> 18687.64 | AZ45: ='Evolutitve SCI'!#REF! -> #REF! | BA45: ='Evolutitve SCI'!I15 -> 25176.86 | BB45: ='Evolutitve SCI'!J15 -> 28401.36 | BC45: ='Evolutitve SCI'!K15 -> 31721.96 | BD45: ='Evolutitve SCI'!L15 -> 34974.86 | BE45: ='Evolutitve SCI'!M15 -> 38262.03 | BF45: ='Evolutitve SCI'!N15 -> 0 | BG45: ='Evolutitve SCI'!O15 -> 3204.94 | BH45: ='Evolutitve SCI'!P15 -> 6422.54 | ... CN45: ='Evolutitve SCI'!AV15 -> 31188919
A46: 10.3 | B46: Interest expense on borrowed funds | C46: ='Evolutitve SCI'!#REF! -> #REF! | D46: ='Evolutitve SCI'!#REF! -> #REF! | E46: ='Evolutitve SCI'!#REF! -> #REF! | F46: ='Evolutitve SCI'!#REF! -> #REF! | G46: ='Evolutitve SCI'!#REF! -> #REF! | H46: ='Evolutitve SCI'!#REF! -> #REF! | I46: ='Evolutitve SCI'!#REF! -> #REF! | J46: ='Evolutitve SCI'!#REF! -> #REF! | ... AR46: ='Evolutitve SCI'!#REF! -> #REF! | AS46: ='Evolutitve SCI'!B14 -> 0 | AT46: ='Evolutitve SCI'!C14 -> 0 | AU46: ='Evolutitve SCI'!D14 -> 0 | AV46: ='Evolutitve SCI'!E14 -> 0 | AW46: ='Evolutitve SCI'!F14 -> 0 | AX46: ='Evolutitve SCI'!G14 -> 0 | AY46: ='Evolutitve SCI'!H14 -> 0 | AZ46: ='Evolutitve SCI'!#REF! -> #REF! | BA46: ='Evolutitve SCI'!I14 -> 0 | BB46: ='Evolutitve SCI'!J14 -> 0 | BC46: ='Evolutitve SCI'!K14 -> 0 | BD46: ='Evolutitve SCI'!L14 -> 0 | BE46: ='Evolutitve SCI'!M14 -> 0 | BF46: ='Evolutitve SCI'!N14 -> 0 | BG46: ='Evolutitve SCI'!O14 -> 0 | BH46: ='Evolutitve SCI'!P14 -> 0 | ... CN46: ='Evolutitve SCI'!AV14 -> 0
A47: 10.4 | B47: Opperating expenses | C47: ='Evolutitve SCI'!#REF! -> #REF! | D47: ='Evolutitve SCI'!#REF! -> #REF! | E47: ='Evolutitve SCI'!#REF! -> #REF! | F47: ='Evolutitve SCI'!#REF! -> #REF! | G47: ='Evolutitve SCI'!#REF! -> #REF! | H47: ='Evolutitve SCI'!#REF! -> #REF! | I47: ='Evolutitve SCI'!#REF! -> #REF! | J47: ='Evolutitve SCI'!#REF! -> #REF! | ... AR47: ='Evolutitve SCI'!#REF! -> #REF! | AS47: ='Evolutitve SCI'!B23 -> 14056548 | AT47: ='Evolutitve SCI'!C23 -> 4849.74 | AU47: ='Evolutitve SCI'!D23 -> 9259.8 | AV47: ='Evolutitve SCI'!E23 -> 18695.19 | AW47: ='Evolutitve SCI'!F23 -> 26723.84 | AX47: ='Evolutitve SCI'!G23 -> 30466.41 | AY47: ='Evolutitve SCI'!H23 -> 34845.96 | AZ47: ='Evolutitve SCI'!#REF! -> #REF! | BA47: ='Evolutitve SCI'!I23 -> 48306.38 | BB47: ='Evolutitve SCI'!J23 -> 53166.13 | BC47: ='Evolutitve SCI'!K23 -> 58811.28 | BD47: ='Evolutitve SCI'!L23 -> 61784.56 | BE47: ='Evolutitve SCI'!M23 -> 70255.34 | BF47: ='Evolutitve SCI'!N23 -> 68296970 | BG47: ='Evolutitve SCI'!O23 -> 5200.1 | BH47: ='Evolutitve SCI'!P23 -> 9829.11 | ... CN47: ='Evolutitve SCI'!AV23 -> 70135827
B50: Total Income | C50: ='Evolutitve SCI'!#REF! -> #REF! | D50: ='Evolutitve SCI'!#REF! -> #REF! | E50: ='Evolutitve SCI'!#REF! -> #REF! | F50: ='Evolutitve SCI'!#REF! -> #REF! | G50: ='Evolutitve SCI'!#REF! -> #REF! | H50: ='Evolutitve SCI'!#REF! -> #REF! | I50: ='Evolutitve SCI'!#REF! -> #REF! | J50: ='Evolutitve SCI'!#REF! -> #REF! | ... AF50: ='Evolutitve SCI'!#REF! -> #REF!
B51: Net Financial Income | C51: ='Evolutitve SCI'!#REF! -> #REF! | D51: ='Evolutitve SCI'!#REF! -> #REF! | E51: ='Evolutitve SCI'!#REF! -> #REF! | F51: ='Evolutitve SCI'!#REF! -> #REF! | G51: ='Evolutitve SCI'!#REF! -> #REF! | H51: ='Evolutitve SCI'!#REF! -> #REF! | I51: ='Evolutitve SCI'!#REF! -> #REF! | J51: ='Evolutitve SCI'!#REF! -> #REF! | ... AF51: ='Evolutitve SCI'!#REF! -> #REF!
B52: Net Income | C52: ='Evolutitve SCI'!#REF! -> #REF! | D52: ='Evolutitve SCI'!#REF! -> #REF! | E52: ='Evolutitve SCI'!#REF! -> #REF! | F52: ='Evolutitve SCI'!#REF! -> #REF! | G52: ='Evolutitve SCI'!#REF! -> #REF! | H52: ='Evolutitve SCI'!#REF! -> #REF! | I52: ='Evolutitve SCI'!#REF! -> #REF! | J52: ='Evolutitve SCI'!#REF! -> #REF! | ... AF52: ='Evolutitve SCI'!#REF! -> #REF!
B53: Div + Int on Deposits | C53: ='Evolutitve SCI'!#REF!+'Evolutitve SCI'!#REF!+'Evolutitve SCI'!#REF! -> #REF! | D53: ='Evolutitve SCI'!#REF!+'Evolutitve SCI'!#REF!+'Evolutitve SCI'!#REF! -> #REF! | E53: ='Evolutitve SCI'!#REF!+'Evolutitve SCI'!#REF!+'Evolutitve SCI'!#REF! -> #REF! | F53: ='Evolutitve SCI'!#REF!+'Evolutitve SCI'!#REF!+'Evolutitve SCI'!#REF! -> #REF! | G53: ='Evolutitve SCI'!#REF!+'Evolutitve SCI'!#REF!+'Evolutitve SCI'!#REF! -> #REF! | H53: ='Evolutitve SCI'!#REF!+'Evolutitve SCI'!#REF!+'Evolutitve SCI'!#REF! -> #REF! | I53: ='Evolutitve SCI'!#REF!+'Evolutitve SCI'!#REF!+'Evolutitve SCI'!#REF! -> #REF! | J53: ='Evolutitve SCI'!#REF!+'Evolutitve SCI'!#REF!+'Evolutitve SCI'!#REF! -> #REF! | ... AF53: ='Evolutitve SCI'!#REF!+'Evolutitve SCI'!#REF!+'Evolutitve SCI'!#REF! -> #REF!
B54: Total Expenses | C54: ='Evolutitve SCI'!#REF!+'Evolutitve SCI'!#REF!+'Evolutitve SCI'!#REF!+'Evolutitve SCI'!#REF!+'Evolutitve SCI'!#REF!+'Evolutitve SCI'!#REF! -> #REF! | D54: ='Evolutitve SCI'!#REF!+'Evolutitve SCI'!#REF!+'Evolutitve SCI'!#REF!+'Evolutitve SCI'!#REF!+'Evolutitve SCI'!#REF!+'Evolutitve SCI'!#REF! -> #REF! | E54: ='Evolutitve SCI'!#REF!+'Evolutitve SCI'!#REF!+'Evolutitve SCI'!#REF!+'Evolutitve SCI'!#REF!+'Evolutitve SCI'!#REF!+'Evolutitve SCI'!#REF! -> #REF! | F54: ='Evolutitve SCI'!#REF!+'Evolutitve SCI'!#REF!+'Evolutitve SCI'!#REF!+'Evolutitve SCI'!#REF!+'Evolutitve SCI'!#REF!+'Evolutitve SCI'!#REF! -> #REF! | G54: ='Evolutitve SCI'!#REF!+'Evolutitve SCI'!#REF!+'Evolutitve SCI'!#REF!+'Evolutitve SCI'!#REF!+'Evolutitve SCI'!#REF!+'Evolutitve SCI'!#REF! -> #REF! | H54: ='Evolutitve SCI'!#REF!+'Evolutitve SCI'!#REF!+'Evolutitve SCI'!#REF!+'Evolutitve SCI'!#REF!+'Evolutitve SCI'!#REF!+'Evolutitve SCI'!#REF! -> #REF! | I54: ='Evolutitve SCI'!#REF!+'Evolutitve SCI'!#REF!+'Evolutitve SCI'!#REF!+'Evolutitve SCI'!#REF!+'Evolutitve SCI'!#REF!+'Evolutitve SCI'!#REF! -> #REF! | J54: ='Evolutitve SCI'!#REF!+'Evolutitve SCI'!#REF!+'Evolutitve SCI'!#REF!+'Evolutitve SCI'!#REF!+'Evolutitve SCI'!#REF!+'Evolutitve SCI'!#REF! -> #REF! | ... AF54: ='Evolutitve SCI'!#REF!+'Evolutitve SCI'!#REF!+'Evolutitve SCI'!#REF!+'Evolutitve SCI'!#REF!+'Evolutitve SCI'!#REF!+'Evolutitve SCI'!#REF! -> #REF!
B55: Liquid Assets | C55: ='Evolutive SFP'!#REF!+'Evolutive SFP'!#REF!+'Evolutive SFP'!#REF!+'Evolutive SFP'!#REF! -> #REF! | D55: ='Evolutive SFP'!#REF!+'Evolutive SFP'!#REF!+'Evolutive SFP'!#REF!+'Evolutive SFP'!#REF! -> #REF! | E55: ='Evolutive SFP'!#REF!+'Evolutive SFP'!#REF!+'Evolutive SFP'!#REF!+'Evolutive SFP'!#REF! -> #REF! | F55: ='Evolutive SFP'!#REF!+'Evolutive SFP'!#REF!+'Evolutive SFP'!#REF!+'Evolutive SFP'!#REF! -> #REF! | G55: ='Evolutive SFP'!#REF!+'Evolutive SFP'!#REF!+'Evolutive SFP'!#REF!+'Evolutive SFP'!#REF! -> #REF! | H55: ='Evolutive SFP'!#REF!+'Evolutive SFP'!#REF!+'Evolutive SFP'!#REF!+'Evolutive SFP'!#REF! -> #REF! | I55: ='Evolutive SFP'!#REF!+'Evolutive SFP'!#REF!+'Evolutive SFP'!#REF!+'Evolutive SFP'!#REF! -> #REF! | J55: ='Evolutive SFP'!#REF!+'Evolutive SFP'!#REF!+'Evolutive SFP'!#REF!+'Evolutive SFP'!#REF! -> #REF! | ... AF55: ='Evolutive SFP'!#REF!+'Evolutive SFP'!#REF!+'Evolutive SFP'!#REF!+'Evolutive SFP'!#REF! -> #REF!
B56: Short term (Deposits + Liabilities) | C56: ='Evolutive SFP'!#REF!+'Evolutive SFP'!#REF!+'Evolutive SFP'!#REF!+'Evolutive SFP'!#REF!+'Evolutive SFP'!#REF!+'Evolutive SFP'!#REF!+'Evolutive SFP'!#REF! -> #REF! | D56: ='Evolutive SFP'!#REF!+'Evolutive SFP'!#REF!+'Evolutive SFP'!#REF!+'Evolutive SFP'!#REF!+'Evolutive SFP'!#REF!+'Evolutive SFP'!#REF!+'Evolutive SFP'!#REF! -> #REF! | E56: ='Evolutive SFP'!#REF!+'Evolutive SFP'!#REF!+'Evolutive SFP'!#REF!+'Evolutive SFP'!#REF!+'Evolutive SFP'!#REF!+'Evolutive SFP'!#REF!+'Evolutive SFP'!#REF! -> #REF! | F56: ='Evolutive SFP'!#REF!+'Evolutive SFP'!#REF!+'Evolutive SFP'!#REF!+'Evolutive SFP'!#REF!+'Evolutive SFP'!#REF!+'Evolutive SFP'!#REF!+'Evolutive SFP'!#REF! -> #REF! | G56: ='Evolutive SFP'!#REF!+'Evolutive SFP'!#REF!+'Evolutive SFP'!#REF!+'Evolutive SFP'!#REF!+'Evolutive SFP'!#REF!+'Evolutive SFP'!#REF!+'Evolutive SFP'!#REF! -> #REF! | H56: ='Evolutive SFP'!#REF!+'Evolutive SFP'!#REF!+'Evolutive SFP'!#REF!+'Evolutive SFP'!#REF!+'Evolutive SFP'!#REF!+'Evolutive SFP'!#REF!+'Evolutive SFP'!#REF! -> #REF! | I56: ='Evolutive SFP'!#REF!+'Evolutive SFP'!#REF!+'Evolutive SFP'!#REF!+'Evolutive SFP'!#REF!+'Evolutive SFP'!#REF!+'Evolutive SFP'!#REF!+'Evolutive SFP'!#REF! -> #REF! | J56: ='Evolutive SFP'!#REF!+'Evolutive SFP'!#REF!+'Evolutive SFP'!#REF!+'Evolutive SFP'!#REF!+'Evolutive SFP'!#REF!+'Evolutive SFP'!#REF!+'Evolutive SFP'!#REF! -> #REF! | ... AF56: ='Evolutive SFP'!#REF!+'Evolutive SFP'!#REF!+'Evolutive SFP'!#REF!+'Evolutive SFP'!#REF!+'Evolutive SFP'!#REF!+'Evolutive SFP'!#REF!+'Evolutive SFP'!#REF! -> #REF!
B57: Operating Expenses | C57: ='Evolutitve SCI'!#REF! -> #REF! | D57: ='Evolutitve SCI'!#REF! -> #REF! | E57: ='Evolutitve SCI'!#REF! -> #REF! | F57: ='Evolutitve SCI'!#REF! -> #REF! | G57: ='Evolutitve SCI'!#REF! -> #REF! | H57: ='Evolutitve SCI'!#REF! -> #REF! | I57: ='Evolutitve SCI'!#REF! -> #REF! | J57: ='Evolutitve SCI'!#REF! -> #REF! | ... AF57: ='Evolutitve SCI'!#REF! -> #REF!
B58: Financial Investments | C58: ='Evolutive SFP'!#REF! -> #REF! | D58: ='Evolutive SFP'!#REF! -> #REF! | E58: ='Evolutive SFP'!#REF! -> #REF! | F58: ='Evolutive SFP'!#REF! -> #REF! | G58: ='Evolutive SFP'!#REF! -> #REF! | H58: ='Evolutive SFP'!#REF! -> #REF! | I58: ='Evolutive SFP'!#REF! -> #REF! | J58: ='Evolutive SFP'!#REF! -> #REF! | ... AF58: ='Evolutive SFP'!#REF! -> #REF!
B59: Equity Investments | C59: ='Evolutive SFP'!#REF!+'Evolutive SFP'!#REF!+'Evolutive SFP'!#REF! -> #REF! | D59: ='Evolutive SFP'!#REF!+'Evolutive SFP'!#REF!+'Evolutive SFP'!#REF! -> #REF! | E59: ='Evolutive SFP'!#REF!+'Evolutive SFP'!#REF!+'Evolutive SFP'!#REF! -> #REF! | F59: ='Evolutive SFP'!#REF!+'Evolutive SFP'!#REF!+'Evolutive SFP'!#REF! -> #REF! | G59: ='Evolutive SFP'!#REF!+'Evolutive SFP'!#REF!+'Evolutive SFP'!#REF! -> #REF! | H59: ='Evolutive SFP'!#REF!+'Evolutive SFP'!#REF!+'Evolutive SFP'!#REF! -> #REF! | I59: ='Evolutive SFP'!#REF!+'Evolutive SFP'!#REF!+'Evolutive SFP'!#REF! -> #REF! | J59: ='Evolutive SFP'!#REF!+'Evolutive SFP'!#REF!+'Evolutive SFP'!#REF! -> #REF! | ... AF59: ='Evolutive SFP'!#REF!+'Evolutive SFP'!#REF!+'Evolutive SFP'!#REF! -> #REF!
B60: Non-Earning Assets | C60: ='Evolutive SFP'!#REF!+'Evolutive SFP'!#REF!+'Evolutive SFP'!#REF! -> #REF! | D60: ='Evolutive SFP'!#REF!+'Evolutive SFP'!#REF!+'Evolutive SFP'!#REF! -> #REF! | E60: ='Evolutive SFP'!#REF!+'Evolutive SFP'!#REF!+'Evolutive SFP'!#REF! -> #REF! | F60: ='Evolutive SFP'!#REF!+'Evolutive SFP'!#REF!+'Evolutive SFP'!#REF! -> #REF! | G60: ='Evolutive SFP'!#REF!+'Evolutive SFP'!#REF!+'Evolutive SFP'!#REF! -> #REF! | H60: ='Evolutive SFP'!#REF!+'Evolutive SFP'!#REF!+'Evolutive SFP'!#REF! -> #REF! | I60: ='Evolutive SFP'!#REF!+'Evolutive SFP'!#REF!+'Evolutive SFP'!#REF! -> #REF! | J60: ='Evolutive SFP'!#REF!+'Evolutive SFP'!#REF!+'Evolutive SFP'!#REF! -> #REF! | ... AF60: ='Evolutive SFP'!#REF!+'Evolutive SFP'!#REF!+'Evolutive SFP'!#REF! -> #REF!

Sheet CASH FLOW
A1: STATEMENT OF CASHFLOWS FOR THE YEAR ENDED 31ST DECEMBER 2015
B2: 2015 | C2: 2014
A3: Cash flows from operating activities
A4: Interest receipts
A5: Interest Payments
A6: Payment to employees and suppliers
A7: Other receipts
A8: (Increase)/Decrease in Operating assets | B8: =B4+B5+B6+B7 -> 0 | C8: =SUM(C4:C7) -> 0
A9: Net loans to members | B9: -21420750 | C9: -19341453
A10: Recievables and prepayments | B10: 3405679 | C10: 644537
A11: Short term investments
A12: Increase/(Decrease) in Operating liabilities | B12: =SUM(B9:B11) -> -18015071 | C12: =SUM(C9:C11) -> -18696916
A13: Deposits from members | B13: 37542318 | C13: 70912356
A14: Decrease/Increase Risk Fund | B14: -2636186 | C14: 17927
A15: Increase/decrease on Interest bearing Liabilities | B15: -7154210 | C15: -4536404
A16: Sundry creditors | B16: -312508 | C16: -2877539
A17: Net cashflow from operating activities before income taxes | B17: =B8+B12+B13+B14+B15+B16 -> 9424343 | C17: =C8+C12+C13+C14+C15+C16 -> 44819424
A18: Income tax paid
A19: Net Cash from Operating activities | B19: =B17+B18 -> 9424343 | C19: =C17+C18 -> 44819424
A21: Cashflow from investing activities
A22: Purchase of Property and equipment | B22: -987736 | C22: -4053993
A23: Purchase of intangible assets
A24: Purchase of financial assets
A25: Movement of other reserves-
A26: Issue of Bonus | B26: -286875 | C26: -534318
A27: Dividends Received
A28: Net Cash from investing activities | B28: =SUM(B22:B27) -> -1274611 | C28: =SUM(C22:C27) -> -4588311 | E28: =810794136-637456683 -> 173337453
A30: Cashflow from financing activities
A31: Share capital contributions | B31: 34941877 | C31: 17467705
A32: Contribution to sinking fund
A33: Repayments of long term borrowings
A34: Dividend paid | B34: -6887998 | C34: -6887998
A35: Honorarium paid | B35: 0 | C35: 0
A36: Net cash from financing activities | B36: =SUM(B31:B35) -> 28053879 | C36: =SUM(C31:C35) -> 10579707
A37: Net (Decrease)/Increase in cash and cash equivalent | B37: =B19+B28+B36 -> 36203611 | C37: =C19+C28+C36 -> 50810820
A38: Cash and cash equivalent at the beginning of the year | B38: 207318182 | C38: 134933687
A39: Cash and cash equivalent at the end of the year | B39: =SUM(B37:B38) -> 243521793 | C39: =SUM(C37:C38) -> 185744507

Sheet Feedback report
A1: STIMA SACCO SOCIETY LIMITED CS/NO: 2207
A2: PERFORMANCE AND COMPLIANCE REPORT AS AT : 30TH JUNE , 2018
B3: Prudential Standard | C3: Audited | D3: Returns | F3: Validated | G3: Average for all Licensed Saccos
C4: 2017 | D4: 43160 | E4: 43252
A5: A. CAPITAL ADEQUACY
A6: Core Capital | B6: ≥10M | C6: =C33 -> 3575294000 | D6: =D33 -> 3.6383881e+09 | E6: =E33 -> 3.8508836e+09 | F6: =F33 -> 0 | G6: =G33 -> 6.9326568e+10
A7: Core Capital/Total Assets | B7: ≥10% | C7: =C33/C29 -> 0.12516247 | D7: =D33/D29 -> 0.12404378 | E7: =E33/E29 -> 0.12810105 | F7: =F33/F29 -> #DIV/0! | G7: =G33/G29 -> 0.15142619
A8: Institutional Capital/Total Assets | B8: ≥8% | C8: =C34/C29 -> 0.084655346 | D8: =D34/D29 -> 0.080427602 | E8: =E34/E29 -> 0.082116799 | F8: =F34/F29 -> #DIV/0! | G8: =G34/G29 -> 0.086793277
A9: B. ASSET QUALITY
A10: NPL (Substandard+Doubtful+Loss) | B10: <5% | C10: =C35/C32 -> 0.083758752 | D10: =D35/D32 -> 0.069905965 | E10: =E35/E32 -> 0.064128919 | F10: =F35/F32 -> #DIV/0! | G10: =G35/G32 -> 0.064216556
A11: Non-Earning Assets | B11: <10% | C11: =C36/C29 -> 0.078233551 | D11: =D36/D29 -> 0.07077156 | E11: =E36/E29 -> 0.073871285 | F11: =F36/F29 -> #DIV/0! | G11: =G36/G29 -> 0.21105592
A12: Equity investments/Deposits | B12: <5% | C12: =C38/C31 -> 0.039319754 | D12: =D38/D31 -> 0.035325792 | E12: =E38/E31 -> 0.037197617 | F12: =F38/F31 -> #DIV/0! | G12: =G38/G31 -> 0.041240427
A13: Equity investments/Core capital | B13: <40% | C13: =C38/C33 -> 0.24098997 | D13: =D38/D33 -> 0.22956689 | E13: =E38/E33 -> 0.22930111 | F13: =F38/F33 -> #DIV/0! | G13: =G38/G33 -> 0.19351903
A14: C. EARNINGS RATING
A15: Yield on Gross Loans | C15: =C41/C32 -> 0.076755322 | D15: =D41/D32 -> 0.019738298 | E15: =E41/E32 -> 0.038638319 | F15: =F41/F32 -> #DIV/0! | G15: =G41/G32 -> 0.060128916
A16: Total Expense/Total Income | C16: =C44/C40 -> 0.8602912 | D16: =D44/D40 -> 0.91284222 | E16: =E44/E40 -> 0.88209003 | F16: =F44/F40 -> #DIV/0! | G16: =G44/G40 -> 0.79898157
A17: Net Income/Average Assets | C17: =C42/C30 -> 0.021114194 | D17: =D42/D30 -> 0.0032004404 | E17: =E42/E30 -> 0.0085246189 | F17: =F42/F30 -> #DIV/0! | G17: =G42/G30 -> 0.014471496
A18: Operating Expenses/Net Income (OPEX) | C18: =C45/C42 -> 1.8241433 | D18: =D45/D42 -> 2.5388457 | E18: =E45/E42 -> 2.0792721 | F18: =F45/F42 -> #DIV/0! | G18: =G45/G42 -> 1.6778105
A19: D. LIQUIDITY
A20: Liquid Assets/Short-term Liabilities | B20: >15% | C20: =C46/C47 -> 0.33588266 | D20: =D46/D47 -> 0.44544133 | E20: =E46/E47 -> 0.45759283 | F20: =F46/F47 -> #DIV/0! | G20: =G46/G47 -> 0.53762833
A21: External Borrowing/Total Assets | B21: <25% | C21: =C48/C29 -> 0.015941271 | D21: =D48/D29 -> 0.014155771 | E21: =E48/E29 -> 0.012698777 | F21: =F48/F29 -> #DIV/0! | G21: =G48/G29 -> 0.048858222
A22: Liquid Assets/Total Assets | C22: =C46/C29 -> 0.089409238 | D22: =D46/D29 -> 0.11709895 | E22: =E46/E29 -> 0.11553873 | F22: =F46/F29 -> #DIV/0! | G22: =G46/G29 -> 0.10366677
A23: E. STRUCTURE/SENSITIVITY TO RISK
A24: Gross loans /Total Assets | B24: 70-80 | C24: =C32/C29 -> 0.81615737 | D24: =D32/D29 -> 0.80219752 | E24: =E32/E29 -> 0.80146237 | F24: =F32/F29 -> #DIV/0! | G24: =G32/G29 -> 0.75746736
A25: Gross loans/Deposits | B25: >100% | C25: =C32/C31 -> 1.0639265 | D25: =D32/D31 -> 0.99515095 | E25: =E32/E31 -> 1.0149377 | F25: =F32/F31 -> #DIV/0! | G25: =G32/G31 -> 1.0660128
A26: Financial Investments/Total Assets | C26: =C39/C29 -> 0.038223399 | D26: =D39/D29 -> 0.02937488 | E26: =E39/E29 -> 0.030250433 | F26: =F39/F29 -> #DIV/0! | G26: =G39/G29 -> 0.043658487
A27: Dividends+Interest on Deposits/Total Income | C27: =C43/C40 -> 0.95525793 | D27: =D43/D40 -> 0.54694558 | E27: =E43/E40 -> 0.54728259 | F27: =F43/F40 -> #DIV/0! | G27: =G43/G40 -> 0.27724023
A28: F. KEY FINANCIAL STATISTICS | C28: 2015 | D28: 2016 | E28: 2017 | G28: AGGREGATE
A29: Total Assets | C29: 28565225000 | D29: 2.9331483e+10 | E29: 3.0061295e+10 | G29: 4.5782417e+11
A30: Average Assets | C30: 26523579000 | D30: 2.8948354e+10 | E30: 2.931326e+10 | G30: 4.5005065e+11
A31: Total Deposits | C31: 21912904000 | D31: 2.3644295e+10 | E31: 2.3738399e+10 | G31: 3.253121e+11
A32: Gross Loans | C32: 23313719000 | D32: 2.3529643e+10 | E32: 2.4092997e+10 | G32: 3.4678687e+11
A33: Core Capital | C33: 3575294000 | D33: 3.6383881e+09 | E33: 3.8508836e+09 | G33: 6.9326568e+10
A34: Institutional Capital | C34: 2418199000 | D34: 2.3590608e+09 | E34: 2.4685373e+09 | G34: 3.973606e+10
A35: Non-performing Loans | C35: 1952728000 | D35: 1.6448624e+09 | E35: 1.5450578e+09 | G35: 2.2269458e+10
A36: Non-Earning Assets | C36: 2234759000 | D36: 2.0758348e+09 | E36: 2.2206665e+09 | G36: 9.66265e+10
A37: Property and Equipment | C37: 235465000 | D37: 2.3485688e+08 | E37: 2.2615095e+08 | G37: 1.5408701e+10
A38: Equity Investments | C38: 861610000 | D38: 8.3525346e+08 | E38: 8.8301186e+08 | G38: 1.341601e+10
A39: Financial Investments | C39: 1091860000 | D39: 8.616088e+08 | E39: 9.0936721e+08 | G39: 1.9987911e+10
A40: Total Income | C40: 4008509000 | D40: 1.0629858e+09 | E40: 2.119281e+09 | G40: 3.2399548e+10
... A48: External Borrowing | C48: 455366000 | D48: 4.1520974e+08 | E48: 3.8174169e+08 | G48: 2.2368475e+10
A49: G. AREAS OF IMPROVEMENT/REGULARTORY CONCERNS
A50: 1. The ratio of NPL is above the prescribed limit
A51: 2
A52: 3
A53: 4
A54: Prepared by: Daniel Mwatu
A56: Checked by:
A58: Approved by: Peter Njuguna
A60: DISCLAIMER: This report is prepared based on information submitted by the Sacco as at the stated date and may change upon verification by the Authority.

Sheet Prudential Ratios
A1: TEMBO SACCO SOCIETY LTD
A2: TEMBO Sacco Financial Perfo
A4: FINANCIAL SOUNDNESS INDICATORS | B4: Prude. Std | C4: Ref. # | D4: 2008 | E4: 2009 | F4: 2010 | G4: 40603 | H4: 40695 | I4: 40787 | J4: 2011 | K4: 2012 | L4: 41275 | M4: 41306 | N4: 41334 | O4: 41365 | P4: 41395 | Q4: 41426 | R4: 41456 | S4: 41487 | T4: 41518 | U4: 41548 | V4: 41579 | W4: 41609 | X4: Dec 2013 audited | Y4: 41640 | Z4: 41671 | AA4: 41699 | AB4: 41730 | AC4: 41760 | AD4: 41791 | AE4: 41821 | AF4: 41852 | AG4: 41883 | AH4: 41913 | AI4: 41944 | AJ4: 41974 | AK4: 2014 Audited | AL4: 2015 Audited | AM4: 2016 Audited | AN4: 42736 | AO4: 42767 | AP4: 42795 | AQ4: 42826 | AR4: 42856 | AS4: 42887 | AT4: 42917 | AU4: 42948 | AV4: 42979 | AW4: 43009 | AX4: 43040 | AY4: 43070 | AZ4: Audited 2017 | BA4: 43101 | BB4: 43132 | BC4: 43160 | BD4: 43191 | BE4: 43221 | BF4: 43252 | BG4: 43282 | BH4: 43313 | BI4: 43344 | BJ4: 43374 | BK4: 43405 | BL4: 43435 | BM4: Audited 2018 | BN4: 43466 | BO4: 43497 | BP4: 43525 | BQ4: 43556 | BR4: 43586 | BS4: 43617 | BT4: 43647 | BU4: 43678 | BV4: 43709 | BW4: 43739 | BX4: 43770 | BY4: 43800 | BZ4: Audited 2019 | CA4: 43831 | CB4: 43862 | CC4: 43891 | CD4: 43922 | CE4: 43952 | CF4: 43983 | CG4: 44013 | CH4: 44044 | CI4: 44075 | CJ4: 44105 | CK4: 44136 | CL4: 44166 | CM4: Audited 2020 | CN4: 44197 | CO4: 44228 | CP4: 44256 | CQ4: 44287 | CR4: 44317 | CS4: 44348 | CT4: 44378 | CU4: 44409 | CV4: 44440 | CW4: 44470 | CX4: 44501 | CY4: 44531 | CZ4: AUDITED 2021 | DA4: 44562 | DB4: 44593 | DC4: 44621 | DD4: 44652 | DE4: 44682 | DF4: 44713 | DG4: 44743 | DH4: 44774 | DI4: 44805 | DJ4: 44835 | DK4: 44866 | DL4: 44896 | DM4: AUDITED 2022 | DN4: 44927 | DO4: 44958 | DP4: 44986 | DQ4: 45017 | DR4: 45047 | DS4: 45078 | DT4: 45108 | DU4: 45139
A5: CAPITAL ADEQUACY REQUIREMENTS
A6: Core capital | B6: ≥ Ksh.10M | C6: 9.a | D6: =[2]Financials!C13/1000000 -> 0 | E6: =[2]Financials!D13/1000000 -> 0 | F6: =[2]Financials!E13/1000000 -> 0 | G6: =[2]Financials!F13/1000000 -> 0 | H6: =[2]Financials!G13/1000000 -> 0 | I6: =[2]Financials!H13/1000000 -> 0 | J6: =[2]Financials!I13/1000000 -> 0 | K6: =[2]Financials!J13/1000000 -> 817.08404 | ... AJ6: =[2]Financials!AI13/1000000 -> 3266.1901 | AK6: =Financials!D11/1000000 -> #REF! | AL6: =Financials!E11/1000000 -> #REF! | AM6: =Financials!F11/1000000 -> #REF! | AN6: =Financials!G11/1000000 -> #REF! | AO6: =Financials!H11/1000000 -> #REF! | AP6: =Financials!I11/1000000 -> #REF! | AQ6: =Financials!J11/1000000 -> #REF! | AR6: =Financials!K11/1000000 -> #REF! | ... DU6: =Financials!CN11/1000000 -> 976.46801
A7: Core capital /Total Assets | B7: ≥ 10% | C7: 9.b | D7: =[2]Financials!C13/[2]Financials!C5 -> #DIV/0! | E7: =[2]Financials!D13/[2]Financials!D5 -> #DIV/0! | F7: =[2]Financials!E13/[2]Financials!E5 -> #DIV/0! | G7: =[2]Financials!F13/[2]Financials!F5 -> #DIV/0! | H7: =[2]Financials!G13/[2]Financials!G5 -> #DIV/0! | I7: =[2]Financials!H13/[2]Financials!H5 -> #DIV/0! | J7: =[2]Financials!I13/[2]Financials!I5 -> #DIV/0! | K7: =[2]Financials!J13/[2]Financials!J5 -> 0.094760341 | ... AJ7: =[2]Financials!AI13/[2]Financials!AI5 -> 0.21601607 | AK7: =Financials!D11/Financials!D4 -> #REF! | AL7: =Financials!E11/Financials!E4 -> #REF! | AM7: =Financials!F11/Financials!F4 -> #REF! | AN7: =Financials!G11/Financials!G4 -> #REF! | AO7: =Financials!H11/Financials!H4 -> #REF! | AP7: =Financials!I11/Financials!I4 -> #REF! | AQ7: =Financials!J11/Financials!J4 -> #REF! | AR7: =Financials!K11/Financials!K4 -> #REF! | ... DU7: =Financials!CN11/Financials!CN4 -> 0.18117331
A8: Core capital /Total Deposits | B8: ≥ 8% | C8: 9.d | D8: =[2]Financials!C13/[2]Financials!C6 -> #DIV/0! | E8: =[2]Financials!D13/[2]Financials!D6 -> #DIV/0! | F8: =[2]Financials!E13/[2]Financials!E6 -> #DIV/0! | G8: =[2]Financials!F13/[2]Financials!F6 -> #DIV/0! | H8: =[2]Financials!G13/[2]Financials!G6 -> #DIV/0! | I8: =[2]Financials!H13/[2]Financials!H6 -> #DIV/0! | J8: =[2]Financials!I13/[2]Financials!I6 -> #DIV/0! | K8: =[2]Financials!J13/[2]Financials!J6 -> 0.10894732 | ... AJ8: =[2]Financials!AI13/[2]Financials!AI6 -> 0.31853331 | AK8: =Financials!D11/Financials!D5 -> #REF! | AL8: =Financials!E11/Financials!E5 -> #REF! | AM8: =Financials!F11/Financials!F5 -> #REF! | AN8: =Financials!G11/Financials!G5 -> #REF! | AO8: =Financials!H11/Financials!H5 -> #REF! | AP8: =Financials!I11/Financials!I5 -> #REF! | AQ8: =Financials!J11/Financials!J5 -> #REF! | AR8: =Financials!K11/Financials!K5 -> #REF! | ... DU8: =Financials!CN11/Financials!CN5 -> 0.24202993
A9: Share Capital/Total Assets | B9: ≤2% | C9: 9.c | D9: =[2]Financials!C17/[2]Financials!C5 -> #DIV/0! | E9: =[2]Financials!D17/[2]Financials!D5 -> #DIV/0! | F9: =[2]Financials!E17/[2]Financials!E5 -> #DIV/0! | G9: =[2]Financials!F17/[2]Financials!F5 -> #DIV/0! | H9: =[2]Financials!G17/[2]Financials!G5 -> #DIV/0! | I9: =[2]Financials!H17/[2]Financials!H5 -> #DIV/0! | J9: =[2]Financials!I17/[2]Financials!I5 -> #DIV/0! | K9: =[2]Financials!J17/[2]Financials!J5 -> 0.012974221 | ... AJ9: =[2]Financials!AI17/[2]Financials!AI5 -> 0.046002918 | AK9: =Financials!D15/Financials!D4 -> #REF! | AL9: =Financials!E15/Financials!E4 -> #REF! | AM9: =Financials!F15/Financials!F4 -> #REF! | AN9: =Financials!G15/Financials!G4 -> #REF! | AO9: =Financials!H15/Financials!H4 -> #REF! | AP9: =Financials!I15/Financials!I4 -> #REF! | AQ9: =Financials!J15/Financials!J4 -> #REF! | AR9: =Financials!K15/Financials!K4 -> #REF! | ... DU9: =Financials!CN15/Financials!CN4 -> 0.043400804
A10: Institutional Capital/Total Assets | B10: ≥ 8% | C10: 9.c | D10: =[2]Financials!C14/[2]Financials!C5 -> #DIV/0! | E10: =[2]Financials!D14/[2]Financials!D5 -> #DIV/0! | F10: =[2]Financials!E14/[2]Financials!E5 -> #DIV/0! | G10: =[2]Financials!F14/[2]Financials!F5 -> #DIV/0! | H10: =[2]Financials!G14/[2]Financials!G5 -> #DIV/0! | I10: =[2]Financials!H14/[2]Financials!H5 -> #DIV/0! | J10: =[2]Financials!I14/[2]Financials!I5 -> #DIV/0! | K10: =[2]Financials!J14/[2]Financials!J5 -> 0.08178612 | ... AJ10: =[2]Financials!AI14/[2]Financials!AI5 -> 0.17001315 | AK10: =Financials!D12/Financials!D4 -> #REF! | AL10: =Financials!E12/Financials!E4 -> #REF! | AM10: =Financials!F12/Financials!F4 -> #REF! | AN10: =Financials!G12/Financials!G4 -> #REF! | AO10: =Financials!H12/Financials!H4 -> #REF! | AP10: =Financials!I12/Financials!I4 -> #REF! | AQ10: =Financials!J12/Financials!J4 -> #REF! | AR10: =Financials!K12/Financials!K4 -> #REF! | ... DU10: =Financials!CN12/Financials!CN4 -> 0.1377725
A12: ASSET MIX AND QUALITY
A13: Non Earning Assets
A14: Non earning Assets/Total assets | B14: ≤ 10% | C14: 48.1 | D14: =[2]Financials!C38/[2]Financials!C5 -> #DIV/0! | E14: =[2]Financials!D38/[2]Financials!D5 -> #DIV/0! | F14: =[2]Financials!E38/[2]Financials!E5 -> #DIV/0! | G14: =[2]Financials!F38/[2]Financials!F5 -> #DIV/0! | H14: =[2]Financials!G38/[2]Financials!G5 -> #DIV/0! | I14: =[2]Financials!H38/[2]Financials!H5 -> #DIV/0! | J14: =[2]Financials!I38/[2]Financials!I5 -> #DIV/0! | K14: =[2]Financials!J38/[2]Financials!J5 -> 0.019195265 | ... AJ14: =[2]Financials!AI38/[2]Financials!AI5 -> 0.042248924 | AK14: =('Evolutive SFP'!#REF!+'Evolutive SFP'!#REF!+'Evolutive SFP'!#REF!-'Evolutive SFP'!#REF!)/'Evolutive SFP'!#REF! -> #REF! | AL14: =('Evolutive SFP'!#REF!+'Evolutive SFP'!#REF!+'Evolutive SFP'!#REF!)/'Evolutive SFP'!#REF! -> #REF! | AM14: =('Evolutive SFP'!#REF!+'Evolutive SFP'!#REF!+'Evolutive SFP'!#REF!)/'Evolutive SFP'!#REF! -> #REF! | AN14: =('Evolutive SFP'!#REF!+'Evolutive SFP'!#REF!+'Evolutive SFP'!#REF!)/'Evolutive SFP'!#REF! -> #REF! | AO14: =('Evolutive SFP'!#REF!+'Evolutive SFP'!#REF!+'Evolutive SFP'!#REF!)/'Evolutive SFP'!#REF! -> #REF! | AP14: =('Evolutive SFP'!#REF!+'Evolutive SFP'!#REF!+'Evolutive SFP'!#REF!)/'Evolutive SFP'!#REF! -> #REF! | AQ14: =('Evolutive SFP'!#REF!+'Evolutive SFP'!#REF!+'Evolutive SFP'!#REF!)/'Evolutive SFP'!#REF! -> #REF! | AR14: =('Evolutive SFP'!#REF!+'Evolutive SFP'!#REF!+'Evolutive SFP'!#REF!)/'Evolutive SFP'!#REF! -> #REF! | AS14: =('Evolutive SFP'!#REF!+'Evolutive SFP'!#REF!+'Evolutive SFP'!#REF!)/'Evolutive SFP'!#REF! -> #REF! | ... BY14: =('Evolutive SFP'!#REF!+'Evolutive SFP'!#REF!+'Evolutive SFP'!#REF!)/'Evolutive SFP'!#REF! -> #REF! | BZ14: =('Evolutive SFP'!B7+'Evolutive SFP'!B17+'Evolutive SFP'!B21)/'Evolutive SFP'!B27 -> 0.052726313 | CA14: =('Evolutive SFP'!C7+'Evolutive SFP'!C17+'Evolutive SFP'!C21)/'Evolutive SFP'!C27 -> 0.054534989 | CB14: =('Evolutive SFP'!D7+'Evolutive SFP'!D17+'Evolutive SFP'!D21)/'Evolutive SFP'!D27 -> 0.044020111 | CC14: =('Evolutive SFP'!E7+'Evolutive SFP'!E17+'Evolutive SFP'!E21)/'Evolutive SFP'!E27 -> 0.043410658 | CD14: =('Evolutive SFP'!F7+'Evolutive SFP'!F17+'Evolutive SFP'!F21)/'Evolutive SFP'!F27 -> 0.060860733 | CE14: =('Evolutive SFP'!G7+'Evolutive SFP'!G17+'Evolutive SFP'!G21)/'Evolutive SFP'!G27 -> 0.043489686 | CF14: =('Evolutive SFP'!H7+'Evolutive SFP'!H17+'Evolutive SFP'!H21)/'Evolutive SFP'!H27 -> 0.044695726 | CG14: =('Evolutive SFP'!I7+'Evolutive SFP'!I17+'Evolutive SFP'!I21)/'Evolutive SFP'!I27 -> 0.042881731 | ... DU14: =('Evolutive SFP'!AW7+'Evolutive SFP'!AW17+'Evolutive SFP'!AW21)/'Evolutive SFP'!AW27 -> #DIV/0!
A15: Property and Equipment/Total Assets | B15: ≤ 5% | C15: 48.1 | D15: =[2]Financials!C39/[2]Financials!C5 -> #DIV/0! | E15: =[2]Financials!D39/[2]Financials!D5 -> #DIV/0! | F15: =[2]Financials!E39/[2]Financials!E5 -> #DIV/0! | G15: =[2]Financials!F39/[2]Financials!F5 -> #DIV/0! | H15: =[2]Financials!G39/[2]Financials!G5 -> #DIV/0! | I15: =[2]Financials!H39/[2]Financials!H5 -> #DIV/0! | J15: =[2]Financials!I39/[2]Financials!I5 -> #DIV/0! | K15: =[2]Financials!J39/[2]Financials!J5 -> 0.019195265 | ... AJ15: =[2]Financials!AI39/[2]Financials!AI5 -> 0.042248924 | AK15: =Financials!D35/Financials!D4 -> #REF! | AL15: =Financials!E35/Financials!E4 -> #REF! | AM15: =Financials!F35/Financials!F4 -> #REF! | AN15: =Financials!G35/Financials!G4 -> #REF! | AO15: =Financials!H35/Financials!H4 -> #REF! | AP15: =Financials!I35/Financials!I4 -> #REF! | AQ15: =Financials!J35/Financials!J4 -> #REF! | AR15: =Financials!K35/Financials!K4 -> #REF! | ... DU15: =Financials!CN35/Financials!CN4 -> 0.020416
