Workbook

Sheet Sheet2
D17: =30329098+16329321+2788735 -> 49447154

Sheet statement of deposit

Sheet STATEMENT OF FINANCIAL POSITION
B1: FORM 6 SASRA2/006
B2: STATEMENT OF FINANCIAL POSITION
B3: NAME OF SACCO SOCIETY: YETU
B4: FINANCIAL YEAR : 2017
B5: START DATE: 1st January 2017
B6: END DATE: 31st December 2017
C7: 2010 | D7: 2011 Audited | E7: 2012 audited | F7: 2013 AUDITED | G7: 2014 AUDITED | H7: AUDITED 2015 | I7: AUDITED 2016 | J7: 42736 | K7: 42767 | L7: 42795 | M7: 42826 | N7: 42856 | O7: 42887 | P7: 42917 | Q7: 42948 | R7: 42979 | S7: 43009 | T7: 43040 | U7: 43070 | V7: AUDITED 2017 | W7: AUDITED 2019 | X7: Dcember 2020 | Y7: AUDITED 2020 | Z7: 44197 | AA7: 44228 | AB7: 44256 | AC7: 44287 | AD7: 44317 | AE7: 44348 | AF7: 44378 | AG7: 44409 | AH7: 44440 | AI7: 44470 | AJ7: 44501 | AK7: 44531 | AL7: Audited 2021 | AM7: 44562 | AN7: 44593 | AO7: 44621 | AP7: 44652 | AQ7: 44682 | AR7: 44713 | AS7: 44743 | AT7: 44774 | AU7: 44805 | AV7: 44835 | AW7: 44866 | AX7: 44896 | AY7: Audited 2022 | AZ7: 44927 | BA7: 44958 | BB7: 44986 | BC7: 45017 | BD7: 45047 | BE7: 45078 | BF7: 45108
A9: Ref No | B9: ASSETS
A10: 1 | B10: Cash & Cash Equivalent | C10: =SUM(C11:C12) -> 169242912 | D10: =SUM(D11:D12) -> 257607037 | E10: =SUM(E11:E12) -> 266034639 | F10: =SUM(F11:F12) -> 396472718 | G10: =SUM(G11:G12) -> 407827391 | H10: =SUM(H11:H12) -> 624424540 | I10: =SUM(I11:I12) -> 420746946 | J10: =SUM(J11:J12) -> 7.2882087e+08 | ... BF10: =SUM(BF11:BF12) -> 1.1457232e+09
A11: 1.1 | B11: Cash in hand(both local and foreign notes and coins) | C11: 5659875 | D11: =257607037-179690522 -> 77916515 | E11: 15117143 | F11: ='[1]10,11,12,13'!$G$43 -> 11530858 | G11: =15905344+1100000+38820+641399+1424491 -> 19110054 | H11: =19214131+1300000+68799+807651+4505344 -> 25895925 | I11: =31664084+4550000+31779+677410+4358010 -> 41281283 | J11: 27605410 | K11: 45114693 | L11: 35947494 | M11: 29188907 | N11: 49471932 | O11: 36007322 | P11: 38435553 | Q11: 29323247 | R11: 40994679 | S11: 42150848 | T11: 55282901 | U11: 45283542 | V11: =40309430+6350000+24439+612009+5722240 -> 53018118 | W11: 41378132 | X11: 37200001 | Y11: =30730467+6450000+206308+515714+5969837+1245573+357487 -> 45475386 | Z11: 28426642 | AA11: 36369510 | AB11: 43235335 | AC11: 42456784 | AD11: 41511498 | AE11: 47226217 | AF11: 36157295 | AG11: 38964562 | AH11: 44352302 | AI11: 48985175 | AJ11: 44484659 | AK11: 4.1337802e+08 | AL11: 64478697 | AM11: 47013157 | AN11: 39791215 | AO11: 42336935 | AP11: 39488722 | AQ11: 40859612 | AR11: 42016946 | AS11: 54794824 | AT11: 35184439 | AU11: 46653739 | AV11: 46813083 | AW11: 53790313 | AX11: 46306289 | AY11: 38940535 | AZ11: 54834000 | BA11: 50877124 | BB11: 56270558 | BC11: 45060785 | BD11: 35975675 | BE11: 43436919 | BF11: 52624586
A12: 1.2 | B12: Cash at bank:(placement with financial institutions) | C12: =169242912-5659875 -> 163583037 | D12: =179690522 -> 179690522 | E12: =266034639-E11 -> 250917496 | F12: ='[1]10,11,12,13'!$G$48-'[1]10,11,12,13'!$G$43 -> 384941860 | G12: =205741791+1064890+181910656 -> 388717337 | H12: =11945236+110843+127304+3146057+295099840+6600000+30462654+2539604+2155811+500000+1217444+1057790+210467402+32101630+997000 -> 598528615 | I12: =979604+111028+127516+279762+340000000+7800000+16909887+7733190-140320+500000+20000+1057206+4087790 -> 379465663 | J12: 7.0121546e+08 | K12: 5.9891297e+08 | L12: 5.4016807e+08 | M12: 5.2916761e+08 | N12: 4.4529108e+08 | O12: 4.3855114e+08 | P12: 4.1590804e+08 | Q12: 3.7217425e+08 | R12: 3.696272e+08 | S12: 1.4966014e+09 | T12: 1.1404416e+09 | U12: 1.0269239e+09 | V12: =9885789+110588+127076+351783+420000000+9000000+12648236+15693241+688304+500000+17410+471011+87790 -> 469581228 | W12: =1066133866-W11 -> 1024755734 | X12: =1259116815.56-70000000 -> 1.1891168e+09 | Y12: =384765963+69494+91717698+185967+110431794+593670514 -> 1180841430 | Z12: 1.1024555e+09 | AA12: 1.0061992e+09 | AB12: 999194890 | AC12: 9.9903538e+08 | AD12: 9.6885439e+08 | AE12: 9.3234648e+08 | AF12: 9.5523646e+08 | AG12: 9.2205699e+08 | AH12: 8.8342735e+08 | AI12: 1.4701645e+09 | AJ12: 1.3411901e+09 | AL12: =271087875+59894+5993809+95527+40425932+188551320+80600000+671459286 -> 1258273643 | AM12: 1.2576145e+09 | AN12: 1.1504264e+09 | AO12: 1.1152005e+09 | AP12: 1.1145403e+09 | AQ12: 1.1278092e+09 | AR12: 1.1139143e+09 | AS12: 1.8707173e+09 | AT12: 1.7752339e+09 | AU12: 1.6212936e+09 | AV12: 1.5731022e+09 | AW12: 1.5381152e+09 | AX12: 1.4559655e+09 | AY12: =1502271759-38940535 -> 1463331224 | AZ12: 1.3651628e+09 | BA12: 1.2053548e+09 | BB12: 1.0921819e+09 | BC12: 1.1214988e+09 | BD12: 1.116658e+09 | BE12: 1.0878421e+09 | BF12: 1.0930986e+09
BF13: 0
A14: 2 | B14: Prepayments & Sundry Receivables | C14: 46579272 | D14: 47499560 | E14: 71142033 | F14: ='[1]5,'!$E$16 -> 72147099 | G14: 75848761 | H14: =56260+3000000+48374+200000+868781+3000+50000+17000+54062881+487494+462668+796000+45000+20000+23438541+2617124+496518+454518+4415+215227+112330+174253+474723+47621 -> 88152728 | I14: =56260+3000000+104553+200000+905659+3000+50000+17000+55234231+14110500+583502+796000+612480+90000+20000+32430901+2490887+496518+42236+2859306+31279+2618516+815007+6242272+487494+130000+1500960+21940 -> 125950501 | J14: 1.3487634e+08 | K14: 1.3039381e+08 | L14: 1.3186059e+08 | M14: 1.3896669e+08 | N14: 1.5144308e+08 | O14: 1.6100822e+08 | P14: 1.7848629e+08 | Q14: 1.8087116e+08 | R14: 1.9173963e+08 | S14: 86004695 | T14: 1.082659e+08 | U14: 1.2278335e+08 | V14: =56260+88358+200000+991501+3000+50000+17000+60725920+1113106+796000+612480+90000+20000+39066692+2422490+496518+29899+4037229+46400+4894469+4207200+487494+130000+750000+1349331+102000 -> 122783347 | W14: 145701460 | X14: 1.6785226e+08 | Y14: =56260+50000+200000+1526864+3000+50000+17000+596316+824000+118000+20000+5745+92297+13318+2014260+578000+341400+1884611+178151+631060+45600+114000+14996+26000-(3079957)+113914696+43800355+1529858 -> 165565830 | Z14: 1.611827e+08 | AA14: 1.7951242e+08 | AB14: 1.8644156e+08 | AC14: 1.9360442e+08 | AD14: 2.037857e+08 | AE14: 2.0615418e+08 | AF14: 2.0436892e+08 | AG14: 2.1421149e+08 | AH14: 2.2805852e+08 | AI14: 1.5373286e+08 | AJ14: 1.73035e+08 | AL14: 168997681 | AM14: 1.7236174e+08 | AN14: 2.0818255e+08 | AO14: 2.1313869e+08 | AP14: 2.1869522e+08 | AQ14: 230946024 | AR14: 2.4862466e+08 | AS14: 1.990429e+08 | AT14: 2.3048805e+08 | AU14: 2.5086998e+08 | AV14: 2.6569739e+08 | AW14: 2.7886857e+08 | AX14: 2.876492e+08 | AY14: 288102791 | AZ14: 2.7572855e+08 | BA14: 2.9291718e+08 | BB14: 3.1376555e+08 | BC14: 3.2639609e+08 | BD14: 3.3909827e+08 | BE14: 3.536472e+08 | BF14: 3.6628387e+08
AY15: 0
A16: 3 | B16: Financial Investments | C16: =SUM(C17:C21) -> 14091580 | D16: =SUM(D17:D21) -> 15191580 | E16: =SUM(E17:E21) -> 15191580 | F16: =SUM('[1]10,11,12,13'!$G$125:$G$130) -> 15985700 | G16: =SUM(G17:G21) -> 26085700 | H16: =SUM(H17:H21) -> 27282077 | I16: =SUM(I17:I21) -> 411782430 | J16: =SUM(J17:J21) -> 31082077 | K16: =SUM(K17:K21) -> 31082077 | L16: =SUM(L17:L21) -> 31082077 | M16: =SUM(M17:M21) -> 31082077 | N16: =SUM(N17:N21) -> 31082077 | ... BF16: =SUM(BF17:BF21) -> 143294140
A17: 3.1 | B17: Government Securities - Treasury Bills/bonds, | F17: 0 | J17: 0 | K17: 0 | L17: 0 | X17: 70000000 | Y17: =70000000 -> 70000000 | Z17: 70000000 | AA17: 70000000 | AB17: 70000000 | AC17: 70000000 | AD17: 70000000 | AE17: 70000000 | AF17: 70000000 | AG17: 70000000 | AH17: 70000000 | AI17: 70000000 | AJ17: 70000000 | AL17: 70000000 | AM17: 70000000 | AN17: 70000000 | AO17: 70000000 | AP17: 70000000 | AQ17: 70000000 | AR17: 70000000 | AS17: 70000000 | AT17: 40000000 | AU17: 40000000 | AV17: 40000000 | AW17: 0 | AX17: 0 | AY17: 0 | AZ17: 0 | BA17: 0 | BB17: 0 | BC17: 0 | BD17: 0 | BE17: 0 | BF17: 0
A18: 3.2 | B18: Other Securities - Commercial papers/Bonds | F18: 0 | J18: 0 | K18: 0 | L18: 0 | Z18: 0 | AA18: 0 | AB18: 0 | AC18: 0 | AD18: 0 | AE18: 0 | AF18: 0 | AG18: 0 | AM18: 0 | AN18: 0 | AO18: 0 | AP18: 0 | AQ18: 0 | AR18: 0 | AS18: 0 | AT18: 0 | AU18: 0 | AV18: 0 | AW18: 0 | AX18: 0 | AY18: 0 | AZ18: 0 | BA18: 0 | BB18: 0 | BC18: 0 | BD18: 0 | BE18: 0 | BF18: 0
A19: 3.3a | B19: Balances in NACCOS (E.g Jungu Kuu, ESS, Savings,Money Market,Coop FD, CFP) | F19: 0 | I19: =346954860+32748493+997000 -> 380700353 | J19: 0 | K19: 0 | L19: 0 | V19: =495029531+33408391+1000000+20170124 -> 549608046 | W19: =12398904+2575560+1000000+12333571+9000 -> 28317035 | Y19: =12398904+2575560+1000000+100000+12333571+9000 -> 28417035 | Z19: 0 | AA19: 0 | AB19: 0 | AC19: 0 | AD19: 0 | AE19: 0 | AF19: 0 | AG19: 0 | AM19: 0 | AN19: 0 | AO19: 0 | AP19: 0 | AQ19: 0 | AR19: 0 | AS19: 0 | AT19: 0 | AU19: 0 | AV19: 0 | AW19: 0 | AX19: 0 | AY19: 0 | AZ19: 0 | BA19: 0 | BB19: 0 | BC19: 0 | BD19: 0 | BE19: 0 | BF19: 0
B20: Equity Investments in NACCOs(Shares in- CIC, KUSCCO, COOP BANK,CAK, KERUSSU) | AL20: =12398904+2575560+1000000+20333571+9000 -> 36317035 | AY20: 137404140 | BF20: 0
A21: 3.3b | B21: Equity Investments in companies - shares/stocks | C21: 14091580 | D21: 15191580 | E21: 15191580 | F21: =SUM('[1]10,11,12,13'!$G$125:$G$130) -> 15985700 | G21: 26085700 | H21: =10332420+2575560+3265097+9000+1000000+100000+10000000 -> 27282077 | I21: =10332420+2575560+7065097+9000+1000000+100000+10000000 -> 31082077 | J21: 31082077 | K21: 31082077 | L21: 31082077 | M21: 31082077 | N21: 31082077 | O21: 31082077 | P21: 31082077 | Q21: 31082077 | R21: 31082077 | S21: 31082077 | T21: 51082077 | U21: 33417035 | V21: =12398904+2575560+1000000+100000+10000000+7333571+9000 -> 33417035 | W21: =100000+10000000 -> 10100000 | X21: 38417035 | Y21: 10000000 | Z21: 38417035 | AA21: 38417035 | AB21: 38417035 | AC21: 38417035 | AD21: 38417035 | AE21: 38417035 | AF21: 48917035 | AG21: 48917035 | AH21: 48917035 | AI21: 46417035 | AJ21: 46417035 | AL21: =100000+10000000 -> 10100000 | AM21: 46417035 | AN21: 58617035 | AO21: 58617035 | AP21: 58617035 | AQ21: 58617035 | AR21: 58617035 | AS21: 58617035 | AT21: 58617035 | AU21: 58617035 | AV21: 58617035 | AW21: 58617035 | AX21: 137404140 | AY21: 0 | AZ21: 137404140 | BA21: 137404140 | BB21: 137404140 | BC21: 137404140 | BD21: 143294140 | BE21: 143294140 | BF21: 143294140
A23: 4 | B23: Net Loan Portfolio | C23: =C24-C25 -> 502161933 | D23: =D24-D25 -> 701336906 | E23: =E24-E25 -> 842727981 | F23: =F24-F25 -> 1018650165 | G23: =G24-G25 -> 1128533399 | H23: =H24-H25 -> 1189398328 | I23: =I24-I25 -> 1390743016 | J23: =J24-J25 -> 1.4342734e+09 | ... BF23: =BF24-BF25 -> 3.7911369e+09
B24: Gross Loan Portfolio | C24: 502161933 | D24: 701336906 | E24: 866580456 | F24: =SUM('[1]10,11,12,13'!$G$83:$G$103) -> 1050502640 | G24: 1169889815 | H24: =971478121+16079464+29061764-2680000+28074187+9490022+49046+2321440+10203+131055567+4574407+73311+11986739+23688653+19598761+11937779+494722+1239178+1505137+1000 -> 1260039501 | I24: =944396801+19556130+35445402+-30000+27290321+172222+11846083+87635+1018525+10203+370493220+4439227+58806+13773291+27239013+12910863+20515212+114722+925659+574033+2214 -> 1490839582 | J24: 1.537245e+09 | K24: 1.5641423e+09 | L24: 1.5932334e+09 | M24: 1.6206928e+09 | N24: 1.6860856e+09 | O24: 1.726473e+09 | P24: 1.765986e+09 | Q24: 1.7962765e+09 | R24: 1.8285024e+09 | S24: 1.4289648e+09 | T24: 1.6339078e+09 | U24: 1.7208272e+09 | V24: =11853049+32617396+597725135+1044797338+33834328 -> 1720827246 | W24: 2700721660 | X24: 2.9836566e+09 | Y24: =2700721660+1831425144-(1548490178) -> 2983656626 | Z24: 3.0212551e+09 | AA24: 3.0695181e+09 | AB24: 3.1303044e+09 | AC24: 3.1805279e+09 | AD24: 3.2399479e+09 | AE24: 3.2950827e+09 | AF24: 3.3209628e+09 | AG24: 3.3497253e+09 | AH24: 3.3692725e+09 | AI24: 3.1778765e+09 | AJ24: 3.3136588e+09 | AL24: 3379491104 | AM24: 3.3663871e+09 | AN24: 3.3998942e+09 | AO24: 3.462765e+09 | AP24: 3.5105662e+09 | AQ24: 3.5436692e+09 | AR24: 3.5968934e+09 | AS24: 3.3836114e+09 | AT24: 3.467788e+09 | AU24: 3.5419276e+09 | AV24: 3.587463e+09 | AW24: 3.6754916e+09 | AX24: 3.7482133e+09 | AY24: 3748213331 | AZ24: 3.7453111e+09 | BA24: 3.8234964e+09 | BB24: 4.0186352e+09 | BC24: 4.0561304e+09 | BD24: 4.1114597e+09 | BE24: 4.1978306e+09 | BF24: 4.2438236e+09
B25: Allowance for Loan Loss | E25: 23852475 | F25: =-'[1]10,11,12,13'!$G$105 -> 31852475 | G25: 41356416 | H25: 70641173 | I25: 100096566 | J25: 1.0297157e+08 | K25: 1.0584657e+08 | L25: 1.0872157e+08 | M25: 1.1159657e+08 | N25: 1.1447157e+08 | O25: 1.1734657e+08 | P25: 1.2022157e+08 | Q25: 1.2309657e+08 | R25: 1.2597157e+08 | S25: 1.2884657e+08 | T25: 1.3172157e+08 | U25: 1.3459657e+08 | V25: 134596566 | W25: 331778022 | X25: 3.7287802e+08 | Y25: 372878022 | Z25: 3.7737802e+08 | AA25: 3.8187802e+08 | AB25: 3.8637802e+08 | AC25: 3.9087802e+08 | AD25: 3.9537802e+08 | AE25: 3.9987802e+08 | AF25: 4.0437802e+08 | AG25: 4.0887802e+08 | AH25: 4.1337802e+08 | AI25: 4.1787802e+08 | AJ25: 4.2237802e+08 | AL25: =23485219+20504695+86912138+42948825+187329149+20697996 -> 381878022 | AM25: 3.8637802e+08 | AN25: 3.9087802e+08 | AO25: 3.8187802e+08 | AP25: 3.8187802e+08 | AQ25: 3.8187802e+08 | AR25: 3.8187802e+08 | AS25: 4.1550538e+08 | AT25: 4.316035e+08 | AU25: 4.3551467e+08 | AV25: 4.4992735e+08 | AW25: 4.5295642e+08 | AX25: 4.359408e+08 | AY25: 435940797 | AZ25: 4.359408e+08 | BA25: 4.359408e+08 | BB25: 4.4795997e+08 | BC25: 4.7331125e+08 | BD25: 4.7116508e+08 | BE25: 4.6823846e+08 | BF25: 4.5268676e+08
A27: 5 | B27: Accounts Receivables | C27: =SUM(C28:C30) -> 0 | D27: =SUM(D28:D30) -> 0 | E27: =SUM(E28:E30) -> 0 | F27: =SUM(F28:F30) -> 0 | G27: =SUM(G28:G30) -> 0 | H27: =SUM(H28:H30) -> 0 | I27: =SUM(I28:I30) -> 0 | J27: =SUM(J28:J30) -> 0 | ... BF27: =SUM(BF28:BF30) -> 0
A28: 5.1 | B28: Tax Recoverable | J28: 0 | K28: 0 | L28: 0 | Z28: 0 | AA28: 0 | AB28: 0 | AC28: 0 | AD28: 0 | AE28: 0 | AF28: 0 | AG28: 0 | AH28: 0 | AI28: 0 | AJ28: 0 | AK28: 0 | AL28: 0 | AM28: 0 | AN28: 0 | AO28: 0 | AP28: 0 | AQ28: 0 | AR28: 0 | AS28: 0 | AT28: 0 | AU28: 0 | AV28: 0 | AW28: 0 | AX28: 0 | AY28: 0 | AZ28: 0 | BA28: 0 | BB28: 0 | BC28: 0 | BD28: 0 | BE28: 0 | BF28: 0
A29: 5.2 | B29: Deferred Tax Assets | J29: 0 | K29: 0 | L29: 0 | Z29: 0 | AA29: 0 | AB29: 0 | AC29: 0 | AD29: 0 | AE29: 0 | AF29: 0 | AG29: 0 | AH29: 0 | AI29: 0 | AJ29: 0 | AK29: 0 | AL29: 0 | AM29: 0 | AN29: 0 | AO29: 0 | AP29: 0 | AQ29: 0 | AR29: 0 | AS29: 0 | AT29: 0 | AU29: 0 | AV29: 0 | AW29: 0 | AX29: 0 | AY29: 0 | AZ29: 0 | BA29: 0 | BB29: 0 | BC29: 0 | BD29: 0 | BE29: 0 | BF29: 0
A30: 5.3 | B30: Retirement Benefit Assets | J30: 0 | K30: 0 | L30: 0 | Z30: 0 | AA30: 0 | AB30: 0 | AC30: 0 | AD30: 0 | AE30: 0 | AF30: 0 | AG30: 0 | AH30: 0 | AI30: 0 | AJ30: 0 | AK30: 0 | AL30: 0 | AM30: 0 | AN30: 0 | AO30: 0 | AP30: 0 | AQ30: 0 | AR30: 0 | AS30: 0 | AT30: 0 | AU30: 0 | AV30: 0 | AW30: 0 | AX30: 0 | AY30: 0 | AZ30: 0 | BA30: 0 | BB30: 0 | BC30: 0 | BD30: 0 | BE30: 0 | BF30: 0
A32: 6 | B32: Property & Equipment & Other assets | C32: =SUM(C33:C37) -> 154877010 | D32: =SUM(D33:D37) -> 163611477 | E32: =SUM(E33:E37) -> 40224658 | F32: =SUM(F33:F37) -> 56850072 | G32: =SUM(G33:G37) -> 61006144 | H32: =SUM(H33:H37) -> 66390514 | I32: =SUM(I33:I37) -> 66106031 | J32: =SUM(J33:J37) -> 64982708 | ... BF32: =SUM(BF33:BF37) -> 1.330682e+08
A33: 6.1 | B33: Investment Properties | J33: 0 | K33: 0 | L33: 0 | Z33: 0 | AA33: 0 | AB33: 0 | AC33: 0 | AD33: 0 | AE33: 0 | AF33: 0 | AG33: 0 | AH33: 0 | AI33: 0 | AJ33: 0 | AM33: 0 | AN33: 0 | AO33: 0 | AP33: 0 | AQ33: 0 | AR33: 0 | AS33: 0 | AT33: 0 | AU33: 0 | AV33: 0 | AW33: 0 | AX33: 0 | AY33: 0 | AZ33: 0 | BA33: 0 | BB33: 0 | BC33: 0 | BD33: 0 | BE33: 0 | BF33: 0
A34: 6.2 | B34: Property & Equipment | C34: 152497884 | D34: 161391712 | E34: 37777814 | F34: 43577028 | G34: =48999115 -> 48999115 | H34: =550003+11888666+1427675+531789+379759+12845142+2480271+4706389+6270301+5172805+5532802 -> 51785602 | I34: =550003+11557867+1427675+813196+253299+11981094+4914703+5641159+3872961+7125211+4119604 -> 52256772 | J34: 51142952 | K34: 50372952 | L34: 57553590 | M34: 56640190 | N34: 57428420 | O34: 56657966 | P34: 55507966 | Q34: 54357966 | R34: 53207966 | S34: 52059766 | T34: 51009766 | U34: 53877677 | V34: =550003+11209775+1427675+1218764+168950+15244790+5082215+6867394+2711073+4987648+4409391 -> 53877678 | W34: 66081765 | X34: 62605321 | Y34: =62605319 -> 62605319 | Z34: 62752548 | AA34: 64668208 | AB34: 65943318 | AC34: 64693318 | AD34: 65141918 | AE34: 72433922 | AF34: 74437722 | AG34: 73861572 | AH34: 72611572 | AI34: 74473498 | AJ34: 73223498 | AL34: 79835394 | AM34: 75525877 | AN34: 75357577 | AO34: 79503660 | AP34: 79303660 | AQ34: 78864420 | AR34: 78016170 | AS34: 78753588 | AT34: 77503588 | AU34: 79023576 | AV34: 81145390 | AW34: 83543968 | AX34: 93512669 | AY34: 87413971 | AZ34: 92396669 | BA34: 91292769 | BB34: 90067769 | BC34: 88857269 | BD34: 88227764 | BE34: 95003332 | BF34: 94336757
A35: 6.3 | B35: Prepaid Lease rentals | J35: 0 | K35: 0 | L35: 0 | Z35: 0 | AA35: 0 | AB35: 0 | AC35: 0 | AD35: 0 | AE35: 0 | AF35: 0 | AG35: 0 | AH35: 0 | AI35: 0 | AJ35: 0 | AM35: 0 | AN35: 0 | AO35: 0 | AP35: 0 | AQ35: 0 | AR35: 0 | AS35: 0 | AT35: 0 | AU35: 0 | AV35: 0 | AW35: 0 | AX35: 0 | AZ35: 0 | BA35: 0 | BB35: 0 | BC35: 0 | BD35: 0 | BE35: 0 | BF35: 0
A36: 6.4 | B36: Intangible Assets | F36: ='[1]5,'!$E$21 -> 10500000 | G36: 10500000 | H36: 10500000 | I36: 10500000 | J36: 10500000 | K36: 10500000 | L36: 10500000 | M36: 10500000 | N36: 10500000 | O36: 10500000 | P36: 10500000 | Q36: 10500000 | R36: 10500000 | S36: 10500000 | T36: 10500000 | U36: 10500000 | V36: 10500000 | W36: 10500000 | X36: 10500000 | Y36: 10500000 | Z36: 10500000 | AA36: 10500000 | AB36: 10500000 | AC36: 10500000 | AD36: 10500000 | AE36: 10500000 | AF36: 10500000 | AG36: 15500000 | AH36: 15500000 | AI36: 15500000 | AJ36: 18840800 | AM36: 18771201 | AN36: 20771201 | AO36: 20771201 | AP36: 20771201 | AQ36: 20771201 | AR36: 20771201 | AS36: 20771201 | AT36: 26771201 | AU36: 26771201 | AV36: 26771201 | AW36: 26771201 | AX36: 28487112 | AY36: =11085811+23500000 -> 34585811 | AZ36: 28487112 | BA36: 31371464 | BB36: 33371464 | BC36: 33371464 | BD36: 33371464 | BE36: 33371464 | BF36: 33371464
A37: 6.5 | B37: Other Assets | C37: 2379126 | D37: 2219765 | E37: 2446844 | F37: =SUM('[1]10,11,12,13'!$G$110:$G$112) -> 2773044 | G37: 1507029 | H37: =3975033+89483+40396 -> 4104912 | I37: =3254493+63067+31699 -> 3349259 | J37: 3339755.7 | K37: 3442543.9 | L37: 3546236.3 | M37: 3523469.8 | N37: 3219292.9 | O37: 3545652.3 | P37: 3362454.4 | Q37: 3281327.4 | R37: 3712309.2 | S37: 3485724.8 | T37: 3491608.7 | U37: 3459012 | V37: =3416988+42024 -> 3459012 | W37: 5795087 | X37: 4960619.8 | Y37: =4694032+184683+81905 -> 4960620 | Z37: 5708255.1 | AA37: 5590625.8 | AB37: 5655718.7 | AC37: 5640373.3 | AD37: 5491151.5 | AE37: 5904890 | AF37: 5147500.8 | AG37: 5459773.5 | AH37: 5246111.4 | AI37: 5155908.9 | AJ37: 5689713.8 | AL37: =6161616+15500000 -> 21661616 | AM37: 6050806.1 | AN37: 6026427 | AO37: 5241792 | AP37: 5538856.7 | AQ37: 5374485.8 | AR37: 4816756.2 | AS37: 5453062.8 | AT37: 7395633 | AU37: 6899271.7 | AV37: 5976955.4 | AW37: 5207044.6 | AX37: 5497155.2 | AY37: 5497154 | AZ37: 6103437.8 | BA37: 4251815.1 | BB37: 4952074.2 | BC37: 5600971.8 | BD37: 5857515.8 | BE37: 5792215.2 | BF37: 5359980.9
B39: Total Assets | C39: =C10+C14+C16+C23+C27+C32 -> 886952707 | D39: =D10+D14+D16+D23+D27+D32 -> 1185246560 | E39: =E10+E14+E16+E23+E27+E32 -> 1235320891 | F39: =F10+F14+F16+F23+F27+F32 -> 1560105754 | G39: =G10+G14+G16+G23+G27+G32 -> 1699301395 | H39: =H10+H14+H16+H23+H27+H32 -> 1995648187 | I39: =I10+I14+I16+I23+I27+I32 -> 2415328924 | J39: =J10+J14+J16+J23+J27+J32 -> 2.3940354e+09 | ... BF39: =BF10+BF14+BF16+BF23+BF27+BF32 -> 5.5795063e+09
G40: =1699301395-G39 -> 0
B42: LIABILITIES
A43: 7 | B43: Savings Deposits - Withdrawable deposits - FOSA) | C43: =559229530-314641029 -> 244588501 | D43: =745419886-D44-D45 -> 330041524 | E43: =881752998-E44-E45 -> 375911745 | F43: ='[1]10,11,12,13'!$G$171-'[1]10,11,12,13'!$G$163-'[1]10,11,12,13'!$G$162 -> 412332952 | G43: =1097902733-G44-G45 -> 380508604 | H43: =17123169+257444328+2542189+20643827+14990455+103497918+64027614+2792952+5016+1331499+1948791+6773804+12347+25240538 -> 518374447 | I43: =17077340+359581397+4351414+21185880+14656346+127426754+3338792+5012+1208901+8439349+8491365+5920+25783228 -> 591551698 | J43: 5.3449424e+08 | K43: 5.3915638e+08 | L43: 4.9327734e+08 | M43: 4.9157957e+08 | N43: 4.8216283e+08 | O43: 4.7359464e+08 | P43: 4.7170944e+08 | Q43: 4.357921e+08 | R43: 4.0520479e+08 | S43: 1.0194839e+09 | T43: 8.527019e+08 | U43: 7.5913658e+08 | V43: =735216946 -> 735216946 | W43: =2347338824-(W44+W45) -> 1164138485 | X43: 8.6261593e+08 | Y43: =2600095208-(Y44+Y45) -> 1303353781 | Z43: 9.0877863e+08 | AA43: 8.4894259e+08 | AB43: 8.5413354e+08 | AC43: 8.3161113e+08 | AD43: 8.1110231e+08 | AE43: 7.8163848e+08 | AF43: 7.7539969e+08 | AG43: 7.2738991e+08 | AH43: 697691752 | AI43: 9.6607065e+08 | AJ43: 9.0680536e+08 | AL43: =17433011+369886504+28125593+23428792+14302573+265494831+555456347+5298339+1651829+6418340+22141214+29286616+10061936+74776466+624622 -> 1424387013 | AM43: 9.8181976e+08 | AN43: 8.9565987e+08 | AO43: 8.78877e+08 | AP43: 8.1876818e+08 | AQ43: 8.3374643e+08 | AR43: 8.0121564e+08 | AS43: 1.2103264e+09 | AT43: 1.1330193e+09 | AU43: 1.0449535e+09 | AV43: 9.9378425e+08 | AW43: 9.6368993e+08 | AX43: 9.2683409e+08 | AY43: 903796942 | AZ43: 1.0848922e+09 | BA43: 9.6368356e+08 | BB43: 9.6927827e+08 | BC43: 9.2796462e+08 | BD43: 9.3759838e+08 | BE43: 9.3675096e+08 | BF43: 9.4000987e+08
A44: 8 | B44: Short Term Deposits (e.g Fixed deposits, special savings) | C44: 54809992 | D44: 71496906 | E44: 70123169 | F44: ='[1]10,11,12,13'!$G$163 -> 128086820 | G44: 129187648 | H44: 138180559 | I44: =136545631 -> 136545631 | J44: 1.384246e+08 | K44: 1.3535966e+08 | L44: 1.3547914e+08 | M44: 1.3457832e+08 | N44: 1.2616683e+08 | O44: 1.2440166e+08 | P44: 1.2383756e+08 | Q44: 1.238467e+08 | R44: 1.3256759e+08 | S44: 1.3952065e+08 | T44: 1.4208416e+08 | U44: 1.4873617e+08 | V44: =148736165 -> 148736165 | W44: 267351145 | X44: 2.9243802e+08 | Y44: 292438021 | Z44: 3.0364147e+08 | AA44: 3.0543566e+08 | AB44: 3.1392218e+08 | AC44: 3.1371406e+08 | AD44: 3.1706284e+08 | AE44: 3.1728967e+08 | AF44: 3.0674438e+08 | AG44: 3.1696244e+08 | AH44: 3.1466149e+08 | AI44: 3.043008e+08 | AJ44: 3.1717381e+08 | AL44: =322814962 -> 322814962 | AM44: 3.3210957e+08 | AN44: 3.3760897e+08 | AO44: 3.4792479e+08 | AP44: 3.869918e+08 | AQ44: 3.7294935e+08 | AR44: 3.711988e+08 | AS44: 3.9741418e+08 | AT44: 3.9463205e+08 | AU44: 3.9756644e+08 | AV44: 3.9625292e+08 | AW44: 4.0455244e+08 | AX44: 4.0285861e+08 | AY44: 402858607 | AZ44: 3.1618299e+08 | BA44: 3.1219422e+08 | BB44: 3.1759302e+08 | BC44: 3.462979e+08 | BD44: 3.2424635e+08 | BE44: 3.1740326e+08 | BF44: 3.1814777e+08
A45: 9 | B45: Non withdrawable deposits (BOSA member deposits) | C45: 259831037 | D45: 343881456 | E45: 435718084 | F45: ='[1]10,11,12,13'!$G$162 -> 533687314 | G45: 588206481 | H45: 645106995 | I45: =705964567+127592317 -> 833556884 | J45: 8.4011294e+08 | K45: 8.4807822e+08 | L45: 8.5622319e+08 | M45: 8.706492e+08 | N45: 8.8252153e+08 | O45: 8.9403489e+08 | P45: 9.0175372e+08 | Q45: 9.0676538e+08 | R45: 9.1362438e+08 | S45: 9.3350164e+08 | T45: 8.9533632e+08 | U45: 9.0823093e+08 | V45: =17194763+476548275+5621617+22083185+14849831+157784164+173013983+4143685+6239+3052308+9402350+14230986+5862+34213314 -> 932150562 | W45: 915849194 | X45: 1.4450413e+09 | Y45: 1004303406 | Z45: 1.4627379e+09 | AA45: 1.4778964e+09 | AB45: 1.5012699e+09 | AC45: 1.5186985e+09 | AD45: 1.5411626e+09 | AE45: 1.5764766e+09 | AF45: 1.5977068e+09 | AG45: 1.6120456e+09 | AH45: 1.621443e+09 | AI45: 1.6289946e+09 | AJ45: 1.6430303e+09 | AL45: 1102313070 | AM45: 1.6740585e+09 | AN45: 1.6890618e+09 | AO45: 1.7101521e+09 | AP45: 1.7352145e+09 | AQ45: 1.7618692e+09 | AR45: 1.8077338e+09 | AS45: 1.824624e+09 | AT45: 1.8370985e+09 | AU45: 1.849297e+09 | AV45: 1.8627261e+09 | AW45: 1.8817101e+09 | AX45: 1.9087583e+09 | AY45: 1931795498 | AZ45: 1.9493737e+09 | BA45: 1.988218e+09 | BB45: 2.0448334e+09 | BC45: 2.0924216e+09 | BD45: 2.1234277e+09 | BE45: 2.1783698e+09 | BF45: 2.2010512e+09
B46: Total Deposit liabilities | C46: =SUM(C43:C45) -> 559229530 | D46: =SUM(D43:D45) -> 745419886 | E46: =SUM(E43:E45) -> 881752998 | F46: =SUM(F43:F45) -> 1074107086 | G46: =SUM(G43:G45) -> 1097902733 | H46: =SUM(H43:H45) -> 1301662001 | I46: =SUM(I43:I45) -> 1561654213 | J46: =SUM(J43:J45) -> 1.5130318e+09 | ... BF46: =SUM(BF43:BF45) -> 3.4592088e+09
A48: 10 | B48: Accounts Payable & Other Liabilities | C48: =SUM(C49:C54) -> 124683624 | D48: =SUM(D49:D54) -> 185272892 | E48: =SUM(E49:E54) -> 116642858 | F48: =SUM(F49:F54) -> 152025659 | G48: =SUM(G49:G54) -> 174706726 | H48: =SUM(H49:H54) -> 183884639 | I48: =SUM(I49:I54) -> 228190754 | J48: =SUM(J49:J54) -> 2.3839207e+08 | ... BF48: =SUM(BF49:BF54) -> 5.1005053e+08
A49: 10.1 | B49: Tax Payable | C49: 131500 | D49: 2499950 | E49: 1750966 | F49: =SUM('[1]10,11,12,13'!$G$183+'[1]10,11,12,13'!$G$184+'[1]10,11,12,13'!$G$185) -> 2670966 | G49: 2499729 | H49: =2499729+3000000-3716966 -> 1782763 | I49: 781663 | J49: 1531663 | K49: 249550 | L49: 999550 | M49: 2436321 | N49: 3186321 | O49: 3372642 | P49: 370267 | Q49: 1120267 | R49: 1306588 | S49: 2056588 | T49: 2806588 | U49: 992909 | V49: =(781663+7000000)-6788754 -> 992909 | X49: 987220 | Y49: 987220 | Z49: 2237220 | AA49: 3487220 | AB49: 4737220 | AC49: 1370000 | AD49: 2620000 | AE49: 229920 | AF49: 1479920 | AG49: 2729920 | AH49: 349920 | AI49: 1599920 | AJ49: 2849920 | AL49: 1469920 | AM49: 3136586.7 | AN49: 4803253.3 | AO49: 6469920 | AP49: 2166666.6 | AQ49: 3833333.3 | AR49: 989919.96 | AS49: 2656586.6 | AT49: 4323253.3 | AU49: 1489919.9 | AV49: 3156586.6 | AW49: 4823253.3 | AX49: 2776794.8 | AY49: 2776795 | AZ49: 8103968.3 | BA49: 9937301.7 | BB49: 11770635 | BC49: 655529.32 | BD49: 2488862.6 | BE49: -2355608 | BF49: -522274.69
A50: 10.2 | B50: Dividends Payable | C50: 38580247 | D50: 46299234 | E50: =56132762-23852475 -> 32280287 | F50: =SUM('[1]10,11,12,13'!$G$190+'[1]10,11,12,13'!$G$192+'[1]10,11,12,13'!$G$195) -> 80035493 | G50: =72781110 -> 72781110 | H50: =72781110+60000000-55323509 -> 77457601 | I50: 104242968 | J50: 1.0424297e+08 | K50: 3741716.2 | L50: 3741716.2 | M50: 3740716.2 | N50: 3740216.2 | O50: 3740216.2 | P50: 3739216.2 | Q50: 3739216.2 | R50: 3739216.2 | S50: 3739216.2 | T50: 3739216.2 | U50: 1.198784e+08 | V50: =104242968+115000000-95625351 -> 123617617 | X50: 1397423.1 | Z50: -196505.45 | AA50: -566669.13 | AB50: -566669.13 | AC50: -566669.13 | AD50: -566669.13 | AE50: -566669.13 | AF50: -566669.13 | AG50: -566669.13 | AH50: -566669.13 | AI50: -566669.13 | AJ50: -566669.13 | AL50: 240000000 | AM50: 13735194 | AN50: 12829975 | AO50: 12829975 | AP50: 12829975 | AQ50: 12829975 | AR50: 12829975 | AS50: 12829975 | AT50: 12829975 | AU50: 12829975 | AV50: 12829975 | AW50: 12829975 | AX50: 12833665 | AY50: 302833665 | AZ50: 19467029 | BA50: 19059454 | BB50: 18944735 | BC50: 18944735 | BD50: 18944735 | BE50: 18944735 | BF50: 18944735
A51: 10.3 | B51: Deferred Tax Liability | J51: 0 | K51: 0 | L51: 0 | Z51: 0 | AA51: 0 | AB51: 0 | AC51: 0 | AD51: 0 | AE51: 0 | AF51: 0 | AG51: 0 | AH51: 0 | AI51: 0 | AJ51: 0 | AM51: 0 | AN51: 0 | AO51: 0 | AP51: 0 | AQ51: 0 | AR51: 0 | AS51: 0 | AT51: 0 | AU51: 0 | AV51: 0 | AW51: 0 | AX51: 0 | AY51: 23968832 | AZ51: 0 | BA51: 0 | BB51: 0 | BC51: 0 | BD51: 0 | BE51: 0 | BF51: 0
A52: 10.4 | B52: Retirement Benefits Liability | J52: 45256436 | K52: 46057186 | L52: 46857936 | M52: 47658686 | N52: 48459436 | O52: 49260186 | P52: 50757456 | Q52: 50861686 | R52: 51402134 | S52: 52202884 | T52: 52835365 | U52: 53636115 | X52: 54475310 | Z52: 55308643 | AA52: 56141977 | AB52: 49073849 | AC52: 49907182 | AD52: 50740515 | AE52: 51573849 | AF52: 52407182 | AG52: 53240515 | AH52: 54073849 | AI52: 54907182 | AJ52: 55740515 | AM52: 57494682 | AN52: 58415515 | AO52: 59336349 | AP52: 60257182 | AQ52: 61178015 | AR52: 63286849 | AS52: 63408382 | AT52: 64334656 | AU52: 65255489 | AV52: 66490962 | AW52: 67427076 | AX52: 68187783 | AY52: 0 | AZ52: 69185100 | BA52: 70198016 | BB52: 66326497 | BC52: 67339414 | BD52: 68728650 | BE52: 69741567 | BF52: 70754483
A53: 10.5 | B53: Other Liabilities | C53: 75384134 | D53: 96676573 | E53: 79611605 | F53: ='[1]5,'!$E$30 -> 69319200 | G53: =99425887 -> 99425887 | H53: =37016428+404412+2169745+164800+15700+56553793+45000+128098+202372+2880+103847+4640433+50920+43645+1326340+278400+772+16820+1479870 -> 104644275 | I53: =44455686+95605+363989+2919745+129800+72572817+48396+522058+2920+126840+50920+105404+947150+70999+290+78119+168700+204225+135000+45060+122400 -> 123166123 | J53: 87361006 | K53: 1.0454973e+08 | L53: 1.058938e+08 | M53: 1.0662074e+08 | N53: 1.1749336e+08 | O53: 1.3771786e+08 | P53: 1.470366e+08 | Q53: 1.5003893e+08 | R53: 1.5905782e+08 | S53: 1.6848327e+08 | T53: 1.8466272e+08 | U53: 1.0460404e+08 | V53: =53636115+149555+274338+3201745+139800+89121409+284408+420736+156054+4007573+203194+1354560+54092+55446+82821+132108+56701+168700+259850+362000+60000+319731 -> 154500936 | W53: =3200000+165400000+22344900+181865862+10009069 -> 382819831 | X53: 3.7287313e+08 | Y53: =195000000+28933207+201128805+6711069 -> 431773081 | Z53: 2.1261691e+08 | AA53: 2.2441106e+08 | AB53: 2.5096967e+08 | AC53: 2.7885137e+08 | AD53: 2.9977381e+08 | AE53: 3.1550103e+08 | AF53: 3.448943e+08 | AG53: 3.6858414e+08 | AH53: 3.8701218e+08 | AI53: 4.1370789e+08 | AJ53: 4.420037e+08 | AL53: =32066110+228558677 -> 260624787 | AM53: 2.5631911e+08 | AN53: 2.7007236e+08 | AO53: 2.9651637e+08 | AP53: 3.2392513e+08 | AQ53: 3.4115489e+08 | AR53: 3.687327e+08 | AS53: 4.0173424e+08 | AT53: 4.2745789e+08 | AU53: 4.5257909e+08 | AV53: 4.7987233e+08 | AW53: 5.1375322e+08 | AX53: 5.2843398e+08 | AY53: 283106520 | AZ53: 2.8055887e+08 | BA53: 2.9777782e+08 | BB53: 3.2852674e+08 | BC53: 3.3297011e+08 | BD53: 3.6351649e+08 | BE53: 3.8395234e+08 | BF53: 4.2087358e+08
A54: 10.6 | B54: External Borrowings | C54: =2987744+7599999 -> 10587743 | D54: =17630469+22166666 -> 39797135 | E54: 3000000 | F54: 0 | J54: 0 | K54: 0 | L54: 0 | R54: 50000000 | X54: 6711068.7 | Z54: 5869715 | AA54: 5874606.3 | AB54: 5879497.7 | AC54: 5037452 | AD54: 5041650 | AE54: 5045848 | AF54: 4203109 | AG54: 4206613 | AH54: 4210115 | AI54: 3366680 | AJ54: 3369487 | AL54: 3372292 | AM54: 2528160 | AN54: 2530268 | AO54: 2532374 | AP54: 1687543 | AQ54: 1688950 | AR54: 1690356 | AS54: 844825 | AT54: 845529 | AU54: 846233 | AV54: 0 | AW54: 0 | AX54: 0 | AY54: 0 | AZ54: 0 | BA54: 0 | BB54: 0 | BC54: 0 | BD54: 0 | BE54: 0 | BF54: 0
B55: Total Liabilities | C55: =SUM(C46+C48) -> 683913154 | D55: =SUM(D46+D48) -> 930692778 | E55: =E46+E48 -> 998395856 | F55: =F46+F48 -> 1226132745 | G55: =G46+G48 -> 1272609459 | H55: =H46+H48 -> 1485546640 | I55: =I46+I48 -> 1789844967 | J55: =J46+J48 -> 1.7514239e+09 | K55: =K46+K48 -> 1.6771924e+09 | L55: =L46+L48 -> 1.6424727e+09 | ... BF55: =BF46+BF48 -> 3.9692593e+09
B57: EQUITY
A58: 11 | B58: Share Capital (Members share capital per Bylaws) | C58: 127388080 | D58: 133080651 | E58: 33482558 | F58: =SUM('[1]10,11,12,13'!$G$205:$G$209) -> 42200680 | G58: 42265385 | H58: =41262989+3102032 -> 44365021 | I58: 49648475 | J58: 50071559 | K58: 53219078 | L58: 53593480 | M58: 53900060 | N58: 54320177 | O58: 54632464 | P58: 54961836 | Q58: 55253930 | R58: 55509080 | S58: 56429805 | T58: 1.1343048e+08 | U58: 1.1378034e+08 | V58: =85202216+28578124 -> 113780340 | W58: 133906127 | X58: 1.4578701e+08 | Y58: =133906127+11880879 -> 145787006 | Z58: 1.4691082e+08 | AA58: 1.4806064e+08 | AB58: 1.4936251e+08 | AC58: 1.5043828e+08 | AD58: 1.5143916e+08 | AE58: 1.5285222e+08 | AF58: 1.5404851e+08 | AG58: 1.5517777e+08 | AH58: 1.5579659e+08 | AI58: 1.5635428e+08 | AJ58: 1.579713e+08 | AL58: 158920399 | AM58: 1.5993374e+08 | AN58: 1.6742152e+08 | AO58: 1.6942436e+08 | AP58: 1.7146157e+08 | AQ58: 1.7419549e+08 | AR58: 1.7589202e+08 | AS58: 1.776338e+08 | AT58: 1.7935782e+08 | AU58: 1.8100341e+08 | AV58: 1.8224587e+08 | AW58: 1.8414555e+08 | AX58: 1.8608216e+08 | AY58: 186082159 | AZ58: 1.9333013e+08 | BA58: 2.0249388e+08 | BB58: 2.104564e+08 | BC58: 2.1863039e+08 | BD58: 2.2191237e+08 | BE58: 2.3546249e+08 | BF58: 2.3765395e+08
A59: 12 | B59: Capital Grants | J59: 0 | K59: 0 | L59: 0 | Z59: 0 | AA59: 0 | AB59: 0 | AC59: 0 | AD59: 0 | AE59: 0 | AF59: 0 | AG59: 0 | AH59: 0 | AI59: 0 | AJ59: 0 | AM59: 0 | AN59: 0 | AO59: 0 | AP59: 0 | AQ59: 0 | AR59: 0 | AS59: 0 | AT59: 0 | AU59: 0 | AV59: 0 | AW59: 0 | AX59: 0 | AY59: 0 | AZ59: 0 | BA59: 0 | BB59: 0 | BC59: 0 | BD59: 0 | BE59: 0 | BF59: 0
A61: 13 | B61: Retained Earnings | C61: =SUM(C62:C63) -> 48170884 | D61: =SUM(D62:D63) -> 84159745 | E61: =E63+E62 -> 145851655 | F61: =F63+F62 -> 212095859 | G61: =G63+G62 -> 284016397 | H61: =H63+H62 -> 348834010 | I61: =I63+I62 -> 386711956 | J61: =J63+J62 -> 4.540086e+08 | K61: =K63+K62 -> 4.5816504e+08 | L61: =L63+L62 -> 4.5993765e+08 | ... BF61: =BF63+BF62 -> 8.2046693e+08
A62: 13.1 | B62: Prior Years' Retained Earnings | C62: 48170884 | D62: 49502968 | E62: 84159745 | F62: ='[1]10,11,12,13'!$I$212 -> 145851655 | G62: 212095859 | H62: 284016397 | I62: 348834011 | J62: 4.3671225e+08 | K62: 4.4159036e+08 | L62: 4.4159036e+08 | M62: 4.3329073e+08 | N62: 4.3329073e+08 | O62: 4.3149073e+08 | P62: 4.3524311e+08 | Q62: 4.3524311e+08 | R62: 4.4159036e+08 | S62: 4.4159036e+08 | T62: 4.4159036e+08 | U62: 386711955 | V62: 386711955 | W62: 445955845 | X62: 4.817885e+08 | Y62: =(481788500-3115764) -> 478672736 | Z62: 6.1867937e+08 | AA62: 6.1867937e+08 | AB62: 6.1867937e+08 | AC62: 6.1867937e+08 | AD62: 6.1867937e+08 | AE62: 6.1867937e+08 | AF62: 6.1867937e+08 | AG62: 6.1867937e+08 | AH62: 6.1867937e+08 | AI62: 6.1867937e+08 | AJ62: 6.1867937e+08 | AL62: =618677814-2027443 -> 616650371 | AM62: 7.367289e+08 | AN62: 7.367289e+08 | AO62: 7.367289e+08 | AP62: 7.367289e+08 | AQ62: 7.367289e+08 | AR62: 7.367289e+08 | AS62: 7.367289e+08 | AT62: 7.367289e+08 | AU62: 7.367289e+08 | AV62: 7.367289e+08 | AW62: 7.367289e+08 | AX62: 7.367289e+08 | AY62: 736728899 | AZ62: 7.6372967e+08 | BA62: 7.6372967e+08 | BB62: 7.6372967e+08 | BC62: 7.6372967e+08 | BD62: 7.6372967e+08 | BE62: 7.6372967e+08 | BF62: 7.6372967e+08
A63: 13.2 | B63: Current Year's Surplus | D63: =48070971-9614194-3800000 -> 34656777 | E63: =145851655-E62 -> 61691910 | F63: ='[1]10,11,12,13'!$G$212-'[1]10,11,12,13'!$I$212 -> 66244204 | G63: =-1878074+96648150-20207644-2641894 -> 71920538 | H63: =348834010-284016397 -> 64817613 | I63: =-70184+114935161-50000000-22987032-4000000 -> 37877945 | J63: 17296353 | K63: 16574679 | L63: 18347291 | M63: 24755020 | N63: 29811500 | O63: 35492108 | P63: 50974134 | Q63: 53756681 | R63: 57644159 | S63: 72555595 | T63: 1.0087482e+08 | U63: 1.0252008e+08 | V63: =-10099768+109520077-50000000-21904015-7000000 -> 20516294 | W63: =44750558+32209-8950112 -> 35832655 | X63: 173259568 | Y63: =173259568+1397423-(34651914) -> 140005077 | Z63: 16449154 | AA63: 20542498 | AB63: 26098716 | AC63: 56923736 | AD63: 62033209 | AE63: 70509337 | AF63: 77741699 | AG63: 83121222 | AH63: 82701514 | AI63: 1.0597957e+08 | AJ63: 1.2625917e+08 | AL63: =184556497-566669-27000000-36911299 -> 120078529 | AM63: 2091969.3 | AN63: 9416719.8 | AO63: 14514661 | AP63: 37357698 | AQ63: 47082688 | AR63: 65882206 | AS63: 56251445 | AT63: 55287206 | AU63: 52793736 | AV63: 60537820 | AW63: 56868033 | AX63: 82788713 | AY63: 63127954 | AZ63: 14515440 | BA63: 17154612 | BB63: 11965579 | BC63: 18647826 | BD63: 24624752 | BE63: 37538034 | BF63: 56737259
A65: 14 | B65: Other Equity Accounts | C65: =SUM(C66:C67) -> 27480589 | D65: =SUM(D66:D67) -> 37313386 | E65: =SUM(E66:E70) -> 57590822 | F65: =SUM(F66:F70) -> 79676470 | G65: =SUM(G66:G70) -> 100410154 | H65: =SUM(H66:H70) -> 116902515 | I65: =SUM(I66:I70) -> 189123526 | J65: =SUM(J66:J70) -> 1.3853138e+08 | K65: =SUM(K66:K70) -> 1.3953821e+08 | L65: =SUM(L66:L70) -> 1.3916606e+08 | ... BF65: =SUM(BF66:BF70) -> 5.5212608e+08
B66: Statutory Reserve | C66: 22297880 | D66: 31912074 | E66: 48489144 | F66: =SUM('[1]10,11,12,13'!$G$215:$G$216) -> 66444985 | G66: 86652629 | H66: =86652629+16492384 -> 103145013 | I66: 126132045 | J66: 1.2613205e+08 | K66: 1.2613205e+08 | L66: 1.2613205e+08 | M66: 1.2613205e+08 | N66: 1.2613205e+08 | O66: 1.2613205e+08 | P66: 1.2613205e+08 | Q66: 1.2613205e+08 | R66: 1.2613205e+08 | S66: 1.2613205e+08 | T66: 1.2613205e+08 | U66: 1.2613205e+08 | V66: =126132045+21904015 -> 148036060 | W66: 180400622 | X66: 1.8040062e+08 | Y66: =180400622+34651914 -> 215052536 | Z66: 2.1505254e+08 | AA66: 2.1505254e+08 | AB66: 2.1505254e+08 | AC66: 2.1505254e+08 | AD66: 2.1505254e+08 | AE66: 2.1505254e+08 | AF66: 2.1505254e+08 | AG66: 2.1505254e+08 | AH66: 2.1505254e+08 | AI66: 2.1505254e+08 | AJ66: 2.1505254e+08 | AL66: 251963835 | AM66: 2.5196384e+08 | AN66: 2.5196384e+08 | AO66: 2.5196384e+08 | AP66: 2.5196384e+08 | AQ66: 2.5196384e+08 | AR66: 2.5196384e+08 | AS66: 2.5196384e+08 | AT66: 2.5196384e+08 | AU66: 2.5196384e+08 | AV66: 2.5196384e+08 | AW66: 2.5196384e+08 | AX66: 2.5196384e+08 | AY66: 268521578 | AZ66: 2.7415492e+08 | BA66: 2.7415492e+08 | BB66: 2.7415492e+08 | BC66: 2.7415492e+08 | BD66: 2.7415492e+08 | BE66: 2.7415492e+08 | BF66: 2.7415492e+08
B67: Other Reserves (provide notes on these reserves) | C67: =1332084+3850625 -> 5182709 | D67: 5401312 | E67: 9101678 | F67: =SUM('[1]10,11,12,13'!$G$219:$G$220) -> 13231485 | G67: 13757525 | H67: =13757525-23 -> 13757502 | I67: 62991481 | J67: 12399331 | K67: 13406164 | L67: 13034014 | M67: 12823759 | N67: 12764919 | O67: 12609392 | P67: 12531452 | Q67: 12219892 | R67: 5616501.1 | S67: 6306756.3 | T67: 6066096.3 | U67: 58115592 | V67: =62991481+2888920+268474+50000000+2066484 -> 118215359 | W67: =160253512+15065437 -> 175318949 | X67: 1.736556e+08 | Y67: =160253512+(15065437+1452411) -> 176771360 | Z67: 1.7523385e+08 | AA67: 1.7493916e+08 | AB67: 1.7470198e+08 | AC67: 1.7428026e+08 | AD67: 1.7413026e+08 | AE67: 1.7390526e+08 | AF67: 1.735589e+08 | AG67: 1.731953e+08 | AH67: 1.7290178e+08 | AI67: 1.7598066e+08 | AJ67: 1.7579276e+08 | AL67: 187253512 | AM67: 2.0184336e+08 | AN67: 2.016756e+08 | AO67: 1.9842614e+08 | AP67: 1.9629014e+08 | AQ67: 1.95812e+08 | AR67: 1.936475e+08 | AS67: 1.898394e+08 | AT67: 1.894994e+08 | AU67: 1.8923381e+08 | AV67: 1.8906931e+08 | AW67: 1.8895617e+08 | AX67: 2.5884769e+08 | AY67: =18769926+187253512 -> 206023438 | AZ67: 2.9599302e+08 | BA67: 2.8242337e+08 | BB67: 2.8110886e+08 | BC67: 2.7925196e+08 | BD67: 2.7940456e+08 | BE67: 2.7828744e+08 | BF67: 2.7797116e+08
B68: Revaluation Reserves (Not part of core capital) | J68: 0 | K68: 0 | L68: 0 | Z68: 0 | AA68: 0 | AB68: 0 | AC68: 0 | AD68: 0 | AE68: 0 | AF68: 0 | AM68: 0 | AN68: 0 | AO68: 0 | AP68: 0 | AQ68: 0 | AR68: 0 | AS68: 0 | AT68: 0 | AU68: 0 | AV68: 0 | AW68: 0 | AX68: 0 | AY68: 55927273 | AZ68: 0 | BA68: 0 | BB68: 0 | BC68: 0 | BD68: 0 | BE68: 0 | BF68: 0
B69: Proposed Dividends | J69: 0 | K69: 0 | L69: 0 | Z69: 0 | AA69: 0 | AB69: 0 | AC69: 0 | AD69: 0 | AE69: 0 | AF69: 0 | AM69: 0 | AN69: 0 | AO69: 0 | AP69: 0 | AQ69: 0 | AR69: 0 | AS69: 0 | AT69: 0 | AU69: 0 | AV69: 0 | AW69: 0 | AX69: 0 | AZ69: 0 | BA69: 0 | BB69: 0 | BC69: 0 | BD69: 0 | BE69: 0 | BF69: 0
B70: Adjustment to Equity | J70: 0 | K70: 0 | L70: 0 | Z70: 0 | AA70: 0 | AB70: 0 | AC70: 0 | AD70: 0 | AE70: 0 | AF70: 0 | AM70: 0 | AN70: 0 | AO70: 0 | AP70: 0 | AQ70: 0 | AR70: 0 | AS70: 0 | AT70: 0 | AU70: 0 | AV70: 0 | AW70: 0 | AX70: 0 | AZ70: 0 | BA70: 0 | BB70: 0 | BC70: 0 | BD70: 0 | BE70: 0 | BF70: 0
B71: Total Equity | C71: =C58+C59+C61+C65 -> 203039553 | D71: =D58+D59+D61+D65+D70 -> 254553782 | E71: =E58+E59+E61+E65 -> 236925035 | F71: =F58+F59+F61+F65 -> 333973009 | G71: =G58+G59+G61+G65 -> 426691936 | H71: =H58+H59+H61+H65 -> 510101546 | I71: =I58+I59+I61+I65 -> 625483957 | J71: =J58+J59+J61+J65 -> 6.4261154e+08 | K71: =K58+K59+K61+K65 -> 6.5092232e+08 | L71: =L58+L59+L61+L65 -> 6.5269719e+08 | ... BF71: =BF58+BF59+BF61+BF65 -> 1.610247e+09
B73: Total Liabilities and Equity | C73: =C55+C71 -> 886952707 | D73: =D55+D71 -> 1185246560 | E73: =E55+E71 -> 1235320891 | F73: =F55+F71 -> 1560105754 | G73: =G55+G71 -> 1699301395 | H73: =H55+H71 -> 1995648186 | I73: =I55+I71 -> 2415328924 | J73: =J55+J71 -> 2.3940354e+09 | ... BF73: =BF55+BF71 -> 5.5795063e+09
C74: =C73-C39 -> 0 | D74: =D73-D39 -> 0 | E74: =E73-E39 -> 0 | F74: =F73-F39 -> 0 | G74: =G73-G39 -> 0 | H74: =H73-H39 -> -1 | I74: =I73-I39 -> 0 | J74: =J73-J39 -> 0 | ... BF74: =BF73-BF39 -> 0
B76: RE | D76: =#REF!-D73 -> #REF!
B77: SR
B78: Surplus
B79: Note: This return should be received within 15 days after end of the month.
B81: AUTHORIZATION:
B82: We declare that this return, to the best of our knowledge and belief is correct.
B83: …………………………………………………..sign……………………………..date……………………..
B84: name of authorizing officer
B85: …………………………………………………..sign……………………………..date……………………..
B86: name of countersigning officer

Sheet STATEMENT OF COMPREHENSIVE INCO
A1: FORM 7 SASRA/007
A2: STATEMENT OF COMPREHENSIVE INCOME
A3: NAME OF SACCO SOCIETY: YETU
A4: FINANCIAL YEAR 2011
A5: START DATE: 1st January
A6: END DATE: 31st December
G7: 2014 AUDITED
A8: Ref No. | C8: 40513 | D8: 40878 | E8: Audited 2012 | F8: AUDITED 2013 | H8: AUDITED 2015 | I8: AUDITED 2016 | J8: 42736 | K8: 42767 | L8: 42795 | M8: 42826 | N8: 42856 | O8: 42887 | P8: 42917 | Q8: 42948 | R8: 42979 | S8: 43009 | T8: 43040 | U8: 43070 | V8: AUDITED 2017 | W8: AUDITED 2019 | X8: 44166 | Y8: AUDITED 2020 | Z8: 44197 | AA8: 44228 | AB8: 44256 | AC8: 44287 | AD8: 44317 | AE8: 44348 | AF8: 44378 | AG8: 44409 | AH8: 44440 | AI8: 44470 | AJ8: 44501 | AK8: 44531 | AL8: AUDITED 2021 | AM8: 44562 | AN8: 44593 | AO8: 44621 | AP8: 44652 | AQ8: 44682 | AR8: 44713 | AS8: 44743 | AT8: 44774 | AU8: 44805 | AV8: 44835 | AW8: 44866 | AX8: 44896 | AY8: Audited 2022 | AZ8: 44927 | BA8: 44958 | BB8: 44986 | BC8: 45017 | BD8: 45047 | BE8: 45078 | BF8: 45108
D9: KShs
A10: 1 | B10: Financial Income | C10: =C11+C15 -> 81774220 | D10: =D11+D15 -> 1.7090549e+08 | E10: =E11+E15 -> 235675793 | F10: =F11+F15 -> 288037618 | G10: =G11+G15 -> 277638373 | H10: =H11+H15 -> 314967423 | I10: =I11+I15 -> 386913271 | J10: =J11+J15 -> 25367152 | ... BF10: =BF11+BF15 -> 4.1967583e+08
A11: 2 | B11: Financial Income from Loans Portfolio | C11: =SUM(C12:C13) -> 73871195 | D11: =SUM(D12:D13) -> 1.2777296e+08 | E11: =SUM(E12:E13) -> 171863513 | F11: =SUM(F12:F13) -> 213223483 | G11: =SUM(G12:G13) -> 201218528 | H11: =SUM(H12:H13) -> 199339025 | I11: =SUM(I12:I13) -> 265160914 | J11: =SUM(J12:J13) -> 22258926 | ... BF11: =SUM(BF12:BF13) -> 3.6381577e+08
A12: 2.1 | B12: Interest on Loan Portfolio | C12: 67225127 | D12: 82427924 | E12: =135798607+3563922 -> 139362529 | F12: 176582685 | G12: 185123085 | H12: =6430246+192908779 -> 199339025 | I12: =15547269+208483419 -> 224030688 | J12: 16403062 | K12: 32799726 | L12: 49532688 | M12: 66592721 | N12: 84208039 | O12: 1.0219755e+08 | P12: 1.2075812e+08 | Q12: 1.3992829e+08 | R12: 1.6025645e+08 | S12: 1.8084914e+08 | T12: 2.0003346e+08 | U12: 2.1870221e+08 | V12: =19085479+206555811 -> 225641290 | W12: 325832925 | X12: 3.7559706e+08 | Y12: =373570484 -> 373570484 | Z12: 33549968 | AA12: 67275548 | AB12: 1.0160622e+08 | AC12: 1.3647068e+08 | AD12: 1.7227046e+08 | AE12: 2.0871353e+08 | AF12: 2.4608875e+08 | AG12: 2.8396699e+08 | AH12: 3.2230828e+08 | AI12: 3.6070991e+08 | AJ12: 3.9920015e+08 | AK12: 4.3924825e+08 | AL12: 452871508 | AM12: 38683722 | AN12: 76843586 | AO12: 1.1569307e+08 | AP12: 1.5506282e+08 | AQ12: 1.9385812e+08 | AR12: 2.349502e+08 | AS12: 2.7708656e+08 | AT12: 3.1683554e+08 | AU12: 3.5752545e+08 | AV12: 3.9867479e+08 | AW12: 4.4211605e+08 | AX12: 4.8531681e+08 | AY12: 485316812 | AZ12: 42709547 | BA12: 85887962 | BB12: 1.3022523e+08 | BC12: 1.7564908e+08 | BD12: 2.2208486e+08 | BE12: 2.6905477e+08 | BF12: 3.163379e+08
A13: 2.2 | B13: Fees & Commission on Loan Portfolio | C13: =8230741-1584673 -> 6646068 | D13: 45345034 | E13: 32500984 | F13: 36640798 | G13: 16095443 | I13: =14238976+26891250 -> 41130226 | J13: 5855863.9 | K13: 9811623.6 | L13: 13111476 | M13: 16309635 | N13: 21197470 | O13: 24781487 | P13: 28415873 | Q13: 31795778 | R13: 35155169 | S13: 37736977 | T13: 66037662 | U13: 76208014 | V13: =46587556 -> 46587556 | W13: 0 | X13: 85530988 | Y13: =88161102+51433393 -> 139594495 | Z13: 7724126.3 | AA13: 13198364 | AB13: 19476688 | AC13: 23987935 | AD13: 30987550 | AE13: 36788398 | AF13: 42165178 | AG13: 46371403 | AH13: 50084111 | AI13: 53304954 | AJ13: 73235728 | AK13: 88036892 | AM13: 5613530.4 | AN13: 10721646 | AO13: 16723439 | AP13: 22419742 | AQ13: 27511641 | AR13: 32096278 | AS13: 49283927 | AT13: 59761934 | AU13: 69107854 | AV13: 75171913 | AW13: 82767837 | AX13: 84678042 | AY13: =79346054+60670454 -> 140016508 | AZ13: 7216026.7 | BA13: 14761485 | BB13: 24569142 | BC13: 29220971 | BD13: 36236050 | BE13: 43188758 | BF13: 47477869
A15: 3 | B15: Financial Income from Investments in: | C15: =SUM(C16:C19) -> 7903025 | D15: =SUM(D16:D19) -> 43132528 | E15: =SUM(E16:E19) -> 63812280 | F15: =SUM(F16:F19) -> 74814135 | G15: =SUM(G16:G19) -> 76419845 | H15: =SUM(H16:H19) -> 115628398 | I15: =SUM(I16:I19) -> 121752357 | J15: =SUM(J16:J19) -> 3108225.9 | ... BF15: =SUM(BF16:BF19) -> 55860066
A16: 3.1 | B16: Government Securities | J16: 0 | K16: 0 | L16: 0 | W16: 0 | X16: 1212386.4 | Y16: 0 | Z16: 363934.58 | AA16: 727869.16 | AB16: 1091803.7 | AC16: 1455738.3 | AD16: 1819672.9 | AE16: 2183607.5 | AF16: 2451306.3 | AG16: 2804849.6 | AH16: 3158393 | AI16: 3511936.3 | AJ16: 3756359.4 | AK16: 4131862.4 | AM16: 375503.01 | AN16: 751006.02 | AO16: 1126509 | AP16: 1502012 | AQ16: 1877515.1 | AR16: 2253018.1 | AS16: 2628521.1 | AT16: 2857399.1 | AU16: 3086277.1 | AV16: 3315155.1 | AW16: 3315155.1 | AX16: 3525586.2 | AZ16: 0 | BA16: 0 | BB16: 0 | BC16: 0 | BD16: 0 | BE16: 0 | BF16: 0
A17: 3.2 | B17: Deposit with Banks and Other Financial Inst. | D17: 744599.53 | E17: 7264605 | G17: 13488763 | H17: 19215771 | I17: 32843403 | J17: 0 | K17: 0 | L17: 0 | N17: 163742.5 | O17: 163742.5 | P17: 328303.69 | Q17: 328303.69 | R17: 328303.69 | S17: 328303.69 | T17: 493687.69 | U17: 659898.59 | V17: =46159306 -> 46159306 | W17: 0 | X17: 82503.87 | Y17: 0 | Z17: 91764.57 | AA17: 127776.76 | AB17: 134020.4 | AC17: 172163.92 | AD17: 182578.18 | AE17: 195696.2 | AF17: 218699.52 | AG17: 266179.16 | AH17: 278307.03 | AI17: 356913.33 | AJ17: 371285.66 | AK17: 375928.39 | AM17: 20724.91 | AN17: 48507.73 | AO17: 56757.2 | AP17: 62224.62 | AQ17: 77353.83 | AR17: 77353.83 | AS17: 116192.7 | AT17: 121345.73 | AU17: 132692.55 | AV17: 146172.62 | AW17: 163935.52 | AX17: 169397.19 | AY17: 127876850 | AZ17: 25234.62 | BA17: 34439.77 | BB17: 53118.63 | BC17: 78102.09 | BD17: 110870.12 | BE17: 146247.96 | BF17: 186246.12
A18: 3.3 | B18: Other Investments - dividend & Interest incomes from investments | C18: 7486550 | E18: 3609778 | F18: 17727545 | G18: 10161679 | H18: 12882628 | I18: 18850066 | J18: 0 | K18: 0 | L18: 0 | V18: =8989071 -> 8989071 | W18: 97520095 | Y18: =13010358+76138677 -> 89149035 | Z18: 0 | AA18: 0 | AB18: 0 | AC18: 0 | AD18: 0 | AE18: 0 | AF18: 0 | AK18: 0 | AL18: =19029527+69970286 -> 88999813 | AM18: 0 | AN18: 0 | AO18: 0 | AP18: 0 | AQ18: 0 | AR18: 0 | AS18: 0 | AT18: 0 | AU18: 0 | AV18: 0 | AW18: 0 | AX18: 0 | AY18: 13408029 | AZ18: 0 | BA18: 0 | BB18: 0 | BC18: 0 | BD18: 0 | BE18: 0 | BF18: 0
A19: 3.4 | B19: Other Operating Income- Salary processing fees, transaction fees, membership fees | C19: =453968+1528560-1566053 -> 416475 | D19: 42387929 | E19: 52937897 | F19: 57086590 | G19: =44053130+1269644+3387710+1558378+596150+1904391 -> 52769403 | H19: =46729689+1480900+1607200+30074574+664995+2972641 -> 83529999 | I19: =61215815+550+3642865+1243224+3956434 -> 70058888 | J19: 3108225.9 | K19: 6014421.8 | L19: 8833672.7 | M19: 14393783 | N19: 17650987 | O19: 20698206 | P19: 23425816 | Q19: 26349223 | R19: 28958712 | S19: 42259158 | T19: 47645473 | U19: 51767352 | V19: =67205558+2187071+914040+3971935 -> 74278604 | W19: 158497457 | X19: 63770255 | Y19: =1034316+1144556+6946985 -> 9125857 | Z19: 5942192.2 | AA19: 10187361 | AB19: 15592233 | AC19: 21043387 | AD19: 25707769 | AE19: 31737731 | AF19: 37547299 | AG19: 41775214 | AH19: 45403948 | AI19: 57791629 | AJ19: 62857856 | AK19: 67114482 | AL19: 152868396 | AM19: 5612614.7 | AN19: 10546316 | AO19: 15950694 | AP19: 22923189 | AQ19: 28574406 | AR19: 34828428 | AS19: 51177168 | AT19: 56335365 | AU19: 61503713 | AV19: 66672242 | AW19: 72218418 | AX19: 77874794 | AY19: =1813087+20494968+228244 -> 22536299 | AZ19: 13541874 | BA19: 20075887 | BB19: 28836918 | BC19: 35444531 | BD19: 42857139 | BE19: 49279005 | BF19: 55673819
A21: 4 | B21: Financial Expense | C21: =SUM(C22:C28) -> 35625225 | D21: =SUM(D22:D28) -> 22039304 | E21: =SUM(E22:E28) -> 70050995 | F21: =SUM(F22:F28) -> 100541517 | G21: =G22+G23+G24+G25+G27+G28 -> 84023090 | H21: =H22+H23+H24+H25+H27+H28 -> 84894530 | I21: =I22+I23+I24+I25+I27+I28 -> 120804092 | J21: =J22+J23+J24+J25+J27+J28 -> 7692621.7 | K21: =K22+K23+K24+K25+K27+K28 -> 19009377 | L21: =L22+L23+L24+L25+L27+L28 -> 27746256 | M21: =M22+M23+M24+M25+M27+M28 -> 37506436 | N21: =N22+N23+N24+N25+N27+N28 -> 49227970 | ... BF21: =BF22+BF23+BF24+BF25+BF27+BF28 -> 2.3118282e+08
A22: 4.2 | B22: Interest Expense on Deposits | D22: 7377984.3 | E22: 48000000 | F22: 83304527 | G22: =16018598+55000000 -> 71018598 | H22: 16756380 | I22: =55275000+45225000+17621204 -> 118121204 | J22: 897209.45 | K22: 2750108.5 | L22: 3387572.1 | M22: 5043210.3 | N22: 8644024.2 | O22: 9414776.4 | P22: 10175311 | Q22: 10962672 | R22: 11842524 | S22: 13173822 | T22: 16612631 | U22: 17936889 | V22: =115000000+17936889 -> 132936889 | W22: 194453667 | X22: 33991846 | Y22: =195000000+9743073+24248773 -> 228991846 | Z22: 3117295.6 | AA22: 6048847.9 | AB22: 9271751.8 | AC22: 12458993 | AD22: 15821837 | AE22: 19059848 | AF22: 22241994 | AG22: 25311159 | AH22: 28370013 | AI22: 31595677 | AJ22: 35004173 | AK22: 38473794 | AL22: =240000000+11425946+27047848 -> 278473794 | AM22: 3552743.8 | AN22: 6808642.2 | AO22: 10312784 | AP22: 13916662 | AQ22: 17879735 | AR22: 21589950 | AS22: 25724638 | AT22: 29885633 | AU22: 33838772 | AV22: 37649128 | AW22: 41152795 | AX22: 44849529 | AY22: 303188965 | AZ22: 3552527 | BA22: 6470536.1 | BB22: 8843769 | BC22: 11212169 | BD22: 14415602 | BE22: 17084780 | BF22: 15685763
A23: 4.3 | B23: Cost of External Borrowings | D23: 12361109 | E23: =30538668-8487673 -> 22050995 | F23: 15150271 | G23: =3333058+4256301 -> 7589359 | H23: =11846+1510782 -> 1522628 | J23: 0 | K23: 0 | L23: 0 | S23: 355068 | T23: 355068 | U23: 355068 | V23: 355068 | W23: 0 | X23: 0 | Y23: 0 | Z23: 5583.33 | AA23: 10474.66 | AB23: 15365.99 | AC23: 20257.33 | AD23: 24455.33 | AE23: 28653.33 | AF23: 32851.33 | AG23: 36355.33 | AH23: 39857.33 | AI23: 43359.33 | AJ23: 46166.33 | AK23: 48971.33 | AM23: 2805 | AN23: 4913 | AO23: 7019 | AP23: 9125 | AQ23: 10532 | AR23: 11938 | AS23: 13344 | AT23: 14048 | AU23: 14752 | AV23: 15456 | AW23: 15456 | AX23: 15456 | AY23: 15456 | AZ23: 0 | BA23: 0 | BB23: 0 | BC23: 0 | BD23: 0 | BE23: 0 | BF23: 0
A24: 4.4 | B24: Dividend Expenses (on member shares) | C24: 35000000 | G24: 0 | H24: 60000000 | J24: 6666666.7 | K24: 16000000 | L24: 24000000 | M24: 32000000 | N24: 40000000 | O24: 48000000 | P24: 56000000 | Q24: 64000000 | R24: 72000000 | S24: 80000000 | T24: 88000000 | U24: 115000000 | W24: 0 | X24: 0 | Y24: 0 | Z24: 20000000 | AA24: 40000000 | AB24: 60000000 | AC24: 80000000 | AD24: 100000000 | AE24: 120000000 | AF24: 140000000 | AG24: 160000000 | AH24: 180000000 | AI24: 200000000 | AJ24: 220000000 | AK24: 240000000 | AM24: 24166667 | AN24: 48333333 | AO24: 72500000 | AP24: 96666667 | AQ24: 1.2083333e+08 | AR24: 145000000 | AS24: 1.6916667e+08 | AT24: 1.9333333e+08 | AU24: 2.175e+08 | AV24: 2.4166667e+08 | AW24: 2.6583333e+08 | AX24: 290000000 | AY24: 0 | AZ24: 28333333 | BA24: 56666667 | BB24: 85000000 | BC24: 85000000 | BD24: 1.1333333e+08 | BE24: 170000000 | BF24: 1.9833333e+08
A25: 4.5 | B25: Other Financial Expense | C25: =1625+174000+15200+434400 -> 625225 | D25: 2300209.9 | F25: 2086719 | G25: =3264000+1922358+33275+179800+15700 -> 5415133 | H25: =3847800+2072222+179800+15700+500000 -> 6615522 | I25: =626+230137+1348669+1103456 -> 2682888 | J25: 128745.5 | K25: 259268.5 | L25: 358683.5 | M25: 463225.5 | N25: 583946 | O25: 694169.5 | P25: 720077 | Q25: 902091 | R25: 1010667.5 | S25: 1110163.5 | T25: 1389210.9 | U25: 1358744.9 | V25: 1358745 | W25: 5937775 | X25: 1565302.9 | Y25: =1565303+3000000+27060+92811 -> 4685174 | Z25: 160557.2 | AA25: 285923.2 | AB25: 418633.2 | AC25: 528252.2 | AD25: 657352.2 | AE25: 805672.2 | AF25: 927266.2 | AG25: 1029628.3 | AH25: 1144884.3 | AI25: 1212294.7 | AJ25: 1357722.7 | AK25: 1482289.7 | AL25: 5200083 | AM25: 378132 | AN25: 1681388.4 | AO25: 2936443.5 | AP25: 4377361.6 | AQ25: 6027924.4 | AR25: 7752690.2 | AS25: 9694547.6 | AT25: 11527856 | AU25: 13596393 | AV25: 15607971 | AW25: 17680359 | AX25: 21361091 | AY25: =27216458-15456 -> 27201002 | AZ25: 3362334 | BA25: 7591433.3 | BB25: 12103740 | BC25: 16393707 | BD25: 21493670 | BE25: 14110595 | BF25: 17163721
AF26: 0 | AG26: 0 | BF26: 0
A27: 4.6 | B27: Fees & Commission Expense | J27: 0 | K27: 0 | L27: 0 | W27: 0 | X27: 0 | Y27: 0 | Z27: 0 | AA27: 0 | AB27: 0 | AC27: 0 | AD27: 0 | AE27: 0 | AF27: 0 | AG27: 0 | AM27: 0 | AN27: 0 | AO27: 0 | AP27: 0 | AQ27: 0 | AR27: 0 | AS27: 0 | AT27: 0 | AU27: 0 | AV27: 0 | AW27: 0 | AX27: 0 | AY27: 0 | AZ27: 0 | BA27: 0 | BB27: 0 | BC27: 0 | BD27: 0 | BE27: 0 | BF27: 0
A28: 4.7 | B28: Other Expense | J28: 0 | K28: 0 | L28: 0 | W28: 0 | X28: 0 | Y28: 0 | Z28: 0 | AA28: 0 | AB28: 0 | AC28: 0 | AD28: 0 | AE28: 0 | AM28: 0 | AN28: 0 | AO28: 0 | AP28: 0 | AQ28: 0 | AR28: 0 | AS28: 0 | AT28: 0 | AU28: 0 | AV28: 0 | AW28: 0 | AX28: 0 | AY28: 0 | AZ28: 0 | BA28: 0 | BB28: 0 | BC28: 0 | BD28: 0 | BE28: 0 | BF28: 0
A30: 5 | B30: Net Financial Income/(Loss) | C30: =C10-C21 -> 46148995 | D30: =D10-D21 -> 1.4886618e+08 | E30: =E10-E21 -> 165624798 | F30: =F10-F21 -> 187496101 | G30: =G10-G21 -> 193615283 | H30: =H10-H21 -> 230072893 | I30: =I10-I21 -> 266109179 | J30: =J10-J21 -> 17674530 | ... BF30: =BF10-BF21 -> 1.8849302e+08
A32: 6 | B32: Allowance for Loan Loss | C32: =C33-C34 -> 0 | D32: =D33-D34 -> 5000000 | E32: =E33-E34 -> 5000005 | F32: =F33-F34 -> 8000000 | G32: =G33-G34 -> 9600000 | H32: =H33-H34 -> 30000000 | I32: =I33-I34 -> 30000000 | J32: =J33-J34 -> 2875000 | ... BF32: =BF33-BF34 -> 16745961
A33: 6.1 | B33: Provision for Loan Losses | D33: 5000000 | E33: 5000005 | F33: 8000000 | G33: 9600000 | H33: 30000000 | I33: =30000000 -> 30000000 | J33: 2875000 | K33: 5750000 | L33: 8625000 | M33: 11500000 | N33: 14375000 | O33: 17250000 | P33: 20125000 | Q33: 23000000 | R33: 25875000 | S33: 28750000 | T33: 31625000 | U33: 34500000 | V33: 34500000 | W33: 162681456 | X33: 41100000 | Y33: 41100000 | Z33: 4500000 | AA33: 9000000 | AB33: 13500000 | AC33: 18000000 | AD33: 22500000 | AE33: 27000000 | AF33: 31500000 | AG33: 36000000 | AH33: 40500000 | AI33: 45000000 | AJ33: 49500000 | AK33: 9000000 | AL33: 9000000 | AM33: 4500000 | AN33: 9000000 | AO33: 0 | AP33: 0 | AQ33: 0 | AR33: 0 | AS33: 33627357 | AT33: 49725477 | AU33: 53636645 | AV33: 68049329 | AW33: 71078402 | AX33: 54062775 | AY33: 54062775 | AZ33: 0 | BA33: 0 | BB33: 12019173 | BC33: 37370458 | BD33: 35224281 | BE33: 32297662 | BF33: 16745961
A34: 6.2 | B34: Value of Loans Recovered | J34: 0 | K34: 0 | L34: 0 | W34: 0 | X34: 0 | Y34: 0 | Z34: 0 | AA34: 0 | AB34: 0 | AC34: 0 | AD34: 0 | AE34: 0 | AF34: 0 | AK34: 0 | AM34: 0 | AN34: 0 | AO34: 0 | AP34: 0 | AQ34: 0 | AR34: 0 | AS34: 0 | AT34: 0 | AU34: 0 | AV34: 0 | AW34: 0 | AX34: 0 | AY34: 0 | AZ34: 0 | BA34: 0 | BB34: 0 | BC34: 0 | BD34: 0 | BE34: 0 | BF34: 0
A36: 7 | B36: Operating Expenses | C36: =SUM(C37:C41) -> 20053569 | D36: =SUM(D37:D41) -> 73581334 | E36: =SUM(E37:E41) -> 69196044 | F36: =SUM(F37:F41) -> 89943298 | G36: =SUM(G37:G41) -> 87367063 | H36: =SUM(H37:H41) -> 117610973 | I36: =SUM(I37:I41) -> 121174021 | J36: =SUM(J37:J41) -> 10629822 | ... BF36: =SUM(BF37:BF41) -> 1.7969144e+08
A37: 7.1 | B37: Personnel Expenses | C37: 10339275 | D37: 31404308 | E37: =14225499+465552+3748614+3180843+2606460+24926+72200+2499536+8249440+752300 -> 35825370 | F37: 45213017 | G37: =16094500+5060307+7088000+3368390+3508807+21997+86000+3223360+11520935+956200 -> 50928496 | H37: =18596000+7340665+8126553+5110312+3029147+37597+98000+3685200+13037510+1113800 -> 60174784 | I37: =10805300+4030919+4488000+3348152+1823424+14190+54120+2157430+8963283+594000+8840700+3298025+3672000+2739397+1491893+11610+44280+1765170+7333595+486000 -> 65961488 | J37: 4983196.3 | K37: 10320309 | L37: 15964636 | M37: 22598575 | N37: 29645863 | O37: 35038781 | P37: 39536167 | Q37: 45850174 | R37: 51929566 | S37: 57575807 | T37: 63321819 | U37: 68657692 | V37: =21177693+8235272+8426921+5027392+3764578+38998+102000+4227385+16586453+1071000 -> 68657692 | W37: 86231438 | X37: 84062797 | Y37: =30866036+7905037+11896847+4010956+1012905+4213271+109200+5608421+6212044+2228080+10000000 -> 84062797 | Z37: 6221490 | AA37: 13740036 | AB37: 22146365 | AC37: 29916078 | AD37: 37970786 | AE37: 47700473 | AF37: 60693892 | AG37: 69579804 | AH37: 78682762 | AI37: 87840492 | AJ37: 96406947 | AK37: 1.0566562e+08 | AL37: 105665615 | AM37: 8651302.8 | AN37: 18195477 | AO37: 27784578 | AP37: 36966794 | AQ37: 49242399 | AR37: 59047292 | AS37: 73110560 | AT37: 81896346 | AU37: 90908105 | AV37: 1.0004573e+08 | AW37: 1.1376377e+08 | AX37: 1.2406294e+08 | AY37: 124062936 | AZ37: 9675331.1 | BA37: 20888827 | BB37: 31581158 | BC37: 43969214 | BD37: 57777877 | BE37: 72083996 | BF37: 87508424
A38: 7.2 | B38: Governance Expenses | C38: 4706687 | D38: 5602590 | E38: =981260+2199092+2303397+158045 -> 5641794 | F38: 8566934 | G38: =991618+5142864+2655313+225609 -> 9015404 | H38: =1349230+7879712+1361956 -> 10590898 | I38: =848190+5080974+460609+693974+4157160+376862 -> 11617769 | J38: 388566 | K38: 1232043 | L38: 3266709 | M38: 3797773 | N38: 4231758 | O38: 4786180 | P38: 5260811 | Q38: 5941943 | R38: 7999904 | S38: 8909164 | T38: 9423622 | U38: 9953610 | V38: =1692952+7357620+903038 -> 9953610 | W38: 22543894 | X38: 12570566 | Y38: =4870072+5071010+1372195+514509+742781 -> 12570567 | Z38: 1551122 | AA38: 2638653 | AB38: 4810788.5 | AC38: 6813027.5 | AD38: 7714846.5 | AE38: 9303104 | AF38: 12251193 | AG38: 13235598 | AH38: 17483564 | AI38: 18838686 | AJ38: 20736476 | AK38: 23427238 | AL38: 23427238 | AM38: 1173003 | AN38: 2868536.5 | AO38: 7252869.5 | AP38: 8673135.5 | AQ38: 7710403.5 | AR38: 12751854 | AS38: 15864776 | AT38: 17871261 | AU38: 23974333 | AV38: 26676236 | AW38: 29869905 | AX38: 33995451 | AY38: 33995451 | AZ38: 2500708 | BA38: 4701879.5 | BB38: 6186601.2 | BC38: 11740599 | BD38: 13815424 | BE38: 16607622 | BF38: 20305216
A39: 7.3 | B39: Marketing Expenses | C39: 897213 | D39: 1120228 | E39: 1661825 | F39: 2477039 | G39: 1284059 | H39: 3960517 | I39: =1143975+935979 -> 2079954 | J39: 9990 | K39: 53390 | L39: 188506 | M39: 203886 | N39: 383406 | O39: 576934 | P39: 698184 | Q39: 987950 | R39: 1050410 | S39: 1135835 | T39: 1147415 | U39: 1195765 | V39: 1195765 | W39: 3666270 | X39: 3278342.6 | Y39: 3278343 | Z39: 844120 | AA39: 983900 | AB39: 1368760 | AC39: 2024420 | AD39: 2143700 | AE39: 2628900 | AF39: 3372718 | AG39: 3437248 | AH39: 4833483 | AI39: 5652088 | AJ39: 7465808 | AK39: 8159982 | AL39: 8159982 | AM39: 900770 | AN39: 1140610 | AO39: 2721740 | AP39: 2759640 | AQ39: 4087900 | AR39: 4820246 | AS39: 6769435.6 | AT39: 7942391.6 | AU39: 8533696.8 | AV39: 8962004.8 | AW39: 12064575 | AX39: 13383312 | AY39: 13383312 | AZ39: 653380 | BA39: 2713463.2 | BB39: 3578741.2 | BC39: 4602231.2 | BD39: 5572996.2 | BE39: 7473586.2 | BF39: 9032959.2
A40: 7.4 | B40: Depreciation and Amortization Charges | C40: 471735 | D40: 18116378 | E40: 7563029 | F40: 8638883 | G40: 6668543 | H40: 9567411 | I40: =5561905+4550650 -> 10112555 | J40: 1150000 | K40: 2300000 | L40: 3450000 | M40: 4600000 | N40: 5750000 | O40: 6900000 | P40: 8050000 | Q40: 9200000 | R40: 10350000 | S40: 11500000 | T40: 12650000 | U40: 10750235 | V40: =10750235 -> 10750235 | W40: 12996272 | X40: 12490225 | Y40: 12490225 | Z40: 1250000 | AA40: 2500000 | AB40: 3750000 | AC40: 5000000 | AD40: 6250000 | AE40: 7500000 | AF40: 8750000 | AG40: 10000000 | AH40: 11250000 | AI40: 12500000 | AJ40: 13750000 | AK40: 10387317 | AL40: 10387317 | AM40: 1250000 | AN40: 2500000 | AO40: 3750000 | AP40: 5000000 | AQ40: 6250000 | AR40: 7500000 | AS40: 8750000 | AT40: 10000000 | AU40: 11250000 | AV40: 12500000 | AW40: 13750000 | AX40: 12590197 | AY40: 12590195 | AZ40: 1375000 | BA40: 2750000 | BB40: 4125000 | BC40: 5500000 | BD40: 6250000 | BE40: 8250000 | BF40: 9625000
A41: 7.5 | B41: Administrative Expenses | C41: =5007607-471735-897213 -> 3638659 | D41: 17337830 | E41: =2984687+300+174000+15200+222626+2277907+499188+876407+12450+2991090+2235883+2388618+3366484+451604+7582 -> 18504026 | F41: 25047425 | G41: =1801732+659600+1926087+42710+1198027+2526895+1827958+4561274+4071050+755408+16220+83600 -> 19470561 | H41: =2315865+641030+3005316+108770+3567027+3503613+2124107+5469196+9220032+825017+99483+169640+2268267 -> 33317363 | I41: =1245026+419052+2182752+82500+98890+1901892+198303+257059+1175650+988847+3120863+2466091+516846+30963+2519494+67012+1018657+342861+1785888+67500+80910+1556094+162248+210321+961895+809056+2553434+2017711+422874+25334+2061404+54828 -> 31402255 | J41: 4098069.6 | K41: 6665494.2 | L41: 9135500.1 | M41: 11207052 | N41: 13608142 | O41: 16075294 | P41: 17242126 | Q41: 21519667 | R41: 24051642 | S41: 27088154 | T41: 29834150 | U41: 32427745 | V41: =2541381+660844+13195+4274880+1900+179800+3895074+267650+380716+2716623+1428162+5727566+4052693+938463+109291+4720738+480000+38770 -> 32427746 | W41: 36589147 | X41: 39828415 | Y41: =4239832+489065+4345920+475240+214600+3117509+3303553+349200+619047+2432558+617436+5772004+4368425+1527056+88677+3740267+965800+135166 -> 36801355 | Z41: 2972622.2 | AA41: 6691705.1 | AB41: 10903960 | AC41: 14313250 | AD41: 17910977 | AE41: 22137471 | AF41: 27262372 | AG41: 31295275 | AH41: 35160516 | AI41: 40147022 | AJ41: 43789528 | AK41: 52538013 | AL41: =48869190+5000000 -> 53869190 | AM41: 4894729.3 | AN41: 9041522.2 | AO41: 16858678 | AP41: 24859921 | AQ41: 26137463 | AR41: 32039925 | AS41: 37432050 | AT41: 42613043 | AU41: 48857117 | AV41: 55688931 | AW41: 66810715 | AX41: 77126527 | AY41: 85416047 | AZ41: 6647544.1 | BA41: 13513914 | BB41: 19271924 | BC41: 26660290 | BD41: 34691325 | BE41: 43338272 | BF41: 53219837
A43: 8 | B43: Net Operating Income | C43: =C30-C32-C36 -> 26095426 | D43: =D30-D32-D36 -> 70284849 | E43: =E30-E32-E36 -> 91428749 | F43: =F30-F32-F36 -> 89552803 | G43: =G30-G32-G36 -> 96648220 | H43: =H30-H32-H36 -> 82461920 | I43: =I30-I32-I36 -> 114935158 | J43: =J30-J32-J36 -> 4169708.5 | ... BF43: =BF30-BF32-BF36 -> -7944380.2
A45: 9 | B45: Net Non- Operating Income/ (Expense) | C45: =C46-C47 -> 0 | D45: =D46-D47 -> 8965033.6 | E45: =E46-E47 -> 357268 | F45: =F46-F47 -> 226400 | G45: =G46-G47 -> 0 | H45: =H46-H47 -> 0 | I45: =I46-I47 -> 0 | J45: =J46-J47 -> 13876644 | ... BF45: =BF46-BF47 -> 77514973
A46: 9.1 | B46: Non- Operating Income | D46: 8965033.6 | E46: 357268 | F46: 226400 | J46: 13876644 | K46: 14779521 | L46: 17496061 | M46: 21872603 | N46: 27563400 | O46: 30887255 | P46: 41103698 | Q46: 43719586 | R46: 45805242 | S46: 48480030 | T46: 49273454 | U46: 54318353 | W46: 0 | X46: 0 | Y46: 0 | Z46: 10649958 | AA46: 13425119 | AB46: 18133372 | AC46: 47868107 | AD46: 48309135 | AE46: 54554495 | AF46: 65052753 | AG46: 67861651 | AH46: 70183559 | AI46: 85633841 | AJ46: 88644611 | AK46: 95832303 | AM46: 2922694 | AN46: 13413414 | AO46: 14088308 | AP46: 35283685 | AQ46: 41696675 | AR46: 62190820 | AS46: 67779114 | AT46: 77518348 | AU46: 78547565 | AV46: 1.0008567e+08 | AW46: 1.0663928e+08 | AX46: 1.375899e+08 | AY46: 0 | AZ46: 8956248 | BA46: 15358225 | BB46: 16491277 | BC46: 28037143 | BD46: 35077007 | BE46: 68115767 | BF46: 77514973
A47: 9.2 | B47: Non- Operating Expense | J47: 0 | K47: 0 | L47: 0 | W47: 0 | X47: 0 | Y47: 0 | Z47: 0 | AA47: 0 | AB47: 0 | AC47: 0 | AD47: 0 | AE47: 0 | AF47: 0 | AG47: 0 | AH47: 0 | AI47: 0 | AJ47: 0 | AK47: 0 | AM47: 0 | AN47: 0 | AO47: 0 | AP47: 0 | AQ47: 0 | AR47: 0 | AS47: 0 | AT47: 0 | AU47: 0 | AV47: 0 | AW47: 0 | AX47: 0 | AY47: 0 | AZ47: 0 | BA47: 0 | BB47: 0 | BC47: 0 | BD47: 0 | BE47: 0 | BF47: 0
A49: 10 | B49: Net Income (Before Taxes and Donations) | C49: =C43+C45 -> 26095426 | D49: =D43+D45 -> 79249882 | E49: =E43+E45 -> 91786017 | F49: =F43+F45 -> 89779203 | G49: =G43+G45 -> 96648220 | H49: =H43+H45 -> 82461920 | I49: =I43+I45 -> 114935158 | J49: =J43+J45 -> 18046353 | ... BF49: =BF43+BF45 -> 69570593
A51: 11 | B51: Taxes (Incomes taxes & Other payable to KRA) | E51: 1650000 | F51: 2750000 | G51: 2641894 | H51: 3000000 | I51: 4000000 | J51: 750000 | K51: 1500000 | L51: 2250000 | M51: 3000000 | N51: 3750000 | O51: 4500000 | P51: 5250000 | Q51: 6000000 | R51: 6750000 | S51: 7500000 | T51: 8250000 | U51: 7000000 | V51: 7000000 | W51: 12000000 | X51: 14200000 | Y51: 14200000 | Z51: 1250000 | AA51: 2500000 | AB51: 3750000 | AC51: 5000000 | AD51: 6250000 | AE51: 7500000 | AF51: 8750000 | AG51: 10000000 | AH51: 11250000 | AI51: 12500000 | AJ51: 13750000 | AK51: 16000000 | AL51: 16000000 | AM51: 1666666.7 | AN51: 3333333.3 | AO51: 5000000 | AP51: 6666666.6 | AQ51: 8333333.3 | AR51: 10000000 | AS51: 11666667 | AT51: 13333333 | AU51: 15000000 | AV51: 16666667 | AW51: 18333333 | AX51: 34918542 | AY51: 24282921 | AZ51: 1833333.3 | BA51: 3666666.7 | BB51: 5500000 | BC51: 7333333.3 | BD51: 9166666.7 | BE51: 11000000 | BF51: 12833333
A53: 12 | B53: Net Income (After Taxes before Donations) | C53: =C49-C51 -> 26095426 | D53: =D49-D51 -> 79249882 | E53: =E49-E51 -> 90136017 | F53: =F49-F51 -> 87029203 | G53: =G49-G51 -> 94006326 | H53: =H49-H51 -> 79461920 | I53: =I49-I51 -> 110935158 | J53: =J49-J51 -> 17296353 | ... BF53: =BF49-BF51 -> 56737259
A54: 13 | B54: Donations | E54: 412995 | J54: 0 | K54: 0 | L54: 0 | AB54: 0 | AC54: 0 | AD54: 0 | AK54: 0 | AM54: 0 | AN54: 0 | AO54: 0 | AP54: 0 | AQ54: 0 | AR54: 0 | AS54: 0 | AT54: 0 | AU54: 0 | AV54: 0 | AW54: 0 | AX54: 0 | AZ54: 0 | BA54: 0 | BB54: 0 | BC54: 0 | BD54: 0 | BE54: 0 | BF54: 0
A56: 14 | B56: Net Income/(After Taxes and Donations) | C56: =C53-C54 -> 26095426 | D56: =D53-D54 -> 79249882 | E56: =E53-E54 -> 89723022 | F56: =F53-F54 -> 87029203 | G56: =G53+G54 -> 94006326 | H56: =H53+H54 -> 79461920 | I56: =I53+I54 -> 110935158 | J56: =J53+J54 -> 17296353 | K56: =K53+K54 -> 16574679 | L56: =L53+L54 -> 18347291 | M56: =M53+M54 -> 24755020 | N56: =N53+N54 -> 29811500 | ... BF56: =BF53+BF54 -> 56737259
B57: Note: This return should be received within 15 days after end of the month. | F57: =F51+F36+F33+F21 -> 201234815 | G57: =G51+G36+G33+G21 -> 183632047 | H57: =H51+H36+H33+H21 -> 235505503 | I57: =I51+I36+I33+I21 -> 275978113 | J57: =J51+J36+J33+J21 -> 21947444 | K57: =K51+K36+K33+K21 -> 46830613 | L57: =L51+L36+L33+L21 -> 70626607 | M57: =M51+M36+M33+M21 -> 94413722 | ... BF57: =BF51+BF36+BF33+BF21 -> 4.4045355e+08
F58: =F57-201234815 -> 0
B59: AUTHORIZATION:
B60: We declare that this return, to the best of our knowledge and belief is correct.
B61: …………………………………………………..sign……………………………..date……………………..
B62: Name of Authorizing Officer
B63: …………………………………………………..sign……………………………..date……………………..
B64: Name of Countersigning Officer

Sheet FINANCIALS
C1: YETU SACCO
C2: Year | D2: Audited 2010 | E2: Audited 2011 | F2: Audited 2012 | G2: AUDITED 2013 | H2: 2014 AUDITED | I2: AUDITED 2015 | J2: AUDITED 2016 | K2: 42736 | L2: 42767 | M2: 42795 | N2: 42826 | O2: 42856 | P2: 42887 | Q2: 42917 | R2: 42948 | S2: 42979 | T2: 43009 | U2: 43040 | V2: 43070 | W2: Audited 2017 | X2: Dcember 2020 | Y2: Audited 2020 | Z2: 44197 | AA2: 44228 | AB2: 44256 | AC2: 44287 | AD2: 44317 | AE2: 44348 | AF2: 44378 | AG2: 44409 | AH2: 44440 | AI2: 44470 | AJ2: 44501 | AK2: 44531 | AL2: AUDITED 2021 | AM2: 44562 | AN2: 44593 | AO2: 44621 | AP2: 44652 | AQ2: 44682 | AR2: 44713 | AS2: 44743 | AT2: 44774 | AU2: 44805 | AV2: 44835 | AW2: 44866 | AX2: 44896 | AY2: Audited 2022 | AZ2: 44927 | BA2: 44958 | BB2: 44986 | BC2: 45017 | BD2: 45047 | BE2: 45078 | BF2: 45108
B3: 1 | C3: Membership
B4: 2 | C4: Total Assets | D4: ='STATEMENT OF FINANCIAL POSITION'!C39 -> 886952707 | E4: ='STATEMENT OF FINANCIAL POSITION'!D39 -> 1185246560 | F4: ='STATEMENT OF FINANCIAL POSITION'!E39 -> 1235320891 | G4: ='STATEMENT OF FINANCIAL POSITION'!F39 -> 1560105754 | H4: ='STATEMENT OF FINANCIAL POSITION'!G39 -> 1699301395 | I4: ='STATEMENT OF FINANCIAL POSITION'!H39 -> 1995648187 | J4: ='STATEMENT OF FINANCIAL POSITION'!I39 -> 2415328924 | K4: ='STATEMENT OF FINANCIAL POSITION'!J39 -> 2.3940354e+09 | ... W4: ='STATEMENT OF FINANCIAL POSITION'!V39 -> 2882475144 | X4: ='STATEMENT OF FINANCIAL POSITION'!X39 -> 4.1914307e+09 | Y4: ='STATEMENT OF FINANCIAL POSITION'!Y39 -> 4189144224 | Z4: ='STATEMENT OF FINANCIAL POSITION'!Z39 -> 4.1233197e+09 | AA4: ='STATEMENT OF FINANCIAL POSITION'!AA39 -> 4.0988971e+09 | AB4: ='STATEMENT OF FINANCIAL POSITION'!AB39 -> 4.1633143e+09 | AC4: ='STATEMENT OF FINANCIAL POSITION'!AC39 -> 4.2139972e+09 | AD4: ='STATEMENT OF FINANCIAL POSITION'!AD39 -> 4.2482716e+09 | AE4: ='STATEMENT OF FINANCIAL POSITION'!AE39 -> 4.2781875e+09 | ... BF4: ='STATEMENT OF FINANCIAL POSITION'!BF39 -> 5.5795063e+09
B5: 3 | C5: Total Deposits | D5: ='STATEMENT OF FINANCIAL POSITION'!C46 -> 559229530 | E5: ='STATEMENT OF FINANCIAL POSITION'!D46 -> 745419886 | F5: ='STATEMENT OF FINANCIAL POSITION'!E46 -> 881752998 | G5: ='STATEMENT OF FINANCIAL POSITION'!F46 -> 1074107086 | H5: ='STATEMENT OF FINANCIAL POSITION'!G46 -> 1097902733 | I5: ='STATEMENT OF FINANCIAL POSITION'!H46 -> 1301662001 | J5: ='STATEMENT OF FINANCIAL POSITION'!I46 -> 1561654213 | K5: ='STATEMENT OF FINANCIAL POSITION'!J46 -> 1.5130318e+09 | ... W5: ='STATEMENT OF FINANCIAL POSITION'!V46 -> 1816103673 | X5: ='STATEMENT OF FINANCIAL POSITION'!X46 -> 2.6000952e+09 | Y5: ='STATEMENT OF FINANCIAL POSITION'!Y46 -> 2600095208 | Z5: ='STATEMENT OF FINANCIAL POSITION'!Z46 -> 2.675158e+09 | AA5: ='STATEMENT OF FINANCIAL POSITION'!AA46 -> 2.6322747e+09 | AB5: ='STATEMENT OF FINANCIAL POSITION'!AB46 -> 2.6693256e+09 | AC5: ='STATEMENT OF FINANCIAL POSITION'!AC46 -> 2664023686 | AD5: ='STATEMENT OF FINANCIAL POSITION'!AD46 -> 2.6693278e+09 | AE5: ='STATEMENT OF FINANCIAL POSITION'!AE46 -> 2.6754047e+09 | ... BF5: ='STATEMENT OF FINANCIAL POSITION'!BF46 -> 3.4592088e+09
B6: 3.1 | C6: Deposits-Members(BOSA) | D6: ='STATEMENT OF FINANCIAL POSITION'!C45 -> 259831037 | E6: ='STATEMENT OF FINANCIAL POSITION'!D45 -> 343881456 | F6: ='STATEMENT OF FINANCIAL POSITION'!E45 -> 435718084 | G6: ='STATEMENT OF FINANCIAL POSITION'!F45 -> 533687314 | H6: ='STATEMENT OF FINANCIAL POSITION'!G45 -> 588206481 | I6: ='STATEMENT OF FINANCIAL POSITION'!H45 -> 645106995 | J6: ='STATEMENT OF FINANCIAL POSITION'!I45 -> 833556884 | K6: ='STATEMENT OF FINANCIAL POSITION'!J45 -> 8.4011294e+08 | ... W6: ='STATEMENT OF FINANCIAL POSITION'!V45 -> 932150562 | X6: ='STATEMENT OF FINANCIAL POSITION'!X45 -> 1.4450413e+09 | Y6: ='STATEMENT OF FINANCIAL POSITION'!Y45 -> 1004303406 | Z6: ='STATEMENT OF FINANCIAL POSITION'!Z45 -> 1.4627379e+09 | AA6: ='STATEMENT OF FINANCIAL POSITION'!AA45 -> 1.4778964e+09 | AB6: ='STATEMENT OF FINANCIAL POSITION'!AB45 -> 1.5012699e+09 | AC6: ='STATEMENT OF FINANCIAL POSITION'!AC45 -> 1.5186985e+09 | AD6: ='STATEMENT OF FINANCIAL POSITION'!AD45 -> 1.5411626e+09 | AE6: ='STATEMENT OF FINANCIAL POSITION'!AE45 -> 1.5764766e+09 | ... BF6: ='STATEMENT OF FINANCIAL POSITION'!BF45 -> 2.2010512e+09
B7: 3.2 | C7: Deposits-Customers(FOSA) | D7: ='STATEMENT OF FINANCIAL POSITION'!C43 -> 244588501 | E7: ='STATEMENT OF FINANCIAL POSITION'!D44 -> 71496906 | F7: ='STATEMENT OF FINANCIAL POSITION'!E43+'STATEMENT OF FINANCIAL POSITION'!E44 -> 446034914 | G7: ='STATEMENT OF FINANCIAL POSITION'!F43+'STATEMENT OF FINANCIAL POSITION'!F44 -> 540419772 | H7: ='STATEMENT OF FINANCIAL POSITION'!G43+'STATEMENT OF FINANCIAL POSITION'!G44 -> 509696252 | I7: ='STATEMENT OF FINANCIAL POSITION'!H43+'STATEMENT OF FINANCIAL POSITION'!H44 -> 656555006 | J7: ='STATEMENT OF FINANCIAL POSITION'!I43+'STATEMENT OF FINANCIAL POSITION'!I44 -> 728097329 | K7: ='STATEMENT OF FINANCIAL POSITION'!J43+'STATEMENT OF FINANCIAL POSITION'!J44 -> 6.7291884e+08 | L7: ='STATEMENT OF FINANCIAL POSITION'!K43+'STATEMENT OF FINANCIAL POSITION'!K44 -> 6.7451603e+08 | M7: ='STATEMENT OF FINANCIAL POSITION'!L43+'STATEMENT OF FINANCIAL POSITION'!L44 -> 6.2875647e+08 | ... W7: ='STATEMENT OF FINANCIAL POSITION'!V43+'STATEMENT OF FINANCIAL POSITION'!V44 -> 883953111 | X7: ='STATEMENT OF FINANCIAL POSITION'!X43+'STATEMENT OF FINANCIAL POSITION'!X44 -> 1.155054e+09 | Y7: ='STATEMENT OF FINANCIAL POSITION'!Y43+'STATEMENT OF FINANCIAL POSITION'!Y44 -> 1595791802 | Z7: ='STATEMENT OF FINANCIAL POSITION'!Z43+'STATEMENT OF FINANCIAL POSITION'!Z44 -> 1.2124201e+09 | AA7: ='STATEMENT OF FINANCIAL POSITION'!AA43+'STATEMENT OF FINANCIAL POSITION'!AA44 -> 1154378248 | AB7: ='STATEMENT OF FINANCIAL POSITION'!AB43+'STATEMENT OF FINANCIAL POSITION'!AB44 -> 1.1680557e+09 | AC7: ='STATEMENT OF FINANCIAL POSITION'!AC43+'STATEMENT OF FINANCIAL POSITION'!AC44 -> 1.1453252e+09 | AD7: ='STATEMENT OF FINANCIAL POSITION'!AD43+'STATEMENT OF FINANCIAL POSITION'!AD44 -> 1.1281652e+09 | AE7: ='STATEMENT OF FINANCIAL POSITION'!AE43+'STATEMENT OF FINANCIAL POSITION'!AE44 -> 1.0989281e+09 | ... BF7: ='STATEMENT OF FINANCIAL POSITION'!BF43+'STATEMENT OF FINANCIAL POSITION'!BF44 -> 1.2581576e+09
B8: 4 | C8: External Borrowing | D8: ='STATEMENT OF FINANCIAL POSITION'!C54 -> 10587743 | E8: ='STATEMENT OF FINANCIAL POSITION'!D54 -> 39797135 | F8: ='STATEMENT OF FINANCIAL POSITION'!E54 -> 3000000 | G8: ='STATEMENT OF FINANCIAL POSITION'!F54 -> 0 | H8: ='STATEMENT OF FINANCIAL POSITION'!G54 -> 0 | I8: ='STATEMENT OF FINANCIAL POSITION'!H54 -> 0 | J8: ='STATEMENT OF FINANCIAL POSITION'!I54 -> 0 | K8: ='STATEMENT OF FINANCIAL POSITION'!J54 -> 0 | ... W8: ='STATEMENT OF FINANCIAL POSITION'!V54 -> 0 | X8: ='STATEMENT OF FINANCIAL POSITION'!X54 -> 6711068.7 | Y8: ='STATEMENT OF FINANCIAL POSITION'!Y54 -> 0 | Z8: ='STATEMENT OF FINANCIAL POSITION'!Z54 -> 5869715 | AA8: ='STATEMENT OF FINANCIAL POSITION'!AA54 -> 5874606.3 | AB8: ='STATEMENT OF FINANCIAL POSITION'!AB54 -> 5879497.7 | AC8: ='STATEMENT OF FINANCIAL POSITION'!AC54 -> 5037452 | AD8: ='STATEMENT OF FINANCIAL POSITION'!AD54 -> 5041650 | AE8: ='STATEMENT OF FINANCIAL POSITION'!AE54 -> 5045848 | ... BF8: ='STATEMENT OF FINANCIAL POSITION'!BF54 -> 0
B10: 5 | C10: Share capital and Reserves
B11: 5.1 | C11: Core Capital | D11: =D14-D23 -> 188947973 | E11: =E14-E23 -> 239362202 | F11: =F14-F23 -> 221733455 | G11: =G14-G23 -> 317987309 | H11: =H14-H23 -> 400606236 | I11: =I14-I23 -> 482819469 | J11: =J14-J23 -> 544401880 | K11: =K14-K23 -> 5.6152946e+08 | ... BF11: =BF14-BF23 -> 1.4169528e+09
B12: 5.2 | C12: Institutional Capital | D12: =D11-D15 -> 61559893 | E12: =E11-E15 -> 106281551 | F12: =F11-F15 -> 188250897 | G12: =G11-G15 -> 275786629 | H12: =H11-H15 -> 358340851 | I12: =I11-I15 -> 438454448 | J12: =J11-J15 -> 494753405 | K12: =K11-K15 -> 5.114579e+08 | ... BF12: =BF11-BF15 -> 1.1792989e+09
B14: 5.3 | C14: Total Capital | D14: =SUM(D15:D21) -> 203039553 | E14: =SUM(E15:E21) -> 254553782 | F14: =SUM(F15:F21) -> 236925035 | G14: =SUM(G15:G21) -> 333973009 | H14: =SUM(H15:H21) -> 426691936 | I14: =SUM(I15:I21) -> 510101546 | J14: =SUM(J15:J21) -> 575483957 | K14: =SUM(K15:K21) -> 5.9261154e+08 | ... BF14: =SUM(BF15:BF21) -> 1.560247e+09
B15: 5.3.1 | C15: Members Share Capital | D15: ='STATEMENT OF FINANCIAL POSITION'!C58 -> 127388080 | E15: ='STATEMENT OF FINANCIAL POSITION'!D58 -> 133080651 | F15: ='STATEMENT OF FINANCIAL POSITION'!E58 -> 33482558 | G15: ='STATEMENT OF FINANCIAL POSITION'!F58 -> 42200680 | H15: ='STATEMENT OF FINANCIAL POSITION'!G58 -> 42265385 | I15: ='STATEMENT OF FINANCIAL POSITION'!H58 -> 44365021 | J15: ='STATEMENT OF FINANCIAL POSITION'!I58 -> 49648475 | K15: ='STATEMENT OF FINANCIAL POSITION'!J58 -> 50071559 | ... W15: ='STATEMENT OF FINANCIAL POSITION'!V58 -> 113780340 | X15: ='STATEMENT OF FINANCIAL POSITION'!X58 -> 1.4578701e+08 | Y15: ='STATEMENT OF FINANCIAL POSITION'!Y58 -> 145787006 | Z15: ='STATEMENT OF FINANCIAL POSITION'!Z58 -> 1.4691082e+08 | AA15: ='STATEMENT OF FINANCIAL POSITION'!AA58 -> 1.4806064e+08 | AB15: ='STATEMENT OF FINANCIAL POSITION'!AB58 -> 1.4936251e+08 | AC15: ='STATEMENT OF FINANCIAL POSITION'!AC58 -> 1.5043828e+08 | AD15: ='STATEMENT OF FINANCIAL POSITION'!AD58 -> 1.5143916e+08 | AE15: ='STATEMENT OF FINANCIAL POSITION'!AE58 -> 1.5285222e+08 | ... BF15: ='STATEMENT OF FINANCIAL POSITION'!BF58 -> 2.3765395e+08
B16: 5.3.3 | C16: Retained Earnings | D16: ='STATEMENT OF FINANCIAL POSITION'!C61 -> 48170884 | E16: ='STATEMENT OF FINANCIAL POSITION'!D61 -> 84159745 | F16: ='STATEMENT OF FINANCIAL POSITION'!E61 -> 145851655 | G16: ='STATEMENT OF FINANCIAL POSITION'!F61 -> 212095859 | H16: ='STATEMENT OF FINANCIAL POSITION'!G61 -> 284016397 | I16: ='STATEMENT OF FINANCIAL POSITION'!H61 -> 348834010 | J16: ='STATEMENT OF FINANCIAL POSITION'!I61 -> 386711956 | K16: ='STATEMENT OF FINANCIAL POSITION'!J61 -> 4.540086e+08 | ... W16: ='STATEMENT OF FINANCIAL POSITION'!V61 -> 407228249 | X16: ='STATEMENT OF FINANCIAL POSITION'!X61 -> 6.5504807e+08 | Y16: ='STATEMENT OF FINANCIAL POSITION'!Y61 -> 618677813 | Z16: ='STATEMENT OF FINANCIAL POSITION'!Z61 -> 6.3512853e+08 | AA16: ='STATEMENT OF FINANCIAL POSITION'!AA61 -> 6.3922187e+08 | AB16: ='STATEMENT OF FINANCIAL POSITION'!AB61 -> 6.4477809e+08 | AC16: ='STATEMENT OF FINANCIAL POSITION'!AC61 -> 6.7560311e+08 | AD16: ='STATEMENT OF FINANCIAL POSITION'!AD61 -> 6.8071258e+08 | AE16: ='STATEMENT OF FINANCIAL POSITION'!AE61 -> 6.8918871e+08 | ... BF16: ='STATEMENT OF FINANCIAL POSITION'!BF61 -> 8.2046693e+08
B17: 5.3.5 | C17: Statutory Reserves | D17: ='STATEMENT OF FINANCIAL POSITION'!C66 -> 22297880 | E17: ='STATEMENT OF FINANCIAL POSITION'!D66 -> 31912074 | F17: ='STATEMENT OF FINANCIAL POSITION'!E66 -> 48489144 | G17: ='STATEMENT OF FINANCIAL POSITION'!F66 -> 66444985 | H17: ='STATEMENT OF FINANCIAL POSITION'!G66 -> 86652629 | I17: ='STATEMENT OF FINANCIAL POSITION'!H66 -> 103145013 | J17: ='STATEMENT OF FINANCIAL POSITION'!I66 -> 126132045 | K17: ='STATEMENT OF FINANCIAL POSITION'!J66 -> 1.2613205e+08 | ... W17: ='STATEMENT OF FINANCIAL POSITION'!V66 -> 148036060 | X17: ='STATEMENT OF FINANCIAL POSITION'!X66 -> 1.8040062e+08 | Y17: ='STATEMENT OF FINANCIAL POSITION'!Y66 -> 215052536 | Z17: ='STATEMENT OF FINANCIAL POSITION'!Z66 -> 2.1505254e+08 | AA17: ='STATEMENT OF FINANCIAL POSITION'!AA66 -> 2.1505254e+08 | AB17: ='STATEMENT OF FINANCIAL POSITION'!AB66 -> 2.1505254e+08 | AC17: ='STATEMENT OF FINANCIAL POSITION'!AC66 -> 2.1505254e+08 | AD17: ='STATEMENT OF FINANCIAL POSITION'!AD66 -> 2.1505254e+08 | AE17: ='STATEMENT OF FINANCIAL POSITION'!AE66 -> 2.1505254e+08 | ... BF17: ='STATEMENT OF FINANCIAL POSITION'!BF66 -> 2.7415492e+08
B18: 5.3.6 | C18: Capital Reserves | D18: ='STATEMENT OF FINANCIAL POSITION'!C67+'STATEMENT OF FINANCIAL POSITION'!C70 -> 5182709 | E18: ='STATEMENT OF FINANCIAL POSITION'!D67+'STATEMENT OF FINANCIAL POSITION'!D70 -> 5401312 | F18: ='STATEMENT OF FINANCIAL POSITION'!E67 -> 9101678 | G18: ='STATEMENT OF FINANCIAL POSITION'!F67 -> 13231485 | H18: ='STATEMENT OF FINANCIAL POSITION'!G67 -> 13757525 | I18: ='STATEMENT OF FINANCIAL POSITION'!H67 -> 13757502 | J18: ='STATEMENT OF FINANCIAL POSITION'!I67-50000000 -> 12991481 | K18: ='STATEMENT OF FINANCIAL POSITION'!J67-50000000 -> -37600669 | L18: ='STATEMENT OF FINANCIAL POSITION'!K67-50000000 -> -36593836 | M18: ='STATEMENT OF FINANCIAL POSITION'!L67-50000000 -> -36965986 | N18: ='STATEMENT OF FINANCIAL POSITION'!M67-50000000 -> -37176241 | O18: ='STATEMENT OF FINANCIAL POSITION'!N67-50000000 -> -37235081 | P18: ='STATEMENT OF FINANCIAL POSITION'!O67-50000000 -> -37390608 | Q18: ='STATEMENT OF FINANCIAL POSITION'!P67-50000000 -> -37468548 | ... W18: ='STATEMENT OF FINANCIAL POSITION'!V67-50000000 -> 68215359 | X18: ='STATEMENT OF FINANCIAL POSITION'!X67-50000000 -> 1.236556e+08 | Y18: ='STATEMENT OF FINANCIAL POSITION'!Y67-50000000 -> 126771360 | Z18: ='STATEMENT OF FINANCIAL POSITION'!Z67-50000000 -> 1.2523385e+08 | AA18: ='STATEMENT OF FINANCIAL POSITION'!AA67-50000000 -> 1.2493916e+08 | AB18: ='STATEMENT OF FINANCIAL POSITION'!AB67-50000000 -> 1.2470198e+08 | AC18: ='STATEMENT OF FINANCIAL POSITION'!AC67-50000000 -> 1.2428026e+08 | AD18: ='STATEMENT OF FINANCIAL POSITION'!AD67-50000000 -> 1.2413026e+08 | AE18: ='STATEMENT OF FINANCIAL POSITION'!AE67-50000000 -> 1.2390526e+08 | ... BF18: ='STATEMENT OF FINANCIAL POSITION'!BF67-50000000 -> 2.2797116e+08
B19: 5.3.7 | C19: Supplementary Capital & reserves
B20: a | C20: Proposed Dividends
B21: b | C21: Risk Mgt Fund
B23: 6 | C23: Investments | D23: =D25+D24 -> 14091580 | E23: =E25+E24 -> 15191580 | F23: =F25+F24 -> 15191580 | G23: =G25+G24 -> 15985700 | H23: =H25+H24 -> 26085700 | I23: =I25+I24 -> 27282077 | J23: =J25+J24 -> 31082077 | K23: =K25+K24 -> 31082077 | ... BF23: =BF25+BF24 -> 143294140
C24: Liquidity investments | D24: ='STATEMENT OF FINANCIAL POSITION'!C17+'STATEMENT OF FINANCIAL POSITION'!C18 -> 0 | E24: ='STATEMENT OF FINANCIAL POSITION'!D17+'STATEMENT OF FINANCIAL POSITION'!D18 -> 0
C25: Equity Investments (at cost) | D25: ='STATEMENT OF FINANCIAL POSITION'!C21 -> 14091580 | E25: ='STATEMENT OF FINANCIAL POSITION'!D21 -> 15191580 | F25: ='STATEMENT OF FINANCIAL POSITION'!E21 -> 15191580 | G25: ='STATEMENT OF FINANCIAL POSITION'!F21 -> 15985700 | H25: ='STATEMENT OF FINANCIAL POSITION'!G21 -> 26085700 | I25: ='STATEMENT OF FINANCIAL POSITION'!H21 -> 27282077 | J25: ='STATEMENT OF FINANCIAL POSITION'!I21 -> 31082077 | K25: ='STATEMENT OF FINANCIAL POSITION'!J21 -> 31082077 | ... W25: ='STATEMENT OF FINANCIAL POSITION'!V21 -> 33417035 | X25: ='STATEMENT OF FINANCIAL POSITION'!X21 -> 38417035 | Y25: ='STATEMENT OF FINANCIAL POSITION'!Y21 -> 10000000 | Z25: ='STATEMENT OF FINANCIAL POSITION'!Z21 -> 38417035 | AA25: ='STATEMENT OF FINANCIAL POSITION'!AA21 -> 38417035 | AB25: ='STATEMENT OF FINANCIAL POSITION'!AB21 -> 38417035 | AC25: ='STATEMENT OF FINANCIAL POSITION'!AC21 -> 38417035 | AD25: ='STATEMENT OF FINANCIAL POSITION'!AD21 -> 38417035 | AE25: ='STATEMENT OF FINANCIAL POSITION'!AE21 -> 38417035 | ... BF25: ='STATEMENT OF FINANCIAL POSITION'!BF21 -> 143294140
B27: 7 | C27: Net Loans & Advances | D27: =D28-D29 -> 502161933 | E27: =E28-E29 -> 677484431 | F27: =F28-F29 -> 834727981 | G27: =G28-G29 -> #REF! | H27: =H28-H29 -> 1128533399 | I27: =I28-I29 -> 1189398328 | J27: =J28-J29 -> 1390743016 | K27: =K28-K29 -> 1.4342734e+09 | ... BF27: =BF28-BF29 -> 3.7911369e+09
B28: 7.1 | C28: Gross Loans & advances | D28: ='STATEMENT OF FINANCIAL POSITION'!C24 -> 502161933 | E28: ='STATEMENT OF FINANCIAL POSITION'!D24 -> 701336906 | F28: ='STATEMENT OF FINANCIAL POSITION'!E24 -> 866580456 | G28: ='STATEMENT OF FINANCIAL POSITION'!F24 -> 1050502640 | H28: ='STATEMENT OF FINANCIAL POSITION'!G24 -> 1169889815 | I28: ='STATEMENT OF FINANCIAL POSITION'!H24 -> 1260039501 | J28: ='STATEMENT OF FINANCIAL POSITION'!I24 -> 1490839582 | K28: ='STATEMENT OF FINANCIAL POSITION'!J24 -> 1.537245e+09 | ... W28: ='STATEMENT OF FINANCIAL POSITION'!V24 -> 1720827246 | X28: ='STATEMENT OF FINANCIAL POSITION'!X24 -> 2.9836566e+09 | Y28: ='STATEMENT OF FINANCIAL POSITION'!Y24 -> 2983656626 | Z28: ='STATEMENT OF FINANCIAL POSITION'!Z24 -> 3.0212551e+09 | AA28: ='STATEMENT OF FINANCIAL POSITION'!AA24 -> 3.0695181e+09 | AB28: ='STATEMENT OF FINANCIAL POSITION'!AB24 -> 3.1303044e+09 | AC28: ='STATEMENT OF FINANCIAL POSITION'!AC24 -> 3.1805279e+09 | AD28: ='STATEMENT OF FINANCIAL POSITION'!AD24 -> 3.2399479e+09 | AE28: ='STATEMENT OF FINANCIAL POSITION'!AE24 -> 3.2950827e+09 | ... BF28: ='STATEMENT OF FINANCIAL POSITION'!BF24 -> 4.2438236e+09
B29: 7.2 | C29: Allowance for loan losses | D29: ='STATEMENT OF FINANCIAL POSITION'!C25 -> 0 | E29: ='STATEMENT OF FINANCIAL POSITION'!E25 -> 23852475 | F29: ='STATEMENT OF FINANCIAL POSITION'!F25 -> 31852475 | G29: ='STATEMENT OF FINANCIAL POSITION'!#REF! -> #REF! | H29: ='STATEMENT OF FINANCIAL POSITION'!G25 -> 41356416 | I29: ='STATEMENT OF FINANCIAL POSITION'!H25 -> 70641173 | J29: ='STATEMENT OF FINANCIAL POSITION'!I25 -> 100096566 | K29: ='STATEMENT OF FINANCIAL POSITION'!J25 -> 1.0297157e+08 | L29: ='STATEMENT OF FINANCIAL POSITION'!K25 -> 1.0584657e+08 | M29: ='STATEMENT OF FINANCIAL POSITION'!L25 -> 1.0872157e+08 | N29: ='STATEMENT OF FINANCIAL POSITION'!M25 -> 1.1159657e+08 | O29: ='STATEMENT OF FINANCIAL POSITION'!N25 -> 1.1447157e+08 | ... W29: ='STATEMENT OF FINANCIAL POSITION'!V25 -> 134596566 | X29: ='STATEMENT OF FINANCIAL POSITION'!X25 -> 3.7287802e+08 | Y29: ='STATEMENT OF FINANCIAL POSITION'!Y25 -> 372878022 | Z29: ='STATEMENT OF FINANCIAL POSITION'!Z25 -> 3.7737802e+08 | AA29: ='STATEMENT OF FINANCIAL POSITION'!AA25 -> 3.8187802e+08 | AB29: ='STATEMENT OF FINANCIAL POSITION'!AB25 -> 3.8637802e+08 | AC29: ='STATEMENT OF FINANCIAL POSITION'!AC25 -> 3.9087802e+08 | AD29: ='STATEMENT OF FINANCIAL POSITION'!AD25 -> 3.9537802e+08 | AE29: ='STATEMENT OF FINANCIAL POSITION'!AE25 -> 3.9987802e+08 | ... BF29: ='STATEMENT OF FINANCIAL POSITION'!BF25 -> 4.5268676e+08
B31: 8 | C31: Non-Earning Assets | D31: ='STATEMENT OF FINANCIAL POSITION'!C14+'STATEMENT OF FINANCIAL POSITION'!C27+'STATEMENT OF FINANCIAL POSITION'!C32 -> 201456282 | E31: ='STATEMENT OF FINANCIAL POSITION'!D14+'STATEMENT OF FINANCIAL POSITION'!D27+'STATEMENT OF FINANCIAL POSITION'!D32 -> 211111037 | F31: ='STATEMENT OF FINANCIAL POSITION'!E14+'STATEMENT OF FINANCIAL POSITION'!E32 -> 111366691 | G31: ='STATEMENT OF FINANCIAL POSITION'!F14+'STATEMENT OF FINANCIAL POSITION'!F32 -> 128997171 | H31: ='STATEMENT OF FINANCIAL POSITION'!G14+'STATEMENT OF FINANCIAL POSITION'!G32 -> 136854905 | I31: ='STATEMENT OF FINANCIAL POSITION'!H14+'STATEMENT OF FINANCIAL POSITION'!H32 -> 154543242 | J31: ='STATEMENT OF FINANCIAL POSITION'!I14+'STATEMENT OF FINANCIAL POSITION'!I32 -> 192056532 | K31: ='STATEMENT OF FINANCIAL POSITION'!J14+'STATEMENT OF FINANCIAL POSITION'!J32 -> 1.9985905e+08 | L31: ='STATEMENT OF FINANCIAL POSITION'!K14+'STATEMENT OF FINANCIAL POSITION'!K32 -> 1.9470931e+08 | M31: ='STATEMENT OF FINANCIAL POSITION'!L14+'STATEMENT OF FINANCIAL POSITION'!L32 -> 2.0346041e+08 | ... W31: ='STATEMENT OF FINANCIAL POSITION'!V14+'STATEMENT OF FINANCIAL POSITION'!V32 -> 190620037 | X31: ='STATEMENT OF FINANCIAL POSITION'!X14+'STATEMENT OF FINANCIAL POSITION'!X32 -> 2.459182e+08 | Y31: ='STATEMENT OF FINANCIAL POSITION'!Y14+'STATEMENT OF FINANCIAL POSITION'!Y32 -> 243631769 | Z31: ='STATEMENT OF FINANCIAL POSITION'!Z14+'STATEMENT OF FINANCIAL POSITION'!Z32 -> 2.401435e+08 | AA31: ='STATEMENT OF FINANCIAL POSITION'!AA14+'STATEMENT OF FINANCIAL POSITION'!AA32 -> 2.6027125e+08 | AB31: ='STATEMENT OF FINANCIAL POSITION'!AB14+'STATEMENT OF FINANCIAL POSITION'!AB32 -> 2.685406e+08 | AC31: ='STATEMENT OF FINANCIAL POSITION'!AC14+'STATEMENT OF FINANCIAL POSITION'!AC32 -> 2.7443811e+08 | AD31: ='STATEMENT OF FINANCIAL POSITION'!AD14+'STATEMENT OF FINANCIAL POSITION'!AD32 -> 284918774 | AE31: ='STATEMENT OF FINANCIAL POSITION'!AE14+'STATEMENT OF FINANCIAL POSITION'!AE32 -> 2.94993e+08 | ... BC31: ='STATEMENT OF FINANCIAL POSITION'!BC14+'STATEMENT OF FINANCIAL POSITION'!BC32 -> 4.542258e+08 | BD31: ='STATEMENT OF FINANCIAL POSITION'!#REF!+'STATEMENT OF FINANCIAL POSITION'!BD32 -> #REF! | BE31: ='STATEMENT OF FINANCIAL POSITION'!#REF!+'STATEMENT OF FINANCIAL POSITION'!BE32 -> #REF! | BF31: ='STATEMENT OF FINANCIAL POSITION'!#REF!+'STATEMENT OF FINANCIAL POSITION'!BF32 -> #REF!
B32: 8.1 | C32: Property and Equipment | D32: ='STATEMENT OF FINANCIAL POSITION'!C34 -> 152497884 | E32: ='STATEMENT OF FINANCIAL POSITION'!D34 -> 161391712 | F32: ='STATEMENT OF FINANCIAL POSITION'!E32 -> 40224658 | G32: ='STATEMENT OF FINANCIAL POSITION'!F32 -> 56850072 | H32: ='STATEMENT OF FINANCIAL POSITION'!G32 -> 61006144 | I32: ='STATEMENT OF FINANCIAL POSITION'!H32 -> 66390514 | J32: ='STATEMENT OF FINANCIAL POSITION'!I32 -> 66106031 | K32: ='STATEMENT OF FINANCIAL POSITION'!J32 -> 64982708 | L32: ='STATEMENT OF FINANCIAL POSITION'!K32 -> 64315496 | M32: ='STATEMENT OF FINANCIAL POSITION'!L32 -> 71599826 | ... W32: ='STATEMENT OF FINANCIAL POSITION'!V32 -> 67836690 | X32: ='STATEMENT OF FINANCIAL POSITION'!X32 -> 78065940 | Y32: ='STATEMENT OF FINANCIAL POSITION'!Y32 -> 78065939 | Z32: ='STATEMENT OF FINANCIAL POSITION'!Z32 -> 78960803 | AA32: ='STATEMENT OF FINANCIAL POSITION'!AA32 -> 80758834 | AB32: ='STATEMENT OF FINANCIAL POSITION'!AB32 -> 82099037 | AC32: ='STATEMENT OF FINANCIAL POSITION'!AC32 -> 80833691 | AD32: ='STATEMENT OF FINANCIAL POSITION'!AD32 -> 81133069 | AE32: ='STATEMENT OF FINANCIAL POSITION'!AE32 -> 88838812 | ... BF32: ='STATEMENT OF FINANCIAL POSITION'!BF32 -> 1.330682e+08
B34: 9 | C34: Turnover | D34: =SUM(D35:D38) -> 81774220 | E34: =SUM(E35:E38) -> 168568169 | F34: ='STATEMENT OF COMPREHENSIVE INCO'!E10 -> 235675793 | G34: ='STATEMENT OF COMPREHENSIVE INCO'!F10 -> 288037618 | H34: ='STATEMENT OF COMPREHENSIVE INCO'!G10 -> 277638373 | I34: ='STATEMENT OF COMPREHENSIVE INCO'!H10 -> 314967423 | J34: ='STATEMENT OF COMPREHENSIVE INCO'!I10 -> 386913271 | K34: ='STATEMENT OF COMPREHENSIVE INCO'!J10 -> 25367152 | L34: ='STATEMENT OF COMPREHENSIVE INCO'!K10 -> 48625771 | M34: ='STATEMENT OF COMPREHENSIVE INCO'!L10 -> 71477836 | ... W34: ='STATEMENT OF COMPREHENSIVE INCO'!V10 -> 401655827 | X34: ='STATEMENT OF COMPREHENSIVE INCO'!X10 -> 5.2619319e+08 | Y34: ='STATEMENT OF COMPREHENSIVE INCO'!Y10 -> 611439871 | Z34: ='STATEMENT OF COMPREHENSIVE INCO'!Z10 -> 47671986 | AA34: ='STATEMENT OF COMPREHENSIVE INCO'!AA10 -> 91516919 | AB34: ='STATEMENT OF COMPREHENSIVE INCO'!AB10 -> 1.3790097e+08 | AC34: ='STATEMENT OF COMPREHENSIVE INCO'!AC10 -> 1.8312991e+08 | AD34: ='STATEMENT OF COMPREHENSIVE INCO'!AD10 -> 2.3096803e+08 | AE34: ='STATEMENT OF COMPREHENSIVE INCO'!AE10 -> 2.7961896e+08 | ... BF34: ='STATEMENT OF COMPREHENSIVE INCO'!BF10 -> 4.1967583e+08
B35: 9.1 | C35: Loan Interest | D35: ='STATEMENT OF COMPREHENSIVE INCO'!C12 -> 67225127 | E35: 111069243 | F35: ='STATEMENT OF COMPREHENSIVE INCO'!E12 -> 139362529 | G35: ='STATEMENT OF COMPREHENSIVE INCO'!F12 -> 176582685 | H35: ='STATEMENT OF COMPREHENSIVE INCO'!G12 -> 185123085 | I35: ='STATEMENT OF COMPREHENSIVE INCO'!H12 -> 199339025 | J35: ='STATEMENT OF COMPREHENSIVE INCO'!I12 -> 224030688 | K35: ='STATEMENT OF COMPREHENSIVE INCO'!J12 -> 16403062 | L35: ='STATEMENT OF COMPREHENSIVE INCO'!K12 -> 32799726 | M35: ='STATEMENT OF COMPREHENSIVE INCO'!L12 -> 49532688 | ... W35: ='STATEMENT OF COMPREHENSIVE INCO'!V12 -> 225641290 | X35: ='STATEMENT OF COMPREHENSIVE INCO'!X12 -> 3.7559706e+08 | Y35: ='STATEMENT OF COMPREHENSIVE INCO'!Y12 -> 373570484 | Z35: ='STATEMENT OF COMPREHENSIVE INCO'!Z12 -> 33549968 | AA35: ='STATEMENT OF COMPREHENSIVE INCO'!AA12 -> 67275548 | AB35: ='STATEMENT OF COMPREHENSIVE INCO'!AB12 -> 1.0160622e+08 | AC35: ='STATEMENT OF COMPREHENSIVE INCO'!AC12 -> 1.3647068e+08 | AD35: ='STATEMENT OF COMPREHENSIVE INCO'!AD12 -> 1.7227046e+08 | AE35: ='STATEMENT OF COMPREHENSIVE INCO'!AE12 -> 2.0871353e+08 | ... BF35: ='STATEMENT OF COMPREHENSIVE INCO'!BF12 -> 3.163379e+08
B36: 9.2 | C36: Income from investments | D36: ='STATEMENT OF COMPREHENSIVE INCO'!C15 -> 7903025 | E36: 10065060 | F36: ='STATEMENT OF COMPREHENSIVE INCO'!E15 -> 63812280 | G36: ='STATEMENT OF COMPREHENSIVE INCO'!F15 -> 74814135 | H36: ='STATEMENT OF COMPREHENSIVE INCO'!G15 -> 76419845 | I36: ='STATEMENT OF COMPREHENSIVE INCO'!H15 -> 115628398 | J36: ='STATEMENT OF COMPREHENSIVE INCO'!I15 -> 121752357 | K36: ='STATEMENT OF COMPREHENSIVE INCO'!J15 -> 3108225.9 | L36: ='STATEMENT OF COMPREHENSIVE INCO'!K15 -> 6014421.8 | M36: ='STATEMENT OF COMPREHENSIVE INCO'!L15 -> 8833672.7 | ... W36: ='STATEMENT OF COMPREHENSIVE INCO'!V15 -> 129426981 | X36: ='STATEMENT OF COMPREHENSIVE INCO'!X15 -> 65065145 | Y36: ='STATEMENT OF COMPREHENSIVE INCO'!Y15 -> 98274892 | Z36: ='STATEMENT OF COMPREHENSIVE INCO'!Z15 -> 6397891.4 | AA36: ='STATEMENT OF COMPREHENSIVE INCO'!AA15 -> 11043007 | AB36: ='STATEMENT OF COMPREHENSIVE INCO'!AB15 -> 16818057 | AC36: ='STATEMENT OF COMPREHENSIVE INCO'!AC15 -> 22671289 | AD36: ='STATEMENT OF COMPREHENSIVE INCO'!AD15 -> 27710020 | AE36: ='STATEMENT OF COMPREHENSIVE INCO'!AE15 -> 34117034 | ... BF36: ='STATEMENT OF COMPREHENSIVE INCO'!BF15 -> 55860066
B37: 9.3 | C37: Fees & Commissions | D37: ='STATEMENT OF COMPREHENSIVE INCO'!C13 -> 6646068 | E37: 47433866 | F37: ='STATEMENT OF COMPREHENSIVE INCO'!E13 -> 32500984 | G37: ='STATEMENT OF COMPREHENSIVE INCO'!F13 -> 36640798 | H37: ='STATEMENT OF COMPREHENSIVE INCO'!G13 -> 16095443 | I37: ='STATEMENT OF COMPREHENSIVE INCO'!H13 -> 0 | J37: ='STATEMENT OF COMPREHENSIVE INCO'!I13 -> 41130226 | K37: ='STATEMENT OF COMPREHENSIVE INCO'!J13 -> 5855863.9 | L37: ='STATEMENT OF COMPREHENSIVE INCO'!K13 -> 9811623.6 | M37: ='STATEMENT OF COMPREHENSIVE INCO'!L13 -> 13111476 | ... W37: ='STATEMENT OF COMPREHENSIVE INCO'!V13 -> 46587556 | X37: ='STATEMENT OF COMPREHENSIVE INCO'!X13 -> 85530988 | Y37: ='STATEMENT OF COMPREHENSIVE INCO'!Y13 -> 139594495 | Z37: ='STATEMENT OF COMPREHENSIVE INCO'!Z13 -> 7724126.3 | AA37: ='STATEMENT OF COMPREHENSIVE INCO'!AA13 -> 13198364 | AB37: ='STATEMENT OF COMPREHENSIVE INCO'!AB13 -> 19476688 | AC37: ='STATEMENT OF COMPREHENSIVE INCO'!AC13 -> 23987935 | AD37: ='STATEMENT OF COMPREHENSIVE INCO'!AD13 -> 30987550 | AE37: ='STATEMENT OF COMPREHENSIVE INCO'!AE13 -> 36788398 | ... BF37: ='STATEMENT OF COMPREHENSIVE INCO'!BF13 -> 47477869
B38: 9.4 | C38: Average yield on loans
B40: 10 | C40: Fianacial and Operating costs | D40: =D44+D43+D42+D41 -> 55053569 | E40: =E44+E43+E42+E41 -> 131526595 | F40: ='STATEMENT OF COMPREHENSIVE INCO'!E21+'STATEMENT OF COMPREHENSIVE INCO'!E36 -> 139247039 | G40: ='STATEMENT OF COMPREHENSIVE INCO'!F21+'STATEMENT OF COMPREHENSIVE INCO'!F36 -> 190484815 | H40: ='STATEMENT OF COMPREHENSIVE INCO'!G21+'STATEMENT OF COMPREHENSIVE INCO'!G36 -> 171390153 | I40: ='STATEMENT OF COMPREHENSIVE INCO'!H21+'STATEMENT OF COMPREHENSIVE INCO'!H36 -> 202505503 | J40: ='STATEMENT OF COMPREHENSIVE INCO'!I21+'STATEMENT OF COMPREHENSIVE INCO'!I36 -> 241978113 | K40: ='STATEMENT OF COMPREHENSIVE INCO'!J21+'STATEMENT OF COMPREHENSIVE INCO'!J36 -> 18322444 | L40: ='STATEMENT OF COMPREHENSIVE INCO'!K21+'STATEMENT OF COMPREHENSIVE INCO'!K36 -> 39580613 | M40: ='STATEMENT OF COMPREHENSIVE INCO'!L21+'STATEMENT OF COMPREHENSIVE INCO'!L36 -> 59751607 | ... W40: ='STATEMENT OF COMPREHENSIVE INCO'!V21+'STATEMENT OF COMPREHENSIVE INCO'!V36 -> 257635750 | X40: ='STATEMENT OF COMPREHENSIVE INCO'!X21+'STATEMENT OF COMPREHENSIVE INCO'!X36 -> 1.8778749e+08 | Y40: ='STATEMENT OF COMPREHENSIVE INCO'!Y21+'STATEMENT OF COMPREHENSIVE INCO'!Y36 -> 382880307 | Z40: ='STATEMENT OF COMPREHENSIVE INCO'!Z21+'STATEMENT OF COMPREHENSIVE INCO'!Z36 -> 36122790 | AA40: ='STATEMENT OF COMPREHENSIVE INCO'!AA21+'STATEMENT OF COMPREHENSIVE INCO'!AA36 -> 72899540 | AB40: ='STATEMENT OF COMPREHENSIVE INCO'!AB21+'STATEMENT OF COMPREHENSIVE INCO'!AB36 -> 1.1268562e+08 | AC40: ='STATEMENT OF COMPREHENSIVE INCO'!AC21+'STATEMENT OF COMPREHENSIVE INCO'!AC36 -> 1.5107428e+08 | AD40: ='STATEMENT OF COMPREHENSIVE INCO'!AD21+'STATEMENT OF COMPREHENSIVE INCO'!AD36 -> 1.8849395e+08 | AE40: ='STATEMENT OF COMPREHENSIVE INCO'!AE21+'STATEMENT OF COMPREHENSIVE INCO'!AE36 -> 2.2916412e+08 | ... BF40: ='STATEMENT OF COMPREHENSIVE INCO'!BF21+'STATEMENT OF COMPREHENSIVE INCO'!BF36 -> 4.1087425e+08
B41: 10.1 | C41: Interest expense on deposits | D41: ='STATEMENT OF COMPREHENSIVE INCO'!C22 -> 0 | E41: 40000000 | F41: ='STATEMENT OF COMPREHENSIVE INCO'!E24 -> 0 | G41: ='STATEMENT OF COMPREHENSIVE INCO'!F24 -> 0 | H41: 55000000 | I41: 55000009 | J41: 55000022 | K41: 55000023 | L41: 55000024 | M41: 55000025 | N41: 55000026 | O41: 55000027 | P41: 55000028 | Q41: 55000029 | R41: 55000030 | S41: 55000031 | T41: 55000032 | U41: 55000033 | V41: 55000034 | W41: 55000035 | X41: 55000036 | Y41: 55000036 | Z41: 55000037 | AA41: 55000038 | AB41: 55000039 | AC41: 55000040 | AD41: 55000041 | AE41: 55000042 | AF41: 55000043 | AG41: 55000044 | AH41: 55000045 | AI41: 55000046 | AJ41: 55000047 | AK41: 55000048 | AL41: 55000049 | AM41: 55000050 | AN41: 55000051 | AO41: 55000052 | AP41: 55000053 | AQ41: 55000054 | AR41: 55000055 | AS41: 55000056 | AT41: 55000057 | AU41: 55000058 | AV41: 55000059 | AW41: 55000060 | AX41: 55000061 | AY41: 55000062 | AZ41: 55000063 | BA41: 55000064 | BB41: 55000065 | BC41: 55000066 | BD41: 55000067 | BE41: 55000068 | BF41: 55000069
B42: 10.2 | C42: Dividend expense on share capital | D42: ='STATEMENT OF COMPREHENSIVE INCO'!C24 -> 35000000 | F42: 0
B43: 10.3 | C43: Interest expense on borrowed funds | D43: ='STATEMENT OF COMPREHENSIVE INCO'!C23 -> 0 | E43: 19745494 | F43: ='STATEMENT OF COMPREHENSIVE INCO'!E23 -> 22050995 | G43: ='STATEMENT OF COMPREHENSIVE INCO'!F23 -> 15150271 | H43: ='STATEMENT OF COMPREHENSIVE INCO'!G23 -> 7589359 | I43: ='STATEMENT OF COMPREHENSIVE INCO'!H23 -> 1522628 | J43: ='STATEMENT OF COMPREHENSIVE INCO'!I23 -> 0 | K43: ='STATEMENT OF COMPREHENSIVE INCO'!J23 -> 0 | L43: ='STATEMENT OF COMPREHENSIVE INCO'!K23 -> 0 | M43: ='STATEMENT OF COMPREHENSIVE INCO'!L23 -> 0 | ... W43: ='STATEMENT OF COMPREHENSIVE INCO'!V23 -> 355068 | X43: ='STATEMENT OF COMPREHENSIVE INCO'!X23 -> 0 | Y43: ='STATEMENT OF COMPREHENSIVE INCO'!Y23 -> 0 | Z43: ='STATEMENT OF COMPREHENSIVE INCO'!Z23 -> 5583.33 | AA43: ='STATEMENT OF COMPREHENSIVE INCO'!AA23 -> 10474.66 | AB43: ='STATEMENT OF COMPREHENSIVE INCO'!AB23 -> 15365.99 | AC43: ='STATEMENT OF COMPREHENSIVE INCO'!AC23 -> 20257.33 | AD43: ='STATEMENT OF COMPREHENSIVE INCO'!AD23 -> 24455.33 | AE43: ='STATEMENT OF COMPREHENSIVE INCO'!AE23 -> 28653.33 | ... BF43: ='STATEMENT OF COMPREHENSIVE INCO'!BF23 -> 0
B44: 10.4 | C44: Opperating expenses | D44: ='STATEMENT OF COMPREHENSIVE INCO'!C36 -> 20053569 | E44: =44632185+27148916 -> 71781101 | F44: ='STATEMENT OF COMPREHENSIVE INCO'!E36 -> 69196044 | G44: ='STATEMENT OF COMPREHENSIVE INCO'!F36 -> 89943298 | H44: ='STATEMENT OF COMPREHENSIVE INCO'!G36 -> 87367063 | I44: ='STATEMENT OF COMPREHENSIVE INCO'!H36 -> 117610973 | J44: ='STATEMENT OF COMPREHENSIVE INCO'!I36 -> 121174021 | K44: ='STATEMENT OF COMPREHENSIVE INCO'!J36 -> 10629822 | L44: ='STATEMENT OF COMPREHENSIVE INCO'!K36 -> 20571236 | M44: ='STATEMENT OF COMPREHENSIVE INCO'!L36 -> 32005351 | ... W44: ='STATEMENT OF COMPREHENSIVE INCO'!V36 -> 122985048 | X44: ='STATEMENT OF COMPREHENSIVE INCO'!X36 -> 1.5223035e+08 | Y44: ='STATEMENT OF COMPREHENSIVE INCO'!Y36 -> 149203287 | Z44: ='STATEMENT OF COMPREHENSIVE INCO'!Z36 -> 12839354 | AA44: ='STATEMENT OF COMPREHENSIVE INCO'!AA36 -> 26554294 | AB44: ='STATEMENT OF COMPREHENSIVE INCO'!AB36 -> 42979873 | AC44: ='STATEMENT OF COMPREHENSIVE INCO'!AC36 -> 58066775 | AD44: ='STATEMENT OF COMPREHENSIVE INCO'!AD36 -> 71990309 | AE44: ='STATEMENT OF COMPREHENSIVE INCO'!AE36 -> 89269948 | ... BF44: ='STATEMENT OF COMPREHENSIVE INCO'!BF36 -> 1.7969144e+08

Sheet PRUDENTIAL RATIOS
B1: YETU Sacco Ltd Financial Performance & Projections
B3: FINANCIAL SOUNDNESS INDICATORS | C3: Prudential Std | D3: 2010 | E3: 2011 | F3: 2012 | G3: AUDITED 2013 | H3: 2014 AUDITED | I3: AUDITED 2015 | J3: AUDITED 2016 | K3: 42736 | L3: 42767 | M3: 42795 | N3: 42826 | O3: 42856 | P3: 42887 | Q3: 42917 | R3: 42948 | S3: 42979 | T3: 43009 | U3: 43040 | V3: 43070 | W3: Audited 2017 | X3: 44166 | Y3: Audited 2020 | Z3: 44197 | AA3: 44228 | AB3: 44256 | AC3: 44287 | AD3: 44317 | AE3: 44348 | AF3: 44378 | AG3: 44409 | AH3: 44440 | AI3: 44470 | AJ3: 44501 | AK3: 44531 | AL3: AUDITED 2021 | AM3: 44562 | AN3: 44593 | AO3: 44621 | AP3: 44652 | AQ3: 44682 | AR3: 44713 | AS3: 44743 | AT3: 44774 | AU3: 44805 | AV3: 44835 | AW3: 44866 | AX3: 44896 | AY3: Audited 2022 | AZ3: 44927 | BA3: 44958 | BB3: 44986 | BC3: 45017 | BD3: 45047 | BE3: 45078 | BF3: 45108
A4: 1 | B4: CAPITAL ADEQUACY REQUIREMENTS
A5: 1.1 | B5: Core capital | C5: ≥ Ksh.10M | D5: =FINANCIALS!D11/1000000 -> 188.94797 | E5: =FINANCIALS!E11/1000000 -> 239.3622 | F5: =FINANCIALS!F11/1000000 -> 221.73345 | G5: =FINANCIALS!G11/1000000 -> 317.98731 | H5: =FINANCIALS!H11/1000000 -> 400.60624 | I5: =FINANCIALS!I11/1000000 -> 482.81947 | J5: =FINANCIALS!J11/1000000 -> 544.40188 | K5: =FINANCIALS!K11/1000000 -> 561.52946 | ... BF5: =FINANCIALS!BF11/1000000 -> 1416.9528
A6: 1.2 | B6: Core capital /Total Assets | C6: ≥ 10% | D6: =FINANCIALS!D11/FINANCIALS!D4 -> 0.21303049 | E6: =FINANCIALS!E11/FINANCIALS!E4 -> 0.2019514 | F6: =FINANCIALS!F11/FINANCIALS!F4 -> 0.17949462 | G6: =FINANCIALS!G11/FINANCIALS!G4 -> 0.2038242 | H6: =FINANCIALS!H11/FINANCIALS!H4 -> 0.23574761 | I6: =FINANCIALS!I11/FINANCIALS!I4 -> 0.24193616 | J6: =FINANCIALS!J11/FINANCIALS!J4 -> 0.22539451 | K6: =FINANCIALS!K11/FINANCIALS!K4 -> 0.23455353 | ... BF6: =FINANCIALS!BF11/FINANCIALS!BF4 -> 0.25395667
A7: 1.3 | B7: Core capital /Total Deposits | C7: ≥ 8% | D7: =FINANCIALS!D11/FINANCIALS!D5 -> 0.33787195 | E7: =FINANCIALS!E11/FINANCIALS!E5 -> 0.32111057 | F7: =FINANCIALS!F11/FINANCIALS!F5 -> 0.2514689 | G7: =FINANCIALS!G11/FINANCIALS!G5 -> 0.29604805 | H7: =FINANCIALS!H11/FINANCIALS!H5 -> 0.36488318 | I7: =FINANCIALS!I11/FINANCIALS!I5 -> 0.37092538 | J7: =FINANCIALS!J11/FINANCIALS!J5 -> 0.3486059 | K7: =FINANCIALS!K11/FINANCIALS!K5 -> 0.37112866 | ... BF7: =FINANCIALS!BF11/FINANCIALS!BF5 -> 0.4096176
A8: 1.4 | B8: Institutional/Total Assets | C8: ≥ 8% | D8: =FINANCIALS!D12/FINANCIALS!D4 -> 0.06940606 | E8: =FINANCIALS!E12/FINANCIALS!E4 -> 0.089670415 | F8: =FINANCIALS!F12/FINANCIALS!F4 -> 0.15239028 | G8: =FINANCIALS!G12/FINANCIALS!G4 -> 0.17677432 | H8: =FINANCIALS!H12/FINANCIALS!H4 -> 0.21087539 | I8: =FINANCIALS!I12/FINANCIALS!I4 -> 0.21970528 | J8: =FINANCIALS!J12/FINANCIALS!J4 -> 0.20483894 | K8: =FINANCIALS!K12/FINANCIALS!K4 -> 0.2136384 | ... BF8: =FINANCIALS!BF12/FINANCIALS!BF4 -> 0.21136258
A10: 2 | B10: ASSET MIX AND QUALITY
A11: 2.1 | B11: Non Earning Assets
A12: 2.1.1 | B12: Non earning Assets/Total assets | C12: ≤ 10% | D12: =FINANCIALS!D31/FINANCIALS!D4 -> 0.22713306 | E12: =FINANCIALS!E31/FINANCIALS!E4 -> 0.17811571 | F12: =FINANCIALS!F31/FINANCIALS!F4 -> 0.090152034 | G12: =FINANCIALS!G31/FINANCIALS!G4 -> 0.082684889 | H12: =FINANCIALS!H31/FINANCIALS!H4 -> 0.080535981 | I12: =FINANCIALS!I31/FINANCIALS!I4 -> 0.077440123 | J12: =FINANCIALS!J31/FINANCIALS!J4 -> 0.079515684 | K12: =FINANCIALS!K31/FINANCIALS!K4 -> 0.083482077 | ... BF12: =FINANCIALS!BF31/FINANCIALS!BF4 -> #REF!
A13: 2.1.2 | B13: Property and Equipment/TA | C13: ≤ 5% | D13: =FINANCIALS!D32/FINANCIALS!D4 -> 0.17193463 | E13: =FINANCIALS!E32/FINANCIALS!E4 -> 0.13616721 | F13: =FINANCIALS!F32/FINANCIALS!F4 -> 0.032562113 | G13: =FINANCIALS!G32/FINANCIALS!G4 -> 0.036439884 | H13: =FINANCIALS!H32/FINANCIALS!H4 -> 0.03590072 | I13: =FINANCIALS!I32/FINANCIALS!I4 -> 0.033267644 | J13: =FINANCIALS!J32/FINANCIALS!J4 -> 0.02736937 | K13: =FINANCIALS!K32/FINANCIALS!K4 -> 0.027143587 | ... BF13: =FINANCIALS!BF32/FINANCIALS!BF4 -> 0.023849458
A15: 2.2 | B15: Earning Assets
A16: 2.2.1 | B16: Non-Govt Securities/Deposits | C16: ≤ 5% | D16: =('STATEMENT OF FINANCIAL POSITION'!C18+'STATEMENT OF FINANCIAL POSITION'!C21)/FINANCIALS!D5 -> 0.025198204 | E16: =('STATEMENT OF FINANCIAL POSITION'!D18+'STATEMENT OF FINANCIAL POSITION'!D21)/FINANCIALS!E5 -> 0.020379896 | F16: =('STATEMENT OF FINANCIAL POSITION'!E18+'STATEMENT OF FINANCIAL POSITION'!E21)/FINANCIALS!F5 -> 0.017228839 | G16: =('STATEMENT OF FINANCIAL POSITION'!F18+'STATEMENT OF FINANCIAL POSITION'!F21)/FINANCIALS!G5 -> 0.014882781 | H16: =('STATEMENT OF FINANCIAL POSITION'!G18+'STATEMENT OF FINANCIAL POSITION'!G21)/FINANCIALS!H5 -> 0.023759573 | I16: =('STATEMENT OF FINANCIAL POSITION'!H18+'STATEMENT OF FINANCIAL POSITION'!H21)/FINANCIALS!I5 -> 0.020959417 | J16: =('STATEMENT OF FINANCIAL POSITION'!I18+'STATEMENT OF FINANCIAL POSITION'!I21)/FINANCIALS!J5 -> 0.019903303 | K16: =('STATEMENT OF FINANCIAL POSITION'!J18+'STATEMENT OF FINANCIAL POSITION'!J21)/FINANCIALS!K5 -> 0.020542911 | ... W16: =('STATEMENT OF FINANCIAL POSITION'!V18+'STATEMENT OF FINANCIAL POSITION'!V21)/FINANCIALS!W5 -> 0.018400401 | X16: =('STATEMENT OF FINANCIAL POSITION'!X18+'STATEMENT OF FINANCIAL POSITION'!X21)/FINANCIALS!X5 -> 0.014775242 | Y16: =('STATEMENT OF FINANCIAL POSITION'!Y18+'STATEMENT OF FINANCIAL POSITION'!Y21)/FINANCIALS!Y5 -> 0.003846013 | Z16: =('STATEMENT OF FINANCIAL POSITION'!Z18+'STATEMENT OF FINANCIAL POSITION'!Z21)/FINANCIALS!Z5 -> 0.01436066 | AA16: =('STATEMENT OF FINANCIAL POSITION'!AA18+'STATEMENT OF FINANCIAL POSITION'!AA21)/FINANCIALS!AA5 -> 0.014594615 | AB16: =('STATEMENT OF FINANCIAL POSITION'!AB18+'STATEMENT OF FINANCIAL POSITION'!AB21)/FINANCIALS!AB5 -> 0.014392038 | AC16: =('STATEMENT OF FINANCIAL POSITION'!AC18+'STATEMENT OF FINANCIAL POSITION'!AC21)/FINANCIALS!AC5 -> 0.014420681 | AD16: =('STATEMENT OF FINANCIAL POSITION'!AD18+'STATEMENT OF FINANCIAL POSITION'!AD21)/FINANCIALS!AD5 -> 0.014392026 | AE16: =('STATEMENT OF FINANCIAL POSITION'!AE18+'STATEMENT OF FINANCIAL POSITION'!AE21)/FINANCIALS!AE5 -> 0.014359336 | ... BF16: =('STATEMENT OF FINANCIAL POSITION'!BF18+'STATEMENT OF FINANCIAL POSITION'!BF21)/FINANCIALS!BF5 -> 0.041423964
A17: 2.2.2 | B17: Non-Govt Securities/Core Capital | C17: ≤ 40% | D17: =('STATEMENT OF FINANCIAL POSITION'!C18+'STATEMENT OF FINANCIAL POSITION'!C21)/FINANCIALS!D11 -> 0.074579154 | E17: =('STATEMENT OF FINANCIAL POSITION'!D18+'STATEMENT OF FINANCIAL POSITION'!D21)/FINANCIALS!E11 -> 0.063466913 | F17: =('STATEMENT OF FINANCIAL POSITION'!E18+'STATEMENT OF FINANCIAL POSITION'!E21)/FINANCIALS!F11 -> 0.068512801 | G17: =('STATEMENT OF FINANCIAL POSITION'!F18+'STATEMENT OF FINANCIAL POSITION'!F21)/FINANCIALS!G11 -> 0.050271503 | H17: =('STATEMENT OF FINANCIAL POSITION'!G21+'STATEMENT OF FINANCIAL POSITION'!G24)/FINANCIALS!H11 -> 2.9854141 | I17: =('STATEMENT OF FINANCIAL POSITION'!H21+'STATEMENT OF FINANCIAL POSITION'!H24)/FINANCIALS!I11 -> 2.6662586 | J17: =('STATEMENT OF FINANCIAL POSITION'!I21+'STATEMENT OF FINANCIAL POSITION'!I24)/FINANCIALS!J11 -> 2.7955849 | K17: =('STATEMENT OF FINANCIAL POSITION'!J21+'STATEMENT OF FINANCIAL POSITION'!J24)/FINANCIALS!K11 -> 2.7929559 | L17: =('STATEMENT OF FINANCIAL POSITION'!K21+'STATEMENT OF FINANCIAL POSITION'!K24)/FINANCIALS!L11 -> 2.7994238 | M17: =('STATEMENT OF FINANCIAL POSITION'!L21+'STATEMENT OF FINANCIAL POSITION'!L24)/FINANCIALS!M11 -> 2.8416244 | N17: =('STATEMENT OF FINANCIAL POSITION'!M21+'STATEMENT OF FINANCIAL POSITION'!M24)/FINANCIALS!N11 -> 2.8987684 | O17: =('STATEMENT OF FINANCIAL POSITION'!N21+'STATEMENT OF FINANCIAL POSITION'!N24)/FINANCIALS!O11 -> 2.9851466 | ... W17: =('STATEMENT OF FINANCIAL POSITION'!V21+'STATEMENT OF FINANCIAL POSITION'!V24)/FINANCIALS!W11 -> 2.4923802 | X17: =('STATEMENT OF FINANCIAL POSITION'!X21+'STATEMENT OF FINANCIAL POSITION'!X24)/FINANCIALS!X11 -> 2.8337052 | Y17: =('STATEMENT OF FINANCIAL POSITION'!Y21+'STATEMENT OF FINANCIAL POSITION'!Y24)/FINANCIALS!Y11 -> 2.7307192 | Z17: =('STATEMENT OF FINANCIAL POSITION'!Z21+'STATEMENT OF FINANCIAL POSITION'!Z24)/FINANCIALS!Z11 -> 2.8228135 | AA17: =('STATEMENT OF FINANCIAL POSITION'!AA21+'STATEMENT OF FINANCIAL POSITION'!AA24)/FINANCIALS!AA11 -> 2.8543093 | AB17: =('STATEMENT OF FINANCIAL POSITION'!AB21+'STATEMENT OF FINANCIAL POSITION'!AB24)/FINANCIALS!AB11 -> 2.8925467 | AC17: =('STATEMENT OF FINANCIAL POSITION'!AC21+'STATEMENT OF FINANCIAL POSITION'!AC24)/FINANCIALS!AC11 -> 2.8563153 | AD17: =('STATEMENT OF FINANCIAL POSITION'!AD21+'STATEMENT OF FINANCIAL POSITION'!AD24)/FINANCIALS!AD11 -> 2.8937367 | AE17: =('STATEMENT OF FINANCIAL POSITION'!AE21+'STATEMENT OF FINANCIAL POSITION'!AE24)/FINANCIALS!AE11 -> 2.9175155 | ... BF17: =('STATEMENT OF FINANCIAL POSITION'!BF21+'STATEMENT OF FINANCIAL POSITION'!BF24)/FINANCIALS!BF11 -> 3.0961636
A18: 2.2.3 | B18: Gross Loans & advances /Total assets | D18: =FINANCIALS!D28/FINANCIALS!D4 -> 0.5661654 | E18: =FINANCIALS!E28/FINANCIALS!E4 -> 0.59172237 | F18: =FINANCIALS!F28/FINANCIALS!F4 -> 0.70150231 | G18: =FINANCIALS!G28/FINANCIALS!G4 -> 0.67335348 | H18: =FINANCIALS!H28/FINANCIALS!H4 -> 0.6884534 | I18: =FINANCIALS!I28/FINANCIALS!I4 -> 0.6313936 | J18: =FINANCIALS!J28/FINANCIALS!J4 -> 0.61724081 | K18: =FINANCIALS!K28/FINANCIALS!K4 -> 0.64211455 | ... BF18: =FINANCIALS!BF28/FINANCIALS!BF4 -> 0.76060917
B19: NPLs to Loan portfolio
A21: 3 | B21: FUNDING MIX
A22: 3.1 | B22: Total Deposits/Total Assets | D22: =FINANCIALS!D5/FINANCIALS!D4 -> 0.63050659 | E22: =FINANCIALS!E5/FINANCIALS!E4 -> 0.62891546 | F22: =FINANCIALS!F5/FINANCIALS!F4 -> 0.71378458 | G22: =FINANCIALS!G5/FINANCIALS!G4 -> 0.68848351 | H22: =FINANCIALS!H5/FINANCIALS!H4 -> 0.64609064 | I22: =FINANCIALS!I5/FINANCIALS!I4 -> 0.65225024 | J22: =FINANCIALS!J5/FINANCIALS!J4 -> 0.64655965 | K22: =FINANCIALS!K5/FINANCIALS!K4 -> 0.63200059 | ... BF22: =FINANCIALS!BF5/FINANCIALS!BF4 -> 0.61998475
A23: 3.1.1 | B23: BOSA Deposits/Total Assets | D23: =FINANCIALS!D6/FINANCIALS!D4 -> 0.29294802 | E23: =FINANCIALS!E6/FINANCIALS!E4 -> 0.29013495 | F23: =FINANCIALS!F6/FINANCIALS!F4 -> 0.35271652 | G23: =FINANCIALS!G6/FINANCIALS!G4 -> 0.34208406 | H23: =FINANCIALS!H6/FINANCIALS!H4 -> 0.34614606 | I23: =FINANCIALS!I6/FINANCIALS!I4 -> 0.32325687 | J23: =FINANCIALS!J6/FINANCIALS!J4 -> 0.34511113 | K23: =FINANCIALS!K6/FINANCIALS!K4 -> 0.35091918 | ... BF23: =FINANCIALS!BF6/FINANCIALS!BF4 -> 0.39448852
A24: 3.1.2 | B24: FOSA Deposits/Total Assets | D24: =FINANCIALS!D7/FINANCIALS!D4 -> 0.27576273 | E24: =FINANCIALS!E7/FINANCIALS!E4 -> 0.060322391 | F24: =FINANCIALS!F7/FINANCIALS!F4 -> 0.36106806 | G24: =FINANCIALS!G7/FINANCIALS!G4 -> 0.34639945 | H24: =FINANCIALS!H7/FINANCIALS!H4 -> 0.29994459 | I24: =FINANCIALS!I7/FINANCIALS!I4 -> 0.32899336 | J24: =FINANCIALS!J7/FINANCIALS!J4 -> 0.30144852 | K24: =FINANCIALS!K7/FINANCIALS!K4 -> 0.28108141 | ... BF24: =FINANCIALS!BF7/FINANCIALS!BF4 -> 0.22549623
A25: 3.2 | B25: External Borrowing/Total assets | C25: ≤ 25% | D25: =FINANCIALS!D8/FINANCIALS!D4 -> 0.011937213 | E25: =FINANCIALS!E8/FINANCIALS!E4 -> 0.033577094 | F25: =FINANCIALS!F8/FINANCIALS!F4 -> 0.0024285188 | G25: =FINANCIALS!G8/FINANCIALS!G4 -> 0 | H25: =FINANCIALS!H8/FINANCIALS!H4 -> 0 | I25: =FINANCIALS!I8/FINANCIALS!I4 -> 0 | J25: =FINANCIALS!J8/FINANCIALS!J4 -> 0 | K25: =FINANCIALS!K8/FINANCIALS!K4 -> 0 | ... BF25: =FINANCIALS!BF8/FINANCIALS!BF4 -> 0
A26: 3.3 | B26: Core capital/total assets | C26: ≥ 10% | D26: =FINANCIALS!D11/FINANCIALS!D4 -> 0.21303049 | E26: =FINANCIALS!E11/FINANCIALS!E4 -> 0.2019514 | F26: =FINANCIALS!F11/FINANCIALS!F4 -> 0.17949462 | G26: =FINANCIALS!G11/FINANCIALS!G4 -> 0.2038242 | H26: =FINANCIALS!H11/FINANCIALS!H4 -> 0.23574761 | I26: =FINANCIALS!I11/FINANCIALS!I4 -> 0.24193616 | J26: =FINANCIALS!J11/FINANCIALS!J4 -> 0.22539451 | K26: =FINANCIALS!K11/FINANCIALS!K4 -> 0.23455353 | ... BF26: =FINANCIALS!BF11/FINANCIALS!BF4 -> 0.25395667
A28: 4 | B28: GROWTH RATIOS
A29: 4.1 | B29: Total Assets | E29: =(FINANCIALS!E4-FINANCIALS!D4)/FINANCIALS!D4 -> 0.33631314 | F29: =(FINANCIALS!F4-FINANCIALS!E4)/FINANCIALS!E4 -> 0.042248029 | G29: =(FINANCIALS!G4-FINANCIALS!F4)/FINANCIALS!F4 -> 0.26291538 | H29: =(FINANCIALS!H4-FINANCIALS!G4)/FINANCIALS!G4 -> 0.089221927 | I29: =(FINANCIALS!I4-FINANCIALS!H4)/FINANCIALS!H4 -> 0.17439331 | J29: =(FINANCIALS!J4-FINANCIALS!I4)/FINANCIALS!I4 -> 0.21029796 | K29: =(FINANCIALS!K4-FINANCIALS!J4)/FINANCIALS!J4 -> -0.0088159976 | L29: =(FINANCIALS!L4-FINANCIALS!K4)/FINANCIALS!K4 -> -0.027535359 | ... BF29: =(FINANCIALS!BF4-FINANCIALS!BE4)/FINANCIALS!BE4 -> 0.015937193
A30: 4.2 | B30: Total Deposits | E30: =(FINANCIALS!E5-FINANCIALS!D5)/FINANCIALS!D5 -> 0.33294085 | F30: =(FINANCIALS!F5-FINANCIALS!E5)/FINANCIALS!E5 -> 0.18289439 | G30: =(FINANCIALS!G5-FINANCIALS!F5)/FINANCIALS!F5 -> 0.21814963 | H30: =(FINANCIALS!H5-FINANCIALS!G5)/FINANCIALS!G5 -> 0.022153887 | I30: =(FINANCIALS!I5-FINANCIALS!H5)/FINANCIALS!H5 -> 0.18558954 | J30: =(FINANCIALS!J5-FINANCIALS!I5)/FINANCIALS!I5 -> 0.19973865 | K30: =(FINANCIALS!K5-FINANCIALS!J5)/FINANCIALS!J5 -> -0.031135211 | L30: =(FINANCIALS!L5-FINANCIALS!K5)/FINANCIALS!K5 -> 0.006320077 | ... BF30: =(FINANCIALS!BF5-FINANCIALS!BE5)/FINANCIALS!BE5 -> 0.0077741153
A31: 4.2.1 | B31: BOSA Deposits | E31: =(FINANCIALS!E6-FINANCIALS!D6)/FINANCIALS!D6 -> 0.32348106 | F31: =(FINANCIALS!F6-FINANCIALS!E6)/FINANCIALS!E6 -> 0.26705897 | G31: =(FINANCIALS!G6-FINANCIALS!F6)/FINANCIALS!F6 -> 0.22484545 | H31: =(FINANCIALS!H6-FINANCIALS!G6)/FINANCIALS!G6 -> 0.10215564 | I31: =(FINANCIALS!I6-FINANCIALS!H6)/FINANCIALS!H6 -> 0.096735612 | J31: =(FINANCIALS!J6-FINANCIALS!I6)/FINANCIALS!I6 -> 0.29212191 | K31: =(FINANCIALS!K6-FINANCIALS!J6)/FINANCIALS!J6 -> 0.0078651581 | L31: =(FINANCIALS!L6-FINANCIALS!K6)/FINANCIALS!K6 -> 0.0094812063 | ... BF31: =(FINANCIALS!BF6-FINANCIALS!BE6)/FINANCIALS!BE6 -> 0.010412101
A32: 4.2.2 | B32: FOSA Deposits | E32: =(FINANCIALS!E7-FINANCIALS!D7)/FINANCIALS!D7 -> -0.70768493 | F32: =(FINANCIALS!F7-FINANCIALS!E7)/FINANCIALS!E7 -> 5.2385205 | G32: =(FINANCIALS!G7-FINANCIALS!F7)/FINANCIALS!F7 -> 0.21160868 | H32: =(FINANCIALS!H7-FINANCIALS!G7)/FINANCIALS!G7 -> -0.056851214 | I32: =(FINANCIALS!I7-FINANCIALS!H7)/FINANCIALS!H7 -> 0.28812995 | J32: =(FINANCIALS!J7-FINANCIALS!I7)/FINANCIALS!I7 -> 0.10896623 | K32: =(FINANCIALS!K7-FINANCIALS!J7)/FINANCIALS!J7 -> -0.075784497 | L32: =(FINANCIALS!L7-FINANCIALS!K7)/FINANCIALS!K7 -> 0.0023735304 | ... BF32: =(FINANCIALS!BF7-FINANCIALS!BE7)/FINANCIALS!BE7 -> 0.0031921354
A33: 4.3 | B33: Total Loans & advances | E33: =(FINANCIALS!E28-FINANCIALS!D28)/FINANCIALS!D28 -> 0.39663495 | F33: =(FINANCIALS!F28-FINANCIALS!E28)/FINANCIALS!E28 -> 0.23561223 | G33: =(FINANCIALS!G28-FINANCIALS!F28)/FINANCIALS!F28 -> 0.21223902 | H33: =(FINANCIALS!H28-FINANCIALS!G28)/FINANCIALS!G28 -> 0.11364767 | I33: =(FINANCIALS!I28-FINANCIALS!H28)/FINANCIALS!H28 -> 0.077058271 | J33: =(FINANCIALS!J28-FINANCIALS!I28)/FINANCIALS!I28 -> 0.18316893 | K33: =(FINANCIALS!K28-FINANCIALS!J28)/FINANCIALS!J28 -> 0.031127008 | L33: =(FINANCIALS!L28-FINANCIALS!K28)/FINANCIALS!K28 -> 0.017497096 | ... BF33: =(FINANCIALS!BF28-FINANCIALS!BE28)/FINANCIALS!BE28 -> 0.010956378
A34: 4.4 | B34: Core capital | E34: =(FINANCIALS!E11-FINANCIALS!D11)/FINANCIALS!D11 -> 0.2668154 | F34: =(FINANCIALS!F11-FINANCIALS!E11)/FINANCIALS!E11 -> -0.073648834 | G34: =(FINANCIALS!G11-FINANCIALS!F11)/FINANCIALS!F11 -> 0.43409712 | H34: =(FINANCIALS!H11-FINANCIALS!G11)/FINANCIALS!G11 -> 0.25981832 | I34: =(FINANCIALS!I11-FINANCIALS!H11)/FINANCIALS!H11 -> 0.20522205 | J34: =(FINANCIALS!J11-FINANCIALS!I11)/FINANCIALS!I11 -> 0.12754749 | K34: =(FINANCIALS!K11-FINANCIALS!J11)/FINANCIALS!J11 -> 0.031461281 | L34: =(FINANCIALS!L11-FINANCIALS!K11)/FINANCIALS!K11 -> 0.014800266 | ... BF34: =(FINANCIALS!BF11-FINANCIALS!BE11)/FINANCIALS!BE11 -> 0.015097592
A35: 4.5 | B35: Turnover | E35: =(FINANCIALS!E34-FINANCIALS!D35)/FINANCIALS!D34 -> 1.2393031 | F35: =(FINANCIALS!F34-FINANCIALS!E35)/FINANCIALS!E34 -> 0.73920569 | G35: =(FINANCIALS!G34-FINANCIALS!F35)/FINANCIALS!F34 -> 0.63084582 | H35: =(FINANCIALS!H34-FINANCIALS!G35)/FINANCIALS!G34 -> 0.35084198 | I35: =(FINANCIALS!I34-FINANCIALS!H35)/FINANCIALS!H34 -> 0.46767432 | J35: =(FINANCIALS!J34-FINANCIALS!I35)/FINANCIALS!I34 -> 0.59553539 | K35: =(FINANCIALS!K34-FINANCIALS!J35)/FINANCIALS!J34 -> -0.51345754 | L35: =(FINANCIALS!L34-FINANCIALS!K35)/FINANCIALS!K34 -> 1.2702533 | ... BF35: =(FINANCIALS!BF34-FINANCIALS!BE35)/FINANCIALS!BE34 -> 0.41646134
A36: 4.6 | B36: Membership
A37: 4.7 | B37: Expenses | E37: =(FINANCIALS!E40-FINANCIALS!D40)/FINANCIALS!D40 -> 1.3890657 | F37: =(FINANCIALS!F40-FINANCIALS!E40)/FINANCIALS!E40 -> 0.058698729 | G37: =(FINANCIALS!G40-FINANCIALS!F40)/FINANCIALS!F40 -> 0.36796313 | H37: =(FINANCIALS!H40-FINANCIALS!G40)/FINANCIALS!G40 -> -0.10024244 | I37: =(FINANCIALS!I40-FINANCIALS!H40)/FINANCIALS!H40 -> 0.18154689 | J37: =(FINANCIALS!J40-FINANCIALS!I40)/FINANCIALS!I40 -> 0.19492117 | K37: =(FINANCIALS!K40-FINANCIALS!J40)/FINANCIALS!J40 -> -0.92428058 | L37: =(FINANCIALS!L40-FINANCIALS!K40)/FINANCIALS!K40 -> 1.1602257 | ... BF37: =(FINANCIALS!BF40-FINANCIALS!BE40)/FINANCIALS!BE40 -> 0.17746269
A39: 5 | B39: Efficiency Ratios
A40: 5.1 | B40: FinCost-Deposits/Avg Deposits | E40: FINANCIALS!E41/((FINANCIALS!D6+FINANCIALS!#REF!'PRUDENTIAL RATIOS'!)/2) | F40: FINANCIALS!E41/((FINANCIALS!D6+FINANCIALS!#REF!'PRUDENTIAL RATIOS'!)/2) | G40: FINANCIALS!E41/((FINANCIALS!D6+FINANCIALS!#REF!'PRUDENTIAL RATIOS'!)/2)
A41: 5.2 | B41: FinCost-Shares/Avg Share capital | E41: =FINANCIALS!E42/((FINANCIALS!E15+FINANCIALS!#REF!)/2) -> #REF! | F41: =FINANCIALS!F42/((FINANCIALS!F15+FINANCIALS!#REF!)/2) -> #REF! | G41: =FINANCIALS!G42/((FINANCIALS!G15+FINANCIALS!#REF!)/2) -> #REF! | H41: =FINANCIALS!H42/((FINANCIALS!H15+FINANCIALS!#REF!)/2) -> #REF! | I41: =FINANCIALS!I42/((FINANCIALS!I15+FINANCIALS!#REF!)/2) -> #REF! | J41: =FINANCIALS!J42/((FINANCIALS!J15+FINANCIALS!#REF!)/2) -> #REF! | K41: =FINANCIALS!K42/((FINANCIALS!K15+FINANCIALS!#REF!)/2) -> #REF! | L41: =FINANCIALS!L42/((FINANCIALS!L15+FINANCIALS!#REF!)/2) -> #REF! | ... AY41: =FINANCIALS!AY42/((FINANCIALS!AY15+FINANCIALS!#REF!)/2) -> #REF!
A42: 5.3 | B42: FinCost-Ext Loans/Avg Ext Loans | E42: =FINANCIALS!E43/((FINANCIALS!E8+FINANCIALS!#REF!)/2) -> #REF! | F42: =FINANCIALS!F43/((FINANCIALS!F8+FINANCIALS!#REF!)/2) -> #REF! | G42: =FINANCIALS!G43/((FINANCIALS!G8+FINANCIALS!#REF!)/2) -> #REF! | H42: =FINANCIALS!H43/((FINANCIALS!H8+FINANCIALS!#REF!)/2) -> #REF! | I42: =FINANCIALS!I43/((FINANCIALS!I8+FINANCIALS!#REF!)/2) -> #REF! | J42: =FINANCIALS!J43/((FINANCIALS!J8+FINANCIALS!#REF!)/2) -> #REF! | K42: =FINANCIALS!K43/((FINANCIALS!K8+FINANCIALS!#REF!)/2) -> #REF! | L42: =FINANCIALS!L43/((FINANCIALS!L8+FINANCIALS!#REF!)/2) -> #REF! | ... AY42: =FINANCIALS!AY43/((FINANCIALS!AY8+FINANCIALS!#REF!)/2) -> #REF!
A43: 5.4 | B43: OpEx/Average Total Assets | E43: =FINANCIALS!E44/((FINANCIALS!E4+FINANCIALS!#REF!)/2) -> #REF! | F43: =FINANCIALS!F44/((FINANCIALS!F4+FINANCIALS!#REF!)/2) -> #REF! | G43: =FINANCIALS!G44/((FINANCIALS!G4+FINANCIALS!#REF!)/2) -> #REF! | H43: =FINANCIALS!H44/((FINANCIALS!H4+FINANCIALS!#REF!)/2) -> #REF! | I43: =FINANCIALS!I44/((FINANCIALS!I4+FINANCIALS!#REF!)/2) -> #REF! | J43: =FINANCIALS!J44/((FINANCIALS!J4+FINANCIALS!#REF!)/2) -> #REF! | K43: =FINANCIALS!K44/((FINANCIALS!K4+FINANCIALS!#REF!)/2) -> #REF! | L43: =FINANCIALS!L44/((FINANCIALS!L4+FINANCIALS!#REF!)/2) -> #REF! | ... AY43: =FINANCIALS!AY44/((FINANCIALS!AY4+FINANCIALS!#REF!)/2) -> #REF!
B44: Opex/Turnover | E44: =FINANCIALS!E44/FINANCIALS!E34 -> 0.42582832 | F44: =FINANCIALS!F44/FINANCIALS!F34 -> 0.29360692 | G44: =FINANCIALS!G44/FINANCIALS!G34 -> 0.31226233 | H44: =FINANCIALS!H44/FINANCIALS!H34 -> 0.31467935 | I44: =FINANCIALS!I44/FINANCIALS!I34 -> 0.37340679 | J44: =FINANCIALS!J44/FINANCIALS!J34 -> 0.31318135 | K44: =FINANCIALS!K44/FINANCIALS!K34 -> 0.41903884 | L44: =FINANCIALS!L44/FINANCIALS!L34 -> 0.42305213 | ... AY44: =FINANCIALS!AY44/FINANCIALS!AY34 -> 0.34143877
A45: 5.5 | B45: Avge yield on Net loans | E45: =FINANCIALS!D35/FINANCIALS!D27 -> 0.13387141 | F45: =FINANCIALS!E35/FINANCIALS!E27 -> 0.16394361 | G45: =FINANCIALS!F35/FINANCIALS!F27 -> 0.16695562 | H45: =FINANCIALS!G35/FINANCIALS!G27 -> #REF! | I45: =FINANCIALS!H35/FINANCIALS!H27 -> 0.16403864 | J45: =FINANCIALS!I35/FINANCIALS!I27 -> 0.16759652 | K45: =FINANCIALS!J35/FINANCIALS!J27 -> 0.16108705 | L45: =FINANCIALS!K35/FINANCIALS!K27 -> 0.011436496 | ... AY45: =FINANCIALS!AX35/FINANCIALS!AX27 -> 0.1465208
A46: 5.6 | B46: Avge yield on Gross loans | E46: =FINANCIALS!D35/FINANCIALS!D28 -> 0.13387141 | F46: =FINANCIALS!E35/FINANCIALS!E28 -> 0.15836789 | G46: =FINANCIALS!F35/FINANCIALS!F28 -> 0.16081892 | H46: =FINANCIALS!G35/FINANCIALS!G28 -> 0.16809352 | I46: =FINANCIALS!H35/FINANCIALS!H28 -> 0.15823976 | J46: =FINANCIALS!I35/FINANCIALS!I28 -> 0.15820062 | K46: =FINANCIALS!J35/FINANCIALS!J28 -> 0.15027149 | L46: =FINANCIALS!K35/FINANCIALS!K28 -> 0.010670428 | ... AY46: =FINANCIALS!AX35/FINANCIALS!AX28 -> 0.12947951
A48: 5.7 | B48: ALL/Average Gross Loan portfolio | E48: =FINANCIALS!E29/((FINANCIALS!E28+FINANCIALS!#REF!)/2) -> #REF! | F48: =FINANCIALS!F29/((FINANCIALS!F28+FINANCIALS!#REF!)/2) -> #REF! | G48: =FINANCIALS!G29/((FINANCIALS!G28+FINANCIALS!#REF!)/2) -> #REF! | H48: =FINANCIALS!H29/((FINANCIALS!H28+FINANCIALS!#REF!)/2) -> #REF! | I48: =FINANCIALS!I29/((FINANCIALS!I28+FINANCIALS!#REF!)/2) -> #REF! | J48: =FINANCIALS!J29/((FINANCIALS!J28+FINANCIALS!#REF!)/2) -> #REF! | K48: =FINANCIALS!K29/((FINANCIALS!K28+FINANCIALS!#REF!)/2) -> #REF! | L48: =FINANCIALS!L29/((FINANCIALS!L28+FINANCIALS!#REF!)/2) -> #REF! | ... AY48: =FINANCIALS!AY29/((FINANCIALS!AY28+FINANCIALS!#REF!)/2) -> #REF!

Sheet CAELS
B1: YETU SACCO CAELS
E3: 2010 Audited | F3: 2011 Audited | G3: 2012 Audited | H3: 2013 Audited | I3: 2014 AUDITED | J3: AUDITED 2015 | K3: AUDITED 2016 | L3: 42736 | M3: 42767 | N3: 42795 | O3: 42826 | P3: 42856 | Q3: 42887 | R3: 42917 | S3: 42948 | T3: 42979 | U3: 43009 | V3: 43040 | W3: 43070 | X3: Audited 2017 | Y3: Audited 2018 | Z3: Audited 2019
B5: CAPITAL ADEQUACY | C5: Core Capital | D5: 10 M | E5: =FINANCIALS!D11 -> 188947973 | F5: =FINANCIALS!E11 -> 239362202 | G5: =FINANCIALS!F11 -> 221733455 | H5: =FINANCIALS!G11 -> 317987309 | I5: =FINANCIALS!H11 -> 400606236 | J5: =FINANCIALS!I11 -> 482819469 | K5: =FINANCIALS!J11 -> 544401880 | L5: =FINANCIALS!K11 -> 5.6152946e+08 | ... X5: =FINANCIALS!W11 -> 703842973 | Y5: =FINANCIALS!Y11 -> 1096288715
C6: CCA | D6: Min 10% | E6: =FINANCIALS!D11/FINANCIALS!D4 -> 0.21303049 | F6: =FINANCIALS!E11/FINANCIALS!E4 -> 0.2019514 | G6: =FINANCIALS!F11/FINANCIALS!F4 -> 0.17949462 | H6: =FINANCIALS!G11/FINANCIALS!G4 -> 0.2038242 | I6: =FINANCIALS!H11/FINANCIALS!H4 -> 0.23574761 | J6: =FINANCIALS!I11/FINANCIALS!I4 -> 0.24193616 | K6: =FINANCIALS!J11/FINANCIALS!J4 -> 0.22539451 | L6: =FINANCIALS!K11/FINANCIALS!K4 -> 0.23455353 | ... X6: =FINANCIALS!W11/FINANCIALS!W4 -> 0.24418007 | Y6: =FINANCIALS!Y11/FINANCIALS!Y4 -> 0.26169753
C7: CCD | D7: Min 8% | E7: =FINANCIALS!D11/FINANCIALS!D5 -> 0.33787195 | F7: =FINANCIALS!E11/FINANCIALS!E5 -> 0.32111057 | G7: =FINANCIALS!F11/FINANCIALS!F5 -> 0.2514689 | H7: =FINANCIALS!G11/FINANCIALS!G5 -> 0.29604805 | I7: =FINANCIALS!H11/FINANCIALS!H5 -> 0.36488318 | J7: =FINANCIALS!I11/FINANCIALS!I5 -> 0.37092538 | K7: =FINANCIALS!J11/FINANCIALS!J5 -> 0.3486059 | L7: =FINANCIALS!K11/FINANCIALS!K5 -> 0.37112866 | ... X7: =FINANCIALS!W11/FINANCIALS!W5 -> 0.3875566 | Y7: =FINANCIALS!Y11/FINANCIALS!Y5 -> 0.42163407
C8: ICA | D8: Min 8% | E8: =(FINANCIALS!D11-FINANCIALS!D15)/FINANCIALS!D4 -> 0.06940606 | F8: =(FINANCIALS!E11-FINANCIALS!E15)/FINANCIALS!E4 -> 0.089670415 | G8: =(FINANCIALS!F11-FINANCIALS!F15)/FINANCIALS!F4 -> 0.15239028 | H8: =(FINANCIALS!G11-FINANCIALS!G15)/FINANCIALS!G4 -> 0.17677432 | I8: =(FINANCIALS!H11-FINANCIALS!H15)/FINANCIALS!H4 -> 0.21087539 | J8: =(FINANCIALS!I11-FINANCIALS!I15)/FINANCIALS!I4 -> 0.21970528 | K8: =(FINANCIALS!J11-FINANCIALS!J15)/FINANCIALS!J4 -> 0.20483894 | L8: =(FINANCIALS!K11-FINANCIALS!K15)/FINANCIALS!K4 -> 0.2136384 | ... X8: =(FINANCIALS!W11-FINANCIALS!W15)/FINANCIALS!W4 -> 0.20470693 | Y8: =(FINANCIALS!Y11-FINANCIALS!Y15)/FINANCIALS!Y4 -> 0.22689639
B10: ASSET QUALITY | C10: A/LNPL30
C11: NPL30
C12: Non-earning Asset ratio | D12: Max 10% | E12: =('STATEMENT OF FINANCIAL POSITION'!C14+'STATEMENT OF FINANCIAL POSITION'!C32)/'STATEMENT OF FINANCIAL POSITION'!C39 -> 0.22713306 | F12: =('STATEMENT OF FINANCIAL POSITION'!D14+'STATEMENT OF FINANCIAL POSITION'!D32)/'STATEMENT OF FINANCIAL POSITION'!D39 -> 0.17811571 | G12: =('STATEMENT OF FINANCIAL POSITION'!E14+'STATEMENT OF FINANCIAL POSITION'!E32)/'STATEMENT OF FINANCIAL POSITION'!E39 -> 0.090152034 | H12: =('STATEMENT OF FINANCIAL POSITION'!F14+'STATEMENT OF FINANCIAL POSITION'!F32)/'STATEMENT OF FINANCIAL POSITION'!F39 -> 0.082684889 | I12: =('STATEMENT OF FINANCIAL POSITION'!G14+'STATEMENT OF FINANCIAL POSITION'!G32)/'STATEMENT OF FINANCIAL POSITION'!G39 -> 0.080535981 | J12: =('STATEMENT OF FINANCIAL POSITION'!H14+'STATEMENT OF FINANCIAL POSITION'!H32)/'STATEMENT OF FINANCIAL POSITION'!H39 -> 0.077440123 | K12: =('STATEMENT OF FINANCIAL POSITION'!I14+'STATEMENT OF FINANCIAL POSITION'!I32)/'STATEMENT OF FINANCIAL POSITION'!I39 -> 0.079515684 | L12: =('STATEMENT OF FINANCIAL POSITION'!J14+'STATEMENT OF FINANCIAL POSITION'!J32)/'STATEMENT OF FINANCIAL POSITION'!J39 -> 0.083482077 | ... X12: =('STATEMENT OF FINANCIAL POSITION'!V14+'STATEMENT OF FINANCIAL POSITION'!V32)/'STATEMENT OF FINANCIAL POSITION'!V39 -> 0.066130678 | Y12: =('STATEMENT OF FINANCIAL POSITION'!Y14+'STATEMENT OF FINANCIAL POSITION'!Y32)/'STATEMENT OF FINANCIAL POSITION'!Y39 -> 0.058157885
C13: Land and Building ratio | D13: Max 5% | E13: =('STATEMENT OF FINANCIAL POSITION'!C34+'STATEMENT OF FINANCIAL POSITION'!C35)/'STATEMENT OF FINANCIAL POSITION'!C39 -> 0.17193463 | F13: =('STATEMENT OF FINANCIAL POSITION'!D34+'STATEMENT OF FINANCIAL POSITION'!D35)/'STATEMENT OF FINANCIAL POSITION'!D39 -> 0.13616721 | G13: =('STATEMENT OF FINANCIAL POSITION'!E34+'STATEMENT OF FINANCIAL POSITION'!E35)/'STATEMENT OF FINANCIAL POSITION'!E39 -> 0.030581377 | H13: =('STATEMENT OF FINANCIAL POSITION'!F34+'STATEMENT OF FINANCIAL POSITION'!F35)/'STATEMENT OF FINANCIAL POSITION'!F39 -> 0.027932099 | I13: =('STATEMENT OF FINANCIAL POSITION'!G34+'STATEMENT OF FINANCIAL POSITION'!G35)/'STATEMENT OF FINANCIAL POSITION'!G39 -> 0.028834858 | J13: =('STATEMENT OF FINANCIAL POSITION'!H34+'STATEMENT OF FINANCIAL POSITION'!H35)/'STATEMENT OF FINANCIAL POSITION'!H39 -> 0.025949264 | K13: =('STATEMENT OF FINANCIAL POSITION'!I34+'STATEMENT OF FINANCIAL POSITION'!I35)/'STATEMENT OF FINANCIAL POSITION'!I39 -> 0.021635468 | L13: =('STATEMENT OF FINANCIAL POSITION'!J34+'STATEMENT OF FINANCIAL POSITION'!J35)/'STATEMENT OF FINANCIAL POSITION'!J39 -> 0.021362655 | ... X13: =('STATEMENT OF FINANCIAL POSITION'!V34+'STATEMENT OF FINANCIAL POSITION'!V35)/'STATEMENT OF FINANCIAL POSITION'!V39 -> 0.018691463 | Y13: =('STATEMENT OF FINANCIAL POSITION'!Y34+'STATEMENT OF FINANCIAL POSITION'!Y35)/'STATEMENT OF FINANCIAL POSITION'!Y39 -> 0.014944656
C14: Non-Government Investment to Deposit ratio | D14: Max 5% | E14: ='STATEMENT OF FINANCIAL POSITION'!C21/'STATEMENT OF FINANCIAL POSITION'!C46 -> 0.025198204 | F14: ='STATEMENT OF FINANCIAL POSITION'!D21/'STATEMENT OF FINANCIAL POSITION'!D46 -> 0.020379896 | G14: ='STATEMENT OF FINANCIAL POSITION'!E21/'STATEMENT OF FINANCIAL POSITION'!E46 -> 0.017228839 | H14: ='STATEMENT OF FINANCIAL POSITION'!F21/'STATEMENT OF FINANCIAL POSITION'!F46 -> 0.014882781 | I14: ='STATEMENT OF FINANCIAL POSITION'!G21/'STATEMENT OF FINANCIAL POSITION'!G46 -> 0.023759573 | J14: ='STATEMENT OF FINANCIAL POSITION'!H21/'STATEMENT OF FINANCIAL POSITION'!H46 -> 0.020959417 | K14: ='STATEMENT OF FINANCIAL POSITION'!I21/'STATEMENT OF FINANCIAL POSITION'!I46 -> 0.019903303 | L14: ='STATEMENT OF FINANCIAL POSITION'!J21/'STATEMENT OF FINANCIAL POSITION'!J46 -> 0.020542911 | ... X14: ='STATEMENT OF FINANCIAL POSITION'!V21/'STATEMENT OF FINANCIAL POSITION'!V46 -> 0.018400401 | Y14: ='STATEMENT OF FINANCIAL POSITION'!Y21/'STATEMENT OF FINANCIAL POSITION'!Y46 -> 0.003846013
C15: Non-Government Investment to Core Capital ratio | D15: Max 40% | E15: ='STATEMENT OF FINANCIAL POSITION'!C21/FINANCIALS!D11 -> 0.074579154 | F15: ='STATEMENT OF FINANCIAL POSITION'!D21/FINANCIALS!E11 -> 0.063466913 | G15: ='STATEMENT OF FINANCIAL POSITION'!E21/FINANCIALS!F11 -> 0.068512801 | H15: ='STATEMENT OF FINANCIAL POSITION'!F21/FINANCIALS!G11 -> 0.050271503 | I15: ='STATEMENT OF FINANCIAL POSITION'!G21/FINANCIALS!H11 -> 0.065115562 | J15: ='STATEMENT OF FINANCIAL POSITION'!H21/FINANCIALS!I11 -> 0.056505752 | K15: ='STATEMENT OF FINANCIAL POSITION'!I21/FINANCIALS!J11 -> 0.057093993 | L15: ='STATEMENT OF FINANCIAL POSITION'!J21/FINANCIALS!K11 -> 0.055352531 | ... X15: ='STATEMENT OF FINANCIAL POSITION'!V21/FINANCIALS!W11 -> 0.047477969 | Y15: ='STATEMENT OF FINANCIAL POSITION'!Y21/FINANCIALS!Y11 -> 0.0091216847
C16: Gross loans/TA | E16: =FINANCIALS!D28/FINANCIALS!D4 -> 0.5661654 | F16: =FINANCIALS!E28/FINANCIALS!E4 -> 0.59172237 | G16: =FINANCIALS!F28/FINANCIALS!F4 -> 0.70150231 | H16: =FINANCIALS!G28/FINANCIALS!G4 -> 0.67335348 | I16: =FINANCIALS!H28/FINANCIALS!H4 -> 0.6884534 | J16: =FINANCIALS!I28/FINANCIALS!I4 -> 0.6313936 | K16: =FINANCIALS!J28/FINANCIALS!J4 -> 0.61724081 | L16: =FINANCIALS!K28/FINANCIALS!K4 -> 0.64211455 | ... X16: =FINANCIALS!W28/FINANCIALS!W4 -> 0.59699639 | Y16: =FINANCIALS!Y28/FINANCIALS!Y4 -> 0.71223536
B18: EARNINGS | C18: ROA | E18: ='STATEMENT OF COMPREHENSIVE INCO'!C56/FINANCIALS!D4 -> 0.02942144 | F18: ='STATEMENT OF COMPREHENSIVE INCO'!D56/FINANCIALS!E4 -> 0.066863626 | G18: ='STATEMENT OF COMPREHENSIVE INCO'!E56/FINANCIALS!F4 -> 0.072631348 | H18: ='STATEMENT OF COMPREHENSIVE INCO'!F56/FINANCIALS!G4 -> 0.055784169 | I18: ='STATEMENT OF COMPREHENSIVE INCO'!G56/FINANCIALS!H4 -> 0.055320572 | J18: ='STATEMENT OF COMPREHENSIVE INCO'!H56/FINANCIALS!I4 -> 0.039817599 | K18: ='STATEMENT OF COMPREHENSIVE INCO'!I56/FINANCIALS!J4 -> 0.045929628 | L18: ='STATEMENT OF COMPREHENSIVE INCO'!J56/FINANCIALS!K4 -> 0.0072247691 | ... X18: ='STATEMENT OF COMPREHENSIVE INCO'!V56/FINANCIALS!W4 -> 0.035566682 | Y18: ='STATEMENT OF COMPREHENSIVE INCO'!Y56/FINANCIALS!Y4 -> 0.041359179
C19: Cost Income ratio | E19: ='STATEMENT OF COMPREHENSIVE INCO'!C36/'STATEMENT OF COMPREHENSIVE INCO'!C30 -> 0.43453967 | F19: ='STATEMENT OF COMPREHENSIVE INCO'!D36/'STATEMENT OF COMPREHENSIVE INCO'!D30 -> 0.49427837 | G19: ='STATEMENT OF COMPREHENSIVE INCO'!E36/'STATEMENT OF COMPREHENSIVE INCO'!E30 -> 0.41778795 | H19: ='STATEMENT OF COMPREHENSIVE INCO'!F36/'STATEMENT OF COMPREHENSIVE INCO'!F30 -> 0.47970756 | I19: ='STATEMENT OF COMPREHENSIVE INCO'!G36/'STATEMENT OF COMPREHENSIVE INCO'!G30 -> 0.45124053 | J19: ='STATEMENT OF COMPREHENSIVE INCO'!H36/'STATEMENT OF COMPREHENSIVE INCO'!H30 -> 0.51119005 | K19: ='STATEMENT OF COMPREHENSIVE INCO'!I36/'STATEMENT OF COMPREHENSIVE INCO'!I30 -> 0.45535453 | L19: ='STATEMENT OF COMPREHENSIVE INCO'!J36/'STATEMENT OF COMPREHENSIVE INCO'!J30 -> 0.60142033 | ... X19: ='STATEMENT OF COMPREHENSIVE INCO'!V36/'STATEMENT OF COMPREHENSIVE INCO'!V30 -> 0.46060932 | Y19: ='STATEMENT OF COMPREHENSIVE INCO'!Y36/'STATEMENT OF COMPREHENSIVE INCO'!Y30 -> 0.39496548
C20: Operating Expense ratio | E20: ='STATEMENT OF COMPREHENSIVE INCO'!C36/'STATEMENT OF FINANCIAL POSITION'!C39 -> 0.022609513 | F20: ='STATEMENT OF COMPREHENSIVE INCO'!D36/'STATEMENT OF FINANCIAL POSITION'!D39 -> 0.062081036 | G20: ='STATEMENT OF COMPREHENSIVE INCO'!E36/'STATEMENT OF FINANCIAL POSITION'!E39 -> 0.056014631 | H20: ='STATEMENT OF COMPREHENSIVE INCO'!F36/'STATEMENT OF FINANCIAL POSITION'!F39 -> 0.057652052 | I20: ='STATEMENT OF COMPREHENSIVE INCO'!G36/'STATEMENT OF FINANCIAL POSITION'!G39 -> 0.051413518 | J20: ='STATEMENT OF COMPREHENSIVE INCO'!H36/'STATEMENT OF FINANCIAL POSITION'!H39 -> 0.058933721 | K20: ='STATEMENT OF COMPREHENSIVE INCO'!I36/'STATEMENT OF FINANCIAL POSITION'!I39 -> 0.050168745 | L20: ='STATEMENT OF COMPREHENSIVE INCO'!J36/'STATEMENT OF FINANCIAL POSITION'!J39 -> 0.0044401273 | ... X20: ='STATEMENT OF COMPREHENSIVE INCO'!V36/'STATEMENT OF FINANCIAL POSITION'!V39 -> 0.042666473 | Y20: ='STATEMENT OF COMPREHENSIVE INCO'!Y36/'STATEMENT OF FINANCIAL POSITION'!Y39 -> 0.035616651
B22: LIQUIDITY | C22: MIN LIQ ratio | D22: Min 15% | E22: ='STATEMENT OF FINANCIAL POSITION'!C10/'STATEMENT OF FINANCIAL POSITION'!C43 -> 0.69194959 | F22: ='STATEMENT OF FINANCIAL POSITION'!D10/'STATEMENT OF FINANCIAL POSITION'!D43 -> 0.78052917 | G22: ='STATEMENT OF FINANCIAL POSITION'!E10/'STATEMENT OF FINANCIAL POSITION'!E43 -> 0.70770505 | H22: ='STATEMENT OF FINANCIAL POSITION'!F10/'STATEMENT OF FINANCIAL POSITION'!F43 -> 0.96153537 | I22: ='STATEMENT OF FINANCIAL POSITION'!G10/'STATEMENT OF FINANCIAL POSITION'!G43 -> 1.0717955 | J22: ='STATEMENT OF FINANCIAL POSITION'!H10/'STATEMENT OF FINANCIAL POSITION'!H43 -> 1.204582 | K22: ='STATEMENT OF FINANCIAL POSITION'!I10/'STATEMENT OF FINANCIAL POSITION'!I43 -> 0.71125981 | L22: ='STATEMENT OF FINANCIAL POSITION'!J10/'STATEMENT OF FINANCIAL POSITION'!J43 -> 1.3635711 | ... X22: ='STATEMENT OF FINANCIAL POSITION'!V10/'STATEMENT OF FINANCIAL POSITION'!V43 -> 0.71080971 | Y22: ='STATEMENT OF FINANCIAL POSITION'!Y10/'STATEMENT OF FINANCIAL POSITION'!Y43 -> 0.94089328
C23: Technical LIQ ratio | E23: ='STATEMENT OF FINANCIAL POSITION'!C10/'STATEMENT OF FINANCIAL POSITION'!C46 -> 0.30263586 | F23: ='STATEMENT OF FINANCIAL POSITION'!D10/'STATEMENT OF FINANCIAL POSITION'!D46 -> 0.34558648 | G23: ='STATEMENT OF FINANCIAL POSITION'!E10/'STATEMENT OF FINANCIAL POSITION'!E46 -> 0.30171107 | H23: ='STATEMENT OF FINANCIAL POSITION'!F10/'STATEMENT OF FINANCIAL POSITION'!F46 -> 0.36911843 | I23: ='STATEMENT OF FINANCIAL POSITION'!G10/'STATEMENT OF FINANCIAL POSITION'!G46 -> 0.3714604 | J23: ='STATEMENT OF FINANCIAL POSITION'!H10/'STATEMENT OF FINANCIAL POSITION'!H46 -> 0.47971327 | K23: ='STATEMENT OF FINANCIAL POSITION'!I10/'STATEMENT OF FINANCIAL POSITION'!I46 -> 0.26942389 | L23: ='STATEMENT OF FINANCIAL POSITION'!J10/'STATEMENT OF FINANCIAL POSITION'!J46 -> 0.48169568 | ... X23: ='STATEMENT OF FINANCIAL POSITION'!V10/'STATEMENT OF FINANCIAL POSITION'!V46 -> 0.28775854 | Y23: ='STATEMENT OF FINANCIAL POSITION'!Y10/'STATEMENT OF FINANCIAL POSITION'!Y46 -> 0.47164304
C24: External Borrowing ratio | D24: Max 25% | E24: ='STATEMENT OF FINANCIAL POSITION'!C54/'STATEMENT OF FINANCIAL POSITION'!C39 -> 0.011937213 | F24: ='STATEMENT OF FINANCIAL POSITION'!D54/'STATEMENT OF FINANCIAL POSITION'!D39 -> 0.033577094 | G24: ='STATEMENT OF FINANCIAL POSITION'!E54/'STATEMENT OF FINANCIAL POSITION'!E39 -> 0.0024285188 | H24: ='STATEMENT OF FINANCIAL POSITION'!F54/'STATEMENT OF FINANCIAL POSITION'!F39 -> 0 | I24: ='STATEMENT OF FINANCIAL POSITION'!G54/'STATEMENT OF FINANCIAL POSITION'!G39 -> 0 | J24: ='STATEMENT OF FINANCIAL POSITION'!H54/'STATEMENT OF FINANCIAL POSITION'!H39 -> 0 | K24: ='STATEMENT OF FINANCIAL POSITION'!I54/'STATEMENT OF FINANCIAL POSITION'!I39 -> 0 | L24: ='STATEMENT OF FINANCIAL POSITION'!J54/'STATEMENT OF FINANCIAL POSITION'!J39 -> 0 | ... X24: ='STATEMENT OF FINANCIAL POSITION'!V54/'STATEMENT OF FINANCIAL POSITION'!V39 -> 0 | Y24: ='STATEMENT OF FINANCIAL POSITION'!Y54/'STATEMENT OF FINANCIAL POSITION'!Y39 -> 0
C25: Liquid Assets to TA ratio | E25: ='STATEMENT OF FINANCIAL POSITION'!C10/'STATEMENT OF FINANCIAL POSITION'!C39 -> 0.19081391 | F25: ='STATEMENT OF FINANCIAL POSITION'!D10/'STATEMENT OF FINANCIAL POSITION'!D39 -> 0.21734468 | G25: ='STATEMENT OF FINANCIAL POSITION'!E10/'STATEMENT OF FINANCIAL POSITION'!E39 -> 0.21535671 | H25: ='STATEMENT OF FINANCIAL POSITION'!F10/'STATEMENT OF FINANCIAL POSITION'!F39 -> 0.25413195 | I25: ='STATEMENT OF FINANCIAL POSITION'!G10/'STATEMENT OF FINANCIAL POSITION'!G39 -> 0.23999709 | J25: ='STATEMENT OF FINANCIAL POSITION'!H10/'STATEMENT OF FINANCIAL POSITION'!H39 -> 0.3128931 | K25: ='STATEMENT OF FINANCIAL POSITION'!I10/'STATEMENT OF FINANCIAL POSITION'!I39 -> 0.17419861 | L25: ='STATEMENT OF FINANCIAL POSITION'!J10/'STATEMENT OF FINANCIAL POSITION'!J39 -> 0.30443196 | ... X25: ='STATEMENT OF FINANCIAL POSITION'!V10/'STATEMENT OF FINANCIAL POSITION'!V39 -> 0.18130229 | Y25: ='STATEMENT OF FINANCIAL POSITION'!Y10/'STATEMENT OF FINANCIAL POSITION'!Y39 -> 0.29273683

Sheet FORM 4
B1: FORM 4 SASRA2/004
B2: RISK CLASSIFICATION OF ASSETS AND PROVISIONING
B3: SACCO SOCIETY CS NUMBER | F3: 6366
B4: FINANCIAL YEAR | F4: 2017
B5: START DATE: | F5: 1/1/2017
B6: END DATE: | F6: password3$
B7: PORTFOLIO AGEING REPORT
C8: A | D8: B | E8: C | F8: D
A9: NO. | B9: CLASSIFICATION | C9: NO. OF A/Cs | D9: OUTSTANDING LOAN PORTFOLIO(Kshs) | E9: REQUIRED PROVISION | F9: REQUIRED PROVISION AMOUNT(Kshs)
A10: 1 | B10: Performing | C10: 9569 | D10: 1.5232014e+09 | E10: 0.01 | F10: =D10*E10 -> 15232014
A11: 2 | B11: Watch | C11: 102 | D11: 4670712.6 | E11: 0.05 | F11: =D11*E11 -> 233535.63
A12: 3 | B12: Substandard | C12: 515 | D12: 33773549 | E12: 0.25 | F12: =D12*E12 -> 8443387.3
A13: 4 | B13: Doubtful | C13: 224 | D13: 5677083.8 | E13: 0.5 | F13: =D13*E13 -> 2838541.9
A14: 5 | B14: Loss | C14: 638 | D14: 26325061 | E14: 1 | F14: =D14*E14 -> 26325061 | G14: =D14+D13+D12 -> 65775694
B15: subtotal | C15: =SUM(C10:C14) -> 11048 | D15: =SUM(D10:D14) -> 1.5936478e+09 | F15: =SUM(F10:F14) -> 53072539
B16: Reschedule/Renegotiated loans
A17: 1 | B17: Performing | C17: 0 | D17: 0 | E17: 0.01 | F17: =D17*E17 -> 0
A18: 2 | B18: Watch | C18: 0 | D18: 0 | E18: 0.05 | F18: =D18*E18 -> 0
A19: 3 | B19: Substandard | C19: 0 | D19: 0 | E19: 0.25 | F19: =D19*E19 -> 0 | G19: =G14/D15 -> 0.041273671
A20: 4 | B20: Doubtful | C20: 0 | D20: 0 | E20: 0.5 | F20: =D20*E20 -> 0 | G20: =G19*100 -> 4.1273671
A21: 5 | B21: Loss | C21: 0 | D21: 0 | E21: 1 | F21: =D21*E21 -> 0
B22: subtotal | C22: =SUM(C16:C21) -> 0 | D22: =SUM(D16:D21) -> 0 | F22: =SUM(F16:F21) -> 0
B23: GRAND TOTAL | C23: =C15+C22 -> 11048 | D23: =D15+D22 -> 1.5936478e+09 | F23: =F15+F22 -> 53072539
A25: Note: This return should be received on or before the 15th day of the month following end of every quarter
B27: AUTHORIZATION:
B28: We declare that this return, to the best of our knowledge and belief is correct.
B29: …………………………………………………..sign……………………………..date……………………..
B30: Name of Authorizing Officer
B31: …………………………………………………..sign……………………………..date……………………..
B32: Name of Countersigning Officer
B36: FORM 4 SASRA2/004
B37: RISK CLASSIFICATION OF ASSETS AND PROVISIONING
B38: SACCO SOCIETY CS NUMBER | F38: 6366
B39: FINANCIAL YEAR | F39: 2017
B40: START DATE: | F40: 1/1/2017
B41: END DATE: | F41: 30/6/2017
B42: PORTFOLIO AGEING REPORT
C43: A | D43: B | E43: C | F43: D
A44: NO. | B44: CLASSIFICATION | C44: NO. OF A/Cs | D44: OUTSTANDING LOAN PORTFOLIO(Kshs) | E44: REQUIRED PROVISION | F44: REQUIRED PROVISION AMOUNT(Kshs)
A45: 1 | B45: Performing | C45: 10401 | D45: 1.6591136e+09 | E45: 0.01 | F45: =D45*E45 -> 16591136
A46: 2 | B46: Watch | C46: 81 | D46: 2163744 | E46: 0.05 | F46: =D46*E46 -> 108187.2
A47: 3 | B47: Substandard | C47: 474 | D47: 27649021 | E47: 0.25 | F47: =D47*E47 -> 6912255.2
A48: 4 | B48: Doubtful | C48: 256 | D48: 11508313 | E48: 0.5 | F48: =D48*E48 -> 5754156.3
A49: 5 | B49: Loss | C49: 664 | D49: 26681484 | E49: 1 | F49: =D49*E49 -> 26681484
B50: subtotal | C50: =SUM(C45:C49) -> 11876 | D50: =SUM(D45:D49) -> 1.7271162e+09 | F50: =SUM(F45:F49) -> 56047219
B51: Reschedule/Renegotiated loans
A52: 1 | B52: Performing | C52: 0 | D52: 0 | E52: 0.01 | F52: =D52*E52 -> 0
A53: 2 | B53: Watch | C53: 0 | D53: 0 | E53: 0.05 | F53: =D53*E53 -> 0
A54: 3 | B54: Substandard | C54: 0 | D54: 0 | E54: 0.25 | F54: =D54*E54 -> 0
A55: 4 | B55: Doubtful | C55: 0 | D55: 0 | E55: 0.5 | F55: =D55*E55 -> 0
A56: 5 | B56: Loss | C56: 0 | D56: 0 | E56: 1 | F56: =D56*E56 -> 0
B57: subtotal | C57: =SUM(C51:C56) -> 0 | D57: =SUM(D51:D56) -> 0 | F57: =SUM(F51:F56) -> 0
B58: GRAND TOTAL | C58: =C50+C57 -> 11876 | D58: =D50+D57 -> 1.7271162e+09 | F58: =F50+F57 -> 56047219
A60: Note: This return should be received on or before the 15th day of the month following end of every quarter
B62: AUTHORIZATION:
B63: We declare that this return, to the best of our knowledge and belief is correct.
B64: …………………………………………………..sign……………………………..date……………………..
B65: Name of Authorizing Officer
B66: …………………………………………………..sign……………………………..date……………………..
B67: Name of Countersigning Officer
B70: FORM 4 SASRA2/004
B71: RISK CLASSIFICATION OF ASSETS AND PROVISIONING
B72: SACCO SOCIETY CS NUMBER | F72: 6366
B73: FINANCIAL YEAR | F73: 2017
B74: START DATE: | F74: 1/1/2017
B75: END DATE: | F75: 30/9/2017
B76: PORTFOLIO AGEING REPORT
C77: A | D77: B | E77: C | F77: D
A78: NO. | B78: CLASSIFICATION | C78: NO. OF A/Cs | D78: OUTSTANDING LOAN PORTFOLIO(Kshs) | E78: REQUIRED PROVISION | F78: REQUIRED PROVISION AMOUNT(Kshs)
A79: 1 | B79: Performing | C79: 11770 | D79: 1.7475483e+09 | E79: 0.01 | F79: =D79*E79 -> 17475483
A80: 2 | B80: Watch | C80: 138 | D80: 5506043 | E80: 0.05 | F80: =D80*E80 -> 275302.15
A81: 3 | B81: Substandard | C81: 385 | D81: 14780152 | E81: 0.25 | F81: =D81*E81 -> 3695038
A82: 4 | B82: Doubtful | C82: 462 | D82: 31526200 | E82: 0.5 | F82: =D82*E82 -> 15763100
A83: 5 | B83: Loss | C83: 770 | D83: 29453503 | E83: 1 | F83: =D83*E83 -> 29453503
B84: subtotal | C84: =SUM(C79:C83) -> 13525 | D84: =SUM(D79:D83) -> 1.8288142e+09 | F84: =SUM(F79:F83) -> 66662426
B85: Reschedule/Renegotiated loans
A86: 1 | B86: Performing | C86: 0 | D86: 0 | E86: 0.01 | F86: =D86*E86 -> 0
A87: 2 | B87: Watch | C87: 0 | D87: 0 | E87: 0.05 | F87: =D87*E87 -> 0
A88: 3 | B88: Substandard | C88: 0 | D88: 0 | E88: 0.25 | F88: =D88*E88 -> 0
A89: 4 | B89: Doubtful | C89: 0 | D89: 0 | E89: 0.5 | F89: =D89*E89 -> 0
A90: 5 | B90: Loss | C90: 0 | D90: 0 | E90: 1 | F90: =D90*E90 -> 0
B91: subtotal | C91: =SUM(C85:C90) -> 0 | D91: =SUM(D85:D90) -> 0 | F91: =SUM(F85:F90) -> 0
B92: GRAND TOTAL | C92: =C84+C91 -> 13525 | D92: =D84+D91 -> 1.8288142e+09 | F92: =F84+F91 -> 66662426
A94: Note: This return should be received on or before the 15th day of the month following end of every quarter
B97: FORM 4 SASRA2/004
B98: RISK CLASSIFICATION OF ASSETS AND PROVISIONING
B99: SACCO SOCIETY CS NUMBER | F99: 6366
B100: FINANCIAL YEAR | F100: 2017
B101: START DATE: | F101: 1/1/2017
B102: END DATE: | F102: 31/12/2017
B103: PORTFOLIO AGEING REPORT
C104: A | D104: B | E104: C | F104: D
A105: NO. | B105: CLASSIFICATION | C105: NO. OF A/Cs | D105: OUTSTANDING LOAN PORTFOLIO(Kshs) | E105: REQUIRED PROVISION | F105: REQUIRED PROVISION AMOUNT(Kshs)
A106: 1 | B106: Performing | C106: 9533 | D106: 1.660293e+09 | E106: 0.01 | F106: =D106*E106 -> 16602930
A107: 2 | B107: Watch | C107: 114 | D107: 4034383.7 | E107: 0.05 | F107: =D107*E107 -> 201719.18
A108: 3 | B108: Substandard | C108: 320 | D108: 13448912 | E108: 0.25 | F108: =D108*E108 -> 3362228.1
A109: 4 | B109: Doubtful | C109: 232 | D109: 7856522.4 | E109: 0.5 | F109: =D109*E109 -> 3928261.2
A110: 5 | B110: Loss | C110: 816 | D110: 35656632 | E110: 1 | F110: =D110*E110 -> 35656632
B111: subtotal | C111: =SUM(C106:C110) -> 11015 | D111: =SUM(D106:D110) -> 1.7212894e+09 | F111: =SUM(F106:F110) -> 59751770
B112: Reschedule/Renegotiated loans
...

Sheet form 3

Sheet Sheet1
D2: 2015
B3: 2013 AUDITED | C3: 2014 AUDITED | D3: 42005 | E3: 42036 | F3: 42064 | G3: 42095 | H3: 42125 | I3: 42156 | J3: 42186 | K3: 42217 | L3: 42248
A4: TOTAL ASSETS | B4: 1560105754 | C4: 1699301395 | D4: 1.6690883e+09 | E4: 1.6573445e+09 | F4: 1.6522602e+09 | G4: 1.6790891e+09 | H4: 1.6889496e+09 | I4: 1.6979441e+09 | J4: 1.7425914e+09 | K4: 1.7777887e+09 | L4: 1.8077999e+09
A5: Total Assets(Millions) | B5: 1699301395 | C5: 1995648187 | D5: 1.9784349e+09 | E5: 1.9420335e+09 | F5: 1.934954e+09 | G5: 1.9671889e+09 | H5: 1.9767845e+09 | I5: 1.9952196e+09 | J5: 2.0187045e+09 | K5: 2.0327864e+09 | L5: 2.0690873e+09
A6: Total Assets(Millions) | B6: 1050502640 | C6: 1169889815 | D6: 1.217913e+09 | E6: 1.2253866e+09 | F6: 1.245855e+09 | G6: 1.2639999e+09 | H6: 1.2886356e+09 | I6: 1.3163532e+09 | J6: 1.3348284e+09 | K6: 1.3624824e+09 | L6: 1.3926775e+09
A7: Total Assets(Millions) | B7: =B5/1000000 -> 1699.3014 | C7: =C5/1000000 -> 1995.6482 | D7: =D5/1000000 -> 1978.4349 | E7: =E5/1000000 -> 1942.0335 | F7: =F5/1000000 -> 1934.954 | G7: =G5/1000000 -> 1967.1889 | H7: =H5/1000000 -> 1976.7845 | I7: =I5/1000000 -> 1995.2196 | ... L7: =L5/1000000 -> 2069.0873
A8: Gross Loans(Millions) | B8: =B6/1000000 -> 1050.5026 | C8: =C6/1000000 -> 1169.8898 | D8: =D6/1000000 -> 1217.913 | E8: =E6/1000000 -> 1225.3866 | F8: =F6/1000000 -> 1245.855 | G8: =G6/1000000 -> 1263.9999 | H8: =H6/1000000 -> 1288.6356 | I8: =I6/1000000 -> 1316.3532 | ... L8: =L6/1000000 -> 1392.6775
A9: Core Capital(Millions) | B9: 317987309 | C9: 400606236 | D9: 4.717554e+08 | E9: 4.2033447e+08 | F9: 4.2349881e+08 | G9: 4.252398e+08 | H9: 4.2931177e+08 | I9: 4.3227318e+08 | J9: 4.3762705e+08 | K9: 4.405222e+08 | L9: 4.4037155e+08
A10: Core Capital(Millions) | B10: =B9/1000000 -> 317.98731 | C10: =C9/1000000 -> 400.60624 | D10: =D9/1000000 -> 471.7554 | E10: =E9/1000000 -> 420.33447 | F10: =F9/1000000 -> 423.49881 | G10: =G9/1000000 -> 425.2398 | H10: =H9/1000000 -> 429.31177 | I10: =I9/1000000 -> 432.27318 | ... L10: =L9/1000000 -> 440.37155
A11: Total Deposits(Millions) | B11: =B12/1000000 -> 317.98868 | C11: =C12/1000000 -> 400.60781 | D11: =D12/1000000 -> 471.75709 | E11: =E12/1000000 -> 420.33612 | F11: =F12/1000000 -> 423.50047 | G11: =G12/1000000 -> 425.24149 | H11: =H12/1000000 -> 429.31349 | I11: =I12/1000000 -> 432.27493 | ... L11: =L12/1000000 -> 440.37338
B12: =SUM(B8:B10) -> 3.1798868e+08 | C12: =SUM(C8:C10) -> 4.0060781e+08 | D12: =SUM(D8:D10) -> 4.7175709e+08 | E12: =SUM(E8:E10) -> 4.2033612e+08 | F12: =SUM(F8:F10) -> 4.2350047e+08 | G12: =SUM(G8:G10) -> 4.2524149e+08 | H12: =SUM(H8:H10) -> 4.2931349e+08 | I12: =SUM(I8:I10) -> 4.3227493e+08 | ... L12: =SUM(L8:L10) -> 4.4037338e+08

Sheet PERFORMANCE TOOL
A1: YETU SACCO SOCIETY LIMITED
A2: PERFORMANCE AND COMPLIANCE REPORT AS AT : 31st December , 2021
B3: Prudential Standard | C3: Audited | D3: Returns | F3: AUDITED 2021 | G3: Aggregate for all Licensed Saccos
C4: 2020 | D4: 30th September , 2021 | E4: 31st December , 2021
A5: A. CAPITAL ADEQUACY
A6: Core Capital | B6: ≥10M | C6: 1146288715 | D6: 1154864001 | E6: - | F6: - | G6: 7290089864
A7: Core Capital/Total Assets | B7: ≥10% | C7: 0.274 | D7: 0.267 | E7: #DIV/0! | F7: #DIV/0! | G7: 0.233
A8: Institutional Capital/Total Assets | B8: ≥8% | C8: 0.239 | D8: 0.231 | E8: #DIV/0! | F8: #DIV/0! | G8: 0.141
A9: B. ASSET QUALITY
A10: NPL (Substandard+Doubtful+Loss) | B10: <5% | C10: 0 | D10: 0.169 | E10: #DIV/0! | F10: #DIV/0! | G10: 0.112
A11: Non-Earning Assets | B11: <10% | C11: 0.058 | D11: 0.074 | E11: #DIV/0! | F11: #DIV/0! | G11: 0.094
A12: Equity investments/Deposits | B12: <5% | C12: 0.004 | D12: 0.019 | E12: #DIV/0! | F12: #DIV/0! | G12: 0.033
A13: Equity investments/Core capital | B13: <40% | C13: 0.009 | D13: 0.042 | E13: #DIV/0! | F13: #DIV/0! | G13: 0.093
A14: C. EARNINGS RATING
A15: Yield on Gross Loans | C15: 0.172 | D15: 0.111 | E15: #DIV/0! | F15: #DIV/0! | G15: 0.19
A16: Total Expense/Total Income | C16: 0.626 | D16: 0.726 | E16: #DIV/0! | F16: #DIV/0! | G16: 0.64
A17: Net Income/Average Assets (ROA) | C17: 0.044 | D17: 0.021 | E17: 0 | F17: #DIV/0! | G17: 0.005
A18: Operating Expenses/Financial Income (OPEX) | C18: 0.244 | D18: 0.3 | E18: #DIV/0! | F18: #DIV/0! | G18: 0.428
A19: D. LIQUIDITY
A20: Liquid Assets/Short-term Liabilities | B20: >15% | C20: 0.346 | D20: 0.687 | E20: #DIV/0! | F20: #DIV/0! | G20: 0.56
A21: External Borrowing/Total Assets | B21: <25% | C21: 0 | D21: 0.001 | E21: #DIV/0! | F21: #DIV/0! | G21: 0.004
A22: Liquid Assets/Total Assets | C22: 0.168 | D22: 0.231 | E22: #DIV/0! | F22: #DIV/0! | G22: 0.178
A23: E. STRUCTURE/SENSITIVITY TO RISK
A24: Gross loans /Total Assets | B24: 70-80 | C24: 0.712 | D24: 0.779 | E24: #DIV/0! | F24: #DIV/0! | G24: 0.749
A25: Gross loans/Deposits | B25: >100% | C25: 1.148 | D25: 1.279 | E25: #DIV/0! | F25: #DIV/0! | G25: 1.134
A26: Financial Investments/Total Assets | C26: 0.27 | D26: 0.045 | E26: #DIV/0! | F26: #DIV/0! | G26: 0.035
A27: Dividends+Interest on Deposits/Total Income | C27: 0.375 | D27: 0.424 | E27: #DIV/0! | F27: #DIV/0! | G27: 0.192
A28: F. KEY FINANCIAL STATISTICS
A29: Total Assets | C29: 4189144224 | D29: 4.3240074e+09 | E29: - | F29: ='STATEMENT OF FINANCIAL POSITION'!AL39 -> 4707277148 | G29: 3.1315916e+10
A30: Average Assets | C30: 3945358538 | D30: 4.0263472e+09 | E30: 2.0957153e+09 | F30: =(F29+C29)/2 -> 4448210686 | G30: 3.2428249e+11
A31: Total Deposits | C31: 2600095208 | D31: 2.6337962e+09 | E31: - | F31: ='STATEMENT OF FINANCIAL POSITION'!AL46 -> 2849515045 | G31: 2.0678842e+10
A32: Gross Loans | C32: 2983656626 | D32: 3.3692725e+09 | E32: - | F32: ='STATEMENT OF FINANCIAL POSITION'!AL24 -> 3379491104 | G32: 2.3448249e+10
A33: Core Capital | C33: 1146288715 | D33: 1.154864e+09 | E33: - | F33: ='STATEMENT OF FINANCIAL POSITION'!AL71-'STATEMENT OF FINANCIAL POSITION'!AL21 -> 1324766646 | G33: 7.2900899e+09
A34: Institutional Capital | C34: 1000501709 | D34: 9.9906741e+08 | E34: - | F34: =F33-'STATEMENT OF FINANCIAL POSITION'!AL58 -> 1165846247 | G34: 4.4001829e+09
A35: Non-performing Loans | C35: - | D35: 5.7092706e+08 | E35: - | F35: =86912138+42948825+187329149 -> 317190112 | G35: 2.6271349e+09
A36: Non-Earning Assets | C36: 243631769 | D36: 3.2141621e+08 | E36: - | F36: ='STATEMENT OF FINANCIAL POSITION'!AL14+'STATEMENT OF FINANCIAL POSITION'!AL32 -> 270494691 | G36: 2.9296353e+09
A37: Property and Equipment | C37: 73105319 | D37: 88111572 | E37: - | F37: ='STATEMENT OF FINANCIAL POSITION'!AL34 -> 79835394 | G37: 1.0078632e+09
A38: Equity Investments | C38: 10000000 | D38: 48917035 | E38: - | F38: ='STATEMENT OF FINANCIAL POSITION'!AL20+'STATEMENT OF FINANCIAL POSITION'!AL21 -> 46417035 | G38: 6.8135989e+08
A39: Financial Investments | C39: 702087549 | D39: 118917035 | E39: - | F39: ='STATEMENT OF FINANCIAL POSITION'!AL16 -> 116417035 | G39: 7.2904865e+08
A40: Liquid Assets | C40: 702646302 | D40: 9.9777965e+08 | E40: - | F40: ='STATEMENT OF FINANCIAL POSITION'!AL10+'STATEMENT OF FINANCIAL POSITION'!AL17 -> 1392752340 | G40: 5.5706274e+09
A41: Short-term Liabilities) | C41: 2028552103 | D41: 1.4532225e+09 | E41: - | F41: ='STATEMENT OF FINANCIAL POSITION'!AL43+'STATEMENT OF FINANCIAL POSITION'!AL44+'STATEMENT OF FINANCIAL POSITION'!AL48-'STATEMENT OF FINANCIAL POSITION'!AL54 -> 2249296682 | G41: 9.9559509e+09
A42: External Borrowing | C42: - | D42: 4210115 | E42: - | F42: ='STATEMENT OF FINANCIAL POSITION'!AL54 -> 3372292 | G42: 113499997
A43: Average Gross Loans | C43: 2842189143 | D43: 3.1389077e+09 | E43: 1.4918283e+09 | F43: =(C32+F32)/2 -> 3181573865 | G43: 2.443856e+11
A44: Total Income | C44: 611439871 | D44: 4.9141659e+08 | E44: - | F44: ='STATEMENT OF COMPREHENSIVE INCO'!AL10 -> 694739717 | G44: 5.2975379e+09
A45: Net Financial Income/Loss | C45: 377762851 | D45: 2.1167828e+08 | E45: - | F45: ='STATEMENT OF COMPREHENSIVE INCO'!AL30 -> 411065840 | G45: 4.170644e+09
A46: Dividends+Interest on Deposits | C46: 228991846 | D46: 2.0837001e+08 | E46: - | F46: ='STATEMENT OF COMPREHENSIVE INCO'!AL22 -> 278473794 | G46: 1.0171274e+09
A47: Operating Expenses | C47: 149203287 | D47: 1.4741032e+08 | E47: - | F47: ='STATEMENT OF COMPREHENSIVE INCO'!AL36 -> 201509342 | G47: 2.2650465e+09
A48: Interest on Loan portfolio+Fees&Commission on Loan | C48: 513164979 | D48: 3.7239239e+08 | E48: - | F48: ='STATEMENT OF COMPREHENSIVE INCO'!AL12 -> 452871508 | G48: 4.4603185e+09
A49: Total Expenses | C49: 382880307 | D49: 3.5696508e+08 | E49: - | F49: ='STATEMENT OF COMPREHENSIVE INCO'!AL36+'STATEMENT OF COMPREHENSIVE INCO'!AL32+'STATEMENT OF COMPREHENSIVE INCO'!AL21 -> 494183219 | G49: 3.3920666e+09
A50: Net Income | C50: 173259564 | D50: 82701514 | E50: - | F50: ='STATEMENT OF COMPREHENSIVE INCO'!AL56 -> 184556498 | G50: 1.5330614e+09
A51: G. AREAS OF IMPROVEMENT/REGULATORY CONCERNS
A52: 1
A53: 2
A54: 3
A55: 4
A56: Prepared by:
A58: Checked by:
A60: Approved by:
A62: DISCLAIMER: This report is prepared based on information submitted by the Sacco as at the stated date and may change upon verification by the Authority.
